{
  "type": "Feature",
  "properties": {
    "addr:full":"3746 Point Nepean Rd Portsea VIC 3944",
    "addr:housenumber":"3746",
    "addr:postcode":"3944",
    "addr:street":"Point Nepean Rd",
    "iso:country":"AU",
    "sg:address":"3746 Point Nepean Rd",
    "sg:city":"Portsea",
    "sg:classifiers":[
        {
            "category":"Retail",
            "subcategory":"Event Space",
            "type":"Services"
        }
    ],
    "sg:phone":"+61 3 5984 8112",
    "sg:postcode":"3944",
    "sg:province":"VIC",
    "sg:tags":[
        "venue",
        "reception",
        "wedding"
    ],
    "wof:name":"Portsea Hotel",
    "wof:placetype":"venue"
},
  "geometry": {"coordinates":[144.71473693900001,-38.3200721741],"type":"Point"}
}