{
  "type": "Feature",
  "properties": {
    "addr:full":"29 Seventh Ave Katoomba NSW 2780",
    "addr:housenumber":"29",
    "addr:postcode":"2780",
    "addr:street":"Seventh Ave",
    "iso:country":"AU",
    "sg:address":"29 Seventh Ave",
    "sg:city":"Katoomba",
    "sg:classifiers":[
        {
            "category":"Communications",
            "subcategory":"Film & Video Production",
            "type":"Services"
        }
    ],
    "sg:phone":"+61 2 4782 1234",
    "sg:postcode":"2780",
    "sg:province":"NSW",
    "sg:tags":[
        "messaging",
        "voice"
    ],
    "wof:name":"Adhear Creative Audio",
    "wof:placetype":"venue"
},
  "geometry": {"coordinates":[150.323196411,-33.6936988831],"type":"Point"}
}