{
  "type": "Feature",
  "properties": {
    "addr:full":"76 rozella Rd Empire Bay NSW 2257",
    "addr:housenumber":"76",
    "addr:postcode":"2257",
    "addr:street":"Rozella Rd",
    "iso:country":"AU",
    "sg:address":"76 rozella Rd",
    "sg:city":"Empire Bay",
    "sg:classifiers":[
        {
            "category":"Building & Trades",
            "subcategory":"Construction",
            "type":"Services"
        }
    ],
    "sg:phone":"+61 418 691 130",
    "sg:postcode":"2257",
    "sg:province":"NSW",
    "sg:tags":[
        "renovation",
        "alterations",
        "extension",
        "contractor"
    ],
    "wof:name":"Wayne Wright Carpentry",
    "wof:placetype":"venue"
},
  "geometry": {"coordinates":[151.36050415,-33.4975852966],"type":"Point"}
}