{
  "type": "Feature",
  "properties": {
    "iso:country":"AU",
    "sg:address":"128 Pitt Rd",
    "sg:city":"North Curl Curl",
    "sg:classifiers":[
        {
            "category":"Communications",
            "type":"Services"
        }
    ],
    "sg:phone":"+61 2 9938 4448",
    "sg:postcode":"2099",
    "sg:province":"NSW",
    "sg:tags":[
        "equipment",
        "satellite"
    ],
    "wof:name":"Satellite Industry Supplies",
    "wof:placetype":"venue"
},
  "geometry": {"coordinates":[151.29083251899999,-33.7624816895],"type":"Point"}
}