{
  "type": "Feature",
  "properties": {
    "iso:country":"AU",
    "sg:address":"5121 Clarence St",
    "sg:city":"Port Macquarie",
    "sg:classifiers":[
        {
            "category":"Professional",
            "subcategory":"Business Services",
            "type":"Services"
        }
    ],
    "sg:phone":"+61 2 6583 4147",
    "sg:postcode":"2444",
    "sg:province":"NSW",
    "sg:tags":[
        "broker"
    ],
    "wof:name":"Port City Realty",
    "wof:placetype":"venue"
},
  "geometry": {"coordinates":[152.913284,-31.428888],"type":"Point"}
}