{
  "type": "Feature",
  "properties": {
    "addr:full":"Fergusons La Avenel VIC 3664",
    "addr:postcode":"3664",
    "iso:country":"AU",
    "sg:address":"Fergusons La",
    "sg:city":"Avenel",
    "sg:classifiers":[
        {
            "category":"Farming",
            "subcategory":"Farm",
            "type":"Manufacturing & Wholesale Goods"
        }
    ],
    "sg:phone":"+61 3 5796 2475",
    "sg:postcode":"3664",
    "sg:province":"VIC",
    "sg:tags":[
        "farmer"
    ],
    "wof:name":"Ferguson W",
    "wof:placetype":"venue"
},
  "geometry": {"coordinates":[145.221466064,-36.8912887573],"type":"Point"}
}