{
  "type": "Feature",
  "properties": {
    "iso:country":"AU",
    "sg:address":"3 Martin Pl",
    "sg:city":"Ashmore",
    "sg:classifiers":[
        {
            "category":"Building & Trades",
            "subcategory":"Construction",
            "type":"Services"
        }
    ],
    "sg:phone":"+61 412 245 860",
    "sg:postcode":"4214",
    "sg:province":"QLD",
    "sg:tags":[
        "contractor"
    ],
    "wof:name":"Stuart Graham Builder",
    "wof:placetype":"venue"
},
  "geometry": {"coordinates":[153.379074097,-27.986125946],"type":"Point"}
}