{
  "type": "Feature",
  "properties": {
    "addr:full":"34 Balloan St Coburg VIC 3058",
    "addr:housenumber":"34",
    "addr:postcode":"3058",
    "addr:street":"Balloan St",
    "iso:country":"AU",
    "sg:address":"34 Balloan St",
    "sg:city":"Coburg",
    "sg:classifiers":[
        {
            "category":"Health Services",
            "subcategory":"Health Practitioner",
            "type":"Services"
        }
    ],
    "sg:phone":"+61 3 9354 6561",
    "sg:postcode":"3058",
    "sg:province":"VIC",
    "sg:tags":[
        "alternative"
    ],
    "wof:name":"Blue Jade Chinese Medicine",
    "wof:placetype":"venue"
},
  "geometry": {"coordinates":[144.95872497600001,-37.7393226624],"type":"Point"}
}