{
  "type": "Feature",
  "properties": {
    "iso:country":"AU",
    "sg:address":"3 Bankside St",
    "sg:city":"Nathan",
    "sg:classifiers":[
        {
            "category":"Shopping",
            "subcategory":"Computers & Home Electronics",
            "type":"Retail Goods"
        }
    ],
    "sg:phone":"+61 7 3274 4144",
    "sg:postcode":"4111",
    "sg:province":"QLD",
    "sg:tags":[
        "hardware",
        "equipment"
    ],
    "wof:name":"Micro Plus Technology",
    "wof:placetype":"venue"
},
  "geometry": {"coordinates":[153.04200744600001,-27.5438117981],"type":"Point"}
}