{
  "type": "Feature",
  "properties": {
    "addr:full":"8 Hope St Rosehill NSW 2142",
    "addr:housenumber":"8",
    "addr:postcode":"2142",
    "addr:street":"Hope St",
    "iso:country":"AU",
    "sg:address":"8 Hope St",
    "sg:city":"Rosehill",
    "sg:classifiers":[
        {
            "category":"Travel",
            "subcategory":"Hotels & Motels",
            "type":"Entertainment"
        }
    ],
    "sg:phone":"+61 2 9687 7711",
    "sg:postcode":"2142",
    "sg:province":"NSW",
    "sg:tags":[
        "accommodation"
    ],
    "sg:website":"http://www.questrosehill.com.au",
    "wof:name":"Quest Rosehill",
    "wof:placetype":"venue"
},
  "geometry": {"coordinates":[151.02127075199999,-33.821308136],"type":"Point"}
}