{
  "type": "Feature",
  "properties": {
    "iso:country":"AU",
    "sg:address":"Cnr Glenarvon & Meads Rds (cnr Glenarvon Rd)",
    "sg:city":"Lorn",
    "sg:classifiers":[
        {
            "category":"Home & Garden",
            "subcategory":"Garden Supply",
            "type":"Retail Goods"
        }
    ],
    "sg:phone":"+61 2 4934 7306",
    "sg:postcode":"2320",
    "sg:province":"NSW",
    "sg:tags":[
        "turf",
        "lawn"
    ],
    "wof:name":"Agturf Supplies",
    "wof:placetype":"venue"
},
  "geometry": {"coordinates":[151.567092895,-32.7304420471],"type":"Point"}
}