{
  "type": "Feature",
  "properties": {
    "addr:full":"4/ 129 Robinson Rd East Geebung QLD 4034",
    "addr:housenumber":"/ 129",
    "addr:postcode":"4034",
    "addr:street":"Robinson Rd East",
    "iso:country":"AU",
    "sg:address":"4/ 129 Robinson Rd",
    "sg:city":"East Geebung",
    "sg:classifiers":[
        {
            "category":"Social Services",
            "subcategory":"Retirement Home",
            "type":"Services"
        }
    ],
    "sg:phone":"+61 7 3265 3258",
    "sg:postcode":"4034",
    "sg:province":"QLD",
    "sg:tags":[
        "t-shirt",
        "supplier"
    ],
    "wof:name":"Lee T. Shirts Pty Ltd",
    "wof:placetype":"venue"
},
  "geometry": {"coordinates":[153.05549600000001,-27.369349],"type":"Point"}
}