{
  "type": "Feature",
  "properties": {
    "iso:country":"AU",
    "sg:address":"15 Terrigal Ave",
    "sg:city":"Turramurra",
    "sg:classifiers":[
        {
            "category":"Banks & Credit Unions",
            "subcategory":"Financial Services",
            "type":"Services"
        }
    ],
    "sg:phone":"+61 2 9144 1379",
    "sg:postcode":"2074",
    "sg:province":"NSW",
    "sg:tags":[
        "planning"
    ],
    "wof:name":"Count Wealth Accountants",
    "wof:placetype":"venue"
},
  "geometry": {"coordinates":[151.13150024399999,-33.7369003296],"type":"Point"}
}