{
  "type": "Feature",
  "properties": {
    "addr:full":"8 Fitzroy St St Kilda VIC 3182",
    "addr:housenumber":"8",
    "addr:postcode":"3182",
    "addr:street":"Fitzroy St",
    "iso:country":"AU",
    "sg:address":"8 Fitzroy St St",
    "sg:city":"Kilda",
    "sg:classifiers":[
        {
            "category":"Real Estate",
            "subcategory":"Real Estate Agent",
            "type":"Services"
        }
    ],
    "sg:phone":"+61 419 303 322",
    "sg:postcode":"3182",
    "sg:province":"VIC",
    "wof:name":"Hall G",
    "wof:placetype":"venue"
},
  "geometry": {"coordinates":[144.97398376500001,-37.8616142273],"type":"Point"}
}