{
  "type": "Feature",
  "properties": {
    "addr:full":"294 Pound Rd Hampton Park VIC 3976",
    "addr:housenumber":"294",
    "addr:postcode":"3976",
    "addr:street":"Pound Rd",
    "iso:country":"AU",
    "sg:address":"294 Pound Rd",
    "sg:city":"Hampton Park",
    "sg:classifiers":[
        {
            "category":"Home & Garden",
            "subcategory":"Building Materials",
            "type":"Retail Goods"
        }
    ],
    "sg:phone":"+61 3 9702 8323",
    "sg:postcode":"3976",
    "sg:province":"VIC",
    "sg:tags":[
        "concrete",
        "gutter",
        "kerb"
    ],
    "wof:name":"Klein Kerbing Pty Ltd",
    "wof:placetype":"venue"
},
  "geometry": {"coordinates":[145.27674865700001,-38.0296096802],"type":"Point"}
}