{
  "type": "Feature",
  "properties": {
    "addr:full":"39 Bridge St North Rockhampton QLD 4701",
    "addr:housenumber":"39",
    "addr:postcode":"4701",
    "addr:street":"Bridge St North",
    "iso:country":"AU",
    "sg:address":"39 Bridge St",
    "sg:city":"North Rockhampton",
    "sg:classifiers":[
        {
            "category":"Travel",
            "subcategory":"Hotels & Motels",
            "type":"Entertainment"
        }
    ],
    "sg:phone":"+61 7 4922 3414",
    "sg:postcode":"4701",
    "sg:province":"QLD",
    "sg:tags":[
        "accommodation"
    ],
    "wof:name":"Anchor Hotel",
    "wof:placetype":"venue"
},
  "geometry": {"coordinates":[150.51963806099999,-23.3722038269],"type":"Point"}
}