{
  "type": "Feature",
  "properties": {
    "addr:full":"64 Dixon St Inverloch VIC 3996",
    "addr:housenumber":"64",
    "addr:postcode":"3996",
    "addr:street":"Dixon St",
    "iso:country":"AU",
    "sg:address":"64 Dixon St",
    "sg:city":"Inverloch",
    "sg:classifiers":[
        {
            "category":"Wholesale",
            "subcategory":"Seafood",
            "type":"Manufacturing & Wholesale Goods"
        }
    ],
    "sg:phone":"+61 3 5674 2858",
    "sg:postcode":"3996",
    "sg:province":"VIC",
    "sg:tags":[
        "fish"
    ],
    "wof:name":"Inlet Seafoods",
    "wof:placetype":"venue"
},
  "geometry": {"coordinates":[145.71723900000001,-38.6315],"type":"Point"}
}