{
  "type": "Feature",
  "properties": {
    "addr:full":"Shop 4/ 1065 Barrenjoy Rd Palm Beach NSW 2108",
    "addr:housenumber":"shop 4 / 1065",
    "addr:postcode":"2108",
    "addr:street":"Barrenjoy Rd",
    "iso:country":"AU",
    "sg:address":"Shop 4/ 1065 Barrenjoy Rd",
    "sg:city":"Palm Beach",
    "sg:classifiers":[
        {
            "category":"Personal",
            "subcategory":"Massage",
            "type":"Services"
        }
    ],
    "sg:phone":"+61 425 331 337",
    "sg:postcode":"2108",
    "sg:province":"NSW",
    "sg:tags":[
        "therapy"
    ],
    "wof:name":"Beach House Therapies",
    "wof:placetype":"venue"
},
  "geometry": {"coordinates":[151.318893433,-33.6016693115],"type":"Point"}
}