{
  "type": "Feature",
  "properties": {
    "addr:full":"426 Canterbury Rd Surrey Hills VIC 3127",
    "addr:housenumber":"426",
    "addr:postcode":"3127",
    "addr:street":"Canterbury Rd",
    "iso:country":"AU",
    "sg:address":"426 Canterbury Rd",
    "sg:city":"Surrey Hills",
    "sg:classifiers":[
        {
            "category":"Landmark",
            "subcategory":"Scenic View",
            "type":"Public Place"
        }
    ],
    "sg:phone":"+61 3 9836 4079",
    "sg:postcode":"3127",
    "sg:province":"VIC",
    "sg:tags":[
        "staircase",
        "handrail"
    ],
    "wof:name":"Gibson & Jones",
    "wof:placetype":"venue"
},
  "geometry": {"coordinates":[145.09963989299999,-37.826374054],"type":"Point"}
}