{
  "type": "Feature",
  "properties": {
    "addr:full":"133b Victoria St Mackay QLD 4740",
    "addr:housenumber":"133b",
    "addr:postcode":"4740",
    "addr:street":"Victoria St",
    "iso:country":"AU",
    "sg:address":"133b Victoria St",
    "sg:city":"Mackay",
    "sg:classifiers":[
        {
            "category":"Banks & Credit Unions",
            "subcategory":"Investment Brokerage",
            "type":"Services"
        }
    ],
    "sg:phone":"+61 7 4957 7786",
    "sg:postcode":"4740",
    "sg:province":"QLD",
    "sg:tags":[
        "finance",
        "broker"
    ],
    "wof:name":"Mortgage Choice",
    "wof:placetype":"venue"
},
  "geometry": {"coordinates":[149.183716,-21.141123],"type":"Point"}
}