{
  "type": "Feature",
  "properties": {
    "iso:country":"AU",
    "sg:address":"Anketell Rd",
    "sg:city":"Kwinana Beach",
    "sg:classifiers":[
        {
            "category":"Conference Center",
            "type":"Public Place"
        }
    ],
    "sg:phone":"+61 8 9419 6622",
    "sg:postcode":"6167",
    "sg:province":"WA",
    "sg:tags":[
        "venue",
        "convention"
    ],
    "wof:name":"Quit Motorplex",
    "wof:placetype":"venue"
},
  "geometry": {"coordinates":[115.78537,-32.209858],"type":"Point"}
}