{
  "type": "Feature",
  "properties": {
    "iso:country":"AU",
    "sg:address":"114 Moor St",
    "sg:city":"Fitzroy",
    "sg:classifiers":[
        {
            "category":"Real Estate",
            "subcategory":"Architect",
            "type":"Services"
        }
    ],
    "sg:phone":"+61 3 9417 6942",
    "sg:postcode":"3065",
    "sg:province":"VIC",
    "wof:name":"Rijavec Architects",
    "wof:placetype":"venue"
},
  "geometry": {"coordinates":[144.978805542,-37.8018074036],"type":"Point"}
}