{
  "type": "Feature",
  "properties": {
    "iso:country":"AU",
    "sg:address":"64 Grand Pde",
    "sg:city":"Redcliffe",
    "sg:classifiers":[
        {
            "category":"Professional",
            "subcategory":"Accounting & Tax Preparation",
            "type":"Services"
        }
    ],
    "sg:phone":"+61 8 9479 7898",
    "sg:postcode":"6104",
    "sg:province":"WA",
    "sg:tags":[
        "consultant",
        "taxation"
    ],
    "wof:name":"Swift Tax Refunds",
    "wof:placetype":"venue"
},
  "geometry": {"coordinates":[115.951316834,-31.9496803284],"type":"Point"}
}