{
  "type": "Feature",
  "properties": {
    "addr:full":"12 The Ridge St Canterbury VIC 3126",
    "addr:housenumber":"12",
    "addr:postcode":"3126",
    "addr:street":"The Ridge St",
    "iso:country":"AU",
    "sg:address":"12 The Ridge St",
    "sg:city":"Canterbury",
    "sg:classifiers":[
        {
            "category":"Health Services",
            "subcategory":"Dentist",
            "type":"Services"
        }
    ],
    "sg:phone":"+61 3 9882 3618",
    "sg:postcode":"3126",
    "sg:province":"VIC",
    "sg:tags":[
        "technician",
        "dental"
    ],
    "wof:name":"Jennings Russ & Rod",
    "wof:placetype":"venue"
},
  "geometry": {"coordinates":[145.064163208,-37.8206672668],"type":"Point"}
}