{
  "type": "Feature",
  "properties": {
    "iso:country":"AU",
    "sg:address":"469 Heidelberg Rd",
    "sg:city":"Fairfield",
    "sg:classifiers":[
        {
            "category":"Professional",
            "subcategory":"Business Services",
            "type":"Services"
        }
    ],
    "sg:phone":"+61 3 9486 4588",
    "sg:postcode":"3078",
    "sg:province":"VIC",
    "sg:tags":[
        "exporter"
    ],
    "wof:name":"Winemarketers",
    "wof:placetype":"venue"
},
  "geometry": {"coordinates":[145.01919555699999,-37.7829322815],"type":"Point"}
}