{
  "type": "Feature",
  "properties": {
    "addr:full":"23 First Ave Sunshine VIC 3020",
    "addr:housenumber":"23",
    "addr:postcode":"3020",
    "addr:street":"First Ave",
    "iso:country":"AU",
    "sg:address":"23 First Ave",
    "sg:city":"Sunshine",
    "sg:classifiers":[
        {
            "category":"Home & Garden",
            "subcategory":"Building Materials",
            "type":"Retail Goods"
        }
    ],
    "sg:phone":"+61 3 9310 1288",
    "sg:postcode":"3020",
    "sg:province":"VIC",
    "sg:tags":[
        "gate"
    ],
    "wof:name":"E & M General Steel",
    "wof:placetype":"venue"
},
  "geometry": {"coordinates":[144.83691400000001,-37.797852],"type":"Point"}
}