{
  "type": "Feature",
  "properties": {
    "addr:full":"2 Fonts Pl Bayswater WA 6053",
    "addr:housenumber":"2",
    "addr:postcode":"6053",
    "addr:street":"Fonts Pl",
    "iso:country":"AU",
    "sg:address":"2 Fonts Pl",
    "sg:city":"Bayswater",
    "sg:classifiers":[
        {
            "category":"Autos & Motor Vehicles",
            "subcategory":"Auto Supplies",
            "type":"Retail Goods"
        }
    ],
    "sg:phone":"+61 8 9377 0080",
    "sg:postcode":"6053",
    "sg:province":"WA",
    "sg:tags":[
        "wheel",
        "four",
        "equipment",
        "drive",
        "accessory"
    ],
    "wof:name":"Rovacraft",
    "wof:placetype":"venue"
},
  "geometry": {"coordinates":[115.922889709,-31.8957576752],"type":"Point"}
}