{
  "type": "Feature",
  "properties": {
    "addr:full":"1101 Latrobe St Ballarat VIC 3350",
    "addr:housenumber":"1101",
    "addr:postcode":"3350",
    "addr:street":"Latrobe St",
    "iso:country":"AU",
    "sg:address":"1101 Latrobe St",
    "sg:city":"Ballarat",
    "sg:classifiers":[
        {
            "category":"Fast Food",
            "type":"Food & Drink"
        }
    ],
    "sg:phone":"+61 3 5335 9296",
    "sg:postcode":"3350",
    "sg:province":"VIC",
    "sg:tags":[
        "away",
        "take"
    ],
    "wof:name":"Latrobe Take-Away-Foods",
    "wof:placetype":"venue"
},
  "geometry": {"coordinates":[143.817184,-37.570709],"type":"Point"}
}