{
  "type": "Feature",
  "properties": {
    "addr:full":"108 Wavely St Bucasia QLD 4750",
    "addr:housenumber":"108",
    "addr:postcode":"4750",
    "addr:street":"Wavely St",
    "iso:country":"AU",
    "sg:address":"108 Wavely St",
    "sg:city":"Bucasia",
    "sg:classifiers":[
        {
            "category":"Building & Trades",
            "subcategory":"Construction",
            "type":"Services"
        }
    ],
    "sg:phone":"+61 419 804 757",
    "sg:postcode":"4750",
    "sg:province":"QLD",
    "sg:tags":[
        "roof"
    ],
    "wof:name":"Paul Fawcett",
    "wof:placetype":"venue"
},
  "geometry": {"coordinates":[149.15954600000001,-21.030525],"type":"Point"}
}