{
  "type": "Feature",
  "properties": {
    "addr:full":"35 Cornish St Sunbury VIC 3429",
    "addr:housenumber":"35",
    "addr:postcode":"3429",
    "addr:street":"Cornish St",
    "iso:country":"AU",
    "sg:address":"35 Cornish St",
    "sg:city":"Sunbury",
    "sg:classifiers":[
        {
            "category":"Social Services",
            "subcategory":"Child Care",
            "type":"Services"
        }
    ],
    "sg:phone":"+61 3 9740 4555",
    "sg:postcode":"3429",
    "sg:province":"VIC",
    "wof:name":"Melbourne Kids",
    "wof:placetype":"venue"
},
  "geometry": {"coordinates":[144.719192505,-37.5749359131],"type":"Point"}
}