{
  "type": "Feature",
  "properties": {
    "addr:full":"15 Thorne St Wynnum QLD 4178",
    "addr:housenumber":"15",
    "addr:postcode":"4178",
    "addr:street":"Thorne St",
    "iso:country":"AU",
    "sg:address":"15 Thorne St",
    "sg:city":"Wynnum",
    "sg:classifiers":[
        {
            "category":"Professional",
            "type":"Services"
        }
    ],
    "sg:phone":"+61 7 3396 2471",
    "sg:postcode":"4178",
    "sg:province":"QLD",
    "sg:tags":[
        "spray",
        "painting"
    ],
    "wof:name":"Roberts Smash Repairs",
    "wof:placetype":"venue"
},
  "geometry": {"coordinates":[153.16755676299999,-27.4391708374],"type":"Point"}
}