{
  "type": "Feature",
  "properties": {
    "addr:full":"17C Brougham St Eltham VIC 3095",
    "addr:housenumber":"17c",
    "addr:postcode":"3095",
    "addr:street":"Brougham St",
    "iso:country":"AU",
    "sg:address":"17C Brougham St",
    "sg:city":"Eltham",
    "sg:classifiers":[
        {
            "category":"Transit Center",
            "subcategory":"Passenger",
            "type":"Transportation"
        }
    ],
    "sg:phone":"+61 3 9439 7499",
    "sg:postcode":"3095",
    "sg:province":"VIC",
    "sg:tags":[
        "wood",
        "moulding",
        "plastic"
    ],
    "wof:name":"Technical Mouldings",
    "wof:placetype":"venue"
},
  "geometry": {"coordinates":[145.1381073,-37.7215881348],"type":"Point"}
}