{
  "type": "Feature",
  "properties": {
    "addr:full":"1st Floor / 324 Wickham St Fortitude Valley QLD 4006",
    "addr:housenumber":"/ 324",
    "addr:postcode":"4006",
    "addr:street":"Wickham St",
    "iso:country":"AU",
    "sg:address":"1st Floor / 324 Wickham St",
    "sg:city":"Fortitude Valley",
    "sg:classifiers":[
        {
            "category":"Sports & Exercise",
            "subcategory":"Gym",
            "type":"Entertainment"
        }
    ],
    "sg:phone":"+61 7 3216 1234",
    "sg:postcode":"4006",
    "sg:province":"QLD",
    "sg:tags":[
        "personal",
        "trainer",
        "fitness"
    ],
    "wof:name":"What Women Want Personal Training",
    "wof:placetype":"venue"
},
  "geometry": {"coordinates":[153.034912109,-27.455997467],"type":"Point"}
}