{
  "type": "Feature",
  "properties": {
    "addr:full":"Lot 10 South West Hwy Picton WA 6229",
    "addr:postcode":"6229",
    "addr:street":"South West Hwy",
    "iso:country":"AU",
    "sg:address":"Lot 10 South West Hwy",
    "sg:city":"Picton",
    "sg:classifiers":[
        {
            "category":"Manufacturing",
            "subcategory":"Building Materials",
            "type":"Manufacturing & Wholesale Goods"
        }
    ],
    "sg:phone":"+61 8 9724 6333",
    "sg:postcode":"6229",
    "sg:province":"WA",
    "sg:tags":[
        "equipment",
        "handling"
    ],
    "wof:name":"United Crane Hire",
    "wof:placetype":"venue"
},
  "geometry": {"coordinates":[115.70433800000001,-33.347912],"type":"Point"}
}