{
  "type": "Feature",
  "properties": {
    "iso:country":"AU",
    "sg:address":"Unit 3/ 73 Beauchamp Rd",
    "sg:city":"Matraville",
    "sg:classifiers":[
        {
            "category":"Retail",
            "subcategory":"Car Wash",
            "type":"Services"
        }
    ],
    "sg:phone":"+61 2 9695 7599",
    "sg:postcode":"2036",
    "sg:province":"NSW",
    "sg:tags":[
        "merchant",
        "oil",
        "refiner"
    ],
    "wof:name":"Kerry Australia Pty Ltd",
    "wof:placetype":"venue"
},
  "geometry": {"coordinates":[151.219772339,-33.9610519409],"type":"Point"}
}