{
  "type": "Feature",
  "properties": {
    "iso:country":"AU",
    "sg:address":"Lot 104 Dampier Pl",
    "sg:city":"Prestons",
    "sg:classifiers":[
        {
            "category":"Building & Trades",
            "subcategory":"Construction",
            "type":"Services"
        }
    ],
    "sg:phone":"+61 2 9608 9100",
    "sg:postcode":"2170",
    "sg:province":"NSW",
    "sg:tags":[
        "fencing",
        "contractor"
    ],
    "wof:name":"5 Star Fencing & Gates",
    "wof:placetype":"venue"
},
  "geometry": {"coordinates":[150.87878418,-33.9306564331],"type":"Point"}
}