{
  "type": "Feature",
  "properties": {
    "iso:country":"AU",
    "sg:address":"Arndale Shopping Centre Cinderella Drv",
    "sg:city":"Springwood",
    "sg:classifiers":[
        {
            "category":"Shopping",
            "subcategory":"Clothing, Apparel, & Fashions",
            "type":"Retail Goods"
        }
    ],
    "sg:phone":"+61 7 3208 4867",
    "sg:postcode":"4127",
    "sg:province":"QLD",
    "sg:tags":[
        "hire",
        "men's",
        "wear",
        "formal"
    ],
    "wof:name":"Top Hat Formal Hire",
    "wof:placetype":"venue"
},
  "geometry": {"coordinates":[153.13267517099999,-27.6164894104],"type":"Point"}
}