{
  "type": "Feature",
  "properties": {
    "addr:full":"Unit 7/ 77- 79 Batt St Penrith NSW 2750",
    "addr:housenumber":"79",
    "addr:postcode":"2750",
    "addr:street":"Batt St",
    "iso:country":"AU",
    "sg:address":"Unit 7/ 77- 79 Batt St",
    "sg:city":"Penrith",
    "sg:classifiers":[
        {
            "category":"Building & Trades",
            "subcategory":"Construction",
            "type":"Services"
        }
    ],
    "sg:phone":"+61 1300 307 174",
    "sg:postcode":"2750",
    "sg:province":"NSW",
    "sg:tags":[
        "welding"
    ],
    "wof:name":"Martins Welding & Engineering Services",
    "wof:placetype":"venue"
},
  "geometry": {"coordinates":[150.68504333499999,-33.7677459717],"type":"Point"}
}