{
  "type": "Feature",
  "properties": {
    "addr:full":"20 Merridown Drv Merrimac QLD 4226",
    "addr:housenumber":"20",
    "addr:postcode":"4226",
    "addr:street":"Merridown Drv",
    "iso:country":"AU",
    "sg:address":"20 Merridown Drv",
    "sg:city":"Merrimac",
    "sg:classifiers":[
        {
            "category":"Retail",
            "subcategory":"Repair Shop",
            "type":"Services"
        }
    ],
    "sg:phone":"+61 412 656 441",
    "sg:postcode":"4226",
    "sg:province":"QLD",
    "sg:tags":[
        "maintenance",
        "pool",
        "swimming"
    ],
    "wof:name":"Maintain-A-Pool",
    "wof:placetype":"venue"
},
  "geometry": {"coordinates":[153.35743713400001,-28.0459327698],"type":"Point"}
}