{
  "type": "Feature",
  "properties": {
    "addr:full":"2/ 4 Woolunga Ave Terrigal NSW 2260",
    "addr:housenumber":"/ 4",
    "addr:postcode":"2260",
    "addr:street":"Woolunga Ave",
    "iso:country":"AU",
    "sg:address":"2/ 4 Woolunga Ave",
    "sg:city":"Terrigal",
    "sg:classifiers":[
        {
            "category":"Personal",
            "subcategory":"Massage",
            "type":"Services"
        }
    ],
    "sg:phone":"+61 2 4385 2825",
    "sg:postcode":"2260",
    "sg:province":"NSW",
    "sg:tags":[
        "therapy"
    ],
    "wof:name":"Leisemann Joanne",
    "wof:placetype":"venue"
},
  "geometry": {"coordinates":[151.44700599999999,-33.451641],"type":"Point"}
}