{
  "type": "Feature",
  "properties": {
    "iso:country":"AU",
    "sg:address":"68 Cornwall St",
    "sg:city":"Katanning",
    "sg:classifiers":[
        {
            "category":"Autos & Motor Vehicles",
            "subcategory":"Fuel & Gas Station",
            "type":"Retail Goods"
        }
    ],
    "sg:phone":"+61 8 9821 2165",
    "sg:postcode":"6317",
    "sg:province":"WA",
    "wof:name":"B.P. Road House Katanning",
    "wof:placetype":"venue"
},
  "geometry": {"coordinates":[117.560470581,-33.7012329102],"type":"Point"}
}