{
  "type": "Feature",
  "properties": {
    "addr:full":"Level 11/ 68 Grenfell St Adelaide SA 5000",
    "addr:housenumber":"/ 68",
    "addr:postcode":"5000",
    "addr:street":"Grenfell St",
    "iso:country":"AU",
    "sg:address":"Level 11/ 68 Grenfell St",
    "sg:city":"Adelaide",
    "sg:classifiers":[
        {
            "category":"Farming",
            "subcategory":"Berry Farm",
            "type":"Manufacturing & Wholesale Goods"
        }
    ],
    "sg:phone":"+61 8 8223 2717",
    "sg:postcode":"5000",
    "sg:province":"SA",
    "sg:tags":[
        "fruit",
        "grower"
    ],
    "wof:name":"Quorn Quandongs Pty Ltd",
    "wof:placetype":"venue"
},
  "geometry": {"coordinates":[138.60220336899999,-34.9240455627],"type":"Point"}
}