{
  "type": "Feature",
  "properties": {
    "iso:country":"AU",
    "sg:address":"163 Marconi Rd",
    "sg:city":"Bonnells Bay",
    "sg:classifiers":[
        {
            "category":"Building & Trades",
            "subcategory":"Plumbing",
            "type":"Services"
        }
    ],
    "sg:phone":"+61 2 4973 1125",
    "sg:postcode":"2264",
    "sg:province":"NSW",
    "sg:tags":[
        "plumber",
        "gasfitters"
    ],
    "wof:name":"Bradshaw L & C",
    "wof:placetype":"venue"
},
  "geometry": {"coordinates":[151.50572199999999,-33.103416],"type":"Point"}
}