{
  "type": "Feature",
  "properties": {
    "iso:country":"AU",
    "sg:address":"Odeon Theatre, 1 Queen St",
    "sg:city":"Norwood",
    "sg:classifiers":[
        {
            "category":"Education",
            "subcategory":"Special Training",
            "type":"Public Place"
        }
    ],
    "sg:phone":"+61 411 121 960",
    "sg:postcode":"5067",
    "sg:province":"SA",
    "sg:tags":[
        "drama",
        "tuition"
    ],
    "wof:name":"Shane Davidson Presents.....",
    "wof:placetype":"venue"
},
  "geometry": {"coordinates":[138.638183594,-34.9150733948],"type":"Point"}
}