{
  "type": "Feature",
  "properties": {
    "addr:full":"18 Noble Ave Northgate QLD 4013",
    "addr:housenumber":"18",
    "addr:postcode":"4013",
    "addr:street":"Noble Ave",
    "iso:country":"AU",
    "sg:address":"18 Noble Ave",
    "sg:city":"Northgate",
    "sg:classifiers":[
        {
            "category":"Home & Garden",
            "subcategory":"Building Materials",
            "type":"Retail Goods"
        }
    ],
    "sg:phone":"+61 7 3260 6144",
    "sg:postcode":"4013",
    "sg:province":"QLD",
    "sg:tags":[
        "merchant",
        "glass",
        "glazier"
    ],
    "wof:name":"Tank Stream",
    "wof:placetype":"venue"
},
  "geometry": {"coordinates":[153.07388305699999,-27.385602951],"type":"Point"}
}