{
  "type": "Feature",
  "properties": {
    "addr:full":"Shop 6, Centro Toombul Sandgate Rd Toombul QLD 4012",
    "addr:housenumber":"shop 6",
    "addr:postcode":"4012",
    "addr:street":"Sandgate Rd",
    "iso:country":"AU",
    "sg:address":"Shop 6, Centro Toombul Sandgate Rd",
    "sg:city":"Toombul",
    "sg:classifiers":[
        {
            "category":"Shopping",
            "subcategory":"Optical Goods",
            "type":"Retail Goods"
        }
    ],
    "sg:phone":"+61 7 3256 6188",
    "sg:postcode":"4012",
    "sg:province":"QLD",
    "sg:tags":[
        "dispenser",
        "prescription"
    ],
    "wof:name":"The Optical Superstore",
    "wof:placetype":"venue"
},
  "geometry": {"coordinates":[153.05982971200001,-27.4076595306],"type":"Point"}
}