{
  "type": "Feature",
  "properties": {
    "iso:country":"AU",
    "sg:address":"5a Stanley St",
    "sg:city":"Wodonga",
    "sg:classifiers":[
        {
            "category":"Banks & Credit Unions",
            "subcategory":"Financial Services",
            "type":"Services"
        }
    ],
    "sg:phone":"+61 2 6024 2030",
    "sg:postcode":"3690",
    "sg:province":"NSW",
    "sg:tags":[
        "loan",
        "finance",
        "mortgage"
    ],
    "wof:name":"Mortgage Finance Solutions",
    "wof:placetype":"venue"
},
  "geometry": {"coordinates":[146.88758850100001,-36.1225166321],"type":"Point"}
}