{
  "type": "Feature",
  "properties": {
    "addr:full":"111 Goss Rd Virginia QLD 4014",
    "addr:housenumber":"111",
    "addr:postcode":"4014",
    "addr:street":"Goss Rd",
    "iso:country":"AU",
    "sg:address":"111 Goss Rd",
    "sg:city":"Virginia",
    "sg:classifiers":[
        {
            "category":"Building & Trades",
            "subcategory":"Construction",
            "type":"Services"
        }
    ],
    "sg:phone":"+61 7 3266 2890",
    "sg:postcode":"4014",
    "sg:province":"QLD",
    "sg:tags":[
        "decking",
        "contractor"
    ],
    "sg:website":"http://www.homeshield.com.au",
    "wof:name":"Homeshield",
    "wof:placetype":"venue"
},
  "geometry": {"coordinates":[153.05426025400001,-27.3854179382],"type":"Point"}
}