{
  "type": "Feature",
  "properties": {
    "addr:full":"Suite 1201 Colonial Mutual life 14 Martin Pl Sydney NSW 2000",
    "addr:housenumber":"1201;14",
    "addr:postcode":"2000",
    "addr:street":"Colonial;Martin Pl",
    "iso:country":"AU",
    "sg:address":"Suite 1201 Colonial Mutual life 14 Martin Pl",
    "sg:city":"Sydney",
    "sg:classifiers":[
        {
            "category":"Health Services",
            "subcategory":"Dentist",
            "type":"Services"
        }
    ],
    "sg:phone":"+61 2 9232 8599",
    "sg:postcode":"2000",
    "sg:province":"NSW",
    "wof:name":"Stow Leonard J",
    "wof:placetype":"venue"
},
  "geometry": {"coordinates":[151.2081604,-33.8673744202],"type":"Point"}
}