{
  "type": "Feature",
  "properties": {
    "addr:full":"Unit 6 7 Clearview Pl Brookvale NSW 2100",
    "addr:housenumber":"7",
    "addr:postcode":"2100",
    "addr:street":"Pl",
    "iso:country":"AU",
    "sg:address":"Unit 6 7 Clearview Pl",
    "sg:city":"Brookvale",
    "sg:classifiers":[
        {
            "category":"Shopping",
            "subcategory":"Computers & Home Electronics",
            "type":"Retail Goods"
        }
    ],
    "sg:phone":"+61 2 9905 2044",
    "sg:postcode":"2100",
    "sg:province":"NSW",
    "sg:tags":[
        "equipment",
        "supply"
    ],
    "wof:name":"Combined Toner Services",
    "wof:placetype":"venue"
},
  "geometry": {"coordinates":[151.262252808,-33.7620925903],"type":"Point"}
}