{
  "type": "Feature",
  "properties": {
    "addr:full":"19 Lawley St Dicky Beach QLD 4551",
    "addr:housenumber":"19",
    "addr:postcode":"4551",
    "addr:street":"Lawley St",
    "iso:country":"AU",
    "sg:address":"19 Lawley St",
    "sg:city":"Dicky Beach",
    "sg:classifiers":[
        {
            "category":"Autos & Motor Vehicles",
            "subcategory":"Boat Sales",
            "type":"Retail Goods"
        }
    ],
    "sg:phone":"+61 7 5491 9492",
    "sg:postcode":"4551",
    "sg:province":"QLD",
    "sg:tags":[
        "builder",
        "yacht",
        "repairer"
    ],
    "wof:name":"Bauer Boat Building",
    "wof:placetype":"venue"
},
  "geometry": {"coordinates":[153.13340759299999,-26.7874145508],"type":"Point"}
}