{
  "type": "Feature",
  "properties": {
    "iso:country":"AU",
    "sg:address":"Silky Oak Drv",
    "sg:city":"Aberglasslyn",
    "sg:classifiers":[
        {
            "category":"Building & Trades",
            "subcategory":"Landscaping Services",
            "type":"Services"
        }
    ],
    "sg:phone":"+61 417 422 975",
    "sg:postcode":"2320",
    "sg:province":"NSW",
    "sg:tags":[
        "designer",
        "landscape",
        "contractor"
    ],
    "wof:name":"Randall's Bobcat Hire",
    "wof:placetype":"venue"
},
  "geometry": {"coordinates":[151.525146484,-32.6968765259],"type":"Point"}
}