{
  "type": "Feature",
  "properties": {
    "addr:full":"2232b Albany Hwy Gosnells WA 6110",
    "addr:housenumber":"2232b",
    "addr:postcode":"6110",
    "addr:street":"Albany Hwy",
    "iso:country":"AU",
    "sg:address":"2232b Albany Hwy",
    "sg:city":"Gosnells",
    "sg:classifiers":[
        {
            "category":"Professional",
            "subcategory":"Management & Consulting",
            "type":"Services"
        }
    ],
    "sg:phone":"+61 8 9398 6333",
    "sg:postcode":"6110",
    "sg:province":"WA",
    "sg:tags":[
        "consultant",
        "business"
    ],
    "wof:name":"Gosnells Centre For Business Development",
    "wof:placetype":"venue"
},
  "geometry": {"coordinates":[116.00469207800001,-32.0736274719],"type":"Point"}
}