{
  "type": "Feature",
  "properties": {
    "addr:full":"Camford Sq Cnr Douglas & Dorsey St Milton QLD 4064",
    "addr:postcode":"4064",
    "addr:street":"Camford Sq Cnr Douglas & Dorsey St",
    "iso:country":"AU",
    "sg:address":"Camford Sq Cnr Douglas & Dorsey St",
    "sg:city":"Milton",
    "sg:classifiers":[
        {
            "category":"Shopping",
            "subcategory":"Antiques",
            "type":"Retail Goods"
        }
    ],
    "sg:phone":"+61 7 3368 1167",
    "sg:postcode":"4064",
    "sg:province":"QLD",
    "wof:name":"Antique Print & Map Company",
    "wof:placetype":"venue"
},
  "geometry": {"coordinates":[153.00335693400001,-27.4717903137],"type":"Point"}
}