{
  "type": "Feature",
  "properties": {
    "iso:country":"AU",
    "sg:address":"7 Anson St",
    "sg:city":"Taminda",
    "sg:classifiers":[
        {
            "category":"Retail",
            "subcategory":"Auto Repair",
            "type":"Services"
        }
    ],
    "sg:phone":"+61 2 6762 5711",
    "sg:postcode":"2340",
    "sg:province":"NSW",
    "sg:tags":[
        "repairer",
        "motor",
        "engineer"
    ],
    "wof:name":"Xcessive Performace Tamworth",
    "wof:placetype":"venue"
},
  "geometry": {"coordinates":[150.91029357900001,-31.0889034271],"type":"Point"}
}