{
  "type": "Feature",
  "properties": {
    "addr:full":"127 Barrier Reef Drv Robina QLD 4226",
    "addr:housenumber":"127",
    "addr:postcode":"4226",
    "addr:street":"Barrier Reef Drv",
    "iso:country":"AU",
    "sg:address":"127 Barrier Reef Drv",
    "sg:city":"Robina",
    "sg:classifiers":[
        {
            "category":"Education",
            "subcategory":"University",
            "type":"Public Place"
        }
    ],
    "sg:phone":"+61 7 5575 3295",
    "sg:postcode":"4226",
    "sg:province":"QLD",
    "sg:tags":[
        "educational",
        "organisation",
        "cultural"
    ],
    "wof:name":"Theatre Organ Society of Australia",
    "wof:placetype":"venue"
},
  "geometry": {"coordinates":[153.410522461,-28.0480823517],"type":"Point"}
}