{
  "type": "Feature",
  "properties": {
    "iso:country":"AU",
    "sg:address":"Abberhill Rd",
    "sg:city":"Melrose",
    "sg:classifiers":[
        {
            "category":"Farming",
            "subcategory":"Farm",
            "type":"Manufacturing & Wholesale Goods"
        }
    ],
    "sg:phone":"+61 8 8666 2196",
    "sg:postcode":"5483",
    "sg:province":"SA",
    "sg:tags":[
        "farmer"
    ],
    "wof:name":"Blieschke K A & K D",
    "wof:placetype":"venue"
},
  "geometry": {"coordinates":[138.182403564,-32.8062210083],"type":"Point"}
}