{
  "type": "Feature",
  "properties": {
    "iso:country":"AU",
    "sg:address":"Graceville Fiveways 7 Park Tce",
    "sg:city":"Graceville",
    "sg:classifiers":[
        {
            "category":"Health Services",
            "subcategory":"Doctor",
            "type":"Services"
        }
    ],
    "sg:phone":"+61 7 3379 1831",
    "sg:postcode":"4075",
    "sg:province":"QLD",
    "sg:tags":[
        "medical",
        "practitioner"
    ],
    "wof:name":"Laserlight Skin Clinic",
    "wof:placetype":"venue"
},
  "geometry": {"coordinates":[152.98178100600001,-27.5219535828],"type":"Point"}
}