{
  "type": "Feature",
  "properties": {
    "addr:full":"Unit 1/ 14 Penrith St Penrith NSW 2750",
    "addr:housenumber":"14",
    "addr:postcode":"2750",
    "addr:street":"Penrith St",
    "iso:country":"AU",
    "sg:address":"Unit 1/ 14 Penrith St",
    "sg:city":"Penrith",
    "sg:classifiers":[
        {
            "category":"Building & Trades",
            "subcategory":"Locksmith",
            "type":"Services"
        }
    ],
    "sg:phone":"+61 2 4722 2898",
    "sg:postcode":"2750",
    "sg:province":"NSW",
    "sg:tags":[
        "lock"
    ],
    "wof:name":"Lock -It Systems Pty Ltd",
    "wof:placetype":"venue"
},
  "geometry": {"coordinates":[150.68374633799999,-33.7668762207],"type":"Point"}
}