{
  "type": "Feature",
  "properties": {
    "addr:full":"166a King William Rd Hyde Park SA 5061",
    "addr:housenumber":"166a",
    "addr:postcode":"5061",
    "addr:street":"King William Rd",
    "iso:country":"AU",
    "sg:address":"166a King William Rd",
    "sg:city":"Hyde Park",
    "sg:classifiers":[
        {
            "category":"Banks & Credit Unions",
            "subcategory":"Bank",
            "type":"Services"
        }
    ],
    "sg:phone":"+61 1300 669 021",
    "sg:postcode":"5061",
    "sg:province":"SA",
    "sg:tags":[
        "broker",
        "mortgage"
    ],
    "wof:name":"Cathy Anderson Finance Pty Ltd",
    "wof:placetype":"venue"
},
  "geometry": {"coordinates":[138.59994506800001,-34.9553909302],"type":"Point"}
}