{
  "type": "Feature",
  "properties": {
    "addr:full":"PO Box 79BK Black Hill VIC 3350",
    "addr:postcode":"3350",
    "iso:country":"AU",
    "sg:address":"PO Box 79BK",
    "sg:city":"Black Hill",
    "sg:classifiers":[
        {
            "category":"Professional",
            "subcategory":"Art Services",
            "type":"Services"
        }
    ],
    "sg:phone":"+61 3 5335 8668",
    "sg:postcode":"3350",
    "sg:province":"VIC",
    "sg:tags":[
        "interior",
        "decorator"
    ],
    "wof:name":"New Aspect Painting & Decorating Pty Ltd",
    "wof:placetype":"venue"
},
  "geometry": {"coordinates":[143.869675,-37.549999],"type":"Point"}
}