{
  "type": "Feature",
  "properties": {
    "addr:full":"110 Bradley St Guyra NSW 2365",
    "addr:housenumber":"110",
    "addr:postcode":"2365",
    "addr:street":"Bradley St",
    "iso:country":"AU",
    "sg:address":"110 Bradley St",
    "sg:city":"Guyra",
    "sg:classifiers":[
        {
            "category":"Cafe",
            "type":"Food & Drink"
        }
    ],
    "sg:phone":"+61 2 6779 1600",
    "sg:postcode":"2365",
    "sg:province":"NSW",
    "wof:name":"Cafe 627",
    "wof:placetype":"venue"
},
  "geometry": {"coordinates":[151.67166137699999,-30.2184391022],"type":"Point"}
}