{
  "type": "Feature",
  "properties": {
    "iso:country":"AU",
    "sg:address":"5- 7 Sydney St",
    "sg:city":"Redcliffe",
    "sg:classifiers":[
        {
            "category":"Social Services",
            "subcategory":"Retirement Home",
            "type":"Services"
        }
    ],
    "sg:phone":"+61 7 3284 2498",
    "sg:postcode":"4020",
    "sg:province":"QLD",
    "sg:tags":[
        "village"
    ],
    "wof:name":"Peninsula Terraces & Haven Retirement Complex",
    "wof:placetype":"venue"
},
  "geometry": {"coordinates":[153.10566700000001,-27.233469],"type":"Point"}
}