{
  "type": "Feature",
  "properties": {
    "iso:country":"AU",
    "sg:address":"Suite 7, 90 Sorrell St",
    "sg:city":"North Parramatta",
    "sg:classifiers":[
        {
            "category":"Retail",
            "subcategory":"Driving School",
            "type":"Services"
        }
    ],
    "sg:phone":"+61 2 9683 7839",
    "sg:postcode":"2151",
    "sg:province":"NSW",
    "wof:name":"Ample Driving School",
    "wof:placetype":"venue"
},
  "geometry": {"coordinates":[151.008666992,-33.8008575439],"type":"Point"}
}