{
  "type": "Feature",
  "properties": {
    "iso:country":"AU",
    "sg:address":"Fishermans Bay Rd",
    "sg:city":"Port Broughton",
    "sg:classifiers":[
        {
            "category":"Farming",
            "subcategory":"Fish & Marine Products",
            "type":"Manufacturing & Wholesale Goods"
        }
    ],
    "sg:phone":"+61 8 8635 2015",
    "sg:postcode":"5522",
    "sg:province":"SA",
    "sg:tags":[
        "fisherman"
    ],
    "wof:name":"Dunstan R P",
    "wof:placetype":"venue"
},
  "geometry": {"coordinates":[137.94404602,-33.5449638367],"type":"Point"}
}