{
  "type": "Feature",
  "properties": {
    "iso:country":"AU",
    "sg:address":"Unit 2A 9-11 Enterprise St",
    "sg:city":"Molendinar",
    "sg:phone":"+61 7 5597 5750",
    "sg:postcode":"4214",
    "sg:province":"QLD",
    "wof:name":"Tank Werx",
    "wof:placetype":"venue"
},
  "geometry": {"coordinates":[153.37736511200001,-27.9779682159],"type":"Point"}
}