{
  "type": "Feature",
  "properties": {
    "iso:country":"AU",
    "sg:address":"1364 North Rd",
    "sg:city":"Oakleigh South",
    "sg:classifiers":[
        {
            "category":"Professional",
            "type":"Services"
        }
    ],
    "sg:phone":"+61 3 9543 3911",
    "sg:postcode":"3167",
    "sg:province":"VIC",
    "sg:tags":[
        "shop",
        "fitting"
    ],
    "wof:name":"Audsley Windows Pty Ltd",
    "wof:placetype":"venue"
},
  "geometry": {"coordinates":[145.11082458499999,-37.9127426147],"type":"Point"}
}