{
  "type": "Feature",
  "properties": {
    "addr:full":"54 Currie St Adelaide SA 5000",
    "addr:housenumber":"54",
    "addr:postcode":"5000",
    "addr:street":"Currie St",
    "iso:country":"AU",
    "sg:address":"54 Currie St",
    "sg:city":"Adelaide",
    "sg:classifiers":[
        {
            "category":"Professional",
            "subcategory":"Art Services",
            "type":"Services"
        }
    ],
    "sg:phone":"+61 8 8415 5153",
    "sg:postcode":"5000",
    "sg:province":"SA",
    "sg:tags":[
        "graphic",
        "designer"
    ],
    "wof:name":"Friendly Business Solutions",
    "wof:placetype":"venue"
},
  "geometry": {"coordinates":[138.59750366200001,-34.9242515564],"type":"Point"}
}