{
  "type": "Feature",
  "properties": {
    "addr:full":"335 Sth Gippsland Hwy Dandenong VIC 3175",
    "addr:housenumber":"335",
    "addr:postcode":"3175",
    "addr:street":"Sth Gippsland Hwy",
    "iso:country":"AU",
    "sg:address":"335 Sth Gippsland Hwy",
    "sg:city":"Dandenong",
    "sg:classifiers":[
        {
            "category":"Taxi",
            "type":"Transportation"
        }
    ],
    "sg:phone":"+61 1300 887 954",
    "sg:postcode":"3175",
    "sg:province":"VIC",
    "sg:tags":[
        "truck"
    ],
    "wof:name":"Atlas Transport & Carriers Agents",
    "wof:placetype":"venue"
},
  "geometry": {"coordinates":[145.22564697300001,-38.0010070801],"type":"Point"}
}