{
  "type": "Feature",
  "properties": {
    "iso:country":"AU",
    "sg:address":"Lvl1/ CBD House 120 Wickham St",
    "sg:city":"Fortitude Valley",
    "sg:classifiers":[
        {
            "category":"Building & Trades",
            "subcategory":"Construction",
            "type":"Services"
        }
    ],
    "sg:phone":"+61 7 3251 6000",
    "sg:postcode":"4006",
    "sg:province":"QLD",
    "sg:tags":[
        "contractor"
    ],
    "wof:name":"CBD",
    "wof:placetype":"venue"
},
  "geometry": {"coordinates":[153.031692505,-27.4594135284],"type":"Point"}
}