{
  "type": "Feature",
  "properties": {
    "addr:full":"600 Little Bourke Street Melbourne VIC 3000",
    "addr:housenumber":"600",
    "addr:postcode":"3000",
    "addr:street":"Little Bourke Street",
    "iso:country":"AU",
    "sg:address":"600 Little Bourke Street",
    "sg:city":"Melbourne",
    "sg:classifiers":[
        {
            "category":"Travel",
            "subcategory":"Hotels & Motels",
            "type":"Entertainment"
        }
    ],
    "sg:phone":"+61 3 9672 0000",
    "sg:postcode":"3000",
    "sg:province":"VIC",
    "sg:tags":[
        "accommodation"
    ],
    "wof:name":"Ibis Little Bourke Street",
    "wof:placetype":"venue"
},
  "geometry": {"coordinates":[144.954620361,-37.815448761],"type":"Point"}
}