{
  "type": "Feature",
  "properties": {
    "addr:full":"41 Wodonga St Beverley SA 5009",
    "addr:housenumber":"41",
    "addr:postcode":"5009",
    "addr:street":"Wodonga St",
    "iso:country":"AU",
    "sg:address":"41 Wodonga St",
    "sg:city":"Beverley",
    "sg:classifiers":[
        {
            "category":"Communications",
            "subcategory":"Film & Video Production",
            "type":"Services"
        }
    ],
    "sg:phone":"+61 8 8347 0002",
    "sg:postcode":"5009",
    "sg:province":"SA",
    "sg:tags":[
        "mirror"
    ],
    "wof:name":"Fastlane Bar Mirrors",
    "wof:placetype":"venue"
},
  "geometry": {"coordinates":[138.54278564399999,-34.8941307068],"type":"Point"}
}