{
  "type": "Feature",
  "properties": {
    "addr:full":"Suite 4/ 23 Brisbane St Launceston TAS 7250",
    "addr:housenumber":"23",
    "addr:postcode":"7250",
    "addr:street":"Brisbane St",
    "iso:country":"AU",
    "sg:address":"Suite 4/ 23 Brisbane St",
    "sg:city":"Launceston",
    "sg:classifiers":[
        {
            "category":"Health Services",
            "subcategory":"Doctor",
            "type":"Services"
        }
    ],
    "sg:phone":"+61 3 6331 6088",
    "sg:postcode":"7250",
    "sg:province":"TAS",
    "sg:tags":[
        "medical",
        "practitioner"
    ],
    "wof:name":"Butorac Roger",
    "wof:placetype":"venue"
},
  "geometry": {"coordinates":[147.14320373499999,-41.4340744019],"type":"Point"}
}