{
  "type": "Feature",
  "properties": {
    "addr:full":"27 Pepperell Ave Glen Waverley VIC 3150",
    "addr:housenumber":"27",
    "addr:postcode":"3150",
    "addr:street":"Pepperell Ave",
    "iso:country":"AU",
    "sg:address":"27 Pepperell Ave",
    "sg:city":"Glen Waverley",
    "sg:classifiers":[
        {
            "category":"Personal",
            "type":"Services"
        }
    ],
    "sg:phone":"+61 3 9802 3408",
    "sg:postcode":"3150",
    "sg:province":"VIC",
    "sg:tags":[
        "dressmaker"
    ],
    "wof:name":"Miss Lynda",
    "wof:placetype":"venue"
},
  "geometry": {"coordinates":[145.15107727,-37.8793640137],"type":"Point"}
}