{
  "type": "Feature",
  "properties": {
    "addr:full":"Shp3/ 19 Channon St Gympie QLD 4570",
    "addr:postcode":"4570",
    "addr:street":"Channon St",
    "iso:country":"AU",
    "sg:address":"Shp3/ 19 Channon St",
    "sg:city":"Gympie",
    "sg:classifiers":[
        {
            "category":"Personal",
            "type":"Services"
        }
    ],
    "sg:phone":"+61 7 5481 1107",
    "sg:postcode":"4570",
    "sg:province":"QLD",
    "sg:tags":[
        "reducing",
        "treatment",
        "weight"
    ],
    "wof:name":"Tony Ferguson Weight Loss Gympie",
    "wof:placetype":"venue"
},
  "geometry": {"coordinates":[152.65782165499999,-26.1889686584],"type":"Point"}
}