{
  "type": "Feature",
  "properties": {
    "iso:country":"AU",
    "sg:address":"Suite 108, 1st Floor 284 Victoria Ave",
    "sg:city":"Chatswood",
    "sg:classifiers":[
        {
            "category":"Health Services",
            "subcategory":"Health Practitioner",
            "type":"Services"
        }
    ],
    "sg:phone":"+61 2 9884 7172",
    "sg:postcode":"2057",
    "sg:province":"NSW",
    "sg:tags":[
        "acupuncture"
    ],
    "wof:name":"Licht Nadine",
    "wof:placetype":"venue"
},
  "geometry": {"coordinates":[151.1866,-33.795361],"type":"Point"}
}