{
  "type": "Feature",
  "properties": {
    "addr:full":"Shop 2/ 200 Old Cleveland Rd Capalaba QLD 4157",
    "addr:housenumber":"shop 2 / 200",
    "addr:postcode":"4157",
    "addr:street":"Old Cleveland Rd",
    "iso:country":"AU",
    "sg:address":"Shop 2/ 200 Old Cleveland Rd",
    "sg:city":"Capalaba",
    "sg:classifiers":[
        {
            "category":"Fast Food",
            "type":"Food & Drink"
        }
    ],
    "sg:phone":"+61 7 3823 2033",
    "sg:postcode":"4157",
    "sg:province":"QLD",
    "sg:tags":[
        "away",
        "take"
    ],
    "wof:name":"Subway",
    "wof:placetype":"venue"
},
  "geometry": {"coordinates":[153.19851684599999,-27.5213775635],"type":"Point"}
}