{
  "type": "Feature",
  "properties": {
    "addr:full":"310 Queen St Melbourne VIC 3000",
    "addr:housenumber":"310",
    "addr:postcode":"3000",
    "addr:street":"Queen St",
    "iso:country":"AU",
    "sg:address":"310 Queen St",
    "sg:city":"Melbourne",
    "sg:classifiers":[
        {
            "category":"Insurance",
            "subcategory":"Hazard Insurance",
            "type":"Services"
        }
    ],
    "sg:phone":"+61 3 8602 9900",
    "sg:postcode":"3000",
    "sg:province":"VIC",
    "sg:tags":[
        "fire",
        "accident",
        "marine"
    ],
    "wof:name":"QBE Insurance (Australia) Limited",
    "wof:placetype":"venue"
},
  "geometry": {"coordinates":[144.95939636200001,-37.8117446899],"type":"Point"}
}