{
  "type": "Feature",
  "properties": {
    "iso:country":"AU",
    "sg:address":"185 Waymouth St",
    "sg:city":"Adelaide",
    "sg:classifiers":[
        {
            "category":"Home & Garden",
            "subcategory":"Furniture",
            "type":"Retail Goods"
        }
    ],
    "sg:phone":"+61 8 8211 9229",
    "sg:postcode":"5000",
    "sg:province":"SA",
    "sg:tags":[
        "business"
    ],
    "sg:website":"http://www.officefurnitureplus.com.au",
    "wof:name":"Office Furniture Plus",
    "wof:placetype":"venue"
},
  "geometry": {"coordinates":[138.59892273,-34.9259414673],"type":"Point"}
}