{
  "type": "Feature",
  "properties": {
    "iso:country":"AU",
    "sg:address":"421 Sturt St",
    "sg:city":"Ballarat",
    "sg:classifiers":[
        {
            "category":"Professional",
            "subcategory":"Art Services",
            "type":"Services"
        }
    ],
    "sg:phone":"+61 3 5332 1800",
    "sg:postcode":"3350",
    "sg:province":"VIC",
    "sg:tags":[
        "interior",
        "decorator"
    ],
    "wof:name":"Red Door Rugs & Mats",
    "wof:placetype":"venue"
},
  "geometry": {"coordinates":[143.853714,-37.56179],"type":"Point"}
}