{
  "type": "Feature",
  "properties": {
    "addr:full":"45 Princes Hwy Dapto NSW 2530",
    "addr:housenumber":"45",
    "addr:postcode":"2530",
    "addr:street":"Princes Hwy",
    "iso:country":"AU",
    "sg:address":"45 Princes Hwy",
    "sg:city":"Dapto",
    "sg:classifiers":[
        {
            "category":"Real Estate",
            "subcategory":"Real Estate Agent",
            "type":"Services"
        }
    ],
    "sg:phone":"+61 2 4261 5222",
    "sg:postcode":"2530",
    "sg:province":"NSW",
    "wof:name":"Bevans Real Estate Group - Illawarra",
    "wof:placetype":"venue"
},
  "geometry": {"coordinates":[150.79550170900001,-34.4926376343],"type":"Point"}
}