{
  "type": "Feature",
  "properties": {
    "addr:full":"161 Bradman St Acacia Ridge QLD 4110",
    "addr:housenumber":"161",
    "addr:postcode":"4110",
    "addr:street":"Bradman St",
    "iso:country":"AU",
    "sg:address":"161 Bradman St",
    "sg:city":"Acacia Ridge",
    "sg:classifiers":[
        {
            "category":"Food & Beverages",
            "subcategory":"Fruits & Vegetables",
            "type":"Retail Goods"
        }
    ],
    "sg:phone":"+61 7 3344 1947",
    "sg:postcode":"4110",
    "sg:province":"QLD",
    "sg:tags":[
        "consultant",
        "catering"
    ],
    "wof:name":"Pacific Coast Catering",
    "wof:placetype":"venue"
},
  "geometry": {"coordinates":[153.03851318400001,-27.5825595856],"type":"Point"}
}