{
  "type": "Feature",
  "properties": {
    "addr:full":"4 Bowen St Banana QLD 4702",
    "addr:housenumber":"4",
    "addr:postcode":"4702",
    "addr:street":"Bowen St",
    "iso:country":"AU",
    "sg:address":"4 Bowen St",
    "sg:city":"Banana",
    "sg:classifiers":[
        {
            "category":"Professional",
            "subcategory":"Business Services",
            "type":"Services"
        }
    ],
    "sg:phone":"+61 7 4995 7216",
    "sg:postcode":"4702",
    "sg:province":"QLD",
    "sg:tags":[
        "livestock",
        "transport"
    ],
    "wof:name":"Wilson T & D",
    "wof:placetype":"venue"
},
  "geometry": {"coordinates":[150.128463745,-24.4707336426],"type":"Point"}
}