{
  "type": "Feature",
  "properties": {
    "addr:full":"23 Cronulla St Cronulla NSW 2230",
    "addr:housenumber":"23",
    "addr:postcode":"2230",
    "addr:street":"Cronulla St",
    "iso:country":"AU",
    "sg:address":"23 Cronulla St",
    "sg:city":"Cronulla",
    "sg:classifiers":[
        {
            "category":"Health Services",
            "subcategory":"Optometrist",
            "type":"Services"
        }
    ],
    "sg:phone":"+61 2 9523 5884",
    "sg:postcode":"2230",
    "sg:province":"NSW",
    "wof:name":"Bell Richard Langshaw Stephen, Walshaw Mark, Merton Chantelle, Watkins Kylie",
    "wof:placetype":"venue"
},
  "geometry": {"coordinates":[151.152633667,-34.0524749756],"type":"Point"}
}