{
  "type": "Feature",
  "properties": {
    "iso:country":"AU",
    "sg:address":"9B Phillip St",
    "sg:city":"Burnie",
    "sg:classifiers":[
        {
            "category":"Shopping",
            "subcategory":"Stationery & Office Supplies",
            "type":"Retail Goods"
        }
    ],
    "sg:phone":"+61 3 6331 3631",
    "sg:postcode":"7320",
    "sg:province":"TAS",
    "sg:tags":[
        "packaging",
        "material"
    ],
    "wof:name":"Tasmanian Packaging Solutions",
    "wof:placetype":"venue"
},
  "geometry": {"coordinates":[145.93382299999999,-41.068722],"type":"Point"}
}