{
  "type": "Feature",
  "properties": {
    "addr:full":"1326 Centre Rd Clayton VIC 3168",
    "addr:housenumber":"1326",
    "addr:postcode":"3168",
    "addr:street":"Centre Rd",
    "iso:country":"AU",
    "sg:address":"1326 Centre Rd",
    "sg:city":"Clayton",
    "sg:classifiers":[
        {
            "category":"Health Services",
            "subcategory":"Doctor",
            "type":"Services"
        }
    ],
    "sg:phone":"+61 3 9544 4655",
    "sg:postcode":"3168",
    "sg:province":"VIC",
    "sg:tags":[
        "medical",
        "practitioner"
    ],
    "wof:name":"Allchin E E",
    "wof:placetype":"venue"
},
  "geometry": {"coordinates":[145.11097717300001,-37.9273910522],"type":"Point"}
}