{
  "type": "Feature",
  "properties": {
    "addr:full":"31 Boardman Rd Bowral NSW 2576",
    "addr:housenumber":"31",
    "addr:postcode":"2576",
    "addr:street":"Boardman Rd",
    "iso:country":"AU",
    "sg:address":"31 Boardman Rd",
    "sg:city":"Bowral",
    "sg:classifiers":[
        {
            "category":"Building & Trades",
            "subcategory":"Construction",
            "type":"Services"
        }
    ],
    "sg:phone":"+61 2 4268 1561",
    "sg:postcode":"2576",
    "sg:province":"NSW",
    "sg:tags":[
        "contractor"
    ],
    "wof:name":"Nu Era Homes Pty Ltd",
    "wof:placetype":"venue"
},
  "geometry": {"coordinates":[150.44265747099999,-34.4988136292],"type":"Point"}
}