{
  "type": "Feature",
  "properties": {
    "addr:full":"85 Main Rd Cardiff NSW 2285",
    "addr:housenumber":"85",
    "addr:postcode":"2285",
    "addr:street":"Main Rd",
    "iso:country":"AU",
    "sg:address":"85 Main Rd",
    "sg:city":"Cardiff",
    "sg:classifiers":[
        {
            "category":"Wholesale",
            "subcategory":"Furniture",
            "type":"Manufacturing & Wholesale Goods"
        }
    ],
    "sg:phone":"+61 2 4954 4455",
    "sg:postcode":"2285",
    "sg:province":"NSW",
    "sg:tags":[
        "wholesaler",
        "mfrs"
    ],
    "wof:name":"Outdoor & Leisure P.V.C. Furniture",
    "wof:placetype":"venue"
},
  "geometry": {"coordinates":[151.67054748499999,-32.939453125],"type":"Point"}
}