{
  "type": "Feature",
  "properties": {
    "iso:country":"AU",
    "sg:address":"Shop 4/ 2 Kern Brothers Drv",
    "sg:city":"Kirwan",
    "sg:classifiers":[
        {
            "category":"Professional",
            "subcategory":"Employment Agencies",
            "type":"Services"
        }
    ],
    "sg:phone":"+61 7 4726 1522",
    "sg:postcode":"4817",
    "sg:province":"QLD",
    "sg:tags":[
        "hire",
        "labour",
        "contractor"
    ],
    "wof:name":"WorkPac Industrial",
    "wof:placetype":"venue"
},
  "geometry": {"coordinates":[146.72709699999999,-19.303162],"type":"Point"}
}