{
  "type": "Feature",
  "properties": {
    "addr:full":"Unit 3 373 Manns Rd Gosford West NSW 2250",
    "addr:housenumber":"373",
    "addr:postcode":"2250",
    "addr:street":"Manns Rd",
    "iso:country":"AU",
    "sg:address":"Unit 3 373 Manns Rd",
    "sg:city":"Gosford West",
    "sg:classifiers":[
        {
            "category":"Building & Trades",
            "subcategory":"Construction",
            "type":"Services"
        }
    ],
    "sg:phone":"+61 2 4325 4769",
    "sg:postcode":"2250",
    "sg:province":"NSW",
    "sg:tags":[
        "stonework",
        "stone",
        "mason"
    ],
    "wof:name":"Stone Signs Australia",
    "wof:placetype":"venue"
},
  "geometry": {"coordinates":[151.31932067899999,-33.4247665405],"type":"Point"}
}