{
  "type": "Feature",
  "properties": {
    "addr:full":"242 Parramatta Rd Stanmore NSW 2048",
    "addr:housenumber":"242",
    "addr:postcode":"2048",
    "addr:street":"Parramatta Rd",
    "iso:country":"AU",
    "sg:address":"242 Parramatta Rd",
    "sg:city":"Stanmore",
    "sg:classifiers":[
        {
            "category":"Personal",
            "subcategory":"Beauty Salon",
            "type":"Services"
        }
    ],
    "sg:phone":"+61 2 9550 0960",
    "sg:postcode":"2048",
    "sg:province":"NSW",
    "wof:name":"Your Beauty Therapist",
    "wof:placetype":"venue"
},
  "geometry": {"coordinates":[151.16561899999999,-33.888214],"type":"Point"}
}