{
  "type": "Feature",
  "properties": {
    "addr:full":"501 Bourke St Melbourne VIC 3000",
    "addr:housenumber":"501",
    "addr:postcode":"3000",
    "addr:street":"Bourke St",
    "iso:country":"AU",
    "sg:address":"501 Bourke St",
    "sg:city":"Melbourne",
    "sg:classifiers":[
        {
            "category":"Professional",
            "subcategory":"Accounting & Tax Preparation",
            "type":"Services"
        }
    ],
    "sg:phone":"+61 1300 744 547",
    "sg:postcode":"3000",
    "sg:province":"VIC",
    "sg:tags":[
        "accountant",
        "auditor"
    ],
    "wof:name":"PMCA",
    "wof:placetype":"venue"
},
  "geometry": {"coordinates":[144.95887756400001,-37.8156166077],"type":"Point"}
}