{
  "type": "Feature",
  "properties": {
    "addr:full":"1 Currie Rd Forestville NSW 2087",
    "addr:housenumber":"1",
    "addr:postcode":"2087",
    "addr:street":"Currie Rd",
    "iso:country":"AU",
    "sg:address":"1 Currie Rd",
    "sg:city":"Forestville",
    "sg:classifiers":[
        {
            "category":"Retail",
            "subcategory":"Auto Repair",
            "type":"Services"
        }
    ],
    "sg:phone":"+61 2 9451 4761",
    "sg:postcode":"2087",
    "sg:province":"NSW",
    "sg:tags":[
        "repairer",
        "motor",
        "engineer"
    ],
    "wof:name":"Safety Service Centre",
    "wof:placetype":"venue"
},
  "geometry": {"coordinates":[151.219284058,-33.7594413757],"type":"Point"}
}