{
  "type": "Feature",
  "properties": {
    "iso:country":"AU",
    "sg:address":"Finniss Vale Drv",
    "sg:city":"Second Valley",
    "sg:classifiers":[
        {
            "category":"Fast Food",
            "type":"Food & Drink"
        }
    ],
    "sg:phone":"+61 8 8598 4064",
    "sg:postcode":"5204",
    "sg:province":"SA",
    "sg:tags":[
        "away",
        "take"
    ],
    "wof:name":"Second Valley Jetty Store",
    "wof:placetype":"venue"
},
  "geometry": {"coordinates":[138.227752686,-35.5275535583],"type":"Point"}
}