{
  "type": "Feature",
  "properties": {
    "addr:full":"1/ 7 Forge St Welshpool WA 6106",
    "addr:housenumber":"/ 7",
    "addr:postcode":"6106",
    "addr:street":"Forge St",
    "iso:country":"AU",
    "sg:address":"1/ 7 Forge St",
    "sg:city":"Welshpool",
    "sg:classifiers":[
        {
            "category":"Retail",
            "subcategory":"Funeral Services",
            "type":"Services"
        }
    ],
    "sg:phone":"+61 8 9358 1400",
    "sg:postcode":"6106",
    "sg:province":"WA",
    "sg:tags":[
        "director"
    ],
    "wof:name":"H.H. Webb & Co Pty Ltd",
    "wof:placetype":"venue"
},
  "geometry": {"coordinates":[115.932411194,-31.9893951416],"type":"Point"}
}