{
  "type": "Feature",
  "properties": {
    "addr:full":"22 White St Kilmore VIC 3764",
    "addr:housenumber":"22",
    "addr:postcode":"3764",
    "addr:street":"White St",
    "iso:country":"AU",
    "sg:address":"22 White St",
    "sg:city":"Kilmore",
    "sg:classifiers":[
        {
            "category":"Social Services",
            "subcategory":"Child Care",
            "type":"Services"
        }
    ],
    "sg:phone":"+61 3 5781 1344",
    "sg:postcode":"3764",
    "sg:province":"VIC",
    "wof:name":"Kilmore Child Care Centre",
    "wof:placetype":"venue"
},
  "geometry": {"coordinates":[144.95309448200001,-37.3000602722],"type":"Point"}
}