{
  "type": "Feature",
  "properties": {
    "iso:country":"AU",
    "sg:address":"2 Durkin Pl",
    "sg:city":"Peakhurst",
    "sg:classifiers":[
        {
            "category":"Building & Trades",
            "subcategory":"Construction",
            "type":"Services"
        }
    ],
    "sg:phone":"+61 2 9534 5400",
    "sg:postcode":"2210",
    "sg:province":"NSW",
    "sg:tags":[
        "contractor"
    ],
    "wof:name":"Lynch C H & S M Pty Ltd",
    "wof:placetype":"venue"
},
  "geometry": {"coordinates":[151.063705,-33.960594],"type":"Point"}
}