{
  "type": "Feature",
  "properties": {
    "iso:country":"AU",
    "sg:address":"PO Box 687",
    "sg:city":"Taree",
    "sg:classifiers":[
        {
            "category":"Building & Trades",
            "subcategory":"Construction",
            "type":"Services"
        }
    ],
    "sg:phone":"+61 2 6553 2463",
    "sg:postcode":"2430",
    "sg:province":"NSW",
    "sg:tags":[
        "excavation",
        "foundation"
    ],
    "wof:name":"B & J Kelliher Pty Ltd",
    "wof:placetype":"venue"
},
  "geometry": {"coordinates":[152.46151699999999,-31.91313],"type":"Point"}
}