{
  "type": "Feature",
  "properties": {
    "addr:full":"9 Donaldson St Griffith NSW 2680",
    "addr:housenumber":"9",
    "addr:postcode":"2680",
    "addr:street":"Donaldson St",
    "iso:country":"AU",
    "sg:address":"9 Donaldson St",
    "sg:city":"Griffith",
    "sg:classifiers":[
        {
            "category":"Wholesale",
            "subcategory":"Machinery & Supplies",
            "type":"Manufacturing & Wholesale Goods"
        }
    ],
    "sg:phone":"+61 2 6962 5282",
    "sg:postcode":"2680",
    "sg:province":"NSW",
    "sg:tags":[
        "equipment",
        "hydraulic"
    ],
    "wof:name":"Griffith Hydraulics Pty Ltd",
    "wof:placetype":"venue"
},
  "geometry": {"coordinates":[146.072067,-34.292576],"type":"Point"}
}