{
  "type": "Feature",
  "properties": {
    "iso:country":"AU",
    "sg:address":"29 Mitta St",
    "sg:city":"Box Hill North",
    "sg:classifiers":[
        {
            "category":"Building & Trades",
            "subcategory":"Cleaning & Sanitation",
            "type":"Services"
        }
    ],
    "sg:phone":"+61 419 311 162",
    "sg:postcode":"3129",
    "sg:province":"VIC",
    "sg:tags":[
        "industrial",
        "commercial",
        "contractor"
    ],
    "wof:name":"Champagne Cleaning",
    "wof:placetype":"venue"
},
  "geometry": {"coordinates":[145.122802734,-37.8052101135],"type":"Point"}
}