{
  "type": "Feature",
  "properties": {
    "iso:country":"AU",
    "sg:address":"179 Fairbairn Rd",
    "sg:city":"Sunshine",
    "sg:classifiers":[
        {
            "category":"Home & Garden",
            "subcategory":"Building Materials",
            "type":"Retail Goods"
        }
    ],
    "sg:phone":"+61 3 9364 9544",
    "sg:postcode":"3020",
    "sg:province":"VIC",
    "sg:tags":[
        "supply"
    ],
    "wof:name":"Able Truss",
    "wof:placetype":"venue"
},
  "geometry": {"coordinates":[144.817398,-37.811932],"type":"Point"}
}