{
  "type": "Feature",
  "properties": {
    "iso:country":"AU",
    "sg:address":"Shp2/ 96 Taren Point Rd",
    "sg:city":"Taren Point",
    "sg:classifiers":[
        {
            "category":"Cafe",
            "type":"Food & Drink"
        }
    ],
    "sg:phone":"+61 2 9531 1525",
    "sg:postcode":"2229",
    "sg:province":"NSW",
    "wof:name":"Hype Expresso Bar",
    "wof:placetype":"venue"
},
  "geometry": {"coordinates":[151.12139892600001,-34.022605896],"type":"Point"}
}