{
  "type": "Feature",
  "properties": {
    "iso:country":"AU",
    "sg:address":"2- 8 Cooks St",
    "sg:city":"Sunshine",
    "sg:classifiers":[
        {
            "category":"Building & Trades",
            "subcategory":"Plumbing",
            "type":"Services"
        }
    ],
    "sg:phone":"+61 3 9312 2166",
    "sg:postcode":"3020",
    "sg:province":"VIC",
    "sg:tags":[
        "plumber",
        "gasfitters"
    ],
    "wof:name":"BPS Plumbing Pty Ltd",
    "wof:placetype":"venue"
},
  "geometry": {"coordinates":[144.815994,-37.81218],"type":"Point"}
}