{
  "type": "Feature",
  "properties": {
    "addr:full":"2- 8 Cooks St Sunshine VIC 3020",
    "addr:housenumber":"8",
    "addr:postcode":"3020",
    "addr:street":"Cooks St",
    "iso:country":"AU",
    "sg:address":"2- 8 Cooks St",
    "sg:city":"Sunshine",
    "sg:classifiers":[
        {
            "category":"Building & Trades",
            "subcategory":"Plumbing",
            "type":"Services"
        }
    ],
    "sg:phone":"+61 3 9312 2166",
    "sg:postcode":"3020",
    "sg:province":"VIC",
    "sg:tags":[
        "plumber",
        "gasfitters"
    ],
    "wof:name":"BPS Plumbing Pty Ltd",
    "wof:placetype":"venue"
},
  "geometry": {"coordinates":[144.81599399999999,-37.81218],"type":"Point"}
}