{
  "type": "Feature",
  "properties": {
    "addr:full":"Shop 4 (Arcade), 250 Carlisle St Balaclava VIC 3183",
    "addr:housenumber":"shop 4;250",
    "addr:postcode":"3183",
    "addr:street":"Arcade;Carlisle St",
    "iso:country":"AU",
    "sg:address":"Shop 4 (Arcade), 250 Carlisle St",
    "sg:city":"Balaclava",
    "sg:classifiers":[
        {
            "category":"Food & Beverages",
            "subcategory":"Bakery",
            "type":"Retail Goods"
        }
    ],
    "sg:phone":"+61 3 9537 2149",
    "sg:postcode":"3183",
    "sg:province":"VIC",
    "sg:tags":[
        "baker"
    ],
    "wof:name":"Two Good For Words Pty Ltd",
    "wof:placetype":"venue"
},
  "geometry": {"coordinates":[144.992477417,-37.8684921265],"type":"Point"}
}