{
  "type": "Feature",
  "properties": {
    "addr:full":"15 Ferguson Rd Leopold VIC 3224",
    "addr:housenumber":"15",
    "addr:postcode":"3224",
    "addr:street":"Ferguson Rd",
    "iso:country":"AU",
    "sg:address":"15 Ferguson Rd",
    "sg:city":"Leopold",
    "sg:classifiers":[
        {
            "category":"Health Services",
            "subcategory":"Health Practitioner",
            "type":"Services"
        }
    ],
    "sg:phone":"+61 3 5250 1713",
    "sg:postcode":"3224",
    "sg:province":"VIC",
    "sg:tags":[
        "psychologist"
    ],
    "wof:name":"Neurofeedback Australia Pty Ltd",
    "wof:placetype":"venue"
},
  "geometry": {"coordinates":[144.46296699999999,-38.190788],"type":"Point"}
}