{
  "type": "Feature",
  "properties": {
    "addr:full":"Stonemaster Drv Stapylton QLD 4207",
    "addr:postcode":"4207",
    "addr:street":"Stonemaster Drv",
    "iso:country":"AU",
    "sg:address":"Stonemaster Drv",
    "sg:city":"Stapylton",
    "sg:classifiers":[
        {
            "category":"Building & Trades",
            "subcategory":"Construction",
            "type":"Services"
        }
    ],
    "sg:phone":"+61 7 3827 7922",
    "sg:postcode":"4207",
    "sg:province":"QLD",
    "sg:tags":[
        "road",
        "contractor"
    ],
    "wof:name":"FRH Group Pty Ltd",
    "wof:placetype":"venue"
},
  "geometry": {"coordinates":[153.2449646,-27.7243347168],"type":"Point"}
}