{
  "type": "Feature",
  "properties": {
    "addr:full":"410/ Aldenhoven Rd Lonsdale SA 5160",
    "addr:housenumber":"410 /",
    "addr:postcode":"5160",
    "addr:street":"Aldenhoven Rd",
    "iso:country":"AU",
    "sg:address":"410/ Aldenhoven Rd",
    "sg:city":"Lonsdale",
    "sg:classifiers":[
        {
            "category":"Health Services",
            "subcategory":"Health Practitioner",
            "type":"Services"
        }
    ],
    "sg:phone":"+61 8 8384 5746",
    "sg:postcode":"5160",
    "sg:province":"SA",
    "sg:tags":[
        "naturopath"
    ],
    "wof:name":"Southern Naturopathic Clinic",
    "wof:placetype":"venue"
},
  "geometry": {"coordinates":[138.4949646,-35.1100387573],"type":"Point"}
}