{
  "type": "Feature",
  "properties": {
    "addr:full":"15/33 Belmore Rd Burwood NSW 2134",
    "addr:housenumber":"15 / 33",
    "addr:postcode":"2134",
    "addr:street":"Belmore Rd",
    "iso:country":"AU",
    "sg:address":"15/33 Belmore Rd",
    "sg:city":"Burwood",
    "sg:classifiers":[
        {
            "category":"Professional",
            "subcategory":"Engineering",
            "type":"Services"
        }
    ],
    "sg:phone":"+61 2 9715 2155",
    "sg:postcode":"2134",
    "sg:province":"NSW",
    "sg:tags":[
        "engineer"
    ],
    "wof:name":"Dong Joo Australia PTY LTD",
    "wof:placetype":"venue"
},
  "geometry": {"coordinates":[151.10223388700001,-33.8785896301],"type":"Point"}
}