{
  "type": "Feature",
  "properties": {
    "addr:full":"Shop 34, Forest Lake Village 235 Forest Lake Blv Forest Lake QLD 4078",
    "addr:housenumber":"shop 34;235",
    "addr:postcode":"4078",
    "addr:street":"Forest Lake Blv",
    "iso:country":"AU",
    "sg:address":"Shop 34, Forest Lake Village 235 Forest Lake Blv",
    "sg:city":"Forest Lake",
    "sg:classifiers":[
        {
            "category":"Real Estate",
            "subcategory":"Real Estate Agent",
            "type":"Services"
        }
    ],
    "sg:phone":"+61 7 3271 4777",
    "sg:postcode":"4078",
    "sg:province":"QLD",
    "wof:name":"Harcourts Queensland Pty Ltd",
    "wof:placetype":"venue"
},
  "geometry": {"coordinates":[152.96864318900001,-27.6256027222],"type":"Point"}
}