{
  "type": "Feature",
  "properties": {
    "addr:full":"Cnr Echuca Rd & Midland Hwy Mooroopna VIC 3629",
    "addr:postcode":"3629",
    "addr:street":"Cnr Echuca Rd & Midland Hwy",
    "iso:country":"AU",
    "sg:address":"Cnr Echuca Rd & Midland Hwy",
    "sg:city":"Mooroopna",
    "sg:classifiers":[
        {
            "category":"Education",
            "subcategory":"Kindergarten",
            "type":"Public Place"
        }
    ],
    "sg:phone":"+61 3 5825 1200",
    "sg:postcode":"3629",
    "sg:province":"VIC",
    "sg:tags":[
        "pre-schools"
    ],
    "wof:name":"Rodney Neighbourhood Kindergarten",
    "wof:placetype":"venue"
},
  "geometry": {"coordinates":[145.36723327600001,-36.3912353516],"type":"Point"}
}