{
  "type": "Feature",
  "properties": {
    "addr:full":"4 Manton Rd Huntingdale VIC 3166",
    "addr:housenumber":"4",
    "addr:postcode":"3166",
    "addr:street":"Manton Rd",
    "iso:country":"AU",
    "sg:address":"4 Manton Rd",
    "sg:city":"Huntingdale",
    "sg:classifiers":[
        {
            "category":"Building & Trades",
            "subcategory":"Construction",
            "type":"Services"
        }
    ],
    "sg:phone":"+61 3 9543 4241",
    "sg:postcode":"3166",
    "sg:province":"VIC",
    "sg:tags":[
        "window",
        "timber"
    ],
    "wof:name":"Huntingdale Timber Windows & Cabinets",
    "wof:placetype":"venue"
},
  "geometry": {"coordinates":[145.10516357399999,-37.9023399353],"type":"Point"}
}