{
  "type": "Feature",
  "properties": {
    "addr:full":"Oxley Hwy Wauchope NSW 2446",
    "addr:postcode":"2446",
    "addr:street":"Oxley Hwy",
    "iso:country":"AU",
    "sg:address":"Oxley Hwy",
    "sg:city":"Wauchope",
    "sg:classifiers":[
        {
            "category":"Education",
            "subcategory":"School",
            "type":"Public Place"
        }
    ],
    "sg:phone":"+61 2 6585 6144",
    "sg:postcode":"2446",
    "sg:province":"NSW",
    "sg:tags":[
        "state",
        "-",
        "nsw"
    ],
    "wof:name":"Huntingdon Public School",
    "wof:placetype":"venue"
},
  "geometry": {"coordinates":[152.733734,-31.457371],"type":"Point"}
}