{
  "type": "Feature",
  "properties": {
    "iso:country":"AU",
    "sg:address":"Pacific Hwy",
    "sg:city":"Karuah",
    "sg:classifiers":[
        {
            "category":"Travel",
            "subcategory":"Hotels & Motels",
            "type":"Entertainment"
        }
    ],
    "sg:phone":"+61 2 4997 5225",
    "sg:postcode":"2324",
    "sg:province":"NSW",
    "wof:name":"Country Life Motel Karuah",
    "wof:placetype":"venue"
},
  "geometry": {"coordinates":[151.93678283700001,-32.6342315674],"type":"Point"}
}