{
  "type": "Feature",
  "properties": {
    "iso:country":"AU",
    "sg:address":"229 Forest Rd",
    "sg:city":"Kirrawee",
    "sg:classifiers":[
        {
            "category":"Social Services",
            "subcategory":"Retirement Home",
            "type":"Services"
        }
    ],
    "sg:phone":"+61 2 9545 1773",
    "sg:postcode":"2232",
    "sg:province":"NSW",
    "sg:tags":[
        "village"
    ],
    "wof:name":"St Vincent De Paul Society Aged Homes",
    "wof:placetype":"venue"
},
  "geometry": {"coordinates":[151.07516479500001,-34.0405273438],"type":"Point"}
}