{
  "type": "Feature",
  "properties": {
    "addr:full":"116 Gill St Charters Towers QLD 4820",
    "addr:housenumber":"116",
    "addr:postcode":"4820",
    "addr:street":"Gill St",
    "iso:country":"AU",
    "sg:address":"116 Gill St",
    "sg:city":"Charters Towers",
    "sg:classifiers":[
        {
            "category":"Retail",
            "subcategory":"Auto Rental",
            "type":"Services"
        }
    ],
    "sg:phone":"+61 7 4787 4115",
    "sg:postcode":"4820",
    "sg:province":"QLD",
    "sg:tags":[
        "car",
        "hire",
        "minibus"
    ],
    "wof:name":"Avis",
    "wof:placetype":"venue"
},
  "geometry": {"coordinates":[146.260864,-20.076618],"type":"Point"}
}