{
  "type": "Feature",
  "properties": {
    "addr:full":"38 Swan St Wollongong NSW 2500",
    "addr:housenumber":"38",
    "addr:postcode":"2500",
    "addr:street":"Swan St",
    "iso:country":"AU",
    "sg:address":"38 Swan St",
    "sg:city":"Wollongong",
    "sg:classifiers":[
        {
            "category":"Professional",
            "subcategory":"Art Services",
            "type":"Services"
        }
    ],
    "sg:phone":"+61 2 4226 4043",
    "sg:postcode":"2500",
    "sg:province":"NSW",
    "sg:tags":[
        "interior",
        "decorator"
    ],
    "wof:name":"Coulson Michaela",
    "wof:placetype":"venue"
},
  "geometry": {"coordinates":[150.89372299999999,-34.435394],"type":"Point"}
}