{
  "type": "Feature",
  "properties": {
    "addr:full":"100 Edith St Wynnum QLD 4178",
    "addr:housenumber":"100",
    "addr:postcode":"4178",
    "addr:street":"Edith St",
    "iso:country":"AU",
    "sg:address":"100 Edith St",
    "sg:city":"Wynnum",
    "sg:classifiers":[
        {
            "category":"Shopping",
            "subcategory":"Clothing, Apparel, & Fashions",
            "type":"Retail Goods"
        }
    ],
    "sg:phone":"+61 7 3396 0324",
    "sg:postcode":"4178",
    "sg:province":"QLD",
    "sg:tags":[
        "recycled",
        "clothing"
    ],
    "wof:name":"Australian Red Cross",
    "wof:placetype":"venue"
},
  "geometry": {"coordinates":[153.173553467,-27.4450721741],"type":"Point"}
}