{
  "type": "Feature",
  "properties": {
    "iso:country":"AU",
    "sg:address":"541 Mount Barker Rd",
    "sg:city":"Bridgewater",
    "sg:classifiers":[
        {
            "category":"Home & Garden",
            "subcategory":"Building Materials",
            "type":"Retail Goods"
        }
    ],
    "sg:phone":"+61 419 843 159",
    "sg:postcode":"5155",
    "sg:province":"SA",
    "sg:tags":[
        "merchant",
        "glass",
        "glazier"
    ],
    "wof:name":"Federation Glass",
    "wof:placetype":"venue"
},
  "geometry": {"coordinates":[138.772384644,-35.013092041],"type":"Point"}
}