{
  "type": "Feature",
  "properties": {
    "addr:full":"5 Monash St Ascot Vale VIC 3032",
    "addr:housenumber":"5",
    "addr:postcode":"3032",
    "addr:street":"Monash St",
    "iso:country":"AU",
    "sg:address":"5 Monash St",
    "sg:city":"Ascot Vale",
    "sg:classifiers":[
        {
            "category":"Professional",
            "subcategory":"Employment Agencies",
            "type":"Services"
        }
    ],
    "sg:phone":"+61 419 007 094",
    "sg:postcode":"3032",
    "sg:province":"VIC",
    "wof:name":"Rob Greenfield",
    "wof:placetype":"venue"
},
  "geometry": {"coordinates":[144.90931699999999,-37.780159],"type":"Point"}
}