{
  "type": "Feature",
  "properties": {
    "iso:country":"AU",
    "sg:address":"\ufffdSilverspring\ufffd Ferguson Rd",
    "sg:city":"Dardanup",
    "sg:classifiers":[
        {
            "category":"Manufacturing",
            "subcategory":"Paper Products",
            "type":"Manufacturing & Wholesale Goods"
        }
    ],
    "sg:phone":"+61 8 9728 1152",
    "sg:postcode":"6236",
    "sg:province":"WA",
    "sg:tags":[
        "sawdust",
        "supplier",
        "shaving"
    ],
    "wof:name":"Depiazzi T J & Sons",
    "wof:placetype":"venue"
},
  "geometry": {"coordinates":[115.759758,-33.398151],"type":"Point"}
}