{
  "type": "Feature",
  "properties": {
    "iso:country":"AU",
    "sg:address":"Bateau Bay Rd",
    "sg:city":"Bateau Bay",
    "sg:classifiers":[
        {
            "category":"Conference Center",
            "type":"Public Place"
        }
    ],
    "sg:phone":"+61 2 4332 1447",
    "sg:postcode":"2261",
    "sg:province":"NSW",
    "sg:tags":[
        "venue",
        "convention"
    ],
    "wof:name":"Blue Lagoon Beach Resort",
    "wof:placetype":"venue"
},
  "geometry": {"coordinates":[151.479706,-33.382908],"type":"Point"}
}