{
  "type": "Feature",
  "properties": {
    "iso:country":"AU",
    "sg:address":"49 Industrial Drv",
    "sg:city":"Mayfield",
    "sg:classifiers":[
        {
            "category":"Retail",
            "subcategory":"Storage",
            "type":"Services"
        }
    ],
    "sg:phone":"+61 2 4968 1555",
    "sg:postcode":"2304",
    "sg:province":"NSW",
    "wof:name":"Safe &#039;n&#039; Sound Self Storage",
    "wof:placetype":"venue"
},
  "geometry": {"coordinates":[151.74703979500001,-32.8928565979],"type":"Point"}
}