{
  "type": "Feature",
  "properties": {
    "addr:full":"\"Alloway Grange\" 232 Thomas Drv Bathurst NSW 2795",
    "addr:housenumber":"232",
    "addr:postcode":"2795",
    "addr:street":"Thomas Drv",
    "iso:country":"AU",
    "sg:address":"\"Alloway Grange\" 232 Thomas Drv",
    "sg:city":"Bathurst",
    "sg:classifiers":[
        {
            "category":"Professional",
            "subcategory":"Art Services",
            "type":"Services"
        }
    ],
    "sg:phone":"+61 2 6337 1728",
    "sg:postcode":"2795",
    "sg:province":"NSW",
    "sg:tags":[
        "interior",
        "decorator"
    ],
    "wof:name":"Rhonda Stocks Interior Decorating",
    "wof:placetype":"venue"
},
  "geometry": {"coordinates":[149.606933594,-33.5515518188],"type":"Point"}
}