{
  "type": "Feature",
  "properties": {
    "addr:full":"3 Industry Rd Wingfield SA 5013",
    "addr:housenumber":"3",
    "addr:postcode":"5013",
    "addr:street":"Industry Rd",
    "iso:country":"AU",
    "sg:address":"3 Industry Rd",
    "sg:city":"Wingfield",
    "sg:classifiers":[
        {
            "category":"Commercial Area",
            "type":"Public Place"
        }
    ],
    "sg:phone":"+61 8 8347 1590",
    "sg:postcode":"5013",
    "sg:province":"SA",
    "sg:tags":[
        "heavy",
        "carrier"
    ],
    "wof:name":"High North Pty Ltd",
    "wof:placetype":"venue"
},
  "geometry": {"coordinates":[138.55299377399999,-34.84740448],"type":"Point"}
}