{
  "type": "Feature",
  "properties": {
    "addr:full":"Newstead Commercial Village, 4 / 76 Doggett St Newstead QLD 4006",
    "addr:housenumber":"/ 76",
    "addr:postcode":"4006",
    "addr:street":"Doggett St",
    "iso:country":"AU",
    "sg:address":"Newstead Commercial Village, 4 / 76 Doggett St",
    "sg:city":"Newstead",
    "sg:classifiers":[
        {
            "category":"Banks & Credit Unions",
            "subcategory":"Financial Services",
            "type":"Services"
        }
    ],
    "sg:phone":"+61 7 3166 4444",
    "sg:postcode":"4006",
    "sg:province":"QLD",
    "sg:tags":[
        "loan",
        "finance",
        "mortgage"
    ],
    "sg:website":"http://www.capitalatcall.com.au",
    "wof:name":"Capital At Call",
    "wof:placetype":"venue"
},
  "geometry": {"coordinates":[153.04356384299999,-27.4519805908],"type":"Point"}
}