{
  "type": "Feature",
  "properties": {
    "addr:full":"Karingal Shopping Centre Cnr Karingal Drv & Cranbo Karingal VIC 3199",
    "addr:postcode":"3199",
    "addr:street":"Cnr Karingal Drv & Cranbo",
    "iso:country":"AU",
    "sg:address":"Karingal Shopping Centre Cnr Karingal Drv & Cranbo",
    "sg:city":"Karingal",
    "sg:classifiers":[
        {
            "category":"Food & Beverages",
            "subcategory":"Supermarket",
            "type":"Retail Goods"
        }
    ],
    "sg:phone":"+61 3 9789 3596",
    "sg:postcode":"3199",
    "sg:province":"VIC",
    "sg:tags":[
        "grocery",
        "store"
    ],
    "wof:name":"Safeway",
    "wof:placetype":"venue"
},
  "geometry": {"coordinates":[145.14802551299999,-38.1490936279],"type":"Point"}
}