{
  "type": "Feature",
  "properties": {
    "addr:full":"127 Frost Rd Salisbury South SA 5106",
    "addr:housenumber":"127",
    "addr:postcode":"5106",
    "addr:street":"Frost Rd",
    "iso:country":"AU",
    "sg:address":"127 Frost Rd",
    "sg:city":"Salisbury South",
    "sg:classifiers":[
        {
            "category":"Health Services",
            "subcategory":"Doctor",
            "type":"Services"
        }
    ],
    "sg:phone":"+61 8 8250 7979",
    "sg:postcode":"5106",
    "sg:province":"SA",
    "sg:tags":[
        "medical",
        "practitioner"
    ],
    "wof:name":"Northern Endoscopy Centre",
    "wof:placetype":"venue"
},
  "geometry": {"coordinates":[138.651276,-34.781464],"type":"Point"}
}