{
  "type": "Feature",
  "properties": {
    "addr:full":"Level 2/John McEwen House 7 National Cct Barton ACT 2600",
    "addr:housenumber":"/;7",
    "addr:postcode":"2600",
    "addr:street":"John Mcewen;National Cct",
    "iso:country":"AU",
    "sg:address":"Level 2/John McEwen House 7 National Cct",
    "sg:city":"Barton",
    "sg:classifiers":[
        {
            "category":"Professional",
            "subcategory":"Engineering",
            "type":"Services"
        }
    ],
    "sg:phone":"+61 2 6270 7777",
    "sg:postcode":"2600",
    "sg:province":"ACT",
    "sg:tags":[
        "consulting",
        "engineer"
    ],
    "wof:name":"Ball Solutions Group",
    "wof:placetype":"venue"
},
  "geometry": {"coordinates":[149.131317139,-35.3104133606],"type":"Point"}
}