{
  "type": "Feature",
  "properties": {
    "addr:full":"798 Burke Rd Camberwell VIC 3124",
    "addr:housenumber":"798",
    "addr:postcode":"3124",
    "addr:street":"Burke Rd",
    "iso:country":"AU",
    "sg:address":"798 Burke Rd",
    "sg:city":"Camberwell",
    "sg:classifiers":[
        {
            "category":"Professional",
            "subcategory":"Accounting & Tax Preparation",
            "type":"Services"
        }
    ],
    "sg:phone":"+61 3 9813 0454",
    "sg:postcode":"3124",
    "sg:province":"VIC",
    "sg:tags":[
        "accountant",
        "auditor"
    ],
    "wof:name":"J T Hall & Co",
    "wof:placetype":"venue"
},
  "geometry": {"coordinates":[145.058319092,-37.8238143921],"type":"Point"}
}