{
  "type": "Feature",
  "properties": {
    "addr:full":"2/ 191 Wollombi Rd Cessnock NSW 2325",
    "addr:housenumber":"/ 191",
    "addr:postcode":"2325",
    "addr:street":"Wollombi Rd",
    "iso:country":"AU",
    "sg:address":"2/ 191 Wollombi Rd",
    "sg:city":"Cessnock",
    "sg:classifiers":[
        {
            "category":"Retail",
            "subcategory":"Auto Repair",
            "type":"Services"
        }
    ],
    "sg:phone":"+61 2 4990 1772",
    "sg:postcode":"2325",
    "sg:province":"NSW",
    "sg:tags":[
        "repairer",
        "motor",
        "engineer"
    ],
    "wof:name":"Scotty's Garage",
    "wof:placetype":"venue"
},
  "geometry": {"coordinates":[151.32893371599999,-32.8493270874],"type":"Point"}
}