{
  "type": "Feature",
  "properties": {
    "iso:country":"AU",
    "sg:address":"Cnr Blair & Strickland Sts",
    "sg:city":"Bunbury",
    "sg:classifiers":[
        {
            "category":"Wholesale",
            "subcategory":"Painting Supplies",
            "type":"Manufacturing & Wholesale Goods"
        }
    ],
    "sg:phone":"+61 8 9721 3988",
    "sg:postcode":"6230",
    "sg:province":"WA",
    "sg:tags":[
        "wholesaler",
        "paint",
        "mfrs"
    ],
    "wof:name":"Solver Paints",
    "wof:placetype":"venue"
},
  "geometry": {"coordinates":[115.64119,-33.336498],"type":"Point"}
}