{
  "type": "Feature",
  "properties": {
    "addr:full":"59 Walters Drv Osborne Park WA 6017",
    "addr:housenumber":"59",
    "addr:postcode":"6017",
    "addr:street":"Walters Drv",
    "iso:country":"AU",
    "sg:address":"59 Walters Drv",
    "sg:city":"Osborne Park",
    "sg:classifiers":[
        {
            "category":"Building & Trades",
            "subcategory":"Construction",
            "type":"Services"
        }
    ],
    "sg:phone":"+61 8 9231 4800",
    "sg:postcode":"6017",
    "sg:province":"WA",
    "sg:tags":[
        "contractor"
    ],
    "wof:name":"Oswald Homes",
    "wof:placetype":"venue"
},
  "geometry": {"coordinates":[115.81391143800001,-31.9126815796],"type":"Point"}
}