{
  "type": "Feature",
  "properties": {
    "addr:full":"30 Hoddle St Bowral NSW 2576",
    "addr:housenumber":"30",
    "addr:postcode":"2576",
    "addr:street":"Hoddle St",
    "iso:country":"AU",
    "sg:address":"30 Hoddle St",
    "sg:city":"Bowral",
    "sg:classifiers":[
        {
            "category":"Health Services",
            "subcategory":"Doctor",
            "type":"Services"
        }
    ],
    "sg:phone":"+61 2 4885 1502",
    "sg:postcode":"2576",
    "sg:province":"NSW",
    "sg:tags":[
        "medical",
        "practitioner"
    ],
    "wof:name":"Robertson Medical Practice",
    "wof:placetype":"venue"
},
  "geometry": {"coordinates":[150.385894775,-34.4550590515],"type":"Point"}
}