{
  "type": "Feature",
  "properties": {
    "iso:country":"AU",
    "sg:address":"Lvl 5 201 Fitzroy St St",
    "sg:city":"Kilda",
    "sg:classifiers":[
        {
            "category":"Banks & Credit Unions",
            "subcategory":"Financial Services",
            "type":"Services"
        }
    ],
    "sg:phone":"+61 3 9536 3530",
    "sg:postcode":"3182",
    "sg:province":"VIC",
    "sg:tags":[
        "financier"
    ],
    "wof:name":"Focus Equipment Finance Limited",
    "wof:placetype":"venue"
},
  "geometry": {"coordinates":[144.98240661599999,-37.8569564819],"type":"Point"}
}