{
  "type": "Feature",
  "properties": {
    "addr:full":"15 Valley View Drv Highbury SA 5089",
    "addr:housenumber":"15",
    "addr:postcode":"5089",
    "addr:street":"Valley View Drv",
    "iso:country":"AU",
    "sg:address":"15 Valley View Drv",
    "sg:city":"Highbury",
    "sg:classifiers":[
        {
            "category":"Building & Trades",
            "subcategory":"Construction",
            "type":"Services"
        }
    ],
    "sg:phone":"+61 418 833 943",
    "sg:postcode":"5089",
    "sg:province":"SA",
    "sg:tags":[
        "earth",
        "excavating",
        "moving",
        "contractor"
    ],
    "wof:name":"FDG Construction Pty Ltd",
    "wof:placetype":"venue"
},
  "geometry": {"coordinates":[138.69404602,-34.857257843],"type":"Point"}
}