{
  "type": "Feature",
  "properties": {
    "addr:full":"579 Hampton St Hampton VIC 3188",
    "addr:housenumber":"579",
    "addr:postcode":"3188",
    "addr:street":"Hampton St",
    "iso:country":"AU",
    "sg:address":"579 Hampton St",
    "sg:city":"Hampton",
    "sg:classifiers":[
        {
            "category":"Sports & Exercise",
            "subcategory":"Ski Slope",
            "type":"Entertainment"
        }
    ],
    "sg:phone":"+61 3 9598 2044",
    "sg:postcode":"3188",
    "sg:province":"VIC",
    "sg:tags":[
        "equipment",
        "hire",
        "retail",
        "snow"
    ],
    "wof:name":"Ski & Board Hampton",
    "wof:placetype":"venue"
},
  "geometry": {"coordinates":[145.00372314399999,-37.9301338196],"type":"Point"}
}