{
  "type": "Feature",
  "properties": {
    "addr:full":"127 Grose Wold Rd Grose Wold NSW 2753",
    "addr:housenumber":"127",
    "addr:postcode":"2753",
    "addr:street":"Grose Wold Rd",
    "iso:country":"AU",
    "sg:address":"127 Grose Wold Rd",
    "sg:city":"Grose Wold",
    "sg:classifiers":[
        {
            "category":"Utilities",
            "subcategory":"Water",
            "type":"Services"
        }
    ],
    "sg:phone":"+61 414 446 526",
    "sg:postcode":"2753",
    "sg:province":"NSW",
    "sg:tags":[
        "cartage"
    ],
    "wof:name":"G & S Water Cartage",
    "wof:placetype":"venue"
},
  "geometry": {"coordinates":[150.67692565900001,-33.599445343],"type":"Point"}
}