{
  "type": "Feature",
  "properties": {
    "iso:country":"AU",
    "sg:address":"661a Old South Head Rd",
    "sg:city":"Vaucluse",
    "sg:classifiers":[
        {
            "category":"Deli",
            "type":"Food & Drink"
        }
    ],
    "sg:phone":"+61 2 9337 4720",
    "sg:postcode":"2030",
    "sg:province":"NSW",
    "sg:tags":[
        "delicatessen"
    ],
    "wof:name":"Confetti's Delicatessen",
    "wof:placetype":"venue"
},
  "geometry": {"coordinates":[151.27845764200001,-33.8649978638],"type":"Point"}
}