{
  "type": "Feature",
  "properties": {
    "addr:full":"Cnr Fullarton & Glen Osmond Rds Fullarton SA 5063",
    "addr:postcode":"5063",
    "addr:street":"Cnr",
    "iso:country":"AU",
    "sg:address":"Cnr Fullarton & Glen Osmond Rds",
    "sg:city":"Fullarton",
    "sg:classifiers":[
        {
            "category":"Food & Beverages",
            "subcategory":"Supermarket",
            "type":"Retail Goods"
        }
    ],
    "sg:phone":"+61 8 8379 9541",
    "sg:postcode":"5063",
    "sg:province":"SA",
    "sg:tags":[
        "grocery",
        "store"
    ],
    "wof:name":"Bi-Lo",
    "wof:placetype":"venue"
},
  "geometry": {"coordinates":[138.62571716299999,-34.9543457031],"type":"Point"}
}