{
  "type": "Feature",
  "properties": {
    "iso:country":"AU",
    "sg:address":"31 Palmerston St",
    "sg:city":"Drysdale",
    "sg:classifiers":[
        {
            "category":"Building & Trades",
            "subcategory":"Construction",
            "type":"Services"
        }
    ],
    "sg:phone":"+61 417 318 115",
    "sg:postcode":"3222",
    "sg:province":"VIC",
    "sg:tags":[
        "contractor"
    ],
    "wof:name":"Steve Pratt 'The House Doctor Pty. Ltd.'",
    "wof:placetype":"venue"
},
  "geometry": {"coordinates":[144.565887,-38.175419],"type":"Point"}
}