{
  "type": "Feature",
  "properties": {
    "addr:full":"73 Redhead St Doolandella QLD 4077",
    "addr:housenumber":"73",
    "addr:postcode":"4077",
    "addr:street":"Redhead St",
    "iso:country":"AU",
    "sg:address":"73 Redhead St",
    "sg:city":"Doolandella",
    "sg:classifiers":[
        {
            "category":"Building & Trades",
            "subcategory":"Construction",
            "type":"Services"
        }
    ],
    "sg:phone":"+61 7 3372 3043",
    "sg:postcode":"4077",
    "sg:province":"QLD",
    "sg:tags":[
        "earth",
        "excavating",
        "moving",
        "contractor"
    ],
    "wof:name":"Saffy A L",
    "wof:placetype":"venue"
},
  "geometry": {"coordinates":[152.98045349099999,-27.6151599884],"type":"Point"}
}