{
  "type": "Feature",
  "properties": {
    "iso:country":"AU",
    "sg:address":"43/ 45 Hastings St",
    "sg:city":"Wauchope",
    "sg:classifiers":[
        {
            "category":"Mining & Drilling",
            "type":"Manufacturing & Wholesale Goods"
        }
    ],
    "sg:phone":"+61 2 6585 2400",
    "sg:postcode":"2446",
    "sg:province":"NSW",
    "sg:tags":[
        "industrial",
        "diamond"
    ],
    "wof:name":"Hilberts Building, Industrial & General Hardware",
    "wof:placetype":"venue"
},
  "geometry": {"coordinates":[152.73225400000001,-31.456633],"type":"Point"}
}