{
  "type": "Feature",
  "properties": {
    "addr:full":"Gum Ave Lucindale SA 5272",
    "addr:postcode":"5272",
    "addr:street":"Gum Ave",
    "iso:country":"AU",
    "sg:address":"Gum Ave",
    "sg:city":"Lucindale",
    "sg:classifiers":[
        {
            "category":"Education",
            "subcategory":"School",
            "type":"Public Place"
        }
    ],
    "sg:phone":"+61 8 8766 2084",
    "sg:postcode":"5272",
    "sg:province":"SA",
    "sg:tags":[
        "state",
        "except",
        "nsw"
    ],
    "wof:name":"Lucindale Area School",
    "wof:placetype":"venue"
},
  "geometry": {"coordinates":[140.36979700000001,-36.973698],"type":"Point"}
}