{
  "type": "Feature",
  "properties": {
    "iso:country":"AU",
    "sg:address":"Elderslie St",
    "sg:city":"Winton",
    "sg:classifiers":[
        {
            "category":"Communications",
            "subcategory":"News Services",
            "type":"Services"
        }
    ],
    "sg:phone":"+61 7 4657 1296",
    "sg:postcode":"4735",
    "sg:province":"QLD",
    "sg:tags":[
        "information",
        "tourist",
        "attractions"
    ],
    "wof:name":"Wookatook Gift & Gem Centre",
    "wof:placetype":"venue"
},
  "geometry": {"coordinates":[143.040146,-22.390291],"type":"Point"}
}