{
  "type": "Feature",
  "properties": {
    "iso:country":"AU",
    "sg:address":"PO Box 1501",
    "sg:city":"Mornington",
    "sg:classifiers":[
        {
            "category":"Retail",
            "subcategory":"Auto Rental",
            "type":"Services"
        }
    ],
    "sg:phone":"+61 400 409 853",
    "sg:postcode":"7018",
    "sg:province":"TAS",
    "sg:tags":[
        "car",
        "wedding"
    ],
    "wof:name":"Jaguar Wedding Cars",
    "wof:placetype":"venue"
},
  "geometry": {"coordinates":[147.39279174800001,-42.8568916321],"type":"Point"}
}