{
  "type": "Feature",
  "properties": {
    "iso:country":"AU",
    "sg:address":"35 Smith St",
    "sg:city":"Parramatta",
    "sg:classifiers":[
        {
            "category":"Professional",
            "subcategory":"Accounting & Tax Preparation",
            "type":"Services"
        }
    ],
    "sg:phone":"+61 2 9840 7000",
    "sg:postcode":"2150",
    "sg:province":"NSW",
    "sg:tags":[
        "accountant",
        "auditor"
    ],
    "wof:name":"Deloitte Touche Tohmatsu",
    "wof:placetype":"venue"
},
  "geometry": {"coordinates":[151.00672912600001,-33.831035614],"type":"Point"}
}