{
  "type": "Feature",
  "properties": {
    "addr:full":"5/61- 63 Victoria Ave Chatswood NSW 2067",
    "addr:housenumber":"/;63",
    "addr:postcode":"2067",
    "addr:street":"61;Victoria Ave",
    "iso:country":"AU",
    "sg:address":"5/61- 63 Victoria Ave",
    "sg:city":"Chatswood",
    "sg:classifiers":[
        {
            "category":"Communications",
            "subcategory":"Film & Video Production",
            "type":"Services"
        }
    ],
    "sg:phone":"+61 2 9496 4060",
    "sg:postcode":"2067",
    "sg:province":"NSW",
    "sg:tags":[
        "messaging",
        "voice"
    ],
    "wof:name":"On-Line Communications",
    "wof:placetype":"venue"
},
  "geometry": {"coordinates":[151.20205688499999,-33.7903747559],"type":"Point"}
}