{
  "type": "Feature",
  "properties": {
    "iso:country":"AU",
    "sg:address":"7 Rennie St",
    "sg:city":"Huntly",
    "sg:classifiers":[
        {
            "category":"Education",
            "subcategory":"Special Training",
            "type":"Public Place"
        }
    ],
    "sg:phone":"+61 3 5448 8909",
    "sg:postcode":"3551",
    "sg:province":"VIC",
    "sg:tags":[
        "development"
    ],
    "wof:name":"Simmons Plant Operator Training & Assessment Services",
    "wof:placetype":"venue"
},
  "geometry": {"coordinates":[144.34197998100001,-36.6623573303],"type":"Point"}
}