{
  "type": "Feature",
  "properties": {
    "addr:full":"Huon Drv South Hobart TAS 7004",
    "addr:postcode":"7004",
    "addr:street":"Huon Drv",
    "iso:country":"AU",
    "sg:address":"Huon Drv",
    "sg:city":"South Hobart",
    "sg:classifiers":[
        {
            "category":"Building & Trades",
            "subcategory":"Plumbing",
            "type":"Services"
        }
    ],
    "sg:phone":"+61 427 776 456",
    "sg:postcode":"7004",
    "sg:province":"TAS",
    "sg:tags":[
        "plumber",
        "gasfitters"
    ],
    "wof:name":"A Countrywide Plumbing",
    "wof:placetype":"venue"
},
  "geometry": {"coordinates":[147.31059265100001,-42.8995780945],"type":"Point"}
}