{
  "type": "Feature",
  "properties": {
    "iso:country":"AU",
    "sg:address":"66 Grote St",
    "sg:city":"Adelaide",
    "sg:classifiers":[
        {
            "category":"Professional",
            "subcategory":"Business Services",
            "type":"Services"
        }
    ],
    "sg:phone":"+61 8 8221 6652",
    "sg:postcode":"5000",
    "sg:province":"SA",
    "sg:tags":[
        "exporter"
    ],
    "wof:name":"Siloam International Pty Ltd",
    "wof:placetype":"venue"
},
  "geometry": {"coordinates":[138.596633911,-34.9285583496],"type":"Point"}
}