{
  "type": "Feature",
  "properties": {
    "iso:country":"AU",
    "sg:address":"Level 7/ 157 Anne St",
    "sg:city":"Brisbane",
    "sg:classifiers":[
        {
            "category":"Banks & Credit Unions",
            "subcategory":"Investment Brokerage",
            "type":"Services"
        }
    ],
    "sg:phone":"+61 7 3226 8100",
    "sg:postcode":"4000",
    "sg:province":"QLD",
    "wof:name":"Financial Synergy Pty Ltd",
    "wof:placetype":"venue"
},
  "geometry": {"coordinates":[153.02479553200001,-27.4675636292],"type":"Point"}
}