{
  "type": "Feature",
  "properties": {
    "addr:full":"220- 224 Coventry St South Melbourne VIC 3205",
    "addr:housenumber":"224",
    "addr:postcode":"3205",
    "addr:street":"Coventry St",
    "iso:country":"AU",
    "sg:address":"220- 224 Coventry St",
    "sg:city":"South Melbourne",
    "sg:classifiers":[
        {
            "category":"Shopping",
            "subcategory":"Mobile Phones",
            "type":"Retail Goods"
        }
    ],
    "sg:phone":"+61 3 9696 7792",
    "sg:postcode":"3205",
    "sg:province":"VIC",
    "sg:tags":[
        "telephone",
        "accessory"
    ],
    "wof:name":"Business To Business",
    "wof:placetype":"venue"
},
  "geometry": {"coordinates":[144.96159399999999,-37.831318],"type":"Point"}
}