{
  "type": "Feature",
  "properties": {
    "addr:full":"75 Gympie Rd Maryborough QLD 4650",
    "addr:housenumber":"75",
    "addr:postcode":"4650",
    "addr:street":"Gympie Rd",
    "iso:country":"AU",
    "sg:address":"75 Gympie Rd",
    "sg:city":"Maryborough",
    "sg:classifiers":[
        {
            "category":"Building & Trades",
            "subcategory":"Construction",
            "type":"Services"
        }
    ],
    "sg:phone":"+61 7 4121 2776",
    "sg:postcode":"4650",
    "sg:province":"QLD",
    "sg:tags":[
        "contractor"
    ],
    "wof:name":"Pappin C H & C J",
    "wof:placetype":"venue"
},
  "geometry": {"coordinates":[152.68156400000001,-25.546318],"type":"Point"}
}