{
  "type": "Feature",
  "properties": {
    "addr:full":"PO Box 698 Bulimba QLD 4171",
    "addr:postcode":"4171",
    "iso:country":"AU",
    "sg:address":"PO Box 698",
    "sg:city":"Bulimba",
    "sg:classifiers":[
        {
            "category":"Building & Trades",
            "subcategory":"Construction",
            "type":"Services"
        }
    ],
    "sg:phone":"+61 7 3899 0032",
    "sg:postcode":"4171",
    "sg:province":"QLD",
    "sg:tags":[
        "window",
        "aluminium"
    ],
    "wof:name":"Queensland Glass Pty Ltd",
    "wof:placetype":"venue"
},
  "geometry": {"coordinates":[153.05929565400001,-27.4513607025],"type":"Point"}
}