{
  "type": "Feature",
  "properties": {
    "addr:full":"1/ 168 Pacific Hwy Tuggerah NSW 2259",
    "addr:housenumber":"/ 168",
    "addr:postcode":"2259",
    "addr:street":"Pacific Hwy",
    "iso:country":"AU",
    "sg:address":"1/ 168 Pacific Hwy",
    "sg:city":"Tuggerah",
    "sg:classifiers":[
        {
            "category":"Shopping",
            "subcategory":"Pets & Pet Supplies",
            "type":"Retail Goods"
        }
    ],
    "sg:phone":"+61 2 4351 2026",
    "sg:postcode":"2259",
    "sg:province":"NSW",
    "sg:tags":[
        "food"
    ],
    "wof:name":"Pet &#039;N&#039; Vet Supplies",
    "wof:placetype":"venue"
},
  "geometry": {"coordinates":[151.42199707,-33.2972412109],"type":"Point"}
}