{
  "type": "Feature",
  "properties": {
    "addr:full":"4 Bertram St Darlington WA 6070",
    "addr:housenumber":"4",
    "addr:postcode":"6070",
    "addr:street":"Bertram St",
    "iso:country":"AU",
    "sg:address":"4 Bertram St",
    "sg:city":"Darlington",
    "sg:classifiers":[
        {
            "category":"Building & Trades",
            "subcategory":"Landscaping Services",
            "type":"Services"
        }
    ],
    "sg:phone":"+61 413 045 568",
    "sg:postcode":"6070",
    "sg:province":"WA",
    "sg:tags":[
        "stump",
        "tree",
        "felling",
        "removal"
    ],
    "wof:name":"Arlington Tree Services",
    "wof:placetype":"venue"
},
  "geometry": {"coordinates":[116.082107544,-31.9110832214],"type":"Point"}
}