{
  "type": "Feature",
  "properties": {
    "addr:full":"168 Hoddle St Abbotsford VIC 3067",
    "addr:housenumber":"168",
    "addr:postcode":"3067",
    "addr:street":"Hoddle St",
    "iso:country":"AU",
    "sg:address":"168 Hoddle St",
    "sg:city":"Abbotsford",
    "sg:classifiers":[
        {
            "category":"Health Services",
            "subcategory":"Doctor",
            "type":"Services"
        }
    ],
    "sg:phone":"+61 3 9416 0400",
    "sg:postcode":"3067",
    "sg:province":"VIC",
    "sg:tags":[
        "medical",
        "practitioner"
    ],
    "wof:name":"Healthscope Pty Ltd",
    "wof:placetype":"venue"
},
  "geometry": {"coordinates":[144.992874145,-37.8021736145],"type":"Point"}
}