{
  "type": "Feature",
  "properties": {
    "addr:full":"272 Church St Corowa NSW 2646",
    "addr:housenumber":"272",
    "addr:postcode":"2646",
    "addr:street":"Church St",
    "iso:country":"AU",
    "sg:address":"272 Church St",
    "sg:city":"Corowa",
    "sg:classifiers":[
        {
            "category":"Building & Trades",
            "subcategory":"Plumbing",
            "type":"Services"
        }
    ],
    "sg:phone":"+61 417 343 975",
    "sg:postcode":"2646",
    "sg:province":"NSW",
    "sg:tags":[
        "plumber",
        "gasfitters"
    ],
    "wof:name":"O&#039;Halloran Robert",
    "wof:placetype":"venue"
},
  "geometry": {"coordinates":[146.37420654300001,-36.0102462769],"type":"Point"}
}