{
  "type": "Feature",
  "properties": {
    "addr:full":"20 Mega St Wanneroo WA 6065",
    "addr:postcode":"6065",
    "addr:street":"Mega St",
    "iso:country":"AU",
    "sg:address":"20 Mega St",
    "sg:city":"Wanneroo",
    "sg:classifiers":[
        {
            "category":"Building & Trades",
            "subcategory":"Construction",
            "type":"Services"
        }
    ],
    "sg:phone":"+61 8 9405 4975",
    "sg:postcode":"6065",
    "sg:province":"WA",
    "sg:tags":[
        "earth",
        "excavating",
        "moving",
        "contractor"
    ],
    "wof:name":"Steve Sewell",
    "wof:placetype":"venue"
},
  "geometry": {"coordinates":[115.80001831,-31.7565860748],"type":"Point"}
}