{
  "type": "Feature",
  "properties": {
    "addr:full":"Bungalow Rd Ballina NSW 2478",
    "addr:postcode":"2478",
    "addr:street":"Bungalow Rd",
    "iso:country":"AU",
    "sg:address":"Bungalow Rd",
    "sg:city":"Ballina",
    "sg:classifiers":[
        {
            "category":"Autos & Motor Vehicles",
            "subcategory":"Fuel & Gas Station",
            "type":"Retail Goods"
        }
    ],
    "sg:phone":"+61 2 6686 5835",
    "sg:postcode":"2478",
    "sg:province":"NSW",
    "wof:name":"BP Australia Limited",
    "wof:placetype":"venue"
},
  "geometry": {"coordinates":[153.56578064000001,-28.8626689911],"type":"Point"}
}