{
  "type": "Feature",
  "properties": {
    "addr:full":"Suite 1 /3 Newcastle Private Medical Suites, New Lamb NSW 2305",
    "addr:housenumber":"3",
    "addr:postcode":"2305",
    "addr:street":"Newcastle",
    "iso:country":"AU",
    "sg:address":"Suite 1",
    "sg:city":"/3 Newcastle Private Medical Suites, New Lamb",
    "sg:classifiers":[
        {
            "category":"Health Services",
            "subcategory":"Doctor",
            "type":"Services"
        }
    ],
    "sg:phone":"+61 2 4950 9999",
    "sg:postcode":"2305",
    "sg:province":"NSW",
    "sg:tags":[
        "medical",
        "practitioner"
    ],
    "wof:name":"Deshpande ,Arvind Dr",
    "wof:placetype":"venue"
},
  "geometry": {"coordinates":[151.71350100000001,-32.920181],"type":"Point"}
}