{
  "type": "Feature",
  "properties": {
    "addr:full":"Unit 2, 2 Commerce Drv Warilla NSW 2528",
    "addr:housenumber":"2",
    "addr:postcode":"2528",
    "addr:street":"Commerce Drv",
    "iso:country":"AU",
    "sg:address":"Unit 2, 2 Commerce Drv",
    "sg:city":"Warilla",
    "sg:classifiers":[
        {
            "category":"Manufacturing",
            "subcategory":"Chemicals & Compounds",
            "type":"Manufacturing & Wholesale Goods"
        }
    ],
    "sg:phone":"+61 2 4297 2017",
    "sg:postcode":"2528",
    "sg:province":"NSW",
    "sg:tags":[
        "oil",
        "recovery",
        "dispersal",
        "spill"
    ],
    "wof:name":"Chemical Brokers The",
    "wof:placetype":"venue"
},
  "geometry": {"coordinates":[150.866577148,-34.547542572],"type":"Point"}
}