{
  "type": "Feature",
  "properties": {
    "iso:country":"AU",
    "sg:address":"Shp5/ 37 Main St",
    "sg:city":"Samford Village",
    "sg:classifiers":[
        {
            "category":"Cafe",
            "type":"Food & Drink"
        }
    ],
    "sg:phone":"+61 7 3289 5555",
    "sg:postcode":"4520",
    "sg:province":"QLD",
    "wof:name":"Sherdelle Expresso Cafe",
    "wof:placetype":"venue"
},
  "geometry": {"coordinates":[152.88694799999999,-27.370361],"type":"Point"}
}