{
  "type": "Feature",
  "properties": {
    "addr:full":"26- 28 Spray Ave Mordialloc VIC 3195",
    "addr:housenumber":"28",
    "addr:postcode":"3195",
    "addr:street":"Spray Ave",
    "iso:country":"AU",
    "sg:address":"26- 28 Spray Ave",
    "sg:city":"Mordialloc",
    "sg:classifiers":[
        {
            "category":"Retail",
            "subcategory":"Storage",
            "type":"Services"
        }
    ],
    "sg:phone":"+61 3 9580 5754",
    "sg:postcode":"3195",
    "sg:province":"VIC",
    "sg:tags":[
        "removal",
        "furniture"
    ],
    "wof:name":"EW Hogan Moving & Storage",
    "wof:placetype":"venue"
},
  "geometry": {"coordinates":[145.10188293499999,-38.0102920532],"type":"Point"}
}