{
  "type": "Feature",
  "properties": {
    "iso:country":"AU",
    "sg:address":"Lake Boga Rd",
    "sg:city":"Ultima",
    "sg:classifiers":[
        {
            "category":"Farming",
            "subcategory":"Farm",
            "type":"Manufacturing & Wholesale Goods"
        }
    ],
    "sg:phone":"+61 3 5039 6361",
    "sg:postcode":"3544",
    "sg:province":"VIC",
    "sg:tags":[
        "farmer"
    ],
    "wof:name":"O&#039;Brien W J & W L",
    "wof:placetype":"venue"
},
  "geometry": {"coordinates":[143.265426636,-35.4662590027],"type":"Point"}
}