{
  "type": "Feature",
  "properties": {
    "addr:full":"14 Narrang St Southport QLD 4215",
    "addr:housenumber":"14",
    "addr:postcode":"4215",
    "addr:street":"Narrang St",
    "iso:country":"AU",
    "sg:address":"14 Narrang St",
    "sg:city":"Southport",
    "sg:classifiers":[
        {
            "category":"Banks & Credit Unions",
            "subcategory":"Bank",
            "type":"Services"
        }
    ],
    "sg:phone":"+61 402 983 798",
    "sg:postcode":"4215",
    "sg:province":"QLD",
    "sg:tags":[
        "broker",
        "mortgage"
    ],
    "wof:name":"Loan Market Southport",
    "wof:placetype":"venue"
},
  "geometry": {"coordinates":[153.41537475600001,-27.9669780731],"type":"Point"}
}