{
  "type": "Feature",
  "properties": {
    "addr:full":"128 Platypus Drv Uralba NSW 2477",
    "addr:housenumber":"128",
    "addr:postcode":"2477",
    "addr:street":"Platypus Drv",
    "iso:country":"AU",
    "sg:address":"128 Platypus Drv",
    "sg:city":"Uralba",
    "sg:classifiers":[
        {
            "category":"Education",
            "subcategory":"Special Training",
            "type":"Public Place"
        }
    ],
    "sg:phone":"+61 2 6628 7163",
    "sg:postcode":"2477",
    "sg:province":"NSW",
    "sg:tags":[
        "school",
        "art"
    ],
    "wof:name":"Maria's Folk Art & Decorative Painting",
    "wof:placetype":"venue"
},
  "geometry": {"coordinates":[153.45603942899999,-28.8792095184],"type":"Point"}
}