{
  "type": "Feature",
  "properties": {
    "addr:full":"25 Florence St Tweed Heads NSW 2485",
    "addr:housenumber":"25",
    "addr:postcode":"2485",
    "addr:street":"Florence St",
    "iso:country":"AU",
    "sg:address":"25 Florence St",
    "sg:city":"Tweed Heads",
    "sg:classifiers":[
        {
            "category":"Professional",
            "subcategory":"Accounting & Tax Preparation",
            "type":"Services"
        }
    ],
    "sg:phone":"+61 7 5536 6227",
    "sg:postcode":"2485",
    "sg:province":"NSW",
    "sg:tags":[
        "consultant",
        "taxation"
    ],
    "wof:name":"Business Development Solutions - Brian Davis",
    "wof:placetype":"venue"
},
  "geometry": {"coordinates":[153.54043579099999,-28.1754455566],"type":"Point"}
}