{
  "type": "Feature",
  "properties": {
    "addr:full":"3 Broadbeach Drv Maslin Beach SA 5170",
    "addr:housenumber":"3",
    "addr:postcode":"5170",
    "addr:street":"Broadbeach Drv",
    "iso:country":"AU",
    "sg:address":"3 Broadbeach Drv",
    "sg:city":"Maslin Beach",
    "sg:classifiers":[
        {
            "category":"Building & Trades",
            "subcategory":"Construction",
            "type":"Services"
        }
    ],
    "sg:phone":"+61 8 8327 1939",
    "sg:postcode":"5170",
    "sg:province":"SA",
    "sg:tags":[
        "brick",
        "paving"
    ],
    "wof:name":"C Mason Landscape",
    "wof:placetype":"venue"
},
  "geometry": {"coordinates":[138.47598266599999,-35.2283782959],"type":"Point"}
}