{
  "type": "Feature",
  "properties": {
    "iso:country":"AU",
    "sg:address":"78 Princeton Ave",
    "sg:city":"Adamstown Heights",
    "sg:classifiers":[
        {
            "category":"Farming",
            "subcategory":"Farm & Veterinary Services",
            "type":"Manufacturing & Wholesale Goods"
        }
    ],
    "sg:phone":"+61 2 4952 2772",
    "sg:postcode":"2289",
    "sg:province":"NSW",
    "sg:tags":[
        "worm"
    ],
    "wof:name":"Sharpening Shop",
    "wof:placetype":"venue"
},
  "geometry": {"coordinates":[151.70474243199999,-32.9459114075],"type":"Point"}
}