{
  "type": "Feature",
  "properties": {
    "addr:full":"34 Kenneth Rd High Wycombe WA 6057",
    "addr:housenumber":"34",
    "addr:postcode":"6057",
    "addr:street":"Kenneth Rd",
    "iso:country":"AU",
    "sg:address":"34 Kenneth Rd",
    "sg:city":"High Wycombe",
    "sg:classifiers":[
        {
            "category":"Professional",
            "subcategory":"Accounting & Tax Preparation",
            "type":"Services"
        }
    ],
    "sg:phone":"+61 8 9454 6860",
    "sg:postcode":"6057",
    "sg:province":"WA",
    "sg:tags":[
        "accountant",
        "auditor"
    ],
    "wof:name":"Miles Barry A",
    "wof:placetype":"venue"
},
  "geometry": {"coordinates":[116.01071167000001,-31.9352912903],"type":"Point"}
}