{
  "type": "Feature",
  "properties": {
    "iso:country":"AU",
    "sg:address":"Factory 2 28 Coolstore Rd",
    "sg:city":"Croydon",
    "sg:classifiers":[
        {
            "category":"Retail",
            "subcategory":"Auto Repair",
            "type":"Services"
        }
    ],
    "sg:phone":"+61 3 9724 9988",
    "sg:postcode":"3136",
    "sg:province":"VIC",
    "sg:tags":[
        "automotive",
        "air conditioning"
    ],
    "wof:name":"Mooroolbark Automotive",
    "wof:placetype":"venue"
},
  "geometry": {"coordinates":[145.28424072300001,-37.7943496704],"type":"Point"}
}