{
  "type": "Feature",
  "properties": {
    "addr:full":"314 Wyndham St Shepparton VIC 3630",
    "addr:housenumber":"314",
    "addr:postcode":"3630",
    "addr:street":"Wyndham St",
    "iso:country":"AU",
    "sg:address":"314 Wyndham St",
    "sg:city":"Shepparton",
    "sg:classifiers":[
        {
            "category":"Shopping",
            "subcategory":"News",
            "type":"Retail Goods"
        }
    ],
    "sg:phone":"+61 3 5821 4126",
    "sg:postcode":"3630",
    "sg:province":"VIC",
    "sg:tags":[
        "magazine",
        "periodical"
    ],
    "wof:name":"Goulburn Valley Newsagency",
    "wof:placetype":"venue"
},
  "geometry": {"coordinates":[145.39935302699999,-36.3801841736],"type":"Point"}
}