{
  "type": "Feature",
  "properties": {
    "addr:full":"4 Franklin Pl Coffs Harbour NSW 2450",
    "addr:housenumber":"4",
    "addr:postcode":"2450",
    "addr:street":"Franklin Pl",
    "iso:country":"AU",
    "sg:address":"4 Franklin Pl",
    "sg:city":"Coffs Harbour",
    "sg:classifiers":[
        {
            "category":"Personal",
            "subcategory":"Beauty Salon",
            "type":"Services"
        }
    ],
    "sg:phone":"+61 2 6651 5788",
    "sg:postcode":"2450",
    "sg:province":"NSW",
    "sg:tags":[
        "hairdresser"
    ],
    "wof:name":"Sandy's Hair Art",
    "wof:placetype":"venue"
},
  "geometry": {"coordinates":[153.1068573,-30.279417038],"type":"Point"}
}