{
  "type": "Feature",
  "properties": {
    "iso:country":"AU",
    "sg:address":"Warwick 8 Cinemas",
    "sg:city":"Warwick",
    "sg:classifiers":[
        {
            "category":"Sports & Exercise",
            "subcategory":"Sports Center",
            "type":"Entertainment"
        }
    ],
    "sg:phone":"+61 8 9243 5794",
    "sg:postcode":"6024",
    "sg:province":"WA",
    "sg:tags":[
        "card",
        "memorabilia"
    ],
    "wof:name":"Star World Memorabilia",
    "wof:placetype":"venue"
},
  "geometry": {"coordinates":[115.80857849100001,-31.8337993622],"type":"Point"}
}