{
  "type": "Feature",
  "properties": {
    "addr:full":"PO Box 342 Wilston QLD 4051",
    "addr:postcode":"4051",
    "iso:country":"AU",
    "sg:address":"PO Box 342",
    "sg:city":"Wilston",
    "sg:classifiers":[
        {
            "category":"Professional",
            "subcategory":"Art Services",
            "type":"Services"
        }
    ],
    "sg:phone":"+61 411 722 957",
    "sg:postcode":"4051",
    "sg:province":"QLD",
    "sg:tags":[
        "decorator",
        "painter"
    ],
    "wof:name":"Brian Hall Painting Contractors",
    "wof:placetype":"venue"
},
  "geometry": {"coordinates":[153.019622803,-27.4321994781],"type":"Point"}
}