{
  "type": "Feature",
  "properties": {
    "iso:country":"AU",
    "sg:address":"22 Lily St",
    "sg:city":"Goodwood",
    "sg:classifiers":[
        {
            "category":"Professional",
            "subcategory":"Art Services",
            "type":"Services"
        }
    ],
    "sg:phone":"+61 8 8272 1824",
    "sg:postcode":"5034",
    "sg:province":"SA",
    "sg:tags":[
        "picture",
        "frame",
        "framing"
    ],
    "wof:name":"Sinclair Lloyd Framers",
    "wof:placetype":"venue"
},
  "geometry": {"coordinates":[138.591796875,-34.9517669678],"type":"Point"}
}