{
  "type": "Feature",
  "properties": {
    "iso:country":"AU",
    "sg:address":"36 Bridges Rd",
    "sg:city":"New Lambton",
    "sg:classifiers":[
        {
            "category":"Health Services",
            "subcategory":"Chiropractor",
            "type":"Services"
        }
    ],
    "sg:phone":"+61 2 4952 9559",
    "sg:postcode":"2305",
    "sg:province":"NSW",
    "wof:name":"A1 Care Chiropractic",
    "wof:placetype":"venue"
},
  "geometry": {"coordinates":[151.719345,-32.92535],"type":"Point"}
}