{
  "type": "Feature",
  "properties": {
    "addr:full":"Lot981/ Industrial Rd Denmark WA 6333",
    "addr:postcode":"6333",
    "addr:street":"Industrial Rd",
    "iso:country":"AU",
    "sg:address":"Lot981/ Industrial Rd",
    "sg:city":"Denmark",
    "sg:classifiers":[
        {
            "category":"Retail",
            "subcategory":"Repair Shop",
            "type":"Services"
        }
    ],
    "sg:phone":"+61 8 9848 2500",
    "sg:postcode":"6333",
    "sg:province":"WA",
    "sg:tags":[
        "machine",
        "repairs",
        "part",
        "dryer",
        "washing"
    ],
    "wof:name":"Denmark Appliance Repairs",
    "wof:placetype":"venue"
},
  "geometry": {"coordinates":[117.355636597,-34.9674606323],"type":"Point"}
}