{
  "type": "Feature",
  "properties": {
    "iso:country":"AU",
    "sg:address":"Shop 1/ 1 Poolwood Rd",
    "sg:city":"Kewarra Beach",
    "sg:classifiers":[
        {
            "category":"Personal",
            "subcategory":"Skin Care",
            "type":"Services"
        }
    ],
    "sg:phone":"+61 7 4057 5533",
    "sg:postcode":"4879",
    "sg:province":"QLD",
    "sg:tags":[
        "treatment"
    ],
    "wof:name":"Baby Dolls Beauty & Laser Boutique",
    "wof:placetype":"venue"
},
  "geometry": {"coordinates":[145.68121337900001,-16.7906360626],"type":"Point"}
}