{
  "type": "Feature",
  "properties": {
    "addr:full":"Suite 86, 24 Buchanan St Balmain NSW 2041",
    "addr:housenumber":"24",
    "addr:postcode":"2041",
    "addr:street":"Buchanan St",
    "iso:country":"AU",
    "sg:address":"Suite 86, 24 Buchanan St",
    "sg:city":"Balmain",
    "sg:classifiers":[
        {
            "category":"Travel",
            "subcategory":"Travel Agent",
            "type":"Entertainment"
        }
    ],
    "sg:phone":"+61 2 9810 5266",
    "sg:postcode":"2041",
    "sg:province":"NSW",
    "sg:tags":[
        "consultant"
    ],
    "wof:name":"Travelations",
    "wof:placetype":"venue"
},
  "geometry": {"coordinates":[151.180206,-33.863392],"type":"Point"}
}