{
  "type": "Feature",
  "properties": {
    "addr:full":"235A St Georges Rd Northcote VIC 3070",
    "addr:postcode":"3070",
    "addr:street":"235A St Georges Rd",
    "iso:country":"AU",
    "sg:address":"235A St Georges Rd",
    "sg:city":"Northcote",
    "sg:classifiers":[
        {
            "category":"Banks & Credit Unions",
            "subcategory":"Financial Services",
            "type":"Services"
        }
    ],
    "sg:phone":"+61 3 9482 6090",
    "sg:postcode":"3070",
    "sg:province":"VIC",
    "sg:tags":[
        "planning"
    ],
    "wof:name":"AXA Financial Planning",
    "wof:placetype":"venue"
},
  "geometry": {"coordinates":[144.99169900000001,-37.764961],"type":"Point"}
}