{
  "type": "Feature",
  "properties": {
    "addr:full":"31 Nelson St Smithton TAS 7330",
    "addr:housenumber":"31",
    "addr:postcode":"7330",
    "addr:street":"Nelson St",
    "iso:country":"AU",
    "sg:address":"31 Nelson St",
    "sg:city":"Smithton",
    "sg:classifiers":[
        {
            "category":"Home & Garden",
            "subcategory":"Carpets & Floor Coverings",
            "type":"Retail Goods"
        }
    ],
    "sg:phone":"+61 409 002 714",
    "sg:postcode":"7330",
    "sg:province":"TAS",
    "sg:tags":[
        "double",
        "window",
        "glazed"
    ],
    "wof:name":"Clark Windows",
    "wof:placetype":"venue"
},
  "geometry": {"coordinates":[145.12013200000001,-40.850346],"type":"Point"}
}