{
  "type": "Feature",
  "properties": {
    "iso:country":"AU",
    "sg:address":"237 Hampshire Rd",
    "sg:city":"Sunshine",
    "sg:classifiers":[
        {
            "category":"Banks & Credit Unions",
            "subcategory":"Financial Services",
            "type":"Services"
        }
    ],
    "sg:phone":"+61 3 9311 8822",
    "sg:postcode":"3020",
    "sg:province":"VIC",
    "sg:tags":[
        "loan",
        "finance",
        "mortgage"
    ],
    "wof:name":"Mortgage House Of Australia",
    "wof:placetype":"venue"
},
  "geometry": {"coordinates":[144.831863,-37.78503],"type":"Point"}
}