{
  "type": "Feature",
  "properties": {
    "iso:country":"AU",
    "sg:address":"28 George St",
    "sg:city":"Mackay",
    "sg:classifiers":[
        {
            "category":"Personal",
            "subcategory":"Beauty Salon",
            "type":"Services"
        }
    ],
    "sg:phone":"+61 7 4957 4311",
    "sg:postcode":"4740",
    "sg:province":"QLD",
    "sg:tags":[
        "hairdresser"
    ],
    "wof:name":"Klippitz Hairworld",
    "wof:placetype":"venue"
},
  "geometry": {"coordinates":[149.18112199999999,-21.150576],"type":"Point"}
}