{
  "type": "Feature",
  "properties": {
    "addr:full":"492 Sheffield Rd Montrose VIC 3765",
    "addr:housenumber":"492",
    "addr:postcode":"3765",
    "addr:street":"Sheffield Rd",
    "iso:country":"AU",
    "sg:address":"492 Sheffield Rd",
    "sg:city":"Montrose",
    "sg:classifiers":[
        {
            "category":"Professional",
            "subcategory":"Art Services",
            "type":"Services"
        }
    ],
    "sg:phone":"+61 3 9728 6396",
    "sg:postcode":"3765",
    "sg:province":"VIC",
    "sg:tags":[
        "artist"
    ],
    "wof:name":"Art Design Unique",
    "wof:placetype":"venue"
},
  "geometry": {"coordinates":[145.35824585,-37.8104019165],"type":"Point"}
}