{
  "type": "Feature",
  "properties": {
    "addr:full":"Coffs Harbour Community Vllge Earl St Coffs Harbour NSW 2450",
    "addr:postcode":"2450",
    "addr:street":"Earl St",
    "iso:country":"AU",
    "sg:address":"Coffs Harbour Community Vllge Earl St",
    "sg:city":"Coffs Harbour",
    "sg:classifiers":[
        {
            "category":"Organizations",
            "subcategory":"Community Association",
            "type":"Services"
        }
    ],
    "sg:phone":"+61 2 6652 5522",
    "sg:postcode":"2450",
    "sg:province":"NSW",
    "sg:tags":[
        "organisation",
        "family",
        "welfare"
    ],
    "wof:name":"Home Care Service Of NSW",
    "wof:placetype":"venue"
},
  "geometry": {"coordinates":[153.118011,-30.299429],"type":"Point"}
}