{
  "type": "Feature",
  "properties": {
    "iso:country":"AU",
    "sg:address":"41 Franklin St",
    "sg:city":"Woolooware",
    "sg:classifiers":[
        {
            "category":"Social Services",
            "subcategory":"Child Care",
            "type":"Services"
        }
    ],
    "sg:phone":"+61 2 9523 9944",
    "sg:postcode":"2230",
    "sg:province":"NSW",
    "wof:name":"Sutherland Shire Council Long Day Care Centre",
    "wof:placetype":"venue"
},
  "geometry": {"coordinates":[151.14793395999999,-34.0475120544],"type":"Point"}
}