{
  "type": "Feature",
  "properties": {
    "iso:country":"AU",
    "sg:address":"151b York St",
    "sg:city":"Subiaco",
    "sg:classifiers":[
        {
            "category":"Wholesale",
            "subcategory":"Meat",
            "type":"Manufacturing & Wholesale Goods"
        }
    ],
    "sg:phone":"+61 8 9380 6440",
    "sg:postcode":"6008",
    "sg:province":"WA",
    "sg:tags":[
        "packing",
        "exporting"
    ],
    "wof:name":"Hamersley Marketing International",
    "wof:placetype":"venue"
},
  "geometry": {"coordinates":[115.83129119900001,-31.9463863373],"type":"Point"}
}