{
  "type": "Feature",
  "properties": {
    "addr:full":"69 Kite St Orange NSW 2800",
    "addr:housenumber":"69",
    "addr:postcode":"2800",
    "addr:street":"Kite St",
    "iso:country":"AU",
    "sg:address":"69 Kite St",
    "sg:city":"Orange",
    "sg:classifiers":[
        {
            "category":"Professional",
            "subcategory":"Engineering",
            "type":"Services"
        }
    ],
    "sg:phone":"+61 2 6369 1880",
    "sg:postcode":"2800",
    "sg:province":"NSW",
    "sg:tags":[
        "consulting",
        "engineer"
    ],
    "wof:name":"G-Kel Engineering Pty Ltd",
    "wof:placetype":"venue"
},
  "geometry": {"coordinates":[149.095336914,-33.2848892212],"type":"Point"}
}