{
  "type": "Feature",
  "properties": {
    "iso:country":"AU",
    "sg:address":"Level 1 55 Grafton St",
    "sg:city":"Bondi Junction",
    "sg:classifiers":[
        {
            "category":"Professional",
            "subcategory":"Art Services",
            "type":"Services"
        }
    ],
    "sg:phone":"+61 2 9369 4777",
    "sg:postcode":"2022",
    "sg:province":"NSW",
    "sg:tags":[
        "graphic",
        "designer"
    ],
    "wof:name":"Claudine Lyons",
    "wof:placetype":"venue"
},
  "geometry": {"coordinates":[151.24577331500001,-33.8904838562],"type":"Point"}
}