{
  "type": "Feature",
  "properties": {
    "iso:country":"AU",
    "sg:address":"Shop 4/ 600 Main North Rd",
    "sg:city":"Munno Para",
    "sg:classifiers":[
        {
            "category":"Fast Food",
            "type":"Food & Drink"
        }
    ],
    "sg:phone":"+61 8 8254 1333",
    "sg:postcode":"5115",
    "sg:province":"SA",
    "sg:tags":[
        "away",
        "take"
    ],
    "wof:name":"Barnacle Bill",
    "wof:placetype":"venue"
},
  "geometry": {"coordinates":[138.696243286,-34.6788139343],"type":"Point"}
}