{
  "type": "Feature",
  "properties": {
    "addr:full":"Thornlie Community Centre Glenbrook Rd Thornlie WA 6108",
    "addr:postcode":"6108",
    "addr:street":"Glenbrook Rd",
    "iso:country":"AU",
    "sg:address":"Thornlie Community Centre Glenbrook Rd",
    "sg:city":"Thornlie",
    "sg:classifiers":[
        {
            "category":"Shopping",
            "subcategory":"Bicycles & Sporting Goods",
            "type":"Retail Goods"
        }
    ],
    "sg:phone":"+61 8 9451 2560",
    "sg:postcode":"6108",
    "sg:province":"WA",
    "sg:tags":[
        "trampoline"
    ],
    "wof:name":"Thornlie Trampoline Club",
    "wof:placetype":"venue"
},
  "geometry": {"coordinates":[115.96975707999999,-32.0545310974],"type":"Point"}
}