{
  "type": "Feature",
  "properties": {
    "addr:full":"254 Henry St Deniliquin NSW 2710",
    "addr:housenumber":"254",
    "addr:postcode":"2710",
    "addr:street":"Henry St",
    "iso:country":"AU",
    "sg:address":"254 Henry St",
    "sg:city":"Deniliquin",
    "sg:classifiers":[
        {
            "category":"Retail",
            "subcategory":"Repair Shop",
            "type":"Services"
        }
    ],
    "sg:phone":"+61 417 629 488",
    "sg:postcode":"2710",
    "sg:province":"NSW",
    "sg:tags":[
        "stove",
        "part",
        "range"
    ],
    "wof:name":"I.D. Appliance Service",
    "wof:placetype":"venue"
},
  "geometry": {"coordinates":[144.95242309599999,-35.5284957886],"type":"Point"}
}