{
  "type": "Feature",
  "properties": {
    "addr:full":"Shop C1 Harbourtown Regional Shopping Centre, Gold & Oxley Drive Biggera Waters QLD 4216",
    "addr:housenumber":"c1",
    "addr:postcode":"4216",
    "addr:street":"Harbourtown Regional Shopping;Drive",
    "iso:country":"AU",
    "sg:address":"Shop C1 Harbourtown Regional Shopping Centre, Gold",
    "sg:city":"& Oxley Drive Biggera Waters",
    "sg:classifiers":[
        {
            "category":"Shopping",
            "subcategory":"Clothing, Apparel, & Fashions",
            "type":"Retail Goods"
        }
    ],
    "sg:phone":"+61 7 5529 2599",
    "sg:postcode":"4216",
    "sg:province":"QLD",
    "sg:tags":[
        "lady",
        "wear"
    ],
    "wof:name":"My Size Pty Ltd",
    "wof:placetype":"venue"
},
  "geometry": {"coordinates":[153.400558472,-27.9347896576],"type":"Point"}
}