{
  "type": "Feature",
  "properties": {
    "iso:country":"AU",
    "sg:address":"Suite 1/ 37 Princes Hwy",
    "sg:city":"Dandenong",
    "sg:classifiers":[
        {
            "category":"Banks & Credit Unions",
            "subcategory":"Investment Brokerage",
            "type":"Services"
        }
    ],
    "sg:phone":"+61 3 9791 1711",
    "sg:postcode":"3175",
    "sg:province":"VIC",
    "sg:tags":[
        "finance",
        "broker"
    ],
    "wof:name":"Plant & Equipment Finance Pty Ltd",
    "wof:placetype":"venue"
},
  "geometry": {"coordinates":[145.212280273,-37.9835166931],"type":"Point"}
}