{
  "type": "Feature",
  "properties": {
    "addr:full":"Federal Hwy Watson ACT 2602",
    "addr:postcode":"2602",
    "addr:street":"Federal Hwy",
    "iso:country":"AU",
    "sg:address":"Federal Hwy",
    "sg:city":"Watson",
    "sg:classifiers":[
        {
            "category":"Travel",
            "subcategory":"Hotels & Motels",
            "type":"Entertainment"
        }
    ],
    "sg:phone":"+61 2 6241 1377",
    "sg:postcode":"2602",
    "sg:province":"ACT",
    "wof:name":"Motel Carotel",
    "wof:placetype":"venue"
},
  "geometry": {"coordinates":[149.14895629899999,-35.2324028015],"type":"Point"}
}