{
  "type": "Feature",
  "properties": {
    "addr:full":"1st Floor 195b Burwood Rd Burwood NSW 2134",
    "addr:housenumber":"195b",
    "addr:postcode":"2134",
    "addr:street":"Burwood Rd",
    "iso:country":"AU",
    "sg:address":"1st Floor 195b Burwood Rd",
    "sg:city":"Burwood",
    "sg:classifiers":[
        {
            "category":"Banks & Credit Unions",
            "subcategory":"Financial Services",
            "type":"Services"
        }
    ],
    "sg:phone":"+61 2 9744 2075",
    "sg:postcode":"2134",
    "sg:province":"NSW",
    "sg:tags":[
        "loan",
        "finance",
        "mortgage"
    ],
    "wof:name":"I Financial Services",
    "wof:placetype":"venue"
},
  "geometry": {"coordinates":[151.10287475600001,-33.8806915283],"type":"Point"}
}