{
  "type": "Feature",
  "properties": {
    "addr:full":"9th Floor 118 King William St Adelaide SA 5000",
    "addr:housenumber":"118",
    "addr:postcode":"5000",
    "addr:street":"King William St",
    "iso:country":"AU",
    "sg:address":"9th Floor 118 King William St",
    "sg:city":"Adelaide",
    "sg:classifiers":[
        {
            "category":"Insurance",
            "subcategory":"Insurance Agent",
            "type":"Services"
        }
    ],
    "sg:phone":"+61 8 8212 1522",
    "sg:postcode":"5000",
    "sg:province":"SA",
    "wof:name":"Martin Insurance Agencies Pty Ltd",
    "wof:placetype":"venue"
},
  "geometry": {"coordinates":[138.600006103,-34.9256477356],"type":"Point"}
}