{
  "type": "Feature",
  "properties": {
    "addr:full":"Level 2, 282 Oxford St Paddington NSW 2021",
    "addr:housenumber":"282",
    "addr:postcode":"2021",
    "addr:street":"Oxford St",
    "iso:country":"AU",
    "sg:address":"Level 2, 282 Oxford St",
    "sg:city":"Paddington",
    "sg:classifiers":[
        {
            "category":"Personal",
            "subcategory":"Beauty Salon",
            "type":"Services"
        }
    ],
    "sg:phone":"+61 2 9361 3399",
    "sg:postcode":"2021",
    "sg:province":"NSW",
    "sg:tags":[
        "wig",
        "hairpiece"
    ],
    "wof:name":"3am Wigs",
    "wof:placetype":"venue"
},
  "geometry": {"coordinates":[151.227981567,-33.8852233887],"type":"Point"}
}