{
  "type": "Feature",
  "properties": {
    "iso:country":"AU",
    "sg:address":"216A Mair St",
    "sg:city":"Ballarat",
    "sg:classifiers":[
        {
            "category":"Real Estate",
            "subcategory":"Real Estate Services",
            "type":"Services"
        }
    ],
    "sg:phone":"+61 3 5338 8355",
    "sg:postcode":"3350",
    "sg:province":"VIC",
    "sg:tags":[
        "valuer"
    ],
    "wof:name":"Landlink Property Group",
    "wof:placetype":"venue"
},
  "geometry": {"coordinates":[143.857391,-37.559483],"type":"Point"}
}