{
  "type": "Feature",
  "properties": {
    "iso:country":"AU",
    "sg:address":"49 Carrington Rd",
    "sg:city":"Toowoomba",
    "sg:classifiers":[
        {
            "category":"Wholesale",
            "subcategory":"Machinery & Supplies",
            "type":"Manufacturing & Wholesale Goods"
        }
    ],
    "sg:phone":"+61 1300 783 379",
    "sg:postcode":"4350",
    "sg:province":"QLD",
    "sg:tags":[
        "agricultural"
    ],
    "sg:website":"http://www.widelandrural.com.au",
    "wof:name":"Wideland Rural & Construction",
    "wof:placetype":"venue"
},
  "geometry": {"coordinates":[151.87649500000001,-27.542072],"type":"Point"}
}