{
  "type": "Feature",
  "properties": {
    "addr:full":"PO Box 2060 Logan City Delivery Centre QLD 4114",
    "addr:postcode":"4114",
    "iso:country":"AU",
    "sg:address":"PO Box 2060",
    "sg:city":"Logan City Delivery Centre",
    "sg:classifiers":[
        {
            "category":"Manufacturing",
            "subcategory":"Building Materials",
            "type":"Manufacturing & Wholesale Goods"
        }
    ],
    "sg:phone":"+61 409 568 177",
    "sg:postcode":"4114",
    "sg:province":"QLD",
    "sg:tags":[
        "equipment",
        "handling"
    ],
    "wof:name":"Manquip Pty Ltd",
    "wof:placetype":"venue"
},
  "geometry": {"coordinates":[153.11332702600001,-27.6484107971],"type":"Point"}
}