{
  "type": "Feature",
  "properties": {
    "addr:full":"383 Canterbury Rd Heathmont VIC 3135",
    "addr:housenumber":"383",
    "addr:postcode":"3135",
    "addr:street":"Canterbury Rd",
    "iso:country":"AU",
    "sg:address":"383 Canterbury Rd",
    "sg:city":"Heathmont",
    "sg:classifiers":[
        {
            "category":"Manufacturing",
            "subcategory":"Signs",
            "type":"Manufacturing & Wholesale Goods"
        }
    ],
    "sg:phone":"+61 3 8801 4045",
    "sg:postcode":"3135",
    "sg:province":"VIC",
    "sg:tags":[
        "traffic",
        "safety"
    ],
    "wof:name":"Legend Graphics",
    "wof:placetype":"venue"
},
  "geometry": {"coordinates":[145.25852966299999,-37.8267822266],"type":"Point"}
}