{
  "type": "Feature",
  "properties": {
    "addr:full":"193 Fenaughty St Kyabram VIC 3620",
    "addr:housenumber":"193",
    "addr:postcode":"3620",
    "addr:street":"Fenaughty St",
    "iso:country":"AU",
    "sg:address":"193 Fenaughty St",
    "sg:city":"Kyabram",
    "sg:classifiers":[
        {
            "category":"Professional",
            "subcategory":"Printing & Photocopies",
            "type":"Services"
        }
    ],
    "sg:phone":"+61 3 5852 2947",
    "sg:postcode":"3620",
    "sg:province":"VIC",
    "sg:tags":[
        "trophy"
    ],
    "wof:name":"Budget Trophies",
    "wof:placetype":"venue"
},
  "geometry": {"coordinates":[145.04800415,-36.3144683838],"type":"Point"}
}