{
  "type": "Feature",
  "properties": {
    "iso:country":"AU",
    "sg:address":"211 Auburn St",
    "sg:city":"Goulburn",
    "sg:classifiers":[
        {
            "category":"Banks & Credit Unions",
            "subcategory":"Bank",
            "type":"Services"
        }
    ],
    "sg:phone":"+61 2 4828 5840",
    "sg:postcode":"2580",
    "sg:province":"NSW",
    "sg:tags":[
        "society"
    ],
    "wof:name":"BDCU",
    "wof:placetype":"venue"
},
  "geometry": {"coordinates":[149.72059631400001,-34.7518234253],"type":"Point"}
}