{
  "type": "Feature",
  "properties": {
    "iso:country":"AU",
    "sg:address":"12 Marine Pde",
    "sg:city":"Southport",
    "sg:classifiers":[
        {
            "category":"Recreation",
            "type":"Entertainment"
        }
    ],
    "sg:phone":"+61 411 268 292",
    "sg:postcode":"4215",
    "sg:province":"QLD",
    "sg:tags":[
        "hire",
        "tour",
        "motor",
        "cycle"
    ],
    "wof:name":"Prestige Motorcycle Cruises",
    "wof:placetype":"venue"
},
  "geometry": {"coordinates":[153.417434692,-27.9714431763],"type":"Point"}
}