{
  "type": "Feature",
  "properties": {
    "iso:country":"AU",
    "sg:address":"15 Richmond Rd",
    "sg:city":"Kingswood",
    "sg:classifiers":[
        {
            "category":"Professional",
            "subcategory":"Engineering",
            "type":"Services"
        }
    ],
    "sg:phone":"+61 2 4731 2876",
    "sg:postcode":"2747",
    "sg:province":"NSW",
    "sg:tags":[
        "engineer"
    ],
    "wof:name":"Jones Engineering Pty Ltd",
    "wof:placetype":"venue"
},
  "geometry": {"coordinates":[150.71939086899999,-33.7535934448],"type":"Point"}
}