{
  "type": "Feature",
  "properties": {
    "addr:full":"92 Pacific Ave Sunshine Beach QLD 4567",
    "addr:housenumber":"92",
    "addr:postcode":"4567",
    "addr:street":"Pacific Ave Sunshine",
    "iso:country":"AU",
    "sg:address":"92 Pacific Ave",
    "sg:city":"Sunshine Beach",
    "sg:classifiers":[
        {
            "category":"Professional",
            "subcategory":"Engineering",
            "type":"Services"
        }
    ],
    "sg:phone":"+61 7 5455 4488",
    "sg:postcode":"4567",
    "sg:province":"QLD",
    "sg:tags":[
        "consulting",
        "engineer"
    ],
    "wof:name":"RPG Consulting Engineers",
    "wof:placetype":"venue"
},
  "geometry": {"coordinates":[153.108886719,-26.4081916809],"type":"Point"}
}