{
  "type": "Feature",
  "properties": {
    "iso:country":"AU",
    "sg:address":"32 Peterkin St",
    "sg:city":"Acacia Ridge",
    "sg:classifiers":[
        {
            "category":"Taxi",
            "type":"Transportation"
        }
    ],
    "sg:phone":"+61 7 3344 4744",
    "sg:postcode":"4110",
    "sg:province":"QLD",
    "sg:tags":[
        "truck"
    ],
    "wof:name":"ABS Courier Services",
    "wof:placetype":"venue"
},
  "geometry": {"coordinates":[153.03785705600001,-27.5776233673],"type":"Point"}
}