{
  "type": "Feature",
  "properties": {
    "addr:full":"24 Jennings St Zillmere QLD 4034",
    "addr:housenumber":"24",
    "addr:postcode":"4034",
    "addr:street":"Jennings St",
    "iso:country":"AU",
    "sg:address":"24 Jennings St",
    "sg:city":"Zillmere",
    "sg:classifiers":[
        {
            "category":"Education",
            "subcategory":"University",
            "type":"Public Place"
        }
    ],
    "sg:phone":"+61 7 3265 7197",
    "sg:postcode":"4034",
    "sg:province":"QLD",
    "sg:tags":[
        "educational",
        "organisation",
        "cultural"
    ],
    "wof:name":"Bhar-El-Ghazel Upper Nile & Equatoria Students&#039; Association (B.U.N.E.S.A) I",
    "wof:placetype":"venue"
},
  "geometry": {"coordinates":[153.040344,-27.360733],"type":"Point"}
}