{
  "type": "Feature",
  "properties": {
    "addr:full":"25 Percy St Mt Gambier SA 5290",
    "addr:housenumber":"25",
    "addr:postcode":"5290",
    "addr:street":"Percy St",
    "iso:country":"AU",
    "sg:address":"25 Percy St",
    "sg:city":"Mt Gambier",
    "sg:classifiers":[
        {
            "category":"Professional",
            "subcategory":"Business Services",
            "type":"Services"
        }
    ],
    "sg:phone":"+61 8 8723 1288",
    "sg:postcode":"5290",
    "sg:province":"SA",
    "sg:tags":[
        "drafting"
    ],
    "wof:name":"Total Design & Drafting",
    "wof:placetype":"venue"
},
  "geometry": {"coordinates":[140.78152499999999,-37.827923],"type":"Point"}
}