{
  "type": "Feature",
  "properties": {
    "addr:full":"1A Lawton House 60 Cecil Ave Castle Hill NSW 2154",
    "addr:housenumber":"1a;house 60",
    "addr:postcode":"2154",
    "addr:street":"Lawton;Cecil Ave",
    "iso:country":"AU",
    "sg:address":"1A Lawton House 60 Cecil Ave",
    "sg:city":"Castle Hill",
    "sg:classifiers":[
        {
            "category":"Health Services",
            "subcategory":"Dentist",
            "type":"Services"
        }
    ],
    "sg:phone":"+61 2 9899 1404",
    "sg:postcode":"2154",
    "sg:province":"NSW",
    "sg:tags":[
        "dental",
        "emergency"
    ],
    "wof:name":"Castle Hill Family Dental Practice",
    "wof:placetype":"venue"
},
  "geometry": {"coordinates":[151.00538635300001,-33.7346153259],"type":"Point"}
}