{
  "type": "Feature",
  "properties": {
    "addr:full":"15 Beresford Ave Chatswood NSW 2067",
    "addr:housenumber":"15",
    "addr:postcode":"2067",
    "addr:street":"Beresford Ave",
    "iso:country":"AU",
    "sg:address":"15 Beresford Ave",
    "sg:city":"Chatswood",
    "sg:classifiers":[
        {
            "category":"Professional",
            "subcategory":"Printing & Photocopies",
            "type":"Services"
        }
    ],
    "sg:phone":"+61 2 9413 4330",
    "sg:postcode":"2067",
    "sg:province":"NSW",
    "sg:tags":[
        "plaque"
    ],
    "sg:website":"http://www.corporatesigns.com.au",
    "wof:name":"Corporate Signs",
    "wof:placetype":"venue"
},
  "geometry": {"coordinates":[151.173904419,-33.8026504517],"type":"Point"}
}