{
  "type": "Feature",
  "properties": {
    "iso:country":"AU",
    "sg:address":"Beach Rd",
    "sg:city":"Torquay",
    "sg:classifiers":[
        {
            "category":"Museum",
            "type":"Entertainment"
        }
    ],
    "sg:phone":"+61 3 5261 4606",
    "sg:postcode":"3228",
    "sg:province":"VIC",
    "wof:name":"Surfworld Australia",
    "wof:placetype":"venue"
},
  "geometry": {"coordinates":[144.318832,-38.326122],"type":"Point"}
}