{
  "type": "Feature",
  "properties": {
    "addr:full":"Shop 2, 958-978 Doncaster Rd Doncaster VIC 3108",
    "addr:housenumber":"shop 2",
    "addr:postcode":"958-978;3108",
    "addr:street":"Doncaster Rd",
    "iso:country":"AU",
    "sg:address":"Shop 2, 958-978 Doncaster Rd",
    "sg:city":"Doncaster",
    "sg:classifiers":[
        {
            "category":"Personal",
            "subcategory":"Barber",
            "type":"Services"
        }
    ],
    "sg:phone":"+61 3 9841 0888",
    "sg:postcode":"3108",
    "sg:province":"VIC",
    "wof:name":"Devon Barber Shop",
    "wof:placetype":"venue"
},
  "geometry": {"coordinates":[145.15728759800001,-37.7887802124],"type":"Point"}
}