{
  "type": "Feature",
  "properties": {
    "addr:full":"90 Willis Crt Vermont VIC 3133",
    "addr:housenumber":"90",
    "addr:postcode":"3133",
    "addr:street":"Willis Crt",
    "iso:country":"AU",
    "sg:address":"90 Willis Crt",
    "sg:city":"Vermont",
    "sg:classifiers":[
        {
            "category":"Personal",
            "subcategory":"Beauty Salon",
            "type":"Services"
        }
    ],
    "sg:phone":"+61 408 623 336",
    "sg:postcode":"3133",
    "sg:province":"VIC",
    "sg:tags":[
        "supply",
        "artist",
        "make-up"
    ],
    "sg:website":"http://glamourlicious.citysearch.com.au",
    "wof:name":"Glamour Licious",
    "wof:placetype":"venue"
},
  "geometry": {"coordinates":[145.19052124000001,-37.8340034485],"type":"Point"}
}