{
  "type": "Feature",
  "properties": {
    "addr:full":"5/ 82 Sugar Rd Maroochydore QLD 4558",
    "addr:housenumber":"/ 82",
    "addr:postcode":"4558",
    "addr:street":"Sugar Rd",
    "iso:country":"AU",
    "sg:address":"5/ 82 Sugar Rd",
    "sg:city":"Maroochydore",
    "sg:classifiers":[
        {
            "category":"Wholesale",
            "subcategory":"Apparel",
            "type":"Manufacturing & Wholesale Goods"
        }
    ],
    "sg:phone":"+61 7 5443 8448",
    "sg:postcode":"4558",
    "sg:province":"QLD",
    "sg:tags":[
        "wholesaler",
        "mfrs",
        "cap",
        "hat"
    ],
    "wof:name":"Coastal Monogramming",
    "wof:placetype":"venue"
},
  "geometry": {"coordinates":[153.08360290499999,-26.6710605621],"type":"Point"}
}