{
  "type": "Feature",
  "properties": {
    "addr:full":"10 Johns Pl Hume ACT 2620",
    "addr:housenumber":"10",
    "addr:postcode":"2620",
    "addr:street":"Johns Pl",
    "iso:country":"AU",
    "sg:address":"10 Johns Pl",
    "sg:city":"Hume",
    "sg:classifiers":[
        {
            "category":"Building & Trades",
            "subcategory":"Construction",
            "type":"Services"
        }
    ],
    "sg:phone":"+61 2 6260 2562",
    "sg:postcode":"2620",
    "sg:province":"ACT",
    "sg:tags":[
        "scaffolding"
    ],
    "wof:name":"Pacific Formwork (Aust) Pty Ltd",
    "wof:placetype":"venue"
},
  "geometry": {"coordinates":[149.17100524899999,-35.3885612488],"type":"Point"}
}