{
  "type": "Feature",
  "properties": {
    "iso:country":"AU",
    "sg:address":"PO Box 6140",
    "sg:city":"Blacktown",
    "sg:classifiers":[
        {
            "category":"Building & Trades",
            "subcategory":"Cleaning & Sanitation",
            "type":"Services"
        }
    ],
    "sg:phone":"+61 2 8824 9075",
    "sg:postcode":"2148",
    "sg:province":"NSW",
    "sg:tags":[
        "industrial",
        "commercial",
        "contractor"
    ],
    "wof:name":"Suesco Cleaning Services",
    "wof:placetype":"venue"
},
  "geometry": {"coordinates":[150.90814209000001,-33.7725982666],"type":"Point"}
}