{
  "type": "Feature",
  "properties": {
    "iso:country":"AU",
    "sg:address":"Pfeiffer Rd",
    "sg:city":"Woodside",
    "sg:classifiers":[
        {
            "category":"Farming",
            "subcategory":"Farm",
            "type":"Manufacturing & Wholesale Goods"
        }
    ],
    "sg:phone":"+61 8 8389 7294",
    "sg:postcode":"5244",
    "sg:province":"SA",
    "sg:tags":[
        "farmer"
    ],
    "wof:name":"Drummond J H",
    "wof:placetype":"venue"
},
  "geometry": {"coordinates":[138.88955688499999,-34.960521698],"type":"Point"}
}