{
  "type": "Feature",
  "properties": {
    "addr:full":"24 Lawrence St Brighton VIC 3186",
    "addr:housenumber":"24",
    "addr:postcode":"3186",
    "addr:street":"Lawrence St",
    "iso:country":"AU",
    "sg:address":"24 Lawrence St",
    "sg:city":"Brighton",
    "sg:classifiers":[
        {
            "category":"Utilities",
            "subcategory":"Electric",
            "type":"Services"
        }
    ],
    "sg:phone":"+61 3 9592 0591",
    "sg:postcode":"3186",
    "sg:province":"VIC",
    "sg:tags":[
        "electrical",
        "contractor"
    ],
    "wof:name":"A Green & Gold Electrics",
    "wof:placetype":"venue"
},
  "geometry": {"coordinates":[145.000366211,-37.9156951904],"type":"Point"}
}