{
  "type": "Feature",
  "properties": {
    "iso:country":"AU",
    "sg:address":"Lvl 7/ 70 Pitt St",
    "sg:city":"Sydney",
    "sg:classifiers":[
        {
            "category":"Government",
            "subcategory":"Customs House",
            "type":"Public Place"
        }
    ],
    "sg:phone":"+61 2 9324 1111",
    "sg:postcode":"2000",
    "sg:province":"NSW",
    "sg:tags":[
        "title",
        "management",
        "stratum"
    ],
    "wof:name":"Aberdeen Strata Pty Ltd",
    "wof:placetype":"venue"
},
  "geometry": {"coordinates":[151.208786011,-33.8659362793],"type":"Point"}
}