{
  "type": "Feature",
  "properties": {
    "addr:full":"85 Eaton Rd Luddenham NSW 2745",
    "addr:housenumber":"85",
    "addr:postcode":"2745",
    "addr:street":"Eaton Rd",
    "iso:country":"AU",
    "sg:address":"85 Eaton Rd",
    "sg:city":"Luddenham",
    "sg:classifiers":[
        {
            "category":"Farming",
            "subcategory":"Poultry Farm",
            "type":"Manufacturing & Wholesale Goods"
        }
    ],
    "sg:phone":"+61 2 4773 3222",
    "sg:postcode":"2745",
    "sg:province":"NSW",
    "sg:tags":[
        "farmer"
    ],
    "wof:name":"Barter & Sons Hatchery",
    "wof:placetype":"venue"
},
  "geometry": {"coordinates":[150.69943237300001,-33.8852958679],"type":"Point"}
}