{
  "type": "Feature",
  "properties": {
    "iso:country":"AU",
    "sg:address":"PO Box 266",
    "sg:city":"Civic Square",
    "sg:classifiers":[
        {
            "category":"Education",
            "subcategory":"University",
            "type":"Public Place"
        }
    ],
    "sg:phone":"+61 2 6273 2437",
    "sg:postcode":"2608",
    "sg:province":"ACT",
    "sg:tags":[
        "educational",
        "organisation",
        "cultural"
    ],
    "wof:name":"Museums Australia",
    "wof:placetype":"venue"
},
  "geometry": {"coordinates":[149.12167358400001,-35.2839012146],"type":"Point"}
}