{
  "type": "Feature",
  "properties": {
    "iso:country":"AU",
    "sg:address":"PO Box 3252",
    "sg:city":"Nerang Delivery Centre",
    "sg:classifiers":[
        {
            "category":"Professional",
            "subcategory":"Business Services",
            "type":"Services"
        }
    ],
    "sg:phone":"+61 400 942 605",
    "sg:postcode":"4211",
    "sg:province":"QLD",
    "sg:tags":[
        "drafting"
    ],
    "wof:name":"Choice Planning CAD Drafting",
    "wof:placetype":"venue"
},
  "geometry": {"coordinates":[153.384033203,-28.0170440674],"type":"Point"}
}