{
  "type": "Feature",
  "properties": {
    "iso:country":"AU",
    "sg:address":"36 Gibson St",
    "sg:city":"Mt Pleasant",
    "sg:classifiers":[
        {
            "category":"Health Services",
            "subcategory":"Doctor",
            "type":"Services"
        }
    ],
    "sg:phone":"+61 8 9364 9985",
    "sg:postcode":"6153",
    "sg:province":"WA",
    "sg:tags":[
        "medical",
        "practitioner"
    ],
    "wof:name":"Mount Pleasant Wellness Centre",
    "wof:placetype":"venue"
},
  "geometry": {"coordinates":[115.842293,-32.020863],"type":"Point"}
}