{
  "type": "Feature",
  "properties": {
    "iso:country":"AU",
    "sg:address":"Shop 1/ 5 Wongala Crs",
    "sg:city":"Beecroft",
    "sg:classifiers":[
        {
            "category":"Personal",
            "subcategory":"Beauty Salon",
            "type":"Services"
        }
    ],
    "sg:phone":"+61 2 9481 9182",
    "sg:postcode":"2119",
    "sg:province":"NSW",
    "sg:tags":[
        "supply",
        "artist",
        "make-up"
    ],
    "wof:name":"The Art Of Hair & Make Up Bridal Designers",
    "wof:placetype":"venue"
},
  "geometry": {"coordinates":[151.06483459500001,-33.7503204346],"type":"Point"}
}