{
  "type": "Feature",
  "properties": {
    "addr:full":"181 Concord Rd North Strathfield NSW 2137",
    "addr:housenumber":"181",
    "addr:postcode":"2137",
    "addr:street":"Concord Rd",
    "iso:country":"AU",
    "sg:address":"181 Concord Rd",
    "sg:city":"North Strathfield",
    "sg:classifiers":[
        {
            "category":"Banks & Credit Unions",
            "subcategory":"Bank",
            "type":"Services"
        }
    ],
    "sg:phone":"+61 13 20 32",
    "sg:postcode":"2137",
    "sg:province":"NSW",
    "wof:name":"Westpac",
    "wof:placetype":"venue"
},
  "geometry": {"coordinates":[151.092193603,-33.8576507568],"type":"Point"}
}