{
  "type": "Feature",
  "properties": {
    "addr:full":"15 Binney Rd Kings Park NSW 2148",
    "addr:housenumber":"15",
    "addr:postcode":"2148",
    "addr:street":"Binney Rd",
    "iso:country":"AU",
    "sg:address":"15 Binney Rd",
    "sg:city":"Kings Park",
    "sg:classifiers":[
        {
            "category":"Wholesale",
            "subcategory":"Metals & Minerals",
            "type":"Manufacturing & Wholesale Goods"
        }
    ],
    "sg:phone":"+61 2 9671 1033",
    "sg:postcode":"2148",
    "sg:province":"NSW",
    "sg:tags":[
        "steel",
        "stainless",
        "product",
        "equipment"
    ],
    "wof:name":"Stanford Stainless Steel MFG Pty Ltd",
    "wof:placetype":"venue"
},
  "geometry": {"coordinates":[150.906494141,-33.7435493469],"type":"Point"}
}