{
  "type": "Feature",
  "properties": {
    "iso:country":"AU",
    "sg:address":"Unit 2, 30 Canvale Rd",
    "sg:city":"Canning Vale",
    "sg:classifiers":[
        {
            "category":"Autos & Motor Vehicles",
            "subcategory":"Auto Supplies",
            "type":"Retail Goods"
        }
    ],
    "sg:phone":"+61 8 9256 3833",
    "sg:postcode":"6155",
    "sg:province":"WA",
    "sg:tags":[
        "car",
        "alarm"
    ],
    "wof:name":"Westside Car Audio",
    "wof:placetype":"venue"
},
  "geometry": {"coordinates":[115.92363,-32.065887],"type":"Point"}
}