{
  "type": "Feature",
  "properties": {
    "addr:full":"20 Counihan Rd Seventeen Mile Rocks QLD 4073",
    "addr:housenumber":"20",
    "addr:postcode":"4073",
    "addr:street":"Counihan Rd",
    "iso:country":"AU",
    "sg:address":"20 Counihan Rd",
    "sg:city":"Seventeen Mile Rocks",
    "sg:classifiers":[
        {
            "category":"Building & Trades",
            "subcategory":"Construction",
            "type":"Services"
        }
    ],
    "sg:phone":"+61 7 3376 8266",
    "sg:postcode":"4073",
    "sg:province":"QLD",
    "sg:tags":[
        "fencing",
        "contractor"
    ],
    "wof:name":"A Fords Timber Centre",
    "wof:placetype":"venue"
},
  "geometry": {"coordinates":[152.95780944800001,-27.5401973724],"type":"Point"}
}