{
  "type": "Feature",
  "properties": {
    "addr:full":"Level 1, 1454 Logan Rd Upper Mt Gravatt QLD 4122",
    "addr:housenumber":"1454",
    "addr:postcode":"4122",
    "addr:street":"Logan Rd Upper",
    "iso:country":"AU",
    "sg:address":"Level 1, 1454 Logan Rd",
    "sg:city":"Upper Mt Gravatt",
    "sg:classifiers":[
        {
            "category":"Banks & Credit Unions",
            "subcategory":"Financial Services",
            "type":"Services"
        }
    ],
    "sg:phone":"+61 1300 657 872",
    "sg:postcode":"4122",
    "sg:province":"QLD",
    "sg:tags":[
        "planning"
    ],
    "wof:name":"CIS Financial Services Pty Ltd",
    "wof:placetype":"venue"
},
  "geometry": {"coordinates":[153.07916259800001,-27.5377197266],"type":"Point"}
}