{
  "type": "Feature",
  "properties": {
    "addr:full":"221 Pacific Hwy Gore Hill NSW 2065",
    "addr:housenumber":"221",
    "addr:postcode":"2065",
    "addr:street":"Pacific Hwy Gore Hill",
    "iso:country":"AU",
    "sg:address":"221 Pacific Hwy",
    "sg:city":"Gore Hill",
    "sg:classifiers":[
        {
            "category":"Shopping",
            "subcategory":"Party Supplies",
            "type":"Retail Goods"
        }
    ],
    "sg:phone":"+61 2 9950 3171",
    "sg:postcode":"2065",
    "sg:province":"NSW",
    "sg:tags":[
        "hire",
        "costume"
    ],
    "wof:name":"ABC Productions",
    "wof:placetype":"venue"
},
  "geometry": {"coordinates":[151.185714722,-33.8214874268],"type":"Point"}
}