{
  "type": "Feature",
  "properties": {
    "addr:full":"107 Muller Rd Hampstead Gardens SA 5086",
    "addr:housenumber":"107",
    "addr:postcode":"5086",
    "addr:street":"Muller Rd",
    "iso:country":"AU",
    "sg:address":"107 Muller Rd",
    "sg:city":"Hampstead Gardens",
    "sg:classifiers":[
        {
            "category":"Retail",
            "subcategory":"Auto Repair",
            "type":"Services"
        }
    ],
    "sg:phone":"+61 8 8261 2328",
    "sg:postcode":"5086",
    "sg:province":"SA",
    "sg:tags":[
        "beater",
        "painter",
        "panel"
    ],
    "wof:name":"Mullers Road Crash Repairs",
    "wof:placetype":"venue"
},
  "geometry": {"coordinates":[138.633865356,-34.8714294434],"type":"Point"}
}