{
  "type": "Feature",
  "properties": {
    "addr:full":"Shop 4/ 144 Indooroopilly Rd Taringa QLD 4068",
    "addr:housenumber":"shop 4 / 144",
    "addr:postcode":"4068",
    "addr:street":"Indooroopilly Rd",
    "iso:country":"AU",
    "sg:address":"Shop 4/ 144 Indooroopilly Rd",
    "sg:city":"Taringa",
    "sg:classifiers":[
        {
            "category":"Food & Beverages",
            "subcategory":"Fruits & Vegetables",
            "type":"Retail Goods"
        }
    ],
    "sg:phone":"+61 418 755 202",
    "sg:postcode":"4068",
    "sg:province":"QLD",
    "sg:tags":[
        "greengrocer",
        "fruiterer"
    ],
    "wof:name":"Naturally Fruit",
    "wof:placetype":"venue"
},
  "geometry": {"coordinates":[152.99105835,-27.4977779388],"type":"Point"}
}