{
  "type": "Feature",
  "properties": {
    "addr:full":"388 Spencer St West Melbourne VIC 3003",
    "addr:housenumber":"388",
    "addr:postcode":"3003",
    "addr:street":"Spencer St",
    "iso:country":"AU",
    "sg:address":"388 Spencer St",
    "sg:city":"West Melbourne",
    "sg:classifiers":[
        {
            "category":"Professional",
            "subcategory":"Printing & Photocopies",
            "type":"Services"
        }
    ],
    "sg:phone":"+61 3 9329 7771",
    "sg:postcode":"3003",
    "sg:province":"VIC",
    "sg:tags":[
        "photocopying"
    ],
    "wof:name":"Minuteman Press",
    "wof:placetype":"venue"
},
  "geometry": {"coordinates":[144.95074462900001,-37.8113365173],"type":"Point"}
}