{
  "type": "Feature",
  "properties": {
    "addr:full":"Flr1/ 132 Wickham St Fortitude Valley QLD 4006",
    "addr:housenumber":"132",
    "addr:postcode":"4006",
    "addr:street":"Wickham St",
    "iso:country":"AU",
    "sg:address":"Flr1/ 132 Wickham St",
    "sg:city":"Fortitude Valley",
    "sg:classifiers":[
        {
            "category":"Travel",
            "subcategory":"Travel Agent",
            "type":"Entertainment"
        }
    ],
    "sg:phone":"+61 7 3850 7699",
    "sg:postcode":"4006",
    "sg:province":"QLD",
    "sg:tags":[
        "consultant"
    ],
    "wof:name":"Gecko Adventures",
    "wof:placetype":"venue"
},
  "geometry": {"coordinates":[153.031784058,-27.4592437744],"type":"Point"}
}