{
  "type": "Feature",
  "properties": {
    "addr:full":"70 Nelson St Bungalow QLD 4870",
    "addr:housenumber":"70",
    "addr:postcode":"4870",
    "addr:street":"Nelson St",
    "iso:country":"AU",
    "sg:address":"70 Nelson St",
    "sg:city":"Bungalow",
    "sg:classifiers":[
        {
            "category":"Home & Garden",
            "subcategory":"Building Materials",
            "type":"Retail Goods"
        }
    ],
    "sg:phone":"+61 7 4035 2777",
    "sg:postcode":"4870",
    "sg:province":"QLD",
    "sg:tags":[
        "tile",
        "roofing"
    ],
    "wof:name":"Cairns Roofing Contractors",
    "wof:placetype":"venue"
},
  "geometry": {"coordinates":[145.76017761200001,-16.9392471313],"type":"Point"}
}