{
  "type": "Feature",
  "properties": {
    "iso:country":"AU",
    "sg:address":"80 Elgee Rd",
    "sg:city":"Midland",
    "sg:classifiers":[
        {
            "category":"Building & Trades",
            "subcategory":"Plumbing",
            "type":"Services"
        }
    ],
    "sg:phone":"+61 8 9274 6311",
    "sg:postcode":"6056",
    "sg:province":"WA",
    "sg:tags":[
        "fitting",
        "hose",
        "supply"
    ],
    "wof:name":"Hydraulic Seals WA",
    "wof:placetype":"venue"
},
  "geometry": {"coordinates":[116.015426636,-31.8943309784],"type":"Point"}
}