{
  "type": "Feature",
  "properties": {
    "iso:country":"AU",
    "sg:address":"30 Kenny St",
    "sg:city":"Cairns",
    "sg:classifiers":[
        {
            "category":"Utilities",
            "subcategory":"Fuel Oil & Lpg",
            "type":"Services"
        }
    ],
    "sg:phone":"+61 7 4031 1214",
    "sg:postcode":"4870",
    "sg:province":"QLD",
    "sg:tags":[
        "merchant"
    ],
    "wof:name":"Caltex Far North Queensland",
    "wof:placetype":"venue"
},
  "geometry": {"coordinates":[145.77569580100001,-16.9307823181],"type":"Point"}
}