{
  "type": "Feature",
  "properties": {
    "addr:full":"PO Box 5424 Maroochydore QLD 4558",
    "addr:postcode":"4558",
    "iso:country":"AU",
    "sg:address":"PO Box 5424",
    "sg:city":"Maroochydore",
    "sg:classifiers":[
        {
            "category":"Professional",
            "subcategory":"Detective & Security Services",
            "type":"Services"
        }
    ],
    "sg:phone":"+61 7 5443 7955",
    "sg:postcode":"4558",
    "sg:province":"QLD",
    "sg:tags":[
        "consultant",
        "system"
    ],
    "wof:name":"Able Locksmiths",
    "wof:placetype":"venue"
},
  "geometry": {"coordinates":[153.06553649899999,-26.6553192139],"type":"Point"}
}