{
  "type": "Feature",
  "properties": {
    "addr:full":"Cnr Queen St & Princess Ave Rosebery NSW 2018",
    "addr:postcode":"2018",
    "addr:street":"Cnr Queen St & Princess Ave",
    "iso:country":"AU",
    "sg:address":"Cnr Queen St & Princess Ave",
    "sg:city":"Rosebery",
    "sg:classifiers":[
        {
            "category":"Manufacturing",
            "subcategory":"Chemicals & Compounds",
            "type":"Manufacturing & Wholesale Goods"
        }
    ],
    "sg:phone":"+61 2 9663 1771",
    "sg:postcode":"2018",
    "sg:province":"NSW",
    "sg:tags":[
        "electroplating"
    ],
    "wof:name":"Alexandria Plating Pty Ltd",
    "wof:placetype":"venue"
},
  "geometry": {"coordinates":[151.20199585,-33.9141845703],"type":"Point"}
}