{
  "type": "Feature",
  "properties": {
    "addr:full":"U2/ 9 Inspiration Drv Wangara WA 6065",
    "addr:housenumber":"9",
    "addr:postcode":"6065",
    "addr:street":"U2 /;Inspiration Drv",
    "iso:country":"AU",
    "sg:address":"U2/ 9 Inspiration Drv",
    "sg:city":"Wangara",
    "sg:classifiers":[
        {
            "category":"Building & Trades",
            "subcategory":"Construction",
            "type":"Services"
        }
    ],
    "sg:phone":"+61 417 933 734",
    "sg:postcode":"6065",
    "sg:province":"WA",
    "sg:tags":[
        "ceiling"
    ],
    "wof:name":"Future Carpentry & Ceilings",
    "wof:placetype":"venue"
},
  "geometry": {"coordinates":[115.83489227299999,-31.7990341187],"type":"Point"}
}