{
  "type": "Feature",
  "properties": {
    "iso:country":"AU",
    "sg:address":"6/ 104 Railway St",
    "sg:city":"Granville",
    "sg:classifiers":[
        {
            "category":"Building & Trades",
            "subcategory":"Cleaning & Sanitation",
            "type":"Services"
        }
    ],
    "sg:phone":"+61 2 9638 2489",
    "sg:postcode":"2142",
    "sg:province":"NSW",
    "sg:tags":[
        "industrial",
        "commercial",
        "contractor"
    ],
    "wof:name":"A & V Facility Services",
    "wof:placetype":"venue"
},
  "geometry": {"coordinates":[150.99794006400001,-33.8274154663],"type":"Point"}
}