{
  "type": "Feature",
  "properties": {
    "addr:full":"Torrens St Richmond TAS 7025",
    "addr:postcode":"7025",
    "addr:street":"Torrens St",
    "iso:country":"AU",
    "sg:address":"Torrens St",
    "sg:city":"Richmond",
    "sg:classifiers":[
        {
            "category":"Professional",
            "subcategory":"Employment Agencies",
            "type":"Services"
        }
    ],
    "sg:phone":"+61 3 6260 1065",
    "sg:postcode":"7025",
    "sg:province":"TAS",
    "sg:tags":[
        "provider",
        "internet"
    ],
    "wof:name":"Online Access Centres",
    "wof:placetype":"venue"
},
  "geometry": {"coordinates":[147.43765258799999,-42.7384033203],"type":"Point"}
}