{
  "type": "Feature",
  "properties": {
    "iso:country":"AU",
    "sg:address":"9/ 11 Queens Rd",
    "sg:city":"Melbourne",
    "sg:classifiers":[
        {
            "category":"Insurance",
            "subcategory":"Hazard Insurance",
            "type":"Services"
        }
    ],
    "sg:phone":"+61 3 9821 4099",
    "sg:postcode":"3001",
    "sg:province":"VIC",
    "sg:tags":[
        "fire",
        "accident",
        "marine"
    ],
    "wof:name":"Combined Insurance Co Of Aust",
    "wof:placetype":"venue"
},
  "geometry": {"coordinates":[144.97398376500001,-37.8380279541],"type":"Point"}
}