{
  "type": "Feature",
  "properties": {
    "addr:full":"The G St Gungahlin ACT 2912",
    "addr:postcode":"2912",
    "addr:street":"St",
    "iso:country":"AU",
    "sg:address":"The G St",
    "sg:city":"Gungahlin",
    "sg:classifiers":[
        {
            "category":"Retail",
            "subcategory":"Repair Shop",
            "type":"Services"
        }
    ],
    "sg:phone":"+61 2 6255 6611",
    "sg:postcode":"2912",
    "sg:province":"ACT",
    "sg:tags":[
        "mending",
        "clothing",
        "alteration"
    ],
    "wof:name":"First Choice Dry Cleaners",
    "wof:placetype":"venue"
},
  "geometry": {"coordinates":[149.137405395,-35.1838493347],"type":"Point"}
}