{
  "type": "Feature",
  "properties": {
    "addr:full":"350 Victoria St Darlinghurst NSW 2010",
    "addr:housenumber":"350",
    "addr:postcode":"2010",
    "addr:street":"Victoria St",
    "iso:country":"AU",
    "sg:address":"350 Victoria St",
    "sg:city":"Darlinghurst",
    "sg:classifiers":[
        {
            "category":"Health Services",
            "subcategory":"Health Practitioner",
            "type":"Services"
        }
    ],
    "sg:phone":"+61 2 9332 7250",
    "sg:postcode":"2010",
    "sg:province":"NSW",
    "sg:tags":[
        "physiotherapist"
    ],
    "wof:name":"De Lapp Kathee",
    "wof:placetype":"venue"
},
  "geometry": {"coordinates":[151.221633911,-33.8779602051],"type":"Point"}
}