{
  "type": "Feature",
  "properties": {
    "addr:full":"5 Ann St Lidcombe NSW 2141",
    "addr:housenumber":"5",
    "addr:postcode":"2141",
    "addr:street":"Ann St",
    "iso:country":"AU",
    "sg:address":"5 Ann St",
    "sg:city":"Lidcombe",
    "sg:classifiers":[
        {
            "category":"Health Services",
            "subcategory":"Health Practitioner",
            "type":"Services"
        }
    ],
    "sg:phone":"+61 2 9649 9099",
    "sg:postcode":"2141",
    "sg:province":"NSW",
    "sg:tags":[
        "acupuncture"
    ],
    "wof:name":"Register Of Acupuncture & Traditional Chinese Medicine Inc",
    "wof:placetype":"venue"
},
  "geometry": {"coordinates":[151.04454040499999,-33.8608283997],"type":"Point"}
}