{
  "type": "Feature",
  "properties": {
    "addr:full":"15 Bakers Rd Oakleigh South VIC 3167",
    "addr:housenumber":"15",
    "addr:postcode":"3167",
    "addr:street":"Bakers Rd",
    "iso:country":"AU",
    "sg:address":"15 Bakers Rd",
    "sg:city":"Oakleigh South",
    "sg:classifiers":[
        {
            "category":"Health Services",
            "subcategory":"Health Practitioner",
            "type":"Services"
        }
    ],
    "sg:phone":"+61 3 9570 2749",
    "sg:postcode":"3167",
    "sg:province":"VIC",
    "sg:tags":[
        "physiotherapist"
    ],
    "wof:name":"Friend Rodney C",
    "wof:placetype":"venue"
},
  "geometry": {"coordinates":[145.08950805699999,-37.9220504761],"type":"Point"}
}