{
  "type": "Feature",
  "properties": {
    "addr:full":"8 Gowther St Leeming WA 6149",
    "addr:housenumber":"8",
    "addr:postcode":"6149",
    "addr:street":"Gowther St",
    "iso:country":"AU",
    "sg:address":"8 Gowther St",
    "sg:city":"Leeming",
    "sg:classifiers":[
        {
            "category":"Home & Garden",
            "subcategory":"Carpets & Floor Coverings",
            "type":"Retail Goods"
        }
    ],
    "sg:phone":"+61 8 9332 5736",
    "sg:postcode":"6149",
    "sg:province":"WA",
    "sg:tags":[
        "tile",
        "wall",
        "layer"
    ],
    "wof:name":"ABC Shower Seal",
    "wof:placetype":"venue"
},
  "geometry": {"coordinates":[115.86164100000001,-32.068707],"type":"Point"}
}