{
  "type": "Feature",
  "properties": {
    "addr:full":"133 Balgownie Rd Balgownie NSW 2519",
    "addr:housenumber":"133",
    "addr:postcode":"2519",
    "addr:street":"Balgownie Rd",
    "iso:country":"AU",
    "sg:address":"133 Balgownie Rd",
    "sg:city":"Balgownie",
    "sg:classifiers":[
        {
            "category":"Personal",
            "subcategory":"Hair Removal",
            "type":"Services"
        }
    ],
    "sg:phone":"+61 2 4284 5602",
    "sg:postcode":"2519",
    "sg:province":"NSW",
    "wof:name":"Balgownie Beauty",
    "wof:placetype":"venue"
},
  "geometry": {"coordinates":[150.87806699999999,-34.388763],"type":"Point"}
}