{
  "type": "Feature",
  "properties": {
    "addr:full":"322 Brunswick St Fortitude Valley QLD 4006",
    "addr:housenumber":"322",
    "addr:postcode":"4006",
    "addr:street":"Brunswick St",
    "iso:country":"AU",
    "sg:address":"322 Brunswick St",
    "sg:city":"Fortitude Valley",
    "sg:classifiers":[
        {
            "category":"Cafe",
            "type":"Food & Drink"
        }
    ],
    "sg:phone":"+61 7 3252 4179",
    "sg:postcode":"4006",
    "sg:province":"QLD",
    "wof:name":"Cosmopoliton Coffee Valley",
    "wof:placetype":"venue"
},
  "geometry": {"coordinates":[153.03474426299999,-27.4580516815],"type":"Point"}
}