{
  "type": "Feature",
  "properties": {
    "addr:full":"PO Box 216 Oakleigh VIC 3166",
    "addr:postcode":"3166",
    "iso:country":"AU",
    "sg:address":"PO Box 216",
    "sg:city":"Oakleigh",
    "sg:classifiers":[
        {
            "category":"Building & Trades",
            "subcategory":"Construction",
            "type":"Services"
        }
    ],
    "sg:phone":"+61 3 9568 4432",
    "sg:postcode":"3166",
    "sg:province":"VIC",
    "sg:tags":[
        "equipment",
        "system",
        "automation"
    ],
    "wof:name":"CAN Automotion Pty Ltd",
    "wof:placetype":"venue"
},
  "geometry": {"coordinates":[145.090942383,-37.9002609253],"type":"Point"}
}