{
  "type": "Feature",
  "properties": {
    "addr:full":"10 Ian Oliver Drv Waikerie SA 5330",
    "addr:housenumber":"10",
    "addr:postcode":"5330",
    "addr:street":"Ian Oliver Drv",
    "iso:country":"AU",
    "sg:address":"10 Ian Oliver Drv",
    "sg:city":"Waikerie",
    "sg:classifiers":[
        {
            "category":"Autos & Motor Vehicles",
            "subcategory":"Automobile Sales",
            "type":"Retail Goods"
        }
    ],
    "sg:phone":"+61 8 8541 2055",
    "sg:postcode":"5330",
    "sg:province":"SA",
    "sg:tags":[
        "car",
        "new"
    ],
    "wof:name":"Errol Matschoss Motors Pty Ltd",
    "wof:placetype":"venue"
},
  "geometry": {"coordinates":[139.988082886,-34.1808929443],"type":"Point"}
}