{
  "type": "Feature",
  "properties": {
    "iso:country":"AU",
    "sg:address":"7 Ripon St",
    "sg:city":"Ballarat",
    "sg:classifiers":[
        {
            "category":"Real Estate",
            "subcategory":"Real Estate Agent",
            "type":"Services"
        }
    ],
    "sg:phone":"+61 3 5334 4177",
    "sg:postcode":"3350",
    "sg:province":"VIC",
    "sg:tags":[
        "motel",
        "hotel",
        "broker"
    ],
    "wof:name":"Rix Daunt Real Estate & Business Brokers",
    "wof:placetype":"venue"
},
  "geometry": {"coordinates":[143.841385,-37.561073],"type":"Point"}
}