{
  "type": "Feature",
  "properties": {
    "addr:full":"96 Albert St Brisbane QLD 4000",
    "addr:housenumber":"96",
    "addr:postcode":"4000",
    "addr:street":"Albert St",
    "iso:country":"AU",
    "sg:address":"96 Albert St",
    "sg:city":"Brisbane",
    "sg:classifiers":[
        {
            "category":"Professional",
            "subcategory":"Computer Services",
            "type":"Services"
        }
    ],
    "sg:phone":"+61 7 3307 6666",
    "sg:postcode":"4000",
    "sg:province":"QLD",
    "sg:tags":[
        "training"
    ],
    "wof:name":"Solutions Central",
    "wof:placetype":"venue"
},
  "geometry": {"coordinates":[153.027252197,-27.4718589783],"type":"Point"}
}