{
  "type": "Feature",
  "properties": {
    "iso:country":"AU",
    "sg:address":"2/2- 4 Main St",
    "sg:city":"Blacktown",
    "sg:classifiers":[
        {
            "category":"Professional",
            "subcategory":"Accounting & Tax Preparation",
            "type":"Services"
        }
    ],
    "sg:phone":"+61 2 9676 8763",
    "sg:postcode":"2148",
    "sg:province":"NSW",
    "sg:tags":[
        "consultant",
        "taxation"
    ],
    "wof:name":"Harvest Income Tax Pty Ltd",
    "wof:placetype":"venue"
},
  "geometry": {"coordinates":[150.906417847,-33.7695159912],"type":"Point"}
}