{
  "type": "Feature",
  "properties": {
    "iso:country":"AU",
    "sg:address":"Old Sturt Hwy",
    "sg:city":"Berri",
    "sg:classifiers":[
        {
            "category":"Wholesale",
            "subcategory":"Scrap",
            "type":"Manufacturing & Wholesale Goods"
        }
    ],
    "sg:phone":"+61 8 8582 2171",
    "sg:postcode":"5343",
    "sg:province":"SA",
    "sg:tags":[
        "merchant",
        "metal"
    ],
    "wof:name":"Central Metals",
    "wof:placetype":"venue"
},
  "geometry": {"coordinates":[140.595214844,-34.2835884094],"type":"Point"}
}