{
  "type": "Feature",
  "properties": {
    "iso:country":"AU",
    "sg:address":"3 / 85 Hunter St",
    "sg:city":"Hornsby",
    "sg:classifiers":[
        {
            "category":"Professional",
            "subcategory":"Engineering",
            "type":"Services"
        }
    ],
    "sg:phone":"+61 2 9482 3844",
    "sg:postcode":"2077",
    "sg:province":"NSW",
    "sg:tags":[
        "engineer",
        "mechanical"
    ],
    "wof:name":"Essential Mechanical Repairs",
    "wof:placetype":"venue"
},
  "geometry": {"coordinates":[151.101196289,-33.6999893188],"type":"Point"}
}