{
  "type": "Feature",
  "properties": {
    "iso:country":"AU",
    "sg:address":"185 Morris Rd",
    "sg:city":"Hoppers Crossing",
    "sg:classifiers":[
        {
            "category":"Banks & Credit Unions",
            "subcategory":"Investment Brokerage",
            "type":"Services"
        }
    ],
    "sg:phone":"+61 3 8742 7501",
    "sg:postcode":"3029",
    "sg:province":"VIC",
    "sg:tags":[
        "care",
        "day",
        "family",
        "child"
    ],
    "wof:name":"VIP Family Day Care",
    "wof:placetype":"venue"
},
  "geometry": {"coordinates":[144.702927,-37.868694],"type":"Point"}
}