{
  "type": "Feature",
  "properties": {
    "addr:full":"34 Polwood St Kempsey NSW 2440",
    "addr:housenumber":"34",
    "addr:postcode":"2440",
    "addr:street":"Polwood St",
    "iso:country":"AU",
    "sg:address":"34 Polwood St",
    "sg:city":"Kempsey",
    "sg:classifiers":[
        {
            "category":"Home & Garden",
            "subcategory":"Building Materials",
            "type":"Retail Goods"
        }
    ],
    "sg:phone":"+61 2 6562 4161",
    "sg:postcode":"2440",
    "sg:province":"NSW",
    "sg:tags":[
        "lawn",
        "cutting",
        "maintenance"
    ],
    "wof:name":"Cooper's Mowing & Maintenance",
    "wof:placetype":"venue"
},
  "geometry": {"coordinates":[152.83502200000001,-31.09197],"type":"Point"}
}