{
  "type": "Feature",
  "properties": {
    "addr:full":"9 Princess Ave North Strathfield NSW 2137",
    "addr:housenumber":"9",
    "addr:postcode":"2137",
    "addr:street":"Princess Ave",
    "iso:country":"AU",
    "sg:address":"9 Princess Ave",
    "sg:city":"North Strathfield",
    "sg:classifiers":[
        {
            "category":"Utilities",
            "subcategory":"Electric",
            "type":"Services"
        }
    ],
    "sg:phone":"+61 407 228 007",
    "sg:postcode":"2137",
    "sg:province":"NSW",
    "sg:tags":[
        "electrical",
        "contractor"
    ],
    "wof:name":"Ross Electrical & Hotwater",
    "wof:placetype":"venue"
},
  "geometry": {"coordinates":[151.09263610799999,-33.8627357483],"type":"Point"}
}