{
  "type": "Feature",
  "properties": {
    "addr:full":"12 Davison Rd Jandakot WA 6164",
    "addr:housenumber":"12",
    "addr:postcode":"6164",
    "addr:street":"Davison Rd",
    "iso:country":"AU",
    "sg:address":"12 Davison Rd",
    "sg:city":"Jandakot",
    "sg:classifiers":[
        {
            "category":"Professional",
            "subcategory":"Detective & Security Services",
            "type":"Services"
        }
    ],
    "sg:phone":"+61 1800 244 112",
    "sg:postcode":"6164",
    "sg:province":"WA",
    "sg:tags":[
        "equipment",
        "window",
        "doors"
    ],
    "wof:name":"Deadlock Security Pty Ltd",
    "wof:placetype":"venue"
},
  "geometry": {"coordinates":[115.84774,-32.125061],"type":"Point"}
}