{
  "type": "Feature",
  "properties": {
    "iso:country":"AU",
    "sg:address":"8 Kings Rd",
    "sg:city":"Five Dock",
    "sg:classifiers":[
        {
            "category":"Social Services",
            "subcategory":"Retirement Home",
            "type":"Services"
        }
    ],
    "sg:phone":"+61 2 9713 8452",
    "sg:postcode":"2046",
    "sg:province":"NSW",
    "sg:tags":[
        "village"
    ],
    "wof:name":"Kitty Doyle Home Units Trust",
    "wof:placetype":"venue"
},
  "geometry": {"coordinates":[151.128326,-33.869392],"type":"Point"}
}