{
  "type": "Feature",
  "properties": {
    "addr:full":"27 Newland St Bondi Junction NSW 2022",
    "addr:housenumber":"27",
    "addr:postcode":"2022",
    "addr:street":"Newland St",
    "iso:country":"AU",
    "sg:address":"27 Newland St",
    "sg:city":"Bondi Junction",
    "sg:classifiers":[
        {
            "category":"Communications",
            "subcategory":"Film & Video Production",
            "type":"Services"
        }
    ],
    "sg:phone":"+61 2 9387 4386",
    "sg:postcode":"2022",
    "sg:province":"NSW",
    "sg:tags":[
        "dvd",
        "library"
    ],
    "wof:name":"Home Pics Video",
    "wof:placetype":"venue"
},
  "geometry": {"coordinates":[151.24707031200001,-33.8927497864],"type":"Point"}
}