{
  "type": "Feature",
  "properties": {
    "addr:full":"110 Brisbane Rd Booval QLD 4304",
    "addr:housenumber":"110",
    "addr:postcode":"4304",
    "addr:street":"Brisbane Rd",
    "iso:country":"AU",
    "sg:address":"110 Brisbane Rd",
    "sg:city":"Booval",
    "sg:classifiers":[
        {
            "category":"Retail",
            "subcategory":"Repair Shop",
            "type":"Services"
        }
    ],
    "sg:phone":"+61 7 3877 9988",
    "sg:postcode":"4304",
    "sg:province":"QLD",
    "sg:tags":[
        "windscreen"
    ],
    "wof:name":"O&#039;Brien",
    "wof:placetype":"venue"
},
  "geometry": {"coordinates":[152.784866333,-27.6136417389],"type":"Point"}
}