{
  "type": "Feature",
  "properties": {
    "addr:full":"2a Mona Rd Darling Point NSW 2027",
    "addr:housenumber":"2a",
    "addr:postcode":"2027",
    "addr:street":"Mona Rd",
    "iso:country":"AU",
    "sg:address":"2a Mona Rd",
    "sg:city":"Darling Point",
    "sg:classifiers":[
        {
            "category":"Government",
            "subcategory":"Department Of Motor Vehicles",
            "type":"Public Place"
        }
    ],
    "sg:phone":"+61 2 9362 3332",
    "sg:postcode":"2027",
    "sg:province":"NSW",
    "sg:tags":[
        "wholesaler",
        "mfrs",
        "accessory"
    ],
    "wof:name":"Saturn Adjustors Pty Ltd",
    "wof:placetype":"venue"
},
  "geometry": {"coordinates":[151.23374939000001,-33.8765907288],"type":"Point"}
}