{
  "type": "Feature",
  "properties": {
    "addr:full":"45 Old Prospect Rd Wentworthville NSW 2145",
    "addr:housenumber":"45",
    "addr:postcode":"2145",
    "addr:street":"Old Prospect Rd",
    "iso:country":"AU",
    "sg:address":"45 Old Prospect Rd",
    "sg:city":"Wentworthville",
    "sg:classifiers":[
        {
            "category":"Real Estate",
            "subcategory":"Real Estate Agent",
            "type":"Services"
        }
    ],
    "sg:phone":"+61 2 9688 1299",
    "sg:postcode":"2145",
    "sg:province":"NSW",
    "wof:name":"Aspect Real Estate Services",
    "wof:placetype":"venue"
},
  "geometry": {"coordinates":[150.969436645,-33.8166656494],"type":"Point"}
}