{
  "type": "Feature",
  "properties": {
    "addr:full":"83 Torquata Drv Mirrabooka WA 6061",
    "addr:housenumber":"83",
    "addr:postcode":"6061",
    "addr:street":"Torquata Drv",
    "iso:country":"AU",
    "sg:address":"83 Torquata Drv",
    "sg:city":"Mirrabooka",
    "sg:classifiers":[
        {
            "category":"Home & Garden",
            "subcategory":"Carpets & Floor Coverings",
            "type":"Retail Goods"
        }
    ],
    "sg:phone":"+61 413 240 029",
    "sg:postcode":"6061",
    "sg:province":"WA",
    "sg:tags":[
        "tile",
        "wall",
        "layer"
    ],
    "wof:name":"New Age Tiling",
    "wof:placetype":"venue"
},
  "geometry": {"coordinates":[115.85912322999999,-31.8556919098],"type":"Point"}
}