{
  "type": "Feature",
  "properties": {
    "iso:country":"AU",
    "sg:address":"861 Canning Hwy",
    "sg:city":"Applecross",
    "sg:classifiers":[
        {
            "category":"Health Services",
            "subcategory":"Dentist",
            "type":"Services"
        }
    ],
    "sg:phone":"+61 8 9364 2880",
    "sg:postcode":"6153",
    "sg:province":"WA",
    "sg:tags":[
        "dental",
        "prosthetist"
    ],
    "wof:name":"Dentures of Distinction",
    "wof:placetype":"venue"
},
  "geometry": {"coordinates":[115.843597,-32.015553],"type":"Point"}
}