{
  "type": "Feature",
  "properties": {
    "iso:country":"AU",
    "sg:address":"Shp1/ 350 High St",
    "sg:city":"Maitland",
    "sg:classifiers":[
        {
            "category":"Shopping",
            "subcategory":"Shoes",
            "type":"Retail Goods"
        }
    ],
    "sg:phone":"+61 2 4933 2167",
    "sg:postcode":"2320",
    "sg:province":"NSW",
    "sg:tags":[
        "footwear"
    ],
    "wof:name":"Gattys Shoes Maitland",
    "wof:placetype":"venue"
},
  "geometry": {"coordinates":[151.553466797,-32.7311286926],"type":"Point"}
}