{
  "type": "Feature",
  "properties": {
    "addr:full":"236 Arthur St New Farm QLD 4005",
    "addr:housenumber":"236",
    "addr:postcode":"4005",
    "addr:street":"Arthur St",
    "iso:country":"AU",
    "sg:address":"236 Arthur St",
    "sg:city":"New Farm",
    "sg:classifiers":[
        {
            "category":"Utilities",
            "subcategory":"Mobile Phone",
            "type":"Services"
        }
    ],
    "sg:phone":"+61 1300 555 768",
    "sg:postcode":"4005",
    "sg:province":"QLD",
    "sg:tags":[
        "repair",
        "telephone"
    ],
    "wof:name":"A The Phone Doctor",
    "wof:placetype":"venue"
},
  "geometry": {"coordinates":[153.04397582999999,-27.4546451569],"type":"Point"}
}