{
  "type": "Feature",
  "properties": {
    "addr:full":"Warrego Hwy Chinchilla QLD 4413",
    "addr:postcode":"4413",
    "addr:street":"Warrego Hwy",
    "iso:country":"AU",
    "sg:address":"Warrego Hwy",
    "sg:city":"Chinchilla",
    "sg:classifiers":[
        {
            "category":"Home & Garden",
            "subcategory":"Building Materials",
            "type":"Retail Goods"
        }
    ],
    "sg:phone":"+61 7 4668 9994",
    "sg:postcode":"4413",
    "sg:province":"QLD",
    "sg:tags":[
        "supply"
    ],
    "wof:name":"Keating Bros. Thrifty Link Hardware",
    "wof:placetype":"venue"
},
  "geometry": {"coordinates":[150.644134522,-26.748872757],"type":"Point"}
}