{
  "type": "Feature",
  "properties": {
    "iso:country":"AU",
    "sg:address":"PO Box 17",
    "sg:city":"Glen Osmond",
    "sg:classifiers":[
        {
            "category":"Building & Trades",
            "subcategory":"Cleaning & Sanitation",
            "type":"Services"
        }
    ],
    "sg:phone":"+61 8 8332 6067",
    "sg:postcode":"5064",
    "sg:province":"SA",
    "sg:tags":[
        "industrial",
        "commercial",
        "contractor"
    ],
    "wof:name":"Allied Maintenance Group",
    "wof:placetype":"venue"
},
  "geometry": {"coordinates":[138.63575744600001,-34.9533500671],"type":"Point"}
}