{
  "type": "Feature",
  "properties": {
    "addr:full":"1 Musgrave Rd Red Hill QLD 4059",
    "addr:housenumber":"1",
    "addr:postcode":"4059",
    "addr:street":"Musgrave Rd",
    "iso:country":"AU",
    "sg:address":"1 Musgrave Rd",
    "sg:city":"Red Hill",
    "sg:classifiers":[
        {
            "category":"Travel",
            "subcategory":"Hotels & Motels",
            "type":"Entertainment"
        }
    ],
    "sg:phone":"+61 7 3831 3353",
    "sg:postcode":"4059",
    "sg:province":"QLD",
    "sg:tags":[
        "accommodation"
    ],
    "wof:name":"Normanby Hotel",
    "wof:placetype":"venue"
},
  "geometry": {"coordinates":[153.01455688499999,-27.4595451355],"type":"Point"}
}