{
  "type": "Feature",
  "properties": {
    "iso:country":"AU",
    "sg:address":"21- 25 Sturt St",
    "sg:city":"Townsville",
    "sg:classifiers":[
        {
            "category":"Banks & Credit Unions",
            "subcategory":"Investment Brokerage",
            "type":"Services"
        }
    ],
    "sg:phone":"+61 7 4772 5555",
    "sg:postcode":"4810",
    "sg:province":"QLD",
    "sg:tags":[
        "management",
        "property"
    ],
    "wof:name":"Accom Townsville",
    "wof:placetype":"venue"
},
  "geometry": {"coordinates":[146.814682,-19.26083],"type":"Point"}
}