{
  "type": "Feature",
  "properties": {
    "addr:full":"Unit 12/ 3 Benjamin Way Rockingham WA 6168",
    "addr:housenumber":"/ 3",
    "addr:postcode":"6168",
    "addr:street":"Benjamin Way",
    "iso:country":"AU",
    "sg:address":"Unit 12/ 3 Benjamin Way",
    "sg:city":"Rockingham",
    "sg:classifiers":[
        {
            "category":"Education",
            "subcategory":"Special Training",
            "type":"Public Place"
        }
    ],
    "sg:phone":"+61 8 9527 3477",
    "sg:postcode":"6168",
    "sg:province":"WA",
    "sg:tags":[
        "development"
    ],
    "sg:website":"http://www.down2earth.com.au",
    "wof:name":"Down To Earth Training & Assessing",
    "wof:placetype":"venue"
},
  "geometry": {"coordinates":[115.734268,-32.279724],"type":"Point"}
}