{
  "type": "Feature",
  "properties": {
    "addr:full":"15 School Rd Menzies Creek VIC 3159",
    "addr:housenumber":"15",
    "addr:postcode":"3159",
    "addr:street":"School Rd",
    "iso:country":"AU",
    "sg:address":"15 School Rd",
    "sg:city":"Menzies Creek",
    "sg:classifiers":[
        {
            "category":"Professional",
            "subcategory":"Employment Agencies",
            "type":"Services"
        }
    ],
    "sg:phone":"+61 418 331 791",
    "sg:postcode":"3159",
    "sg:province":"VIC",
    "sg:tags":[
        "provider",
        "internet"
    ],
    "wof:name":"Jaytech Internet & Computer Services",
    "wof:placetype":"venue"
},
  "geometry": {"coordinates":[145.395095825,-37.9178657532],"type":"Point"}
}