{
  "type": "Feature",
  "properties": {
    "addr:full":"9 Max Forman Crt Como WA 6152",
    "addr:housenumber":"9",
    "addr:postcode":"6152",
    "addr:street":"Max Forman Crt",
    "iso:country":"AU",
    "sg:address":"9 Max Forman Crt",
    "sg:city":"Como",
    "sg:classifiers":[
        {
            "category":"Health Services",
            "subcategory":"Health Practitioner",
            "type":"Services"
        }
    ],
    "sg:phone":"+61 8 9474 1086",
    "sg:postcode":"6152",
    "sg:province":"WA",
    "sg:tags":[
        "acupuncture"
    ],
    "wof:name":"Li Jun Chinese Herbal Medicine Centre",
    "wof:placetype":"venue"
},
  "geometry": {"coordinates":[115.880531,-31.995455],"type":"Point"}
}