{
  "type": "Feature",
  "properties": {
    "addr:full":"PO Box 251 Creswick VIC 3363",
    "addr:postcode":"3363",
    "iso:country":"AU",
    "sg:address":"PO Box 251",
    "sg:city":"Creswick",
    "sg:classifiers":[
        {
            "category":"Professional",
            "subcategory":"Accounting & Tax Preparation",
            "type":"Services"
        }
    ],
    "sg:phone":"+61 3 5345 1362",
    "sg:postcode":"3363",
    "sg:province":"VIC",
    "sg:tags":[
        "bookkeeping"
    ],
    "wof:name":"David O'Brien Bookkeeping Service",
    "wof:placetype":"venue"
},
  "geometry": {"coordinates":[143.894897461,-37.4234008789],"type":"Point"}
}