{
  "type": "Feature",
  "properties": {
    "addr:full":"7 Kembla St Fyshwick ACT 2609",
    "addr:housenumber":"7",
    "addr:postcode":"2609",
    "addr:street":"Kembla St",
    "iso:country":"AU",
    "sg:address":"7 Kembla St",
    "sg:city":"Fyshwick",
    "sg:classifiers":[
        {
            "category":"Personal",
            "subcategory":"Adult",
            "type":"Services"
        }
    ],
    "sg:phone":"+61 2 6228 1020",
    "sg:postcode":"2609",
    "sg:province":"ACT",
    "sg:tags":[
        "product"
    ],
    "wof:name":"Spice of Life Adult Store",
    "wof:placetype":"venue"
},
  "geometry": {"coordinates":[149.17843627900001,-35.3255081177],"type":"Point"}
}