{
  "type": "Feature",
  "properties": {
    "addr:full":"1298 Wynnum Rd Tingalpa QLD 4173",
    "addr:housenumber":"1298",
    "addr:postcode":"4173",
    "addr:street":"Wynnum Rd",
    "iso:country":"AU",
    "sg:address":"1298 Wynnum Rd",
    "sg:city":"Tingalpa",
    "sg:classifiers":[
        {
            "category":"Banks & Credit Unions",
            "subcategory":"Bank",
            "type":"Services"
        }
    ],
    "sg:phone":"+61 7 3348 9168",
    "sg:postcode":"4173",
    "sg:province":"QLD",
    "sg:tags":[
        "broker",
        "mortgage"
    ],
    "wof:name":"McDavitt & Associates Financial Solutions",
    "wof:placetype":"venue"
},
  "geometry": {"coordinates":[153.12840270999999,-27.4737625122],"type":"Point"}
}