{
  "type": "Feature",
  "properties": {
    "addr:full":"41 Owen Rd Kelmscott WA 6111",
    "addr:housenumber":"41",
    "addr:postcode":"6111",
    "addr:street":"Owen Rd",
    "iso:country":"AU",
    "sg:address":"41 Owen Rd",
    "sg:city":"Kelmscott",
    "sg:classifiers":[
        {
            "category":"Retail",
            "subcategory":"Auto Repair",
            "type":"Services"
        }
    ],
    "sg:phone":"+61 8 9399 1331",
    "sg:postcode":"6111",
    "sg:province":"WA",
    "sg:tags":[
        "electrical"
    ],
    "wof:name":"Genik Auto Electrics",
    "wof:placetype":"venue"
},
  "geometry": {"coordinates":[116.00601196300001,-32.132522583],"type":"Point"}
}