{
  "type": "Feature",
  "properties": {
    "iso:country":"AU",
    "sg:address":"84- 86 Balaclava Rd",
    "sg:city":"Earlville",
    "sg:classifiers":[
        {
            "category":"Education",
            "subcategory":"Kindergarten",
            "type":"Public Place"
        }
    ],
    "sg:phone":"+61 7 4054 1424",
    "sg:postcode":"4870",
    "sg:province":"QLD",
    "sg:tags":[
        "pre-schools"
    ],
    "wof:name":"Balaclava Road Children's Centre",
    "wof:placetype":"venue"
},
  "geometry": {"coordinates":[145.73045349099999,-16.9450206757],"type":"Point"}
}