{
  "type": "Feature",
  "properties": {
    "iso:country":"AU",
    "sg:address":"10 Telegraph Rd",
    "sg:city":"Kingscote",
    "sg:classifiers":[
        {
            "category":"Utilities",
            "subcategory":"Fuel Oil & Lpg",
            "type":"Services"
        }
    ],
    "sg:phone":"+61 8 8553 2842",
    "sg:postcode":"5223",
    "sg:province":"SA",
    "sg:tags":[
        "merchant"
    ],
    "wof:name":"K.I. Fuel Services",
    "wof:placetype":"venue"
},
  "geometry": {"coordinates":[137.63963317899999,-35.653301239],"type":"Point"}
}