{
  "type": "Feature",
  "properties": {
    "iso:country":"AU",
    "sg:address":"Cemetry Rd",
    "sg:city":"Cawarral",
    "sg:classifiers":[
        {
            "category":"Farming",
            "subcategory":"Fish & Marine Products",
            "type":"Manufacturing & Wholesale Goods"
        }
    ],
    "sg:phone":"+61 7 4934 4218",
    "sg:postcode":"4702",
    "sg:province":"QLD",
    "sg:tags":[
        "fisherman"
    ],
    "wof:name":"Dittmann B P",
    "wof:placetype":"venue"
},
  "geometry": {"coordinates":[150.675018311,-23.2555999756],"type":"Point"}
}