{
  "type": "Feature",
  "properties": {
    "addr:full":"The Gallery 36 Lennox St Newtown NSW 2042",
    "addr:housenumber":"36",
    "addr:postcode":"2042",
    "addr:street":"Lennox St",
    "iso:country":"AU",
    "sg:address":"The Gallery 36 Lennox St",
    "sg:city":"Newtown",
    "sg:classifiers":[
        {
            "category":"Government",
            "subcategory":"Post Office",
            "type":"Public Place"
        }
    ],
    "sg:phone":"+61 2 9517 3280",
    "sg:postcode":"2042",
    "sg:province":"NSW",
    "sg:tags":[
        "yoga"
    ],
    "wof:name":"Samadhi Yoga & Natural Therapies Centre",
    "wof:placetype":"venue"
},
  "geometry": {"coordinates":[151.17953499999999,-33.895653],"type":"Point"}
}