{
  "type": "Feature",
  "properties": {
    "addr:full":"48 Johanna St Trinity Park QLD 4879",
    "addr:housenumber":"48",
    "addr:postcode":"4879",
    "addr:street":"Johanna St",
    "iso:country":"AU",
    "sg:address":"48 Johanna St",
    "sg:city":"Trinity Park",
    "sg:classifiers":[
        {
            "category":"Education",
            "subcategory":"Dance Studio",
            "type":"Public Place"
        }
    ],
    "sg:phone":"+61 7 4057 2330",
    "sg:postcode":"4879",
    "sg:province":"QLD",
    "sg:tags":[
        "venue",
        "tuition"
    ],
    "wof:name":"Beaches Belly Dance",
    "wof:placetype":"venue"
},
  "geometry": {"coordinates":[145.69244384800001,-16.8080387115],"type":"Point"}
}