{
  "type": "Feature",
  "properties": {
    "addr:full":"23 Ebenezer Pl Adelaide SA 5000",
    "addr:housenumber":"23",
    "addr:postcode":"5000",
    "addr:street":"Ebenezer Pl",
    "iso:country":"AU",
    "sg:address":"23 Ebenezer Pl",
    "sg:city":"Adelaide",
    "sg:classifiers":[
        {
            "category":"Manufacturing",
            "subcategory":"Furniture",
            "type":"Manufacturing & Wholesale Goods"
        }
    ],
    "sg:phone":"+61 8 8359 2358",
    "sg:postcode":"5000",
    "sg:province":"SA",
    "sg:tags":[
        "builder",
        "designer",
        "custom"
    ],
    "wof:name":"Studio Barcelona",
    "wof:placetype":"venue"
},
  "geometry": {"coordinates":[138.60935974099999,-34.9230537415],"type":"Point"}
}