{
  "type": "Feature",
  "properties": {
    "iso:country":"AU",
    "sg:address":"538 Frankston-Dandenong Rd",
    "sg:city":"Carrum Downs",
    "sg:classifiers":[
        {
            "category":"Wholesale",
            "subcategory":"Furniture",
            "type":"Manufacturing & Wholesale Goods"
        }
    ],
    "sg:phone":"+61 3 9775 0399",
    "sg:postcode":"3201",
    "sg:province":"VIC",
    "sg:tags":[
        "wholesaler",
        "mfrs"
    ],
    "wof:name":"Bali In Carrum Downs",
    "wof:placetype":"venue"
},
  "geometry": {"coordinates":[145.16867099999999,-38.103485],"type":"Point"}
}