{
  "type": "Feature",
  "properties": {
    "addr:full":"108 Victoria St George Town TAS 7253",
    "addr:housenumber":"108",
    "addr:postcode":"7253",
    "addr:street":"Victoria St",
    "iso:country":"AU",
    "sg:address":"108 Victoria St",
    "sg:city":"George Town",
    "sg:classifiers":[
        {
            "category":"Wholesale",
            "subcategory":"Machinery & Supplies",
            "type":"Manufacturing & Wholesale Goods"
        }
    ],
    "sg:phone":"+61 3 6382 4144",
    "sg:postcode":"7253",
    "sg:province":"TAS",
    "sg:tags":[
        "process",
        "instrument",
        "control"
    ],
    "wof:name":"Temtrol Technologies",
    "wof:placetype":"venue"
},
  "geometry": {"coordinates":[146.83799743599999,-41.1102409363],"type":"Point"}
}