{
  "type": "Feature",
  "properties": {
    "addr:full":"Level 5, 50 York St Sydney NSW 2000",
    "addr:housenumber":"50",
    "addr:postcode":"2000",
    "addr:street":"York St",
    "iso:country":"AU",
    "sg:address":"Level 5, 50 York St",
    "sg:city":"Sydney",
    "sg:classifiers":[
        {
            "category":"Organizations",
            "subcategory":"Professional Association",
            "type":"Services"
        }
    ],
    "sg:phone":"+61 2 9279 0022",
    "sg:postcode":"2000",
    "sg:province":"NSW",
    "sg:tags":[
        "web",
        "internet"
    ],
    "sg:website":"http://www.impressdesign.com.au",
    "wof:name":"Impress Design",
    "wof:placetype":"venue"
},
  "geometry": {"coordinates":[151.206344605,-33.8696937561],"type":"Point"}
}