{
  "type": "Feature",
  "properties": {
    "addr:full":"Ste 707/ 2 Queen St Melbourne VIC 3000",
    "addr:housenumber":"/ 2",
    "addr:postcode":"3000",
    "addr:street":"Queen St",
    "iso:country":"AU",
    "sg:address":"Ste 707/ 2 Queen St",
    "sg:city":"Melbourne",
    "sg:classifiers":[
        {
            "category":"Professional",
            "subcategory":"Engineering",
            "type":"Services"
        }
    ],
    "sg:phone":"+61 3 9629 3088",
    "sg:postcode":"3000",
    "sg:province":"VIC",
    "sg:tags":[
        "civil",
        "engineer"
    ],
    "wof:name":"D P S Pty Ltd",
    "wof:placetype":"venue"
},
  "geometry": {"coordinates":[144.96127319300001,-37.8190002441],"type":"Point"}
}