{
  "type": "Feature",
  "properties": {
    "addr:full":"PO Box 8118 Wodonga VIC 3690",
    "addr:postcode":"3690",
    "iso:country":"AU",
    "sg:address":"PO Box 8118",
    "sg:city":"Wodonga",
    "sg:classifiers":[
        {
            "category":"Utilities",
            "subcategory":"Electric",
            "type":"Services"
        }
    ],
    "sg:phone":"+61 429 493 593",
    "sg:postcode":"3690",
    "sg:province":"VIC",
    "sg:tags":[
        "electrical",
        "contractor"
    ],
    "wof:name":"Modtec Electrical Services",
    "wof:placetype":"venue"
},
  "geometry": {"coordinates":[146.892501831,-36.1128997803],"type":"Point"}
}