{
  "type": "Feature",
  "properties": {
    "addr:full":"64 Brook St Muswellbrook NSW 2333",
    "addr:housenumber":"64",
    "addr:postcode":"2333",
    "addr:street":"Brook St",
    "iso:country":"AU",
    "sg:address":"64 Brook St",
    "sg:city":"Muswellbrook",
    "sg:classifiers":[
        {
            "category":"Health Services",
            "subcategory":"Doctor",
            "type":"Services"
        }
    ],
    "sg:phone":"+61 2 6543 1222",
    "sg:postcode":"2333",
    "sg:province":"NSW",
    "sg:tags":[
        "medical",
        "practitioner"
    ],
    "wof:name":"Brook Medical Centre",
    "wof:placetype":"venue"
},
  "geometry": {"coordinates":[150.889328003,-32.2635765076],"type":"Point"}
}