{
  "type": "Feature",
  "properties": {
    "iso:country":"AU",
    "sg:address":"257 Shute Harbour Rd",
    "sg:city":"Airlie Beach",
    "sg:classifiers":[
        {
            "category":"Health Services",
            "subcategory":"Doctor",
            "type":"Services"
        }
    ],
    "sg:phone":"+61 7 4946 6241",
    "sg:postcode":"4802",
    "sg:province":"QLD",
    "sg:tags":[
        "medical",
        "practitioner"
    ],
    "wof:name":"Whitsunday Doctors Service",
    "wof:placetype":"venue"
},
  "geometry": {"coordinates":[148.71646118199999,-20.2677288055],"type":"Point"}
}