{
  "type": "Feature",
  "properties": {
    "addr:full":"15 Myall Rd Waratah NSW 2298",
    "addr:housenumber":"15",
    "addr:postcode":"2298",
    "addr:street":"Myall Rd",
    "iso:country":"AU",
    "sg:address":"15 Myall Rd",
    "sg:city":"Waratah",
    "sg:classifiers":[
        {
            "category":"Travel",
            "subcategory":"Hostel",
            "type":"Entertainment"
        }
    ],
    "sg:phone":"+61 2 4935 0300",
    "sg:postcode":"2298",
    "sg:province":"NSW",
    "sg:tags":[
        "home"
    ],
    "wof:name":"Maroba",
    "wof:placetype":"venue"
},
  "geometry": {"coordinates":[151.720046997,-32.9018554688],"type":"Point"}
}