{
  "type": "Feature",
  "properties": {
    "addr:full":"449 South Rd Moorabbin VIC 3189",
    "addr:housenumber":"449",
    "addr:postcode":"3189",
    "addr:street":"South Rd",
    "iso:country":"AU",
    "sg:address":"449 South Rd",
    "sg:city":"Moorabbin",
    "sg:classifiers":[
        {
            "category":"Professional",
            "subcategory":"Computer Services",
            "type":"Services"
        }
    ],
    "sg:phone":"+61 3 9553 0717",
    "sg:postcode":"3189",
    "sg:province":"VIC",
    "sg:tags":[
        "repairs",
        "upgrade",
        "equipment"
    ],
    "wof:name":"My Mac Moorabbin",
    "wof:placetype":"venue"
},
  "geometry": {"coordinates":[145.04689025900001,-37.9347343445],"type":"Point"}
}