{
  "type": "Feature",
  "properties": {
    "iso:country":"AU",
    "sg:address":"284 Grange Rd",
    "sg:city":"Flinders Park",
    "sg:classifiers":[
        {
            "category":"Home & Garden",
            "subcategory":"Building Materials",
            "type":"Retail Goods"
        }
    ],
    "sg:phone":"+61 8 8234 7144",
    "sg:postcode":"5025",
    "sg:province":"SA",
    "sg:tags":[
        "retaining",
        "wall"
    ],
    "wof:name":"Australian Paving Centre",
    "wof:placetype":"venue"
},
  "geometry": {"coordinates":[138.53538513199999,-34.9054603577],"type":"Point"}
}