{
  "type": "Feature",
  "properties": {
    "addr:full":"Memorial Drv Tewantin QLD 4565",
    "addr:postcode":"4565",
    "addr:street":"Memorial Drv",
    "iso:country":"AU",
    "sg:address":"Memorial Drv",
    "sg:city":"Tewantin",
    "sg:classifiers":[
        {
            "category":"Autos & Motor Vehicles",
            "subcategory":"Fuel & Gas Station",
            "type":"Retail Goods"
        }
    ],
    "sg:phone":"+61 7 5449 8551",
    "sg:postcode":"4565",
    "sg:province":"QLD",
    "wof:name":"Caltex Tewantin",
    "wof:placetype":"venue"
},
  "geometry": {"coordinates":[153.03941345199999,-26.393661499],"type":"Point"}
}