{
  "type": "Feature",
  "properties": {
    "addr:full":"1 Oxide St Broken Hill NSW 2880",
    "addr:housenumber":"1",
    "addr:postcode":"2880",
    "addr:street":"Oxide St",
    "iso:country":"AU",
    "sg:address":"1 Oxide St",
    "sg:city":"Broken Hill",
    "sg:classifiers":[
        {
            "category":"Fast Food",
            "type":"Food & Drink"
        }
    ],
    "sg:phone":"+61 8 8088 5860",
    "sg:postcode":"2880",
    "sg:province":"NSW",
    "sg:tags":[
        "away",
        "take"
    ],
    "wof:name":"Silver City Chinese Restaurant",
    "wof:placetype":"venue"
},
  "geometry": {"coordinates":[141.468353272,-31.9579124451],"type":"Point"}
}