{
  "type": "Feature",
  "properties": {
    "addr:full":"62a Patterson St Tennant Creek NT 0860",
    "addr:housenumber":"62a",
    "addr:postcode":"nt 0860",
    "addr:street":"Patterson St",
    "iso:country":"AU",
    "sg:address":"62a Patterson St",
    "sg:city":"Tennant Creek",
    "sg:classifiers":[
        {
            "category":"Travel",
            "subcategory":"Travel Agent",
            "type":"Entertainment"
        }
    ],
    "sg:phone":"+61 8 8962 2211",
    "sg:postcode":"0860",
    "sg:province":"NT",
    "sg:tags":[
        "consultant"
    ],
    "wof:name":"Travelworld Tennant Creek",
    "wof:placetype":"venue"
},
  "geometry": {"coordinates":[134.191025,-19.646357],"type":"Point"}
}