{
  "type": "Feature",
  "properties": {
    "addr:full":"202 Barkly St St Kilda VIC 3182",
    "addr:housenumber":"202",
    "addr:postcode":"3182",
    "addr:street":"Barkly St",
    "iso:country":"AU",
    "sg:address":"202 Barkly St",
    "sg:city":"St Kilda",
    "sg:classifiers":[
        {
            "category":"Travel",
            "subcategory":"Hotels & Motels",
            "type":"Entertainment"
        }
    ],
    "sg:phone":"+61 3 9534 2200",
    "sg:postcode":"3182",
    "sg:province":"VIC",
    "sg:tags":[
        "accommodation"
    ],
    "wof:name":"Village Belle Hotel",
    "wof:placetype":"venue"
},
  "geometry": {"coordinates":[144.98089599599999,-37.8698234558],"type":"Point"}
}