{
  "type": "Feature",
  "properties": {
    "addr:full":"Wilsonton Medical Centre, Richmond Dr Wilsonton QLD 4350",
    "addr:postcode":"4350",
    "addr:street":"Richmond Dr",
    "iso:country":"AU",
    "sg:address":"Wilsonton Medical Centre, Richmond Dr",
    "sg:city":"Wilsonton",
    "sg:classifiers":[
        {
            "category":"Health Services",
            "subcategory":"Doctor",
            "type":"Services"
        }
    ],
    "sg:phone":"+61 7 4633 1939",
    "sg:postcode":"4350",
    "sg:province":"QLD",
    "sg:tags":[
        "medical",
        "practitioner"
    ],
    "wof:name":"Hopson Peter Dr",
    "wof:placetype":"venue"
},
  "geometry": {"coordinates":[151.924072,-27.541397],"type":"Point"}
}