{
  "type": "Feature",
  "properties": {
    "iso:country":"AU",
    "sg:address":"PO Box 4166",
    "sg:city":"Lake Haven",
    "sg:classifiers":[
        {
            "category":"Professional",
            "subcategory":"Detective & Security Services",
            "type":"Services"
        }
    ],
    "sg:phone":"+61 2 4393 1348",
    "sg:postcode":"2263",
    "sg:province":"NSW",
    "sg:tags":[
        "consultant",
        "system"
    ],
    "wof:name":"Waveguide Antenna Electrical & Security",
    "wof:placetype":"venue"
},
  "geometry": {"coordinates":[151.500137,-33.243938],"type":"Point"}
}