{
  "type": "Feature",
  "properties": {
    "iso:country":"AU",
    "sg:address":"Shop 40a Brice Ave",
    "sg:city":"Mooroolbark",
    "sg:classifiers":[
        {
            "category":"Personal",
            "subcategory":"Shoe Repair & Shine",
            "type":"Services"
        }
    ],
    "sg:phone":"+61 419 357 306",
    "sg:postcode":"3138",
    "sg:province":"VIC",
    "sg:tags":[
        "footwear"
    ],
    "wof:name":"Rocky The Cobbler",
    "wof:placetype":"venue"
},
  "geometry": {"coordinates":[145.31271362300001,-37.7852172852],"type":"Point"}
}