{
  "type": "Feature",
  "properties": {
    "addr:full":"15 Bligh St Kilkivan QLD 4600",
    "addr:housenumber":"15",
    "addr:postcode":"4600",
    "addr:street":"Bligh St",
    "iso:country":"AU",
    "sg:address":"15 Bligh St",
    "sg:city":"Kilkivan",
    "sg:classifiers":[
        {
            "category":"Food & Beverages",
            "subcategory":"Supermarket",
            "type":"Retail Goods"
        }
    ],
    "sg:phone":"+61 7 5484 1141",
    "sg:postcode":"4600",
    "sg:province":"QLD",
    "sg:tags":[
        "grocery",
        "store"
    ],
    "wof:name":"Kilkivan General Store",
    "wof:placetype":"venue"
},
  "geometry": {"coordinates":[152.24299600000001,-26.086569],"type":"Point"}
}