{
  "type": "Feature",
  "properties": {
    "addr:full":"116 Old Pitt Town Rd Oakville NSW 2765",
    "addr:housenumber":"116",
    "addr:postcode":"2765",
    "addr:street":"Old Pitt Town Rd",
    "iso:country":"AU",
    "sg:address":"116 Old Pitt Town Rd",
    "sg:city":"Oakville",
    "sg:classifiers":[
        {
            "category":"Utilities",
            "subcategory":"Electric",
            "type":"Services"
        }
    ],
    "sg:phone":"+61 416 234 099",
    "sg:postcode":"2765",
    "sg:province":"NSW",
    "sg:tags":[
        "electrical",
        "contractor"
    ],
    "wof:name":"D.J.C. Electrics",
    "wof:placetype":"venue"
},
  "geometry": {"coordinates":[150.89381408700001,-33.6349182129],"type":"Point"}
}