{
  "type": "Feature",
  "properties": {
    "addr:full":"31 Sandringham St Sans Souci NSW 2219",
    "addr:housenumber":"31",
    "addr:postcode":"2219",
    "addr:street":"Sandringham St",
    "iso:country":"AU",
    "sg:address":"31 Sandringham St",
    "sg:city":"Sans Souci",
    "sg:classifiers":[
        {
            "category":"Retail",
            "subcategory":"Auto Repair",
            "type":"Services"
        }
    ],
    "sg:phone":"+61 2 9529 6693",
    "sg:postcode":"2219",
    "sg:province":"NSW",
    "sg:tags":[
        "beater",
        "painter",
        "panel"
    ],
    "wof:name":"Albert G Dunn Smash Repairs",
    "wof:placetype":"venue"
},
  "geometry": {"coordinates":[151.13626099999999,-33.991154],"type":"Point"}
}