{
  "type": "Feature",
  "properties": {
    "addr:full":"59 Strong Ave Thomastown VIC 3074",
    "addr:housenumber":"59",
    "addr:postcode":"3074",
    "addr:street":"Strong Ave",
    "iso:country":"AU",
    "sg:address":"59 Strong Ave",
    "sg:city":"Thomastown",
    "sg:classifiers":[
        {
            "category":"Wholesale",
            "subcategory":"Scrap",
            "type":"Manufacturing & Wholesale Goods"
        }
    ],
    "sg:phone":"+61 419 394 711",
    "sg:postcode":"3074",
    "sg:province":"VIC",
    "sg:tags":[
        "merchant",
        "metal"
    ],
    "wof:name":"Industrial Machinery",
    "wof:placetype":"venue"
},
  "geometry": {"coordinates":[145.006057739,-37.6884918213],"type":"Point"}
}