{
  "type": "Feature",
  "properties": {
    "addr:full":"98- 100 Chapel St Marrickville NSW 2204",
    "addr:housenumber":"100",
    "addr:postcode":"2204",
    "addr:street":"98;Chapel St",
    "iso:country":"AU",
    "sg:address":"98- 100 Chapel St",
    "sg:city":"Marrickville",
    "sg:classifiers":[
        {
            "category":"Professional",
            "subcategory":"Art Services",
            "type":"Services"
        }
    ],
    "sg:phone":"+61 2 9560 8544",
    "sg:postcode":"2204",
    "sg:province":"NSW",
    "sg:tags":[
        "graphic",
        "designer"
    ],
    "wof:name":"Aspire Design & Print",
    "wof:placetype":"venue"
},
  "geometry": {"coordinates":[151.16304,-33.90612],"type":"Point"}
}