{
  "type": "Feature",
  "properties": {
    "iso:country":"AU",
    "sg:address":"11 Clifford St",
    "sg:city":"Toowoomba",
    "sg:classifiers":[
        {
            "category":"Farming",
            "subcategory":"Farm & Veterinary Services",
            "type":"Manufacturing & Wholesale Goods"
        }
    ],
    "sg:phone":"+61 7 4632 8230",
    "sg:postcode":"4350",
    "sg:province":"QLD",
    "sg:tags":[
        "agricultural",
        "advisory"
    ],
    "wof:name":"Feedlot Services Australia",
    "wof:placetype":"venue"
},
  "geometry": {"coordinates":[151.947174,-27.561197],"type":"Point"}
}