{
  "type": "Feature",
  "properties": {
    "addr:full":"PO Box 83 Freeling SA 5372",
    "addr:postcode":"5372",
    "iso:country":"AU",
    "sg:address":"PO Box 83",
    "sg:city":"Freeling",
    "sg:classifiers":[
        {
            "category":"Professional",
            "subcategory":"Computer Services",
            "type":"Services"
        }
    ],
    "sg:phone":"+61 411 118 196",
    "sg:postcode":"5372",
    "sg:province":"SA",
    "sg:tags":[
        "repairs",
        "upgrade",
        "equipment"
    ],
    "wof:name":"D & D Computing Services",
    "wof:placetype":"venue"
},
  "geometry": {"coordinates":[138.816162109,-34.4525413513],"type":"Point"}
}