{
  "type": "Feature",
  "properties": {
    "iso:country":"AU",
    "sg:address":"5 Trifecta Pl",
    "sg:city":"Oak Flats",
    "sg:classifiers":[
        {
            "category":"Building & Trades",
            "subcategory":"Landscaping Services",
            "type":"Services"
        }
    ],
    "sg:phone":"+61 2 4257 7726",
    "sg:postcode":"2529",
    "sg:province":"NSW",
    "sg:tags":[
        "stump",
        "tree",
        "felling",
        "removal"
    ],
    "wof:name":"S & K Tree Service",
    "wof:placetype":"venue"
},
  "geometry": {"coordinates":[150.828887939,-34.4727592468],"type":"Point"}
}