{
  "type": "Feature",
  "properties": {
    "iso:country":"AU",
    "sg:address":"154 Beaconsfield St",
    "sg:city":"Revesby",
    "sg:classifiers":[
        {
            "category":"Manufacturing",
            "subcategory":"Tools & Machinery",
            "type":"Manufacturing & Wholesale Goods"
        }
    ],
    "sg:phone":"+61 2 9772 4477",
    "sg:postcode":"2212",
    "sg:province":"NSW",
    "sg:tags":[
        "toolmaker"
    ],
    "wof:name":"Bell Dies Sydney P/L",
    "wof:placetype":"venue"
},
  "geometry": {"coordinates":[150.996582,-33.942032],"type":"Point"}
}