{
  "type": "Feature",
  "properties": {
    "addr:full":"Unit 3, 87 Newlands Rd Reservoir VIC 3073",
    "addr:housenumber":"87",
    "addr:postcode":"3073",
    "addr:street":"Newlands Rd",
    "iso:country":"AU",
    "sg:address":"Unit 3, 87 Newlands Rd",
    "sg:city":"Reservoir",
    "sg:classifiers":[
        {
            "category":"Communications",
            "subcategory":"Television Station",
            "type":"Services"
        }
    ],
    "sg:phone":"+61 3 9495 7899",
    "sg:postcode":"3073",
    "sg:province":"VIC",
    "sg:tags":[
        "equipment",
        "radio"
    ],
    "wof:name":"BSA",
    "wof:placetype":"venue"
},
  "geometry": {"coordinates":[144.97300720199999,-37.7275276184],"type":"Point"}
}