{
  "type": "Feature",
  "properties": {
    "addr:full":"PO Box 1421 Sunnybank Hills QLD 4109",
    "addr:postcode":"4109",
    "iso:country":"AU",
    "sg:address":"PO Box 1421",
    "sg:city":"Sunnybank Hills",
    "sg:classifiers":[
        {
            "category":"Building & Trades",
            "subcategory":"Construction",
            "type":"Services"
        }
    ],
    "sg:phone":"+61 7 3272 4881",
    "sg:postcode":"4109",
    "sg:province":"QLD",
    "sg:tags":[
        "management"
    ],
    "wof:name":"Kemson Constructions",
    "wof:placetype":"venue"
},
  "geometry": {"coordinates":[153.05857849099999,-27.598690033],"type":"Point"}
}