{
  "type": "Feature",
  "properties": {
    "addr:full":"22/ 50 Carr Coogee NSW 2034",
    "addr:housenumber":"22 / 50",
    "addr:postcode":"2034",
    "addr:street":"Carr Coogee",
    "iso:country":"AU",
    "sg:address":"22/ 50 Carr",
    "sg:city":"Coogee",
    "sg:classifiers":[
        {
            "category":"Airline",
            "type":"Transportation"
        }
    ],
    "sg:phone":"+61 416 147 795",
    "sg:postcode":"2034",
    "sg:province":"NSW",
    "sg:tags":[
        "aircraft",
        "rental",
        "charter"
    ],
    "wof:name":"Personal Jet Transport",
    "wof:placetype":"venue"
},
  "geometry": {"coordinates":[151.256515503,-33.922908783],"type":"Point"}
}