{
  "type": "Feature",
  "properties": {
    "addr:full":"Garden City Towers 2/ 18 Mt Gravatt-Capalaba Rd Mt Gravatt QLD 4122",
    "addr:housenumber":"2 / 18",
    "addr:postcode":"4122",
    "addr:street":"Mt Gravatt-Capalaba Rd",
    "iso:country":"AU",
    "sg:address":"Garden City Towers 2/ 18 Mt Gravatt-Capalaba Rd",
    "sg:city":"Mt Gravatt",
    "sg:classifiers":[
        {
            "category":"Social Services",
            "subcategory":"Child Care",
            "type":"Services"
        }
    ],
    "sg:phone":"+61 7 3343 7877",
    "sg:postcode":"4122",
    "sg:province":"QLD",
    "wof:name":"Scallywags Play Centres Pty Ltd",
    "wof:placetype":"venue"
},
  "geometry": {"coordinates":[153.082229614,-27.5593070984],"type":"Point"}
}