{
  "type": "Feature",
  "properties": {
    "iso:country":"AU",
    "sg:address":"5 Steele St",
    "sg:city":"Devonport",
    "sg:classifiers":[
        {
            "category":"Banks & Credit Unions",
            "subcategory":"Financial Services",
            "type":"Services"
        }
    ],
    "sg:phone":"+61 13 27 22",
    "sg:postcode":"7310",
    "sg:province":"TAS",
    "sg:tags":[
        "financier"
    ],
    "wof:name":"RACT",
    "wof:placetype":"venue"
},
  "geometry": {"coordinates":[146.36216735799999,-41.1818389893],"type":"Point"}
}