{
  "type": "Feature",
  "properties": {
    "addr:full":"128 Curlewis St Swan Hill VIC 3585",
    "addr:housenumber":"128",
    "addr:postcode":"3585",
    "addr:street":"Curlewis St",
    "iso:country":"AU",
    "sg:address":"128 Curlewis St",
    "sg:city":"Swan Hill",
    "sg:classifiers":[
        {
            "category":"Building & Trades",
            "subcategory":"Equipment Rental",
            "type":"Services"
        }
    ],
    "sg:phone":"+61 3 5032 2594",
    "sg:postcode":"3585",
    "sg:province":"VIC",
    "sg:tags":[
        "saw"
    ],
    "wof:name":"Swan Hill Mower & Saw",
    "wof:placetype":"venue"
},
  "geometry": {"coordinates":[143.561035,-35.339668],"type":"Point"}
}