{
  "type": "Feature",
  "properties": {
    "addr:full":"7 Rockingham Beach Rd Rockingham WA 6168",
    "addr:housenumber":"7",
    "addr:postcode":"6168",
    "addr:street":"Rockingham Beach Rd",
    "iso:country":"AU",
    "sg:address":"7 Rockingham Beach Rd",
    "sg:city":"Rockingham",
    "sg:classifiers":[
        {
            "category":"Recreation",
            "subcategory":"Fishing",
            "type":"Entertainment"
        }
    ],
    "sg:phone":"+61 8 9527 1565",
    "sg:postcode":"6168",
    "sg:province":"WA",
    "sg:tags":[
        "tackle"
    ],
    "wof:name":"Camping & Leisure Store",
    "wof:placetype":"venue"
},
  "geometry": {"coordinates":[115.72985799999999,-32.275578],"type":"Point"}
}