{
  "type": "Feature",
  "properties": {
    "iso:country":"AU",
    "sg:address":"28 Dunorlan Rd",
    "sg:city":"Edwardstown",
    "sg:classifiers":[
        {
            "category":"Building & Trades",
            "subcategory":"Construction",
            "type":"Services"
        }
    ],
    "sg:phone":"+61 8 8276 8222",
    "sg:postcode":"5039",
    "sg:province":"SA",
    "sg:tags":[
        "contractor"
    ],
    "wof:name":"Weir S.J. Pty Ltd",
    "wof:placetype":"venue"
},
  "geometry": {"coordinates":[138.57078552199999,-34.9867172241],"type":"Point"}
}