{
  "type": "Feature",
  "properties": {
    "iso:country":"AU",
    "sg:address":"Shop 2, 15 Railway Tce",
    "sg:city":"Rockingham",
    "sg:classifiers":[
        {
            "category":"Shopping",
            "subcategory":"Discount & Variety Stores",
            "type":"Retail Goods"
        }
    ],
    "sg:phone":"+61 8 9527 8733",
    "sg:postcode":"6168",
    "sg:province":"WA",
    "sg:tags":[
        "shop",
        "adult"
    ],
    "wof:name":"Adultshop.com",
    "wof:placetype":"venue"
},
  "geometry": {"coordinates":[115.72936199999999,-32.276695],"type":"Point"}
}