{
  "type": "Feature",
  "properties": {
    "iso:country":"AU",
    "sg:address":"117 Lachlan St",
    "sg:city":"Forbes",
    "sg:classifiers":[
        {
            "category":"Travel",
            "subcategory":"Hotels & Motels",
            "type":"Entertainment"
        }
    ],
    "sg:phone":"+61 2 6851 1399",
    "sg:postcode":"2871",
    "sg:province":"NSW",
    "sg:tags":[
        "accommodation"
    ],
    "wof:name":"Post Office Hotel Forbes",
    "wof:placetype":"venue"
},
  "geometry": {"coordinates":[148.006607,-33.386314],"type":"Point"}
}