{
  "type": "Feature",
  "properties": {
    "addr:full":"123 Lacey St East Cannington WA 6107",
    "addr:housenumber":"123",
    "addr:postcode":"6107",
    "addr:street":"Lacey St East",
    "iso:country":"AU",
    "sg:address":"123 Lacey St",
    "sg:city":"East Cannington",
    "sg:classifiers":[
        {
            "category":"Wholesale",
            "subcategory":"Machinery & Supplies",
            "type":"Manufacturing & Wholesale Goods"
        }
    ],
    "sg:phone":"+61 8 9458 3753",
    "sg:postcode":"6107",
    "sg:province":"WA",
    "sg:tags":[
        "agricultural"
    ],
    "wof:name":"Gibbs Tractor Service",
    "wof:placetype":"venue"
},
  "geometry": {"coordinates":[115.963539123,-32.0105171204],"type":"Point"}
}