{
  "type": "Feature",
  "properties": {
    "addr:full":"Fiveways Rd Brandon QLD 4808",
    "addr:postcode":"4808",
    "addr:street":"Fiveways Rd",
    "iso:country":"AU",
    "sg:address":"Fiveways Rd",
    "sg:city":"Brandon",
    "sg:classifiers":[
        {
            "category":"Airline",
            "type":"Transportation"
        }
    ],
    "sg:phone":"+61 7 4782 5242",
    "sg:postcode":"4808",
    "sg:province":"QLD",
    "sg:tags":[
        "aircraft",
        "rental",
        "charter"
    ],
    "wof:name":"Ayr Flying Services Pty Ltd",
    "wof:placetype":"venue"
},
  "geometry": {"coordinates":[147.33663940400001,-19.5770187378],"type":"Point"}
}