{
  "type": "Feature",
  "properties": {
    "addr:full":"1 Rous Head Rd North Fremantle WA 6159",
    "addr:housenumber":"1",
    "addr:postcode":"6159",
    "addr:street":"Rous Head Rd",
    "iso:country":"AU",
    "sg:address":"1 Rous Head Rd",
    "sg:city":"North Fremantle",
    "sg:classifiers":[
        {
            "category":"Professional",
            "type":"Services"
        }
    ],
    "sg:phone":"+61 8 9432 5200",
    "sg:postcode":"6159",
    "sg:province":"WA",
    "sg:tags":[
        "forwarding",
        "agent",
        "transport"
    ],
    "wof:name":"POTA Global Management Pty Ltd",
    "wof:placetype":"venue"
},
  "geometry": {"coordinates":[115.736214,-32.04665],"type":"Point"}
}