{
  "type": "Feature",
  "properties": {
    "addr:full":"Level 8 West 55 Currie St Adelaide SA 5000",
    "addr:housenumber":"55",
    "addr:postcode":"5000",
    "addr:street":"West;Currie St",
    "iso:country":"AU",
    "sg:address":"Level 8 West 55 Currie St",
    "sg:city":"Adelaide",
    "sg:classifiers":[
        {
            "category":"Health Services",
            "subcategory":"Doctor",
            "type":"Services"
        }
    ],
    "sg:phone":"+61 1300 361 046",
    "sg:postcode":"5000",
    "sg:province":"SA",
    "sg:tags":[
        "occupational",
        "safety"
    ],
    "wof:name":"Health for Industry",
    "wof:placetype":"venue"
},
  "geometry": {"coordinates":[138.59678649899999,-34.9247207642],"type":"Point"}
}