{
  "type": "Feature",
  "properties": {
    "addr:full":"Shp1/ 85 The Esplanade Paynesville VIC 3880",
    "addr:housenumber":"85",
    "addr:postcode":"3880",
    "addr:street":"The Esplanade",
    "iso:country":"AU",
    "sg:address":"Shp1/ 85 The Esplanade",
    "sg:city":"Paynesville",
    "sg:classifiers":[
        {
            "category":"Bars & Pubs",
            "subcategory":"Wine Bar",
            "type":"Food & Drink"
        }
    ],
    "sg:phone":"+61 3 5156 1395",
    "sg:postcode":"3880",
    "sg:province":"VIC",
    "wof:name":"Wine Justice Paynesville",
    "wof:placetype":"venue"
},
  "geometry": {"coordinates":[147.72013855,-37.9074211121],"type":"Point"}
}