{
  "type": "Feature",
  "properties": {
    "addr:full":"26 Agnes St Mt Gambier SA 5290",
    "addr:housenumber":"26",
    "addr:postcode":"5290",
    "addr:street":"Agnes St",
    "iso:country":"AU",
    "sg:address":"26 Agnes St",
    "sg:city":"Mt Gambier",
    "sg:classifiers":[
        {
            "category":"Professional",
            "subcategory":"Art Services",
            "type":"Services"
        }
    ],
    "sg:phone":"+61 419 844 621",
    "sg:postcode":"5290",
    "sg:province":"SA",
    "sg:tags":[
        "decorator",
        "painter"
    ],
    "wof:name":"Gunn David Painter & Decorator",
    "wof:placetype":"venue"
},
  "geometry": {"coordinates":[140.772751,-37.821857],"type":"Point"}
}