{
  "type": "Feature",
  "properties": {
    "addr:full":"52 Alison Rd Carrara QLD 4211",
    "addr:housenumber":"52",
    "addr:postcode":"4211",
    "addr:street":"Alison Rd",
    "iso:country":"AU",
    "sg:address":"52 Alison Rd",
    "sg:city":"Carrara",
    "sg:classifiers":[
        {
            "category":"Manufacturing",
            "subcategory":"Jewelry",
            "type":"Manufacturing & Wholesale Goods"
        }
    ],
    "sg:phone":"+61 7 5594 1554",
    "sg:postcode":"4211",
    "sg:province":"QLD",
    "sg:tags":[
        "mfrg",
        "jeweller"
    ],
    "wof:name":"Anvil Jewellery Co",
    "wof:placetype":"venue"
},
  "geometry": {"coordinates":[153.355224609,-28.0217514038],"type":"Point"}
}