{
  "type": "Feature",
  "properties": {
    "addr:full":"311 Maitland Rd Cessnock NSW 2325",
    "addr:housenumber":"311",
    "addr:postcode":"2325",
    "addr:street":"Maitland Rd",
    "iso:country":"AU",
    "sg:address":"311 Maitland Rd",
    "sg:city":"Cessnock",
    "sg:classifiers":[
        {
            "category":"Autos & Motor Vehicles",
            "subcategory":"Automobile Sales",
            "type":"Retail Goods"
        }
    ],
    "sg:phone":"+61 2 4990 1566",
    "sg:postcode":"2325",
    "sg:province":"NSW",
    "sg:tags":[
        "car",
        "new"
    ],
    "wof:name":"Cessnock Mitsubishi",
    "wof:placetype":"venue"
},
  "geometry": {"coordinates":[151.36677551299999,-32.8285751343],"type":"Point"}
}