{
  "type": "Feature",
  "properties": {
    "addr:full":"Fcty 2/ 4 Tathra St Gosford West NSW 2250",
    "addr:housenumber":"/ 4",
    "addr:postcode":"2250",
    "addr:street":"Tathra St",
    "iso:country":"AU",
    "sg:address":"Fcty 2/ 4 Tathra St",
    "sg:city":"Gosford West",
    "sg:classifiers":[
        {
            "category":"Manufacturing",
            "subcategory":"Metals",
            "type":"Manufacturing & Wholesale Goods"
        }
    ],
    "sg:phone":"+61 2 4324 1505",
    "sg:postcode":"2250",
    "sg:province":"NSW",
    "sg:tags":[
        "steel",
        "fabricator",
        "mfrs"
    ],
    "wof:name":"RG Fabrications Pty Limited",
    "wof:placetype":"venue"
},
  "geometry": {"coordinates":[151.3175354,-33.4210472107],"type":"Point"}
}