{
  "type": "Feature",
  "properties": {
    "addr:full":"86 Mowbray Drv Wantirna South VIC 3152",
    "addr:housenumber":"86",
    "addr:postcode":"3152",
    "addr:street":"Mowbray Drv",
    "iso:country":"AU",
    "sg:address":"86 Mowbray Drv",
    "sg:city":"Wantirna South",
    "sg:classifiers":[
        {
            "category":"Arts & Performance",
            "subcategory":"Music",
            "type":"Entertainment"
        }
    ],
    "sg:phone":"+61 411 071 752",
    "sg:postcode":"3152",
    "sg:province":"VIC",
    "sg:tags":[
        "mobile",
        "jockey",
        "disc"
    ],
    "wof:name":"Wizard's Disco",
    "wof:placetype":"venue"
},
  "geometry": {"coordinates":[145.22465515100001,-37.8855323792],"type":"Point"}
}