{
  "type": "Feature",
  "properties": {
    "iso:country":"AU",
    "sg:address":"Lot 13/ 150 Abbotsford Rd",
    "sg:city":"Picton",
    "sg:classifiers":[
        {
            "category":"Real Estate",
            "subcategory":"Architect",
            "type":"Services"
        }
    ],
    "sg:phone":"+61 2 4677 2255",
    "sg:postcode":"2571",
    "sg:province":"NSW",
    "sg:tags":[
        "building",
        "designer"
    ],
    "wof:name":"Home Plans & D.A Services",
    "wof:placetype":"venue"
},
  "geometry": {"coordinates":[150.58612060600001,-34.1465530396],"type":"Point"}
}