{
  "type": "Feature",
  "properties": {
    "addr:full":"32 Hill St Kapunda SA 5373",
    "addr:housenumber":"32",
    "addr:postcode":"5373",
    "addr:street":"Hill St",
    "iso:country":"AU",
    "sg:address":"32 Hill St",
    "sg:city":"Kapunda",
    "sg:classifiers":[
        {
            "category":"Health Services",
            "subcategory":"Doctor",
            "type":"Services"
        }
    ],
    "sg:phone":"+61 8 8566 2900",
    "sg:postcode":"5373",
    "sg:province":"SA",
    "sg:tags":[
        "medical",
        "practitioner"
    ],
    "wof:name":"Kapunda Medical Practice",
    "wof:placetype":"venue"
},
  "geometry": {"coordinates":[138.91215515100001,-34.3394889832],"type":"Point"}
}