{
  "type": "Feature",
  "properties": {
    "addr:full":"15 Holmes Crt Mt Warren Park QLD 4207",
    "addr:housenumber":"15",
    "addr:postcode":"4207",
    "addr:street":"Holmes Crt Mt Warren",
    "iso:country":"AU",
    "sg:address":"15 Holmes Crt",
    "sg:city":"Mt Warren Park",
    "sg:classifiers":[
        {
            "category":"Home & Garden",
            "subcategory":"Carpets & Floor Coverings",
            "type":"Retail Goods"
        }
    ],
    "sg:phone":"+61 411 599 961",
    "sg:postcode":"4207",
    "sg:province":"QLD",
    "sg:tags":[
        "tile",
        "wall"
    ],
    "wof:name":"Sun City Tiling",
    "wof:placetype":"venue"
},
  "geometry": {"coordinates":[153.20585632300001,-27.7294254303],"type":"Point"}
}