{
  "type": "Feature",
  "properties": {
    "iso:country":"AU",
    "sg:address":"301 High St",
    "sg:city":"Shepparton",
    "sg:classifiers":[
        {
            "category":"Social Services",
            "subcategory":"Child Care",
            "type":"Services"
        }
    ],
    "sg:phone":"+61 3 5831 1757",
    "sg:postcode":"3630",
    "sg:province":"VIC",
    "wof:name":"Elizabeth Hildebrand Child Care Centre",
    "wof:placetype":"venue"
},
  "geometry": {"coordinates":[145.41114807100001,-36.3824501038],"type":"Point"}
}