{
  "type": "Feature",
  "properties": {
    "addr:full":"171 Orchard Rd Chester Hill NSW 2162",
    "addr:housenumber":"171",
    "addr:postcode":"2162",
    "addr:street":"Orchard Rd",
    "iso:country":"AU",
    "sg:address":"171 Orchard Rd",
    "sg:city":"Chester Hill",
    "sg:classifiers":[
        {
            "category":"Retail",
            "subcategory":"Car Wash",
            "type":"Services"
        }
    ],
    "sg:phone":"+61 2 9738 8777",
    "sg:postcode":"2162",
    "sg:province":"NSW",
    "sg:tags":[
        "auction",
        "motor"
    ],
    "wof:name":"Tony Hyman Motor Auctions Pty Ltd",
    "wof:placetype":"venue"
},
  "geometry": {"coordinates":[150.995605469,-33.895160675],"type":"Point"}
}