{
  "type": "Feature",
  "properties": {
    "iso:country":"AU",
    "sg:address":"45 Levanswell Rd",
    "sg:city":"Moorabbin",
    "sg:classifiers":[
        {
            "category":"Autos & Motor Vehicles",
            "subcategory":"Auto Supplies",
            "type":"Retail Goods"
        }
    ],
    "sg:phone":"+61 3 9532 2622",
    "sg:postcode":"3189",
    "sg:province":"VIC",
    "sg:tags":[
        "tyre"
    ],
    "wof:name":"Joe's Tyres",
    "wof:placetype":"venue"
},
  "geometry": {"coordinates":[145.06846618599999,-37.9449806213],"type":"Point"}
}