{
  "type": "Feature",
  "properties": {
    "addr:full":"469 Nepean Hwy Frankston VIC 3199",
    "addr:housenumber":"469",
    "addr:postcode":"3199",
    "addr:street":"Nepean Hwy",
    "iso:country":"AU",
    "sg:address":"469 Nepean Hwy",
    "sg:city":"Frankston",
    "sg:classifiers":[
        {
            "category":"Professional",
            "subcategory":"Art Services",
            "type":"Services"
        }
    ],
    "sg:phone":"+61 3 9783 8980",
    "sg:postcode":"3199",
    "sg:province":"VIC",
    "sg:tags":[
        "picture",
        "frame",
        "framing"
    ],
    "wof:name":"Framer's Workshop The",
    "wof:placetype":"venue"
},
  "geometry": {"coordinates":[145.01011657699999,-37.9074821472],"type":"Point"}
}