{
  "type": "Feature",
  "properties": {
    "addr:full":"19 Station Rd Cheltenham VIC 3192",
    "addr:housenumber":"19",
    "addr:postcode":"3192",
    "addr:street":"Station Rd",
    "iso:country":"AU",
    "sg:address":"19 Station Rd",
    "sg:city":"Cheltenham",
    "sg:classifiers":[
        {
            "category":"Personal",
            "subcategory":"Beauty Salon",
            "type":"Services"
        }
    ],
    "sg:phone":"+61 3 9583 5854",
    "sg:postcode":"3192",
    "sg:province":"VIC",
    "sg:tags":[
        "hairdresser"
    ],
    "wof:name":"2nd Opinion Hair Design Pty Ltd",
    "wof:placetype":"venue"
},
  "geometry": {"coordinates":[145.05628967300001,-37.9669265747],"type":"Point"}
}