{
  "type": "Feature",
  "properties": {
    "iso:country":"AU",
    "sg:address":"4/ 24 Spruson St",
    "sg:city":"Neutral Bay",
    "sg:classifiers":[
        {
            "category":"Utilities",
            "subcategory":"Electric",
            "type":"Services"
        }
    ],
    "sg:phone":"+61 419 922 351",
    "sg:postcode":"2089",
    "sg:province":"NSW",
    "sg:tags":[
        "electrical",
        "contractor"
    ],
    "wof:name":"Anthony Clancy Electrical Services",
    "wof:placetype":"venue"
},
  "geometry": {"coordinates":[151.21578979500001,-33.8378601074],"type":"Point"}
}