{
  "type": "Feature",
  "properties": {
    "iso:country":"AU",
    "sg:address":"4 Westfield Shopngtown Eas St",
    "sg:city":"Pagewood",
    "sg:classifiers":[
        {
            "category":"Food & Beverages",
            "subcategory":"Supermarket",
            "type":"Retail Goods"
        }
    ],
    "sg:phone":"+61 2 9344 5797",
    "sg:postcode":"2035",
    "sg:province":"NSW",
    "sg:tags":[
        "grocery",
        "store"
    ],
    "wof:name":"Franklins Stores",
    "wof:placetype":"venue"
},
  "geometry": {"coordinates":[151.22450256400001,-33.9438209534],"type":"Point"}
}