{
  "type": "Feature",
  "properties": {
    "iso:country":"AU",
    "sg:address":"58 Blackwood St",
    "sg:city":"Carnegie",
    "sg:classifiers":[
        {
            "category":"Building & Trades",
            "subcategory":"Construction",
            "type":"Services"
        }
    ],
    "sg:phone":"+61 411 428 179",
    "sg:postcode":"3163",
    "sg:province":"VIC",
    "sg:tags":[
        "polishing",
        "sanding",
        "floor"
    ],
    "wof:name":"Malvern Floors",
    "wof:placetype":"venue"
},
  "geometry": {"coordinates":[145.06123352,-37.8866577148],"type":"Point"}
}