{
  "type": "Feature",
  "properties": {
    "iso:country":"AU",
    "sg:address":"3/ 4 Shakespeare Gr St",
    "sg:city":"Kilda",
    "sg:classifiers":[
        {
            "category":"Professional",
            "subcategory":"Business Services",
            "type":"Services"
        }
    ],
    "sg:phone":"+61 3 9534 4411",
    "sg:postcode":"3182",
    "sg:province":"VIC",
    "sg:tags":[
        "broker"
    ],
    "wof:name":"Business Broking Solutions Pty Ltd",
    "wof:placetype":"venue"
},
  "geometry": {"coordinates":[144.97845459000001,-37.8679428101],"type":"Point"}
}