{
  "type": "Feature",
  "properties": {
    "iso:country":"AU",
    "sg:address":"20 Clarendon Rd",
    "sg:city":"Peakhurst",
    "sg:classifiers":[
        {
            "category":"Professional",
            "subcategory":"Art Services",
            "type":"Services"
        }
    ],
    "sg:phone":"+61 2 9153 9934",
    "sg:postcode":"2210",
    "sg:province":"NSW",
    "sg:tags":[
        "decorator",
        "painter"
    ],
    "wof:name":"David North",
    "wof:placetype":"venue"
},
  "geometry": {"coordinates":[151.04875200000001,-33.957371],"type":"Point"}
}