{
  "type": "Feature",
  "properties": {
    "iso:country":"AU",
    "sg:address":"Shop 28",
    "sg:city":"Lake Macquarie Fair Mt Hutton",
    "sg:classifiers":[
        {
            "category":"Shopping",
            "subcategory":"Shoes",
            "type":"Retail Goods"
        }
    ],
    "sg:phone":"+61 2 4948 4029",
    "sg:postcode":"2290",
    "sg:province":"NSW",
    "sg:tags":[
        "footwear"
    ],
    "wof:name":"Payless Shoes",
    "wof:placetype":"venue"
},
  "geometry": {"coordinates":[151.68063354500001,-32.9937591553],"type":"Point"}
}