{
  "type": "Feature",
  "properties": {
    "addr:full":"39 Napier St Deniliquin NSW 2710",
    "addr:housenumber":"39",
    "addr:postcode":"2710",
    "addr:street":"Napier St",
    "iso:country":"AU",
    "sg:address":"39 Napier St",
    "sg:city":"Deniliquin",
    "sg:classifiers":[
        {
            "category":"Shopping",
            "subcategory":"Shoes",
            "type":"Retail Goods"
        }
    ],
    "sg:phone":"+61 3 5881 2307",
    "sg:postcode":"2710",
    "sg:province":"NSW",
    "sg:tags":[
        "footwear"
    ],
    "wof:name":"Kazmar Shoes",
    "wof:placetype":"venue"
},
  "geometry": {"coordinates":[144.959060669,-35.5312614441],"type":"Point"}
}