{
  "type": "Feature",
  "properties": {
    "iso:country":"AU",
    "sg:address":"310 Whitehorse Rd",
    "sg:city":"Balwyn",
    "sg:classifiers":[
        {
            "category":"Banks & Credit Unions",
            "subcategory":"Bank",
            "type":"Services"
        }
    ],
    "sg:phone":"+61 3 9830 4700",
    "sg:postcode":"3103",
    "sg:province":"VIC",
    "sg:tags":[
        "equipment",
        "sale",
        "point"
    ],
    "wof:name":"Retail Management Computer Systems Pty Ltd",
    "wof:placetype":"venue"
},
  "geometry": {"coordinates":[145.084182739,-37.8133049011],"type":"Point"}
}