{
  "type": "Feature",
  "properties": {
    "addr:full":"21 Properjohn Rd Capel WA 6271",
    "addr:housenumber":"21",
    "addr:postcode":"6271",
    "addr:street":"Properjohn Rd",
    "iso:country":"AU",
    "sg:address":"21 Properjohn Rd",
    "sg:city":"Capel",
    "sg:classifiers":[
        {
            "category":"Health Services",
            "subcategory":"Doctor",
            "type":"Services"
        }
    ],
    "sg:phone":"+61 8 9727 2405",
    "sg:postcode":"6271",
    "sg:province":"WA",
    "sg:tags":[
        "medical",
        "practitioner"
    ],
    "wof:name":"Capel Medical Centre",
    "wof:placetype":"venue"
},
  "geometry": {"coordinates":[115.562232971,-33.5561408997],"type":"Point"}
}