{
  "type": "Feature",
  "properties": {
    "addr:full":"Bldg2/ 458 Airport Ave Bankstown Aerodrome NSW 2200",
    "addr:housenumber":"458",
    "addr:postcode":"2200",
    "addr:street":"Airport Ave",
    "iso:country":"AU",
    "sg:address":"Bldg2/ 458 Airport Ave",
    "sg:city":"Bankstown Aerodrome",
    "sg:classifiers":[
        {
            "category":"Airline",
            "type":"Transportation"
        }
    ],
    "sg:phone":"+61 2 9707 1386",
    "sg:postcode":"2200",
    "sg:province":"NSW",
    "sg:tags":[
        "aircraft",
        "rental",
        "charter"
    ],
    "wof:name":"Australian Air Services Pty Ltd",
    "wof:placetype":"venue"
},
  "geometry": {"coordinates":[150.991455,-33.919544],"type":"Point"}
}