{
  "type": "Feature",
  "properties": {
    "iso:country":"AU",
    "sg:address":"28 Curagul Rd",
    "sg:city":"North Turramurra",
    "sg:classifiers":[
        {
            "category":"Social Services",
            "subcategory":"Retirement Home",
            "type":"Services"
        }
    ],
    "sg:phone":"+61 2 9144 7016",
    "sg:postcode":"2074",
    "sg:province":"NSW",
    "sg:tags":[
        "village"
    ],
    "wof:name":"Cotswolds Village The",
    "wof:placetype":"venue"
},
  "geometry": {"coordinates":[151.14930725100001,-33.6981735229],"type":"Point"}
}