{
  "type": "Feature",
  "properties": {
    "addr:full":"31 Castieau Strs Higgins ACT 2615",
    "addr:housenumber":"31",
    "addr:postcode":"2615",
    "addr:street":"Castieau Strs",
    "iso:country":"AU",
    "sg:address":"31 Castieau Strs",
    "sg:city":"Higgins",
    "sg:classifiers":[
        {
            "category":"Building & Trades",
            "subcategory":"Plumbing",
            "type":"Services"
        }
    ],
    "sg:phone":"+61 419 416 897",
    "sg:postcode":"2615",
    "sg:province":"ACT",
    "sg:tags":[
        "plumber",
        "gasfitters"
    ],
    "wof:name":"ABS Plumbing Services",
    "wof:placetype":"venue"
},
  "geometry": {"coordinates":[149.03050231899999,-35.2303504944],"type":"Point"}
}