{
  "type": "Feature",
  "properties": {
    "addr:full":"129 The Boulevard, Caringbah NSW Caringbah NSW 2229",
    "addr:housenumber":"129",
    "addr:postcode":"2229",
    "addr:street":"The Boulevard",
    "iso:country":"AU",
    "sg:address":"129 The Boulevard, Caringbah NSW",
    "sg:city":"Caringbah",
    "sg:classifiers":[
        {
            "category":"Health Services",
            "subcategory":"Doctor",
            "type":"Services"
        }
    ],
    "sg:phone":"+61 2 9525 9644",
    "sg:postcode":"2229",
    "sg:province":"NSW",
    "sg:tags":[
        "occupational",
        "safety"
    ],
    "sg:website":"http://www.reflexequip.com.au",
    "wof:name":"Reflex",
    "wof:placetype":"venue"
},
  "geometry": {"coordinates":[151.12147522000001,-34.0465011597],"type":"Point"}
}