{
  "type": "Feature",
  "properties": {
    "iso:country":"AU",
    "sg:address":"Level 2, 11- 15 Falcon St",
    "sg:city":"Crows Nest",
    "sg:classifiers":[
        {
            "category":"Professional",
            "subcategory":"Computer Services",
            "type":"Services"
        }
    ],
    "sg:phone":"+61 2 9468 3535",
    "sg:postcode":"2065",
    "sg:province":"NSW",
    "sg:tags":[
        "consultant",
        "system"
    ],
    "wof:name":"AVA Systems Pty Ltd",
    "wof:placetype":"venue"
},
  "geometry": {"coordinates":[151.20176696799999,-33.8279266357],"type":"Point"}
}