{
  "type": "Feature",
  "properties": {
    "addr:full":"82 Cooks Pde St Clair NSW 2759",
    "addr:housenumber":"82",
    "addr:postcode":"2759",
    "addr:street":"Cooks Pde",
    "iso:country":"AU",
    "sg:address":"82 Cooks Pde",
    "sg:city":"St Clair",
    "sg:classifiers":[
        {
            "category":"Arts & Performance",
            "subcategory":"Music",
            "type":"Entertainment"
        }
    ],
    "sg:phone":"+61 418 233 886",
    "sg:postcode":"2759",
    "sg:province":"NSW",
    "sg:tags":[
        "mobile",
        "jockey",
        "disc"
    ],
    "wof:name":"Ray Ragers Music On The Moove",
    "wof:placetype":"venue"
},
  "geometry": {"coordinates":[150.77619934099999,-33.8050270081],"type":"Point"}
}