{
  "type": "Feature",
  "properties": {
    "addr:full":"1/ 578 President Ave Sutherland NSW 2232",
    "addr:housenumber":"/ 578",
    "addr:postcode":"2232",
    "addr:street":"President Ave",
    "iso:country":"AU",
    "sg:address":"1/ 578 President Ave",
    "sg:city":"Sutherland",
    "sg:classifiers":[
        {
            "category":"Personal",
            "subcategory":"Beauty Salon",
            "type":"Services"
        }
    ],
    "sg:phone":"+61 2 9545 1775",
    "sg:postcode":"2232",
    "sg:province":"NSW",
    "wof:name":"Tristines Beauty Room & Retreat",
    "wof:placetype":"venue"
},
  "geometry": {"coordinates":[151.05714416500001,-34.0335845947],"type":"Point"}
}