{
  "type": "Feature",
  "properties": {
    "addr:full":"101 Spurway St Ermington NSW 2115",
    "addr:housenumber":"101",
    "addr:postcode":"2115",
    "addr:street":"Spurway St",
    "iso:country":"AU",
    "sg:address":"101 Spurway St",
    "sg:city":"Ermington",
    "sg:classifiers":[
        {
            "category":"Building & Trades",
            "subcategory":"Construction",
            "type":"Services"
        }
    ],
    "sg:phone":"+61 416 210 636",
    "sg:postcode":"2115",
    "sg:province":"NSW",
    "sg:tags":[
        "renovation",
        "alterations",
        "extension",
        "contractor"
    ],
    "wof:name":"Eternity Constructions Pty Ltd",
    "wof:placetype":"venue"
},
  "geometry": {"coordinates":[151.05584716800001,-33.8108406067],"type":"Point"}
}