{
  "type": "Feature",
  "properties": {
    "iso:country":"AU",
    "sg:address":"11 Russell St",
    "sg:city":"Toowoomba",
    "sg:classifiers":[
        {
            "category":"Personal",
            "type":"Services"
        }
    ],
    "sg:phone":"+61 7 4638 3622",
    "sg:postcode":"4350",
    "sg:province":"QLD",
    "sg:tags":[
        "gift"
    ],
    "wof:name":"Southerden & C & J Florists",
    "wof:placetype":"venue"
},
  "geometry": {"coordinates":[151.95503199999999,-27.559122],"type":"Point"}
}