{
  "type": "Feature",
  "properties": {
    "addr:full":"593 Olive St Albury NSW 2640",
    "addr:housenumber":"593",
    "addr:postcode":"2640",
    "addr:street":"Olive St",
    "iso:country":"AU",
    "sg:address":"593 Olive St",
    "sg:city":"Albury",
    "sg:classifiers":[
        {
            "category":"Government",
            "subcategory":"Court House",
            "type":"Public Place"
        }
    ],
    "sg:phone":"+61 2 6021 7099",
    "sg:postcode":"2640",
    "sg:province":"NSW",
    "sg:tags":[
        "personal",
        "marriage",
        "family",
        "counselling"
    ],
    "wof:name":"St David's Unitingcare",
    "wof:placetype":"venue"
},
  "geometry": {"coordinates":[146.91868591299999,-36.0773468018],"type":"Point"}
}