{
  "type": "Feature",
  "properties": {
    "addr:full":"Lot 49 Lucas St Beacon WA 6472",
    "addr:postcode":"6472",
    "addr:street":"Lucas St",
    "iso:country":"AU",
    "sg:address":"Lot 49 Lucas St",
    "sg:city":"Beacon",
    "sg:classifiers":[
        {
            "category":"Retail",
            "subcategory":"Repair Shop",
            "type":"Services"
        }
    ],
    "sg:phone":"+61 8 9686 1010",
    "sg:postcode":"6472",
    "sg:province":"WA",
    "sg:tags":[
        "windscreen"
    ],
    "wof:name":"Beacon Panel & Paint",
    "wof:placetype":"venue"
},
  "geometry": {"coordinates":[117.865196228,-30.4509067535],"type":"Point"}
}