{
  "type": "Feature",
  "properties": {
    "iso:country":"AU",
    "sg:address":"41 Dunn Rd",
    "sg:city":"Rocklea",
    "sg:classifiers":[
        {
            "category":"Professional",
            "subcategory":"Detective & Security Services",
            "type":"Services"
        }
    ],
    "sg:phone":"+61 7 3216 7055",
    "sg:postcode":"4106",
    "sg:province":"QLD",
    "sg:tags":[
        "consultant",
        "laser"
    ],
    "wof:name":"Dowding & Mills",
    "wof:placetype":"venue"
},
  "geometry": {"coordinates":[152.99530029300001,-27.5554447174],"type":"Point"}
}