{
  "type": "Feature",
  "properties": {
    "iso:country":"AU",
    "sg:address":"Unit 2/ 12 South St",
    "sg:city":"Wodonga",
    "sg:classifiers":[
        {
            "category":"Retail",
            "subcategory":"Repair Shop",
            "type":"Services"
        }
    ],
    "sg:phone":"+61 2 6024 4718",
    "sg:postcode":"3690",
    "sg:province":"VIC",
    "sg:tags":[
        "machine",
        "repairs",
        "part",
        "dryer",
        "washing"
    ],
    "wof:name":"Wodonga Electronic Repairs",
    "wof:placetype":"venue"
},
  "geometry": {"coordinates":[146.89060974099999,-36.1191177368],"type":"Point"}
}