{
  "type": "Feature",
  "properties": {
    "addr:full":"Cnr of Brisbane & Wollumbin Sts Murwillumbah NSW 2484",
    "addr:postcode":"2484",
    "iso:country":"AU",
    "sg:address":"Cnr of Brisbane & Wollumbin Sts",
    "sg:city":"Murwillumbah",
    "sg:classifiers":[
        {
            "category":"Real Estate",
            "subcategory":"Real Estate Agent",
            "type":"Services"
        }
    ],
    "sg:phone":"+61 2 6672 7300",
    "sg:postcode":"2484",
    "sg:province":"NSW",
    "wof:name":"Wal Dennes Real Estate",
    "wof:placetype":"venue"
},
  "geometry": {"coordinates":[153.39527893100001,-28.3304901123],"type":"Point"}
}