{
  "type": "Feature",
  "properties": {
    "iso:country":"AU",
    "sg:address":"2/ 4",
    "sg:city":"Hilton Currumbin",
    "sg:classifiers":[
        {
            "category":"Home & Garden",
            "subcategory":"Furniture",
            "type":"Retail Goods"
        }
    ],
    "sg:phone":"+61 7 5598 1832",
    "sg:postcode":"4223",
    "sg:province":"QLD",
    "sg:tags":[
        "outdoor"
    ],
    "wof:name":"Currumbin Aluminium Welding",
    "wof:placetype":"venue"
},
  "geometry": {"coordinates":[153.47361755399999,-28.1475658417],"type":"Point"}
}