{
  "type": "Feature",
  "properties": {
    "addr:full":"7 Cooper St Heddon Greta NSW 2321",
    "addr:housenumber":"7",
    "addr:postcode":"2321",
    "addr:street":"Cooper St",
    "iso:country":"AU",
    "sg:address":"7 Cooper St",
    "sg:city":"Heddon Greta",
    "sg:classifiers":[
        {
            "category":"Utilities",
            "subcategory":"Water",
            "type":"Services"
        }
    ],
    "sg:phone":"+61 2 4936 1666",
    "sg:postcode":"2321",
    "sg:province":"NSW",
    "sg:tags":[
        "hot",
        "system"
    ],
    "wof:name":"Greg Brown Electrical",
    "wof:placetype":"venue"
},
  "geometry": {"coordinates":[151.51121520999999,-32.8002510071],"type":"Point"}
}