{
  "type": "Feature",
  "properties": {
    "addr:full":"41 Childs Ave Bouldercombe QLD 4702",
    "addr:housenumber":"41",
    "addr:postcode":"4702",
    "addr:street":"Childs Ave",
    "iso:country":"AU",
    "sg:address":"41 Childs Ave",
    "sg:city":"Bouldercombe",
    "sg:classifiers":[
        {
            "category":"Building & Trades",
            "subcategory":"Plumbing",
            "type":"Services"
        }
    ],
    "sg:phone":"+61 7 4934 0040",
    "sg:postcode":"4702",
    "sg:province":"QLD",
    "sg:tags":[
        "plumber",
        "gasfitters"
    ],
    "wof:name":"Greg Ward Plumbing",
    "wof:placetype":"venue"
},
  "geometry": {"coordinates":[150.49064636200001,-23.5406551361],"type":"Point"}
}