{
  "type": "Feature",
  "properties": {
    "iso:country":"AU",
    "sg:address":"196-214 Cormack Rd",
    "sg:city":"Wingfield",
    "sg:classifiers":[
        {
            "category":"Manufacturing",
            "subcategory":"Wood Products",
            "type":"Manufacturing & Wholesale Goods"
        }
    ],
    "sg:phone":"+61 8 8243 0300",
    "sg:postcode":"5013",
    "sg:province":"SA",
    "sg:tags":[
        "pallet",
        "platform"
    ],
    "wof:name":"Loscam Pallet Hire",
    "wof:placetype":"venue"
},
  "geometry": {"coordinates":[138.56483459500001,-34.8403701782],"type":"Point"}
}