{
  "type": "Feature",
  "properties": {
    "addr:full":"14 Weeden Drv Vermont South VIC 3133",
    "addr:housenumber":"14",
    "addr:postcode":"3133",
    "addr:street":"Weeden Drv",
    "iso:country":"AU",
    "sg:address":"14 Weeden Drv",
    "sg:city":"Vermont South",
    "sg:classifiers":[
        {
            "category":"Professional",
            "subcategory":"Business Services",
            "type":"Services"
        }
    ],
    "sg:phone":"+61 418 314 854",
    "sg:postcode":"3133",
    "sg:province":"VIC",
    "sg:tags":[
        "consultant",
        "system"
    ],
    "wof:name":"Change Management Consulting Pty Ltd",
    "wof:placetype":"venue"
},
  "geometry": {"coordinates":[145.17137145999999,-37.8592758179],"type":"Point"}
}