{
  "type": "Feature",
  "properties": {
    "addr:full":"17 Argyle St Millers Point NSW 2000",
    "addr:housenumber":"17",
    "addr:postcode":"2000",
    "addr:street":"Argyle St",
    "iso:country":"AU",
    "sg:address":"17 Argyle St",
    "sg:city":"Millers Point",
    "sg:classifiers":[
        {
            "category":"Social Services",
            "subcategory":"Adult Care",
            "type":"Services"
        }
    ],
    "sg:phone":"+61 2 9244 3692",
    "sg:postcode":"2000",
    "sg:province":"NSW",
    "sg:tags":[
        "aged"
    ],
    "wof:name":"Millers Point Activity Centre & Food Services",
    "wof:placetype":"venue"
},
  "geometry": {"coordinates":[151.207641602,-33.8591499329],"type":"Point"}
}