{
  "type": "Feature",
  "properties": {
    "addr:full":"62 Ellen St Port Pirie SA 5540",
    "addr:housenumber":"62",
    "addr:postcode":"5540",
    "addr:street":"Ellen St",
    "iso:country":"AU",
    "sg:address":"62 Ellen St",
    "sg:city":"Port Pirie",
    "sg:classifiers":[
        {
            "category":"Professional",
            "subcategory":"Art Services",
            "type":"Services"
        }
    ],
    "sg:phone":"+61 8 8633 0557",
    "sg:postcode":"5540",
    "sg:province":"SA",
    "sg:tags":[
        "picture",
        "frame",
        "framing"
    ],
    "wof:name":"Arts End Framing Gallery",
    "wof:placetype":"venue"
},
  "geometry": {"coordinates":[138.00987243599999,-33.1758460999],"type":"Point"}
}