{
  "type": "Feature",
  "properties": {
    "addr:full":"34 Dowling St Forbes NSW 2871",
    "addr:housenumber":"34",
    "addr:postcode":"2871",
    "addr:street":"Dowling St",
    "iso:country":"AU",
    "sg:address":"34 Dowling St",
    "sg:city":"Forbes",
    "sg:classifiers":[
        {
            "category":"Autos & Motor Vehicles",
            "subcategory":"Automobile Sales",
            "type":"Retail Goods"
        }
    ],
    "sg:phone":"+61 2 6851 1644",
    "sg:postcode":"2871",
    "sg:province":"NSW",
    "sg:tags":[
        "car",
        "used"
    ],
    "wof:name":"Jeffery Toyota",
    "wof:placetype":"venue"
},
  "geometry": {"coordinates":[148.01045199999999,-33.382027],"type":"Point"}
}