{
  "type": "Feature",
  "properties": {
    "addr:full":"11 Coonooer St Kangaroo Flat VIC 3555",
    "addr:housenumber":"11",
    "addr:postcode":"3555",
    "addr:street":"Coonooer St",
    "iso:country":"AU",
    "sg:address":"11 Coonooer St",
    "sg:city":"Kangaroo Flat",
    "sg:classifiers":[
        {
            "category":"Professional",
            "subcategory":"Engineering",
            "type":"Services"
        }
    ],
    "sg:phone":"+61 3 5447 9762",
    "sg:postcode":"3555",
    "sg:province":"VIC",
    "sg:tags":[
        "engineer"
    ],
    "wof:name":"QME Quarry & Mining Engineering",
    "wof:placetype":"venue"
},
  "geometry": {"coordinates":[144.25747680699999,-36.7912368774],"type":"Point"}
}