{
  "type": "Feature",
  "properties": {
    "iso:country":"AU",
    "sg:address":"138 Goldie St",
    "sg:city":"Wynyard",
    "sg:classifiers":[
        {
            "category":"Health Services",
            "subcategory":"Health Practitioner",
            "type":"Services"
        }
    ],
    "sg:phone":"+61 3 6442 2201",
    "sg:postcode":"7325",
    "sg:province":"TAS",
    "sg:tags":[
        "physiotherapist"
    ],
    "wof:name":"Wynyard Physiotherapy",
    "wof:placetype":"venue"
},
  "geometry": {"coordinates":[145.724213,-40.990421],"type":"Point"}
}