{
  "type": "Feature",
  "properties": {
    "iso:country":"AU",
    "sg:address":"188 East St",
    "sg:city":"Rockhampton",
    "sg:classifiers":[
        {
            "category":"Health Services",
            "subcategory":"Doctor",
            "type":"Services"
        }
    ],
    "sg:phone":"+61 7 4927 0666",
    "sg:postcode":"4700",
    "sg:province":"QLD",
    "sg:tags":[
        "occupational",
        "safety"
    ],
    "wof:name":"New Horizons Safety & Training Services",
    "wof:placetype":"venue"
},
  "geometry": {"coordinates":[150.52162170400001,-23.3895893097],"type":"Point"}
}