{
  "type": "Feature",
  "properties": {
    "addr:full":"1 Clyde Rd Berwick VIC 3806",
    "addr:housenumber":"1",
    "addr:postcode":"3806",
    "addr:street":"Clyde Rd",
    "iso:country":"AU",
    "sg:address":"1 Clyde Rd",
    "sg:city":"Berwick",
    "sg:classifiers":[
        {
            "category":"Professional",
            "subcategory":"Computer Services",
            "type":"Services"
        }
    ],
    "sg:phone":"+61 3 9707 3828",
    "sg:postcode":"3806",
    "sg:province":"VIC",
    "sg:tags":[
        "consultant",
        "system"
    ],
    "wof:name":"Gigabit Computing Pty Ltd",
    "wof:placetype":"venue"
},
  "geometry": {"coordinates":[145.343841553,-38.0316162109],"type":"Point"}
}