{
  "type": "Feature",
  "properties": {
    "addr:full":"5 Tavistock St Wagin WA 6315",
    "addr:housenumber":"5",
    "addr:postcode":"6315",
    "addr:street":"Tavistock St",
    "iso:country":"AU",
    "sg:address":"5 Tavistock St",
    "sg:city":"Wagin",
    "sg:classifiers":[
        {
            "category":"Professional",
            "subcategory":"Accounting & Tax Preparation",
            "type":"Services"
        }
    ],
    "sg:phone":"+61 8 9861 1744",
    "sg:postcode":"6315",
    "sg:province":"WA",
    "sg:tags":[
        "accountant",
        "auditor"
    ],
    "wof:name":"Attewells",
    "wof:placetype":"venue"
},
  "geometry": {"coordinates":[117.34487915,-33.3099632263],"type":"Point"}
}