{
  "type": "Feature",
  "properties": {
    "iso:country":"AU",
    "sg:address":"2/ 11 Sunshine Beach Rd",
    "sg:city":"Noosa Heads",
    "sg:classifiers":[
        {
            "category":"Professional",
            "subcategory":"Engineering",
            "type":"Services"
        }
    ],
    "sg:phone":"+61 7 5474 9081",
    "sg:postcode":"4567",
    "sg:province":"QLD",
    "sg:tags":[
        "consulting",
        "engineer"
    ],
    "wof:name":"Callaghan & Toth",
    "wof:placetype":"venue"
},
  "geometry": {"coordinates":[153.09146118199999,-26.3977680206],"type":"Point"}
}