{
  "type": "Feature",
  "properties": {
    "iso:country":"AU",
    "sg:address":"Chermside Podiatry Clinic 19 Sparkes St",
    "sg:city":"Chermside",
    "sg:classifiers":[
        {
            "category":"Health Services",
            "subcategory":"Doctor",
            "type":"Services"
        }
    ],
    "sg:phone":"+61 7 3256 4155",
    "sg:postcode":"4032",
    "sg:province":"QLD",
    "sg:tags":[
        "podiatrist"
    ],
    "wof:name":"Bampton Margaret",
    "wof:placetype":"venue"
},
  "geometry": {"coordinates":[153.02969400000001,-27.387199],"type":"Point"}
}