{
  "type": "Feature",
  "properties": {
    "addr:full":"34 Primrose St Belgian Gardens QLD 4810",
    "addr:housenumber":"34",
    "addr:postcode":"4810",
    "addr:street":"Primrose St",
    "iso:country":"AU",
    "sg:address":"34 Primrose St",
    "sg:city":"Belgian Gardens",
    "sg:classifiers":[
        {
            "category":"Personal",
            "subcategory":"Beauty Salon",
            "type":"Services"
        }
    ],
    "sg:phone":"+61 7 4721 0807",
    "sg:postcode":"4810",
    "sg:province":"QLD",
    "wof:name":"Detox Holistic Healthcare",
    "wof:placetype":"venue"
},
  "geometry": {"coordinates":[146.79818700000001,-19.244362],"type":"Point"}
}