{
  "type": "Feature",
  "properties": {
    "addr:full":"RMB 8146/ Boonoonar Rd Colignan VIC 3494",
    "addr:housenumber":"8146 / boonoonar",
    "addr:postcode":"3494",
    "addr:street":"Rd",
    "iso:country":"AU",
    "sg:address":"RMB 8146/ Boonoonar Rd",
    "sg:city":"Colignan",
    "sg:classifiers":[
        {
            "category":"Farming",
            "subcategory":"Vineyard",
            "type":"Manufacturing & Wholesale Goods"
        }
    ],
    "sg:phone":"+61 3 5029 1149",
    "sg:postcode":"3494",
    "sg:province":"VIC",
    "sg:tags":[
        "winery"
    ],
    "wof:name":"Murray Vineyards Pty Ltd",
    "wof:placetype":"venue"
},
  "geometry": {"coordinates":[142.350708008,-34.5430183411],"type":"Point"}
}