{
  "type": "Feature",
  "properties": {
    "addr:full":"U5/ 394 Henley Beach Rd Lockleys SA 5032",
    "addr:housenumber":"394",
    "addr:postcode":"5032",
    "addr:street":"U5 /;Henley Beach Rd",
    "iso:country":"AU",
    "sg:address":"U5/ 394 Henley Beach Rd",
    "sg:city":"Lockleys",
    "sg:classifiers":[
        {
            "category":"Building & Trades",
            "subcategory":"Construction",
            "type":"Services"
        }
    ],
    "sg:phone":"+61 8 8234 7828",
    "sg:postcode":"5032",
    "sg:province":"SA",
    "sg:tags":[
        "course",
        "golf",
        "equipment"
    ],
    "wof:name":"Tasman Golf Pty Ltd",
    "wof:placetype":"venue"
},
  "geometry": {"coordinates":[138.53457641599999,-34.9267196655],"type":"Point"}
}