{
  "type": "Feature",
  "properties": {
    "iso:country":"AU",
    "sg:address":"U1- 54 Reserve Drv",
    "sg:city":"Mandurah",
    "sg:classifiers":[
        {
            "category":"Shopping",
            "subcategory":"Pawn Shop",
            "type":"Retail Goods"
        }
    ],
    "sg:phone":"+61 8 9582 0999",
    "sg:postcode":"6210",
    "sg:province":"WA",
    "sg:tags":[
        "pawnbroker"
    ],
    "wof:name":"Kashmart Mandurah",
    "wof:placetype":"venue"
},
  "geometry": {"coordinates":[115.741928,-32.512844],"type":"Point"}
}