{
  "type": "Feature",
  "properties": {
    "iso:country":"AU",
    "sg:address":"47 Rocky Point Rd",
    "sg:city":"Kogarah",
    "sg:classifiers":[
        {
            "category":"Professional",
            "subcategory":"Accounting & Tax Preparation",
            "type":"Services"
        }
    ],
    "sg:phone":"+61 2 9553 8350",
    "sg:postcode":"2217",
    "sg:province":"NSW",
    "sg:tags":[
        "consultant",
        "taxation"
    ],
    "wof:name":"O'Brien Burrell & Co Pty Ltd",
    "wof:placetype":"venue"
},
  "geometry": {"coordinates":[151.136215,-33.972603],"type":"Point"}
}