{
  "type": "Feature",
  "properties": {
    "iso:country":"AU",
    "sg:address":"268 Orrong Rd",
    "sg:city":"Caulfield North",
    "sg:classifiers":[
        {
            "category":"Health Services",
            "subcategory":"Health Practitioner",
            "type":"Services"
        }
    ],
    "sg:phone":"+61 3 9525 9339",
    "sg:postcode":"3161",
    "sg:province":"VIC",
    "sg:tags":[
        "naturopath"
    ],
    "wof:name":"Velevski Miriam",
    "wof:placetype":"venue"
},
  "geometry": {"coordinates":[145.00878906200001,-37.8705024719],"type":"Point"}
}