{
  "type": "Feature",
  "properties": {
    "addr:full":"412 Lawrence St Wodonga West VIC 3690",
    "addr:housenumber":"412",
    "addr:postcode":"3690",
    "addr:street":"Lawrence St",
    "iso:country":"AU",
    "sg:address":"412 Lawrence St",
    "sg:city":"Wodonga West",
    "sg:classifiers":[
        {
            "category":"Education",
            "subcategory":"Kindergarten",
            "type":"Public Place"
        }
    ],
    "sg:phone":"+61 2 6059 4786",
    "sg:postcode":"3690",
    "sg:province":"VIC",
    "sg:tags":[
        "pre-schools"
    ],
    "wof:name":"K 4 Kidz",
    "wof:placetype":"venue"
},
  "geometry": {"coordinates":[146.85523986800001,-36.1198387146],"type":"Point"}
}