{
  "type": "Feature",
  "properties": {
    "addr:full":"344 High St Echuca VIC 3564",
    "addr:housenumber":"344",
    "addr:postcode":"3564",
    "addr:street":"High St",
    "iso:country":"AU",
    "sg:address":"344 High St",
    "sg:city":"Echuca",
    "sg:classifiers":[
        {
            "category":"Retail",
            "subcategory":"Veterinary Services",
            "type":"Services"
        }
    ],
    "sg:phone":"+61 3 5482 3202",
    "sg:postcode":"3564",
    "sg:province":"VIC",
    "sg:tags":[
        "surgeon"
    ],
    "wof:name":"Hall Michael B",
    "wof:placetype":"venue"
},
  "geometry": {"coordinates":[144.75296020499999,-36.147895813],"type":"Point"}
}