{
  "type": "Feature",
  "properties": {
    "iso:country":"AU",
    "sg:address":"35 Armstrong Rd",
    "sg:city":"Cannon Hill",
    "sg:classifiers":[
        {
            "category":"Building & Trades",
            "subcategory":"Construction",
            "type":"Services"
        }
    ],
    "sg:phone":"+61 7 3399 5293",
    "sg:postcode":"4170",
    "sg:province":"QLD",
    "sg:tags":[
        "roof"
    ],
    "wof:name":"A.J. & S. Woodward",
    "wof:placetype":"venue"
},
  "geometry": {"coordinates":[153.08274841299999,-27.4658985138],"type":"Point"}
}