{
  "type": "Feature",
  "properties": {
    "iso:country":"AU",
    "sg:address":"7- 9 Bakewell St",
    "sg:city":"Cranbourne",
    "sg:classifiers":[
        {
            "category":"Real Estate",
            "subcategory":"Surveying",
            "type":"Services"
        }
    ],
    "sg:phone":"+61 3 5996 4133",
    "sg:postcode":"3977",
    "sg:province":"VIC",
    "sg:tags":[
        "surveyor",
        "land"
    ],
    "wof:name":"Nilsson, Noel & Holmes",
    "wof:placetype":"venue"
},
  "geometry": {"coordinates":[145.28448486299999,-38.1106376648],"type":"Point"}
}