{
  "type": "Feature",
  "properties": {
    "iso:country":"AU",
    "sg:address":"Shop 16/ 61 President Wilson Walk",
    "sg:city":"Tanilba Bay",
    "sg:classifiers":[
        {
            "category":"Cafe",
            "type":"Food & Drink"
        }
    ],
    "sg:phone":"+61 2 4982 5322",
    "sg:postcode":"2319",
    "sg:province":"NSW",
    "wof:name":"The Cookie House",
    "wof:placetype":"venue"
},
  "geometry": {"coordinates":[152.002243,-32.734066],"type":"Point"}
}