{
  "type": "Feature",
  "properties": {
    "addr:full":"Unit 25 20 Edward St Bondi NSW 2026",
    "addr:housenumber":"20",
    "addr:postcode":"2026",
    "addr:street":"Edward St",
    "iso:country":"AU",
    "sg:address":"Unit 25 20 Edward St",
    "sg:city":"Bondi",
    "sg:classifiers":[
        {
            "category":"Professional",
            "subcategory":"Art Services",
            "type":"Services"
        }
    ],
    "sg:phone":"+61 2 9365 6653",
    "sg:postcode":"2026",
    "sg:province":"NSW",
    "sg:tags":[
        "decorator",
        "painter"
    ],
    "wof:name":"Michael's Living Colour",
    "wof:placetype":"venue"
},
  "geometry": {"coordinates":[151.26873779300001,-33.8931083679],"type":"Point"}
}