{
  "type": "Feature",
  "properties": {
    "iso:country":"AU",
    "sg:address":"Shop 5, 1050 Rockingham Rd",
    "sg:city":"Wattleup",
    "sg:classifiers":[
        {
            "category":"Real Estate",
            "subcategory":"Real Estate Agent",
            "type":"Services"
        }
    ],
    "sg:phone":"+61 8 9437 9000",
    "sg:postcode":"6166",
    "sg:province":"WA",
    "wof:name":"Ray White Wattleup",
    "wof:placetype":"venue"
},
  "geometry": {"coordinates":[115.79425000000001,-32.178463],"type":"Point"}
}