{
  "type": "Feature",
  "properties": {
    "iso:country":"AU",
    "sg:address":"13 White St",
    "sg:city":"Waikerie",
    "sg:classifiers":[
        {
            "category":"Communications",
            "subcategory":"Film & Video Production",
            "type":"Services"
        }
    ],
    "sg:phone":"+61 8 8541 3775",
    "sg:postcode":"5330",
    "sg:province":"SA",
    "sg:tags":[
        "dvd",
        "library"
    ],
    "wof:name":"Waikerie Community Classic Video",
    "wof:placetype":"venue"
},
  "geometry": {"coordinates":[139.987091064,-34.1792907715],"type":"Point"}
}