{
  "type": "Feature",
  "properties": {
    "iso:country":"AU",
    "sg:address":"East Adelaide Medical Centre, 50 Hutt St",
    "sg:city":"Adelaide",
    "sg:classifiers":[
        {
            "category":"Health Services",
            "subcategory":"Health Practitioner",
            "type":"Services"
        }
    ],
    "sg:phone":"+61 407 610 452",
    "sg:postcode":"5000",
    "sg:province":"SA",
    "sg:tags":[
        "pathologist",
        "speech"
    ],
    "wof:name":"Flavell Johanna",
    "wof:placetype":"venue"
},
  "geometry": {"coordinates":[138.61216735799999,-34.9268798828],"type":"Point"}
}