{
  "type": "Feature",
  "properties": {
    "addr:full":"368 Dundas St Rye VIC 3941",
    "addr:housenumber":"368",
    "addr:postcode":"3941",
    "addr:street":"Dundas St",
    "iso:country":"AU",
    "sg:address":"368 Dundas St",
    "sg:city":"Rye",
    "sg:classifiers":[
        {
            "category":"Food & Beverages",
            "subcategory":"Liquor & Beverages",
            "type":"Retail Goods"
        }
    ],
    "sg:phone":"+61 3 5985 4999",
    "sg:postcode":"3941",
    "sg:province":"VIC",
    "sg:tags":[
        "store"
    ],
    "wof:name":"Back Beach Cellars",
    "wof:placetype":"venue"
},
  "geometry": {"coordinates":[144.81219482399999,-38.4023132324],"type":"Point"}
}