{
  "type": "Feature",
  "properties": {
    "iso:country":"AU",
    "sg:address":"31 Powlett St",
    "sg:city":"Kilmore",
    "sg:classifiers":[
        {
            "category":"Retail",
            "subcategory":"Funeral Services",
            "type":"Services"
        }
    ],
    "sg:phone":"+61 3 5782 1140",
    "sg:postcode":"3764",
    "sg:province":"VIC",
    "sg:tags":[
        "director"
    ],
    "wof:name":"Skehan A & Co",
    "wof:placetype":"venue"
},
  "geometry": {"coordinates":[144.951446533,-37.2990875244],"type":"Point"}
}