{
  "type": "Feature",
  "properties": {
    "iso:country":"AU",
    "sg:address":"Suite 3, 113 Main Rd",
    "sg:city":"Moonah",
    "sg:classifiers":[
        {
            "category":"Health Services",
            "subcategory":"Health Practitioner",
            "type":"Services"
        }
    ],
    "sg:phone":"+61 3 6278 7240",
    "sg:postcode":"7009",
    "sg:province":"TAS",
    "sg:tags":[
        "hypnotherapy"
    ],
    "sg:website":"http://www.hypnosouth.com.au",
    "wof:name":"Hypnosis South Tasmania",
    "wof:placetype":"venue"
},
  "geometry": {"coordinates":[147.294647217,-42.8460922241],"type":"Point"}
}