{
  "type": "Feature",
  "properties": {
    "addr:full":"2 Bimbil St Albion QLD 4010",
    "addr:housenumber":"2",
    "addr:postcode":"4010",
    "addr:street":"Bimbil St",
    "iso:country":"AU",
    "sg:address":"2 Bimbil St",
    "sg:city":"Albion",
    "sg:classifiers":[
        {
            "category":"Professional",
            "type":"Services"
        }
    ],
    "sg:phone":"+61 7 3262 9742",
    "sg:postcode":"4010",
    "sg:province":"QLD",
    "sg:tags":[
        "courier"
    ],
    "wof:name":"Pack & Send",
    "wof:placetype":"venue"
},
  "geometry": {"coordinates":[153.042205811,-27.4331130981],"type":"Point"}
}