{
  "type": "Feature",
  "properties": {
    "addr:full":"99- 105 McDowell St Welshpool WA 6106",
    "addr:housenumber":"105",
    "addr:postcode":"6106",
    "addr:street":"99;Mcdowell St",
    "iso:country":"AU",
    "sg:address":"99- 105 McDowell St",
    "sg:city":"Welshpool",
    "sg:classifiers":[
        {
            "category":"Manufacturing",
            "subcategory":"Metals",
            "type":"Manufacturing & Wholesale Goods"
        }
    ],
    "sg:phone":"+61 8 9458 1188",
    "sg:postcode":"6106",
    "sg:province":"WA",
    "sg:tags":[
        "sheet",
        "worker"
    ],
    "sg:website":"http://www.phoenixmetal.com.au",
    "wof:name":"Phoenix Metalform",
    "wof:placetype":"venue"
},
  "geometry": {"coordinates":[115.973838806,-31.988653183],"type":"Point"}
}