{
  "type": "Feature",
  "properties": {
    "addr:full":"2/ 14 Clive St Springvale VIC 3171",
    "addr:housenumber":"/ 14",
    "addr:postcode":"3171",
    "addr:street":"Clive St",
    "iso:country":"AU",
    "sg:address":"2/ 14 Clive St",
    "sg:city":"Springvale",
    "sg:classifiers":[
        {
            "category":"Shopping",
            "subcategory":"Clothing, Apparel, & Fashions",
            "type":"Retail Goods"
        }
    ],
    "sg:phone":"+61 3 9548 4808",
    "sg:postcode":"3171",
    "sg:province":"VIC",
    "sg:tags":[
        "sportswear"
    ],
    "wof:name":"Auscrosse",
    "wof:placetype":"venue"
},
  "geometry": {"coordinates":[145.149459839,-37.9339447021],"type":"Point"}
}