{
  "type": "Feature",
  "properties": {
    "addr:full":"22 Cornellius St Dandenong VIC 3175",
    "addr:housenumber":"22",
    "addr:postcode":"3175",
    "addr:street":"Cornellius St",
    "iso:country":"AU",
    "sg:address":"22 Cornellius St",
    "sg:city":"Dandenong",
    "sg:classifiers":[
        {
            "category":"Building & Trades",
            "subcategory":"Construction",
            "type":"Services"
        }
    ],
    "sg:phone":"+61 3 9792 5043",
    "sg:postcode":"3175",
    "sg:province":"VIC",
    "sg:tags":[
        "concrete",
        "paving"
    ],
    "wof:name":"Conflenti Concrete Paving",
    "wof:placetype":"venue"
},
  "geometry": {"coordinates":[145.22584533700001,-37.9717788696],"type":"Point"}
}