{
  "type": "Feature",
  "properties": {
    "addr:full":"93 Huet St Nundah QLD 4012",
    "addr:housenumber":"93",
    "addr:postcode":"4012",
    "addr:street":"Huet St",
    "iso:country":"AU",
    "sg:address":"93 Huet St",
    "sg:city":"Nundah",
    "sg:classifiers":[
        {
            "category":"Communications",
            "subcategory":"News Services",
            "type":"Services"
        }
    ],
    "sg:phone":"+61 7 3256 6952",
    "sg:postcode":"4012",
    "sg:province":"QLD",
    "sg:tags":[
        "information",
        "tourist",
        "attractions"
    ],
    "wof:name":"Birding Services Brisbane",
    "wof:placetype":"venue"
},
  "geometry": {"coordinates":[153.050048828,-27.402961731],"type":"Point"}
}