{
  "type": "Feature",
  "properties": {
    "addr:full":"Hawkwood Rd Derri Derra QLD 4626",
    "addr:postcode":"4626",
    "addr:street":"Hawkwood Rd",
    "iso:country":"AU",
    "sg:address":"Hawkwood Rd",
    "sg:city":"Derri Derra",
    "sg:classifiers":[
        {
            "category":"Farming",
            "subcategory":"Orchard",
            "type":"Manufacturing & Wholesale Goods"
        }
    ],
    "sg:phone":"+61 7 4165 6165",
    "sg:postcode":"4626",
    "sg:province":"QLD",
    "sg:tags":[
        "citrus",
        "fruit",
        "grower"
    ],
    "wof:name":"Auburnvale Citrus Pty Ltd",
    "wof:placetype":"venue"
},
  "geometry": {"coordinates":[151.22923299999999,-25.663034],"type":"Point"}
}