{
  "type": "Feature",
  "properties": {
    "iso:country":"AU",
    "sg:address":"Unit 2/ 93 Norma Rd",
    "sg:city":"Myaree",
    "sg:classifiers":[
        {
            "category":"Shopping",
            "subcategory":"Computers & Home Electronics",
            "type":"Retail Goods"
        }
    ],
    "sg:phone":"+61 8 9329 9070",
    "sg:postcode":"6154",
    "sg:province":"WA",
    "sg:tags":[
        "hi-fi",
        "equipment"
    ],
    "wof:name":"Audiocraft",
    "wof:placetype":"venue"
},
  "geometry": {"coordinates":[115.822151,-32.042793],"type":"Point"}
}