{
  "type": "Feature",
  "properties": {
    "iso:country":"AU",
    "sg:address":"2 Harold Francis Drv",
    "sg:city":"Coffs Harbour",
    "sg:classifiers":[
        {
            "category":"Professional",
            "subcategory":"Management & Consulting",
            "type":"Services"
        }
    ],
    "sg:phone":"+61 2 6652 9500",
    "sg:postcode":"2450",
    "sg:province":"NSW",
    "sg:tags":[
        "consultant",
        "migration"
    ],
    "wof:name":"Colin King",
    "wof:placetype":"venue"
},
  "geometry": {"coordinates":[153.1017,-30.296253],"type":"Point"}
}