{
  "type": "Feature",
  "properties": {
    "addr:full":"906 Ingham Rd Bohle QLD 4818",
    "addr:housenumber":"906",
    "addr:postcode":"4818",
    "addr:street":"Ingham Rd",
    "iso:country":"AU",
    "sg:address":"906 Ingham Rd",
    "sg:city":"Bohle",
    "sg:classifiers":[
        {
            "category":"Professional",
            "subcategory":"Engineering",
            "type":"Services"
        }
    ],
    "sg:phone":"+61 427 778 177",
    "sg:postcode":"4818",
    "sg:province":"QLD",
    "sg:tags":[
        "engineer"
    ],
    "wof:name":"Horwood Engineering",
    "wof:placetype":"venue"
},
  "geometry": {"coordinates":[146.714508,-19.261801],"type":"Point"}
}