{
  "type": "Feature",
  "properties": {
    "iso:country":"AU",
    "sg:address":"9/ 187 Macquarie St",
    "sg:city":"Sydney",
    "sg:classifiers":[
        {
            "category":"Health Services",
            "subcategory":"Dentist",
            "type":"Services"
        }
    ],
    "sg:phone":"+61 2 9232 3333",
    "sg:postcode":"2000",
    "sg:province":"NSW",
    "wof:name":"Sofianidis Nick",
    "wof:placetype":"venue"
},
  "geometry": {"coordinates":[151.21217346200001,-33.8671836853],"type":"Point"}
}