{
  "type": "Feature",
  "properties": {
    "iso:country":"AU",
    "sg:address":"56 Orchardtown Rd",
    "sg:city":"New Lambton",
    "sg:classifiers":[
        {
            "category":"Personal",
            "subcategory":"Hair Removal",
            "type":"Services"
        }
    ],
    "sg:phone":"+61 2 4957 7222",
    "sg:postcode":"2305",
    "sg:province":"NSW",
    "wof:name":"Hairfree New Lambton",
    "wof:placetype":"venue"
},
  "geometry": {"coordinates":[151.707687,-32.93354],"type":"Point"}
}