{
  "type": "Feature",
  "properties": {
    "iso:country":"AU",
    "sg:address":"24 Ormond Rd",
    "sg:city":"Elwood",
    "sg:classifiers":[
        {
            "category":"Sports & Exercise",
            "subcategory":"Gym",
            "type":"Entertainment"
        }
    ],
    "sg:phone":"+61 412 551 810",
    "sg:postcode":"3184",
    "sg:province":"VIC",
    "sg:tags":[
        "personal",
        "trainer",
        "fitness"
    ],
    "wof:name":"Back2Basics Personal Training",
    "wof:placetype":"venue"
},
  "geometry": {"coordinates":[144.98289489699999,-37.8826751709],"type":"Point"}
}