{
  "type": "Feature",
  "properties": {
    "addr:full":"226 Malop St Geelong VIC 3220",
    "addr:housenumber":"226",
    "addr:postcode":"3220",
    "addr:street":"Malop St",
    "iso:country":"AU",
    "sg:address":"226 Malop St",
    "sg:city":"Geelong",
    "sg:classifiers":[
        {
            "category":"Professional",
            "subcategory":"Accounting & Tax Preparation",
            "type":"Services"
        }
    ],
    "sg:phone":"+61 3 5223 3899",
    "sg:postcode":"3220",
    "sg:province":"VIC",
    "sg:tags":[
        "consultant",
        "taxation"
    ],
    "wof:name":"Enza Hughes",
    "wof:placetype":"venue"
},
  "geometry": {"coordinates":[144.367142,-38.149117],"type":"Point"}
}