{
  "type": "Feature",
  "properties": {
    "iso:country":"AU",
    "sg:address":"158 Cumberland Ave",
    "sg:city":"Castle Hill",
    "sg:classifiers":[
        {
            "category":"Banks & Credit Unions",
            "subcategory":"Bank",
            "type":"Services"
        }
    ],
    "sg:phone":"+61 2 8207 3167",
    "sg:postcode":"2154",
    "sg:province":"NSW",
    "sg:tags":[
        "equipment",
        "sale",
        "point"
    ],
    "wof:name":"Barcoder",
    "wof:placetype":"venue"
},
  "geometry": {"coordinates":[150.99333190900001,-33.7239265442],"type":"Point"}
}