{
  "type": "Feature",
  "properties": {
    "iso:country":"AU",
    "sg:address":"546 Greenhill Rd",
    "sg:city":"Hazelwood Park",
    "sg:classifiers":[
        {
            "category":"Building & Trades",
            "subcategory":"Construction",
            "type":"Services"
        }
    ],
    "sg:phone":"+61 8 8431 9844",
    "sg:postcode":"5066",
    "sg:province":"SA",
    "sg:tags":[
        "industrial",
        "commercial",
        "air conditioning"
    ],
    "wof:name":"Climat",
    "wof:placetype":"venue"
},
  "geometry": {"coordinates":[138.65963745100001,-34.938495636],"type":"Point"}
}