{
  "type": "Feature",
  "properties": {
    "iso:country":"AU",
    "sg:address":"3 Ennis St",
    "sg:city":"Balmain",
    "sg:classifiers":[
        {
            "category":"Autos & Motor Vehicles",
            "subcategory":"Boat Sales",
            "type":"Retail Goods"
        }
    ],
    "sg:phone":"+61 2 9810 2877",
    "sg:postcode":"2041",
    "sg:province":"NSW",
    "sg:tags":[
        "builder",
        "yacht",
        "repairer"
    ],
    "wof:name":"Handwritten",
    "wof:placetype":"venue"
},
  "geometry": {"coordinates":[151.178146,-33.860489],"type":"Point"}
}