{
  "type": "Feature",
  "properties": {
    "iso:country":"AU",
    "sg:address":"14 Somer St",
    "sg:city":"Hyde Park",
    "sg:classifiers":[
        {
            "category":"Retail",
            "subcategory":"Auto Repair",
            "type":"Services"
        }
    ],
    "sg:phone":"+61 7 4772 0774",
    "sg:postcode":"4812",
    "sg:province":"QLD",
    "sg:tags":[
        "repairer",
        "motor",
        "engineer"
    ],
    "wof:name":"Hyund Serv",
    "wof:placetype":"venue"
},
  "geometry": {"coordinates":[146.800705,-19.273485],"type":"Point"}
}