{
  "type": "Feature",
  "properties": {
    "addr:full":"51 McShane St Campbelltown SA 5074",
    "addr:housenumber":"51",
    "addr:postcode":"5074",
    "addr:street":"Mcshane St",
    "iso:country":"AU",
    "sg:address":"51 McShane St",
    "sg:city":"Campbelltown",
    "sg:classifiers":[
        {
            "category":"Manufacturing",
            "subcategory":"Food",
            "type":"Manufacturing & Wholesale Goods"
        }
    ],
    "sg:phone":"+61 8 8365 0222",
    "sg:postcode":"5074",
    "sg:province":"SA",
    "sg:tags":[
        "function",
        "catering"
    ],
    "wof:name":"Aussie Ripper Roasts",
    "wof:placetype":"venue"
},
  "geometry": {"coordinates":[138.65835571299999,-34.8763999939],"type":"Point"}
}