{
  "type": "Feature",
  "properties": {
    "addr:full":"Shop 7 Lakeshore Shopping Village Lakeshore Ave Buderim QLD 4556",
    "addr:housenumber":"shop 7",
    "addr:postcode":"4556",
    "addr:street":"Lakeshore Shopping Village Lakeshore Ave",
    "iso:country":"AU",
    "sg:address":"Shop 7 Lakeshore Shopping Village Lakeshore Ave",
    "sg:city":"Buderim",
    "sg:classifiers":[
        {
            "category":"Health Services",
            "subcategory":"Dentist",
            "type":"Services"
        }
    ],
    "sg:phone":"+61 7 5553 2888",
    "sg:postcode":"4556",
    "sg:province":"QLD",
    "wof:name":"Ricketts Simone Dr",
    "wof:placetype":"venue"
},
  "geometry": {"coordinates":[153.06715393100001,-26.6663379669],"type":"Point"}
}