{
  "type": "Feature",
  "properties": {
    "iso:country":"AU",
    "sg:address":"Unit 1/ 37 Jindalee Rd",
    "sg:city":"Port Macquarie",
    "sg:classifiers":[
        {
            "category":"Professional",
            "subcategory":"Engineering",
            "type":"Services"
        }
    ],
    "sg:phone":"+61 2 5524 0900",
    "sg:postcode":"2444",
    "sg:province":"NSW",
    "sg:tags":[
        "consultant",
        "geotechnical",
        "engineer"
    ],
    "wof:name":"Coffey Geotechnics Pty Ltd",
    "wof:placetype":"venue"
},
  "geometry": {"coordinates":[152.884277,-31.452305],"type":"Point"}
}