{
  "type": "Feature",
  "properties": {
    "addr:full":"325 Sydney Rd Balgowlah NSW 2093",
    "addr:housenumber":"325",
    "addr:postcode":"2093",
    "addr:street":"Sydney Rd",
    "iso:country":"AU",
    "sg:address":"325 Sydney Rd",
    "sg:city":"Balgowlah",
    "sg:classifiers":[
        {
            "category":"Health Services",
            "subcategory":"Health Practitioner",
            "type":"Services"
        }
    ],
    "sg:phone":"+61 2 9957 1198",
    "sg:postcode":"2093",
    "sg:province":"NSW",
    "sg:tags":[
        "acupuncture"
    ],
    "wof:name":"Edwards & Scott Chinese Medicine Clinic",
    "wof:placetype":"venue"
},
  "geometry": {"coordinates":[151.265136719,-33.7944946289],"type":"Point"}
}