{
  "type": "Feature",
  "properties": {
    "addr:full":"117 Spring St Reservoir VIC 3073",
    "addr:housenumber":"117",
    "addr:postcode":"3073",
    "addr:street":"Spring St",
    "iso:country":"AU",
    "sg:address":"117 Spring St",
    "sg:city":"Reservoir",
    "sg:classifiers":[
        {
            "category":"Fast Food",
            "type":"Food & Drink"
        }
    ],
    "sg:phone":"+61 3 9470 6055",
    "sg:postcode":"3073",
    "sg:province":"VIC",
    "sg:tags":[
        "away",
        "take"
    ],
    "wof:name":"Sam's Pizza & Pasta",
    "wof:placetype":"venue"
},
  "geometry": {"coordinates":[145.007202148,-37.7149658203],"type":"Point"}
}