{
  "type": "Feature",
  "properties": {
    "addr:full":"2 Days Rd Grange QLD 4051",
    "addr:postcode":"4051",
    "addr:street":"Days Rd",
    "iso:country":"AU",
    "sg:address":"2 Days Rd",
    "sg:city":"Grange",
    "sg:classifiers":[
        {
            "category":"Personal",
            "subcategory":"Beauty Salon",
            "type":"Services"
        }
    ],
    "sg:phone":"+61 7 3356 4156",
    "sg:postcode":"4051",
    "sg:province":"QLD",
    "sg:tags":[
        "hairdresser"
    ],
    "wof:name":"Totovoco",
    "wof:placetype":"venue"
},
  "geometry": {"coordinates":[153.023147583,-27.4272994995],"type":"Point"}
}