{
  "type": "Feature",
  "properties": {
    "addr:full":"29 Herbert St Laura SA 5480",
    "addr:housenumber":"29",
    "addr:postcode":"5480",
    "addr:street":"Herbert St",
    "iso:country":"AU",
    "sg:address":"29 Herbert St",
    "sg:city":"Laura",
    "sg:classifiers":[
        {
            "category":"Personal",
            "subcategory":"Beauty Salon",
            "type":"Services"
        }
    ],
    "sg:phone":"+61 8 8663 2462",
    "sg:postcode":"5480",
    "sg:province":"SA",
    "sg:tags":[
        "hairdresser"
    ],
    "wof:name":"Laura Hair Affair",
    "wof:placetype":"venue"
},
  "geometry": {"coordinates":[138.30076599099999,-33.1851463318],"type":"Point"}
}