{
  "type": "Feature",
  "properties": {
    "iso:country":"AU",
    "sg:address":"Shop 34 Karingal Hub Shopping Centre",
    "sg:city":"Frankston",
    "sg:classifiers":[
        {
            "category":"Shopping",
            "subcategory":"Clothing, Apparel, & Fashions",
            "type":"Retail Goods"
        }
    ],
    "sg:phone":"+61 3 9789 9099",
    "sg:postcode":"3199",
    "sg:province":"VIC",
    "sg:tags":[
        "lady",
        "wear"
    ],
    "wof:name":"Suzanne Grae",
    "wof:placetype":"venue"
},
  "geometry": {"coordinates":[145.294647217,-37.7669410706],"type":"Point"}
}