{
  "type": "Feature",
  "properties": {
    "iso:country":"AU",
    "sg:address":"45 Gayndah Rd",
    "sg:city":"Maryborough",
    "sg:classifiers":[
        {
            "category":"Commercial Area",
            "type":"Public Place"
        }
    ],
    "sg:phone":"+61 7 4121 2716",
    "sg:postcode":"4650",
    "sg:province":"QLD",
    "sg:tags":[
        "heavy",
        "carrier"
    ],
    "wof:name":"Timber City Towing Service",
    "wof:placetype":"venue"
},
  "geometry": {"coordinates":[152.665817,-25.51675],"type":"Point"}
}