{
  "type": "Feature",
  "properties": {
    "addr:full":"544 Peel St Tamworth NSW 2340",
    "addr:housenumber":"544",
    "addr:postcode":"2340",
    "addr:street":"Peel St",
    "iso:country":"AU",
    "sg:address":"544 Peel St",
    "sg:city":"Tamworth",
    "sg:classifiers":[
        {
            "category":"Professional",
            "subcategory":"Accounting & Tax Preparation",
            "type":"Services"
        }
    ],
    "sg:phone":"+61 2 6766 2044",
    "sg:postcode":"2340",
    "sg:province":"NSW",
    "sg:tags":[
        "consultant",
        "taxation"
    ],
    "wof:name":"Barber P E & Co",
    "wof:placetype":"venue"
},
  "geometry": {"coordinates":[150.938232422,-31.0994987488],"type":"Point"}
}