{
  "type": "Feature",
  "properties": {
    "addr:full":"Shop 23 Argyle Mall Shopping Centre Goulburn NSW 2580",
    "addr:housenumber":"shop 23",
    "addr:postcode":"2580",
    "addr:street":"Argyle Mall",
    "iso:country":"AU",
    "sg:address":"Shop 23 Argyle Mall Shopping Centre",
    "sg:city":"Goulburn",
    "sg:classifiers":[
        {
            "category":"Shopping",
            "subcategory":"Clothing, Apparel, & Fashions",
            "type":"Retail Goods"
        }
    ],
    "sg:phone":"+61 2 4822 2036",
    "sg:postcode":"2580",
    "sg:province":"NSW",
    "sg:tags":[
        "lady",
        "wear"
    ],
    "wof:name":"Rockmans Stores Pty Limited",
    "wof:placetype":"venue"
},
  "geometry": {"coordinates":[149.73440551799999,-34.7438926697],"type":"Point"}
}