{
  "type": "Feature",
  "properties": {
    "iso:country":"AU",
    "sg:address":"47a Hunter St",
    "sg:city":"Bundaberg",
    "sg:classifiers":[
        {
            "category":"Building & Trades",
            "subcategory":"Pest Control",
            "type":"Services"
        }
    ],
    "sg:phone":"+61 7 4153 4500",
    "sg:postcode":"4670",
    "sg:province":"QLD",
    "wof:name":"Bundaberg Bug Busters Pest Management",
    "wof:placetype":"venue"
},
  "geometry": {"coordinates":[152.36050415,-24.8808937073],"type":"Point"}
}