{
  "type": "Feature",
  "properties": {
    "addr:full":"John St Salisbury SA 5108",
    "addr:postcode":"5108",
    "addr:street":"John St",
    "iso:country":"AU",
    "sg:address":"John St",
    "sg:city":"Salisbury",
    "sg:classifiers":[
        {
            "category":"Food & Beverages",
            "subcategory":"Supermarket",
            "type":"Retail Goods"
        }
    ],
    "sg:phone":"+61 8 8258 9033",
    "sg:postcode":"5108",
    "sg:province":"SA",
    "sg:tags":[
        "grocery",
        "store"
    ],
    "wof:name":"Bi-Lo",
    "wof:placetype":"venue"
},
  "geometry": {"coordinates":[138.644363403,-34.7626914978],"type":"Point"}
}