{
  "type": "Feature",
  "properties": {
    "iso:country":"AU",
    "sg:address":"60 Bega Rd",
    "sg:city":"Kingston",
    "sg:classifiers":[
        {
            "category":"Manufacturing",
            "subcategory":"Metals",
            "type":"Manufacturing & Wholesale Goods"
        }
    ],
    "sg:phone":"+61 7 3386 0641",
    "sg:postcode":"4114",
    "sg:province":"QLD",
    "sg:tags":[
        "steel",
        "fabricator",
        "mfrs"
    ],
    "wof:name":"Anything Metal",
    "wof:placetype":"venue"
},
  "geometry": {"coordinates":[153.11581420900001,-27.6643886566],"type":"Point"}
}