{
  "type": "Feature",
  "properties": {
    "addr:full":"Curtis Rd Waikerie SA 5330",
    "addr:postcode":"5330",
    "addr:street":"Curtis Rd",
    "iso:country":"AU",
    "sg:address":"Curtis Rd",
    "sg:city":"Waikerie",
    "sg:classifiers":[
        {
            "category":"Wholesale",
            "subcategory":"Auto Parts",
            "type":"Manufacturing & Wholesale Goods"
        }
    ],
    "sg:phone":"+61 8 8541 3155",
    "sg:postcode":"5330",
    "sg:province":"SA",
    "sg:tags":[
        "recyclers"
    ],
    "wof:name":"Waikerie Auto Wreckers",
    "wof:placetype":"venue"
},
  "geometry": {"coordinates":[140.00845336899999,-34.1896972656],"type":"Point"}
}