{
  "type": "Feature",
  "properties": {
    "iso:country":"AU",
    "sg:address":"Shop 10, Broadwater Tce",
    "sg:city":"Redland Bay",
    "sg:classifiers":[
        {
            "category":"Personal",
            "subcategory":"Beauty Salon",
            "type":"Services"
        }
    ],
    "sg:phone":"+61 7 3206 8483",
    "sg:postcode":"4165",
    "sg:province":"QLD",
    "sg:tags":[
        "hairdresser"
    ],
    "wof:name":"TJ's Unisex Hair Studio",
    "wof:placetype":"venue"
},
  "geometry": {"coordinates":[153.30169677699999,-27.6039009094],"type":"Point"}
}