{
  "type": "Feature",
  "properties": {
    "addr:full":"Veale Gardens Cnr South Tce & Peacock Rd Adelaide SA 5000",
    "addr:postcode":"5000",
    "addr:street":"Cnr South Tce & Peacock Rd",
    "iso:country":"AU",
    "sg:address":"Veale Gardens Cnr South Tce & Peacock Rd",
    "sg:city":"Adelaide",
    "sg:classifiers":[
        {
            "category":"Retail",
            "subcategory":"Event Space",
            "type":"Services"
        }
    ],
    "sg:phone":"+61 8 8212 7444",
    "sg:postcode":"5000",
    "sg:province":"SA",
    "sg:tags":[
        "venue",
        "reception",
        "wedding"
    ],
    "sg:website":"http://www.adelaidepavilion.com.au",
    "wof:name":"Adelaide Pavilion",
    "wof:placetype":"venue"
},
  "geometry": {"coordinates":[138.60060119600001,-34.9357948303],"type":"Point"}
}