{
  "type": "Feature",
  "properties": {
    "iso:country":"AU",
    "sg:address":"112 Blueridge Drv",
    "sg:city":"Blue Haven",
    "sg:classifiers":[
        {
            "category":"Building & Trades",
            "subcategory":"Landscaping Services",
            "type":"Services"
        }
    ],
    "sg:phone":"+61 415 100 794",
    "sg:postcode":"2262",
    "sg:province":"NSW",
    "sg:tags":[
        "designer",
        "landscape",
        "contractor"
    ],
    "wof:name":"Specialty Retaining Walls",
    "wof:placetype":"venue"
},
  "geometry": {"coordinates":[151.513748,-33.206886],"type":"Point"}
}