{
  "type": "Feature",
  "properties": {
    "iso:country":"AU",
    "sg:address":"153 Mt Peter Rd",
    "sg:city":"Edmonton",
    "sg:classifiers":[
        {
            "category":"Professional",
            "subcategory":"Computer Services",
            "type":"Services"
        }
    ],
    "sg:phone":"+61 417 002 794",
    "sg:postcode":"4869",
    "sg:province":"QLD",
    "sg:tags":[
        "package",
        "software"
    ],
    "wof:name":"Osborne Keith & Ron",
    "wof:placetype":"venue"
},
  "geometry": {"coordinates":[145.74104309099999,-17.0224323273],"type":"Point"}
}