{
  "type": "Feature",
  "properties": {
    "addr:full":"9 Goodwood Rd Wayville SA 5034",
    "addr:housenumber":"9",
    "addr:postcode":"5034",
    "addr:street":"Goodwood Rd",
    "iso:country":"AU",
    "sg:address":"9 Goodwood Rd",
    "sg:city":"Wayville",
    "sg:classifiers":[
        {
            "category":"Food & Beverages",
            "subcategory":"Fruits & Vegetables",
            "type":"Retail Goods"
        }
    ],
    "sg:phone":"+61 8 8299 9399",
    "sg:postcode":"5034",
    "sg:province":"SA",
    "sg:tags":[
        "consultant",
        "catering"
    ],
    "wof:name":"Business Bakery The",
    "wof:placetype":"venue"
},
  "geometry": {"coordinates":[138.58920288100001,-34.9429779053],"type":"Point"}
}