{
  "type": "Feature",
  "properties": {
    "addr:full":"35 Franklin St Moorabbin VIC 3189",
    "addr:housenumber":"35",
    "addr:postcode":"3189",
    "addr:street":"Franklin St",
    "iso:country":"AU",
    "sg:address":"35 Franklin St",
    "sg:city":"Moorabbin",
    "sg:classifiers":[
        {
            "category":"Professional",
            "subcategory":"Engineering",
            "type":"Services"
        }
    ],
    "sg:phone":"+61 3 9553 5327",
    "sg:postcode":"3189",
    "sg:province":"VIC",
    "sg:tags":[
        "consulting",
        "engineer"
    ],
    "wof:name":"Jolade Pty Ltd",
    "wof:placetype":"venue"
},
  "geometry": {"coordinates":[145.053588867,-37.9373207092],"type":"Point"}
}