{
  "type": "Feature",
  "properties": {
    "iso:country":"AU",
    "sg:address":"431 Riversdale Rd",
    "sg:city":"Hawthorn",
    "sg:classifiers":[
        {
            "category":"Shopping",
            "subcategory":"Computers & Home Electronics",
            "type":"Retail Goods"
        }
    ],
    "sg:phone":"+61 3 9813 1711",
    "sg:postcode":"3122",
    "sg:province":"VIC",
    "sg:tags":[
        "hardware",
        "equipment"
    ],
    "wof:name":"Syber Business Applications",
    "wof:placetype":"venue"
},
  "geometry": {"coordinates":[145.02752685600001,-37.8286933899],"type":"Point"}
}