{
  "type": "Feature",
  "properties": {
    "addr:full":"Leslie St Maitland NSW 2320",
    "addr:postcode":"2320",
    "addr:street":"Leslie St",
    "iso:country":"AU",
    "sg:address":"Leslie St",
    "sg:city":"Maitland",
    "sg:classifiers":[
        {
            "category":"Education",
            "subcategory":"Music School",
            "type":"Public Place"
        }
    ],
    "sg:phone":"+61 2 4926 1111",
    "sg:postcode":"2320",
    "sg:province":"NSW",
    "sg:tags":[
        "teacher"
    ],
    "wof:name":"Armstrong Sue B.Mus",
    "wof:placetype":"venue"
},
  "geometry": {"coordinates":[151.56364440900001,-32.7283859253],"type":"Point"}
}