{
  "type": "Feature",
  "properties": {
    "iso:country":"AU",
    "sg:address":"21 Truck City Drv",
    "sg:city":"Campbellfield",
    "sg:classifiers":[
        {
            "category":"Park",
            "subcategory":"County",
            "type":"Public Place"
        }
    ],
    "sg:phone":"+61 3 9303 7700",
    "sg:postcode":"3061",
    "sg:province":"VIC",
    "sg:tags":[
        "box",
        "fibre",
        "carton",
        "secondhand",
        "cardboard"
    ],
    "wof:name":"Complete Pizza Packaging Pty Ltd",
    "wof:placetype":"venue"
},
  "geometry": {"coordinates":[144.947357178,-37.6478309631],"type":"Point"}
}