{
  "type": "Feature",
  "properties": {
    "iso:country":"AU",
    "sg:address":"77 Victoria St",
    "sg:city":"Taree",
    "sg:classifiers":[
        {
            "category":"Travel",
            "subcategory":"Hotels & Motels",
            "type":"Entertainment"
        }
    ],
    "sg:phone":"+61 2 6552 3966",
    "sg:postcode":"2430",
    "sg:province":"NSW",
    "wof:name":"In Town Motor Inn",
    "wof:placetype":"venue"
},
  "geometry": {"coordinates":[152.464325,-31.911289],"type":"Point"}
}