{
  "type": "Feature",
  "properties": {
    "addr:full":"Factory 8 385 McClelland Drv Langwarrin VIC 3910",
    "addr:housenumber":"385",
    "addr:postcode":"3910",
    "addr:street":"Mcclelland Drv",
    "iso:country":"AU",
    "sg:address":"Factory 8 385 McClelland Drv",
    "sg:city":"Langwarrin",
    "sg:classifiers":[
        {
            "category":"Building & Trades",
            "subcategory":"Construction",
            "type":"Services"
        }
    ],
    "sg:phone":"+61 3 9789 3888",
    "sg:postcode":"3910",
    "sg:province":"VIC",
    "sg:tags":[
        "contractor"
    ],
    "wof:name":"Hasteen Builders",
    "wof:placetype":"venue"
},
  "geometry": {"coordinates":[145.168212891,-38.168346405],"type":"Point"}
}