{
  "type": "Feature",
  "properties": {
    "addr:full":"U41/7- 9 Production Rd Taren Point NSW 2229",
    "addr:housenumber":"9",
    "addr:postcode":"2229",
    "addr:street":"/ 7;Production Rd",
    "iso:country":"AU",
    "sg:address":"U41/7- 9 Production Rd",
    "sg:city":"Taren Point",
    "sg:classifiers":[
        {
            "category":"Shopping",
            "subcategory":"Party Supplies",
            "type":"Retail Goods"
        }
    ],
    "sg:phone":"+61 2 9525 0149",
    "sg:postcode":"2229",
    "sg:province":"NSW",
    "wof:name":"Production Road Party Goods",
    "wof:placetype":"venue"
},
  "geometry": {"coordinates":[151.12620544399999,-34.022480011],"type":"Point"}
}