{
  "type": "Feature",
  "properties": {
    "addr:full":"Lot 262/ Deviation Rd Naracoorte SA 5271",
    "addr:postcode":"5271",
    "addr:street":"Deviation Rd",
    "iso:country":"AU",
    "sg:address":"Lot 262/ Deviation Rd",
    "sg:city":"Naracoorte",
    "sg:classifiers":[
        {
            "category":"Building & Trades",
            "subcategory":"Cleaning & Sanitation",
            "type":"Services"
        }
    ],
    "sg:phone":"+61 8 8762 4991",
    "sg:postcode":"5271",
    "sg:province":"SA",
    "sg:tags":[
        "abrasive",
        "blasting"
    ],
    "wof:name":"Sherif & Kerrys Soda Blast",
    "wof:placetype":"venue"
},
  "geometry": {"coordinates":[140.73443603499999,-36.9632415771],"type":"Point"}
}