{
  "type": "Feature",
  "properties": {
    "addr:full":"21 Silica Rd Wattle Grove WA 6107",
    "addr:housenumber":"21",
    "addr:postcode":"6107",
    "addr:street":"Silica Rd",
    "iso:country":"AU",
    "sg:address":"21 Silica Rd",
    "sg:city":"Wattle Grove",
    "sg:classifiers":[
        {
            "category":"Arena",
            "subcategory":"Indoor Arena",
            "type":"Entertainment"
        }
    ],
    "sg:phone":"+61 8 9359 1316",
    "sg:postcode":"6107",
    "sg:province":"WA",
    "sg:tags":[
        "modelmakers"
    ],
    "wof:name":"J & K Arch Model Designers",
    "wof:placetype":"venue"
},
  "geometry": {"coordinates":[115.98422241199999,-31.9923324585],"type":"Point"}
}