{
  "type": "Feature",
  "properties": {
    "addr:full":"42 Barker St Casino NSW 2470",
    "addr:housenumber":"42",
    "addr:postcode":"2470",
    "addr:street":"Barker St",
    "iso:country":"AU",
    "sg:address":"42 Barker St",
    "sg:city":"Casino",
    "sg:classifiers":[
        {
            "category":"Professional",
            "subcategory":"Employment Agencies",
            "type":"Services"
        }
    ],
    "sg:phone":"+61 2 6662 3239",
    "sg:postcode":"2470",
    "sg:province":"NSW",
    "sg:tags":[
        "occupational",
        "therapist"
    ],
    "wof:name":"Mal's Myotherapy Clinic",
    "wof:placetype":"venue"
},
  "geometry": {"coordinates":[153.04019165,-28.8637733459],"type":"Point"}
}