{
  "type": "Feature",
  "properties": {
    "addr:full":"86b Albert St Creswick VIC 3363",
    "addr:housenumber":"86b",
    "addr:postcode":"3363",
    "addr:street":"Albert St",
    "iso:country":"AU",
    "sg:address":"86b Albert St",
    "sg:city":"Creswick",
    "sg:classifiers":[
        {
            "category":"Wholesale",
            "subcategory":"Non-durable Goods",
            "type":"Manufacturing & Wholesale Goods"
        }
    ],
    "sg:phone":"+61 3 5345 1120",
    "sg:postcode":"3363",
    "sg:province":"VIC",
    "sg:tags":[
        "wholesaler",
        "craft",
        "mfrs"
    ],
    "wof:name":"Cascade House Australia",
    "wof:placetype":"venue"
},
  "geometry": {"coordinates":[143.894454956,-37.4246330261],"type":"Point"}
}