{
  "type": "Feature",
  "properties": {
    "iso:country":"AU",
    "sg:address":"40 Holts St",
    "sg:city":"Whittlesea",
    "sg:classifiers":[
        {
            "category":"Building & Trades",
            "subcategory":"Construction",
            "type":"Services"
        }
    ],
    "sg:phone":"+61 427 506 175",
    "sg:postcode":"3757",
    "sg:province":"VIC",
    "sg:tags":[
        "fencing",
        "contractor"
    ],
    "wof:name":"Whittlesea Contracting",
    "wof:placetype":"venue"
},
  "geometry": {"coordinates":[145.095016,-37.447617],"type":"Point"}
}