{
  "type": "Feature",
  "properties": {
    "addr:full":"166 Victoria St Potts Point NSW 2011",
    "addr:housenumber":"166",
    "addr:postcode":"2011",
    "addr:street":"Victoria St",
    "iso:country":"AU",
    "sg:address":"166 Victoria St",
    "sg:city":"Potts Point",
    "sg:classifiers":[
        {
            "category":"Travel",
            "subcategory":"Hotels & Motels",
            "type":"Entertainment"
        }
    ],
    "sg:phone":"+61 2 9326 9539",
    "sg:postcode":"2011",
    "sg:province":"NSW",
    "sg:tags":[
        "accommodation"
    ],
    "wof:name":"Highfield Private Hotel",
    "wof:placetype":"venue"
},
  "geometry": {"coordinates":[151.222457886,-33.8742866516],"type":"Point"}
}