{
  "type": "Feature",
  "properties": {
    "addr:full":"22 Carew St Nundah QLD 4012",
    "addr:housenumber":"22",
    "addr:postcode":"4012",
    "addr:street":"Carew St",
    "iso:country":"AU",
    "sg:address":"22 Carew St",
    "sg:city":"Nundah",
    "sg:classifiers":[
        {
            "category":"Professional",
            "subcategory":"Art Services",
            "type":"Services"
        }
    ],
    "sg:phone":"+61 412 881 524",
    "sg:postcode":"4012",
    "sg:province":"QLD",
    "sg:tags":[
        "decorator",
        "painter"
    ],
    "wof:name":"McNee Painting Services",
    "wof:placetype":"venue"
},
  "geometry": {"coordinates":[153.05340576200001,-27.4047832489],"type":"Point"}
}