{
  "type": "Feature",
  "properties": {
    "addr:full":"100 Byfield St Northam WA 6401",
    "addr:housenumber":"100",
    "addr:postcode":"6401",
    "addr:street":"Byfield St",
    "iso:country":"AU",
    "sg:address":"100 Byfield St",
    "sg:city":"Northam",
    "sg:classifiers":[
        {
            "category":"Industrial Area",
            "type":"Public Place"
        }
    ],
    "sg:phone":"+61 8 9622 1333",
    "sg:postcode":"6401",
    "sg:province":"WA",
    "sg:tags":[
        "rural",
        "shed"
    ],
    "wof:name":"Dempster Steel",
    "wof:placetype":"venue"
},
  "geometry": {"coordinates":[116.68115997300001,-31.6564025879],"type":"Point"}
}