{
  "type": "Feature",
  "properties": {
    "addr:full":"8 Melaleuca St Caboolture QLD 4510",
    "addr:housenumber":"8",
    "addr:postcode":"4510",
    "addr:street":"Melaleuca St",
    "iso:country":"AU",
    "sg:address":"8 Melaleuca St",
    "sg:city":"Caboolture",
    "sg:classifiers":[
        {
            "category":"Arts & Performance",
            "subcategory":"Music",
            "type":"Entertainment"
        }
    ],
    "sg:phone":"+61 1800 100 606",
    "sg:postcode":"4510",
    "sg:province":"QLD",
    "sg:tags":[
        "mobile",
        "jockey",
        "disc"
    ],
    "wof:name":"Mobydisc",
    "wof:placetype":"venue"
},
  "geometry": {"coordinates":[152.928909,-27.074667],"type":"Point"}
}