{
  "type": "Feature",
  "properties": {
    "addr:full":"Benwarden Rd Cobains VIC 3851",
    "addr:postcode":"3851",
    "addr:street":"Benwarden Rd",
    "iso:country":"AU",
    "sg:address":"Benwarden Rd",
    "sg:city":"Cobains",
    "sg:classifiers":[
        {
            "category":"Farming",
            "subcategory":"Farm",
            "type":"Manufacturing & Wholesale Goods"
        }
    ],
    "sg:phone":"+61 3 5149 8373",
    "sg:postcode":"3851",
    "sg:province":"VIC",
    "sg:tags":[
        "farmer"
    ],
    "wof:name":"French A D",
    "wof:placetype":"venue"
},
  "geometry": {"coordinates":[147.115600586,-38.0730514526],"type":"Point"}
}