{
  "type": "Feature",
  "properties": {
    "iso:country":"AU",
    "sg:address":"71 Foothills Rd",
    "sg:city":"Balgownie",
    "sg:classifiers":[
        {
            "category":"Personal",
            "subcategory":"Nail Salon",
            "type":"Services"
        }
    ],
    "sg:phone":"+61 2 4284 9999",
    "sg:postcode":"2519",
    "sg:province":"NSW",
    "sg:tags":[
        "artificial"
    ],
    "wof:name":"Allure Hair & Beauty Studio",
    "wof:placetype":"venue"
},
  "geometry": {"coordinates":[150.89352400000001,-34.391586],"type":"Point"}
}