{
  "type": "Feature",
  "properties": {
    "addr:full":"12 Berwen St Chelsea VIC 3196",
    "addr:housenumber":"12",
    "addr:postcode":"3196",
    "addr:street":"Berwen St",
    "iso:country":"AU",
    "sg:address":"12 Berwen St",
    "sg:city":"Chelsea",
    "sg:classifiers":[
        {
            "category":"Building & Trades",
            "subcategory":"Cleaning & Sanitation",
            "type":"Services"
        }
    ],
    "sg:phone":"+61 3 9772 5274",
    "sg:postcode":"3196",
    "sg:province":"VIC",
    "sg:tags":[
        "chemical",
        "pressure",
        "steam",
        "contractor"
    ],
    "wof:name":"Jetman Cleaning Services",
    "wof:placetype":"venue"
},
  "geometry": {"coordinates":[145.11224365199999,-38.0481643677],"type":"Point"}
}