{
  "type": "Feature",
  "properties": {
    "iso:country":"AU",
    "sg:address":"204 Luskintyre Rd",
    "sg:city":"Luskintyre",
    "sg:classifiers":[
        {
            "category":"Building & Trades",
            "subcategory":"Plumbing",
            "type":"Services"
        }
    ],
    "sg:phone":"+61 2 4930 6277",
    "sg:postcode":"2321",
    "sg:province":"NSW",
    "sg:tags":[
        "pump",
        "repairer"
    ],
    "wof:name":"Maitland Rural Repairs",
    "wof:placetype":"venue"
},
  "geometry": {"coordinates":[151.427276611,-32.6836242676],"type":"Point"}
}