{
  "type": "Feature",
  "properties": {
    "addr:full":"Lot 6/ 7 Hexham Pl Wetherill Park NSW 2164",
    "addr:housenumber":"6 / 7",
    "addr:postcode":"2164",
    "addr:street":"Pl",
    "iso:country":"AU",
    "sg:address":"Lot 6/ 7 Hexham Pl",
    "sg:city":"Wetherill Park",
    "sg:classifiers":[
        {
            "category":"Building & Trades",
            "subcategory":"Construction",
            "type":"Services"
        }
    ],
    "sg:phone":"+61 2 9756 1077",
    "sg:postcode":"2164",
    "sg:province":"NSW",
    "sg:tags":[
        "spouting",
        "guttering"
    ],
    "wof:name":"Stoddart Metal Building Products",
    "wof:placetype":"venue"
},
  "geometry": {"coordinates":[150.88900756800001,-33.8394393921],"type":"Point"}
}