{
  "type": "Feature",
  "properties": {
    "addr:full":"31 Morwick St Strathfield NSW 2135",
    "addr:housenumber":"31",
    "addr:postcode":"2135",
    "addr:street":"Morwick St",
    "iso:country":"AU",
    "sg:address":"31 Morwick St",
    "sg:city":"Strathfield",
    "sg:classifiers":[
        {
            "category":"Autos & Motor Vehicles",
            "subcategory":"Boat Sales",
            "type":"Retail Goods"
        }
    ],
    "sg:phone":"+61 2 9744 9065",
    "sg:postcode":"2135",
    "sg:province":"NSW",
    "sg:tags":[
        "equipment",
        "yacht"
    ],
    "wof:name":"Cridland & Allen Engineering",
    "wof:placetype":"venue"
},
  "geometry": {"coordinates":[151.09426879899999,-33.8746490479],"type":"Point"}
}