{
  "type": "Feature",
  "properties": {
    "addr:full":"7 Dobney Ave Wagga Wagga NSW 2650",
    "addr:housenumber":"7",
    "addr:postcode":"2650",
    "addr:street":"Dobney Ave",
    "iso:country":"AU",
    "sg:address":"7 Dobney Ave",
    "sg:city":"Wagga Wagga",
    "sg:classifiers":[
        {
            "category":"Retail",
            "subcategory":"Repair Shop",
            "type":"Services"
        }
    ],
    "sg:phone":"+61 2 6925 9455",
    "sg:postcode":"2650",
    "sg:province":"NSW",
    "sg:tags":[
        "upholsterer"
    ],
    "wof:name":"DJ And CM Huthwaite Upholstery",
    "wof:placetype":"venue"
},
  "geometry": {"coordinates":[147.34893798799999,-35.1165428162],"type":"Point"}
}