{
  "type": "Feature",
  "properties": {
    "addr:full":"Unit 8 63 Annerley Rd Woolloongabba QLD 4102",
    "addr:housenumber":"63",
    "addr:postcode":"4102",
    "addr:street":"Annerley Rd",
    "iso:country":"AU",
    "sg:address":"Unit 8 63 Annerley Rd",
    "sg:city":"Woolloongabba",
    "sg:classifiers":[
        {
            "category":"Professional",
            "subcategory":"Business Services",
            "type":"Services"
        }
    ],
    "sg:phone":"+61 7 3844 3955",
    "sg:postcode":"4102",
    "sg:province":"QLD",
    "sg:tags":[
        "drafting"
    ],
    "wof:name":"Steelcad Drafting Pty Ltd",
    "wof:placetype":"venue"
},
  "geometry": {"coordinates":[153.02767944300001,-27.4890213013],"type":"Point"}
}