{
  "type": "Feature",
  "properties": {
    "addr:full":"Home & Building Display Centre, Pacific Hwy Chatswood Hills QLD 4127",
    "addr:postcode":"4127",
    "addr:street":"Pacific Hwy",
    "iso:country":"AU",
    "sg:address":"Home & Building Display Centre, Pacific Hwy",
    "sg:city":"Chatswood Hills",
    "sg:classifiers":[
        {
            "category":"Home & Garden",
            "subcategory":"Building Materials",
            "type":"Retail Goods"
        }
    ],
    "sg:phone":"+61 7 3841 2175",
    "sg:postcode":"4127",
    "sg:province":"QLD",
    "sg:tags":[
        "fitting",
        "door"
    ],
    "wof:name":"Shoji Screens",
    "wof:placetype":"venue"
},
  "geometry": {"coordinates":[153.13296508799999,-27.6325759888],"type":"Point"}
}