{
  "type": "Feature",
  "properties": {
    "addr:full":"429 Stafford Rd Stafford QLD 4053",
    "addr:housenumber":"429",
    "addr:postcode":"4053",
    "addr:street":"Stafford Rd",
    "iso:country":"AU",
    "sg:address":"429 Stafford Rd",
    "sg:city":"Stafford",
    "sg:classifiers":[
        {
            "category":"Personal",
            "subcategory":"Tanning Parlor",
            "type":"Services"
        }
    ],
    "sg:phone":"+61 7 3356 6888",
    "sg:postcode":"4053",
    "sg:province":"QLD",
    "sg:tags":[
        "solarium"
    ],
    "wof:name":"Stafford Solariums",
    "wof:placetype":"venue"
},
  "geometry": {"coordinates":[153.01104736299999,-27.4095058441],"type":"Point"}
}