{
  "type": "Feature",
  "properties": {
    "addr:full":"4 Seton Rd Moorebank NSW 2170",
    "addr:housenumber":"4",
    "addr:postcode":"2170",
    "addr:street":"Seton Rd",
    "iso:country":"AU",
    "sg:address":"4 Seton Rd",
    "sg:city":"Moorebank",
    "sg:classifiers":[
        {
            "category":"Professional",
            "type":"Services"
        }
    ],
    "sg:phone":"+61 2 9601 2120",
    "sg:postcode":"2170",
    "sg:province":"NSW",
    "sg:tags":[
        "transport"
    ],
    "wof:name":"Perth Road Express",
    "wof:placetype":"venue"
},
  "geometry": {"coordinates":[150.94097900400001,-33.9332809448],"type":"Point"}
}