{
  "type": "Feature",
  "properties": {
    "addr:full":"955 Brunswick St New Farm QLD 4005",
    "addr:housenumber":"955",
    "addr:postcode":"4005",
    "addr:street":"Brunswick St",
    "iso:country":"AU",
    "sg:address":"955 Brunswick St",
    "sg:city":"New Farm",
    "sg:classifiers":[
        {
            "category":"Social Services",
            "subcategory":"Child Care",
            "type":"Services"
        }
    ],
    "sg:phone":"+61 7 3358 4595",
    "sg:postcode":"4005",
    "sg:province":"QLD",
    "wof:name":"Jack & Jill Child Care Centre",
    "wof:placetype":"venue"
},
  "geometry": {"coordinates":[153.04887390100001,-27.4693641663],"type":"Point"}
}