{
  "type": "Feature",
  "properties": {
    "addr:full":"170 Scott St Cairns QLD 4870",
    "addr:housenumber":"170",
    "addr:postcode":"4870",
    "addr:street":"Scott St",
    "iso:country":"AU",
    "sg:address":"170 Scott St",
    "sg:city":"Cairns",
    "sg:classifiers":[
        {
            "category":"Insurance",
            "subcategory":"Hazard Insurance",
            "type":"Services"
        }
    ],
    "sg:phone":"+61 7 4051 4922",
    "sg:postcode":"4870",
    "sg:province":"QLD",
    "sg:tags":[
        "fire",
        "accident",
        "marine"
    ],
    "wof:name":"Boat Scene",
    "wof:placetype":"venue"
},
  "geometry": {"coordinates":[145.75120544399999,-16.9408683777],"type":"Point"}
}