{
  "type": "Feature",
  "properties": {
    "addr:full":"234 Crown St Wollongong NSW 2500",
    "addr:housenumber":"234",
    "addr:postcode":"2500",
    "addr:street":"Crown St",
    "iso:country":"AU",
    "sg:address":"234 Crown St",
    "sg:city":"Wollongong",
    "sg:classifiers":[
        {
            "category":"Shopping",
            "subcategory":"Mobile Phones",
            "type":"Retail Goods"
        }
    ],
    "sg:phone":"+61 2 4227 6343",
    "sg:postcode":"2500",
    "sg:province":"NSW",
    "sg:tags":[
        "telephone",
        "accessory"
    ],
    "wof:name":"Mobile Gallery",
    "wof:placetype":"venue"
},
  "geometry": {"coordinates":[150.89198300000001,-34.424934],"type":"Point"}
}