{
  "type": "Feature",
  "properties": {
    "addr:full":"2/ 14 Groom St Gordon Park QLD 4031",
    "addr:housenumber":"/ 14",
    "addr:postcode":"4031",
    "addr:street":"Groom St",
    "iso:country":"AU",
    "sg:address":"2/ 14 Groom St",
    "sg:city":"Gordon Park",
    "sg:classifiers":[
        {
            "category":"Utilities",
            "subcategory":"Telephone",
            "type":"Services"
        }
    ],
    "sg:phone":"+61 7 3857 1399",
    "sg:postcode":"4031",
    "sg:province":"QLD",
    "sg:tags":[
        "installation",
        "system",
        "maintenance"
    ],
    "wof:name":"Bennick Communications Pty Ltd",
    "wof:placetype":"venue"
},
  "geometry": {"coordinates":[153.02894599999999,-27.420252],"type":"Point"}
}