{
  "type": "Feature",
  "properties": {
    "addr:full":"166 Crooked Rd Romsey VIC 3434",
    "addr:housenumber":"166",
    "addr:postcode":"3434",
    "addr:street":"Crooked Rd",
    "iso:country":"AU",
    "sg:address":"166 Crooked Rd",
    "sg:city":"Romsey",
    "sg:classifiers":[
        {
            "category":"Wholesale",
            "subcategory":"Plants",
            "type":"Manufacturing & Wholesale Goods"
        }
    ],
    "sg:phone":"+61 3 5429 5206",
    "sg:postcode":"3434",
    "sg:province":"VIC",
    "sg:tags":[
        "florist"
    ],
    "wof:name":"Romsey Roses",
    "wof:placetype":"venue"
},
  "geometry": {"coordinates":[144.72267150900001,-37.3177528381],"type":"Point"}
}