{
  "type": "Feature",
  "properties": {
    "iso:country":"AU",
    "sg:address":"Koroit Ave",
    "sg:city":"Broadmeadows",
    "sg:classifiers":[
        {
            "category":"Education",
            "subcategory":"School",
            "type":"Public Place"
        }
    ],
    "sg:phone":"+61 3 9309 3477",
    "sg:postcode":"3047",
    "sg:province":"VIC",
    "sg:tags":[
        "state",
        "except",
        "nsw"
    ],
    "wof:name":"Hume Valley School",
    "wof:placetype":"venue"
},
  "geometry": {"coordinates":[144.926239014,-37.6721115112],"type":"Point"}
}