{
  "type": "Feature",
  "properties": {
    "addr:full":"107 View St Bendigo VIC 3550",
    "addr:housenumber":"107",
    "addr:postcode":"3550",
    "addr:street":"View St",
    "iso:country":"AU",
    "sg:address":"107 View St",
    "sg:city":"Bendigo",
    "sg:classifiers":[
        {
            "category":"Shopping",
            "subcategory":"Antiques",
            "type":"Retail Goods"
        }
    ],
    "sg:phone":"+61 3 5443 3192",
    "sg:postcode":"3550",
    "sg:province":"VIC",
    "wof:name":"Heather Bell Antiques",
    "wof:placetype":"venue"
},
  "geometry": {"coordinates":[144.27619934099999,-36.7577552795],"type":"Point"}
}