{
  "type": "Feature",
  "properties": {
    "iso:country":"AU",
    "sg:address":"140- 142 Langridge St",
    "sg:city":"Collingwood",
    "sg:classifiers":[
        {
            "category":"Shopping",
            "subcategory":"Clothing, Apparel, & Fashions",
            "type":"Retail Goods"
        }
    ],
    "sg:phone":"+61 3 9417 7630",
    "sg:postcode":"3066",
    "sg:province":"VIC",
    "sg:tags":[
        "wholesaler",
        "children's",
        "mfrs",
        "wear"
    ],
    "wof:name":"N.F. Eye",
    "wof:placetype":"venue"
},
  "geometry": {"coordinates":[144.98980712900001,-37.8068161011],"type":"Point"}
}