{
  "type": "Feature",
  "properties": {
    "iso:country":"AU",
    "sg:address":"Shed 9/ 84 Ingleston Rd",
    "sg:city":"Wakerley",
    "sg:classifiers":[
        {
            "category":"Retail",
            "subcategory":"Storage",
            "type":"Services"
        }
    ],
    "sg:phone":"+61 7 3890 7011",
    "sg:postcode":"4154",
    "sg:province":"QLD",
    "sg:tags":[
        "removal",
        "furniture"
    ],
    "wof:name":"A AAABACUS Giffen Furniture Removals",
    "wof:placetype":"venue"
},
  "geometry": {"coordinates":[153.142669678,-27.4816169739],"type":"Point"}
}