{
  "type": "Feature",
  "properties": {
    "iso:country":"AU",
    "sg:address":"2/ 129 Grigor St",
    "sg:city":"Caloundra",
    "sg:classifiers":[
        {
            "category":"Retail",
            "subcategory":"Repair Shop",
            "type":"Services"
        }
    ],
    "sg:phone":"+61 7 5491 6166",
    "sg:postcode":"4551",
    "sg:province":"QLD",
    "sg:tags":[
        "stove",
        "part",
        "range"
    ],
    "wof:name":"Nicklin Electrical",
    "wof:placetype":"venue"
},
  "geometry": {"coordinates":[153.13328552199999,-26.790933609],"type":"Point"}
}