{
  "type": "Feature",
  "properties": {
    "addr:full":"PO Box 63w Fairfield West NSW 2165",
    "addr:postcode":"2165",
    "iso:country":"AU",
    "sg:address":"PO Box 63w",
    "sg:city":"Fairfield West",
    "sg:classifiers":[
        {
            "category":"Banks & Credit Unions",
            "subcategory":"Financial Services",
            "type":"Services"
        }
    ],
    "sg:phone":"+61 400 702 320",
    "sg:postcode":"2165",
    "sg:province":"NSW",
    "sg:tags":[
        "assistance",
        "roadside"
    ],
    "wof:name":"Matthew's Towing",
    "wof:placetype":"venue"
},
  "geometry": {"coordinates":[150.92300415,-33.8691596985],"type":"Point"}
}