{
  "type": "Feature",
  "properties": {
    "addr:full":"5 Rudge St Dianella WA 6059",
    "addr:housenumber":"5",
    "addr:postcode":"6059",
    "addr:street":"Rudge St",
    "iso:country":"AU",
    "sg:address":"5 Rudge St",
    "sg:city":"Dianella",
    "sg:classifiers":[
        {
            "category":"Utilities",
            "type":"Services"
        }
    ],
    "sg:phone":"+61 8 9276 6917",
    "sg:postcode":"6059",
    "sg:province":"WA",
    "sg:tags":[
        "refrigeration",
        "industrial",
        "commercial",
        "retail"
    ],
    "wof:name":"Anfreeze Industrial Refrigeration Pty Ltd",
    "wof:placetype":"venue"
},
  "geometry": {"coordinates":[115.798522949,-32.0490570068],"type":"Point"}
}