{
  "type": "Feature",
  "properties": {
    "addr:full":"83 Jetty Rd Rosebud VIC 3939",
    "addr:housenumber":"83",
    "addr:postcode":"3939",
    "addr:street":"Jetty Rd",
    "iso:country":"AU",
    "sg:address":"83 Jetty Rd",
    "sg:city":"Rosebud",
    "sg:classifiers":[
        {
            "category":"Professional",
            "subcategory":"Art Services",
            "type":"Services"
        }
    ],
    "sg:phone":"+61 419 666 580",
    "sg:postcode":"3939",
    "sg:province":"VIC",
    "sg:tags":[
        "decorator",
        "painter"
    ],
    "wof:name":"Tony Santilli",
    "wof:placetype":"venue"
},
  "geometry": {"coordinates":[144.90916442899999,-38.3626441956],"type":"Point"}
}