{
  "type": "Feature",
  "properties": {
    "addr:full":"Lot 2 Cnr Winterfold Rd & Carrington St Hamilton Hill WA 6163",
    "addr:housenumber":"cnr",
    "addr:postcode":"6163",
    "addr:street":"Winterfold Rd & Carrington St",
    "iso:country":"AU",
    "sg:address":"Lot 2 Cnr Winterfold Rd & Carrington St",
    "sg:city":"Hamilton Hill",
    "sg:classifiers":[
        {
            "category":"Autos & Motor Vehicles",
            "subcategory":"Fuel & Gas Station",
            "type":"Retail Goods"
        }
    ],
    "sg:phone":"+61 8 9314 7441",
    "sg:postcode":"6163",
    "sg:province":"WA",
    "wof:name":"Quick Stop Fuel",
    "wof:placetype":"venue"
},
  "geometry": {"coordinates":[115.78064000000001,-32.074772],"type":"Point"}
}