{
  "type": "Feature",
  "properties": {
    "addr:full":"7 Kathmaur Ave Carole Park QLD 4300",
    "addr:housenumber":"7",
    "addr:postcode":"4300",
    "addr:street":"Kathmaur Ave",
    "iso:country":"AU",
    "sg:address":"7 Kathmaur Ave",
    "sg:city":"Carole Park",
    "sg:classifiers":[
        {
            "category":"Building & Trades",
            "subcategory":"Plumbing",
            "type":"Services"
        }
    ],
    "sg:phone":"+61 7 3271 2469",
    "sg:postcode":"4300",
    "sg:province":"QLD",
    "sg:tags":[
        "plumber",
        "gasfitters"
    ],
    "wof:name":"Marshall J G & V M E",
    "wof:placetype":"venue"
},
  "geometry": {"coordinates":[152.935379028,-27.6099033356],"type":"Point"}
}