{
  "type": "Feature",
  "properties": {
    "addr:full":"Suite 5, 9- 11 Montford Crs Lyneham North ACT 2602",
    "addr:housenumber":"9 11",
    "addr:postcode":"2602",
    "addr:street":"Montford Crs",
    "iso:country":"AU",
    "sg:address":"Suite 5, 9- 11 Montford Crs",
    "sg:city":"Lyneham North",
    "sg:classifiers":[
        {
            "category":"Health Services",
            "subcategory":"Chiropractor",
            "type":"Services"
        }
    ],
    "sg:phone":"+61 2 6257 6055",
    "sg:postcode":"2602",
    "sg:province":"ACT",
    "wof:name":"Adjust for Health",
    "wof:placetype":"venue"
},
  "geometry": {"coordinates":[149.135162353,-35.249370575],"type":"Point"}
}