{
  "type": "Feature",
  "properties": {
    "iso:country":"AU",
    "sg:address":"31 Victoria St",
    "sg:city":"Prospect",
    "sg:classifiers":[
        {
            "category":"Personal",
            "subcategory":"Massage",
            "type":"Services"
        }
    ],
    "sg:phone":"+61 8 8342 1424",
    "sg:postcode":"5082",
    "sg:province":"SA",
    "sg:tags":[
        "therapy"
    ],
    "wof:name":"Womens Health Practice",
    "wof:placetype":"venue"
},
  "geometry": {"coordinates":[138.590744019,-34.8805084229],"type":"Point"}
}