{
  "type": "Feature",
  "properties": {
    "addr:full":"Cnr Pender Pl & Elgin St Maitland NSW 2320",
    "addr:postcode":"2320",
    "addr:street":"Cnr Pender Pl & Elgin St",
    "iso:country":"AU",
    "sg:address":"Cnr Pender Pl & Elgin St",
    "sg:city":"Maitland",
    "sg:classifiers":[
        {
            "category":"Food & Beverages",
            "subcategory":"Liquor & Beverages",
            "type":"Retail Goods"
        }
    ],
    "sg:phone":"+61 2 4933 8099",
    "sg:postcode":"2320",
    "sg:province":"NSW",
    "sg:tags":[
        "store"
    ],
    "wof:name":"Macs Liquor",
    "wof:placetype":"venue"
},
  "geometry": {"coordinates":[151.5546875,-32.7319297791],"type":"Point"}
}