{
  "type": "Feature",
  "properties": {
    "addr:full":"44 Peninsula Ave Rye VIC 3941",
    "addr:housenumber":"44",
    "addr:postcode":"3941",
    "addr:street":"Peninsula Ave",
    "iso:country":"AU",
    "sg:address":"44 Peninsula Ave",
    "sg:city":"Rye",
    "sg:classifiers":[
        {
            "category":"Retail",
            "subcategory":"Auto Repair",
            "type":"Services"
        }
    ],
    "sg:phone":"+61 3 5985 2022",
    "sg:postcode":"3941",
    "sg:province":"VIC",
    "sg:tags":[
        "beater",
        "painter",
        "panel"
    ],
    "wof:name":"Peninsula Panels",
    "wof:placetype":"venue"
},
  "geometry": {"coordinates":[144.80642700199999,-38.3761787415],"type":"Point"}
}