{
  "type": "Feature",
  "properties": {
    "addr:full":"U 3/ 11 Packard Ave Castle Hill NSW 2154",
    "addr:housenumber":"11",
    "addr:postcode":"2154",
    "addr:street":"Packard Ave",
    "iso:country":"AU",
    "sg:address":"U 3/ 11 Packard Ave",
    "sg:city":"Castle Hill",
    "sg:classifiers":[
        {
            "category":"Government",
            "subcategory":"Fire Station",
            "type":"Public Place"
        }
    ],
    "sg:phone":"+61 2 9680 1725",
    "sg:postcode":"2154",
    "sg:province":"NSW",
    "sg:tags":[
        "equipment",
        "protection",
        "consultant"
    ],
    "wof:name":"Blazemaster Fire Protection",
    "wof:placetype":"venue"
},
  "geometry": {"coordinates":[150.98312377900001,-33.7346534729],"type":"Point"}
}