{
  "type": "Feature",
  "properties": {
    "addr:full":"431 Highbury Rd Burwood East VIC 3151",
    "addr:housenumber":"431",
    "addr:postcode":"3151",
    "addr:street":"Highbury Rd",
    "iso:country":"AU",
    "sg:address":"431 Highbury Rd",
    "sg:city":"Burwood East",
    "sg:classifiers":[
        {
            "category":"Fast Food",
            "type":"Food & Drink"
        }
    ],
    "sg:phone":"+61 3 9887 9566",
    "sg:postcode":"3151",
    "sg:province":"VIC",
    "sg:tags":[
        "away",
        "take"
    ],
    "wof:name":"Totino's Pizza",
    "wof:placetype":"venue"
},
  "geometry": {"coordinates":[145.131713867,-37.8574371338],"type":"Point"}
}