{
  "type": "Feature",
  "properties": {
    "iso:country":"AU",
    "sg:address":"8 Jennings Crt",
    "sg:city":"Rosebud",
    "sg:classifiers":[
        {
            "category":"Autos & Motor Vehicles",
            "subcategory":"Auto Supplies",
            "type":"Retail Goods"
        }
    ],
    "sg:phone":"+61 3 5981 2669",
    "sg:postcode":"3939",
    "sg:province":"VIC",
    "sg:tags":[
        "part",
        "cycles",
        "accessory"
    ],
    "wof:name":"Advanced Motorcycle Repairs",
    "wof:placetype":"venue"
},
  "geometry": {"coordinates":[144.883087158,-38.3800697327],"type":"Point"}
}