{
  "type": "Feature",
  "properties": {
    "addr:full":"222 Merrylands Rd Merrylands NSW 2160",
    "addr:housenumber":"222",
    "addr:postcode":"2160",
    "addr:street":"Merrylands Rd",
    "iso:country":"AU",
    "sg:address":"222 Merrylands Rd",
    "sg:city":"Merrylands",
    "sg:classifiers":[
        {
            "category":"Banks & Credit Unions",
            "subcategory":"Bank",
            "type":"Services"
        }
    ],
    "sg:phone":"+61 13 20 32",
    "sg:postcode":"2160",
    "sg:province":"NSW",
    "wof:name":"Westpac",
    "wof:placetype":"venue"
},
  "geometry": {"coordinates":[150.98849487300001,-33.8363113403],"type":"Point"}
}