{
  "type": "Feature",
  "properties": {
    "addr:full":"46 Langford Drv Kariong NSW 2250",
    "addr:housenumber":"46",
    "addr:postcode":"2250",
    "addr:street":"Langford Drv",
    "iso:country":"AU",
    "sg:address":"46 Langford Drv",
    "sg:city":"Kariong",
    "sg:classifiers":[
        {
            "category":"Social Services",
            "subcategory":"Child Care",
            "type":"Services"
        }
    ],
    "sg:phone":"+61 2 4340 1823",
    "sg:postcode":"2250",
    "sg:province":"NSW",
    "wof:name":"Kariong Child Care Centre",
    "wof:placetype":"venue"
},
  "geometry": {"coordinates":[151.29412841800001,-33.4391326904],"type":"Point"}
}