{
  "type": "Feature",
  "properties": {
    "iso:country":"AU",
    "sg:address":"26 Zenith Ave",
    "sg:city":"Chermside",
    "sg:classifiers":[
        {
            "category":"Home & Garden",
            "subcategory":"Building Materials",
            "type":"Retail Goods"
        }
    ],
    "sg:phone":"+61 412 571 992",
    "sg:postcode":"4032",
    "sg:province":"QLD",
    "sg:tags":[
        "lawn",
        "cutting",
        "maintenance"
    ],
    "wof:name":"Allan Harris Lawn & Property Maintenance",
    "wof:placetype":"venue"
},
  "geometry": {"coordinates":[153.026489,-27.383642],"type":"Point"}
}