{
  "type": "Feature",
  "properties": {
    "addr:full":"3/ 23 Wyong Rd Tumbi Umbi NSW 2261",
    "addr:housenumber":"/ 23",
    "addr:postcode":"2261",
    "addr:street":"Wyong Rd",
    "iso:country":"AU",
    "sg:address":"3/ 23 Wyong Rd",
    "sg:city":"Tumbi Umbi",
    "sg:classifiers":[
        {
            "category":"Personal",
            "subcategory":"Beauty Salon",
            "type":"Services"
        }
    ],
    "sg:phone":"+61 2 4388 2888",
    "sg:postcode":"2261",
    "sg:province":"NSW",
    "sg:tags":[
        "hairdresser"
    ],
    "wof:name":"Shimmer Dezigns",
    "wof:placetype":"venue"
},
  "geometry": {"coordinates":[151.44769299999999,-33.362583],"type":"Point"}
}