{
  "type": "Feature",
  "properties": {
    "addr:full":"36 Andrews St Burwood VIC 3125",
    "addr:housenumber":"36",
    "addr:postcode":"3125",
    "addr:street":"Andrews St",
    "iso:country":"AU",
    "sg:address":"36 Andrews St",
    "sg:city":"Burwood",
    "sg:classifiers":[
        {
            "category":"Building & Trades",
            "subcategory":"Plumbing",
            "type":"Services"
        }
    ],
    "sg:phone":"+61 3 9808 9009",
    "sg:postcode":"3125",
    "sg:province":"VIC",
    "sg:tags":[
        "plumber",
        "gasfitters"
    ],
    "wof:name":"Kluwer Australia",
    "wof:placetype":"venue"
},
  "geometry": {"coordinates":[145.12838745100001,-37.8484992981],"type":"Point"}
}