{
  "type": "Feature",
  "properties": {
    "addr:full":"15b Gibson St Mt Pleasant WA 6153",
    "addr:housenumber":"15b",
    "addr:postcode":"6153",
    "addr:street":"Gibson St",
    "iso:country":"AU",
    "sg:address":"15b Gibson St",
    "sg:city":"Mt Pleasant",
    "sg:classifiers":[
        {
            "category":"Home & Garden",
            "subcategory":"Building Materials",
            "type":"Retail Goods"
        }
    ],
    "sg:phone":"+61 407 472 825",
    "sg:postcode":"6153",
    "sg:province":"WA",
    "sg:tags":[
        "lawn",
        "cutting",
        "maintenance"
    ],
    "wof:name":"Phoenix Lawn Mowing Service",
    "wof:placetype":"venue"
},
  "geometry": {"coordinates":[115.84478,-32.019817],"type":"Point"}
}