{
  "type": "Feature",
  "properties": {
    "iso:country":"AU",
    "sg:address":"28 Saunders Drv",
    "sg:city":"Mudgeeraba",
    "sg:classifiers":[
        {
            "category":"Building & Trades",
            "subcategory":"Construction",
            "type":"Services"
        }
    ],
    "sg:phone":"+61 411 178 884",
    "sg:postcode":"4213",
    "sg:province":"QLD",
    "sg:tags":[
        "brick",
        "paving"
    ],
    "wof:name":"In Line Pavers",
    "wof:placetype":"venue"
},
  "geometry": {"coordinates":[153.35577392600001,-28.1152229309],"type":"Point"}
}