{
  "type": "Feature",
  "properties": {
    "addr:full":"102 Norma Rd Myaree WA 6154",
    "addr:housenumber":"102",
    "addr:postcode":"6154",
    "addr:street":"Norma Rd",
    "iso:country":"AU",
    "sg:address":"102 Norma Rd",
    "sg:city":"Myaree",
    "sg:classifiers":[
        {
            "category":"Home & Garden",
            "subcategory":"Carpets & Floor Coverings",
            "type":"Retail Goods"
        }
    ],
    "sg:phone":"+61 8 9330 3210",
    "sg:postcode":"6154",
    "sg:province":"WA",
    "wof:name":"All Natural Floor Coverings",
    "wof:placetype":"venue"
},
  "geometry": {"coordinates":[115.82215100000001,-32.043125],"type":"Point"}
}