{
  "type": "Feature",
  "properties": {
    "iso:country":"AU",
    "sg:address":"102 Norma Rd",
    "sg:city":"Myaree",
    "sg:classifiers":[
        {
            "category":"Home & Garden",
            "subcategory":"Carpets & Floor Coverings",
            "type":"Retail Goods"
        }
    ],
    "sg:phone":"+61 8 9330 3210",
    "sg:postcode":"6154",
    "sg:province":"WA",
    "wof:name":"All Natural Floor Coverings",
    "wof:placetype":"venue"
},
  "geometry": {"coordinates":[115.822151,-32.043125],"type":"Point"}
}