{
  "type": "Feature",
  "properties": {
    "iso:country":"AU",
    "sg:address":"64 Purchase Rd",
    "sg:city":"Cherrybrook",
    "sg:classifiers":[
        {
            "category":"Building & Trades",
            "subcategory":"Landscaping Services",
            "type":"Services"
        }
    ],
    "sg:phone":"+61 400 394 473",
    "sg:postcode":"2126",
    "sg:province":"NSW",
    "sg:tags":[
        "stump",
        "tree",
        "felling",
        "removal"
    ],
    "wof:name":"Advanced Tree Services",
    "wof:placetype":"venue"
},
  "geometry": {"coordinates":[151.04005432100001,-33.7181053162],"type":"Point"}
}