{
  "type": "Feature",
  "properties": {
    "addr:full":"2 Maiella St Stapylton QLD 4207",
    "addr:housenumber":"2",
    "addr:postcode":"4207",
    "addr:street":"Maiella St",
    "iso:country":"AU",
    "sg:address":"2 Maiella St",
    "sg:city":"Stapylton",
    "sg:classifiers":[
        {
            "category":"Cafe",
            "type":"Food & Drink"
        }
    ],
    "sg:phone":"+61 7 3807 9539",
    "sg:postcode":"4207",
    "sg:province":"QLD",
    "wof:name":"Cafe Maiella",
    "wof:placetype":"venue"
},
  "geometry": {"coordinates":[153.233276367,-27.7372703552],"type":"Point"}
}