{
  "type": "Feature",
  "properties": {
    "iso:country":"AU",
    "sg:address":"29 Kirby Rd",
    "sg:city":"Aspley",
    "sg:classifiers":[
        {
            "category":"Retail",
            "subcategory":"Event Space",
            "type":"Services"
        }
    ],
    "sg:phone":"+61 7 3862 8333",
    "sg:postcode":"4034",
    "sg:province":"QLD",
    "sg:tags":[
        "function",
        "organiser"
    ],
    "wof:name":"Aspley Leagues Club",
    "wof:placetype":"venue"
},
  "geometry": {"coordinates":[153.027267,-27.360317],"type":"Point"}
}