{
  "type": "Feature",
  "properties": {
    "iso:country":"AU",
    "sg:address":"37 Matthew St",
    "sg:city":"Stafford",
    "sg:classifiers":[
        {
            "category":"Arts & Performance",
            "subcategory":"Theater",
            "type":"Entertainment"
        }
    ],
    "sg:phone":"+61 412 131 860",
    "sg:postcode":"4053",
    "sg:province":"QLD",
    "sg:tags":[
        "theatrical",
        "supply"
    ],
    "wof:name":"David Walters Lighting Design",
    "wof:placetype":"venue"
},
  "geometry": {"coordinates":[153.00471496599999,-27.4126796722],"type":"Point"}
}