{
  "type": "Feature",
  "properties": {
    "iso:country":"AU",
    "sg:address":"990 Princes Hwy",
    "sg:city":"Moriac",
    "sg:classifiers":[
        {
            "category":"Wholesale",
            "subcategory":"Auto Parts",
            "type":"Manufacturing & Wholesale Goods"
        }
    ],
    "sg:phone":"+61 3 5266 2015",
    "sg:postcode":"3240",
    "sg:province":"VIC",
    "sg:tags":[
        "recyclers"
    ],
    "wof:name":"Westcoast F100 Salvage",
    "wof:placetype":"venue"
},
  "geometry": {"coordinates":[144.198486328,-38.2122840881],"type":"Point"}
}