{
  "type": "Feature",
  "properties": {
    "addr:full":"Shp3/ 2 Balgownie Drv Peregian Springs QLD 4573",
    "addr:postcode":"4573",
    "addr:street":"Balgownie Drv",
    "iso:country":"AU",
    "sg:address":"Shp3/ 2 Balgownie Drv",
    "sg:city":"Peregian Springs",
    "sg:classifiers":[
        {
            "category":"Restaurant",
            "type":"Food & Drink"
        }
    ],
    "sg:phone":"+61 7 5448 1911",
    "sg:postcode":"4573",
    "sg:province":"QLD",
    "wof:name":"Chez Andre",
    "wof:placetype":"venue"
},
  "geometry": {"coordinates":[153.06729100000001,-26.487787],"type":"Point"}
}