{
  "type": "Feature",
  "properties": {
    "iso:country":"AU",
    "sg:address":"19 North Boyd St",
    "sg:city":"Nimmitabel",
    "sg:classifiers":[
        {
            "category":"Building & Trades",
            "subcategory":"Landscaping Services",
            "type":"Services"
        }
    ],
    "sg:phone":"+61 2 6454 6156",
    "sg:postcode":"2631",
    "sg:province":"NSW",
    "sg:tags":[
        "control",
        "weed"
    ],
    "wof:name":"Buckley's Weed Spraying",
    "wof:placetype":"venue"
},
  "geometry": {"coordinates":[149.282012939,-36.5135650635],"type":"Point"}
}