{
  "type": "Feature",
  "properties": {
    "addr:full":"PO Box 133 Greenwood WA 6024",
    "addr:postcode":"6024",
    "iso:country":"AU",
    "sg:address":"PO Box 133",
    "sg:city":"Greenwood",
    "sg:classifiers":[
        {
            "category":"Health Services",
            "subcategory":"Dentist",
            "type":"Services"
        }
    ],
    "sg:phone":"+61 1300 136 919",
    "sg:postcode":"6024",
    "sg:province":"WA",
    "sg:tags":[
        "qld",
        "orthodontist"
    ],
    "wof:name":"Profile Orthodontics.",
    "wof:placetype":"venue"
},
  "geometry": {"coordinates":[115.801742554,-31.8309402466],"type":"Point"}
}