{
  "type": "Feature",
  "properties": {
    "iso:country":"AU",
    "sg:address":"16a Lithgow St",
    "sg:city":"Fyshwick",
    "sg:classifiers":[
        {
            "category":"Social Services",
            "subcategory":"Retirement Home",
            "type":"Services"
        }
    ],
    "sg:phone":"+61 2 6270 7650",
    "sg:postcode":"2609",
    "sg:province":"ACT",
    "sg:tags":[
        "environmental",
        "consultant",
        "pollution"
    ],
    "wof:name":"Ecowise Environmental Ltd",
    "wof:placetype":"venue"
},
  "geometry": {"coordinates":[149.165893555,-35.329990387],"type":"Point"}
}