{
  "type": "Feature",
  "properties": {
    "addr:full":"37 5 Chasely St Toowong QLD 4066",
    "addr:housenumber":"5",
    "addr:postcode":"4066",
    "addr:street":"37;Chasely St",
    "iso:country":"AU",
    "sg:address":"37 5 Chasely St",
    "sg:city":"Toowong",
    "sg:classifiers":[
        {
            "category":"Health Services",
            "subcategory":"Doctor",
            "type":"Services"
        }
    ],
    "sg:phone":"+61 7 3374 0222",
    "sg:postcode":"4066",
    "sg:province":"QLD",
    "sg:tags":[
        "occupational",
        "safety"
    ],
    "wof:name":"QBD (Qld) - Risk Management Services",
    "wof:placetype":"venue"
},
  "geometry": {"coordinates":[152.99830627399999,-27.4774570465],"type":"Point"}
}