{
  "type": "Feature",
  "properties": {
    "addr:full":"21 Reserve St Wembley WA 6014",
    "addr:housenumber":"21",
    "addr:postcode":"6014",
    "addr:street":"Reserve St",
    "iso:country":"AU",
    "sg:address":"21 Reserve St",
    "sg:city":"Wembley",
    "sg:classifiers":[
        {
            "category":"Building & Trades",
            "subcategory":"Landscaping Services",
            "type":"Services"
        }
    ],
    "sg:phone":"+61 8 9387 4097",
    "sg:postcode":"6014",
    "sg:province":"WA",
    "sg:tags":[
        "stump",
        "tree",
        "felling",
        "removal"
    ],
    "wof:name":"Professional Tree Surgeons",
    "wof:placetype":"venue"
},
  "geometry": {"coordinates":[115.806381226,-31.9382858276],"type":"Point"}
}