{
  "type": "Feature",
  "properties": {
    "iso:country":"AU",
    "sg:address":"2/ 106 Percival Rd",
    "sg:city":"Stanmore",
    "sg:classifiers":[
        {
            "category":"Parking",
            "type":"Transportation"
        }
    ],
    "sg:phone":"+61 2 9566 4899",
    "sg:postcode":"2048",
    "sg:province":"NSW",
    "sg:tags":[
        "equipment",
        "system"
    ],
    "wof:name":"Car Parking Solutions",
    "wof:placetype":"venue"
},
  "geometry": {"coordinates":[151.164108,-33.893604],"type":"Point"}
}