{
  "type": "Feature",
  "properties": {
    "iso:country":"AU",
    "sg:address":"16 Railway Pde",
    "sg:city":"Thornleigh",
    "sg:classifiers":[
        {
            "category":"Professional",
            "type":"Services"
        }
    ],
    "sg:phone":"+61 2 9875 5527",
    "sg:postcode":"2120",
    "sg:province":"NSW",
    "sg:tags":[
        "auctioneer"
    ],
    "wof:name":"Bargain Hunt Auctions",
    "wof:placetype":"venue"
},
  "geometry": {"coordinates":[151.080276489,-33.7304115295],"type":"Point"}
}