{
  "type": "Feature",
  "properties": {
    "addr:full":"16 Victor Rd Brookvale NSW 2100",
    "addr:housenumber":"16",
    "addr:postcode":"2100",
    "addr:street":"Victor Rd",
    "iso:country":"AU",
    "sg:address":"16 Victor Rd",
    "sg:city":"Brookvale",
    "sg:classifiers":[
        {
            "category":"Health Services",
            "subcategory":"Nursing And Care Facility",
            "type":"Services"
        }
    ],
    "sg:phone":"+61 2 9905 4154",
    "sg:postcode":"2100",
    "sg:province":"NSW",
    "sg:tags":[
        "home"
    ],
    "wof:name":"Armenian Rest Home Association",
    "wof:placetype":"venue"
},
  "geometry": {"coordinates":[151.277267456,-33.7590904236],"type":"Point"}
}