{
  "type": "Feature",
  "properties": {
    "addr:full":"7 Tingira Crs Sunrise Beach QLD 4567",
    "addr:housenumber":"7",
    "addr:postcode":"4567",
    "addr:street":"Tingira Crs",
    "iso:country":"AU",
    "sg:address":"7 Tingira Crs",
    "sg:city":"Sunrise Beach",
    "sg:classifiers":[
        {
            "category":"Wholesale",
            "subcategory":"Meat",
            "type":"Manufacturing & Wholesale Goods"
        }
    ],
    "sg:phone":"+61 7 5474 5311",
    "sg:postcode":"4567",
    "sg:province":"QLD",
    "sg:tags":[
        "packing",
        "exporting"
    ],
    "wof:name":"Luttick Australia Pty Ltd",
    "wof:placetype":"venue"
},
  "geometry": {"coordinates":[153.107543945,-26.4113197327],"type":"Point"}
}