{
  "type": "Feature",
  "properties": {
    "iso:country":"AU",
    "sg:address":"59 Ansell St",
    "sg:city":"Semaphore",
    "sg:classifiers":[
        {
            "category":"Utilities",
            "subcategory":"Refuse",
            "type":"Services"
        }
    ],
    "sg:phone":"+61 8 8242 7339",
    "sg:postcode":"5019",
    "sg:province":"SA",
    "sg:tags":[
        "disposal",
        "reduction",
        "waste"
    ],
    "wof:name":"Super Bins",
    "wof:placetype":"venue"
},
  "geometry": {"coordinates":[138.48687744099999,-34.8423919678],"type":"Point"}
}