{
  "type": "Feature",
  "properties": {
    "iso:country":"AU",
    "sg:address":"3 Jagger St",
    "sg:city":"McDowall",
    "sg:classifiers":[
        {
            "category":"Personal",
            "type":"Services"
        }
    ],
    "sg:phone":"+61 7 3353 1391",
    "sg:postcode":"4053",
    "sg:province":"QLD",
    "sg:tags":[
        "reducing",
        "treatment",
        "weight"
    ],
    "wof:name":"Jenny Burton",
    "wof:placetype":"venue"
},
  "geometry": {"coordinates":[152.99432373100001,-27.3849487305],"type":"Point"}
}