{
  "type": "Feature",
  "properties": {
    "addr:full":"21 Yurong St (Cnr Stanley St) East Sydney NSW 2010",
    "addr:housenumber":"21",
    "addr:postcode":"2010",
    "addr:street":"Yurong St Cnr Stanley St East",
    "iso:country":"AU",
    "sg:address":"21 Yurong St (Cnr Stanley St)",
    "sg:city":"East Sydney",
    "sg:classifiers":[
        {
            "category":"Restaurant",
            "type":"Food & Drink"
        }
    ],
    "sg:phone":"+61 2 9360 4558",
    "sg:postcode":"2010",
    "sg:province":"NSW",
    "wof:name":"Beppi's Restaurant",
    "wof:placetype":"venue"
},
  "geometry": {"coordinates":[151.214080811,-33.8750610352],"type":"Point"}
}