{
  "type": "Feature",
  "properties": {
    "iso:country":"AU",
    "sg:address":"Shop 6 33 Rockingham Rd",
    "sg:city":"Rockingham",
    "sg:classifiers":[
        {
            "category":"Fast Food",
            "type":"Food & Drink"
        }
    ],
    "sg:phone":"+61 8 9527 9177",
    "sg:postcode":"6168",
    "sg:province":"WA",
    "sg:tags":[
        "away",
        "take"
    ],
    "wof:name":"Indian Delights",
    "wof:placetype":"venue"
},
  "geometry": {"coordinates":[115.757622,-32.250061],"type":"Point"}
}