{
  "type": "Feature",
  "properties": {
    "addr:full":"Lvl 1, Phoenix Hse Annexe, 3 Violet St Redcliffe QLD 4020",
    "addr:housenumber":"3",
    "addr:postcode":"4020",
    "addr:street":"Violet St",
    "iso:country":"AU",
    "sg:address":"Lvl 1, Phoenix Hse Annexe, 3 Violet St",
    "sg:city":"Redcliffe",
    "sg:classifiers":[
        {
            "category":"Banks & Credit Unions",
            "subcategory":"Bank",
            "type":"Services"
        }
    ],
    "sg:phone":"+61 7 3283 8744",
    "sg:postcode":"4020",
    "sg:province":"QLD",
    "sg:tags":[
        "broker",
        "mortgage"
    ],
    "wof:name":"City Pacific Finance",
    "wof:placetype":"venue"
},
  "geometry": {"coordinates":[153.11364699999999,-27.229214],"type":"Point"}
}