{
  "type": "Feature",
  "properties": {
    "addr:full":"17 Kokoda St Port Augusta SA 5700",
    "addr:housenumber":"17",
    "addr:postcode":"5700",
    "addr:street":"Kokoda St",
    "iso:country":"AU",
    "sg:address":"17 Kokoda St",
    "sg:city":"Port Augusta",
    "sg:classifiers":[
        {
            "category":"Wholesale",
            "subcategory":"Farm Supplies",
            "type":"Manufacturing & Wholesale Goods"
        }
    ],
    "sg:phone":"+61 8 8642 2038",
    "sg:postcode":"5700",
    "sg:province":"SA",
    "sg:tags":[
        "feed",
        "supplement",
        "stock"
    ],
    "wof:name":"Turners Agencies",
    "wof:placetype":"venue"
},
  "geometry": {"coordinates":[137.781784058,-32.4936485291],"type":"Point"}
}