{
  "type": "Feature",
  "properties": {
    "iso:country":"AU",
    "sg:address":"504 Talbot St",
    "sg:city":"(Sth) Ballarat",
    "sg:classifiers":[
        {
            "category":"Personal",
            "subcategory":"Tanning Parlor",
            "type":"Services"
        }
    ],
    "sg:phone":"+61 401 558 016",
    "sg:postcode":"3350",
    "sg:province":"VIC",
    "sg:tags":[
        "solarium"
    ],
    "wof:name":"Coco Bliss Beauty",
    "wof:placetype":"venue"
},
  "geometry": {"coordinates":[143.841064,-37.570461],"type":"Point"}
}