{
  "type": "Feature",
  "properties": {
    "addr:full":"Suite 6 25 Wiltshire St Salisbury SA 5108",
    "addr:housenumber":"25",
    "addr:postcode":"5108",
    "addr:street":"Wiltshire St",
    "iso:country":"AU",
    "sg:address":"Suite 6 25 Wiltshire St",
    "sg:city":"Salisbury",
    "sg:classifiers":[
        {
            "category":"Professional",
            "subcategory":"Employment Agencies",
            "type":"Services"
        }
    ],
    "sg:phone":"+61 8 8281 3483",
    "sg:postcode":"5108",
    "sg:province":"SA",
    "wof:name":"Westaff",
    "wof:placetype":"venue"
},
  "geometry": {"coordinates":[138.64564514200001,-34.7633934021],"type":"Point"}
}