{
  "type": "Feature",
  "properties": {
    "addr:full":"3 Hewdon Rd Australind WA 6233",
    "addr:housenumber":"3",
    "addr:postcode":"6233",
    "addr:street":"Hewdon Rd",
    "iso:country":"AU",
    "sg:address":"3 Hewdon Rd",
    "sg:city":"Australind",
    "sg:classifiers":[
        {
            "category":"Retail",
            "subcategory":"Repair Shop",
            "type":"Services"
        }
    ],
    "sg:phone":"+61 8 9797 0334",
    "sg:postcode":"6233",
    "sg:province":"WA",
    "sg:tags":[
        "upholsterer"
    ],
    "wof:name":"Szyma's Motor Trimmers & Upholsterers",
    "wof:placetype":"venue"
},
  "geometry": {"coordinates":[115.745644,-33.277042],"type":"Point"}
}