{
  "type": "Feature",
  "properties": {
    "iso:country":"AU",
    "sg:address":"Level 3, 2 Ocean St",
    "sg:city":"Maroochydore",
    "sg:classifiers":[
        {
            "category":"Health Services",
            "subcategory":"Health Practitioner",
            "type":"Services"
        }
    ],
    "sg:phone":"+61 405 789 184",
    "sg:postcode":"4558",
    "sg:province":"QLD",
    "sg:tags":[
        "psychologist"
    ],
    "wof:name":"O&#039;Shea Melanie Dr",
    "wof:placetype":"venue"
},
  "geometry": {"coordinates":[153.09193420400001,-26.6517391205],"type":"Point"}
}