{
  "type": "Feature",
  "properties": {
    "iso:country":"AU",
    "sg:address":"27 Smeaton St",
    "sg:city":"Clunes",
    "sg:classifiers":[
        {
            "category":"Building & Trades",
            "subcategory":"Construction",
            "type":"Services"
        }
    ],
    "sg:phone":"+61 3 5345 3044",
    "sg:postcode":"3370",
    "sg:province":"VIC",
    "sg:tags":[
        "fencing",
        "contractor"
    ],
    "wof:name":"Howden Fencing & Gates",
    "wof:placetype":"venue"
},
  "geometry": {"coordinates":[143.787475586,-37.2952804565],"type":"Point"}
}