{
  "type": "Feature",
  "properties": {
    "addr:full":"39 Middle Farm Rd Armidale NSW 2350",
    "addr:housenumber":"39",
    "addr:postcode":"2350",
    "addr:street":"Middle Farm Rd",
    "iso:country":"AU",
    "sg:address":"39 Middle Farm Rd",
    "sg:city":"Armidale",
    "sg:classifiers":[
        {
            "category":"Building & Trades",
            "subcategory":"Construction",
            "type":"Services"
        }
    ],
    "sg:phone":"+61 412 858 423",
    "sg:postcode":"2350",
    "sg:province":"NSW",
    "sg:tags":[
        "earth",
        "excavating",
        "moving",
        "contractor"
    ],
    "wof:name":"Bowden's Bobcat Service",
    "wof:placetype":"venue"
},
  "geometry": {"coordinates":[151.666213989,-30.522102356],"type":"Point"}
}