{
  "type": "Feature",
  "properties": {
    "addr:full":"23 Davis Rd Wetherill Park NSW 2164",
    "addr:housenumber":"23",
    "addr:postcode":"2164",
    "addr:street":"Davis Rd",
    "iso:country":"AU",
    "sg:address":"23 Davis Rd",
    "sg:city":"Wetherill Park",
    "sg:classifiers":[
        {
            "category":"Manufacturing",
            "subcategory":"Paper Products",
            "type":"Manufacturing & Wholesale Goods"
        }
    ],
    "sg:phone":"+61 2 9604 8855",
    "sg:postcode":"2164",
    "sg:province":"NSW",
    "sg:tags":[
        "metal",
        "non-ferrous",
        "foundry"
    ],
    "wof:name":"Nonferral Pty Ltd",
    "wof:placetype":"venue"
},
  "geometry": {"coordinates":[150.9012146,-33.8365135193],"type":"Point"}
}