{
  "type": "Feature",
  "properties": {
    "iso:country":"AU",
    "sg:address":"PO Box 207",
    "sg:city":"Fawkner",
    "sg:classifiers":[
        {
            "category":"Retail",
            "subcategory":"Auto Repair",
            "type":"Services"
        }
    ],
    "sg:phone":"+61 418 369 634",
    "sg:postcode":"3060",
    "sg:province":"VIC",
    "sg:tags":[
        "electrical"
    ],
    "wof:name":"Mode Auto Electrical",
    "wof:placetype":"venue"
},
  "geometry": {"coordinates":[144.969406128,-37.7048110962],"type":"Point"}
}