{
  "type": "Feature",
  "properties": {
    "addr:full":"92 Otho St Inverell NSW 2360",
    "addr:housenumber":"92",
    "addr:postcode":"2360",
    "addr:street":"Otho St",
    "iso:country":"AU",
    "sg:address":"92 Otho St",
    "sg:city":"Inverell",
    "sg:classifiers":[
        {
            "category":"Shopping",
            "subcategory":"Stationery & Office Supplies",
            "type":"Retail Goods"
        }
    ],
    "sg:phone":"+61 2 6722 3488",
    "sg:postcode":"2360",
    "sg:province":"NSW",
    "wof:name":"Inverell Office & Packaging Supplies",
    "wof:placetype":"venue"
},
  "geometry": {"coordinates":[151.11323547399999,-29.7751216888],"type":"Point"}
}