{
  "type": "Feature",
  "properties": {
    "iso:country":"AU",
    "sg:address":"92 Bridge St",
    "sg:city":"Fortitude Valley",
    "sg:classifiers":[
        {
            "category":"Personal",
            "subcategory":"Shoe Repair & Shine",
            "type":"Services"
        }
    ],
    "sg:phone":"+61 7 3854 1080",
    "sg:postcode":"4006",
    "sg:province":"QLD",
    "sg:tags":[
        "reconditioning",
        "business",
        "furniture"
    ],
    "wof:name":"A.C.R.",
    "wof:placetype":"venue"
},
  "geometry": {"coordinates":[153.03556823700001,-27.4545383453],"type":"Point"}
}