{
  "type": "Feature",
  "properties": {
    "iso:country":"AU",
    "sg:address":"Shop 6/ 160 Racecourse Rd",
    "sg:city":"Ascot",
    "sg:classifiers":[
        {
            "category":"Shopping",
            "subcategory":"Clothing, Apparel, & Fashions",
            "type":"Retail Goods"
        }
    ],
    "sg:phone":"+61 7 3868 3729",
    "sg:postcode":"4007",
    "sg:province":"QLD",
    "sg:tags":[
        "maternity",
        "wear"
    ],
    "wof:name":"Kids Couture",
    "wof:placetype":"venue"
},
  "geometry": {"coordinates":[153.065277,-27.432259],"type":"Point"}
}