{
  "type": "Feature",
  "properties": {
    "addr:full":"46 Raglan Rd Mt Lawley WA 6050",
    "addr:housenumber":"46",
    "addr:postcode":"6050",
    "addr:street":"Raglan Rd",
    "iso:country":"AU",
    "sg:address":"46 Raglan Rd",
    "sg:city":"Mt Lawley",
    "sg:classifiers":[
        {
            "category":"Banks & Credit Unions",
            "subcategory":"Financial Services",
            "type":"Services"
        }
    ],
    "sg:phone":"+61 1300 300 889",
    "sg:postcode":"6050",
    "sg:province":"WA",
    "sg:tags":[
        "planning"
    ],
    "wof:name":"MoneyBags",
    "wof:placetype":"venue"
},
  "geometry": {"coordinates":[115.868423462,-31.9337253571],"type":"Point"}
}