{
  "type": "Feature",
  "properties": {
    "addr:full":"5 Amundsen Ave Shoalhaven Heads NSW 2535",
    "addr:housenumber":"5",
    "addr:postcode":"2535",
    "addr:street":"Amundsen Ave;Heads",
    "iso:country":"AU",
    "sg:address":"5 Amundsen Ave",
    "sg:city":"Shoalhaven Heads",
    "sg:classifiers":[
        {
            "category":"Home & Garden",
            "subcategory":"Building Materials",
            "type":"Retail Goods"
        }
    ],
    "sg:phone":"+61 2 4448 5655",
    "sg:postcode":"2535",
    "sg:province":"NSW",
    "sg:tags":[
        "tile",
        "roofing"
    ],
    "wof:name":"B & H Thomson Roof Tilers Pty Ltd",
    "wof:placetype":"venue"
},
  "geometry": {"coordinates":[150.737670898,-34.8453483582],"type":"Point"}
}