{
  "type": "Feature",
  "properties": {
    "addr:full":"85- 87 The Esp Cairns QLD 4870",
    "addr:housenumber":"87",
    "addr:postcode":"4870",
    "addr:street":"The Esp",
    "iso:country":"AU",
    "sg:address":"85- 87",
    "sg:city":"The Esp Cairns",
    "sg:classifiers":[
        {
            "category":"Banks & Credit Unions",
            "subcategory":"Bureau De Change",
            "type":"Services"
        }
    ],
    "sg:phone":"+61 7 4052 1762",
    "sg:postcode":"4870",
    "sg:province":"QLD",
    "sg:tags":[
        "currency",
        "exchange",
        "foreign"
    ],
    "wof:name":"MoneyGram",
    "wof:placetype":"venue"
},
  "geometry": {"coordinates":[145.66958618199999,-17.0185699463],"type":"Point"}
}