{
  "type": "Feature",
  "properties": {
    "addr:full":"144 Lavarack Ave Eagle Farm QLD 4009",
    "addr:housenumber":"144",
    "addr:postcode":"4009",
    "addr:street":"Lavarack Ave",
    "iso:country":"AU",
    "sg:address":"144 Lavarack Ave",
    "sg:city":"Eagle Farm",
    "sg:classifiers":[
        {
            "category":"Manufacturing",
            "subcategory":"Metals",
            "type":"Manufacturing & Wholesale Goods"
        }
    ],
    "sg:phone":"+61 7 3268 5811",
    "sg:postcode":"4009",
    "sg:province":"QLD",
    "sg:tags":[
        "sheet",
        "worker"
    ],
    "wof:name":"Emersteel Fabricators",
    "wof:placetype":"venue"
},
  "geometry": {"coordinates":[153.102218628,-27.431186676],"type":"Point"}
}