{
  "type": "Feature",
  "properties": {
    "iso:country":"AU",
    "sg:address":"5 Phillips St",
    "sg:city":"Thebarton",
    "sg:classifiers":[
        {
            "category":"Home & Garden",
            "subcategory":"Hardware",
            "type":"Retail Goods"
        }
    ],
    "sg:phone":"+61 8 8234 8665",
    "sg:postcode":"5031",
    "sg:province":"SA",
    "sg:tags":[
        "part",
        "air conditioning"
    ],
    "wof:name":"Automated Building Solutions (SA) Pty Ltd",
    "wof:placetype":"venue"
},
  "geometry": {"coordinates":[138.57684326200001,-34.9135971069],"type":"Point"}
}