{
  "type": "Feature",
  "properties": {
    "addr:full":"693 Brunswick St New Farm QLD 4005",
    "addr:housenumber":"693",
    "addr:postcode":"4005",
    "addr:street":"Brunswick St",
    "iso:country":"AU",
    "sg:address":"693 Brunswick St",
    "sg:city":"New Farm",
    "sg:classifiers":[
        {
            "category":"Government",
            "subcategory":"Customs House",
            "type":"Public Place"
        }
    ],
    "sg:phone":"+61 7 5570 2352",
    "sg:postcode":"4005",
    "sg:province":"QLD",
    "sg:tags":[
        "title",
        "management",
        "stratum"
    ],
    "wof:name":"B M Body Corporate",
    "wof:placetype":"venue"
},
  "geometry": {"coordinates":[153.04197692899999,-27.4640808105],"type":"Point"}
}