{
  "type": "Feature",
  "properties": {
    "addr:full":"49 Parramatta Rd Concord NSW 2137",
    "addr:housenumber":"49",
    "addr:postcode":"2137",
    "addr:street":"Parramatta Rd",
    "iso:country":"AU",
    "sg:address":"49 Parramatta Rd",
    "sg:city":"Concord",
    "sg:classifiers":[
        {
            "category":"Shopping",
            "subcategory":"Mobile Phones",
            "type":"Retail Goods"
        }
    ],
    "sg:phone":"+61 13 11 77",
    "sg:postcode":"2137",
    "sg:province":"NSW",
    "sg:tags":[
        "telephone",
        "accessory"
    ],
    "wof:name":"Strathfield",
    "wof:placetype":"venue"
},
  "geometry": {"coordinates":[151.103973389,-33.8684768677],"type":"Point"}
}