{
  "type": "Feature",
  "properties": {
    "iso:country":"AU",
    "sg:address":"553a North Rd",
    "sg:city":"Ormond",
    "sg:classifiers":[
        {
            "category":"Food & Beverages",
            "subcategory":"Specialty",
            "type":"Retail Goods"
        }
    ],
    "sg:phone":"+61 3 9578 6400",
    "sg:postcode":"3204",
    "sg:province":"VIC",
    "sg:tags":[
        "product",
        "health"
    ],
    "sg:website":"http://www.sunnybrookonline.com.au",
    "wof:name":"Sunnybrook Health Store",
    "wof:placetype":"venue"
},
  "geometry": {"coordinates":[145.04269400000001,-37.904137],"type":"Point"}
}