{
  "type": "Feature",
  "properties": {
    "addr:full":"3 Kempsey St Blacktown NSW 2148",
    "addr:housenumber":"3",
    "addr:postcode":"2148",
    "addr:street":"Kempsey St",
    "iso:country":"AU",
    "sg:address":"3 Kempsey St",
    "sg:city":"Blacktown",
    "sg:classifiers":[
        {
            "category":"Health Services",
            "subcategory":"Doctor",
            "type":"Services"
        }
    ],
    "sg:phone":"+61 2 9621 5399",
    "sg:postcode":"2148",
    "sg:province":"NSW",
    "sg:tags":[
        "medical",
        "practitioner"
    ],
    "wof:name":"Blumenthal N J Dr",
    "wof:placetype":"venue"
},
  "geometry": {"coordinates":[150.91395568900001,-33.7745018005],"type":"Point"}
}