{
  "type": "Feature",
  "properties": {
    "addr:full":"Schrank Rd Daradgee QLD 4860",
    "addr:postcode":"4860",
    "addr:street":"Schrank Rd",
    "iso:country":"AU",
    "sg:address":"Schrank Rd",
    "sg:city":"Daradgee",
    "sg:classifiers":[
        {
            "category":"Farming",
            "subcategory":"Berry Farm",
            "type":"Manufacturing & Wholesale Goods"
        }
    ],
    "sg:phone":"+61 7 4063 3739",
    "sg:postcode":"4860",
    "sg:province":"QLD",
    "sg:tags":[
        "fruit",
        "grower"
    ],
    "wof:name":"Plath T W",
    "wof:placetype":"venue"
},
  "geometry": {"coordinates":[145.98135375999999,-17.4802799225],"type":"Point"}
}