{
  "type": "Feature",
  "properties": {
    "addr:full":"PO Box 388 Five Dock NSW 2046",
    "addr:postcode":"2046",
    "iso:country":"AU",
    "sg:address":"PO Box 388",
    "sg:city":"Five Dock",
    "sg:classifiers":[
        {
            "category":"Shopping",
            "subcategory":"Computers & Home Electronics",
            "type":"Retail Goods"
        }
    ],
    "sg:phone":"+61 2 8753 0941",
    "sg:postcode":"2046",
    "sg:province":"NSW",
    "sg:tags":[
        "equipment",
        "multimedia"
    ],
    "wof:name":"Quirk Media",
    "wof:placetype":"venue"
},
  "geometry": {"coordinates":[151.128693,-33.87104],"type":"Point"}
}