{
  "type": "Feature",
  "properties": {
    "addr:full":"PO Box 5171 McLaren Vale SA 5171",
    "addr:postcode":"5171",
    "iso:country":"AU",
    "sg:address":"PO Box 5171",
    "sg:city":"McLaren Vale",
    "sg:classifiers":[
        {
            "category":"Manufacturing",
            "subcategory":"Food",
            "type":"Manufacturing & Wholesale Goods"
        }
    ],
    "sg:phone":"+61 416 224 264",
    "sg:postcode":"5171",
    "sg:province":"SA",
    "sg:tags":[
        "function",
        "catering"
    ],
    "wof:name":"Relish Sisters Superior Catering",
    "wof:placetype":"venue"
},
  "geometry": {"coordinates":[138.59555053700001,-35.2062568665],"type":"Point"}
}