{
  "type": "Feature",
  "properties": {
    "iso:country":"AU",
    "sg:address":"17 Langmead Rd",
    "sg:city":"Silverdale",
    "sg:classifiers":[
        {
            "category":"Shopping",
            "subcategory":"Computers & Home Electronics",
            "type":"Retail Goods"
        }
    ],
    "sg:phone":"+61 2 4774 2485",
    "sg:postcode":"2752",
    "sg:province":"NSW",
    "sg:tags":[
        "small",
        "equipment",
        "business"
    ],
    "wof:name":"CNC Automation",
    "wof:placetype":"venue"
},
  "geometry": {"coordinates":[150.62464904800001,-33.8987770081],"type":"Point"}
}