{
  "type": "Feature",
  "properties": {
    "addr:full":"Unit 1 14 Resolution Drv Caringbah NSW 2229",
    "addr:housenumber":"14",
    "addr:postcode":"2229",
    "addr:street":"Resolution Drv",
    "iso:country":"AU",
    "sg:address":"Unit 1 14 Resolution Drv",
    "sg:city":"Caringbah",
    "sg:classifiers":[
        {
            "category":"Home & Garden",
            "subcategory":"Carpets & Floor Coverings",
            "type":"Retail Goods"
        }
    ],
    "sg:phone":"+61 2 9540 1550",
    "sg:postcode":"2229",
    "sg:province":"NSW",
    "sg:tags":[
        "tile",
        "wall"
    ],
    "wof:name":"McAloon Enterprises",
    "wof:placetype":"venue"
},
  "geometry": {"coordinates":[151.13258361800001,-34.0330276489],"type":"Point"}
}