{
  "type": "Feature",
  "properties": {
    "addr:full":"36 Archerfield Rd Darra QLD 4076",
    "addr:housenumber":"36",
    "addr:postcode":"4076",
    "addr:street":"Archerfield Rd",
    "iso:country":"AU",
    "sg:address":"36 Archerfield Rd",
    "sg:city":"Darra",
    "sg:classifiers":[
        {
            "category":"Home & Garden",
            "subcategory":"Building Materials",
            "type":"Retail Goods"
        }
    ],
    "sg:phone":"+61 7 3725 5302",
    "sg:postcode":"4076",
    "sg:province":"QLD",
    "sg:tags":[
        "insulation"
    ],
    "wof:name":"Precision Tubewinders",
    "wof:placetype":"venue"
},
  "geometry": {"coordinates":[152.954803467,-27.5762367249],"type":"Point"}
}