{
  "type": "Feature",
  "properties": {
    "iso:country":"AU",
    "sg:address":"48 Victoria St",
    "sg:city":"Ulverstone",
    "sg:classifiers":[
        {
            "category":"Health Services",
            "subcategory":"Health Practitioner",
            "type":"Services"
        }
    ],
    "sg:phone":"+61 3 6425 9500",
    "sg:postcode":"7315",
    "sg:province":"TAS",
    "sg:tags":[
        "physiotherapist"
    ],
    "wof:name":"Ulverstone Physiotherapy",
    "wof:placetype":"venue"
},
  "geometry": {"coordinates":[146.17315673799999,-41.1569862366],"type":"Point"}
}