{
  "type": "Feature",
  "properties": {
    "iso:country":"AU",
    "sg:address":"19 Charles St",
    "sg:city":"Roma",
    "sg:classifiers":[
        {
            "category":"Home & Garden",
            "subcategory":"Building Materials",
            "type":"Retail Goods"
        }
    ],
    "sg:phone":"+61 427 373 875",
    "sg:postcode":"4455",
    "sg:province":"QLD",
    "sg:tags":[
        "lawn",
        "cutting",
        "maintenance"
    ],
    "wof:name":"South-West QLD Gardens & Landscapes",
    "wof:placetype":"venue"
},
  "geometry": {"coordinates":[148.79266357399999,-26.5684490204],"type":"Point"}
}