{
  "type": "Feature",
  "properties": {
    "iso:country":"AU",
    "sg:address":"Unit 8/ 2 Eden Park Drv",
    "sg:city":"North Ryde",
    "sg:classifiers":[
        {
            "category":"Manufacturing",
            "subcategory":"Tools & Machinery",
            "type":"Manufacturing & Wholesale Goods"
        }
    ],
    "sg:phone":"+61 2 9889 5811",
    "sg:postcode":"2113",
    "sg:province":"NSW",
    "sg:tags":[
        "abrasive"
    ],
    "wof:name":"Klingspor Abrasives Technology",
    "wof:placetype":"venue"
},
  "geometry": {"coordinates":[151.13092040999999,-33.785785675],"type":"Point"}
}