{
  "type": "Feature",
  "properties": {
    "addr:full":"Shop 1 150- 154 Oxford St Leederville WA 6007",
    "addr:housenumber":"shop 1;154",
    "addr:postcode":"150;6007",
    "addr:street":"Oxford St",
    "iso:country":"AU",
    "sg:address":"Shop 1 150- 154 Oxford St",
    "sg:city":"Leederville",
    "sg:classifiers":[
        {
            "category":"Cafe",
            "type":"Food & Drink"
        }
    ],
    "sg:phone":"+61 8 9201 0255",
    "sg:postcode":"6007",
    "sg:province":"WA",
    "wof:name":"Gloria Jean's Coffees",
    "wof:placetype":"venue"
},
  "geometry": {"coordinates":[115.841392517,-31.9365272522],"type":"Point"}
}