{
  "type": "Feature",
  "properties": {
    "iso:country":"AU",
    "sg:address":"52A Watton St",
    "sg:city":"Werribee",
    "sg:classifiers":[
        {
            "category":"Arena",
            "subcategory":"Sports Club",
            "type":"Entertainment"
        }
    ],
    "sg:phone":"+61 3 9734 9800",
    "sg:postcode":"3030",
    "sg:province":"VIC",
    "sg:tags":[
        "defence",
        "supply",
        "self",
        "instruction",
        "martial art"
    ],
    "wof:name":"Melbourne Ju Jitsu Academy",
    "wof:placetype":"venue"
},
  "geometry": {"coordinates":[144.659561,-37.90213],"type":"Point"}
}