{
  "type": "Feature",
  "properties": {
    "addr:full":"143 Claisebrook Rd Perth WA 6000",
    "addr:housenumber":"143",
    "addr:postcode":"6000",
    "addr:street":"Claisebrook Rd",
    "iso:country":"AU",
    "sg:address":"143 Claisebrook Rd",
    "sg:city":"Perth",
    "sg:classifiers":[
        {
            "category":"Professional",
            "subcategory":"Printing & Photocopies",
            "type":"Services"
        }
    ],
    "sg:phone":"+61 8 9227 8566",
    "sg:postcode":"6000",
    "sg:province":"WA",
    "sg:tags":[
        "embroidery"
    ],
    "sg:website":"http://www.embroidery.com.au",
    "wof:name":"Embroidery Plus",
    "wof:placetype":"venue"
},
  "geometry": {"coordinates":[115.87313079800001,-31.9474029541],"type":"Point"}
}