{
  "type": "Feature",
  "properties": {
    "addr:full":"30 Wylds Rd Glenorie NSW 2157",
    "addr:housenumber":"30",
    "addr:postcode":"2157",
    "addr:street":"Wylds Rd",
    "iso:country":"AU",
    "sg:address":"30 Wylds Rd",
    "sg:city":"Glenorie",
    "sg:classifiers":[
        {
            "category":"Professional",
            "subcategory":"Detective & Security Services",
            "type":"Services"
        }
    ],
    "sg:phone":"+61 2 9651 5000",
    "sg:postcode":"2157",
    "sg:province":"NSW",
    "sg:tags":[
        "identification",
        "system"
    ],
    "wof:name":"Mag-Tek Pty Limited",
    "wof:placetype":"venue"
},
  "geometry": {"coordinates":[151.024093628,-33.6236877441],"type":"Point"}
}