{
  "type": "Feature",
  "properties": {
    "addr:full":"78-80 Malcomson St North Mackay QLD 4740",
    "addr:housenumber":"78-80",
    "addr:postcode":"4740",
    "addr:street":"Malcomson St",
    "iso:country":"AU",
    "sg:address":"78-80 Malcomson St",
    "sg:city":"North Mackay",
    "sg:classifiers":[
        {
            "category":"Autos & Motor Vehicles",
            "subcategory":"Fuel & Gas Station",
            "type":"Retail Goods"
        }
    ],
    "sg:phone":"+61 7 4942 3635",
    "sg:postcode":"4740",
    "sg:province":"QLD",
    "wof:name":"Caltex Norgate Star Service Station",
    "wof:placetype":"venue"
},
  "geometry": {"coordinates":[149.17622399999999,-21.122702],"type":"Point"}
}