{
  "type": "Feature",
  "properties": {
    "addr:full":"4 Lucca Rd Wyong North NSW 2259",
    "addr:housenumber":"4",
    "addr:postcode":"2259",
    "addr:street":"Lucca Rd",
    "iso:country":"AU",
    "sg:address":"4 Lucca Rd",
    "sg:city":"Wyong North",
    "sg:classifiers":[
        {
            "category":"Building & Trades",
            "subcategory":"Plumbing",
            "type":"Services"
        }
    ],
    "sg:phone":"+61 2 4352 2188",
    "sg:postcode":"2259",
    "sg:province":"NSW",
    "sg:tags":[
        "pipe",
        "fabricator"
    ],
    "wof:name":"Morson Engineering Pty Ltd",
    "wof:placetype":"venue"
},
  "geometry": {"coordinates":[151.41911315900001,-33.3097610474],"type":"Point"}
}