{
  "type": "Feature",
  "properties": {
    "addr:full":"28 Hicks St Charters Towers QLD 4820",
    "addr:housenumber":"28",
    "addr:postcode":"4820",
    "addr:street":"Hicks St",
    "iso:country":"AU",
    "sg:address":"28 Hicks St",
    "sg:city":"Charters Towers",
    "sg:classifiers":[
        {
            "category":"Education",
            "subcategory":"University",
            "type":"Public Place"
        }
    ],
    "sg:phone":"+61 7 4787 3099",
    "sg:postcode":"4820",
    "sg:province":"QLD",
    "sg:tags":[
        "educational",
        "organisation",
        "cultural"
    ],
    "wof:name":"QCPCA- Northern Regional Council",
    "wof:placetype":"venue"
},
  "geometry": {"coordinates":[146.26109299999999,-20.061106],"type":"Point"}
}