{
  "type": "Feature",
  "properties": {
    "addr:full":"12 George Rd Salamander Bay NSW 2317",
    "addr:housenumber":"12",
    "addr:postcode":"2317",
    "addr:street":"George Rd",
    "iso:country":"AU",
    "sg:address":"12 George Rd",
    "sg:city":"Salamander Bay",
    "sg:classifiers":[
        {
            "category":"Shopping",
            "subcategory":"Computers & Home Electronics",
            "type":"Retail Goods"
        }
    ],
    "sg:phone":"+61 2 4982 0922",
    "sg:postcode":"2317",
    "sg:province":"NSW",
    "sg:tags":[
        "equipment",
        "part",
        "electronic"
    ],
    "wof:name":"PacSat Jaycar Stockist",
    "wof:placetype":"venue"
},
  "geometry": {"coordinates":[152.074997,-32.726662],"type":"Point"}
}