{
  "type": "Feature",
  "properties": {
    "iso:country":"AU",
    "sg:address":"Unit 5, 42 Farrall Rd",
    "sg:city":"Midvale",
    "sg:classifiers":[
        {
            "category":"Real Estate",
            "subcategory":"Surveying",
            "type":"Services"
        }
    ],
    "sg:phone":"+61 8 9250 6620",
    "sg:postcode":"6056",
    "sg:province":"WA",
    "sg:tags":[
        "surveyor",
        "land"
    ],
    "wof:name":"Survey West Pty Ltd",
    "wof:placetype":"venue"
},
  "geometry": {"coordinates":[116.03362274200001,-31.8843803406],"type":"Point"}
}