{
  "type": "Feature",
  "properties": {
    "addr:full":"Shop 6 Stock Exchange Arcade Charters Towers QLD 4820",
    "addr:housenumber":"shop 6 stock",
    "addr:postcode":"4820",
    "addr:street":"Exchange Arcade",
    "iso:country":"AU",
    "sg:address":"Shop 6 Stock Exchange Arcade",
    "sg:city":"Charters Towers",
    "sg:classifiers":[
        {
            "category":"Personal",
            "subcategory":"Beauty Salon",
            "type":"Services"
        }
    ],
    "sg:phone":"+61 7 4787 8757",
    "sg:postcode":"4820",
    "sg:province":"QLD",
    "sg:tags":[
        "hairdresser"
    ],
    "wof:name":"How Bizarre Hair",
    "wof:placetype":"venue"
},
  "geometry": {"coordinates":[146.26315299999999,-20.0774],"type":"Point"}
}