{
  "type": "Feature",
  "properties": {
    "addr:full":"29 Mary St Northmead NSW 2152",
    "addr:housenumber":"29",
    "addr:postcode":"2152",
    "addr:street":"Mary St",
    "iso:country":"AU",
    "sg:address":"29 Mary St",
    "sg:city":"Northmead",
    "sg:classifiers":[
        {
            "category":"Home & Garden",
            "subcategory":"Carpets & Floor Coverings",
            "type":"Retail Goods"
        }
    ],
    "sg:phone":"+61 2 9639 3006",
    "sg:postcode":"2152",
    "sg:province":"NSW",
    "sg:tags":[
        "tile",
        "wall",
        "layer"
    ],
    "wof:name":"Heeney W F & C E",
    "wof:placetype":"venue"
},
  "geometry": {"coordinates":[151.002685547,-33.7793464661],"type":"Point"}
}