{
  "type": "Feature",
  "properties": {
    "iso:country":"AU",
    "sg:address":"Shop 4, Auburn Shopng Vlge",
    "sg:city":"Auburn",
    "sg:classifiers":[
        {
            "category":"Shopping",
            "subcategory":"Clothing, Apparel, & Fashions",
            "type":"Retail Goods"
        }
    ],
    "sg:phone":"+61 2 9646 3824",
    "sg:postcode":"2144",
    "sg:province":"NSW",
    "sg:tags":[
        "lady",
        "wear"
    ],
    "wof:name":"Catwalk Fashions",
    "wof:placetype":"venue"
},
  "geometry": {"coordinates":[151.032302856,-33.8545417786],"type":"Point"}
}