{
  "type": "Feature",
  "properties": {
    "iso:country":"AU",
    "sg:address":"9 Arvona Ave",
    "sg:city":"Sunshine North",
    "sg:classifiers":[
        {
            "category":"Manufacturing",
            "subcategory":"Rubber & Plastics",
            "type":"Manufacturing & Wholesale Goods"
        }
    ],
    "sg:phone":"+61 3 9312 3706",
    "sg:postcode":"3020",
    "sg:province":"VIC",
    "sg:tags":[
        "wholesaler",
        "product",
        "mfrs"
    ],
    "wof:name":"Perma Rubber Products Pty Ltd",
    "wof:placetype":"venue"
},
  "geometry": {"coordinates":[144.835052,-37.76178],"type":"Point"}
}