{
  "type": "Feature",
  "properties": {
    "addr:full":"53 Queen St Woollahra NSW 2025",
    "addr:housenumber":"53",
    "addr:postcode":"2025",
    "addr:street":"Queen St",
    "iso:country":"AU",
    "sg:address":"53 Queen St",
    "sg:city":"Woollahra",
    "sg:classifiers":[
        {
            "category":"Personal",
            "subcategory":"Beauty Salon",
            "type":"Services"
        }
    ],
    "sg:phone":"+61 2 9363 3391",
    "sg:postcode":"2025",
    "sg:province":"NSW",
    "wof:name":"Nicole Roorda Beauty Therapy",
    "wof:placetype":"venue"
},
  "geometry": {"coordinates":[151.23516845699999,-33.8889274597],"type":"Point"}
}