{
  "type": "Feature",
  "properties": {
    "addr:full":"1/ 19-21 Coldstream St Yamba NSW 2464",
    "addr:housenumber":"/ 19-21",
    "addr:postcode":"2464",
    "addr:street":"Coldstream St",
    "iso:country":"AU",
    "sg:address":"1/ 19-21 Coldstream St",
    "sg:city":"Yamba",
    "sg:classifiers":[
        {
            "category":"Real Estate",
            "subcategory":"Real Estate Agent",
            "type":"Services"
        }
    ],
    "sg:phone":"+61 2 6646 2299",
    "sg:postcode":"2464",
    "sg:province":"NSW",
    "wof:name":"Mike Macqueen First National",
    "wof:placetype":"venue"
},
  "geometry": {"coordinates":[153.35992431599999,-29.4370765686],"type":"Point"}
}