{
  "type": "Feature",
  "properties": {
    "iso:country":"AU",
    "sg:address":"Maroondah Audiology, 8 Warrandyte Rd",
    "sg:city":"Ringwood",
    "sg:classifiers":[
        {
            "category":"Personal",
            "subcategory":"Hair Removal",
            "type":"Services"
        }
    ],
    "sg:phone":"+61 1300 365 273",
    "sg:postcode":"3134",
    "sg:province":"VIC",
    "wof:name":"The Australian Laser Clinic",
    "wof:placetype":"venue"
},
  "geometry": {"coordinates":[145.230957031,-37.813583374],"type":"Point"}
}