{
  "type": "Feature",
  "properties": {
    "addr:full":"72 York St Launceston TAS 7250",
    "addr:housenumber":"72",
    "addr:postcode":"7250",
    "addr:street":"York St",
    "iso:country":"AU",
    "sg:address":"72 York St",
    "sg:city":"Launceston",
    "sg:classifiers":[
        {
            "category":"Organizations",
            "subcategory":"Labor Organization",
            "type":"Services"
        }
    ],
    "sg:phone":"+61 3 6331 8166",
    "sg:postcode":"7250",
    "sg:province":"TAS",
    "sg:tags":[
        "union"
    ],
    "sg:website":"http://www.sdatas.asn.au",
    "wof:name":"Shop Distributive & Allied Employees&#039; Association",
    "wof:placetype":"venue"
},
  "geometry": {"coordinates":[147.14219665499999,-41.4368400574],"type":"Point"}
}