{
  "type": "Feature",
  "properties": {
    "addr:full":"Chatswood Chase Archer St Chatswood NSW 2067",
    "addr:postcode":"2067",
    "addr:street":"Archer St",
    "iso:country":"AU",
    "sg:address":"Chatswood Chase Archer St",
    "sg:city":"Chatswood",
    "sg:classifiers":[
        {
            "category":"Shopping",
            "subcategory":"Clothing, Apparel, & Fashions",
            "type":"Retail Goods"
        }
    ],
    "sg:phone":"+61 2 9904 6401",
    "sg:postcode":"2067",
    "sg:province":"NSW",
    "sg:tags":[
        "lady",
        "wear"
    ],
    "wof:name":"Davenport Liz",
    "wof:placetype":"venue"
},
  "geometry": {"coordinates":[151.185256958,-33.7953605652],"type":"Point"}
}