{
  "type": "Feature",
  "properties": {
    "iso:country":"AU",
    "sg:address":"8 Ferguson St",
    "sg:city":"Kewdale",
    "sg:classifiers":[
        {
            "category":"Professional",
            "type":"Services"
        }
    ],
    "sg:phone":"+61 8 9353 2292",
    "sg:postcode":"6105",
    "sg:province":"WA",
    "sg:tags":[
        "transport"
    ],
    "wof:name":"Shaws Cartage Contractors",
    "wof:placetype":"venue"
},
  "geometry": {"coordinates":[115.963478088,-31.9791545868],"type":"Point"}
}