{
  "type": "Feature",
  "properties": {
    "iso:country":"AU",
    "sg:address":"Unit 6, 15 Sefton Rd",
    "sg:city":"Thornleigh",
    "sg:classifiers":[
        {
            "category":"Retail",
            "subcategory":"Auto Repair",
            "type":"Services"
        }
    ],
    "sg:phone":"+61 2 9484 5893",
    "sg:postcode":"2120",
    "sg:province":"NSW",
    "sg:tags":[
        "repairer",
        "motor",
        "engineer"
    ],
    "wof:name":"Chicks Nev Auto Service",
    "wof:placetype":"venue"
},
  "geometry": {"coordinates":[151.08404540999999,-33.7215995789],"type":"Point"}
}