{
  "type": "Feature",
  "properties": {
    "addr:full":"36 Windrest Ave Aspley QLD 4034",
    "addr:housenumber":"36",
    "addr:postcode":"4034",
    "addr:street":"Windrest Ave",
    "iso:country":"AU",
    "sg:address":"36 Windrest Ave",
    "sg:city":"Aspley",
    "sg:classifiers":[
        {
            "category":"Utilities",
            "subcategory":"Electric",
            "type":"Services"
        }
    ],
    "sg:phone":"+61 402 914 018",
    "sg:postcode":"4034",
    "sg:province":"QLD",
    "sg:tags":[
        "electrical",
        "contractor"
    ],
    "wof:name":"Andrew Knight Electrical",
    "wof:placetype":"venue"
},
  "geometry": {"coordinates":[153.019226,-27.361538],"type":"Point"}
}