{
  "type": "Feature",
  "properties": {
    "iso:country":"AU",
    "sg:address":"57 Randell St",
    "sg:city":"Mannum",
    "sg:classifiers":[
        {
            "category":"Personal",
            "subcategory":"Barber",
            "type":"Services"
        }
    ],
    "sg:phone":"+61 8 8569 1732",
    "sg:postcode":"5238",
    "sg:province":"SA",
    "wof:name":"Mannum Hair Designs",
    "wof:placetype":"venue"
},
  "geometry": {"coordinates":[139.312103272,-34.9140281677],"type":"Point"}
}