{
  "type": "Feature",
  "properties": {
    "addr:full":"Suite 5/ 1 Ashley St Hornsby NSW 2077",
    "addr:housenumber":"1",
    "addr:postcode":"2077",
    "addr:street":"Ashley St",
    "iso:country":"AU",
    "sg:address":"Suite 5/ 1 Ashley St",
    "sg:city":"Hornsby",
    "sg:classifiers":[
        {
            "category":"Health Services",
            "subcategory":"Dentist",
            "type":"Services"
        }
    ],
    "sg:phone":"+61 2 9477 7650",
    "sg:postcode":"2077",
    "sg:province":"NSW",
    "sg:tags":[
        "technician",
        "dental"
    ],
    "wof:name":"McGlynn Stephen Dental Laboratories Pty Ltd",
    "wof:placetype":"venue"
},
  "geometry": {"coordinates":[151.09727477999999,-33.7050857544],"type":"Point"}
}