{
  "type": "Feature",
  "properties": {
    "addr:full":"2 Shell St St Kilda SA 5110",
    "addr:housenumber":"2",
    "addr:postcode":"5110",
    "addr:street":"Shell St",
    "iso:country":"AU",
    "sg:address":"2 Shell St St",
    "sg:city":"Kilda",
    "sg:classifiers":[
        {
            "category":"Utilities",
            "subcategory":"Electric",
            "type":"Services"
        }
    ],
    "sg:phone":"+61 8 8280 6031",
    "sg:postcode":"5110",
    "sg:province":"SA",
    "sg:tags":[
        "electrical",
        "contractor"
    ],
    "wof:name":"Virgo Electrical Pty Ltd",
    "wof:placetype":"venue"
},
  "geometry": {"coordinates":[138.53627014200001,-34.7398948669],"type":"Point"}
}