{
  "type": "Feature",
  "properties": {
    "iso:country":"AU",
    "sg:address":"1190 Lower North East Rd",
    "sg:city":"Highbury",
    "sg:classifiers":[
        {
            "category":"Building & Trades",
            "subcategory":"Construction",
            "type":"Services"
        }
    ],
    "sg:phone":"+61 402 785 699",
    "sg:postcode":"5089",
    "sg:province":"SA",
    "sg:tags":[
        "pool",
        "swimming"
    ],
    "wof:name":"Elite Pool Constructions (SA) Pty Ltd",
    "wof:placetype":"venue"
},
  "geometry": {"coordinates":[138.71734619099999,-34.84582901],"type":"Point"}
}