{
  "type": "Feature",
  "properties": {
    "addr:full":"216 Margaret St Toowoomba QLD 4350",
    "addr:housenumber":"216",
    "addr:postcode":"4350",
    "addr:street":"Margaret St",
    "iso:country":"AU",
    "sg:address":"216 Margaret St",
    "sg:city":"Toowoomba",
    "sg:classifiers":[
        {
            "category":"Banks & Credit Unions",
            "subcategory":"Bank",
            "type":"Services"
        }
    ],
    "sg:phone":"+61 1300 651 125",
    "sg:postcode":"4350",
    "sg:province":"QLD",
    "wof:name":"Suncorp",
    "wof:placetype":"venue"
},
  "geometry": {"coordinates":[151.95220900000001,-27.560961],"type":"Point"}
}