{
  "type": "Feature",
  "properties": {
    "addr:full":"Shop 1 Lot 401 Corkhill Drv Tilba Tilba NSW 2546",
    "addr:housenumber":"shop 1 lot 401",
    "addr:postcode":"2546",
    "addr:street":"Corkhill Drv",
    "iso:country":"AU",
    "sg:address":"Shop 1 Lot 401 Corkhill Drv",
    "sg:city":"Tilba Tilba",
    "sg:classifiers":[
        {
            "category":"Cafe",
            "type":"Food & Drink"
        }
    ],
    "sg:phone":"+61 2 4473 7055",
    "sg:postcode":"2546",
    "sg:province":"NSW",
    "wof:name":"Love At First Bite",
    "wof:placetype":"venue"
},
  "geometry": {"coordinates":[150.079025269,-36.3148803711],"type":"Point"}
}