{
  "type": "Feature",
  "properties": {
    "iso:country":"AU",
    "sg:address":"Shop 14/ 7 Railway Tce",
    "sg:city":"Rockingham",
    "sg:classifiers":[
        {
            "category":"Personal",
            "subcategory":"Day Spa",
            "type":"Services"
        }
    ],
    "sg:phone":"+61 8 9529 3333",
    "sg:postcode":"6168",
    "sg:province":"WA",
    "wof:name":"Urban Retreat Day Spa",
    "wof:placetype":"venue"
},
  "geometry": {"coordinates":[115.728539,-32.275864],"type":"Point"}
}