{
  "type": "Feature",
  "properties": {
    "addr:full":"222 Ferry Rd Southport QLD 4215",
    "addr:housenumber":"222",
    "addr:postcode":"4215",
    "addr:street":"Ferry Rd",
    "iso:country":"AU",
    "sg:address":"222 Ferry Rd",
    "sg:city":"Southport",
    "sg:classifiers":[
        {
            "category":"Real Estate",
            "subcategory":"Developer",
            "type":"Services"
        }
    ],
    "sg:phone":"+61 7 5591 8808",
    "sg:postcode":"4215",
    "sg:province":"QLD",
    "sg:tags":[
        "development"
    ],
    "wof:name":"Queensland 2000",
    "wof:placetype":"venue"
},
  "geometry": {"coordinates":[153.41290283199999,-27.9896640778],"type":"Point"}
}