{
  "type": "Feature",
  "properties": {
    "addr:full":"130 Belair Rd Hawthorn SA 5062",
    "addr:housenumber":"130",
    "addr:postcode":"5062",
    "addr:street":"Belair Rd",
    "iso:country":"AU",
    "sg:address":"130 Belair Rd",
    "sg:city":"Hawthorn",
    "sg:classifiers":[
        {
            "category":"Personal",
            "subcategory":"Massage",
            "type":"Services"
        }
    ],
    "sg:phone":"+61 403 316 712",
    "sg:postcode":"5062",
    "sg:province":"SA",
    "sg:tags":[
        "therapy"
    ],
    "wof:name":"Total Body Therapy",
    "wof:placetype":"venue"
},
  "geometry": {"coordinates":[138.608886719,-34.971157074],"type":"Point"}
}