{
  "type": "Feature",
  "properties": {
    "iso:country":"AU",
    "sg:address":"130 Belair Rd",
    "sg:city":"Hawthorn",
    "sg:classifiers":[
        {
            "category":"Personal",
            "subcategory":"Massage",
            "type":"Services"
        }
    ],
    "sg:phone":"+61 403 316 712",
    "sg:postcode":"5062",
    "sg:province":"SA",
    "sg:tags":[
        "therapy"
    ],
    "wof:name":"Total Body Therapy",
    "wof:placetype":"venue"
},
  "geometry": {"coordinates":[138.608886719,-34.971157074],"type":"Point"}
}