{
  "type": "Feature",
  "properties": {
    "iso:country":"AU",
    "sg:address":"131 Old Kent Rd",
    "sg:city":"Greenacre",
    "sg:classifiers":[
        {
            "category":"Building & Trades",
            "subcategory":"Construction",
            "type":"Services"
        }
    ],
    "sg:phone":"+61 2 9758 8478",
    "sg:postcode":"2190",
    "sg:province":"NSW",
    "sg:tags":[
        "plasterboard",
        "plasterer",
        "fixer"
    ],
    "wof:name":"Conceptual Interiors Pty Ltd",
    "wof:placetype":"venue"
},
  "geometry": {"coordinates":[151.049713,-33.913612],"type":"Point"}
}