{
  "type": "Feature",
  "properties": {
    "addr:full":"Pittwater Rd Dee Why NSW 2099",
    "addr:postcode":"2099",
    "addr:street":"Pittwater Rd",
    "iso:country":"AU",
    "sg:address":"Pittwater Rd",
    "sg:city":"Dee Why",
    "sg:classifiers":[
        {
            "category":"Government",
            "subcategory":"Court House",
            "type":"Public Place"
        }
    ],
    "sg:phone":"+61 425 278 408",
    "sg:postcode":"2099",
    "sg:province":"NSW",
    "sg:tags":[
        "personal",
        "marriage",
        "family",
        "counselling"
    ],
    "wof:name":"CreativeChange Counselling Northern Beaches;",
    "wof:placetype":"venue"
},
  "geometry": {"coordinates":[151.285232544,-33.7537498474],"type":"Point"}
}