{
  "type": "Feature",
  "properties": {
    "addr:full":"346 Springvale Rd Springvale VIC 3171",
    "addr:housenumber":"346",
    "addr:postcode":"3171",
    "addr:street":"Springvale Rd",
    "iso:country":"AU",
    "sg:address":"346 Springvale Rd",
    "sg:city":"Springvale",
    "sg:classifiers":[
        {
            "category":"Health Services",
            "subcategory":"Doctor",
            "type":"Services"
        }
    ],
    "sg:phone":"+61 3 9547 0222",
    "sg:postcode":"3171",
    "sg:province":"VIC",
    "sg:tags":[
        "medical",
        "practitioner"
    ],
    "wof:name":"Szyman D",
    "wof:placetype":"venue"
},
  "geometry": {"coordinates":[145.151046753,-37.9575157166],"type":"Point"}
}