{
  "type": "Feature",
  "properties": {
    "iso:country":"AU",
    "sg:address":"Richmond St",
    "sg:city":"Wardell",
    "sg:classifiers":[
        {
            "category":"Travel",
            "subcategory":"Hotels & Motels",
            "type":"Entertainment"
        }
    ],
    "sg:phone":"+61 2 6683 4197",
    "sg:postcode":"2477",
    "sg:province":"NSW",
    "sg:tags":[
        "accommodation"
    ],
    "wof:name":"Royal Hotel Wardell",
    "wof:placetype":"venue"
},
  "geometry": {"coordinates":[153.46653747600001,-28.9518032074],"type":"Point"}
}