{
  "type": "Feature",
  "properties": {
    "addr:full":"Level 2 Building 8 Lord St Botany NSW 2019",
    "addr:housenumber":"building",
    "addr:postcode":"2019",
    "addr:street":"Lord St",
    "iso:country":"AU",
    "sg:address":"Level 2 Building 8 Lord St",
    "sg:city":"Botany",
    "sg:classifiers":[
        {
            "category":"Manufacturing",
            "subcategory":"Rubber & Plastics",
            "type":"Manufacturing & Wholesale Goods"
        }
    ],
    "sg:phone":"+61 2 8336 6363",
    "sg:postcode":"2019",
    "sg:province":"NSW",
    "sg:tags":[
        "equipment",
        "card"
    ],
    "wof:name":"ACG Smartgate Pty Ltd",
    "wof:placetype":"venue"
},
  "geometry": {"coordinates":[151.20489501899999,-33.9549865723],"type":"Point"}
}