{
  "type": "Feature",
  "properties": {
    "addr:full":"130 Watson Rd Girgarre VIC 3624",
    "addr:housenumber":"130",
    "addr:postcode":"3624",
    "addr:street":"Watson Rd",
    "iso:country":"AU",
    "sg:address":"130 Watson Rd",
    "sg:city":"Girgarre",
    "sg:classifiers":[
        {
            "category":"Farming",
            "subcategory":"Farm & Veterinary Services",
            "type":"Manufacturing & Wholesale Goods"
        }
    ],
    "sg:phone":"+61 3 5854 6564",
    "sg:postcode":"3624",
    "sg:province":"VIC",
    "sg:tags":[
        "blacksmith",
        "farrier"
    ],
    "wof:name":"Golbourn Valley Shoeing Service",
    "wof:placetype":"venue"
},
  "geometry": {"coordinates":[144.93228149399999,-36.4190444946],"type":"Point"}
}