{
  "type": "Feature",
  "properties": {
    "addr:full":"37 Gardiner St Wagga Wagga NSW 2650",
    "addr:housenumber":"37",
    "addr:postcode":"2650",
    "addr:street":"Gardiner St",
    "iso:country":"AU",
    "sg:address":"37 Gardiner St",
    "sg:city":"Wagga Wagga",
    "sg:classifiers":[
        {
            "category":"Travel",
            "subcategory":"Hotels & Motels",
            "type":"Entertainment"
        }
    ],
    "sg:phone":"+61 2 6921 2279",
    "sg:postcode":"2650",
    "sg:province":"NSW",
    "sg:tags":[
        "accommodation"
    ],
    "wof:name":"Black Swan Hotel",
    "wof:placetype":"venue"
},
  "geometry": {"coordinates":[147.373580933,-35.0906333923],"type":"Point"}
}