{
  "type": "Feature",
  "properties": {
    "addr:full":"193 Barrington St Spearwood WA 6163",
    "addr:housenumber":"193",
    "addr:postcode":"6163",
    "addr:street":"Barrington St",
    "iso:country":"AU",
    "sg:address":"193 Barrington St",
    "sg:city":"Spearwood",
    "sg:classifiers":[
        {
            "category":"Freight",
            "type":"Transportation"
        }
    ],
    "sg:phone":"+61 8 9434 2298",
    "sg:postcode":"6163",
    "sg:province":"WA",
    "sg:tags":[
        "light",
        "carrier"
    ],
    "wof:name":"Spearwood Transport",
    "wof:placetype":"venue"
},
  "geometry": {"coordinates":[115.788673,-32.116508],"type":"Point"}
}