{
  "type": "Feature",
  "properties": {
    "addr:full":"Shop 5, Yambo St Morisset NSW 2264",
    "addr:housenumber":"shop 5",
    "addr:postcode":"2264",
    "addr:street":"Yambo St",
    "iso:country":"AU",
    "sg:address":"Shop 5, Yambo St",
    "sg:city":"Morisset",
    "sg:classifiers":[
        {
            "category":"Manufacturing",
            "subcategory":"Food",
            "type":"Manufacturing & Wholesale Goods"
        }
    ],
    "sg:phone":"+61 2 4973 6508",
    "sg:postcode":"2264",
    "sg:province":"NSW",
    "sg:tags":[
        "function",
        "catering"
    ],
    "wof:name":"Henny Penny Foods",
    "wof:placetype":"venue"
},
  "geometry": {"coordinates":[151.487167,-33.107674],"type":"Point"}
}