{
  "type": "Feature",
  "properties": {
    "iso:country":"AU",
    "sg:address":"101-103 Glenferrie Rd",
    "sg:city":"Malvern",
    "sg:classifiers":[
        {
            "category":"Shopping",
            "subcategory":"Clothing, Apparel, & Fashions",
            "type":"Retail Goods"
        }
    ],
    "sg:phone":"+61 3 9509 2100",
    "sg:postcode":"3144",
    "sg:province":"VIC",
    "sg:tags":[
        "menswear"
    ],
    "wof:name":"Gaz Man",
    "wof:placetype":"venue"
},
  "geometry": {"coordinates":[145.02815246599999,-37.8624649048],"type":"Point"}
}