{
  "type": "Feature",
  "properties": {
    "iso:country":"AU",
    "sg:address":"17 Nimala St",
    "sg:city":"Rosny",
    "sg:classifiers":[
        {
            "category":"Insurance",
            "subcategory":"Hazard Insurance",
            "type":"Services"
        }
    ],
    "sg:phone":"+61 3 6244 2440",
    "sg:postcode":"7018",
    "sg:province":"TAS",
    "sg:tags":[
        "loss",
        "adjuster",
        "assessor"
    ],
    "wof:name":"Altype Pty Ltd",
    "wof:placetype":"venue"
},
  "geometry": {"coordinates":[147.35650634800001,-42.8726654053],"type":"Point"}
}