{
  "type": "Feature",
  "properties": {
    "iso:country":"AU",
    "sg:address":"16 Jackson St",
    "sg:city":"Horsham",
    "sg:classifiers":[
        {
            "category":"Building & Trades",
            "subcategory":"Plumbing",
            "type":"Services"
        }
    ],
    "sg:phone":"+61 417 381 470",
    "sg:postcode":"3400",
    "sg:province":"VIC",
    "sg:tags":[
        "plumber",
        "gasfitters"
    ],
    "wof:name":"Young John C",
    "wof:placetype":"venue"
},
  "geometry": {"coordinates":[142.189285278,-36.7231254578],"type":"Point"}
}