{
  "type": "Feature",
  "properties": {
    "addr:full":"18 Holmes Rd Moonee Ponds VIC 3039",
    "addr:housenumber":"18",
    "addr:postcode":"3039",
    "addr:street":"Holmes Rd",
    "iso:country":"AU",
    "sg:address":"18 Holmes Rd",
    "sg:city":"Moonee Ponds",
    "sg:classifiers":[
        {
            "category":"Personal",
            "subcategory":"Tattoo Parlor",
            "type":"Services"
        }
    ],
    "sg:phone":"+61 3 9370 5301",
    "sg:postcode":"3039",
    "sg:province":"VIC",
    "sg:tags":[
        "tattooing"
    ],
    "wof:name":"Soul Inn House",
    "wof:placetype":"venue"
},
  "geometry": {"coordinates":[144.918488,-37.766323],"type":"Point"}
}