{
  "type": "Feature",
  "properties": {
    "addr:full":"Suite 7, 75-79 Dempster St Esperance WA 6450",
    "addr:housenumber":"75-79",
    "addr:postcode":"6450",
    "addr:street":"Dempster St",
    "iso:country":"AU",
    "sg:address":"Suite 7, 75-79 Dempster St",
    "sg:city":"Esperance",
    "sg:classifiers":[
        {
            "category":"Professional",
            "subcategory":"Management & Consulting",
            "type":"Services"
        }
    ],
    "sg:phone":"+61 8 9071 2173",
    "sg:postcode":"6450",
    "sg:province":"WA",
    "sg:tags":[
        "consultant",
        "business"
    ],
    "wof:name":"Smith Shearer",
    "wof:placetype":"venue"
},
  "geometry": {"coordinates":[121.891616821,-33.8608093262],"type":"Point"}
}