{
  "type": "Feature",
  "properties": {
    "addr:full":"Unit 4 & 5 Two Rocks Marina Sovereign Drv Two Rocks WA 6037",
    "addr:housenumber":"&",
    "addr:postcode":"6037",
    "addr:street":"Sovereign Drv",
    "iso:country":"AU",
    "sg:address":"Unit 4 & 5 Two Rocks Marina Sovereign Drv",
    "sg:city":"Two Rocks",
    "sg:classifiers":[
        {
            "category":"Autos & Motor Vehicles",
            "subcategory":"Boat Sales",
            "type":"Retail Goods"
        }
    ],
    "sg:phone":"+61 8 9561 5555",
    "sg:postcode":"6037",
    "sg:province":"WA",
    "sg:tags":[
        "yacht"
    ],
    "wof:name":"Two Rocks Marine Boat Brokers",
    "wof:placetype":"venue"
},
  "geometry": {"coordinates":[115.58869934099999,-31.5012874603],"type":"Point"}
}