{
  "type": "Feature",
  "properties": {
    "addr:full":"Coolamon Scenic Drv Coorabell NSW 2479",
    "addr:postcode":"2479",
    "addr:street":"Scenic Drv",
    "iso:country":"AU",
    "sg:address":"Coolamon Scenic Drv",
    "sg:city":"Coorabell",
    "sg:classifiers":[
        {
            "category":"Real Estate",
            "subcategory":"Surveying",
            "type":"Services"
        }
    ],
    "sg:phone":"+61 2 6684 7799",
    "sg:postcode":"2479",
    "sg:province":"NSW",
    "sg:tags":[
        "surveyor",
        "land"
    ],
    "wof:name":"Prikulis Robert",
    "wof:placetype":"venue"
},
  "geometry": {"coordinates":[153.50253295900001,-28.6319293976],"type":"Point"}
}