{
  "type": "Feature",
  "properties": {
    "addr:full":"82 Hamilton Rd Fairfield NSW 2165",
    "addr:housenumber":"82",
    "addr:postcode":"2165",
    "addr:street":"Hamilton Rd",
    "iso:country":"AU",
    "sg:address":"82 Hamilton Rd",
    "sg:city":"Fairfield",
    "sg:classifiers":[
        {
            "category":"Retail",
            "subcategory":"Auto Repair",
            "type":"Services"
        }
    ],
    "sg:phone":"+61 2 9727 4006",
    "sg:postcode":"2165",
    "sg:province":"NSW",
    "sg:tags":[
        "beater",
        "painter",
        "panel"
    ],
    "wof:name":"Hamilton Road Smash Repairs",
    "wof:placetype":"venue"
},
  "geometry": {"coordinates":[150.95010375999999,-33.8730812073],"type":"Point"}
}