{
  "type": "Feature",
  "properties": {
    "iso:country":"AU",
    "sg:address":"30 Craig St",
    "sg:city":"Long Gully",
    "sg:classifiers":[
        {
            "category":"Home & Garden",
            "subcategory":"Building Materials",
            "type":"Retail Goods"
        }
    ],
    "sg:phone":"+61 3 5442 6226",
    "sg:postcode":"3550",
    "sg:province":"VIC",
    "sg:tags":[
        "roofing"
    ],
    "wof:name":"Surdex Steel Pty Ltd",
    "wof:placetype":"venue"
},
  "geometry": {"coordinates":[144.26121520999999,-36.7422409058],"type":"Point"}
}