{
  "type": "Feature",
  "properties": {
    "iso:country":"AU",
    "sg:address":"1/ 10 Archibald St",
    "sg:city":"Toowoomba",
    "sg:classifiers":[
        {
            "category":"Shopping",
            "subcategory":"Computers & Home Electronics",
            "type":"Retail Goods"
        }
    ],
    "sg:phone":"+61 7 4637 8811",
    "sg:postcode":"4350",
    "sg:province":"QLD",
    "sg:tags":[
        "hardware",
        "equipment"
    ],
    "sg:website":"http://www.qcp.com.au",
    "wof:name":"Queensland Computers & Peripherals",
    "wof:placetype":"venue"
},
  "geometry": {"coordinates":[151.955276,-27.554253],"type":"Point"}
}