{
  "type": "Feature",
  "properties": {
    "addr:full":"65 Anderson St Cairns QLD 4870",
    "addr:housenumber":"65",
    "addr:postcode":"4870",
    "addr:street":"Anderson St",
    "iso:country":"AU",
    "sg:address":"65 Anderson St",
    "sg:city":"Cairns",
    "sg:classifiers":[
        {
            "category":"Wholesale",
            "subcategory":"Metals & Minerals",
            "type":"Manufacturing & Wholesale Goods"
        }
    ],
    "sg:phone":"+61 7 4051 4413",
    "sg:postcode":"4870",
    "sg:province":"QLD",
    "sg:tags":[
        "equipment",
        "prospecting",
        "gold"
    ],
    "wof:name":"Nth Qld Miners Den",
    "wof:placetype":"venue"
},
  "geometry": {"coordinates":[145.74911499000001,-16.9149684906],"type":"Point"}
}