{
  "type": "Feature",
  "properties": {
    "addr:full":"2 Robertson Rd Woonona NSW 2517",
    "addr:housenumber":"2",
    "addr:postcode":"2517",
    "addr:street":"Robertson Rd",
    "iso:country":"AU",
    "sg:address":"2 Robertson Rd",
    "sg:city":"Woonona",
    "sg:classifiers":[
        {
            "category":"Sports & Exercise",
            "subcategory":"Gym",
            "type":"Entertainment"
        }
    ],
    "sg:phone":"+61 2 4283 6881",
    "sg:postcode":"2517",
    "sg:province":"NSW",
    "sg:tags":[
        "health",
        "fitness"
    ],
    "wof:name":"Be Will Management",
    "wof:placetype":"venue"
},
  "geometry": {"coordinates":[150.91877700000001,-34.353161],"type":"Point"}
}