{
  "type": "Feature",
  "properties": {
    "iso:country":"AU",
    "sg:address":"Shop 40, Stables Shopping Centre, Childs Road",
    "sg:city":"Mill Park",
    "sg:classifiers":[
        {
            "category":"Health Services",
            "subcategory":"Doctor",
            "type":"Services"
        }
    ],
    "sg:phone":"+61 3 9436 6000",
    "sg:postcode":"3082",
    "sg:province":"VIC",
    "sg:tags":[
        "medical",
        "practitioner"
    ],
    "wof:name":"Mill Park Betta Health",
    "wof:placetype":"venue"
},
  "geometry": {"coordinates":[145.061935425,-37.667137146],"type":"Point"}
}