{
  "type": "Feature",
  "properties": {
    "addr:full":"Keegan St Mt Gambier SA 5290",
    "addr:postcode":"5290",
    "addr:street":"Keegan St",
    "iso:country":"AU",
    "sg:address":"Keegan St",
    "sg:city":"Mt Gambier",
    "sg:classifiers":[
        {
            "category":"Sports & Exercise",
            "subcategory":"Gym",
            "type":"Entertainment"
        }
    ],
    "sg:phone":"+61 8 8723 5555",
    "sg:postcode":"5290",
    "sg:province":"SA",
    "sg:tags":[
        "health",
        "fitness"
    ],
    "wof:name":"Tonic Health Club",
    "wof:placetype":"venue"
},
  "geometry": {"coordinates":[140.78654499999999,-37.827961],"type":"Point"}
}