{
  "type": "Feature",
  "properties": {
    "addr:full":"3a / 10 College Ave Shellharbour City Centre NSW 2529",
    "addr:housenumber":"3a / 10",
    "addr:postcode":"2529",
    "addr:street":"College Ave",
    "iso:country":"AU",
    "sg:address":"3a / 10 College Ave",
    "sg:city":"Shellharbour City Centre",
    "sg:classifiers":[
        {
            "category":"Health Services",
            "subcategory":"Doctor",
            "type":"Services"
        }
    ],
    "sg:phone":"+61 2 4297 8033",
    "sg:postcode":"2529",
    "sg:province":"NSW",
    "sg:tags":[
        "medical",
        "practitioner"
    ],
    "wof:name":"South Coast Nuclear Medicine",
    "wof:placetype":"venue"
},
  "geometry": {"coordinates":[150.83700561500001,-34.5616111755],"type":"Point"}
}