{
  "type": "Feature",
  "properties": {
    "addr:full":"5 Victoria Ave Concord West NSW 2138",
    "addr:housenumber":"5",
    "addr:postcode":"2138",
    "addr:street":"Victoria Ave",
    "iso:country":"AU",
    "sg:address":"5 Victoria Ave",
    "sg:city":"Concord West",
    "sg:classifiers":[
        {
            "category":"Health Services",
            "subcategory":"Doctor",
            "type":"Services"
        }
    ],
    "sg:phone":"+61 2 9743 1054",
    "sg:postcode":"2138",
    "sg:province":"NSW",
    "sg:tags":[
        "medical",
        "practitioner"
    ],
    "wof:name":"Muller Bede K",
    "wof:placetype":"venue"
},
  "geometry": {"coordinates":[151.08877563499999,-33.8477592468],"type":"Point"}
}