{
  "type": "Feature",
  "properties": {
    "addr:full":"3 Lyons St Newstead VIC 3462",
    "addr:housenumber":"3",
    "addr:postcode":"3462",
    "addr:street":"Lyons St",
    "iso:country":"AU",
    "sg:address":"3 Lyons St",
    "sg:city":"Newstead",
    "sg:classifiers":[
        {
            "category":"Shopping",
            "subcategory":"News",
            "type":"Retail Goods"
        }
    ],
    "sg:phone":"+61 3 5476 2777",
    "sg:postcode":"3462",
    "sg:province":"VIC",
    "sg:tags":[
        "magazine",
        "periodical"
    ],
    "wof:name":"Newstead Press",
    "wof:placetype":"venue"
},
  "geometry": {"coordinates":[144.06175231899999,-37.106590271],"type":"Point"}
}