{
  "type": "Feature",
  "properties": {
    "iso:country":"AU",
    "sg:address":"Level 2, 11 Ruth St",
    "sg:city":"Perth",
    "sg:classifiers":[
        {
            "category":"Real Estate",
            "subcategory":"Architect",
            "type":"Services"
        }
    ],
    "sg:phone":"+61 8 9328 6659",
    "sg:postcode":"6000",
    "sg:province":"WA",
    "sg:tags":[
        "building",
        "designer"
    ],
    "wof:name":"Casella Designs",
    "wof:placetype":"venue"
},
  "geometry": {"coordinates":[115.862983704,-31.941865921],"type":"Point"}
}