{
  "type": "Feature",
  "properties": {
    "addr:full":"Christie Centre, 320 Adelaide St Brisbane QLD 4000",
    "addr:housenumber":"320",
    "addr:postcode":"4000",
    "addr:street":"Adelaide St",
    "iso:country":"AU",
    "sg:address":"Christie Centre, 320 Adelaide St",
    "sg:city":"Brisbane",
    "sg:classifiers":[
        {
            "category":"Professional",
            "subcategory":"Business Services",
            "type":"Services"
        }
    ],
    "sg:phone":"+61 7 3010 9788",
    "sg:postcode":"4000",
    "sg:province":"QLD",
    "sg:tags":[
        "broker"
    ],
    "wof:name":"Business Sales Australia",
    "wof:placetype":"venue"
},
  "geometry": {"coordinates":[153.02923584000001,-27.4649868011],"type":"Point"}
}