{
  "type": "Feature",
  "properties": {
    "addr:full":"Cnr Curragundi Rd & Arrabri Ave Jindalee QLD 4074",
    "addr:postcode":"4074",
    "addr:street":"Cnr Curragundi Rd & Arrabri Ave",
    "iso:country":"AU",
    "sg:address":"Cnr Curragundi Rd & Arrabri Ave",
    "sg:city":"Jindalee",
    "sg:classifiers":[
        {
            "category":"Real Estate",
            "subcategory":"Real Estate Agent",
            "type":"Services"
        }
    ],
    "sg:phone":"+61 7 3376 3055",
    "sg:postcode":"4074",
    "sg:province":"QLD",
    "wof:name":"Bennett Paul Real Estate The Professionals",
    "wof:placetype":"venue"
},
  "geometry": {"coordinates":[152.94172668499999,-27.5363082886],"type":"Point"}
}