{
  "type": "Feature",
  "properties": {
    "iso:country":"AU",
    "sg:address":"PO Box 711",
    "sg:city":"Virginia",
    "sg:classifiers":[
        {
            "category":"Professional",
            "subcategory":"Management & Consulting",
            "type":"Services"
        }
    ],
    "sg:phone":"+61 416 274 201",
    "sg:postcode":"4014",
    "sg:province":"QLD",
    "sg:tags":[
        "consultant",
        "energy"
    ],
    "wof:name":"Utilimax",
    "wof:placetype":"venue"
},
  "geometry": {"coordinates":[153.06463623100001,-27.3816890717],"type":"Point"}
}