{
  "type": "Feature",
  "properties": {
    "addr:full":"8 Cedrela St Moggill QLD 4070",
    "addr:housenumber":"8",
    "addr:postcode":"4070",
    "addr:street":"Cedrela St",
    "iso:country":"AU",
    "sg:address":"8 Cedrela St",
    "sg:city":"Moggill",
    "sg:classifiers":[
        {
            "category":"Professional",
            "subcategory":"Employment Agencies",
            "type":"Services"
        }
    ],
    "sg:phone":"+61 7 3202 5602",
    "sg:postcode":"4070",
    "sg:province":"QLD",
    "wof:name":"The Right Step for You",
    "wof:placetype":"venue"
},
  "geometry": {"coordinates":[152.88771057100001,-27.5688209534],"type":"Point"}
}