{
  "type": "Feature",
  "properties": {
    "iso:country":"AU",
    "sg:address":"Lot 21 Cashmore Rd",
    "sg:city":"Portland",
    "sg:classifiers":[
        {
            "category":"Home & Garden",
            "subcategory":"Garden Supply",
            "type":"Retail Goods"
        }
    ],
    "sg:phone":"+61 3 5523 6642",
    "sg:postcode":"3305",
    "sg:province":"VIC",
    "sg:tags":[
        "landscape"
    ],
    "wof:name":"Lovells Garden Supplies",
    "wof:placetype":"venue"
},
  "geometry": {"coordinates":[141.591064453,-38.3216819763],"type":"Point"}
}