{
  "type": "Feature",
  "properties": {
    "iso:country":"AU",
    "sg:address":"5 Hughes St",
    "sg:city":"Berri",
    "sg:classifiers":[
        {
            "category":"Building & Trades",
            "subcategory":"Construction",
            "type":"Services"
        }
    ],
    "sg:phone":"+61 8 8582 2731",
    "sg:postcode":"5343",
    "sg:province":"SA",
    "sg:tags":[
        "monumental",
        "mason"
    ],
    "wof:name":"Riverland Memorials",
    "wof:placetype":"venue"
},
  "geometry": {"coordinates":[140.60125732399999,-34.2713279724],"type":"Point"}
}