{
  "type": "Feature",
  "properties": {
    "addr:full":"28 Brookvale Ave Brookvale NSW 2100",
    "addr:housenumber":"28",
    "addr:postcode":"2100",
    "addr:street":"Brookvale Ave",
    "iso:country":"AU",
    "sg:address":"28 Brookvale Ave",
    "sg:city":"Brookvale",
    "sg:classifiers":[
        {
            "category":"Personal",
            "type":"Services"
        }
    ],
    "sg:phone":"+61 2 9907 2210",
    "sg:postcode":"2100",
    "sg:province":"NSW",
    "sg:tags":[
        "reducing",
        "treatment",
        "weight"
    ],
    "wof:name":"Herbalife Brookvale",
    "wof:placetype":"venue"
},
  "geometry": {"coordinates":[151.26742553700001,-33.7621002197],"type":"Point"}
}