{
  "type": "Feature",
  "properties": {
    "addr:full":"20 Aspen Ave Terrigal NSW 2260",
    "addr:housenumber":"20",
    "addr:postcode":"2260",
    "addr:street":"Aspen Ave",
    "iso:country":"AU",
    "sg:address":"20 Aspen Ave",
    "sg:city":"Terrigal",
    "sg:classifiers":[
        {
            "category":"Health Services",
            "subcategory":"Doctor",
            "type":"Services"
        }
    ],
    "sg:phone":"+61 2 4384 3880",
    "sg:postcode":"2260",
    "sg:province":"NSW",
    "sg:tags":[
        "reflexology"
    ],
    "wof:name":"Terrigal Health & Harmony",
    "wof:placetype":"venue"
},
  "geometry": {"coordinates":[151.43351699999999,-33.433422],"type":"Point"}
}