{
  "type": "Feature",
  "properties": {
    "addr:full":"97 Rose St Wooloowin QLD 4030",
    "addr:housenumber":"97",
    "addr:postcode":"4030",
    "addr:street":"Rose St",
    "iso:country":"AU",
    "sg:address":"97 Rose St",
    "sg:city":"Wooloowin",
    "sg:classifiers":[
        {
            "category":"Travel",
            "subcategory":"Travel Agent",
            "type":"Entertainment"
        }
    ],
    "sg:phone":"+61 7 3857 1444",
    "sg:postcode":"4030",
    "sg:province":"QLD",
    "sg:tags":[
        "consultant"
    ],
    "wof:name":"Lets Travel Corporate Services",
    "wof:placetype":"venue"
},
  "geometry": {"coordinates":[153.04693599999999,-27.414513],"type":"Point"}
}