{
  "type": "Feature",
  "properties": {
    "iso:country":"AU",
    "sg:address":"Unit 1 11 Watt St",
    "sg:city":"Newcastle",
    "sg:classifiers":[
        {
            "category":"Professional",
            "subcategory":"Business Services",
            "type":"Services"
        }
    ],
    "sg:phone":"+61 2 4925 3030",
    "sg:postcode":"2300",
    "sg:province":"NSW",
    "sg:tags":[
        "management",
        "event"
    ],
    "wof:name":"Bluefish Corporate Events",
    "wof:placetype":"venue"
},
  "geometry": {"coordinates":[151.78471400000001,-32.92728],"type":"Point"}
}