{
  "type": "Feature",
  "properties": {
    "addr:full":"184 Main St Bairnsdale VIC 3875",
    "addr:housenumber":"184",
    "addr:postcode":"3875",
    "addr:street":"Main St",
    "iso:country":"AU",
    "sg:address":"184 Main St",
    "sg:city":"Bairnsdale",
    "sg:classifiers":[
        {
            "category":"Personal",
            "subcategory":"Massage",
            "type":"Services"
        }
    ],
    "sg:phone":"+61 3 5152 4257",
    "sg:postcode":"3875",
    "sg:province":"VIC",
    "sg:tags":[
        "therapy"
    ],
    "wof:name":"Bairnsdale Nutrition Centre",
    "wof:placetype":"venue"
},
  "geometry": {"coordinates":[147.827224731,-37.7086296082],"type":"Point"}
}