{
  "type": "Feature",
  "properties": {
    "addr:full":"620 Kingsford Smith Drv Hamilton QLD 4007",
    "addr:housenumber":"620",
    "addr:postcode":"4007",
    "addr:street":"Kingsford Smith Drv",
    "iso:country":"AU",
    "sg:address":"620 Kingsford Smith Drv",
    "sg:city":"Hamilton",
    "sg:classifiers":[
        {
            "category":"Travel",
            "subcategory":"Hotels & Motels",
            "type":"Entertainment"
        }
    ],
    "sg:phone":"+61 7 3268 5899",
    "sg:postcode":"4007",
    "sg:province":"QLD",
    "wof:name":"Quality Inn Airport Heritage",
    "wof:placetype":"venue"
},
  "geometry": {"coordinates":[153.073013,-27.436527],"type":"Point"}
}