{
  "type": "Feature",
  "properties": {
    "addr:full":"Ste111/ 283 Alfred St North Sydney NSW 2060",
    "addr:housenumber":"283",
    "addr:postcode":"2060",
    "addr:street":"Alfred St",
    "iso:country":"AU",
    "sg:address":"Ste111/ 283 Alfred St",
    "sg:city":"North Sydney",
    "sg:classifiers":[
        {
            "category":"Shopping",
            "subcategory":"Stationery & Office Supplies",
            "type":"Retail Goods"
        }
    ],
    "sg:phone":"+61 2 9922 3388",
    "sg:postcode":"2060",
    "sg:province":"NSW",
    "sg:tags":[
        "partition"
    ],
    "wof:name":"Cedarcrest Australia Pty Ltd",
    "wof:placetype":"venue"
},
  "geometry": {"coordinates":[151.20587158199999,-33.8326263428],"type":"Point"}
}