{
  "type": "Feature",
  "properties": {
    "addr:full":"Fcty6/ 69 Elm Park Drv Hoppers Crossing VIC 3029",
    "addr:housenumber":"69",
    "addr:postcode":"3029",
    "addr:street":"Elm Park Drv",
    "iso:country":"AU",
    "sg:address":"Fcty6/ 69 Elm Park Drv",
    "sg:city":"Hoppers Crossing",
    "sg:classifiers":[
        {
            "category":"Wholesale",
            "subcategory":"Machinery & Supplies",
            "type":"Manufacturing & Wholesale Goods"
        }
    ],
    "sg:phone":"+61 3 9974 6545",
    "sg:postcode":"3029",
    "sg:province":"VIC",
    "sg:tags":[
        "distributor",
        "crane",
        "mfrs"
    ],
    "wof:name":"West Crane Services Pty Ltd",
    "wof:placetype":"venue"
},
  "geometry": {"coordinates":[144.719055,-37.87088],"type":"Point"}
}