{
  "type": "Feature",
  "properties": {
    "iso:country":"AU",
    "sg:address":"101 Edward St",
    "sg:city":"East Perth",
    "sg:classifiers":[
        {
            "category":"Restaurant",
            "type":"Food & Drink"
        }
    ],
    "sg:phone":"+61 8 9328 1143",
    "sg:postcode":"6004",
    "sg:province":"WA",
    "sg:website":"http://www.accoladewa.com.au",
    "wof:name":"The Coolgardie Safe",
    "wof:placetype":"venue"
},
  "geometry": {"coordinates":[115.869010925,-31.9476337433],"type":"Point"}
}