{
  "type": "Feature",
  "properties": {
    "addr:full":"41- 45 Princess Hwy St Peters NSW 2044",
    "addr:housenumber":"45",
    "addr:postcode":"2044",
    "addr:street":"Princess Hwy",
    "iso:country":"AU",
    "sg:address":"41- 45 Princess Hwy St",
    "sg:city":"Peters",
    "sg:classifiers":[
        {
            "category":"Manufacturing",
            "subcategory":"Textiles",
            "type":"Manufacturing & Wholesale Goods"
        }
    ],
    "sg:phone":"+61 2 9550 1055",
    "sg:postcode":"2044",
    "sg:province":"NSW",
    "sg:tags":[
        "wholesaler",
        "knitwear",
        "mfrs"
    ],
    "wof:name":"Boulevarde Corporation Pty Ltd. Decoy Sydney",
    "wof:placetype":"venue"
},
  "geometry": {"coordinates":[151.18038899999999,-33.910229],"type":"Point"}
}