{
  "type": "Feature",
  "properties": {
    "iso:country":"AU",
    "sg:address":"Ste14/ 849 South Dowling St",
    "sg:city":"Waterloo",
    "sg:classifiers":[
        {
            "category":"Professional",
            "subcategory":"Computer Services",
            "type":"Services"
        }
    ],
    "sg:phone":"+61 2 9310 3935",
    "sg:postcode":"2017",
    "sg:province":"NSW",
    "sg:tags":[
        "repairs",
        "upgrade",
        "equipment"
    ],
    "wof:name":"Key-Tech Computers",
    "wof:placetype":"venue"
},
  "geometry": {"coordinates":[151.21534729000001,-33.8979644775],"type":"Point"}
}