{
  "type": "Feature",
  "properties": {
    "addr:full":"53 Eppalock Dr Wyndham Vale VIC 3024",
    "addr:housenumber":"53",
    "addr:postcode":"3024",
    "addr:street":"Eppalock Dr",
    "iso:country":"AU",
    "sg:address":"53 Eppalock Dr",
    "sg:city":"Wyndham Vale",
    "sg:classifiers":[
        {
            "category":"Professional",
            "subcategory":"Accounting & Tax Preparation",
            "type":"Services"
        }
    ],
    "sg:phone":"+61 412 811 702",
    "sg:postcode":"3024",
    "sg:province":"VIC",
    "sg:tags":[
        "accountant",
        "auditor"
    ],
    "wof:name":"MId-Year Taxation and Accounting Experts Pty Ltd.",
    "wof:placetype":"venue"
},
  "geometry": {"coordinates":[144.609711,-37.880272],"type":"Point"}
}