{
  "type": "Feature",
  "properties": {
    "addr:full":"23 Stone St Stafford QLD 4053",
    "addr:housenumber":"23",
    "addr:postcode":"4053",
    "addr:street":"Stone St",
    "iso:country":"AU",
    "sg:address":"23 Stone St",
    "sg:city":"Stafford",
    "sg:classifiers":[
        {
            "category":"Retail",
            "subcategory":"Auto Repair",
            "type":"Services"
        }
    ],
    "sg:phone":"+61 7 3356 7366",
    "sg:postcode":"4053",
    "sg:province":"QLD",
    "sg:tags":[
        "repairer",
        "motor",
        "engineer"
    ],
    "wof:name":"Northern Suburbs Automatic Transmissions",
    "wof:placetype":"venue"
},
  "geometry": {"coordinates":[153.015060425,-27.4160232544],"type":"Point"}
}