{
  "type": "Feature",
  "properties": {
    "iso:country":"AU",
    "sg:address":"26-28 Tarwin St",
    "sg:city":"Morwell",
    "sg:classifiers":[
        {
            "category":"Education",
            "subcategory":"Special Training",
            "type":"Public Place"
        }
    ],
    "sg:phone":"+61 3 5134 5890",
    "sg:postcode":"3840",
    "sg:province":"VIC",
    "sg:tags":[
        "development"
    ],
    "wof:name":"Employment Innovations Victoria Training & Development",
    "wof:placetype":"venue"
},
  "geometry": {"coordinates":[146.39686584500001,-38.2401351929],"type":"Point"}
}