{
  "type": "Feature",
  "properties": {
    "addr:full":"1 Elgata St The Gap QLD 4061",
    "addr:housenumber":"1",
    "addr:postcode":"4061",
    "addr:street":"Elgata St",
    "iso:country":"AU",
    "sg:address":"1 Elgata St",
    "sg:city":"The Gap",
    "sg:classifiers":[
        {
            "category":"Retail",
            "subcategory":"Auto Repair",
            "type":"Services"
        }
    ],
    "sg:phone":"+61 419 996 713",
    "sg:postcode":"4061",
    "sg:province":"QLD",
    "sg:tags":[
        "repairer",
        "motor",
        "engineer"
    ],
    "wof:name":"The Flying Mechanics",
    "wof:placetype":"venue"
},
  "geometry": {"coordinates":[152.93629455600001,-27.4492282867],"type":"Point"}
}