{
  "type": "Feature",
  "properties": {
    "iso:country":"AU",
    "sg:address":"Unit 3, 277 Lane Cove Rd",
    "sg:city":"North Ryde",
    "sg:classifiers":[
        {
            "category":"Shopping",
            "subcategory":"Computers & Home Electronics",
            "type":"Retail Goods"
        }
    ],
    "sg:phone":"+61 2 9889 4011",
    "sg:postcode":"2113",
    "sg:province":"NSW",
    "sg:tags":[
        "equipment",
        "part",
        "electronic"
    ],
    "wof:name":"Franklin Electronic Publishers",
    "wof:placetype":"venue"
},
  "geometry": {"coordinates":[151.129272461,-33.7846031189],"type":"Point"}
}