{
  "type": "Feature",
  "properties": {
    "addr:full":"Walmar Rd Kootingal NSW 2352",
    "addr:postcode":"2352",
    "addr:street":"Walmar Rd",
    "iso:country":"AU",
    "sg:address":"Walmar Rd",
    "sg:city":"Kootingal",
    "sg:classifiers":[
        {
            "category":"Wholesale",
            "subcategory":"Farm Supplies",
            "type":"Manufacturing & Wholesale Goods"
        }
    ],
    "sg:phone":"+61 2 6760 5191",
    "sg:postcode":"2352",
    "sg:province":"NSW",
    "sg:tags":[
        "feed",
        "supplement",
        "stock"
    ],
    "wof:name":"Maleea Hay",
    "wof:placetype":"venue"
},
  "geometry": {"coordinates":[151.04945373499999,-31.0528793335],"type":"Point"}
}