{
  "type": "Feature",
  "properties": {
    "addr:full":"8 Lentara St Currimundi QLD 4551",
    "addr:housenumber":"8",
    "addr:postcode":"4551",
    "addr:street":"Lentara St",
    "iso:country":"AU",
    "sg:address":"8 Lentara St",
    "sg:city":"Currimundi",
    "sg:classifiers":[
        {
            "category":"Building & Trades",
            "subcategory":"Pest Control",
            "type":"Services"
        }
    ],
    "sg:phone":"+61 7 5492 6112",
    "sg:postcode":"4551",
    "sg:province":"QLD",
    "wof:name":"Kings Carpet Kleaning & Pest Control",
    "wof:placetype":"venue"
},
  "geometry": {"coordinates":[153.12005615199999,-26.7750225067],"type":"Point"}
}