{
  "type": "Feature",
  "properties": {
    "iso:country":"AU",
    "sg:address":"Suite 5, Lvl 5, 20 Macquarie St",
    "sg:city":"Parramatta",
    "sg:classifiers":[
        {
            "category":"Professional",
            "subcategory":"Employment Agencies",
            "type":"Services"
        }
    ],
    "sg:phone":"+61 2 9687 7166",
    "sg:postcode":"2150",
    "sg:province":"NSW",
    "sg:website":"http://www.chefnet.net.au",
    "wof:name":"Chefnet",
    "wof:placetype":"venue"
},
  "geometry": {"coordinates":[150.94453430199999,-33.8707733154],"type":"Point"}
}