{
  "type": "Feature",
  "properties": {
    "iso:country":"AU",
    "sg:address":"Shop 9 Carine Glade Shopng Cntr",
    "sg:city":"Carine",
    "sg:classifiers":[
        {
            "category":"Shopping",
            "subcategory":"Clothing, Apparel, & Fashions",
            "type":"Retail Goods"
        }
    ],
    "sg:phone":"+61 8 9448 8666",
    "sg:postcode":"6020",
    "sg:province":"WA",
    "sg:tags":[
        "sportswear"
    ],
    "wof:name":"Jim Kidd Sports",
    "wof:placetype":"venue"
},
  "geometry": {"coordinates":[115.81186676,-31.8384094238],"type":"Point"}
}