{
  "type": "Feature",
  "properties": {
    "iso:country":"AU",
    "sg:address":"268 Boundary Rd",
    "sg:city":"Shepparton East",
    "sg:classifiers":[
        {
            "category":"Manufacturing",
            "subcategory":"Furniture",
            "type":"Manufacturing & Wholesale Goods"
        }
    ],
    "sg:phone":"+61 438 712 229",
    "sg:postcode":"3631",
    "sg:province":"VIC",
    "sg:tags":[
        "builder",
        "designer",
        "custom"
    ],
    "wof:name":"Metalogy",
    "wof:placetype":"venue"
},
  "geometry": {"coordinates":[145.49826049800001,-36.382068634],"type":"Point"}
}