{
  "type": "Feature",
  "properties": {
    "addr:full":"22 Oxford St Nebo QLD 4742",
    "addr:housenumber":"22",
    "addr:postcode":"4742",
    "addr:street":"Oxford St",
    "iso:country":"AU",
    "sg:address":"22 Oxford St",
    "sg:city":"Nebo",
    "sg:classifiers":[
        {
            "category":"Education",
            "subcategory":"School",
            "type":"Public Place"
        }
    ],
    "sg:phone":"+61 7 4950 5211",
    "sg:postcode":"4742",
    "sg:province":"QLD",
    "sg:tags":[
        "state",
        "except",
        "nsw"
    ],
    "wof:name":"Nebo Primary School",
    "wof:placetype":"venue"
},
  "geometry": {"coordinates":[148.69169600000001,-21.695257],"type":"Point"}
}