{
  "type": "Feature",
  "properties": {
    "addr:full":"30 Clairvaux La Bathurst NSW 2795",
    "addr:housenumber":"30",
    "addr:postcode":"2795",
    "addr:street":"Clairvaux La",
    "iso:country":"AU",
    "sg:address":"30 Clairvaux La",
    "sg:city":"Bathurst",
    "sg:classifiers":[
        {
            "category":"Building & Trades",
            "subcategory":"Plumbing",
            "type":"Services"
        }
    ],
    "sg:phone":"+61 419 635 425",
    "sg:postcode":"2795",
    "sg:province":"NSW",
    "sg:tags":[
        "plumber",
        "gasfitters"
    ],
    "wof:name":"Mark Tobin Plumbing Pty Ltd",
    "wof:placetype":"venue"
},
  "geometry": {"coordinates":[149.55354309099999,-33.5437316895],"type":"Point"}
}