{
  "type": "Feature",
  "properties": {
    "iso:country":"AU",
    "sg:address":"Shop 9",
    "sg:city":"Whitsunday Shopping Centre Cannonvale",
    "sg:classifiers":[
        {
            "category":"Shopping",
            "subcategory":"Clothing, Apparel, & Fashions",
            "type":"Retail Goods"
        }
    ],
    "sg:phone":"+61 7 4948 0600",
    "sg:postcode":"4802",
    "sg:province":"QLD",
    "sg:tags":[
        "boutique"
    ],
    "wof:name":"Blaze",
    "wof:placetype":"venue"
},
  "geometry": {"coordinates":[148.78736877399999,-20.2876834869],"type":"Point"}
}