{
  "type": "Feature",
  "properties": {
    "iso:country":"AU",
    "sg:address":"26 Park St",
    "sg:city":"Urangan",
    "sg:classifiers":[
        {
            "category":"Utilities",
            "subcategory":"Electric",
            "type":"Services"
        }
    ],
    "sg:phone":"+61 7 4125 1024",
    "sg:postcode":"4655",
    "sg:province":"QLD",
    "sg:tags":[
        "electrical",
        "contractor"
    ],
    "wof:name":"Wilson Ian",
    "wof:placetype":"venue"
},
  "geometry": {"coordinates":[152.887634,-25.295593],"type":"Point"}
}