{
  "type": "Feature",
  "properties": {
    "iso:country":"AU",
    "sg:address":"9 Richardson St",
    "sg:city":"Pacific Paradise",
    "sg:classifiers":[
        {
            "category":"Building & Trades",
            "subcategory":"Construction",
            "type":"Services"
        }
    ],
    "sg:phone":"+61 7 5448 7243",
    "sg:postcode":"4564",
    "sg:province":"QLD",
    "sg:tags":[
        "fencing",
        "contractor"
    ],
    "wof:name":"Pricerite Fencing",
    "wof:placetype":"venue"
},
  "geometry": {"coordinates":[153.07907104500001,-26.6151504517],"type":"Point"}
}