{
  "type": "Feature",
  "properties": {
    "iso:country":"AU",
    "sg:address":"457 Peachester Rd",
    "sg:city":"Beerwah",
    "sg:classifiers":[
        {
            "category":"Building & Trades",
            "subcategory":"Landscaping Services",
            "type":"Services"
        }
    ],
    "sg:phone":"+61 7 5494 0484",
    "sg:postcode":"4519",
    "sg:province":"QLD",
    "sg:tags":[
        "firebreak",
        "clearing",
        "land",
        "contractor"
    ],
    "wof:name":"Mooloolah Valley Slashing & Mowing",
    "wof:placetype":"venue"
},
  "geometry": {"coordinates":[152.95571899999999,-26.857296],"type":"Point"}
}