{
  "type": "Feature",
  "properties": {
    "iso:country":"AU",
    "sg:address":"17 South Arm Hwy",
    "sg:city":"Mornington",
    "sg:classifiers":[
        {
            "category":"Banks & Credit Unions",
            "subcategory":"Bank",
            "type":"Services"
        }
    ],
    "sg:phone":"+61 3 6244 5544",
    "sg:postcode":"7018",
    "sg:province":"TAS",
    "sg:tags":[
        "line",
        "marking",
        "road"
    ],
    "wof:name":"Brighton Painting",
    "wof:placetype":"venue"
},
  "geometry": {"coordinates":[147.393997192,-42.8587989807],"type":"Point"}
}