{
  "type": "Feature",
  "properties": {
    "addr:full":"52 Argus St Cheltenham VIC 3192",
    "addr:housenumber":"52",
    "addr:postcode":"3192",
    "addr:street":"Argus St",
    "iso:country":"AU",
    "sg:address":"52 Argus St",
    "sg:city":"Cheltenham",
    "sg:classifiers":[
        {
            "category":"Wholesale",
            "subcategory":"Machinery & Supplies",
            "type":"Manufacturing & Wholesale Goods"
        }
    ],
    "sg:phone":"+61 3 9585 5089",
    "sg:postcode":"3192",
    "sg:province":"VIC",
    "sg:tags":[
        "instrument",
        "scientific"
    ],
    "wof:name":"Karmtek Pty Ltd",
    "wof:placetype":"venue"
},
  "geometry": {"coordinates":[145.06317138700001,-37.9589271545],"type":"Point"}
}