{
  "type": "Feature",
  "properties": {
    "addr:full":"56 Station St Wentworthville NSW 2145",
    "addr:housenumber":"56",
    "addr:postcode":"2145",
    "addr:street":"Station St",
    "iso:country":"AU",
    "sg:address":"56 Station St",
    "sg:city":"Wentworthville",
    "sg:classifiers":[
        {
            "category":"Travel",
            "subcategory":"Hotels & Motels",
            "type":"Entertainment"
        }
    ],
    "sg:phone":"+61 2 9631 8426",
    "sg:postcode":"2145",
    "sg:province":"NSW",
    "sg:tags":[
        "accommodation"
    ],
    "wof:name":"Wentworthville Hotel",
    "wof:placetype":"venue"
},
  "geometry": {"coordinates":[150.97207641599999,-33.8085670471],"type":"Point"}
}