{
  "type": "Feature",
  "properties": {
    "addr:full":"Cnr Forest Rd & Botany St Hurstville NSW 2220",
    "addr:postcode":"2220",
    "addr:street":"Cnr Forest Rd & Botany St",
    "iso:country":"AU",
    "sg:address":"Cnr Forest Rd & Botany St",
    "sg:city":"Hurstville",
    "sg:classifiers":[
        {
            "category":"Banks & Credit Unions",
            "subcategory":"Financial Services",
            "type":"Services"
        }
    ],
    "sg:phone":"+61 2 9587 3500",
    "sg:postcode":"2220",
    "sg:province":"NSW",
    "sg:tags":[
        "planning"
    ],
    "wof:name":"Associated Planners Financial Services Limited",
    "wof:placetype":"venue"
},
  "geometry": {"coordinates":[151.10104370100001,-33.9671897888],"type":"Point"}
}