{
  "type": "Feature",
  "properties": {
    "addr:full":"71 Edward Ogilvie Drv Clarenza NSW 2460",
    "addr:housenumber":"71",
    "addr:postcode":"2460",
    "addr:street":"Edward Ogilvie Drv",
    "iso:country":"AU",
    "sg:address":"71 Edward Ogilvie Drv",
    "sg:city":"Clarenza",
    "sg:classifiers":[
        {
            "category":"Building & Trades",
            "subcategory":"Construction",
            "type":"Services"
        }
    ],
    "sg:phone":"+61 2 6643 2552",
    "sg:postcode":"2460",
    "sg:province":"NSW",
    "sg:tags":[
        "roof"
    ],
    "wof:name":"Petch Geoffrey",
    "wof:placetype":"venue"
},
  "geometry": {"coordinates":[152.96441650400001,-29.7240962982],"type":"Point"}
}