{
  "type": "Feature",
  "properties": {
    "addr:full":"12 Brunker Rd Greenacre NSW 2190",
    "addr:housenumber":"12",
    "addr:postcode":"2190",
    "addr:street":"Brunker Rd",
    "iso:country":"AU",
    "sg:address":"12 Brunker Rd",
    "sg:city":"Greenacre",
    "sg:classifiers":[
        {
            "category":"Retail",
            "subcategory":"Auto Repair",
            "type":"Services"
        }
    ],
    "sg:phone":"+61 2 9796 1339",
    "sg:postcode":"2190",
    "sg:province":"NSW",
    "sg:tags":[
        "beater",
        "painter",
        "panel"
    ],
    "wof:name":"Mr Bodyworks Smash Repair Centre",
    "wof:placetype":"venue"
},
  "geometry": {"coordinates":[151.04318237300001,-33.8999176025],"type":"Point"}
}