{
  "type": "Feature",
  "properties": {
    "iso:country":"AU",
    "sg:address":"2 Blair St",
    "sg:city":"Bunbury",
    "sg:classifiers":[
        {
            "category":"Arts & Performance",
            "subcategory":"Theater",
            "type":"Entertainment"
        }
    ],
    "sg:phone":"+61 8 9791 1133",
    "sg:postcode":"6230",
    "sg:province":"WA",
    "sg:tags":[
        "theatre"
    ],
    "wof:name":"Bunbury Regional Entertainment Centre",
    "wof:placetype":"venue"
},
  "geometry": {"coordinates":[115.638138,-33.322319],"type":"Point"}
}