{
  "type": "Feature",
  "properties": {
    "addr:full":"231 King St Newtown NSW 2042",
    "addr:housenumber":"231",
    "addr:postcode":"2042",
    "addr:street":"King St",
    "iso:country":"AU",
    "sg:address":"231 King St",
    "sg:city":"Newtown",
    "sg:classifiers":[
        {
            "category":"Personal",
            "subcategory":"Beauty Salon",
            "type":"Services"
        }
    ],
    "sg:phone":"+61 2 9550 4240",
    "sg:postcode":"2042",
    "sg:province":"NSW",
    "wof:name":"Body & Soul",
    "wof:placetype":"venue"
},
  "geometry": {"coordinates":[151.18138099999999,-33.895344],"type":"Point"}
}