{
  "type": "Feature",
  "properties": {
    "addr:full":"591 South Dowling St Moore Park NSW 2021",
    "addr:housenumber":"591",
    "addr:postcode":"2021",
    "addr:street":"South Dowling St",
    "iso:country":"AU",
    "sg:address":"591 South Dowling St",
    "sg:city":"Moore Park",
    "sg:classifiers":[
        {
            "category":"Government",
            "subcategory":"Court House",
            "type":"Public Place"
        }
    ],
    "sg:phone":"+61 2 9361 4542",
    "sg:postcode":"2021",
    "sg:province":"NSW",
    "sg:tags":[
        "personal",
        "marriage",
        "family",
        "counselling"
    ],
    "wof:name":"Alcoholism Advisory Telephone Service",
    "wof:placetype":"venue"
},
  "geometry": {"coordinates":[151.21690368599999,-33.8905715942],"type":"Point"}
}