{
  "type": "Feature",
  "properties": {
    "iso:country":"AU",
    "sg:address":"38a Laddner St",
    "sg:city":"Myaree BC",
    "sg:classifiers":[
        {
            "category":"Manufacturing",
            "subcategory":"Tools & Machinery",
            "type":"Manufacturing & Wholesale Goods"
        }
    ],
    "sg:phone":"+61 417 947 873",
    "sg:postcode":"6960",
    "sg:province":"WA",
    "sg:tags":[
        "earth",
        "excavating",
        "moving",
        "equipment"
    ],
    "wof:name":"Total Plumbing & Excavations",
    "wof:placetype":"venue"
},
  "geometry": {"coordinates":[115.815689,-32.03994],"type":"Point"}
}