{
  "type": "Feature",
  "properties": {
    "addr:full":"7/ 344 Norton St Leichhardt NSW 2040",
    "addr:housenumber":"/ 344",
    "addr:postcode":"2040",
    "addr:street":"Norton St",
    "iso:country":"AU",
    "sg:address":"7/ 344 Norton St",
    "sg:city":"Leichhardt",
    "sg:classifiers":[
        {
            "category":"Personal",
            "subcategory":"Hair Removal",
            "type":"Services"
        }
    ],
    "sg:phone":"+61 2 9560 0311",
    "sg:postcode":"2040",
    "sg:province":"NSW",
    "wof:name":"Nicolsons Electrolysis",
    "wof:placetype":"venue"
},
  "geometry": {"coordinates":[151.155914,-33.875206],"type":"Point"}
}