{
  "type": "Feature",
  "properties": {
    "addr:full":"258 Warrigal Rd Burwood VIC 3125",
    "addr:housenumber":"258",
    "addr:postcode":"3125",
    "addr:street":"Warrigal Rd",
    "iso:country":"AU",
    "sg:address":"258 Warrigal Rd",
    "sg:city":"Burwood",
    "sg:classifiers":[
        {
            "category":"Health Services",
            "subcategory":"Doctor",
            "type":"Services"
        }
    ],
    "sg:phone":"+61 3 9808 3139",
    "sg:postcode":"3125",
    "sg:province":"VIC",
    "sg:tags":[
        "medical",
        "practitioner"
    ],
    "wof:name":"Dondey Dr Joanne",
    "wof:placetype":"venue"
},
  "geometry": {"coordinates":[145.09527587900001,-37.8514175415],"type":"Point"}
}