{
  "type": "Feature",
  "properties": {
    "addr:full":"9 Second Ave Bonny Hills NSW 2445",
    "addr:housenumber":"9",
    "addr:postcode":"2445",
    "addr:street":"Second Ave",
    "iso:country":"AU",
    "sg:address":"9 Second Ave",
    "sg:city":"Bonny Hills",
    "sg:classifiers":[
        {
            "category":"Building & Trades",
            "subcategory":"Construction",
            "type":"Services"
        }
    ],
    "sg:phone":"+61 2 6585 5215",
    "sg:postcode":"2445",
    "sg:province":"NSW",
    "sg:tags":[
        "contractor"
    ],
    "wof:name":"McCudden N & A",
    "wof:placetype":"venue"
},
  "geometry": {"coordinates":[152.84286499999999,-31.597172],"type":"Point"}
}