{
  "type": "Feature",
  "properties": {
    "addr:full":"414 Goodwood Rd Cumberland Park SA 5041",
    "addr:housenumber":"414",
    "addr:postcode":"5041",
    "addr:street":"Goodwood Rd",
    "iso:country":"AU",
    "sg:address":"414 Goodwood Rd",
    "sg:city":"Cumberland Park",
    "sg:classifiers":[
        {
            "category":"Real Estate",
            "subcategory":"Real Estate Agent",
            "type":"Services"
        }
    ],
    "sg:phone":"+61 8 8271 3844",
    "sg:postcode":"5041",
    "sg:province":"SA",
    "wof:name":"Venn Real Estate",
    "wof:placetype":"venue"
},
  "geometry": {"coordinates":[138.591003,-34.971233],"type":"Point"}
}