{
  "type": "Feature",
  "properties": {
    "addr:full":"Unit 14d/ 169 Unley Rd Unley SA 5061",
    "addr:housenumber":"14d / 169",
    "addr:postcode":"5061",
    "addr:street":"Unley Rd",
    "iso:country":"AU",
    "sg:address":"Unit 14d/ 169 Unley Rd",
    "sg:city":"Unley",
    "sg:classifiers":[
        {
            "category":"Professional",
            "subcategory":"Management & Consulting",
            "type":"Services"
        }
    ],
    "sg:phone":"+61 8 8357 9955",
    "sg:postcode":"5061",
    "sg:province":"SA",
    "sg:tags":[
        "consultant"
    ],
    "wof:name":"Geering Solutions",
    "wof:placetype":"venue"
},
  "geometry": {"coordinates":[138.607543945,-34.9503364563],"type":"Point"}
}