{
  "type": "Feature",
  "properties": {
    "addr:full":"1 Cleg St Artarmon NSW 2064",
    "addr:housenumber":"1",
    "addr:postcode":"2064",
    "addr:street":"Cleg St",
    "iso:country":"AU",
    "sg:address":"1 Cleg St",
    "sg:city":"Artarmon",
    "sg:classifiers":[
        {
            "category":"Sports & Exercise",
            "subcategory":"Climbing Gym",
            "type":"Entertainment"
        }
    ],
    "sg:phone":"+61 2 9436 2820",
    "sg:postcode":"2064",
    "sg:province":"NSW",
    "sg:tags":[
        "repetition",
        "engineer"
    ],
    "wof:name":"E L Williams Pty Ltd",
    "wof:placetype":"venue"
},
  "geometry": {"coordinates":[151.19187927199999,-33.8140144348],"type":"Point"}
}