{
  "type": "Feature",
  "properties": {
    "iso:country":"AU",
    "sg:address":"10 Glebe St",
    "sg:city":"Wollongong",
    "sg:classifiers":[
        {
            "category":"Building & Trades",
            "subcategory":"Construction",
            "type":"Services"
        }
    ],
    "sg:phone":"+61 414 376 228",
    "sg:postcode":"2500",
    "sg:province":"NSW",
    "sg:tags":[
        "rendering",
        "cement"
    ],
    "wof:name":"Yilmaz Cement Rendering",
    "wof:placetype":"venue"
},
  "geometry": {"coordinates":[150.896713,-34.431213],"type":"Point"}
}