{
  "type": "Feature",
  "properties": {
    "iso:country":"AU",
    "sg:address":"9 Omaha St",
    "sg:city":"Belfield",
    "sg:classifiers":[
        {
            "category":"Transit Center",
            "subcategory":"Freight",
            "type":"Transportation"
        }
    ],
    "sg:phone":"+61 411 786 276",
    "sg:postcode":"2191",
    "sg:province":"NSW",
    "sg:tags":[
        "building",
        "information"
    ],
    "wof:name":"John Makdessi",
    "wof:placetype":"venue"
},
  "geometry": {"coordinates":[151.091629,-33.906227],"type":"Point"}
}