{
  "type": "Feature",
  "properties": {
    "addr:full":"28 Hindley St Adelaide SA 5000",
    "addr:housenumber":"28",
    "addr:postcode":"5000",
    "addr:street":"Hindley St",
    "iso:country":"AU",
    "sg:address":"28 Hindley St",
    "sg:city":"Adelaide",
    "sg:classifiers":[
        {
            "category":"Professional",
            "subcategory":"Detective & Security Services",
            "type":"Services"
        }
    ],
    "sg:phone":"+61 8 8211 8199",
    "sg:postcode":"5000",
    "sg:province":"SA",
    "sg:tags":[
        "consultant",
        "system"
    ],
    "sg:website":"http://www.commercialsecurity.com.au",
    "wof:name":"Commercial Security Solutions Pty Ltd",
    "wof:placetype":"venue"
},
  "geometry": {"coordinates":[138.59823608400001,-34.9229202271],"type":"Point"}
}