{
  "type": "Feature",
  "properties": {
    "addr:full":"U22/ 9 Hoyle Ave Castle Hill NSW 2154",
    "addr:postcode":"2154",
    "addr:street":"/;Hoyle Ave",
    "iso:country":"AU",
    "sg:address":"U22/ 9 Hoyle Ave",
    "sg:city":"Castle Hill",
    "sg:classifiers":[
        {
            "category":"Professional",
            "subcategory":"Testing Lab",
            "type":"Services"
        }
    ],
    "sg:phone":"+61 2 8850 6251",
    "sg:postcode":"2154",
    "sg:province":"NSW",
    "sg:tags":[
        "equipment"
    ],
    "wof:name":"Guardian Interlock Systems",
    "wof:placetype":"venue"
},
  "geometry": {"coordinates":[150.98312377900001,-33.7314720154],"type":"Point"}
}