{
  "type": "Feature",
  "properties": {
    "addr:full":"Suite 203, 12 Waters St Neutral Bay NSW 2089",
    "addr:housenumber":"12",
    "addr:postcode":"2089",
    "addr:street":"Waters St",
    "iso:country":"AU",
    "sg:address":"Suite 203, 12 Waters St",
    "sg:city":"Neutral Bay",
    "sg:classifiers":[
        {
            "category":"Health Services",
            "subcategory":"Doctor",
            "type":"Services"
        }
    ],
    "sg:phone":"+61 2 9953 9388",
    "sg:postcode":"2089",
    "sg:province":"NSW",
    "sg:tags":[
        "nurse",
        "nursing"
    ],
    "wof:name":"Gordon Nurses",
    "wof:placetype":"venue"
},
  "geometry": {"coordinates":[151.223480225,-33.830783844],"type":"Point"}
}