{
  "type": "Feature",
  "properties": {
    "iso:country":"AU",
    "sg:address":"12 Clara St",
    "sg:city":"Logan Central",
    "sg:classifiers":[
        {
            "category":"Building & Trades",
            "subcategory":"Construction",
            "type":"Services"
        }
    ],
    "sg:phone":"+61 7 3808 1369",
    "sg:postcode":"4114",
    "sg:province":"QLD",
    "sg:tags":[
        "earth",
        "excavating",
        "moving",
        "contractor"
    ],
    "wof:name":"G & R Bobcat Hire",
    "wof:placetype":"venue"
},
  "geometry": {"coordinates":[153.11328125,-27.644744873],"type":"Point"}
}