{
  "type": "Feature",
  "properties": {
    "addr:full":"58 Quay St Bundaberg QLD 4670",
    "addr:housenumber":"58",
    "addr:postcode":"4670",
    "addr:street":"Quay St",
    "iso:country":"AU",
    "sg:address":"58 Quay St",
    "sg:city":"Bundaberg",
    "sg:classifiers":[
        {
            "category":"Banks & Credit Unions",
            "subcategory":"Financial Services",
            "type":"Services"
        }
    ],
    "sg:phone":"+61 7 4153 5558",
    "sg:postcode":"4670",
    "sg:province":"QLD",
    "sg:tags":[
        "annuity",
        "rollover",
        "superannuation",
        "consultant"
    ],
    "wof:name":"Mort Wagner Financial Services Pty Ltd",
    "wof:placetype":"venue"
},
  "geometry": {"coordinates":[152.34849548299999,-24.8659591675],"type":"Point"}
}