{
  "type": "Feature",
  "properties": {
    "iso:country":"AU",
    "sg:address":"Cnr Arthur St & Tramway Ave",
    "sg:city":"Parramatta",
    "sg:classifiers":[
        {
            "category":"Retail",
            "subcategory":"Auto Repair",
            "type":"Services"
        }
    ],
    "sg:phone":"+61 2 9841 8800",
    "sg:postcode":"2150",
    "sg:province":"NSW",
    "sg:tags":[
        "repairer",
        "motor",
        "engineer"
    ],
    "wof:name":"Trivett",
    "wof:placetype":"venue"
},
  "geometry": {"coordinates":[151.01976013199999,-33.8174934387],"type":"Point"}
}