{
  "type": "Feature",
  "properties": {
    "addr:full":"48 High St Boonah QLD 4310",
    "addr:housenumber":"48",
    "addr:postcode":"4310",
    "addr:street":"High St Boonah",
    "iso:country":"AU",
    "sg:address":"48 High St",
    "sg:city":"Boonah",
    "sg:classifiers":[
        {
            "category":"Shopping",
            "subcategory":"Crafts & Fabrics",
            "type":"Retail Goods"
        }
    ],
    "sg:phone":"+61 7 5463 1526",
    "sg:postcode":"4310",
    "sg:province":"QLD",
    "sg:tags":[
        "draper"
    ],
    "wof:name":"Maynards",
    "wof:placetype":"venue"
},
  "geometry": {"coordinates":[152.68234252900001,-27.9976043701],"type":"Point"}
}