{
  "type": "Feature",
  "properties": {
    "addr:full":"13-15 Carlisle St Camden Park SA 5038",
    "addr:housenumber":"13-15",
    "addr:postcode":"5038",
    "addr:street":"Carlisle St",
    "iso:country":"AU",
    "sg:address":"13-15 Carlisle St",
    "sg:city":"Camden Park",
    "sg:classifiers":[
        {
            "category":"Social Services",
            "subcategory":"Child Care",
            "type":"Services"
        }
    ],
    "sg:phone":"+61 8 8295 7844",
    "sg:postcode":"5038",
    "sg:province":"SA",
    "wof:name":"Camden Park Child Care Centre",
    "wof:placetype":"venue"
},
  "geometry": {"coordinates":[138.53884887699999,-34.9707221985],"type":"Point"}
}