{
  "type": "Feature",
  "properties": {
    "addr:full":"9 Mosey St Landsdale WA 6065",
    "addr:housenumber":"9",
    "addr:postcode":"6065",
    "addr:street":"Mosey St",
    "iso:country":"AU",
    "sg:address":"9 Mosey St",
    "sg:city":"Landsdale",
    "sg:classifiers":[
        {
            "category":"Retail",
            "subcategory":"Storage",
            "type":"Services"
        }
    ],
    "sg:phone":"+61 8 9303 2345",
    "sg:postcode":"6065",
    "sg:province":"WA",
    "sg:tags":[
        "removal",
        "furniture"
    ],
    "wof:name":"Statewide Removals",
    "wof:placetype":"venue"
},
  "geometry": {"coordinates":[115.84105682400001,-31.8022823334],"type":"Point"}
}