{
  "type": "Feature",
  "properties": {
    "iso:country":"AU",
    "sg:address":"Unit 1/ 74 Wellington St",
    "sg:city":"East Perth",
    "sg:classifiers":[
        {
            "category":"Retail",
            "subcategory":"Self-service Laundry",
            "type":"Services"
        }
    ],
    "sg:phone":"+61 8 9221 8255",
    "sg:postcode":"6004",
    "sg:province":"WA",
    "wof:name":"Jack's Wash House",
    "wof:placetype":"venue"
},
  "geometry": {"coordinates":[115.87310791,-31.9559860229],"type":"Point"}
}