{
  "type": "Feature",
  "properties": {
    "addr:full":"32 Phillips St Thebarton SA 5031",
    "addr:housenumber":"32",
    "addr:postcode":"5031",
    "addr:street":"Phillips St",
    "iso:country":"AU",
    "sg:address":"32 Phillips St",
    "sg:city":"Thebarton",
    "sg:classifiers":[
        {
            "category":"Deli",
            "type":"Food & Drink"
        }
    ],
    "sg:phone":"+61 8 8352 5103",
    "sg:postcode":"5031",
    "sg:province":"SA",
    "sg:tags":[
        "delicatessen"
    ],
    "wof:name":"Cassoudakis N",
    "wof:placetype":"venue"
},
  "geometry": {"coordinates":[138.57398986800001,-34.9136657715],"type":"Point"}
}