{
  "type": "Feature",
  "properties": {
    "addr:full":"Carlton Beach Rd Carlton Beach TAS 7173",
    "addr:postcode":"7173",
    "addr:street":"Beach Rd",
    "iso:country":"AU",
    "sg:address":"Carlton Beach Rd",
    "sg:city":"Carlton Beach",
    "sg:classifiers":[
        {
            "category":"Arena",
            "subcategory":"Sports Club",
            "type":"Entertainment"
        }
    ],
    "sg:phone":"+61 3 6265 8102",
    "sg:postcode":"7173",
    "sg:province":"TAS",
    "sg:tags":[
        "life",
        "surfing",
        "saving"
    ],
    "wof:name":"Carlton Park Surf Life Saving Club",
    "wof:placetype":"venue"
},
  "geometry": {"coordinates":[147.64486694300001,-42.8669891357],"type":"Point"}
}