{
  "type": "Feature",
  "properties": {
    "addr:full":"Cnr Buckley & Victoria Sts Footscray VIC 3011",
    "addr:postcode":"3011",
    "addr:street":"Cnr",
    "iso:country":"AU",
    "sg:address":"Cnr Buckley & Victoria Sts",
    "sg:city":"Footscray",
    "sg:classifiers":[
        {
            "category":"Food & Beverages",
            "subcategory":"Groceries & Convenience Stores",
            "type":"Retail Goods"
        }
    ],
    "sg:phone":"+61 3 9687 6473",
    "sg:postcode":"3011",
    "sg:province":"VIC",
    "wof:name":"Shahr Investments Pty Ltd",
    "wof:placetype":"venue"
},
  "geometry": {"coordinates":[144.88815307600001,-37.8024406433],"type":"Point"}
}