{
  "type": "Feature",
  "properties": {
    "addr:full":"Shop 93a Mt Druitt Marketown Mt Druitt NSW 2770",
    "addr:housenumber":"93a",
    "addr:postcode":"2770",
    "addr:street":"Mt",
    "iso:country":"AU",
    "sg:address":"Shop 93a Mt Druitt Marketown",
    "sg:city":"Mt Druitt",
    "sg:classifiers":[
        {
            "category":"Shopping",
            "subcategory":"Clothing, Apparel, & Fashions",
            "type":"Retail Goods"
        }
    ],
    "sg:phone":"+61 2 9832 1935",
    "sg:postcode":"2770",
    "sg:province":"NSW",
    "sg:tags":[
        "lady",
        "wear"
    ],
    "wof:name":"Silhouette",
    "wof:placetype":"venue"
},
  "geometry": {"coordinates":[150.81086730999999,-33.7738342285],"type":"Point"}
}