{
  "type": "Feature",
  "properties": {
    "addr:full":"38 Church St Wodonga VIC 3690",
    "addr:housenumber":"38",
    "addr:postcode":"3690",
    "addr:street":"Church St",
    "iso:country":"AU",
    "sg:address":"38 Church St",
    "sg:city":"Wodonga",
    "sg:classifiers":[
        {
            "category":"Building & Trades",
            "subcategory":"Construction",
            "type":"Services"
        }
    ],
    "sg:phone":"+61 1800 021 905",
    "sg:postcode":"3690",
    "sg:province":"VIC",
    "sg:tags":[
        "pool",
        "swimming"
    ],
    "wof:name":"Stid Guseli Pools Of Bendigo",
    "wof:placetype":"venue"
},
  "geometry": {"coordinates":[146.890258789,-36.115234375],"type":"Point"}
}