{
  "type": "Feature",
  "properties": {
    "addr:full":"Ormsby Terrace 7 James Service Place Mandurah WA 6210",
    "addr:housenumber":"7",
    "addr:postcode":"6210",
    "addr:street":"Ormsby Terrace;James Service Place",
    "iso:country":"AU",
    "sg:address":"Ormsby Terrace 7 James Service Place",
    "sg:city":"Mandurah",
    "sg:classifiers":[
        {
            "category":"Cinema",
            "subcategory":"Movie Theater",
            "type":"Entertainment"
        }
    ],
    "sg:phone":"+61 8 9535 2800",
    "sg:postcode":"6210",
    "sg:province":"WA",
    "wof:name":"Reading Cinemas Mandurah",
    "wof:placetype":"venue"
},
  "geometry": {"coordinates":[115.719009,-32.52689],"type":"Point"}
}