{
  "type": "Feature",
  "properties": {
    "addr:full":"322 Place Rd Geraldton WA 6530",
    "addr:housenumber":"322",
    "addr:postcode":"6530",
    "addr:street":"Place Rd",
    "iso:country":"AU",
    "sg:address":"322 Place Rd",
    "sg:city":"Geraldton",
    "sg:classifiers":[
        {
            "category":"Home & Garden",
            "subcategory":"Building Materials",
            "type":"Retail Goods"
        }
    ],
    "sg:phone":"+61 8 9964 1629",
    "sg:postcode":"6530",
    "sg:province":"WA",
    "sg:tags":[
        "merchant",
        "glass",
        "glazier"
    ],
    "wof:name":"Midwest Windscreens",
    "wof:placetype":"venue"
},
  "geometry": {"coordinates":[114.632820129,-28.7591533661],"type":"Point"}
}