{
  "type": "Feature",
  "properties": {
    "addr:full":"3 Coote Crt Currumbin QLD 4223",
    "addr:housenumber":"3",
    "addr:postcode":"4223",
    "addr:street":"Coote Crt",
    "iso:country":"AU",
    "sg:address":"3 Coote Crt",
    "sg:city":"Currumbin",
    "sg:classifiers":[
        {
            "category":"Building & Trades",
            "subcategory":"Construction",
            "type":"Services"
        }
    ],
    "sg:phone":"+61 413 266 600",
    "sg:postcode":"4223",
    "sg:province":"QLD",
    "sg:tags":[
        "brick",
        "paving"
    ],
    "wof:name":"A Class Paving",
    "wof:placetype":"venue"
},
  "geometry": {"coordinates":[153.45475769000001,-28.1454753876],"type":"Point"}
}