{
  "type": "Feature",
  "properties": {
    "iso:country":"AU",
    "sg:address":"98-100 Lucan St",
    "sg:city":"Corowa",
    "sg:classifiers":[
        {
            "category":"Freight",
            "type":"Transportation"
        }
    ],
    "sg:phone":"+61 2 6033 3111",
    "sg:postcode":"2646",
    "sg:province":"NSW",
    "sg:tags":[
        "light",
        "carrier"
    ],
    "wof:name":"PIRNAG M & S",
    "wof:placetype":"venue"
},
  "geometry": {"coordinates":[146.377853394,-36.0144996643],"type":"Point"}
}