{
  "type": "Feature",
  "properties": {
    "addr:full":"2 Loch St Nedlands WA 6009",
    "addr:housenumber":"2",
    "addr:postcode":"6009",
    "addr:street":"Loch St",
    "iso:country":"AU",
    "sg:address":"2 Loch St",
    "sg:city":"Nedlands",
    "sg:classifiers":[
        {
            "category":"Food & Beverages",
            "subcategory":"Bakery",
            "type":"Retail Goods"
        }
    ],
    "sg:phone":"+61 8 9389 1890",
    "sg:postcode":"6009",
    "sg:province":"WA",
    "sg:tags":[
        "cake",
        "shop",
        "pastry"
    ],
    "wof:name":"Maison Perry",
    "wof:placetype":"venue"
},
  "geometry": {"coordinates":[115.79151899999999,-31.975359],"type":"Point"}
}