{
  "type": "Feature",
  "properties": {
    "iso:country":"AU",
    "sg:address":"30 Short St",
    "sg:city":"Bankstown",
    "sg:phone":"+61 2 9790 2830",
    "sg:postcode":"2200",
    "sg:province":"NSW",
    "wof:name":"Sydney Glass Pty Ltd",
    "wof:placetype":"venue"
},
  "geometry": {"coordinates":[151.03801,-33.934895],"type":"Point"}
}