{
  "type": "Feature",
  "properties": {
    "addr:full":"PO Box 157 Tathra NSW 2550",
    "addr:postcode":"2550",
    "iso:country":"AU",
    "sg:address":"PO Box 157",
    "sg:city":"Tathra",
    "sg:classifiers":[
        {
            "category":"Recreation",
            "subcategory":"Boat Charter",
            "type":"Entertainment"
        }
    ],
    "sg:phone":"+61 2 6494 1214",
    "sg:postcode":"2550",
    "sg:province":"NSW",
    "wof:name":"Good Times Tathra Charters",
    "wof:placetype":"venue"
},
  "geometry": {"coordinates":[149.985397339,-36.7294692993],"type":"Point"}
}