{
  "type": "Feature",
  "properties": {
    "iso:country":"AU",
    "sg:address":"580 Elizabeth St",
    "sg:city":"Melbourne",
    "sg:classifiers":[
        {
            "category":"Arts & Performance",
            "subcategory":"Art Gallery",
            "type":"Entertainment"
        }
    ],
    "sg:phone":"+61 3 9349 4040",
    "sg:postcode":"3000",
    "sg:province":"VIC",
    "wof:name":"Smart Art Direct (Vic)",
    "wof:placetype":"venue"
},
  "geometry": {"coordinates":[144.95912170400001,-37.8047485352],"type":"Point"}
}