{
  "type": "Feature",
  "properties": {
    "iso:country":"AU",
    "sg:address":"Factory 218- 220 Station St",
    "sg:city":"Thomastown",
    "sg:classifiers":[
        {
            "category":"Retail",
            "subcategory":"Auto Repair",
            "type":"Services"
        }
    ],
    "sg:phone":"+61 3 9465 3322",
    "sg:postcode":"3074",
    "sg:province":"VIC",
    "sg:tags":[
        "repairer",
        "motor",
        "engineer"
    ],
    "wof:name":"Norwich Auto Repairs",
    "wof:placetype":"venue"
},
  "geometry": {"coordinates":[145.015350342,-37.6780471802],"type":"Point"}
}