{
  "type": "Feature",
  "properties": {
    "iso:country":"AU",
    "sg:address":"Roseneath St",
    "sg:city":"Geelong",
    "sg:classifiers":[
        {
            "category":"Home & Garden",
            "subcategory":"Building Materials",
            "type":"Retail Goods"
        }
    ],
    "sg:phone":"+61 3 5278 5277",
    "sg:postcode":"3220",
    "sg:province":"VIC",
    "sg:tags":[
        "pre-mixed",
        "concrete"
    ],
    "wof:name":"Readymix",
    "wof:placetype":"venue"
},
  "geometry": {"coordinates":[144.349045,-38.121395],"type":"Point"}
}