{
  "type": "Feature",
  "properties": {
    "addr:full":"21 Somers Pde Altona VIC 3018",
    "addr:housenumber":"21",
    "addr:postcode":"3018",
    "addr:street":"Somers Pde",
    "iso:country":"AU",
    "sg:address":"21 Somers Pde",
    "sg:city":"Altona",
    "sg:classifiers":[
        {
            "category":"Food & Beverages",
            "subcategory":"Groceries & Convenience Stores",
            "type":"Retail Goods"
        }
    ],
    "sg:phone":"+61 3 9398 1374",
    "sg:postcode":"3018",
    "sg:province":"VIC",
    "wof:name":"Somers Milk Bar",
    "wof:placetype":"venue"
},
  "geometry": {"coordinates":[144.811035156,-37.8701972961],"type":"Point"}
}