{
  "type": "Feature",
  "properties": {
    "iso:country":"AU",
    "sg:address":"163 Hawkesbury Rd",
    "sg:city":"Westmead",
    "sg:classifiers":[
        {
            "category":"Health Services",
            "subcategory":"Health Practitioner",
            "type":"Services"
        }
    ],
    "sg:phone":"+61 2 9633 4077",
    "sg:postcode":"2145",
    "sg:province":"NSW",
    "sg:tags":[
        "psychologist"
    ],
    "wof:name":"Brain & Behaviour Centre",
    "wof:placetype":"venue"
},
  "geometry": {"coordinates":[150.988571167,-33.8065032959],"type":"Point"}
}