{
  "type": "Feature",
  "properties": {
    "addr:full":"Rouchel Rd Aberdeen NSW 2336",
    "addr:postcode":"2336",
    "addr:street":"Rouchel Rd",
    "iso:country":"AU",
    "sg:address":"Rouchel Rd",
    "sg:city":"Aberdeen",
    "sg:classifiers":[
        {
            "category":"Building & Trades",
            "subcategory":"Construction",
            "type":"Services"
        }
    ],
    "sg:phone":"+61 2 6543 7467",
    "sg:postcode":"2336",
    "sg:province":"NSW",
    "sg:tags":[
        "contractor"
    ],
    "wof:name":"Hall Garry",
    "wof:placetype":"venue"
},
  "geometry": {"coordinates":[150.89613342300001,-32.1543159485],"type":"Point"}
}