{
  "type": "Feature",
  "properties": {
    "iso:country":"AU",
    "sg:address":"2 Sunlight Drv",
    "sg:city":"Burleigh Heads",
    "sg:classifiers":[
        {
            "category":"Fast Food",
            "type":"Food & Drink"
        }
    ],
    "sg:phone":"+61 7 5576 0635",
    "sg:postcode":"4220",
    "sg:province":"QLD",
    "sg:tags":[
        "away",
        "take"
    ],
    "wof:name":"Sunlight Snack Bar",
    "wof:placetype":"venue"
},
  "geometry": {"coordinates":[153.43453979500001,-28.1005020142],"type":"Point"}
}