{
  "type": "Feature",
  "properties": {
    "addr:full":"10 Central Coast Hwy Gosford NSW 2250",
    "addr:housenumber":"10",
    "addr:postcode":"2250",
    "addr:street":"Central Coast Hwy",
    "iso:country":"AU",
    "sg:address":"10 Central Coast Hwy",
    "sg:city":"Gosford",
    "sg:classifiers":[
        {
            "category":"Manufacturing",
            "subcategory":"Motor Vehicles & Parts",
            "type":"Manufacturing & Wholesale Goods"
        }
    ],
    "sg:phone":"+61 1800 033 526",
    "sg:postcode":"2250",
    "sg:province":"NSW",
    "sg:tags":[
        "replacement"
    ],
    "wof:name":"Ac Delco",
    "wof:placetype":"venue"
},
  "geometry": {"coordinates":[151.34249877900001,-33.4237213135],"type":"Point"}
}