{
  "type": "Feature",
  "properties": {
    "addr:full":"61 Drysdale Ave Hamlyn Heights VIC 3215",
    "addr:housenumber":"61",
    "addr:postcode":"3215",
    "addr:street":"Drysdale Ave",
    "iso:country":"AU",
    "sg:address":"61 Drysdale Ave",
    "sg:city":"Hamlyn Heights",
    "sg:classifiers":[
        {
            "category":"Building & Trades",
            "subcategory":"Plumbing",
            "type":"Services"
        }
    ],
    "sg:phone":"+61 3 5277 2774",
    "sg:postcode":"3215",
    "sg:province":"VIC",
    "sg:tags":[
        "plumber",
        "gasfitters"
    ],
    "wof:name":"Drenovac Michael Plumbing",
    "wof:placetype":"venue"
},
  "geometry": {"coordinates":[144.32159423799999,-38.1230430603],"type":"Point"}
}