{
  "type": "Feature",
  "properties": {
    "addr:full":"4/ 16 Sturt St Mt Gambier SA 5290",
    "addr:housenumber":"/ 16",
    "addr:postcode":"5290",
    "addr:street":"Sturt St",
    "iso:country":"AU",
    "sg:address":"4/ 16 Sturt St",
    "sg:city":"Mt Gambier",
    "sg:classifiers":[
        {
            "category":"Professional",
            "subcategory":"Computer Services",
            "type":"Services"
        }
    ],
    "sg:phone":"+61 8 8723 6066",
    "sg:postcode":"5290",
    "sg:province":"SA",
    "sg:tags":[
        "training"
    ],
    "wof:name":"Green Triangle Workplace Training",
    "wof:placetype":"venue"
},
  "geometry": {"coordinates":[140.784164,-37.831711],"type":"Point"}
}