{
  "type": "Feature",
  "properties": {
    "addr:full":"33 Henderson Rd Knoxfield VIC 3180",
    "addr:housenumber":"33",
    "addr:postcode":"3180",
    "addr:street":"Henderson Rd",
    "iso:country":"AU",
    "sg:address":"33 Henderson Rd",
    "sg:city":"Knoxfield",
    "sg:classifiers":[
        {
            "category":"Bus Charters",
            "type":"Transportation"
        }
    ],
    "sg:phone":"+61 3 9753 2400",
    "sg:postcode":"3180",
    "sg:province":"VIC",
    "sg:tags":[
        "builder"
    ],
    "wof:name":"Eastcoast Truck & Bus Service Centres",
    "wof:placetype":"venue"
},
  "geometry": {"coordinates":[145.248504639,-37.9044914246],"type":"Point"}
}