{
  "type": "Feature",
  "properties": {
    "addr:full":"PO Box 663 Haberfield NSW 2045",
    "addr:postcode":"2045",
    "iso:country":"AU",
    "sg:address":"PO Box 663",
    "sg:city":"Haberfield",
    "sg:classifiers":[
        {
            "category":"Home & Garden",
            "subcategory":"Furniture",
            "type":"Retail Goods"
        }
    ],
    "sg:phone":"+61 2 9719 1330",
    "sg:postcode":"2045",
    "sg:province":"NSW",
    "sg:tags":[
        "repair",
        "restoration"
    ],
    "wof:name":"Artisano Pty Ltd",
    "wof:placetype":"venue"
},
  "geometry": {"coordinates":[151.13926699999999,-33.881031],"type":"Point"}
}