{
  "type": "Feature",
  "properties": {
    "addr:full":"195 Hartley St Cairns QLD 4870",
    "addr:housenumber":"195",
    "addr:postcode":"4870",
    "addr:street":"Hartley St",
    "iso:country":"AU",
    "sg:address":"195 Hartley St",
    "sg:city":"Cairns",
    "sg:classifiers":[
        {
            "category":"Building & Trades",
            "subcategory":"Construction",
            "type":"Services"
        }
    ],
    "sg:phone":"+61 417 789 350",
    "sg:postcode":"4870",
    "sg:province":"QLD",
    "sg:tags":[
        "scaffolding"
    ],
    "sg:website":"http://www.fahlstromscaffolding.com",
    "wof:name":"Fahlstrom Scaffolding",
    "wof:placetype":"venue"
},
  "geometry": {"coordinates":[145.754196167,-16.9451255798],"type":"Point"}
}