{
  "type": "Feature",
  "properties": {
    "addr:full":"39 Bricknell Rd Attadale WA 6156",
    "addr:housenumber":"39",
    "addr:postcode":"6156",
    "addr:street":"Bricknell Rd",
    "iso:country":"AU",
    "sg:address":"39 Bricknell Rd",
    "sg:city":"Attadale",
    "sg:classifiers":[
        {
            "category":"Retail",
            "subcategory":"Driving School",
            "type":"Services"
        }
    ],
    "sg:phone":"+61 8 9330 2746",
    "sg:postcode":"6156",
    "sg:province":"WA",
    "wof:name":"Mel's Driving School",
    "wof:placetype":"venue"
},
  "geometry": {"coordinates":[115.80873099999999,-32.026615],"type":"Point"}
}