{
  "type": "Feature",
  "properties": {
    "iso:country":"AU",
    "sg:address":"225 Windsor Rd",
    "sg:city":"Northmead",
    "sg:classifiers":[
        {
            "category":"Fast Food",
            "type":"Food & Drink"
        }
    ],
    "sg:phone":"+61 2 9639 3603",
    "sg:postcode":"2152",
    "sg:province":"NSW",
    "sg:tags":[
        "away",
        "take"
    ],
    "wof:name":"McDonald's Family Restaurants",
    "wof:placetype":"venue"
},
  "geometry": {"coordinates":[151.001464844,-33.7746238708],"type":"Point"}
}