{
  "type": "Feature",
  "properties": {
    "addr:full":"116-118 Maffra St Coolaroo VIC 3048",
    "addr:postcode":"116-118;3048",
    "addr:street":"Maffra St",
    "iso:country":"AU",
    "sg:address":"116-118 Maffra St",
    "sg:city":"Coolaroo",
    "sg:classifiers":[
        {
            "category":"Building & Trades",
            "subcategory":"Construction",
            "type":"Services"
        }
    ],
    "sg:phone":"+61 3 9309 6555",
    "sg:postcode":"3048",
    "sg:province":"VIC",
    "sg:tags":[
        "earth",
        "excavating",
        "moving",
        "contractor"
    ],
    "wof:name":"Prestige Bobcat",
    "wof:placetype":"venue"
},
  "geometry": {"coordinates":[144.93975800000001,-37.657013],"type":"Point"}
}