{
  "type": "Feature",
  "properties": {
    "addr:full":"50 President Ave Caringbah NSW 2229",
    "addr:housenumber":"50",
    "addr:postcode":"2229",
    "addr:street":"President Ave",
    "iso:country":"AU",
    "sg:address":"50 President Ave",
    "sg:city":"Caringbah",
    "sg:classifiers":[
        {
            "category":"Building & Trades",
            "subcategory":"Construction",
            "type":"Services"
        }
    ],
    "sg:phone":"+61 2 9525 7067",
    "sg:postcode":"2229",
    "sg:province":"NSW",
    "sg:tags":[
        "pool",
        "swimming"
    ],
    "wof:name":"Clark Pools & Spas",
    "wof:placetype":"venue"
},
  "geometry": {"coordinates":[151.120697022,-34.0429573059],"type":"Point"}
}