{
  "type": "Feature",
  "properties": {
    "addr:full":"6 Fox Rd East Ryde NSW 2113",
    "addr:housenumber":"6",
    "addr:postcode":"2113",
    "addr:street":"Fox Rd East",
    "iso:country":"AU",
    "sg:address":"6 Fox Rd",
    "sg:city":"East Ryde",
    "sg:classifiers":[
        {
            "category":"Home & Garden",
            "subcategory":"Building Materials",
            "type":"Retail Goods"
        }
    ],
    "sg:phone":"+61 2 9878 4193",
    "sg:postcode":"2113",
    "sg:province":"NSW",
    "sg:tags":[
        "fitting",
        "door"
    ],
    "wof:name":"Geoff Bate Technical Service Pty Ltd",
    "wof:placetype":"venue"
},
  "geometry": {"coordinates":[151.13090515100001,-33.8064994812],"type":"Point"}
}