{
  "type": "Feature",
  "properties": {
    "addr:full":"Homebase Centre, 1/24 Blaxland Rd Campbelltown NSW 2560",
    "addr:housenumber":"1 / 24",
    "addr:postcode":"2560",
    "addr:street":"Blaxland Rd",
    "iso:country":"AU",
    "sg:address":"Homebase Centre, 1/24 Blaxland Rd",
    "sg:city":"Campbelltown",
    "sg:classifiers":[
        {
            "category":"Home & Garden",
            "subcategory":"Carpets & Floor Coverings",
            "type":"Retail Goods"
        }
    ],
    "sg:phone":"+61 2 4625 1794",
    "sg:postcode":"2560",
    "sg:province":"NSW",
    "sg:tags":[
        "mattress"
    ],
    "wof:name":"Sleep City",
    "wof:placetype":"venue"
},
  "geometry": {"coordinates":[150.82493591299999,-34.063167572],"type":"Point"}
}