{
  "type": "Feature",
  "properties": {
    "addr:full":"76 Oxford St Paddington NSW 2021",
    "addr:housenumber":"76",
    "addr:postcode":"2021",
    "addr:street":"Oxford St",
    "iso:country":"AU",
    "sg:address":"76 Oxford St",
    "sg:city":"Paddington",
    "sg:classifiers":[
        {
            "category":"Education",
            "subcategory":"Special Training",
            "type":"Public Place"
        }
    ],
    "sg:phone":"+61 417 736 145",
    "sg:postcode":"2021",
    "sg:province":"NSW",
    "sg:tags":[
        "development"
    ],
    "wof:name":"Aims At Work",
    "wof:placetype":"venue"
},
  "geometry": {"coordinates":[151.220977783,-33.8832054138],"type":"Point"}
}