{
  "type": "Feature",
  "properties": {
    "addr:full":"2 Stockdale Rd O'Connor WA 6163",
    "addr:housenumber":"2",
    "addr:postcode":"6163",
    "addr:street":"Stockdale Rd",
    "iso:country":"AU",
    "sg:address":"2 Stockdale Rd",
    "sg:city":"O'Connor",
    "sg:classifiers":[
        {
            "category":"Building & Trades",
            "subcategory":"Construction",
            "type":"Services"
        }
    ],
    "sg:phone":"+61 8 9337 4490",
    "sg:postcode":"6163",
    "sg:province":"WA",
    "sg:tags":[
        "earth",
        "excavating",
        "moving",
        "contractor"
    ],
    "wof:name":"Bellagio Bobcat Service",
    "wof:placetype":"venue"
},
  "geometry": {"coordinates":[115.793137,-32.056717],"type":"Point"}
}