{
  "type": "Feature",
  "properties": {
    "iso:country":"AU",
    "sg:address":"56 Cammarlie St",
    "sg:city":"Panania",
    "sg:classifiers":[
        {
            "category":"Home & Garden",
            "subcategory":"Building Materials",
            "type":"Retail Goods"
        }
    ],
    "sg:phone":"+61 2 9774 4685",
    "sg:postcode":"2213",
    "sg:province":"NSW",
    "sg:tags":[
        "merchant",
        "glass",
        "glazier"
    ],
    "wof:name":"Expo Glass Installation",
    "wof:placetype":"venue"
},
  "geometry": {"coordinates":[150.990036,-33.954453],"type":"Point"}
}