{
  "type": "Feature",
  "properties": {
    "addr:full":"186 Memorial Dr Eumundi QLD 4562",
    "addr:housenumber":"186",
    "addr:postcode":"4562",
    "addr:street":"Memorial Dr Eumundi",
    "iso:country":"AU",
    "sg:address":"186 Memorial Dr",
    "sg:city":"Eumundi",
    "sg:classifiers":[
        {
            "category":"Government",
            "subcategory":"Post Office",
            "type":"Public Place"
        }
    ],
    "sg:phone":"+61 7 5442 8360",
    "sg:postcode":"4562",
    "sg:province":"QLD",
    "sg:tags":[
        "yoga"
    ],
    "wof:name":"Soul Song Yoga Products",
    "wof:placetype":"venue"
},
  "geometry": {"coordinates":[152.95127868599999,-26.475605011],"type":"Point"}
}