{
  "type": "Feature",
  "properties": {
    "iso:country":"AU",
    "sg:address":"Bass Hwy",
    "sg:city":"Elizabeth Town",
    "sg:classifiers":[
        {
            "category":"Autos & Motor Vehicles",
            "subcategory":"Fuel & Gas Station",
            "type":"Retail Goods"
        }
    ],
    "sg:phone":"+61 3 6368 1216",
    "sg:postcode":"7304",
    "sg:province":"TAS",
    "wof:name":"Elizabeth Town Road House",
    "wof:placetype":"venue"
},
  "geometry": {"coordinates":[146.562134,-41.467632],"type":"Point"}
}