{
  "type": "Feature",
  "properties": {
    "addr:full":"Shp4/ Jones St Balcatta WA 6021",
    "addr:postcode":"6021",
    "addr:street":"St",
    "iso:country":"AU",
    "sg:address":"Shp4/ Jones St",
    "sg:city":"Balcatta",
    "sg:classifiers":[
        {
            "category":"Food & Beverages",
            "subcategory":"Bakery",
            "type":"Retail Goods"
        }
    ],
    "sg:phone":"+61 8 9349 2549",
    "sg:postcode":"6021",
    "sg:province":"WA",
    "sg:tags":[
        "baker"
    ],
    "wof:name":"Amelia Heights Bakery",
    "wof:placetype":"venue"
},
  "geometry": {"coordinates":[115.820800781,-31.8731803894],"type":"Point"}
}