{
  "type": "Feature",
  "properties": {
    "addr:full":"723 Laurie St Ballarat VIC 3350",
    "addr:housenumber":"723",
    "addr:postcode":"3350",
    "addr:street":"Laurie St",
    "iso:country":"AU",
    "sg:address":"723 Laurie St",
    "sg:city":"Ballarat",
    "sg:classifiers":[
        {
            "category":"Organizations",
            "subcategory":"Professional Association",
            "type":"Services"
        }
    ],
    "sg:phone":"+61 3 5338 7111",
    "sg:postcode":"3350",
    "sg:province":"VIC",
    "sg:tags":[
        "web",
        "internet"
    ],
    "wof:name":"Driftwood www.dw.com.au",
    "wof:placetype":"venue"
},
  "geometry": {"coordinates":[143.857178,-37.576149],"type":"Point"}
}