{
  "type": "Feature",
  "properties": {
    "addr:full":"17 Cavell St West Hobart TAS 7000",
    "addr:housenumber":"17",
    "addr:postcode":"7000",
    "addr:street":"Cavell St",
    "iso:country":"AU",
    "sg:address":"17 Cavell St",
    "sg:city":"West Hobart",
    "sg:classifiers":[
        {
            "category":"Travel",
            "subcategory":"Hotels & Motels",
            "type":"Entertainment"
        }
    ],
    "sg:phone":"+61 3 6231 1188",
    "sg:postcode":"7000",
    "sg:province":"TAS",
    "sg:website":"http://www.mayfaironcavell.com",
    "wof:name":"Mayfair On Cavell",
    "wof:placetype":"venue"
},
  "geometry": {"coordinates":[147.314178467,-42.8862571716],"type":"Point"}
}