{
  "type": "Feature",
  "properties": {
    "addr:full":"16 Conrad St Warwick QLD 4370",
    "addr:housenumber":"16",
    "addr:postcode":"4370",
    "addr:street":"Conrad St",
    "iso:country":"AU",
    "sg:address":"16 Conrad St",
    "sg:city":"Warwick",
    "sg:classifiers":[
        {
            "category":"School Buses",
            "type":"Transportation"
        }
    ],
    "sg:phone":"+61 409 872 565",
    "sg:postcode":"4370",
    "sg:province":"QLD",
    "sg:tags":[
        "brick"
    ],
    "wof:name":"Warwick Brick Works Pty. Ltd.",
    "wof:placetype":"venue"
},
  "geometry": {"coordinates":[152.039993286,-28.2292442322],"type":"Point"}
}