{
  "type": "Feature",
  "properties": {
    "addr:full":"109 Firebrace St Horsham VIC 3400",
    "addr:housenumber":"109",
    "addr:postcode":"3400",
    "addr:street":"Firebrace St",
    "iso:country":"AU",
    "sg:address":"109 Firebrace St",
    "sg:city":"Horsham",
    "sg:classifiers":[
        {
            "category":"Travel",
            "subcategory":"Hotels & Motels",
            "type":"Entertainment"
        }
    ],
    "sg:phone":"+61 3 5382 0125",
    "sg:postcode":"3400",
    "sg:province":"VIC",
    "wof:name":"Comfort Inn Capital Horsham",
    "wof:placetype":"venue"
},
  "geometry": {"coordinates":[142.199905395,-36.7175941467],"type":"Point"}
}