{
  "type": "Feature",
  "properties": {
    "addr:full":"177 Bridge St Oakey QLD 4401",
    "addr:housenumber":"177",
    "addr:postcode":"4401",
    "addr:street":"Bridge St",
    "iso:country":"AU",
    "sg:address":"177 Bridge St",
    "sg:city":"Oakey",
    "sg:classifiers":[
        {
            "category":"Autos & Motor Vehicles",
            "subcategory":"Automobile Sales",
            "type":"Retail Goods"
        }
    ],
    "sg:phone":"+61 7 4691 1033",
    "sg:postcode":"4401",
    "sg:province":"QLD",
    "sg:tags":[
        "car",
        "new"
    ],
    "wof:name":"Black Toyota",
    "wof:placetype":"venue"
},
  "geometry": {"coordinates":[151.710647583,-27.4271087646],"type":"Point"}
}