{
  "type": "Feature",
  "properties": {
    "addr:full":"7 Turner St Glen Iris VIC 3146",
    "addr:housenumber":"7",
    "addr:postcode":"3146",
    "addr:street":"Turner St",
    "iso:country":"AU",
    "sg:address":"7 Turner St",
    "sg:city":"Glen Iris",
    "sg:classifiers":[
        {
            "category":"Building & Trades",
            "subcategory":"Cleaning & Sanitation",
            "type":"Services"
        }
    ],
    "sg:phone":"+61 400 924 527",
    "sg:postcode":"3146",
    "sg:province":"VIC",
    "sg:tags":[
        "sweeping",
        "machine"
    ],
    "wof:name":"Unique Plant Services Pty Ltd",
    "wof:placetype":"venue"
},
  "geometry": {"coordinates":[145.05456543,-37.8465461731],"type":"Point"}
}