{
  "type": "Feature",
  "properties": {
    "addr:full":"2a Kingfisher Ave Ballajura WA 6066",
    "addr:housenumber":"2a",
    "addr:postcode":"6066",
    "addr:street":"Kingfisher Ave",
    "iso:country":"AU",
    "sg:address":"2a Kingfisher Ave",
    "sg:city":"Ballajura",
    "sg:classifiers":[
        {
            "category":"Health Services",
            "subcategory":"Dentist",
            "type":"Services"
        }
    ],
    "sg:phone":"+61 8 9249 4250",
    "sg:postcode":"6066",
    "sg:province":"WA",
    "wof:name":"Chin Jeremy Dr",
    "wof:placetype":"venue"
},
  "geometry": {"coordinates":[115.896026611,-31.8388652802],"type":"Point"}
}