{
  "type": "Feature",
  "properties": {
    "addr:full":"501 North Rd Ormond VIC 3204",
    "addr:housenumber":"501",
    "addr:postcode":"3204",
    "addr:street":"North Rd",
    "iso:country":"AU",
    "sg:address":"501 North Rd",
    "sg:city":"Ormond",
    "sg:classifiers":[
        {
            "category":"Cafe",
            "type":"Food & Drink"
        }
    ],
    "sg:phone":"+61 3 9578 3165",
    "sg:postcode":"3204",
    "sg:province":"VIC",
    "wof:name":"Bakery Copper Cafe",
    "wof:placetype":"venue"
},
  "geometry": {"coordinates":[145.04040499999999,-37.903835],"type":"Point"}
}