{
  "type": "Feature",
  "properties": {
    "addr:full":"Shop 2/ 171 Waterloo Rd Greenacre NSW 2190",
    "addr:housenumber":"shop 2 / 171",
    "addr:postcode":"2190",
    "addr:street":"Waterloo Rd",
    "iso:country":"AU",
    "sg:address":"Shop 2/ 171 Waterloo Rd",
    "sg:city":"Greenacre",
    "sg:classifiers":[
        {
            "category":"Personal",
            "subcategory":"Beauty Salon",
            "type":"Services"
        }
    ],
    "sg:phone":"+61 2 9750 0258",
    "sg:postcode":"2190",
    "sg:province":"NSW",
    "sg:tags":[
        "hairdresser"
    ],
    "wof:name":"Totally Styled Family Hair Centre",
    "wof:placetype":"venue"
},
  "geometry": {"coordinates":[151.05877699999999,-33.898579],"type":"Point"}
}