{
  "type": "Feature",
  "properties": {
    "addr:full":"Level 1 1155-1161 High St Armadale VIC 3143",
    "addr:housenumber":"1155-1161",
    "addr:postcode":"3143",
    "addr:street":"High St",
    "iso:country":"AU",
    "sg:address":"Level 1 1155-1161 High St",
    "sg:city":"Armadale",
    "sg:classifiers":[
        {
            "category":"Health Services",
            "subcategory":"Dentist",
            "type":"Services"
        }
    ],
    "sg:phone":"+61 1300 762 770",
    "sg:postcode":"3143",
    "sg:province":"VIC",
    "wof:name":"Creative Smiles",
    "wof:placetype":"venue"
},
  "geometry": {"coordinates":[145.02639770499999,-37.856098175],"type":"Point"}
}