{
  "type": "Feature",
  "properties": {
    "addr:full":"Arrowsmith St Beveridge VIC 3753",
    "addr:postcode":"3753",
    "addr:street":"Arrowsmith St",
    "iso:country":"AU",
    "sg:address":"Arrowsmith St",
    "sg:city":"Beveridge",
    "sg:classifiers":[
        {
            "category":"Education",
            "subcategory":"School",
            "type":"Public Place"
        }
    ],
    "sg:phone":"+61 3 9745 2264",
    "sg:postcode":"3753",
    "sg:province":"VIC",
    "sg:tags":[
        "state",
        "except",
        "nsw"
    ],
    "wof:name":"Beveridge Primary",
    "wof:placetype":"venue"
},
  "geometry": {"coordinates":[144.96296699999999,-37.470135],"type":"Point"}
}