{
  "type": "Feature",
  "properties": {
    "iso:country":"AU",
    "sg:address":"Forestway Family Medical Cntr, 22 Forest Way",
    "sg:city":"Frenchs Forest",
    "sg:classifiers":[
        {
            "category":"Health Services",
            "subcategory":"Doctor",
            "type":"Services"
        }
    ],
    "sg:phone":"+61 2 9452 3877",
    "sg:postcode":"2086",
    "sg:province":"NSW",
    "sg:tags":[
        "medical",
        "practitioner"
    ],
    "wof:name":"SDS Pathology",
    "wof:placetype":"venue"
},
  "geometry": {"coordinates":[151.222198486,-33.745300293],"type":"Point"}
}