{
  "type": "Feature",
  "properties": {
    "addr:full":"Level 5/ 11 Queens Rd Melbourne VIC 3004",
    "addr:housenumber":"/ 11",
    "addr:postcode":"3004",
    "addr:street":"Queens Rd",
    "iso:country":"AU",
    "sg:address":"Level 5/ 11 Queens Rd",
    "sg:city":"Melbourne",
    "sg:classifiers":[
        {
            "category":"Professional",
            "subcategory":"Accounting & Tax Preparation",
            "type":"Services"
        }
    ],
    "sg:phone":"+61 3 9869 7130",
    "sg:postcode":"3004",
    "sg:province":"VIC",
    "sg:tags":[
        "bookkeeping"
    ],
    "wof:name":"Angelis Business Services",
    "wof:placetype":"venue"
},
  "geometry": {"coordinates":[144.97398376500001,-37.8380279541],"type":"Point"}
}