{
  "type": "Feature",
  "properties": {
    "addr:full":"Mt Pleasant Plaza Phillip St North Mackay QLD 4740",
    "addr:postcode":"4740",
    "addr:street":"Phillip St",
    "iso:country":"AU",
    "sg:address":"Mt Pleasant Plaza Phillip St",
    "sg:city":"North Mackay",
    "sg:classifiers":[
        {
            "category":"Health Services",
            "subcategory":"Dentist",
            "type":"Services"
        }
    ],
    "sg:phone":"+61 7 4942 3272",
    "sg:postcode":"4740",
    "sg:province":"QLD",
    "wof:name":"Deane PT, Coey JR, Stuart JC, Pearson SJ & Cahill MP",
    "wof:placetype":"venue"
},
  "geometry": {"coordinates":[149.167923,-21.11104],"type":"Point"}
}