{
  "type": "Feature",
  "properties": {
    "addr:full":"113 Delany Ave Bright VIC 3741",
    "addr:housenumber":"113",
    "addr:postcode":"3741",
    "addr:street":"Delany Ave",
    "iso:country":"AU",
    "sg:address":"113 Delany Ave",
    "sg:city":"Bright",
    "sg:classifiers":[
        {
            "category":"Travel",
            "subcategory":"Hotels & Motels",
            "type":"Entertainment"
        }
    ],
    "sg:phone":"+61 3 5755 1833",
    "sg:postcode":"3741",
    "sg:province":"VIC",
    "wof:name":"Bright Chalet",
    "wof:placetype":"venue"
},
  "geometry": {"coordinates":[146.96470600000001,-36.726757],"type":"Point"}
}