{
  "type": "Feature",
  "properties": {
    "addr:full":"Rear 33 Dobney Ave Wagga Wagga NSW 2650",
    "addr:housenumber":"33",
    "addr:postcode":"2650",
    "addr:street":"Dobney Ave",
    "iso:country":"AU",
    "sg:address":"Rear 33 Dobney Ave",
    "sg:city":"Wagga Wagga",
    "sg:classifiers":[
        {
            "category":"Retail",
            "subcategory":"Auto Repair",
            "type":"Services"
        }
    ],
    "sg:phone":"+61 2 6925 3966",
    "sg:postcode":"2650",
    "sg:province":"NSW",
    "sg:tags":[
        "repairer",
        "motor",
        "engineer"
    ],
    "wof:name":"Alan Gamble Automotive",
    "wof:placetype":"venue"
},
  "geometry": {"coordinates":[147.346755981,-35.1187019348],"type":"Point"}
}