{
  "type": "Feature",
  "properties": {
    "addr:full":"170 Russell St Melbourne VIC 3000",
    "addr:housenumber":"170",
    "addr:postcode":"3000",
    "addr:street":"Russell St",
    "iso:country":"AU",
    "sg:address":"170 Russell St",
    "sg:city":"Melbourne",
    "sg:classifiers":[
        {
            "category":"Bars & Pubs",
            "subcategory":"Nightclub",
            "type":"Food & Drink"
        }
    ],
    "sg:phone":"+61 3 9639 4000",
    "sg:postcode":"3000",
    "sg:province":"VIC",
    "sg:tags":[
        "discotheque"
    ],
    "wof:name":"The Billboard Nightclub",
    "wof:placetype":"venue"
},
  "geometry": {"coordinates":[144.968017578,-37.8121910095],"type":"Point"}
}