{
  "type": "Feature",
  "properties": {
    "addr:full":"17 Lynelle St Sunnybank Hills QLD 4109",
    "addr:housenumber":"17",
    "addr:postcode":"4109",
    "addr:street":"Lynelle St",
    "iso:country":"AU",
    "sg:address":"17 Lynelle St",
    "sg:city":"Sunnybank Hills",
    "sg:classifiers":[
        {
            "category":"Professional",
            "subcategory":"Art Services",
            "type":"Services"
        }
    ],
    "sg:phone":"+61 7 3273 5527",
    "sg:postcode":"4109",
    "sg:province":"QLD",
    "sg:tags":[
        "floral",
        "teacher"
    ],
    "wof:name":"Japanese Flower Arrangement",
    "wof:placetype":"venue"
},
  "geometry": {"coordinates":[153.05418395999999,-27.6028289795],"type":"Point"}
}