{
  "type": "Feature",
  "properties": {
    "addr:full":"134 Coonanbarra Rd Wahroonga NSW 2076",
    "addr:housenumber":"134",
    "addr:postcode":"2076",
    "addr:street":"Coonanbarra Rd",
    "iso:country":"AU",
    "sg:address":"134 Coonanbarra Rd",
    "sg:city":"Wahroonga",
    "sg:classifiers":[
        {
            "category":"Wholesale",
            "subcategory":"Machinery & Supplies",
            "type":"Manufacturing & Wholesale Goods"
        }
    ],
    "sg:phone":"+61 2 9943 0785",
    "sg:postcode":"2076",
    "sg:province":"NSW",
    "sg:tags":[
        "instrument",
        "scientific"
    ],
    "wof:name":"Optind Pty Ltd",
    "wof:placetype":"venue"
},
  "geometry": {"coordinates":[151.118209839,-33.708820343],"type":"Point"}
}