{
  "type": "Feature",
  "properties": {
    "iso:country":"AU",
    "sg:address":"20 Eskdale Crt",
    "sg:city":"Eltham",
    "sg:classifiers":[
        {
            "category":"Retail",
            "subcategory":"Repair Shop",
            "type":"Services"
        }
    ],
    "sg:phone":"+61 3 9439 6624",
    "sg:postcode":"3095",
    "sg:province":"VIC",
    "sg:tags":[
        "maintenance",
        "pool",
        "swimming"
    ],
    "wof:name":"Ace Pool And Spa",
    "wof:placetype":"venue"
},
  "geometry": {"coordinates":[145.138580322,-37.6940078735],"type":"Point"}
}