{
  "type": "Feature",
  "properties": {
    "addr:full":"37 Bellbird Ave Taylors Lakes VIC 3038",
    "addr:housenumber":"37",
    "addr:postcode":"3038",
    "addr:street":"Bellbird Ave",
    "iso:country":"AU",
    "sg:address":"37 Bellbird Ave",
    "sg:city":"Taylors Lakes",
    "sg:classifiers":[
        {
            "category":"Building & Trades",
            "subcategory":"Landscaping Services",
            "type":"Services"
        }
    ],
    "sg:phone":"+61 409 719 517",
    "sg:postcode":"3038",
    "sg:province":"VIC",
    "sg:tags":[
        "gardener"
    ],
    "wof:name":"Lakes Landscape & Design",
    "wof:placetype":"venue"
},
  "geometry": {"coordinates":[144.78385900000001,-37.696388],"type":"Point"}
}