{
  "type": "Feature",
  "properties": {
    "iso:country":"AU",
    "sg:address":"PO Box 907 St",
    "sg:city":"Ives",
    "sg:classifiers":[
        {
            "category":"Building & Trades",
            "subcategory":"Landscaping Services",
            "type":"Services"
        }
    ],
    "sg:phone":"+61 2 9449 2801",
    "sg:postcode":"2075",
    "sg:province":"NSW",
    "sg:tags":[
        "gardener"
    ],
    "wof:name":"Andrew Luckie",
    "wof:placetype":"venue"
},
  "geometry": {"coordinates":[151.16558837900001,-33.7382392883],"type":"Point"}
}