{
  "type": "Feature",
  "properties": {
    "addr:full":"179 Conadilly St Gunnedah NSW 2380",
    "addr:housenumber":"179",
    "addr:postcode":"2380",
    "addr:street":"Conadilly St",
    "iso:country":"AU",
    "sg:address":"179 Conadilly St",
    "sg:city":"Gunnedah",
    "sg:classifiers":[
        {
            "category":"Real Estate",
            "subcategory":"Real Estate Agent",
            "type":"Services"
        }
    ],
    "sg:phone":"+61 2 6742 1828",
    "sg:postcode":"2380",
    "sg:province":"NSW",
    "wof:name":"Davidson Cameron & Co",
    "wof:placetype":"venue"
},
  "geometry": {"coordinates":[150.25267028799999,-30.9783363342],"type":"Point"}
}