{
  "type": "Feature",
  "properties": {
    "iso:country":"AU",
    "sg:address":"45 Craig Rd",
    "sg:city":"Cranbourne",
    "sg:classifiers":[
        {
            "category":"Building & Trades",
            "subcategory":"Pest Control",
            "type":"Services"
        }
    ],
    "sg:phone":"+61 3 5996 5843",
    "sg:postcode":"3977",
    "sg:province":"VIC",
    "sg:tags":[
        "horse",
        "transport"
    ],
    "wof:name":"Mornington - Cranbourne Float Service",
    "wof:placetype":"venue"
},
  "geometry": {"coordinates":[145.29348754899999,-38.1408042908],"type":"Point"}
}