{
  "type": "Feature",
  "properties": {
    "addr:full":"Unit 1 42- 50 Stud Rd Bayswater VIC 3153",
    "addr:housenumber":"42 50",
    "addr:postcode":"3153",
    "addr:street":"Stud Rd",
    "iso:country":"AU",
    "sg:address":"Unit 1 42- 50 Stud Rd",
    "sg:city":"Bayswater",
    "sg:classifiers":[
        {
            "category":"Professional",
            "subcategory":"Accounting & Tax Preparation",
            "type":"Services"
        }
    ],
    "sg:phone":"+61 3 9720 5133",
    "sg:postcode":"3153",
    "sg:province":"VIC",
    "sg:tags":[
        "consultant",
        "taxation"
    ],
    "wof:name":"John W Whitworth & Associates",
    "wof:placetype":"venue"
},
  "geometry": {"coordinates":[145.246658325,-37.8466339111],"type":"Point"}
}