{
  "type": "Feature",
  "properties": {
    "addr:full":"137 High St Mansfield VIC 3722",
    "addr:housenumber":"137",
    "addr:postcode":"3722",
    "addr:street":"High St",
    "iso:country":"AU",
    "sg:address":"137 High St",
    "sg:city":"Mansfield",
    "sg:classifiers":[
        {
            "category":"Taxi",
            "type":"Transportation"
        }
    ],
    "sg:phone":"+61 408 579 268",
    "sg:postcode":"3722",
    "sg:province":"VIC",
    "sg:tags":[
        "cab"
    ],
    "wof:name":"Mansfield Taxis",
    "wof:placetype":"venue"
},
  "geometry": {"coordinates":[146.08589172399999,-37.0517044067],"type":"Point"}
}