{
  "type": "Feature",
  "properties": {
    "addr:full":"PO Box 302 Footscray West VIC 3012",
    "addr:postcode":"3012",
    "iso:country":"AU",
    "sg:address":"PO Box 302",
    "sg:city":"Footscray West",
    "sg:classifiers":[
        {
            "category":"Wholesale",
            "subcategory":"Machinery & Supplies",
            "type":"Manufacturing & Wholesale Goods"
        }
    ],
    "sg:phone":"+61 3 9318 5909",
    "sg:postcode":"3012",
    "sg:province":"VIC",
    "sg:tags":[
        "bearing",
        "bushing"
    ],
    "wof:name":"Schaeffler Walzlager",
    "wof:placetype":"venue"
},
  "geometry": {"coordinates":[144.90626525900001,-37.8056678772],"type":"Point"}
}