{
  "type": "Feature",
  "properties": {
    "iso:country":"AU",
    "sg:address":"1/ 7 Tahiti Ave",
    "sg:city":"Palm Beach",
    "sg:classifiers":[
        {
            "category":"Industrial Area",
            "type":"Public Place"
        }
    ],
    "sg:phone":"+61 7 5559 5532",
    "sg:postcode":"4221",
    "sg:province":"QLD",
    "sg:tags":[
        "rural",
        "shed"
    ],
    "wof:name":"Steelway Buildings",
    "wof:placetype":"venue"
},
  "geometry": {"coordinates":[153.47169494600001,-28.1302604675],"type":"Point"}
}