{
  "type": "Feature",
  "properties": {
    "iso:country":"AU",
    "sg:address":"4 Oakhampton Crt",
    "sg:city":"Toronto",
    "sg:classifiers":[
        {
            "category":"Personal",
            "subcategory":"Massage",
            "type":"Services"
        }
    ],
    "sg:phone":"+61 419 421 140",
    "sg:postcode":"2283",
    "sg:province":"NSW",
    "sg:tags":[
        "therapy"
    ],
    "wof:name":"Jodi Mackie Massage Therapist",
    "wof:placetype":"venue"
},
  "geometry": {"coordinates":[151.599777222,-33.0217094421],"type":"Point"}
}