{
  "type": "Feature",
  "properties": {
    "iso:country":"AU",
    "sg:address":"116 Gordon St",
    "sg:city":"Gordon Park",
    "sg:classifiers":[
        {
            "category":"Banks & Credit Unions",
            "subcategory":"Financial Services",
            "type":"Services"
        }
    ],
    "sg:phone":"+61 7 3357 8866",
    "sg:postcode":"4031",
    "sg:province":"QLD",
    "sg:tags":[
        "planning"
    ],
    "wof:name":"Barlow Consulting Group",
    "wof:placetype":"venue"
},
  "geometry": {"coordinates":[153.02856399999999,-27.418161],"type":"Point"}
}