{
  "type": "Feature",
  "properties": {
    "addr:full":"571- 573 Doncaster Rd Doncaster VIC 3108",
    "addr:housenumber":"573",
    "addr:postcode":"3108",
    "addr:street":"Doncaster Rd",
    "iso:country":"AU",
    "sg:address":"571- 573 Doncaster Rd",
    "sg:city":"Doncaster",
    "sg:classifiers":[
        {
            "category":"Autos & Motor Vehicles",
            "subcategory":"Automobile Sales",
            "type":"Retail Goods"
        }
    ],
    "sg:phone":"+61 3 9429 8000",
    "sg:postcode":"3108",
    "sg:province":"VIC",
    "sg:tags":[
        "car",
        "used"
    ],
    "wof:name":"Ferrari Lance Dixon",
    "wof:placetype":"venue"
},
  "geometry": {"coordinates":[145.12164306599999,-37.7877311707],"type":"Point"}
}