{
  "type": "Feature",
  "properties": {
    "addr:full":"356 South Dowling St Paddington NSW 2021",
    "addr:housenumber":"356",
    "addr:postcode":"2021",
    "addr:street":"South Dowling St",
    "iso:country":"AU",
    "sg:address":"356 South Dowling St",
    "sg:city":"Paddington",
    "sg:classifiers":[
        {
            "category":"Wholesale",
            "subcategory":"Meat",
            "type":"Manufacturing & Wholesale Goods"
        }
    ],
    "sg:phone":"+61 2 9360 7844",
    "sg:postcode":"2021",
    "sg:province":"NSW",
    "sg:tags":[
        "packing",
        "exporting"
    ],
    "wof:name":"Henry Woolfe Meat Packing Pty Ltd",
    "wof:placetype":"venue"
},
  "geometry": {"coordinates":[151.218475342,-33.88438797],"type":"Point"}
}