{
  "type": "Feature",
  "properties": {
    "addr:full":"Unit 3, 226 Carr Pl Leederville WA 6007",
    "addr:housenumber":"226",
    "addr:postcode":"6007",
    "addr:street":"Carr Pl",
    "iso:country":"AU",
    "sg:address":"Unit 3, 226 Carr Pl",
    "sg:city":"Leederville",
    "sg:classifiers":[
        {
            "category":"Building & Trades",
            "subcategory":"Cleaning & Sanitation",
            "type":"Services"
        }
    ],
    "sg:phone":"+61 8 9443 5910",
    "sg:postcode":"6007",
    "sg:province":"WA",
    "sg:tags":[
        "industrial",
        "commercial",
        "contractor"
    ],
    "wof:name":"Acaddia Commercial Cleaning",
    "wof:placetype":"venue"
},
  "geometry": {"coordinates":[115.84227752699999,-31.9372825623],"type":"Point"}
}