{
  "type": "Feature",
  "properties": {
    "addr:full":"Shop 6/ 320 Pacific Hwy Hornsby NSW 2077",
    "addr:housenumber":"shop 6 / 320",
    "addr:postcode":"2077",
    "addr:street":"Pacific Hwy",
    "iso:country":"AU",
    "sg:address":"Shop 6/ 320 Pacific Hwy",
    "sg:city":"Hornsby",
    "sg:classifiers":[
        {
            "category":"Arts & Performance",
            "subcategory":"Dance",
            "type":"Entertainment"
        }
    ],
    "sg:phone":"+61 2 9477 7810",
    "sg:postcode":"2077",
    "sg:province":"NSW",
    "sg:tags":[
        "theatrical",
        "ballet",
        "tuition"
    ],
    "wof:name":"Eileen Phillips Dance Academy",
    "wof:placetype":"venue"
},
  "geometry": {"coordinates":[151.098342895,-33.6970596313],"type":"Point"}
}