{
  "type": "Feature",
  "properties": {
    "addr:full":"Lvl 12, 179 Elizabeth St Sydney NSW 2000",
    "addr:housenumber":"179",
    "addr:postcode":"2000",
    "addr:street":"Elizabeth St",
    "iso:country":"AU",
    "sg:address":"Lvl 12, 179 Elizabeth St",
    "sg:city":"Sydney",
    "sg:classifiers":[
        {
            "category":"Education",
            "subcategory":"Special Training",
            "type":"Public Place"
        }
    ],
    "sg:phone":"+61 2 9269 8000",
    "sg:postcode":"2000",
    "sg:province":"NSW",
    "sg:tags":[
        "development"
    ],
    "sg:website":"http://www.learngroup.com.au",
    "wof:name":"The Learning Group Pty Ltd",
    "wof:placetype":"venue"
},
  "geometry": {"coordinates":[151.209884644,-33.8724250793],"type":"Point"}
}