{
  "type": "Feature",
  "properties": {
    "addr:full":"111 Franklin St Adelaide SA 5000",
    "addr:housenumber":"111",
    "addr:postcode":"5000",
    "addr:street":"Franklin St",
    "iso:country":"AU",
    "sg:address":"111 Franklin St",
    "sg:city":"Adelaide",
    "sg:classifiers":[
        {
            "category":"Freight",
            "type":"Transportation"
        }
    ],
    "sg:phone":"+61 8 8415 5599",
    "sg:postcode":"5000",
    "sg:province":"SA",
    "sg:tags":[
        "light",
        "carrier"
    ],
    "wof:name":"Stateliner Coachfreight",
    "wof:placetype":"venue"
},
  "geometry": {"coordinates":[138.594680786,-34.9275665283],"type":"Point"}
}