{
  "type": "Feature",
  "properties": {
    "addr:full":"46 Browallia Crs Loftus NSW 2232",
    "addr:housenumber":"46",
    "addr:postcode":"2232",
    "addr:street":"Browallia Crs",
    "iso:country":"AU",
    "sg:address":"46 Browallia Crs",
    "sg:city":"Loftus",
    "sg:classifiers":[
        {
            "category":"Professional",
            "subcategory":"Computer Services",
            "type":"Services"
        }
    ],
    "sg:phone":"+61 2 9521 3863",
    "sg:postcode":"2232",
    "sg:province":"NSW",
    "sg:tags":[
        "consultant",
        "system"
    ],
    "wof:name":"Voor Enterprises",
    "wof:placetype":"venue"
},
  "geometry": {"coordinates":[151.04940795900001,-34.0512504578],"type":"Point"}
}