{
  "type": "Feature",
  "properties": {
    "addr:full":"78 Arnold St Bendigo VIC 3550",
    "addr:housenumber":"78",
    "addr:postcode":"3550",
    "addr:street":"Arnold St",
    "iso:country":"AU",
    "sg:address":"78 Arnold St",
    "sg:city":"Bendigo",
    "sg:classifiers":[
        {
            "category":"Health Services",
            "subcategory":"Chiropractor",
            "type":"Services"
        }
    ],
    "sg:phone":"+61 3 5443 0922",
    "sg:postcode":"3550",
    "sg:province":"VIC",
    "wof:name":"Mawby Chiropractic",
    "wof:placetype":"venue"
},
  "geometry": {"coordinates":[144.28590393100001,-36.7518005371],"type":"Point"}
}