{
  "type": "Feature",
  "properties": {
    "iso:country":"AU",
    "sg:address":"75 Oban Rd",
    "sg:city":"Ringwood North",
    "sg:classifiers":[
        {
            "category":"Manufacturing",
            "subcategory":"Food",
            "type":"Manufacturing & Wholesale Goods"
        }
    ],
    "sg:phone":"+61 3 9876 1028",
    "sg:postcode":"3134",
    "sg:province":"VIC",
    "sg:tags":[
        "function",
        "catering"
    ],
    "wof:name":"Carousel Home Catering",
    "wof:placetype":"venue"
},
  "geometry": {"coordinates":[145.24411010700001,-37.7950782776],"type":"Point"}
}