{
  "type": "Feature",
  "properties": {
    "iso:country":"AU",
    "sg:address":"37 Knox St",
    "sg:city":"Double Bay",
    "sg:classifiers":[
        {
            "category":"Shopping",
            "subcategory":"Shoes",
            "type":"Retail Goods"
        }
    ],
    "sg:phone":"+61 2 9327 7197",
    "sg:postcode":"2028",
    "sg:province":"NSW",
    "sg:tags":[
        "footwear"
    ],
    "wof:name":"Edward Meller",
    "wof:placetype":"venue"
},
  "geometry": {"coordinates":[151.24200439399999,-33.8766288757],"type":"Point"}
}