{
  "type": "Feature",
  "properties": {
    "addr:full":"Unit 4/ 41 Uralla Rd Port Macquarie NSW 2444",
    "addr:housenumber":"41",
    "addr:postcode":"2444",
    "addr:street":"Uralla Rd",
    "iso:country":"AU",
    "sg:address":"Unit 4/ 41 Uralla Rd",
    "sg:city":"Port Macquarie",
    "sg:classifiers":[
        {
            "category":"Manufacturing",
            "subcategory":"Electronics",
            "type":"Manufacturing & Wholesale Goods"
        }
    ],
    "sg:phone":"+61 2 6581 2077",
    "sg:postcode":"2444",
    "sg:province":"NSW",
    "sg:tags":[
        "wholesaler",
        "equipment",
        "part",
        "mfrs",
        "refrigeration"
    ],
    "wof:name":"Actrol Parts",
    "wof:placetype":"venue"
},
  "geometry": {"coordinates":[152.883118,-31.45372],"type":"Point"}
}