{
  "type": "Feature",
  "properties": {
    "addr:full":"65 Telford St Virginia QLD 4014",
    "addr:housenumber":"65",
    "addr:postcode":"4014",
    "addr:street":"Telford St",
    "iso:country":"AU",
    "sg:address":"65 Telford St",
    "sg:city":"Virginia",
    "sg:classifiers":[
        {
            "category":"Building & Trades",
            "subcategory":"Equipment Rental",
            "type":"Services"
        }
    ],
    "sg:phone":"+61 1300 368 707",
    "sg:postcode":"4014",
    "sg:province":"QLD",
    "sg:tags":[
        "demolition",
        "contractor"
    ],
    "wof:name":"Enviro Group Pty Ltd",
    "wof:placetype":"venue"
},
  "geometry": {"coordinates":[153.06526184099999,-27.3684654236],"type":"Point"}
}