{
  "type": "Feature",
  "properties": {
    "iso:country":"AU",
    "sg:address":"Mersing Rd",
    "sg:city":"Bathurst",
    "sg:classifiers":[
        {
            "category":"Real Estate",
            "subcategory":"Real Estate Services",
            "type":"Services"
        }
    ],
    "sg:phone":"+61 2 6337 3649",
    "sg:postcode":"2795",
    "sg:province":"NSW",
    "sg:tags":[
        "valuer"
    ],
    "wof:name":"Australian Appraisals",
    "wof:placetype":"venue"
},
  "geometry": {"coordinates":[149.70594787600001,-33.4181556702],"type":"Point"}
}