{
  "type": "Feature",
  "properties": {
    "addr:full":"Washington Ave Tingalpa QLD 4173",
    "addr:postcode":"4173",
    "addr:street":"Washington Ave",
    "iso:country":"AU",
    "sg:address":"Washington Ave",
    "sg:city":"Tingalpa",
    "sg:classifiers":[
        {
            "category":"Arena",
            "subcategory":"Sports Club",
            "type":"Entertainment"
        }
    ],
    "sg:phone":"+61 7 3390 4960",
    "sg:postcode":"4173",
    "sg:province":"QLD",
    "sg:tags":[
        "organisation",
        "sporting"
    ],
    "wof:name":"South Brisbane softball Association",
    "wof:placetype":"venue"
},
  "geometry": {"coordinates":[153.121948242,-27.476480484],"type":"Point"}
}