{
  "type": "Feature",
  "properties": {
    "iso:country":"AU",
    "sg:address":"Blg8/ 360 Swanston St",
    "sg:city":"Melbourne",
    "sg:classifiers":[
        {
            "category":"Cafe",
            "type":"Food & Drink"
        }
    ],
    "sg:phone":"+61 3 9663 0528",
    "sg:postcode":"3000",
    "sg:province":"VIC",
    "wof:name":"Monkee Juice Pty Ltd",
    "wof:placetype":"venue"
},
  "geometry": {"coordinates":[144.96363830600001,-37.8088264465],"type":"Point"}
}