{
  "type": "Feature",
  "properties": {
    "addr:full":"384 Wanneroo Rd Wangara WA 6065",
    "addr:housenumber":"384",
    "addr:postcode":"6065",
    "addr:street":"Wanneroo Rd",
    "iso:country":"AU",
    "sg:address":"384 Wanneroo Rd",
    "sg:city":"Wangara",
    "sg:classifiers":[
        {
            "category":"Home & Garden",
            "subcategory":"Garden Supply",
            "type":"Retail Goods"
        }
    ],
    "sg:phone":"+61 8 9409 9899",
    "sg:postcode":"6065",
    "sg:province":"WA",
    "sg:tags":[
        "landscape"
    ],
    "wof:name":"Lena Nursery",
    "wof:placetype":"venue"
},
  "geometry": {"coordinates":[115.81735229500001,-31.8004570007],"type":"Point"}
}