{
  "type": "Feature",
  "properties": {
    "addr:full":"34 Jaffa Rd Dural NSW 2158",
    "addr:housenumber":"34",
    "addr:postcode":"2158",
    "addr:street":"Jaffa Rd",
    "iso:country":"AU",
    "sg:address":"34 Jaffa Rd",
    "sg:city":"Dural",
    "sg:classifiers":[
        {
            "category":"Retail",
            "subcategory":"Auto Rental",
            "type":"Services"
        }
    ],
    "sg:phone":"+61 2 9651 2141",
    "sg:postcode":"2158",
    "sg:province":"NSW",
    "sg:tags":[
        "car",
        "hire",
        "minibus"
    ],
    "wof:name":"Dural Mini Bus Service",
    "wof:placetype":"venue"
},
  "geometry": {"coordinates":[151.02487182600001,-33.6941375732],"type":"Point"}
}