{
  "type": "Feature",
  "properties": {
    "addr:full":"PO Box 82 Snowtown SA 5520",
    "addr:postcode":"5520",
    "iso:country":"AU",
    "sg:address":"PO Box 82",
    "sg:city":"Snowtown",
    "sg:classifiers":[
        {
            "category":"Farming",
            "subcategory":"Farm",
            "type":"Manufacturing & Wholesale Goods"
        }
    ],
    "sg:phone":"+61 8 8865 2029",
    "sg:postcode":"5520",
    "sg:province":"SA",
    "sg:tags":[
        "farmer"
    ],
    "wof:name":"Ashby K T & Sons Pty Ltd",
    "wof:placetype":"venue"
},
  "geometry": {"coordinates":[138.20669555699999,-33.7859802246],"type":"Point"}
}