{
  "type": "Feature",
  "properties": {
    "iso:country":"AU",
    "sg:address":"20 Mary St",
    "sg:city":"Lilyfield",
    "sg:classifiers":[
        {
            "category":"Building & Trades",
            "subcategory":"Construction",
            "type":"Services"
        }
    ],
    "sg:phone":"+61 413 181 710",
    "sg:postcode":"2040",
    "sg:province":"NSW",
    "sg:tags":[
        "stonework",
        "stone",
        "mason"
    ],
    "wof:name":"Landers Michael",
    "wof:placetype":"venue"
},
  "geometry": {"coordinates":[151.15484599999999,-33.871796],"type":"Point"}
}