{
  "type": "Feature",
  "properties": {
    "iso:country":"AU",
    "sg:address":"Unit 1,37 Houston Rd",
    "sg:city":"Kingsford",
    "sg:classifiers":[
        {
            "category":"Shopping",
            "type":"Retail Goods"
        }
    ],
    "sg:phone":"+61 438 984 828",
    "sg:postcode":"2032",
    "sg:province":"NSW",
    "sg:tags":[
        "equipment",
        "safety",
        "accessory"
    ],
    "wof:name":"Centraline Safety products",
    "wof:placetype":"venue"
},
  "geometry": {"coordinates":[151.22492980999999,-33.9198188782],"type":"Point"}
}