{
  "type": "Feature",
  "properties": {
    "iso:country":"AU",
    "sg:address":"577 Morphett Rd",
    "sg:city":"Seacombe Gardens",
    "sg:classifiers":[
        {
            "category":"Fast Food",
            "type":"Food & Drink"
        }
    ],
    "sg:phone":"+61 8 8298 4098",
    "sg:postcode":"5047",
    "sg:province":"SA",
    "sg:tags":[
        "away",
        "take"
    ],
    "wof:name":"Sea Land Pizza & Seafood",
    "wof:placetype":"venue"
},
  "geometry": {"coordinates":[138.54179400000001,-35.026585],"type":"Point"}
}