{
  "type": "Feature",
  "properties": {
    "iso:country":"AU",
    "sg:address":"PO Box 1917",
    "sg:city":"Macquarie Centre",
    "sg:classifiers":[
        {
            "category":"Professional",
            "subcategory":"Detective & Security Services",
            "type":"Services"
        }
    ],
    "sg:phone":"+61 2 9889 0229",
    "sg:postcode":"2113",
    "sg:province":"NSW",
    "sg:tags":[
        "investigator"
    ],
    "wof:name":"Computer & Fraud Investigation Pty Limited",
    "wof:placetype":"venue"
},
  "geometry": {"coordinates":[151.13319397000001,-33.7892303467],"type":"Point"}
}