{
  "type": "Feature",
  "properties": {
    "addr:full":"Suite 3/ 670 Canterbury Rd Surrey Hills VIC 3127",
    "addr:housenumber":"/ 670",
    "addr:postcode":"3127",
    "addr:street":"Canterbury Rd",
    "iso:country":"AU",
    "sg:address":"Suite 3/ 670 Canterbury Rd",
    "sg:city":"Surrey Hills",
    "sg:classifiers":[
        {
            "category":"Professional",
            "subcategory":"Accounting & Tax Preparation",
            "type":"Services"
        }
    ],
    "sg:phone":"+61 3 9899 9933",
    "sg:postcode":"3127",
    "sg:province":"VIC",
    "sg:tags":[
        "deduction",
        "payroll"
    ],
    "wof:name":"Paywell Australia Pty Ltd",
    "wof:placetype":"venue"
},
  "geometry": {"coordinates":[145.1015625,-37.8265800476],"type":"Point"}
}