{
  "type": "Feature",
  "properties": {
    "addr:full":"68 Kirkham Rd West Keysborough VIC 3173",
    "addr:housenumber":"68",
    "addr:postcode":"3173",
    "addr:street":"Kirkham Rd West",
    "iso:country":"AU",
    "sg:address":"68 Kirkham Rd West",
    "sg:city":"Keysborough",
    "sg:classifiers":[
        {
            "category":"Manufacturing",
            "subcategory":"Rubber & Plastics",
            "type":"Manufacturing & Wholesale Goods"
        }
    ],
    "sg:phone":"+61 3 9798 8088",
    "sg:postcode":"3173",
    "sg:province":"VIC",
    "sg:tags":[
        "moulders"
    ],
    "wof:name":"D.M.G. Industries Pty Ltd",
    "wof:placetype":"venue"
},
  "geometry": {"coordinates":[145.187698364,-37.9961662292],"type":"Point"}
}