{
  "type": "Feature",
  "properties": {
    "addr:full":"27 Ashford Ave Milperra NSW 2214",
    "addr:housenumber":"27",
    "addr:postcode":"2214",
    "addr:street":"Ashford Ave",
    "iso:country":"AU",
    "sg:address":"27 Ashford Ave",
    "sg:city":"Milperra",
    "sg:classifiers":[
        {
            "category":"Manufacturing",
            "subcategory":"Glass & Minerals",
            "type":"Manufacturing & Wholesale Goods"
        }
    ],
    "sg:phone":"+61 2 9774 5077",
    "sg:postcode":"2214",
    "sg:province":"NSW",
    "sg:tags":[
        "equipment",
        "processing",
        "handling"
    ],
    "wof:name":"C.R.L. North Pty Ltd",
    "wof:placetype":"venue"
},
  "geometry": {"coordinates":[150.990555,-33.932114],"type":"Point"}
}