{
  "type": "Feature",
  "properties": {
    "iso:country":"AU",
    "sg:address":"47 West Burleigh Rd",
    "sg:city":"Burleigh Heads",
    "sg:classifiers":[
        {
            "category":"Health Services",
            "subcategory":"Doctor",
            "type":"Services"
        }
    ],
    "sg:phone":"+61 7 5535 1844",
    "sg:postcode":"4220",
    "sg:province":"QLD",
    "sg:tags":[
        "medical",
        "practitioner"
    ],
    "wof:name":"Ryan Seamus Dr",
    "wof:placetype":"venue"
},
  "geometry": {"coordinates":[153.442626953,-28.1005344391],"type":"Point"}
}