{
  "type": "Feature",
  "properties": {
    "iso:country":"AU",
    "sg:address":"17 Tolmie St",
    "sg:city":"Mt Gambier",
    "sg:classifiers":[
        {
            "category":"Building & Trades",
            "subcategory":"Construction",
            "type":"Services"
        }
    ],
    "sg:phone":"+61 8 8725 9006",
    "sg:postcode":"5290",
    "sg:province":"SA",
    "sg:tags":[
        "earth",
        "excavating",
        "moving",
        "contractor"
    ],
    "wof:name":"Walker And Gray Earthworks",
    "wof:placetype":"venue"
},
  "geometry": {"coordinates":[140.789841,-37.816738],"type":"Point"}
}