{
  "type": "Feature",
  "properties": {
    "iso:country":"AU",
    "sg:address":"78 Macquarie St",
    "sg:city":"George Town",
    "sg:classifiers":[
        {
            "category":"Government",
            "subcategory":"Post Office",
            "type":"Public Place"
        }
    ],
    "sg:phone":"+61 13 13 18",
    "sg:postcode":"7253",
    "sg:province":"TAS",
    "sg:tags":[
        "postal"
    ],
    "wof:name":"Australia Post",
    "wof:placetype":"venue"
},
  "geometry": {"coordinates":[146.82415771500001,-41.1067352295],"type":"Point"}
}