{
  "type": "Feature",
  "properties": {
    "addr:full":"310 Main South Rd Morphett Vale SA 5162",
    "addr:housenumber":"310",
    "addr:postcode":"5162",
    "addr:street":"Main South Rd",
    "iso:country":"AU",
    "sg:address":"310 Main South Rd",
    "sg:city":"Morphett Vale",
    "sg:classifiers":[
        {
            "category":"Home & Garden",
            "subcategory":"Kitchen Supply",
            "type":"Retail Goods"
        }
    ],
    "sg:phone":"+61 411 210 077",
    "sg:postcode":"5162",
    "sg:province":"SA",
    "sg:tags":[
        "sharpening"
    ],
    "wof:name":"The Knife Man",
    "wof:placetype":"venue"
},
  "geometry": {"coordinates":[138.52279663100001,-35.1104812622],"type":"Point"}
}