{
  "type": "Feature",
  "properties": {
    "addr:full":"St Kilda VIC 3182",
    "addr:postcode":"3182",
    "iso:country":"AU",
    "sg:address":"St",
    "sg:city":"Kilda",
    "sg:classifiers":[
        {
            "category":"Government",
            "subcategory":"Court House",
            "type":"Public Place"
        }
    ],
    "sg:phone":"+61 3 9526 6958",
    "sg:postcode":"3182",
    "sg:province":"VIC",
    "sg:tags":[
        "personal",
        "marriage",
        "family",
        "counselling"
    ],
    "wof:name":"Judith Ayre Holistic Counselling & Psychotherapy",
    "wof:placetype":"venue"
},
  "geometry": {"coordinates":[144.97959899899999,-37.8584403992],"type":"Point"}
}