{
  "type": "Feature",
  "properties": {
    "addr:full":"192 Nicholson St Footscray VIC 3011",
    "addr:housenumber":"192",
    "addr:postcode":"3011",
    "addr:street":"Nicholson St",
    "iso:country":"AU",
    "sg:address":"192 Nicholson St",
    "sg:city":"Footscray",
    "sg:classifiers":[
        {
            "category":"Travel",
            "subcategory":"Travel Agent",
            "type":"Entertainment"
        }
    ],
    "sg:phone":"+61 3 9687 1334",
    "sg:postcode":"3011",
    "sg:province":"VIC",
    "sg:tags":[
        "consultant"
    ],
    "wof:name":"Pasla Air Travel",
    "wof:placetype":"venue"
},
  "geometry": {"coordinates":[144.898895264,-37.802520752],"type":"Point"}
}