{
  "type": "Feature",
  "properties": {
    "addr:full":"9 Machinery Rd Yandina QLD 4561",
    "addr:postcode":"4561",
    "addr:street":"Machinery Rd",
    "iso:country":"AU",
    "sg:address":"9 Machinery Rd",
    "sg:city":"Yandina",
    "sg:classifiers":[
        {
            "category":"Wholesale",
            "subcategory":"Auto Parts",
            "type":"Manufacturing & Wholesale Goods"
        }
    ],
    "sg:phone":"+61 7 5472 7200",
    "sg:postcode":"4561",
    "sg:province":"QLD",
    "sg:tags":[
        "wholesaler",
        "mfrs",
        "lacquer"
    ],
    "wof:name":"Coastline Distributors Pty Ltd",
    "wof:placetype":"venue"
},
  "geometry": {"coordinates":[152.96202087399999,-26.5561466217],"type":"Point"}
}