{
  "type": "Feature",
  "properties": {
    "addr:full":"2A Pitcairn Ave Urrbrae SA 5064",
    "addr:housenumber":"2a",
    "addr:postcode":"5064",
    "addr:street":"Pitcairn Ave",
    "iso:country":"AU",
    "sg:address":"2A Pitcairn Ave",
    "sg:city":"Urrbrae",
    "sg:classifiers":[
        {
            "category":"Health Services",
            "subcategory":"Health Practitioner",
            "type":"Services"
        }
    ],
    "sg:phone":"+61 8 8271 7582",
    "sg:postcode":"5064",
    "sg:province":"SA",
    "sg:tags":[
        "naturopath"
    ],
    "wof:name":"Jezioranski Teresa",
    "wof:placetype":"venue"
},
  "geometry": {"coordinates":[138.638946533,-34.9641113281],"type":"Point"}
}