{
  "type": "Feature",
  "properties": {
    "addr:full":"5 Mahoney Drv Claremont TAS 7011",
    "addr:housenumber":"5",
    "addr:postcode":"7011",
    "addr:street":"Mahoney Drv",
    "iso:country":"AU",
    "sg:address":"5 Mahoney Drv",
    "sg:city":"Claremont",
    "sg:classifiers":[
        {
            "category":"Building & Trades",
            "subcategory":"Construction",
            "type":"Services"
        }
    ],
    "sg:phone":"+61 411 693 506",
    "sg:postcode":"7011",
    "sg:province":"TAS",
    "sg:tags":[
        "contractor"
    ],
    "wof:name":"Deegan Peter",
    "wof:placetype":"venue"
},
  "geometry": {"coordinates":[147.242431641,-42.7805671692],"type":"Point"}
}