{
  "type": "Feature",
  "properties": {
    "addr:full":"16 Napier St Warragul VIC 3820",
    "addr:housenumber":"16",
    "addr:postcode":"3820",
    "addr:street":"Napier St",
    "iso:country":"AU",
    "sg:address":"16 Napier St",
    "sg:city":"Warragul",
    "sg:classifiers":[
        {
            "category":"Personal",
            "subcategory":"Beauty Salon",
            "type":"Services"
        }
    ],
    "sg:phone":"+61 3 5622 0057",
    "sg:postcode":"3820",
    "sg:province":"VIC",
    "wof:name":"TTT Trim & Tone",
    "wof:placetype":"venue"
},
  "geometry": {"coordinates":[145.929596,-38.161877],"type":"Point"}
}