{
  "type": "Feature",
  "properties": {
    "iso:country":"AU",
    "sg:address":"ShopR1, Collier Rd",
    "sg:city":"Morley East",
    "sg:classifiers":[
        {
            "category":"Health Services",
            "subcategory":"Doctor",
            "type":"Services"
        }
    ],
    "sg:phone":"+61 8 9307 0707",
    "sg:postcode":"6062",
    "sg:province":"WA",
    "sg:tags":[
        "medical",
        "practitioner"
    ],
    "wof:name":"Belridge Medical Group",
    "wof:placetype":"venue"
},
  "geometry": {"coordinates":[115.917892456,-31.8889694214],"type":"Point"}
}