{
  "type": "Feature",
  "properties": {
    "addr:full":"915 MacArthur St Ballarat VIC 3350",
    "addr:housenumber":"915",
    "addr:postcode":"3350",
    "addr:street":"Macarthur St",
    "iso:country":"AU",
    "sg:address":"915 MacArthur St",
    "sg:city":"Ballarat",
    "sg:classifiers":[
        {
            "category":"Professional",
            "subcategory":"Art Services",
            "type":"Services"
        }
    ],
    "sg:phone":"+61 3 5333 4848",
    "sg:postcode":"3350",
    "sg:province":"VIC",
    "sg:tags":[
        "interior",
        "decorator"
    ],
    "wof:name":"Harlequin Designs",
    "wof:placetype":"venue"
},
  "geometry": {"coordinates":[143.84790000000001,-37.549904],"type":"Point"}
}