{
  "type": "Feature",
  "properties": {
    "addr:full":"Unit 10/ 98 Old Pittwater Rd Brookvale NSW 2100",
    "addr:housenumber":"/ 98",
    "addr:postcode":"2100",
    "addr:street":"Old Pittwater Rd",
    "iso:country":"AU",
    "sg:address":"Unit 10/ 98 Old Pittwater Rd",
    "sg:city":"Brookvale",
    "sg:classifiers":[
        {
            "category":"Military Area",
            "subcategory":"Air Force Base",
            "type":"Public Place"
        }
    ],
    "sg:phone":"+61 2 9905 9996",
    "sg:postcode":"2100",
    "sg:province":"NSW",
    "sg:tags":[
        "mounting",
        "finishing"
    ],
    "wof:name":"All Mounting & Die Cutting Services Pty Ltd",
    "wof:placetype":"venue"
},
  "geometry": {"coordinates":[151.26356506400001,-33.7635498047],"type":"Point"}
}