{
  "type": "Feature",
  "properties": {
    "addr:full":"PO Box 21 Hilltop NSW 2575",
    "addr:postcode":"2575",
    "iso:country":"AU",
    "sg:address":"PO Box 21",
    "sg:city":"Hilltop",
    "sg:classifiers":[
        {
            "category":"Professional",
            "subcategory":"Detective & Security Services",
            "type":"Services"
        }
    ],
    "sg:phone":"+61 423 121 612",
    "sg:postcode":"2575",
    "sg:province":"NSW",
    "sg:tags":[
        "domestic",
        "alarm",
        "commercial",
        "burglar"
    ],
    "wof:name":"Allround Lectronics",
    "wof:placetype":"venue"
},
  "geometry": {"coordinates":[150.390716553,-34.3214492798],"type":"Point"}
}