{
  "type": "Feature",
  "properties": {
    "addr:full":"60 Burns Rd Wahroonga NSW 2076",
    "addr:housenumber":"60",
    "addr:postcode":"2076",
    "addr:street":"Burns Rd",
    "iso:country":"AU",
    "sg:address":"60 Burns Rd",
    "sg:city":"Wahroonga",
    "sg:classifiers":[
        {
            "category":"Education",
            "subcategory":"School",
            "type":"Public Place"
        }
    ],
    "sg:phone":"+61 2 9487 1700",
    "sg:postcode":"2076",
    "sg:province":"NSW",
    "wof:name":"Catholic Schools Centre For The Visually Impaired",
    "wof:placetype":"venue"
},
  "geometry": {"coordinates":[151.12611389200001,-33.714099884],"type":"Point"}
}