{
  "type": "Feature",
  "properties": {
    "addr:full":"1 North St Batemans Bay NSW 2536",
    "addr:housenumber":"1",
    "addr:postcode":"2536",
    "addr:street":"North St",
    "iso:country":"AU",
    "sg:address":"1 North St",
    "sg:city":"Batemans Bay",
    "sg:classifiers":[
        {
            "category":"Real Estate",
            "subcategory":"Real Estate Agent",
            "type":"Services"
        }
    ],
    "sg:phone":"+61 2 4472 9888",
    "sg:postcode":"2536",
    "sg:province":"NSW",
    "wof:name":"Buckley Ken Caravan Park Broker",
    "wof:placetype":"venue"
},
  "geometry": {"coordinates":[150.17771911599999,-35.7060203552],"type":"Point"}
}