{
  "type": "Feature",
  "properties": {
    "addr:full":"77 Tallagandra Drv Quakers Hill NSW 2763",
    "addr:housenumber":"77",
    "addr:postcode":"2763",
    "addr:street":"Tallagandra Drv",
    "iso:country":"AU",
    "sg:address":"77 Tallagandra Drv",
    "sg:city":"Quakers Hill",
    "sg:classifiers":[
        {
            "category":"Building & Trades",
            "subcategory":"Construction",
            "type":"Services"
        }
    ],
    "sg:phone":"+61 2 9837 7865",
    "sg:postcode":"2763",
    "sg:province":"NSW",
    "sg:tags":[
        "contractor"
    ],
    "wof:name":"Thornlands Development Corporation",
    "wof:placetype":"venue"
},
  "geometry": {"coordinates":[150.87513732900001,-33.7406616211],"type":"Point"}
}