{
  "type": "Feature",
  "properties": {
    "addr:full":"9 Arbutus St Mosman NSW 2088",
    "addr:housenumber":"9",
    "addr:postcode":"2088",
    "addr:street":"Arbutus St",
    "iso:country":"AU",
    "sg:address":"9 Arbutus St",
    "sg:city":"Mosman",
    "sg:classifiers":[
        {
            "category":"Professional",
            "subcategory":"Employment Agencies",
            "type":"Services"
        }
    ],
    "sg:phone":"+61 2 9969 2870",
    "sg:postcode":"2088",
    "sg:province":"NSW",
    "sg:tags":[
        "occupational",
        "therapist"
    ],
    "wof:name":"Ernst S",
    "wof:placetype":"venue"
},
  "geometry": {"coordinates":[151.24598693900001,-33.8251304626],"type":"Point"}
}