{
  "type": "Feature",
  "properties": {
    "iso:country":"AU",
    "sg:address":"16 Mayfield Rd",
    "sg:city":"Moorooka",
    "sg:classifiers":[
        {
            "category":"Real Estate",
            "subcategory":"Real Estate Agent",
            "type":"Services"
        }
    ],
    "sg:phone":"+61 7 3892 4844",
    "sg:postcode":"4105",
    "sg:province":"QLD",
    "wof:name":"Daynes Residential Real Estate",
    "wof:placetype":"venue"
},
  "geometry": {"coordinates":[153.02597045900001,-27.532793045],"type":"Point"}
}