{
  "type": "Feature",
  "properties": {
    "iso:country":"AU",
    "sg:address":"Grn Flr, 223",
    "sg:city":"Belgrave Esp Sylvania Waters",
    "sg:classifiers":[
        {
            "category":"Health Services",
            "subcategory":"Health Practitioner",
            "type":"Services"
        }
    ],
    "sg:phone":"+61 2 9544 6555",
    "sg:postcode":"2224",
    "sg:province":"NSW",
    "sg:tags":[
        "physiotherapist"
    ],
    "wof:name":"Southern Districts Sports Physiotherapy",
    "wof:placetype":"venue"
},
  "geometry": {"coordinates":[151.10969543499999,-34.0239257812],"type":"Point"}
}