{
  "type": "Feature",
  "properties": {
    "iso:country":"AU",
    "sg:address":"127 Murarrie Rd",
    "sg:city":"Murarrie",
    "sg:classifiers":[
        {
            "category":"Retail",
            "subcategory":"Auto Repair",
            "type":"Services"
        }
    ],
    "sg:phone":"+61 7 3890 1948",
    "sg:postcode":"4172",
    "sg:province":"QLD",
    "sg:tags":[
        "body",
        "motor",
        "trimmer"
    ],
    "wof:name":"Lledo Trimmers",
    "wof:placetype":"venue"
},
  "geometry": {"coordinates":[153.102859497,-27.4652061462],"type":"Point"}
}