{
  "type": "Feature",
  "properties": {
    "addr:full":"Cnr Ipswich Rd & Michlin St Moorooka QLD 4105",
    "addr:postcode":"4105",
    "addr:street":"Ipswich Rd & Michlin St",
    "iso:country":"AU",
    "sg:address":"Cnr Ipswich Rd & Michlin St",
    "sg:city":"Moorooka",
    "sg:classifiers":[
        {
            "category":"Retail",
            "subcategory":"Event Space",
            "type":"Services"
        }
    ],
    "sg:phone":"+61 7 3848 4444",
    "sg:postcode":"4105",
    "sg:province":"QLD",
    "sg:tags":[
        "venue",
        "reception",
        "wedding"
    ],
    "wof:name":"A City Party Hire",
    "wof:placetype":"venue"
},
  "geometry": {"coordinates":[153.01985168499999,-27.5285778046],"type":"Point"}
}