{
  "type": "Feature",
  "properties": {
    "iso:country":"AU",
    "sg:address":"PO Box 297",
    "sg:city":"New Lambton",
    "sg:classifiers":[
        {
            "category":"Utilities",
            "subcategory":"Electric",
            "type":"Services"
        }
    ],
    "sg:phone":"+61 418 431 456",
    "sg:postcode":"2305",
    "sg:province":"NSW",
    "sg:tags":[
        "electrical",
        "contractor"
    ],
    "wof:name":"Eltrec Pty Ltd",
    "wof:placetype":"venue"
},
  "geometry": {"coordinates":[151.713501,-32.920181],"type":"Point"}
}