{
  "type": "Feature",
  "properties": {
    "addr:full":"6 South Banff Rd Floreat WA 6014",
    "addr:housenumber":"6",
    "addr:postcode":"6014",
    "addr:street":"South Banff Rd",
    "iso:country":"AU",
    "sg:address":"6 South Banff Rd",
    "sg:city":"Floreat",
    "sg:classifiers":[
        {
            "category":"Health Services",
            "subcategory":"Health Practitioner",
            "type":"Services"
        }
    ],
    "sg:phone":"+61 8 9387 6567",
    "sg:postcode":"6014",
    "sg:province":"WA",
    "sg:tags":[
        "psychologist"
    ],
    "wof:name":"Williams J",
    "wof:placetype":"venue"
},
  "geometry": {"coordinates":[115.800849915,-31.9327373505],"type":"Point"}
}