{
  "type": "Feature",
  "properties": {
    "addr:full":"293 Sandgate Rd Albion QLD 4010",
    "addr:housenumber":"293",
    "addr:postcode":"4010",
    "addr:street":"Sandgate Rd",
    "iso:country":"AU",
    "sg:address":"293 Sandgate Rd",
    "sg:city":"Albion",
    "sg:classifiers":[
        {
            "category":"Manufacturing",
            "subcategory":"Food",
            "type":"Manufacturing & Wholesale Goods"
        }
    ],
    "sg:phone":"+61 7 3862 4599",
    "sg:postcode":"4010",
    "sg:province":"QLD",
    "sg:tags":[
        "function",
        "catering"
    ],
    "wof:name":"Efes One Turkish Catering Co",
    "wof:placetype":"venue"
},
  "geometry": {"coordinates":[153.04182434099999,-27.4301681519],"type":"Point"}
}