{
  "type": "Feature",
  "properties": {
    "addr:full":"Factory 2 5 Ovata Drv Tullamarine VIC 3043",
    "addr:housenumber":"5",
    "addr:postcode":"3043",
    "addr:street":"Ovata Drv",
    "iso:country":"AU",
    "sg:address":"Factory 2 5 Ovata Drv",
    "sg:city":"Tullamarine",
    "sg:classifiers":[
        {
            "category":"Manufacturing",
            "subcategory":"Chemicals & Compounds",
            "type":"Manufacturing & Wholesale Goods"
        }
    ],
    "sg:phone":"+61 3 9330 2333",
    "sg:postcode":"3043",
    "sg:province":"VIC",
    "sg:tags":[
        "electroplating"
    ],
    "wof:name":"Eurocoat Powder Coating",
    "wof:placetype":"venue"
},
  "geometry": {"coordinates":[144.86544799800001,-37.7113075256],"type":"Point"}
}