{
  "type": "Feature",
  "properties": {
    "addr:full":"2a Meredith St Elwood VIC 3184",
    "addr:housenumber":"2a",
    "addr:postcode":"3184",
    "addr:street":"Meredith St",
    "iso:country":"AU",
    "sg:address":"2a Meredith St",
    "sg:city":"Elwood",
    "sg:classifiers":[
        {
            "category":"Professional",
            "subcategory":"Management & Consulting",
            "type":"Services"
        }
    ],
    "sg:phone":"+61 438 393 795",
    "sg:postcode":"3184",
    "sg:province":"VIC",
    "sg:tags":[
        "consultant",
        "migration"
    ],
    "wof:name":"S P Fahey Immigration Services",
    "wof:placetype":"venue"
},
  "geometry": {"coordinates":[144.98321533199999,-37.8773422241],"type":"Point"}
}