{
  "type": "Feature",
  "properties": {
    "addr:full":"Suite 1, Level 1, 42 Nerang St Southport QLD 4215",
    "addr:housenumber":"42",
    "addr:postcode":"4215",
    "addr:street":"Nerang St",
    "iso:country":"AU",
    "sg:address":"Suite 1, Level 1, 42 Nerang St",
    "sg:city":"Southport",
    "sg:classifiers":[
        {
            "category":"Building & Trades",
            "subcategory":"Construction",
            "type":"Services"
        }
    ],
    "sg:phone":"+61 7 5531 4966",
    "sg:postcode":"4215",
    "sg:province":"QLD",
    "sg:tags":[
        "contractor"
    ],
    "wof:name":"Limeplace Constructions Pty Ltd",
    "wof:placetype":"venue"
},
  "geometry": {"coordinates":[153.4140625,-27.9676399231],"type":"Point"}
}