{
  "type": "Feature",
  "properties": {
    "addr:full":"Shop 1 Centro Hervey Bay Shopping Centre Boat Harbou QLD 4655",
    "addr:housenumber":"shop 1",
    "addr:postcode":"4655",
    "iso:country":"AU",
    "sg:address":"Shop 1",
    "sg:city":"Centro Hervey Bay Shopping Centre Boat Harbou",
    "sg:classifiers":[
        {
            "category":"Travel",
            "subcategory":"Travel Agent",
            "type":"Entertainment"
        }
    ],
    "sg:phone":"+61 7 4124 4000",
    "sg:postcode":"4655",
    "sg:province":"QLD",
    "sg:tags":[
        "consultant"
    ],
    "wof:name":"Hervey Bay Coach Terminal & Transit Centre",
    "wof:placetype":"venue"
},
  "geometry": {"coordinates":[152.836288,-25.287842],"type":"Point"}
}