{
  "type": "Feature",
  "properties": {
    "iso:country":"AU",
    "sg:address":"11- 126 Compton Rd",
    "sg:city":"Logan Central",
    "sg:classifiers":[
        {
            "category":"Building & Trades",
            "subcategory":"Cleaning & Sanitation",
            "type":"Services"
        }
    ],
    "sg:phone":"+61 7 3808 1055",
    "sg:postcode":"4114",
    "sg:province":"QLD",
    "sg:tags":[
        "chemical",
        "pressure",
        "steam",
        "contractor"
    ],
    "wof:name":"J &#039;n&#039; T Cleaning Services",
    "wof:placetype":"venue"
},
  "geometry": {"coordinates":[153.113677978,-27.6200790405],"type":"Point"}
}