{
  "type": "Feature",
  "properties": {
    "iso:country":"AU",
    "sg:address":"4 Dugan St",
    "sg:city":"Deakin",
    "sg:classifiers":[
        {
            "category":"Professional",
            "subcategory":"Accounting & Tax Preparation",
            "type":"Services"
        }
    ],
    "sg:phone":"+61 2 6281 3360",
    "sg:postcode":"2600",
    "sg:province":"ACT",
    "sg:tags":[
        "accountant",
        "auditor"
    ],
    "wof:name":"Auswild & Co",
    "wof:placetype":"venue"
},
  "geometry": {"coordinates":[149.109283447,-35.3188247681],"type":"Point"}
}