{
  "type": "Feature",
  "properties": {
    "iso:country":"AU",
    "sg:address":"3 Antony St",
    "sg:city":"Christie Downs",
    "sg:classifiers":[
        {
            "category":"Building & Trades",
            "subcategory":"Construction",
            "type":"Services"
        }
    ],
    "sg:phone":"+61 412 572 766",
    "sg:postcode":"5164",
    "sg:province":"SA",
    "sg:tags":[
        "welding"
    ],
    "wof:name":"Keast Welding",
    "wof:placetype":"venue"
},
  "geometry": {"coordinates":[138.49940490700001,-35.1320495605],"type":"Point"}
}