{
  "type": "Feature",
  "properties": {
    "addr:full":"Viero Rd Brandon QLD 4808",
    "addr:postcode":"4808",
    "addr:street":"Viero Rd",
    "iso:country":"AU",
    "sg:address":"Viero Rd",
    "sg:city":"Brandon",
    "sg:classifiers":[
        {
            "category":"Farming",
            "subcategory":"Farm",
            "type":"Manufacturing & Wholesale Goods"
        }
    ],
    "sg:phone":"+61 417 643 287",
    "sg:postcode":"4808",
    "sg:province":"QLD",
    "sg:tags":[
        "farmer"
    ],
    "wof:name":"Viero John W",
    "wof:placetype":"venue"
},
  "geometry": {"coordinates":[147.31871032699999,-19.5801410675],"type":"Point"}
}