{
  "type": "Feature",
  "properties": {
    "addr:full":"Unit 7 42 Collingwood St Osborne Park WA 6017",
    "addr:housenumber":"42",
    "addr:postcode":"6017",
    "addr:street":"Collingwood St",
    "iso:country":"AU",
    "sg:address":"Unit 7 42 Collingwood St",
    "sg:city":"Osborne Park",
    "sg:classifiers":[
        {
            "category":"Organizations",
            "subcategory":"Community Association",
            "type":"Services"
        }
    ],
    "sg:phone":"+61 8 9446 1671",
    "sg:postcode":"6017",
    "sg:province":"WA",
    "sg:tags":[
        "organisation",
        "family",
        "welfare"
    ],
    "wof:name":"Growing Families International",
    "wof:placetype":"venue"
},
  "geometry": {"coordinates":[115.815368652,-31.9030342102],"type":"Point"}
}