{
  "type": "Feature",
  "properties": {
    "addr:full":"Bendigo St Bendigo VIC 3550",
    "addr:postcode":"3550",
    "addr:street":"Bendigo St",
    "iso:country":"AU",
    "sg:address":"Bendigo St",
    "sg:city":"Bendigo",
    "sg:classifiers":[
        {
            "category":"Building & Trades",
            "subcategory":"Pest Control",
            "type":"Services"
        }
    ],
    "sg:phone":"+61 1800 067 711",
    "sg:postcode":"3550",
    "sg:province":"VIC",
    "wof:name":"Natural Pest Control",
    "wof:placetype":"venue"
},
  "geometry": {"coordinates":[144.294998169,-36.7726402283],"type":"Point"}
}