{
  "type": "Feature",
  "properties": {
    "iso:country":"AU",
    "sg:address":"PO Box 154",
    "sg:city":"Scone",
    "sg:classifiers":[
        {
            "category":"Building & Trades",
            "subcategory":"Plumbing",
            "type":"Services"
        }
    ],
    "sg:phone":"+61 2 6545 2361",
    "sg:postcode":"2337",
    "sg:province":"NSW",
    "sg:tags":[
        "plumber",
        "gasfitters"
    ],
    "wof:name":"Carr PJ & DS",
    "wof:placetype":"venue"
},
  "geometry": {"coordinates":[150.86781310999999,-32.0457496643],"type":"Point"}
}