{
  "type": "Feature",
  "properties": {
    "addr:full":"Factory 8, 57- 59 Melverton Drv Hallam VIC 3803",
    "addr:housenumber":"57 59",
    "addr:postcode":"3803",
    "addr:street":"Melverton Drv",
    "iso:country":"AU",
    "sg:address":"Factory 8, 57- 59 Melverton Drv",
    "sg:city":"Hallam",
    "sg:classifiers":[
        {
            "category":"Autos & Motor Vehicles",
            "subcategory":"Auto Supplies",
            "type":"Retail Goods"
        }
    ],
    "sg:phone":"+61 1800 676 317",
    "sg:postcode":"3803",
    "sg:province":"VIC",
    "sg:tags":[
        "garage",
        "equipment"
    ],
    "wof:name":"Alljacks & Hoists",
    "wof:placetype":"venue"
},
  "geometry": {"coordinates":[145.272537231,-38.0115852356],"type":"Point"}
}