{
  "type": "Feature",
  "properties": {
    "addr:full":"1153 High St Armadale VIC 3143",
    "addr:housenumber":"1153",
    "addr:postcode":"3143",
    "addr:street":"High St",
    "iso:country":"AU",
    "sg:address":"1153 High St",
    "sg:city":"Armadale",
    "sg:classifiers":[
        {
            "category":"Shopping",
            "subcategory":"Jewelry",
            "type":"Retail Goods"
        }
    ],
    "sg:phone":"+61 3 9822 0455",
    "sg:postcode":"3143",
    "sg:province":"VIC",
    "sg:tags":[
        "jeweller"
    ],
    "wof:name":"Impala-Armadale",
    "wof:placetype":"venue"
},
  "geometry": {"coordinates":[145.026290894,-37.856086731],"type":"Point"}
}