{
  "type": "Feature",
  "properties": {
    "iso:country":"AU",
    "sg:address":"132 Torquay Rd",
    "sg:city":"Grovedale",
    "sg:classifiers":[
        {
            "category":"Home & Garden",
            "subcategory":"Carpets & Floor Coverings",
            "type":"Retail Goods"
        }
    ],
    "sg:phone":"+61 3 5241 1108",
    "sg:postcode":"3216",
    "sg:province":"VIC",
    "sg:tags":[
        "mattress"
    ],
    "wof:name":"Slumberworld",
    "wof:placetype":"venue"
},
  "geometry": {"coordinates":[144.34051513700001,-38.2066764832],"type":"Point"}
}