{
  "type": "Feature",
  "properties": {
    "iso:country":"AU",
    "sg:address":"Shop 5 K-Mart Plaza Mount St",
    "sg:city":"Burnie",
    "sg:classifiers":[
        {
            "category":"Shopping",
            "subcategory":"Jewelry",
            "type":"Retail Goods"
        }
    ],
    "sg:phone":"+61 3 6431 8580",
    "sg:postcode":"7320",
    "sg:province":"TAS",
    "sg:tags":[
        "jeweller"
    ],
    "wof:name":"Kleins Jewellery",
    "wof:placetype":"venue"
},
  "geometry": {"coordinates":[145.899719,-41.076279],"type":"Point"}
}