{
  "type": "Feature",
  "properties": {
    "addr:full":"1/ 25 Norfolk Ave Nowra South NSW 2541",
    "addr:housenumber":"/ 25",
    "addr:postcode":"2541",
    "addr:street":"Norfolk Ave",
    "iso:country":"AU",
    "sg:address":"1/ 25 Norfolk Ave",
    "sg:city":"Nowra South",
    "sg:classifiers":[
        {
            "category":"Sports & Exercise",
            "subcategory":"Ski Resort",
            "type":"Entertainment"
        }
    ],
    "sg:phone":"+61 2 4423 0977",
    "sg:postcode":"2541",
    "sg:province":"NSW",
    "sg:tags":[
        "propelled",
        "jet"
    ],
    "wof:name":"O 2 Motor Sports",
    "wof:placetype":"venue"
},
  "geometry": {"coordinates":[150.60409545900001,-34.9050178528],"type":"Point"}
}