{
  "type": "Feature",
  "properties": {
    "addr:full":"Suite 101/ 332 Oxford St Bondi Junction NSW 2022",
    "addr:housenumber":"/ 332",
    "addr:postcode":"2022",
    "addr:street":"Oxford St",
    "iso:country":"AU",
    "sg:address":"Suite 101/ 332 Oxford St",
    "sg:city":"Bondi Junction",
    "sg:classifiers":[
        {
            "category":"Professional",
            "subcategory":"Accounting & Tax Preparation",
            "type":"Services"
        }
    ],
    "sg:phone":"+61 2 9387 4890",
    "sg:postcode":"2022",
    "sg:province":"NSW",
    "sg:tags":[
        "accountant",
        "auditor"
    ],
    "wof:name":"Cofficient",
    "wof:placetype":"venue"
},
  "geometry": {"coordinates":[151.246017456,-33.8912200928],"type":"Point"}
}