{
  "type": "Feature",
  "properties": {
    "addr:full":"24/ 2a Bayswater Rd Kings Cross NSW 2011",
    "addr:housenumber":"24 / 2a",
    "addr:postcode":"2011",
    "addr:street":"Bayswater Rd",
    "iso:country":"AU",
    "sg:address":"24/ 2a Bayswater Rd",
    "sg:city":"Kings Cross",
    "sg:classifiers":[
        {
            "category":"Professional",
            "subcategory":"Business Services",
            "type":"Services"
        }
    ],
    "sg:phone":"+61 2 9368 0434",
    "sg:postcode":"2011",
    "sg:province":"NSW",
    "sg:tags":[
        "consultant",
        "promoter",
        "entertainment"
    ],
    "wof:name":"Tropfest Pty Ltd",
    "wof:placetype":"venue"
},
  "geometry": {"coordinates":[151.22303772000001,-33.8750572205],"type":"Point"}
}