{
  "type": "Feature",
  "properties": {
    "addr:full":"Homebase Shopping Centre Shop 8 & 9, 19 Stoddart R Blacktown NSW 2148",
    "addr:housenumber":"shop 8 &;19",
    "addr:postcode":"2148",
    "addr:street":"9;R Blacktown",
    "iso:country":"AU",
    "sg:address":"Homebase Shopping Centre Shop 8 & 9, 19 Stoddart R",
    "sg:city":"Blacktown",
    "sg:classifiers":[
        {
            "category":"Home & Garden",
            "subcategory":"Carpets & Floor Coverings",
            "type":"Retail Goods"
        }
    ],
    "sg:phone":"+61 2 9688 4528",
    "sg:postcode":"2148",
    "sg:province":"NSW",
    "sg:tags":[
        "tile",
        "wall"
    ],
    "wof:name":"Ceramic Tile Market",
    "wof:placetype":"venue"
},
  "geometry": {"coordinates":[150.920166016,-33.799911499],"type":"Point"}
}