{
  "type": "Feature",
  "properties": {
    "addr:full":"129 Dalton Rd Thomastown VIC 3074",
    "addr:housenumber":"129",
    "addr:postcode":"3074",
    "addr:street":"Dalton Rd",
    "iso:country":"AU",
    "sg:address":"129 Dalton Rd",
    "sg:city":"Thomastown",
    "sg:classifiers":[
        {
            "category":"Building & Trades",
            "subcategory":"Construction",
            "type":"Services"
        }
    ],
    "sg:phone":"+61 419 322 841",
    "sg:postcode":"3074",
    "sg:province":"VIC",
    "sg:tags":[
        "concrete",
        "paving"
    ],
    "wof:name":"Sampa Concrete Paving",
    "wof:placetype":"venue"
},
  "geometry": {"coordinates":[145.03012085,-37.6774902344],"type":"Point"}
}