{
  "type": "Feature",
  "properties": {
    "addr:full":"2 Barden Rd Gilgandra NSW 2827",
    "addr:housenumber":"2",
    "addr:postcode":"2827",
    "addr:street":"Barden Rd",
    "iso:country":"AU",
    "sg:address":"2 Barden Rd",
    "sg:city":"Gilgandra",
    "sg:classifiers":[
        {
            "category":"Food & Beverages",
            "subcategory":"Groceries & Convenience Stores",
            "type":"Retail Goods"
        }
    ],
    "sg:phone":"+61 2 6847 1032",
    "sg:postcode":"2827",
    "sg:province":"NSW",
    "wof:name":"Top Shop The",
    "wof:placetype":"venue"
},
  "geometry": {"coordinates":[148.64689636200001,-31.7094078064],"type":"Point"}
}