{
  "type": "Feature",
  "properties": {
    "iso:country":"AU",
    "sg:address":"3C Douglass St",
    "sg:city":"Geelong",
    "sg:classifiers":[
        {
            "category":"Arena",
            "subcategory":"Sports Club",
            "type":"Entertainment"
        }
    ],
    "sg:phone":"+61 1300 663 879",
    "sg:postcode":"3220",
    "sg:province":"VIC",
    "sg:tags":[
        "defence",
        "supply",
        "self",
        "instruction",
        "martial art"
    ],
    "wof:name":"Issei Ryu Bujutsu",
    "wof:placetype":"venue"
},
  "geometry": {"coordinates":[144.33265700000001,-38.133072],"type":"Point"}
}