{
  "type": "Feature",
  "properties": {
    "addr:full":"473 Hammond Rd Dandenong South VIC 3175",
    "addr:housenumber":"473",
    "addr:postcode":"3175",
    "addr:street":"Hammond Rd",
    "iso:country":"AU",
    "sg:address":"473 Hammond Rd",
    "sg:city":"Dandenong South",
    "sg:classifiers":[
        {
            "category":"Manufacturing",
            "subcategory":"Glass & Minerals",
            "type":"Manufacturing & Wholesale Goods"
        }
    ],
    "sg:phone":"+61 3 9768 2400",
    "sg:postcode":"3175",
    "sg:province":"VIC",
    "sg:tags":[
        "bending",
        "tube"
    ],
    "wof:name":"Glennsam Welding & Fabrication Pty Ltd",
    "wof:placetype":"venue"
},
  "geometry": {"coordinates":[145.20274352999999,-38.0294914246],"type":"Point"}
}