{
  "type": "Feature",
  "properties": {
    "addr:full":"5-7 Woodbury Business Centre 172 McIvor Rd Bendigo VIC 3550",
    "addr:housenumber":"5-7;172",
    "addr:postcode":"3550",
    "addr:street":"Woodbury Business;Mcivor Rd",
    "iso:country":"AU",
    "sg:address":"5-7 Woodbury Business Centre 172 McIvor Rd",
    "sg:city":"Bendigo",
    "sg:classifiers":[
        {
            "category":"Banks & Credit Unions",
            "subcategory":"Financial Services",
            "type":"Services"
        }
    ],
    "sg:phone":"+61 3 5441 6911",
    "sg:postcode":"3550",
    "sg:province":"VIC",
    "sg:tags":[
        "annuity",
        "rollover",
        "superannuation",
        "consultant"
    ],
    "wof:name":"OptiWealth Solutions",
    "wof:placetype":"venue"
},
  "geometry": {"coordinates":[144.310424805,-36.759311676],"type":"Point"}
}