{
  "type": "Feature",
  "properties": {
    "addr:full":"7 Mount Barker Rd Littlehampton SA 5250",
    "addr:housenumber":"7",
    "addr:postcode":"5250",
    "addr:street":"Mount Barker Rd",
    "iso:country":"AU",
    "sg:address":"7 Mount Barker Rd",
    "sg:city":"Littlehampton",
    "sg:classifiers":[
        {
            "category":"Shopping",
            "subcategory":"Luggage & Leather Goods",
            "type":"Retail Goods"
        }
    ],
    "sg:phone":"+61 8 8398 5135",
    "sg:postcode":"5250",
    "sg:province":"SA",
    "wof:name":"Horseland Superstore",
    "wof:placetype":"venue"
},
  "geometry": {"coordinates":[138.85011291500001,-35.0537071228],"type":"Point"}
}