{
  "type": "Feature",
  "properties": {
    "iso:country":"AU",
    "sg:address":"472 George St",
    "sg:city":"Sydney",
    "sg:classifiers":[
        {
            "category":"Manufacturing",
            "subcategory":"Jewelry",
            "type":"Manufacturing & Wholesale Goods"
        }
    ],
    "sg:phone":"+61 2 9267 5471",
    "sg:postcode":"2000",
    "sg:province":"NSW",
    "sg:tags":[
        "mfrg",
        "jeweller"
    ],
    "wof:name":"Bower Bird Design Pty Ltd",
    "wof:placetype":"venue"
},
  "geometry": {"coordinates":[151.20715332,-33.8714103699],"type":"Point"}
}