{
  "type": "Feature",
  "properties": {
    "addr:full":"14 Cedar St Lindisfarne TAS 7015",
    "addr:housenumber":"14",
    "addr:postcode":"7015",
    "addr:street":"Cedar St",
    "iso:country":"AU",
    "sg:address":"14 Cedar St",
    "sg:city":"Lindisfarne",
    "sg:classifiers":[
        {
            "category":"Arena",
            "subcategory":"Sports Club",
            "type":"Entertainment"
        }
    ],
    "sg:phone":"+61 3 6243 7545",
    "sg:postcode":"7015",
    "sg:province":"TAS",
    "sg:tags":[
        "organisation",
        "sporting"
    ],
    "wof:name":"Special Olympics Tasmania",
    "wof:placetype":"venue"
},
  "geometry": {"coordinates":[147.36827087399999,-42.8496704102],"type":"Point"}
}