{
  "type": "Feature",
  "properties": {
    "iso:country":"AU",
    "sg:address":"3 Mirabelle Cntr Ward Pl",
    "sg:city":"Round Corner",
    "sg:classifiers":[
        {
            "category":"Personal",
            "subcategory":"Beauty Salon",
            "type":"Services"
        }
    ],
    "sg:phone":"+61 2 9651 1792",
    "sg:postcode":"2158",
    "sg:province":"NSW",
    "sg:tags":[
        "hairdresser"
    ],
    "wof:name":"Soignee The Last Word In Hair Design",
    "wof:placetype":"venue"
},
  "geometry": {"coordinates":[151.02012634299999,-33.6927757263],"type":"Point"}
}