{
  "type": "Feature",
  "properties": {
    "addr:full":"Marma St Murtoa VIC 3390",
    "addr:postcode":"3390",
    "addr:street":"Marma St",
    "iso:country":"AU",
    "sg:address":"Marma St",
    "sg:city":"Murtoa",
    "sg:classifiers":[
        {
            "category":"Professional",
            "subcategory":"Business Services",
            "type":"Services"
        }
    ],
    "sg:phone":"+61 3 5385 2560",
    "sg:postcode":"3390",
    "sg:province":"VIC",
    "sg:tags":[
        "livestock",
        "transport"
    ],
    "wof:name":"Lindsay D J & L M",
    "wof:placetype":"venue"
},
  "geometry": {"coordinates":[142.47401428200001,-36.6201515198],"type":"Point"}
}