{
  "type": "Feature",
  "properties": {
    "iso:country":"AU",
    "sg:address":"Unit 4 25 Langley Rd",
    "sg:city":"Port Douglas",
    "sg:classifiers":[
        {
            "category":"Real Estate",
            "subcategory":"Architect",
            "type":"Services"
        }
    ],
    "sg:phone":"+61 7 4098 5572",
    "sg:postcode":"4877",
    "sg:province":"QLD",
    "wof:name":"Best Overend & Associates",
    "wof:placetype":"venue"
},
  "geometry": {"coordinates":[145.46624755900001,-16.5170974731],"type":"Point"}
}