{
  "type": "Feature",
  "properties": {
    "addr:full":"4 Moss Ave Marleston SA 5033",
    "addr:housenumber":"4",
    "addr:postcode":"5033",
    "addr:street":"Moss Ave",
    "iso:country":"AU",
    "sg:address":"4 Moss Ave",
    "sg:city":"Marleston",
    "sg:classifiers":[
        {
            "category":"Building & Trades",
            "subcategory":"Equipment Rental",
            "type":"Services"
        }
    ],
    "sg:phone":"+61 8 8293 6687",
    "sg:postcode":"5033",
    "sg:province":"SA",
    "sg:tags":[
        "supply",
        "catering"
    ],
    "wof:name":"M.S. Thomas Electrical",
    "wof:placetype":"venue"
},
  "geometry": {"coordinates":[138.56683349599999,-34.9427642822],"type":"Point"}
}