{
  "type": "Feature",
  "properties": {
    "addr:full":"55 Verve Rd Callala Beach NSW 2540",
    "addr:housenumber":"55",
    "addr:postcode":"2540",
    "addr:street":"Verve Rd",
    "iso:country":"AU",
    "sg:address":"55 Verve Rd",
    "sg:city":"Callala Beach",
    "sg:classifiers":[
        {
            "category":"Building & Trades",
            "subcategory":"Landscaping Services",
            "type":"Services"
        }
    ],
    "sg:phone":"+61 2 4446 6647",
    "sg:postcode":"2540",
    "sg:province":"NSW",
    "sg:tags":[
        "stump",
        "tree",
        "felling",
        "removal"
    ],
    "wof:name":"C. T. Tree Services",
    "wof:placetype":"venue"
},
  "geometry": {"coordinates":[150.70489501899999,-35.0060577393],"type":"Point"}
}