{
  "type": "Feature",
  "properties": {
    "iso:country":"AU",
    "sg:address":"Suite E, 304 King St",
    "sg:city":"Newtown",
    "sg:classifiers":[
        {
            "category":"Health Services",
            "subcategory":"Health Practitioner",
            "type":"Services"
        }
    ],
    "sg:phone":"+61 2 9591 2671",
    "sg:postcode":"2042",
    "sg:province":"NSW",
    "sg:tags":[
        "hypnotherapy"
    ],
    "wof:name":"Feenan Ross",
    "wof:placetype":"venue"
},
  "geometry": {"coordinates":[151.179657,-33.896854],"type":"Point"}
}