{
  "type": "Feature",
  "properties": {
    "addr:full":"Shop 1, 27 Sackville St Port Fairy VIC 3284",
    "addr:housenumber":"shop;27",
    "addr:postcode":"3284",
    "addr:street":"Sackville St",
    "iso:country":"AU",
    "sg:address":"Shop 1, 27 Sackville St",
    "sg:city":"Port Fairy",
    "sg:classifiers":[
        {
            "category":"Shopping",
            "subcategory":"Clothing, Apparel, & Fashions",
            "type":"Retail Goods"
        }
    ],
    "sg:phone":"+61 3 5568 2160",
    "sg:postcode":"3284",
    "sg:province":"VIC",
    "sg:tags":[
        "lady",
        "wear"
    ],
    "wof:name":"Mangowood",
    "wof:placetype":"venue"
},
  "geometry": {"coordinates":[142.2368927,-38.3854255676],"type":"Point"}
}