{
  "type": "Feature",
  "properties": {
    "iso:country":"AU",
    "sg:address":"18 Boston Ave",
    "sg:city":"Bundoora",
    "sg:classifiers":[
        {
            "category":"Retail",
            "subcategory":"Storage",
            "type":"Services"
        }
    ],
    "sg:phone":"+61 3 9440 2711",
    "sg:postcode":"3083",
    "sg:province":"VIC",
    "sg:tags":[
        "removal",
        "furniture"
    ],
    "wof:name":"Chapmans Furniture Removals",
    "wof:placetype":"venue"
},
  "geometry": {"coordinates":[145.07810974099999,-37.6962432861],"type":"Point"}
}