{
  "type": "Feature",
  "properties": {
    "addr:full":"Walkers Rd Loch VIC 3945",
    "addr:postcode":"3945",
    "addr:street":"Walkers Rd",
    "iso:country":"AU",
    "sg:address":"Walkers Rd",
    "sg:city":"Loch",
    "sg:classifiers":[
        {
            "category":"Farming",
            "subcategory":"Livestock Farm",
            "type":"Manufacturing & Wholesale Goods"
        }
    ],
    "sg:phone":"+61 3 5659 4307",
    "sg:postcode":"3945",
    "sg:province":"VIC",
    "sg:tags":[
        "breeder",
        "horse",
        "stud"
    ],
    "wof:name":"Provis J",
    "wof:placetype":"venue"
},
  "geometry": {"coordinates":[145.680145264,-38.3774185181],"type":"Point"}
}