{
  "type": "Feature",
  "properties": {
    "iso:country":"AU",
    "sg:address":"462- 472 West St",
    "sg:city":"Toowoomba",
    "sg:classifiers":[
        {
            "category":"Health Services",
            "subcategory":"Doctor",
            "type":"Services"
        }
    ],
    "sg:phone":"+61 7 4630 2155",
    "sg:postcode":"4350",
    "sg:province":"QLD",
    "sg:tags":[
        "medical",
        "practitioner"
    ],
    "wof:name":"Matthews Sharon Dr",
    "wof:placetype":"venue"
},
  "geometry": {"coordinates":[151.93519599999999,-27.607407],"type":"Point"}
}