{
  "type": "Feature",
  "properties": {
    "addr:full":"1 Emma Pl North Fremantle WA 6159",
    "addr:housenumber":"1",
    "addr:postcode":"6159",
    "addr:street":"Emma Pl",
    "iso:country":"AU",
    "sg:address":"1 Emma Pl",
    "sg:city":"North Fremantle",
    "sg:classifiers":[
        {
            "category":"Recreation",
            "subcategory":"Boat Charter",
            "type":"Entertainment"
        }
    ],
    "sg:phone":"+61 8 9430 5844",
    "sg:postcode":"6159",
    "sg:province":"WA",
    "wof:name":"Rottnest Express",
    "wof:placetype":"venue"
},
  "geometry": {"coordinates":[115.729889,-32.053246],"type":"Point"}
}