{
  "type": "Feature",
  "properties": {
    "addr:full":"53 Carrington St Darlington Point NSW 2706",
    "addr:housenumber":"53",
    "addr:postcode":"2706",
    "addr:street":"Carrington St",
    "iso:country":"AU",
    "sg:address":"53 Carrington St",
    "sg:city":"Darlington Point",
    "sg:classifiers":[
        {
            "category":"Cafe",
            "type":"Food & Drink"
        }
    ],
    "sg:phone":"+61 2 6968 4333",
    "sg:postcode":"2706",
    "sg:province":"NSW",
    "wof:name":"Gumview Cafe",
    "wof:placetype":"venue"
},
  "geometry": {"coordinates":[145.99528503400001,-34.574596405],"type":"Point"}
}