{
  "type": "Feature",
  "properties": {
    "addr:full":"Marina Mirage Shopng Cntr Seaworld Drv Main Beach QLD 4217",
    "addr:postcode":"4217",
    "addr:street":"Seaworld Drv",
    "iso:country":"AU",
    "sg:address":"Marina Mirage Shopng Cntr Seaworld Drv",
    "sg:city":"Main Beach",
    "sg:classifiers":[
        {
            "category":"Shopping",
            "subcategory":"Clothing, Apparel, & Fashions",
            "type":"Retail Goods"
        }
    ],
    "sg:phone":"+61 7 5591 2033",
    "sg:postcode":"4217",
    "sg:province":"QLD",
    "sg:tags":[
        "menswear"
    ],
    "wof:name":"Mandate",
    "wof:placetype":"venue"
},
  "geometry": {"coordinates":[153.424880981,-27.968580246],"type":"Point"}
}