{
  "type": "Feature",
  "properties": {
    "iso:country":"AU",
    "sg:address":"Shop 5",
    "sg:city":"b, Dimmey&#039;s Plz Flinders Mall Townsville",
    "sg:classifiers":[
        {
            "category":"Personal",
            "subcategory":"Beauty Salon",
            "type":"Services"
        }
    ],
    "sg:phone":"+61 7 4772 7913",
    "sg:postcode":"4810",
    "sg:province":"QLD",
    "sg:tags":[
        "hairdresser"
    ],
    "wof:name":"About Town Hairdressing",
    "wof:placetype":"venue"
},
  "geometry": {"coordinates":[146.75546299999999,-19.2351],"type":"Point"}
}