{
  "type": "Feature",
  "properties": {
    "addr:full":"PO Box 5015 Wonga Park VIC 3115",
    "addr:postcode":"3115",
    "iso:country":"AU",
    "sg:address":"PO Box 5015",
    "sg:city":"Wonga Park",
    "sg:classifiers":[
        {
            "category":"Utilities",
            "type":"Services"
        }
    ],
    "sg:phone":"+61 3 9722 2622",
    "sg:postcode":"3115",
    "sg:province":"VIC",
    "sg:tags":[
        "refrigeration",
        "industrial",
        "commercial",
        "retail"
    ],
    "wof:name":"Fuller Refrigeration",
    "wof:placetype":"venue"
},
  "geometry": {"coordinates":[145.27154540999999,-37.7358093262],"type":"Point"}
}