{
  "type": "Feature",
  "properties": {
    "addr:full":"9 Donovan St Osborne Park WA 6017",
    "addr:housenumber":"9",
    "addr:postcode":"6017",
    "addr:street":"Donovan St",
    "iso:country":"AU",
    "sg:address":"9 Donovan St",
    "sg:city":"Osborne Park",
    "sg:classifiers":[
        {
            "category":"Shopping",
            "subcategory":"Party Supplies",
            "type":"Retail Goods"
        }
    ],
    "sg:phone":"+61 1300 657 798",
    "sg:postcode":"6017",
    "sg:province":"WA",
    "sg:tags":[
        "children's"
    ],
    "wof:name":"The Gymbus",
    "wof:placetype":"venue"
},
  "geometry": {"coordinates":[115.826721191,-31.913734436],"type":"Point"}
}