{
  "type": "Feature",
  "properties": {
    "addr:full":"PO Box 425 Cootamundra NSW 2590",
    "addr:postcode":"2590",
    "iso:country":"AU",
    "sg:address":"PO Box 425",
    "sg:city":"Cootamundra",
    "sg:classifiers":[
        {
            "category":"Real Estate",
            "subcategory":"Architect",
            "type":"Services"
        }
    ],
    "sg:phone":"+61 2 6942 7125",
    "sg:postcode":"2590",
    "sg:province":"NSW",
    "wof:name":"Sing Wong Design",
    "wof:placetype":"venue"
},
  "geometry": {"coordinates":[148.02609252900001,-34.6400413513],"type":"Point"}
}