{
  "type": "Feature",
  "properties": {
    "iso:country":"AU",
    "sg:address":"5 Wilkinson St",
    "sg:city":"Toowoomba",
    "sg:classifiers":[
        {
            "category":"Wholesale",
            "subcategory":"Auto Parts",
            "type":"Manufacturing & Wholesale Goods"
        }
    ],
    "sg:phone":"+61 7 4613 1322",
    "sg:postcode":"4350",
    "sg:province":"QLD",
    "sg:tags":[
        "recyclers"
    ],
    "wof:name":"Japanese Auto Wreckers",
    "wof:placetype":"venue"
},
  "geometry": {"coordinates":[151.951202,-27.538963],"type":"Point"}
}