{
  "type": "Feature",
  "properties": {
    "addr:full":"39 Willcock St Ardross WA 6153",
    "addr:housenumber":"39",
    "addr:postcode":"6153",
    "addr:street":"Willcock St",
    "iso:country":"AU",
    "sg:address":"39 Willcock St",
    "sg:city":"Ardross",
    "sg:classifiers":[
        {
            "category":"Real Estate",
            "subcategory":"Architect",
            "type":"Services"
        }
    ],
    "sg:phone":"+61 8 9316 3025",
    "sg:postcode":"6153",
    "sg:province":"WA",
    "wof:name":"Faigen Phil",
    "wof:placetype":"venue"
},
  "geometry": {"coordinates":[115.836349,-32.021458],"type":"Point"}
}