{
  "type": "Feature",
  "properties": {
    "iso:country":"AU",
    "sg:address":"51 Andrew St",
    "sg:city":"Rocklea",
    "sg:classifiers":[
        {
            "category":"Retail",
            "subcategory":"Car Wash",
            "type":"Services"
        }
    ],
    "sg:phone":"+61 7 3277 2015",
    "sg:postcode":"4106",
    "sg:province":"QLD",
    "sg:tags":[
        "truck",
        "cleaning"
    ],
    "wof:name":"Forward Detailing",
    "wof:placetype":"venue"
},
  "geometry": {"coordinates":[153.007614136,-27.5478134155],"type":"Point"}
}