{
  "type": "Feature",
  "properties": {
    "addr:full":"5 44-48 Bowral St Bowral NSW 2576",
    "addr:housenumber":"5 44-48",
    "addr:postcode":"2576",
    "addr:street":"Bowral St",
    "iso:country":"AU",
    "sg:address":"5 44-48 Bowral St",
    "sg:city":"Bowral",
    "sg:classifiers":[
        {
            "category":"Health Services",
            "subcategory":"Chiropractor",
            "type":"Services"
        }
    ],
    "sg:phone":"+61 2 4862 5363",
    "sg:postcode":"2576",
    "sg:province":"NSW",
    "wof:name":"The Well Adjusted Practice",
    "wof:placetype":"venue"
},
  "geometry": {"coordinates":[150.415405273,-34.4827537537],"type":"Point"}
}