{
  "type": "Feature",
  "properties": {
    "addr:full":"Shp 4/ 103 Victoria St Gosford East NSW 2250",
    "addr:housenumber":"/ 103",
    "addr:postcode":"2250",
    "addr:street":"Victoria St",
    "iso:country":"AU",
    "sg:address":"Shp 4/ 103 Victoria St",
    "sg:city":"Gosford East",
    "sg:classifiers":[
        {
            "category":"Food & Beverages",
            "subcategory":"Fruits & Vegetables",
            "type":"Retail Goods"
        }
    ],
    "sg:phone":"+61 2 4324 8708",
    "sg:postcode":"2250",
    "sg:province":"NSW",
    "sg:tags":[
        "consultant",
        "catering"
    ],
    "wof:name":"Caffe Jam",
    "wof:placetype":"venue"
},
  "geometry": {"coordinates":[151.35319519000001,-33.437046051],"type":"Point"}
}