{
  "type": "Feature",
  "properties": {
    "addr:full":"70 Pacific Hwy Ourimbah NSW 2258",
    "addr:housenumber":"70",
    "addr:postcode":"2258",
    "addr:street":"Pacific Hwy",
    "iso:country":"AU",
    "sg:address":"70 Pacific Hwy",
    "sg:city":"Ourimbah",
    "sg:classifiers":[
        {
            "category":"Professional",
            "type":"Services"
        }
    ],
    "sg:phone":"+61 1300 306 830",
    "sg:postcode":"2258",
    "sg:province":"NSW",
    "sg:tags":[
        "control",
        "equipment",
        "traffic"
    ],
    "wof:name":"Workforce International",
    "wof:placetype":"venue"
},
  "geometry": {"coordinates":[151.37034606899999,-33.3479499817],"type":"Point"}
}