{
  "type": "Feature",
  "properties": {
    "addr:full":"330 High St Maitland NSW 2320",
    "addr:housenumber":"330",
    "addr:postcode":"2320",
    "addr:street":"High St",
    "iso:country":"AU",
    "sg:address":"330 High St",
    "sg:city":"Maitland",
    "sg:classifiers":[
        {
            "category":"Professional",
            "subcategory":"Printing & Photocopies",
            "type":"Services"
        }
    ],
    "sg:phone":"+61 2 4933 2444",
    "sg:postcode":"2320",
    "sg:province":"NSW",
    "sg:tags":[
        "laminating"
    ],
    "wof:name":"Maitland Laminating Services",
    "wof:placetype":"venue"
},
  "geometry": {"coordinates":[151.553466797,-32.731136322],"type":"Point"}
}