{
  "type": "Feature",
  "properties": {
    "addr:full":"22 Ocean St Victor Harbor SA 5211",
    "addr:housenumber":"22",
    "addr:postcode":"5211",
    "addr:street":"Ocean St",
    "iso:country":"AU",
    "sg:address":"22 Ocean St",
    "sg:city":"Victor Harbor",
    "sg:classifiers":[
        {
            "category":"Professional",
            "subcategory":"Printing & Photocopies",
            "type":"Services"
        }
    ],
    "sg:phone":"+61 8 8552 1766",
    "sg:postcode":"5211",
    "sg:province":"SA",
    "sg:tags":[
        "trophy"
    ],
    "wof:name":"Tonkin's Sportscene",
    "wof:placetype":"venue"
},
  "geometry": {"coordinates":[138.623336792,-35.5548744202],"type":"Point"}
}