{
  "type": "Feature",
  "properties": {
    "iso:country":"AU",
    "sg:address":"U2/ 19 Westside Drv",
    "sg:city":"Laverton North",
    "sg:classifiers":[
        {
            "category":"Shopping",
            "subcategory":"Stationery & Office Supplies",
            "type":"Retail Goods"
        }
    ],
    "sg:phone":"+61 3 9315 1399",
    "sg:postcode":"3026",
    "sg:province":"VIC",
    "sg:tags":[
        "packaging",
        "material"
    ],
    "wof:name":"Aline Packaging",
    "wof:placetype":"venue"
},
  "geometry": {"coordinates":[144.82286099999999,-37.818748],"type":"Point"}
}