{
  "type": "Feature",
  "properties": {
    "iso:country":"AU",
    "sg:address":"5A The Plaza, Spencer St",
    "sg:city":"Bunbury",
    "sg:classifiers":[
        {
            "category":"Real Estate",
            "subcategory":"Real Estate Agent",
            "type":"Services"
        }
    ],
    "sg:phone":"+61 8 9780 9111",
    "sg:postcode":"6230",
    "sg:province":"WA",
    "wof:name":"Remax Harbour City",
    "wof:placetype":"venue"
},
  "geometry": {"coordinates":[115.64167,-33.352669],"type":"Point"}
}