{
  "type": "Feature",
  "properties": {
    "addr:full":"323 Princes Hwy Bulli NSW 2516",
    "addr:housenumber":"323",
    "addr:postcode":"2516",
    "addr:street":"Princes Hwy",
    "iso:country":"AU",
    "sg:address":"323 Princes Hwy",
    "sg:city":"Bulli",
    "sg:classifiers":[
        {
            "category":"Fast Food",
            "type":"Food & Drink"
        }
    ],
    "sg:phone":"+61 2 4284 1061",
    "sg:postcode":"2516",
    "sg:province":"NSW",
    "sg:tags":[
        "away",
        "take"
    ],
    "wof:name":"Illawarra Fisheries",
    "wof:placetype":"venue"
},
  "geometry": {"coordinates":[150.90954600000001,-34.338455],"type":"Point"}
}