{
  "type": "Feature",
  "properties": {
    "iso:country":"AU",
    "sg:address":"Olive St",
    "sg:city":"Baulkham Hills",
    "sg:classifiers":[
        {
            "category":"Banks & Credit Unions",
            "subcategory":"Financial Services",
            "type":"Services"
        }
    ],
    "sg:phone":"+61 2 8852 8100",
    "sg:postcode":"2153",
    "sg:province":"NSW",
    "sg:tags":[
        "loan",
        "finance",
        "mortgage"
    ],
    "wof:name":"Aussie",
    "wof:placetype":"venue"
},
  "geometry": {"coordinates":[150.99293518100001,-33.759601593],"type":"Point"}
}