{
  "type": "Feature",
  "properties": {
    "iso:country":"AU",
    "sg:address":"Pacific Hwy",
    "sg:city":"Belmont",
    "sg:classifiers":[
        {
            "category":"Mining & Drilling",
            "type":"Manufacturing & Wholesale Goods"
        }
    ],
    "sg:phone":"+61 2 4947 7288",
    "sg:postcode":"2280",
    "sg:province":"NSW",
    "sg:tags":[
        "equipment",
        "quarrying",
        "supply"
    ],
    "wof:name":"Firefly International",
    "wof:placetype":"venue"
},
  "geometry": {"coordinates":[151.66015625,-33.0366210938],"type":"Point"}
}