{
  "type": "Feature",
  "properties": {
    "iso:country":"AU",
    "sg:address":"Unit 2/ 1 Christian Crt",
    "sg:city":"Bayswater",
    "sg:classifiers":[
        {
            "category":"Communications",
            "subcategory":"News Services",
            "type":"Services"
        }
    ],
    "sg:phone":"+61 8 9371 3695",
    "sg:postcode":"6053",
    "sg:province":"WA",
    "sg:tags":[
        "information",
        "tourist",
        "attractions"
    ],
    "wof:name":"Westernxposure",
    "wof:placetype":"venue"
},
  "geometry": {"coordinates":[115.91620636,-31.9094352722],"type":"Point"}
}