{
  "type": "Feature",
  "properties": {
    "addr:full":"Shop 4 662 Old Calder Hwy Keilor VIC 3036",
    "addr:housenumber":"shop 4 662",
    "addr:postcode":"3036",
    "addr:street":"Old Calder Hwy",
    "iso:country":"AU",
    "sg:address":"Shop 4 662 Old Calder Hwy",
    "sg:city":"Keilor",
    "sg:classifiers":[
        {
            "category":"Personal",
            "subcategory":"Beauty Salon",
            "type":"Services"
        }
    ],
    "sg:phone":"+61 3 9331 5118",
    "sg:postcode":"3036",
    "sg:province":"VIC",
    "sg:tags":[
        "hairdresser"
    ],
    "wof:name":"Madusa Hair Studio",
    "wof:placetype":"venue"
},
  "geometry": {"coordinates":[144.83770799999999,-37.720779],"type":"Point"}
}