{
  "type": "Feature",
  "properties": {
    "iso:country":"AU",
    "sg:address":"67 Wellington St",
    "sg:city":"Riverstone",
    "sg:classifiers":[
        {
            "category":"Manufacturing",
            "subcategory":"Metals",
            "type":"Manufacturing & Wholesale Goods"
        }
    ],
    "sg:phone":"+61 2 9627 6237",
    "sg:postcode":"2765",
    "sg:province":"NSW",
    "sg:tags":[
        "steel",
        "fabricator",
        "mfrs"
    ],
    "wof:name":"Fabinox",
    "wof:placetype":"venue"
},
  "geometry": {"coordinates":[150.86325073200001,-33.6651344299],"type":"Point"}
}