{
  "type": "Feature",
  "properties": {
    "iso:country":"AU",
    "sg:address":"Royal Oak Plaza 269 Charters Towers Rd",
    "sg:city":"Mysterton",
    "sg:classifiers":[
        {
            "category":"Fast Food",
            "type":"Food & Drink"
        }
    ],
    "sg:phone":"+61 7 4728 6666",
    "sg:postcode":"4812",
    "sg:province":"QLD",
    "sg:tags":[
        "away",
        "take"
    ],
    "wof:name":"La Porchetta",
    "wof:placetype":"venue"
},
  "geometry": {"coordinates":[146.79629499999999,-19.289335],"type":"Point"}
}