{
  "type": "Feature",
  "properties": {
    "addr:full":"Shop 9 Elizabeth Arcade High St Penrith NSW 2751",
    "addr:housenumber":"shop 9",
    "addr:postcode":"2751",
    "addr:street":"Elizabeth;High St",
    "iso:country":"AU",
    "sg:address":"Shop 9 Elizabeth Arcade High St",
    "sg:city":"Penrith",
    "sg:classifiers":[
        {
            "category":"Personal",
            "subcategory":"Beauty Salon",
            "type":"Services"
        }
    ],
    "sg:phone":"+61 2 4722 5622",
    "sg:postcode":"2751",
    "sg:province":"NSW",
    "wof:name":"Branches Of Beauty",
    "wof:placetype":"venue"
},
  "geometry": {"coordinates":[150.69601440400001,-33.7440681458],"type":"Point"}
}