{
  "type": "Feature",
  "properties": {
    "iso:country":"AU",
    "sg:address":"Lot 37 Bailey St",
    "sg:city":"Dongara",
    "sg:classifiers":[
        {
            "category":"Building & Trades",
            "subcategory":"Construction",
            "type":"Services"
        }
    ],
    "sg:phone":"+61 428 388 858",
    "sg:postcode":"6525",
    "sg:province":"WA",
    "sg:tags":[
        "concrete",
        "contractor"
    ],
    "wof:name":"Central West Concrete",
    "wof:placetype":"venue"
},
  "geometry": {"coordinates":[114.94605255099999,-29.2504291534],"type":"Point"}
}