{
  "type": "Feature",
  "properties": {
    "addr:full":"CNR Gladstone Rd & Derby St, Rockhampton QLD 4700",
    "addr:postcode":"4700",
    "addr:street":"Cnr Gladstone Rd & Derby St",
    "iso:country":"AU",
    "sg:address":"CNR Gladstone Rd",
    "sg:city":"& Derby St, Rockhampton",
    "sg:classifiers":[
        {
            "category":"Home & Garden",
            "subcategory":"Garden Supply",
            "type":"Retail Goods"
        }
    ],
    "sg:phone":"+61 7 4939 2990",
    "sg:postcode":"4700",
    "sg:province":"QLD",
    "sg:tags":[
        "landscape"
    ],
    "wof:name":"Prestige Garden & Gift",
    "wof:placetype":"venue"
},
  "geometry": {"coordinates":[150.50579834000001,-23.3990077972],"type":"Point"}
}