{
  "type": "Feature",
  "properties": {
    "addr:full":"420 Springwood Rd Springwood QLD 4127",
    "addr:housenumber":"420",
    "addr:postcode":"4127",
    "addr:street":"Springwood Rd",
    "iso:country":"AU",
    "sg:address":"420 Springwood Rd",
    "sg:city":"Springwood",
    "sg:classifiers":[
        {
            "category":"Building & Trades",
            "subcategory":"Construction",
            "type":"Services"
        }
    ],
    "sg:phone":"+61 7 3299 3228",
    "sg:postcode":"4127",
    "sg:province":"QLD",
    "sg:tags":[
        "tennis court",
        "repair"
    ],
    "wof:name":"Cambridge Tennis Gameplan",
    "wof:placetype":"venue"
},
  "geometry": {"coordinates":[153.149368286,-27.6277694702],"type":"Point"}
}