{
  "type": "Feature",
  "properties": {
    "iso:country":"AU",
    "sg:address":"2/ 432 Punt Rd",
    "sg:city":"South Yarra",
    "sg:classifiers":[
        {
            "category":"Shopping",
            "subcategory":"Computers & Home Electronics",
            "type":"Retail Goods"
        }
    ],
    "sg:phone":"+61 1300 766 625",
    "sg:postcode":"3141",
    "sg:province":"VIC",
    "sg:tags":[
        "equipment",
        "multimedia"
    ],
    "wof:name":"WWWDesign",
    "wof:placetype":"venue"
},
  "geometry": {"coordinates":[144.98680114699999,-37.8377418518],"type":"Point"}
}