{
  "type": "Feature",
  "properties": {
    "addr:full":"2349 Point Nepean Rd Rye VIC 3941",
    "addr:housenumber":"2349",
    "addr:postcode":"3941",
    "addr:street":"Point Nepean Rd",
    "iso:country":"AU",
    "sg:address":"2349 Point Nepean Rd",
    "sg:city":"Rye",
    "sg:classifiers":[
        {
            "category":"Banks & Credit Unions",
            "subcategory":"Bank",
            "type":"Services"
        }
    ],
    "sg:phone":"+61 3 5985 9755",
    "sg:postcode":"3941",
    "sg:province":"VIC",
    "wof:name":"Bendigo Community Bank",
    "wof:placetype":"venue"
},
  "geometry": {"coordinates":[144.823974609,-38.3706283569],"type":"Point"}
}