{
  "type": "Feature",
  "properties": {
    "addr:full":"34 Second St Millicent SA 5280",
    "addr:housenumber":"34",
    "addr:postcode":"5280",
    "addr:street":"Second St",
    "iso:country":"AU",
    "sg:address":"34 Second St",
    "sg:city":"Millicent",
    "sg:classifiers":[
        {
            "category":"Professional",
            "subcategory":"Art Services",
            "type":"Services"
        }
    ],
    "sg:phone":"+61 8 8733 4153",
    "sg:postcode":"5280",
    "sg:province":"SA",
    "sg:tags":[
        "decorator",
        "painter"
    ],
    "wof:name":"John Giurastante Master Painter & Decorator",
    "wof:placetype":"venue"
},
  "geometry": {"coordinates":[140.33970600000001,-37.592155],"type":"Point"}
}