{
  "type": "Feature",
  "properties": {
    "addr:full":"Shop 23/202- 205 Railway Pde Cabramatta NSW 2166",
    "addr:housenumber":"shop 23 / 202 205",
    "addr:postcode":"2166",
    "addr:street":"Railway Pde",
    "iso:country":"AU",
    "sg:address":"Shop 23/202- 205 Railway Pde",
    "sg:city":"Cabramatta",
    "sg:classifiers":[
        {
            "category":"Shopping",
            "subcategory":"Optical Goods",
            "type":"Retail Goods"
        }
    ],
    "sg:phone":"+61 2 9724 9796",
    "sg:postcode":"2166",
    "sg:province":"NSW",
    "sg:tags":[
        "dispenser",
        "prescription"
    ],
    "wof:name":"L&#039;Optical Pty Ltd",
    "wof:placetype":"venue"
},
  "geometry": {"coordinates":[150.938323975,-33.8951644897],"type":"Point"}
}