{
  "type": "Feature",
  "properties": {
    "iso:country":"AU",
    "sg:address":"743 Victoria Rd",
    "sg:city":"Ryde",
    "sg:classifiers":[
        {
            "category":"Shopping",
            "subcategory":"Discount & Variety Stores",
            "type":"Retail Goods"
        }
    ],
    "sg:phone":"+61 2 9809 6888",
    "sg:postcode":"2112",
    "sg:province":"NSW",
    "sg:tags":[
        "register",
        "cash"
    ],
    "wof:name":"City Cash Register & Scale Co.",
    "wof:placetype":"venue"
},
  "geometry": {"coordinates":[151.10354614299999,-33.8157234192],"type":"Point"}
}