{
  "type": "Feature",
  "properties": {
    "addr:full":"19 Cameron St Alice Springs NT 0870",
    "addr:housenumber":"19",
    "addr:postcode":"nt 0870",
    "addr:street":"Cameron St",
    "iso:country":"AU",
    "sg:address":"19 Cameron St",
    "sg:city":"Alice Springs",
    "sg:classifiers":[
        {
            "category":"Real Estate",
            "subcategory":"Real Estate Agent",
            "type":"Services"
        }
    ],
    "sg:phone":"+61 8 8953 1784",
    "sg:postcode":"0870",
    "sg:province":"NT",
    "sg:tags":[
        "handyman's",
        "equipment",
        "hire",
        "builders",
        "contractor"
    ],
    "wof:name":"Alice Backhoe & Bobcat Hire",
    "wof:placetype":"venue"
},
  "geometry": {"coordinates":[133.867843628,-23.6726322174],"type":"Point"}
}