{
  "type": "Feature",
  "properties": {
    "addr:full":"31c Hutchinson St Mt Barker SA 5251",
    "addr:housenumber":"31c",
    "addr:postcode":"5251",
    "addr:street":"Hutchinson St Mt",
    "iso:country":"AU",
    "sg:address":"31c Hutchinson St",
    "sg:city":"Mt Barker",
    "sg:classifiers":[
        {
            "category":"Travel",
            "subcategory":"Travel Agent",
            "type":"Entertainment"
        }
    ],
    "sg:phone":"+61 8 8391 5277",
    "sg:postcode":"5251",
    "sg:province":"SA",
    "sg:tags":[
        "consultant"
    ],
    "wof:name":"Travelscene Mount Barker",
    "wof:placetype":"venue"
},
  "geometry": {"coordinates":[138.86007690400001,-35.0663604736],"type":"Point"}
}