{
  "type": "Feature",
  "properties": {
    "addr:full":"36 Kinkora Pl Queanbeyan ACT 2620",
    "addr:housenumber":"36",
    "addr:postcode":"2620",
    "addr:street":"Pl",
    "iso:country":"AU",
    "sg:address":"36 Kinkora Pl",
    "sg:city":"Queanbeyan",
    "sg:classifiers":[
        {
            "category":"Building & Trades",
            "subcategory":"Plumbing",
            "type":"Services"
        }
    ],
    "sg:phone":"+61 418 632 395",
    "sg:postcode":"2620",
    "sg:province":"ACT",
    "sg:tags":[
        "plumber",
        "gasfitters"
    ],
    "wof:name":"Bob Bradley",
    "wof:placetype":"venue"
},
  "geometry": {"coordinates":[149.22105407699999,-35.3472900391],"type":"Point"}
}