{
  "type": "Feature",
  "properties": {
    "iso:country":"AU",
    "sg:address":"1927a Malvern Rd",
    "sg:city":"Malvern East",
    "sg:classifiers":[
        {
            "category":"Education",
            "subcategory":"Dance Studio",
            "type":"Public Place"
        }
    ],
    "sg:phone":"+61 3 9885 6370",
    "sg:postcode":"3145",
    "sg:province":"VIC",
    "sg:tags":[
        "venue",
        "tuition"
    ],
    "wof:name":"Granada Dance Centre",
    "wof:placetype":"venue"
},
  "geometry": {"coordinates":[145.060791016,-37.8692245483],"type":"Point"}
}