{
  "type": "Feature",
  "properties": {
    "addr:full":"Suite 204/ 9 Bay St Southport QLD 4215",
    "addr:housenumber":"/ 9",
    "addr:postcode":"4215",
    "addr:street":"Bay St",
    "iso:country":"AU",
    "sg:address":"Suite 204/ 9 Bay St",
    "sg:city":"Southport",
    "sg:classifiers":[
        {
            "category":"Health Services",
            "subcategory":"Health Practitioner",
            "type":"Services"
        }
    ],
    "sg:phone":"+61 7 5531 2358",
    "sg:postcode":"4215",
    "sg:province":"QLD",
    "sg:tags":[
        "acupuncture"
    ],
    "wof:name":"Paul McLeod",
    "wof:placetype":"venue"
},
  "geometry": {"coordinates":[153.41177368199999,-27.9669246674],"type":"Point"}
}