{
  "type": "Feature",
  "properties": {
    "addr:full":"147 Agincourt Rd Marsfield NSW 2122",
    "addr:housenumber":"147",
    "addr:postcode":"2122",
    "addr:street":"Agincourt Rd",
    "iso:country":"AU",
    "sg:address":"147 Agincourt Rd",
    "sg:city":"Marsfield",
    "sg:classifiers":[
        {
            "category":"Professional",
            "subcategory":"Detective & Security Services",
            "type":"Services"
        }
    ],
    "sg:phone":"+61 2 9888 3111",
    "sg:postcode":"2122",
    "sg:province":"NSW",
    "sg:tags":[
        "equipment",
        "window",
        "doors"
    ],
    "wof:name":"Trellis Barrier Security Systems",
    "wof:placetype":"venue"
},
  "geometry": {"coordinates":[151.107147217,-33.7870979309],"type":"Point"}
}