{
  "type": "Feature",
  "properties": {
    "addr:full":"2 Bowi St Cooma NSW 2630",
    "addr:housenumber":"2",
    "addr:postcode":"2630",
    "addr:street":"Bowi St",
    "iso:country":"AU",
    "sg:address":"2 Bowi St",
    "sg:city":"Cooma",
    "sg:classifiers":[
        {
            "category":"Social Services",
            "subcategory":"Adult Care",
            "type":"Services"
        }
    ],
    "sg:phone":"+61 428 331 731",
    "sg:postcode":"2630",
    "sg:province":"NSW",
    "sg:tags":[
        "towing"
    ],
    "wof:name":"Extreme Towing",
    "wof:placetype":"venue"
},
  "geometry": {"coordinates":[149.12986755399999,-36.2223930359],"type":"Point"}
}