{
  "type": "Feature",
  "properties": {
    "iso:country":"AU",
    "sg:address":"2 Bulga Pl",
    "sg:city":"Ocean Grove",
    "sg:classifiers":[
        {
            "category":"Shopping",
            "subcategory":"Computers & Home Electronics",
            "type":"Retail Goods"
        }
    ],
    "sg:phone":"+61 421 592 876",
    "sg:postcode":"3226",
    "sg:province":"VIC",
    "sg:tags":[
        "hardware",
        "equipment"
    ],
    "wof:name":"TLB Computer Systems",
    "wof:placetype":"venue"
},
  "geometry": {"coordinates":[144.554047,-38.256088],"type":"Point"}
}