{
  "type": "Feature",
  "properties": {
    "addr:full":"81 Old South Head Rd Bondi Junction NSW 2022",
    "addr:housenumber":"81",
    "addr:postcode":"2022",
    "addr:street":"Old South Head Rd",
    "iso:country":"AU",
    "sg:address":"81 Old South Head Rd",
    "sg:city":"Bondi Junction",
    "sg:classifiers":[
        {
            "category":"Health Services",
            "subcategory":"Health Practitioner",
            "type":"Services"
        }
    ],
    "sg:phone":"+61 2 9389 0897",
    "sg:postcode":"2022",
    "sg:province":"NSW",
    "sg:tags":[
        "hypnotherapy"
    ],
    "wof:name":"Stengelis Ingrid",
    "wof:placetype":"venue"
},
  "geometry": {"coordinates":[151.25425720199999,-33.8906974792],"type":"Point"}
}