{
  "type": "Feature",
  "properties": {
    "addr:full":"PO Box 322 Rockingham WA 6168",
    "addr:postcode":"6168",
    "iso:country":"AU",
    "sg:address":"PO Box 322",
    "sg:city":"Rockingham",
    "sg:classifiers":[
        {
            "category":"Building & Trades",
            "subcategory":"Cleaning & Sanitation",
            "type":"Services"
        }
    ],
    "sg:phone":"+61 8 9593 8230",
    "sg:postcode":"6168",
    "sg:province":"WA",
    "sg:tags":[
        "chemical",
        "pressure",
        "steam",
        "contractor"
    ],
    "wof:name":"Aquasolve High Pressure Cleaning",
    "wof:placetype":"venue"
},
  "geometry": {"coordinates":[115.741027832,-32.2803993225],"type":"Point"}
}