{
  "type": "Feature",
  "properties": {
    "addr:full":"2 Treen St Balga WA 6061",
    "addr:housenumber":"2",
    "addr:postcode":"6061",
    "addr:street":"Treen St",
    "iso:country":"AU",
    "sg:address":"2 Treen St",
    "sg:city":"Balga",
    "sg:classifiers":[
        {
            "category":"Health Services",
            "subcategory":"Chiropractor",
            "type":"Services"
        }
    ],
    "sg:phone":"+61 8 9342 4927",
    "sg:postcode":"6061",
    "sg:province":"WA",
    "wof:name":"De Coster L.D.",
    "wof:placetype":"venue"
},
  "geometry": {"coordinates":[115.824287415,-31.8461818695],"type":"Point"}
}