{
  "type": "Feature",
  "properties": {
    "addr:full":"Gateway Shopping Centre 27 Cole St Sorell TAS 7172",
    "addr:housenumber":"27",
    "addr:postcode":"7172",
    "addr:street":"Cole St",
    "iso:country":"AU",
    "sg:address":"Gateway Shopping Centre 27 Cole St",
    "sg:city":"Sorell",
    "sg:classifiers":[
        {
            "category":"Travel",
            "subcategory":"Travel Agent",
            "type":"Entertainment"
        }
    ],
    "sg:phone":"+61 3 6265 3377",
    "sg:postcode":"7172",
    "sg:province":"TAS",
    "sg:tags":[
        "consultant"
    ],
    "wof:name":"Australian Discount Travel & Tours",
    "wof:placetype":"venue"
},
  "geometry": {"coordinates":[147.56349182100001,-42.7814216614],"type":"Point"}
}