{
  "type": "Feature",
  "properties": {
    "addr:full":"Casula Rd Casula NSW 2170",
    "addr:postcode":"2170",
    "addr:street":"Casula Rd",
    "iso:country":"AU",
    "sg:address":"Casula Rd",
    "sg:city":"Casula",
    "sg:classifiers":[
        {
            "category":"Professional",
            "type":"Services"
        }
    ],
    "sg:phone":"+61 2 9602 0535",
    "sg:postcode":"2170",
    "sg:province":"NSW",
    "sg:tags":[
        "courier"
    ],
    "wof:name":"Prescription Courier Service",
    "wof:placetype":"venue"
},
  "geometry": {"coordinates":[150.90768432600001,-33.9497756958],"type":"Point"}
}