{
  "type": "Feature",
  "properties": {
    "iso:country":"AU",
    "sg:address":"205 Orchard Rd",
    "sg:city":"Crows Nest",
    "sg:classifiers":[
        {
            "category":"Home & Garden",
            "subcategory":"Garden Supply",
            "type":"Retail Goods"
        }
    ],
    "sg:phone":"+61 428 265 097",
    "sg:postcode":"4355",
    "sg:province":"QLD",
    "sg:tags":[
        "landscape"
    ],
    "wof:name":"Range Rock Supplies",
    "wof:placetype":"venue"
},
  "geometry": {"coordinates":[152.07058699999999,-27.276226],"type":"Point"}
}