{
  "type": "Feature",
  "properties": {
    "iso:country":"AU",
    "sg:address":"36 Mary St",
    "sg:city":"Gympie",
    "sg:classifiers":[
        {
            "category":"Shopping",
            "subcategory":"Clothing, Apparel, & Fashions",
            "type":"Retail Goods"
        }
    ],
    "sg:phone":"+61 7 5482 7961",
    "sg:postcode":"4570",
    "sg:province":"QLD",
    "sg:tags":[
        "lady",
        "wear"
    ],
    "wof:name":"On Location Boutique",
    "wof:placetype":"venue"
},
  "geometry": {"coordinates":[152.664428711,-26.1902332306],"type":"Point"}
}