{
  "type": "Feature",
  "properties": {
    "iso:country":"AU",
    "sg:address":"20 Railway Ave",
    "sg:city":"Garfield",
    "sg:classifiers":[
        {
            "category":"Utilities",
            "type":"Services"
        }
    ],
    "sg:phone":"+61 3 5629 1166",
    "sg:postcode":"3814",
    "sg:province":"VIC",
    "sg:tags":[
        "refrigeration",
        "industrial",
        "commercial",
        "retail"
    ],
    "wof:name":"B & E Fox Refrigeration Pty Ltd",
    "wof:placetype":"venue"
},
  "geometry": {"coordinates":[145.68190000000001,-38.092636],"type":"Point"}
}