{
  "type": "Feature",
  "properties": {
    "iso:country":"AU",
    "sg:address":"303 Macquarie St",
    "sg:city":"Hobart",
    "sg:classifiers":[
        {
            "category":"Health Services",
            "subcategory":"Doctor",
            "type":"Services"
        }
    ],
    "sg:phone":"+61 3 6223 1610",
    "sg:postcode":"7000",
    "sg:province":"TAS",
    "sg:tags":[
        "medical",
        "practitioner"
    ],
    "wof:name":"Wallace Jeremy",
    "wof:placetype":"venue"
},
  "geometry": {"coordinates":[147.320037842,-42.8904190063],"type":"Point"}
}