{
  "type": "Feature",
  "properties": {
    "addr:full":"7 Davies St Vaucluse NSW 2030",
    "addr:housenumber":"7",
    "addr:postcode":"2030",
    "addr:street":"Davies St",
    "iso:country":"AU",
    "sg:address":"7 Davies St",
    "sg:city":"Vaucluse",
    "sg:classifiers":[
        {
            "category":"Personal",
            "subcategory":"Beauty Salon",
            "type":"Services"
        }
    ],
    "sg:phone":"+61 2 9337 5490",
    "sg:postcode":"2030",
    "sg:province":"NSW",
    "sg:tags":[
        "hairdresser"
    ],
    "wof:name":"Nirvana Hairdressing",
    "wof:placetype":"venue"
},
  "geometry": {"coordinates":[151.28294372600001,-33.8501358032],"type":"Point"}
}