{
  "type": "Feature",
  "properties": {
    "addr:full":"67 Rooks Rd Mitcham VIC 3132",
    "addr:housenumber":"67",
    "addr:postcode":"3132",
    "addr:street":"Rooks Rd",
    "iso:country":"AU",
    "sg:address":"67 Rooks Rd",
    "sg:city":"Mitcham",
    "sg:classifiers":[
        {
            "category":"Arts & Performance",
            "subcategory":"Dance",
            "type":"Entertainment"
        }
    ],
    "sg:phone":"+61 3 9870 1254",
    "sg:postcode":"3132",
    "sg:province":"VIC",
    "sg:tags":[
        "theatrical",
        "ballet",
        "tuition"
    ],
    "wof:name":"Donna Morgan's Eastern Dance Centre",
    "wof:placetype":"venue"
},
  "geometry": {"coordinates":[145.18568420400001,-37.8244018555],"type":"Point"}
}