{
  "type": "Feature",
  "properties": {
    "iso:country":"AU",
    "sg:address":"10 Williams Rd",
    "sg:city":"Kelmscott",
    "sg:classifiers":[
        {
            "category":"Retail",
            "subcategory":"Repair Shop",
            "type":"Services"
        }
    ],
    "sg:phone":"+61 8 9399 4398",
    "sg:postcode":"6111",
    "sg:province":"WA",
    "sg:tags":[
        "machine",
        "repairs",
        "part",
        "dryer",
        "washing"
    ],
    "wof:name":"Bentley Home Service",
    "wof:placetype":"venue"
},
  "geometry": {"coordinates":[116.007972717,-32.1314315796],"type":"Point"}
}