{
  "type": "Feature",
  "properties": {
    "iso:country":"AU",
    "sg:address":"16/ 2 Mead Drv",
    "sg:city":"Chipping Norton",
    "sg:classifiers":[
        {
            "category":"Real Estate",
            "subcategory":"Surveying",
            "type":"Services"
        }
    ],
    "sg:phone":"+61 2 9723 0181",
    "sg:postcode":"2170",
    "sg:province":"NSW",
    "sg:tags":[
        "acoustic",
        "material"
    ],
    "wof:name":"Active Insulation",
    "wof:placetype":"venue"
},
  "geometry": {"coordinates":[150.96499633799999,-33.9119606018],"type":"Point"}
}