{
  "type": "Feature",
  "properties": {
    "addr:full":"43 Ely St Revesby NSW 2212",
    "addr:housenumber":"43",
    "addr:postcode":"2212",
    "addr:street":"Ely St",
    "iso:country":"AU",
    "sg:address":"43 Ely St",
    "sg:city":"Revesby",
    "sg:classifiers":[
        {
            "category":"Professional",
            "subcategory":"Art Services",
            "type":"Services"
        }
    ],
    "sg:phone":"+61 2 9792 7140",
    "sg:postcode":"2212",
    "sg:province":"NSW",
    "sg:tags":[
        "product",
        "industrial",
        "designer"
    ],
    "wof:name":"Somitec",
    "wof:placetype":"venue"
},
  "geometry": {"coordinates":[151.012497,-33.940971],"type":"Point"}
}