{
  "type": "Feature",
  "properties": {
    "addr:full":"45 Hillcrest Ave Mona Vale NSW 2103",
    "addr:housenumber":"45",
    "addr:postcode":"2103",
    "addr:street":"Hillcrest Ave",
    "iso:country":"AU",
    "sg:address":"45 Hillcrest Ave",
    "sg:city":"Mona Vale",
    "sg:classifiers":[
        {
            "category":"Shopping",
            "subcategory":"Clothing, Apparel, & Fashions",
            "type":"Retail Goods"
        }
    ],
    "sg:phone":"+61 2 9999 2900",
    "sg:postcode":"2103",
    "sg:province":"NSW",
    "sg:tags":[
        "millinery"
    ],
    "wof:name":"Sharyne Mullens",
    "wof:placetype":"venue"
},
  "geometry": {"coordinates":[151.3177948,-33.6728515625],"type":"Point"}
}