{
  "type": "Feature",
  "properties": {
    "iso:country":"AU",
    "sg:address":"2 Sheahan St",
    "sg:city":"Cootamundra",
    "sg:classifiers":[
        {
            "category":"Building & Trades",
            "subcategory":"Construction",
            "type":"Services"
        }
    ],
    "sg:phone":"+61 2 6942 2459",
    "sg:postcode":"2590",
    "sg:province":"NSW",
    "sg:tags":[
        "joiner",
        "carpenter"
    ],
    "wof:name":"Fallon Carpentry Service",
    "wof:placetype":"venue"
},
  "geometry": {"coordinates":[148.02609252900001,-34.6400413513],"type":"Point"}
}