{
  "type": "Feature",
  "properties": {
    "addr:full":"61 Sorlie Rd Frenchs Forest NSW 2086",
    "addr:housenumber":"61",
    "addr:postcode":"2086",
    "addr:street":"Sorlie Rd",
    "iso:country":"AU",
    "sg:address":"61 Sorlie Rd",
    "sg:city":"Frenchs Forest",
    "sg:classifiers":[
        {
            "category":"Restaurant",
            "type":"Food & Drink"
        }
    ],
    "sg:phone":"+61 2 9452 3350",
    "sg:postcode":"2086",
    "sg:province":"NSW",
    "wof:name":"Dash of Chilli",
    "wof:placetype":"venue"
},
  "geometry": {"coordinates":[151.21525573700001,-33.7453269958],"type":"Point"}
}