{
  "type": "Feature",
  "properties": {
    "iso:country":"AU",
    "sg:address":"3 Boomerang St",
    "sg:city":"The Entrance",
    "sg:classifiers":[
        {
            "category":"Education",
            "subcategory":"Special Training",
            "type":"Public Place"
        }
    ],
    "sg:phone":"+61 2 4334 6966",
    "sg:postcode":"2261",
    "sg:province":"NSW",
    "sg:tags":[
        "development"
    ],
    "wof:name":"WorkWise",
    "wof:placetype":"venue"
},
  "geometry": {"coordinates":[151.495377,-33.350334],"type":"Point"}
}