{
  "type": "Feature",
  "properties": {
    "addr:full":"18 Main St Eildon VIC 3713",
    "addr:housenumber":"18",
    "addr:postcode":"3713",
    "addr:street":"Main St",
    "iso:country":"AU",
    "sg:address":"18 Main St",
    "sg:city":"Eildon",
    "sg:classifiers":[
        {
            "category":"Cafe",
            "type":"Food & Drink"
        }
    ],
    "sg:phone":"+61 3 5774 2196",
    "sg:postcode":"3713",
    "sg:province":"VIC",
    "wof:name":"Cafe Eildon",
    "wof:placetype":"venue"
},
  "geometry": {"coordinates":[145.909988403,-37.2324180603],"type":"Point"}
}