{
  "type": "Feature",
  "properties": {
    "iso:country":"AU",
    "sg:address":"Shop 13, Star Court Arc",
    "sg:city":"Lismore",
    "sg:classifiers":[
        {
            "category":"Professional",
            "subcategory":"Printing & Photocopies",
            "type":"Services"
        }
    ],
    "sg:phone":"+61 2 6622 0441",
    "sg:postcode":"2480",
    "sg:province":"NSW",
    "sg:tags":[
        "trophy"
    ],
    "wof:name":"Summerland Trophies",
    "wof:placetype":"venue"
},
  "geometry": {"coordinates":[153.27818298299999,-28.8139896393],"type":"Point"}
}