{
  "type": "Feature",
  "properties": {
    "addr:full":"2/ 498 Ipswich Rd Annerley QLD 4103",
    "addr:housenumber":"/ 498",
    "addr:postcode":"4103",
    "addr:street":"Ipswich Rd",
    "iso:country":"AU",
    "sg:address":"2/ 498 Ipswich Rd",
    "sg:city":"Annerley",
    "sg:classifiers":[
        {
            "category":"Shopping",
            "subcategory":"Clothing, Apparel, & Fashions",
            "type":"Retail Goods"
        }
    ],
    "sg:phone":"+61 7 3892 4471",
    "sg:postcode":"4103",
    "sg:province":"QLD",
    "sg:tags":[
        "recycled",
        "clothing"
    ],
    "wof:name":"Good Works Company",
    "wof:placetype":"venue"
},
  "geometry": {"coordinates":[153.03228759800001,-27.5110797882],"type":"Point"}
}