{
  "type": "Feature",
  "properties": {
    "iso:country":"AU",
    "sg:address":"48 Golden Grove Drv",
    "sg:city":"Narre Warren",
    "sg:classifiers":[
        {
            "category":"Building & Trades",
            "subcategory":"Construction",
            "type":"Services"
        }
    ],
    "sg:phone":"+61 3 8786 5227",
    "sg:postcode":"3805",
    "sg:province":"VIC",
    "sg:tags":[
        "contractor"
    ],
    "wof:name":"Home Lodge",
    "wof:placetype":"venue"
},
  "geometry": {"coordinates":[145.296997,-38.067547],"type":"Point"}
}