{
  "type": "Feature",
  "properties": {
    "addr:full":"Suite 6, Harbord Village Centre-Cnr Moore & Albert Harbord NSW 2096",
    "addr:postcode":"2096",
    "iso:country":"AU",
    "sg:address":"Suite 6, Harbord Village Centre-Cnr Moore & Albert",
    "sg:city":"Harbord",
    "sg:classifiers":[
        {
            "category":"Health Services",
            "subcategory":"Dentist",
            "type":"Services"
        }
    ],
    "sg:phone":"+61 2 9905 2022",
    "sg:postcode":"2096",
    "sg:province":"NSW",
    "wof:name":"Sargeant Trevor Dr",
    "wof:placetype":"venue"
},
  "geometry": {"coordinates":[151.28024292000001,-33.7780914307],"type":"Point"}
}