{
  "type": "Feature",
  "properties": {
    "addr:full":"5 Faraday St West Hobart TAS 7000",
    "addr:housenumber":"5",
    "addr:postcode":"7000",
    "addr:street":"Faraday St",
    "iso:country":"AU",
    "sg:address":"5 Faraday St",
    "sg:city":"West Hobart",
    "sg:classifiers":[
        {
            "category":"Arts & Performance",
            "subcategory":"Theater",
            "type":"Entertainment"
        }
    ],
    "sg:phone":"+61 3 6234 4009",
    "sg:postcode":"7000",
    "sg:province":"TAS",
    "sg:tags":[
        "theatre"
    ],
    "wof:name":"Hobart Playback Theatre Company",
    "wof:placetype":"venue"
},
  "geometry": {"coordinates":[147.31492614699999,-42.8848190308],"type":"Point"}
}