{
  "type": "Feature",
  "properties": {
    "iso:country":"AU",
    "sg:address":"PO Box 3038",
    "sg:city":"Success",
    "sg:classifiers":[
        {
            "category":"Manufacturing",
            "subcategory":"Aerospace",
            "type":"Manufacturing & Wholesale Goods"
        }
    ],
    "sg:phone":"+61 409 080 437",
    "sg:postcode":"6964",
    "sg:province":"WA",
    "sg:tags":[
        "equipment",
        "aircraft",
        "maintenance"
    ],
    "wof:name":"AV Clean",
    "wof:placetype":"venue"
},
  "geometry": {"coordinates":[115.846428,-32.15659],"type":"Point"}
}