{
  "type": "Feature",
  "properties": {
    "addr:full":"878 Port Rd Woodville South SA 5011",
    "addr:housenumber":"878",
    "addr:postcode":"5011",
    "addr:street":"Port Rd",
    "iso:country":"AU",
    "sg:address":"878 Port Rd",
    "sg:city":"Woodville South",
    "sg:classifiers":[
        {
            "category":"Food & Beverages",
            "subcategory":"Liquor & Beverages",
            "type":"Retail Goods"
        }
    ],
    "sg:phone":"+61 8 8347 1133",
    "sg:postcode":"5011",
    "sg:province":"SA",
    "sg:tags":[
        "store"
    ],
    "wof:name":"Liquorsmart Pty Ltd",
    "wof:placetype":"venue"
},
  "geometry": {"coordinates":[138.53465270999999,-34.8808288574],"type":"Point"}
}