{
  "type": "Feature",
  "properties": {
    "addr:full":"Shop 64 Marsh Pde Casula NSW 2170",
    "addr:housenumber":"shop 64",
    "addr:postcode":"2170",
    "addr:street":"Marsh Pde",
    "iso:country":"AU",
    "sg:address":"Shop 64 Marsh Pde",
    "sg:city":"Casula",
    "sg:classifiers":[
        {
            "category":"Home & Garden",
            "subcategory":"Building Materials",
            "type":"Retail Goods"
        }
    ],
    "sg:phone":"+61 2 9822 7202",
    "sg:postcode":"2170",
    "sg:province":"NSW",
    "sg:tags":[
        "merchant",
        "glass",
        "glazier"
    ],
    "wof:name":"Tahmoor Glass",
    "wof:placetype":"venue"
},
  "geometry": {"coordinates":[150.91009521500001,-33.9466133118],"type":"Point"}
}