{
  "type": "Feature",
  "properties": {
    "iso:country":"AU",
    "sg:address":"28 Ross St",
    "sg:city":"Glebe",
    "sg:classifiers":[
        {
            "category":"Government",
            "subcategory":"Court House",
            "type":"Public Place"
        }
    ],
    "sg:phone":"+61 410 561 032",
    "sg:postcode":"2037",
    "sg:province":"NSW",
    "sg:tags":[
        "personal",
        "marriage",
        "family",
        "counselling"
    ],
    "wof:name":"Anam Cara Counselling & Psychotherapy",
    "wof:placetype":"venue"
},
  "geometry": {"coordinates":[151.18095398,-33.8807525635],"type":"Point"}
}