{
  "type": "Feature",
  "properties": {
    "addr:full":"Rene St Tewantin QLD 4565",
    "addr:postcode":"4565",
    "addr:street":"Rene St",
    "iso:country":"AU",
    "sg:address":"Rene St",
    "sg:city":"Tewantin",
    "sg:classifiers":[
        {
            "category":"Farming",
            "subcategory":"Dairy Farm",
            "type":"Manufacturing & Wholesale Goods"
        }
    ],
    "sg:phone":"+61 7 5474 3192",
    "sg:postcode":"4565",
    "sg:province":"QLD",
    "sg:tags":[
        "wholesaler",
        "product",
        "mfrs"
    ],
    "wof:name":"Harco Dairy Food Distributors",
    "wof:placetype":"venue"
},
  "geometry": {"coordinates":[153.02882385300001,-26.3923187256],"type":"Point"}
}