{
  "type": "Feature",
  "properties": {
    "addr:full":"PO Box 2135 Footscray VIC 3011",
    "addr:postcode":"3011",
    "iso:country":"AU",
    "sg:address":"PO Box 2135",
    "sg:city":"Footscray",
    "sg:classifiers":[
        {
            "category":"Manufacturing",
            "subcategory":"Tools & Machinery",
            "type":"Manufacturing & Wholesale Goods"
        }
    ],
    "sg:phone":"+61 417 568 589",
    "sg:postcode":"3011",
    "sg:province":"VIC",
    "sg:tags":[
        "supplier",
        "diamond"
    ],
    "wof:name":"Zamin Holdings Pty Ltd",
    "wof:placetype":"venue"
},
  "geometry": {"coordinates":[144.89125060999999,-37.7917098999],"type":"Point"}
}