{
  "type": "Feature",
  "properties": {
    "iso:country":"AU",
    "sg:address":"18 Grand Pde",
    "sg:city":"Epping",
    "sg:classifiers":[
        {
            "category":"Building & Trades",
            "subcategory":"Equipment Rental",
            "type":"Services"
        }
    ],
    "sg:phone":"+61 3 9408 6440",
    "sg:postcode":"3076",
    "sg:province":"VIC",
    "sg:tags":[
        "demolition",
        "contractor"
    ],
    "wof:name":"Toms Handyman Services",
    "wof:placetype":"venue"
},
  "geometry": {"coordinates":[145.02838134800001,-37.6561965942],"type":"Point"}
}