{
  "type": "Feature",
  "properties": {
    "addr:full":"7-9 Bellevue Rd Bellevue Hill NSW 2023",
    "addr:housenumber":"7-9",
    "addr:postcode":"2023",
    "addr:street":"Bellevue Rd",
    "iso:country":"AU",
    "sg:address":"7-9 Bellevue Rd",
    "sg:city":"Bellevue Hill",
    "sg:classifiers":[
        {
            "category":"Personal",
            "subcategory":"Shoe Repair & Shine",
            "type":"Services"
        }
    ],
    "sg:phone":"+61 2 9387 7288",
    "sg:postcode":"2023",
    "sg:province":"NSW",
    "sg:tags":[
        "footwear"
    ],
    "wof:name":"Bellevue Hill Shoe Repair",
    "wof:placetype":"venue"
},
  "geometry": {"coordinates":[151.25851440400001,-33.8864746094],"type":"Point"}
}