{
  "type": "Feature",
  "properties": {
    "iso:country":"AU",
    "sg:address":"2 Marlborough St",
    "sg:city":"Glenroy",
    "sg:classifiers":[
        {
            "category":"Home & Garden",
            "subcategory":"Building Materials",
            "type":"Retail Goods"
        }
    ],
    "sg:phone":"+61 3 9300 1111",
    "sg:postcode":"3046",
    "sg:province":"VIC",
    "sg:tags":[
        "laminate",
        "laminated",
        "panel"
    ],
    "wof:name":"&#034;A&#034; Series Pty Ltd",
    "wof:placetype":"venue"
},
  "geometry": {"coordinates":[144.917877197,-37.7041778564],"type":"Point"}
}