{
  "type": "Feature",
  "properties": {
    "addr:full":"72 Crystal Downs Drv Blackmans Bay TAS 7052",
    "addr:housenumber":"72",
    "addr:postcode":"7052",
    "addr:street":"Crystal Downs Drv",
    "iso:country":"AU",
    "sg:address":"72 Crystal Downs Drv",
    "sg:city":"Blackmans Bay",
    "sg:classifiers":[
        {
            "category":"Personal",
            "type":"Services"
        }
    ],
    "sg:phone":"+61 3 6229 3578",
    "sg:postcode":"7052",
    "sg:province":"TAS",
    "sg:tags":[
        "wallpapering",
        "wallcovering"
    ],
    "wof:name":"Dimond Michael J",
    "wof:placetype":"venue"
},
  "geometry": {"coordinates":[147.314865,-43.000866],"type":"Point"}
}