{
  "type": "Feature",
  "properties": {
    "addr:full":"13th Floor 222 Kingsway St South Melbourne VIC 3205",
    "addr:housenumber":"222",
    "addr:postcode":"3205",
    "addr:street":"Kingsway St",
    "iso:country":"AU",
    "sg:address":"13th Floor 222 Kingsway St",
    "sg:city":"South Melbourne",
    "sg:classifiers":[
        {
            "category":"Professional",
            "subcategory":"Accounting & Tax Preparation",
            "type":"Services"
        }
    ],
    "sg:phone":"+61 3 9690 5700",
    "sg:postcode":"3205",
    "sg:province":"VIC",
    "sg:tags":[
        "accountant",
        "auditor"
    ],
    "wof:name":"Stanley T G",
    "wof:placetype":"venue"
},
  "geometry": {"coordinates":[144.95585600000001,-37.833881],"type":"Point"}
}