{
  "type": "Feature",
  "properties": {
    "addr:full":"Bay 14 Bayside Cct Laurieton NSW 2443",
    "addr:housenumber":"14",
    "addr:postcode":"2443",
    "addr:street":"Bayside Cct",
    "iso:country":"AU",
    "sg:address":"Bay 14",
    "sg:city":"Bayside Cct Laurieton",
    "sg:classifiers":[
        {
            "category":"Professional",
            "type":"Services"
        }
    ],
    "sg:phone":"+61 2 6559 7199",
    "sg:postcode":"2443",
    "sg:province":"NSW",
    "sg:tags":[
        "spray",
        "painting"
    ],
    "wof:name":"B & B Goodison",
    "wof:placetype":"venue"
},
  "geometry": {"coordinates":[152.823837,-31.637335],"type":"Point"}
}