{
  "type": "Feature",
  "properties": {
    "addr:full":"PO Box 803 Torquay VIC 3228",
    "addr:postcode":"3228",
    "iso:country":"AU",
    "sg:address":"PO Box 803",
    "sg:city":"Torquay",
    "sg:classifiers":[
        {
            "category":"Building & Trades",
            "subcategory":"Plumbing",
            "type":"Services"
        }
    ],
    "sg:phone":"+61 412 350 933",
    "sg:postcode":"3228",
    "sg:province":"VIC",
    "sg:tags":[
        "plumber",
        "gasfitters"
    ],
    "wof:name":"Steed Plumbing",
    "wof:placetype":"venue"
},
  "geometry": {"coordinates":[144.31811500000001,-38.329899],"type":"Point"}
}