{
  "type": "Feature",
  "properties": {
    "addr:full":"99 O'Shanassy St Sunbury VIC 3429",
    "addr:housenumber":"99",
    "addr:postcode":"3429",
    "addr:street":"O'Shanassy St",
    "iso:country":"AU",
    "sg:address":"99 O'Shanassy St",
    "sg:city":"Sunbury",
    "sg:classifiers":[
        {
            "category":"Food & Beverages",
            "subcategory":"Liquor & Beverages",
            "type":"Retail Goods"
        }
    ],
    "sg:phone":"+61 3 9744 1450",
    "sg:postcode":"3429",
    "sg:province":"VIC",
    "sg:tags":[
        "store"
    ],
    "wof:name":"Sunbury Cellars",
    "wof:placetype":"venue"
},
  "geometry": {"coordinates":[144.73062133799999,-37.5805664062],"type":"Point"}
}