{
  "type": "Feature",
  "properties": {
    "addr:full":"191 Blackburn Rd Mt Waverley VIC 3149",
    "addr:housenumber":"191",
    "addr:postcode":"3149",
    "addr:street":"Blackburn Rd",
    "iso:country":"AU",
    "sg:address":"191 Blackburn Rd",
    "sg:city":"Mt Waverley",
    "sg:classifiers":[
        {
            "category":"Real Estate",
            "subcategory":"Real Estate Agent",
            "type":"Services"
        }
    ],
    "sg:phone":"+61 3 9802 7777",
    "sg:postcode":"3149",
    "sg:province":"VIC",
    "wof:name":"Allen Maher Real Estate Pty Ltd",
    "wof:placetype":"venue"
},
  "geometry": {"coordinates":[145.14831543,-37.871711731],"type":"Point"}
}