{
  "type": "Feature",
  "properties": {
    "addr:full":"2/ 161 Orlando St Coffs Harbour NSW 2450",
    "addr:housenumber":"/ 161",
    "addr:postcode":"2450",
    "addr:street":"Orlando St",
    "iso:country":"AU",
    "sg:address":"2/ 161 Orlando St",
    "sg:city":"Coffs Harbour",
    "sg:classifiers":[
        {
            "category":"Retail",
            "subcategory":"Auto Repair",
            "type":"Services"
        }
    ],
    "sg:phone":"+61 1800 001 122",
    "sg:postcode":"2450",
    "sg:province":"NSW",
    "sg:tags":[
        "transmission",
        "automotive",
        "car"
    ],
    "wof:name":"Greenaways Gearboxes & Differentials",
    "wof:placetype":"venue"
},
  "geometry": {"coordinates":[153.13064600000001,-30.289173],"type":"Point"}
}