{
  "type": "Feature",
  "properties": {
    "addr:full":"44 Eastern Ave Bilinga QLD 4225",
    "addr:housenumber":"44",
    "addr:postcode":"4225",
    "addr:street":"Eastern Ave",
    "iso:country":"AU",
    "sg:address":"44 Eastern Ave",
    "sg:city":"Bilinga",
    "sg:classifiers":[
        {
            "category":"Airline",
            "type":"Transportation"
        }
    ],
    "sg:phone":"+61 7 5506 8400",
    "sg:postcode":"4225",
    "sg:province":"QLD",
    "sg:tags":[
        "aircraft",
        "rental",
        "charter"
    ],
    "wof:name":"Careflight Queensland",
    "wof:placetype":"venue"
},
  "geometry": {"coordinates":[153.51017761200001,-28.1613826752],"type":"Point"}
}