{
  "type": "Feature",
  "properties": {
    "iso:country":"AU",
    "sg:address":"16 Dutruc St",
    "sg:city":"Randwick",
    "sg:classifiers":[
        {
            "category":"Professional",
            "subcategory":"Art Services",
            "type":"Services"
        }
    ],
    "sg:phone":"+61 2 9398 4748",
    "sg:postcode":"2031",
    "sg:province":"NSW",
    "sg:tags":[
        "decorator",
        "painter"
    ],
    "wof:name":"Devenay James",
    "wof:placetype":"venue"
},
  "geometry": {"coordinates":[151.245483398,-33.9103088379],"type":"Point"}
}