{
  "type": "Feature",
  "properties": {
    "addr:full":"77 Corfield St Hervey Bay QLD 4655",
    "addr:housenumber":"77",
    "addr:postcode":"4655",
    "addr:street":"Corfield St",
    "iso:country":"AU",
    "sg:address":"77 Corfield St",
    "sg:city":"Hervey Bay",
    "sg:classifiers":[
        {
            "category":"Building & Trades",
            "subcategory":"Construction",
            "type":"Services"
        }
    ],
    "sg:phone":"+61 7 4124 8201",
    "sg:postcode":"4655",
    "sg:province":"QLD",
    "sg:tags":[
        "insulation",
        "contractor"
    ],
    "wof:name":"Alsafe Insulation Warehouse",
    "wof:placetype":"venue"
},
  "geometry": {"coordinates":[152.822632,-25.251154],"type":"Point"}
}