{
  "type": "Feature",
  "properties": {
    "addr:full":"85 Travers St Wagga Wagga NSW 2650",
    "addr:housenumber":"85",
    "addr:postcode":"2650",
    "addr:street":"Travers St",
    "iso:country":"AU",
    "sg:address":"85 Travers St",
    "sg:city":"Wagga Wagga",
    "sg:classifiers":[
        {
            "category":"Professional",
            "type":"Services"
        }
    ],
    "sg:phone":"+61 2 6938 6900",
    "sg:postcode":"2650",
    "sg:province":"NSW",
    "sg:tags":[
        "transport"
    ],
    "wof:name":"Toll AutoLogistics",
    "wof:placetype":"venue"
},
  "geometry": {"coordinates":[147.35624694800001,-35.0999221802],"type":"Point"}
}