{
  "type": "Feature",
  "properties": {
    "addr:full":"19 Hyde St Bellingen NSW 2454",
    "addr:housenumber":"19",
    "addr:postcode":"2454",
    "addr:street":"Hyde St",
    "iso:country":"AU",
    "sg:address":"19 Hyde St",
    "sg:city":"Bellingen",
    "sg:classifiers":[
        {
            "category":"Real Estate",
            "subcategory":"Real Estate Agent",
            "type":"Services"
        }
    ],
    "sg:phone":"+61 2 6655 1123",
    "sg:postcode":"2454",
    "sg:province":"NSW",
    "wof:name":"Bob Hamilton Real Estate",
    "wof:placetype":"venue"
},
  "geometry": {"coordinates":[152.89773600000001,-30.452415],"type":"Point"}
}