{
  "type": "Feature",
  "properties": {
    "iso:country":"AU",
    "sg:address":"103 McLaughlin St",
    "sg:city":"North Rockhampton",
    "sg:classifiers":[
        {
            "category":"Home & Garden",
            "subcategory":"Building Materials",
            "type":"Retail Goods"
        }
    ],
    "sg:phone":"+61 1300 033 623",
    "sg:postcode":"4701",
    "sg:province":"QLD",
    "sg:tags":[
        "fencing"
    ],
    "wof:name":"ETs Fencing & Bobcat Hire",
    "wof:placetype":"venue"
},
  "geometry": {"coordinates":[150.51167297399999,-23.3342456818],"type":"Point"}
}