{
  "type": "Feature",
  "properties": {
    "addr:full":"95 Avalon Rd Sheldon QLD 4157",
    "addr:housenumber":"95",
    "addr:postcode":"4157",
    "addr:street":"Avalon Rd",
    "iso:country":"AU",
    "sg:address":"95 Avalon Rd",
    "sg:city":"Sheldon",
    "sg:classifiers":[
        {
            "category":"Building & Trades",
            "subcategory":"Plumbing",
            "type":"Services"
        }
    ],
    "sg:phone":"+61 1800 775 511",
    "sg:postcode":"4157",
    "sg:province":"QLD",
    "sg:tags":[
        "pump",
        "repairer"
    ],
    "wof:name":"Prime Pumps Pty Ltd",
    "wof:placetype":"venue"
},
  "geometry": {"coordinates":[153.19786071799999,-27.5713024139],"type":"Point"}
}