{
  "type": "Feature",
  "properties": {
    "addr:full":"Shop 99/1- 5 Meeks St Kingsford NSW 2032",
    "addr:housenumber":"shop 99 / 1 5",
    "addr:postcode":"2032",
    "addr:street":"Meeks St",
    "iso:country":"AU",
    "sg:address":"Shop 99/1- 5 Meeks St",
    "sg:city":"Kingsford",
    "sg:classifiers":[
        {
            "category":"Building & Trades",
            "subcategory":"Locksmith",
            "type":"Services"
        }
    ],
    "sg:phone":"+61 2 9663 1889",
    "sg:postcode":"2032",
    "sg:province":"NSW",
    "sg:tags":[
        "lock"
    ],
    "wof:name":"Kingsford Locksmiths",
    "wof:placetype":"venue"
},
  "geometry": {"coordinates":[151.228240967,-33.922744751],"type":"Point"}
}