{
  "type": "Feature",
  "properties": {
    "iso:country":"AU",
    "sg:address":"72 Meridan Way",
    "sg:city":"Meridan Plains",
    "sg:classifiers":[
        {
            "category":"Autos & Motor Vehicles",
            "subcategory":"Automobile Sales",
            "type":"Retail Goods"
        }
    ],
    "sg:phone":"+61 7 5491 2560",
    "sg:postcode":"4551",
    "sg:province":"QLD",
    "sg:tags":[
        "equipment",
        "trailer"
    ],
    "wof:name":"Caravan Repair Centre",
    "wof:placetype":"venue"
},
  "geometry": {"coordinates":[153.099533081,-26.7621898651],"type":"Point"}
}