{
  "type": "Feature",
  "properties": {
    "iso:country":"AU",
    "sg:address":"208 Wellington St",
    "sg:city":"Collingwood",
    "sg:classifiers":[
        {
            "category":"Organizations",
            "subcategory":"Non-profit Organization",
            "type":"Services"
        }
    ],
    "sg:phone":"+61 1800 805 384",
    "sg:postcode":"3066",
    "sg:province":"VIC",
    "sg:tags":[
        "support",
        "disability",
        "organisation"
    ],
    "wof:name":"ParaQuad Victoria",
    "wof:placetype":"venue"
},
  "geometry": {"coordinates":[144.986984253,-37.8022460938],"type":"Point"}
}