{
  "type": "Feature",
  "properties": {
    "addr:full":"34 Hydrae St Revesby NSW 2212",
    "addr:housenumber":"34",
    "addr:postcode":"2212",
    "addr:street":"Hydrae St",
    "iso:country":"AU",
    "sg:address":"34 Hydrae St",
    "sg:city":"Revesby",
    "sg:classifiers":[
        {
            "category":"Social Services",
            "subcategory":"Retirement Home",
            "type":"Services"
        }
    ],
    "sg:phone":"+61 2 9773 7466",
    "sg:postcode":"2212",
    "sg:province":"NSW",
    "sg:tags":[
        "village"
    ],
    "wof:name":"Bankstown City Aged Care - Yallambee Village (Hostel)",
    "wof:placetype":"venue"
},
  "geometry": {"coordinates":[151.02015700000001,-33.958279],"type":"Point"}
}