{
  "type": "Feature",
  "properties": {
    "addr:full":"20 Whitelodge Rd Paradise SA 5075",
    "addr:housenumber":"20",
    "addr:postcode":"5075",
    "addr:street":"Whitelodge Rd",
    "iso:country":"AU",
    "sg:address":"20 Whitelodge Rd",
    "sg:city":"Paradise",
    "sg:classifiers":[
        {
            "category":"Sports & Exercise",
            "subcategory":"Sports Center",
            "type":"Entertainment"
        }
    ],
    "sg:phone":"+61 8 8337 4258",
    "sg:postcode":"5075",
    "sg:province":"SA",
    "sg:tags":[
        "coach",
        "tennis"
    ],
    "wof:name":"Tietz Ian",
    "wof:placetype":"venue"
},
  "geometry": {"coordinates":[138.66114807100001,-34.8662643433],"type":"Point"}
}