{
  "type": "Feature",
  "properties": {
    "addr:full":"1/ 114 Penshurst St Penshurst NSW 2222",
    "addr:housenumber":"/ 114",
    "addr:postcode":"2222",
    "addr:street":"Penshurst St",
    "iso:country":"AU",
    "sg:address":"1/ 114 Penshurst St",
    "sg:city":"Penshurst",
    "sg:classifiers":[
        {
            "category":"Health Services",
            "subcategory":"Doctor",
            "type":"Services"
        }
    ],
    "sg:phone":"+61 2 9580 9808",
    "sg:postcode":"2222",
    "sg:province":"NSW",
    "sg:tags":[
        "medical",
        "practitioner"
    ],
    "wof:name":"Khan H Dr",
    "wof:placetype":"venue"
},
  "geometry": {"coordinates":[151.085083008,-33.961265564],"type":"Point"}
}