{
  "type": "Feature",
  "properties": {
    "iso:country":"AU",
    "sg:address":"16 Darwin St",
    "sg:city":"Marysville",
    "sg:classifiers":[
        {
            "category":"Travel",
            "subcategory":"Hotels & Motels",
            "type":"Entertainment"
        }
    ],
    "sg:phone":"+61 3 5963 3247",
    "sg:postcode":"3779",
    "sg:province":"VIC",
    "wof:name":"Scenic B & B Motel",
    "wof:placetype":"venue"
},
  "geometry": {"coordinates":[145.743439,-37.50948],"type":"Point"}
}