{
  "type": "Feature",
  "properties": {
    "iso:country":"AU",
    "sg:address":"84 Smith St",
    "sg:city":"Darwin",
    "sg:classifiers":[
        {
            "category":"Professional",
            "type":"Services"
        }
    ],
    "sg:phone":"+61 8 8982 8899",
    "sg:postcode":"0800",
    "sg:province":"NT",
    "sg:tags":[
        "valuer"
    ],
    "wof:name":"R. J. Bowen & Associates",
    "wof:placetype":"venue"
},
  "geometry": {"coordinates":[130.83909606899999,-12.4603357315],"type":"Point"}
}