{
  "type": "Feature",
  "properties": {
    "iso:country":"AU",
    "sg:address":"93 Golden Four Drv",
    "sg:city":"Bilinga",
    "sg:classifiers":[
        {
            "category":"Organizations",
            "subcategory":"Community Association",
            "type":"Services"
        }
    ],
    "sg:phone":"+61 7 5536 2173",
    "sg:postcode":"4225",
    "sg:province":"QLD",
    "sg:tags":[
        "organisation",
        "family",
        "welfare"
    ],
    "wof:name":"Blair Athol Accommodation & Support Programme",
    "wof:placetype":"venue"
},
  "geometry": {"coordinates":[153.51736450199999,-28.164276123],"type":"Point"}
}