{
  "type": "Feature",
  "properties": {
    "addr:full":"100 Fairfield St Fairfield NSW 2165",
    "addr:housenumber":"100",
    "addr:postcode":"2165",
    "addr:street":"Fairfield St",
    "iso:country":"AU",
    "sg:address":"100 Fairfield St",
    "sg:city":"Fairfield",
    "sg:classifiers":[
        {
            "category":"Retail",
            "subcategory":"Funeral Services",
            "type":"Services"
        }
    ],
    "sg:phone":"+61 2 9681 2355",
    "sg:postcode":"2165",
    "sg:province":"NSW",
    "sg:tags":[
        "supply"
    ],
    "wof:name":"Beta Casket Co",
    "wof:placetype":"venue"
},
  "geometry": {"coordinates":[150.970993042,-33.8684043884],"type":"Point"}
}