{
  "type": "Feature",
  "properties": {
    "addr:full":"41 Station Rd Logan Central QLD 4114",
    "addr:housenumber":"41",
    "addr:postcode":"4114",
    "addr:street":"Station Rd",
    "iso:country":"AU",
    "sg:address":"41 Station Rd",
    "sg:city":"Logan Central",
    "sg:classifiers":[
        {
            "category":"Health Services",
            "subcategory":"Doctor",
            "type":"Services"
        }
    ],
    "sg:phone":"+61 7 3299 1199",
    "sg:postcode":"4114",
    "sg:province":"QLD",
    "sg:tags":[
        "medical",
        "practitioner"
    ],
    "wof:name":"Woodridge Clinic",
    "wof:placetype":"venue"
},
  "geometry": {"coordinates":[153.10403442399999,-27.6377277374],"type":"Point"}
}