{
  "type": "Feature",
  "properties": {
    "addr:full":"112 Mica St Carole Park QLD 4300",
    "addr:housenumber":"112",
    "addr:postcode":"4300",
    "addr:street":"Mica St",
    "iso:country":"AU",
    "sg:address":"112 Mica St",
    "sg:city":"Carole Park",
    "sg:classifiers":[
        {
            "category":"Professional",
            "subcategory":"Detective & Security Services",
            "type":"Services"
        }
    ],
    "sg:phone":"+61 7 3271 5133",
    "sg:postcode":"4300",
    "sg:province":"QLD",
    "sg:tags":[
        "consultant",
        "laser"
    ],
    "wof:name":"Acute Laser",
    "wof:placetype":"venue"
},
  "geometry": {"coordinates":[152.93347168,-27.6217823029],"type":"Point"}
}