{
  "type": "Feature",
  "properties": {
    "addr:full":"34 Moore St Woodridge QLD 4114",
    "addr:housenumber":"34",
    "addr:postcode":"4114",
    "addr:street":"Moore St",
    "iso:country":"AU",
    "sg:address":"34 Moore St",
    "sg:city":"Woodridge",
    "sg:classifiers":[
        {
            "category":"Retail",
            "subcategory":"Auto Repair",
            "type":"Services"
        }
    ],
    "sg:phone":"+61 417 193 410",
    "sg:postcode":"4114",
    "sg:province":"QLD",
    "sg:tags":[
        "repairer",
        "motor",
        "engineer"
    ],
    "wof:name":"Trax Mechanical",
    "wof:placetype":"venue"
},
  "geometry": {"coordinates":[153.11341857900001,-27.6400318146],"type":"Point"}
}