{
  "type": "Feature",
  "properties": {
    "addr:full":"Hambleton Hill Rd Singleton NSW 2330",
    "addr:postcode":"2330",
    "addr:street":"Hambleton Hill Rd",
    "iso:country":"AU",
    "sg:address":"Hambleton Hill Rd",
    "sg:city":"Singleton",
    "sg:classifiers":[
        {
            "category":"Professional",
            "type":"Services"
        }
    ],
    "sg:phone":"+61 1300 366 684",
    "sg:postcode":"2330",
    "sg:province":"NSW",
    "sg:tags":[
        "transport"
    ],
    "wof:name":"Toll IPEC",
    "wof:placetype":"venue"
},
  "geometry": {"coordinates":[151.124268,-32.59676],"type":"Point"}
}