{
  "type": "Feature",
  "properties": {
    "addr:full":"Cnr Wheeler Crs. & Coghill Drv. Currumbin QLD 4223",
    "addr:postcode":"4223",
    "addr:street":"Cnr Wheeler",
    "iso:country":"AU",
    "sg:address":"Cnr Wheeler Crs. & Coghill Drv.",
    "sg:city":"Currumbin",
    "sg:classifiers":[
        {
            "category":"Arena",
            "subcategory":"Indoor Arena",
            "type":"Entertainment"
        }
    ],
    "sg:phone":"+61 7 5598 1855",
    "sg:postcode":"4223",
    "sg:province":"QLD",
    "sg:tags":[
        "interior",
        "panelling"
    ],
    "wof:name":"Sharp Plywood Pty. Ltd.",
    "wof:placetype":"venue"
},
  "geometry": {"coordinates":[153.47541809099999,-28.1490058899],"type":"Point"}
}