{
  "type": "Feature",
  "properties": {
    "iso:country":"AU",
    "sg:address":"6 Beach St",
    "sg:city":"Wollongong",
    "sg:classifiers":[
        {
            "category":"Retail",
            "subcategory":"Auto Repair",
            "type":"Services"
        }
    ],
    "sg:phone":"+61 2 4228 0016",
    "sg:postcode":"2500",
    "sg:province":"NSW",
    "sg:tags":[
        "repairer",
        "motor",
        "engineer"
    ],
    "wof:name":"Kev's Automotive Repair Centre",
    "wof:placetype":"venue"
},
  "geometry": {"coordinates":[150.897141,-34.433308],"type":"Point"}
}