{
  "type": "Feature",
  "properties": {
    "addr:full":"PO Box 16 Darwin NT 0801",
    "addr:postcode":"nt 0801",
    "iso:country":"AU",
    "sg:address":"PO Box 16",
    "sg:city":"Darwin",
    "sg:classifiers":[
        {
            "category":"Utilities",
            "subcategory":"Water",
            "type":"Services"
        }
    ],
    "sg:phone":"+61 429 896 069",
    "sg:postcode":"0801",
    "sg:province":"NT",
    "sg:tags":[
        "cartage"
    ],
    "wof:name":"Wayne's Water Cartage",
    "wof:placetype":"venue"
},
  "geometry": {"coordinates":[130.84190368599999,-12.4613304138],"type":"Point"}
}