{
  "type": "Feature",
  "properties": {
    "addr:full":"11/ 86 Sheppard St Hume ACT 2620",
    "addr:housenumber":"11 / 86",
    "addr:postcode":"2620",
    "addr:street":"Sheppard St",
    "iso:country":"AU",
    "sg:address":"11/ 86 Sheppard St",
    "sg:city":"Hume",
    "sg:classifiers":[
        {
            "category":"Building & Trades",
            "subcategory":"Construction",
            "type":"Services"
        }
    ],
    "sg:phone":"+61 2 6260 1666",
    "sg:postcode":"2620",
    "sg:province":"ACT",
    "sg:tags":[
        "industrial",
        "commercial",
        "air conditioning"
    ],
    "wof:name":"Icon Air Conditioning",
    "wof:placetype":"venue"
},
  "geometry": {"coordinates":[149.082397461,-35.3620109558],"type":"Point"}
}