{
  "type": "Feature",
  "properties": {
    "addr:full":"Cnr Ducat St & Ourim Rd Tweed Heads NSW 2485",
    "addr:postcode":"2485",
    "addr:street":"Cnr Ducat St & Ourim Rd",
    "iso:country":"AU",
    "sg:address":"Cnr Ducat St & Ourim Rd",
    "sg:city":"Tweed Heads",
    "sg:classifiers":[
        {
            "category":"Shopping",
            "subcategory":"Bicycles & Sporting Goods",
            "type":"Retail Goods"
        }
    ],
    "sg:phone":"+61 7 5536 6519",
    "sg:postcode":"2485",
    "sg:province":"NSW",
    "sg:tags":[
        "chemical",
        "equipment",
        "pool",
        "swimming"
    ],
    "wof:name":"Wyuna Pool Shop & Service",
    "wof:placetype":"venue"
},
  "geometry": {"coordinates":[153.53985595699999,-28.1784820557],"type":"Point"}
}