{
  "type": "Feature",
  "properties": {
    "addr:full":"Foti Rd Pickering Brook WA 6076",
    "addr:postcode":"6076",
    "addr:street":"Foti Rd",
    "iso:country":"AU",
    "sg:address":"Foti Rd",
    "sg:city":"Pickering Brook",
    "sg:classifiers":[
        {
            "category":"Farming",
            "subcategory":"Farm",
            "type":"Manufacturing & Wholesale Goods"
        }
    ],
    "sg:phone":"+61 8 9293 8254",
    "sg:postcode":"6076",
    "sg:province":"WA",
    "sg:tags":[
        "farmer"
    ],
    "wof:name":"O&#039;Meagher G S & L",
    "wof:placetype":"venue"
},
  "geometry": {"coordinates":[116.11592865,-32.033744812],"type":"Point"}
}