{
  "type": "Feature",
  "properties": {
    "addr:full":"38 Main St Moresby QLD 4871",
    "addr:housenumber":"38",
    "addr:postcode":"4871",
    "addr:street":"Main St",
    "iso:country":"AU",
    "sg:address":"38 Main St",
    "sg:city":"Moresby",
    "sg:classifiers":[
        {
            "category":"Autos & Motor Vehicles",
            "subcategory":"Automobile Sales",
            "type":"Retail Goods"
        }
    ],
    "sg:phone":"+61 7 4063 2358",
    "sg:postcode":"4871",
    "sg:province":"QLD",
    "sg:tags":[
        "car",
        "used"
    ],
    "wof:name":"Moresby Motor & Caravan Mart Pty Ltd",
    "wof:placetype":"venue"
},
  "geometry": {"coordinates":[145.329986572,-16.6743984222],"type":"Point"}
}