{
  "type": "Feature",
  "properties": {
    "iso:country":"AU",
    "sg:address":"428 King St",
    "sg:city":"Newtown",
    "sg:classifiers":[
        {
            "category":"Manufacturing",
            "subcategory":"Pottery",
            "type":"Manufacturing & Wholesale Goods"
        }
    ],
    "sg:phone":"+61 2 9557 0718",
    "sg:postcode":"2042",
    "sg:province":"NSW",
    "wof:name":"Tranquality",
    "wof:placetype":"venue"
},
  "geometry": {"coordinates":[151.178314,-33.900288],"type":"Point"}
}