{
  "type": "Feature",
  "properties": {
    "iso:country":"AU",
    "sg:address":"Homequest 2000, 4 Consolo Ave",
    "sg:city":"Parklea",
    "sg:classifiers":[
        {
            "category":"Building & Trades",
            "subcategory":"Construction",
            "type":"Services"
        }
    ],
    "sg:phone":"+61 2 9629 4499",
    "sg:postcode":"2768",
    "sg:province":"NSW",
    "sg:tags":[
        "contractor"
    ],
    "wof:name":"Ian D McDonald Homes Pty Ltd",
    "wof:placetype":"venue"
},
  "geometry": {"coordinates":[150.936859,-33.721802],"type":"Point"}
}