{
  "type": "Feature",
  "properties": {
    "iso:country":"AU",
    "sg:address":"255- 259 Campbell St",
    "sg:city":"Swan Hill",
    "sg:classifiers":[
        {
            "category":"Retail",
            "subcategory":"Event Space",
            "type":"Services"
        }
    ],
    "sg:phone":"+61 3 5032 4408",
    "sg:postcode":"3585",
    "sg:province":"VIC",
    "sg:tags":[
        "function",
        "organiser"
    ],
    "wof:name":"Quo-Vadis Restaurant & Pizza Parlour",
    "wof:placetype":"venue"
},
  "geometry": {"coordinates":[143.560577,-35.341743],"type":"Point"}
}