{
  "type": "Feature",
  "properties": {
    "addr:full":"Shop 8, 35 Ferry St Kangaroo Point QLD 4169",
    "addr:housenumber":"shop;35",
    "addr:postcode":"4169",
    "addr:street":"Ferry St",
    "iso:country":"AU",
    "sg:address":"Shop 8, 35 Ferry St",
    "sg:city":"Kangaroo Point",
    "sg:classifiers":[
        {
            "category":"Real Estate",
            "subcategory":"Real Estate Agent",
            "type":"Services"
        }
    ],
    "sg:phone":"+61 7 3392 2700",
    "sg:postcode":"4169",
    "sg:province":"QLD",
    "wof:name":"Pamela Neil Real Estate Agency",
    "wof:placetype":"venue"
},
  "geometry": {"coordinates":[153.037017822,-27.4721469879],"type":"Point"}
}