{
  "type": "Feature",
  "properties": {
    "addr:full":"145 Herries St Toowoomba QLD 4350",
    "addr:housenumber":"145",
    "addr:postcode":"4350",
    "addr:street":"Herries St",
    "iso:country":"AU",
    "sg:address":"145 Herries St",
    "sg:city":"Toowoomba",
    "sg:classifiers":[
        {
            "category":"Real Estate",
            "subcategory":"Real Estate Agent",
            "type":"Services"
        }
    ],
    "sg:phone":"+61 7 4632 9185",
    "sg:postcode":"4350",
    "sg:province":"QLD",
    "wof:name":"Cumming Wilson Wall",
    "wof:placetype":"venue"
},
  "geometry": {"coordinates":[151.936691,-27.562099],"type":"Point"}
}