{
  "type": "Feature",
  "properties": {
    "iso:country":"AU",
    "sg:address":"6 Evans St",
    "sg:city":"Hobart",
    "sg:classifiers":[
        {
            "category":"Freight",
            "type":"Transportation"
        }
    ],
    "sg:phone":"+61 3 6231 1618",
    "sg:postcode":"7000",
    "sg:province":"TAS",
    "sg:tags":[
        "transport",
        "refrigerated"
    ],
    "wof:name":"Edwards Transport",
    "wof:placetype":"venue"
},
  "geometry": {"coordinates":[147.33401489299999,-42.8799171448],"type":"Point"}
}