{
  "type": "Feature",
  "properties": {
    "iso:country":"AU",
    "sg:address":"171 Gilmore Rd",
    "sg:city":"Queanbeyan",
    "sg:classifiers":[
        {
            "category":"Autos & Motor Vehicles",
            "subcategory":"Auto Supplies",
            "type":"Retail Goods"
        }
    ],
    "sg:phone":"+61 2 6299 3131",
    "sg:postcode":"2620",
    "sg:province":"ACT",
    "sg:tags":[
        "part",
        "cycles",
        "accessory"
    ],
    "wof:name":"Capital Harley-Davidson",
    "wof:placetype":"venue"
},
  "geometry": {"coordinates":[149.206939697,-35.3502082825],"type":"Point"}
}