{
  "type": "Feature",
  "properties": {
    "addr:full":"18 Glendale Crt Kilsyth VIC 3137",
    "addr:housenumber":"18",
    "addr:postcode":"3137",
    "addr:street":"Glendale Crt",
    "iso:country":"AU",
    "sg:address":"18 Glendale Crt",
    "sg:city":"Kilsyth",
    "sg:classifiers":[
        {
            "category":"Retail",
            "subcategory":"Driving School",
            "type":"Services"
        }
    ],
    "sg:phone":"+61 3 9723 2150",
    "sg:postcode":"3137",
    "sg:province":"VIC",
    "wof:name":"Yarra Valley Driver Education",
    "wof:placetype":"venue"
},
  "geometry": {"coordinates":[145.31869506800001,-37.8059234619],"type":"Point"}
}