{
  "type": "Feature",
  "properties": {
    "iso:country":"AU",
    "sg:address":"PO Box 1079",
    "sg:city":"Flagstaff Hill",
    "sg:classifiers":[
        {
            "category":"Professional",
            "subcategory":"Management & Consulting",
            "type":"Services"
        }
    ],
    "sg:phone":"+61 8 8270 6236",
    "sg:postcode":"5159",
    "sg:province":"SA",
    "sg:tags":[
        "consultant"
    ],
    "wof:name":"Inspired Business Consulting & Personal Development",
    "wof:placetype":"venue"
},
  "geometry": {"coordinates":[138.589569092,-35.0505714417],"type":"Point"}
}