{
  "type": "Feature",
  "properties": {
    "addr:full":"927 South Rd Clarence Gardens SA 5039",
    "addr:housenumber":"927",
    "addr:postcode":"5039",
    "addr:street":"South Rd",
    "iso:country":"AU",
    "sg:address":"927 South Rd",
    "sg:city":"Clarence Gardens",
    "sg:classifiers":[
        {
            "category":"Home & Garden",
            "subcategory":"Hardware",
            "type":"Retail Goods"
        }
    ],
    "sg:phone":"+61 8 8351 0411",
    "sg:postcode":"5039",
    "sg:province":"SA",
    "sg:tags":[
        "plumber",
        "supply"
    ],
    "wof:name":"Tradelink Plumbing Centres",
    "wof:placetype":"venue"
},
  "geometry": {"coordinates":[138.57388305699999,-34.9767913818],"type":"Point"}
}