{
  "type": "Feature",
  "properties": {
    "addr:full":"Suite 1 53-54 Mountain Gate Shopping Centre Ferntree Gully VIC 3156",
    "addr:housenumber":"53-54",
    "addr:postcode":"3156",
    "addr:street":"Mountain",
    "iso:country":"AU",
    "sg:address":"Suite 1 53-54 Mountain Gate Shopping Centre",
    "sg:city":"Ferntree Gully",
    "sg:classifiers":[
        {
            "category":"Real Estate",
            "subcategory":"Surveying",
            "type":"Services"
        }
    ],
    "sg:phone":"+61 3 9756 0570",
    "sg:postcode":"3156",
    "sg:province":"VIC",
    "sg:tags":[
        "surveyor",
        "land"
    ],
    "wof:name":"DB Guiney & Associates",
    "wof:placetype":"venue"
},
  "geometry": {"coordinates":[145.27479553200001,-37.8894691467],"type":"Point"}
}