{
  "type": "Feature",
  "properties": {
    "addr:full":"7 Metcalfe St Wallsend NSW 2287",
    "addr:housenumber":"7",
    "addr:postcode":"2287",
    "addr:street":"Metcalfe St",
    "iso:country":"AU",
    "sg:address":"7 Metcalfe St",
    "sg:city":"Wallsend",
    "sg:classifiers":[
        {
            "category":"Health Services",
            "subcategory":"Chiropractor",
            "type":"Services"
        }
    ],
    "sg:phone":"+61 2 4955 9122",
    "sg:postcode":"2287",
    "sg:province":"NSW",
    "wof:name":"Nadalin R",
    "wof:placetype":"venue"
},
  "geometry": {"coordinates":[151.6693573,-32.9037284851],"type":"Point"}
}