{
  "type": "Feature",
  "properties": {
    "iso:country":"AU",
    "sg:address":"38 Woodburn St",
    "sg:city":"Evans Head",
    "sg:classifiers":[
        {
            "category":"Travel",
            "subcategory":"Hotels & Motels",
            "type":"Entertainment"
        }
    ],
    "sg:phone":"+61 2 6682 4318",
    "sg:postcode":"2473",
    "sg:province":"NSW",
    "wof:name":"Evans Head Pacific Motor Inn",
    "wof:placetype":"venue"
},
  "geometry": {"coordinates":[153.430221558,-29.1169872284],"type":"Point"}
}