{
  "type": "Feature",
  "properties": {
    "addr:full":"43 Princes Hwy West Wollongong NSW 2500",
    "addr:housenumber":"43",
    "addr:postcode":"2500",
    "addr:street":"Princes Hwy West",
    "iso:country":"AU",
    "sg:address":"43 Princes Hwy",
    "sg:city":"West Wollongong",
    "sg:classifiers":[
        {
            "category":"Shopping",
            "subcategory":"Pets & Pet Supplies",
            "type":"Retail Goods"
        }
    ],
    "sg:phone":"+61 1300 655 896",
    "sg:postcode":"2500",
    "sg:province":"NSW",
    "sg:tags":[
        "food"
    ],
    "wof:name":"Petbarn Pty Ltd",
    "wof:placetype":"venue"
},
  "geometry": {"coordinates":[150.86999499999999,-34.426895],"type":"Point"}
}