{
  "type": "Feature",
  "properties": {
    "iso:country":"AU",
    "sg:address":"97 Scarborough Beach Rd",
    "sg:city":"Mt Hawthorn",
    "sg:classifiers":[
        {
            "category":"Health Services",
            "subcategory":"Health Practitioner",
            "type":"Services"
        }
    ],
    "sg:phone":"+61 412 405 801",
    "sg:postcode":"6016",
    "sg:province":"WA",
    "sg:tags":[
        "bowen",
        "therapy"
    ],
    "wof:name":"Anne Clark",
    "wof:placetype":"venue"
},
  "geometry": {"coordinates":[115.844299316,-31.9235210419],"type":"Point"}
}