{
  "type": "Feature",
  "properties": {
    "iso:country":"AU",
    "sg:address":"472- 480 Riversdale Rd",
    "sg:city":"Camberwell",
    "sg:classifiers":[
        {
            "category":"Retail",
            "subcategory":"Auto Repair",
            "type":"Services"
        }
    ],
    "sg:phone":"+61 3 9882 3000",
    "sg:postcode":"3124",
    "sg:province":"VIC",
    "sg:tags":[
        "repairer",
        "motor",
        "engineer"
    ],
    "wof:name":"Camberwell Honda",
    "wof:placetype":"venue"
},
  "geometry": {"coordinates":[145.05633544899999,-37.8314094543],"type":"Point"}
}