{
  "type": "Feature",
  "properties": {
    "addr:full":"Forster Shopping Village Breese Pde Forster NSW 2428",
    "addr:postcode":"2428",
    "addr:street":"Breese Pde",
    "iso:country":"AU",
    "sg:address":"Forster Shopping Village Breese Pde",
    "sg:city":"Forster",
    "sg:classifiers":[
        {
            "category":"Professional",
            "subcategory":"Accounting & Tax Preparation",
            "type":"Services"
        }
    ],
    "sg:phone":"+61 2 6554 5601",
    "sg:postcode":"2428",
    "sg:province":"NSW",
    "sg:tags":[
        "consultant",
        "taxation"
    ],
    "wof:name":"Block H & R",
    "wof:placetype":"venue"
},
  "geometry": {"coordinates":[152.52041600000001,-32.200291],"type":"Point"}
}