{
  "type": "Feature",
  "properties": {
    "addr:full":"23 Santalum St Kambalda West WA 6444",
    "addr:housenumber":"23",
    "addr:postcode":"6444",
    "addr:street":"Santalum St",
    "iso:country":"AU",
    "sg:address":"23 Santalum St",
    "sg:city":"Kambalda West",
    "sg:classifiers":[
        {
            "category":"Professional",
            "type":"Services"
        }
    ],
    "sg:phone":"+61 8 9027 1867",
    "sg:postcode":"6444",
    "sg:province":"WA",
    "sg:tags":[
        "transport"
    ],
    "wof:name":"Roxys Courier",
    "wof:placetype":"venue"
},
  "geometry": {"coordinates":[121.610717773,-31.2098007202],"type":"Point"}
}