{
  "type": "Feature",
  "properties": {
    "addr:full":"Slopes Rd North Richmond NSW 2754",
    "addr:postcode":"2754",
    "addr:street":"Slopes Rd",
    "iso:country":"AU",
    "sg:address":"Slopes Rd",
    "sg:city":"North Richmond",
    "sg:classifiers":[
        {
            "category":"Home & Garden",
            "subcategory":"Building Materials",
            "type":"Retail Goods"
        }
    ],
    "sg:phone":"+61 2 4573 0717",
    "sg:postcode":"2754",
    "sg:province":"NSW",
    "sg:tags":[
        "lawn",
        "cutting",
        "maintenance"
    ],
    "wof:name":"Barj Mowing & Property Maintenance",
    "wof:placetype":"venue"
},
  "geometry": {"coordinates":[150.70835876500001,-33.5524864197],"type":"Point"}
}