{
  "type": "Feature",
  "properties": {
    "addr:full":"3 Parker St Pascoe Vale VIC 3044",
    "addr:housenumber":"3",
    "addr:postcode":"3044",
    "addr:street":"Parker St",
    "iso:country":"AU",
    "sg:address":"3 Parker St",
    "sg:city":"Pascoe Vale",
    "sg:classifiers":[
        {
            "category":"Banks & Credit Unions",
            "subcategory":"Bank",
            "type":"Services"
        }
    ],
    "sg:phone":"+61 3 9374 2472",
    "sg:postcode":"3044",
    "sg:province":"VIC",
    "sg:tags":[
        "broker",
        "mortgage"
    ],
    "wof:name":"Smartline",
    "wof:placetype":"venue"
},
  "geometry": {"coordinates":[144.92750549300001,-37.7304611206],"type":"Point"}
}