{
  "type": "Feature",
  "properties": {
    "iso:country":"AU",
    "sg:address":"916 Mt Dandenong Rd",
    "sg:city":"Montrose",
    "sg:classifiers":[
        {
            "category":"Food & Beverages",
            "subcategory":"Liquor & Beverages",
            "type":"Retail Goods"
        }
    ],
    "sg:phone":"+61 3 9728 4744",
    "sg:postcode":"3765",
    "sg:province":"VIC",
    "sg:tags":[
        "store"
    ],
    "wof:name":"Cheeers Liquor Group",
    "wof:placetype":"venue"
},
  "geometry": {"coordinates":[145.33551025400001,-37.8112068176],"type":"Point"}
}