{
  "type": "Feature",
  "properties": {
    "addr:full":"Shop 6, 926 Mt Dandenong Tourist Rd Montrose VIC 3765",
    "addr:housenumber":"shop 6 926",
    "addr:postcode":"3765",
    "addr:street":"Mt Dandenong Tourist Rd",
    "iso:country":"AU",
    "sg:address":"Shop 6, 926 Mt Dandenong Tourist Rd",
    "sg:city":"Montrose",
    "sg:classifiers":[
        {
            "category":"Real Estate",
            "subcategory":"Real Estate Agent",
            "type":"Services"
        }
    ],
    "sg:phone":"+61 3 9752 5559",
    "sg:postcode":"3765",
    "sg:province":"VIC",
    "wof:name":"Bell Estate",
    "wof:placetype":"venue"
},
  "geometry": {"coordinates":[145.34396362300001,-37.8109321594],"type":"Point"}
}