{
  "type": "Feature",
  "properties": {
    "addr:full":"3 Sir John Overall Drv Helensvale QLD 4212",
    "addr:housenumber":"3",
    "addr:postcode":"4212",
    "addr:street":"Sir John Overall Drv",
    "iso:country":"AU",
    "sg:address":"3 Sir John Overall Drv",
    "sg:city":"Helensvale",
    "sg:classifiers":[
        {
            "category":"Real Estate",
            "subcategory":"Real Estate Services",
            "type":"Services"
        }
    ],
    "sg:phone":"+61 7 5573 7100",
    "sg:postcode":"4212",
    "sg:province":"QLD",
    "sg:tags":[
        "valuer"
    ],
    "wof:name":"Kohler Bird Appraisals",
    "wof:placetype":"venue"
},
  "geometry": {"coordinates":[153.33624267600001,-27.9219512939],"type":"Point"}
}