{
  "type": "Feature",
  "properties": {
    "iso:country":"AU",
    "sg:address":"7 Simon St",
    "sg:city":"Blackburn North",
    "sg:classifiers":[
        {
            "category":"Home & Garden",
            "subcategory":"Building Materials",
            "type":"Retail Goods"
        }
    ],
    "sg:phone":"+61 3 9877 1446",
    "sg:postcode":"3130",
    "sg:province":"VIC",
    "sg:tags":[
        "lawn",
        "cutting",
        "maintenance"
    ],
    "wof:name":"Pegg F",
    "wof:placetype":"venue"
},
  "geometry": {"coordinates":[145.15760803200001,-37.8025245667],"type":"Point"}
}