{
  "type": "Feature",
  "properties": {
    "addr:full":"3 Gordon St Alpha QLD 4724",
    "addr:housenumber":"3",
    "addr:postcode":"4724",
    "addr:street":"Gordon St",
    "iso:country":"AU",
    "sg:address":"3 Gordon St",
    "sg:city":"Alpha",
    "sg:classifiers":[
        {
            "category":"Health Services",
            "subcategory":"Doctor",
            "type":"Services"
        }
    ],
    "sg:phone":"+61 7 4985 1152",
    "sg:postcode":"4724",
    "sg:province":"QLD",
    "sg:tags":[
        "medical",
        "practitioner"
    ],
    "wof:name":"Alpha Private Surgery",
    "wof:placetype":"venue"
},
  "geometry": {"coordinates":[146.63731384299999,-23.6545944214],"type":"Point"}
}