{
  "type": "Feature",
  "properties": {
    "addr:full":"181 Old South Rd Nowra NSW 2541",
    "addr:housenumber":"181",
    "addr:postcode":"2541",
    "addr:street":"Old South Rd",
    "iso:country":"AU",
    "sg:address":"181 Old South Rd",
    "sg:city":"Nowra",
    "sg:classifiers":[
        {
            "category":"Professional",
            "subcategory":"Art Services",
            "type":"Services"
        }
    ],
    "sg:phone":"+61 2 4423 0525",
    "sg:postcode":"2541",
    "sg:province":"NSW",
    "sg:tags":[
        "decorator",
        "painter"
    ],
    "wof:name":"Wayne Mc Kee Painting and Decorating",
    "wof:placetype":"venue"
},
  "geometry": {"coordinates":[150.59387207,-34.8777999878],"type":"Point"}
}