{
  "type": "Feature",
  "properties": {
    "iso:country":"AU",
    "sg:address":"22- 28 Phoenix St",
    "sg:city":"Brunswick",
    "sg:classifiers":[
        {
            "category":"Organizations",
            "subcategory":"Community Association",
            "type":"Services"
        }
    ],
    "sg:phone":"+61 3 9380 9214",
    "sg:postcode":"3056",
    "sg:province":"VIC",
    "sg:tags":[
        "cheese",
        "product"
    ],
    "wof:name":"Delphic Wholesalers (Aust) Pty Ltd",
    "wof:placetype":"venue"
},
  "geometry": {"coordinates":[144.95797729500001,-37.7697753906],"type":"Point"}
}