{
  "type": "Feature",
  "properties": {
    "addr:full":"Fy 2/ 2 Elata Drv Tullamarine VIC 3043",
    "addr:housenumber":"2 / 2",
    "addr:postcode":"3043",
    "addr:street":"Fy;Elata Drv",
    "iso:country":"AU",
    "sg:address":"Fy 2/ 2 Elata Drv",
    "sg:city":"Tullamarine",
    "sg:classifiers":[
        {
            "category":"Home & Garden",
            "subcategory":"Building Materials",
            "type":"Retail Goods"
        }
    ],
    "sg:phone":"+61 3 8336 1010",
    "sg:postcode":"3043",
    "sg:province":"VIC",
    "sg:tags":[
        "decorative",
        "coating"
    ],
    "wof:name":"Unique Coatings Solutions",
    "wof:placetype":"venue"
},
  "geometry": {"coordinates":[144.86065673799999,-37.7140884399],"type":"Point"}
}