{
  "type": "Feature",
  "properties": {
    "addr:full":"U4/ 20 Sundercombe St Osborne Park WA 6017",
    "addr:postcode":"6017",
    "addr:street":"U4 / 20 Sundercombe St",
    "iso:country":"AU",
    "sg:address":"U4/ 20 Sundercombe St",
    "sg:city":"Osborne Park",
    "sg:classifiers":[
        {
            "category":"Home & Garden",
            "subcategory":"Carpets & Floor Coverings",
            "type":"Retail Goods"
        }
    ],
    "sg:phone":"+61 8 9242 8560",
    "sg:postcode":"6017",
    "sg:province":"WA",
    "sg:tags":[
        "flooring",
        "parquet"
    ],
    "wof:name":"Quality Floors 2 Go",
    "wof:placetype":"venue"
},
  "geometry": {"coordinates":[115.81288146999999,-31.9036808014],"type":"Point"}
}