{
  "type": "Feature",
  "properties": {
    "addr:full":"26 Garema Pl Canberra City ACT 2601",
    "addr:housenumber":"26",
    "addr:postcode":"2601",
    "addr:street":"Garema Pl",
    "iso:country":"AU",
    "sg:address":"26 Garema Pl",
    "sg:city":"Canberra City",
    "sg:classifiers":[
        {
            "category":"Shopping",
            "subcategory":"Shoes",
            "type":"Retail Goods"
        }
    ],
    "sg:phone":"+61 2 6247 9104",
    "sg:postcode":"2601",
    "sg:province":"ACT",
    "sg:tags":[
        "footwear"
    ],
    "wof:name":"Frawleys Comfort Centre",
    "wof:placetype":"venue"
},
  "geometry": {"coordinates":[149.13218689000001,-35.2785301208],"type":"Point"}
}