{
  "type": "Feature",
  "properties": {
    "iso:country":"AU",
    "sg:address":"22 Lefroy Rd",
    "sg:city":"Bull Creek",
    "sg:classifiers":[
        {
            "category":"Social Services",
            "subcategory":"Adult Care",
            "type":"Services"
        }
    ],
    "sg:phone":"+61 8 9310 1877",
    "sg:postcode":"6149",
    "sg:province":"WA",
    "sg:tags":[
        "aged"
    ],
    "wof:name":"Lefroy Day Club",
    "wof:placetype":"venue"
},
  "geometry": {"coordinates":[115.870461,-32.053852],"type":"Point"}
}