{
  "type": "Feature",
  "properties": {
    "addr:full":"5095 Huon Hwy Geeveston TAS 7116",
    "addr:housenumber":"5095",
    "addr:postcode":"7116",
    "addr:street":"Huon Hwy",
    "iso:country":"AU",
    "sg:address":"5095 Huon Hwy",
    "sg:city":"Geeveston",
    "sg:classifiers":[
        {
            "category":"Professional",
            "subcategory":"Accounting & Tax Preparation",
            "type":"Services"
        }
    ],
    "sg:phone":"+61 3 6297 1885",
    "sg:postcode":"7116",
    "sg:province":"TAS",
    "sg:tags":[
        "bookkeeping"
    ],
    "wof:name":"MW Bookkeeping Services",
    "wof:placetype":"venue"
},
  "geometry": {"coordinates":[146.93235778799999,-43.1857757568],"type":"Point"}
}