{
  "type": "Feature",
  "properties": {
    "addr:full":"U4/ 7 Leichhardt St Waverley NSW 2024",
    "addr:housenumber":"7",
    "addr:postcode":"2024",
    "addr:street":"U4 /;Leichhardt St",
    "iso:country":"AU",
    "sg:address":"U4/ 7 Leichhardt St",
    "sg:city":"Waverley",
    "sg:classifiers":[
        {
            "category":"Wholesale",
            "subcategory":"Tobacco Products",
            "type":"Manufacturing & Wholesale Goods"
        }
    ],
    "sg:phone":"+61 2 9387 4656",
    "sg:postcode":"2024",
    "sg:province":"NSW",
    "sg:tags":[
        "environmental"
    ],
    "wof:name":"Energess",
    "wof:placetype":"venue"
},
  "geometry": {"coordinates":[151.25689697300001,-33.904460907],"type":"Point"}
}