{
  "type": "Feature",
  "properties": {
    "addr:full":"51 Wallendoon St Cootamundra NSW 2590",
    "addr:housenumber":"51",
    "addr:postcode":"2590",
    "addr:street":"Wallendoon St",
    "iso:country":"AU",
    "sg:address":"51 Wallendoon St",
    "sg:city":"Cootamundra",
    "sg:classifiers":[
        {
            "category":"Retail",
            "subcategory":"Auto Repair",
            "type":"Services"
        }
    ],
    "sg:phone":"+61 2 6942 3057",
    "sg:postcode":"2590",
    "sg:province":"NSW",
    "sg:tags":[
        "repairer",
        "motor",
        "engineer"
    ],
    "wof:name":"S M Auto Repairs",
    "wof:placetype":"venue"
},
  "geometry": {"coordinates":[148.02786254899999,-34.6410598755],"type":"Point"}
}