{
  "type": "Feature",
  "properties": {
    "addr:full":"26 Second St Orroroo SA 5431",
    "addr:housenumber":"26",
    "addr:postcode":"5431",
    "addr:street":"Second St",
    "iso:country":"AU",
    "sg:address":"26 Second St",
    "sg:city":"Orroroo",
    "sg:classifiers":[
        {
            "category":"Military Area",
            "subcategory":"Air Force Base",
            "type":"Public Place"
        }
    ],
    "sg:phone":"+61 8 8658 1206",
    "sg:postcode":"5431",
    "sg:province":"SA",
    "sg:tags":[
        "windmill"
    ],
    "wof:name":"Northern Windmills & Agencies",
    "wof:placetype":"venue"
},
  "geometry": {"coordinates":[138.61346435600001,-32.7342758179],"type":"Point"}
}