{
  "type": "Feature",
  "properties": {
    "addr:full":"92- 98 Sydenham Rd Marrickville NSW 2204",
    "addr:housenumber":"98",
    "addr:postcode":"2204",
    "addr:street":"Sydenham Rd",
    "iso:country":"AU",
    "sg:address":"92- 98 Sydenham Rd",
    "sg:city":"Marrickville",
    "sg:classifiers":[
        {
            "category":"Farming",
            "subcategory":"Dairy Farm",
            "type":"Manufacturing & Wholesale Goods"
        }
    ],
    "sg:phone":"+61 2 9557 7222",
    "sg:postcode":"2204",
    "sg:province":"NSW",
    "sg:tags":[
        "wholesaler",
        "product",
        "mfrs"
    ],
    "wof:name":"Evia Yoghurt",
    "wof:placetype":"venue"
},
  "geometry": {"coordinates":[151.162689,-33.910137],"type":"Point"}
}