{
  "type": "Feature",
  "properties": {
    "addr:full":"5 Rose St Croydon Park NSW 2133",
    "addr:housenumber":"5",
    "addr:postcode":"2133",
    "addr:street":"Rose St",
    "iso:country":"AU",
    "sg:address":"5 Rose St",
    "sg:city":"Croydon Park",
    "sg:classifiers":[
        {
            "category":"Professional",
            "subcategory":"Business Services",
            "type":"Services"
        }
    ],
    "sg:phone":"+61 2 9745 3031",
    "sg:postcode":"2133",
    "sg:province":"NSW",
    "sg:tags":[
        "drafting"
    ],
    "wof:name":"Blue Mist Designs",
    "wof:placetype":"venue"
},
  "geometry": {"coordinates":[151.102172852,-33.8927116394],"type":"Point"}
}