{
  "type": "Feature",
  "properties": {
    "addr:full":"9 Glenview Crt Underwood QLD 4119",
    "addr:housenumber":"9",
    "addr:postcode":"4119",
    "addr:street":"Glenview Crt",
    "iso:country":"AU",
    "sg:address":"9 Glenview Crt",
    "sg:city":"Underwood",
    "sg:classifiers":[
        {
            "category":"Building & Trades",
            "subcategory":"Construction",
            "type":"Services"
        }
    ],
    "sg:phone":"+61 7 3219 0477",
    "sg:postcode":"4119",
    "sg:province":"QLD",
    "sg:tags":[
        "joiner",
        "carpenter"
    ],
    "wof:name":"Finn Carpenter & Building Service",
    "wof:placetype":"venue"
},
  "geometry": {"coordinates":[153.111526489,-27.6140594482],"type":"Point"}
}