{
  "type": "Feature",
  "properties": {
    "iso:country":"AU",
    "sg:address":"386 Kensington Rd",
    "sg:city":"Erindale",
    "sg:classifiers":[
        {
            "category":"Health Services",
            "subcategory":"Doctor",
            "type":"Services"
        }
    ],
    "sg:phone":"+61 8 8431 2077",
    "sg:postcode":"5066",
    "sg:province":"SA",
    "sg:tags":[
        "medical",
        "practitioner"
    ],
    "wof:name":"Ramsey Elizabeth J",
    "wof:placetype":"venue"
},
  "geometry": {"coordinates":[138.66531372099999,-34.9258460999],"type":"Point"}
}