{
  "type": "Feature",
  "properties": {
    "addr:full":"2 King St Waterford West QLD 4133",
    "addr:housenumber":"2",
    "addr:postcode":"4133",
    "addr:street":"King St",
    "iso:country":"AU",
    "sg:address":"2 King St",
    "sg:city":"Waterford West",
    "sg:classifiers":[
        {
            "category":"Utilities",
            "subcategory":"Water",
            "type":"Services"
        }
    ],
    "sg:phone":"+61 408 758 940",
    "sg:postcode":"4133",
    "sg:province":"QLD",
    "sg:tags":[
        "cartage"
    ],
    "wof:name":"K J & D J Schmidt",
    "wof:placetype":"venue"
},
  "geometry": {"coordinates":[153.13682556099999,-27.6949462891],"type":"Point"}
}