{
  "type": "Feature",
  "properties": {
    "iso:country":"AU",
    "sg:address":"18 Bergin Creek Rd",
    "sg:city":"Bunya",
    "sg:classifiers":[
        {
            "category":"Real Estate",
            "subcategory":"Surveying",
            "type":"Services"
        }
    ],
    "sg:phone":"+61 7 3851 1974",
    "sg:postcode":"4055",
    "sg:province":"QLD",
    "sg:tags":[
        "surveyor",
        "land"
    ],
    "wof:name":"Bruce Hallett Surveys",
    "wof:placetype":"venue"
},
  "geometry": {"coordinates":[152.930175781,-27.3740520477],"type":"Point"}
}