{
  "type": "Feature",
  "properties": {
    "iso:country":"AU",
    "sg:address":"173 The Entrance Rd",
    "sg:city":"Erina",
    "sg:classifiers":[
        {
            "category":"Professional",
            "type":"Services"
        }
    ],
    "sg:phone":"+61 2 4367 7955",
    "sg:postcode":"2250",
    "sg:province":"NSW",
    "sg:tags":[
        "shop",
        "fitting"
    ],
    "wof:name":"Supreme Shower Screens",
    "wof:placetype":"venue"
},
  "geometry": {"coordinates":[151.384689331,-33.4361724854],"type":"Point"}
}