{
  "type": "Feature",
  "properties": {
    "iso:country":"AU",
    "sg:address":"75 Cecil St",
    "sg:city":"South Melbourne",
    "sg:classifiers":[
        {
            "category":"Real Estate",
            "subcategory":"Real Estate Agent",
            "type":"Services"
        }
    ],
    "sg:phone":"+61 3 9690 9422",
    "sg:postcode":"3205",
    "sg:province":"VIC",
    "wof:name":"Richard O'Brien & Associates Pty Ltd",
    "wof:placetype":"venue"
},
  "geometry": {"coordinates":[144.960938,-37.838173],"type":"Point"}
}