{
  "type": "Feature",
  "properties": {
    "iso:country":"AU",
    "sg:address":"PO Box 3009",
    "sg:city":"GMC Morwell",
    "sg:classifiers":[
        {
            "category":"Building & Trades",
            "subcategory":"Construction",
            "type":"Services"
        }
    ],
    "sg:phone":"+61 3 5134 1333",
    "sg:postcode":"3840",
    "sg:province":"VIC",
    "sg:tags":[
        "contractor"
    ],
    "wof:name":"SA & R Tactor",
    "wof:placetype":"venue"
},
  "geometry": {"coordinates":[146.39114379899999,-38.2888298035],"type":"Point"}
}