{
  "type": "Feature",
  "properties": {
    "addr:full":"5a Aldershot Rd Lonsdale SA 5160",
    "addr:housenumber":"5a",
    "addr:postcode":"5160",
    "addr:street":"Aldershot Rd",
    "iso:country":"AU",
    "sg:address":"5a Aldershot Rd",
    "sg:city":"Lonsdale",
    "sg:classifiers":[
        {
            "category":"Shopping",
            "subcategory":"Stationery & Office Supplies",
            "type":"Retail Goods"
        }
    ],
    "sg:phone":"+61 8 8326 5750",
    "sg:postcode":"5160",
    "sg:province":"SA",
    "sg:tags":[
        "equipment",
        "badge",
        "making"
    ],
    "wof:name":"Fleurieu Embroidery",
    "wof:placetype":"venue"
},
  "geometry": {"coordinates":[138.50749206500001,-35.11510849],"type":"Point"}
}