{
  "type": "Feature",
  "properties": {
    "addr:full":"163 Gaffney St Broken Hill NSW 2880",
    "addr:housenumber":"163",
    "addr:postcode":"2880",
    "addr:street":"Gaffney St",
    "iso:country":"AU",
    "sg:address":"163 Gaffney St",
    "sg:city":"Broken Hill",
    "sg:classifiers":[
        {
            "category":"Professional",
            "subcategory":"Art Services",
            "type":"Services"
        }
    ],
    "sg:phone":"+61 8 8087 5177",
    "sg:postcode":"2880",
    "sg:province":"NSW",
    "sg:tags":[
        "decorator",
        "painter"
    ],
    "wof:name":"Vincent R W & Pritchard W T",
    "wof:placetype":"venue"
},
  "geometry": {"coordinates":[141.448974609,-31.9730911255],"type":"Point"}
}