{
  "type": "Feature",
  "properties": {
    "addr:full":"68a Rowells Rd Lockleys SA 5032",
    "addr:housenumber":"68a",
    "addr:postcode":"5032",
    "addr:street":"Rowells Rd",
    "iso:country":"AU",
    "sg:address":"68a Rowells Rd",
    "sg:city":"Lockleys",
    "sg:classifiers":[
        {
            "category":"Retail",
            "subcategory":"Auto Repair",
            "type":"Services"
        }
    ],
    "sg:phone":"+61 8 8443 3135",
    "sg:postcode":"5032",
    "sg:province":"SA",
    "sg:tags":[
        "beater",
        "painter",
        "panel"
    ],
    "wof:name":"Lockleys Crash Repairs",
    "wof:placetype":"venue"
},
  "geometry": {"coordinates":[138.53511047399999,-34.9191207886],"type":"Point"}
}