{
  "type": "Feature",
  "properties": {
    "addr:full":"Shop 202, Carlingford Shopping Centre, Cnr Pennant Carlingford NSW 2118",
    "addr:housenumber":"202",
    "addr:postcode":"2118",
    "addr:street":"Cnr Pennant",
    "iso:country":"AU",
    "sg:address":"Shop 202, Carlingford Shopping Centre, Cnr Pennant",
    "sg:city":"Carlingford",
    "sg:classifiers":[
        {
            "category":"Professional",
            "subcategory":"Accounting & Tax Preparation",
            "type":"Services"
        }
    ],
    "sg:phone":"+61 2 9873 4217",
    "sg:postcode":"2118",
    "sg:province":"NSW",
    "sg:tags":[
        "consultant",
        "taxation"
    ],
    "wof:name":"Block H R",
    "wof:placetype":"venue"
},
  "geometry": {"coordinates":[151.05230712900001,-33.7794075012],"type":"Point"}
}