{
  "type": "Feature",
  "properties": {
    "iso:country":"AU",
    "sg:address":"190 Blaxland Rd",
    "sg:city":"Ryde",
    "sg:classifiers":[
        {
            "category":"Personal",
            "subcategory":"Beauty Salon",
            "type":"Services"
        }
    ],
    "sg:phone":"+61 2 9809 7799",
    "sg:postcode":"2112",
    "sg:province":"NSW",
    "wof:name":"Leannes Total Hair & Beauty",
    "wof:placetype":"venue"
},
  "geometry": {"coordinates":[151.10545349099999,-33.8104362488],"type":"Point"}
}