{
  "type": "Feature",
  "properties": {
    "addr:full":"31 Wren St Ascot QLD 4007",
    "addr:housenumber":"31",
    "addr:postcode":"4007",
    "addr:street":"Wren St",
    "iso:country":"AU",
    "sg:address":"31 Wren St",
    "sg:city":"Ascot",
    "sg:classifiers":[
        {
            "category":"Professional",
            "subcategory":"Computer Services",
            "type":"Services"
        }
    ],
    "sg:phone":"+61 417 613 405",
    "sg:postcode":"4007",
    "sg:province":"QLD",
    "sg:tags":[
        "consultant",
        "system"
    ],
    "wof:name":"Jacom Pty Ltd",
    "wof:placetype":"venue"
},
  "geometry": {"coordinates":[153.056915,-27.429941],"type":"Point"}
}