{
  "type": "Feature",
  "properties": {
    "addr:full":"85 Whatley Crs Bayswater WA 6053",
    "addr:housenumber":"85",
    "addr:postcode":"6053",
    "addr:street":"Whatley Crs",
    "iso:country":"AU",
    "sg:address":"85 Whatley Crs",
    "sg:city":"Bayswater",
    "sg:classifiers":[
        {
            "category":"Government",
            "subcategory":"Post Office",
            "type":"Public Place"
        }
    ],
    "sg:phone":"+61 8 9271 1111",
    "sg:postcode":"6053",
    "sg:province":"WA",
    "sg:tags":[
        "postal"
    ],
    "wof:name":"Australia Post",
    "wof:placetype":"venue"
},
  "geometry": {"coordinates":[115.91607666,-31.9139003754],"type":"Point"}
}