{
  "type": "Feature",
  "properties": {
    "iso:country":"AU",
    "sg:address":"Haddon Drv",
    "sg:city":"Ballan",
    "sg:classifiers":[
        {
            "category":"Manufacturing",
            "subcategory":"Buildings",
            "type":"Manufacturing & Wholesale Goods"
        }
    ],
    "sg:phone":"+61 3 5368 1681",
    "sg:postcode":"3342",
    "sg:province":"VIC",
    "sg:tags":[
        "transportable",
        "domestic",
        "relocatable"
    ],
    "wof:name":"Timberset Homes",
    "wof:placetype":"venue"
},
  "geometry": {"coordinates":[144.238586,-37.610512],"type":"Point"}
}