{
  "type": "Feature",
  "properties": {
    "iso:country":"AU",
    "sg:address":"190 Invermay Rd",
    "sg:city":"Invermay",
    "sg:classifiers":[
        {
            "category":"Recreation",
            "subcategory":"Fishing",
            "type":"Entertainment"
        }
    ],
    "sg:phone":"+61 3 6326 5990",
    "sg:postcode":"7248",
    "sg:province":"TAS",
    "sg:tags":[
        "tackle"
    ],
    "wof:name":"Fishing Gear",
    "wof:placetype":"venue"
},
  "geometry": {"coordinates":[147.13255310100001,-41.4106903076],"type":"Point"}
}