{
  "type": "Feature",
  "properties": {
    "addr:full":"127C Fryers St Shepparton VIC 3630",
    "addr:postcode":"3630",
    "addr:street":"Fryers St",
    "iso:country":"AU",
    "sg:address":"127C Fryers St",
    "sg:city":"Shepparton",
    "sg:classifiers":[
        {
            "category":"Health Services",
            "subcategory":"Hospital",
            "type":"Services"
        }
    ],
    "sg:phone":"+61 3 5831 6266",
    "sg:postcode":"3630",
    "sg:province":"VIC",
    "sg:tags":[
        "quarantine"
    ],
    "wof:name":"Australian Quarantine Inspection Service",
    "wof:placetype":"venue"
},
  "geometry": {"coordinates":[145.402999878,-36.3792419434],"type":"Point"}
}