{
  "type": "Feature",
  "properties": {
    "addr:full":"9 Fernwood Ave Ringwood East VIC 3135",
    "addr:housenumber":"9",
    "addr:postcode":"3135",
    "addr:street":"Fernwood Ave",
    "iso:country":"AU",
    "sg:address":"9 Fernwood Ave",
    "sg:city":"Ringwood East",
    "sg:classifiers":[
        {
            "category":"Building & Trades",
            "subcategory":"Construction",
            "type":"Services"
        }
    ],
    "sg:phone":"+61 3 9720 2040",
    "sg:postcode":"3135",
    "sg:province":"VIC",
    "sg:tags":[
        "renovation",
        "alterations",
        "extension",
        "contractor"
    ],
    "wof:name":"Matan Constructions",
    "wof:placetype":"venue"
},
  "geometry": {"coordinates":[145.256317139,-37.825252533],"type":"Point"}
}