{
  "type": "Feature",
  "properties": {
    "iso:country":"AU",
    "sg:address":"16 Allies Rd",
    "sg:city":"Barden Ridge",
    "sg:classifiers":[
        {
            "category":"Education",
            "subcategory":"School",
            "type":"Public Place"
        }
    ],
    "sg:phone":"+61 2 8525 5111",
    "sg:postcode":"2234",
    "sg:province":"NSW",
    "wof:name":"Sutherland Shire Christian School",
    "wof:placetype":"venue"
},
  "geometry": {"coordinates":[151.00755310100001,-34.0361557007],"type":"Point"}
}