{
  "type": "Feature",
  "properties": {
    "addr:full":"Factory 5 /4 Patrick Court, Seaford VIC 3198",
    "addr:housenumber":"/ 4",
    "addr:postcode":"3198",
    "addr:street":"Patrick Court",
    "iso:country":"AU",
    "sg:address":"Factory 5",
    "sg:city":"/4 Patrick Court, Seaford",
    "sg:classifiers":[
        {
            "category":"Utilities",
            "type":"Services"
        }
    ],
    "sg:phone":"+61 3 9786 8346",
    "sg:postcode":"3198",
    "sg:province":"VIC",
    "sg:tags":[
        "equipment",
        "towing"
    ],
    "wof:name":"Peninsula Towbars",
    "wof:placetype":"venue"
},
  "geometry": {"coordinates":[145.135253906,-38.1180801392],"type":"Point"}
}