{
  "type": "Feature",
  "properties": {
    "addr:full":"Suite 4 & 5/ 673 Boronia Rd Wantirna VIC 3152",
    "addr:housenumber":"& 5 / 673",
    "addr:postcode":"3152",
    "addr:street":"Boronia Rd",
    "iso:country":"AU",
    "sg:address":"Suite 4 & 5/ 673 Boronia Rd",
    "sg:city":"Wantirna",
    "sg:classifiers":[
        {
            "category":"Wholesale",
            "subcategory":"Machinery & Supplies",
            "type":"Manufacturing & Wholesale Goods"
        }
    ],
    "sg:phone":"+61 3 9800 4677",
    "sg:postcode":"3152",
    "sg:province":"VIC",
    "sg:tags":[
        "instrument"
    ],
    "sg:website":"http://www.testo.com.au",
    "wof:name":"Testo Pty Ltd",
    "wof:placetype":"venue"
},
  "geometry": {"coordinates":[145.228683472,-37.8476905823],"type":"Point"}
}