{
  "type": "Feature",
  "properties": {
    "addr:full":"625 Boundary Rd Coopers Plains QLD 4108",
    "addr:housenumber":"625",
    "addr:postcode":"4108",
    "addr:street":"Boundary Rd",
    "iso:country":"AU",
    "sg:address":"625 Boundary Rd",
    "sg:city":"Coopers Plains",
    "sg:classifiers":[
        {
            "category":"Shopping",
            "type":"Retail Goods"
        }
    ],
    "sg:phone":"+61 7 3275 7222",
    "sg:postcode":"4108",
    "sg:province":"QLD",
    "sg:tags":[
        "equipment",
        "safety",
        "accessory"
    ],
    "wof:name":"Blackwood J & Son Ltd",
    "wof:placetype":"venue"
},
  "geometry": {"coordinates":[153.02218627900001,-27.5681629181],"type":"Point"}
}