{
  "type": "Feature",
  "properties": {
    "addr:full":"28 John St Cabramatta NSW 2166",
    "addr:housenumber":"28",
    "addr:postcode":"2166",
    "addr:street":"John St",
    "iso:country":"AU",
    "sg:address":"28 John St",
    "sg:city":"Cabramatta",
    "sg:classifiers":[
        {
            "category":"Banks & Credit Unions",
            "subcategory":"Bank",
            "type":"Services"
        }
    ],
    "sg:phone":"+61 13 20 32",
    "sg:postcode":"2166",
    "sg:province":"NSW",
    "wof:name":"Westpac",
    "wof:placetype":"venue"
},
  "geometry": {"coordinates":[150.93707275400001,-33.8953399658],"type":"Point"}
}