{
  "type": "Feature",
  "properties": {
    "addr:full":"35 Beanland St Jamboree Heights QLD 4074",
    "addr:housenumber":"35",
    "addr:postcode":"4074",
    "addr:street":"Beanland St",
    "iso:country":"AU",
    "sg:address":"35 Beanland St",
    "sg:city":"Jamboree Heights",
    "sg:classifiers":[
        {
            "category":"Education",
            "subcategory":"School",
            "type":"Public Place"
        }
    ],
    "sg:phone":"+61 7 3725 5646",
    "sg:postcode":"4074",
    "sg:province":"QLD",
    "sg:tags":[
        "state",
        "except",
        "nsw"
    ],
    "wof:name":"Jamboree Heights Preschool",
    "wof:placetype":"venue"
},
  "geometry": {"coordinates":[152.92897033700001,-27.5548286438],"type":"Point"}
}