{
  "type": "Feature",
  "properties": {
    "iso:country":"AU",
    "sg:address":"95 Aquarium Ave",
    "sg:city":"Hemmant",
    "sg:classifiers":[
        {
            "category":"Train Station",
            "subcategory":"Rail",
            "type":"Transportation"
        }
    ],
    "sg:phone":"+61 7 3390 8922",
    "sg:postcode":"4174",
    "sg:province":"QLD",
    "sg:tags":[
        "marine",
        "engineer"
    ],
    "wof:name":"Propellor Nozzle Fabrication Pty Ltd",
    "wof:placetype":"venue"
},
  "geometry": {"coordinates":[153.12623596200001,-27.4424858093],"type":"Point"}
}