{
  "type": "Feature",
  "properties": {
    "iso:country":"AU",
    "sg:address":"Cnr Holberton & Hill Sts",
    "sg:city":"Toowoomba",
    "sg:classifiers":[
        {
            "category":"Shopping",
            "subcategory":"Antiques",
            "type":"Retail Goods"
        }
    ],
    "sg:phone":"+61 7 4633 3676",
    "sg:postcode":"4350",
    "sg:province":"QLD",
    "wof:name":"Hollyhock Antiques",
    "wof:placetype":"venue"
},
  "geometry": {"coordinates":[151.932343,-27.562037],"type":"Point"}
}