{
  "type": "Feature",
  "properties": {
    "addr:full":"5 Dove St Bowen QLD 4805",
    "addr:housenumber":"5",
    "addr:postcode":"4805",
    "addr:street":"Dove St",
    "iso:country":"AU",
    "sg:address":"5 Dove St",
    "sg:city":"Bowen",
    "sg:classifiers":[
        {
            "category":"Building & Trades",
            "subcategory":"Cleaning & Sanitation",
            "type":"Services"
        }
    ],
    "sg:phone":"+61 7 4786 2497",
    "sg:postcode":"4805",
    "sg:province":"QLD",
    "sg:tags":[
        "industrial",
        "commercial",
        "contractor"
    ],
    "wof:name":"Bowen Maxi Clean",
    "wof:placetype":"venue"
},
  "geometry": {"coordinates":[148.229644775,-20.0054607391],"type":"Point"}
}