{
  "type": "Feature",
  "properties": {
    "addr:full":"14 Tomakin Rd Mogo NSW 2536",
    "addr:housenumber":"14",
    "addr:postcode":"2536",
    "addr:street":"Tomakin Rd",
    "iso:country":"AU",
    "sg:address":"14 Tomakin Rd",
    "sg:city":"Mogo",
    "sg:classifiers":[
        {
            "category":"Manufacturing",
            "subcategory":"Furniture",
            "type":"Manufacturing & Wholesale Goods"
        }
    ],
    "sg:phone":"+61 2 4474 4075",
    "sg:postcode":"2536",
    "sg:province":"NSW",
    "sg:tags":[
        "builder",
        "designer",
        "custom"
    ],
    "wof:name":"Designs By Daniel",
    "wof:placetype":"venue"
},
  "geometry": {"coordinates":[150.14146423299999,-35.7847518921],"type":"Point"}
}