{
  "type": "Feature",
  "properties": {
    "addr:full":"Springmount Rd Middle Creek QLD 4872",
    "addr:postcode":"4872",
    "addr:street":"Springmount Rd",
    "iso:country":"AU",
    "sg:address":"Springmount Rd",
    "sg:city":"Middle Creek",
    "sg:classifiers":[
        {
            "category":"Farming",
            "subcategory":"Farm",
            "type":"Manufacturing & Wholesale Goods"
        }
    ],
    "sg:phone":"+61 7 4093 4440",
    "sg:postcode":"4872",
    "sg:province":"QLD",
    "sg:tags":[
        "farmer"
    ],
    "wof:name":"De Zen G",
    "wof:placetype":"venue"
},
  "geometry": {"coordinates":[145.29835510300001,-17.1676979065],"type":"Point"}
}