{
  "type": "Feature",
  "properties": {
    "addr:full":"431 Terrigal Drv Erina NSW 2250",
    "addr:housenumber":"431",
    "addr:postcode":"2250",
    "addr:street":"Terrigal Drv",
    "iso:country":"AU",
    "sg:address":"431 Terrigal Drv",
    "sg:city":"Erina",
    "sg:classifiers":[
        {
            "category":"Health Services",
            "subcategory":"Doctor",
            "type":"Services"
        }
    ],
    "sg:phone":"+61 2 4365 4999",
    "sg:postcode":"2250",
    "sg:province":"NSW",
    "sg:tags":[
        "medical",
        "practitioner"
    ],
    "wof:name":"Bardon Elvira Dr",
    "wof:placetype":"venue"
},
  "geometry": {"coordinates":[151.39117431599999,-33.4339179993],"type":"Point"}
}