{
  "type": "Feature",
  "properties": {
    "addr:full":"653 Stud Rd Scoresby VIC 3179",
    "addr:housenumber":"653",
    "addr:postcode":"3179",
    "addr:street":"Stud Rd",
    "iso:country":"AU",
    "sg:address":"653 Stud Rd",
    "sg:city":"Scoresby",
    "sg:classifiers":[
        {
            "category":"Health Services",
            "subcategory":"Dentist",
            "type":"Services"
        }
    ],
    "sg:phone":"+61 3 9759 9066",
    "sg:postcode":"3179",
    "sg:province":"VIC",
    "wof:name":"Mahadevan Krishanti Dr",
    "wof:placetype":"venue"
},
  "geometry": {"coordinates":[145.233352661,-37.8903694153],"type":"Point"}
}