{
  "type": "Feature",
  "properties": {
    "iso:country":"AU",
    "sg:address":"15 Muraban Rd",
    "sg:city":"Dural",
    "sg:classifiers":[
        {
            "category":"Building & Trades",
            "subcategory":"Cleaning & Sanitation",
            "type":"Services"
        }
    ],
    "sg:phone":"+61 2 9651 2190",
    "sg:postcode":"2158",
    "sg:province":"NSW",
    "sg:tags":[
        "wall",
        "brick"
    ],
    "wof:name":"Jetwash Services",
    "wof:placetype":"venue"
},
  "geometry": {"coordinates":[151.05242919899999,-33.6728515625],"type":"Point"}
}