{
  "type": "Feature",
  "properties": {
    "addr:full":"Mater Medical Centre, L2, 200 Pacific Hwy North Sydney NSW 2060",
    "addr:housenumber":"200",
    "addr:postcode":"2060",
    "addr:street":"L2;Pacific Hwy",
    "iso:country":"AU",
    "sg:address":"Mater Medical Centre, L2, 200 Pacific Hwy",
    "sg:city":"North Sydney",
    "sg:classifiers":[
        {
            "category":"Health Services",
            "subcategory":"Doctor",
            "type":"Services"
        }
    ],
    "sg:phone":"+61 2 9957 7780",
    "sg:postcode":"2060",
    "sg:province":"NSW",
    "sg:tags":[
        "medical",
        "practitioner"
    ],
    "wof:name":"Kwok Adrian J Dr",
    "wof:placetype":"venue"
},
  "geometry": {"coordinates":[151.20252990700001,-33.830406189],"type":"Point"}
}