{
  "type": "Feature",
  "properties": {
    "addr:full":"105 Hartley St Bungalow QLD 4870",
    "addr:housenumber":"105",
    "addr:postcode":"4870",
    "addr:street":"Hartley St",
    "iso:country":"AU",
    "sg:address":"105 Hartley St",
    "sg:city":"Bungalow",
    "sg:classifiers":[
        {
            "category":"Freight",
            "type":"Transportation"
        }
    ],
    "sg:phone":"+61 7 4035 4436",
    "sg:postcode":"4870",
    "sg:province":"QLD",
    "sg:tags":[
        "light",
        "carrier"
    ],
    "wof:name":"Star Track Express",
    "wof:placetype":"venue"
},
  "geometry": {"coordinates":[145.757202148,-16.9427833557],"type":"Point"}
}