{
  "type": "Feature",
  "properties": {
    "addr:full":"28 Jellicoe St Hurstville Grove NSW 2220",
    "addr:housenumber":"28",
    "addr:postcode":"2220",
    "addr:street":"Jellicoe St",
    "iso:country":"AU",
    "sg:address":"28 Jellicoe St",
    "sg:city":"Hurstville Grove",
    "sg:classifiers":[
        {
            "category":"Education",
            "subcategory":"Special Training",
            "type":"Public Place"
        }
    ],
    "sg:phone":"+61 416 245 131",
    "sg:postcode":"2220",
    "sg:province":"NSW",
    "sg:tags":[
        "development"
    ],
    "wof:name":"Millennium Training Services",
    "wof:placetype":"venue"
},
  "geometry": {"coordinates":[151.09375,-33.9767570496],"type":"Point"}
}