{
  "type": "Feature",
  "properties": {
    "addr:full":"46 Pritchard St Annandale NSW 2038",
    "addr:housenumber":"46",
    "addr:postcode":"2038",
    "addr:street":"Pritchard St",
    "iso:country":"AU",
    "sg:address":"46 Pritchard St",
    "sg:city":"Annandale",
    "sg:classifiers":[
        {
            "category":"Health Services",
            "subcategory":"Health Practitioner",
            "type":"Services"
        }
    ],
    "sg:phone":"+61 2 9810 7852",
    "sg:postcode":"2038",
    "sg:province":"NSW",
    "sg:tags":[
        "osteopath"
    ],
    "wof:name":"Ward Geoffrey N",
    "wof:placetype":"venue"
},
  "geometry": {"coordinates":[151.17033386200001,-33.8744544983],"type":"Point"}
}