{
  "type": "Feature",
  "properties": {
    "iso:country":"AU",
    "sg:address":"12 Clarke St",
    "sg:city":"Granville",
    "sg:classifiers":[
        {
            "category":"Health Services",
            "subcategory":"Doctor",
            "type":"Services"
        }
    ],
    "sg:phone":"+61 2 9637 1905",
    "sg:postcode":"2142",
    "sg:province":"NSW",
    "sg:tags":[
        "podiatrist"
    ],
    "wof:name":"Bjornsson B E",
    "wof:placetype":"venue"
},
  "geometry": {"coordinates":[151.00294494600001,-33.8361320496],"type":"Point"}
}