{
  "type": "Feature",
  "properties": {
    "addr:full":"U68/ 1a Hopkins St Footscray VIC 3011",
    "addr:postcode":"3011",
    "addr:street":"/ 1A Hopkins St",
    "iso:country":"AU",
    "sg:address":"U68/ 1a Hopkins St",
    "sg:city":"Footscray",
    "sg:classifiers":[
        {
            "category":"Cafe",
            "type":"Food & Drink"
        }
    ],
    "sg:phone":"+61 3 9687 8070",
    "sg:postcode":"3011",
    "sg:province":"VIC",
    "wof:name":"Selam Bar & Cafe",
    "wof:placetype":"venue"
},
  "geometry": {"coordinates":[144.909103394,-37.8009414673],"type":"Point"}
}