{
  "type": "Feature",
  "properties": {
    "addr:full":"Shop 37, 135 Sailors Bay Rd Northbridge NSW 2063",
    "addr:housenumber":"shop 37",
    "addr:postcode":"135;2063",
    "addr:street":"Sailors Bay Rd",
    "iso:country":"AU",
    "sg:address":"Shop 37, 135 Sailors Bay Rd",
    "sg:city":"Northbridge",
    "sg:classifiers":[
        {
            "category":"Retail",
            "subcategory":"Repair Shop",
            "type":"Services"
        }
    ],
    "sg:phone":"+61 2 9967 2888",
    "sg:postcode":"2063",
    "sg:province":"NSW",
    "sg:tags":[
        "restorer",
        "repairer",
        "carpet"
    ],
    "wof:name":"Bijan Exclusive Rugs",
    "wof:placetype":"venue"
},
  "geometry": {"coordinates":[151.210693359,-33.8106880188],"type":"Point"}
}