{
  "type": "Feature",
  "properties": {
    "iso:country":"AU",
    "sg:address":"12 Mclaren Ct",
    "sg:city":"Mildura",
    "sg:classifiers":[
        {
            "category":"Autos & Motor Vehicles",
            "subcategory":"Automobile Sales",
            "type":"Retail Goods"
        }
    ],
    "sg:phone":"+61 3 5025 4538",
    "sg:postcode":"3500",
    "sg:province":"VIC",
    "sg:tags":[
        "car",
        "used"
    ],
    "wof:name":"Northwest Auto Brokers",
    "wof:placetype":"venue"
},
  "geometry": {"coordinates":[142.169754028,-34.1954841614],"type":"Point"}
}