{
  "type": "Feature",
  "properties": {
    "addr:full":"68 Berkshire Rd Sunshine VIC 3020",
    "addr:housenumber":"68",
    "addr:postcode":"3020",
    "addr:street":"Berkshire Rd",
    "iso:country":"AU",
    "sg:address":"68 Berkshire Rd",
    "sg:city":"Sunshine",
    "sg:classifiers":[
        {
            "category":"Retail",
            "subcategory":"Storage",
            "type":"Services"
        }
    ],
    "sg:phone":"+61 3 9544 3444",
    "sg:postcode":"3020",
    "sg:province":"VIC",
    "sg:tags":[
        "shelving",
        "system"
    ],
    "wof:name":"McLeod J.C. Pty Ltd",
    "wof:placetype":"venue"
},
  "geometry": {"coordinates":[144.83944700000001,-37.765095],"type":"Point"}
}