{
  "type": "Feature",
  "properties": {
    "addr:full":"25 Racecourse Rd Donald VIC 3480",
    "addr:housenumber":"25",
    "addr:postcode":"3480",
    "addr:street":"Racecourse Rd",
    "iso:country":"AU",
    "sg:address":"25 Racecourse Rd",
    "sg:city":"Donald",
    "sg:classifiers":[
        {
            "category":"Professional",
            "type":"Services"
        }
    ],
    "sg:phone":"+61 3 5497 2225",
    "sg:postcode":"3480",
    "sg:province":"VIC",
    "sg:tags":[
        "forwarding",
        "agent",
        "transport"
    ],
    "wof:name":"Rev Toy Transport",
    "wof:placetype":"venue"
},
  "geometry": {"coordinates":[142.99290466299999,-36.3663635254],"type":"Point"}
}