{
  "type": "Feature",
  "properties": {
    "iso:country":"AU",
    "sg:address":"U1/ 200 Toongabbie Rd",
    "sg:city":"Girraween",
    "sg:classifiers":[
        {
            "category":"Retail",
            "subcategory":"Auto Repair",
            "type":"Services"
        }
    ],
    "sg:phone":"+61 2 9636 7270",
    "sg:postcode":"2145",
    "sg:province":"NSW",
    "sg:tags":[
        "repairer",
        "motor",
        "engineer"
    ],
    "wof:name":"J & J Automotive Repairs",
    "wof:placetype":"venue"
},
  "geometry": {"coordinates":[150.937057495,-33.8022537231],"type":"Point"}
}