{
  "type": "Feature",
  "properties": {
    "iso:country":"AU",
    "sg:address":"PO Box 457",
    "sg:city":"Castlemaine",
    "sg:classifiers":[
        {
            "category":"Professional",
            "subcategory":"Testing Lab",
            "type":"Services"
        }
    ],
    "sg:phone":"+61 3 5470 6173",
    "sg:postcode":"3450",
    "sg:province":"VIC",
    "sg:tags":[
        "soil",
        "investigation"
    ],
    "wof:name":"Provincial Geotechnical Pty Ltd",
    "wof:placetype":"venue"
},
  "geometry": {"coordinates":[144.216552734,-37.0669288635],"type":"Point"}
}