{
  "type": "Feature",
  "properties": {
    "addr:full":"1/ 22 Railway St Liverpool NSW 2170",
    "addr:housenumber":"/ 22",
    "addr:postcode":"2170",
    "addr:street":"Railway St",
    "iso:country":"AU",
    "sg:address":"1/ 22 Railway St",
    "sg:city":"Liverpool",
    "sg:classifiers":[
        {
            "category":"Personal",
            "subcategory":"Tattoo Parlor",
            "type":"Services"
        }
    ],
    "sg:phone":"+61 2 9602 1115",
    "sg:postcode":"2170",
    "sg:province":"NSW",
    "sg:tags":[
        "tattooing"
    ],
    "wof:name":"Raven Tattoo And Body Piercing Studio",
    "wof:placetype":"venue"
},
  "geometry": {"coordinates":[150.925582886,-33.9243812561],"type":"Point"}
}