{
  "type": "Feature",
  "properties": {
    "iso:country":"AU",
    "sg:address":"Cnr Newell Hwy & Hereford St",
    "sg:city":"Forbes",
    "sg:classifiers":[
        {
            "category":"Manufacturing",
            "subcategory":"Retail Goods",
            "type":"Manufacturing & Wholesale Goods"
        }
    ],
    "sg:phone":"+61 2 6851 1611",
    "sg:postcode":"2871",
    "sg:province":"NSW",
    "sg:tags":[
        "merchant",
        "pump",
        "mfrs"
    ],
    "wof:name":"Midpro Engineering Pty Ltd",
    "wof:placetype":"venue"
},
  "geometry": {"coordinates":[148.011536,-33.380543],"type":"Point"}
}