{
  "type": "Feature",
  "properties": {
    "iso:country":"AU",
    "sg:address":"PO Box 5",
    "sg:city":"Alberton",
    "sg:classifiers":[
        {
            "category":"Building & Trades",
            "subcategory":"Construction",
            "type":"Services"
        }
    ],
    "sg:phone":"+61 3 5182 5607",
    "sg:postcode":"3971",
    "sg:province":"VIC",
    "sg:tags":[
        "monumental",
        "mason"
    ],
    "wof:name":"Casbolt T M & E",
    "wof:placetype":"venue"
},
  "geometry": {"coordinates":[146.665817261,-38.6218986511],"type":"Point"}
}