{
  "type": "Feature",
  "properties": {
    "addr:full":"RMB 470 Kootingal NSW 2352",
    "addr:postcode":"2352",
    "iso:country":"AU",
    "sg:address":"RMB 470",
    "sg:city":"Kootingal",
    "sg:classifiers":[
        {
            "category":"Farming",
            "subcategory":"Farm & Veterinary Services",
            "type":"Manufacturing & Wholesale Goods"
        }
    ],
    "sg:phone":"+61 2 6760 9272",
    "sg:postcode":"2352",
    "sg:province":"NSW",
    "sg:tags":[
        "poultry",
        "processing",
        "supply"
    ],
    "wof:name":"Quast C & L & Son Pty Ltd",
    "wof:placetype":"venue"
},
  "geometry": {"coordinates":[151.04945373499999,-31.0528793335],"type":"Point"}
}