{
  "type": "Feature",
  "properties": {
    "iso:country":"AU",
    "sg:address":"U1/ 71 Market St",
    "sg:city":"Mudgee",
    "sg:classifiers":[
        {
            "category":"Fast Food",
            "type":"Food & Drink"
        }
    ],
    "sg:phone":"+61 2 6372 1617",
    "sg:postcode":"2850",
    "sg:province":"NSW",
    "sg:tags":[
        "away",
        "take"
    ],
    "wof:name":"Fine Foods on Market",
    "wof:placetype":"venue"
},
  "geometry": {"coordinates":[149.575562,-32.587852],"type":"Point"}
}