{
  "type": "Feature",
  "properties": {
    "addr:full":"2 Skipton St Box Hill VIC 3128",
    "addr:housenumber":"2",
    "addr:postcode":"3128",
    "addr:street":"Skipton St",
    "iso:country":"AU",
    "sg:address":"2 Skipton St",
    "sg:city":"Box Hill",
    "sg:classifiers":[
        {
            "category":"Building & Trades",
            "subcategory":"Landscaping Services",
            "type":"Services"
        }
    ],
    "sg:phone":"+61 438 549 092",
    "sg:postcode":"3128",
    "sg:province":"VIC",
    "sg:tags":[
        "designer",
        "landscape",
        "contractor"
    ],
    "wof:name":"Garden Planners Landscaping",
    "wof:placetype":"venue"
},
  "geometry": {"coordinates":[145.13604736299999,-37.8157081604],"type":"Point"}
}