{
  "type": "Feature",
  "properties": {
    "iso:country":"AU",
    "sg:address":"260 Gympie Rd",
    "sg:city":"Strathpine",
    "sg:classifiers":[
        {
            "category":"Travel",
            "subcategory":"Hotels & Motels",
            "type":"Entertainment"
        }
    ],
    "sg:phone":"+61 7 3889 9960",
    "sg:postcode":"4500",
    "sg:province":"QLD",
    "sg:tags":[
        "pub"
    ],
    "wof:name":"Four Mile Creek Hotel",
    "wof:placetype":"venue"
},
  "geometry": {"coordinates":[152.988357544,-27.3021564484],"type":"Point"}
}