{
  "type": "Feature",
  "properties": {
    "iso:country":"AU",
    "sg:address":"13 Richards St",
    "sg:city":"Breadalbane",
    "sg:classifiers":[
        {
            "category":"Freight",
            "type":"Transportation"
        }
    ],
    "sg:phone":"+61 3 6391 0111",
    "sg:postcode":"7258",
    "sg:province":"TAS",
    "sg:tags":[
        "transport",
        "refrigerated"
    ],
    "wof:name":"Statewide Refrigerated Transport",
    "wof:placetype":"venue"
},
  "geometry": {"coordinates":[147.19903564399999,-41.536857605],"type":"Point"}
}