{
  "type": "Feature",
  "properties": {
    "addr:full":"Birdwood Ave South Yarra VIC 3141",
    "addr:postcode":"3141",
    "addr:street":"Birdwood Ave",
    "iso:country":"AU",
    "sg:address":"Birdwood Ave",
    "sg:city":"South Yarra",
    "sg:classifiers":[
        {
            "category":"Communications",
            "subcategory":"News Services",
            "type":"Services"
        }
    ],
    "sg:phone":"+61 3 9654 5528",
    "sg:postcode":"3141",
    "sg:province":"VIC",
    "sg:tags":[
        "information",
        "tourist",
        "attractions"
    ],
    "wof:name":"National Trust Of Australia (Victoria)",
    "wof:placetype":"venue"
},
  "geometry": {"coordinates":[144.99111938499999,-37.8378791809],"type":"Point"}
}