{
  "type": "Feature",
  "properties": {
    "iso:country":"AU",
    "sg:address":"Unit A6/27- 29 Fariola St",
    "sg:city":"Silverwater",
    "sg:classifiers":[
        {
            "category":"Manufacturing",
            "subcategory":"Motor Vehicles & Parts",
            "type":"Manufacturing & Wholesale Goods"
        }
    ],
    "sg:phone":"+61 2 9737 8644",
    "sg:postcode":"2128",
    "sg:province":"NSW",
    "sg:tags":[
        "engine",
        "equipment",
        "diesel"
    ],
    "wof:name":"Engine Australia",
    "wof:placetype":"venue"
},
  "geometry": {"coordinates":[151.05267334000001,-33.8351974487],"type":"Point"}
}