{
  "type": "Feature",
  "properties": {
    "addr:full":"105 Booth St Annandale NSW 2038",
    "addr:housenumber":"105",
    "addr:postcode":"2038",
    "addr:street":"Booth St",
    "iso:country":"AU",
    "sg:address":"105 Booth St",
    "sg:city":"Annandale",
    "sg:classifiers":[
        {
            "category":"Shopping",
            "subcategory":"Baby Store",
            "type":"Retail Goods"
        }
    ],
    "sg:phone":"+61 2 9660 7992",
    "sg:postcode":"2038",
    "sg:province":"NSW",
    "sg:tags":[
        "children's",
        "wear"
    ],
    "wof:name":"Infancy",
    "wof:placetype":"venue"
},
  "geometry": {"coordinates":[151.171585083,-33.8815765381],"type":"Point"}
}