{
  "type": "Feature",
  "properties": {
    "addr:full":"Railway St Penrith NSW 2750",
    "addr:postcode":"2750",
    "addr:street":"Railway St",
    "iso:country":"AU",
    "sg:address":"Railway St",
    "sg:city":"Penrith",
    "sg:classifiers":[
        {
            "category":"Cinema",
            "subcategory":"Movie Theater",
            "type":"Entertainment"
        }
    ],
    "sg:phone":"+61 2 4721 5735",
    "sg:postcode":"2750",
    "sg:province":"NSW",
    "wof:name":"Q Theatre",
    "wof:placetype":"venue"
},
  "geometry": {"coordinates":[150.67149352999999,-33.7450561523],"type":"Point"}
}