{
  "type": "Feature",
  "properties": {
    "iso:country":"AU",
    "sg:address":"376 Manns Rd",
    "sg:city":"Gosford West",
    "sg:classifiers":[
        {
            "category":"Farming",
            "subcategory":"Fish & Marine Products",
            "type":"Manufacturing & Wholesale Goods"
        }
    ],
    "sg:phone":"+61 2 4324 7144",
    "sg:postcode":"2250",
    "sg:province":"NSW",
    "sg:tags":[
        "wire"
    ],
    "wof:name":"Protective Fencing Pty Ltd",
    "wof:placetype":"venue"
},
  "geometry": {"coordinates":[151.31932067899999,-33.4247779846],"type":"Point"}
}