{
  "type": "Feature",
  "properties": {
    "addr:full":"43 Geaneys La Deeragun QLD 4818",
    "addr:housenumber":"43",
    "addr:postcode":"4818",
    "addr:street":"Geaneys La Deeragun",
    "iso:country":"AU",
    "sg:address":"43 Geaneys La",
    "sg:city":"Deeragun",
    "sg:classifiers":[
        {
            "category":"Building & Trades",
            "subcategory":"Equipment Rental",
            "type":"Services"
        }
    ],
    "sg:phone":"+61 7 4751 6722",
    "sg:postcode":"4818",
    "sg:province":"QLD",
    "sg:tags":[
        "supply",
        "catering"
    ],
    "wof:name":"Slush Puppies",
    "wof:placetype":"venue"
},
  "geometry": {"coordinates":[146.667282,-19.248234],"type":"Point"}
}