{
  "type": "Feature",
  "properties": {
    "iso:country":"AU",
    "sg:address":"45 Festival Crs",
    "sg:city":"Keysborough",
    "sg:classifiers":[
        {
            "category":"Building & Trades",
            "subcategory":"Construction",
            "type":"Services"
        }
    ],
    "sg:phone":"+61 3 9798 2313",
    "sg:postcode":"3173",
    "sg:province":"VIC",
    "sg:tags":[
        "polishing",
        "sanding",
        "floor"
    ],
    "wof:name":"Clayton Floor Surfacing",
    "wof:placetype":"venue"
},
  "geometry": {"coordinates":[145.166015625,-38.0063705444],"type":"Point"}
}