{
  "type": "Feature",
  "properties": {
    "addr:full":"Studio 46/ 61 Buckingham St Surry Hills NSW 2010",
    "addr:housenumber":"61",
    "addr:postcode":"2010",
    "addr:street":"Buckingham St",
    "iso:country":"AU",
    "sg:address":"Studio 46/ 61 Buckingham St",
    "sg:city":"Surry Hills",
    "sg:classifiers":[
        {
            "category":"Arts & Performance",
            "subcategory":"Art Gallery",
            "type":"Entertainment"
        }
    ],
    "sg:phone":"+61 2 9699 6610",
    "sg:postcode":"2010",
    "sg:province":"NSW",
    "wof:name":"Under Water Australia",
    "wof:placetype":"venue"
},
  "geometry": {"coordinates":[151.20701599099999,-33.8888053894],"type":"Point"}
}