{
  "type": "Feature",
  "properties": {
    "addr:full":"1 70 Grey St Keiraville NSW 2500",
    "addr:housenumber":"70",
    "addr:postcode":"2500",
    "addr:street":"1;Grey St",
    "iso:country":"AU",
    "sg:address":"1 70 Grey St",
    "sg:city":"Keiraville",
    "sg:classifiers":[
        {
            "category":"Wholesale",
            "subcategory":"Construction Materials",
            "type":"Manufacturing & Wholesale Goods"
        }
    ],
    "sg:phone":"+61 2 4228 6905",
    "sg:postcode":"2500",
    "sg:province":"NSW",
    "sg:tags":[
        "wholesaler",
        "lighting",
        "mfrs",
        "accessory"
    ],
    "wof:name":"Lumos Lighting Pty Ltd",
    "wof:placetype":"venue"
},
  "geometry": {"coordinates":[150.87178,-34.416126],"type":"Point"}
}