{
  "type": "Feature",
  "properties": {
    "addr:full":"8/ 16 Belmore Rd Punchbowl NSW 2196",
    "addr:housenumber":"/ 16",
    "addr:postcode":"2196",
    "addr:street":"Belmore Rd",
    "iso:country":"AU",
    "sg:address":"8/ 16 Belmore Rd",
    "sg:city":"Punchbowl",
    "sg:classifiers":[
        {
            "category":"Professional",
            "subcategory":"Detective & Security Services",
            "type":"Services"
        }
    ],
    "sg:phone":"+61 2 9740 9310",
    "sg:postcode":"2196",
    "sg:province":"NSW",
    "sg:tags":[
        "equipment",
        "window",
        "doors"
    ],
    "wof:name":"D & R Hinton Steel Fabrications Pty Ltd",
    "wof:placetype":"venue"
},
  "geometry": {"coordinates":[151.05607599999999,-33.933273],"type":"Point"}
}