{
  "type": "Feature",
  "properties": {
    "iso:country":"AU",
    "sg:address":"6 Blue Mountain Crs",
    "sg:city":"Warner",
    "sg:classifiers":[
        {
            "category":"Professional",
            "subcategory":"Art Services",
            "type":"Services"
        }
    ],
    "sg:phone":"+61 418 180 993",
    "sg:postcode":"4500",
    "sg:province":"QLD",
    "sg:tags":[
        "decorator",
        "painter"
    ],
    "wof:name":"Bell's Tradesmen Painters",
    "wof:placetype":"venue"
},
  "geometry": {"coordinates":[152.96220398,-27.3281593323],"type":"Point"}
}