{
  "type": "Feature",
  "properties": {
    "addr:full":"Bathers Beach Mews Rd Fremantle WA 6160",
    "addr:postcode":"6160",
    "addr:street":"Mews Rd",
    "iso:country":"AU",
    "sg:address":"Bathers Beach Mews Rd",
    "sg:city":"Fremantle",
    "sg:classifiers":[
        {
            "category":"Shopping",
            "subcategory":"Party Supplies",
            "type":"Retail Goods"
        }
    ],
    "sg:phone":"+61 8 9335 9636",
    "sg:postcode":"6160",
    "sg:province":"WA",
    "sg:tags":[
        "children's"
    ],
    "wof:name":"Kidogo Arthouse",
    "wof:placetype":"venue"
},
  "geometry": {"coordinates":[115.745987,-32.059181],"type":"Point"}
}