{
  "type": "Feature",
  "properties": {
    "addr:full":"51 Pierce Ave Little Mountain QLD 4551",
    "addr:housenumber":"51",
    "addr:postcode":"4551",
    "addr:street":"Pierce Ave",
    "iso:country":"AU",
    "sg:address":"51 Pierce Ave",
    "sg:city":"Little Mountain",
    "sg:classifiers":[
        {
            "category":"Home & Garden",
            "subcategory":"Building Materials",
            "type":"Retail Goods"
        }
    ],
    "sg:phone":"+61 7 5491 5120",
    "sg:postcode":"4551",
    "sg:province":"QLD",
    "sg:tags":[
        "fencing"
    ],
    "wof:name":"Little Mountain Produce",
    "wof:placetype":"venue"
},
  "geometry": {"coordinates":[153.08233642600001,-26.7855606079],"type":"Point"}
}