{
  "type": "Feature",
  "properties": {
    "iso:country":"AU",
    "sg:address":"6 Earl St",
    "sg:city":"Coffs Harbour",
    "sg:classifiers":[
        {
            "category":"Health Services",
            "subcategory":"Medical Lab",
            "type":"Services"
        }
    ],
    "sg:phone":"+61 2 6652 6481",
    "sg:postcode":"2450",
    "sg:province":"NSW",
    "sg:tags":[
        "laboratory",
        "dental"
    ],
    "wof:name":"Wolf Machatch",
    "wof:placetype":"venue"
},
  "geometry": {"coordinates":[153.116547,-30.300819],"type":"Point"}
}