{
  "type": "Feature",
  "properties": {
    "iso:country":"AU",
    "sg:address":"PO Box 509",
    "sg:city":"Altona North",
    "sg:classifiers":[
        {
            "category":"Real Estate",
            "subcategory":"Real Estate Operator",
            "type":"Services"
        }
    ],
    "sg:phone":"+61 409 435 611",
    "sg:postcode":"3025",
    "sg:province":"VIC",
    "sg:tags":[
        "concrete",
        "pumping"
    ],
    "wof:name":"Bayside Metro Concrete Pumping",
    "wof:placetype":"venue"
},
  "geometry": {"coordinates":[144.841583,-37.830509],"type":"Point"}
}