{
  "type": "Feature",
  "properties": {
    "iso:country":"AU",
    "sg:address":"78 Cherry La",
    "sg:city":"Laverton North",
    "sg:classifiers":[
        {
            "category":"Retail",
            "subcategory":"Auto Repair",
            "type":"Services"
        }
    ],
    "sg:phone":"+61 3 9926 9999",
    "sg:postcode":"3026",
    "sg:province":"VIC",
    "sg:tags":[
        "beater",
        "painter",
        "panel"
    ],
    "wof:name":"TDG Autocare Australia",
    "wof:placetype":"venue"
},
  "geometry": {"coordinates":[144.797394,-37.836536],"type":"Point"}
}