{
  "type": "Feature",
  "properties": {
    "addr:full":"29 McNicol Rd Tecoma VIC 3160",
    "addr:housenumber":"29",
    "addr:postcode":"3160",
    "addr:street":"Mcnicol Rd",
    "iso:country":"AU",
    "sg:address":"29 McNicol Rd",
    "sg:city":"Tecoma",
    "sg:classifiers":[
        {
            "category":"Building & Trades",
            "subcategory":"Cleaning & Sanitation",
            "type":"Services"
        }
    ],
    "sg:phone":"+61 3 9752 6543",
    "sg:postcode":"3160",
    "sg:province":"VIC",
    "sg:tags":[
        "sweep",
        "chimney"
    ],
    "wof:name":"Australian Chimney Cleaning",
    "wof:placetype":"venue"
},
  "geometry": {"coordinates":[145.343017578,-37.9109992981],"type":"Point"}
}