{
  "type": "Feature",
  "properties": {
    "addr:full":"38 Hooper St Randwick NSW 2031",
    "addr:housenumber":"38",
    "addr:postcode":"2031",
    "addr:street":"Hooper St",
    "iso:country":"AU",
    "sg:address":"38 Hooper St",
    "sg:city":"Randwick",
    "sg:classifiers":[
        {
            "category":"Building & Trades",
            "subcategory":"Construction",
            "type":"Services"
        }
    ],
    "sg:phone":"+61 2 9398 5074",
    "sg:postcode":"2031",
    "sg:province":"NSW",
    "sg:tags":[
        "contractor"
    ],
    "wof:name":"Parsons John D",
    "wof:placetype":"venue"
},
  "geometry": {"coordinates":[151.250823975,-33.9053649902],"type":"Point"}
}