{
  "type": "Feature",
  "properties": {
    "addr:full":"Fact 4/ 13 Harvest Crt Southport QLD 4215",
    "addr:housenumber":"4 / 13",
    "addr:postcode":"4215",
    "addr:street":"Fact;Harvest Crt",
    "iso:country":"AU",
    "sg:address":"Fact 4/ 13 Harvest Crt",
    "sg:city":"Southport",
    "sg:classifiers":[
        {
            "category":"Autos & Motor Vehicles",
            "subcategory":"Auto Supplies",
            "type":"Retail Goods"
        }
    ],
    "sg:phone":"+61 7 5531 1727",
    "sg:postcode":"4215",
    "sg:province":"QLD",
    "sg:tags":[
        "speedometer"
    ],
    "wof:name":"Action Speedo",
    "wof:placetype":"venue"
},
  "geometry": {"coordinates":[153.41009521500001,-27.9785251617],"type":"Point"}
}