{
  "type": "Feature",
  "properties": {
    "addr:full":"91 Main St Minyip VIC 3392",
    "addr:housenumber":"91",
    "addr:postcode":"3392",
    "addr:street":"Main St",
    "iso:country":"AU",
    "sg:address":"91 Main St",
    "sg:city":"Minyip",
    "sg:classifiers":[
        {
            "category":"Fast Food",
            "type":"Food & Drink"
        }
    ],
    "sg:phone":"+61 3 5385 7493",
    "sg:postcode":"3392",
    "sg:province":"VIC",
    "sg:tags":[
        "away",
        "take"
    ],
    "wof:name":"Minyip Take Away",
    "wof:placetype":"venue"
},
  "geometry": {"coordinates":[142.588425,-36.459042],"type":"Point"}
}