{
  "type": "Feature",
  "properties": {
    "addr:full":"Shop 9 & 10 Merridowns SC Jura St Carrara QLD 4211",
    "addr:housenumber":"shop 9 & 10",
    "addr:postcode":"4211",
    "addr:street":"Merridowns;Jura St",
    "iso:country":"AU",
    "sg:address":"Shop 9 & 10 Merridowns SC Jura St",
    "sg:city":"Carrara",
    "sg:classifiers":[
        {
            "category":"Food & Beverages",
            "subcategory":"Liquor & Beverages",
            "type":"Retail Goods"
        }
    ],
    "sg:phone":"+61 7 5530 7221",
    "sg:postcode":"4211",
    "sg:province":"QLD",
    "sg:tags":[
        "store"
    ],
    "wof:name":"BWS Liquor Stores",
    "wof:placetype":"venue"
},
  "geometry": {"coordinates":[153.38435363799999,-28.0171432495],"type":"Point"}
}