{
  "type": "Feature",
  "properties": {
    "addr:full":"591 Dorset Rd Bayswater VIC 3153",
    "addr:housenumber":"591",
    "addr:postcode":"3153",
    "addr:street":"Dorset Rd",
    "iso:country":"AU",
    "sg:address":"591 Dorset Rd",
    "sg:city":"Bayswater",
    "sg:classifiers":[
        {
            "category":"Autos & Motor Vehicles",
            "subcategory":"Fuel & Gas Station",
            "type":"Retail Goods"
        }
    ],
    "sg:phone":"+61 3 9761 5905",
    "sg:postcode":"3153",
    "sg:province":"VIC",
    "wof:name":"Plus Petrol",
    "wof:placetype":"venue"
},
  "geometry": {"coordinates":[145.28793335,-37.8239097595],"type":"Point"}
}