{
  "type": "Feature",
  "properties": {
    "addr:full":"156 New Town Rd New Town TAS 7008",
    "addr:housenumber":"156",
    "addr:postcode":"7008",
    "addr:street":"New Town Rd",
    "iso:country":"AU",
    "sg:address":"156 New Town Rd",
    "sg:city":"New Town",
    "sg:classifiers":[
        {
            "category":"Banks & Credit Unions",
            "subcategory":"Bank",
            "type":"Services"
        }
    ],
    "sg:phone":"+61 1300 662 424",
    "sg:postcode":"7008",
    "sg:province":"TAS",
    "sg:tags":[
        "equipment",
        "sale",
        "point"
    ],
    "wof:name":"Prosys Office Techonolgies",
    "wof:placetype":"venue"
},
  "geometry": {"coordinates":[147.305343628,-42.8594093323],"type":"Point"}
}