{
  "type": "Feature",
  "properties": {
    "addr:full":"67 Lime Ave Mildura VIC 3500",
    "addr:housenumber":"67",
    "addr:postcode":"3500",
    "addr:street":"Lime Ave",
    "iso:country":"AU",
    "sg:address":"67 Lime Ave",
    "sg:city":"Mildura",
    "sg:classifiers":[
        {
            "category":"Banks & Credit Unions",
            "subcategory":"Investment Brokerage",
            "type":"Services"
        }
    ],
    "sg:phone":"+61 3 5021 2200",
    "sg:postcode":"3500",
    "sg:province":"VIC",
    "sg:tags":[
        "management",
        "property"
    ],
    "wof:name":"Collie & Tierney First National",
    "wof:placetype":"venue"
},
  "geometry": {"coordinates":[142.159393311,-34.1840896606],"type":"Point"}
}