{
  "type": "Feature",
  "properties": {
    "addr:full":"246 Parramatta Rd Stanmore NSW 2048",
    "addr:housenumber":"246",
    "addr:postcode":"2048",
    "addr:street":"Parramatta Rd",
    "iso:country":"AU",
    "sg:address":"246 Parramatta Rd",
    "sg:city":"Stanmore",
    "sg:classifiers":[
        {
            "category":"Shopping",
            "subcategory":"Computers & Home Electronics",
            "type":"Retail Goods"
        }
    ],
    "sg:phone":"+61 2 9560 0666",
    "sg:postcode":"2048",
    "sg:province":"NSW",
    "sg:tags":[
        "hardware",
        "equipment"
    ],
    "wof:name":"Micro Mania",
    "wof:placetype":"venue"
},
  "geometry": {"coordinates":[151.165527,-33.888226],"type":"Point"}
}