{
  "type": "Feature",
  "properties": {
    "addr:full":"Lot 6 Chewko Rd Mareeba QLD 4880",
    "addr:postcode":"4880",
    "addr:street":"Chewko Rd",
    "iso:country":"AU",
    "sg:address":"Lot 6 Chewko Rd",
    "sg:city":"Mareeba",
    "sg:classifiers":[
        {
            "category":"Building & Trades",
            "subcategory":"Construction",
            "type":"Services"
        }
    ],
    "sg:phone":"+61 417 641 388",
    "sg:postcode":"4880",
    "sg:province":"QLD",
    "sg:tags":[
        "earth",
        "excavating",
        "moving",
        "contractor"
    ],
    "wof:name":"Sullivan Tony Truck & Loader Hire",
    "wof:placetype":"venue"
},
  "geometry": {"coordinates":[145.416625977,-16.9988975525],"type":"Point"}
}