{
  "type": "Feature",
  "properties": {
    "addr:full":"93 Guthrie St Osborne Park WA 6017",
    "addr:housenumber":"93",
    "addr:postcode":"6017",
    "addr:street":"Guthrie St",
    "iso:country":"AU",
    "sg:address":"93 Guthrie St",
    "sg:city":"Osborne Park",
    "sg:classifiers":[
        {
            "category":"Retail",
            "subcategory":"Auto Repair",
            "type":"Services"
        }
    ],
    "sg:phone":"+61 8 9445 2252",
    "sg:postcode":"6017",
    "sg:province":"WA",
    "sg:tags":[
        "repairer",
        "motor",
        "engineer"
    ],
    "wof:name":"Osborne Automotives",
    "wof:placetype":"venue"
},
  "geometry": {"coordinates":[115.817230225,-31.9071884155],"type":"Point"}
}