{
  "type": "Feature",
  "properties": {
    "iso:country":"AU",
    "sg:address":"Camaroo La",
    "sg:city":"Sutton Forest",
    "sg:classifiers":[
        {
            "category":"Building & Trades",
            "subcategory":"Landscaping Services",
            "type":"Services"
        }
    ],
    "sg:phone":"+61 2 4868 3246",
    "sg:postcode":"2577",
    "sg:province":"NSW",
    "sg:tags":[
        "horticultural",
        "consultant"
    ],
    "wof:name":"Andrew Lawsons Horticultural Service",
    "wof:placetype":"venue"
},
  "geometry": {"coordinates":[150.348098755,-34.5606002808],"type":"Point"}
}