{
  "type": "Feature",
  "properties": {
    "addr:full":"483 South Rd Regency Park SA 5010",
    "addr:housenumber":"483",
    "addr:postcode":"5010",
    "addr:street":"South Rd",
    "iso:country":"AU",
    "sg:address":"483 South Rd",
    "sg:city":"Regency Park",
    "sg:classifiers":[
        {
            "category":"Building & Trades",
            "subcategory":"Equipment Rental",
            "type":"Services"
        }
    ],
    "sg:phone":"+61 8 8340 3655",
    "sg:postcode":"5010",
    "sg:province":"SA",
    "sg:tags":[
        "supply",
        "catering"
    ],
    "wof:name":"Cellar Plus",
    "wof:placetype":"venue"
},
  "geometry": {"coordinates":[138.57090759299999,-34.8665657043],"type":"Point"}
}