{
  "type": "Feature",
  "properties": {
    "iso:country":"AU",
    "sg:address":"122 Toolara Rd",
    "sg:city":"Tin Can Bay",
    "sg:classifiers":[
        {
            "category":"Real Estate",
            "subcategory":"Real Estate Agent",
            "type":"Services"
        }
    ],
    "sg:phone":"+61 7 5486 4248",
    "sg:postcode":"4580",
    "sg:province":"QLD",
    "wof:name":"Tin Can Bay Real Estate",
    "wof:placetype":"venue"
},
  "geometry": {"coordinates":[153.00567626899999,-25.9183750153],"type":"Point"}
}