{
  "type": "Feature",
  "properties": {
    "addr:full":"Milroy & Moran Sts Bendigo VIC 3550",
    "addr:postcode":"3550",
    "addr:street":"Sts",
    "iso:country":"AU",
    "sg:address":"Milroy & Moran Sts",
    "sg:city":"Bendigo",
    "sg:classifiers":[
        {
            "category":"Autos & Motor Vehicles",
            "subcategory":"Fuel & Gas Station",
            "type":"Retail Goods"
        }
    ],
    "sg:phone":"+61 3 5443 1898",
    "sg:postcode":"3550",
    "sg:province":"VIC",
    "wof:name":"BP Australia Limited",
    "wof:placetype":"venue"
},
  "geometry": {"coordinates":[144.27378845199999,-36.7516975403],"type":"Point"}
}