{
  "type": "Feature",
  "properties": {
    "iso:country":"AU",
    "sg:address":"64 Gympie St",
    "sg:city":"Tewantin",
    "sg:classifiers":[
        {
            "category":"Professional",
            "subcategory":"Art Services",
            "type":"Services"
        }
    ],
    "sg:phone":"+61 7 5447 1997",
    "sg:postcode":"4565",
    "sg:province":"QLD",
    "sg:tags":[
        "decorator",
        "painter"
    ],
    "wof:name":"Shane's Painting Service",
    "wof:placetype":"venue"
},
  "geometry": {"coordinates":[153.03520202600001,-26.3854103088],"type":"Point"}
}