{
  "type": "Feature",
  "properties": {
    "iso:country":"AU",
    "sg:address":"Lot 206, May St",
    "sg:city":"Newdegate",
    "sg:classifiers":[
        {
            "category":"Retail",
            "subcategory":"Auto Repair",
            "type":"Services"
        }
    ],
    "sg:phone":"+61 8 9871 1667",
    "sg:postcode":"6355",
    "sg:province":"WA",
    "sg:tags":[
        "electrical"
    ],
    "wof:name":"Gosling Ray",
    "wof:placetype":"venue"
},
  "geometry": {"coordinates":[119.02491000000001,-33.094158],"type":"Point"}
}