{
  "type": "Feature",
  "properties": {
    "addr:full":"Cnr Hume St & Wodonga Pl Albury NSW 2640",
    "addr:postcode":"2640",
    "addr:street":"Cnr Hume St &;Pl",
    "iso:country":"AU",
    "sg:address":"Cnr Hume St & Wodonga Pl",
    "sg:city":"Albury",
    "sg:classifiers":[
        {
            "category":"Autos & Motor Vehicles",
            "subcategory":"Automobile Sales",
            "type":"Retail Goods"
        }
    ],
    "sg:phone":"+61 2 6021 1566",
    "sg:postcode":"2640",
    "sg:province":"NSW",
    "sg:tags":[
        "car",
        "new"
    ],
    "wof:name":"Alessi Chrysler Jeep",
    "wof:placetype":"venue"
},
  "geometry": {"coordinates":[146.908813477,-36.0840759277],"type":"Point"}
}