{
  "type": "Feature",
  "properties": {
    "addr:full":"Unit 5, 39 Secam St Mansfield QLD 4122",
    "addr:housenumber":"39",
    "addr:postcode":"4122",
    "addr:street":"Secam St",
    "iso:country":"AU",
    "sg:address":"Unit 5, 39 Secam St",
    "sg:city":"Mansfield",
    "sg:classifiers":[
        {
            "category":"Building & Trades",
            "subcategory":"Construction",
            "type":"Services"
        }
    ],
    "sg:phone":"+61 7 3849 2022",
    "sg:postcode":"4122",
    "sg:province":"QLD",
    "sg:tags":[
        "window",
        "tinting"
    ],
    "wof:name":"Tintplus",
    "wof:placetype":"venue"
},
  "geometry": {"coordinates":[153.098480225,-27.5306606293],"type":"Point"}
}