{
  "type": "Feature",
  "properties": {
    "iso:country":"AU",
    "sg:address":"130 Woodpark Rd",
    "sg:city":"Smithfield",
    "sg:classifiers":[
        {
            "category":"Professional",
            "subcategory":"Engineering",
            "type":"Services"
        }
    ],
    "sg:phone":"+61 2 9721 5900",
    "sg:postcode":"2164",
    "sg:province":"NSW",
    "sg:tags":[
        "engineer"
    ],
    "wof:name":"Schmidt & Muller",
    "wof:placetype":"venue"
},
  "geometry": {"coordinates":[150.93307495100001,-33.8361968994],"type":"Point"}
}