{
  "type": "Feature",
  "properties": {
    "addr:full":"FSD Pharmacy 52 Cunningham St Dalby QLD 4405",
    "addr:housenumber":"52",
    "addr:postcode":"4405",
    "addr:street":"Cunningham St",
    "iso:country":"AU",
    "sg:address":"FSD Pharmacy 52 Cunningham St",
    "sg:city":"Dalby",
    "sg:classifiers":[
        {
            "category":"Health Services",
            "subcategory":"Health Practitioner",
            "type":"Services"
        }
    ],
    "sg:phone":"+61 412 744 501",
    "sg:postcode":"4405",
    "sg:province":"QLD",
    "sg:tags":[
        "psychologist"
    ],
    "wof:name":"Irene Mullens",
    "wof:placetype":"venue"
},
  "geometry": {"coordinates":[151.26484680199999,-27.1822242737],"type":"Point"}
}