{
  "type": "Feature",
  "properties": {
    "addr:full":"67 Main Rd Paynesville VIC 3880",
    "addr:housenumber":"67",
    "addr:postcode":"3880",
    "addr:street":"Main Rd",
    "iso:country":"AU",
    "sg:address":"67 Main Rd",
    "sg:city":"Paynesville",
    "sg:classifiers":[
        {
            "category":"Farming",
            "subcategory":"Dairy Farm",
            "type":"Manufacturing & Wholesale Goods"
        }
    ],
    "sg:phone":"+61 3 5156 6507",
    "sg:postcode":"3880",
    "sg:province":"VIC",
    "wof:name":"Paynesville Dairy",
    "wof:placetype":"venue"
},
  "geometry": {"coordinates":[147.72013855,-37.9074211121],"type":"Point"}
}