{
  "type": "Feature",
  "properties": {
    "iso:country":"AU",
    "sg:address":"12th Floor/ 28 Latimer Rd",
    "sg:city":"Bellevue Hill",
    "sg:classifiers":[
        {
            "category":"Airline",
            "type":"Transportation"
        }
    ],
    "sg:phone":"+61 2 9363 4903",
    "sg:postcode":"2023",
    "sg:province":"NSW",
    "sg:tags":[
        "agent"
    ],
    "wof:name":"Australia Air International Pty Ltd",
    "wof:placetype":"venue"
},
  "geometry": {"coordinates":[151.261184692,-33.8785591125],"type":"Point"}
}