{
  "type": "Feature",
  "properties": {
    "addr:full":"1600 Hume Hwy Campbellfield VIC 3061",
    "addr:housenumber":"1600",
    "addr:postcode":"3061",
    "addr:street":"Hume Hwy",
    "iso:country":"AU",
    "sg:address":"1600 Hume Hwy",
    "sg:city":"Campbellfield",
    "sg:classifiers":[
        {
            "category":"Wholesale",
            "subcategory":"Auto Parts",
            "type":"Manufacturing & Wholesale Goods"
        }
    ],
    "sg:phone":"+61 3 9357 1111",
    "sg:postcode":"3061",
    "sg:province":"VIC",
    "sg:tags":[
        "recyclers"
    ],
    "wof:name":"Vicstate Auto Centre",
    "wof:placetype":"venue"
},
  "geometry": {"coordinates":[144.95758056599999,-37.6829071045],"type":"Point"}
}