{
  "type": "Feature",
  "properties": {
    "addr:full":"16 Berkshire Rd Sunshine North VIC 3020",
    "addr:housenumber":"16",
    "addr:postcode":"3020",
    "addr:street":"Berkshire Rd",
    "iso:country":"AU",
    "sg:address":"16 Berkshire Rd",
    "sg:city":"Sunshine North",
    "sg:classifiers":[
        {
            "category":"Home & Garden",
            "subcategory":"Building Materials",
            "type":"Retail Goods"
        }
    ],
    "sg:phone":"+61 3 9311 3011",
    "sg:postcode":"3020",
    "sg:province":"VIC",
    "sg:tags":[
        "tile",
        "roofing"
    ],
    "wof:name":"Western Way Roofing",
    "wof:placetype":"venue"
},
  "geometry": {"coordinates":[144.84316999999999,-37.765808],"type":"Point"}
}