{
  "type": "Feature",
  "properties": {
    "addr:full":"Shop 4 Ballina Shopping Centre Cnr Kerr Fox St Ballina NSW 2478",
    "addr:housenumber":"shop 4",
    "addr:postcode":"2478",
    "addr:street":"Cnr Kerr Fox St",
    "iso:country":"AU",
    "sg:address":"Shop 4 Ballina Shopping Centre Cnr Kerr Fox St",
    "sg:city":"Ballina",
    "sg:classifiers":[
        {
            "category":"Shopping",
            "subcategory":"Clothing, Apparel, & Fashions",
            "type":"Retail Goods"
        }
    ],
    "sg:phone":"+61 2 6686 0225",
    "sg:postcode":"2478",
    "sg:province":"NSW",
    "sg:tags":[
        "menswear"
    ],
    "wof:name":"Lowes",
    "wof:placetype":"venue"
},
  "geometry": {"coordinates":[153.56031799300001,-28.8605175018],"type":"Point"}
}