{
  "type": "Feature",
  "properties": {
    "addr:full":"67 Kallay St Westall VIC 3169",
    "addr:housenumber":"67",
    "addr:postcode":"3169",
    "addr:street":"Kallay St",
    "iso:country":"AU",
    "sg:address":"67 Kallay St",
    "sg:city":"Westall",
    "sg:classifiers":[
        {
            "category":"Professional",
            "subcategory":"Detective & Security Services",
            "type":"Services"
        }
    ],
    "sg:phone":"+61 3 9544 7775",
    "sg:postcode":"3169",
    "sg:province":"VIC",
    "sg:tags":[
        "domestic",
        "alarm",
        "commercial",
        "burglar"
    ],
    "wof:name":"Visual Electronic Services",
    "wof:placetype":"venue"
},
  "geometry": {"coordinates":[145.11610412600001,-37.9371414185],"type":"Point"}
}