{
  "type": "Feature",
  "properties": {
    "iso:country":"AU",
    "sg:address":"Payne St",
    "sg:city":"Exmouth",
    "sg:classifiers":[
        {
            "category":"Social Services",
            "subcategory":"Child Care",
            "type":"Services"
        }
    ],
    "sg:phone":"+61 8 9949 1354",
    "sg:postcode":"6707",
    "sg:province":"WA",
    "sg:tags":[
        "support",
        "health"
    ],
    "wof:name":"Child Health Services",
    "wof:placetype":"venue"
},
  "geometry": {"coordinates":[114.12448120099999,-21.9312553406],"type":"Point"}
}