{
  "type": "Feature",
  "properties": {
    "iso:country":"AU",
    "sg:address":"9a Foster St",
    "sg:city":"Queanbeyan",
    "sg:classifiers":[
        {
            "category":"Building & Trades",
            "subcategory":"Construction",
            "type":"Services"
        }
    ],
    "sg:phone":"+61 2 6284 4404",
    "sg:postcode":"2620",
    "sg:province":"NSW",
    "sg:tags":[
        "welding"
    ],
    "wof:name":"Metalwork Unlimited",
    "wof:placetype":"venue"
},
  "geometry": {"coordinates":[149.24566650400001,-35.337272644],"type":"Point"}
}