{
  "type": "Feature",
  "properties": {
    "addr:full":"3 Seaforth Ave Cronulla NSW 2230",
    "addr:housenumber":"3",
    "addr:postcode":"2230",
    "addr:street":"Seaforth Ave",
    "iso:country":"AU",
    "sg:address":"3 Seaforth Ave",
    "sg:city":"Cronulla",
    "sg:classifiers":[
        {
            "category":"Retail",
            "subcategory":"Auto Repair",
            "type":"Services"
        }
    ],
    "sg:phone":"+61 2 9523 5219",
    "sg:postcode":"2230",
    "sg:province":"NSW",
    "sg:tags":[
        "repairer",
        "motor",
        "engineer"
    ],
    "wof:name":"Atkins Chris Automotive & Engineering Services",
    "wof:placetype":"venue"
},
  "geometry": {"coordinates":[151.145187378,-34.0513153076],"type":"Point"}
}