{
  "type": "Feature",
  "properties": {
    "iso:country":"AU",
    "sg:address":"Shp 3/ 693 Ann St",
    "sg:city":"Fortitude Valley",
    "sg:classifiers":[
        {
            "category":"Shopping",
            "subcategory":"Clothing, Apparel, & Fashions",
            "type":"Retail Goods"
        }
    ],
    "sg:phone":"+61 7 3252 4883",
    "sg:postcode":"4006",
    "sg:province":"QLD",
    "sg:tags":[
        "menswear"
    ],
    "wof:name":"Always Habit",
    "wof:placetype":"venue"
},
  "geometry": {"coordinates":[153.035552978,-27.4581260681],"type":"Point"}
}