{
  "type": "Feature",
  "properties": {
    "iso:country":"AU",
    "sg:address":"34b Pick Ave",
    "sg:city":"Mt Gambier",
    "sg:classifiers":[
        {
            "category":"Fast Food",
            "type":"Food & Drink"
        }
    ],
    "sg:phone":"+61 8 8725 2333",
    "sg:postcode":"5290",
    "sg:province":"SA",
    "sg:tags":[
        "away",
        "take"
    ],
    "wof:name":"Thomo's Takeaway",
    "wof:placetype":"venue"
},
  "geometry": {"coordinates":[140.797287,-37.837643],"type":"Point"}
}