{
  "type": "Feature",
  "properties": {
    "addr:full":"23 Rivendell Drv Tweed Heads South NSW 2486",
    "addr:housenumber":"23",
    "addr:postcode":"2486",
    "addr:street":"Rivendell Drv",
    "iso:country":"AU",
    "sg:address":"23 Rivendell Drv",
    "sg:city":"Tweed Heads South",
    "sg:classifiers":[
        {
            "category":"Shopping",
            "type":"Retail Goods"
        }
    ],
    "sg:phone":"+61 7 5523 6002",
    "sg:postcode":"2486",
    "sg:province":"NSW",
    "sg:tags":[
        "equipment",
        "safety",
        "accessory"
    ],
    "wof:name":"Brims Tweed Frame & Trusses Pty Ltd",
    "wof:placetype":"venue"
},
  "geometry": {"coordinates":[153.54396057100001,-28.2056903839],"type":"Point"}
}