{
  "type": "Feature",
  "properties": {
    "addr:full":"Unit 2/ 46 Smith St Southport QLD 4215",
    "addr:housenumber":"46",
    "addr:postcode":"4215",
    "addr:street":"Smith St",
    "iso:country":"AU",
    "sg:address":"Unit 2/ 46 Smith St",
    "sg:city":"Southport",
    "sg:classifiers":[
        {
            "category":"Building & Trades",
            "subcategory":"Cleaning & Sanitation",
            "type":"Services"
        }
    ],
    "sg:phone":"+61 7 5528 6522",
    "sg:postcode":"4215",
    "sg:province":"QLD",
    "sg:tags":[
        "cleaner",
        "repairer",
        "roof"
    ],
    "sg:website":"http://www.evershield.com.au",
    "wof:name":"EverShield",
    "wof:placetype":"venue"
},
  "geometry": {"coordinates":[153.404785156,-27.9635047913],"type":"Point"}
}