{
  "type": "Feature",
  "properties": {
    "addr:full":"37 Dandenong St Dandenong VIC 3175",
    "addr:housenumber":"37",
    "addr:postcode":"3175",
    "addr:street":"Dandenong St",
    "iso:country":"AU",
    "sg:address":"37 Dandenong St",
    "sg:city":"Dandenong",
    "sg:classifiers":[
        {
            "category":"Manufacturing",
            "subcategory":"Tools & Machinery",
            "type":"Manufacturing & Wholesale Goods"
        }
    ],
    "sg:phone":"+61 3 9791 6070",
    "sg:postcode":"3175",
    "sg:province":"VIC",
    "sg:tags":[
        "toolmaker"
    ],
    "wof:name":"Scandia Tooling Australia Pty Ltd",
    "wof:placetype":"venue"
},
  "geometry": {"coordinates":[145.19973754899999,-37.9936981201],"type":"Point"}
}