{
  "type": "Feature",
  "properties": {
    "addr:full":"Cnr McGregor & Captain Cook Rds Smithfield QLD 4350",
    "addr:housenumber":"cnr",
    "addr:postcode":"4350",
    "iso:country":"AU",
    "sg:address":"Cnr McGregor & Captain Cook Rds",
    "sg:city":"Smithfield",
    "sg:classifiers":[
        {
            "category":"Real Estate",
            "subcategory":"Real Estate Agent",
            "type":"Services"
        }
    ],
    "sg:phone":"+61 7 4057 6111",
    "sg:postcode":"4350",
    "sg:province":"QLD",
    "wof:name":"L J Hooker",
    "wof:placetype":"venue"
},
  "geometry": {"coordinates":[151.92860400000001,-27.586323],"type":"Point"}
}