{
  "type": "Feature",
  "properties": {
    "addr:full":"296 Greenhill Rd Glenside SA 5065",
    "addr:housenumber":"296",
    "addr:postcode":"5065",
    "addr:street":"Greenhill Rd",
    "iso:country":"AU",
    "sg:address":"296 Greenhill Rd",
    "sg:city":"Glenside",
    "sg:classifiers":[
        {
            "category":"Health Services",
            "subcategory":"Health Practitioner",
            "type":"Services"
        }
    ],
    "sg:phone":"+61 8 8338 4110",
    "sg:postcode":"5065",
    "sg:province":"SA",
    "sg:tags":[
        "alternative"
    ],
    "wof:name":"Life Spa Wellness Centre Pty Ltd",
    "wof:placetype":"venue"
},
  "geometry": {"coordinates":[138.635223389,-34.9397354126],"type":"Point"}
}