{
  "type": "Feature",
  "properties": {
    "iso:country":"AU",
    "sg:address":"41 Charles St",
    "sg:city":"Moonah",
    "sg:classifiers":[
        {
            "category":"Retail",
            "subcategory":"Driving School",
            "type":"Services"
        }
    ],
    "sg:phone":"+61 1300 366 640",
    "sg:postcode":"7009",
    "sg:province":"TAS",
    "wof:name":"Stay Upright Motor Cycle Techniques",
    "wof:placetype":"venue"
},
  "geometry": {"coordinates":[147.29275512699999,-42.8462028503],"type":"Point"}
}