{
  "type": "Feature",
  "properties": {
    "iso:country":"AU",
    "sg:address":"12/ 1 Derby St",
    "sg:city":"Kogarah",
    "sg:classifiers":[
        {
            "category":"Health Services",
            "subcategory":"Doctor",
            "type":"Services"
        }
    ],
    "sg:phone":"+61 2 9588 9888",
    "sg:postcode":"2217",
    "sg:province":"NSW",
    "sg:tags":[
        "medical",
        "practitioner"
    ],
    "wof:name":"Southern Peadiatrics & Allergy",
    "wof:placetype":"venue"
},
  "geometry": {"coordinates":[151.13227800000001,-33.965496],"type":"Point"}
}