{
  "type": "Feature",
  "properties": {
    "addr:full":"20 Sinclair Ave Glen Iris VIC 3146",
    "addr:housenumber":"20",
    "addr:postcode":"3146",
    "addr:street":"Sinclair Ave",
    "iso:country":"AU",
    "sg:address":"20 Sinclair Ave",
    "sg:city":"Glen Iris",
    "sg:classifiers":[
        {
            "category":"Organizations",
            "subcategory":"Membership Organization",
            "type":"Services"
        }
    ],
    "sg:phone":"+61 3 9824 7884",
    "sg:postcode":"3146",
    "sg:province":"VIC",
    "sg:tags":[
        "club",
        "bridge"
    ],
    "wof:name":"Kattery Bridge Club",
    "wof:placetype":"venue"
},
  "geometry": {"coordinates":[145.05213928200001,-37.8504714966],"type":"Point"}
}