{
  "type": "Feature",
  "properties": {
    "addr:full":"McDouall Stuart Ave Whyalla Stuart SA 5608",
    "addr:postcode":"5608",
    "addr:street":"Stuart Ave",
    "iso:country":"AU",
    "sg:address":"McDouall Stuart Ave",
    "sg:city":"Whyalla Stuart",
    "sg:classifiers":[
        {
            "category":"Food & Beverages",
            "subcategory":"Supermarket",
            "type":"Retail Goods"
        }
    ],
    "sg:phone":"+61 8 8645 3859",
    "sg:postcode":"5608",
    "sg:province":"SA",
    "sg:tags":[
        "grocery",
        "store"
    ],
    "wof:name":"Bi-Lo Supermarket",
    "wof:placetype":"venue"
},
  "geometry": {"coordinates":[137.52795399999999,-33.010925],"type":"Point"}
}