{
  "type": "Feature",
  "properties": {
    "addr:full":"Unit 2/ 206 Box Rd Miranda NSW 2228",
    "addr:housenumber":"/ 206",
    "addr:postcode":"2228",
    "addr:street":"Box Rd",
    "iso:country":"AU",
    "sg:address":"Unit 2/ 206 Box Rd",
    "sg:city":"Miranda",
    "sg:classifiers":[
        {
            "category":"Autos & Motor Vehicles",
            "subcategory":"Boat Sales",
            "type":"Retail Goods"
        }
    ],
    "sg:phone":"+61 2 9544 7899",
    "sg:postcode":"2228",
    "sg:province":"NSW",
    "sg:tags":[
        "yacht"
    ],
    "wof:name":"Sydney Inflatables",
    "wof:placetype":"venue"
},
  "geometry": {"coordinates":[151.105667114,-34.0221443176],"type":"Point"}
}