{
  "type": "Feature",
  "properties": {
    "addr:full":"1/ 128 Ayr St Doncaster VIC 3108",
    "addr:housenumber":"/ 128",
    "addr:postcode":"3108",
    "addr:street":"Ayr St",
    "iso:country":"AU",
    "sg:address":"1/ 128 Ayr St",
    "sg:city":"Doncaster",
    "sg:classifiers":[
        {
            "category":"Wholesale",
            "subcategory":"Chemicals & Plastics",
            "type":"Manufacturing & Wholesale Goods"
        }
    ],
    "sg:phone":"+61 3 9850 9997",
    "sg:postcode":"3108",
    "sg:province":"VIC",
    "sg:tags":[
        "bag"
    ],
    "wof:name":"Bagco Pty Ltd",
    "wof:placetype":"venue"
},
  "geometry": {"coordinates":[145.10392761200001,-37.7764968872],"type":"Point"}
}