{
  "type": "Feature",
  "properties": {
    "iso:country":"AU",
    "sg:address":"9 William St",
    "sg:city":"Gladstone",
    "sg:classifiers":[
        {
            "category":"Retail",
            "subcategory":"Repair Shop",
            "type":"Services"
        }
    ],
    "sg:phone":"+61 7 4972 7620",
    "sg:postcode":"4680",
    "sg:province":"QLD",
    "sg:tags":[
        "machine",
        "sewing"
    ],
    "wof:name":"Crafty Sewing Patch",
    "wof:placetype":"venue"
},
  "geometry": {"coordinates":[151.25666809099999,-23.8436031342],"type":"Point"}
}