{
  "type": "Feature",
  "properties": {
    "addr:full":"300 Albert Rd South Melbourne VIC 3205",
    "addr:housenumber":"300",
    "addr:postcode":"3205",
    "addr:street":"Albert Rd",
    "iso:country":"AU",
    "sg:address":"300 Albert Rd",
    "sg:city":"South Melbourne",
    "sg:classifiers":[
        {
            "category":"Health Services",
            "subcategory":"Health Practitioner",
            "type":"Services"
        }
    ],
    "sg:phone":"+61 3 9699 2499",
    "sg:postcode":"3205",
    "sg:province":"VIC",
    "sg:tags":[
        "osteopath"
    ],
    "wof:name":"Centre for Musculoskeletal Medicine",
    "wof:placetype":"venue"
},
  "geometry": {"coordinates":[144.96305799999999,-37.838848],"type":"Point"}
}