{
  "type": "Feature",
  "properties": {
    "iso:country":"AU",
    "sg:address":"18a Russell Rd",
    "sg:city":"Henderson",
    "sg:classifiers":[
        {
            "category":"Autos & Motor Vehicles",
            "subcategory":"Boat Sales",
            "type":"Retail Goods"
        }
    ],
    "sg:phone":"+61 8 9437 3111",
    "sg:postcode":"6166",
    "sg:province":"WA",
    "sg:tags":[
        "yacht"
    ],
    "wof:name":"Thomascraft 2000 Pty Ltd",
    "wof:placetype":"venue"
},
  "geometry": {"coordinates":[115.79026,-32.146927],"type":"Point"}
}