{
  "type": "Feature",
  "properties": {
    "iso:country":"AU",
    "sg:address":"U 1/ 42 Stanbel Rd",
    "sg:city":"Salisbury Plain",
    "sg:classifiers":[
        {
            "category":"Autos & Motor Vehicles",
            "subcategory":"Auto Supplies",
            "type":"Retail Goods"
        }
    ],
    "sg:phone":"+61 8 8258 4049",
    "sg:postcode":"5109",
    "sg:province":"SA",
    "sg:tags":[
        "accessory"
    ],
    "wof:name":"Advanced Body Kits",
    "wof:placetype":"venue"
},
  "geometry": {"coordinates":[138.65640258799999,-34.7674026489],"type":"Point"}
}