{
  "type": "Feature",
  "properties": {
    "iso:country":"AU",
    "sg:address":"7 Tabletop Rd",
    "sg:city":"Terrigal",
    "sg:classifiers":[
        {
            "category":"Professional",
            "subcategory":"Employment Agencies",
            "type":"Services"
        }
    ],
    "sg:phone":"+61 1300 655 366",
    "sg:postcode":"2260",
    "sg:province":"NSW",
    "sg:tags":[
        "provider",
        "internet"
    ],
    "wof:name":"Nobby Hotkey.",
    "wof:placetype":"venue"
},
  "geometry": {"coordinates":[151.43785099999999,-33.452141],"type":"Point"}
}