{
  "type": "Feature",
  "properties": {
    "addr:full":"85 Lambton Rd Broadmeadow NSW 2292",
    "addr:housenumber":"85",
    "addr:postcode":"2292",
    "addr:street":"Lambton Rd",
    "iso:country":"AU",
    "sg:address":"85 Lambton Rd",
    "sg:city":"Broadmeadow",
    "sg:classifiers":[
        {
            "category":"Retail",
            "subcategory":"Auto Repair",
            "type":"Services"
        }
    ],
    "sg:phone":"+61 2 4961 1946",
    "sg:postcode":"2292",
    "sg:province":"NSW",
    "sg:tags":[
        "repairer",
        "motor",
        "engineer"
    ],
    "wof:name":"Paul Skewes European Car Centre",
    "wof:placetype":"venue"
},
  "geometry": {"coordinates":[151.730712891,-32.9243011475],"type":"Point"}
}