{
  "type": "Feature",
  "properties": {
    "addr:full":"96 Daws Rd Edwardstown SA 5039",
    "addr:housenumber":"96",
    "addr:postcode":"5039",
    "addr:street":"Daws Rd",
    "iso:country":"AU",
    "sg:address":"96 Daws Rd",
    "sg:city":"Edwardstown",
    "sg:classifiers":[
        {
            "category":"Professional",
            "subcategory":"Engineering",
            "type":"Services"
        }
    ],
    "sg:phone":"+61 8 8277 8988",
    "sg:postcode":"5039",
    "sg:province":"SA",
    "sg:tags":[
        "diesel",
        "engineer"
    ],
    "wof:name":"Llordan Diesel",
    "wof:placetype":"venue"
},
  "geometry": {"coordinates":[138.57041931099999,-34.9932136536],"type":"Point"}
}