{
  "type": "Feature",
  "properties": {
    "addr:full":"175 Stewart's Rd Kongwak VIC 3951",
    "addr:housenumber":"175",
    "addr:postcode":"3951",
    "addr:street":"Stewart'S Rd",
    "iso:country":"AU",
    "sg:address":"175 Stewart's Rd",
    "sg:city":"Kongwak",
    "sg:classifiers":[
        {
            "category":"Farming",
            "subcategory":"Vineyard",
            "type":"Manufacturing & Wholesale Goods"
        }
    ],
    "sg:phone":"+61 3 5657 4241",
    "sg:postcode":"3951",
    "sg:province":"VIC",
    "sg:tags":[
        "winery"
    ],
    "wof:name":"Paradise Enough Wines",
    "wof:placetype":"venue"
},
  "geometry": {"coordinates":[145.75523376500001,-38.3821105957],"type":"Point"}
}