{
  "type": "Feature",
  "properties": {
    "addr:full":"33d Christina Rd Villawood NSW 2163",
    "addr:housenumber":"33d",
    "addr:postcode":"2163",
    "addr:street":"Christina Rd",
    "iso:country":"AU",
    "sg:address":"33d Christina Rd",
    "sg:city":"Villawood",
    "sg:classifiers":[
        {
            "category":"Manufacturing",
            "subcategory":"Retail Goods",
            "type":"Manufacturing & Wholesale Goods"
        }
    ],
    "sg:phone":"+61 2 9726 7922",
    "sg:postcode":"2163",
    "sg:province":"NSW",
    "sg:tags":[
        "merchant",
        "pump",
        "mfrs"
    ],
    "wof:name":"Stauff Corporation Pty Ltd",
    "wof:placetype":"venue"
},
  "geometry": {"coordinates":[150.98982238799999,-33.8815917969],"type":"Point"}
}