{
  "type": "Feature",
  "properties": {
    "iso:country":"AU",
    "sg:address":"108 Spit Rd",
    "sg:city":"Mosman",
    "sg:classifiers":[
        {
            "category":"Real Estate",
            "subcategory":"Developer",
            "type":"Services"
        }
    ],
    "sg:phone":"+61 2 9969 1671",
    "sg:postcode":"2088",
    "sg:province":"NSW",
    "sg:tags":[
        "chartering",
        "ship",
        "broker"
    ],
    "wof:name":"Cadence Cruises",
    "wof:placetype":"venue"
},
  "geometry": {"coordinates":[151.243743897,-33.8206443787],"type":"Point"}
}