{
  "type": "Feature",
  "properties": {
    "addr:full":"17 Vernon St Mittagong NSW 2575",
    "addr:housenumber":"17",
    "addr:postcode":"2575",
    "addr:street":"Vernon St",
    "iso:country":"AU",
    "sg:address":"17 Vernon St",
    "sg:city":"Mittagong",
    "sg:classifiers":[
        {
            "category":"Shopping",
            "subcategory":"Stationery & Office Supplies",
            "type":"Retail Goods"
        }
    ],
    "sg:phone":"+61 2 4871 1263",
    "sg:postcode":"2575",
    "sg:province":"NSW",
    "sg:tags":[
        "equipment",
        "facsimile"
    ],
    "wof:name":"Anchor Computers",
    "wof:placetype":"venue"
},
  "geometry": {"coordinates":[150.44769287099999,-34.4540901184],"type":"Point"}
}