{
  "type": "Feature",
  "properties": {
    "iso:country":"AU",
    "sg:address":"33 Lionel St",
    "sg:city":"Naval Base",
    "sg:classifiers":[
        {
            "category":"Retail",
            "subcategory":"Auto Repair",
            "type":"Services"
        }
    ],
    "sg:phone":"+61 8 9437 2141",
    "sg:postcode":"6165",
    "sg:province":"WA",
    "sg:tags":[
        "bus",
        "truck"
    ],
    "wof:name":"PetroQuip Pty Ltd Truck & Trailer",
    "wof:placetype":"venue"
},
  "geometry": {"coordinates":[115.786209,-32.195702],"type":"Point"}
}