{
  "type": "Feature",
  "properties": {
    "addr:full":"U 13/ 19 Mary St Lidcombe NSW 2141",
    "addr:housenumber":"13 / 19",
    "addr:postcode":"2141",
    "addr:street":"Mary St",
    "iso:country":"AU",
    "sg:address":"U 13/ 19 Mary St",
    "sg:city":"Lidcombe",
    "sg:classifiers":[
        {
            "category":"Education",
            "subcategory":"University",
            "type":"Public Place"
        }
    ],
    "sg:phone":"+61 2 9749 4706",
    "sg:postcode":"2141",
    "sg:province":"NSW",
    "sg:tags":[
        "college",
        "tertiary"
    ],
    "wof:name":"Ukrainian Studies Foundation in Australia",
    "wof:placetype":"venue"
},
  "geometry": {"coordinates":[151.04783630399999,-33.8627815247],"type":"Point"}
}