{
  "type": "Feature",
  "properties": {
    "iso:country":"AU",
    "sg:address":"15 Laurence Rd",
    "sg:city":"Walliston",
    "sg:classifiers":[
        {
            "category":"Retail",
            "subcategory":"Auto Repair",
            "type":"Services"
        }
    ],
    "sg:phone":"+61 8 9291 8802",
    "sg:postcode":"6076",
    "sg:province":"WA",
    "sg:tags":[
        "repairer",
        "motor",
        "engineer"
    ],
    "wof:name":"Wilson's M Auto Service Centre",
    "wof:placetype":"venue"
},
  "geometry": {"coordinates":[116.07317352299999,-31.9937763214],"type":"Point"}
}