{
  "type": "Feature",
  "properties": {
    "iso:country":"AU",
    "sg:address":"9 Pyrus St",
    "sg:city":"Duncraig",
    "sg:classifiers":[
        {
            "category":"Education",
            "subcategory":"Special Training",
            "type":"Public Place"
        }
    ],
    "sg:phone":"+61 8 9246 3470",
    "sg:postcode":"6023",
    "sg:province":"WA",
    "sg:tags":[
        "development"
    ],
    "wof:name":"Graham Green & Associates",
    "wof:placetype":"venue"
},
  "geometry": {"coordinates":[115.774032593,-31.832736969],"type":"Point"}
}