{
  "type": "Feature",
  "properties": {
    "iso:country":"AU",
    "sg:address":"739a Punchbowl Rd",
    "sg:city":"Punchbowl",
    "sg:classifiers":[
        {
            "category":"Travel",
            "subcategory":"Travel Agent",
            "type":"Entertainment"
        }
    ],
    "sg:phone":"+61 2 9793 7855",
    "sg:postcode":"2196",
    "sg:province":"NSW",
    "sg:tags":[
        "consultant"
    ],
    "wof:name":"Ace Travel Services Pty Ltd",
    "wof:placetype":"venue"
},
  "geometry": {"coordinates":[151.057678,-33.923756],"type":"Point"}
}