{
  "type": "Feature",
  "properties": {
    "iso:country":"AU",
    "sg:address":"2 Murray St",
    "sg:city":"Taringa",
    "sg:classifiers":[
        {
            "category":"Real Estate",
            "subcategory":"Real Estate Agent",
            "type":"Services"
        }
    ],
    "sg:phone":"+61 7 3378 1375",
    "sg:postcode":"4068",
    "sg:province":"QLD",
    "sg:tags":[
        "export"
    ],
    "wof:name":"Asia Direct",
    "wof:placetype":"venue"
},
  "geometry": {"coordinates":[152.96975707999999,-27.492685318],"type":"Point"}
}