{
  "type": "Feature",
  "properties": {
    "addr:full":"Suite 203, 36- 38 Victoria East St Burwood NSW 2134",
    "addr:housenumber":"38",
    "addr:postcode":"2134",
    "addr:street":"36;St",
    "iso:country":"AU",
    "sg:address":"Suite 203, 36- 38 Victoria East St",
    "sg:city":"Burwood",
    "sg:classifiers":[
        {
            "category":"Banks & Credit Unions",
            "subcategory":"Investment Brokerage",
            "type":"Services"
        }
    ],
    "sg:phone":"+61 2 9747 1211",
    "sg:postcode":"2134",
    "sg:province":"NSW",
    "wof:name":"Lifespan Financial Planning Pty Ltd",
    "wof:placetype":"venue"
},
  "geometry": {"coordinates":[151.105865478,-33.8752937317],"type":"Point"}
}