{
  "type": "Feature",
  "properties": {
    "addr:full":"89 Substation Rd Nambour QLD 4560",
    "addr:postcode":"4560",
    "addr:street":"Substation Rd",
    "iso:country":"AU",
    "sg:address":"89 Substation Rd",
    "sg:city":"Nambour",
    "sg:classifiers":[
        {
            "category":"Building & Trades",
            "subcategory":"Construction",
            "type":"Services"
        }
    ],
    "sg:phone":"+61 7 5441 1224",
    "sg:postcode":"4560",
    "sg:province":"QLD",
    "sg:tags":[
        "contractor"
    ],
    "wof:name":"Kilby PR & LC",
    "wof:placetype":"venue"
},
  "geometry": {"coordinates":[152.94752502399999,-26.6092357635],"type":"Point"}
}