{
  "type": "Feature",
  "properties": {
    "addr:full":"Community Centre 17 Sturt Dundas NSW 2117",
    "addr:housenumber":"17",
    "addr:postcode":"2117",
    "addr:street":"Sturt",
    "iso:country":"AU",
    "sg:address":"Community Centre 17 Sturt",
    "sg:city":"Dundas",
    "sg:classifiers":[
        {
            "category":"Social Services",
            "subcategory":"Child Care",
            "type":"Services"
        }
    ],
    "sg:phone":"+61 2 9638 6511",
    "sg:postcode":"2117",
    "sg:province":"NSW",
    "sg:tags":[
        "support",
        "health"
    ],
    "wof:name":"Early Childhood Health Centres",
    "wof:placetype":"venue"
},
  "geometry": {"coordinates":[151.04524230999999,-33.7970657349],"type":"Point"}
}