{
  "type": "Feature",
  "properties": {
    "addr:full":"8 Martin St St Kilda VIC 3182",
    "addr:housenumber":"8",
    "addr:postcode":"3182",
    "addr:street":"Martin St",
    "iso:country":"AU",
    "sg:address":"8 Martin St",
    "sg:city":"St Kilda",
    "sg:classifiers":[
        {
            "category":"Arts & Performance",
            "subcategory":"Art Gallery",
            "type":"Entertainment"
        }
    ],
    "sg:phone":"+61 3 9593 9366",
    "sg:postcode":"3182",
    "sg:province":"VIC",
    "wof:name":"Brightspace",
    "wof:placetype":"venue"
},
  "geometry": {"coordinates":[144.98764038100001,-37.8667526245],"type":"Point"}
}