{
  "type": "Feature",
  "properties": {
    "iso:country":"AU",
    "sg:address":"Level 1/ 86 Mann St",
    "sg:city":"Gosford",
    "sg:classifiers":[
        {
            "category":"Education",
            "subcategory":"Special Training",
            "type":"Public Place"
        }
    ],
    "sg:phone":"+61 2 4323 9172",
    "sg:postcode":"2250",
    "sg:province":"NSW",
    "sg:tags":[
        "development"
    ],
    "wof:name":"WorkWise",
    "wof:placetype":"venue"
},
  "geometry": {"coordinates":[151.34158325199999,-33.4273681641],"type":"Point"}
}