{
  "type": "Feature",
  "properties": {
    "addr:full":"Tallwood Drv Rainbow Flat NSW 2430",
    "addr:postcode":"2430",
    "addr:street":"Tallwood Drv Rainbow",
    "iso:country":"AU",
    "sg:address":"Tallwood Drv",
    "sg:city":"Rainbow Flat",
    "sg:classifiers":[
        {
            "category":"Building & Trades",
            "subcategory":"Construction",
            "type":"Services"
        }
    ],
    "sg:phone":"+61 2 6559 2824",
    "sg:postcode":"2430",
    "sg:province":"NSW",
    "sg:tags":[
        "contractor"
    ],
    "wof:name":"Dunleavin Homes",
    "wof:placetype":"venue"
},
  "geometry": {"coordinates":[152.48988299999999,-32.048283],"type":"Point"}
}