{
  "type": "Feature",
  "properties": {
    "addr:full":"Shop 1043A Westfield Carousel, 1383 Albany Highway Cannington WA 6107",
    "addr:housenumber":"1043a;1383",
    "addr:postcode":"6107",
    "addr:street":"Westfield Carousel;Albany Highway",
    "iso:country":"AU",
    "sg:address":"Shop 1043A Westfield Carousel, 1383 Albany Highway",
    "sg:city":"Cannington",
    "sg:classifiers":[
        {
            "category":"Health Services",
            "subcategory":"Optometrist",
            "type":"Services"
        }
    ],
    "sg:phone":"+61 8 9358 1950",
    "sg:postcode":"6107",
    "sg:province":"WA",
    "sg:website":"http://www.optometrists.asn.au",
    "wof:name":"Crystal Vision",
    "wof:placetype":"venue"
},
  "geometry": {"coordinates":[115.937210083,-32.0212440491],"type":"Point"}
}