{
  "type": "Feature",
  "properties": {
    "addr:full":"127 Newbridge Rd Moorebank NSW 2170",
    "addr:housenumber":"127",
    "addr:postcode":"2170",
    "addr:street":"Newbridge Rd",
    "iso:country":"AU",
    "sg:address":"127 Newbridge Rd",
    "sg:city":"Moorebank",
    "sg:classifiers":[
        {
            "category":"Building & Trades",
            "subcategory":"Equipment Rental",
            "type":"Services"
        }
    ],
    "sg:phone":"+61 412 257 945",
    "sg:postcode":"2170",
    "sg:province":"NSW",
    "sg:tags":[
        "party",
        "hire"
    ],
    "wof:name":"Renta Mobile Coolroom",
    "wof:placetype":"venue"
},
  "geometry": {"coordinates":[150.94000244099999,-33.9296722412],"type":"Point"}
}