{
  "type": "Feature",
  "properties": {
    "addr:full":"6A Hay Ave Wangaratta VIC 3677",
    "addr:housenumber":"6a",
    "addr:postcode":"3677",
    "addr:street":"Hay Ave",
    "iso:country":"AU",
    "sg:address":"6A Hay Ave",
    "sg:city":"Wangaratta",
    "sg:classifiers":[
        {
            "category":"Retail",
            "subcategory":"Storage",
            "type":"Services"
        }
    ],
    "sg:phone":"+61 428 573 038",
    "sg:postcode":"3677",
    "sg:province":"VIC",
    "sg:tags":[
        "cold"
    ],
    "wof:name":"LINK COLD STORAGE",
    "wof:placetype":"venue"
},
  "geometry": {"coordinates":[146.31050109899999,-36.3653182983],"type":"Point"}
}