{
  "type": "Feature",
  "properties": {
    "iso:country":"AU",
    "sg:address":"Dingley Dell Rd",
    "sg:city":"Thorpdale",
    "sg:classifiers":[
        {
            "category":"Farming",
            "subcategory":"Farm",
            "type":"Manufacturing & Wholesale Goods"
        }
    ],
    "sg:phone":"+61 3 5634 6386",
    "sg:postcode":"3835",
    "sg:province":"VIC",
    "sg:tags":[
        "farmer"
    ],
    "wof:name":"Cornwall H A",
    "wof:placetype":"venue"
},
  "geometry": {"coordinates":[146.163406,-38.32122],"type":"Point"}
}