{
  "type": "Feature",
  "properties": {
    "iso:country":"AU",
    "sg:address":"Meyer Rd",
    "sg:city":"Lonsdale",
    "sg:classifiers":[
        {
            "category":"Manufacturing",
            "subcategory":"Motor Vehicles & Parts",
            "type":"Manufacturing & Wholesale Goods"
        }
    ],
    "sg:phone":"+61 1300 873 554",
    "sg:postcode":"5160",
    "sg:province":"SA",
    "sg:tags":[
        "replacement"
    ],
    "wof:name":"Abandon Auto Dismantlers",
    "wof:placetype":"venue"
},
  "geometry": {"coordinates":[138.499801636,-35.1020126343],"type":"Point"}
}