{
  "type": "Feature",
  "properties": {
    "iso:country":"AU",
    "sg:address":"Lvl 1, 415a Albany Hwy",
    "sg:city":"Victoria Park",
    "sg:classifiers":[
        {
            "category":"Professional",
            "subcategory":"Art Services",
            "type":"Services"
        }
    ],
    "sg:phone":"+61 8 9450 6864",
    "sg:postcode":"6100",
    "sg:province":"WA",
    "sg:tags":[
        "graphic",
        "designer"
    ],
    "wof:name":"DB Graphics",
    "wof:placetype":"venue"
},
  "geometry": {"coordinates":[115.897506714,-31.9748935699],"type":"Point"}
}