{
  "type": "Feature",
  "properties": {
    "addr:full":"Lot 1758 Grafton Cres Winnellie NT 0820",
    "addr:housenumber":"1758",
    "addr:postcode":"nt 0820",
    "addr:street":"Grafton Cres",
    "iso:country":"AU",
    "sg:address":"Lot 1758 Grafton Cres",
    "sg:city":"Winnellie",
    "sg:classifiers":[
        {
            "category":"Home & Garden",
            "subcategory":"Hardware",
            "type":"Retail Goods"
        }
    ],
    "sg:phone":"+61 8 8947 0766",
    "sg:postcode":"0820",
    "sg:province":"NT",
    "sg:tags":[
        "generating",
        "set",
        "generator"
    ],
    "wof:name":"Cummins",
    "wof:placetype":"venue"
},
  "geometry": {"coordinates":[130.89439392099999,-12.4263296127],"type":"Point"}
}