{
  "type": "Feature",
  "properties": {
    "addr:full":"1102 Benetook Ave Mildura VIC 3500",
    "addr:housenumber":"1102",
    "addr:postcode":"3500",
    "addr:street":"Benetook Ave",
    "iso:country":"AU",
    "sg:address":"1102 Benetook Ave",
    "sg:city":"Mildura",
    "sg:classifiers":[
        {
            "category":"Manufacturing",
            "subcategory":"Metals",
            "type":"Manufacturing & Wholesale Goods"
        }
    ],
    "sg:phone":"+61 3 5023 2162",
    "sg:postcode":"3500",
    "sg:province":"VIC",
    "sg:tags":[
        "steel",
        "fabricator",
        "mfrs"
    ],
    "wof:name":"Steel Frames Mildura Pty Ltd",
    "wof:placetype":"venue"
},
  "geometry": {"coordinates":[142.171783447,-34.2023086548],"type":"Point"}
}