{
  "type": "Feature",
  "properties": {
    "addr:full":"366 Fords Rd Forest TAS 7330",
    "addr:housenumber":"366",
    "addr:postcode":"7330",
    "addr:street":"Fords Rd",
    "iso:country":"AU",
    "sg:address":"366 Fords Rd",
    "sg:city":"Forest",
    "sg:classifiers":[
        {
            "category":"Farming",
            "subcategory":"Farm",
            "type":"Manufacturing & Wholesale Goods"
        }
    ],
    "sg:phone":"+61 3 6458 3396",
    "sg:postcode":"7330",
    "sg:province":"TAS",
    "sg:tags":[
        "farmer"
    ],
    "wof:name":"House Brothers Farms",
    "wof:placetype":"venue"
},
  "geometry": {"coordinates":[145.230637,-40.847775],"type":"Point"}
}