{
  "type": "Feature",
  "properties": {
    "iso:country":"AU",
    "sg:address":"45 Hilltop Ave",
    "sg:city":"Blacktown",
    "sg:classifiers":[
        {
            "category":"Recreation",
            "subcategory":"Boat Charter",
            "type":"Entertainment"
        }
    ],
    "sg:phone":"+61 2 9622 9026",
    "sg:postcode":"2148",
    "sg:province":"NSW",
    "wof:name":"Goodtime Boat Charters.",
    "wof:placetype":"venue"
},
  "geometry": {"coordinates":[150.89030456500001,-33.7769889832],"type":"Point"}
}