{
  "type": "Feature",
  "properties": {
    "addr:full":"Shop 6a Stargate Shopping Cntr 49 Chelmsford Ave Port Kennedy WA 6172",
    "addr:housenumber":"shop 6a;49",
    "addr:postcode":"6172",
    "addr:street":"Stargate Shopping Cntr;Chelmsford Ave",
    "iso:country":"AU",
    "sg:address":"Shop 6a Stargate Shopping Cntr 49 Chelmsford Ave",
    "sg:city":"Port Kennedy",
    "sg:classifiers":[
        {
            "category":"Personal",
            "subcategory":"Beauty Salon",
            "type":"Services"
        }
    ],
    "sg:phone":"+61 8 9594 0539",
    "sg:postcode":"6172",
    "sg:province":"WA",
    "wof:name":"Beauty FX",
    "wof:placetype":"venue"
},
  "geometry": {"coordinates":[115.754349,-32.352623],"type":"Point"}
}