{
  "type": "Feature",
  "properties": {
    "iso:country":"AU",
    "sg:address":"1st Floor 458 Rocky Point Rd",
    "sg:city":"Sans Souci",
    "sg:classifiers":[
        {
            "category":"Government",
            "subcategory":"Department Of Motor Vehicles",
            "type":"Public Place"
        }
    ],
    "sg:phone":"+61 2 8558 5100",
    "sg:postcode":"2219",
    "sg:province":"NSW",
    "sg:tags":[
        "tank",
        "cleaning"
    ],
    "wof:name":"Worth Recycling Pty Ltd",
    "wof:placetype":"venue"
},
  "geometry": {"coordinates":[151.133728,-33.990032],"type":"Point"}
}