{
  "type": "Feature",
  "properties": {
    "iso:country":"AU",
    "sg:address":"Fact 7- 29 Barry St",
    "sg:city":"Bayswater",
    "sg:classifiers":[
        {
            "category":"Home & Garden",
            "subcategory":"Household Appliances",
            "type":"Retail Goods"
        }
    ],
    "sg:phone":"+61 3 9720 3444",
    "sg:postcode":"3153",
    "sg:province":"VIC",
    "sg:tags":[
        "heating",
        "system"
    ],
    "wof:name":"Alpine Wood Heating",
    "wof:placetype":"venue"
},
  "geometry": {"coordinates":[145.27610778799999,-37.8469543457],"type":"Point"}
}