{
  "type": "Feature",
  "properties": {
    "addr:full":"438 Carrington St Hamilton Hill WA 6163",
    "addr:housenumber":"438",
    "addr:postcode":"6163",
    "addr:street":"Carrington St",
    "iso:country":"AU",
    "sg:address":"438 Carrington St",
    "sg:city":"Hamilton Hill",
    "sg:classifiers":[
        {
            "category":"Shopping",
            "subcategory":"Pawn Shop",
            "type":"Retail Goods"
        }
    ],
    "sg:phone":"+61 8 9434 1093",
    "sg:postcode":"6163",
    "sg:province":"WA",
    "sg:tags":[
        "pawnbroker"
    ],
    "wof:name":"Money Traders The",
    "wof:placetype":"venue"
},
  "geometry": {"coordinates":[115.77806099999999,-32.082069],"type":"Point"}
}