{
  "type": "Feature",
  "properties": {
    "iso:country":"AU",
    "sg:address":"2/ 8 Ballantyne Rd",
    "sg:city":"Kewdale",
    "sg:classifiers":[
        {
            "category":"Building & Trades",
            "subcategory":"Plumbing",
            "type":"Services"
        }
    ],
    "sg:phone":"+61 8 9353 3993",
    "sg:postcode":"6105",
    "sg:province":"WA",
    "sg:tags":[
        "equipment",
        "valves"
    ],
    "wof:name":"DeZURIK# Valves",
    "wof:placetype":"venue"
},
  "geometry": {"coordinates":[115.937110901,-31.9853153229],"type":"Point"}
}