{
  "type": "Feature",
  "properties": {
    "addr:full":"4 Keane Crt Old Reynella SA 5161",
    "addr:housenumber":"4",
    "addr:postcode":"5161",
    "addr:street":"Keane Crt",
    "iso:country":"AU",
    "sg:address":"4 Keane Crt",
    "sg:city":"Old Reynella",
    "sg:classifiers":[
        {
            "category":"Building & Trades",
            "subcategory":"Cleaning & Sanitation",
            "type":"Services"
        }
    ],
    "sg:phone":"+61 409 181 880",
    "sg:postcode":"5161",
    "sg:province":"SA",
    "sg:tags":[
        "cleaner",
        "repairer",
        "roof"
    ],
    "wof:name":"Southland Roofing & Guttering",
    "wof:placetype":"venue"
},
  "geometry": {"coordinates":[138.53770446799999,-35.0993080139],"type":"Point"}
}