{
  "type": "Feature",
  "properties": {
    "addr:full":"26-40 Pound Rd (West) Dandenong South VIC 3164",
    "addr:housenumber":"26-40",
    "addr:postcode":"3164",
    "addr:street":"Pound Rd West",
    "iso:country":"AU",
    "sg:address":"26-40 Pound Rd",
    "sg:city":"(West) Dandenong South",
    "sg:classifiers":[
        {
            "category":"Manufacturing",
            "subcategory":"Metals",
            "type":"Manufacturing & Wholesale Goods"
        }
    ],
    "sg:phone":"+61 1300 130 171",
    "sg:postcode":"3164",
    "sg:province":"VIC",
    "sg:tags":[
        "wholesaler",
        "aluminium",
        "mfrs"
    ],
    "wof:name":"ALSPEC",
    "wof:placetype":"venue"
},
  "geometry": {"coordinates":[145.25338745100001,-38.0265731812],"type":"Point"}
}