{
  "type": "Feature",
  "properties": {
    "addr:full":"Factory 6/ 100 Station St Nunawading VIC 3131",
    "addr:housenumber":"/ 100",
    "addr:postcode":"3131",
    "addr:street":"Station St",
    "iso:country":"AU",
    "sg:address":"Factory 6/ 100 Station St",
    "sg:city":"Nunawading",
    "sg:classifiers":[
        {
            "category":"Retail",
            "subcategory":"Laundry & Dry Cleaning",
            "type":"Services"
        }
    ],
    "sg:phone":"+61 3 9874 8600",
    "sg:postcode":"3131",
    "sg:province":"VIC",
    "wof:name":"Executive Valet & Laundry Services Pty Ltd",
    "wof:placetype":"venue"
},
  "geometry": {"coordinates":[145.18083190900001,-37.8199958801],"type":"Point"}
}