{
  "type": "Feature",
  "properties": {
    "iso:country":"AU",
    "sg:address":"26 Kent St",
    "sg:city":"Rockingham",
    "sg:classifiers":[
        {
            "category":"Professional",
            "subcategory":"Employment Agencies",
            "type":"Services"
        }
    ],
    "sg:phone":"+61 8 9592 1828",
    "sg:postcode":"6168",
    "sg:province":"WA",
    "sg:tags":[
        "entertainer",
        "agent"
    ],
    "wof:name":"Stone City Entertainment",
    "wof:placetype":"venue"
},
  "geometry": {"coordinates":[115.733383,-32.274609],"type":"Point"}
}