{
  "type": "Feature",
  "properties": {
    "iso:country":"AU",
    "sg:address":"158 Collins St",
    "sg:city":"Hobart",
    "sg:classifiers":[
        {
            "category":"Health Services",
            "subcategory":"Dentist",
            "type":"Services"
        }
    ],
    "sg:phone":"+61 3 6224 3575",
    "sg:postcode":"7000",
    "sg:province":"TAS",
    "wof:name":"Grenness M J",
    "wof:placetype":"venue"
},
  "geometry": {"coordinates":[147.32676696799999,-42.883972168],"type":"Point"}
}