{
  "type": "Feature",
  "properties": {
    "iso:country":"AU",
    "sg:address":"78 Dawson St",
    "sg:city":"Brunswick",
    "sg:classifiers":[
        {
            "category":"Building & Trades",
            "subcategory":"Construction",
            "type":"Services"
        }
    ],
    "sg:phone":"+61 3 9380 6841",
    "sg:postcode":"3056",
    "sg:province":"VIC",
    "sg:tags":[
        "brick",
        "paving"
    ],
    "wof:name":"Clifton Brick Manufacturers Pty Ltd",
    "wof:placetype":"venue"
},
  "geometry": {"coordinates":[144.95176696799999,-37.7704429626],"type":"Point"}
}