{
  "type": "Feature",
  "properties": {
    "addr:full":"85 Thornton Drv Greenwith SA 5125",
    "addr:housenumber":"85",
    "addr:postcode":"5125",
    "addr:street":"Thornton Drv",
    "iso:country":"AU",
    "sg:address":"85 Thornton Drv",
    "sg:city":"Greenwith",
    "sg:classifiers":[
        {
            "category":"Arts & Performance",
            "subcategory":"Art Gallery",
            "type":"Entertainment"
        }
    ],
    "sg:phone":"+61 8 8288 1350",
    "sg:postcode":"5125",
    "sg:province":"SA",
    "sg:tags":[
        "non-ferrous",
        "metal"
    ],
    "wof:name":"Minalysis",
    "wof:placetype":"venue"
},
  "geometry": {"coordinates":[138.712692,-34.772785],"type":"Point"}
}