{
  "type": "Feature",
  "properties": {
    "addr:full":"G1, 37 Bligh St Sydney NSW 2000",
    "addr:housenumber":"37",
    "addr:postcode":"2000",
    "addr:street":"G1;Bligh St",
    "iso:country":"AU",
    "sg:address":"G1, 37 Bligh St",
    "sg:city":"Sydney",
    "sg:classifiers":[
        {
            "category":"Travel",
            "subcategory":"Travel Agent",
            "type":"Entertainment"
        }
    ],
    "sg:phone":"+61 2 8222 1288",
    "sg:postcode":"2000",
    "sg:province":"NSW",
    "sg:tags":[
        "wholesaler"
    ],
    "wof:name":"Direct Flights International Pty Ltd",
    "wof:placetype":"venue"
},
  "geometry": {"coordinates":[151.209884644,-33.8660888672],"type":"Point"}
}