{
  "type": "Feature",
  "properties": {
    "iso:country":"AU",
    "sg:address":"10 Thorn St",
    "sg:city":"Ipswich",
    "sg:classifiers":[
        {
            "category":"Structure",
            "subcategory":"Office Building",
            "type":"Public Place"
        }
    ],
    "sg:phone":"+61 7 3812 9149",
    "sg:postcode":"4305",
    "sg:province":"QLD",
    "sg:tags":[
        "tie",
        "concrete",
        "formwork",
        "form",
        "accessory"
    ],
    "sg:website":"http://www.vbform.com.au",
    "wof:name":"VB Form Pty Ltd",
    "wof:placetype":"venue"
},
  "geometry": {"coordinates":[152.76484680199999,-27.6166954041],"type":"Point"}
}