{
  "type": "Feature",
  "properties": {
    "addr:full":"Shop 15-16 City Walk Arcade, Dean St Albury NSW 2640",
    "addr:housenumber":"15-16",
    "addr:postcode":"2640",
    "addr:street":"City Walk Arcade Dean St",
    "iso:country":"AU",
    "sg:address":"Shop 15-16 City Walk Arcade, Dean St",
    "sg:city":"Albury",
    "sg:classifiers":[
        {
            "category":"Food & Beverages",
            "subcategory":"Specialty",
            "type":"Retail Goods"
        }
    ],
    "sg:phone":"+61 2 6021 6991",
    "sg:postcode":"2640",
    "sg:province":"NSW",
    "sg:tags":[
        "delicacy"
    ],
    "wof:name":"Deli Piccante",
    "wof:placetype":"venue"
},
  "geometry": {"coordinates":[146.905197144,-36.0793991089],"type":"Point"}
}