{
  "type": "Feature",
  "properties": {
    "addr:full":"427 Silvan Rd Monbulk VIC 3793",
    "addr:housenumber":"427",
    "addr:postcode":"3793",
    "addr:street":"Silvan Rd",
    "iso:country":"AU",
    "sg:address":"427 Silvan Rd",
    "sg:city":"Monbulk",
    "sg:classifiers":[
        {
            "category":"Building & Trades",
            "subcategory":"Plumbing",
            "type":"Services"
        }
    ],
    "sg:phone":"+61 3 9756 6364",
    "sg:postcode":"3793",
    "sg:province":"VIC",
    "sg:tags":[
        "plumber",
        "gasfitters"
    ],
    "wof:name":"Deacon A S",
    "wof:placetype":"venue"
},
  "geometry": {"coordinates":[145.386795044,-37.8585891724],"type":"Point"}
}