{
  "type": "Feature",
  "properties": {
    "addr:full":"350 King St West Melbourne VIC 3003",
    "addr:housenumber":"350",
    "addr:postcode":"3003",
    "addr:street":"King St",
    "iso:country":"AU",
    "sg:address":"350 King St",
    "sg:city":"West Melbourne",
    "sg:classifiers":[
        {
            "category":"Building & Trades",
            "subcategory":"Cleaning & Sanitation",
            "type":"Services"
        }
    ],
    "sg:phone":"+61 3 9883 4159",
    "sg:postcode":"3003",
    "sg:province":"VIC",
    "sg:tags":[
        "window"
    ],
    "wof:name":"Priority Cleaning Services",
    "wof:placetype":"venue"
},
  "geometry": {"coordinates":[144.952224731,-37.8086967468],"type":"Point"}
}