{
  "type": "Feature",
  "properties": {
    "iso:country":"AU",
    "sg:address":"Essex St",
    "sg:city":"Minto",
    "sg:classifiers":[
        {
            "category":"Home & Garden",
            "subcategory":"Building Materials",
            "type":"Retail Goods"
        }
    ],
    "sg:phone":"+61 1300 552 555",
    "sg:postcode":"2566",
    "sg:province":"NSW",
    "sg:tags":[
        "pre-mixed",
        "concrete"
    ],
    "wof:name":"Boral Concrete",
    "wof:placetype":"venue"
},
  "geometry": {"coordinates":[150.84376525900001,-34.0211181641],"type":"Point"}
}