{
  "type": "Feature",
  "properties": {
    "iso:country":"AU",
    "sg:address":"U 103/ 2 Pembroke St",
    "sg:city":"Epping",
    "sg:classifiers":[
        {
            "category":"Wholesale",
            "subcategory":"Drugs",
            "type":"Manufacturing & Wholesale Goods"
        }
    ],
    "sg:phone":"+61 2 9876 3148",
    "sg:postcode":"2121",
    "sg:province":"NSW",
    "sg:tags":[
        "wholesaler",
        "pharmaceutical",
        "product",
        "mfrs"
    ],
    "wof:name":"Sharp Marketing Pty Ltd",
    "wof:placetype":"venue"
},
  "geometry": {"coordinates":[151.083129883,-33.7725601196],"type":"Point"}
}