{
  "type": "Feature",
  "properties": {
    "iso:country":"AU",
    "sg:address":"2 Hawley St",
    "sg:city":"Newstead",
    "sg:classifiers":[
        {
            "category":"Sports & Exercise",
            "subcategory":"Gym",
            "type":"Entertainment"
        }
    ],
    "sg:phone":"+61 1300 791 981",
    "sg:postcode":"7250",
    "sg:province":"TAS",
    "sg:tags":[
        "health",
        "fitness"
    ],
    "wof:name":"Rush Business",
    "wof:placetype":"venue"
},
  "geometry": {"coordinates":[147.15646362300001,-41.4348983765],"type":"Point"}
}