{
  "type": "Feature",
  "properties": {
    "addr:full":"PO Box 597 Castle Hill NSW 2154",
    "addr:postcode":"2154",
    "iso:country":"AU",
    "sg:address":"PO Box 597",
    "sg:city":"Castle Hill",
    "sg:classifiers":[
        {
            "category":"Arena",
            "subcategory":"Sports Club",
            "type":"Entertainment"
        }
    ],
    "sg:phone":"+61 2 9634 4167",
    "sg:postcode":"2154",
    "sg:province":"NSW",
    "sg:tags":[
        "organisation",
        "sporting"
    ],
    "wof:name":"NSW Hardcourt Tennis Association, The",
    "wof:placetype":"venue"
},
  "geometry": {"coordinates":[151.003814697,-33.7317695618],"type":"Point"}
}