{
  "type": "Feature",
  "properties": {
    "addr:full":"112 The Lakes Drv Glenmore Park NSW 2745",
    "addr:housenumber":"112",
    "addr:postcode":"2745",
    "addr:street":"The Lakes Drv",
    "iso:country":"AU",
    "sg:address":"112 The Lakes Drv",
    "sg:city":"Glenmore Park",
    "sg:classifiers":[
        {
            "category":"Health Services",
            "subcategory":"Doctor",
            "type":"Services"
        }
    ],
    "sg:phone":"+61 2 4733 2888",
    "sg:postcode":"2745",
    "sg:province":"NSW",
    "sg:tags":[
        "medical",
        "practitioner"
    ],
    "wof:name":"Oze-Med Glenmore Park",
    "wof:placetype":"venue"
},
  "geometry": {"coordinates":[150.67320251500001,-33.7842483521],"type":"Point"}
}