{
  "type": "Feature",
  "properties": {
    "addr:full":"Dolphin Shopping Centre Dolphin Ave Tin Can Bay QLD 4580",
    "addr:postcode":"4580",
    "addr:street":"Dolphin Ave;Can Bay",
    "iso:country":"AU",
    "sg:address":"Dolphin Shopping Centre Dolphin Ave",
    "sg:city":"Tin Can Bay",
    "sg:classifiers":[
        {
            "category":"Banks & Credit Unions",
            "subcategory":"Investment Brokerage",
            "type":"Services"
        }
    ],
    "sg:phone":"+61 7 5486 4300",
    "sg:postcode":"4580",
    "sg:province":"QLD",
    "sg:tags":[
        "management",
        "property"
    ],
    "wof:name":"First National Real Estate",
    "wof:placetype":"venue"
},
  "geometry": {"coordinates":[153.00079345699999,-25.9164276123],"type":"Point"}
}