{
  "type": "Feature",
  "properties": {
    "addr:full":"Shp2/ 4 Dayboro Rd Petrie QLD 4502",
    "addr:postcode":"4502",
    "addr:street":"Dayboro Rd",
    "iso:country":"AU",
    "sg:address":"Shp2/ 4 Dayboro Rd",
    "sg:city":"Petrie",
    "sg:classifiers":[
        {
            "category":"Personal",
            "subcategory":"Nail Salon",
            "type":"Services"
        }
    ],
    "sg:phone":"+61 7 3889 0392",
    "sg:postcode":"4502",
    "sg:province":"QLD",
    "sg:tags":[
        "artificial"
    ],
    "wof:name":"Ladybirds Club The",
    "wof:placetype":"venue"
},
  "geometry": {"coordinates":[152.974487305,-27.2682857513],"type":"Point"}
}