{
  "type": "Feature",
  "properties": {
    "iso:country":"AU",
    "sg:address":"Dimboola Rd",
    "sg:city":"Horsham",
    "sg:classifiers":[
        {
            "category":"Wholesale",
            "subcategory":"Machinery & Supplies",
            "type":"Manufacturing & Wholesale Goods"
        }
    ],
    "sg:phone":"+61 3 5382 0071",
    "sg:postcode":"3400",
    "sg:province":"VIC",
    "sg:tags":[
        "agricultural"
    ],
    "wof:name":"William Adams Pty Ltd",
    "wof:placetype":"venue"
},
  "geometry": {"coordinates":[142.19880676299999,-36.7116775513],"type":"Point"}
}