{
  "type": "Feature",
  "properties": {
    "addr:full":"20- 26 Danaraga Crt Chambers Flat QLD 4133",
    "addr:housenumber":"26",
    "addr:postcode":"4133",
    "addr:street":"Danaraga Crt",
    "iso:country":"AU",
    "sg:address":"20- 26 Danaraga Crt",
    "sg:city":"Chambers Flat",
    "sg:classifiers":[
        {
            "category":"Building & Trades",
            "subcategory":"Construction",
            "type":"Services"
        }
    ],
    "sg:phone":"+61 417 192 302",
    "sg:postcode":"4133",
    "sg:province":"QLD",
    "sg:tags":[
        "pool",
        "swimming"
    ],
    "wof:name":"Cameo Pools & Pool Finishing",
    "wof:placetype":"venue"
},
  "geometry": {"coordinates":[153.06661987300001,-27.7288913727],"type":"Point"}
}