{
  "type": "Feature",
  "properties": {
    "iso:country":"AU",
    "sg:address":"Unit E37 78 Gibson Ave",
    "sg:city":"Padstow",
    "sg:classifiers":[
        {
            "category":"Professional",
            "subcategory":"Engineering",
            "type":"Services"
        }
    ],
    "sg:phone":"+61 2 9773 9034",
    "sg:postcode":"2211",
    "sg:province":"NSW",
    "sg:tags":[
        "engineer"
    ],
    "wof:name":"L.W.K. Engineering Pty Ltd",
    "wof:placetype":"venue"
},
  "geometry": {"coordinates":[151.027893,-33.940811],"type":"Point"}
}