{
  "type": "Feature",
  "properties": {
    "addr:full":"20 Nattai St Tahmoor NSW 2573",
    "addr:housenumber":"20",
    "addr:postcode":"2573",
    "addr:street":"Nattai St",
    "iso:country":"AU",
    "sg:address":"20 Nattai St",
    "sg:city":"Tahmoor",
    "sg:classifiers":[
        {
            "category":"Farming",
            "subcategory":"Poultry Farm",
            "type":"Manufacturing & Wholesale Goods"
        }
    ],
    "sg:phone":"+61 2 4681 9722",
    "sg:postcode":"2573",
    "sg:province":"NSW",
    "sg:tags":[
        "farmer"
    ],
    "wof:name":"Brian Larkin Laying Pullets",
    "wof:placetype":"venue"
},
  "geometry": {"coordinates":[150.57659912099999,-34.2285614014],"type":"Point"}
}