{
  "type": "Feature",
  "properties": {
    "iso:country":"AU",
    "sg:address":"17 Cairnes Crs",
    "sg:city":"Malvern East",
    "sg:classifiers":[
        {
            "category":"Shopping",
            "subcategory":"Party Supplies",
            "type":"Retail Goods"
        }
    ],
    "sg:phone":"+61 3 9571 5450",
    "sg:postcode":"3145",
    "sg:province":"VIC",
    "sg:tags":[
        "children's"
    ],
    "wof:name":"Spangles Theme Parties",
    "wof:placetype":"venue"
},
  "geometry": {"coordinates":[145.04826355,-37.8754501343],"type":"Point"}
}