{
  "type": "Feature",
  "properties": {
    "addr:full":"6 Wittenoom St Geraldton WA 6530",
    "addr:housenumber":"6",
    "addr:postcode":"6530",
    "addr:street":"Wittenoom St",
    "iso:country":"AU",
    "sg:address":"6 Wittenoom St",
    "sg:city":"Geraldton",
    "sg:classifiers":[
        {
            "category":"Farming",
            "subcategory":"Fish & Marine Products",
            "type":"Manufacturing & Wholesale Goods"
        }
    ],
    "sg:phone":"+61 8 9921 1760",
    "sg:postcode":"6530",
    "sg:province":"WA",
    "sg:tags":[
        "fisherman"
    ],
    "wof:name":"Hewitt R E",
    "wof:placetype":"venue"
},
  "geometry": {"coordinates":[114.619537353,-28.7690944672],"type":"Point"}
}