{
  "type": "Feature",
  "properties": {
    "addr:full":"4 Woodland Drv Reedy Creek QLD 4227",
    "addr:housenumber":"4",
    "addr:postcode":"4227",
    "addr:street":"Woodland Drv",
    "iso:country":"AU",
    "sg:address":"4 Woodland Drv",
    "sg:city":"Reedy Creek",
    "sg:classifiers":[
        {
            "category":"Professional",
            "subcategory":"Art Services",
            "type":"Services"
        }
    ],
    "sg:phone":"+61 7 5593 6635",
    "sg:postcode":"4227",
    "sg:province":"QLD",
    "sg:tags":[
        "artist"
    ],
    "wof:name":"Lisa Borg",
    "wof:placetype":"venue"
},
  "geometry": {"coordinates":[153.40136718799999,-28.1103382111],"type":"Point"}
}