{
  "type": "Feature",
  "properties": {
    "addr:full":"Cnr Falmouth & Quakers Hill Rds Marayong NSW 2148",
    "addr:postcode":"2148",
    "iso:country":"AU",
    "sg:address":"Cnr Falmouth & Quakers Hill Rds",
    "sg:city":"Marayong",
    "sg:classifiers":[
        {
            "category":"Food & Beverages",
            "subcategory":"Supermarket",
            "type":"Retail Goods"
        }
    ],
    "sg:phone":"+61 2 9626 8433",
    "sg:postcode":"2148",
    "sg:province":"NSW",
    "sg:tags":[
        "grocery",
        "store"
    ],
    "wof:name":"Woolworths Ltd",
    "wof:placetype":"venue"
},
  "geometry": {"coordinates":[150.88575744600001,-33.739528656],"type":"Point"}
}