{
  "type": "Feature",
  "properties": {
    "addr:full":"Main Rd Fennell Bay NSW 2283",
    "addr:postcode":"2283",
    "addr:street":"Main Rd",
    "iso:country":"AU",
    "sg:address":"Main Rd",
    "sg:city":"Fennell Bay",
    "sg:classifiers":[
        {
            "category":"Recreation",
            "subcategory":"Boat Charter",
            "type":"Entertainment"
        }
    ],
    "sg:phone":"+61 2 4959 7047",
    "sg:postcode":"2283",
    "sg:province":"NSW",
    "sg:tags":[
        "hire",
        "drive"
    ],
    "wof:name":"Dave & Mals Boat Hire",
    "wof:placetype":"venue"
},
  "geometry": {"coordinates":[151.59994506800001,-32.9927215576],"type":"Point"}
}