{
  "type": "Feature",
  "properties": {
    "iso:country":"AU",
    "sg:address":"14 Daniel St",
    "sg:city":"Caloundra",
    "sg:classifiers":[
        {
            "category":"Building & Trades",
            "subcategory":"Construction",
            "type":"Services"
        }
    ],
    "sg:phone":"+61 7 5492 8244",
    "sg:postcode":"4551",
    "sg:province":"QLD",
    "sg:tags":[
        "contractor"
    ],
    "wof:name":"Besteel Frames Pty Ltd",
    "wof:placetype":"venue"
},
  "geometry": {"coordinates":[153.109130859,-26.7932834625],"type":"Point"}
}