{
  "type": "Feature",
  "properties": {
    "addr:full":"14 Blackwood Rd Mitchelton QLD 4053",
    "addr:housenumber":"14",
    "addr:postcode":"4053",
    "addr:street":"Blackwood Rd",
    "iso:country":"AU",
    "sg:address":"14 Blackwood Rd",
    "sg:city":"Mitchelton",
    "sg:classifiers":[
        {
            "category":"Personal",
            "subcategory":"Beauty Salon",
            "type":"Services"
        }
    ],
    "sg:phone":"+61 7 3355 2494",
    "sg:postcode":"4053",
    "sg:province":"QLD",
    "sg:tags":[
        "hairdresser"
    ],
    "wof:name":"Style Company The",
    "wof:placetype":"venue"
},
  "geometry": {"coordinates":[152.97401428200001,-27.412771225],"type":"Point"}
}