{
  "type": "Feature",
  "properties": {
    "iso:country":"AU",
    "sg:address":"Kiosk 4 Centre Court Paradise Cntr Cavill Ave",
    "sg:city":"Surfers Paradise",
    "sg:classifiers":[
        {
            "category":"Cafe",
            "type":"Food & Drink"
        }
    ],
    "sg:phone":"+61 7 5592 3525",
    "sg:postcode":"4217",
    "sg:province":"QLD",
    "wof:name":"Gloria Jean's Coffees",
    "wof:placetype":"venue"
},
  "geometry": {"coordinates":[153.42901611299999,-28.0018787384],"type":"Point"}
}