{
  "type": "Feature",
  "properties": {
    "addr:full":"250 Newman Rd Geebung QLD 4034",
    "addr:housenumber":"250",
    "addr:postcode":"4034",
    "addr:street":"Newman Rd",
    "iso:country":"AU",
    "sg:address":"250 Newman Rd",
    "sg:city":"Geebung",
    "sg:classifiers":[
        {
            "category":"Education",
            "subcategory":"School",
            "type":"Public Place"
        }
    ],
    "sg:phone":"+61 7 3623 8777",
    "sg:postcode":"4034",
    "sg:province":"QLD",
    "sg:tags":[
        "state",
        "except",
        "nsw"
    ],
    "wof:name":"Geebung Primary",
    "wof:placetype":"venue"
},
  "geometry": {"coordinates":[153.046753,-27.374161],"type":"Point"}
}