{
  "type": "Feature",
  "properties": {
    "addr:full":"95 Tamar St Ballina NSW 2478",
    "addr:housenumber":"95",
    "addr:postcode":"2478",
    "addr:street":"Tamar St",
    "iso:country":"AU",
    "sg:address":"95 Tamar St",
    "sg:city":"Ballina",
    "sg:classifiers":[
        {
            "category":"Banks & Credit Unions",
            "subcategory":"Financial Services",
            "type":"Services"
        }
    ],
    "sg:phone":"+61 2 6686 7600",
    "sg:postcode":"2478",
    "sg:province":"NSW",
    "sg:tags":[
        "annuity",
        "rollover",
        "superannuation",
        "consultant"
    ],
    "wof:name":"RetireInvest",
    "wof:placetype":"venue"
},
  "geometry": {"coordinates":[153.558761597,-28.8682003021],"type":"Point"}
}