{
  "type": "Feature",
  "properties": {
    "iso:country":"AU",
    "sg:address":"4 Grace St",
    "sg:city":"Ferndale",
    "sg:classifiers":[
        {
            "category":"Building & Trades",
            "subcategory":"Construction",
            "type":"Services"
        }
    ],
    "sg:phone":"+61 8 9458 8460",
    "sg:postcode":"6148",
    "sg:province":"WA",
    "sg:tags":[
        "joiner",
        "carpenter"
    ],
    "wof:name":"P F Carpentry & Cabinets",
    "wof:placetype":"venue"
},
  "geometry": {"coordinates":[115.934967,-32.028675],"type":"Point"}
}