{
  "type": "Feature",
  "properties": {
    "iso:country":"AU",
    "sg:address":"200 Wells St",
    "sg:city":"South Melbourne",
    "sg:classifiers":[
        {
            "category":"Real Estate",
            "subcategory":"Real Estate Agent",
            "type":"Services"
        }
    ],
    "sg:phone":"+61 3 9699 7500",
    "sg:postcode":"3205",
    "sg:province":"VIC",
    "wof:name":"Lemon Baxter Pty Ltd",
    "wof:placetype":"venue"
},
  "geometry": {"coordinates":[144.969986,-37.832596],"type":"Point"}
}