{
  "type": "Feature",
  "properties": {
    "iso:country":"AU",
    "sg:address":"2 Whitestone Drv",
    "sg:city":"Austins Ferry",
    "sg:classifiers":[
        {
            "category":"Professional",
            "subcategory":"Engineering",
            "type":"Services"
        }
    ],
    "sg:phone":"+61 3 6249 8799",
    "sg:postcode":"7011",
    "sg:province":"TAS",
    "sg:tags":[
        "civil",
        "engineer"
    ],
    "wof:name":"Andrew Walter Constructions",
    "wof:placetype":"venue"
},
  "geometry": {"coordinates":[147.245407105,-42.7661933899],"type":"Point"}
}