{
  "type": "Feature",
  "properties": {
    "iso:country":"AU",
    "sg:address":"Shop 27 Casuarina Shopng Sq",
    "sg:city":"Casuarina",
    "sg:classifiers":[
        {
            "category":"Shopping",
            "subcategory":"Stationery & Office Supplies",
            "type":"Retail Goods"
        }
    ],
    "sg:phone":"+61 8 8945 6366",
    "sg:postcode":"0810",
    "sg:province":"NT",
    "sg:tags":[
        "merchant",
        "paper"
    ],
    "wof:name":"Copytime",
    "wof:placetype":"venue"
},
  "geometry": {"coordinates":[130.846832275,-12.3787002563],"type":"Point"}
}