{
  "type": "Feature",
  "properties": {
    "addr:full":"22 Mccartin St Leongatha VIC 3953",
    "addr:housenumber":"22",
    "addr:postcode":"3953",
    "addr:street":"Mccartin St",
    "iso:country":"AU",
    "sg:address":"22 Mccartin St",
    "sg:city":"Leongatha",
    "sg:classifiers":[
        {
            "category":"Shopping",
            "subcategory":"Shoes",
            "type":"Retail Goods"
        }
    ],
    "sg:phone":"+61 3 5662 2096",
    "sg:postcode":"3953",
    "sg:province":"VIC",
    "sg:tags":[
        "footwear"
    ],
    "wof:name":"Leongatha ShoeGallery",
    "wof:placetype":"venue"
},
  "geometry": {"coordinates":[145.94557189899999,-38.4764862061],"type":"Point"}
}