{
  "type": "Feature",
  "properties": {
    "iso:country":"AU",
    "sg:address":"Shop 1 Cnr Condon & Neale Sts",
    "sg:city":"Bendigo",
    "sg:classifiers":[
        {
            "category":"Retail",
            "subcategory":"Laundry & Dry Cleaning",
            "type":"Services"
        }
    ],
    "sg:phone":"+61 3 5442 4663",
    "sg:postcode":"3550",
    "sg:province":"VIC",
    "wof:name":"Iron Express & Laundrette",
    "wof:placetype":"venue"
},
  "geometry": {"coordinates":[144.291473389,-36.7678451538],"type":"Point"}
}