{
  "type": "Feature",
  "properties": {
    "iso:country":"AU",
    "sg:address":"98a Denham St",
    "sg:city":"Rockhampton",
    "sg:classifiers":[
        {
            "category":"Fast Food",
            "type":"Food & Drink"
        }
    ],
    "sg:phone":"+61 7 4927 7144",
    "sg:postcode":"4700",
    "sg:province":"QLD",
    "sg:tags":[
        "away",
        "take"
    ],
    "wof:name":"Hong Kong Seafood Restaurant",
    "wof:placetype":"venue"
},
  "geometry": {"coordinates":[150.498535156,-23.3876781464],"type":"Point"}
}