{
  "type": "Feature",
  "properties": {
    "addr:full":"14 Bega Rd Kingston QLD 4114",
    "addr:housenumber":"14",
    "addr:postcode":"4114",
    "addr:street":"Bega Rd",
    "iso:country":"AU",
    "sg:address":"14 Bega Rd",
    "sg:city":"Kingston",
    "sg:classifiers":[
        {
            "category":"Wholesale",
            "subcategory":"Auto Parts",
            "type":"Manufacturing & Wholesale Goods"
        }
    ],
    "sg:phone":"+61 7 3208 5466",
    "sg:postcode":"4114",
    "sg:province":"QLD",
    "sg:tags":[
        "recyclers"
    ],
    "wof:name":"Bega Road Wrecking",
    "wof:placetype":"venue"
},
  "geometry": {"coordinates":[153.117462158,-27.6645908356],"type":"Point"}
}