{
  "type": "Feature",
  "properties": {
    "addr:full":"21 Rugby St West Swan WA 6055",
    "addr:housenumber":"21",
    "addr:postcode":"6055",
    "addr:street":"Rugby St West",
    "iso:country":"AU",
    "sg:address":"21 Rugby St",
    "sg:city":"West Swan",
    "sg:classifiers":[
        {
            "category":"Communications",
            "type":"Services"
        }
    ],
    "sg:phone":"+61 8 9374 0167",
    "sg:postcode":"6055",
    "sg:province":"WA",
    "sg:tags":[
        "equipment",
        "radio"
    ],
    "wof:name":"JBA Engineering Pty Ltd",
    "wof:placetype":"venue"
},
  "geometry": {"coordinates":[115.96498099999999,-31.853531],"type":"Point"}
}