{
  "type": "Feature",
  "properties": {
    "addr:full":"70 Dale St Port Adelaide SA 5015",
    "addr:housenumber":"70",
    "addr:postcode":"5015",
    "addr:street":"Dale St",
    "iso:country":"AU",
    "sg:address":"70 Dale St",
    "sg:city":"Port Adelaide",
    "sg:classifiers":[
        {
            "category":"Professional",
            "subcategory":"Accounting & Tax Preparation",
            "type":"Services"
        }
    ],
    "sg:phone":"+61 8 8241 0713",
    "sg:postcode":"5015",
    "sg:province":"SA",
    "sg:tags":[
        "accountant",
        "auditor"
    ],
    "wof:name":"H&R Block",
    "wof:placetype":"venue"
},
  "geometry": {"coordinates":[138.504364014,-34.8468818665],"type":"Point"}
}