{
  "type": "Feature",
  "properties": {
    "addr:full":"5 Gladstone St Pimlico QLD 4812",
    "addr:housenumber":"5",
    "addr:postcode":"4812",
    "addr:street":"Gladstone St",
    "iso:country":"AU",
    "sg:address":"5 Gladstone St",
    "sg:city":"Pimlico",
    "sg:classifiers":[
        {
            "category":"Professional",
            "subcategory":"Art Services",
            "type":"Services"
        }
    ],
    "sg:phone":"+61 7 4728 4533",
    "sg:postcode":"4812",
    "sg:province":"QLD",
    "sg:tags":[
        "graphic",
        "designer"
    ],
    "wof:name":"Ideazine",
    "wof:placetype":"venue"
},
  "geometry": {"coordinates":[146.79066499999999,-19.283642],"type":"Point"}
}