{
  "type": "Feature",
  "properties": {
    "iso:country":"AU",
    "sg:address":"5 Gladstone St",
    "sg:city":"Pimlico",
    "sg:classifiers":[
        {
            "category":"Professional",
            "subcategory":"Art Services",
            "type":"Services"
        }
    ],
    "sg:phone":"+61 7 4728 4533",
    "sg:postcode":"4812",
    "sg:province":"QLD",
    "sg:tags":[
        "graphic",
        "designer"
    ],
    "wof:name":"Ideazine",
    "wof:placetype":"venue"
},
  "geometry": {"coordinates":[146.790665,-19.283642],"type":"Point"}
}