{
  "type": "Feature",
  "properties": {
    "addr:full":"23 Wellington Rd Morley WA 6062",
    "addr:housenumber":"23",
    "addr:postcode":"6062",
    "addr:street":"Wellington Rd",
    "iso:country":"AU",
    "sg:address":"23 Wellington Rd",
    "sg:city":"Morley",
    "sg:classifiers":[
        {
            "category":"Education",
            "subcategory":"Special Training",
            "type":"Public Place"
        }
    ],
    "sg:phone":"+61 8 9375 8838",
    "sg:postcode":"6062",
    "sg:province":"WA",
    "sg:tags":[
        "tuition-educational"
    ],
    "wof:name":"Top Tots Early Learning Development Centre",
    "wof:placetype":"venue"
},
  "geometry": {"coordinates":[115.895202637,-31.8929653168],"type":"Point"}
}