{
  "type": "Feature",
  "properties": {
    "iso:country":"AU",
    "sg:address":"29- 31 Evans St",
    "sg:city":"Inverell",
    "sg:classifiers":[
        {
            "category":"Autos & Motor Vehicles",
            "subcategory":"Automobile Sales",
            "type":"Retail Goods"
        }
    ],
    "sg:phone":"+61 2 6722 1088",
    "sg:postcode":"2360",
    "sg:province":"NSW",
    "sg:tags":[
        "car",
        "new"
    ],
    "wof:name":"New England Toyota",
    "wof:placetype":"venue"
},
  "geometry": {"coordinates":[151.11392211899999,-29.7751617432],"type":"Point"}
}