{
  "type": "Feature",
  "properties": {
    "addr:full":"109 Pitt St Sydney NSW 2001",
    "addr:housenumber":"109",
    "addr:postcode":"2001",
    "addr:street":"Pitt St",
    "iso:country":"AU",
    "sg:address":"109 Pitt St",
    "sg:city":"Sydney",
    "sg:classifiers":[
        {
            "category":"Organizations",
            "subcategory":"Non-profit Organization",
            "type":"Services"
        }
    ],
    "sg:phone":"+61 1300 362 190",
    "sg:postcode":"2001",
    "sg:province":"NSW",
    "sg:tags":[
        "support",
        "disability",
        "organisation"
    ],
    "wof:name":"MSSA Care Personnel",
    "wof:placetype":"venue"
},
  "geometry": {"coordinates":[151.208450317,-33.8661270142],"type":"Point"}
}