{
  "type": "Feature",
  "properties": {
    "addr:full":"1132 Teven Rd Alstonville NSW 2477",
    "addr:housenumber":"1132",
    "addr:postcode":"2477",
    "addr:street":"Teven Rd",
    "iso:country":"AU",
    "sg:address":"1132 Teven Rd",
    "sg:city":"Alstonville",
    "sg:classifiers":[
        {
            "category":"Farming",
            "subcategory":"Nursery",
            "type":"Manufacturing & Wholesale Goods"
        }
    ],
    "sg:phone":"+61 2 6628 3952",
    "sg:postcode":"2477",
    "sg:province":"NSW",
    "wof:name":"Natures Decor",
    "wof:placetype":"venue"
},
  "geometry": {"coordinates":[153.46287536599999,-28.8210105896],"type":"Point"}
}