{
  "type": "Feature",
  "properties": {
    "addr:full":"26 The Entrance Rd The Entrance NSW 2261",
    "addr:housenumber":"26",
    "addr:postcode":"2261",
    "addr:street":"The Entrance Rd",
    "iso:country":"AU",
    "sg:address":"26 The Entrance Rd",
    "sg:city":"The Entrance",
    "sg:classifiers":[
        {
            "category":"Personal",
            "subcategory":"Tanning Parlor",
            "type":"Services"
        }
    ],
    "sg:phone":"+61 2 4332 2444",
    "sg:postcode":"2261",
    "sg:province":"NSW",
    "sg:tags":[
        "solarium"
    ],
    "wof:name":"Bliss Hair Beauty Body",
    "wof:placetype":"venue"
},
  "geometry": {"coordinates":[151.49754300000001,-33.343369],"type":"Point"}
}