{
  "type": "Feature",
  "properties": {
    "iso:country":"AU",
    "sg:address":"Yeates Crs",
    "sg:city":"Dysart",
    "sg:classifiers":[
        {
            "category":"Social Services",
            "subcategory":"Child Care",
            "type":"Services"
        }
    ],
    "sg:phone":"+61 7 4958 1840",
    "sg:postcode":"4745",
    "sg:province":"QLD",
    "wof:name":"Dysart Daycare/Neighbourhood Centre",
    "wof:placetype":"venue"
},
  "geometry": {"coordinates":[148.33836400000001,-22.59236],"type":"Point"}
}