{
  "type": "Feature",
  "properties": {
    "iso:country":"AU",
    "sg:address":"112a Scarborough St",
    "sg:city":"Southport",
    "sg:classifiers":[
        {
            "category":"Professional",
            "subcategory":"Computer Services",
            "type":"Services"
        }
    ],
    "sg:phone":"+61 7 5526 4116",
    "sg:postcode":"4215",
    "sg:province":"QLD",
    "sg:tags":[
        "package",
        "software"
    ],
    "wof:name":"Datatrue International Pty Ltd",
    "wof:placetype":"venue"
},
  "geometry": {"coordinates":[153.41305542000001,-27.9661102295],"type":"Point"}
}