{
  "type": "Feature",
  "properties": {
    "addr:full":"53 Summerville Crs Noosa Heads QLD 4567",
    "addr:housenumber":"53",
    "addr:postcode":"4567",
    "addr:street":"Summerville Crs",
    "iso:country":"AU",
    "sg:address":"53 Summerville Crs",
    "sg:city":"Noosa Heads",
    "sg:classifiers":[
        {
            "category":"Mining & Drilling",
            "type":"Manufacturing & Wholesale Goods"
        }
    ],
    "sg:phone":"+61 418 259 508",
    "sg:postcode":"4567",
    "sg:province":"QLD",
    "sg:tags":[
        "boring",
        "contractor"
    ],
    "wof:name":"Mavtech Drilling",
    "wof:placetype":"venue"
},
  "geometry": {"coordinates":[153.086105347,-26.3990192413],"type":"Point"}
}