{
  "type": "Feature",
  "properties": {
    "addr:full":"302- 308 Wyndham St Shepparton VIC 3630",
    "addr:housenumber":"302 308",
    "addr:postcode":"3630",
    "addr:street":"Wyndham St",
    "iso:country":"AU",
    "sg:address":"302- 308 Wyndham St",
    "sg:city":"Shepparton",
    "sg:classifiers":[
        {
            "category":"Fast Food",
            "type":"Food & Drink"
        }
    ],
    "sg:phone":"+61 3 5821 3737",
    "sg:postcode":"3630",
    "sg:province":"VIC",
    "sg:tags":[
        "away",
        "take"
    ],
    "wof:name":"Shepparton Family Restaurant",
    "wof:placetype":"venue"
},
  "geometry": {"coordinates":[145.39941406200001,-36.3798828125],"type":"Point"}
}