{
  "type": "Feature",
  "properties": {
    "iso:country":"AU",
    "sg:address":"24 Maple Ave",
    "sg:city":"Forestville",
    "sg:classifiers":[
        {
            "category":"Military Area",
            "subcategory":"Air Force Base",
            "type":"Public Place"
        }
    ],
    "sg:phone":"+61 8 8371 4788",
    "sg:postcode":"5035",
    "sg:province":"SA",
    "sg:tags":[
        "water",
        "distilled"
    ],
    "wof:name":"Rowater Australia",
    "wof:placetype":"venue"
},
  "geometry": {"coordinates":[138.58177185100001,-34.947845459],"type":"Point"}
}