{
  "type": "Feature",
  "properties": {
    "addr:full":"Phillip St Kenilworth QLD 4574",
    "addr:postcode":"4574",
    "addr:street":"Phillip St",
    "iso:country":"AU",
    "sg:address":"Phillip St",
    "sg:city":"Kenilworth",
    "sg:classifiers":[
        {
            "category":"Government",
            "subcategory":"Fire Station",
            "type":"Public Place"
        }
    ],
    "sg:phone":"+61 7 5446 0249",
    "sg:postcode":"4574",
    "sg:province":"QLD",
    "sg:tags":[
        "brigade"
    ],
    "wof:name":"Fire Brigades",
    "wof:placetype":"venue"
},
  "geometry": {"coordinates":[152.72695899999999,-26.594873],"type":"Point"}
}