{
  "type": "Feature",
  "properties": {
    "iso:country":"AU",
    "sg:address":"Phillip St",
    "sg:city":"Kenilworth",
    "sg:classifiers":[
        {
            "category":"Government",
            "subcategory":"Fire Station",
            "type":"Public Place"
        }
    ],
    "sg:phone":"+61 7 5446 0249",
    "sg:postcode":"4574",
    "sg:province":"QLD",
    "sg:tags":[
        "brigade"
    ],
    "wof:name":"Fire Brigades",
    "wof:placetype":"venue"
},
  "geometry": {"coordinates":[152.726959,-26.594873],"type":"Point"}
}