{
  "type": "Feature",
  "properties": {
    "iso:country":"AU",
    "sg:address":"28 Bessie St",
    "sg:city":"South Grafton",
    "sg:classifiers":[
        {
            "category":"Retail",
            "subcategory":"Storage",
            "type":"Services"
        }
    ],
    "sg:phone":"+61 2 6643 3384",
    "sg:postcode":"2460",
    "sg:province":"NSW",
    "wof:name":"S & D Welch Removals & Storage",
    "wof:placetype":"venue"
},
  "geometry": {"coordinates":[152.942016602,-29.7072200775],"type":"Point"}
}