{
  "type": "Feature",
  "properties": {
    "addr:full":"16 Isa St Fyshwick ACT 2609",
    "addr:housenumber":"16",
    "addr:postcode":"2609",
    "addr:street":"Isa St",
    "iso:country":"AU",
    "sg:address":"16 Isa St",
    "sg:city":"Fyshwick",
    "sg:classifiers":[
        {
            "category":"Retail",
            "subcategory":"Auto Repair",
            "type":"Services"
        }
    ],
    "sg:phone":"+61 2 6280 5683",
    "sg:postcode":"2609",
    "sg:province":"ACT",
    "sg:tags":[
        "repairer",
        "motor",
        "engineer"
    ],
    "wof:name":"Farrell Jim & Son Smash Repairs",
    "wof:placetype":"venue"
},
  "geometry": {"coordinates":[149.17202758799999,-35.3270759583],"type":"Point"}
}