{
  "type": "Feature",
  "properties": {
    "addr:full":"59 Oaktree Drv Hampton Park VIC 3976",
    "addr:housenumber":"59",
    "addr:postcode":"3976",
    "addr:street":"Oaktree Drv",
    "iso:country":"AU",
    "sg:address":"59 Oaktree Drv",
    "sg:city":"Hampton Park",
    "sg:classifiers":[
        {
            "category":"Health Services",
            "subcategory":"Dentist",
            "type":"Services"
        }
    ],
    "sg:phone":"+61 3 8787 8981",
    "sg:postcode":"3976",
    "sg:province":"VIC",
    "wof:name":"Oaktree Family Dentist",
    "wof:placetype":"venue"
},
  "geometry": {"coordinates":[145.26165771500001,-38.0234642029],"type":"Point"}
}