{
  "type": "Feature",
  "properties": {
    "iso:country":"AU",
    "sg:address":"405 Campbell St",
    "sg:city":"Swan Hill",
    "sg:classifiers":[
        {
            "category":"Retail",
            "subcategory":"Event Space",
            "type":"Services"
        }
    ],
    "sg:phone":"+61 1800 654 576",
    "sg:postcode":"3585",
    "sg:province":"NSW",
    "sg:tags":[
        "venue",
        "reception",
        "wedding"
    ],
    "wof:name":"Sundowner",
    "wof:placetype":"venue"
},
  "geometry": {"coordinates":[143.56189,-35.346497],"type":"Point"}
}