{
  "type": "Feature",
  "properties": {
    "iso:country":"AU",
    "sg:address":"Banool Rd",
    "sg:city":"Tallangatta",
    "sg:classifiers":[
        {
            "category":"Social Services",
            "subcategory":"Child Care",
            "type":"Services"
        }
    ],
    "sg:phone":"+61 2 6071 2215",
    "sg:postcode":"3700",
    "sg:province":"VIC",
    "sg:tags":[
        "support",
        "health"
    ],
    "wof:name":"Maternal & Child Health Centres",
    "wof:placetype":"venue"
},
  "geometry": {"coordinates":[147.17796325699999,-36.2174987793],"type":"Point"}
}