{
  "type": "Feature",
  "properties": {
    "addr:full":"5 Central St Broadmeadows VIC 3047",
    "addr:housenumber":"5",
    "addr:postcode":"3047",
    "addr:street":"Central St",
    "iso:country":"AU",
    "sg:address":"5 Central St",
    "sg:city":"Broadmeadows",
    "sg:classifiers":[
        {
            "category":"Fast Food",
            "type":"Food & Drink"
        }
    ],
    "sg:phone":"+61 3 9302 3541",
    "sg:postcode":"3047",
    "sg:province":"VIC",
    "sg:tags":[
        "away",
        "take"
    ],
    "wof:name":"Central Grove Fish & Chips",
    "wof:placetype":"venue"
},
  "geometry": {"coordinates":[144.933151245,-37.6865234375],"type":"Point"}
}