{
  "type": "Feature",
  "properties": {
    "iso:country":"AU",
    "sg:address":"Factory 7/ 8 Brock St",
    "sg:city":"Thomastown",
    "sg:classifiers":[
        {
            "category":"Retail",
            "subcategory":"Auto Repair",
            "type":"Services"
        }
    ],
    "sg:phone":"+61 3 9464 4388",
    "sg:postcode":"3074",
    "sg:province":"VIC",
    "sg:tags":[
        "repairer",
        "motor",
        "engineer"
    ],
    "wof:name":"Brima Automotive Repairs Pty Ltd",
    "wof:placetype":"venue"
},
  "geometry": {"coordinates":[145.02537536599999,-37.6890335083],"type":"Point"}
}