{
  "type": "Feature",
  "properties": {
    "addr:full":"39 Windsor St Richmond NSW 2753",
    "addr:housenumber":"39",
    "addr:postcode":"2753",
    "addr:street":"Windsor St",
    "iso:country":"AU",
    "sg:address":"39 Windsor St",
    "sg:city":"Richmond",
    "sg:classifiers":[
        {
            "category":"Personal",
            "subcategory":"Day Spa",
            "type":"Services"
        }
    ],
    "sg:phone":"+61 2 4578 5505",
    "sg:postcode":"2753",
    "sg:province":"NSW",
    "wof:name":"Panache Hair Health & Beauty",
    "wof:placetype":"venue"
},
  "geometry": {"coordinates":[150.75683593799999,-33.599445343],"type":"Point"}
}