{
  "type": "Feature",
  "properties": {
    "addr:full":"468 South Pine Rd Everton Park QLD 4053",
    "addr:housenumber":"468",
    "addr:postcode":"4053",
    "addr:street":"South Pine Rd",
    "iso:country":"AU",
    "sg:address":"468 South Pine Rd",
    "sg:city":"Everton Park",
    "sg:classifiers":[
        {
            "category":"Professional",
            "subcategory":"Accounting & Tax Preparation",
            "type":"Services"
        }
    ],
    "sg:phone":"+61 7 3855 3722",
    "sg:postcode":"4053",
    "sg:province":"QLD",
    "sg:tags":[
        "accountant",
        "auditor"
    ],
    "wof:name":"Rush Patrick",
    "wof:placetype":"venue"
},
  "geometry": {"coordinates":[152.99073791500001,-27.4082145691],"type":"Point"}
}