{
  "type": "Feature",
  "properties": {
    "addr:full":"7/ 177 Bannister Rd Canning Vale WA 6155",
    "addr:housenumber":"/ 177",
    "addr:postcode":"6155",
    "addr:street":"Bannister Rd",
    "iso:country":"AU",
    "sg:address":"7/ 177 Bannister Rd",
    "sg:city":"Canning Vale",
    "sg:classifiers":[
        {
            "category":"Professional",
            "subcategory":"Printing & Photocopies",
            "type":"Services"
        }
    ],
    "sg:phone":"+61 8 9256 4988",
    "sg:postcode":"6155",
    "sg:province":"WA",
    "sg:tags":[
        "photocopying"
    ],
    "wof:name":"Worldwide Online Printing",
    "wof:placetype":"venue"
},
  "geometry": {"coordinates":[115.905693,-32.060989],"type":"Point"}
}