{
  "type": "Feature",
  "properties": {
    "addr:full":"16 Swan Rd Morwell VIC 3840",
    "addr:housenumber":"16",
    "addr:postcode":"3840",
    "addr:street":"Swan Rd",
    "iso:country":"AU",
    "sg:address":"16 Swan Rd",
    "sg:city":"Morwell",
    "sg:classifiers":[
        {
            "category":"Professional",
            "subcategory":"Art Services",
            "type":"Services"
        }
    ],
    "sg:phone":"+61 3 5134 8955",
    "sg:postcode":"3840",
    "sg:province":"VIC",
    "sg:tags":[
        "decorator",
        "painter"
    ],
    "wof:name":"Programmed Maintenance Services Limited",
    "wof:placetype":"venue"
},
  "geometry": {"coordinates":[146.44232177699999,-38.2419319153],"type":"Point"}
}