{
  "type": "Feature",
  "properties": {
    "addr:full":"29 Woodward St Normanton QLD 4890",
    "addr:housenumber":"29",
    "addr:postcode":"4890",
    "addr:street":"Woodward St",
    "iso:country":"AU",
    "sg:address":"29 Woodward St",
    "sg:city":"Normanton",
    "sg:classifiers":[
        {
            "category":"Food & Beverages",
            "subcategory":"Groceries & Convenience Stores",
            "type":"Retail Goods"
        }
    ],
    "sg:phone":"+61 7 4745 1235",
    "sg:postcode":"4890",
    "sg:province":"QLD",
    "wof:name":"Normanton Traders",
    "wof:placetype":"venue"
},
  "geometry": {"coordinates":[141.07586669899999,-17.6718578339],"type":"Point"}
}