{
  "type": "Feature",
  "properties": {
    "addr:full":"2a Hillview Rd Eastwood NSW 2122",
    "addr:housenumber":"2a",
    "addr:postcode":"2122",
    "addr:street":"Hillview Rd",
    "iso:country":"AU",
    "sg:address":"2a Hillview Rd",
    "sg:city":"Eastwood",
    "sg:classifiers":[
        {
            "category":"Professional",
            "subcategory":"Lawyer & Legal Services",
            "type":"Services"
        }
    ],
    "sg:phone":"+61 2 9858 1444",
    "sg:postcode":"2122",
    "sg:province":"NSW",
    "sg:tags":[
        "wills",
        "probate",
        "estate"
    ],
    "wof:name":"Pain David & Co",
    "wof:placetype":"venue"
},
  "geometry": {"coordinates":[151.08012390100001,-33.7895507812],"type":"Point"}
}