{
  "type": "Feature",
  "properties": {
    "addr:full":"3/ 13 Villiers Drv Currumbin QLD 4223",
    "addr:housenumber":"/ 13",
    "addr:postcode":"4223",
    "addr:street":"Villiers Drv",
    "iso:country":"AU",
    "sg:address":"3/ 13 Villiers Drv",
    "sg:city":"Currumbin",
    "sg:classifiers":[
        {
            "category":"Wholesale",
            "subcategory":"Metals & Minerals",
            "type":"Manufacturing & Wholesale Goods"
        }
    ],
    "sg:phone":"+61 7 5598 2388",
    "sg:postcode":"4223",
    "sg:province":"QLD",
    "sg:tags":[
        "steel",
        "stainless",
        "product",
        "equipment"
    ],
    "wof:name":"Ace Fasteners",
    "wof:placetype":"venue"
},
  "geometry": {"coordinates":[153.47383117699999,-28.1511001587],"type":"Point"}
}