{
  "type": "Feature",
  "properties": {
    "iso:country":"AU",
    "sg:address":"7 Mortimer Ave",
    "sg:city":"Mt Stuart",
    "sg:classifiers":[
        {
            "category":"Building & Trades",
            "subcategory":"Construction",
            "type":"Services"
        }
    ],
    "sg:phone":"+61 3 6272 0706",
    "sg:postcode":"7000",
    "sg:province":"TAS",
    "sg:tags":[
        "contractor"
    ],
    "wof:name":"Sherrin Development Pty Ltd",
    "wof:placetype":"venue"
},
  "geometry": {"coordinates":[147.308868408,-42.8686904907],"type":"Point"}
}