{
  "type": "Feature",
  "properties": {
    "addr:full":"Level 2 236 Bourke Steet Myer Department Store Melbourne VIC 3000",
    "addr:housenumber":"236",
    "addr:postcode":"3000",
    "addr:street":"Bourke Steet",
    "iso:country":"AU",
    "sg:address":"Level 2 236",
    "sg:city":"Bourke Steet Myer Department Store Melbourne",
    "sg:classifiers":[
        {
            "category":"Personal",
            "subcategory":"Shoe Repair & Shine",
            "type":"Services"
        }
    ],
    "sg:phone":"+61 3 9661 2109",
    "sg:postcode":"3000",
    "sg:province":"VIC",
    "sg:tags":[
        "footwear"
    ],
    "wof:name":"Cavallo Nero Quality Shoe Repairs",
    "wof:placetype":"venue"
},
  "geometry": {"coordinates":[144.966064453,-37.8132553101],"type":"Point"}
}