{
  "type": "Feature",
  "properties": {
    "addr:full":"78 Richmond Rd Westbourne Park SA 5041",
    "addr:housenumber":"78",
    "addr:postcode":"5041",
    "addr:street":"Richmond Rd",
    "iso:country":"AU",
    "sg:address":"78 Richmond Rd",
    "sg:city":"Westbourne Park",
    "sg:classifiers":[
        {
            "category":"Professional",
            "subcategory":"Art Services",
            "type":"Services"
        }
    ],
    "sg:phone":"+61 8 8357 1568",
    "sg:postcode":"5041",
    "sg:province":"SA",
    "sg:tags":[
        "decorator",
        "painter"
    ],
    "wof:name":"K & J Painting",
    "wof:placetype":"venue"
},
  "geometry": {"coordinates":[138.59854100000001,-34.970829],"type":"Point"}
}