{
  "type": "Feature",
  "properties": {
    "iso:country":"AU",
    "sg:address":"57 St Albans Rd",
    "sg:city":"East Geelong",
    "sg:classifiers":[
        {
            "category":"Shopping",
            "type":"Retail Goods"
        }
    ],
    "sg:phone":"+61 3 5223 2276",
    "sg:postcode":"3219",
    "sg:province":"VIC",
    "sg:tags":[
        "new age",
        "product"
    ],
    "wof:name":"Gallery Of Enlightenment",
    "wof:placetype":"venue"
},
  "geometry": {"coordinates":[144.37272644000001,-38.1627616882],"type":"Point"}
}