{
  "type": "Feature",
  "properties": {
    "iso:country":"AU",
    "sg:address":"4 Tattersall Rd",
    "sg:city":"Blacktown",
    "sg:classifiers":[
        {
            "category":"Professional",
            "subcategory":"Engineering",
            "type":"Services"
        }
    ],
    "sg:phone":"+61 2 9621 1428",
    "sg:postcode":"2148",
    "sg:province":"NSW",
    "sg:tags":[
        "consulting",
        "engineer"
    ],
    "wof:name":"A. D'Urso & Associates Pty Ltd",
    "wof:placetype":"venue"
},
  "geometry": {"coordinates":[150.915359497,-33.7491226196],"type":"Point"}
}