{
  "type": "Feature",
  "properties": {
    "addr:full":"12 Rio St Bayswater WA 6053",
    "addr:housenumber":"12",
    "addr:postcode":"6053",
    "addr:street":"Rio St",
    "iso:country":"AU",
    "sg:address":"12 Rio St",
    "sg:city":"Bayswater",
    "sg:classifiers":[
        {
            "category":"Wholesale",
            "subcategory":"Machinery & Supplies",
            "type":"Manufacturing & Wholesale Goods"
        }
    ],
    "sg:phone":"+61 8 9272 1189",
    "sg:postcode":"6053",
    "sg:province":"WA",
    "sg:tags":[
        "equipment",
        "welding"
    ],
    "wof:name":"Dyna Fusion Industries",
    "wof:placetype":"venue"
},
  "geometry": {"coordinates":[115.921882629,-31.9111499786],"type":"Point"}
}