{
  "type": "Feature",
  "properties": {
    "iso:country":"AU",
    "sg:address":"25 Holmes Rd",
    "sg:city":"Moonee Ponds",
    "sg:classifiers":[
        {
            "category":"Personal",
            "subcategory":"Beauty Salon",
            "type":"Services"
        }
    ],
    "sg:phone":"+61 3 9375 4990",
    "sg:postcode":"3039",
    "sg:province":"VIC",
    "sg:tags":[
        "hairdresser"
    ],
    "wof:name":"Flounces",
    "wof:placetype":"venue"
},
  "geometry": {"coordinates":[144.91833500000001,-37.766567],"type":"Point"}
}