{
  "type": "Feature",
  "properties": {
    "addr:full":"Shop 5a Ballajura Shopng Cntr Ballajura WA 6066",
    "addr:housenumber":"shop 5a",
    "addr:postcode":"6066",
    "iso:country":"AU",
    "sg:address":"Shop 5a Ballajura Shopng Cntr",
    "sg:city":"Ballajura",
    "sg:classifiers":[
        {
            "category":"Personal",
            "subcategory":"Beauty Salon",
            "type":"Services"
        }
    ],
    "sg:phone":"+61 8 9249 3626",
    "sg:postcode":"6066",
    "sg:province":"WA",
    "sg:tags":[
        "hairdresser"
    ],
    "wof:name":"Trim For Him And Her Hair Design",
    "wof:placetype":"venue"
},
  "geometry": {"coordinates":[115.897216797,-31.8382892609],"type":"Point"}
}