{
  "type": "Feature",
  "properties": {
    "addr:full":"16 Hall St Newcastle West NSW 2302",
    "addr:housenumber":"16",
    "addr:postcode":"2302",
    "addr:street":"Hall St",
    "iso:country":"AU",
    "sg:address":"16 Hall St",
    "sg:city":"Newcastle West",
    "sg:classifiers":[
        {
            "category":"Retail",
            "subcategory":"Auto Repair",
            "type":"Services"
        }
    ],
    "sg:phone":"+61 2 4929 1318",
    "sg:postcode":"2302",
    "sg:province":"NSW",
    "sg:tags":[
        "repairer",
        "motor",
        "engineer"
    ],
    "wof:name":"Duncan & West Automotive Repairers",
    "wof:placetype":"venue"
},
  "geometry": {"coordinates":[151.76402300000001,-32.929691],"type":"Point"}
}