{
  "type": "Feature",
  "properties": {
    "iso:country":"AU",
    "sg:address":"35 Dukes Hwy",
    "sg:city":"Bordertown",
    "sg:classifiers":[
        {
            "category":"Insurance",
            "subcategory":"Hazard Insurance",
            "type":"Services"
        }
    ],
    "sg:phone":"+61 8 8752 1777",
    "sg:postcode":"5268",
    "sg:province":"SA",
    "sg:tags":[
        "fire",
        "accident",
        "marine"
    ],
    "wof:name":"CGU Insuarnce",
    "wof:placetype":"venue"
},
  "geometry": {"coordinates":[140.77311700000001,-36.306454],"type":"Point"}
}