{
  "type": "Feature",
  "properties": {
    "addr:full":"262 Waterloo Rd Collingwood VIC 3066",
    "addr:housenumber":"262",
    "addr:postcode":"3066",
    "addr:street":"Waterloo Rd",
    "iso:country":"AU",
    "sg:address":"262 Waterloo Rd",
    "sg:city":"Collingwood",
    "sg:classifiers":[
        {
            "category":"Manufacturing",
            "subcategory":"Apparel",
            "type":"Manufacturing & Wholesale Goods"
        }
    ],
    "sg:phone":"+61 3 9419 7688",
    "sg:postcode":"3066",
    "sg:province":"VIC",
    "sg:tags":[
        "makers-up",
        "clothing"
    ],
    "wof:name":"Cam Fashions Pty Ltd",
    "wof:placetype":"venue"
},
  "geometry": {"coordinates":[144.98716735799999,-37.806224823],"type":"Point"}
}