{
  "type": "Feature",
  "properties": {
    "addr:full":"5 Pioneer Ave Thornleigh NSW 2120",
    "addr:housenumber":"5",
    "addr:postcode":"2120",
    "addr:street":"Pioneer Ave",
    "iso:country":"AU",
    "sg:address":"5 Pioneer Ave",
    "sg:city":"Thornleigh",
    "sg:classifiers":[
        {
            "category":"Retail",
            "subcategory":"Auto Repair",
            "type":"Services"
        }
    ],
    "sg:phone":"+61 2 9980 8855",
    "sg:postcode":"2120",
    "sg:province":"NSW",
    "sg:tags":[
        "repairer",
        "motor",
        "engineer"
    ],
    "wof:name":"Mannell Motors",
    "wof:placetype":"venue"
},
  "geometry": {"coordinates":[151.08413696299999,-33.7246398926],"type":"Point"}
}