{
  "type": "Feature",
  "properties": {
    "addr:full":"75 Albany St Coffs Harbour NSW 2450",
    "addr:housenumber":"75",
    "addr:postcode":"2450",
    "addr:street":"Albany St",
    "iso:country":"AU",
    "sg:address":"75 Albany St",
    "sg:city":"Coffs Harbour",
    "sg:classifiers":[
        {
            "category":"Health Services",
            "subcategory":"Doctor",
            "type":"Services"
        }
    ],
    "sg:phone":"+61 2 6651 3824",
    "sg:postcode":"2450",
    "sg:province":"NSW",
    "sg:tags":[
        "podiatrist"
    ],
    "wof:name":"Jennifer Kitchen",
    "wof:placetype":"venue"
},
  "geometry": {"coordinates":[153.116364,-30.300825],"type":"Point"}
}