{
  "type": "Feature",
  "properties": {
    "addr:full":"Shop 45 Mill Park Stables Shopng Cntr Mill Park VIC 3082",
    "addr:housenumber":"shop 45",
    "addr:postcode":"3082",
    "iso:country":"AU",
    "sg:address":"Shop 45",
    "sg:city":"Mill Park Stables Shopng Cntr Mill Park",
    "sg:classifiers":[
        {
            "category":"Real Estate",
            "subcategory":"Real Estate Agent",
            "type":"Services"
        }
    ],
    "sg:phone":"+61 3 9404 4955",
    "sg:postcode":"3082",
    "sg:province":"VIC",
    "wof:name":"Love Real Estate",
    "wof:placetype":"venue"
},
  "geometry": {"coordinates":[145.06312560999999,-37.6774559021],"type":"Point"}
}