{
  "type": "Feature",
  "properties": {
    "addr:full":"Suite 1311/ 183 Kent St Sydney NSW 2000",
    "addr:housenumber":"1311 / 183",
    "addr:postcode":"2000",
    "addr:street":"Kent St",
    "iso:country":"AU",
    "sg:address":"Suite 1311/ 183 Kent St",
    "sg:city":"Sydney",
    "sg:classifiers":[
        {
            "category":"Professional",
            "subcategory":"Accounting & Tax Preparation",
            "type":"Services"
        }
    ],
    "sg:phone":"+61 2 9251 8222",
    "sg:postcode":"2000",
    "sg:province":"NSW",
    "sg:tags":[
        "consultant",
        "taxation"
    ],
    "wof:name":"Evans & Co Accounting Services",
    "wof:placetype":"venue"
},
  "geometry": {"coordinates":[151.20370483400001,-33.8628120422],"type":"Point"}
}