{
  "type": "Feature",
  "properties": {
    "iso:country":"AU",
    "sg:address":"Montgomery St",
    "sg:city":"Skipton",
    "sg:classifiers":[
        {
            "category":"Social Services",
            "subcategory":"Child Care",
            "type":"Services"
        }
    ],
    "sg:phone":"+61 3 5340 2233",
    "sg:postcode":"3361",
    "sg:province":"VIC",
    "sg:tags":[
        "support",
        "health"
    ],
    "wof:name":"Maternal & Child Health Centres",
    "wof:placetype":"venue"
},
  "geometry": {"coordinates":[143.36431884800001,-37.6883201599],"type":"Point"}
}