{
  "type": "Feature",
  "properties": {
    "iso:country":"AU",
    "sg:address":"30 Red House Crs",
    "sg:city":"McGraths Hill",
    "sg:classifiers":[
        {
            "category":"Real Estate",
            "subcategory":"Surveying",
            "type":"Services"
        }
    ],
    "sg:phone":"+61 2 4577 5020",
    "sg:postcode":"2756",
    "sg:province":"NSW",
    "sg:tags":[
        "surveyor",
        "land"
    ],
    "wof:name":"D J Hore & Associates",
    "wof:placetype":"venue"
},
  "geometry": {"coordinates":[150.84263610799999,-33.6120681763],"type":"Point"}
}