{
  "type": "Feature",
  "properties": {
    "addr:full":"152 Cooper St Essendon VIC 3040",
    "addr:housenumber":"152",
    "addr:postcode":"3040",
    "addr:street":"Cooper St",
    "iso:country":"AU",
    "sg:address":"152 Cooper St",
    "sg:city":"Essendon",
    "sg:classifiers":[
        {
            "category":"Social Services",
            "subcategory":"Retirement Home",
            "type":"Services"
        }
    ],
    "sg:phone":"+61 3 9379 4006",
    "sg:postcode":"3040",
    "sg:province":"VIC",
    "sg:tags":[
        "village"
    ],
    "wof:name":"Windermere Retirement Lodge",
    "wof:placetype":"venue"
},
  "geometry": {"coordinates":[144.89935302699999,-37.7402153015],"type":"Point"}
}