{
  "type": "Feature",
  "properties": {
    "addr:full":"PO Box 43420 Casuarina NT 0811",
    "addr:postcode":"nt 0811",
    "iso:country":"AU",
    "sg:address":"PO Box 43420",
    "sg:city":"Casuarina",
    "sg:classifiers":[
        {
            "category":"Professional",
            "subcategory":"Business Services",
            "type":"Services"
        }
    ],
    "sg:phone":"+61 407 189 521",
    "sg:postcode":"0811",
    "sg:province":"NT",
    "sg:tags":[
        "drafting"
    ],
    "wof:name":"Byrne Design & Drafting Pty Ltd",
    "wof:placetype":"venue"
},
  "geometry": {"coordinates":[130.858886719,-12.3764762878],"type":"Point"}
}