{
  "type": "Feature",
  "properties": {
    "iso:country":"AU",
    "sg:address":"Shop 20, Rapid Creek Business Village",
    "sg:city":"Rapid Creek",
    "sg:classifiers":[
        {
            "category":"Organizations",
            "subcategory":"Community Association",
            "type":"Services"
        }
    ],
    "sg:phone":"+61 8 8985 1085",
    "sg:postcode":"0810",
    "sg:province":"NT",
    "sg:tags":[
        "organisation",
        "family",
        "welfare"
    ],
    "wof:name":"Kidsafe NT",
    "wof:placetype":"venue"
},
  "geometry": {"coordinates":[130.86451721200001,-12.3855161667],"type":"Point"}
}