{
  "type": "Feature",
  "properties": {
    "addr:full":"49 Archer St Pearsall WA 6065",
    "addr:housenumber":"49",
    "addr:postcode":"6065",
    "addr:street":"Archer St",
    "iso:country":"AU",
    "sg:address":"49 Archer St",
    "sg:city":"Pearsall",
    "sg:classifiers":[
        {
            "category":"Manufacturing",
            "subcategory":"Food",
            "type":"Manufacturing & Wholesale Goods"
        }
    ],
    "sg:phone":"+61 8 9405 1784",
    "sg:postcode":"6065",
    "sg:province":"WA",
    "sg:tags":[
        "function",
        "catering"
    ],
    "wof:name":"The Great Australian Hamburger",
    "wof:placetype":"venue"
},
  "geometry": {"coordinates":[115.813491821,-31.7808666229],"type":"Point"}
}