{
  "type": "Feature",
  "properties": {
    "addr:full":"22 Havilah Rd Long Gully VIC 3550",
    "addr:housenumber":"22",
    "addr:postcode":"3550",
    "addr:street":"Havilah Rd",
    "iso:country":"AU",
    "sg:address":"22 Havilah Rd",
    "sg:city":"Long Gully",
    "sg:classifiers":[
        {
            "category":"Arena",
            "subcategory":"Sports Club",
            "type":"Entertainment"
        }
    ],
    "sg:phone":"+61 413 284 610",
    "sg:postcode":"3550",
    "sg:province":"VIC",
    "sg:tags":[
        "defence",
        "supply",
        "self",
        "instruction",
        "martial art"
    ],
    "wof:name":"Arnis Eskrima Kali",
    "wof:placetype":"venue"
},
  "geometry": {"coordinates":[144.262161255,-36.7463607788],"type":"Point"}
}