{
  "type": "Feature",
  "properties": {
    "addr:full":"1b George St Mortdale NSW 2223",
    "addr:housenumber":"1b",
    "addr:postcode":"2223",
    "addr:street":"George St",
    "iso:country":"AU",
    "sg:address":"1b George St",
    "sg:city":"Mortdale",
    "sg:classifiers":[
        {
            "category":"Personal",
            "subcategory":"Beauty Salon",
            "type":"Services"
        }
    ],
    "sg:phone":"+61 2 9585 1130",
    "sg:postcode":"2223",
    "sg:province":"NSW",
    "sg:tags":[
        "hairdresser"
    ],
    "wof:name":"Sam's Top Cut",
    "wof:placetype":"venue"
},
  "geometry": {"coordinates":[151.08001709000001,-33.9727401733],"type":"Point"}
}