{
  "type": "Feature",
  "properties": {
    "addr:full":"325 Clarendon St South Melbourne VIC 3205",
    "addr:housenumber":"325",
    "addr:postcode":"3205",
    "addr:street":"Clarendon St",
    "iso:country":"AU",
    "sg:address":"325 Clarendon St",
    "sg:city":"South Melbourne",
    "sg:classifiers":[
        {
            "category":"Education",
            "subcategory":"School",
            "type":"Public Place"
        }
    ],
    "sg:phone":"+61 3 9690 5769",
    "sg:postcode":"3205",
    "sg:province":"VIC",
    "sg:tags":[
        "supply"
    ],
    "wof:name":"Whitelaws Quality Toys",
    "wof:placetype":"venue"
},
  "geometry": {"coordinates":[144.961533,-37.834702],"type":"Point"}
}