{
  "type": "Feature",
  "properties": {
    "addr:full":"Lot 70 Boggy Creek Rd Bungawalbin NSW 2469",
    "addr:postcode":"2469",
    "addr:street":"Boggy Creek Rd",
    "iso:country":"AU",
    "sg:address":"Lot 70 Boggy Creek Rd",
    "sg:city":"Bungawalbin",
    "sg:classifiers":[
        {
            "category":"Bars & Pubs",
            "subcategory":"Biergarten",
            "type":"Food & Drink"
        }
    ],
    "sg:phone":"+61 2 6683 2480",
    "sg:postcode":"2469",
    "sg:province":"NSW",
    "sg:tags":[
        "eucalyptus",
        "oil",
        "tree",
        "essential",
        "tea"
    ],
    "wof:name":"Melaleuca Plantations",
    "wof:placetype":"venue"
},
  "geometry": {"coordinates":[153.250366211,-29.0779132843],"type":"Point"}
}