{
  "type": "Feature",
  "properties": {
    "addr:full":"Locked Bag 350 Clayton South VIC 3169",
    "addr:postcode":"3169",
    "iso:country":"AU",
    "sg:address":"Locked Bag 350",
    "sg:city":"Clayton South",
    "sg:classifiers":[
        {
            "category":"Communications",
            "subcategory":"Film & Video Production",
            "type":"Services"
        }
    ],
    "sg:phone":"+61 1300 722 292",
    "sg:postcode":"3169",
    "sg:province":"VIC",
    "sg:tags":[
        "dvd",
        "library"
    ],
    "wof:name":"Web Flicks Pty Ltd",
    "wof:placetype":"venue"
},
  "geometry": {"coordinates":[145.119338989,-37.9278678894],"type":"Point"}
}