{
  "type": "Feature",
  "properties": {
    "iso:country":"AU",
    "sg:address":"11 Devonport Rd",
    "sg:city":"Devonport",
    "sg:classifiers":[
        {
            "category":"Autos & Motor Vehicles",
            "subcategory":"Boat Sales",
            "type":"Retail Goods"
        }
    ],
    "sg:phone":"+61 417 139 504",
    "sg:postcode":"7310",
    "sg:province":"TAS",
    "sg:tags":[
        "builder",
        "yacht",
        "repairer"
    ],
    "wof:name":"Arabena Refinishing Industry",
    "wof:placetype":"venue"
},
  "geometry": {"coordinates":[146.36358642600001,-41.1956176758],"type":"Point"}
}