{
  "type": "Feature",
  "properties": {
    "addr:full":"PO Box 695 Subiaco WA 6904",
    "addr:postcode":"6904",
    "iso:country":"AU",
    "sg:address":"PO Box 695",
    "sg:city":"Subiaco",
    "sg:classifiers":[
        {
            "category":"Professional",
            "subcategory":"Art Services",
            "type":"Services"
        }
    ],
    "sg:phone":"+61 423 800 153",
    "sg:postcode":"6904",
    "sg:province":"WA",
    "sg:tags":[
        "decorator",
        "painter"
    ],
    "wof:name":"Calibre Coatings",
    "wof:placetype":"venue"
},
  "geometry": {"coordinates":[115.817261,-31.96817],"type":"Point"}
}