{
  "type": "Feature",
  "properties": {
    "iso:country":"AU",
    "sg:address":"East St",
    "sg:city":"Scarness",
    "sg:classifiers":[
        {
            "category":"Education",
            "subcategory":"Kindergarten",
            "type":"Public Place"
        }
    ],
    "sg:phone":"+61 7 4128 1452",
    "sg:postcode":"4655",
    "sg:province":"QLD",
    "sg:tags":[
        "pre-schools"
    ],
    "wof:name":"Hervey Bay Community Kindergarten & Preschool",
    "wof:placetype":"venue"
},
  "geometry": {"coordinates":[152.850067,-25.286989],"type":"Point"}
}