{
  "type": "Feature",
  "properties": {
    "iso:country":"AU",
    "sg:address":"487 Swan St",
    "sg:city":"Richmond",
    "sg:classifiers":[
        {
            "category":"Wholesale",
            "subcategory":"Vending Machines",
            "type":"Manufacturing & Wholesale Goods"
        }
    ],
    "sg:phone":"+61 3 9427 1033",
    "sg:postcode":"3121",
    "sg:province":"VIC",
    "sg:tags":[
        "equipment",
        "mailing"
    ],
    "wof:name":"Bowe Systec Pty Ltd",
    "wof:placetype":"venue"
},
  "geometry": {"coordinates":[145.01040649399999,-37.8269042969],"type":"Point"}
}