{
  "type": "Feature",
  "properties": {
    "addr:full":"722 Pennant Hills Rd Carlingford NSW 2118",
    "addr:housenumber":"722",
    "addr:postcode":"2118",
    "addr:street":"Pennant Hills Rd",
    "iso:country":"AU",
    "sg:address":"722 Pennant Hills Rd",
    "sg:city":"Carlingford",
    "sg:classifiers":[
        {
            "category":"Health Services",
            "subcategory":"Doctor",
            "type":"Services"
        }
    ],
    "sg:phone":"+61 2 9872 3303",
    "sg:postcode":"2118",
    "sg:province":"NSW",
    "sg:tags":[
        "medical",
        "practitioner"
    ],
    "wof:name":"Northwest Radiology",
    "wof:placetype":"venue"
},
  "geometry": {"coordinates":[151.04725647000001,-33.766204834],"type":"Point"}
}