{
  "type": "Feature",
  "properties": {
    "iso:country":"AU",
    "sg:address":"570 Wickham St",
    "sg:city":"Fortitude Valley",
    "sg:classifiers":[
        {
            "category":"Autos & Motor Vehicles",
            "subcategory":"Automobile Sales",
            "type":"Retail Goods"
        }
    ],
    "sg:phone":"+61 7 3257 7222",
    "sg:postcode":"4006",
    "sg:province":"QLD",
    "sg:tags":[
        "car",
        "new"
    ],
    "wof:name":"Bentley Brisbane",
    "wof:placetype":"venue"
},
  "geometry": {"coordinates":[153.03863525400001,-27.4524269104],"type":"Point"}
}