{
  "type": "Feature",
  "properties": {
    "addr:full":"95 Frenchmans Rd Randwick NSW 2031",
    "addr:housenumber":"95",
    "addr:postcode":"2031",
    "addr:street":"Frenchmans Rd",
    "iso:country":"AU",
    "sg:address":"95 Frenchmans Rd",
    "sg:city":"Randwick",
    "sg:classifiers":[
        {
            "category":"Retail",
            "subcategory":"Auto Repair",
            "type":"Services"
        }
    ],
    "sg:phone":"+61 2 9398 7060",
    "sg:postcode":"2031",
    "sg:province":"NSW",
    "sg:tags":[
        "beater",
        "painter",
        "panel"
    ],
    "wof:name":"Randwick Car Repairs",
    "wof:placetype":"venue"
},
  "geometry": {"coordinates":[151.249313355,-33.9071884155],"type":"Point"}
}