{
  "type": "Feature",
  "properties": {
    "iso:country":"AU",
    "sg:address":"1 Colbury Rd",
    "sg:city":"Bayswater",
    "sg:classifiers":[
        {
            "category":"Health Services",
            "subcategory":"Health Practitioner",
            "type":"Services"
        }
    ],
    "sg:phone":"+61 418 339 312",
    "sg:postcode":"3153",
    "sg:province":"VIC",
    "sg:tags":[
        "hypnotherapy"
    ],
    "wof:name":"Holmes Marilyn",
    "wof:placetype":"venue"
},
  "geometry": {"coordinates":[145.29783630399999,-37.8291397095],"type":"Point"}
}