{
  "type": "Feature",
  "properties": {
    "addr:full":"5- 7 Poat St Picton WA 6229",
    "addr:housenumber":"7",
    "addr:postcode":"6229",
    "addr:street":"Poat St",
    "iso:country":"AU",
    "sg:address":"5- 7 Poat St",
    "sg:city":"Picton",
    "sg:classifiers":[
        {
            "category":"Manufacturing",
            "subcategory":"Tools & Machinery",
            "type":"Manufacturing & Wholesale Goods"
        }
    ],
    "sg:phone":"+61 8 9725 4885",
    "sg:postcode":"6229",
    "sg:province":"WA",
    "sg:tags":[
        "earth",
        "excavating",
        "moving",
        "equipment"
    ],
    "wof:name":"CJD Equipment Pty Ltd",
    "wof:placetype":"venue"
},
  "geometry": {"coordinates":[115.68800400000001,-33.350349],"type":"Point"}
}