{
  "type": "Feature",
  "properties": {
    "addr:full":"Shop G2 2 Elizabeth Plaza Cnr Elizabeth Plaza & Mount St North Sydney NSW 2060",
    "addr:housenumber":"2",
    "addr:postcode":"2060",
    "addr:street":"G2;Cnr Elizabeth;St",
    "iso:country":"AU",
    "sg:address":"Shop G2 2 Elizabeth Plaza Cnr Elizabeth Plaza & Mount St",
    "sg:city":"North Sydney",
    "sg:classifiers":[
        {
            "category":"Travel",
            "subcategory":"Travel Agent",
            "type":"Entertainment"
        }
    ],
    "sg:phone":"+61 1300 735 865",
    "sg:postcode":"2060",
    "sg:province":"NSW",
    "sg:tags":[
        "consultant"
    ],
    "wof:name":"Escape Travel",
    "wof:placetype":"venue"
},
  "geometry": {"coordinates":[151.205535889,-33.8386154175],"type":"Point"}
}