{
  "type": "Feature",
  "properties": {
    "addr:full":"15 Warwick St Hobart TAS 7000",
    "addr:housenumber":"15",
    "addr:postcode":"7000",
    "addr:street":"Warwick St",
    "iso:country":"AU",
    "sg:address":"15 Warwick St",
    "sg:city":"Hobart",
    "sg:classifiers":[
        {
            "category":"Banks & Credit Unions",
            "subcategory":"Investment Brokerage",
            "type":"Services"
        }
    ],
    "sg:phone":"+61 3 6213 3318",
    "sg:postcode":"7000",
    "sg:province":"TAS",
    "sg:tags":[
        "finance",
        "broker"
    ],
    "wof:name":"Fresh Finance",
    "wof:placetype":"venue"
},
  "geometry": {"coordinates":[147.32327270499999,-42.87449646],"type":"Point"}
}