{
  "type": "Feature",
  "properties": {
    "addr:full":"Shop 21 Upper Level Kippa-Ring Vlge Kippa-Ring QLD 4021",
    "addr:housenumber":"shop 21",
    "addr:postcode":"4021",
    "addr:street":"Upper Level Kippa-Ring Vlge",
    "iso:country":"AU",
    "sg:address":"Shop 21",
    "sg:city":"Upper Level Kippa-Ring Vlge Kippa-Ring",
    "sg:classifiers":[
        {
            "category":"Retail",
            "subcategory":"Repair Shop",
            "type":"Services"
        }
    ],
    "sg:phone":"+61 7 3883 1825",
    "sg:postcode":"4021",
    "sg:province":"QLD",
    "sg:tags":[
        "machine",
        "sewing"
    ],
    "wof:name":"Northside Sewing Centre",
    "wof:placetype":"venue"
},
  "geometry": {"coordinates":[153.07818599999999,-27.217501],"type":"Point"}
}