{
  "type": "Feature",
  "properties": {
    "iso:country":"AU",
    "sg:address":"1749 Pittwater Rd",
    "sg:city":"Mona Vale",
    "sg:classifiers":[
        {
            "category":"Shopping",
            "subcategory":"Mobile Phones",
            "type":"Retail Goods"
        }
    ],
    "sg:phone":"+61 2 9979 1190",
    "sg:postcode":"2103",
    "sg:province":"NSW",
    "sg:tags":[
        "telephone",
        "accessory"
    ],
    "wof:name":"Telecell",
    "wof:placetype":"venue"
},
  "geometry": {"coordinates":[151.30320739699999,-33.6783447266],"type":"Point"}
}