{
  "type": "Feature",
  "properties": {
    "addr:full":"337a Nepean Hwy Frankston VIC 3199",
    "addr:housenumber":"337a",
    "addr:postcode":"3199",
    "addr:street":"Nepean Hwy",
    "iso:country":"AU",
    "sg:address":"337a Nepean Hwy",
    "sg:city":"Frankston",
    "sg:classifiers":[
        {
            "category":"Travel",
            "subcategory":"Hotels & Motels",
            "type":"Entertainment"
        }
    ],
    "sg:phone":"+61 3 5975 2130",
    "sg:postcode":"3199",
    "sg:province":"VIC",
    "wof:name":"Abbey Serviced Apartments",
    "wof:placetype":"venue"
},
  "geometry": {"coordinates":[145.083892822,-37.9954795837],"type":"Point"}
}