{
  "type": "Feature",
  "properties": {
    "addr:full":"127 Allingham St Armidale NSW 2350",
    "addr:housenumber":"127",
    "addr:postcode":"2350",
    "addr:street":"Allingham St",
    "iso:country":"AU",
    "sg:address":"127 Allingham St",
    "sg:city":"Armidale",
    "sg:classifiers":[
        {
            "category":"Education",
            "subcategory":"Kindergarten",
            "type":"Public Place"
        }
    ],
    "sg:phone":"+61 2 6772 2695",
    "sg:postcode":"2350",
    "sg:province":"NSW",
    "sg:tags":[
        "pre-schools"
    ],
    "wof:name":"Armidale Community Pre-School Inc",
    "wof:placetype":"venue"
},
  "geometry": {"coordinates":[151.660980225,-30.5135116577],"type":"Point"}
}