{
  "type": "Feature",
  "properties": {
    "addr:full":"70- 72 Rajah Rd Ocean Shores NSW 2483",
    "addr:housenumber":"72",
    "addr:postcode":"2483",
    "addr:street":"Rajah Rd",
    "iso:country":"AU",
    "sg:address":"70- 72 Rajah Rd",
    "sg:city":"Ocean Shores",
    "sg:classifiers":[
        {
            "category":"Health Services",
            "subcategory":"Health Practitioner",
            "type":"Services"
        }
    ],
    "sg:phone":"+61 2 6680 3499",
    "sg:postcode":"2483",
    "sg:province":"NSW",
    "sg:tags":[
        "physiotherapist"
    ],
    "wof:name":"Ocean Shores Physiotherapy",
    "wof:placetype":"venue"
},
  "geometry": {"coordinates":[153.544067383,-28.5275783539],"type":"Point"}
}