{
  "type": "Feature",
  "properties": {
    "addr:full":"7 Sheriff St Forestdale QLD 4118",
    "addr:housenumber":"7",
    "addr:postcode":"4118",
    "addr:street":"Sheriff St",
    "iso:country":"AU",
    "sg:address":"7 Sheriff St",
    "sg:city":"Forestdale",
    "sg:classifiers":[
        {
            "category":"Professional",
            "subcategory":"Accounting & Tax Preparation",
            "type":"Services"
        }
    ],
    "sg:phone":"+61 7 3800 3478",
    "sg:postcode":"4118",
    "sg:province":"QLD",
    "sg:tags":[
        "bookkeeping"
    ],
    "wof:name":"Books &#039;n&#039; Bas",
    "wof:placetype":"venue"
},
  "geometry": {"coordinates":[153.00729370100001,-27.6613292694],"type":"Point"}
}