{
  "type": "Feature",
  "properties": {
    "addr:full":"312/ 396 Scarborough Beach Rd Osborne Park WA 6017",
    "addr:housenumber":"312 / 396",
    "addr:postcode":"6017",
    "addr:street":"Scarborough Beach Rd",
    "iso:country":"AU",
    "sg:address":"312/ 396 Scarborough Beach Rd",
    "sg:city":"Osborne Park",
    "sg:classifiers":[
        {
            "category":"Manufacturing",
            "subcategory":"Building Materials",
            "type":"Manufacturing & Wholesale Goods"
        }
    ],
    "sg:phone":"+61 8 9242 3288",
    "sg:postcode":"6017",
    "sg:province":"WA",
    "sg:tags":[
        "equipment",
        "handling"
    ],
    "wof:name":"Unica Products",
    "wof:placetype":"venue"
},
  "geometry": {"coordinates":[115.814582825,-31.9106483459],"type":"Point"}
}