{
  "type": "Feature",
  "properties": {
    "addr:full":"Cnr Victor Cres & Princes Hwy Narre Warren VIC 3805",
    "addr:postcode":"3805",
    "addr:street":"Cnr Victor Cres & Princes Hwy",
    "iso:country":"AU",
    "sg:address":"Cnr Victor Cres & Princes Hwy",
    "sg:city":"Narre Warren",
    "sg:classifiers":[
        {
            "category":"Manufacturing",
            "subcategory":"Motor Vehicles & Parts",
            "type":"Manufacturing & Wholesale Goods"
        }
    ],
    "sg:phone":"+61 3 9705 1800",
    "sg:postcode":"3805",
    "sg:province":"VIC",
    "sg:tags":[
        "replacement"
    ],
    "wof:name":"Bevic Auto Parts",
    "wof:placetype":"venue"
},
  "geometry": {"coordinates":[145.30865499999999,-38.02084],"type":"Point"}
}