{
  "type": "Feature",
  "properties": {
    "addr:full":"36 Aquarium Ave Hemmant QLD 4174",
    "addr:postcode":"4174",
    "addr:street":"Aquarium Ave",
    "iso:country":"AU",
    "sg:address":"36 Aquarium Ave",
    "sg:city":"Hemmant",
    "sg:classifiers":[
        {
            "category":"Sports & Exercise",
            "subcategory":"Climbing Gym",
            "type":"Entertainment"
        }
    ],
    "sg:phone":"+61 7 3890 1071",
    "sg:postcode":"4174",
    "sg:province":"QLD",
    "sg:tags":[
        "repetition",
        "engineer"
    ],
    "wof:name":"MacGregor Industries",
    "wof:placetype":"venue"
},
  "geometry": {"coordinates":[153.12608337399999,-27.4432868958],"type":"Point"}
}