{
  "type": "Feature",
  "properties": {
    "addr:full":"Suite 3/ 14 Stafford St Midland WA 6056",
    "addr:housenumber":"14",
    "addr:postcode":"6056",
    "addr:street":"Stafford St",
    "iso:country":"AU",
    "sg:address":"Suite 3/ 14 Stafford St",
    "sg:city":"Midland",
    "sg:classifiers":[
        {
            "category":"Health Services",
            "subcategory":"Doctor",
            "type":"Services"
        }
    ],
    "sg:phone":"+61 8 9274 5166",
    "sg:postcode":"6056",
    "sg:province":"WA",
    "sg:tags":[
        "medical",
        "practitioner"
    ],
    "wof:name":"Langlands D R",
    "wof:placetype":"venue"
},
  "geometry": {"coordinates":[116.004562378,-31.8881111145],"type":"Point"}
}