{
  "type": "Feature",
  "properties": {
    "iso:country":"AU",
    "sg:address":"40 Mercedes Drv",
    "sg:city":"Thomastown",
    "sg:classifiers":[
        {
            "category":"Professional",
            "subcategory":"Art Services",
            "type":"Services"
        }
    ],
    "sg:phone":"+61 3 9465 5688",
    "sg:postcode":"3074",
    "sg:province":"VIC",
    "sg:tags":[
        "product",
        "industrial",
        "designer"
    ],
    "wof:name":"Enterprise Tooling Pty Ltd",
    "wof:placetype":"venue"
},
  "geometry": {"coordinates":[145.03457641599999,-37.6887054443],"type":"Point"}
}