{
  "type": "Feature",
  "properties": {
    "iso:country":"AU",
    "sg:address":"89a Whyte St",
    "sg:city":"Coleraine",
    "sg:classifiers":[
        {
            "category":"Personal",
            "subcategory":"Beauty Salon",
            "type":"Services"
        }
    ],
    "sg:phone":"+61 3 5575 2901",
    "sg:postcode":"3315",
    "sg:province":"VIC",
    "sg:tags":[
        "hairdresser"
    ],
    "wof:name":"JMI Hair Design",
    "wof:placetype":"venue"
},
  "geometry": {"coordinates":[141.69236755399999,-37.5983810425],"type":"Point"}
}