{
  "type": "Feature",
  "properties": {
    "addr:full":"Shop 3,83- 89 Mollison St Kyneton VIC 3444",
    "addr:housenumber":"3,83 89",
    "addr:postcode":"3444",
    "addr:street":"Mollison St",
    "iso:country":"AU",
    "sg:address":"Shop 3,83- 89 Mollison St",
    "sg:city":"Kyneton",
    "sg:classifiers":[
        {
            "category":"Food & Beverages",
            "subcategory":"Liquor & Beverages",
            "type":"Retail Goods"
        }
    ],
    "sg:phone":"+61 3 5422 1599",
    "sg:postcode":"3444",
    "sg:province":"VIC",
    "sg:tags":[
        "store"
    ],
    "wof:name":"Liquor Legends",
    "wof:placetype":"venue"
},
  "geometry": {"coordinates":[144.453125,-37.2488174438],"type":"Point"}
}