{
  "type": "Feature",
  "properties": {
    "addr:full":"10 Tamar Pl Fairfield West NSW 2165",
    "addr:housenumber":"10",
    "addr:postcode":"2165",
    "addr:street":"Tamar Pl",
    "iso:country":"AU",
    "sg:address":"10 Tamar Pl",
    "sg:city":"Fairfield West",
    "sg:classifiers":[
        {
            "category":"Professional",
            "subcategory":"Art Services",
            "type":"Services"
        }
    ],
    "sg:phone":"+61 2 9604 7389",
    "sg:postcode":"2165",
    "sg:province":"NSW",
    "sg:tags":[
        "decorator",
        "painter"
    ],
    "wof:name":"Browning Dennis J & O L",
    "wof:placetype":"venue"
},
  "geometry": {"coordinates":[150.91978454599999,-33.8643684387],"type":"Point"}
}