{
  "type": "Feature",
  "properties": {
    "addr:full":"Algona Crt St Helena VIC 3088",
    "addr:postcode":"3088",
    "addr:street":"Algona Crt",
    "iso:country":"AU",
    "sg:address":"Algona Crt",
    "sg:city":"St Helena",
    "sg:classifiers":[
        {
            "category":"Retail",
            "subcategory":"Repair Shop",
            "type":"Services"
        }
    ],
    "sg:phone":"+61 3 9432 6993",
    "sg:postcode":"3088",
    "sg:province":"VIC",
    "sg:tags":[
        "upholsterer"
    ],
    "wof:name":"Jenkins Furniture Pty Ltd",
    "wof:placetype":"venue"
},
  "geometry": {"coordinates":[145.12974548299999,-37.6901702881],"type":"Point"}
}