{
  "type": "Feature",
  "properties": {
    "addr:full":"136 Chester Rd Eight Mile Plains QLD 4113",
    "addr:housenumber":"136",
    "addr:postcode":"4113",
    "addr:street":"Chester Rd",
    "iso:country":"AU",
    "sg:address":"136 Chester Rd",
    "sg:city":"Eight Mile Plains",
    "sg:classifiers":[
        {
            "category":"Health Services",
            "subcategory":"Health Practitioner",
            "type":"Services"
        }
    ],
    "sg:phone":"+61 7 3423 0066",
    "sg:postcode":"4113",
    "sg:province":"QLD",
    "sg:tags":[
        "alternative"
    ],
    "wof:name":"Computerised Stress Reduction",
    "wof:placetype":"venue"
},
  "geometry": {"coordinates":[153.08920288100001,-27.5785293579],"type":"Point"}
}