{
  "type": "Feature",
  "properties": {
    "iso:country":"AU",
    "sg:address":"PO Box 719",
    "sg:city":"Niddrie",
    "sg:classifiers":[
        {
            "category":"Government",
            "subcategory":"Fire Station",
            "type":"Public Place"
        }
    ],
    "sg:phone":"+61 427 777 147",
    "sg:postcode":"3042",
    "sg:province":"VIC",
    "sg:tags":[
        "equipment",
        "protection",
        "consultant"
    ],
    "wof:name":"AGS Fire Detection",
    "wof:placetype":"venue"
},
  "geometry": {"coordinates":[144.88845825199999,-37.7357711792],"type":"Point"}
}