{
  "type": "Feature",
  "properties": {
    "addr:full":"Lvl 9/ 171 Latrobe St Melbourne VIC 3000",
    "addr:housenumber":"/ 171",
    "addr:postcode":"3000",
    "addr:street":"Latrobe St",
    "iso:country":"AU",
    "sg:address":"Lvl 9/ 171 Latrobe St",
    "sg:city":"Melbourne",
    "sg:classifiers":[
        {
            "category":"Building & Trades",
            "subcategory":"Cleaning & Sanitation",
            "type":"Services"
        }
    ],
    "sg:phone":"+61 1800 600 052",
    "sg:postcode":"3000",
    "sg:province":"VIC",
    "sg:tags":[
        "industrial",
        "commercial",
        "contractor"
    ],
    "wof:name":"Master Blinds Group",
    "wof:placetype":"venue"
},
  "geometry": {"coordinates":[144.96664428700001,-37.8088989258],"type":"Point"}
}