{
  "type": "Feature",
  "properties": {
    "addr:full":"70- 72 Wattle Park Ave Moolap VIC 3221",
    "addr:housenumber":"72",
    "addr:postcode":"3221",
    "addr:street":"Wattle Park Ave",
    "iso:country":"AU",
    "sg:address":"70- 72 Wattle Park Ave",
    "sg:city":"Moolap",
    "sg:classifiers":[
        {
            "category":"Fast Food",
            "type":"Food & Drink"
        }
    ],
    "sg:phone":"+61 3 5248 2082",
    "sg:postcode":"3221",
    "sg:province":"VIC",
    "sg:tags":[
        "away",
        "take"
    ],
    "wof:name":"Moolap Takeaway",
    "wof:placetype":"venue"
},
  "geometry": {"coordinates":[144.408401,-38.168533],"type":"Point"}
}