{
  "type": "Feature",
  "properties": {
    "addr:full":"18 Little Oxford St Collingwood VIC 3066",
    "addr:housenumber":"18",
    "addr:postcode":"3066",
    "addr:street":"Little Oxford St",
    "iso:country":"AU",
    "sg:address":"18 Little Oxford St",
    "sg:city":"Collingwood",
    "sg:classifiers":[
        {
            "category":"Shopping",
            "subcategory":"News",
            "type":"Retail Goods"
        }
    ],
    "sg:phone":"+61 3 9415 8713",
    "sg:postcode":"3066",
    "sg:province":"VIC",
    "sg:tags":[
        "magazine",
        "periodical"
    ],
    "wof:name":"Pantone",
    "wof:placetype":"venue"
},
  "geometry": {"coordinates":[144.984100342,-37.8056106567],"type":"Point"}
}