{
  "type": "Feature",
  "properties": {
    "addr:full":"Unit 1 / 15 Jasper Rd Moorabbin VIC 3189",
    "addr:housenumber":"15",
    "addr:postcode":"3189",
    "addr:street":"Jasper Rd",
    "iso:country":"AU",
    "sg:address":"Unit 1 / 15 Jasper Rd",
    "sg:city":"Moorabbin",
    "sg:classifiers":[
        {
            "category":"Health Services",
            "subcategory":"Health Practitioner",
            "type":"Services"
        }
    ],
    "sg:phone":"+61 3 9557 9807",
    "sg:postcode":"3189",
    "sg:province":"VIC",
    "sg:tags":[
        "acupuncture"
    ],
    "wof:name":"Aust- China Chinese Medical Centre Moorabbin",
    "wof:placetype":"venue"
},
  "geometry": {"coordinates":[145.03892517099999,-37.932674408],"type":"Point"}
}