{
  "type": "Feature",
  "properties": {
    "iso:country":"AU",
    "sg:address":"9 Broughton St",
    "sg:city":"Moss Vale",
    "sg:classifiers":[
        {
            "category":"Building & Trades",
            "subcategory":"Construction",
            "type":"Services"
        }
    ],
    "sg:phone":"+61 2 4868 2308",
    "sg:postcode":"2577",
    "sg:province":"NSW",
    "sg:tags":[
        "contractor"
    ],
    "wof:name":"D B Fry Constructions",
    "wof:placetype":"venue"
},
  "geometry": {"coordinates":[150.36520385700001,-34.5574073792],"type":"Point"}
}