{
  "type": "Feature",
  "properties": {
    "iso:country":"AU",
    "sg:address":"201 Carlingford Rd",
    "sg:city":"Carlingford",
    "sg:classifiers":[
        {
            "category":"Home & Garden",
            "subcategory":"Carpets & Floor Coverings",
            "type":"Retail Goods"
        }
    ],
    "sg:phone":"+61 2 9869 7513",
    "sg:postcode":"2118",
    "sg:province":"NSW",
    "sg:tags":[
        "tile",
        "wall",
        "layer"
    ],
    "wof:name":"Avery J E",
    "wof:placetype":"venue"
},
  "geometry": {"coordinates":[151.05622863799999,-33.7768630981],"type":"Point"}
}