{
  "type": "Feature",
  "properties": {
    "addr:full":"78 Liebig St Warrnambool VIC 3280",
    "addr:housenumber":"78",
    "addr:postcode":"3280",
    "addr:street":"Liebig St",
    "iso:country":"AU",
    "sg:address":"78 Liebig St",
    "sg:city":"Warrnambool",
    "sg:classifiers":[
        {
            "category":"Restaurant",
            "type":"Food & Drink"
        }
    ],
    "sg:phone":"+61 3 5561 3188",
    "sg:postcode":"3280",
    "sg:province":"VIC",
    "wof:name":"Donnellys Restaurant",
    "wof:placetype":"venue"
},
  "geometry": {"coordinates":[142.48313903799999,-38.3846626282],"type":"Point"}
}