{
  "type": "Feature",
  "properties": {
    "addr:full":"339 Payneham St Marden SA 5070",
    "addr:housenumber":"339",
    "addr:postcode":"5070",
    "addr:street":"Payneham St",
    "iso:country":"AU",
    "sg:address":"339 Payneham St",
    "sg:city":"Marden",
    "sg:classifiers":[
        {
            "category":"School Buses",
            "type":"Transportation"
        }
    ],
    "sg:phone":"+61 8 8132 1800",
    "sg:postcode":"5070",
    "sg:province":"SA",
    "sg:tags":[
        "nanny"
    ],
    "wof:name":"Nanny SA",
    "wof:placetype":"venue"
},
  "geometry": {"coordinates":[138.63822937,-34.897151947],"type":"Point"}
}