{
  "type": "Feature",
  "properties": {
    "addr:full":"23 Patrick St Stawell VIC 3380",
    "addr:housenumber":"23",
    "addr:postcode":"3380",
    "addr:street":"Patrick St",
    "iso:country":"AU",
    "sg:address":"23 Patrick St",
    "sg:city":"Stawell",
    "sg:classifiers":[
        {
            "category":"Organizations",
            "subcategory":"Non-profit Organization",
            "type":"Services"
        }
    ],
    "sg:phone":"+61 3 5358 4410",
    "sg:postcode":"3380",
    "sg:province":"VIC",
    "sg:tags":[
        "environmental",
        "organisation",
        "conservation"
    ],
    "wof:name":"Project Platypus Association",
    "wof:placetype":"venue"
},
  "geometry": {"coordinates":[142.784698486,-37.0564651489],"type":"Point"}
}