{
  "type": "Feature",
  "properties": {
    "addr:full":"1 Griffiths Drv Moana SA 5169",
    "addr:housenumber":"1",
    "addr:postcode":"5169",
    "addr:street":"Griffiths Drv",
    "iso:country":"AU",
    "sg:address":"1 Griffiths Drv",
    "sg:city":"Moana",
    "sg:classifiers":[
        {
            "category":"Real Estate",
            "subcategory":"Real Estate Agent",
            "type":"Services"
        }
    ],
    "sg:phone":"+61 8 8386 2322",
    "sg:postcode":"5169",
    "sg:province":"SA",
    "wof:name":"Southgate Real Estate",
    "wof:placetype":"venue"
},
  "geometry": {"coordinates":[138.47392273,-35.1968727112],"type":"Point"}
}