{
  "type": "Feature",
  "properties": {
    "addr:full":"2/28 Constitution Rd Ryde NSW 2112",
    "addr:housenumber":"/ 28",
    "addr:postcode":"2112",
    "addr:street":"Constitution Rd",
    "iso:country":"AU",
    "sg:address":"2/28 Constitution Rd",
    "sg:city":"Ryde",
    "sg:classifiers":[
        {
            "category":"Retail",
            "subcategory":"Auto Repair",
            "type":"Services"
        }
    ],
    "sg:phone":"+61 2 9807 3841",
    "sg:postcode":"2112",
    "sg:province":"NSW",
    "sg:tags":[
        "repairer",
        "motor",
        "engineer"
    ],
    "wof:name":"Alogrep Mechanical",
    "wof:placetype":"venue"
},
  "geometry": {"coordinates":[151.093215942,-33.8168106079],"type":"Point"}
}