{
  "type": "Feature",
  "properties": {
    "iso:country":"AU",
    "sg:address":"3 / 2 Roberts Ave",
    "sg:city":"Randwick",
    "sg:classifiers":[
        {
            "category":"Professional",
            "subcategory":"Computer Services",
            "type":"Services"
        }
    ],
    "sg:phone":"+61 408 438 488",
    "sg:postcode":"2031",
    "sg:province":"NSW",
    "sg:tags":[
        "equipment",
        "networking",
        "installation"
    ],
    "sg:website":"http://www.boostit.com.au",
    "wof:name":"BOOSTIT Computer Services",
    "wof:placetype":"venue"
},
  "geometry": {"coordinates":[151.25088500999999,-33.9071578979],"type":"Point"}
}