{
  "type": "Feature",
  "properties": {
    "iso:country":"AU",
    "sg:address":"307 Dana St",
    "sg:city":"Ballarat",
    "sg:classifiers":[
        {
            "category":"Autos & Motor Vehicles",
            "subcategory":"Auto Supplies",
            "type":"Retail Goods"
        }
    ],
    "sg:phone":"+61 3 5332 4048",
    "sg:postcode":"3350",
    "sg:province":"VIC",
    "sg:tags":[
        "car",
        "alarm"
    ],
    "wof:name":"Dana Auto-Electrics Pty Ltd",
    "wof:placetype":"venue"
},
  "geometry": {"coordinates":[143.854645,-37.563957],"type":"Point"}
}