{
  "type": "Feature",
  "properties": {
    "addr:full":"55 Korong Rd Heidelberg West VIC 3081",
    "addr:housenumber":"55",
    "addr:postcode":"3081",
    "addr:street":"Korong Rd",
    "iso:country":"AU",
    "sg:address":"55 Korong Rd",
    "sg:city":"Heidelberg West",
    "sg:classifiers":[
        {
            "category":"Manufacturing",
            "subcategory":"Metals",
            "type":"Manufacturing & Wholesale Goods"
        }
    ],
    "sg:phone":"+61 3 9459 3488",
    "sg:postcode":"3081",
    "sg:province":"VIC",
    "sg:tags":[
        "sheet",
        "worker"
    ],
    "wof:name":"Martins Steel Processing Pty Ltd",
    "wof:placetype":"venue"
},
  "geometry": {"coordinates":[145.047042847,-37.7317810059],"type":"Point"}
}