{
  "type": "Feature",
  "properties": {
    "addr:full":"15 King Ave Balgowlah NSW 2093",
    "addr:housenumber":"15",
    "addr:postcode":"2093",
    "addr:street":"King Ave",
    "iso:country":"AU",
    "sg:address":"15 King Ave",
    "sg:city":"Balgowlah",
    "sg:classifiers":[
        {
            "category":"Building & Trades",
            "subcategory":"Construction",
            "type":"Services"
        }
    ],
    "sg:phone":"+61 2 8966 9844",
    "sg:postcode":"2093",
    "sg:province":"NSW",
    "sg:tags":[
        "contractor"
    ],
    "wof:name":"Asheville Pacific Pty Ltd",
    "wof:placetype":"venue"
},
  "geometry": {"coordinates":[151.267776489,-33.7974128723],"type":"Point"}
}