{
  "type": "Feature",
  "properties": {
    "addr:full":"20A Liddiard St Hawthorn VIC 3122",
    "addr:housenumber":"20a",
    "addr:postcode":"3122",
    "addr:street":"Liddiard St",
    "iso:country":"AU",
    "sg:address":"20A Liddiard St",
    "sg:city":"Hawthorn",
    "sg:classifiers":[
        {
            "category":"Education",
            "subcategory":"School",
            "type":"Public Place"
        }
    ],
    "sg:phone":"+61 1800 134 442",
    "sg:postcode":"3122",
    "sg:province":"VIC",
    "sg:tags":[
        "supply"
    ],
    "wof:name":"Australian Presentation Systems Pty Ltd",
    "wof:placetype":"venue"
},
  "geometry": {"coordinates":[145.03753662099999,-37.8190956116],"type":"Point"}
}