{
  "type": "Feature",
  "properties": {
    "iso:country":"AU",
    "sg:address":"144 Renmark Ave",
    "sg:city":"Renmark",
    "sg:classifiers":[
        {
            "category":"Autos & Motor Vehicles",
            "subcategory":"Auto Supplies",
            "type":"Retail Goods"
        }
    ],
    "sg:phone":"+61 8 8586 5519",
    "sg:postcode":"5341",
    "sg:province":"SA",
    "sg:tags":[
        "accessory"
    ],
    "wof:name":"Autopro",
    "wof:placetype":"venue"
},
  "geometry": {"coordinates":[140.744628906,-34.1756668091],"type":"Point"}
}