{
  "type": "Feature",
  "properties": {
    "addr:full":"175 Grange Rd Flinders Park SA 5025",
    "addr:housenumber":"175",
    "addr:postcode":"5025",
    "addr:street":"Grange Rd",
    "iso:country":"AU",
    "sg:address":"175 Grange Rd",
    "sg:city":"Flinders Park",
    "sg:classifiers":[
        {
            "category":"Food & Beverages",
            "subcategory":"Supermarket",
            "type":"Retail Goods"
        }
    ],
    "sg:phone":"+61 8 8345 5148",
    "sg:postcode":"5025",
    "sg:province":"SA",
    "sg:tags":[
        "grocery",
        "store"
    ],
    "wof:name":"IGA Food Stores",
    "wof:placetype":"venue"
},
  "geometry": {"coordinates":[138.547607422,-34.9045753479],"type":"Point"}
}