{
  "type": "Feature",
  "properties": {
    "iso:country":"AU",
    "sg:address":"Suite 319, 160 Castlereagh St",
    "sg:city":"Sydney",
    "sg:classifiers":[
        {
            "category":"Manufacturing",
            "subcategory":"Jewelry",
            "type":"Manufacturing & Wholesale Goods"
        }
    ],
    "sg:phone":"+61 2 9264 9402",
    "sg:postcode":"2000",
    "sg:province":"NSW",
    "sg:tags":[
        "mfrg",
        "jeweller"
    ],
    "wof:name":"Michael Stedman Classic Jewellery",
    "wof:placetype":"venue"
},
  "geometry": {"coordinates":[151.20945739699999,-33.8722724915],"type":"Point"}
}