{
  "type": "Feature",
  "properties": {
    "addr:full":"Unit 6 Linkwood Court 19 Cavendish St Mittagong NSW 2575",
    "addr:housenumber":"19",
    "addr:postcode":"2575",
    "addr:street":"Linkwood;Cavendish St",
    "iso:country":"AU",
    "sg:address":"Unit 6 Linkwood Court 19 Cavendish St",
    "sg:city":"Mittagong",
    "sg:classifiers":[
        {
            "category":"Home & Garden",
            "subcategory":"Home Furnishings",
            "type":"Retail Goods"
        }
    ],
    "sg:phone":"+61 2 4872 2211",
    "sg:postcode":"2575",
    "sg:province":"NSW",
    "sg:tags":[
        "shower",
        "screen"
    ],
    "wof:name":"Platinum Shower Screens & Wardrobes",
    "wof:placetype":"venue"
},
  "geometry": {"coordinates":[150.43365478499999,-34.450340271],"type":"Point"}
}