{
  "type": "Feature",
  "properties": {
    "addr:full":"St Kilda Marina Complex, Marine Pde St Kilda VIC 3182",
    "addr:postcode":"3182",
    "addr:street":"Marine Pde",
    "iso:country":"AU",
    "sg:address":"St Kilda Marina Complex, Marine Pde",
    "sg:city":"St Kilda",
    "sg:classifiers":[
        {
            "category":"Recreation",
            "subcategory":"Marina",
            "type":"Entertainment"
        }
    ],
    "sg:phone":"+61 3 9525 3720",
    "sg:postcode":"3182",
    "sg:province":"VIC",
    "wof:name":"St Kilda Marina Pty Ltd",
    "wof:placetype":"venue"
},
  "geometry": {"coordinates":[144.97584533700001,-37.8690757751],"type":"Point"}
}