{
  "type": "Feature",
  "properties": {
    "addr:full":"Lot 3 Bergmans Rd Walkerston QLD 4751",
    "addr:postcode":"4751",
    "addr:street":"Bergmans Rd",
    "iso:country":"AU",
    "sg:address":"Lot 3 Bergmans Rd",
    "sg:city":"Walkerston",
    "sg:classifiers":[
        {
            "category":"Professional",
            "subcategory":"Business Services",
            "type":"Services"
        }
    ],
    "sg:phone":"+61 7 4959 3902",
    "sg:postcode":"4751",
    "sg:province":"QLD",
    "sg:tags":[
        "drafting"
    ],
    "wof:name":"Rick Barron Drafting Pty Ltd",
    "wof:placetype":"venue"
},
  "geometry": {"coordinates":[149.040527,-21.185221],"type":"Point"}
}