{
  "type": "Feature",
  "properties": {
    "iso:country":"AU",
    "sg:address":"475 Torrens Rd",
    "sg:city":"Woodville",
    "sg:classifiers":[
        {
            "category":"Health Services",
            "subcategory":"Doctor",
            "type":"Services"
        }
    ],
    "sg:phone":"+61 8 8445 7788",
    "sg:postcode":"5011",
    "sg:province":"SA",
    "sg:tags":[
        "medical",
        "practitioner"
    ],
    "wof:name":"Schwarz P J & McLeod P V Drs",
    "wof:placetype":"venue"
},
  "geometry": {"coordinates":[138.54768371599999,-34.8748550415],"type":"Point"}
}