{
  "type": "Feature",
  "properties": {
    "addr:full":"289 Stafford Rd Stafford QLD 4053",
    "addr:housenumber":"289",
    "addr:postcode":"4053",
    "addr:street":"Stafford Rd",
    "iso:country":"AU",
    "sg:address":"289 Stafford Rd",
    "sg:city":"Stafford",
    "sg:classifiers":[
        {
            "category":"Health Services",
            "subcategory":"Medical Lab",
            "type":"Services"
        }
    ],
    "sg:phone":"+61 7 3856 4810",
    "sg:postcode":"4053",
    "sg:province":"QLD",
    "sg:tags":[
        "laboratory",
        "dental"
    ],
    "wof:name":"Greg Wittkopp",
    "wof:placetype":"venue"
},
  "geometry": {"coordinates":[153.018844605,-27.410577774],"type":"Point"}
}