{
  "type": "Feature",
  "properties": {
    "addr:full":"14 Jamieson Pde Collaroy NSW 2097",
    "addr:housenumber":"14",
    "addr:postcode":"2097",
    "addr:street":"Jamieson Pde",
    "iso:country":"AU",
    "sg:address":"14 Jamieson Pde",
    "sg:city":"Collaroy",
    "sg:classifiers":[
        {
            "category":"Building & Trades",
            "subcategory":"Plumbing",
            "type":"Services"
        }
    ],
    "sg:phone":"+61 2 9971 2922",
    "sg:postcode":"2097",
    "sg:province":"NSW",
    "sg:tags":[
        "plumber",
        "gasfitters"
    ],
    "wof:name":"Balgowlah Plumbing",
    "wof:placetype":"venue"
},
  "geometry": {"coordinates":[151.30003356899999,-33.7383422852],"type":"Point"}
}