{
  "type": "Feature",
  "properties": {
    "addr:full":"153 Centre Dandenong Rd Cheltenham VIC 3192",
    "addr:housenumber":"153",
    "addr:postcode":"3192",
    "addr:street":"Centre Dandenong Rd",
    "iso:country":"AU",
    "sg:address":"153 Centre Dandenong Rd",
    "sg:city":"Cheltenham",
    "sg:classifiers":[
        {
            "category":"Manufacturing",
            "subcategory":"Buildings",
            "type":"Manufacturing & Wholesale Goods"
        }
    ],
    "sg:phone":"+61 1300 730 022",
    "sg:postcode":"3192",
    "sg:province":"VIC",
    "sg:tags":[
        "house",
        "gazebo",
        "shade"
    ],
    "wof:name":"Rotundas Of Melbourne",
    "wof:placetype":"venue"
},
  "geometry": {"coordinates":[145.074493408,-37.9675559998],"type":"Point"}
}