{
  "type": "Feature",
  "properties": {
    "iso:country":"AU",
    "sg:address":"28 Elmhurst Rd",
    "sg:city":"Tullamarine",
    "sg:classifiers":[
        {
            "category":"Personal",
            "subcategory":"Beauty Salon",
            "type":"Services"
        }
    ],
    "sg:phone":"+61 414 530 961",
    "sg:postcode":"3043",
    "sg:province":"VIC",
    "sg:tags":[
        "supply",
        "artist",
        "make-up"
    ],
    "wof:name":"Glamour Addictions",
    "wof:placetype":"venue"
},
  "geometry": {"coordinates":[144.88798523,-37.6954193115],"type":"Point"}
}