{
  "type": "Feature",
  "properties": {
    "addr:full":"Suite 106 / 566 St Kilda Rd Melbourne VIC 3004",
    "addr:housenumber":"/ 566",
    "addr:postcode":"3004",
    "addr:street":"St Kilda Rd",
    "iso:country":"AU",
    "sg:address":"Suite 106 / 566 St Kilda Rd",
    "sg:city":"Melbourne",
    "sg:classifiers":[
        {
            "category":"Professional",
            "subcategory":"Computer Services",
            "type":"Services"
        }
    ],
    "sg:phone":"+61 3 9526 8169",
    "sg:postcode":"3004",
    "sg:province":"VIC",
    "sg:tags":[
        "package",
        "software"
    ],
    "wof:name":"Syspro Software Pty Ltd",
    "wof:placetype":"venue"
},
  "geometry": {"coordinates":[144.97903442399999,-37.8467979431],"type":"Point"}
}