{
  "type": "Feature",
  "properties": {
    "addr:full":"25 Svenesen St Westcourt QLD 4870",
    "addr:housenumber":"25",
    "addr:postcode":"4870",
    "addr:street":"Svenesen St",
    "iso:country":"AU",
    "sg:address":"25 Svenesen St",
    "sg:city":"Westcourt",
    "sg:classifiers":[
        {
            "category":"Professional",
            "subcategory":"Engineering",
            "type":"Services"
        }
    ],
    "sg:phone":"+61 7 4041 4011",
    "sg:postcode":"4870",
    "sg:province":"QLD",
    "sg:tags":[
        "engineer"
    ],
    "wof:name":"Shaw K.W. & B Marine & General Engineers",
    "wof:placetype":"venue"
},
  "geometry": {"coordinates":[145.75083923299999,-16.9379234314],"type":"Point"}
}