{
  "type": "Feature",
  "properties": {
    "iso:country":"AU",
    "sg:address":"224 Waterworks Rd",
    "sg:city":"Ashgrove",
    "sg:classifiers":[
        {
            "category":"Shopping",
            "subcategory":"Pawn Shop",
            "type":"Retail Goods"
        }
    ],
    "sg:phone":"+61 7 3366 1777",
    "sg:postcode":"4060",
    "sg:province":"QLD",
    "sg:tags":[
        "pawnbroker"
    ],
    "wof:name":"Ashgrove Cash Exchange",
    "wof:placetype":"venue"
},
  "geometry": {"coordinates":[152.993377686,-27.4455318451],"type":"Point"}
}