{
  "type": "Feature",
  "properties": {
    "addr:full":"53 Cabramatta Rd Mosman NSW 2088",
    "addr:housenumber":"53",
    "addr:postcode":"2088",
    "addr:street":"Cabramatta Rd",
    "iso:country":"AU",
    "sg:address":"53 Cabramatta Rd",
    "sg:city":"Mosman",
    "sg:classifiers":[
        {
            "category":"Shopping",
            "subcategory":"Musical Instruments",
            "type":"Retail Goods"
        }
    ],
    "sg:phone":"+61 2 9909 1267",
    "sg:postcode":"2088",
    "sg:province":"NSW",
    "sg:tags":[
        "musician",
        "agent"
    ],
    "wof:name":"Burgess Nadia",
    "wof:placetype":"venue"
},
  "geometry": {"coordinates":[151.233718872,-33.8293952942],"type":"Point"}
}