{
  "type": "Feature",
  "properties": {
    "addr:full":"143 Bourke St Goulburn NSW 2580",
    "addr:housenumber":"143",
    "addr:postcode":"2580",
    "addr:street":"Bourke St",
    "iso:country":"AU",
    "sg:address":"143 Bourke St",
    "sg:city":"Goulburn",
    "sg:classifiers":[
        {
            "category":"Professional",
            "subcategory":"Accounting & Tax Preparation",
            "type":"Services"
        }
    ],
    "sg:phone":"+61 2 4821 1066",
    "sg:postcode":"2580",
    "sg:province":"NSW",
    "sg:tags":[
        "consultant",
        "taxation"
    ],
    "wof:name":"RSM Bird Cameron",
    "wof:placetype":"venue"
},
  "geometry": {"coordinates":[149.717651367,-34.7520484924],"type":"Point"}
}