{
  "type": "Feature",
  "properties": {
    "addr:full":"25 Stranbrook Ave Mt Ousley NSW 2519",
    "addr:housenumber":"25",
    "addr:postcode":"2519",
    "addr:street":"Stranbrook Ave Mt",
    "iso:country":"AU",
    "sg:address":"25 Stranbrook Ave",
    "sg:city":"Mt Ousley",
    "sg:classifiers":[
        {
            "category":"Education",
            "subcategory":"Special Training",
            "type":"Public Place"
        }
    ],
    "sg:phone":"+61 2 4229 1575",
    "sg:postcode":"2519",
    "sg:province":"NSW",
    "sg:tags":[
        "development"
    ],
    "wof:name":"Mtraining",
    "wof:placetype":"venue"
},
  "geometry": {"coordinates":[150.881134,-34.399979],"type":"Point"}
}