{
  "type": "Feature",
  "properties": {
    "addr:full":"6 Minga St Ryde NSW 2112",
    "addr:housenumber":"6",
    "addr:postcode":"2112",
    "addr:street":"Minga St",
    "iso:country":"AU",
    "sg:address":"6 Minga St",
    "sg:city":"Ryde",
    "sg:classifiers":[
        {
            "category":"Manufacturing",
            "subcategory":"Tools & Machinery",
            "type":"Manufacturing & Wholesale Goods"
        }
    ],
    "sg:phone":"+61 414 447 216",
    "sg:postcode":"2112",
    "sg:province":"NSW",
    "sg:tags":[
        "toolmaker"
    ],
    "wof:name":"The Constructive Urge",
    "wof:placetype":"venue"
},
  "geometry": {"coordinates":[151.11964416500001,-33.8076972961],"type":"Point"}
}