{
  "type": "Feature",
  "properties": {
    "addr:full":"PO Box 495 Tweed Heads QLD 2485",
    "addr:postcode":"2485",
    "iso:country":"AU",
    "sg:address":"PO Box 495",
    "sg:city":"Tweed Heads",
    "sg:classifiers":[
        {
            "category":"Banks & Credit Unions",
            "subcategory":"Financial Services",
            "type":"Services"
        }
    ],
    "sg:phone":"+61 1300 660 108",
    "sg:postcode":"2485",
    "sg:province":"QLD",
    "sg:tags":[
        "annuity",
        "rollover",
        "superannuation",
        "consultant"
    ],
    "wof:name":"Abbey Financial Planners",
    "wof:placetype":"venue"
},
  "geometry": {"coordinates":[153.54066467300001,-28.179693222],"type":"Point"}
}