{
  "type": "Feature",
  "properties": {
    "addr:full":"51 Culcross Drv Narangba QLD 4504",
    "addr:housenumber":"51",
    "addr:postcode":"4504",
    "addr:street":"Culcross Drv",
    "iso:country":"AU",
    "sg:address":"51 Culcross Drv",
    "sg:city":"Narangba",
    "sg:classifiers":[
        {
            "category":"Manufacturing",
            "subcategory":"Tools & Machinery",
            "type":"Manufacturing & Wholesale Goods"
        }
    ],
    "sg:phone":"+61 418 723 065",
    "sg:postcode":"4504",
    "sg:province":"QLD",
    "sg:tags":[
        "earth",
        "excavating",
        "moving",
        "equipment"
    ],
    "wof:name":"G.H. Rosenlund Contractors",
    "wof:placetype":"venue"
},
  "geometry": {"coordinates":[152.92973327600001,-27.1867389679],"type":"Point"}
}