{
  "type": "Feature",
  "properties": {
    "iso:country":"AU",
    "sg:address":"Shop 1146 Westfield",
    "sg:city":"Marion",
    "sg:classifiers":[
        {
            "category":"Food & Beverages",
            "subcategory":"Meat & Fish",
            "type":"Retail Goods"
        }
    ],
    "sg:phone":"+61 8 8296 1070",
    "sg:postcode":"5043",
    "sg:province":"SA",
    "sg:tags":[
        "seafood"
    ],
    "wof:name":"Manuel's Seafoods",
    "wof:placetype":"venue"
},
  "geometry": {"coordinates":[138.55647300000001,-35.01725],"type":"Point"}
}