{
  "type": "Feature",
  "properties": {
    "addr:full":"20 Blackbutt Rd Port Macquarie NSW 2444",
    "addr:housenumber":"20",
    "addr:postcode":"2444",
    "addr:street":"Blackbutt Rd",
    "iso:country":"AU",
    "sg:address":"20 Blackbutt Rd",
    "sg:city":"Port Macquarie",
    "sg:classifiers":[
        {
            "category":"Home & Garden",
            "subcategory":"Building Materials",
            "type":"Retail Goods"
        }
    ],
    "sg:phone":"+61 2 6585 2688",
    "sg:postcode":"2444",
    "sg:province":"NSW",
    "sg:tags":[
        "wall",
        "frame",
        "truss",
        "roof"
    ],
    "wof:name":"East Coast Frames & Trusses",
    "wof:placetype":"venue"
},
  "geometry": {"coordinates":[152.88810699999999,-31.453264],"type":"Point"}
}