{
  "type": "Feature",
  "properties": {
    "iso:country":"AU",
    "sg:address":"9 Eric Crs",
    "sg:city":"Annerley",
    "sg:classifiers":[
        {
            "category":"Shopping",
            "subcategory":"Bicycles & Sporting Goods",
            "type":"Retail Goods"
        }
    ],
    "sg:phone":"+61 7 3848 0552",
    "sg:postcode":"4103",
    "sg:province":"QLD",
    "sg:tags":[
        "chemical",
        "equipment",
        "pool",
        "swimming"
    ],
    "wof:name":"The Pool Smith",
    "wof:placetype":"venue"
},
  "geometry": {"coordinates":[153.031784058,-27.5140094757],"type":"Point"}
}