{
  "type": "Feature",
  "properties": {
    "addr:full":"1046 Dandenong Rd Carnegie VIC 3163",
    "addr:housenumber":"1046",
    "addr:postcode":"3163",
    "addr:street":"Dandenong Rd",
    "iso:country":"AU",
    "sg:address":"1046 Dandenong Rd",
    "sg:city":"Carnegie",
    "sg:classifiers":[
        {
            "category":"Retail",
            "subcategory":"Event Space",
            "type":"Services"
        }
    ],
    "sg:phone":"+61 3 9563 5815",
    "sg:postcode":"3163",
    "sg:province":"VIC",
    "sg:tags":[
        "venue",
        "reception",
        "wedding"
    ],
    "wof:name":"Matrioshka Restaurant & Reception",
    "wof:placetype":"venue"
},
  "geometry": {"coordinates":[145.0546875,-37.8837432861],"type":"Point"}
}