{
  "type": "Feature",
  "properties": {
    "addr:full":"401 Hobart Rd Youngtown TAS 7249",
    "addr:housenumber":"401",
    "addr:postcode":"7249",
    "addr:street":"Hobart Rd",
    "iso:country":"AU",
    "sg:address":"401 Hobart Rd",
    "sg:city":"Youngtown",
    "sg:classifiers":[
        {
            "category":"Building & Trades",
            "subcategory":"Construction",
            "type":"Services"
        }
    ],
    "sg:phone":"+61 408 110 106",
    "sg:postcode":"7249",
    "sg:province":"TAS",
    "sg:tags":[
        "fencing",
        "contractor"
    ],
    "wof:name":"Pratt Engineering",
    "wof:placetype":"venue"
},
  "geometry": {"coordinates":[147.16801452600001,-41.4886207581],"type":"Point"}
}