{
  "type": "Feature",
  "properties": {
    "addr:full":"1 Queen St Norwood SA 5067",
    "addr:housenumber":"1",
    "addr:postcode":"5067",
    "addr:street":"Queen St",
    "iso:country":"AU",
    "sg:address":"1 Queen St",
    "sg:city":"Norwood",
    "sg:classifiers":[
        {
            "category":"Food & Beverages",
            "subcategory":"Liquor & Beverages",
            "type":"Retail Goods"
        }
    ],
    "sg:phone":"+61 8 8331 7546",
    "sg:postcode":"5067",
    "sg:province":"SA",
    "sg:tags":[
        "store"
    ],
    "wof:name":"Independent Brands Australia",
    "wof:placetype":"venue"
},
  "geometry": {"coordinates":[138.638183594,-34.9150733948],"type":"Point"}
}