{
  "type": "Feature",
  "properties": {
    "addr:full":"42 Levanswell Rd Moorabbin VIC 3189",
    "addr:housenumber":"42",
    "addr:postcode":"3189",
    "addr:street":"Levanswell Rd",
    "iso:country":"AU",
    "sg:address":"42 Levanswell Rd",
    "sg:city":"Moorabbin",
    "sg:classifiers":[
        {
            "category":"Manufacturing",
            "subcategory":"Motor Vehicles & Parts",
            "type":"Manufacturing & Wholesale Goods"
        }
    ],
    "sg:phone":"+61 3 9555 8251",
    "sg:postcode":"3189",
    "sg:province":"VIC",
    "sg:tags":[
        "die",
        "casting"
    ],
    "wof:name":"Austmould Pty Ltd",
    "wof:placetype":"venue"
},
  "geometry": {"coordinates":[145.067504883,-37.944984436],"type":"Point"}
}