{
  "type": "Feature",
  "properties": {
    "iso:country":"AU",
    "sg:address":"PO Box 150",
    "sg:city":"Punchbowl",
    "sg:classifiers":[
        {
            "category":"Home & Garden",
            "subcategory":"Building Materials",
            "type":"Retail Goods"
        }
    ],
    "sg:phone":"+61 2 9785 8817",
    "sg:postcode":"2196",
    "sg:province":"NSW",
    "sg:tags":[
        "lawn",
        "cutting",
        "maintenance"
    ],
    "wof:name":"Sam Gardening Care Services",
    "wof:placetype":"venue"
},
  "geometry": {"coordinates":[151.053741,-33.92585],"type":"Point"}
}