{
  "type": "Feature",
  "properties": {
    "addr:full":"14 Dobney Ave Wagga Wagga NSW 2650",
    "addr:housenumber":"14",
    "addr:postcode":"2650",
    "addr:street":"Dobney Ave",
    "iso:country":"AU",
    "sg:address":"14 Dobney Ave",
    "sg:city":"Wagga Wagga",
    "sg:classifiers":[
        {
            "category":"Taxi",
            "type":"Transportation"
        }
    ],
    "sg:phone":"+61 408 692 484",
    "sg:postcode":"2650",
    "sg:province":"NSW",
    "sg:tags":[
        "truck"
    ],
    "wof:name":"Langfields Transport",
    "wof:placetype":"venue"
},
  "geometry": {"coordinates":[147.34788513199999,-35.117980957],"type":"Point"}
}