{
  "type": "Feature",
  "properties": {
    "addr:full":"Cnr Dunns Rd & Sandgate St Balaklava SA 5461",
    "addr:postcode":"5461",
    "addr:street":"Cnr Dunns Rd & Sandgate St",
    "iso:country":"AU",
    "sg:address":"Cnr Dunns Rd & Sandgate St",
    "sg:city":"Balaklava",
    "sg:classifiers":[
        {
            "category":"Commercial Area",
            "type":"Public Place"
        }
    ],
    "sg:phone":"+61 408 831 971",
    "sg:postcode":"5461",
    "sg:province":"SA",
    "sg:tags":[
        "heavy",
        "carrier"
    ],
    "wof:name":"Balaklava Transport",
    "wof:placetype":"venue"
},
  "geometry": {"coordinates":[138.43077099999999,-34.147072],"type":"Point"}
}