{
  "type": "Feature",
  "properties": {
    "addr:full":"Rowley Rd Armadale WA 6112",
    "addr:postcode":"6112",
    "addr:street":"Rowley Rd",
    "iso:country":"AU",
    "sg:address":"Rowley Rd",
    "sg:city":"Armadale",
    "sg:classifiers":[
        {
            "category":"Professional",
            "subcategory":"Engineering",
            "type":"Services"
        }
    ],
    "sg:phone":"+61 8 9455 4484",
    "sg:postcode":"6112",
    "sg:province":"WA",
    "sg:tags":[
        "consulting",
        "engineer"
    ],
    "wof:name":"Rawlinson P.E. & Associates",
    "wof:placetype":"venue"
},
  "geometry": {"coordinates":[115.995429993,-32.178527832],"type":"Point"}
}