{
  "type": "Feature",
  "properties": {
    "addr:full":"35 Burkitt St Page ACT 2614",
    "addr:housenumber":"35",
    "addr:postcode":"2614",
    "addr:street":"Burkitt St",
    "iso:country":"AU",
    "sg:address":"35 Burkitt St",
    "sg:city":"Page",
    "sg:classifiers":[
        {
            "category":"Retail",
            "subcategory":"Event Space",
            "type":"Services"
        }
    ],
    "sg:phone":"+61 2 6255 1794",
    "sg:postcode":"2614",
    "sg:province":"ACT",
    "sg:tags":[
        "venue",
        "reception",
        "wedding"
    ],
    "wof:name":"Villaggio Sant' Antonio",
    "wof:placetype":"venue"
},
  "geometry": {"coordinates":[149.05198669399999,-35.236328125],"type":"Point"}
}