{
  "type": "Feature",
  "properties": {
    "addr:full":"Kyle Ave Bentley WA 6102",
    "addr:postcode":"6102",
    "addr:street":"Kyle Ave",
    "iso:country":"AU",
    "sg:address":"Kyle Ave",
    "sg:city":"Bentley",
    "sg:classifiers":[
        {
            "category":"Social Services",
            "subcategory":"Retirement Home",
            "type":"Services"
        }
    ],
    "sg:phone":"+61 8 9313 2005",
    "sg:postcode":"6102",
    "sg:province":"WA",
    "sg:tags":[
        "accommodation",
        "special"
    ],
    "wof:name":"Rotary International House & Japan House",
    "wof:placetype":"venue"
},
  "geometry": {"coordinates":[115.889427185,-32.0102081299],"type":"Point"}
}