{
  "type": "Feature",
  "properties": {
    "addr:full":"CBD Redfern NSW 2016",
    "addr:postcode":"2016",
    "iso:country":"AU",
    "sg:address":"CBD",
    "sg:city":"Redfern",
    "sg:classifiers":[
        {
            "category":"Shopping",
            "subcategory":"Computers & Home Electronics",
            "type":"Retail Goods"
        }
    ],
    "sg:phone":"+61 2 9319 6713",
    "sg:postcode":"2016",
    "sg:province":"NSW",
    "sg:tags":[
        "equipment",
        "supply"
    ],
    "wof:name":"Laser Printer Toner Refills & Repairs",
    "wof:placetype":"venue"
},
  "geometry": {"coordinates":[151.206787109,-33.8931007385],"type":"Point"}
}