{
  "type": "Feature",
  "properties": {
    "iso:country":"AU",
    "sg:address":"Cnr Murray & Patrick Sts",
    "sg:city":"Hobart",
    "sg:classifiers":[
        {
            "category":"Insurance",
            "subcategory":"Hazard Insurance",
            "type":"Services"
        }
    ],
    "sg:phone":"+61 13 27 22",
    "sg:postcode":"7000",
    "sg:province":"TAS",
    "sg:tags":[
        "motor",
        "vehicle"
    ],
    "wof:name":"RACT Insurance",
    "wof:placetype":"venue"
},
  "geometry": {"coordinates":[147.31495666500001,-42.8748512268],"type":"Point"}
}