{
  "type": "Feature",
  "properties": {
    "addr:full":"11 Isa St Fyshwick ACT 2609",
    "addr:housenumber":"11",
    "addr:postcode":"2609",
    "addr:street":"Isa St",
    "iso:country":"AU",
    "sg:address":"11 Isa St",
    "sg:city":"Fyshwick",
    "sg:classifiers":[
        {
            "category":"Government",
            "subcategory":"Fire Station",
            "type":"Public Place"
        }
    ],
    "sg:phone":"+61 2 6280 5610",
    "sg:postcode":"2609",
    "sg:province":"ACT",
    "sg:tags":[
        "spring",
        "shock",
        "absorbers",
        "suspension"
    ],
    "wof:name":"Revell Steering Fyshwick",
    "wof:placetype":"venue"
},
  "geometry": {"coordinates":[149.17137145999999,-35.327381134],"type":"Point"}
}