{
  "type": "Feature",
  "properties": {
    "iso:country":"AU",
    "sg:address":"32 Angel Ave",
    "sg:city":"Murgon",
    "sg:classifiers":[
        {
            "category":"Education",
            "subcategory":"School",
            "type":"Public Place"
        }
    ],
    "sg:phone":"+61 7 4168 1627",
    "sg:postcode":"4605",
    "sg:province":"QLD",
    "sg:tags":[
        "co-educational"
    ],
    "wof:name":"St Joseph's Primary",
    "wof:placetype":"venue"
},
  "geometry": {"coordinates":[151.94555700000001,-26.239206],"type":"Point"}
}