{
  "type": "Feature",
  "properties": {
    "iso:country":"AU",
    "sg:address":"5 Kelvin Rd St",
    "sg:city":"Ives",
    "sg:classifiers":[
        {
            "category":"Government",
            "subcategory":"Court House",
            "type":"Public Place"
        }
    ],
    "sg:phone":"+61 2 9440 3534",
    "sg:postcode":"2075",
    "sg:province":"NSW",
    "sg:tags":[
        "personal",
        "marriage",
        "family",
        "counselling"
    ],
    "wof:name":"Street Jason",
    "wof:placetype":"venue"
},
  "geometry": {"coordinates":[151.16940307600001,-33.7394485474],"type":"Point"}
}