{
  "type": "Feature",
  "properties": {
    "iso:country":"AU",
    "sg:address":"2/12 Leslie St",
    "sg:city":"Dandenong South",
    "sg:classifiers":[
        {
            "category":"Utilities",
            "subcategory":"Electric",
            "type":"Services"
        }
    ],
    "sg:phone":"+61 3 9791 1866",
    "sg:postcode":"3175",
    "sg:province":"VIC",
    "sg:tags":[
        "electrical",
        "contractor"
    ],
    "wof:name":"Varney Electrical Pty Ltd",
    "wof:placetype":"venue"
},
  "geometry": {"coordinates":[145.198654175,-37.9918785095],"type":"Point"}
}