{
  "type": "Feature",
  "properties": {
    "iso:country":"AU",
    "sg:address":"32 Kelso St",
    "sg:city":"Richmond",
    "sg:classifiers":[
        {
            "category":"Professional",
            "subcategory":"Business Services",
            "type":"Services"
        }
    ],
    "sg:phone":"+61 3 9427 7111",
    "sg:postcode":"3121",
    "sg:province":"VIC",
    "sg:tags":[
        "fashion",
        "agent"
    ],
    "wof:name":"Crawford Saris Agencies Pty Ltd",
    "wof:placetype":"venue"
},
  "geometry": {"coordinates":[144.990402222,-37.8283119202],"type":"Point"}
}