{
  "type": "Feature",
  "properties": {
    "addr:full":"Lot 1 Sunnybank Rd Niagara Park NSW 2250",
    "addr:housenumber":"1",
    "addr:postcode":"2250",
    "addr:street":"Sunnybank Rd",
    "iso:country":"AU",
    "sg:address":"Lot 1 Sunnybank Rd",
    "sg:city":"Niagara Park",
    "sg:classifiers":[
        {
            "category":"Home & Garden",
            "subcategory":"Building Materials",
            "type":"Retail Goods"
        }
    ],
    "sg:phone":"+61 2 4329 7712",
    "sg:postcode":"2250",
    "sg:province":"NSW",
    "sg:tags":[
        "fitting",
        "door"
    ],
    "wof:name":"Best Doors and Frames Pty Ltd",
    "wof:placetype":"venue"
},
  "geometry": {"coordinates":[151.35873413100001,-33.3808479309],"type":"Point"}
}