{
  "type": "Feature",
  "properties": {
    "addr:full":"2 Bachli Crt Rosanna VIC 3084",
    "addr:housenumber":"2",
    "addr:postcode":"3084",
    "addr:street":"Bachli Crt",
    "iso:country":"AU",
    "sg:address":"2 Bachli Crt",
    "sg:city":"Rosanna",
    "sg:classifiers":[
        {
            "category":"Health Services",
            "subcategory":"Doctor",
            "type":"Services"
        }
    ],
    "sg:phone":"+61 419 875 056",
    "sg:postcode":"3084",
    "sg:province":"VIC",
    "sg:tags":[
        "occupational",
        "safety"
    ],
    "wof:name":"Business Risk Consultancy",
    "wof:placetype":"venue"
},
  "geometry": {"coordinates":[145.06797790499999,-37.7402763367],"type":"Point"}
}