{
  "type": "Feature",
  "properties": {
    "addr:full":"221 Collins St Hobart TAS 7000",
    "addr:housenumber":"221",
    "addr:postcode":"7000",
    "addr:street":"Collins St",
    "iso:country":"AU",
    "sg:address":"221 Collins St",
    "sg:city":"Hobart",
    "sg:classifiers":[
        {
            "category":"Professional",
            "subcategory":"Computer Services",
            "type":"Services"
        }
    ],
    "sg:phone":"+61 3 6231 9433",
    "sg:postcode":"7000",
    "sg:province":"TAS",
    "sg:tags":[
        "repairs",
        "upgrade",
        "equipment"
    ],
    "wof:name":"Hobart Computer Repairs",
    "wof:placetype":"venue"
},
  "geometry": {"coordinates":[147.322174072,-42.8871955872],"type":"Point"}
}