{
  "type": "Feature",
  "properties": {
    "iso:country":"AU",
    "sg:address":"Suite 8/ 32 Richardson St",
    "sg:city":"West Perth",
    "sg:classifiers":[
        {
            "category":"Health Services",
            "subcategory":"Health Practitioner",
            "type":"Services"
        }
    ],
    "sg:phone":"+61 8 9214 3960",
    "sg:postcode":"6005",
    "sg:province":"WA",
    "sg:tags":[
        "psychologist"
    ],
    "wof:name":"Family Psychology Practice",
    "wof:placetype":"venue"
},
  "geometry": {"coordinates":[115.841506958,-31.9497241974],"type":"Point"}
}