{
  "type": "Feature",
  "properties": {
    "addr:full":"Level 1/ 4 Douglas St Southbank VIC 3006",
    "addr:housenumber":"/ 4",
    "addr:postcode":"3006",
    "addr:street":"Douglas St",
    "iso:country":"AU",
    "sg:address":"Level 1/ 4 Douglas St",
    "sg:city":"Southbank",
    "sg:classifiers":[
        {
            "category":"Shopping",
            "subcategory":"Computers & Home Electronics",
            "type":"Retail Goods"
        }
    ],
    "sg:phone":"+61 3 9682 6700",
    "sg:postcode":"3006",
    "sg:province":"VIC",
    "sg:tags":[
        "hardware",
        "equipment"
    ],
    "wof:name":"Information Potential Pty Ltd",
    "wof:placetype":"venue"
},
  "geometry": {"coordinates":[144.95330810600001,-37.8289451599],"type":"Point"}
}