{
  "type": "Feature",
  "properties": {
    "addr:full":"33 Hargrave St Campbelltown NSW 2560",
    "addr:housenumber":"33",
    "addr:postcode":"2560",
    "addr:street":"Hargrave St",
    "iso:country":"AU",
    "sg:address":"33 Hargrave St",
    "sg:city":"Campbelltown",
    "sg:classifiers":[
        {
            "category":"Building & Trades",
            "subcategory":"Landscaping Services",
            "type":"Services"
        }
    ],
    "sg:phone":"+61 2 4625 7138",
    "sg:postcode":"2560",
    "sg:province":"NSW",
    "sg:tags":[
        "control",
        "weed"
    ],
    "wof:name":"Ovington's Pest Control",
    "wof:placetype":"venue"
},
  "geometry": {"coordinates":[150.838256836,-34.0615081787],"type":"Point"}
}