{
  "type": "Feature",
  "properties": {
    "addr:full":"PO Box 578 Mascot NSW 2020",
    "addr:postcode":"2020",
    "iso:country":"AU",
    "sg:address":"PO Box 578",
    "sg:city":"Mascot",
    "sg:classifiers":[
        {
            "category":"Wholesale",
            "subcategory":"Machinery & Supplies",
            "type":"Manufacturing & Wholesale Goods"
        }
    ],
    "sg:phone":"+61 2 8339 0123",
    "sg:postcode":"2020",
    "sg:province":"NSW",
    "sg:tags":[
        "rigging",
        "equipment",
        "hoisting"
    ],
    "wof:name":"Mcgrath Industries",
    "wof:placetype":"venue"
},
  "geometry": {"coordinates":[151.19451904300001,-33.9301681519],"type":"Point"}
}