{
  "type": "Feature",
  "properties": {
    "addr:full":"303 Pulteney St Adelaide SA 5000",
    "addr:housenumber":"303",
    "addr:postcode":"5000",
    "addr:street":"Pulteney St",
    "iso:country":"AU",
    "sg:address":"303 Pulteney St",
    "sg:city":"Adelaide",
    "sg:classifiers":[
        {
            "category":"Banks & Credit Unions",
            "subcategory":"Bank",
            "type":"Services"
        }
    ],
    "sg:phone":"+61 8 8223 1461",
    "sg:postcode":"5000",
    "sg:province":"SA",
    "sg:tags":[
        "equipment",
        "sale",
        "point"
    ],
    "wof:name":"Displayline",
    "wof:placetype":"venue"
},
  "geometry": {"coordinates":[138.60598754899999,-34.9302253723],"type":"Point"}
}