{
  "type": "Feature",
  "properties": {
    "iso:country":"AU",
    "sg:address":"31 Peate Ave",
    "sg:city":"Glen Iris",
    "sg:classifiers":[
        {
            "category":"Wholesale",
            "subcategory":"Seafood",
            "type":"Manufacturing & Wholesale Goods"
        }
    ],
    "sg:phone":"+61 411 850 944",
    "sg:postcode":"3146",
    "sg:province":"VIC",
    "sg:tags":[
        "fish"
    ],
    "wof:name":"Tassal Ltd",
    "wof:placetype":"venue"
},
  "geometry": {"coordinates":[145.06292724599999,-37.8488388062],"type":"Point"}
}