{
  "type": "Feature",
  "properties": {
    "addr:full":"11/ 34 Myddleton Ave Fairfield NSW 2165",
    "addr:housenumber":"11 / 34",
    "addr:postcode":"2165",
    "addr:street":"Myddleton Ave",
    "iso:country":"AU",
    "sg:address":"11/ 34 Myddleton Ave",
    "sg:city":"Fairfield",
    "sg:classifiers":[
        {
            "category":"Professional",
            "subcategory":"Art Services",
            "type":"Services"
        }
    ],
    "sg:phone":"+61 2 9724 7896",
    "sg:postcode":"2165",
    "sg:province":"NSW",
    "sg:tags":[
        "artist"
    ],
    "wof:name":"Do-Art Studio",
    "wof:placetype":"venue"
},
  "geometry": {"coordinates":[150.95111084000001,-33.8618049622],"type":"Point"}
}