{
  "type": "Feature",
  "properties": {
    "addr:full":"75 Elder St Lambton NSW 2299",
    "addr:housenumber":"75",
    "addr:postcode":"2299",
    "addr:street":"Elder St",
    "iso:country":"AU",
    "sg:address":"75 Elder St",
    "sg:city":"Lambton",
    "sg:classifiers":[
        {
            "category":"Social Services",
            "subcategory":"Child Care",
            "type":"Services"
        }
    ],
    "sg:phone":"+61 2 4957 1987",
    "sg:postcode":"2299",
    "sg:province":"NSW",
    "sg:tags":[
        "support",
        "health"
    ],
    "wof:name":"Child Health Centres",
    "wof:placetype":"venue"
},
  "geometry": {"coordinates":[151.709350586,-32.9115524292],"type":"Point"}
}