{
  "type": "Feature",
  "properties": {
    "addr:full":"11 Barangaroo St Chisholm ACT 2905",
    "addr:housenumber":"11",
    "addr:postcode":"2905",
    "addr:street":"Barangaroo St",
    "iso:country":"AU",
    "sg:address":"11 Barangaroo St",
    "sg:city":"Chisholm",
    "sg:classifiers":[
        {
            "category":"Arts & Performance",
            "subcategory":"Comedy Club",
            "type":"Entertainment"
        }
    ],
    "sg:phone":"+61 2 6291 0825",
    "sg:postcode":"2905",
    "sg:province":"ACT",
    "sg:tags":[
        "piano",
        "removal"
    ],
    "wof:name":"Beethoven Piano & Safe Movers",
    "wof:placetype":"venue"
},
  "geometry": {"coordinates":[149.12286376899999,-35.427444458],"type":"Point"}
}