{
  "type": "Feature",
  "properties": {
    "addr:full":"30 Millers Rd Brooklyn VIC 3025",
    "addr:housenumber":"30",
    "addr:postcode":"3025",
    "addr:street":"Millers Rd",
    "iso:country":"AU",
    "sg:address":"30 Millers Rd",
    "sg:city":"Brooklyn",
    "sg:classifiers":[
        {
            "category":"Fast Food",
            "type":"Food & Drink"
        }
    ],
    "sg:phone":"+61 3 9314 3062",
    "sg:postcode":"3025",
    "sg:province":"VIC",
    "sg:tags":[
        "away",
        "take"
    ],
    "wof:name":"Westgate Takeaway",
    "wof:placetype":"venue"
},
  "geometry": {"coordinates":[144.849243,-37.819824],"type":"Point"}
}