{
  "type": "Feature",
  "properties": {
    "iso:country":"AU",
    "sg:address":"43 Clifton Rd",
    "sg:city":"Clovelly",
    "sg:classifiers":[
        {
            "category":"Building & Trades",
            "subcategory":"Landscaping Services",
            "type":"Services"
        }
    ],
    "sg:phone":"+61 2 9665 7024",
    "sg:postcode":"2031",
    "sg:province":"NSW",
    "sg:tags":[
        "gardener"
    ],
    "wof:name":"Higo Gardens Of Sydney",
    "wof:placetype":"venue"
},
  "geometry": {"coordinates":[151.262283325,-33.9112739563],"type":"Point"}
}