{
  "type": "Feature",
  "properties": {
    "iso:country":"AU",
    "sg:address":"2 Lethbridge St",
    "sg:city":"Penrith",
    "sg:classifiers":[
        {
            "category":"Professional",
            "subcategory":"Accounting & Tax Preparation",
            "type":"Services"
        }
    ],
    "sg:phone":"+61 2 4731 3022",
    "sg:postcode":"2750",
    "sg:province":"NSW",
    "sg:tags":[
        "consultant",
        "taxation"
    ],
    "wof:name":"Geoff White & Co.",
    "wof:placetype":"venue"
},
  "geometry": {"coordinates":[150.711135864,-33.7588920593],"type":"Point"}
}