{
  "type": "Feature",
  "properties": {
    "addr:full":"6 Capital Link Drv Campbellfield VIC 3061",
    "addr:housenumber":"6",
    "addr:postcode":"3061",
    "addr:street":"Capital Link Drv",
    "iso:country":"AU",
    "sg:address":"6 Capital Link Drv",
    "sg:city":"Campbellfield",
    "sg:classifiers":[
        {
            "category":"Autos & Motor Vehicles",
            "subcategory":"Auto Supplies",
            "type":"Retail Goods"
        }
    ],
    "sg:phone":"+61 3 9357 0423",
    "sg:postcode":"3061",
    "sg:province":"VIC",
    "sg:tags":[
        "camper-trailers",
        "caravan",
        "equipment"
    ],
    "wof:name":"Quest Caravans",
    "wof:placetype":"venue"
},
  "geometry": {"coordinates":[144.96414184599999,-37.6583557129],"type":"Point"}
}