{
  "type": "Feature",
  "properties": {
    "addr:full":"Unit 6, Cnr Flinders Rd & Angus Ave Nowra South NSW 2541",
    "addr:housenumber":"cnr",
    "addr:postcode":"2541",
    "addr:street":"Flinders Rd & Angus Ave",
    "iso:country":"AU",
    "sg:address":"Unit 6, Cnr Flinders Rd & Angus Ave",
    "sg:city":"Nowra South",
    "sg:classifiers":[
        {
            "category":"Shopping",
            "subcategory":"Beauty & Cosmetics",
            "type":"Retail Goods"
        }
    ],
    "sg:phone":"+61 2 4423 0118",
    "sg:postcode":"2541",
    "sg:province":"NSW",
    "sg:tags":[
        "equipment",
        "salon",
        "supply"
    ],
    "wof:name":"Ardour Beauty",
    "wof:placetype":"venue"
},
  "geometry": {"coordinates":[150.58013915999999,-34.9050750732],"type":"Point"}
}