{
  "type": "Feature",
  "properties": {
    "iso:country":"AU",
    "sg:address":"43 Boronia Rd",
    "sg:city":"Boronia",
    "sg:classifiers":[
        {
            "category":"Health Services",
            "subcategory":"Doctor",
            "type":"Services"
        }
    ],
    "sg:phone":"+61 3 9761 1244",
    "sg:postcode":"3155",
    "sg:province":"VIC",
    "sg:tags":[
        "medical",
        "practitioner"
    ],
    "wof:name":"Sasidharan,Suhanya Dr.",
    "wof:placetype":"venue"
},
  "geometry": {"coordinates":[145.29180908199999,-37.86277771],"type":"Point"}
}