{
  "type": "Feature",
  "properties": {
    "iso:country":"AU",
    "sg:address":"Berry Brow Rd",
    "sg:city":"Bakers Hill",
    "sg:classifiers":[
        {
            "category":"Wholesale",
            "subcategory":"Farm Supplies",
            "type":"Manufacturing & Wholesale Goods"
        }
    ],
    "sg:phone":"+61 8 9574 1414",
    "sg:postcode":"6562",
    "sg:province":"WA",
    "sg:tags":[
        "equipment"
    ],
    "wof:name":"Norrish Service Group",
    "wof:placetype":"venue"
},
  "geometry": {"coordinates":[116.457359,-31.749971],"type":"Point"}
}