{
  "type": "Feature",
  "properties": {
    "iso:country":"AU",
    "sg:address":"51 Torrens St",
    "sg:city":"Victor Harbor",
    "sg:classifiers":[
        {
            "category":"Real Estate",
            "subcategory":"Surveying",
            "type":"Services"
        }
    ],
    "sg:phone":"+61 8 8552 9133",
    "sg:postcode":"5211",
    "sg:province":"SA",
    "sg:tags":[
        "surveyor",
        "land"
    ],
    "wof:name":"Civil Surveys & Design Pty Ltd",
    "wof:placetype":"venue"
},
  "geometry": {"coordinates":[138.62025451700001,-35.5552825928],"type":"Point"}
}