{
  "type": "Feature",
  "properties": {
    "addr:full":"87 Grandview St Pymble NSW 2073",
    "addr:housenumber":"87",
    "addr:postcode":"2073",
    "addr:street":"Grandview St",
    "iso:country":"AU",
    "sg:address":"87 Grandview St",
    "sg:city":"Pymble",
    "sg:classifiers":[
        {
            "category":"Health Services",
            "subcategory":"Health Practitioner",
            "type":"Services"
        }
    ],
    "sg:phone":"+61 2 9988 4574",
    "sg:postcode":"2073",
    "sg:province":"NSW",
    "sg:tags":[
        "psychotherapist"
    ],
    "wof:name":"Karinya Centre Pty Ltd",
    "wof:placetype":"venue"
},
  "geometry": {"coordinates":[151.141967773,-33.7443161011],"type":"Point"}
}