{
  "type": "Feature",
  "properties": {
    "iso:country":"AU",
    "sg:address":"22 Gore St",
    "sg:city":"Albion",
    "sg:classifiers":[
        {
            "category":"Education",
            "subcategory":"Dance Studio",
            "type":"Public Place"
        }
    ],
    "sg:phone":"+61 1300 765 354",
    "sg:postcode":"4010",
    "sg:province":"QLD",
    "sg:tags":[
        "training",
        "video",
        "film"
    ],
    "sg:website":"http://www.qsft.qld.edu.au/",
    "wof:name":"Queensland School of Film & Television",
    "wof:placetype":"venue"
},
  "geometry": {"coordinates":[153.04144287099999,-27.4321918488],"type":"Point"}
}