{
  "type": "Feature",
  "properties": {
    "addr:full":"28 Deloraine St Lyons ACT 2606",
    "addr:housenumber":"28",
    "addr:postcode":"2606",
    "addr:street":"Deloraine St",
    "iso:country":"AU",
    "sg:address":"28 Deloraine St",
    "sg:city":"Lyons",
    "sg:classifiers":[
        {
            "category":"Professional",
            "subcategory":"Art Services",
            "type":"Services"
        }
    ],
    "sg:phone":"+61 2 6285 2067",
    "sg:postcode":"2606",
    "sg:province":"ACT",
    "sg:tags":[
        "picture",
        "frame",
        "framing"
    ],
    "wof:name":"Boddy F J",
    "wof:placetype":"venue"
},
  "geometry": {"coordinates":[149.07864379899999,-35.3375816345],"type":"Point"}
}