{
  "type": "Feature",
  "properties": {
    "iso:country":"AU",
    "sg:address":"Shop 9, 76 Enoggera Rd",
    "sg:city":"Newmarket",
    "sg:classifiers":[
        {
            "category":"Government",
            "subcategory":"Court House",
            "type":"Public Place"
        }
    ],
    "sg:phone":"+61 407 626 469",
    "sg:postcode":"4051",
    "sg:province":"QLD",
    "sg:tags":[
        "personal",
        "marriage",
        "family",
        "counselling"
    ],
    "wof:name":"Tess van den Bergh",
    "wof:placetype":"venue"
},
  "geometry": {"coordinates":[153.00706481899999,-27.4381427765],"type":"Point"}
}