{
  "type": "Feature",
  "properties": {
    "iso:country":"AU",
    "sg:address":"6a Watton St",
    "sg:city":"Werribee",
    "sg:classifiers":[
        {
            "category":"Real Estate",
            "subcategory":"Real Estate Agent",
            "type":"Services"
        }
    ],
    "sg:phone":"+61 3 9741 5900",
    "sg:postcode":"3030",
    "sg:province":"VIC",
    "wof:name":"Professionals Triwest Real Estate",
    "wof:placetype":"venue"
},
  "geometry": {"coordinates":[144.662827,-37.900055],"type":"Point"}
}