{
  "type": "Feature",
  "properties": {
    "iso:country":"AU",
    "sg:address":"507 Chapple La",
    "sg:city":"Broken Hill",
    "sg:classifiers":[
        {
            "category":"Arena",
            "subcategory":"Sports Club",
            "type":"Entertainment"
        }
    ],
    "sg:phone":"+61 8 8087 3022",
    "sg:postcode":"2880",
    "sg:province":"NSW",
    "sg:tags":[
        "organisation",
        "sporting"
    ],
    "wof:name":"Excelsior Sportsground Management Committee",
    "wof:placetype":"venue"
},
  "geometry": {"coordinates":[141.46664428700001,-31.9467220306],"type":"Point"}
}