{
  "type": "Feature",
  "properties": {
    "addr:full":"13 Oaklands Rd Somerton Park SA 5044",
    "addr:housenumber":"13",
    "addr:postcode":"5044",
    "addr:street":"Oaklands Rd",
    "iso:country":"AU",
    "sg:address":"13 Oaklands Rd",
    "sg:city":"Somerton Park",
    "sg:classifiers":[
        {
            "category":"Utilities",
            "subcategory":"Water",
            "type":"Services"
        }
    ],
    "sg:phone":"+61 8 8336 9444",
    "sg:postcode":"5044",
    "sg:province":"SA",
    "sg:tags":[
        "hot",
        "system"
    ],
    "wof:name":"Hall & Baum Pty Ltd",
    "wof:placetype":"venue"
},
  "geometry": {"coordinates":[138.52323899999999,-34.997208],"type":"Point"}
}