{
  "type": "Feature",
  "properties": {
    "addr:full":"Cusacks La Jimboomba QLD 4280",
    "addr:postcode":"4280",
    "iso:country":"AU",
    "sg:address":"Cusacks La",
    "sg:city":"Jimboomba",
    "sg:classifiers":[
        {
            "category":"Home & Garden",
            "subcategory":"Garden Supply",
            "type":"Retail Goods"
        }
    ],
    "sg:phone":"+61 7 3114 8244",
    "sg:postcode":"4280",
    "sg:province":"QLD",
    "sg:tags":[
        "turf",
        "lawn"
    ],
    "wof:name":"Jimboomba Turf Group",
    "wof:placetype":"venue"
},
  "geometry": {"coordinates":[153.02641299999999,-27.831095],"type":"Point"}
}