{
  "type": "Feature",
  "properties": {
    "addr:full":"23 Shields Crs Booragoon WA 6154",
    "addr:housenumber":"23",
    "addr:postcode":"6154",
    "addr:street":"Shields Crs",
    "iso:country":"AU",
    "sg:address":"23 Shields Crs",
    "sg:city":"Booragoon",
    "sg:classifiers":[
        {
            "category":"Wholesale",
            "subcategory":"Construction Materials",
            "type":"Manufacturing & Wholesale Goods"
        }
    ],
    "sg:phone":"+61 8 9317 8922",
    "sg:postcode":"6154",
    "sg:province":"WA",
    "sg:tags":[
        "wholesaler",
        "lighting",
        "mfrs",
        "accessory"
    ],
    "wof:name":"Electrical Distributors Of W.A.",
    "wof:placetype":"venue"
},
  "geometry": {"coordinates":[115.832329,-32.036018],"type":"Point"}
}