{
  "type": "Feature",
  "properties": {
    "addr:full":"351 Concord Rd Concord West NSW 2138",
    "addr:housenumber":"351",
    "addr:postcode":"2138",
    "addr:street":"Concord Rd",
    "iso:country":"AU",
    "sg:address":"351 Concord Rd",
    "sg:city":"Concord West",
    "sg:classifiers":[
        {
            "category":"Professional",
            "subcategory":"Detective & Security Services",
            "type":"Services"
        }
    ],
    "sg:phone":"+61 2 9743 3344",
    "sg:postcode":"2138",
    "sg:province":"NSW",
    "sg:tags":[
        "guard",
        "patrol"
    ],
    "wof:name":"Site Security Patrols & Alarms",
    "wof:placetype":"venue"
},
  "geometry": {"coordinates":[151.08958435100001,-33.8471298218],"type":"Point"}
}