{
  "type": "Feature",
  "properties": {
    "addr:full":"76 Glenferrie Rd Malvern VIC 3144",
    "addr:housenumber":"76",
    "addr:postcode":"3144",
    "addr:street":"Glenferrie Rd",
    "iso:country":"AU",
    "sg:address":"76 Glenferrie Rd",
    "sg:city":"Malvern",
    "sg:classifiers":[
        {
            "category":"Personal",
            "subcategory":"Beauty Salon",
            "type":"Services"
        }
    ],
    "sg:phone":"+61 3 9509 1422",
    "sg:postcode":"3144",
    "sg:province":"VIC",
    "sg:tags":[
        "hairdresser"
    ],
    "wof:name":"Rucci Hair Design",
    "wof:placetype":"venue"
},
  "geometry": {"coordinates":[145.02842712399999,-37.8628540039],"type":"Point"}
}