{
  "type": "Feature",
  "properties": {
    "iso:country":"AU",
    "sg:address":"229 Robinson St",
    "sg:city":"Carnarvon",
    "sg:classifiers":[
        {
            "category":"Retail",
            "subcategory":"Auto Repair",
            "type":"Services"
        }
    ],
    "sg:phone":"+61 8 9941 1159",
    "sg:postcode":"6701",
    "sg:province":"WA",
    "sg:tags":[
        "clutch",
        "brake"
    ],
    "wof:name":"North West Auto's",
    "wof:placetype":"venue"
},
  "geometry": {"coordinates":[113.656448364,-24.884847641],"type":"Point"}
}