{
  "type": "Feature",
  "properties": {
    "addr:full":"65 Robey St Mascot NSW 2020",
    "addr:housenumber":"65",
    "addr:postcode":"2020",
    "addr:street":"Robey St",
    "iso:country":"AU",
    "sg:address":"65 Robey St",
    "sg:city":"Mascot",
    "sg:classifiers":[
        {
            "category":"Professional",
            "subcategory":"Engineering",
            "type":"Services"
        }
    ],
    "sg:phone":"+61 2 9669 6331",
    "sg:postcode":"2020",
    "sg:province":"NSW",
    "sg:tags":[
        "consulting",
        "engineer"
    ],
    "wof:name":"Carters Peter & Associates Pty Ltd",
    "wof:placetype":"venue"
},
  "geometry": {"coordinates":[151.190353394,-33.9310340881],"type":"Point"}
}