{
  "type": "Feature",
  "properties": {
    "addr:full":"2/ 75 Fortitude Vly Long Island QLD 4741",
    "addr:housenumber":"/ 75",
    "addr:postcode":"4741",
    "addr:street":"Fortitude Vly",
    "iso:country":"AU",
    "sg:address":"2/ 75",
    "sg:city":"Fortitude Vly Long Island",
    "sg:classifiers":[
        {
            "category":"Wholesale",
            "subcategory":"Painting Supplies",
            "type":"Manufacturing & Wholesale Goods"
        }
    ],
    "sg:phone":"+61 7 3252 5966",
    "sg:postcode":"4741",
    "sg:province":"QLD",
    "sg:tags":[
        "painter"
    ],
    "wof:name":"Wattyl",
    "wof:placetype":"venue"
},
  "geometry": {"coordinates":[148.339584,-21.01993],"type":"Point"}
}