{
  "type": "Feature",
  "properties": {
    "iso:country":"AU",
    "sg:address":"26 Finniss St",
    "sg:city":"Gawler",
    "sg:classifiers":[
        {
            "category":"Professional",
            "type":"Services"
        }
    ],
    "sg:phone":"+61 8 8523 5222",
    "sg:postcode":"5118",
    "sg:province":"SA",
    "sg:tags":[
        "transport"
    ],
    "wof:name":"J & C Transport SA Pty Ltd",
    "wof:placetype":"venue"
},
  "geometry": {"coordinates":[138.742828,-34.597878],"type":"Point"}
}