{
  "type": "Feature",
  "properties": {
    "iso:country":"AU",
    "sg:address":"217 Oban Rd",
    "sg:city":"Ringwood North",
    "sg:classifiers":[
        {
            "category":"Building & Trades",
            "subcategory":"Construction",
            "type":"Services"
        }
    ],
    "sg:phone":"+61 3 9879 9156",
    "sg:postcode":"3134",
    "sg:province":"VIC",
    "sg:tags":[
        "contractor"
    ],
    "wof:name":"Donaldson Homes Pty Ltd",
    "wof:placetype":"venue"
},
  "geometry": {"coordinates":[145.221923828,-37.7924537659],"type":"Point"}
}