{
  "type": "Feature",
  "properties": {
    "addr:full":"2 Vicki St Blackburn VIC 3130",
    "addr:housenumber":"2",
    "addr:postcode":"3130",
    "addr:street":"Vicki St",
    "iso:country":"AU",
    "sg:address":"2 Vicki St",
    "sg:city":"Blackburn",
    "sg:classifiers":[
        {
            "category":"Retail",
            "subcategory":"Event Space",
            "type":"Services"
        }
    ],
    "sg:phone":"+61 3 9878 4156",
    "sg:postcode":"3130",
    "sg:province":"VIC",
    "sg:tags":[
        "function",
        "organiser"
    ],
    "wof:name":"Le Calvados",
    "wof:placetype":"venue"
},
  "geometry": {"coordinates":[145.155639648,-37.8408927917],"type":"Point"}
}