{
  "type": "Feature",
  "properties": {
    "addr:full":"28 King St Grafton NSW 2460",
    "addr:housenumber":"28",
    "addr:postcode":"2460",
    "addr:street":"King St",
    "iso:country":"AU",
    "sg:address":"28 King St",
    "sg:city":"Grafton",
    "sg:classifiers":[
        {
            "category":"Retail",
            "subcategory":"Laundry & Dry Cleaning",
            "type":"Services"
        }
    ],
    "sg:phone":"+61 412 481 358",
    "sg:postcode":"2460",
    "sg:province":"NSW",
    "wof:name":"Jacaranda Laundry",
    "wof:placetype":"venue"
},
  "geometry": {"coordinates":[152.933105469,-29.6895160675],"type":"Point"}
}