{
  "type": "Feature",
  "properties": {
    "iso:country":"AU",
    "sg:address":"Hepworth St",
    "sg:city":"Berri",
    "sg:classifiers":[
        {
            "category":"Organizations",
            "subcategory":"Professional Association",
            "type":"Services"
        }
    ],
    "sg:phone":"+61 8 8582 3399",
    "sg:postcode":"5343",
    "sg:province":"SA",
    "sg:tags":[
        "organisation",
        "business"
    ],
    "wof:name":"Institute Of Medical & Veterinary Science",
    "wof:placetype":"venue"
},
  "geometry": {"coordinates":[140.59983825699999,-34.2767562866],"type":"Point"}
}