{
  "type": "Feature",
  "properties": {
    "addr:full":"550 Riversdale Rd Camberwell VIC 3124",
    "addr:housenumber":"550",
    "addr:postcode":"3124",
    "addr:street":"Riversdale Rd",
    "iso:country":"AU",
    "sg:address":"550 Riversdale Rd",
    "sg:city":"Camberwell",
    "sg:classifiers":[
        {
            "category":"Food & Beverages",
            "subcategory":"Supermarket",
            "type":"Retail Goods"
        }
    ],
    "sg:phone":"+61 3 9813 2697",
    "sg:postcode":"3124",
    "sg:province":"VIC",
    "sg:tags":[
        "grocery",
        "store"
    ],
    "wof:name":"Safeway + Plus Petrol",
    "wof:placetype":"venue"
},
  "geometry": {"coordinates":[145.05900573700001,-37.8317146301],"type":"Point"}
}