{
  "type": "Feature",
  "properties": {
    "iso:country":"AU",
    "sg:address":"Cnr Amazons Pl & Pavilions Cl",
    "sg:city":"Jindalee",
    "sg:classifiers":[
        {
            "category":"Education",
            "subcategory":"Special Training",
            "type":"Public Place"
        }
    ],
    "sg:phone":"+61 7 3725 5555",
    "sg:postcode":"4074",
    "sg:province":"QLD",
    "sg:tags":[
        "development"
    ],
    "wof:name":"ACQ Conference & Event Management",
    "wof:placetype":"venue"
},
  "geometry": {"coordinates":[152.94883727999999,-27.5323467255],"type":"Point"}
}