{
  "type": "Feature",
  "properties": {
    "addr:full":"368 Dean St North Rockhampton QLD 4701",
    "addr:housenumber":"368",
    "addr:postcode":"4701",
    "addr:street":"Dean St North",
    "iso:country":"AU",
    "sg:address":"368 Dean St",
    "sg:city":"North Rockhampton",
    "sg:classifiers":[
        {
            "category":"Food & Beverages",
            "subcategory":"Liquor & Beverages",
            "type":"Retail Goods"
        }
    ],
    "sg:phone":"+61 7 4928 4888",
    "sg:postcode":"4701",
    "sg:province":"QLD",
    "sg:tags":[
        "store"
    ],
    "wof:name":"North Rockhampton Bottle Shop",
    "wof:placetype":"venue"
},
  "geometry": {"coordinates":[150.53729248100001,-23.3488006592],"type":"Point"}
}