{
  "type": "Feature",
  "properties": {
    "iso:country":"AU",
    "sg:address":"PO Box 585",
    "sg:city":"Mossman",
    "sg:classifiers":[
        {
            "category":"Real Estate",
            "subcategory":"Real Estate Agent",
            "type":"Services"
        }
    ],
    "sg:phone":"+61 428 988 418",
    "sg:postcode":"4873",
    "sg:province":"QLD",
    "sg:tags":[
        "handyman's",
        "equipment",
        "hire",
        "builders",
        "contractor"
    ],
    "wof:name":"Kelly's Crane Hire Pty Ltd",
    "wof:placetype":"venue"
},
  "geometry": {"coordinates":[145.37359619099999,-16.4611606598],"type":"Point"}
}