{
  "type": "Feature",
  "properties": {
    "addr:full":"40 Mataram Rd Woongarrah NSW 2259",
    "addr:housenumber":"40",
    "addr:postcode":"2259",
    "addr:street":"Mataram Rd",
    "iso:country":"AU",
    "sg:address":"40 Mataram Rd",
    "sg:city":"Woongarrah",
    "sg:classifiers":[
        {
            "category":"Building & Trades",
            "subcategory":"Construction",
            "type":"Services"
        }
    ],
    "sg:phone":"+61 1800 654 943",
    "sg:postcode":"2259",
    "sg:province":"NSW",
    "sg:tags":[
        "earth",
        "excavating",
        "moving",
        "contractor"
    ],
    "wof:name":"Coastrock & Earth Excavations",
    "wof:placetype":"venue"
},
  "geometry": {"coordinates":[151.487991333,-33.2431411743],"type":"Point"}
}