{
  "type": "Feature",
  "properties": {
    "addr:full":"39 Kathryn Crt Riddells Creek VIC 3431",
    "addr:housenumber":"39",
    "addr:postcode":"3431",
    "addr:street":"Kathryn Crt",
    "iso:country":"AU",
    "sg:address":"39 Kathryn Crt",
    "sg:city":"Riddells Creek",
    "sg:classifiers":[
        {
            "category":"Professional",
            "subcategory":"Accounting & Tax Preparation",
            "type":"Services"
        }
    ],
    "sg:phone":"+61 3 5428 7830",
    "sg:postcode":"3431",
    "sg:province":"VIC",
    "sg:tags":[
        "consultant",
        "taxation"
    ],
    "wof:name":"Riddell Accounting Services",
    "wof:placetype":"venue"
},
  "geometry": {"coordinates":[144.699615478,-37.45885849],"type":"Point"}
}