{
  "type": "Feature",
  "properties": {
    "addr:full":"2 Lydia Ave Surrey Downs SA 5126",
    "addr:housenumber":"2",
    "addr:postcode":"5126",
    "addr:street":"Lydia Ave",
    "iso:country":"AU",
    "sg:address":"2 Lydia Ave",
    "sg:city":"Surrey Downs",
    "sg:classifiers":[
        {
            "category":"Building & Trades",
            "subcategory":"Plumbing",
            "type":"Services"
        }
    ],
    "sg:phone":"+61 8 8251 1694",
    "sg:postcode":"5126",
    "sg:province":"SA",
    "sg:tags":[
        "plumber",
        "gasfitters"
    ],
    "wof:name":"R & V Plumbing",
    "wof:placetype":"venue"
},
  "geometry": {"coordinates":[138.716186523,-34.8048248291],"type":"Point"}
}