{
  "type": "Feature",
  "properties": {
    "addr:full":"208 Torquay Rd Grovedale VIC 3216",
    "addr:housenumber":"208",
    "addr:postcode":"3216",
    "addr:street":"Torquay Rd",
    "iso:country":"AU",
    "sg:address":"208 Torquay Rd",
    "sg:city":"Grovedale",
    "sg:classifiers":[
        {
            "category":"School Buses",
            "type":"Transportation"
        }
    ],
    "sg:phone":"+61 3 5245 7633",
    "sg:postcode":"3216",
    "sg:province":"VIC",
    "sg:tags":[
        "brick"
    ],
    "wof:name":"Selkirk Bricks & Pavers",
    "wof:placetype":"venue"
},
  "geometry": {"coordinates":[144.34048461899999,-38.2067527771],"type":"Point"}
}