{
  "type": "Feature",
  "properties": {
    "addr:full":"16 Perthville Crt Hillbank SA 5112",
    "addr:housenumber":"16",
    "addr:postcode":"5112",
    "addr:street":"Perthville Crt",
    "iso:country":"AU",
    "sg:address":"16 Perthville Crt",
    "sg:city":"Hillbank",
    "sg:classifiers":[
        {
            "category":"Building & Trades",
            "subcategory":"Construction",
            "type":"Services"
        }
    ],
    "sg:phone":"+61 401 305 078",
    "sg:postcode":"5112",
    "sg:province":"SA",
    "sg:tags":[
        "stonework",
        "stone",
        "mason"
    ],
    "wof:name":"Sean O&#039;Grady",
    "wof:placetype":"venue"
},
  "geometry": {"coordinates":[138.68708801299999,-34.7324295044],"type":"Point"}
}