{
  "type": "Feature",
  "properties": {
    "addr:full":"3 Cobbity St Seven Hills NSW 2147",
    "addr:housenumber":"3",
    "addr:postcode":"2147",
    "addr:street":"Cobbity St",
    "iso:country":"AU",
    "sg:address":"3 Cobbity St",
    "sg:city":"Seven Hills",
    "sg:classifiers":[
        {
            "category":"Professional",
            "subcategory":"Art Services",
            "type":"Services"
        }
    ],
    "sg:phone":"+61 418 995 326",
    "sg:postcode":"2147",
    "sg:province":"NSW",
    "sg:tags":[
        "decorator",
        "painter"
    ],
    "wof:name":"Arrow Painting",
    "wof:placetype":"venue"
},
  "geometry": {"coordinates":[150.95001220699999,-33.7645263672],"type":"Point"}
}