{
  "type": "Feature",
  "properties": {
    "addr:full":"1 Cecil Ave Pennant Hills NSW 2120",
    "addr:housenumber":"1",
    "addr:postcode":"2120",
    "addr:street":"Cecil Ave",
    "iso:country":"AU",
    "sg:address":"1 Cecil Ave",
    "sg:city":"Pennant Hills",
    "sg:classifiers":[
        {
            "category":"Building & Trades",
            "subcategory":"Pest Control",
            "type":"Services"
        }
    ],
    "sg:phone":"+61 419 015 257",
    "sg:postcode":"2120",
    "sg:province":"NSW",
    "wof:name":"Possum Advice & Removal",
    "wof:placetype":"venue"
},
  "geometry": {"coordinates":[151.07672119099999,-33.7393112183],"type":"Point"}
}