{
  "type": "Feature",
  "properties": {
    "addr:full":"81 Watsonia Rd Watsonia VIC 3087",
    "addr:housenumber":"81",
    "addr:postcode":"3087",
    "addr:street":"Watsonia Rd",
    "iso:country":"AU",
    "sg:address":"81 Watsonia Rd",
    "sg:city":"Watsonia",
    "sg:classifiers":[
        {
            "category":"Communications",
            "subcategory":"Film & Video Production",
            "type":"Services"
        }
    ],
    "sg:phone":"+61 3 9434 3221",
    "sg:postcode":"3087",
    "sg:province":"VIC",
    "sg:tags":[
        "dvd",
        "library"
    ],
    "wof:name":"Watsonia Video",
    "wof:placetype":"venue"
},
  "geometry": {"coordinates":[145.082763672,-37.709400177],"type":"Point"}
}