{
  "type": "Feature",
  "properties": {
    "iso:country":"AU",
    "sg:address":"14 Wilson St",
    "sg:city":"Strathfield",
    "sg:classifiers":[
        {
            "category":"Building & Trades",
            "subcategory":"Construction",
            "type":"Services"
        }
    ],
    "sg:phone":"+61 419 297 647",
    "sg:postcode":"2135",
    "sg:province":"NSW",
    "sg:tags":[
        "contractor"
    ],
    "wof:name":"Kevin Barry Building Service",
    "wof:placetype":"venue"
},
  "geometry": {"coordinates":[151.074050903,-33.8786888123],"type":"Point"}
}