{
  "type": "Feature",
  "properties": {
    "addr:full":"6a Balmoral Ave Springvale VIC 3171",
    "addr:housenumber":"6a",
    "addr:postcode":"3171",
    "addr:street":"Balmoral Ave",
    "iso:country":"AU",
    "sg:address":"6a Balmoral Ave",
    "sg:city":"Springvale",
    "sg:classifiers":[
        {
            "category":"Personal",
            "subcategory":"Beauty Salon",
            "type":"Services"
        }
    ],
    "sg:phone":"+61 3 9546 5479",
    "sg:postcode":"3171",
    "sg:province":"VIC",
    "sg:tags":[
        "hairdresser"
    ],
    "wof:name":"Hollywood Unisex Hair Studio",
    "wof:placetype":"venue"
},
  "geometry": {"coordinates":[145.152267456,-37.9497375488],"type":"Point"}
}