{
  "type": "Feature",
  "properties": {
    "iso:country":"AU",
    "sg:address":"Shop 5/ 202 Scott St",
    "sg:city":"Cairns",
    "sg:classifiers":[
        {
            "category":"Retail",
            "subcategory":"Repair Shop",
            "type":"Services"
        }
    ],
    "sg:phone":"+61 7 4054 1866",
    "sg:postcode":"4870",
    "sg:province":"QLD",
    "sg:tags":[
        "upholsterer"
    ],
    "wof:name":"Far Northern Lounge Makers",
    "wof:placetype":"venue"
},
  "geometry": {"coordinates":[145.752609253,-16.9400005341],"type":"Point"}
}