{
  "type": "Feature",
  "properties": {
    "addr:full":"Cnr Victoria Ave & Gladstone Rd Castle Hill NSW 2154",
    "addr:postcode":"2154",
    "addr:street":"Cnr Victoria Ave & Gladstone Rd",
    "iso:country":"AU",
    "sg:address":"Cnr Victoria Ave & Gladstone Rd",
    "sg:city":"Castle Hill",
    "sg:classifiers":[
        {
            "category":"Home & Garden",
            "subcategory":"Furniture",
            "type":"Retail Goods"
        }
    ],
    "sg:phone":"+61 2 9659 0122",
    "sg:postcode":"2154",
    "sg:province":"NSW",
    "sg:tags":[
        "business"
    ],
    "wof:name":"Desks Etc",
    "wof:placetype":"venue"
},
  "geometry": {"coordinates":[150.98161315900001,-33.7353782654],"type":"Point"}
}