{
  "type": "Feature",
  "properties": {
    "iso:country":"AU",
    "sg:address":"293 Kensington Rd",
    "sg:city":"Kensington Park",
    "sg:classifiers":[
        {
            "category":"Health Services",
            "subcategory":"Chiropractor",
            "type":"Services"
        }
    ],
    "sg:phone":"+61 8 8364 6663",
    "sg:postcode":"5068",
    "sg:province":"SA",
    "wof:name":"Bartram Victoria Dr",
    "wof:placetype":"venue"
},
  "geometry": {"coordinates":[138.655593872,-34.9260787964],"type":"Point"}
}