{
  "type": "Feature",
  "properties": {
    "addr:full":"Ste1/ 10 Ninth Ave Rosebud VIC 3939",
    "addr:housenumber":"10",
    "addr:postcode":"3939",
    "addr:street":"Ninth Ave",
    "iso:country":"AU",
    "sg:address":"Ste1/ 10 Ninth Ave",
    "sg:city":"Rosebud",
    "sg:classifiers":[
        {
            "category":"Professional",
            "subcategory":"Employment Agencies",
            "type":"Services"
        }
    ],
    "sg:phone":"+61 3 5986 4623",
    "sg:postcode":"3939",
    "sg:province":"VIC",
    "wof:name":"Peninsula Training & Employment Program Inc",
    "wof:placetype":"venue"
},
  "geometry": {"coordinates":[144.90379333499999,-38.3565711975],"type":"Point"}
}