{
  "type": "Feature",
  "properties": {
    "iso:country":"AU",
    "sg:address":"16 Jolly Nose Drv",
    "sg:city":"Bonny Hills",
    "sg:classifiers":[
        {
            "category":"Health Services",
            "subcategory":"Chiropractor",
            "type":"Services"
        }
    ],
    "sg:phone":"+61 2 6585 5005",
    "sg:postcode":"2445",
    "sg:province":"NSW",
    "wof:name":"Bridson David",
    "wof:placetype":"venue"
},
  "geometry": {"coordinates":[152.81504799999999,-31.573463],"type":"Point"}
}