{
  "type": "Feature",
  "properties": {
    "addr:full":"14 Howgate Crt Eltham VIC 3095",
    "addr:housenumber":"14",
    "addr:postcode":"3095",
    "addr:street":"Howgate Crt",
    "iso:country":"AU",
    "sg:address":"14 Howgate Crt",
    "sg:city":"Eltham",
    "sg:classifiers":[
        {
            "category":"Home & Garden",
            "subcategory":"Carpets & Floor Coverings",
            "type":"Retail Goods"
        }
    ],
    "sg:phone":"+61 3 9439 2112",
    "sg:postcode":"3095",
    "sg:province":"VIC",
    "sg:tags":[
        "tile",
        "wall",
        "layer"
    ],
    "wof:name":"Nass H & R",
    "wof:placetype":"venue"
},
  "geometry": {"coordinates":[145.158035278,-37.7212638855],"type":"Point"}
}