{
  "type": "Feature",
  "properties": {
    "addr:full":"Office 5 94 Byrnes St Mareeba QLD 4880",
    "addr:housenumber":"94",
    "addr:postcode":"4880",
    "addr:street":"Byrnes St",
    "iso:country":"AU",
    "sg:address":"Office 5 94 Byrnes St",
    "sg:city":"Mareeba",
    "sg:classifiers":[
        {
            "category":"Farming",
            "subcategory":"Farm & Veterinary Services",
            "type":"Manufacturing & Wholesale Goods"
        }
    ],
    "sg:phone":"+61 7 4092 6720",
    "sg:postcode":"4880",
    "sg:province":"QLD",
    "sg:tags":[
        "irrigation",
        "reticulation",
        "system"
    ],
    "wof:name":"North Australian Water Strategies",
    "wof:placetype":"venue"
},
  "geometry": {"coordinates":[145.422363281,-16.9937229156],"type":"Point"}
}