{
  "type": "Feature",
  "properties": {
    "iso:country":"AU",
    "sg:address":"Suite26/ 8 Avenue Of The America's",
    "sg:city":"Newington",
    "sg:classifiers":[
        {
            "category":"Professional",
            "subcategory":"Accounting & Tax Preparation",
            "type":"Services"
        }
    ],
    "sg:phone":"+61 2 9731 2001",
    "sg:postcode":"2127",
    "sg:province":"NSW",
    "sg:tags":[
        "accountant",
        "auditor"
    ],
    "wof:name":"The Financial Position",
    "wof:placetype":"venue"
},
  "geometry": {"coordinates":[151.05499267600001,-33.8398857117],"type":"Point"}
}