{
  "type": "Feature",
  "properties": {
    "iso:country":"AU",
    "sg:address":"Shp1/ 323 Main Rd",
    "sg:city":"St Albans",
    "sg:classifiers":[
        {
            "category":"Shopping",
            "subcategory":"Pawn Shop",
            "type":"Retail Goods"
        }
    ],
    "sg:phone":"+61 3 9362 1735",
    "sg:postcode":"3021",
    "sg:province":"VIC",
    "sg:tags":[
        "pawnbroker"
    ],
    "wof:name":"Greater Trader Pawnbrokers",
    "wof:placetype":"venue"
},
  "geometry": {"coordinates":[144.800217,-37.744255],"type":"Point"}
}