{
  "type": "Feature",
  "properties": {
    "iso:country":"AU",
    "sg:address":"4/ 5 Lyrebird St",
    "sg:city":"Buderim",
    "sg:classifiers":[
        {
            "category":"Health Services",
            "subcategory":"Health Practitioner",
            "type":"Services"
        }
    ],
    "sg:phone":"+61 7 5444 2751",
    "sg:postcode":"4556",
    "sg:province":"QLD",
    "sg:tags":[
        "physiotherapist"
    ],
    "wof:name":"Northcoast Physiotherapy Clinic",
    "wof:placetype":"venue"
},
  "geometry": {"coordinates":[153.09127807600001,-26.6833686829],"type":"Point"}
}