{
  "type": "Feature",
  "properties": {
    "iso:country":"AU",
    "sg:address":"7 Egret Pl",
    "sg:city":"Woronora Heights",
    "sg:classifiers":[
        {
            "category":"Building & Trades",
            "subcategory":"Construction",
            "type":"Services"
        }
    ],
    "sg:phone":"+61 2 9545 1178",
    "sg:postcode":"2233",
    "sg:province":"NSW",
    "sg:tags":[
        "contractor"
    ],
    "wof:name":"John Buckley Architectural Design Drafting And Building Services",
    "wof:placetype":"venue"
},
  "geometry": {"coordinates":[151.030853272,-34.0365524292],"type":"Point"}
}