{
  "type": "Feature",
  "properties": {
    "addr:full":"26 High St Frankston VIC 3199",
    "addr:housenumber":"26",
    "addr:postcode":"3199",
    "addr:street":"High St",
    "iso:country":"AU",
    "sg:address":"26 High St",
    "sg:city":"Frankston",
    "sg:classifiers":[
        {
            "category":"Professional",
            "subcategory":"Employment Agencies",
            "type":"Services"
        }
    ],
    "sg:phone":"+61 3 9770 0633",
    "sg:postcode":"3199",
    "sg:province":"VIC",
    "wof:name":"Job Futures",
    "wof:placetype":"venue"
},
  "geometry": {"coordinates":[145.28318786599999,-38.1120681763],"type":"Point"}
}