{
  "type": "Feature",
  "properties": {
    "addr:full":"769 Doncaster Rd Doncaster VIC 3108",
    "addr:housenumber":"769",
    "addr:postcode":"3108",
    "addr:street":"Doncaster Rd",
    "iso:country":"AU",
    "sg:address":"769 Doncaster Rd",
    "sg:city":"Doncaster",
    "sg:classifiers":[
        {
            "category":"Government",
            "subcategory":"Court House",
            "type":"Public Place"
        }
    ],
    "sg:phone":"+61 3 9848 2177",
    "sg:postcode":"3108",
    "sg:province":"VIC",
    "sg:tags":[
        "personal",
        "marriage",
        "family",
        "counselling"
    ],
    "wof:name":"Glenda Bishop",
    "wof:placetype":"venue"
},
  "geometry": {"coordinates":[145.13539123499999,-37.7865142822],"type":"Point"}
}