{
  "type": "Feature",
  "properties": {
    "iso:country":"AU",
    "sg:address":"13d Acacia St",
    "sg:city":"Byron Bay",
    "sg:classifiers":[
        {
            "category":"Professional",
            "subcategory":"Printing & Photocopies",
            "type":"Services"
        }
    ],
    "sg:phone":"+61 2 6685 7890",
    "sg:postcode":"2481",
    "sg:province":"NSW",
    "sg:tags":[
        "trophy"
    ],
    "wof:name":"Byron Bay Signs & Trophies",
    "wof:placetype":"venue"
},
  "geometry": {"coordinates":[153.5859375,-28.6359138489],"type":"Point"}
}