{
  "type": "Feature",
  "properties": {
    "addr:full":"Fctry 3 1 Rosella St Frankston VIC 3199",
    "addr:housenumber":"3 1",
    "addr:postcode":"3199",
    "addr:street":"Fctry;Rosella St",
    "iso:country":"AU",
    "sg:address":"Fctry 3 1 Rosella St",
    "sg:city":"Frankston",
    "sg:classifiers":[
        {
            "category":"Professional",
            "subcategory":"Engineering",
            "type":"Services"
        }
    ],
    "sg:phone":"+61 3 9769 6345",
    "sg:postcode":"3199",
    "sg:province":"VIC",
    "sg:tags":[
        "engineer"
    ],
    "wof:name":"E & A Allen Engineering",
    "wof:placetype":"venue"
},
  "geometry": {"coordinates":[145.12651062,-38.1306610107],"type":"Point"}
}