{
  "type": "Feature",
  "properties": {
    "addr:full":"168 Merrigang St Bowral NSW 2576",
    "addr:housenumber":"168",
    "addr:postcode":"2576",
    "addr:street":"Merrigang St",
    "iso:country":"AU",
    "sg:address":"168 Merrigang St",
    "sg:city":"Bowral",
    "sg:classifiers":[
        {
            "category":"Utilities",
            "subcategory":"Electric",
            "type":"Services"
        }
    ],
    "sg:phone":"+61 418 288 621",
    "sg:postcode":"2576",
    "sg:province":"NSW",
    "sg:tags":[
        "electrical",
        "contractor"
    ],
    "wof:name":"Bob VanOs Electrics",
    "wof:placetype":"venue"
},
  "geometry": {"coordinates":[150.43440246599999,-34.4799499512],"type":"Point"}
}