{
  "type": "Feature",
  "properties": {
    "addr:full":"105 Station Rd Seven Hills NSW 2147",
    "addr:housenumber":"105",
    "addr:postcode":"2147",
    "addr:street":"Station Rd",
    "iso:country":"AU",
    "sg:address":"105 Station Rd",
    "sg:city":"Seven Hills",
    "sg:classifiers":[
        {
            "category":"Retail",
            "subcategory":"Auto Repair",
            "type":"Services"
        }
    ],
    "sg:phone":"+61 2 9838 9366",
    "sg:postcode":"2147",
    "sg:province":"NSW",
    "sg:tags":[
        "repairer",
        "motor",
        "engineer"
    ],
    "wof:name":"Taurus Service Centre Caltex Seven Hills",
    "wof:placetype":"venue"
},
  "geometry": {"coordinates":[150.94461059599999,-33.7740783691],"type":"Point"}
}