{
  "type": "Feature",
  "properties": {
    "iso:country":"AU",
    "sg:address":"194 Numurkah Rd",
    "sg:city":"Shepparton",
    "sg:classifiers":[
        {
            "category":"Building & Trades",
            "subcategory":"Construction",
            "type":"Services"
        }
    ],
    "sg:phone":"+61 3 5821 2665",
    "sg:postcode":"3630",
    "sg:province":"VIC",
    "sg:tags":[
        "window",
        "aluminium"
    ],
    "wof:name":"Dowell",
    "wof:placetype":"venue"
},
  "geometry": {"coordinates":[145.401855469,-36.3520355225],"type":"Point"}
}