{
  "type": "Feature",
  "properties": {
    "iso:country":"AU",
    "sg:address":"19 Morningbird Cl",
    "sg:city":"St Clair",
    "sg:classifiers":[
        {
            "category":"Organizations",
            "subcategory":"Membership Organization",
            "type":"Services"
        }
    ],
    "sg:phone":"+61 2 9670 6989",
    "sg:postcode":"2759",
    "sg:province":"NSW",
    "sg:tags":[
        "recording",
        "system",
        "time"
    ],
    "wof:name":"Omicron Time Systems",
    "wof:placetype":"venue"
},
  "geometry": {"coordinates":[150.77980041500001,-33.7973594666],"type":"Point"}
}