{
  "type": "Feature",
  "properties": {
    "addr:full":"11 Highlands St Wavell Heights QLD 4012",
    "addr:housenumber":"11",
    "addr:postcode":"4012",
    "addr:street":"Highlands St",
    "iso:country":"AU",
    "sg:address":"11 Highlands St",
    "sg:city":"Wavell Heights",
    "sg:classifiers":[
        {
            "category":"Building & Trades",
            "subcategory":"Plumbing",
            "type":"Services"
        }
    ],
    "sg:phone":"+61 7 3266 6177",
    "sg:postcode":"4012",
    "sg:province":"QLD",
    "sg:tags":[
        "plumber",
        "gasfitters"
    ],
    "wof:name":"A & G W Hood & Sons",
    "wof:placetype":"venue"
},
  "geometry": {"coordinates":[153.05128479000001,-27.3936824799],"type":"Point"}
}