{
  "type": "Feature",
  "properties": {
    "iso:country":"AU",
    "sg:address":"Shop 1, Loxton House, Bridge St",
    "sg:city":"Muswellbrook",
    "sg:classifiers":[
        {
            "category":"Personal",
            "subcategory":"Beauty Salon",
            "type":"Services"
        }
    ],
    "sg:phone":"+61 2 6541 1663",
    "sg:postcode":"2333",
    "sg:province":"NSW",
    "sg:tags":[
        "supply",
        "artist",
        "make-up"
    ],
    "wof:name":"Colonial Classic Salon The",
    "wof:placetype":"venue"
},
  "geometry": {"coordinates":[150.88824462900001,-32.2660865784],"type":"Point"}
}