{
  "type": "Feature",
  "properties": {
    "addr:full":"Ste 502/ 60 Miller St North Sydney NSW 2060",
    "addr:housenumber":"/ 60",
    "addr:postcode":"2060",
    "addr:street":"Miller St",
    "iso:country":"AU",
    "sg:address":"Ste 502/ 60 Miller St",
    "sg:city":"North Sydney",
    "sg:classifiers":[
        {
            "category":"Banks & Credit Unions",
            "subcategory":"Financial Services",
            "type":"Services"
        }
    ],
    "sg:phone":"+61 2 9299 9875",
    "sg:postcode":"2060",
    "sg:province":"NSW",
    "sg:tags":[
        "annuity",
        "rollover",
        "superannuation",
        "consultant"
    ],
    "wof:name":"Fowke Birch & Assoc Pty Ltd",
    "wof:placetype":"venue"
},
  "geometry": {"coordinates":[151.206665039,-33.839176178],"type":"Point"}
}