{
  "type": "Feature",
  "properties": {
    "addr:full":"32 Fairy St Warrnambool VIC 3280",
    "addr:housenumber":"32",
    "addr:postcode":"3280",
    "addr:street":"Fairy St",
    "iso:country":"AU",
    "sg:address":"32 Fairy St",
    "sg:city":"Warrnambool",
    "sg:classifiers":[
        {
            "category":"Sports & Exercise",
            "subcategory":"Race Track",
            "type":"Entertainment"
        }
    ],
    "sg:phone":"+61 3 5562 8229",
    "sg:postcode":"3280",
    "sg:province":"VIC",
    "sg:tags":[
        "club",
        "racing",
        "motor"
    ],
    "wof:name":"Premier Speedway",
    "wof:placetype":"venue"
},
  "geometry": {"coordinates":[142.47753906200001,-38.3839454651],"type":"Point"}
}