{
  "type": "Feature",
  "properties": {
    "iso:country":"AU",
    "sg:address":"4/ 17 Britton Rd",
    "sg:city":"Seville",
    "sg:classifiers":[
        {
            "category":"Shopping",
            "subcategory":"Crafts & Fabrics",
            "type":"Retail Goods"
        }
    ],
    "sg:phone":"+61 3 5964 4845",
    "sg:postcode":"3139",
    "sg:province":"VIC",
    "sg:tags":[
        "supply"
    ],
    "wof:name":"Banksia Beads",
    "wof:placetype":"venue"
},
  "geometry": {"coordinates":[145.458084106,-37.7768554688],"type":"Point"}
}