{
  "type": "Feature",
  "properties": {
    "iso:country":"AU",
    "sg:address":"22 Walz St",
    "sg:city":"Rockdale",
    "sg:classifiers":[
        {
            "category":"Food & Beverages",
            "subcategory":"Supermarket",
            "type":"Retail Goods"
        }
    ],
    "sg:phone":"+61 2 9599 3239",
    "sg:postcode":"2216",
    "sg:province":"NSW",
    "sg:tags":[
        "grocery",
        "store"
    ],
    "wof:name":"Taoube Fruit Market",
    "wof:placetype":"venue"
},
  "geometry": {"coordinates":[151.135391,-33.951675],"type":"Point"}
}