{
  "type": "Feature",
  "properties": {
    "addr:full":"84 Hill St North Ipswich QLD 4305",
    "addr:housenumber":"84",
    "addr:postcode":"4305",
    "addr:street":"Hill St",
    "iso:country":"AU",
    "sg:address":"84 Hill St",
    "sg:city":"North Ipswich",
    "sg:classifiers":[
        {
            "category":"Social Services",
            "subcategory":"Child Care",
            "type":"Services"
        }
    ],
    "sg:phone":"+61 7 3281 0351",
    "sg:postcode":"4305",
    "sg:province":"QLD",
    "wof:name":"North Ipswich Child Care Centre Inc",
    "wof:placetype":"venue"
},
  "geometry": {"coordinates":[152.76873779300001,-27.591676712],"type":"Point"}
}