{
  "type": "Feature",
  "properties": {
    "iso:country":"AU",
    "sg:address":"5/ 29 Point Walter Rd",
    "sg:city":"Bicton",
    "sg:classifiers":[
        {
            "category":"Mining & Drilling",
            "type":"Manufacturing & Wholesale Goods"
        }
    ],
    "sg:phone":"+61 8 9438 1584",
    "sg:postcode":"6157",
    "sg:province":"WA",
    "sg:tags":[
        "geologist"
    ],
    "wof:name":"Argold Holdings Pty Ltd",
    "wof:placetype":"venue"
},
  "geometry": {"coordinates":[115.78443900000001,-32.033241],"type":"Point"}
}