{
  "type": "Feature",
  "properties": {
    "iso:country":"AU",
    "sg:address":"187 Main St",
    "sg:city":"West Wyalong",
    "sg:classifiers":[
        {
            "category":"Food & Beverages",
            "subcategory":"Bakery",
            "type":"Retail Goods"
        }
    ],
    "sg:phone":"+61 2 6972 1777",
    "sg:postcode":"2671",
    "sg:province":"NSW",
    "sg:tags":[
        "baker"
    ],
    "wof:name":"Roundabout Bakery West Wyalong",
    "wof:placetype":"venue"
},
  "geometry": {"coordinates":[147.201416016,-33.9222717285],"type":"Point"}
}