{
  "type": "Feature",
  "properties": {
    "addr:full":"Cnr Somerville Rd & Wren St Hampton Park VIC 3976",
    "addr:postcode":"3976",
    "addr:street":"Cnr Somerville Rd & Wren St",
    "iso:country":"AU",
    "sg:address":"Cnr Somerville Rd & Wren St",
    "sg:city":"Hampton Park",
    "sg:classifiers":[
        {
            "category":"Health Services",
            "subcategory":"Dentist",
            "type":"Services"
        }
    ],
    "sg:phone":"+61 3 9799 3300",
    "sg:postcode":"3976",
    "sg:province":"VIC",
    "wof:name":"Dental Extra Care",
    "wof:placetype":"venue"
},
  "geometry": {"coordinates":[145.26742553700001,-38.0321273804],"type":"Point"}
}