{
  "type": "Feature",
  "properties": {
    "addr:full":"49 Botany Rd Waterloo NSW 2017",
    "addr:housenumber":"49",
    "addr:postcode":"2017",
    "addr:street":"Botany Rd",
    "iso:country":"AU",
    "sg:address":"49 Botany Rd",
    "sg:city":"Waterloo",
    "sg:classifiers":[
        {
            "category":"Retail",
            "subcategory":"Auto Rental",
            "type":"Services"
        }
    ],
    "sg:phone":"+61 2 8303 2222",
    "sg:postcode":"2017",
    "sg:province":"NSW",
    "sg:tags":[
        "car",
        "hire",
        "minibus"
    ],
    "wof:name":"Red Spot Rentals",
    "wof:placetype":"venue"
},
  "geometry": {"coordinates":[151.19943237300001,-33.8967514038],"type":"Point"}
}