{
  "type": "Feature",
  "properties": {
    "addr:full":"Lisle St Katanning WA 6317",
    "addr:postcode":"6317",
    "addr:street":"Lisle St",
    "iso:country":"AU",
    "sg:address":"Lisle St",
    "sg:city":"Katanning",
    "sg:classifiers":[
        {
            "category":"Wholesale",
            "subcategory":"Fruits & Vegetables",
            "type":"Manufacturing & Wholesale Goods"
        }
    ],
    "sg:phone":"+61 8 9821 1244",
    "sg:postcode":"6317",
    "sg:province":"WA",
    "sg:tags":[
        "produce",
        "grain"
    ],
    "wof:name":"Co -Operative Bulk Handling Ltd",
    "wof:placetype":"venue"
},
  "geometry": {"coordinates":[117.553451538,-33.6880989075],"type":"Point"}
}