{
  "type": "Feature",
  "properties": {
    "addr:full":"73 Bancroft Rd Pinkenba QLD 4008",
    "addr:housenumber":"73",
    "addr:postcode":"4008",
    "addr:street":"Bancroft Rd",
    "iso:country":"AU",
    "sg:address":"73 Bancroft Rd",
    "sg:city":"Pinkenba",
    "sg:classifiers":[
        {
            "category":"Utilities",
            "subcategory":"Recycling",
            "type":"Services"
        }
    ],
    "sg:phone":"+61 7 3860 5911",
    "sg:postcode":"4008",
    "sg:province":"QLD",
    "wof:name":"Astron Plastics PTY LTD",
    "wof:placetype":"venue"
},
  "geometry": {"coordinates":[153.133346558,-27.3954563141],"type":"Point"}
}