{
  "type": "Feature",
  "properties": {
    "iso:country":"AU",
    "sg:address":"3 Glenwood Ave",
    "sg:city":"Beaumaris",
    "sg:classifiers":[
        {
            "category":"Professional",
            "subcategory":"Accounting & Tax Preparation",
            "type":"Services"
        }
    ],
    "sg:phone":"+61 3 9589 7939",
    "sg:postcode":"3193",
    "sg:province":"VIC",
    "sg:tags":[
        "consultant",
        "taxation"
    ],
    "wof:name":"Bayside Taxation Services",
    "wof:placetype":"venue"
},
  "geometry": {"coordinates":[145.02891540499999,-37.9852485657],"type":"Point"}
}