{
  "type": "Feature",
  "properties": {
    "addr:full":"84 Valley View Drv McLaren Vale SA 5171",
    "addr:housenumber":"84",
    "addr:postcode":"5171",
    "addr:street":"Valley View Drv",
    "iso:country":"AU",
    "sg:address":"84 Valley View Drv",
    "sg:city":"McLaren Vale",
    "sg:classifiers":[
        {
            "category":"Health Services",
            "subcategory":"Nursing And Care Facility",
            "type":"Services"
        }
    ],
    "sg:phone":"+61 8 8329 4900",
    "sg:postcode":"5171",
    "sg:province":"SA",
    "sg:tags":[
        "home"
    ],
    "wof:name":"Colton Court Nursing Home",
    "wof:placetype":"venue"
},
  "geometry": {"coordinates":[138.534255981,-35.2195701599],"type":"Point"}
}