{
  "type": "Feature",
  "properties": {
    "addr:full":"197 Richmond Rd Richmond SA 5033",
    "addr:housenumber":"197",
    "addr:postcode":"5033",
    "addr:street":"Richmond Rd",
    "iso:country":"AU",
    "sg:address":"197 Richmond Rd",
    "sg:city":"Richmond",
    "sg:classifiers":[
        {
            "category":"Health Services",
            "subcategory":"Doctor",
            "type":"Services"
        }
    ],
    "sg:phone":"+61 8 8443 5566",
    "sg:postcode":"5033",
    "sg:province":"SA",
    "sg:tags":[
        "medical",
        "practitioner"
    ],
    "wof:name":"Pearce Donald H Dr",
    "wof:placetype":"venue"
},
  "geometry": {"coordinates":[138.562057495,-34.9424171448],"type":"Point"}
}