{
  "type": "Feature",
  "properties": {
    "addr:full":"Cnr Soldier & Butcher Rds Roleystone WA 6111",
    "addr:postcode":"6111",
    "iso:country":"AU",
    "sg:address":"Cnr Soldier & Butcher Rds",
    "sg:city":"Roleystone",
    "sg:classifiers":[
        {
            "category":"Health Services",
            "subcategory":"Health Practitioner",
            "type":"Services"
        }
    ],
    "sg:phone":"+61 8 9397 5970",
    "sg:postcode":"6111",
    "sg:province":"WA",
    "sg:tags":[
        "psychologist"
    ],
    "wof:name":"Tender Jura",
    "wof:placetype":"venue"
},
  "geometry": {"coordinates":[116.060836792,-32.1302947998],"type":"Point"}
}