{
  "type": "Feature",
  "properties": {
    "addr:full":". 48 Brookland Ave Frankston VIC 3199",
    "addr:housenumber":"48",
    "addr:postcode":"3199",
    "addr:street":"Brookland Ave",
    "iso:country":"AU",
    "sg:address":". 48 Brookland Ave",
    "sg:city":"Frankston",
    "sg:classifiers":[
        {
            "category":"Building & Trades",
            "subcategory":"Construction",
            "type":"Services"
        }
    ],
    "sg:phone":"+61 3 9789 4455",
    "sg:postcode":"3199",
    "sg:province":"VIC",
    "sg:tags":[
        "window",
        "tinting"
    ],
    "wof:name":"Ace Tinting",
    "wof:placetype":"venue"
},
  "geometry": {"coordinates":[145.15737915,-38.1381072998],"type":"Point"}
}