{
  "type": "Feature",
  "properties": {
    "addr:full":"5/ 96 Albert St Brisbane QLD 4000",
    "addr:housenumber":"/ 96",
    "addr:postcode":"4000",
    "addr:street":"Albert St",
    "iso:country":"AU",
    "sg:address":"5/ 96 Albert St",
    "sg:city":"Brisbane",
    "sg:classifiers":[
        {
            "category":"Insurance",
            "subcategory":"Title Insurance",
            "type":"Services"
        }
    ],
    "sg:phone":"+61 7 3323 6666",
    "sg:postcode":"4000",
    "sg:province":"QLD",
    "sg:tags":[
        "searcher"
    ],
    "wof:name":"PCFOX & Associates",
    "wof:placetype":"venue"
},
  "geometry": {"coordinates":[153.027252197,-27.4718589783],"type":"Point"}
}