{
  "type": "Feature",
  "properties": {
    "iso:country":"AU",
    "sg:address":"Unit 4, 50 Atwell St",
    "sg:city":"Landsdale",
    "sg:classifiers":[
        {
            "category":"Autos & Motor Vehicles",
            "subcategory":"Auto Supplies",
            "type":"Retail Goods"
        }
    ],
    "sg:phone":"+61 403 574 222",
    "sg:postcode":"6065",
    "sg:province":"WA",
    "sg:tags":[
        "camper-trailers",
        "caravan",
        "equipment"
    ],
    "wof:name":"Follow Me Campers",
    "wof:placetype":"venue"
},
  "geometry": {"coordinates":[115.84777832,-31.8029747009],"type":"Point"}
}