{
  "type": "Feature",
  "properties": {
    "addr:full":"PO Box 120 Minto NSW 2566",
    "addr:postcode":"2566",
    "iso:country":"AU",
    "sg:address":"PO Box 120",
    "sg:city":"Minto",
    "sg:classifiers":[
        {
            "category":"Building & Trades",
            "subcategory":"Cleaning & Sanitation",
            "type":"Services"
        }
    ],
    "sg:phone":"+61 2 4627 4881",
    "sg:postcode":"2566",
    "sg:province":"NSW",
    "sg:tags":[
        "industrial",
        "commercial",
        "contractor"
    ],
    "wof:name":"Minto Cleaning Services",
    "wof:placetype":"venue"
},
  "geometry": {"coordinates":[150.84469604500001,-34.0311889648],"type":"Point"}
}