{
  "type": "Feature",
  "properties": {
    "iso:country":"AU",
    "sg:address":"29 Corner of Glyde Canning Hwy",
    "sg:city":"East Fremantle",
    "sg:classifiers":[
        {
            "category":"Shopping",
            "subcategory":"Clothing, Apparel, & Fashions",
            "type":"Retail Goods"
        }
    ],
    "sg:phone":"+61 8 9339 8048",
    "sg:postcode":"6158",
    "sg:province":"WA",
    "sg:tags":[
        "accessory"
    ],
    "wof:name":"Vivance Home",
    "wof:placetype":"venue"
},
  "geometry": {"coordinates":[115.76683,-32.040936],"type":"Point"}
}