{
  "type": "Feature",
  "properties": {
    "iso:country":"AU",
    "sg:address":"6 Cuballing East Rd",
    "sg:city":"Cuballing",
    "sg:classifiers":[
        {
            "category":"Building & Trades",
            "subcategory":"Construction",
            "type":"Services"
        }
    ],
    "sg:phone":"+61 8 9883 6116",
    "sg:postcode":"6311",
    "sg:province":"WA",
    "sg:tags":[
        "earth",
        "excavating",
        "moving",
        "contractor"
    ],
    "wof:name":"G S Hobbs Contracting",
    "wof:placetype":"venue"
},
  "geometry": {"coordinates":[117.184913635,-32.8170509338],"type":"Point"}
}