{
  "type": "Feature",
  "properties": {
    "iso:country":"AU",
    "sg:address":"Shop 6A Bull Creek Shopng Cntr",
    "sg:city":"Bull Creek",
    "sg:classifiers":[
        {
            "category":"Shopping",
            "subcategory":"Mobile Phones",
            "type":"Retail Goods"
        }
    ],
    "sg:phone":"+61 8 9492 4206",
    "sg:postcode":"6149",
    "sg:province":"WA",
    "sg:tags":[
        "telephone",
        "accessory"
    ],
    "wof:name":"Vodafone",
    "wof:placetype":"venue"
},
  "geometry": {"coordinates":[115.859512,-32.049484],"type":"Point"}
}