{
  "type": "Feature",
  "properties": {
    "addr:full":"Evans Rd Barmera SA 5345",
    "addr:postcode":"5345",
    "addr:street":"Evans Rd",
    "iso:country":"AU",
    "sg:address":"Evans Rd",
    "sg:city":"Barmera",
    "sg:classifiers":[
        {
            "category":"Building & Trades",
            "subcategory":"Construction",
            "type":"Services"
        }
    ],
    "sg:phone":"+61 8 8588 2918",
    "sg:postcode":"5345",
    "sg:province":"SA",
    "sg:tags":[
        "contractor"
    ],
    "wof:name":"Hamood Building",
    "wof:placetype":"venue"
},
  "geometry": {"coordinates":[140.45677185100001,-34.2644996643],"type":"Point"}
}