{
  "type": "Feature",
  "properties": {
    "addr:full":"765c Hawthorn Rd Brighton East VIC 3187",
    "addr:housenumber":"765c",
    "addr:postcode":"3187",
    "addr:street":"Hawthorn Rd",
    "iso:country":"AU",
    "sg:address":"765c Hawthorn Rd",
    "sg:city":"Brighton East",
    "sg:classifiers":[
        {
            "category":"Building & Trades",
            "subcategory":"Equipment Rental",
            "type":"Services"
        }
    ],
    "sg:phone":"+61 3 9591 0766",
    "sg:postcode":"3187",
    "sg:province":"VIC",
    "sg:tags":[
        "supply",
        "catering"
    ],
    "wof:name":"Curtin (VIC) Pty Ltd",
    "wof:placetype":"venue"
},
  "geometry": {"coordinates":[145.01710510300001,-37.9137496948],"type":"Point"}
}