{
  "type": "Feature",
  "properties": {
    "addr:full":"PO Box 706 Hamilton QLD 4007",
    "addr:postcode":"4007",
    "iso:country":"AU",
    "sg:address":"PO Box 706",
    "sg:city":"Hamilton",
    "sg:classifiers":[
        {
            "category":"Social Services",
            "subcategory":"Retirement Home",
            "type":"Services"
        }
    ],
    "sg:phone":"+61 7 3217 5614",
    "sg:postcode":"4007",
    "sg:province":"QLD",
    "sg:tags":[
        "environmental",
        "consultant",
        "pollution"
    ],
    "wof:name":"Denashore",
    "wof:placetype":"venue"
},
  "geometry": {"coordinates":[153.064606,-27.4375],"type":"Point"}
}