{
  "type": "Feature",
  "properties": {
    "addr:full":"Level 2, 85 Smith St Wollongong NSW 2500",
    "addr:housenumber":"85",
    "addr:postcode":"2500",
    "addr:street":"Smith St",
    "iso:country":"AU",
    "sg:address":"Level 2, 85 Smith St",
    "sg:city":"Wollongong",
    "sg:classifiers":[
        {
            "category":"Real Estate",
            "subcategory":"Real Estate Agent",
            "type":"Services"
        }
    ],
    "sg:phone":"+61 2 4228 0099",
    "sg:postcode":"2500",
    "sg:province":"NSW",
    "wof:name":"Zweep & Connolly Property Consultants",
    "wof:placetype":"venue"
},
  "geometry": {"coordinates":[150.89129600000001,-34.421291],"type":"Point"}
}