{
  "type": "Feature",
  "properties": {
    "addr:full":"PO Box 256 West Ryde Private Boxes NSW 1685",
    "addr:postcode":"1685",
    "addr:street":"West Ryde Private",
    "iso:country":"AU",
    "sg:address":"PO Box 256",
    "sg:city":"West Ryde Private Boxes",
    "sg:classifiers":[
        {
            "category":"Banks & Credit Unions",
            "subcategory":"Investment Brokerage",
            "type":"Services"
        }
    ],
    "sg:phone":"+61 2 9687 9434",
    "sg:postcode":"1685",
    "sg:province":"NSW",
    "wof:name":"Spilsbury Enterprises Pty Ltd",
    "wof:placetype":"venue"
},
  "geometry": {"coordinates":[151.0887146,-33.8077087402],"type":"Point"}
}