{
  "type": "Feature",
  "properties": {
    "iso:country":"AU",
    "sg:address":"Lot 758 Berrigan Drv",
    "sg:city":"South Lake",
    "sg:classifiers":[
        {
            "category":"Food & Beverages",
            "subcategory":"Liquor & Beverages",
            "type":"Retail Goods"
        }
    ],
    "sg:phone":"+61 8 9417 5489",
    "sg:postcode":"6164",
    "sg:province":"WA",
    "sg:tags":[
        "store"
    ],
    "wof:name":"South Lake Liquor Barons",
    "wof:placetype":"venue"
},
  "geometry": {"coordinates":[115.84071400000001,-32.110905],"type":"Point"}
}