{
  "type": "Feature",
  "properties": {
    "addr:full":"29 Beringarra Ave Malaga WA 6090",
    "addr:housenumber":"29",
    "addr:postcode":"6090",
    "addr:street":"Beringarra Ave",
    "iso:country":"AU",
    "sg:address":"29 Beringarra Ave",
    "sg:city":"Malaga",
    "sg:classifiers":[
        {
            "category":"Manufacturing",
            "subcategory":"Retail Goods",
            "type":"Manufacturing & Wholesale Goods"
        }
    ],
    "sg:phone":"+61 1800 721 878",
    "sg:postcode":"6090",
    "sg:province":"WA",
    "sg:tags":[
        "merchant",
        "pump",
        "mfrs"
    ],
    "wof:name":"Power Proving Services",
    "wof:placetype":"venue"
},
  "geometry": {"coordinates":[115.896682739,-31.8635864258],"type":"Point"}
}