{
  "type": "Feature",
  "properties": {
    "addr:full":"222 Carp St Bega NSW 2550",
    "addr:housenumber":"222",
    "addr:postcode":"2550",
    "addr:street":"Carp St",
    "iso:country":"AU",
    "sg:address":"222 Carp St",
    "sg:city":"Bega",
    "sg:classifiers":[
        {
            "category":"Shopping",
            "subcategory":"Jewelry",
            "type":"Retail Goods"
        }
    ],
    "sg:phone":"+61 2 6492 1564",
    "sg:postcode":"2550",
    "sg:province":"NSW",
    "sg:tags":[
        "jeweller"
    ],
    "wof:name":"Jewellery For You",
    "wof:placetype":"venue"
},
  "geometry": {"coordinates":[149.84379577600001,-36.6742935181],"type":"Point"}
}