{
  "type": "Feature",
  "properties": {
    "iso:country":"AU",
    "sg:address":"7 Callistemon Rd",
    "sg:city":"Warabrook",
    "sg:classifiers":[
        {
            "category":"Military Area",
            "subcategory":"Air Force Base",
            "type":"Public Place"
        }
    ],
    "sg:phone":"+61 2 4967 6770",
    "sg:postcode":"2304",
    "sg:province":"NSW",
    "sg:tags":[
        "box",
        "case",
        "wood"
    ],
    "wof:name":"Hunter Special Woodwork",
    "wof:placetype":"venue"
},
  "geometry": {"coordinates":[151.71780395499999,-32.8891487122],"type":"Point"}
}