{
  "type": "Feature",
  "properties": {
    "addr:full":"58 Pacific Hwy Long Jetty NSW 2261",
    "addr:housenumber":"58",
    "addr:postcode":"2261",
    "addr:street":"Pacific Hwy Long",
    "iso:country":"AU",
    "sg:address":"58 Pacific Hwy",
    "sg:city":"Long Jetty",
    "sg:classifiers":[
        {
            "category":"Retail",
            "subcategory":"Auto Repair",
            "type":"Services"
        }
    ],
    "sg:phone":"+61 2 4332 1601",
    "sg:postcode":"2261",
    "sg:province":"NSW",
    "sg:tags":[
        "repairer",
        "motor",
        "engineer"
    ],
    "wof:name":"Repco Authorised Service",
    "wof:placetype":"venue"
},
  "geometry": {"coordinates":[151.49087499999999,-33.358929],"type":"Point"}
}