{
  "type": "Feature",
  "properties": {
    "addr:full":"Shop 5, 92 Alma St Maryborough VIC 3465",
    "addr:housenumber":"shop;92",
    "addr:postcode":"3465",
    "addr:street":"Alma St",
    "iso:country":"AU",
    "sg:address":"Shop 5, 92 Alma St",
    "sg:city":"Maryborough",
    "sg:classifiers":[
        {
            "category":"Real Estate",
            "subcategory":"Real Estate Agent",
            "type":"Services"
        }
    ],
    "sg:phone":"+61 3 5461 3588",
    "sg:postcode":"3465",
    "sg:province":"VIC",
    "wof:name":"Central Goldfields Real Estate",
    "wof:placetype":"venue"
},
  "geometry": {"coordinates":[143.74020385700001,-37.0454521179],"type":"Point"}
}