{
  "type": "Feature",
  "properties": {
    "addr:full":"Shop 3 Woodrising Shopping Centre Booragul NSW 2284",
    "addr:housenumber":"shop 3",
    "addr:postcode":"2284",
    "addr:street":"Woodrising",
    "iso:country":"AU",
    "sg:address":"Shop 3 Woodrising Shopping Centre",
    "sg:city":"Booragul",
    "sg:classifiers":[
        {
            "category":"Food & Beverages",
            "subcategory":"Bakery",
            "type":"Retail Goods"
        }
    ],
    "sg:phone":"+61 2 4950 4694",
    "sg:postcode":"2284",
    "sg:province":"NSW",
    "sg:tags":[
        "baker"
    ],
    "wof:name":"Woodrising Bakery",
    "wof:placetype":"venue"
},
  "geometry": {"coordinates":[151.60638427699999,-32.9744110107],"type":"Point"}
}