{
  "type": "Feature",
  "properties": {
    "addr:full":"24 Boronia St Granville NSW 2142",
    "addr:housenumber":"24",
    "addr:postcode":"2142",
    "addr:street":"Boronia St",
    "iso:country":"AU",
    "sg:address":"24 Boronia St",
    "sg:city":"Granville",
    "sg:classifiers":[
        {
            "category":"Government",
            "subcategory":"Fire Station",
            "type":"Public Place"
        }
    ],
    "sg:phone":"+61 2 9885 1224",
    "sg:postcode":"2142",
    "sg:province":"NSW",
    "sg:tags":[
        "equipment",
        "protection",
        "consultant"
    ],
    "wof:name":"National Fire Extinguisher Sales & Service",
    "wof:placetype":"venue"
},
  "geometry": {"coordinates":[151.014434814,-33.8493309021],"type":"Point"}
}