{
  "type": "Feature",
  "properties": {
    "addr:full":"2 Pearl Crt Berrimah NT 0828",
    "addr:housenumber":"2",
    "addr:postcode":"nt 0828",
    "addr:street":"Pearl Crt",
    "iso:country":"AU",
    "sg:address":"2 Pearl Crt",
    "sg:city":"Berrimah",
    "sg:classifiers":[
        {
            "category":"Utilities",
            "subcategory":"Recycling",
            "type":"Services"
        }
    ],
    "sg:phone":"+61 8 8947 3915",
    "sg:postcode":"0828",
    "sg:province":"NT",
    "wof:name":"Smorgon Steel Recycling",
    "wof:placetype":"venue"
},
  "geometry": {"coordinates":[130.92738342300001,-12.4772386551],"type":"Point"}
}