{
  "type": "Feature",
  "properties": {
    "iso:country":"AU",
    "sg:address":"57 Trade St",
    "sg:city":"Lytton",
    "sg:classifiers":[
        {
            "category":"Military Area",
            "subcategory":"Coast Guard Base",
            "type":"Public Place"
        }
    ],
    "sg:phone":"+61 7 3393 6555",
    "sg:postcode":"4178",
    "sg:province":"QLD",
    "sg:tags":[
        "worker",
        "metal",
        "machinery",
        "sheet"
    ],
    "wof:name":"Advanced Robotic Technology Pty Ltd",
    "wof:placetype":"venue"
},
  "geometry": {"coordinates":[153.148727417,-27.4270191193],"type":"Point"}
}