{
  "type": "Feature",
  "properties": {
    "addr:full":"10 Gemalla Rd Margate TAS 7054",
    "addr:housenumber":"10",
    "addr:postcode":"7054",
    "addr:street":"Gemalla Rd",
    "iso:country":"AU",
    "sg:address":"10 Gemalla Rd",
    "sg:city":"Margate",
    "sg:classifiers":[
        {
            "category":"Autos & Motor Vehicles",
            "subcategory":"Motorcycle Sales",
            "type":"Retail Goods"
        }
    ],
    "sg:phone":"+61 3 6267 1456",
    "sg:postcode":"7054",
    "sg:province":"TAS",
    "sg:tags":[
        "outboard"
    ],
    "wof:name":"Channel Marine",
    "wof:placetype":"venue"
},
  "geometry": {"coordinates":[147.26809700000001,-43.036999],"type":"Point"}
}