{
  "type": "Feature",
  "properties": {
    "addr:full":"47 Grantham St Brunswick West VIC 3055",
    "addr:housenumber":"47",
    "addr:postcode":"3055",
    "addr:street":"Grantham St",
    "iso:country":"AU",
    "sg:address":"47 Grantham St",
    "sg:city":"Brunswick West",
    "sg:classifiers":[
        {
            "category":"Education",
            "subcategory":"Vocational School",
            "type":"Public Place"
        }
    ],
    "sg:phone":"+61 3 9380 5337",
    "sg:postcode":"3055",
    "sg:province":"VIC",
    "sg:tags":[
        "tafe",
        "college",
        "training"
    ],
    "wof:name":"Melbourne School Of Knowledge Management Pty Ltd",
    "wof:placetype":"venue"
},
  "geometry": {"coordinates":[144.94915771500001,-37.7726402283],"type":"Point"}
}