{
  "type": "Feature",
  "properties": {
    "addr:full":"212 Berkeley St Carlton VIC 3053",
    "addr:housenumber":"212",
    "addr:postcode":"3053",
    "addr:street":"Berkeley St",
    "iso:country":"AU",
    "sg:address":"212 Berkeley St",
    "sg:city":"Carlton",
    "sg:classifiers":[
        {
            "category":"Wholesale",
            "subcategory":"Electrical",
            "type":"Manufacturing & Wholesale Goods"
        }
    ],
    "sg:phone":"+61 3 9347 4588",
    "sg:postcode":"3053",
    "sg:province":"VIC",
    "sg:tags":[
        "control",
        "equipment",
        "switch"
    ],
    "wof:name":"Elsafe Australia Pty Ltd",
    "wof:placetype":"venue"
},
  "geometry": {"coordinates":[144.958862305,-37.8005523682],"type":"Point"}
}