{
  "type": "Feature",
  "properties": {
    "iso:country":"AU",
    "sg:address":"36 Hotham Pde",
    "sg:city":"Artarmon",
    "sg:classifiers":[
        {
            "category":"Building & Trades",
            "subcategory":"Construction",
            "type":"Services"
        }
    ],
    "sg:phone":"+61 13 88 31",
    "sg:postcode":"1570",
    "sg:province":"NSW",
    "sg:tags":[
        "window",
        "tinting"
    ],
    "wof:name":"SunGard",
    "wof:placetype":"venue"
},
  "geometry": {"coordinates":[151.182846,-33.814384],"type":"Point"}
}