{
  "type": "Feature",
  "properties": {
    "iso:country":"AU",
    "sg:address":"26 Gertrude St",
    "sg:city":"Fitzroy",
    "sg:classifiers":[
        {
            "category":"Communications",
            "type":"Services"
        }
    ],
    "sg:phone":"+61 3 9419 6364",
    "sg:postcode":"3065",
    "sg:province":"VIC",
    "sg:tags":[
        "public",
        "system",
        "address"
    ],
    "wof:name":"ARC Sound Reinforcement Pty Ltd",
    "wof:placetype":"venue"
},
  "geometry": {"coordinates":[144.97503662099999,-37.8056297302],"type":"Point"}
}