{
  "type": "Feature",
  "properties": {
    "addr:full":"18b Excelsior Pde Marrickville NSW 2204",
    "addr:housenumber":"18b",
    "addr:postcode":"2204",
    "addr:street":"Excelsior Pde",
    "iso:country":"AU",
    "sg:address":"18b Excelsior Pde",
    "sg:city":"Marrickville",
    "sg:classifiers":[
        {
            "category":"Professional",
            "subcategory":"Art Services",
            "type":"Services"
        }
    ],
    "sg:phone":"+61 2 9591 2662",
    "sg:postcode":"2204",
    "sg:province":"NSW",
    "sg:tags":[
        "graphic",
        "designer"
    ],
    "wof:name":"JFK Studio Productions",
    "wof:placetype":"venue"
},
  "geometry": {"coordinates":[151.152176,-33.918507],"type":"Point"}
}