{
  "type": "Feature",
  "properties": {
    "addr:full":"1043 Waugh Rd North Albury NSW 2640",
    "addr:housenumber":"1043",
    "addr:postcode":"2640",
    "addr:street":"Waugh Rd",
    "iso:country":"AU",
    "sg:address":"1043 Waugh Rd",
    "sg:city":"North Albury",
    "sg:classifiers":[
        {
            "category":"Home & Garden",
            "subcategory":"Furniture",
            "type":"Retail Goods"
        }
    ],
    "sg:phone":"+61 2 6040 3239",
    "sg:postcode":"2640",
    "sg:province":"NSW",
    "sg:tags":[
        "repair",
        "restoration"
    ],
    "wof:name":"Twin Cities Upholstery Centre",
    "wof:placetype":"venue"
},
  "geometry": {"coordinates":[146.92933654800001,-36.0550880432],"type":"Point"}
}