{
  "type": "Feature",
  "properties": {
    "addr:full":"426 Riley St Surry Hills NSW 2010",
    "addr:housenumber":"426",
    "addr:postcode":"2010",
    "addr:street":"Riley St",
    "iso:country":"AU",
    "sg:address":"426 Riley St",
    "sg:city":"Surry Hills",
    "sg:classifiers":[
        {
            "category":"Professional",
            "subcategory":"Employment Agencies",
            "type":"Services"
        }
    ],
    "sg:phone":"+61 2 9318 2188",
    "sg:postcode":"2010",
    "sg:province":"NSW",
    "sg:tags":[
        "provider",
        "internet"
    ],
    "wof:name":"Bondi Internet Services",
    "wof:placetype":"venue"
},
  "geometry": {"coordinates":[151.21226501500001,-33.8876495361],"type":"Point"}
}