{
  "type": "Feature",
  "properties": {
    "addr:full":"Unit 2a 32 Prindiville Drv Wangara WA 6065",
    "addr:housenumber":"unit 2a 32",
    "addr:postcode":"6065",
    "addr:street":"Prindiville Drv",
    "iso:country":"AU",
    "sg:address":"Unit 2a 32 Prindiville Drv",
    "sg:city":"Wangara",
    "sg:classifiers":[
        {
            "category":"Government",
            "subcategory":"Post Office",
            "type":"Public Place"
        }
    ],
    "sg:phone":"+61 8 9409 5333",
    "sg:postcode":"6065",
    "sg:province":"WA",
    "sg:tags":[
        "yoga"
    ],
    "wof:name":"Yoga Teachers Association of Western Australia",
    "wof:placetype":"venue"
},
  "geometry": {"coordinates":[115.820419312,-31.7911071777],"type":"Point"}
}