{
  "type": "Feature",
  "properties": {
    "iso:country":"AU",
    "sg:address":"Unit 5, 192A Kingsgrove Rd",
    "sg:city":"Kingsgrove",
    "sg:classifiers":[
        {
            "category":"Professional",
            "subcategory":"Testing Lab",
            "type":"Services"
        }
    ],
    "sg:phone":"+61 2 9150 0944",
    "sg:postcode":"2208",
    "sg:province":"NSW",
    "sg:tags":[
        "inspection"
    ],
    "wof:name":"New Dawn Digitizing",
    "wof:placetype":"venue"
},
  "geometry": {"coordinates":[151.10032699999999,-33.936356],"type":"Point"}
}