{
  "type": "Feature",
  "properties": {
    "addr:full":"Shop 139, Bay City Plaza Geelong VIC 3220",
    "addr:housenumber":"139",
    "addr:postcode":"3220",
    "addr:street":"Bay",
    "iso:country":"AU",
    "sg:address":"Shop 139, Bay City Plaza",
    "sg:city":"Geelong",
    "sg:classifiers":[
        {
            "category":"Banks & Credit Unions",
            "subcategory":"Financial Services",
            "type":"Services"
        }
    ],
    "sg:phone":"+61 1800 630 705",
    "sg:postcode":"3220",
    "sg:province":"VIC",
    "sg:tags":[
        "planning"
    ],
    "wof:name":"St Andrew's Financial Services",
    "wof:placetype":"venue"
},
  "geometry": {"coordinates":[144.35292100000001,-38.121243],"type":"Point"}
}