{
  "type": "Feature",
  "properties": {
    "addr:full":"474 Wellington St Clifton Hill VIC 3068",
    "addr:housenumber":"474",
    "addr:postcode":"3068",
    "addr:street":"Wellington St",
    "iso:country":"AU",
    "sg:address":"474 Wellington St",
    "sg:city":"Clifton Hill",
    "sg:classifiers":[
        {
            "category":"Building & Trades",
            "subcategory":"Plumbing",
            "type":"Services"
        }
    ],
    "sg:phone":"+61 419 307 274",
    "sg:postcode":"3068",
    "sg:province":"VIC",
    "sg:tags":[
        "plumber",
        "gasfitters"
    ],
    "wof:name":"General Asset Maintenance",
    "wof:placetype":"venue"
},
  "geometry": {"coordinates":[144.989013672,-37.790309906],"type":"Point"}
}