{
  "type": "Feature",
  "properties": {
    "addr:full":"488 Scarborough Beach Rd Osborne Park WA 6017",
    "addr:housenumber":"488",
    "addr:postcode":"6017",
    "addr:street":"Scarborough Beach Rd",
    "iso:country":"AU",
    "sg:address":"488 Scarborough Beach Rd",
    "sg:city":"Osborne Park",
    "sg:classifiers":[
        {
            "category":"Health Services",
            "subcategory":"Dentist",
            "type":"Services"
        }
    ],
    "sg:phone":"+61 8 9244 1382",
    "sg:postcode":"6017",
    "sg:province":"WA",
    "wof:name":"Tran Chinh",
    "wof:placetype":"venue"
},
  "geometry": {"coordinates":[115.80536651600001,-31.9046401978],"type":"Point"}
}