{
  "type": "Feature",
  "properties": {
    "addr:full":"81 Reibey St Ulverstone TAS 7315",
    "addr:housenumber":"81",
    "addr:postcode":"7315",
    "addr:street":"Reibey St",
    "iso:country":"AU",
    "sg:address":"81 Reibey St",
    "sg:city":"Ulverstone",
    "sg:classifiers":[
        {
            "category":"Retail",
            "subcategory":"Repair Shop",
            "type":"Services"
        }
    ],
    "sg:phone":"+61 3 6425 2753",
    "sg:postcode":"7315",
    "sg:province":"TAS",
    "sg:tags":[
        "mending",
        "clothing",
        "alteration"
    ],
    "wof:name":"Kings Dry Cleaners",
    "wof:placetype":"venue"
},
  "geometry": {"coordinates":[146.173736572,-41.1574287415],"type":"Point"}
}