{
  "type": "Feature",
  "properties": {
    "iso:country":"AU",
    "sg:address":"Cnr Omar & Keogh Sts",
    "sg:city":"Ipswich West",
    "sg:classifiers":[
        {
            "category":"Education",
            "subcategory":"School",
            "type":"Public Place"
        }
    ],
    "sg:phone":"+61 7 3813 5222",
    "sg:postcode":"4305",
    "sg:province":"QLD",
    "sg:tags":[
        "state",
        "except",
        "nsw"
    ],
    "wof:name":"Ipswich West Primary",
    "wof:placetype":"venue"
},
  "geometry": {"coordinates":[152.75254821799999,-27.6171703339],"type":"Point"}
}