{
  "type": "Feature",
  "properties": {
    "iso:country":"AU",
    "sg:address":"123 Military Rd",
    "sg:city":"Guildford",
    "sg:classifiers":[
        {
            "category":"Food & Beverages",
            "subcategory":"Groceries & Convenience Stores",
            "type":"Retail Goods"
        }
    ],
    "sg:phone":"+61 2 9892 3640",
    "sg:postcode":"2161",
    "sg:province":"NSW",
    "wof:name":"All African Food",
    "wof:placetype":"venue"
},
  "geometry": {"coordinates":[150.98434448200001,-33.8538017273],"type":"Point"}
}