{
  "type": "Feature",
  "properties": {
    "iso:country":"AU",
    "sg:address":"19 Carnarvon St",
    "sg:city":"Broome",
    "sg:classifiers":[
        {
            "category":"Food & Beverages",
            "subcategory":"Groceries & Convenience Stores",
            "type":"Retail Goods"
        }
    ],
    "sg:phone":"+61 8 9192 1267",
    "sg:postcode":"6725",
    "sg:province":"WA",
    "wof:name":"Yuen Wing Store",
    "wof:placetype":"venue"
},
  "geometry": {"coordinates":[122.243736267,-17.9534893036],"type":"Point"}
}