{
  "type": "Feature",
  "properties": {
    "iso:country":"AU",
    "sg:address":"Suite 1A Lvl 2/ 73 Church St",
    "sg:city":"Wollongong",
    "sg:classifiers":[
        {
            "category":"Banks & Credit Unions",
            "subcategory":"Financial Services",
            "type":"Services"
        }
    ],
    "sg:phone":"+61 2 4229 6137",
    "sg:postcode":"2500",
    "sg:province":"NSW",
    "sg:tags":[
        "financier"
    ],
    "wof:name":"City Finance",
    "wof:placetype":"venue"
},
  "geometry": {"coordinates":[150.895996,-34.423615],"type":"Point"}
}