{
  "type": "Feature",
  "properties": {
    "addr:full":"28 Marina Drv Melton VIC 3337",
    "addr:housenumber":"28",
    "addr:postcode":"3337",
    "addr:street":"Marina Drv",
    "iso:country":"AU",
    "sg:address":"28 Marina Drv",
    "sg:city":"Melton",
    "sg:classifiers":[
        {
            "category":"Retail",
            "subcategory":"Storage",
            "type":"Services"
        }
    ],
    "sg:phone":"+61 425 881 105",
    "sg:postcode":"3337",
    "sg:province":"VIC",
    "sg:tags":[
        "removal",
        "furniture"
    ],
    "wof:name":"DTS Removals",
    "wof:placetype":"venue"
},
  "geometry": {"coordinates":[144.582336,-37.678513],"type":"Point"}
}