{
  "type": "Feature",
  "properties": {
    "iso:country":"AU",
    "sg:address":"Victoria Hwy",
    "sg:city":"Timber Creek",
    "sg:classifiers":[
        {
            "category":"Travel",
            "subcategory":"Hotels & Motels",
            "type":"Entertainment"
        }
    ],
    "sg:phone":"+61 8 8975 0722",
    "sg:postcode":"0852",
    "sg:province":"NT",
    "wof:name":"Timber Creek Hotel",
    "wof:placetype":"venue"
},
  "geometry": {"coordinates":[130.480133,-15.661616],"type":"Point"}
}