{
  "type": "Feature",
  "properties": {
    "iso:country":"AU",
    "sg:address":"Quambi, Springs Rd",
    "sg:city":"Mt Barker",
    "sg:classifiers":[
        {
            "category":"Health Services",
            "subcategory":"Health Practitioner",
            "type":"Services"
        }
    ],
    "sg:phone":"+61 8 8391 5414",
    "sg:postcode":"5251",
    "sg:province":"SA",
    "sg:tags":[
        "bowen",
        "therapy"
    ],
    "wof:name":"Tamar Winderbaum",
    "wof:placetype":"venue"
},
  "geometry": {"coordinates":[138.867675781,-35.0650405884],"type":"Point"}
}