{
  "type": "Feature",
  "properties": {
    "addr:full":"Suite 50,Level 5, 320 Adelaide Street Brisbane QLD 4000",
    "addr:housenumber":"320",
    "addr:postcode":"4000",
    "addr:street":"Adelaide Street",
    "iso:country":"AU",
    "sg:address":"Suite 50,Level 5, 320",
    "sg:city":"Adelaide Street Brisbane",
    "sg:classifiers":[
        {
            "category":"Shopping",
            "subcategory":"Mobile Phones",
            "type":"Retail Goods"
        }
    ],
    "sg:phone":"+61 7 3010 9449",
    "sg:postcode":"4000",
    "sg:province":"QLD",
    "sg:tags":[
        "telephone",
        "accessory"
    ],
    "wof:name":"Allphones",
    "wof:placetype":"venue"
},
  "geometry": {"coordinates":[153.02923584000001,-27.4649868011],"type":"Point"}
}