{
  "type": "Feature",
  "properties": {
    "iso:country":"AU",
    "sg:address":"20 Hines Rd",
    "sg:city":"O'Connor",
    "sg:classifiers":[
        {
            "category":"Wholesale",
            "subcategory":"Home Furnishings",
            "type":"Manufacturing & Wholesale Goods"
        }
    ],
    "sg:phone":"+61 8 9331 9800",
    "sg:postcode":"6163",
    "sg:province":"WA",
    "sg:tags":[
        "wholesaler",
        "mfrs",
        "manchester"
    ],
    "wof:name":"Bambury",
    "wof:placetype":"venue"
},
  "geometry": {"coordinates":[115.784218,-32.059547],"type":"Point"}
}