{
  "type": "Feature",
  "properties": {
    "iso:country":"AU",
    "sg:address":"Shop 35, Westfield Shoppingtown, Tea Tree Plaza, 9",
    "sg:city":"Modbury",
    "sg:classifiers":[
        {
            "category":"Shopping",
            "subcategory":"Computers & Home Electronics",
            "type":"Retail Goods"
        }
    ],
    "sg:phone":"+61 8 8264 1214",
    "sg:postcode":"5092",
    "sg:province":"SA",
    "sg:tags":[
        "equipment",
        "part",
        "electronic"
    ],
    "wof:name":"Tandy",
    "wof:placetype":"venue"
},
  "geometry": {"coordinates":[138.68934631400001,-34.8309783936],"type":"Point"}
}