{
  "type": "Feature",
  "properties": {
    "addr:full":"100 Williams St Kings Cross NSW 2011",
    "addr:housenumber":"100",
    "addr:postcode":"2011",
    "addr:street":"Williams St",
    "iso:country":"AU",
    "sg:address":"100 Williams St",
    "sg:city":"Kings Cross",
    "sg:classifiers":[
        {
            "category":"Retail",
            "subcategory":"Auto Rental",
            "type":"Services"
        }
    ],
    "sg:phone":"+61 2 8255 9050",
    "sg:postcode":"2011",
    "sg:province":"NSW",
    "sg:tags":[
        "car",
        "hire",
        "minibus"
    ],
    "wof:name":"Europcar",
    "wof:placetype":"venue"
},
  "geometry": {"coordinates":[151.222045898,-33.8754234314],"type":"Point"}
}