{
  "type": "Feature",
  "properties": {
    "addr:full":"85 Crockford St Northgate QLD 4013",
    "addr:housenumber":"85",
    "addr:postcode":"4013",
    "addr:street":"Crockford St",
    "iso:country":"AU",
    "sg:address":"85 Crockford St",
    "sg:city":"Northgate",
    "sg:classifiers":[
        {
            "category":"Home & Garden",
            "subcategory":"Carpets & Floor Coverings",
            "type":"Retail Goods"
        }
    ],
    "sg:phone":"+61 7 3266 7477",
    "sg:postcode":"4013",
    "sg:province":"QLD",
    "wof:name":"Brady Tile Imports Pty Ltd",
    "wof:placetype":"venue"
},
  "geometry": {"coordinates":[153.077667236,-27.3867645264],"type":"Point"}
}