{
  "type": "Feature",
  "properties": {
    "addr:full":"1 / 109 Hunter St Hornsby NSW 2077",
    "addr:housenumber":"/ 109",
    "addr:postcode":"2077",
    "addr:street":"Hunter St",
    "iso:country":"AU",
    "sg:address":"1 / 109 Hunter St",
    "sg:city":"Hornsby",
    "sg:classifiers":[
        {
            "category":"Real Estate",
            "subcategory":"Surveying",
            "type":"Services"
        }
    ],
    "sg:phone":"+61 2 9477 3999",
    "sg:postcode":"2077",
    "sg:province":"NSW",
    "sg:tags":[
        "surveyor",
        "land"
    ],
    "wof:name":"McKittrick Fry & O'Hagan",
    "wof:placetype":"venue"
},
  "geometry": {"coordinates":[151.101486206,-33.6985626221],"type":"Point"}
}