{
  "type": "Feature",
  "properties": {
    "iso:country":"AU",
    "sg:address":"PO Box 624",
    "sg:city":"Toorak",
    "sg:classifiers":[
        {
            "category":"Building & Trades",
            "subcategory":"Landscaping Services",
            "type":"Services"
        }
    ],
    "sg:phone":"+61 438 762 269",
    "sg:postcode":"3142",
    "sg:province":"VIC",
    "sg:tags":[
        "gardener"
    ],
    "wof:name":"Botanical Garden Care Melbourne",
    "wof:placetype":"venue"
},
  "geometry": {"coordinates":[145.017944336,-37.8410415649],"type":"Point"}
}