{
  "type": "Feature",
  "properties": {
    "addr:full":"Cnr Harrison & Thomas Sts Cardiff NSW 2285",
    "addr:postcode":"2285",
    "addr:street":"Cnr Harrison",
    "iso:country":"AU",
    "sg:address":"Cnr Harrison & Thomas Sts",
    "sg:city":"Cardiff",
    "sg:classifiers":[
        {
            "category":"Health Services",
            "subcategory":"Doctor",
            "type":"Services"
        }
    ],
    "sg:phone":"+61 2 4954 0855",
    "sg:postcode":"2285",
    "sg:province":"NSW",
    "sg:tags":[
        "medical",
        "practitioner"
    ],
    "wof:name":"Hayes G.H. & Noble G.K.",
    "wof:placetype":"venue"
},
  "geometry": {"coordinates":[151.686645508,-32.9375076294],"type":"Point"}
}