{
  "type": "Feature",
  "properties": {
    "addr:full":"34 Prospero St Murwillumbah NSW 2484",
    "addr:housenumber":"34",
    "addr:postcode":"2484",
    "addr:street":"Prospero St",
    "iso:country":"AU",
    "sg:address":"34 Prospero St",
    "sg:city":"Murwillumbah",
    "sg:classifiers":[
        {
            "category":"Autos & Motor Vehicles",
            "subcategory":"Automobile Sales",
            "type":"Retail Goods"
        }
    ],
    "sg:phone":"+61 2 6672 1666",
    "sg:postcode":"2484",
    "sg:province":"NSW",
    "sg:tags":[
        "car",
        "new"
    ],
    "wof:name":"Hayes Toyota",
    "wof:placetype":"venue"
},
  "geometry": {"coordinates":[153.401245117,-28.3293418884],"type":"Point"}
}