{
  "type": "Feature",
  "properties": {
    "iso:country":"AU",
    "sg:address":"51 Belemba Ave",
    "sg:city":"Roselands",
    "sg:classifiers":[
        {
            "category":"Professional",
            "subcategory":"Accounting & Tax Preparation",
            "type":"Services"
        }
    ],
    "sg:phone":"+61 2 9759 2125",
    "sg:postcode":"2196",
    "sg:province":"NSW",
    "sg:tags":[
        "accountant",
        "auditor"
    ],
    "wof:name":"Ridani Violetta & Co",
    "wof:placetype":"venue"
},
  "geometry": {"coordinates":[151.078918,-33.931515],"type":"Point"}
}