{
  "type": "Feature",
  "properties": {
    "iso:country":"AU",
    "sg:address":"147 Doncaster Rd",
    "sg:city":"Balwyn North",
    "sg:classifiers":[
        {
            "category":"Building & Trades",
            "subcategory":"Landscaping Services",
            "type":"Services"
        }
    ],
    "sg:phone":"+61 412 005 100",
    "sg:postcode":"3104",
    "sg:province":"VIC",
    "sg:tags":[
        "designer",
        "landscape",
        "contractor"
    ],
    "wof:name":"Kabbage Patch Horticultural Services",
    "wof:placetype":"venue"
},
  "geometry": {"coordinates":[145.085037231,-37.7946434021],"type":"Point"}
}