{
  "type": "Feature",
  "properties": {
    "iso:country":"AU",
    "sg:address":"25 Weemala St",
    "sg:city":"Budgewoi",
    "sg:classifiers":[
        {
            "category":"Shopping",
            "subcategory":"Discount & Variety Stores",
            "type":"Retail Goods"
        }
    ],
    "sg:phone":"+61 412 822 345",
    "sg:postcode":"2262",
    "sg:province":"NSW",
    "sg:tags":[
        "register",
        "cash"
    ],
    "wof:name":"Coastal Retail Systems",
    "wof:placetype":"venue"
},
  "geometry": {"coordinates":[151.565384,-33.23571],"type":"Point"}
}