{
  "type": "Feature",
  "properties": {
    "addr:full":"Shop 1, 193 Maitland Rd Mayfield NSW 2304",
    "addr:housenumber":"shop 1 193",
    "addr:postcode":"2304",
    "addr:street":"Maitland Rd",
    "iso:country":"AU",
    "sg:address":"Shop 1, 193 Maitland Rd",
    "sg:city":"Mayfield",
    "sg:classifiers":[
        {
            "category":"Professional",
            "subcategory":"Detective & Security Services",
            "type":"Services"
        }
    ],
    "sg:phone":"+61 2 4967 5870",
    "sg:postcode":"2304",
    "sg:province":"NSW",
    "sg:tags":[
        "equipment",
        "window",
        "doors"
    ],
    "wof:name":"Wynstan Blinds & Doors",
    "wof:placetype":"venue"
},
  "geometry": {"coordinates":[151.73631286599999,-32.8969802856],"type":"Point"}
}