{
  "type": "Feature",
  "properties": {
    "addr:full":"Kilcoy Beerwah Rd Stanmore QLD 4514",
    "addr:postcode":"4514",
    "addr:street":"Beerwah Rd",
    "iso:country":"AU",
    "sg:address":"Kilcoy Beerwah Rd",
    "sg:city":"Stanmore",
    "sg:classifiers":[
        {
            "category":"Building & Trades",
            "subcategory":"Construction",
            "type":"Services"
        }
    ],
    "sg:phone":"+61 439 880 307",
    "sg:postcode":"4514",
    "sg:province":"QLD",
    "sg:tags":[
        "polishing",
        "sanding",
        "floor"
    ],
    "wof:name":"In 2 Floors Floor Stripping",
    "wof:placetype":"venue"
},
  "geometry": {"coordinates":[152.77722199999999,-26.904692],"type":"Point"}
}