{
  "type": "Feature",
  "properties": {
    "iso:country":"AU",
    "sg:address":"Level 18, 123 Eagle St",
    "sg:city":"Brisbane",
    "sg:classifiers":[
        {
            "category":"Professional",
            "subcategory":"Detective & Security Services",
            "type":"Services"
        }
    ],
    "sg:phone":"+61 1300 555 320",
    "sg:postcode":"4000",
    "sg:province":"QLD",
    "sg:tags":[
        "guard",
        "patrol"
    ],
    "wof:name":"Wilson Services",
    "wof:placetype":"venue"
},
  "geometry": {"coordinates":[153.03010559099999,-27.4673233032],"type":"Point"}
}