{
  "type": "Feature",
  "properties": {
    "iso:country":"AU",
    "sg:address":"25 Whittaker Ave",
    "sg:city":"Laverton North",
    "sg:classifiers":[
        {
            "category":"Education",
            "subcategory":"Kindergarten",
            "type":"Public Place"
        }
    ],
    "sg:phone":"+61 3 9369 2815",
    "sg:postcode":"3026",
    "sg:province":"VIC",
    "sg:tags":[
        "pre-schools"
    ],
    "wof:name":"Laverton North Kindergarten Inc.",
    "wof:placetype":"venue"
},
  "geometry": {"coordinates":[144.773499,-37.851192],"type":"Point"}
}