{
  "type": "Feature",
  "properties": {
    "iso:country":"AU",
    "sg:address":"42 Buttaba Ave",
    "sg:city":"Belmont North",
    "sg:classifiers":[
        {
            "category":"Professional",
            "subcategory":"Computer Services",
            "type":"Services"
        }
    ],
    "sg:phone":"+61 2 4945 3758",
    "sg:postcode":"2280",
    "sg:province":"NSW",
    "sg:tags":[
        "equipment",
        "networking",
        "installation"
    ],
    "wof:name":"Mister Computer Studios",
    "wof:placetype":"venue"
},
  "geometry": {"coordinates":[151.67573547399999,-33.0206756592],"type":"Point"}
}