{
  "type": "Feature",
  "properties": {
    "addr:full":"104 Victor Crs Narre Warren VIC 3805",
    "addr:housenumber":"104",
    "addr:postcode":"3805",
    "addr:street":"Victor Crs",
    "iso:country":"AU",
    "sg:address":"104 Victor Crs",
    "sg:city":"Narre Warren",
    "sg:classifiers":[
        {
            "category":"Wholesale",
            "subcategory":"Painting Supplies",
            "type":"Manufacturing & Wholesale Goods"
        }
    ],
    "sg:phone":"+61 3 8790 1872",
    "sg:postcode":"3805",
    "sg:province":"VIC",
    "sg:tags":[
        "wholesaler",
        "paint",
        "mfrs"
    ],
    "wof:name":"Solver Paints",
    "wof:placetype":"venue"
},
  "geometry": {"coordinates":[145.305588,-38.02042],"type":"Point"}
}