{
  "type": "Feature",
  "properties": {
    "iso:country":"AU",
    "sg:address":"9 Keith Pl",
    "sg:city":"Hamlyn Heights",
    "sg:classifiers":[
        {
            "category":"Professional",
            "subcategory":"Business Services",
            "type":"Services"
        }
    ],
    "sg:phone":"+61 3 5272 3000",
    "sg:postcode":"3215",
    "sg:province":"VIC",
    "sg:tags":[
        "drafting"
    ],
    "wof:name":"MTV Design Pty. Ltd.",
    "wof:placetype":"venue"
},
  "geometry": {"coordinates":[144.32267761200001,-38.1088829041],"type":"Point"}
}