{
  "type": "Feature",
  "properties": {
    "addr:full":"87 Castlereagh St Sydney NSW 2000",
    "addr:housenumber":"87",
    "addr:postcode":"2000",
    "addr:street":"Castlereagh St",
    "iso:country":"AU",
    "sg:address":"87 Castlereagh St",
    "sg:city":"Sydney",
    "sg:classifiers":[
        {
            "category":"Shopping",
            "subcategory":"Clothing, Apparel, & Fashions",
            "type":"Retail Goods"
        }
    ],
    "sg:phone":"+61 2 9223 0140",
    "sg:postcode":"2000",
    "sg:province":"NSW",
    "sg:tags":[
        "textile",
        "designer"
    ],
    "wof:name":"Birgit Frances Australia",
    "wof:placetype":"venue"
},
  "geometry": {"coordinates":[151.20942688,-33.8698310852],"type":"Point"}
}