{
  "type": "Feature",
  "properties": {
    "iso:country":"AU",
    "sg:address":"14 High St",
    "sg:city":"Wauchope",
    "sg:classifiers":[
        {
            "category":"Real Estate",
            "subcategory":"Real Estate Agent",
            "type":"Services"
        }
    ],
    "sg:phone":"+61 2 6585 2000",
    "sg:postcode":"2446",
    "sg:province":"NSW",
    "wof:name":"Century 21 Country Coast Real Estate",
    "wof:placetype":"venue"
},
  "geometry": {"coordinates":[152.733963,-31.45752],"type":"Point"}
}