{
  "type": "Feature",
  "properties": {
    "addr:full":"10 Kitchen Rd Dandenong VIC 3175",
    "addr:housenumber":"10",
    "addr:postcode":"3175",
    "addr:street":"Kitchen Rd",
    "iso:country":"AU",
    "sg:address":"10 Kitchen Rd",
    "sg:city":"Dandenong",
    "sg:classifiers":[
        {
            "category":"Utilities",
            "subcategory":"Telephone",
            "type":"Services"
        }
    ],
    "sg:phone":"+61 3 9212 4216",
    "sg:postcode":"3175",
    "sg:province":"VIC",
    "sg:tags":[
        "installation",
        "system",
        "maintenance"
    ],
    "wof:name":"Fujecom Pty Ltd",
    "wof:placetype":"venue"
},
  "geometry": {"coordinates":[145.22401428200001,-38.0257492065],"type":"Point"}
}