{
  "type": "Feature",
  "properties": {
    "addr:full":"Cnr Shaws & Tarneit Rds Werribee VIC 3030",
    "addr:postcode":"3030",
    "addr:street":"Cnr",
    "iso:country":"AU",
    "sg:address":"Cnr Shaws & Tarneit Rds",
    "sg:city":"Werribee",
    "sg:classifiers":[
        {
            "category":"Deli",
            "type":"Food & Drink"
        }
    ],
    "sg:phone":"+61 3 9742 5722",
    "sg:postcode":"3030",
    "sg:province":"VIC",
    "sg:tags":[
        "delicatessen"
    ],
    "wof:name":"Josie's Deli",
    "wof:placetype":"venue"
},
  "geometry": {"coordinates":[144.66355899999999,-37.89016],"type":"Point"}
}