{
  "type": "Feature",
  "properties": {
    "addr:full":"6 Nairana St Invermay TAS 7248",
    "addr:housenumber":"6",
    "addr:postcode":"7248",
    "addr:street":"Nairana St",
    "iso:country":"AU",
    "sg:address":"6 Nairana St",
    "sg:city":"Invermay",
    "sg:classifiers":[
        {
            "category":"Wholesale",
            "subcategory":"Painting Supplies",
            "type":"Manufacturing & Wholesale Goods"
        }
    ],
    "sg:phone":"+61 3 6334 0388",
    "sg:postcode":"7248",
    "sg:province":"TAS",
    "sg:tags":[
        "product",
        "cleaning"
    ],
    "wof:name":"Kempo Manufacturing Co",
    "wof:placetype":"venue"
},
  "geometry": {"coordinates":[147.126754761,-41.4246902466],"type":"Point"}
}