{
  "type": "Feature",
  "properties": {
    "addr:full":"7/1 Ivory La Leichhardt NSW 2040",
    "addr:housenumber":"/ 1",
    "addr:postcode":"2040",
    "addr:street":"Ivory La",
    "iso:country":"AU",
    "sg:address":"7/1 Ivory La",
    "sg:city":"Leichhardt",
    "sg:classifiers":[
        {
            "category":"Professional",
            "subcategory":"Art Services",
            "type":"Services"
        }
    ],
    "sg:phone":"+61 417 257 440",
    "sg:postcode":"2040",
    "sg:province":"NSW",
    "sg:tags":[
        "graphic",
        "designer"
    ],
    "wof:name":"Design Hall Pty Ltd",
    "wof:placetype":"venue"
},
  "geometry": {"coordinates":[151.151535,-33.88755],"type":"Point"}
}