{
  "type": "Feature",
  "properties": {
    "iso:country":"AU",
    "sg:address":"11 Ford St",
    "sg:city":"Berry",
    "sg:classifiers":[
        {
            "category":"Building & Trades",
            "subcategory":"Construction",
            "type":"Services"
        }
    ],
    "sg:phone":"+61 2 4464 2153",
    "sg:postcode":"2535",
    "sg:province":"NSW",
    "sg:tags":[
        "polishing",
        "sanding",
        "floor"
    ],
    "wof:name":"John W.Blow",
    "wof:placetype":"venue"
},
  "geometry": {"coordinates":[150.684692383,-34.7728691101],"type":"Point"}
}