{
  "type": "Feature",
  "properties": {
    "addr:full":"55 Marian St Mt Isa QLD 4825",
    "addr:housenumber":"55",
    "addr:postcode":"4825",
    "addr:street":"Marian St",
    "iso:country":"AU",
    "sg:address":"55 Marian St",
    "sg:city":"Mt Isa",
    "sg:classifiers":[
        {
            "category":"Building & Trades",
            "subcategory":"Construction",
            "type":"Services"
        }
    ],
    "sg:phone":"+61 439 665 277",
    "sg:postcode":"4825",
    "sg:province":"QLD",
    "sg:tags":[
        "renovation",
        "alterations",
        "extension",
        "contractor"
    ],
    "wof:name":"Crayford Constructions Pty Ltd",
    "wof:placetype":"venue"
},
  "geometry": {"coordinates":[139.49627699999999,-20.726048],"type":"Point"}
}