{
  "type": "Feature",
  "properties": {
    "iso:country":"AU",
    "sg:address":"Shp4/ 34 Edward St",
    "sg:city":"Currie",
    "sg:classifiers":[
        {
            "category":"Professional",
            "subcategory":"Secretarial Services",
            "type":"Services"
        }
    ],
    "sg:phone":"+61 3 6462 1910",
    "sg:postcode":"7256",
    "sg:province":"TAS",
    "sg:tags":[
        "typing"
    ],
    "wof:name":"Rededge",
    "wof:placetype":"venue"
},
  "geometry": {"coordinates":[143.85403442399999,-39.9314804077],"type":"Point"}
}