{
  "type": "Feature",
  "properties": {
    "addr:full":"29 Dransfield Way Epping VIC 3076",
    "addr:housenumber":"29",
    "addr:postcode":"3076",
    "addr:street":"Dransfield Way",
    "iso:country":"AU",
    "sg:address":"29 Dransfield Way",
    "sg:city":"Epping",
    "sg:classifiers":[
        {
            "category":"Mining & Drilling",
            "type":"Manufacturing & Wholesale Goods"
        }
    ],
    "sg:phone":"+61 417 568 356",
    "sg:postcode":"3076",
    "sg:province":"VIC",
    "sg:tags":[
        "concrete",
        "breaking",
        "grinding",
        "sawing"
    ],
    "wof:name":"Direct Cut Pty Ltd",
    "wof:placetype":"venue"
},
  "geometry": {"coordinates":[145.05039977999999,-37.637840271],"type":"Point"}
}