{
  "type": "Feature",
  "properties": {
    "addr:full":"117 Harrington St Hobart TAS 7000",
    "addr:housenumber":"117",
    "addr:postcode":"7000",
    "addr:street":"Harrington St",
    "iso:country":"AU",
    "sg:address":"117 Harrington St",
    "sg:city":"Hobart",
    "sg:classifiers":[
        {
            "category":"Professional",
            "subcategory":"Engineering",
            "type":"Services"
        }
    ],
    "sg:phone":"+61 3 6231 2555",
    "sg:postcode":"7000",
    "sg:province":"TAS",
    "sg:tags":[
        "electrical",
        "engineer"
    ],
    "wof:name":"Johnstone McGee & Gandy",
    "wof:placetype":"venue"
},
  "geometry": {"coordinates":[147.32347106899999,-42.883266449],"type":"Point"}
}