{
  "type": "Feature",
  "properties": {
    "addr:full":"Shop 10 1244 Marmion Ave Currambine WA 6028",
    "addr:housenumber":"shop 10",
    "addr:postcode":"1244;6028",
    "addr:street":"Marmion Ave",
    "iso:country":"AU",
    "sg:address":"Shop 10 1244 Marmion Ave",
    "sg:city":"Currambine",
    "sg:classifiers":[
        {
            "category":"Fast Food",
            "type":"Food & Drink"
        }
    ],
    "sg:phone":"+61 8 9305 3599",
    "sg:postcode":"6028",
    "sg:province":"WA",
    "sg:tags":[
        "away",
        "take"
    ],
    "wof:name":"Currambine Ocean Fish & Chips",
    "wof:placetype":"venue"
},
  "geometry": {"coordinates":[115.73822784399999,-31.7416610718],"type":"Point"}
}