{
  "type": "Feature",
  "properties": {
    "addr:full":"Suite 1/ 10 Nicklin Way Minyama QLD 4575",
    "addr:housenumber":"10",
    "addr:postcode":"4575",
    "addr:street":"Nicklin Way",
    "iso:country":"AU",
    "sg:address":"Suite 1/ 10 Nicklin Way",
    "sg:city":"Minyama",
    "sg:classifiers":[
        {
            "category":"Health Services",
            "subcategory":"Dentist",
            "type":"Services"
        }
    ],
    "sg:phone":"+61 7 5444 7100",
    "sg:postcode":"4575",
    "sg:province":"QLD",
    "wof:name":"Jill Armour Dr",
    "wof:placetype":"venue"
},
  "geometry": {"coordinates":[153.12262000000001,-26.700216],"type":"Point"}
}