{
  "type": "Feature",
  "properties": {
    "addr:full":"PO Box 129 Lower Plenty VIC 3093",
    "addr:postcode":"3093",
    "iso:country":"AU",
    "sg:address":"PO Box 129",
    "sg:city":"Lower Plenty",
    "sg:classifiers":[
        {
            "category":"Arts & Performance",
            "subcategory":"Music",
            "type":"Entertainment"
        }
    ],
    "sg:phone":"+61 1800 000 178",
    "sg:postcode":"3093",
    "sg:province":"VIC",
    "sg:tags":[
        "mobile",
        "jockey",
        "disc"
    ],
    "wof:name":"Discosource DJs",
    "wof:placetype":"venue"
},
  "geometry": {"coordinates":[145.11796569800001,-37.7384605408],"type":"Point"}
}