{
  "type": "Feature",
  "properties": {
    "addr:full":"34 Seventh St Murray Bridge SA 5253",
    "addr:housenumber":"34",
    "addr:postcode":"5253",
    "addr:street":"Seventh St",
    "iso:country":"AU",
    "sg:address":"34 Seventh St",
    "sg:city":"Murray Bridge",
    "sg:classifiers":[
        {
            "category":"Health Services",
            "subcategory":"Chiropractor",
            "type":"Services"
        }
    ],
    "sg:phone":"+61 8 8532 3366",
    "sg:postcode":"5253",
    "sg:province":"SA",
    "wof:name":"Murray Valley Chiropractic Centre",
    "wof:placetype":"venue"
},
  "geometry": {"coordinates":[139.27345275900001,-35.117565155],"type":"Point"}
}