{
  "type": "Feature",
  "properties": {
    "iso:country":"AU",
    "sg:address":"Unit 7/ 30 Swan St",
    "sg:city":"Wollongong",
    "sg:classifiers":[
        {
            "category":"Manufacturing",
            "subcategory":"Wood Products",
            "type":"Manufacturing & Wholesale Goods"
        }
    ],
    "sg:phone":"+61 2 4229 2935",
    "sg:postcode":"2500",
    "sg:province":"NSW",
    "sg:tags":[
        "polisher",
        "french"
    ],
    "wof:name":"Illawarra Furniture Restorations",
    "wof:placetype":"venue"
},
  "geometry": {"coordinates":[150.897995,-34.435997],"type":"Point"}
}