{
  "type": "Feature",
  "properties": {
    "iso:country":"AU",
    "sg:address":"26c Commercial Drv",
    "sg:city":"Dandenong",
    "sg:classifiers":[
        {
            "category":"Retail",
            "subcategory":"Auto Repair",
            "type":"Services"
        }
    ],
    "sg:phone":"+61 3 9768 3318",
    "sg:postcode":"3175",
    "sg:province":"VIC",
    "sg:tags":[
        "testing",
        "inspection",
        "motor",
        "vehicle"
    ],
    "wof:name":"The Roadworthy Shop",
    "wof:placetype":"venue"
},
  "geometry": {"coordinates":[145.22903442399999,-38.0223960876],"type":"Point"}
}