{
  "type": "Feature",
  "properties": {
    "addr:full":"30 Rome Rd Wanneroo WA 6065",
    "addr:housenumber":"30",
    "addr:postcode":"6065",
    "addr:street":"Rome Rd",
    "iso:country":"AU",
    "sg:address":"30 Rome Rd",
    "sg:city":"Wanneroo",
    "sg:classifiers":[
        {
            "category":"Wholesale",
            "subcategory":"Non-durable Goods",
            "type":"Manufacturing & Wholesale Goods"
        }
    ],
    "sg:phone":"+61 8 9405 6415",
    "sg:postcode":"6065",
    "sg:province":"WA",
    "sg:tags":[
        "wholesaler",
        "craft",
        "mfrs"
    ],
    "wof:name":"Shades Of Brilliance",
    "wof:placetype":"venue"
},
  "geometry": {"coordinates":[115.826347351,-31.751625061],"type":"Point"}
}