{
  "type": "Feature",
  "properties": {
    "addr:full":"3 Manuka Rd Berwick VIC 3806",
    "addr:housenumber":"3",
    "addr:postcode":"3806",
    "addr:street":"Manuka Rd",
    "iso:country":"AU",
    "sg:address":"3 Manuka Rd",
    "sg:city":"Berwick",
    "sg:classifiers":[
        {
            "category":"Health Services",
            "subcategory":"Dentist",
            "type":"Services"
        }
    ],
    "sg:phone":"+61 3 9707 3956",
    "sg:postcode":"3806",
    "sg:province":"VIC",
    "sg:tags":[
        "technician",
        "dental"
    ],
    "wof:name":"Crown Dental Laboratory Pty Ltd",
    "wof:placetype":"venue"
},
  "geometry": {"coordinates":[145.36073303200001,-38.0389442444],"type":"Point"}
}