{
  "type": "Feature",
  "properties": {
    "iso:country":"AU",
    "sg:address":"87 Vincent St",
    "sg:city":"Cessnock",
    "sg:classifiers":[
        {
            "category":"Personal",
            "subcategory":"Tattoo Parlor",
            "type":"Services"
        }
    ],
    "sg:phone":"+61 2 4990 8410",
    "sg:postcode":"2325",
    "sg:province":"NSW",
    "sg:tags":[
        "tattooing"
    ],
    "wof:name":"Tattoo Nation",
    "wof:placetype":"venue"
},
  "geometry": {"coordinates":[151.356201172,-32.8346366882],"type":"Point"}
}