{
  "type": "Feature",
  "properties": {
    "addr:full":"61 Nish St Echuca VIC 3564",
    "addr:housenumber":"61",
    "addr:postcode":"3564",
    "addr:street":"Nish St",
    "iso:country":"AU",
    "sg:address":"61 Nish St",
    "sg:city":"Echuca",
    "sg:classifiers":[
        {
            "category":"Health Services",
            "subcategory":"Health Practitioner",
            "type":"Services"
        }
    ],
    "sg:phone":"+61 3 5480 7366",
    "sg:postcode":"3564",
    "sg:province":"VIC",
    "sg:tags":[
        "naturopath"
    ],
    "wof:name":"Naturopathic Diagnostic Clinic",
    "wof:placetype":"venue"
},
  "geometry": {"coordinates":[144.75059509299999,-36.1279907227],"type":"Point"}
}