{
  "type": "Feature",
  "properties": {
    "addr:full":"Suite 1, 155 King William Rd Hyde Park SA 5061",
    "addr:housenumber":"155",
    "addr:postcode":"5061",
    "addr:street":"King William Rd",
    "iso:country":"AU",
    "sg:address":"Suite 1, 155 King William Rd",
    "sg:city":"Hyde Park",
    "sg:classifiers":[
        {
            "category":"Health Services",
            "subcategory":"Health Practitioner",
            "type":"Services"
        }
    ],
    "sg:phone":"+61 8 8373 4922",
    "sg:postcode":"5061",
    "sg:province":"SA",
    "sg:tags":[
        "physiotherapist"
    ],
    "wof:name":"Goodwood Physiotherapy",
    "wof:placetype":"venue"
},
  "geometry": {"coordinates":[138.60038757300001,-34.9564590454],"type":"Point"}
}