{
  "type": "Feature",
  "properties": {
    "addr:full":"20 Bonchester Crt Duncraig WA 6023",
    "addr:housenumber":"20",
    "addr:postcode":"6023",
    "addr:street":"Bonchester Crt",
    "iso:country":"AU",
    "sg:address":"20 Bonchester Crt",
    "sg:city":"Duncraig",
    "sg:classifiers":[
        {
            "category":"Shopping",
            "subcategory":"Party Supplies",
            "type":"Retail Goods"
        }
    ],
    "sg:phone":"+61 8 9305 3502",
    "sg:postcode":"6023",
    "sg:province":"WA",
    "wof:name":"Flamingo Fun Lawn Characters",
    "wof:placetype":"venue"
},
  "geometry": {"coordinates":[115.771980286,-31.8388385773],"type":"Point"}
}