{
  "type": "Feature",
  "properties": {
    "addr:full":"1 Civic Rd Auburn NSW 2144",
    "addr:housenumber":"1",
    "addr:postcode":"2144",
    "addr:street":"Civic Rd",
    "iso:country":"AU",
    "sg:address":"1 Civic Rd",
    "sg:city":"Auburn",
    "sg:classifiers":[
        {
            "category":"Personal",
            "subcategory":"Beauty Salon",
            "type":"Services"
        }
    ],
    "sg:phone":"+61 2 9643 5530",
    "sg:postcode":"2144",
    "sg:province":"NSW",
    "sg:tags":[
        "hairdresser"
    ],
    "wof:name":"B & F Hair Line",
    "wof:placetype":"venue"
},
  "geometry": {"coordinates":[151.02838134800001,-33.8578300476],"type":"Point"}
}