{
  "type": "Feature",
  "properties": {
    "addr:full":"143 Brand Hwy Geraldton WA 6530",
    "addr:housenumber":"143",
    "addr:postcode":"6530",
    "addr:street":"Brand Hwy",
    "iso:country":"AU",
    "sg:address":"143 Brand Hwy",
    "sg:city":"Geraldton",
    "sg:classifiers":[
        {
            "category":"Social Services",
            "subcategory":"Child Care",
            "type":"Services"
        }
    ],
    "sg:phone":"+61 8 9921 6061",
    "sg:postcode":"6530",
    "sg:province":"WA",
    "wof:name":"Little Buccaneers Child Care Centre",
    "wof:placetype":"venue"
},
  "geometry": {"coordinates":[114.621238709,-28.8018264771],"type":"Point"}
}