{
  "type": "Feature",
  "properties": {
    "iso:country":"AU",
    "sg:address":"Kow Swamp Rd",
    "sg:city":"Leitchville",
    "sg:classifiers":[
        {
            "category":"Farming",
            "subcategory":"Farm",
            "type":"Manufacturing & Wholesale Goods"
        }
    ],
    "sg:phone":"+61 3 5456 7343",
    "sg:postcode":"3567",
    "sg:province":"VIC",
    "sg:tags":[
        "farmer"
    ],
    "wof:name":"Bowland B M",
    "wof:placetype":"venue"
},
  "geometry": {"coordinates":[144.292434692,-35.9219093323],"type":"Point"}
}