{
  "type": "Feature",
  "properties": {
    "addr:full":"Ste 4 Lvl 2 Royal Arcade 175 Oxford St Bondi Junction NSW 2022",
    "addr:housenumber":"175",
    "addr:postcode":"2022",
    "addr:street":"Royal Arcade;Oxford St",
    "iso:country":"AU",
    "sg:address":"Ste 4 Lvl 2 Royal Arcade 175 Oxford St",
    "sg:city":"Bondi Junction",
    "sg:classifiers":[
        {
            "category":"Health Services",
            "subcategory":"Chiropractor",
            "type":"Services"
        }
    ],
    "sg:phone":"+61 2 9369 4092",
    "sg:postcode":"2022",
    "sg:province":"NSW",
    "wof:name":"Gilsenan Simon",
    "wof:placetype":"venue"
},
  "geometry": {"coordinates":[151.248504639,-33.8920822144],"type":"Point"}
}