{
  "type": "Feature",
  "properties": {
    "addr:full":"54 Mary St Gympie QLD 4570",
    "addr:housenumber":"54",
    "addr:postcode":"4570",
    "addr:street":"Mary St",
    "iso:country":"AU",
    "sg:address":"54 Mary St",
    "sg:city":"Gympie",
    "sg:classifiers":[
        {
            "category":"Travel",
            "subcategory":"Travel Agent",
            "type":"Entertainment"
        }
    ],
    "sg:phone":"+61 7 5482 6999",
    "sg:postcode":"4570",
    "sg:province":"QLD",
    "sg:tags":[
        "consultant"
    ],
    "wof:name":"Travelscene Gympie",
    "wof:placetype":"venue"
},
  "geometry": {"coordinates":[152.663970947,-26.1902523041],"type":"Point"}
}