{
  "type": "Feature",
  "properties": {
    "addr:full":"Unit 3/ 14 Sovereign Pl South Windsor NSW 2756",
    "addr:housenumber":"14",
    "addr:postcode":"2756",
    "addr:street":"Sovereign Pl",
    "iso:country":"AU",
    "sg:address":"Unit 3/ 14 Sovereign Pl",
    "sg:city":"South Windsor",
    "sg:classifiers":[
        {
            "category":"Professional",
            "type":"Services"
        }
    ],
    "sg:phone":"+61 2 4587 9757",
    "sg:postcode":"2756",
    "sg:province":"NSW",
    "sg:tags":[
        "shop",
        "fitting"
    ],
    "wof:name":"Hanna's Joinery Pty Ltd",
    "wof:placetype":"venue"
},
  "geometry": {"coordinates":[150.814254761,-33.6194496155],"type":"Point"}
}