{
  "type": "Feature",
  "properties": {
    "iso:country":"AU",
    "sg:address":"5 Kuyora Pl",
    "sg:city":"Elanora Heights",
    "sg:classifiers":[
        {
            "category":"Professional",
            "subcategory":"Printing & Photocopies",
            "type":"Services"
        }
    ],
    "sg:phone":"+61 2 9913 2511",
    "sg:postcode":"2101",
    "sg:province":"NSW",
    "sg:tags":[
        "plaque"
    ],
    "wof:name":"Bronze Plaques Australia",
    "wof:placetype":"venue"
},
  "geometry": {"coordinates":[151.28805500000001,-33.695415],"type":"Point"}
}