{
  "type": "Feature",
  "properties": {
    "addr:full":"200 Merri St Warrnambool VIC 3280",
    "addr:housenumber":"200",
    "addr:postcode":"3280",
    "addr:street":"Merri St",
    "iso:country":"AU",
    "sg:address":"200 Merri St",
    "sg:city":"Warrnambool",
    "sg:classifiers":[
        {
            "category":"Professional",
            "subcategory":"Employment Agencies",
            "type":"Services"
        }
    ],
    "sg:phone":"+61 3 5562 5423",
    "sg:postcode":"3280",
    "sg:province":"VIC",
    "wof:name":"Mentor",
    "wof:placetype":"venue"
},
  "geometry": {"coordinates":[142.47630310100001,-38.3849639893],"type":"Point"}
}