{
  "type": "Feature",
  "properties": {
    "iso:country":"AU",
    "sg:address":"64 Hallam Rd",
    "sg:city":"Hampton Park",
    "sg:classifiers":[
        {
            "category":"Professional",
            "subcategory":"Accounting & Tax Preparation",
            "type":"Services"
        }
    ],
    "sg:phone":"+61 3 9799 6788",
    "sg:postcode":"3976",
    "sg:province":"VIC",
    "sg:tags":[
        "accountant",
        "auditor"
    ],
    "wof:name":"C J Lohrey Pty Ltd",
    "wof:placetype":"venue"
},
  "geometry": {"coordinates":[145.267669678,-38.0341491699],"type":"Point"}
}