{
  "type": "Feature",
  "properties": {
    "iso:country":"AU",
    "sg:address":"28 Capper St",
    "sg:city":"Gayndah",
    "sg:classifiers":[
        {
            "category":"Banks & Credit Unions",
            "subcategory":"Bank",
            "type":"Services"
        }
    ],
    "sg:phone":"+61 7 4161 1738",
    "sg:postcode":"4625",
    "sg:province":"QLD",
    "wof:name":"Wide Bay Australia Ltd",
    "wof:placetype":"venue"
},
  "geometry": {"coordinates":[151.60957300000001,-25.624901],"type":"Point"}
}