{
  "type": "Feature",
  "properties": {
    "iso:country":"AU",
    "sg:address":"PO Box 7333",
    "sg:city":"Toowoomba",
    "sg:classifiers":[
        {
            "category":"Building & Trades",
            "subcategory":"Construction",
            "type":"Services"
        }
    ],
    "sg:phone":"+61 7 4697 5182",
    "sg:postcode":"4352",
    "sg:province":"QLD",
    "sg:tags":[
        "roof"
    ],
    "wof:name":"Skips Roofing",
    "wof:placetype":"venue"
},
  "geometry": {"coordinates":[151.953292847,-27.5614490509],"type":"Point"}
}