{
  "type": "Feature",
  "properties": {
    "addr:full":"Shop 5 10-12 Clarke St Crows Nest NSW 2065",
    "addr:housenumber":"shop 5 10-12",
    "addr:postcode":"2065",
    "addr:street":"Clarke St",
    "iso:country":"AU",
    "sg:address":"Shop 5 10-12 Clarke St",
    "sg:city":"Crows Nest",
    "sg:classifiers":[
        {
            "category":"Shopping",
            "subcategory":"Computers & Home Electronics",
            "type":"Retail Goods"
        }
    ],
    "sg:phone":"+61 2 9437 5437",
    "sg:postcode":"2065",
    "sg:province":"NSW",
    "sg:tags":[
        "small",
        "equipment",
        "business"
    ],
    "wof:name":"T.I. Computers",
    "wof:placetype":"venue"
},
  "geometry": {"coordinates":[151.19993591299999,-33.8257446289],"type":"Point"}
}