{
  "type": "Feature",
  "properties": {
    "iso:country":"AU",
    "sg:address":"No. 9 Tammany Drv",
    "sg:city":"Clarinda",
    "sg:classifiers":[
        {
            "category":"Professional",
            "subcategory":"Printing & Photocopies",
            "type":"Services"
        }
    ],
    "sg:phone":"+61 3 9551 4680",
    "sg:postcode":"3169",
    "sg:province":"VIC",
    "sg:tags":[
        "rubber",
        "stamp",
        "metal"
    ],
    "wof:name":"Dynamic Rubber Stamp Makers",
    "wof:placetype":"venue"
},
  "geometry": {"coordinates":[145.09919738799999,-37.9435081482],"type":"Point"}
}