{
  "type": "Feature",
  "properties": {
    "addr:full":"3/ 2255 Point Nepean Rd Rye VIC 3941",
    "addr:housenumber":"/ 2255",
    "addr:postcode":"3941",
    "addr:street":"Nepean Rd",
    "iso:country":"AU",
    "sg:address":"3/ 2255 Point Nepean Rd",
    "sg:city":"Rye",
    "sg:classifiers":[
        {
            "category":"Health Services",
            "subcategory":"Health Practitioner",
            "type":"Services"
        }
    ],
    "sg:phone":"+61 3 5985 2470",
    "sg:postcode":"3941",
    "sg:province":"VIC",
    "sg:tags":[
        "psychologist"
    ],
    "sg:website":"http://www.jha.net.au",
    "wof:name":"Judith Homa Psychologists",
    "wof:placetype":"venue"
},
  "geometry": {"coordinates":[144.826904297,-38.3710136414],"type":"Point"}
}