{
  "type": "Feature",
  "properties": {
    "addr:full":"117 Franciscan Ave Frankston VIC 3199",
    "addr:housenumber":"117",
    "addr:postcode":"3199",
    "addr:street":"Franciscan Ave",
    "iso:country":"AU",
    "sg:address":"117 Franciscan Ave",
    "sg:city":"Frankston",
    "sg:classifiers":[
        {
            "category":"Food & Beverages",
            "subcategory":"Groceries & Convenience Stores",
            "type":"Retail Goods"
        }
    ],
    "sg:phone":"+61 3 9789 1533",
    "sg:postcode":"3199",
    "sg:province":"VIC",
    "wof:name":"Franciscan General Store",
    "wof:placetype":"venue"
},
  "geometry": {"coordinates":[145.15592956500001,-38.1650009155],"type":"Point"}
}