{
  "type": "Feature",
  "properties": {
    "iso:country":"AU",
    "sg:address":"Cnr Bluebell & Valentine Rds",
    "sg:city":"Alexandra Hills",
    "sg:classifiers":[
        {
            "category":"Food & Beverages",
            "subcategory":"Groceries & Convenience Stores",
            "type":"Retail Goods"
        }
    ],
    "sg:phone":"+61 7 3824 2396",
    "sg:postcode":"4161",
    "sg:province":"QLD",
    "wof:name":"Alex Hills AUR Express Food Store",
    "wof:placetype":"venue"
},
  "geometry": {"coordinates":[153.21841430699999,-27.5146121979],"type":"Point"}
}