{
  "type": "Feature",
  "properties": {
    "addr:full":"49 Cheltenham St Highgate SA 5063",
    "addr:housenumber":"49",
    "addr:postcode":"5063",
    "addr:street":"Cheltenham St",
    "iso:country":"AU",
    "sg:address":"49 Cheltenham St",
    "sg:city":"Highgate",
    "sg:classifiers":[
        {
            "category":"Education",
            "subcategory":"School",
            "type":"Public Place"
        }
    ],
    "sg:phone":"+61 8 8272 0444",
    "sg:postcode":"5063",
    "sg:province":"SA",
    "sg:tags":[
        "co-educational"
    ],
    "wof:name":"Concordia College",
    "wof:placetype":"venue"
},
  "geometry": {"coordinates":[138.617675781,-34.9592056274],"type":"Point"}
}