{
  "type": "Feature",
  "properties": {
    "addr:full":"Lvl1/ 40 King St Sydney NSW 2000",
    "addr:housenumber":"40",
    "addr:postcode":"2000",
    "addr:street":"King St",
    "iso:country":"AU",
    "sg:address":"Lvl1/ 40 King St",
    "sg:city":"Sydney",
    "sg:classifiers":[
        {
            "category":"Shopping",
            "subcategory":"Computers & Home Electronics",
            "type":"Retail Goods"
        }
    ],
    "sg:phone":"+61 2 9299 5993",
    "sg:postcode":"2000",
    "sg:province":"NSW",
    "sg:tags":[
        "equipment",
        "multimedia"
    ],
    "wof:name":"Get Price Pty Ltd",
    "wof:placetype":"venue"
},
  "geometry": {"coordinates":[151.20469665499999,-33.8685913086],"type":"Point"}
}