{
  "type": "Feature",
  "properties": {
    "iso:country":"AU",
    "sg:address":"10 Maud St",
    "sg:city":"Newstead",
    "sg:classifiers":[
        {
            "category":"Shopping",
            "subcategory":"Crafts & Fabrics",
            "type":"Retail Goods"
        }
    ],
    "sg:phone":"+61 7 3252 8441",
    "sg:postcode":"4006",
    "sg:province":"QLD",
    "sg:tags":[
        "upholstering",
        "supply"
    ],
    "wof:name":"SMS Fabrics",
    "wof:placetype":"venue"
},
  "geometry": {"coordinates":[153.04396057100001,-27.4447460175],"type":"Point"}
}