{
  "type": "Feature",
  "properties": {
    "addr:full":"Level 11/ 100 Miller St North Sydney NSW 2059",
    "addr:housenumber":"/ 100",
    "addr:postcode":"2059",
    "addr:street":"Miller St",
    "iso:country":"AU",
    "sg:address":"Level 11/ 100 Miller St",
    "sg:city":"North Sydney",
    "sg:classifiers":[
        {
            "category":"Professional",
            "subcategory":"Employment Agencies",
            "type":"Services"
        }
    ],
    "sg:phone":"+61 2 9492 0000",
    "sg:postcode":"2059",
    "sg:province":"NSW",
    "wof:name":"E-Contract",
    "wof:placetype":"venue"
},
  "geometry": {"coordinates":[151.20695499999999,-33.83754],"type":"Point"}
}