{
  "type": "Feature",
  "properties": {
    "addr:full":"Cnr East Boundary Rd & Ardena Crt Bentleigh East VIC 3165",
    "addr:postcode":"3165",
    "addr:street":"Cnr East Boundary Rd & Ardena Crt",
    "iso:country":"AU",
    "sg:address":"Cnr East Boundary Rd & Ardena Crt",
    "sg:city":"Bentleigh East",
    "sg:classifiers":[
        {
            "category":"Autos & Motor Vehicles",
            "subcategory":"Fuel & Gas Station",
            "type":"Retail Goods"
        }
    ],
    "sg:phone":"+61 3 9579 4287",
    "sg:postcode":"3165",
    "sg:province":"VIC",
    "wof:name":"Shell Select East Bentleigh",
    "wof:placetype":"venue"
},
  "geometry": {"coordinates":[145.059326172,-37.9206848145],"type":"Point"}
}