{
  "type": "Feature",
  "properties": {
    "addr:full":"11 Vista St Caringbah NSW 2229",
    "addr:housenumber":"11",
    "addr:postcode":"2229",
    "addr:street":"Vista St",
    "iso:country":"AU",
    "sg:address":"11 Vista St",
    "sg:city":"Caringbah",
    "sg:classifiers":[
        {
            "category":"Travel",
            "subcategory":"Hostel",
            "type":"Entertainment"
        }
    ],
    "sg:phone":"+61 2 9524 7806",
    "sg:postcode":"2229",
    "sg:province":"NSW",
    "sg:tags":[
        "home"
    ],
    "wof:name":"Vista House",
    "wof:placetype":"venue"
},
  "geometry": {"coordinates":[151.11659240700001,-34.0433616638],"type":"Point"}
}