{
  "type": "Feature",
  "properties": {
    "addr:full":"12 Gregory St Mackay QLD 4740",
    "addr:housenumber":"12",
    "addr:postcode":"4740",
    "addr:street":"Gregory St",
    "iso:country":"AU",
    "sg:address":"12 Gregory St",
    "sg:city":"Mackay",
    "sg:classifiers":[
        {
            "category":"Education",
            "subcategory":"Special Training",
            "type":"Public Place"
        }
    ],
    "sg:phone":"+61 7 4951 1233",
    "sg:postcode":"4740",
    "sg:province":"QLD",
    "sg:tags":[
        "development"
    ],
    "sg:website":"http://www.madec.org.au",
    "wof:name":"MADEC",
    "wof:placetype":"venue"
},
  "geometry": {"coordinates":[149.18455499999999,-21.140684],"type":"Point"}
}