{
  "type": "Feature",
  "properties": {
    "addr:full":"Level 5, 49 Sherwood Rd Toowong QLD 4066",
    "addr:housenumber":"49",
    "addr:postcode":"4066",
    "addr:street":"Sherwood Rd",
    "iso:country":"AU",
    "sg:address":"Level 5, 49 Sherwood Rd",
    "sg:city":"Toowong",
    "sg:classifiers":[
        {
            "category":"Professional",
            "subcategory":"Employment Agencies",
            "type":"Services"
        }
    ],
    "sg:phone":"+61 7 3371 8888",
    "sg:postcode":"4066",
    "sg:province":"QLD",
    "wof:name":"The Childcare Team",
    "wof:placetype":"venue"
},
  "geometry": {"coordinates":[152.99079895,-27.4851932526],"type":"Point"}
}