{
  "type": "Feature",
  "properties": {
    "addr:full":"68 Theresa St Emerald QLD 4720",
    "addr:housenumber":"68",
    "addr:postcode":"4720",
    "addr:street":"Theresa St",
    "iso:country":"AU",
    "sg:address":"68 Theresa St",
    "sg:city":"Emerald",
    "sg:classifiers":[
        {
            "category":"Building & Trades",
            "subcategory":"Construction",
            "type":"Services"
        }
    ],
    "sg:phone":"+61 7 4982 1576",
    "sg:postcode":"4720",
    "sg:province":"QLD",
    "sg:tags":[
        "concrete",
        "contractor"
    ],
    "wof:name":"P J & J L Young Concreting",
    "wof:placetype":"venue"
},
  "geometry": {"coordinates":[148.16395600000001,-23.522007],"type":"Point"}
}