{
  "type": "Feature",
  "properties": {
    "addr:full":"51 First Ave Rodd Point NSW 2046",
    "addr:housenumber":"51",
    "addr:postcode":"2046",
    "addr:street":"First Ave",
    "iso:country":"AU",
    "sg:address":"51 First Ave",
    "sg:city":"Rodd Point",
    "sg:classifiers":[
        {
            "category":"Retail",
            "subcategory":"Auto Repair",
            "type":"Services"
        }
    ],
    "sg:phone":"+61 2 9713 8158",
    "sg:postcode":"2046",
    "sg:province":"NSW",
    "sg:tags":[
        "repairer",
        "motor",
        "engineer"
    ],
    "wof:name":"Rodd Point Motors",
    "wof:placetype":"venue"
},
  "geometry": {"coordinates":[151.141525,-33.866337],"type":"Point"}
}