{
  "type": "Feature",
  "properties": {
    "addr:full":"Bicentenial Drv Golden Grove SA 5125",
    "addr:postcode":"5125",
    "addr:street":"Bicentenial Drv",
    "iso:country":"AU",
    "sg:address":"Bicentenial Drv",
    "sg:city":"Golden Grove",
    "sg:classifiers":[
        {
            "category":"Education",
            "subcategory":"School",
            "type":"Public Place"
        }
    ],
    "sg:phone":"+61 8 8289 3137",
    "sg:postcode":"5125",
    "sg:province":"SA",
    "sg:tags":[
        "state",
        "except",
        "nsw"
    ],
    "wof:name":"Golden Grove Primary",
    "wof:placetype":"venue"
},
  "geometry": {"coordinates":[138.71232599999999,-34.785069],"type":"Point"}
}