{
  "type": "Feature",
  "properties": {
    "iso:country":"AU",
    "sg:address":"32 Lebanon St",
    "sg:city":"Brighton",
    "sg:classifiers":[
        {
            "category":"Train Station",
            "subcategory":"Light Rail",
            "type":"Transportation"
        }
    ],
    "sg:phone":"+61 431 445 097",
    "sg:postcode":"4017",
    "sg:province":"QLD",
    "sg:tags":[
        "equipment",
        "energy",
        "solar"
    ],
    "wof:name":"Ivis Solar Technology Pty Ltd",
    "wof:placetype":"venue"
},
  "geometry": {"coordinates":[153.04710388199999,-27.3047885895],"type":"Point"}
}