{
  "type": "Feature",
  "properties": {
    "addr:full":"676 Centaur Rd Lavington NSW 2641",
    "addr:housenumber":"676",
    "addr:postcode":"2641",
    "addr:street":"Centaur Rd",
    "iso:country":"AU",
    "sg:address":"676 Centaur Rd",
    "sg:city":"Lavington",
    "sg:classifiers":[
        {
            "category":"Building & Trades",
            "subcategory":"Construction",
            "type":"Services"
        }
    ],
    "sg:phone":"+61 2 6025 3359",
    "sg:postcode":"2641",
    "sg:province":"NSW",
    "sg:tags":[
        "scaffolding"
    ],
    "wof:name":"J.S.B. Scaffold",
    "wof:placetype":"venue"
},
  "geometry": {"coordinates":[146.92022705100001,-36.0355644226],"type":"Point"}
}