{
  "type": "Feature",
  "properties": {
    "iso:country":"AU",
    "sg:address":"PO Box 274",
    "sg:city":"Wavell Heights",
    "sg:classifiers":[
        {
            "category":"Utilities",
            "subcategory":"Electric",
            "type":"Services"
        }
    ],
    "sg:phone":"+61 7 3314 6934",
    "sg:postcode":"4012",
    "sg:province":"QLD",
    "sg:tags":[
        "electrical",
        "contractor"
    ],
    "wof:name":"Wire-Not Electrical",
    "wof:placetype":"venue"
},
  "geometry": {"coordinates":[153.056518555,-27.3959197998],"type":"Point"}
}