{
  "type": "Feature",
  "properties": {
    "iso:country":"AU",
    "sg:address":"466 Parramatta Rd",
    "sg:city":"Petersham",
    "sg:classifiers":[
        {
            "category":"Manufacturing",
            "subcategory":"Glass & Minerals",
            "type":"Manufacturing & Wholesale Goods"
        }
    ],
    "sg:phone":"+61 2 9568 5376",
    "sg:postcode":"2049",
    "sg:province":"NSW",
    "sg:tags":[
        "stained"
    ],
    "wof:name":"Glassfield",
    "wof:placetype":"venue"
},
  "geometry": {"coordinates":[151.158569,-33.888214],"type":"Point"}
}