{
  "type": "Feature",
  "properties": {
    "addr:full":"176 Thuringowa Drv Kirwan QLD 4817",
    "addr:housenumber":"176",
    "addr:postcode":"4817",
    "addr:street":"Thuringowa Drv",
    "iso:country":"AU",
    "sg:address":"176 Thuringowa Drv",
    "sg:city":"Kirwan",
    "sg:classifiers":[
        {
            "category":"Retail",
            "subcategory":"Veterinary Services",
            "type":"Services"
        }
    ],
    "sg:phone":"+61 7 4773 4111",
    "sg:postcode":"4817",
    "sg:province":"QLD",
    "sg:tags":[
        "surgeon"
    ],
    "wof:name":"Reeves Helen",
    "wof:placetype":"venue"
},
  "geometry": {"coordinates":[146.73556500000001,-19.301092],"type":"Point"}
}