{
  "type": "Feature",
  "properties": {
    "iso:country":"AU",
    "sg:address":"9/ 95 White St",
    "sg:city":"Mordialloc",
    "sg:classifiers":[
        {
            "category":"Professional",
            "subcategory":"Engineering",
            "type":"Services"
        }
    ],
    "sg:phone":"+61 3 9580 4853",
    "sg:postcode":"3195",
    "sg:province":"VIC",
    "sg:tags":[
        "engineer"
    ],
    "wof:name":"Mawfit Washer & Gasket Co",
    "wof:placetype":"venue"
},
  "geometry": {"coordinates":[145.09472656200001,-37.999420166],"type":"Point"}
}