{
  "type": "Feature",
  "properties": {
    "addr:full":"15 Nile St Glenelg SA 5045",
    "addr:housenumber":"15",
    "addr:postcode":"5045",
    "addr:street":"Nile St",
    "iso:country":"AU",
    "sg:address":"15 Nile St",
    "sg:city":"Glenelg",
    "sg:classifiers":[
        {
            "category":"Professional",
            "subcategory":"Lawyer & Legal Services",
            "type":"Services"
        }
    ],
    "sg:phone":"+61 8 8294 5253",
    "sg:postcode":"5045",
    "sg:province":"SA",
    "sg:tags":[
        "wills",
        "probate",
        "estate"
    ],
    "wof:name":"Baycity Law",
    "wof:placetype":"venue"
},
  "geometry": {"coordinates":[138.51466400000001,-34.979252],"type":"Point"}
}