{
  "type": "Feature",
  "properties": {
    "iso:country":"AU",
    "sg:address":"35 Laser Drv",
    "sg:city":"Rowville",
    "sg:classifiers":[
        {
            "category":"Professional",
            "subcategory":"Detective & Security Services",
            "type":"Services"
        }
    ],
    "sg:phone":"+61 1800 333 074",
    "sg:postcode":"3178",
    "sg:province":"VIC",
    "sg:tags":[
        "identification",
        "system"
    ],
    "wof:name":"Matthews Intelligent Identification",
    "wof:placetype":"venue"
},
  "geometry": {"coordinates":[145.244216919,-37.9106559753],"type":"Point"}
}