{
  "type": "Feature",
  "properties": {
    "addr:full":"2 Foster St Lake Cargelligo NSW 2672",
    "addr:housenumber":"2",
    "addr:postcode":"2672",
    "addr:street":"Foster St",
    "iso:country":"AU",
    "sg:address":"2 Foster St",
    "sg:city":"Lake Cargelligo",
    "sg:classifiers":[
        {
            "category":"Travel",
            "subcategory":"Hotels & Motels",
            "type":"Entertainment"
        }
    ],
    "sg:phone":"+61 2 6898 1201",
    "sg:postcode":"2672",
    "sg:province":"NSW",
    "wof:name":"Lachlan Way Motel",
    "wof:placetype":"venue"
},
  "geometry": {"coordinates":[146.37571716299999,-33.2979774475],"type":"Point"}
}