{
  "type": "Feature",
  "properties": {
    "addr:full":"3/ 44 Peninsula Blv Seaford VIC 3198",
    "addr:housenumber":"/ 44",
    "addr:postcode":"3198",
    "addr:street":"Peninsula Blv",
    "iso:country":"AU",
    "sg:address":"3/ 44",
    "sg:city":"Peninsula Blv Seaford",
    "sg:classifiers":[
        {
            "category":"Personal",
            "subcategory":"Massage",
            "type":"Services"
        }
    ],
    "sg:phone":"+61 3 9782 4689",
    "sg:postcode":"3198",
    "sg:province":"VIC",
    "sg:tags":[
        "therapy"
    ],
    "wof:name":"Ocean Breeze Massage Therapies",
    "wof:placetype":"venue"
},
  "geometry": {"coordinates":[145.139434814,-38.1158218384],"type":"Point"}
}