{
  "type": "Feature",
  "properties": {
    "addr:full":"25 Portsmouth Rd Erina NSW 2250",
    "addr:housenumber":"25",
    "addr:postcode":"2250",
    "addr:street":"Portsmouth Rd",
    "iso:country":"AU",
    "sg:address":"25 Portsmouth Rd",
    "sg:city":"Erina",
    "sg:classifiers":[
        {
            "category":"Manufacturing",
            "subcategory":"Food",
            "type":"Manufacturing & Wholesale Goods"
        }
    ],
    "sg:phone":"+61 2 4365 6155",
    "sg:postcode":"2250",
    "sg:province":"NSW",
    "sg:tags":[
        "function",
        "catering"
    ],
    "wof:name":"Fragrant Gardens Erina Catering",
    "wof:placetype":"venue"
},
  "geometry": {"coordinates":[151.40277099599999,-33.4314346313],"type":"Point"}
}