{
  "type": "Feature",
  "properties": {
    "addr:full":"160 Unley Rd Unley SA 5061",
    "addr:housenumber":"160",
    "addr:postcode":"5061",
    "addr:street":"Unley Rd",
    "iso:country":"AU",
    "sg:address":"160 Unley Rd",
    "sg:city":"Unley",
    "sg:classifiers":[
        {
            "category":"Health Services",
            "subcategory":"Dentist",
            "type":"Services"
        }
    ],
    "sg:phone":"+61 8 8271 7506",
    "sg:postcode":"5061",
    "sg:province":"SA",
    "wof:name":"Gryst Mark",
    "wof:placetype":"venue"
},
  "geometry": {"coordinates":[138.60719299300001,-34.949054718],"type":"Point"}
}