{
  "type": "Feature",
  "properties": {
    "iso:country":"AU",
    "sg:address":"Look Rd",
    "sg:city":"Waroona",
    "sg:classifiers":[
        {
            "category":"Farming",
            "subcategory":"Farm",
            "type":"Manufacturing & Wholesale Goods"
        }
    ],
    "sg:phone":"+61 8 9733 1261",
    "sg:postcode":"6215",
    "sg:province":"WA",
    "sg:tags":[
        "farmer"
    ],
    "wof:name":"Look J J & L",
    "wof:placetype":"venue"
},
  "geometry": {"coordinates":[115.910988,-32.80204],"type":"Point"}
}