{
  "type": "Feature",
  "properties": {
    "iso:country":"AU",
    "sg:address":"162 Norton St",
    "sg:city":"Leichhardt",
    "sg:classifiers":[
        {
            "category":"Fast Food",
            "type":"Food & Drink"
        }
    ],
    "sg:phone":"+61 2 9550 0774",
    "sg:postcode":"2040",
    "sg:province":"NSW",
    "sg:tags":[
        "away",
        "take"
    ],
    "wof:name":"Bombay Grill",
    "wof:placetype":"venue"
},
  "geometry": {"coordinates":[151.156647,-33.881565],"type":"Point"}
}