{
  "type": "Feature",
  "properties": {
    "iso:country":"AU",
    "sg:address":"Shop GA21 Toowong Village SC, 9 Sherwood Rd",
    "sg:city":"Toowong",
    "sg:classifiers":[
        {
            "category":"Shopping",
            "subcategory":"Mobile Phones",
            "type":"Retail Goods"
        }
    ],
    "sg:phone":"+61 7 3876 9398",
    "sg:postcode":"4066",
    "sg:province":"QLD",
    "sg:tags":[
        "telephone",
        "accessory"
    ],
    "wof:name":"Telstra Shop",
    "wof:placetype":"venue"
},
  "geometry": {"coordinates":[152.991897583,-27.4856147766],"type":"Point"}
}