{
  "type": "Feature",
  "properties": {
    "addr:full":"100 Levanswell Rd Moorabbin VIC 3189",
    "addr:housenumber":"100",
    "addr:postcode":"3189",
    "addr:street":"Levanswell Rd",
    "iso:country":"AU",
    "sg:address":"100 Levanswell Rd",
    "sg:city":"Moorabbin",
    "sg:classifiers":[
        {
            "category":"Wholesale",
            "subcategory":"Toys & Hobbies",
            "type":"Manufacturing & Wholesale Goods"
        }
    ],
    "sg:phone":"+61 3 9532 3733",
    "sg:postcode":"3189",
    "sg:province":"VIC",
    "wof:name":"Global Toys & Gifts",
    "wof:placetype":"venue"
},
  "geometry": {"coordinates":[145.074295044,-37.946105957],"type":"Point"}
}