{
  "type": "Feature",
  "properties": {
    "iso:country":"AU",
    "sg:address":"55 Griffiths St",
    "sg:city":"Toowoomba",
    "sg:classifiers":[
        {
            "category":"Home & Garden",
            "subcategory":"Garden Supply",
            "type":"Retail Goods"
        }
    ],
    "sg:phone":"+61 7 4632 5510",
    "sg:postcode":"4350",
    "sg:province":"QLD",
    "sg:tags":[
        "equipment"
    ],
    "wof:name":"Lattice Designs",
    "wof:placetype":"venue"
},
  "geometry": {"coordinates":[151.954727,-27.529781],"type":"Point"}
}