{
  "type": "Feature",
  "properties": {
    "addr:full":"39 Murray Valley Hwy Echuca VIC 3564",
    "addr:housenumber":"39",
    "addr:postcode":"3564",
    "addr:street":"Murray Valley Hwy",
    "iso:country":"AU",
    "sg:address":"39 Murray Valley Hwy",
    "sg:city":"Echuca",
    "sg:classifiers":[
        {
            "category":"Building & Trades",
            "subcategory":"Construction",
            "type":"Services"
        }
    ],
    "sg:phone":"+61 3 5480 1733",
    "sg:postcode":"3564",
    "sg:province":"VIC",
    "sg:tags":[
        "earth",
        "excavating",
        "moving",
        "contractor"
    ],
    "wof:name":"Northern Constructions Group Aust. Pty. Ltd.",
    "wof:placetype":"venue"
},
  "geometry": {"coordinates":[144.75157165499999,-36.140499115],"type":"Point"}
}