{
  "type": "Feature",
  "properties": {
    "addr:full":"43 Fairfield St Fairfield NSW 2165",
    "addr:housenumber":"43",
    "addr:postcode":"2165",
    "addr:street":"Fairfield St",
    "iso:country":"AU",
    "sg:address":"43 Fairfield St",
    "sg:city":"Fairfield",
    "sg:classifiers":[
        {
            "category":"Retail",
            "subcategory":"Auto Repair",
            "type":"Services"
        }
    ],
    "sg:phone":"+61 2 9681 2899",
    "sg:postcode":"2165",
    "sg:province":"NSW",
    "sg:tags":[
        "clutch",
        "brake"
    ],
    "wof:name":"Western Mufflers",
    "wof:placetype":"venue"
},
  "geometry": {"coordinates":[150.97186279300001,-33.8685112],"type":"Point"}
}