{
  "type": "Feature",
  "properties": {
    "addr:full":"Kiosk 2 The Pines Shopping Centre, Cnr Guineas Crk Rd & KP McGrath Drv Elanora QLD 4221",
    "addr:postcode":"4221",
    "addr:street":"Cnr Guineas Crk Rd &;Mcgrath Drv",
    "iso:country":"AU",
    "sg:address":"Kiosk 2 The Pines Shopping Centre, Cnr Guineas Crk Rd & KP McGrath Drv",
    "sg:city":"Elanora",
    "sg:classifiers":[
        {
            "category":"Building & Trades",
            "subcategory":"Locksmith",
            "type":"Services"
        }
    ],
    "sg:phone":"+61 7 5598 1308",
    "sg:postcode":"4221",
    "sg:province":"QLD",
    "sg:tags":[
        "lock"
    ],
    "wof:name":"Mister Minit",
    "wof:placetype":"venue"
},
  "geometry": {"coordinates":[153.46051025400001,-28.1234436035],"type":"Point"}
}