{
  "type": "Feature",
  "properties": {
    "addr:full":"245a Glenferrie Rd Malvern VIC 3144",
    "addr:housenumber":"245a",
    "addr:postcode":"3144",
    "addr:street":"Glenferrie Rd",
    "iso:country":"AU",
    "sg:address":"245a Glenferrie Rd",
    "sg:city":"Malvern",
    "sg:classifiers":[
        {
            "category":"Shopping",
            "type":"Retail Goods"
        }
    ],
    "sg:phone":"+61 3 9509 2421",
    "sg:postcode":"3144",
    "sg:province":"VIC",
    "sg:tags":[
        "new age",
        "product"
    ],
    "wof:name":"Sacred Source",
    "wof:placetype":"venue"
},
  "geometry": {"coordinates":[145.02891540499999,-37.8578605652],"type":"Point"}
}