{
  "type": "Feature",
  "properties": {
    "iso:country":"AU",
    "sg:address":"31 Maddens La",
    "sg:city":"Coldstream",
    "sg:classifiers":[
        {
            "category":"Food & Beverages",
            "subcategory":"Liquor & Beverages",
            "type":"Retail Goods"
        }
    ],
    "sg:phone":"+61 3 5964 9410",
    "sg:postcode":"3770",
    "sg:province":"VIC",
    "sg:tags":[
        "merchant",
        "spirit",
        "wine"
    ],
    "wof:name":"Coldstream Hills Cellar Door Sales",
    "wof:placetype":"venue"
},
  "geometry": {"coordinates":[145.462891,-37.71912],"type":"Point"}
}