{
  "type": "Feature",
  "properties": {
    "iso:country":"AU",
    "sg:address":"30 Olive Crt",
    "sg:city":"Bagshot",
    "sg:classifiers":[
        {
            "category":"Home & Garden",
            "subcategory":"Garden Supply",
            "type":"Retail Goods"
        }
    ],
    "sg:phone":"+61 3 5448 8840",
    "sg:postcode":"3551",
    "sg:province":"VIC",
    "sg:tags":[
        "equipment",
        "greenhouses"
    ],
    "wof:name":"Gill David Greenhouses",
    "wof:placetype":"venue"
},
  "geometry": {"coordinates":[144.38783264200001,-36.6657867432],"type":"Point"}
}