{
  "type": "Feature",
  "properties": {
    "addr:full":"53 Pine Ave Leeton NSW 2705",
    "addr:housenumber":"53",
    "addr:postcode":"2705",
    "addr:street":"Pine Ave",
    "iso:country":"AU",
    "sg:address":"53 Pine Ave",
    "sg:city":"Leeton",
    "sg:classifiers":[
        {
            "category":"Shopping",
            "type":"Retail Goods"
        }
    ],
    "sg:phone":"+61 2 6953 2555",
    "sg:postcode":"2705",
    "sg:province":"NSW",
    "sg:tags":[
        "agent",
        "stock"
    ],
    "wof:name":"Breed & Hutchinson Pty Ltd",
    "wof:placetype":"venue"
},
  "geometry": {"coordinates":[146.404953003,-34.5515174866],"type":"Point"}
}