{
  "type": "Feature",
  "properties": {
    "iso:country":"AU",
    "sg:address":"1089 Old Princess Hwy",
    "sg:city":"Engadine",
    "sg:classifiers":[
        {
            "category":"Fast Food",
            "type":"Food & Drink"
        }
    ],
    "sg:phone":"+61 2 9548 3544",
    "sg:postcode":"2233",
    "sg:province":"NSW",
    "sg:tags":[
        "away",
        "take"
    ],
    "wof:name":"Mie Thai Takeaway",
    "wof:placetype":"venue"
},
  "geometry": {"coordinates":[151.01202392600001,-34.066204071],"type":"Point"}
}