{
  "type": "Feature",
  "properties": {
    "iso:country":"AU",
    "sg:address":"302 Rocky Point Rd",
    "sg:city":"Ramsgate",
    "sg:classifiers":[
        {
            "category":"Health Services",
            "subcategory":"Dentist",
            "type":"Services"
        }
    ],
    "sg:phone":"+61 2 9529 3760",
    "sg:postcode":"2217",
    "sg:province":"NSW",
    "wof:name":"Southern Sydney Dental Care",
    "wof:placetype":"venue"
},
  "geometry": {"coordinates":[151.136459,-33.984077],"type":"Point"}
}