{
  "type": "Feature",
  "properties": {
    "addr:full":"PO Box 863 Benalla VIC 3672",
    "addr:postcode":"3672",
    "iso:country":"AU",
    "sg:address":"PO Box 863",
    "sg:city":"Benalla",
    "sg:classifiers":[
        {
            "category":"Building & Trades",
            "subcategory":"Construction",
            "type":"Services"
        }
    ],
    "sg:phone":"+61 3 5762 6634",
    "sg:postcode":"3672",
    "sg:province":"VIC",
    "sg:tags":[
        "contractor"
    ],
    "wof:name":"Benalla Builders",
    "wof:placetype":"venue"
},
  "geometry": {"coordinates":[146.00680500000001,-36.57111],"type":"Point"}
}