{
  "type": "Feature",
  "properties": {
    "addr:full":"33 Carron St Page ACT 2614",
    "addr:housenumber":"33",
    "addr:postcode":"2614",
    "addr:street":"Carron St",
    "iso:country":"AU",
    "sg:address":"33 Carron St",
    "sg:city":"Page",
    "sg:classifiers":[
        {
            "category":"Education",
            "subcategory":"Vocational School",
            "type":"Public Place"
        }
    ],
    "sg:phone":"+61 2 6254 6645",
    "sg:postcode":"2614",
    "sg:province":"ACT",
    "sg:tags":[
        "cake",
        "decorating",
        "decorator"
    ],
    "wof:name":"Amelia's Cakes",
    "wof:placetype":"venue"
},
  "geometry": {"coordinates":[149.04669189399999,-35.2414093018],"type":"Point"}
}