{
  "type": "Feature",
  "properties": {
    "addr:full":"31 Marinus Pl Erina NSW 2250",
    "addr:housenumber":"31",
    "addr:postcode":"2250",
    "addr:street":"Marinus Pl",
    "iso:country":"AU",
    "sg:address":"31 Marinus Pl",
    "sg:city":"Erina",
    "sg:classifiers":[
        {
            "category":"Manufacturing",
            "subcategory":"Wood Products",
            "type":"Manufacturing & Wholesale Goods"
        }
    ],
    "sg:phone":"+61 2 4365 1253",
    "sg:postcode":"2250",
    "sg:province":"NSW",
    "sg:tags":[
        "polisher",
        "french"
    ],
    "wof:name":"Donel Furniture",
    "wof:placetype":"venue"
},
  "geometry": {"coordinates":[151.385055542,-33.4337387085],"type":"Point"}
}