{
  "type": "Feature",
  "properties": {
    "iso:country":"AU",
    "sg:address":"PO Box 1413",
    "sg:city":"Milton",
    "sg:classifiers":[
        {
            "category":"Real Estate",
            "subcategory":"Real Estate Agent",
            "type":"Services"
        }
    ],
    "sg:phone":"+61 7 3720 9688",
    "sg:postcode":"4064",
    "sg:province":"QLD",
    "wof:name":"Project Property Sales",
    "wof:placetype":"venue"
},
  "geometry": {"coordinates":[153.0052948,-27.4685897827],"type":"Point"}
}