{
  "type": "Feature",
  "properties": {
    "addr:full":"293 Main Rd Emerald VIC 3782",
    "addr:housenumber":"293",
    "addr:postcode":"3782",
    "addr:street":"Main Rd",
    "iso:country":"AU",
    "sg:address":"293 Main Rd",
    "sg:city":"Emerald",
    "sg:classifiers":[
        {
            "category":"Banks & Credit Unions",
            "subcategory":"Investment Brokerage",
            "type":"Services"
        }
    ],
    "sg:phone":"+61 407 392 577",
    "sg:postcode":"3782",
    "sg:province":"VIC",
    "sg:tags":[
        "water",
        "reticulation",
        "contractor"
    ],
    "wof:name":"Ezy Watering Systems Pty Ltd",
    "wof:placetype":"venue"
},
  "geometry": {"coordinates":[145.441193,-37.932167],"type":"Point"}
}