{
  "type": "Feature",
  "properties": {
    "addr:full":"102 King St Buderim QLD 4556",
    "addr:housenumber":"102",
    "addr:postcode":"4556",
    "addr:street":"King St",
    "iso:country":"AU",
    "sg:address":"102 King St",
    "sg:city":"Buderim",
    "sg:classifiers":[
        {
            "category":"Deli",
            "type":"Food & Drink"
        }
    ],
    "sg:phone":"+61 7 5445 2181",
    "sg:postcode":"4556",
    "sg:province":"QLD",
    "sg:tags":[
        "delicatessen"
    ],
    "wof:name":"Buderim Delicatessen",
    "wof:placetype":"venue"
},
  "geometry": {"coordinates":[153.065917969,-26.6826953888],"type":"Point"}
}