{
  "type": "Feature",
  "properties": {
    "addr:full":"Cnr Wells & Thompson St Frankston VIC 3199",
    "addr:postcode":"3199",
    "addr:street":"Cnr;St",
    "iso:country":"AU",
    "sg:address":"Cnr Wells & Thompson St",
    "sg:city":"Frankston",
    "sg:classifiers":[
        {
            "category":"Retail",
            "subcategory":"Event Space",
            "type":"Services"
        }
    ],
    "sg:phone":"+61 1300 787 453",
    "sg:postcode":"3199",
    "sg:province":"VIC",
    "sg:tags":[
        "function",
        "organiser"
    ],
    "wof:name":"Strike Bowling Bar",
    "wof:placetype":"venue"
},
  "geometry": {"coordinates":[145.12179565400001,-38.1415710449],"type":"Point"}
}