{
  "type": "Feature",
  "properties": {
    "iso:country":"AU",
    "sg:address":"104 Frobisher St",
    "sg:city":"Osborne Park",
    "sg:classifiers":[
        {
            "category":"Autos & Motor Vehicles",
            "subcategory":"Auto Supplies",
            "type":"Retail Goods"
        }
    ],
    "sg:phone":"+61 8 9443 9100",
    "sg:postcode":"6017",
    "sg:province":"WA",
    "sg:tags":[
        "tyre"
    ],
    "wof:name":"Tyres Wholesalers Direct",
    "wof:placetype":"venue"
},
  "geometry": {"coordinates":[115.819580078,-31.9045295715],"type":"Point"}
}