{
  "type": "Feature",
  "properties": {
    "addr:full":"1 Baldwin St Caloundra QLD 4551",
    "addr:housenumber":"1",
    "addr:postcode":"4551",
    "addr:street":"Baldwin St",
    "iso:country":"AU",
    "sg:address":"1 Baldwin St",
    "sg:city":"Caloundra",
    "sg:classifiers":[
        {
            "category":"Wholesale",
            "subcategory":"Electrical",
            "type":"Manufacturing & Wholesale Goods"
        }
    ],
    "sg:phone":"+61 7 5491 3666",
    "sg:postcode":"4551",
    "sg:province":"QLD",
    "sg:tags":[
        "wholesaler"
    ],
    "wof:name":"GEC Australia Pty Ltd",
    "wof:placetype":"venue"
},
  "geometry": {"coordinates":[153.120193481,-26.8040142059],"type":"Point"}
}