{
  "type": "Feature",
  "properties": {
    "addr:full":"Shops 8 & 9 Bilo Arcade 92 Evans St Sunbury VIC 3429",
    "addr:housenumber":"shops 8 &;92",
    "addr:postcode":"3429",
    "addr:street":"Bilo;Evans St",
    "iso:country":"AU",
    "sg:address":"Shops 8 & 9 Bilo Arcade 92 Evans St",
    "sg:city":"Sunbury",
    "sg:classifiers":[
        {
            "category":"Fast Food",
            "type":"Food & Drink"
        }
    ],
    "sg:phone":"+61 3 9746 5844",
    "sg:postcode":"3429",
    "sg:province":"VIC",
    "sg:tags":[
        "away",
        "take"
    ],
    "wof:name":"Dominos Pizza",
    "wof:placetype":"venue"
},
  "geometry": {"coordinates":[144.72833251899999,-37.5808525085],"type":"Point"}
}