{
  "type": "Feature",
  "properties": {
    "iso:country":"AU",
    "sg:address":"Lot 1 Western Hwy",
    "sg:city":"Dadswells Bridge",
    "sg:classifiers":[
        {
            "category":"Social Services",
            "subcategory":"Job Training",
            "type":"Services"
        }
    ],
    "sg:phone":"+61 419 563 306",
    "sg:postcode":"3385",
    "sg:province":"VIC",
    "sg:tags":[
        "control",
        "equipment",
        "noise"
    ],
    "wof:name":"Brad Engineering Services",
    "wof:placetype":"venue"
},
  "geometry": {"coordinates":[142.51026916500001,-36.9153594971],"type":"Point"}
}