{
  "type": "Feature",
  "properties": {
    "iso:country":"AU",
    "sg:address":"181 Adderley St",
    "sg:city":"West Melbourne",
    "sg:classifiers":[
        {
            "category":"Fast Food",
            "type":"Food & Drink"
        }
    ],
    "sg:phone":"+61 3 9328 1697",
    "sg:postcode":"3003",
    "sg:province":"VIC",
    "sg:tags":[
        "away",
        "take"
    ],
    "wof:name":"Jimmy V's Gourmet Food and Coffee Bar",
    "wof:placetype":"venue"
},
  "geometry": {"coordinates":[144.946136475,-37.8088340759],"type":"Point"}
}