{
  "type": "Feature",
  "properties": {
    "iso:country":"AU",
    "sg:address":"PO Box 497",
    "sg:city":"Mundaring",
    "sg:classifiers":[
        {
            "category":"Retail",
            "subcategory":"Laundry & Dry Cleaning",
            "type":"Services"
        }
    ],
    "sg:phone":"+61 8 9295 1392",
    "sg:postcode":"6073",
    "sg:province":"WA",
    "sg:tags":[
        "cloth",
        "supply"
    ],
    "wof:name":"Ace Rag Traders",
    "wof:placetype":"venue"
},
  "geometry": {"coordinates":[116.167037964,-31.921880722],"type":"Point"}
}