{
  "type": "Feature",
  "properties": {
    "addr:full":"114 Corio St Geelong VIC 3220",
    "addr:housenumber":"114",
    "addr:postcode":"3220",
    "addr:street":"Corio St",
    "iso:country":"AU",
    "sg:address":"114 Corio St",
    "sg:city":"Geelong",
    "sg:classifiers":[
        {
            "category":"Insurance",
            "subcategory":"Life Insurance",
            "type":"Services"
        }
    ],
    "sg:phone":"+61 3 5222 1664",
    "sg:postcode":"3220",
    "sg:province":"VIC",
    "wof:name":"Chapman Welsh Financial Services",
    "wof:placetype":"venue"
},
  "geometry": {"coordinates":[144.364914,-38.1474],"type":"Point"}
}