{
  "type": "Feature",
  "properties": {
    "iso:country":"AU",
    "sg:address":"16-18 Enterprise Dr",
    "sg:city":"Beaudesert",
    "sg:classifiers":[
        {
            "category":"Building & Trades",
            "subcategory":"Equipment Rental",
            "type":"Services"
        }
    ],
    "sg:phone":"+61 428 452 505",
    "sg:postcode":"4285",
    "sg:province":"QLD",
    "sg:tags":[
        "crane",
        "hire"
    ],
    "wof:name":"Regional Crane Hire Pty Ltd",
    "wof:placetype":"venue"
},
  "geometry": {"coordinates":[152.994354,-27.967981],"type":"Point"}
}