{
  "type": "Feature",
  "properties": {
    "addr:full":"shop 4 / 166 Grey St South Bank QLD 4101",
    "addr:housenumber":"shop 4 / 166",
    "addr:postcode":"4101",
    "addr:street":"Grey St",
    "iso:country":"AU",
    "sg:address":"shop 4 / 166 Grey St",
    "sg:city":"South Bank",
    "sg:classifiers":[
        {
            "category":"Food & Beverages",
            "subcategory":"Groceries & Convenience Stores",
            "type":"Retail Goods"
        }
    ],
    "sg:phone":"+61 7 3844 7688",
    "sg:postcode":"4101",
    "sg:province":"QLD",
    "wof:name":"Lucky 7 South Bank",
    "wof:placetype":"venue"
},
  "geometry": {"coordinates":[153.02151489299999,-27.4781742096],"type":"Point"}
}