{
  "type": "Feature",
  "properties": {
    "addr:full":"92 Denham St Rockhampton QLD 4700",
    "addr:housenumber":"92",
    "addr:postcode":"4700",
    "addr:street":"Denham St",
    "iso:country":"AU",
    "sg:address":"92 Denham St",
    "sg:city":"Rockhampton",
    "sg:classifiers":[
        {
            "category":"Personal",
            "type":"Services"
        }
    ],
    "sg:phone":"+61 7 4921 2308",
    "sg:postcode":"4700",
    "sg:province":"QLD",
    "sg:tags":[
        "gift"
    ],
    "wof:name":"Sweet & Shabby",
    "wof:placetype":"venue"
},
  "geometry": {"coordinates":[150.49856567399999,-23.3876628876],"type":"Point"}
}