{
  "type": "Feature",
  "properties": {
    "iso:country":"AU",
    "sg:address":"250 Centre Rd",
    "sg:city":"Bentleigh",
    "sg:classifiers":[
        {
            "category":"Health Services",
            "subcategory":"Health Practitioner",
            "type":"Services"
        }
    ],
    "sg:phone":"+61 3 9557 5802",
    "sg:postcode":"3204",
    "sg:province":"VIC",
    "sg:tags":[
        "bowen",
        "therapy"
    ],
    "wof:name":"Centre Rd Chinese Medical Centre",
    "wof:placetype":"venue"
},
  "geometry": {"coordinates":[145.030457,-37.917568],"type":"Point"}
}