{
  "type": "Feature",
  "properties": {
    "addr:full":"38 Coal Point Rd Coal Point NSW 2283",
    "addr:housenumber":"38",
    "addr:postcode":"2283",
    "addr:street":"Coal Point Rd",
    "iso:country":"AU",
    "sg:address":"38 Coal Point Rd",
    "sg:city":"Coal Point",
    "sg:classifiers":[
        {
            "category":"Professional",
            "subcategory":"Computer Services",
            "type":"Services"
        }
    ],
    "sg:phone":"+61 417 671 530",
    "sg:postcode":"2283",
    "sg:province":"NSW",
    "sg:tags":[
        "training"
    ],
    "wof:name":"ArrowLogic",
    "wof:placetype":"venue"
},
  "geometry": {"coordinates":[151.610473633,-33.0424232483],"type":"Point"}
}