{
  "type": "Feature",
  "properties": {
    "addr:full":"Meredith Rd Meredith VIC 3333",
    "addr:postcode":"3333",
    "addr:street":"Meredith Rd",
    "iso:country":"AU",
    "sg:address":"Meredith Rd",
    "sg:city":"Meredith",
    "sg:classifiers":[
        {
            "category":"Building & Trades",
            "subcategory":"Landscaping Services",
            "type":"Services"
        }
    ],
    "sg:phone":"+61 3 5286 1358",
    "sg:postcode":"3333",
    "sg:province":"VIC",
    "sg:tags":[
        "grazier"
    ],
    "wof:name":"Giuffre A&C Pty Ltd",
    "wof:placetype":"venue"
},
  "geometry": {"coordinates":[144.02525329599999,-37.8515701294],"type":"Point"}
}