{
  "type": "Feature",
  "properties": {
    "addr:full":"90 Main St Greensborough VIC 3088",
    "addr:housenumber":"90",
    "addr:postcode":"3088",
    "addr:street":"Main St",
    "iso:country":"AU",
    "sg:address":"90 Main St",
    "sg:city":"Greensborough",
    "sg:classifiers":[
        {
            "category":"Personal",
            "subcategory":"Beauty Salon",
            "type":"Services"
        }
    ],
    "sg:phone":"+61 3 9435 2211",
    "sg:postcode":"3088",
    "sg:province":"VIC",
    "wof:name":"Brazilian Butterfly",
    "wof:placetype":"venue"
},
  "geometry": {"coordinates":[145.10513305699999,-37.7031707764],"type":"Point"}
}