{
  "type": "Feature",
  "properties": {
    "addr:full":"25 Morgan St Bairnsdale VIC 3875",
    "addr:housenumber":"25",
    "addr:postcode":"3875",
    "addr:street":"Morgan St",
    "iso:country":"AU",
    "sg:address":"25 Morgan St",
    "sg:city":"Bairnsdale",
    "sg:classifiers":[
        {
            "category":"Education",
            "subcategory":"School",
            "type":"Public Place"
        }
    ],
    "sg:phone":"+61 3 5152 2828",
    "sg:postcode":"3875",
    "sg:province":"VIC",
    "wof:name":"Bairnsdale Steiner School",
    "wof:placetype":"venue"
},
  "geometry": {"coordinates":[147.60546875,-37.8198165894],"type":"Point"}
}