{
  "type": "Feature",
  "properties": {
    "addr:full":"Shop 10 Heathridge Vlge Shopng Cntr Heathridge WA 6027",
    "addr:housenumber":"shop 10",
    "addr:postcode":"6027",
    "addr:street":"Heathridge Vlge Shopng Cntr",
    "iso:country":"AU",
    "sg:address":"Shop 10 Heathridge Vlge Shopng Cntr",
    "sg:city":"Heathridge",
    "sg:classifiers":[
        {
            "category":"Deli",
            "type":"Food & Drink"
        }
    ],
    "sg:phone":"+61 8 9401 9642",
    "sg:postcode":"6027",
    "sg:province":"WA",
    "sg:tags":[
        "delicatessen"
    ],
    "wof:name":"Heathridge Delicatessen",
    "wof:placetype":"venue"
},
  "geometry": {"coordinates":[115.76226043699999,-31.7636108398],"type":"Point"}
}