{
  "type": "Feature",
  "properties": {
    "iso:country":"AU",
    "sg:address":"1 South St",
    "sg:city":"Kempsey",
    "sg:classifiers":[
        {
            "category":"Professional",
            "subcategory":"Detective & Security Services",
            "type":"Services"
        }
    ],
    "sg:phone":"+61 2 6562 7244",
    "sg:postcode":"2440",
    "sg:province":"NSW",
    "sg:tags":[
        "equipment",
        "window",
        "doors"
    ],
    "wof:name":"Farrawell Aluminium",
    "wof:placetype":"venue"
},
  "geometry": {"coordinates":[152.831573,-31.100847],"type":"Point"}
}