{
  "type": "Feature",
  "properties": {
    "iso:country":"AU",
    "sg:address":"Suite 5 1st Floor 78- 80 Dale St",
    "sg:city":"Port Adelaide",
    "sg:classifiers":[
        {
            "category":"Health Services",
            "subcategory":"Dentist",
            "type":"Services"
        }
    ],
    "sg:phone":"+61 8 8240 0943",
    "sg:postcode":"5015",
    "sg:province":"SA",
    "wof:name":"Douvartzidis Isaia",
    "wof:placetype":"venue"
},
  "geometry": {"coordinates":[138.50517273,-34.8467216492],"type":"Point"}
}