{
  "type": "Feature",
  "properties": {
    "addr:full":"Lake St Cairns QLD 4870",
    "addr:postcode":"4870",
    "addr:street":"Lake St",
    "iso:country":"AU",
    "sg:address":"Lake St",
    "sg:city":"Cairns",
    "sg:classifiers":[
        {
            "category":"Museum",
            "type":"Entertainment"
        }
    ],
    "sg:phone":"+61 7 4051 5586",
    "sg:postcode":"4870",
    "sg:province":"QLD",
    "wof:name":"Cairns Historical Society Museum",
    "wof:placetype":"venue"
},
  "geometry": {"coordinates":[145.779205322,-16.9260311127],"type":"Point"}
}