{
  "type": "Feature",
  "properties": {
    "iso:country":"AU",
    "sg:address":"432 The Entrance Rd",
    "sg:city":"Erina Heights",
    "sg:classifiers":[
        {
            "category":"Professional",
            "subcategory":"Art Services",
            "type":"Services"
        }
    ],
    "sg:phone":"+61 2 4367 7106",
    "sg:postcode":"2260",
    "sg:province":"NSW",
    "sg:tags":[
        "decorator",
        "painter"
    ],
    "wof:name":"De Zeeuw A V A & R G",
    "wof:placetype":"venue"
},
  "geometry": {"coordinates":[151.40621899999999,-33.425159],"type":"Point"}
}