{
  "type": "Feature",
  "properties": {
    "addr:full":"26 A Edwards Rd Wahroonga NSW 2076",
    "addr:housenumber":"26 a",
    "addr:postcode":"2076",
    "addr:street":"Edwards Rd",
    "iso:country":"AU",
    "sg:address":"26 A Edwards Rd",
    "sg:city":"Wahroonga",
    "sg:classifiers":[
        {
            "category":"Shopping",
            "subcategory":"Stationery & Office Supplies",
            "type":"Retail Goods"
        }
    ],
    "sg:phone":"+61 2 9487 2011",
    "sg:postcode":"2076",
    "sg:province":"NSW",
    "sg:tags":[
        "packaging",
        "material"
    ],
    "wof:name":"Metalprint Australia Pty Ltd",
    "wof:placetype":"venue"
},
  "geometry": {"coordinates":[151.117385864,-33.7187194824],"type":"Point"}
}