{
  "type": "Feature",
  "properties": {
    "iso:country":"AU",
    "sg:address":"PO Box 342",
    "sg:city":"North Adelaide",
    "sg:classifiers":[
        {
            "category":"Organizations",
            "subcategory":"Membership Organization",
            "type":"Services"
        }
    ],
    "sg:phone":"+61 500 803 500",
    "sg:postcode":"5006",
    "sg:province":"SA",
    "sg:tags":[
        "club",
        "car"
    ],
    "wof:name":"Rover Car Club of S.A. Incorporated",
    "wof:placetype":"venue"
},
  "geometry": {"coordinates":[138.59492492699999,-34.9090194702],"type":"Point"}
}