{
  "type": "Feature",
  "properties": {
    "addr:full":"8 Cheppen St The Gap QLD 4061",
    "addr:housenumber":"8",
    "addr:postcode":"4061",
    "addr:street":"Cheppen St",
    "iso:country":"AU",
    "sg:address":"8 Cheppen St",
    "sg:city":"The Gap",
    "sg:classifiers":[
        {
            "category":"Professional",
            "subcategory":"Management & Consulting",
            "type":"Services"
        }
    ],
    "sg:phone":"+61 7 3300 3192",
    "sg:postcode":"4061",
    "sg:province":"QLD",
    "sg:tags":[
        "consultant"
    ],
    "wof:name":"Change Focus Enterprises",
    "wof:placetype":"venue"
},
  "geometry": {"coordinates":[152.940505981,-27.441116333],"type":"Point"}
}