{
  "type": "Feature",
  "properties": {
    "addr:full":"309 Coventry St Melbourne VIC 3000",
    "addr:housenumber":"309",
    "addr:postcode":"3000",
    "addr:street":"Coventry St",
    "iso:country":"AU",
    "sg:address":"309 Coventry St",
    "sg:city":"Melbourne",
    "sg:classifiers":[
        {
            "category":"Personal",
            "subcategory":"Beauty Salon",
            "type":"Services"
        }
    ],
    "sg:phone":"+61 3 9398 0302",
    "sg:postcode":"3000",
    "sg:province":"VIC",
    "sg:tags":[
        "hairdresser"
    ],
    "wof:name":"Short Back & Sideways",
    "wof:placetype":"venue"
},
  "geometry": {"coordinates":[144.95718383799999,-37.8328170776],"type":"Point"}
}