{
  "type": "Feature",
  "properties": {
    "iso:country":"AU",
    "sg:address":"140 Rouse St",
    "sg:city":"Port Melbourne",
    "sg:classifiers":[
        {
            "category":"Deli",
            "type":"Food & Drink"
        }
    ],
    "sg:phone":"+61 3 9681 8558",
    "sg:postcode":"3207",
    "sg:province":"VIC",
    "sg:tags":[
        "delicatessen"
    ],
    "wof:name":"Gourmet Garage",
    "wof:placetype":"venue"
},
  "geometry": {"coordinates":[144.939423,-37.841927],"type":"Point"}
}