{
  "type": "Feature",
  "properties": {
    "addr:full":"Shop 10 N.K. Centre 450 High St Penrith NSW 2750",
    "addr:housenumber":"shop 10;450",
    "addr:postcode":"2750",
    "addr:street":"High St",
    "iso:country":"AU",
    "sg:address":"Shop 10 N.K. Centre 450 High St",
    "sg:city":"Penrith",
    "sg:classifiers":[
        {
            "category":"Education",
            "subcategory":"Vocational School",
            "type":"Public Place"
        }
    ],
    "sg:phone":"+61 2 4722 9580",
    "sg:postcode":"2750",
    "sg:province":"NSW",
    "sg:tags":[
        "cake",
        "decorating",
        "decorator"
    ],
    "wof:name":"One Stop Cake Decorations",
    "wof:placetype":"venue"
},
  "geometry": {"coordinates":[150.915557861,-33.8949356079],"type":"Point"}
}