{
  "type": "Feature",
  "properties": {
    "iso:country":"AU",
    "sg:address":"15 Llewellyn Pl",
    "sg:city":"Eumemmerring",
    "sg:classifiers":[
        {
            "category":"Transit Center",
            "subcategory":"Passenger",
            "type":"Transportation"
        }
    ],
    "sg:phone":"+61 3 9793 6363",
    "sg:postcode":"3177",
    "sg:province":"VIC",
    "sg:tags":[
        "frozen",
        "food",
        "retail"
    ],
    "wof:name":"Shop At Home Supermarkets",
    "wof:placetype":"venue"
},
  "geometry": {"coordinates":[145.24554443400001,-38.000629425],"type":"Point"}
}