{
  "type": "Feature",
  "properties": {
    "iso:country":"AU",
    "sg:address":"25 Brian St",
    "sg:city":"Bentleigh East",
    "sg:classifiers":[
        {
            "category":"Real Estate",
            "subcategory":"Surveying",
            "type":"Services"
        }
    ],
    "sg:phone":"+61 3 9557 8364",
    "sg:postcode":"3165",
    "sg:province":"VIC",
    "sg:tags":[
        "building",
        "surveyor"
    ],
    "wof:name":"Energy Recycling",
    "wof:placetype":"venue"
},
  "geometry": {"coordinates":[145.05325317399999,-37.9247741699],"type":"Point"}
}