{
  "type": "Feature",
  "properties": {
    "iso:country":"AU",
    "sg:address":"6 Gammon Crt",
    "sg:city":"Greenwith",
    "sg:classifiers":[
        {
            "category":"Wholesale",
            "subcategory":"Machinery & Supplies",
            "type":"Manufacturing & Wholesale Goods"
        }
    ],
    "sg:phone":"+61 8 8288 0661",
    "sg:postcode":"5125",
    "sg:province":"SA",
    "sg:tags":[
        "process",
        "instrument",
        "control"
    ],
    "wof:name":"Endress & Hauser",
    "wof:placetype":"venue"
},
  "geometry": {"coordinates":[138.716339,-34.775883],"type":"Point"}
}