{
  "type": "Feature",
  "properties": {
    "addr:full":"Shop 3/ 370 Main Rd Wellington Point QLD 4160",
    "addr:housenumber":"shop 3 / 370",
    "addr:postcode":"4160",
    "addr:street":"Main Rd",
    "iso:country":"AU",
    "sg:address":"Shop 3/ 370 Main Rd",
    "sg:city":"Wellington Point",
    "sg:classifiers":[
        {
            "category":"Personal",
            "subcategory":"Beauty Salon",
            "type":"Services"
        }
    ],
    "sg:phone":"+61 7 3207 3777",
    "sg:postcode":"4160",
    "sg:province":"QLD",
    "sg:tags":[
        "hairdresser"
    ],
    "wof:name":"Revelations In Hair Design",
    "wof:placetype":"venue"
},
  "geometry": {"coordinates":[153.238006592,-27.4854469299],"type":"Point"}
}