{
  "type": "Feature",
  "properties": {
    "iso:country":"AU",
    "sg:address":"15 McInnes St",
    "sg:city":"Ridleyton",
    "sg:classifiers":[
        {
            "category":"Retail",
            "subcategory":"Auto Repair",
            "type":"Services"
        }
    ],
    "sg:phone":"+61 8 8340 2366",
    "sg:postcode":"5008",
    "sg:province":"SA",
    "sg:tags":[
        "repairer",
        "motor",
        "engineer"
    ],
    "wof:name":"Lovato Autogas Pty Ltd",
    "wof:placetype":"venue"
},
  "geometry": {"coordinates":[138.568375,-34.899784],"type":"Point"}
}