{
  "type": "Feature",
  "properties": {
    "addr:full":"75a Monash Ave Como WA 6152",
    "addr:housenumber":"75a",
    "addr:postcode":"6152",
    "addr:street":"Monash Ave",
    "iso:country":"AU",
    "sg:address":"75a Monash Ave",
    "sg:city":"Como",
    "sg:classifiers":[
        {
            "category":"Professional",
            "subcategory":"Business Services",
            "type":"Services"
        }
    ],
    "sg:phone":"+61 410 229 311",
    "sg:postcode":"6152",
    "sg:province":"WA",
    "sg:tags":[
        "management",
        "event"
    ],
    "wof:name":"WA Events & Projects",
    "wof:placetype":"venue"
},
  "geometry": {"coordinates":[115.877228,-31.991987],"type":"Point"}
}