{
  "type": "Feature",
  "properties": {
    "addr:full":"247 Third St Morawa WA 6623",
    "addr:housenumber":"247",
    "addr:postcode":"6623",
    "addr:street":"Third St",
    "iso:country":"AU",
    "sg:address":"247 Third St",
    "sg:city":"Morawa",
    "sg:classifiers":[
        {
            "category":"Building & Trades",
            "subcategory":"Construction",
            "type":"Services"
        }
    ],
    "sg:phone":"+61 8 9971 1627",
    "sg:postcode":"6623",
    "sg:province":"WA",
    "sg:tags":[
        "renovation",
        "alterations",
        "extension",
        "contractor"
    ],
    "wof:name":"Perum Building & Construction Pty Ltd",
    "wof:placetype":"venue"
},
  "geometry": {"coordinates":[116.009239197,-29.2127799988],"type":"Point"}
}