{
  "type": "Feature",
  "properties": {
    "iso:country":"AU",
    "sg:address":"38 Gayndah Rd",
    "sg:city":"Maryborough",
    "sg:classifiers":[
        {
            "category":"Building & Trades",
            "subcategory":"Construction",
            "type":"Services"
        }
    ],
    "sg:phone":"+61 7 4121 0200",
    "sg:postcode":"4650",
    "sg:province":"QLD",
    "sg:tags":[
        "concrete",
        "paving"
    ],
    "wof:name":"Greg Watsons Landscape Supplies",
    "wof:placetype":"venue"
},
  "geometry": {"coordinates":[152.664444,-25.516508],"type":"Point"}
}