{
  "type": "Feature",
  "properties": {
    "addr:full":"142 Balcombe Rd Mentone VIC 3194",
    "addr:housenumber":"142",
    "addr:postcode":"3194",
    "addr:street":"Balcombe Rd",
    "iso:country":"AU",
    "sg:address":"142 Balcombe Rd",
    "sg:city":"Mentone",
    "sg:classifiers":[
        {
            "category":"Personal",
            "subcategory":"Tanning Parlor",
            "type":"Services"
        }
    ],
    "sg:phone":"+61 3 9583 9011",
    "sg:postcode":"3194",
    "sg:province":"VIC",
    "sg:tags":[
        "solarium"
    ],
    "wof:name":"Body Bronze",
    "wof:placetype":"venue"
},
  "geometry": {"coordinates":[145.063110352,-37.9809150696],"type":"Point"}
}