{
  "type": "Feature",
  "properties": {
    "addr:full":"23 Tooth Ave Paddington QLD 4064",
    "addr:housenumber":"23",
    "addr:postcode":"4064",
    "addr:street":"Tooth Ave",
    "iso:country":"AU",
    "sg:address":"23 Tooth Ave",
    "sg:city":"Paddington",
    "sg:classifiers":[
        {
            "category":"Travel",
            "subcategory":"Travel Agent",
            "type":"Entertainment"
        }
    ],
    "sg:phone":"+61 1800 630 068",
    "sg:postcode":"4064",
    "sg:province":"QLD",
    "sg:tags":[
        "tour",
        "holiday",
        "adventure"
    ],
    "wof:name":"Australian Corporate Safaris",
    "wof:placetype":"venue"
},
  "geometry": {"coordinates":[152.99298095699999,-27.4564476013],"type":"Point"}
}