{
  "type": "Feature",
  "properties": {
    "iso:country":"AU",
    "sg:address":"Bruce Hwy",
    "sg:city":"Raglan",
    "sg:classifiers":[
        {
            "category":"Travel",
            "subcategory":"Hotels & Motels",
            "type":"Entertainment"
        }
    ],
    "sg:phone":"+61 7 4934 6558",
    "sg:postcode":"4697",
    "sg:province":"QLD",
    "sg:tags":[
        "accommodation"
    ],
    "wof:name":"Raglan Tavern",
    "wof:placetype":"venue"
},
  "geometry": {"coordinates":[150.841537,-23.744448],"type":"Point"}
}