{
  "type": "Feature",
  "properties": {
    "iso:country":"AU",
    "sg:address":"4 Davids Cl",
    "sg:city":"Somersby",
    "sg:classifiers":[
        {
            "category":"Building & Trades",
            "subcategory":"Construction",
            "type":"Services"
        }
    ],
    "sg:phone":"+61 2 4340 2366",
    "sg:postcode":"2250",
    "sg:province":"NSW",
    "sg:tags":[
        "earth",
        "excavating",
        "moving",
        "contractor"
    ],
    "sg:website":"http://www.adamloweearthmoving.com.au",
    "wof:name":"Adam Lowe Earthmoving Pty Ltd",
    "wof:placetype":"venue"
},
  "geometry": {"coordinates":[151.27992248499999,-33.3779792786],"type":"Point"}
}