{
  "type": "Feature",
  "properties": {
    "addr:full":"67 Snook St Clontarf QLD 4019",
    "addr:housenumber":"67",
    "addr:postcode":"4019",
    "addr:street":"Snook St",
    "iso:country":"AU",
    "sg:address":"67 Snook St",
    "sg:city":"Clontarf",
    "sg:classifiers":[
        {
            "category":"Banks & Credit Unions",
            "subcategory":"Bureau De Change",
            "type":"Services"
        }
    ],
    "sg:phone":"+61 7 3883 2330",
    "sg:postcode":"4019",
    "sg:province":"QLD",
    "sg:tags":[
        "repairs",
        "part",
        "appliance",
        "electrical"
    ],
    "wof:name":"Electric Motor Solutions",
    "wof:placetype":"venue"
},
  "geometry": {"coordinates":[153.08433532699999,-27.241147995],"type":"Point"}
}