{
  "type": "Feature",
  "properties": {
    "addr:full":"Shop 11/ 17 Howard Arc Dee Why NSW 2099",
    "addr:housenumber":"shop 11 / 17",
    "addr:postcode":"2099",
    "addr:street":"Howard Arc",
    "iso:country":"AU",
    "sg:address":"Shop 11/ 17 Howard Arc",
    "sg:city":"Dee Why",
    "sg:classifiers":[
        {
            "category":"Shopping",
            "subcategory":"Clothing, Apparel, & Fashions",
            "type":"Retail Goods"
        }
    ],
    "sg:phone":"+61 2 9971 8682",
    "sg:postcode":"2099",
    "sg:province":"NSW",
    "sg:tags":[
        "boutique"
    ],
    "wof:name":"Totalook Clothing",
    "wof:placetype":"venue"
},
  "geometry": {"coordinates":[151.28822326700001,-33.7528038025],"type":"Point"}
}