{
  "type": "Feature",
  "properties": {
    "iso:country":"AU",
    "sg:address":"128 Scrub Hill Rd",
    "sg:city":"Hervey Bay",
    "sg:classifiers":[
        {
            "category":"Building & Trades",
            "subcategory":"Construction",
            "type":"Services"
        }
    ],
    "sg:phone":"+61 410 310 863",
    "sg:postcode":"4655",
    "sg:province":"QLD",
    "sg:tags":[
        "scaffolding"
    ],
    "wof:name":"ACD Scaffolding",
    "wof:placetype":"venue"
},
  "geometry": {"coordinates":[152.807434,-25.302099],"type":"Point"}
}