{
  "type": "Feature",
  "properties": {
    "iso:country":"AU",
    "sg:address":"17 Lathams Rd",
    "sg:city":"Carrum Downs",
    "sg:classifiers":[
        {
            "category":"Retail",
            "subcategory":"Auto Rental",
            "type":"Services"
        }
    ],
    "sg:phone":"+61 3 9775 0998",
    "sg:postcode":"3201",
    "sg:province":"VIC",
    "sg:tags":[
        "car",
        "hire",
        "minibus"
    ],
    "wof:name":"Titan Car Hire",
    "wof:placetype":"venue"
},
  "geometry": {"coordinates":[145.169693,-38.099117],"type":"Point"}
}