{
  "type": "Feature",
  "properties": {
    "addr:full":"Shop 2/ 1 Mons Rd Forest Glen QLD 4556",
    "addr:housenumber":"shop 2 / 1",
    "addr:postcode":"4556",
    "addr:street":"Mons Rd",
    "iso:country":"AU",
    "sg:address":"Shop 2/ 1 Mons Rd",
    "sg:city":"Forest Glen",
    "sg:classifiers":[
        {
            "category":"Food & Beverages",
            "subcategory":"Fruits & Vegetables",
            "type":"Retail Goods"
        }
    ],
    "sg:phone":"+61 7 5476 9455",
    "sg:postcode":"4556",
    "sg:province":"QLD",
    "sg:tags":[
        "greengrocer",
        "fruiterer"
    ],
    "wof:name":"Forest Glen Fruit Vegies & Gifts",
    "wof:placetype":"venue"
},
  "geometry": {"coordinates":[153.01319885300001,-26.6885147095],"type":"Point"}
}