{
  "type": "Feature",
  "properties": {
    "addr:full":"Level 1/ 308 Centre Rd Bentleigh VIC 3204",
    "addr:housenumber":"/ 308",
    "addr:postcode":"3204",
    "addr:street":"Centre Rd",
    "iso:country":"AU",
    "sg:address":"Level 1/ 308 Centre Rd",
    "sg:city":"Bentleigh",
    "sg:classifiers":[
        {
            "category":"Banks & Credit Unions",
            "subcategory":"Financial Services",
            "type":"Services"
        }
    ],
    "sg:phone":"+61 3 9557 1057",
    "sg:postcode":"3204",
    "sg:province":"VIC",
    "sg:tags":[
        "planning"
    ],
    "wof:name":"AMP Financial Planning Accredited",
    "wof:placetype":"venue"
},
  "geometry": {"coordinates":[145.03280599999999,-37.91785],"type":"Point"}
}