{
  "type": "Feature",
  "properties": {
    "iso:country":"AU",
    "sg:address":"8005 Melbourne Rd",
    "sg:city":"Shepparton",
    "sg:classifiers":[
        {
            "category":"Shopping",
            "type":"Retail Goods"
        }
    ],
    "sg:phone":"+61 3 5823 5477",
    "sg:postcode":"3630",
    "sg:province":"VIC",
    "sg:tags":[
        "equipment",
        "safety",
        "accessory"
    ],
    "wof:name":"The Safety Factory",
    "wof:placetype":"venue"
},
  "geometry": {"coordinates":[145.39289855999999,-36.4097213745],"type":"Point"}
}