{
  "type": "Feature",
  "properties": {
    "addr:full":"497 Wentworth Ave Toongabbie NSW 2146",
    "addr:housenumber":"497",
    "addr:postcode":"2146",
    "addr:street":"Wentworth Ave",
    "iso:country":"AU",
    "sg:address":"497 Wentworth Ave",
    "sg:city":"Toongabbie",
    "sg:classifiers":[
        {
            "category":"Airport",
            "subcategory":"General Aviation",
            "type":"Transportation"
        }
    ],
    "sg:phone":"+61 2 9896 8833",
    "sg:postcode":"2146",
    "sg:province":"NSW",
    "sg:tags":[
        "pressure",
        "gauge"
    ],
    "wof:name":"JCB Instruments",
    "wof:placetype":"venue"
},
  "geometry": {"coordinates":[150.95173645,-33.7863502502],"type":"Point"}
}