{
  "type": "Feature",
  "properties": {
    "addr:full":"34 Harvest Crt Southport QLD 4215",
    "addr:housenumber":"34",
    "addr:postcode":"4215",
    "addr:street":"Harvest Crt",
    "iso:country":"AU",
    "sg:address":"34 Harvest Crt",
    "sg:city":"Southport",
    "sg:classifiers":[
        {
            "category":"Shopping",
            "subcategory":"Bicycles & Sporting Goods",
            "type":"Retail Goods"
        }
    ],
    "sg:phone":"+61 7 5591 1040",
    "sg:postcode":"4215",
    "sg:province":"QLD",
    "sg:tags":[
        "chemical",
        "equipment",
        "pool",
        "swimming"
    ],
    "wof:name":"Splash Pool Shop",
    "wof:placetype":"venue"
},
  "geometry": {"coordinates":[153.40855407699999,-27.9785327911],"type":"Point"}
}