{
  "type": "Feature",
  "properties": {
    "addr:full":"Factory 2/ 9 The Concourse Cowes VIC 3922",
    "addr:housenumber":"/ 9",
    "addr:postcode":"3922",
    "addr:street":"The Concourse",
    "iso:country":"AU",
    "sg:address":"Factory 2/ 9",
    "sg:city":"The Concourse Cowes",
    "sg:classifiers":[
        {
            "category":"Home & Garden",
            "subcategory":"Carpets & Floor Coverings",
            "type":"Retail Goods"
        }
    ],
    "sg:phone":"+61 3 5952 6377",
    "sg:postcode":"3922",
    "sg:province":"VIC",
    "sg:tags":[
        "wood"
    ],
    "wof:name":"Island Carpets & Vinyl",
    "wof:placetype":"venue"
},
  "geometry": {"coordinates":[145.250564575,-38.4567604065],"type":"Point"}
}