{
  "type": "Feature",
  "properties": {
    "addr:full":"31 Wests Rd Maribyrnong VIC 3032",
    "addr:housenumber":"31",
    "addr:postcode":"3032",
    "addr:street":"Wests Rd",
    "iso:country":"AU",
    "sg:address":"31 Wests Rd",
    "sg:city":"Maribyrnong",
    "sg:classifiers":[
        {
            "category":"Social Services",
            "subcategory":"Adult Care",
            "type":"Services"
        }
    ],
    "sg:phone":"+61 3 9318 8700",
    "sg:postcode":"3032",
    "sg:province":"VIC",
    "sg:tags":[
        "aged"
    ],
    "wof:name":"Wyngate Care",
    "wof:placetype":"venue"
},
  "geometry": {"coordinates":[144.88136299999999,-37.772995],"type":"Point"}
}