{
  "type": "Feature",
  "properties": {
    "iso:country":"AU",
    "sg:address":"35 Granada Pde",
    "sg:city":"Alstonville",
    "sg:classifiers":[
        {
            "category":"Building & Trades",
            "subcategory":"Plumbing",
            "type":"Services"
        }
    ],
    "sg:phone":"+61 2 6628 5064",
    "sg:postcode":"2477",
    "sg:province":"NSW",
    "sg:tags":[
        "plumber",
        "gasfitters"
    ],
    "wof:name":"Grant Wannan Plumbing",
    "wof:placetype":"venue"
},
  "geometry": {"coordinates":[153.45463562,-28.8425045013],"type":"Point"}
}