{
  "type": "Feature",
  "properties": {
    "iso:country":"AU",
    "sg:address":"Burleigh Office Park Office 5 Lvl 1 5 Executive Drv",
    "sg:city":"Burleigh Heads",
    "sg:classifiers":[
        {
            "category":"Insurance",
            "subcategory":"Insurance Agent",
            "type":"Services"
        }
    ],
    "sg:phone":"+61 7 5593 7473",
    "sg:postcode":"4220",
    "sg:province":"QLD",
    "sg:tags":[
        "broker"
    ],
    "sg:website":"http://www.genesisbro.com.au",
    "wof:name":"Genesis Insurance Brokers Australia",
    "wof:placetype":"venue"
},
  "geometry": {"coordinates":[153.423294067,-28.0990982056],"type":"Point"}
}