{
  "type": "Feature",
  "properties": {
    "addr:full":"Cnr Bannister & South Rds Canning Vale WA 6155",
    "addr:postcode":"6155",
    "addr:street":"Cnr",
    "iso:country":"AU",
    "sg:address":"Cnr Bannister & South Rds",
    "sg:city":"Canning Vale",
    "sg:classifiers":[
        {
            "category":"Banks & Credit Unions",
            "subcategory":"Bank",
            "type":"Services"
        }
    ],
    "sg:phone":"+61 13 20 32",
    "sg:postcode":"6155",
    "sg:province":"WA",
    "wof:name":"Westpac",
    "wof:placetype":"venue"
},
  "geometry": {"coordinates":[115.92858099999999,-32.080261],"type":"Point"}
}