{
  "type": "Feature",
  "properties": {
    "addr:full":"Mona Rd Edgecliff NSW 2027",
    "addr:postcode":"2027",
    "addr:street":"Mona Rd",
    "iso:country":"AU",
    "sg:address":"Mona Rd",
    "sg:city":"Edgecliff",
    "sg:classifiers":[
        {
            "category":"Retail",
            "subcategory":"Storage",
            "type":"Services"
        }
    ],
    "sg:phone":"+61 406 687 315",
    "sg:postcode":"2027",
    "sg:province":"NSW",
    "sg:tags":[
        "removal",
        "furniture"
    ],
    "wof:name":"Yahn Niczyporczyk",
    "wof:placetype":"venue"
},
  "geometry": {"coordinates":[151.23387145999999,-33.8769950867],"type":"Point"}
}