{
  "type": "Feature",
  "properties": {
    "addr:full":"Cnr Jensen & Hewitt Sts Colyton NSW 2760",
    "addr:postcode":"2760",
    "iso:country":"AU",
    "sg:address":"Cnr Jensen & Hewitt Sts",
    "sg:city":"Colyton",
    "sg:classifiers":[
        {
            "category":"Health Services",
            "subcategory":"Dentist",
            "type":"Services"
        }
    ],
    "sg:phone":"+61 2 9623 6726",
    "sg:postcode":"2760",
    "sg:province":"NSW",
    "wof:name":"Kah K Dr",
    "wof:placetype":"venue"
},
  "geometry": {"coordinates":[150.80023193400001,-33.7854919434],"type":"Point"}
}