{
  "type": "Feature",
  "properties": {
    "addr:full":"U4/ 416 The Entrance Rd Long Jetty NSW 2261",
    "addr:housenumber":"416",
    "addr:postcode":"2261",
    "addr:street":"U4 /;The Entrance Rd",
    "iso:country":"AU",
    "sg:address":"U4/ 416 The Entrance Rd",
    "sg:city":"Long Jetty",
    "sg:classifiers":[
        {
            "category":"Shopping",
            "subcategory":"Bicycles & Sporting Goods",
            "type":"Retail Goods"
        }
    ],
    "sg:phone":"+61 2 4332 6489",
    "sg:postcode":"2261",
    "sg:province":"NSW",
    "sg:tags":[
        "chemical",
        "equipment",
        "pool",
        "swimming"
    ],
    "wof:name":"Jetty Pool Shop",
    "wof:placetype":"venue"
},
  "geometry": {"coordinates":[151.48048399999999,-33.36235],"type":"Point"}
}