{
  "type": "Feature",
  "properties": {
    "iso:country":"AU",
    "sg:address":"6 Hardware St",
    "sg:city":"Melbourne",
    "sg:classifiers":[
        {
            "category":"Shopping",
            "subcategory":"Jewelry",
            "type":"Retail Goods"
        }
    ],
    "sg:phone":"+61 3 9670 8282",
    "sg:postcode":"3000",
    "sg:province":"VIC",
    "sg:tags":[
        "jeweller"
    ],
    "wof:name":"Bradley Gary",
    "wof:placetype":"venue"
},
  "geometry": {"coordinates":[144.96058654800001,-37.812210083],"type":"Point"}
}