{
  "type": "Feature",
  "properties": {
    "addr:full":"112 Jerrold St Sherwood QLD 4075",
    "addr:housenumber":"112",
    "addr:postcode":"4075",
    "addr:street":"Jerrold St",
    "iso:country":"AU",
    "sg:address":"112 Jerrold St",
    "sg:city":"Sherwood",
    "sg:classifiers":[
        {
            "category":"Home & Garden",
            "subcategory":"Building Materials",
            "type":"Retail Goods"
        }
    ],
    "sg:phone":"+61 7 3278 2922",
    "sg:postcode":"4075",
    "sg:province":"QLD",
    "sg:tags":[
        "merchant",
        "glass",
        "glazier"
    ],
    "wof:name":"All Type Glass & Commercial Pty Ltd",
    "wof:placetype":"venue"
},
  "geometry": {"coordinates":[152.98739624000001,-27.5332565308],"type":"Point"}
}