{
  "type": "Feature",
  "properties": {
    "iso:country":"AU",
    "sg:address":"20 Marco Ave",
    "sg:city":"Revesby",
    "sg:classifiers":[
        {
            "category":"Food & Beverages",
            "subcategory":"Bakery",
            "type":"Retail Goods"
        }
    ],
    "sg:phone":"+61 2 9771 2753",
    "sg:postcode":"2212",
    "sg:province":"NSW",
    "sg:tags":[
        "baker"
    ],
    "wof:name":"Eiffel Hot Bread Shop",
    "wof:placetype":"venue"
},
  "geometry": {"coordinates":[151.016556,-33.951714],"type":"Point"}
}