{
  "type": "Feature",
  "properties": {
    "addr:full":"229 Macquarie St Sydney NSW 2000",
    "addr:housenumber":"229",
    "addr:postcode":"2000",
    "addr:street":"Macquarie St",
    "iso:country":"AU",
    "sg:address":"229 Macquarie St",
    "sg:city":"Sydney",
    "sg:classifiers":[
        {
            "category":"Health Services",
            "subcategory":"Dentist",
            "type":"Services"
        }
    ],
    "sg:phone":"+61 2 9232 1718",
    "sg:postcode":"2000",
    "sg:province":"NSW",
    "wof:name":"Godfrey E",
    "wof:placetype":"venue"
},
  "geometry": {"coordinates":[151.21191406200001,-33.8690109253],"type":"Point"}
}