{
  "type": "Feature",
  "properties": {
    "iso:country":"AU",
    "sg:address":"16 Cowper St",
    "sg:city":"Granville",
    "sg:classifiers":[
        {
            "category":"Utilities",
            "subcategory":"Mobile Phone",
            "type":"Services"
        }
    ],
    "sg:phone":"+61 2 9637 7000",
    "sg:postcode":"2142",
    "sg:province":"NSW",
    "sg:tags":[
        "assembly",
        "part",
        "electronic"
    ],
    "wof:name":"Qualitec Ltd.",
    "wof:placetype":"venue"
},
  "geometry": {"coordinates":[151.014328003,-33.8325004578],"type":"Point"}
}