{
  "type": "Feature",
  "properties": {
    "addr:full":"97 Main St Mornington VIC 3931",
    "addr:housenumber":"97",
    "addr:postcode":"3931",
    "addr:street":"Main St",
    "iso:country":"AU",
    "sg:address":"97 Main St",
    "sg:city":"Mornington",
    "sg:classifiers":[
        {
            "category":"Shopping",
            "subcategory":"Stationery & Office Supplies",
            "type":"Retail Goods"
        }
    ],
    "sg:phone":"+61 3 5975 8200",
    "sg:postcode":"3931",
    "sg:province":"VIC",
    "wof:name":"Mornington Officesmart",
    "wof:placetype":"venue"
},
  "geometry": {"coordinates":[145.03851318400001,-38.2196998596],"type":"Point"}
}