{
  "type": "Feature",
  "properties": {
    "addr:full":"22 Essington St Mitchell ACT 2911",
    "addr:housenumber":"22",
    "addr:postcode":"2911",
    "addr:street":"Essington St",
    "iso:country":"AU",
    "sg:address":"22 Essington St",
    "sg:city":"Mitchell",
    "sg:classifiers":[
        {
            "category":"Home & Garden",
            "subcategory":"Carpets & Floor Coverings",
            "type":"Retail Goods"
        }
    ],
    "sg:phone":"+61 2 6162 3080",
    "sg:postcode":"2911",
    "sg:province":"ACT",
    "sg:tags":[
        "tile",
        "wall"
    ],
    "wof:name":"Tile Flair",
    "wof:placetype":"venue"
},
  "geometry": {"coordinates":[149.141647339,-35.2129478455],"type":"Point"}
}