{
  "type": "Feature",
  "properties": {
    "iso:country":"AU",
    "sg:address":"419 Dorans Rd",
    "sg:city":"Sandford",
    "sg:classifiers":[
        {
            "category":"Building & Trades",
            "subcategory":"Plumbing",
            "type":"Services"
        }
    ],
    "sg:phone":"+61 412 521 911",
    "sg:postcode":"7020",
    "sg:province":"TAS",
    "sg:tags":[
        "plumber",
        "gasfitters"
    ],
    "wof:name":"Glover Plumbing Pty Ltd",
    "wof:placetype":"venue"
},
  "geometry": {"coordinates":[147.466033936,-42.9270553589],"type":"Point"}
}