{
  "type": "Feature",
  "properties": {
    "iso:country":"AU",
    "sg:address":"PO Box 2022",
    "sg:city":"Kelvin Grove",
    "sg:classifiers":[
        {
            "category":"Personal",
            "subcategory":"Beauty Salon",
            "type":"Services"
        }
    ],
    "sg:phone":"+61 401 800 442",
    "sg:postcode":"4059",
    "sg:province":"QLD",
    "sg:tags":[
        "hairdresser"
    ],
    "wof:name":"Dr Dread Hair NET",
    "wof:placetype":"venue"
},
  "geometry": {"coordinates":[153.009307861,-27.4453601837],"type":"Point"}
}