{
  "type": "Feature",
  "properties": {
    "iso:country":"AU",
    "sg:address":"Shp1/ 36-38 Hanson Rd",
    "sg:city":"Woodville Gardens",
    "sg:classifiers":[
        {
            "category":"Restaurant",
            "type":"Food & Drink"
        }
    ],
    "sg:phone":"+61 8 8243 1288",
    "sg:postcode":"5012",
    "sg:province":"SA",
    "wof:name":"Dang Quan Restaraunt",
    "wof:placetype":"venue"
},
  "geometry": {"coordinates":[138.54818725600001,-34.8694572449],"type":"Point"}
}