{
  "type": "Feature",
  "properties": {
    "addr:full":"Unit 1/ 123 Keen St Lismore NSW 2480",
    "addr:housenumber":"/ 123",
    "addr:postcode":"2480",
    "addr:street":"Keen St",
    "iso:country":"AU",
    "sg:address":"Unit 1/ 123 Keen St",
    "sg:city":"Lismore",
    "sg:classifiers":[
        {
            "category":"Professional",
            "subcategory":"Art Services",
            "type":"Services"
        }
    ],
    "sg:phone":"+61 2 6622 2646",
    "sg:postcode":"2480",
    "sg:province":"NSW",
    "sg:tags":[
        "interior",
        "decorator"
    ],
    "wof:name":"Marina Cavalieri Textile Design & Decor",
    "wof:placetype":"venue"
},
  "geometry": {"coordinates":[153.27832031200001,-28.8095092773],"type":"Point"}
}