{
  "type": "Feature",
  "properties": {
    "addr:full":"1175 Logan Rd Holland Park QLD 4121",
    "addr:housenumber":"1175",
    "addr:postcode":"4121",
    "addr:street":"Logan Rd",
    "iso:country":"AU",
    "sg:address":"1175 Logan Rd",
    "sg:city":"Holland Park",
    "sg:classifiers":[
        {
            "category":"Health Services",
            "subcategory":"Health Practitioner",
            "type":"Services"
        }
    ],
    "sg:phone":"+61 7 3349 8353",
    "sg:postcode":"4121",
    "sg:province":"QLD",
    "sg:tags":[
        "hypnotherapy"
    ],
    "wof:name":"The Park Health & Wellbeing Clinic",
    "wof:placetype":"venue"
},
  "geometry": {"coordinates":[153.07078552199999,-27.5287055969],"type":"Point"}
}