{
  "type": "Feature",
  "properties": {
    "iso:country":"AU",
    "sg:address":"15 Enterprise Crt",
    "sg:city":"Lonsdale",
    "sg:classifiers":[
        {
            "category":"Home & Garden",
            "subcategory":"Garden Supply",
            "type":"Retail Goods"
        }
    ],
    "sg:phone":"+61 421 699 641",
    "sg:postcode":"5160",
    "sg:province":"SA",
    "sg:tags":[
        "equipment"
    ],
    "wof:name":"Cutting Edge Horticulture",
    "wof:placetype":"venue"
},
  "geometry": {"coordinates":[138.49180602999999,-35.12109375],"type":"Point"}
}