{
  "type": "Feature",
  "properties": {
    "iso:country":"AU",
    "sg:address":"119 Wright St",
    "sg:city":"East Devonport",
    "sg:classifiers":[
        {
            "category":"Freight",
            "type":"Transportation"
        }
    ],
    "sg:phone":"+61 3 6427 0538",
    "sg:postcode":"7310",
    "sg:province":"TAS",
    "sg:tags":[
        "car",
        "carrier",
        "transporting"
    ],
    "wof:name":"Auto Trans Express (Aust) Pty. Ltd.",
    "wof:placetype":"venue"
},
  "geometry": {"coordinates":[146.369338989,-41.1845970154],"type":"Point"}
}