{
  "type": "Feature",
  "properties": {
    "addr:full":"196 Ontario Ave Mildura VIC 3500",
    "addr:housenumber":"196",
    "addr:postcode":"3500",
    "addr:street":"Ontario Ave",
    "iso:country":"AU",
    "sg:address":"196 Ontario Ave",
    "sg:city":"Mildura",
    "sg:classifiers":[
        {
            "category":"Health Services",
            "subcategory":"Doctor",
            "type":"Services"
        }
    ],
    "sg:phone":"+61 3 5023 7311",
    "sg:postcode":"3500",
    "sg:province":"VIC",
    "sg:tags":[
        "medical",
        "practitioner"
    ],
    "wof:name":"Ontario Medical Clinic Pty Ltd",
    "wof:placetype":"venue"
},
  "geometry": {"coordinates":[142.14421081500001,-34.1840515137],"type":"Point"}
}