{
  "type": "Feature",
  "properties": {
    "iso:country":"AU",
    "sg:address":"20 Boronia Ave",
    "sg:city":"Daisy Hill",
    "sg:classifiers":[
        {
            "category":"Home & Garden",
            "subcategory":"Carpets & Floor Coverings",
            "type":"Retail Goods"
        }
    ],
    "sg:phone":"+61 404 381 624",
    "sg:postcode":"4127",
    "sg:province":"QLD",
    "sg:tags":[
        "tile",
        "wall",
        "layer"
    ],
    "wof:name":"Power Tiling Brisbane",
    "wof:placetype":"venue"
},
  "geometry": {"coordinates":[153.14744567899999,-27.6430492401],"type":"Point"}
}