{
  "type": "Feature",
  "properties": {
    "addr:full":"406 Nepean Hwy Chelsea VIC 3196",
    "addr:housenumber":"406",
    "addr:postcode":"3196",
    "addr:street":"Nepean Hwy",
    "iso:country":"AU",
    "sg:address":"406 Nepean Hwy",
    "sg:city":"Chelsea",
    "sg:classifiers":[
        {
            "category":"Real Estate",
            "subcategory":"Real Estate Agent",
            "type":"Services"
        }
    ],
    "sg:phone":"+61 3 9707 8800",
    "sg:postcode":"3196",
    "sg:province":"VIC",
    "wof:name":"Stockdale & Leggo Pty Ltd",
    "wof:placetype":"venue"
},
  "geometry": {"coordinates":[145.11640930199999,-38.0536117554],"type":"Point"}
}