{
  "type": "Feature",
  "properties": {
    "iso:country":"AU",
    "sg:address":"PO Box 1126",
    "sg:city":"Tewantin",
    "sg:classifiers":[
        {
            "category":"Building & Trades",
            "subcategory":"Construction",
            "type":"Services"
        }
    ],
    "sg:phone":"+61 7 5473 0920",
    "sg:postcode":"4565",
    "sg:province":"QLD",
    "sg:tags":[
        "contractor"
    ],
    "wof:name":"CAS Constructions",
    "wof:placetype":"venue"
},
  "geometry": {"coordinates":[153.02789306599999,-26.3908996582],"type":"Point"}
}