{
  "type": "Feature",
  "properties": {
    "iso:country":"AU",
    "sg:address":"42 Gordon St",
    "sg:city":"Naracoorte",
    "sg:classifiers":[
        {
            "category":"Professional",
            "type":"Services"
        }
    ],
    "sg:phone":"+61 8 8762 0620",
    "sg:postcode":"5271",
    "sg:province":"SA",
    "sg:tags":[
        "shop",
        "fitting"
    ],
    "wof:name":"Hill PC & SC",
    "wof:placetype":"venue"
},
  "geometry": {"coordinates":[140.742477,-36.959579],"type":"Point"}
}