{
  "type": "Feature",
  "properties": {
    "addr:full":"4/ 666 Gympie Rd Lawnton QLD 4501",
    "addr:housenumber":"/ 666",
    "addr:postcode":"4501",
    "addr:street":"Gympie Rd",
    "iso:country":"AU",
    "sg:address":"4/ 666 Gympie Rd",
    "sg:city":"Lawnton",
    "sg:classifiers":[
        {
            "category":"Home & Garden",
            "subcategory":"Household Appliances",
            "type":"Retail Goods"
        }
    ],
    "sg:phone":"+61 7 3205 9645",
    "sg:postcode":"4501",
    "sg:province":"QLD",
    "sg:tags":[
        "equipment",
        "gas"
    ],
    "wof:name":"Precision Gas Springs",
    "wof:placetype":"venue"
},
  "geometry": {"coordinates":[152.982543945,-27.2803573608],"type":"Point"}
}