{
  "type": "Feature",
  "properties": {
    "addr:full":"23a Vernon St South Kingsville VIC 3015",
    "addr:housenumber":"23a",
    "addr:postcode":"3015",
    "addr:street":"Vernon St South",
    "iso:country":"AU",
    "sg:address":"23a Vernon St",
    "sg:city":"South Kingsville",
    "sg:classifiers":[
        {
            "category":"Communications",
            "type":"Services"
        }
    ],
    "sg:phone":"+61 3 9391 0899",
    "sg:postcode":"3015",
    "sg:province":"VIC",
    "sg:tags":[
        "translation"
    ],
    "sg:website":"http://www.chrispooletranslation.com.au",
    "wof:name":"Chris Poole Translation",
    "wof:placetype":"venue"
},
  "geometry": {"coordinates":[144.87205505399999,-37.8294448853],"type":"Point"}
}