{
  "type": "Feature",
  "properties": {
    "addr:full":"8 Lucas Crs Ormeau QLD 4208",
    "addr:housenumber":"8",
    "addr:postcode":"4208",
    "addr:street":"Lucas Crs",
    "iso:country":"AU",
    "sg:address":"8 Lucas Crs",
    "sg:city":"Ormeau",
    "sg:classifiers":[
        {
            "category":"Personal",
            "subcategory":"Nail Salon",
            "type":"Services"
        }
    ],
    "sg:phone":"+61 434 351 974",
    "sg:postcode":"4208",
    "sg:province":"QLD",
    "sg:tags":[
        "artificial"
    ],
    "sg:website":"http://www.nailsbybrooke.com.au",
    "wof:name":"Nails by Brooke",
    "wof:placetype":"venue"
},
  "geometry": {"coordinates":[153.244216919,-27.7652397156],"type":"Point"}
}