{
  "type": "Feature",
  "properties": {
    "addr:full":"200 Aumuller St Westcourt QLD 4870",
    "addr:housenumber":"200",
    "addr:postcode":"4870",
    "addr:street":"Aumuller St",
    "iso:country":"AU",
    "sg:address":"200 Aumuller St",
    "sg:city":"Westcourt",
    "sg:classifiers":[
        {
            "category":"Travel",
            "subcategory":"Hotels & Motels",
            "type":"Entertainment"
        }
    ],
    "sg:phone":"+61 7 4051 3277",
    "sg:postcode":"4870",
    "sg:province":"QLD",
    "wof:name":"Westcourt Tavern",
    "wof:placetype":"venue"
},
  "geometry": {"coordinates":[145.75840759299999,-16.9301357269],"type":"Point"}
}