{
  "type": "Feature",
  "properties": {
    "addr:full":"Daniels St Emerald QLD 4720",
    "addr:postcode":"4720",
    "addr:street":"Daniels St",
    "iso:country":"AU",
    "sg:address":"Daniels St",
    "sg:city":"Emerald",
    "sg:classifiers":[
        {
            "category":"Commercial Area",
            "type":"Public Place"
        }
    ],
    "sg:phone":"+61 7 4982 1966",
    "sg:postcode":"4720",
    "sg:province":"QLD",
    "sg:tags":[
        "heavy",
        "carrier"
    ],
    "wof:name":"Emerald Carrying Co",
    "wof:placetype":"venue"
},
  "geometry": {"coordinates":[148.14913899999999,-23.525028],"type":"Point"}
}