{
  "type": "Feature",
  "properties": {
    "addr:full":"1259 Main North Rd Para Hills West SA 5096",
    "addr:housenumber":"1259",
    "addr:postcode":"5096",
    "addr:street":"Main North Rd Para Hills West",
    "iso:country":"AU",
    "sg:address":"1259 Main North Rd",
    "sg:city":"Para Hills West",
    "sg:classifiers":[
        {
            "category":"Building & Trades",
            "subcategory":"Equipment Rental",
            "type":"Services"
        }
    ],
    "sg:phone":"+61 8 8349 6111",
    "sg:postcode":"5096",
    "sg:province":"SA",
    "sg:tags":[
        "platform",
        "hire",
        "work",
        "elevating"
    ],
    "wof:name":"Y-Climb Tower Hire",
    "wof:placetype":"venue"
},
  "geometry": {"coordinates":[138.63279724099999,-34.8079490662],"type":"Point"}
}