{
  "type": "Feature",
  "properties": {
    "addr:full":"16 Marion St Bankstown NSW 2200",
    "addr:housenumber":"16",
    "addr:postcode":"2200",
    "addr:street":"Marion St",
    "iso:country":"AU",
    "sg:address":"16 Marion St",
    "sg:city":"Bankstown",
    "sg:classifiers":[
        {
            "category":"Real Estate",
            "subcategory":"Real Estate Agent",
            "type":"Services"
        }
    ],
    "sg:phone":"+61 2 9708 4388",
    "sg:postcode":"2200",
    "sg:province":"NSW",
    "wof:name":"Bankstown City Real Estate",
    "wof:placetype":"venue"
},
  "geometry": {"coordinates":[151.03289799999999,-33.917366],"type":"Point"}
}