{
  "type": "Feature",
  "properties": {
    "addr:full":"79 Walters Drv Forrestfield WA 6058",
    "addr:housenumber":"79",
    "addr:postcode":"6058",
    "addr:street":"Walters Drv",
    "iso:country":"AU",
    "sg:address":"79 Walters Drv",
    "sg:city":"Forrestfield",
    "sg:classifiers":[
        {
            "category":"Building & Trades",
            "subcategory":"Construction",
            "type":"Services"
        }
    ],
    "sg:phone":"+61 8 9358 4755",
    "sg:postcode":"6058",
    "sg:province":"WA",
    "sg:tags":[
        "industrial",
        "commercial",
        "air conditioning"
    ],
    "wof:name":"Bonaire",
    "wof:placetype":"venue"
},
  "geometry": {"coordinates":[115.995758057,-31.9659976959],"type":"Point"}
}