{
  "type": "Feature",
  "properties": {
    "addr:full":"2/ 4 Bonz Pl Seven Hills NSW 2147",
    "addr:housenumber":"/ 4",
    "addr:postcode":"2147",
    "addr:street":"Bonz Pl",
    "iso:country":"AU",
    "sg:address":"2/ 4 Bonz Pl",
    "sg:city":"Seven Hills",
    "sg:classifiers":[
        {
            "category":"Shopping",
            "subcategory":"Party Supplies",
            "type":"Retail Goods"
        }
    ],
    "sg:phone":"+61 2 9674 5800",
    "sg:postcode":"2147",
    "sg:province":"NSW",
    "sg:tags":[
        "equipment",
        "laminating"
    ],
    "wof:name":"Celmac Pty Ltd",
    "wof:placetype":"venue"
},
  "geometry": {"coordinates":[150.95550537099999,-33.7723197937],"type":"Point"}
}