{
  "type": "Feature",
  "properties": {
    "iso:country":"AU",
    "sg:address":"883 Hampton St",
    "sg:city":"Brighton",
    "sg:classifiers":[
        {
            "category":"Health Services",
            "subcategory":"Doctor",
            "type":"Services"
        }
    ],
    "sg:phone":"+61 3 9340 5844",
    "sg:postcode":"3186",
    "sg:province":"VIC",
    "sg:tags":[
        "medical",
        "practitioner"
    ],
    "wof:name":"Read Katrina",
    "wof:placetype":"venue"
},
  "geometry": {"coordinates":[145.00749206500001,-37.909954071],"type":"Point"}
}