{
  "type": "Feature",
  "properties": {
    "addr:full":"L3 530 Collins St Melbourne VIC 3000",
    "addr:housenumber":"530",
    "addr:postcode":"3000",
    "addr:street":"Collins St",
    "iso:country":"AU",
    "sg:address":"L3 530 Collins St",
    "sg:city":"Melbourne",
    "sg:classifiers":[
        {
            "category":"Banks & Credit Unions",
            "subcategory":"Financial Services",
            "type":"Services"
        }
    ],
    "sg:phone":"+61 3 9665 0200",
    "sg:postcode":"3000",
    "sg:province":"VIC",
    "sg:tags":[
        "advisory",
        "planning",
        "retirement"
    ],
    "wof:name":"Trust Company Of Australia Limited",
    "wof:placetype":"venue"
},
  "geometry": {"coordinates":[144.95668029800001,-37.8182106018],"type":"Point"}
}