{
  "type": "Feature",
  "properties": {
    "iso:country":"AU",
    "sg:address":"403 Coolart Rd",
    "sg:city":"Somerville",
    "sg:classifiers":[
        {
            "category":"Building & Trades",
            "subcategory":"Plumbing",
            "type":"Services"
        }
    ],
    "sg:phone":"+61 418 554 328",
    "sg:postcode":"3912",
    "sg:province":"VIC",
    "sg:tags":[
        "plumber",
        "gasfitters"
    ],
    "wof:name":"Kempson Plumbing",
    "wof:placetype":"venue"
},
  "geometry": {"coordinates":[145.15538024899999,-38.2192001343],"type":"Point"}
}