{
  "type": "Feature",
  "properties": {
    "addr:full":"87 Epsom Rd Rosebery NSW 2018",
    "addr:housenumber":"87",
    "addr:postcode":"2018",
    "addr:street":"Epsom Rd",
    "iso:country":"AU",
    "sg:address":"87 Epsom Rd",
    "sg:city":"Rosebery",
    "sg:classifiers":[
        {
            "category":"Retail",
            "subcategory":"Storage",
            "type":"Services"
        }
    ],
    "sg:phone":"+61 2 8345 6000",
    "sg:postcode":"2018",
    "sg:province":"NSW",
    "sg:website":"http://www.storageplus.com.au",
    "wof:name":"Storage Plus",
    "wof:placetype":"venue"
},
  "geometry": {"coordinates":[151.21258544899999,-33.9122924805],"type":"Point"}
}