{
  "type": "Feature",
  "properties": {
    "addr:full":"375 George St Deniliquin NSW 2710",
    "addr:housenumber":"375",
    "addr:postcode":"2710",
    "addr:street":"George St",
    "iso:country":"AU",
    "sg:address":"375 George St",
    "sg:city":"Deniliquin",
    "sg:classifiers":[
        {
            "category":"Professional",
            "subcategory":"Accounting & Tax Preparation",
            "type":"Services"
        }
    ],
    "sg:phone":"+61 3 5881 2939",
    "sg:postcode":"2710",
    "sg:province":"NSW",
    "sg:tags":[
        "consultant",
        "taxation"
    ],
    "wof:name":"H&R Block",
    "wof:placetype":"venue"
},
  "geometry": {"coordinates":[144.962692261,-35.5264091492],"type":"Point"}
}