{
  "type": "Feature",
  "properties": {
    "addr:full":"7 Namatjira Crt Mulgrave VIC 3170",
    "addr:housenumber":"7",
    "addr:postcode":"3170",
    "addr:street":"Namatjira Crt",
    "iso:country":"AU",
    "sg:address":"7 Namatjira Crt",
    "sg:city":"Mulgrave",
    "sg:classifiers":[
        {
            "category":"Utilities",
            "subcategory":"Electric",
            "type":"Services"
        }
    ],
    "sg:phone":"+61 3 9560 4515",
    "sg:postcode":"3170",
    "sg:province":"VIC",
    "sg:tags":[
        "electrical",
        "contractor"
    ],
    "wof:name":"Skysign Electrical Pty Ltd",
    "wof:placetype":"venue"
},
  "geometry": {"coordinates":[145.165252686,-37.9131355286],"type":"Point"}
}