{
  "type": "Feature",
  "properties": {
    "addr:full":"93 Southwell Rd Hall ACT 2618",
    "addr:housenumber":"93",
    "addr:postcode":"2618",
    "addr:street":"Southwell Rd",
    "iso:country":"AU",
    "sg:address":"93 Southwell Rd",
    "sg:city":"Hall",
    "sg:classifiers":[
        {
            "category":"Professional",
            "subcategory":"Detective & Security Services",
            "type":"Services"
        }
    ],
    "sg:phone":"+61 2 6230 2453",
    "sg:postcode":"2618",
    "sg:province":"ACT",
    "sg:tags":[
        "consultant",
        "system"
    ],
    "wof:name":"Torrens Building Software",
    "wof:placetype":"venue"
},
  "geometry": {"coordinates":[149.004196167,-35.1573905945],"type":"Point"}
}