{
  "type": "Feature",
  "properties": {
    "addr:full":"195 Little Collins St Melbourne VIC 3000",
    "addr:housenumber":"195",
    "addr:postcode":"3000",
    "addr:street":"Little Collins St",
    "iso:country":"AU",
    "sg:address":"195 Little Collins St",
    "sg:city":"Melbourne",
    "sg:classifiers":[
        {
            "category":"Personal",
            "subcategory":"Beauty Salon",
            "type":"Services"
        }
    ],
    "sg:phone":"+61 3 9654 9444",
    "sg:postcode":"3000",
    "sg:province":"VIC",
    "sg:tags":[
        "hairdresser"
    ],
    "wof:name":"Toni & Guy Hairdressing Melbourne Georges",
    "wof:placetype":"venue"
},
  "geometry": {"coordinates":[144.96777343799999,-37.8141365051],"type":"Point"}
}