{
  "type": "Feature",
  "properties": {
    "iso:country":"AU",
    "sg:address":"19 Aurora Ave",
    "sg:city":"Queanbeyan",
    "sg:classifiers":[
        {
            "category":"Utilities",
            "subcategory":"Electric",
            "type":"Services"
        }
    ],
    "sg:phone":"+61 2 6297 6044",
    "sg:postcode":"2620",
    "sg:province":"NSW",
    "sg:tags":[
        "electrical",
        "contractor"
    ],
    "wof:name":"Brooks Marchant Ind (ACT) Pty Ltd",
    "wof:placetype":"venue"
},
  "geometry": {"coordinates":[149.245605469,-35.3384590149],"type":"Point"}
}