{
  "type": "Feature",
  "properties": {
    "iso:country":"AU",
    "sg:address":"14 Denman St",
    "sg:city":"Eastwood",
    "sg:classifiers":[
        {
            "category":"Train Station",
            "subcategory":"Rail",
            "type":"Transportation"
        }
    ],
    "sg:phone":"+61 2 9874 8970",
    "sg:postcode":"2122",
    "sg:province":"NSW",
    "sg:tags":[
        "marine",
        "engineer"
    ],
    "wof:name":"Castle Hill Marine Engineering",
    "wof:placetype":"venue"
},
  "geometry": {"coordinates":[151.071166992,-33.7964134216],"type":"Point"}
}