{
  "type": "Feature",
  "properties": {
    "addr:full":"13a Mary St Brighton SA 5048",
    "addr:housenumber":"13a",
    "addr:postcode":"5048",
    "addr:street":"Mary St",
    "iso:country":"AU",
    "sg:address":"13a Mary St",
    "sg:city":"Brighton",
    "sg:classifiers":[
        {
            "category":"Utilities",
            "subcategory":"Electric",
            "type":"Services"
        }
    ],
    "sg:phone":"+61 8 8376 2919",
    "sg:postcode":"5048",
    "sg:province":"SA",
    "sg:tags":[
        "electrical",
        "contractor"
    ],
    "wof:name":"Coastal Power",
    "wof:placetype":"venue"
},
  "geometry": {"coordinates":[138.53517199999999,-35.028641],"type":"Point"}
}