{
  "type": "Feature",
  "properties": {
    "addr:full":"Shop 3/ 23 Mary St Surry Hills NSW 2010",
    "addr:housenumber":"shop 3 / 23",
    "addr:postcode":"2010",
    "addr:street":"Mary St",
    "iso:country":"AU",
    "sg:address":"Shop 3/ 23 Mary St",
    "sg:city":"Surry Hills",
    "sg:classifiers":[
        {
            "category":"Cafe",
            "type":"Food & Drink"
        }
    ],
    "sg:phone":"+61 2 9280 2615",
    "sg:postcode":"2010",
    "sg:province":"NSW",
    "wof:name":"Toast Cafe",
    "wof:placetype":"venue"
},
  "geometry": {"coordinates":[151.20996093799999,-33.8817100525],"type":"Point"}
}