{
  "type": "Feature",
  "properties": {
    "addr:full":"15 French Ave Merredin WA 6415",
    "addr:housenumber":"15",
    "addr:postcode":"6415",
    "addr:street":"French Ave",
    "iso:country":"AU",
    "sg:address":"15 French Ave",
    "sg:city":"Merredin",
    "sg:classifiers":[
        {
            "category":"Organizations",
            "subcategory":"Community Association",
            "type":"Services"
        }
    ],
    "sg:phone":"+61 8 9041 2233",
    "sg:postcode":"6415",
    "sg:province":"WA",
    "sg:tags":[
        "club",
        "senior",
        "citizen"
    ],
    "wof:name":"Merredin Senior Centre Inc",
    "wof:placetype":"venue"
},
  "geometry": {"coordinates":[118.277740478,-31.4856185913],"type":"Point"}
}