{
  "type": "Feature",
  "properties": {
    "addr:full":"153 Burgundy St Heidelberg VIC 3084",
    "addr:housenumber":"153",
    "addr:postcode":"3084",
    "addr:street":"Burgundy St",
    "iso:country":"AU",
    "sg:address":"153 Burgundy St",
    "sg:city":"Heidelberg",
    "sg:classifiers":[
        {
            "category":"Health Services",
            "subcategory":"Optometrist",
            "type":"Services"
        }
    ],
    "sg:phone":"+61 3 9458 5777",
    "sg:postcode":"3084",
    "sg:province":"VIC",
    "wof:name":"Heidelberg Optical",
    "wof:placetype":"venue"
},
  "geometry": {"coordinates":[145.06495666500001,-37.756149292],"type":"Point"}
}