{
  "type": "Feature",
  "properties": {
    "addr:full":"15 Dalrymple Drv Gladstone QLD 4680",
    "addr:housenumber":"15",
    "addr:postcode":"4680",
    "addr:street":"Dalrymple Drv",
    "iso:country":"AU",
    "sg:address":"15 Dalrymple Drv",
    "sg:city":"Gladstone",
    "sg:classifiers":[
        {
            "category":"Professional",
            "type":"Services"
        }
    ],
    "sg:phone":"+61 7 4979 1480",
    "sg:postcode":"4680",
    "sg:province":"QLD",
    "sg:tags":[
        "transport"
    ],
    "wof:name":"A & G Carriers",
    "wof:placetype":"venue"
},
  "geometry": {"coordinates":[151.270355225,-23.8819446564],"type":"Point"}
}