{
  "type": "Feature",
  "properties": {
    "addr:full":"3 Avon Pl Duffy ACT 2611",
    "addr:housenumber":"3",
    "addr:postcode":"2611",
    "addr:street":"Avon Pl",
    "iso:country":"AU",
    "sg:address":"3 Avon Pl",
    "sg:city":"Duffy",
    "sg:classifiers":[
        {
            "category":"Personal",
            "subcategory":"Massage",
            "type":"Services"
        }
    ],
    "sg:phone":"+61 2 6288 0118",
    "sg:postcode":"2611",
    "sg:province":"ACT",
    "sg:tags":[
        "therapy"
    ],
    "wof:name":"Karen Cheong Remedial Therapy",
    "wof:placetype":"venue"
},
  "geometry": {"coordinates":[149.028686523,-35.3335418701],"type":"Point"}
}