{
  "type": "Feature",
  "properties": {
    "addr:full":"4 Wahroonga Drv Tamworth NSW 2340",
    "addr:housenumber":"4",
    "addr:postcode":"2340",
    "addr:street":"Wahroonga Drv",
    "iso:country":"AU",
    "sg:address":"4 Wahroonga Drv",
    "sg:city":"Tamworth",
    "sg:classifiers":[
        {
            "category":"Manufacturing",
            "subcategory":"Motor Vehicles & Parts",
            "type":"Manufacturing & Wholesale Goods"
        }
    ],
    "sg:phone":"+61 2 6762 8604",
    "sg:postcode":"2340",
    "sg:province":"NSW",
    "sg:tags":[
        "engine",
        "equipment",
        "diesel"
    ],
    "wof:name":"VM Motori",
    "wof:placetype":"venue"
},
  "geometry": {"coordinates":[150.903442383,-31.1212902069],"type":"Point"}
}