{
  "type": "Feature",
  "properties": {
    "addr:full":"300 Nelson Rd Darlington WA 6070",
    "addr:housenumber":"300",
    "addr:postcode":"6070",
    "addr:street":"Nelson Rd",
    "iso:country":"AU",
    "sg:address":"300 Nelson Rd",
    "sg:city":"Darlington",
    "sg:classifiers":[
        {
            "category":"Social Services",
            "subcategory":"Retirement Home",
            "type":"Services"
        }
    ],
    "sg:phone":"+61 8 9299 7837",
    "sg:postcode":"6070",
    "sg:province":"WA",
    "sg:tags":[
        "environmental",
        "consultant",
        "pollution"
    ],
    "wof:name":"Greg Barrett & Associates",
    "wof:placetype":"venue"
},
  "geometry": {"coordinates":[116.092590332,-31.9215717316],"type":"Point"}
}