{
  "type": "Feature",
  "properties": {
    "addr:full":"PO Box 277 Northgate QLD 4013",
    "addr:postcode":"4013",
    "iso:country":"AU",
    "sg:address":"PO Box 277",
    "sg:city":"Northgate",
    "sg:classifiers":[
        {
            "category":"Building & Trades",
            "subcategory":"Plumbing",
            "type":"Services"
        }
    ],
    "sg:phone":"+61 7 3861 5992",
    "sg:postcode":"4013",
    "sg:province":"QLD",
    "sg:tags":[
        "plumber",
        "gasfitters"
    ],
    "wof:name":"Sands Plumbing Darren",
    "wof:placetype":"venue"
},
  "geometry": {"coordinates":[153.07354736299999,-27.3899993896],"type":"Point"}
}