{
  "type": "Feature",
  "properties": {
    "iso:country":"AU",
    "sg:address":"344 Crown St",
    "sg:city":"Wollongong",
    "sg:classifiers":[
        {
            "category":"Real Estate",
            "subcategory":"Architect",
            "type":"Services"
        }
    ],
    "sg:phone":"+61 2 4229 8933",
    "sg:postcode":"2500",
    "sg:province":"NSW",
    "wof:name":"Whitehead Fred Architect",
    "wof:placetype":"venue"
},
  "geometry": {"coordinates":[150.880997,-34.425945],"type":"Point"}
}