{
  "type": "Feature",
  "properties": {
    "iso:country":"AU",
    "sg:address":"22 Wogolin Rd",
    "sg:city":"Wickepin",
    "sg:classifiers":[
        {
            "category":"Shopping",
            "type":"Retail Goods"
        }
    ],
    "sg:phone":"+61 8 9888 1016",
    "sg:postcode":"6370",
    "sg:province":"WA",
    "sg:tags":[
        "agent",
        "stock"
    ],
    "wof:name":"Elders Limited",
    "wof:placetype":"venue"
},
  "geometry": {"coordinates":[117.49781,-32.781673],"type":"Point"}
}