{
  "type": "Feature",
  "properties": {
    "addr:full":"Victoria St Peterborough SA 5422",
    "addr:postcode":"5422",
    "addr:street":"Victoria St",
    "iso:country":"AU",
    "sg:address":"Victoria St",
    "sg:city":"Peterborough",
    "sg:classifiers":[
        {
            "category":"Health Services",
            "subcategory":"Dentist",
            "type":"Services"
        }
    ],
    "sg:phone":"+61 8 8651 2736",
    "sg:postcode":"5422",
    "sg:province":"SA",
    "wof:name":"Dental-S.A. Dental Service",
    "wof:placetype":"venue"
},
  "geometry": {"coordinates":[138.84051513700001,-32.9730415344],"type":"Point"}
}