{
  "type": "Feature",
  "properties": {
    "addr:full":"31 Station Rd Indooroopilly QLD 4068",
    "addr:housenumber":"31",
    "addr:postcode":"4068",
    "addr:street":"Station Rd",
    "iso:country":"AU",
    "sg:address":"31 Station Rd",
    "sg:city":"Indooroopilly",
    "sg:classifiers":[
        {
            "category":"Shopping",
            "subcategory":"Computers & Home Electronics",
            "type":"Retail Goods"
        }
    ],
    "sg:phone":"+61 7 3878 3018",
    "sg:postcode":"4068",
    "sg:province":"QLD",
    "sg:tags":[
        "hardware",
        "equipment"
    ],
    "wof:name":"A Save-On Computers Pty Ltd",
    "wof:placetype":"venue"
},
  "geometry": {"coordinates":[152.973953247,-27.5018196106],"type":"Point"}
}