{
  "type": "Feature",
  "properties": {
    "addr:full":"55 Northmore Crs Winthrop WA 6150",
    "addr:housenumber":"55",
    "addr:postcode":"6150",
    "addr:street":"Northmore Crs",
    "iso:country":"AU",
    "sg:address":"55 Northmore Crs",
    "sg:city":"Winthrop",
    "sg:classifiers":[
        {
            "category":"Professional",
            "subcategory":"Detective & Security Services",
            "type":"Services"
        }
    ],
    "sg:phone":"+61 8 9332 7141",
    "sg:postcode":"6150",
    "sg:province":"WA",
    "sg:tags":[
        "consultant",
        "system"
    ],
    "wof:name":"Meakins Security & Electrics",
    "wof:placetype":"venue"
},
  "geometry": {"coordinates":[115.83300800000001,-32.058788],"type":"Point"}
}