{
  "type": "Feature",
  "properties": {
    "addr:full":"114 Doveton St (South) Ballarat VIC 3350",
    "addr:housenumber":"114",
    "addr:postcode":"3350",
    "addr:street":"Doveton St South",
    "iso:country":"AU",
    "sg:address":"114 Doveton St (South)",
    "sg:city":"Ballarat",
    "sg:classifiers":[
        {
            "category":"Health Services",
            "subcategory":"Health Practitioner",
            "type":"Services"
        }
    ],
    "sg:phone":"+61 437 120 350",
    "sg:postcode":"3350",
    "sg:province":"VIC",
    "sg:tags":[
        "psychologist"
    ],
    "wof:name":"Joanne Fritch Dr",
    "wof:placetype":"venue"
},
  "geometry": {"coordinates":[143.85405,-37.564903],"type":"Point"}
}