{
  "type": "Feature",
  "properties": {
    "iso:country":"AU",
    "sg:address":"1a Johnston St",
    "sg:city":"Dalwallinu",
    "sg:classifiers":[
        {
            "category":"Autos & Motor Vehicles",
            "subcategory":"Auto Supplies",
            "type":"Retail Goods"
        }
    ],
    "sg:phone":"+61 8 9661 1206",
    "sg:postcode":"6609",
    "sg:province":"WA",
    "sg:tags":[
        "tyre"
    ],
    "wof:name":"Dalwallinu Tyre Service & Farm Supplies",
    "wof:placetype":"venue"
},
  "geometry": {"coordinates":[116.66229248,-30.2795333862],"type":"Point"}
}