{
  "type": "Feature",
  "properties": {
    "addr:full":"703 Stafford Rd Everton Park QLD 4053",
    "addr:housenumber":"703",
    "addr:postcode":"4053",
    "addr:street":"Stafford Rd",
    "iso:country":"AU",
    "sg:address":"703 Stafford Rd",
    "sg:city":"Everton Park",
    "sg:classifiers":[
        {
            "category":"Building & Trades",
            "subcategory":"Plumbing",
            "type":"Services"
        }
    ],
    "sg:phone":"+61 7 3355 6635",
    "sg:postcode":"4053",
    "sg:province":"QLD",
    "sg:tags":[
        "drainers"
    ],
    "wof:name":"Brooker Drainage Pty Ltd",
    "wof:placetype":"venue"
},
  "geometry": {"coordinates":[152.99444580100001,-27.4070739746],"type":"Point"}
}