{
  "type": "Feature",
  "properties": {
    "addr:full":"1876 Ipswich Rd Rocklea QLD 4106",
    "addr:housenumber":"1876",
    "addr:postcode":"4106",
    "addr:street":"Ipswich Rd",
    "iso:country":"AU",
    "sg:address":"1876 Ipswich Rd",
    "sg:city":"Rocklea",
    "sg:classifiers":[
        {
            "category":"Building & Trades",
            "subcategory":"Plumbing",
            "type":"Services"
        }
    ],
    "sg:phone":"+61 7 3274 5033",
    "sg:postcode":"4106",
    "sg:province":"QLD",
    "sg:tags":[
        "fitting",
        "hose",
        "supply"
    ],
    "wof:name":"Industrial Hose & Fittings Qld",
    "wof:placetype":"venue"
},
  "geometry": {"coordinates":[152.996994019,-27.561132431],"type":"Point"}
}