{
  "type": "Feature",
  "properties": {
    "addr:full":"12 Cheshire St Wagga Wagga NSW 2650",
    "addr:housenumber":"12",
    "addr:postcode":"2650",
    "addr:street":"Cheshire St",
    "iso:country":"AU",
    "sg:address":"12 Cheshire St",
    "sg:city":"Wagga Wagga",
    "sg:classifiers":[
        {
            "category":"Professional",
            "subcategory":"Testing Lab",
            "type":"Services"
        }
    ],
    "sg:phone":"+61 2 6925 1025",
    "sg:postcode":"2650",
    "sg:province":"NSW",
    "sg:tags":[
        "inspection"
    ],
    "wof:name":"Dial A Micron",
    "wof:placetype":"venue"
},
  "geometry": {"coordinates":[147.34584045400001,-35.1243782043],"type":"Point"}
}