{
  "type": "Feature",
  "properties": {
    "iso:country":"AU",
    "sg:address":"26 Old Pacific Hwy",
    "sg:city":"Newrybar",
    "sg:classifiers":[
        {
            "category":"Wholesale",
            "subcategory":"Machinery & Supplies",
            "type":"Manufacturing & Wholesale Goods"
        }
    ],
    "sg:phone":"+61 2 6687 1537",
    "sg:postcode":"2479",
    "sg:province":"NSW",
    "sg:tags":[
        "equipment",
        "hydraulic"
    ],
    "wof:name":"Bangalow Hydraulics",
    "wof:placetype":"venue"
},
  "geometry": {"coordinates":[153.53112793,-28.7194042206],"type":"Point"}
}