{
  "type": "Feature",
  "properties": {
    "addr:full":"35 Yarra Rd Phillip Bay NSW 2036",
    "addr:housenumber":"35",
    "addr:postcode":"2036",
    "addr:street":"Yarra Rd",
    "iso:country":"AU",
    "sg:address":"35 Yarra Rd",
    "sg:city":"Phillip Bay",
    "sg:classifiers":[
        {
            "category":"Retail",
            "subcategory":"Repair Shop",
            "type":"Services"
        }
    ],
    "sg:phone":"+61 2 9661 6212",
    "sg:postcode":"2036",
    "sg:province":"NSW",
    "sg:tags":[
        "repairing",
        "piano",
        "tuning"
    ],
    "wof:name":"Allen Andersen Jnr",
    "wof:placetype":"venue"
},
  "geometry": {"coordinates":[151.233276367,-33.9802284241],"type":"Point"}
}