{
  "type": "Feature",
  "properties": {
    "iso:country":"AU",
    "sg:address":"41 Berriman Drv",
    "sg:city":"Wangara",
    "sg:classifiers":[
        {
            "category":"Autos & Motor Vehicles",
            "subcategory":"Recreational Vehicle Sales",
            "type":"Retail Goods"
        }
    ],
    "sg:phone":"+61 8 9409 2544",
    "sg:postcode":"6065",
    "sg:province":"WA",
    "sg:tags":[
        "ducting",
        "ductwork"
    ],
    "wof:name":"Metaltech Fabrications",
    "wof:placetype":"venue"
},
  "geometry": {"coordinates":[115.823570252,-31.7934322357],"type":"Point"}
}