{
  "type": "Feature",
  "properties": {
    "iso:country":"AU",
    "sg:address":"Forrestfield Primary School 45 Sussex Rd",
    "sg:city":"Forrestfield",
    "sg:classifiers":[
        {
            "category":"Education",
            "subcategory":"School",
            "type":"Public Place"
        }
    ],
    "sg:phone":"+61 8 9453 6277",
    "sg:postcode":"6058",
    "sg:province":"WA",
    "sg:tags":[
        "state",
        "except",
        "nsw"
    ],
    "wof:name":"Schools Government (Public)",
    "wof:placetype":"venue"
},
  "geometry": {"coordinates":[116.008308411,-31.9905338287],"type":"Point"}
}