{
  "type": "Feature",
  "properties": {
    "addr:full":"4 Yalkuri Drv Nerang QLD 4211",
    "addr:housenumber":"4",
    "addr:postcode":"4211",
    "addr:street":"Yalkuri Drv",
    "iso:country":"AU",
    "sg:address":"4 Yalkuri Drv",
    "sg:city":"Nerang",
    "sg:classifiers":[
        {
            "category":"Building & Trades",
            "subcategory":"Construction",
            "type":"Services"
        }
    ],
    "sg:phone":"+61 412 219 929",
    "sg:postcode":"4211",
    "sg:province":"QLD",
    "sg:tags":[
        "contractor"
    ],
    "wof:name":"Z & B Plasterers",
    "wof:placetype":"venue"
},
  "geometry": {"coordinates":[153.316314697,-27.9920215607],"type":"Point"}
}