{
  "type": "Feature",
  "properties": {
    "iso:country":"AU",
    "sg:address":"1 Izett St",
    "sg:city":"Prahran",
    "sg:classifiers":[
        {
            "category":"Professional",
            "subcategory":"Computer Services",
            "type":"Services"
        }
    ],
    "sg:phone":"+61 3 9521 2188",
    "sg:postcode":"3181",
    "sg:province":"VIC",
    "sg:tags":[
        "package",
        "software"
    ],
    "wof:name":"Double Z Computer Pty Ltd",
    "wof:placetype":"venue"
},
  "geometry": {"coordinates":[144.99177551299999,-37.8491973877],"type":"Point"}
}