{
  "type": "Feature",
  "properties": {
    "addr:full":"12 Robson Rd Hectorville SA 5073",
    "addr:housenumber":"12",
    "addr:postcode":"5073",
    "addr:street":"Robson Rd",
    "iso:country":"AU",
    "sg:address":"12 Robson Rd",
    "sg:city":"Hectorville",
    "sg:classifiers":[
        {
            "category":"Education",
            "subcategory":"School",
            "type":"Public Place"
        }
    ],
    "sg:phone":"+61 8 8337 1411",
    "sg:postcode":"5073",
    "sg:province":"SA",
    "sg:tags":[
        "state",
        "except",
        "nsw"
    ],
    "wof:name":"Newton Primary",
    "wof:placetype":"venue"
},
  "geometry": {"coordinates":[138.667404175,-34.890083313],"type":"Point"}
}