{
  "type": "Feature",
  "properties": {
    "iso:country":"AU",
    "sg:address":"38 Newman Rd",
    "sg:city":"Moorooka",
    "sg:classifiers":[
        {
            "category":"Professional",
            "subcategory":"Employment Agencies",
            "type":"Services"
        }
    ],
    "sg:phone":"+61 417 720 678",
    "sg:postcode":"4105",
    "sg:province":"QLD",
    "sg:tags":[
        "provider",
        "internet"
    ],
    "wof:name":"Netpack",
    "wof:placetype":"venue"
},
  "geometry": {"coordinates":[153.01481628400001,-27.5399246216],"type":"Point"}
}