{
  "type": "Feature",
  "properties": {
    "addr:full":"12 Beach St Bellerive TAS 7018",
    "addr:housenumber":"12",
    "addr:postcode":"7018",
    "addr:street":"Beach St",
    "iso:country":"AU",
    "sg:address":"12 Beach St",
    "sg:city":"Bellerive",
    "sg:classifiers":[
        {
            "category":"Professional",
            "subcategory":"Art Services",
            "type":"Services"
        }
    ],
    "sg:phone":"+61 3 6244 1472",
    "sg:postcode":"7018",
    "sg:province":"TAS",
    "sg:tags":[
        "decorator",
        "painter"
    ],
    "wof:name":"Barwise S C",
    "wof:placetype":"venue"
},
  "geometry": {"coordinates":[147.37562560999999,-42.8768768311],"type":"Point"}
}