{
  "type": "Feature",
  "properties": {
    "iso:country":"AU",
    "sg:address":"Centra Park Lysaght St",
    "sg:city":"Coolum Beach",
    "sg:classifiers":[
        {
            "category":"Manufacturing",
            "subcategory":"Buildings",
            "type":"Manufacturing & Wholesale Goods"
        }
    ],
    "sg:phone":"+61 7 5447 1556",
    "sg:postcode":"4573",
    "sg:province":"QLD",
    "sg:tags":[
        "transportable",
        "domestic",
        "relocatable"
    ],
    "wof:name":"New Image Homes Pty Ltd",
    "wof:placetype":"venue"
},
  "geometry": {"coordinates":[153.061646,-26.520958],"type":"Point"}
}