{
  "type": "Feature",
  "properties": {
    "addr:full":"136 Princes Hwy Ulladulla NSW 2539",
    "addr:housenumber":"136",
    "addr:postcode":"2539",
    "addr:street":"Princes Hwy",
    "iso:country":"AU",
    "sg:address":"136 Princes Hwy",
    "sg:city":"Ulladulla",
    "sg:classifiers":[
        {
            "category":"Professional",
            "subcategory":"Accounting & Tax Preparation",
            "type":"Services"
        }
    ],
    "sg:phone":"+61 2 4455 7066",
    "sg:postcode":"2539",
    "sg:province":"NSW",
    "sg:tags":[
        "consultant",
        "taxation"
    ],
    "wof:name":"Smith Moir & Associates",
    "wof:placetype":"venue"
},
  "geometry": {"coordinates":[150.47364807100001,-35.361076355],"type":"Point"}
}