{
  "type": "Feature",
  "properties": {
    "addr:full":"26 Rowan St Mona Vale NSW 2103",
    "addr:housenumber":"26",
    "addr:postcode":"2103",
    "addr:street":"Rowan St",
    "iso:country":"AU",
    "sg:address":"26 Rowan St",
    "sg:city":"Mona Vale",
    "sg:classifiers":[
        {
            "category":"Building & Trades",
            "subcategory":"Construction",
            "type":"Services"
        }
    ],
    "sg:phone":"+61 2 9999 0393",
    "sg:postcode":"2103",
    "sg:province":"NSW",
    "sg:tags":[
        "contractor"
    ],
    "wof:name":"North Peninsula Constructions Pty Ltd",
    "wof:placetype":"venue"
},
  "geometry": {"coordinates":[151.30030822800001,-33.6823425293],"type":"Point"}
}