{
  "type": "Feature",
  "properties": {
    "addr:full":"32 Firefly St Pelican Waters QLD 4551",
    "addr:housenumber":"32",
    "addr:postcode":"4551",
    "addr:street":"Firefly St",
    "iso:country":"AU",
    "sg:address":"32 Firefly St",
    "sg:city":"Pelican Waters",
    "sg:classifiers":[
        {
            "category":"Insurance",
            "subcategory":"Insurance Agent",
            "type":"Services"
        }
    ],
    "sg:phone":"+61 421 188 979",
    "sg:postcode":"4551",
    "sg:province":"QLD",
    "sg:tags":[
        "broker"
    ],
    "wof:name":"Wealthpath Financial Services",
    "wof:placetype":"venue"
},
  "geometry": {"coordinates":[153.1015625,-26.8313350677],"type":"Point"}
}