{
  "type": "Feature",
  "properties": {
    "iso:country":"AU",
    "sg:address":"Shop 10/ 246 Hay St",
    "sg:city":"East Perth",
    "sg:classifiers":[
        {
            "category":"Food & Beverages",
            "subcategory":"Supermarket",
            "type":"Retail Goods"
        }
    ],
    "sg:phone":"+61 8 9221 0700",
    "sg:postcode":"6004",
    "sg:province":"WA",
    "sg:tags":[
        "grocery",
        "store"
    ],
    "wof:name":"Carlton Fresh",
    "wof:placetype":"venue"
},
  "geometry": {"coordinates":[115.870620727,-31.9578723907],"type":"Point"}
}