{
  "type": "Feature",
  "properties": {
    "addr:full":"4 Pitt St Chatham NSW 2430",
    "addr:housenumber":"4",
    "addr:postcode":"2430",
    "addr:street":"Pitt St",
    "iso:country":"AU",
    "sg:address":"4 Pitt St",
    "sg:city":"Chatham",
    "sg:classifiers":[
        {
            "category":"Wholesale",
            "subcategory":"Seafood",
            "type":"Manufacturing & Wholesale Goods"
        }
    ],
    "sg:phone":"+61 2 6552 1323",
    "sg:postcode":"2430",
    "sg:province":"NSW",
    "sg:tags":[
        "fish"
    ],
    "wof:name":"Taree Fishermen's Co-Op Socy Ltd",
    "wof:placetype":"venue"
},
  "geometry": {"coordinates":[152.47955300000001,-31.904873],"type":"Point"}
}