{
  "type": "Feature",
  "properties": {
    "addr:full":"12 Frawley Crt Tarneit VIC 3029",
    "addr:housenumber":"12",
    "addr:postcode":"3029",
    "addr:street":"Frawley Crt",
    "iso:country":"AU",
    "sg:address":"12 Frawley Crt",
    "sg:city":"Tarneit",
    "sg:classifiers":[
        {
            "category":"Professional",
            "subcategory":"Management & Consulting",
            "type":"Services"
        }
    ],
    "sg:phone":"+61 3 9741 7478",
    "sg:postcode":"3029",
    "sg:province":"VIC",
    "sg:tags":[
        "consultant"
    ],
    "wof:name":"Jed Management Consulting Pty Ltd",
    "wof:placetype":"venue"
},
  "geometry": {"coordinates":[144.658478,-37.869755],"type":"Point"}
}