{
  "type": "Feature",
  "properties": {
    "addr:full":"1/ 78 Ferndell St Granville NSW 2142",
    "addr:housenumber":"/ 78",
    "addr:postcode":"2142",
    "addr:street":"Ferndell St",
    "iso:country":"AU",
    "sg:address":"1/ 78 Ferndell St",
    "sg:city":"Granville",
    "sg:classifiers":[
        {
            "category":"Autos & Motor Vehicles",
            "subcategory":"Auto Supplies",
            "type":"Retail Goods"
        }
    ],
    "sg:phone":"+61 2 9334 8888",
    "sg:postcode":"2142",
    "sg:province":"NSW",
    "sg:tags":[
        "transmission",
        "equipment",
        "power"
    ],
    "wof:name":"Western Electric Australia Pty. Ltd.",
    "wof:placetype":"venue"
},
  "geometry": {"coordinates":[151.007125855,-33.8723487854],"type":"Point"}
}