{
  "type": "Feature",
  "properties": {
    "iso:country":"AU",
    "sg:address":"41 Cascade St",
    "sg:city":"Paddington",
    "sg:classifiers":[
        {
            "category":"Food & Beverages",
            "subcategory":"Supermarket",
            "type":"Retail Goods"
        }
    ],
    "sg:phone":"+61 2 8354 1405",
    "sg:postcode":"2021",
    "sg:province":"NSW",
    "sg:tags":[
        "grocery",
        "store"
    ],
    "wof:name":"Cascade Grocery Supermarket",
    "wof:placetype":"venue"
},
  "geometry": {"coordinates":[151.23211669899999,-33.8822937012],"type":"Point"}
}