{
  "type": "Feature",
  "properties": {
    "addr:full":"Level 2, 2 Holt St Surry Hills NSW 2010",
    "addr:housenumber":"2",
    "addr:postcode":"2010",
    "addr:street":"Holt St",
    "iso:country":"AU",
    "sg:address":"Level 2, 2 Holt St",
    "sg:city":"Surry Hills",
    "sg:classifiers":[
        {
            "category":"Building & Trades",
            "subcategory":"Landscaping Services",
            "type":"Services"
        }
    ],
    "sg:phone":"+61 2 9288 2873",
    "sg:postcode":"2010",
    "sg:province":"NSW",
    "sg:tags":[
        "designer",
        "landscape",
        "contractor"
    ],
    "wof:name":"homesite.com.au",
    "wof:placetype":"venue"
},
  "geometry": {"coordinates":[151.20916748100001,-33.8849182129],"type":"Point"}
}