{
  "type": "Feature",
  "properties": {
    "addr:full":"Katoomba Exchange Katoomba NSW 2780",
    "addr:postcode":"2780",
    "iso:country":"AU",
    "sg:address":"Katoomba Exchange",
    "sg:city":"Katoomba",
    "sg:classifiers":[
        {
            "category":"Cafe",
            "type":"Food & Drink"
        }
    ],
    "sg:phone":"+61 2 4782 2086",
    "sg:postcode":"2780",
    "sg:province":"NSW",
    "wof:name":"Sugar & Spice Cafe",
    "wof:placetype":"venue"
},
  "geometry": {"coordinates":[150.31152343799999,-33.7151947021],"type":"Point"}
}