{
  "type": "Feature",
  "properties": {
    "addr:full":"587B Robinson Rd Aspley QLD 4034",
    "addr:housenumber":"587b",
    "addr:postcode":"4034",
    "addr:street":"Robinson Rd",
    "iso:country":"AU",
    "sg:address":"587B Robinson Rd",
    "sg:city":"Aspley",
    "sg:classifiers":[
        {
            "category":"Personal",
            "subcategory":"Nail Salon",
            "type":"Services"
        }
    ],
    "sg:phone":"+61 7 3263 7416",
    "sg:postcode":"4034",
    "sg:province":"QLD",
    "sg:tags":[
        "artificial"
    ],
    "wof:name":"Illusions Beauty & Nail Centre",
    "wof:placetype":"venue"
},
  "geometry": {"coordinates":[153.025284,-27.364891],"type":"Point"}
}