{
  "type": "Feature",
  "properties": {
    "iso:country":"AU",
    "sg:address":"248 Boorowa St",
    "sg:city":"Young",
    "sg:classifiers":[
        {
            "category":"Wholesale",
            "subcategory":"Home Furnishings",
            "type":"Manufacturing & Wholesale Goods"
        }
    ],
    "sg:phone":"+61 2 6382 6915",
    "sg:postcode":"2594",
    "sg:province":"NSW",
    "sg:tags":[
        "wholesaler",
        "bedding",
        "mfrs",
        "bed"
    ],
    "wof:name":"Terry Bros Furniture & Bedding",
    "wof:placetype":"venue"
},
  "geometry": {"coordinates":[148.285919189,-34.3099060059],"type":"Point"}
}