{
  "type": "Feature",
  "properties": {
    "addr:full":"25 Selby St Adelaide SA 5000",
    "addr:housenumber":"25",
    "addr:postcode":"5000",
    "addr:street":"Selby St",
    "iso:country":"AU",
    "sg:address":"25 Selby St",
    "sg:city":"Adelaide",
    "sg:classifiers":[
        {
            "category":"Shopping",
            "subcategory":"Computers & Home Electronics",
            "type":"Retail Goods"
        }
    ],
    "sg:phone":"+61 8 8231 0175",
    "sg:postcode":"5000",
    "sg:province":"SA",
    "sg:tags":[
        "equipment",
        "multimedia"
    ],
    "wof:name":"Kukan Studio",
    "wof:placetype":"venue"
},
  "geometry": {"coordinates":[138.59277343799999,-34.9318084717],"type":"Point"}
}