{
  "type": "Feature",
  "properties": {
    "addr:full":"421a George St Sydney NSW 2000",
    "addr:housenumber":"421a",
    "addr:postcode":"2000",
    "addr:street":"George St",
    "iso:country":"AU",
    "sg:address":"421a George St",
    "sg:city":"Sydney",
    "sg:classifiers":[
        {
            "category":"Shopping",
            "subcategory":"Computers & Home Electronics",
            "type":"Retail Goods"
        }
    ],
    "sg:phone":"+61 2 9662 0300",
    "sg:postcode":"2000",
    "sg:province":"NSW",
    "sg:tags":[
        "hi-fi",
        "equipment"
    ],
    "wof:name":"HomeZone Retravision",
    "wof:placetype":"venue"
},
  "geometry": {"coordinates":[151.206832886,-33.8705215454],"type":"Point"}
}