{
  "type": "Feature",
  "properties": {
    "addr:full":"33 Prince Edward Ave Culburra Beach NSW 2540",
    "addr:housenumber":"33",
    "addr:postcode":"2540",
    "addr:street":"Prince Edward Ave",
    "iso:country":"AU",
    "sg:address":"33 Prince Edward Ave",
    "sg:city":"Culburra Beach",
    "sg:classifiers":[
        {
            "category":"Building & Trades",
            "subcategory":"Construction",
            "type":"Services"
        }
    ],
    "sg:phone":"+61 2 4447 4902",
    "sg:postcode":"2540",
    "sg:province":"NSW",
    "sg:tags":[
        "plasterboard",
        "plasterer",
        "fixer"
    ],
    "wof:name":"Wayne Steinhour Plasterers",
    "wof:placetype":"venue"
},
  "geometry": {"coordinates":[150.76174926799999,-34.9158363342],"type":"Point"}
}