{
  "type": "Feature",
  "properties": {
    "iso:country":"AU",
    "sg:address":"161 Morgan Ave",
    "sg:city":"Melrose Park",
    "sg:classifiers":[
        {
            "category":"Building & Trades",
            "subcategory":"Construction",
            "type":"Services"
        }
    ],
    "sg:phone":"+61 418 836 988",
    "sg:postcode":"5039",
    "sg:province":"SA",
    "sg:tags":[
        "brick",
        "paving"
    ],
    "wof:name":"Paving By John",
    "wof:placetype":"venue"
},
  "geometry": {"coordinates":[138.57708740199999,-34.9886512756],"type":"Point"}
}