{
  "type": "Feature",
  "properties": {
    "addr:full":"25 Maitland Rd Hexham NSW 2322",
    "addr:housenumber":"25",
    "addr:postcode":"2322",
    "addr:street":"Maitland Rd",
    "iso:country":"AU",
    "sg:address":"25 Maitland Rd",
    "sg:city":"Hexham",
    "sg:classifiers":[
        {
            "category":"Autos & Motor Vehicles",
            "subcategory":"Fuel & Gas Station",
            "type":"Retail Goods"
        }
    ],
    "sg:phone":"+61 2 4964 8305",
    "sg:postcode":"2322",
    "sg:province":"NSW",
    "wof:name":"Hexham Truck Port",
    "wof:placetype":"venue"
},
  "geometry": {"coordinates":[151.569915772,-32.7095947266],"type":"Point"}
}