{
  "type": "Feature",
  "properties": {
    "addr:full":"11 Hayes St Scone NSW 2337",
    "addr:housenumber":"11",
    "addr:postcode":"2337",
    "addr:street":"Hayes St",
    "iso:country":"AU",
    "sg:address":"11 Hayes St",
    "sg:city":"Scone",
    "sg:classifiers":[
        {
            "category":"Professional",
            "subcategory":"Detective & Security Services",
            "type":"Services"
        }
    ],
    "sg:phone":"+61 2 6545 2962",
    "sg:postcode":"2337",
    "sg:province":"NSW",
    "sg:tags":[
        "equipment",
        "window",
        "doors"
    ],
    "wof:name":"Upper Hunter Security Doors & Screens",
    "wof:placetype":"venue"
},
  "geometry": {"coordinates":[150.87057495100001,-32.0420303345],"type":"Point"}
}