{
  "type": "Feature",
  "properties": {
    "iso:country":"AU",
    "sg:address":"Unit 5 24 Poletti Rd",
    "sg:city":"Jandakot",
    "sg:classifiers":[
        {
            "category":"Retail",
            "subcategory":"Auto Repair",
            "type":"Services"
        }
    ],
    "sg:phone":"+61 8 9417 9910",
    "sg:postcode":"6164",
    "sg:province":"WA",
    "sg:tags":[
        "repairer",
        "motor",
        "engineer"
    ],
    "wof:name":"Automotive Specialist The",
    "wof:placetype":"venue"
},
  "geometry": {"coordinates":[115.848221,-32.125229],"type":"Point"}
}