{
  "type": "Feature",
  "properties": {
    "iso:country":"AU",
    "sg:address":"24a/ Gordon Crs",
    "sg:city":"Denistone",
    "sg:classifiers":[
        {
            "category":"Retail",
            "subcategory":"Auto Repair",
            "type":"Services"
        }
    ],
    "sg:phone":"+61 425 225 284",
    "sg:postcode":"2114",
    "sg:province":"NSW",
    "sg:tags":[
        "repairer",
        "motor",
        "engineer"
    ],
    "wof:name":"City Central Mechanical",
    "wof:placetype":"venue"
},
  "geometry": {"coordinates":[151.08833313,-33.7965087891],"type":"Point"}
}