{
  "type": "Feature",
  "properties": {
    "iso:country":"AU",
    "sg:address":"42c Caramut Rd",
    "sg:city":"Warrnambool",
    "sg:classifiers":[
        {
            "category":"Professional",
            "subcategory":"Computer Services",
            "type":"Services"
        }
    ],
    "sg:phone":"+61 3 5562 0700",
    "sg:postcode":"3280",
    "sg:province":"VIC",
    "sg:tags":[
        "package",
        "software"
    ],
    "wof:name":"Accrivia Pty Ltd",
    "wof:placetype":"venue"
},
  "geometry": {"coordinates":[142.49879455600001,-38.3870124817],"type":"Point"}
}