{
  "type": "Feature",
  "properties": {
    "addr:full":"3 Koiyog Rd Wyee NSW 2259",
    "addr:housenumber":"3",
    "addr:postcode":"2259",
    "addr:street":"Koiyog Rd",
    "iso:country":"AU",
    "sg:address":"3 Koiyog Rd",
    "sg:city":"Wyee",
    "sg:classifiers":[
        {
            "category":"Building & Trades",
            "subcategory":"Construction",
            "type":"Services"
        }
    ],
    "sg:phone":"+61 418 435 586",
    "sg:postcode":"2259",
    "sg:province":"NSW",
    "sg:tags":[
        "concrete",
        "contractor"
    ],
    "wof:name":"Harry McKenzie & Partners",
    "wof:placetype":"venue"
},
  "geometry": {"coordinates":[151.49302673299999,-33.1841087341],"type":"Point"}
}