{
  "type": "Feature",
  "properties": {
    "iso:country":"AU",
    "sg:address":"65 George Ave",
    "sg:city":"Whyalla Playford",
    "sg:classifiers":[
        {
            "category":"Education",
            "subcategory":"University",
            "type":"Public Place"
        }
    ],
    "sg:phone":"+61 8 8645 2745",
    "sg:postcode":"5600",
    "sg:province":"SA",
    "sg:tags":[
        "educational",
        "organisation",
        "cultural"
    ],
    "wof:name":"Whyallina Heritage Aboriginal Corporation",
    "wof:placetype":"venue"
},
  "geometry": {"coordinates":[137.540894,-33.01984],"type":"Point"}
}