{
  "type": "Feature",
  "properties": {
    "iso:country":"AU",
    "sg:address":"PO Box 146",
    "sg:city":"Edensor Park",
    "sg:classifiers":[
        {
            "category":"Retail",
            "subcategory":"Auto Rental",
            "type":"Services"
        }
    ],
    "sg:phone":"+61 412 152 230",
    "sg:postcode":"2176",
    "sg:province":"NSW",
    "sg:tags":[
        "car",
        "hire",
        "minibus"
    ],
    "wof:name":"Revline",
    "wof:placetype":"venue"
},
  "geometry": {"coordinates":[150.87254333499999,-33.8778800964],"type":"Point"}
}