{
  "type": "Feature",
  "properties": {
    "addr:full":"143 Chapel St Windsor VIC 3181",
    "addr:housenumber":"143",
    "addr:postcode":"3181",
    "addr:street":"Chapel St",
    "iso:country":"AU",
    "sg:address":"143 Chapel St",
    "sg:city":"Windsor",
    "sg:classifiers":[
        {
            "category":"Shopping",
            "subcategory":"Party Supplies",
            "type":"Retail Goods"
        }
    ],
    "sg:phone":"+61 3 9510 0905",
    "sg:postcode":"3181",
    "sg:province":"VIC",
    "sg:tags":[
        "hire",
        "costume"
    ],
    "wof:name":"Its My World",
    "wof:placetype":"venue"
},
  "geometry": {"coordinates":[144.99298095699999,-37.8530158997],"type":"Point"}
}