{
  "type": "Feature",
  "properties": {
    "iso:country":"AU",
    "sg:address":"Catalina Rd",
    "sg:city":"Marlow Lagoon",
    "sg:classifiers":[
        {
            "category":"Arena",
            "subcategory":"Indoor Arena",
            "type":"Entertainment"
        }
    ],
    "sg:phone":"+61 8 8932 2633",
    "sg:postcode":"0830",
    "sg:province":"NT",
    "sg:tags":[
        "club",
        "angling"
    ],
    "wof:name":"Palmerston Game Fishing Club",
    "wof:placetype":"venue"
},
  "geometry": {"coordinates":[130.95901499999999,-12.504907],"type":"Point"}
}