{
  "type": "Feature",
  "properties": {
    "addr:full":"527 High Street Rd Mt Waverley VIC 3149",
    "addr:housenumber":"527",
    "addr:postcode":"3149",
    "addr:street":"High Street Rd",
    "iso:country":"AU",
    "sg:address":"527 High Street Rd",
    "sg:city":"Mt Waverley",
    "sg:classifiers":[
        {
            "category":"Retail",
            "subcategory":"Veterinary Services",
            "type":"Services"
        }
    ],
    "sg:phone":"+61 3 9802 8392",
    "sg:postcode":"3149",
    "sg:province":"VIC",
    "sg:tags":[
        "surgeon"
    ],
    "wof:name":"High Street Rd Animal Hospital",
    "wof:placetype":"venue"
},
  "geometry": {"coordinates":[145.13856506400001,-37.8708496094],"type":"Point"}
}