{
  "type": "Feature",
  "properties": {
    "iso:country":"AU",
    "sg:address":"1080 Gympie Rd",
    "sg:city":"Chermside",
    "sg:classifiers":[
        {
            "category":"Autos & Motor Vehicles",
            "subcategory":"Fuel & Gas Station",
            "type":"Retail Goods"
        }
    ],
    "sg:phone":"+61 7 3359 4117",
    "sg:postcode":"4032",
    "sg:province":"QLD",
    "wof:name":"Liberty Service Stations",
    "wof:placetype":"venue"
},
  "geometry": {"coordinates":[153.025513,-27.375092],"type":"Point"}
}