{
  "type": "Feature",
  "properties": {
    "addr:full":"RMB 44 Manypeaks North WA 6328",
    "addr:housenumber":"44",
    "addr:postcode":"6328",
    "addr:street":"Manypeaks North",
    "iso:country":"AU",
    "sg:address":"RMB 44",
    "sg:city":"Manypeaks North",
    "sg:classifiers":[
        {
            "category":"Farming",
            "subcategory":"Farm",
            "type":"Manufacturing & Wholesale Goods"
        }
    ],
    "sg:phone":"+61 8 9846 8012",
    "sg:postcode":"6328",
    "sg:province":"WA",
    "sg:tags":[
        "farmer"
    ],
    "wof:name":"Blyth J & R",
    "wof:placetype":"venue"
},
  "geometry": {"coordinates":[118.48104858400001,-34.6237602234],"type":"Point"}
}