{
  "type": "Feature",
  "properties": {
    "addr:full":"70 Waterloo Rd Trafalgar VIC 3824",
    "addr:housenumber":"70",
    "addr:postcode":"3824",
    "addr:street":"Waterloo Rd",
    "iso:country":"AU",
    "sg:address":"70 Waterloo Rd",
    "sg:city":"Trafalgar",
    "sg:classifiers":[
        {
            "category":"Social Services",
            "subcategory":"Adult Care",
            "type":"Services"
        }
    ],
    "sg:phone":"+61 3 5633 1477",
    "sg:postcode":"3824",
    "sg:province":"VIC",
    "sg:tags":[
        "towing"
    ],
    "wof:name":"Trafalgar Panels",
    "wof:placetype":"venue"
},
  "geometry": {"coordinates":[146.153854,-38.206596],"type":"Point"}
}