{
  "type": "Feature",
  "properties": {
    "addr:full":"Berehaven Ave Thornlie WA 6108",
    "addr:postcode":"6108",
    "addr:street":"Berehaven Ave",
    "iso:country":"AU",
    "sg:address":"Berehaven Ave",
    "sg:city":"Thornlie",
    "sg:classifiers":[
        {
            "category":"Arena",
            "subcategory":"Sports Club",
            "type":"Entertainment"
        }
    ],
    "sg:phone":"+61 8 9459 6161",
    "sg:postcode":"6108",
    "sg:province":"WA",
    "sg:tags":[
        "australian",
        "football",
        "rule"
    ],
    "wof:name":"Thornlie Football & Sportsmans Club Inc",
    "wof:placetype":"venue"
},
  "geometry": {"coordinates":[115.95175170900001,-32.0588645935],"type":"Point"}
}