{
  "type": "Feature",
  "properties": {
    "addr:full":"PO Box 257 Redbank QLD 4301",
    "addr:postcode":"4301",
    "iso:country":"AU",
    "sg:address":"PO Box 257",
    "sg:city":"Redbank",
    "sg:classifiers":[
        {
            "category":"Travel",
            "subcategory":"Travel Agent",
            "type":"Entertainment"
        }
    ],
    "sg:phone":"+61 7 3389 0428",
    "sg:postcode":"4301",
    "sg:province":"QLD",
    "sg:tags":[
        "tour",
        "holiday",
        "adventure"
    ],
    "wof:name":"Concorde Coach Charter",
    "wof:placetype":"venue"
},
  "geometry": {"coordinates":[152.86929321299999,-27.6029090881],"type":"Point"}
}