{
  "type": "Feature",
  "properties": {
    "addr:full":"497 Hannan St Kalgoorlie WA 6430",
    "addr:housenumber":"497",
    "addr:postcode":"6430",
    "addr:street":"Hannan St",
    "iso:country":"AU",
    "sg:address":"497 Hannan St",
    "sg:city":"Kalgoorlie",
    "sg:classifiers":[
        {
            "category":"Travel",
            "subcategory":"Hotels & Motels",
            "type":"Entertainment"
        }
    ],
    "sg:phone":"+61 8 9026 3399",
    "sg:postcode":"6430",
    "sg:province":"WA",
    "wof:name":"Kalgoorlie Star & Garter Hotel/Motel",
    "wof:placetype":"venue"
},
  "geometry": {"coordinates":[121.463912964,-30.7555351257],"type":"Point"}
}