{
  "type": "Feature",
  "properties": {
    "addr:full":"4 Lincoln La Joondalup WA 6027",
    "addr:housenumber":"4",
    "addr:postcode":"6027",
    "addr:street":"Lincoln La",
    "iso:country":"AU",
    "sg:address":"4 Lincoln La",
    "sg:city":"Joondalup",
    "sg:classifiers":[
        {
            "category":"Education",
            "subcategory":"Dance Studio",
            "type":"Public Place"
        }
    ],
    "sg:phone":"+61 8 9300 9499",
    "sg:postcode":"6027",
    "sg:province":"WA",
    "sg:tags":[
        "venue",
        "tuition"
    ],
    "wof:name":"Toddle Bop",
    "wof:placetype":"venue"
},
  "geometry": {"coordinates":[115.764297485,-31.7507629395],"type":"Point"}
}