{
  "type": "Feature",
  "properties": {
    "addr:full":"204 Oxley Rd Graceville QLD 4075",
    "addr:housenumber":"204",
    "addr:postcode":"4075",
    "addr:street":"Oxley Rd",
    "iso:country":"AU",
    "sg:address":"204 Oxley Rd",
    "sg:city":"Graceville",
    "sg:classifiers":[
        {
            "category":"Real Estate",
            "subcategory":"Real Estate Agent",
            "type":"Services"
        }
    ],
    "sg:phone":"+61 7 3379 4599",
    "sg:postcode":"4075",
    "sg:province":"QLD",
    "wof:name":"RealWay Property Consultants Graceville",
    "wof:placetype":"venue"
},
  "geometry": {"coordinates":[152.97926330600001,-27.5200939178],"type":"Point"}
}