{
  "type": "Feature",
  "properties": {
    "iso:country":"AU",
    "sg:address":"17 Tardent St",
    "sg:city":"Biggenden",
    "sg:classifiers":[
        {
            "category":"Utilities",
            "type":"Services"
        }
    ],
    "sg:phone":"+61 7 4127 1421",
    "sg:postcode":"4621",
    "sg:province":"QLD",
    "sg:tags":[
        "refrigeration",
        "industrial",
        "commercial",
        "retail"
    ],
    "wof:name":"Day Electrical",
    "wof:placetype":"venue"
},
  "geometry": {"coordinates":[152.040146,-25.512032],"type":"Point"}
}