{
  "type": "Feature",
  "properties": {
    "iso:country":"AU",
    "sg:address":"University Drv",
    "sg:city":"Callaghan",
    "sg:classifiers":[
        {
            "category":"Professional",
            "subcategory":"Engineering",
            "type":"Services"
        }
    ],
    "sg:phone":"+61 2 4962 0912",
    "sg:postcode":"2308",
    "sg:province":"NSW",
    "sg:tags":[
        "electrical",
        "engineer"
    ],
    "wof:name":"Quality Data Australia Pty Ltd",
    "wof:placetype":"venue"
},
  "geometry": {"coordinates":[151.70358300000001,-32.896381],"type":"Point"}
}