{
  "type": "Feature",
  "properties": {
    "iso:country":"AU",
    "sg:address":"Shop 10R/ 33 Moore St",
    "sg:city":"Liverpool",
    "sg:classifiers":[
        {
            "category":"Personal",
            "subcategory":"Beauty Salon",
            "type":"Services"
        }
    ],
    "sg:phone":"+61 2 9601 2160",
    "sg:postcode":"2170",
    "sg:province":"NSW",
    "wof:name":"Complete Care In Beauty & Nails",
    "wof:placetype":"venue"
},
  "geometry": {"coordinates":[150.91244506800001,-33.921005249],"type":"Point"}
}