{
  "type": "Feature",
  "properties": {
    "addr:full":"37 Diplacus Drv Palm Beach QLD 4221",
    "addr:housenumber":"37",
    "addr:postcode":"4221",
    "addr:street":"Diplacus Drv",
    "iso:country":"AU",
    "sg:address":"37 Diplacus Drv",
    "sg:city":"Palm Beach",
    "sg:classifiers":[
        {
            "category":"Building & Trades",
            "subcategory":"Construction",
            "type":"Services"
        }
    ],
    "sg:phone":"+61 7 5520 7277",
    "sg:postcode":"4221",
    "sg:province":"QLD",
    "sg:tags":[
        "repair",
        "maintenance",
        "contractor"
    ],
    "wof:name":"Frankland Building",
    "wof:placetype":"venue"
},
  "geometry": {"coordinates":[153.449783325,-28.112033844],"type":"Point"}
}