{
  "type": "Feature",
  "properties": {
    "iso:country":"AU",
    "sg:address":"43 Byron St",
    "sg:city":"Footscray",
    "sg:classifiers":[
        {
            "category":"Health Services",
            "subcategory":"Doctor",
            "type":"Services"
        }
    ],
    "sg:phone":"+61 3 9396 1600",
    "sg:postcode":"3011",
    "sg:province":"VIC",
    "sg:tags":[
        "medical",
        "practitioner"
    ],
    "wof:name":"Le Anh Dr",
    "wof:placetype":"venue"
},
  "geometry": {"coordinates":[144.90119934099999,-37.7993469238],"type":"Point"}
}