{
  "type": "Feature",
  "properties": {
    "addr:full":"Shop 4 Kimberley Park Centre Cnr Lyndale St & Chat Shailer Park QLD 4128",
    "addr:housenumber":"shop 4",
    "addr:postcode":"4128",
    "addr:street":"Kimberley Park Centre Cnr Lyndale St &",
    "iso:country":"AU",
    "sg:address":"Shop 4 Kimberley Park Centre Cnr Lyndale St & Chat",
    "sg:city":"Shailer Park",
    "sg:classifiers":[
        {
            "category":"Professional",
            "subcategory":"Printing & Photocopies",
            "type":"Services"
        }
    ],
    "sg:phone":"+61 7 3801 1860",
    "sg:postcode":"4128",
    "sg:province":"QLD",
    "sg:tags":[
        "trophy"
    ],
    "wof:name":"Accolades Awards",
    "wof:placetype":"venue"
},
  "geometry": {"coordinates":[153.17251586899999,-27.6437072754],"type":"Point"}
}