{
  "type": "Feature",
  "properties": {
    "iso:country":"AU",
    "sg:address":"25 Richards Rd",
    "sg:city":"Narangba",
    "sg:classifiers":[
        {
            "category":"Professional",
            "subcategory":"Employment Agencies",
            "type":"Services"
        }
    ],
    "sg:phone":"+61 7 3888 6589",
    "sg:postcode":"4504",
    "sg:province":"QLD",
    "sg:tags":[
        "occupational",
        "therapist"
    ],
    "wof:name":"Debra Bone Occupational Therapist",
    "wof:placetype":"venue"
},
  "geometry": {"coordinates":[152.97901916500001,-27.2040138245],"type":"Point"}
}