{
  "type": "Feature",
  "properties": {
    "addr:full":"168 Abernethy Rd Belmont WA 6104",
    "addr:housenumber":"168",
    "addr:postcode":"6104",
    "addr:street":"Abernethy Rd",
    "iso:country":"AU",
    "sg:address":"168 Abernethy Rd",
    "sg:city":"Belmont",
    "sg:classifiers":[
        {
            "category":"Wholesale",
            "subcategory":"Drugs",
            "type":"Manufacturing & Wholesale Goods"
        }
    ],
    "sg:phone":"+61 8 9475 0999",
    "sg:postcode":"6104",
    "sg:province":"WA",
    "sg:tags":[
        "wholesaler",
        "pharmaceutical",
        "product",
        "mfrs"
    ],
    "wof:name":"Pfizer Australia Pty Ltd",
    "wof:placetype":"venue"
},
  "geometry": {"coordinates":[115.92810821499999,-31.9557723999],"type":"Point"}
}