{
  "type": "Feature",
  "properties": {
    "addr:full":"37 Crisp St Wangaratta VIC 3677",
    "addr:housenumber":"37",
    "addr:postcode":"3677",
    "addr:street":"Crisp St",
    "iso:country":"AU",
    "sg:address":"37 Crisp St",
    "sg:city":"Wangaratta",
    "sg:classifiers":[
        {
            "category":"Professional",
            "subcategory":"Business Services",
            "type":"Services"
        }
    ],
    "sg:phone":"+61 3 5722 9400",
    "sg:postcode":"3677",
    "sg:province":"VIC",
    "sg:tags":[
        "drafting"
    ],
    "wof:name":"Freedom of Design Pty Ltd",
    "wof:placetype":"venue"
},
  "geometry": {"coordinates":[146.31950378400001,-36.3619232178],"type":"Point"}
}