{
  "type": "Feature",
  "properties": {
    "addr:full":"112 Vera Pl Dardanup WA 6236",
    "addr:housenumber":"112",
    "addr:postcode":"6236",
    "addr:street":"Vera Pl",
    "iso:country":"AU",
    "sg:address":"112 Vera Pl",
    "sg:city":"Dardanup",
    "sg:classifiers":[
        {
            "category":"Retail",
            "subcategory":"Storage",
            "type":"Services"
        }
    ],
    "sg:phone":"+61 8 9728 0178",
    "sg:postcode":"6236",
    "sg:province":"WA",
    "sg:tags":[
        "removal",
        "furniture"
    ],
    "wof:name":"All Area Removals",
    "wof:placetype":"venue"
},
  "geometry": {"coordinates":[115.732224,-33.383602],"type":"Point"}
}