{
  "type": "Feature",
  "properties": {
    "iso:country":"AU",
    "sg:address":"PO Box 5197",
    "sg:city":", Q. Super Centre Mermaid Waters",
    "sg:classifiers":[
        {
            "category":"Banks & Credit Unions",
            "subcategory":"Bank",
            "type":"Services"
        }
    ],
    "sg:phone":"+61 7 5526 7533",
    "sg:postcode":"4218",
    "sg:province":"QLD",
    "sg:tags":[
        "broker",
        "mortgage"
    ],
    "wof:name":"Allied Mortgage Corporation (Qld) Commercial",
    "wof:placetype":"venue"
},
  "geometry": {"coordinates":[153.41163635300001,-28.0360908508],"type":"Point"}
}