{
  "type": "Feature",
  "properties": {
    "addr:full":"14/ 214 Wellington Rd Mulgrave VIC 3170",
    "addr:housenumber":"14 / 214",
    "addr:postcode":"3170",
    "addr:street":"Wellington Rd",
    "iso:country":"AU",
    "sg:address":"14/ 214 Wellington Rd",
    "sg:city":"Mulgrave",
    "sg:classifiers":[
        {
            "category":"Wholesale",
            "subcategory":"Electrical",
            "type":"Manufacturing & Wholesale Goods"
        }
    ],
    "sg:phone":"+61 3 9562 2033",
    "sg:postcode":"3170",
    "sg:province":"VIC",
    "sg:tags":[
        "wholesaler"
    ],
    "wof:name":"Middendorp Electric Co Pty Ltd",
    "wof:placetype":"venue"
},
  "geometry": {"coordinates":[145.147994995,-37.9174003601],"type":"Point"}
}