{
  "type": "Feature",
  "properties": {
    "iso:country":"AU",
    "sg:address":"24a Taylor St",
    "sg:city":"Kadina",
    "sg:classifiers":[
        {
            "category":"Personal",
            "subcategory":"Beauty Salon",
            "type":"Services"
        }
    ],
    "sg:phone":"+61 8 8821 3121",
    "sg:postcode":"5554",
    "sg:province":"SA",
    "sg:tags":[
        "hairdresser"
    ],
    "wof:name":"Short Cutz By Janine",
    "wof:placetype":"venue"
},
  "geometry": {"coordinates":[137.71232605,-33.9627761841],"type":"Point"}
}