{
  "type": "Feature",
  "properties": {
    "iso:country":"AU",
    "sg:address":"16 Phillip St",
    "sg:city":"Parramatta",
    "sg:classifiers":[
        {
            "category":"Real Estate",
            "subcategory":"Real Estate Agent",
            "type":"Services"
        }
    ],
    "sg:phone":"+61 2 9635 4000",
    "sg:postcode":"2150",
    "sg:province":"NSW",
    "wof:name":"Laing + Simmons Parramatta",
    "wof:placetype":"venue"
},
  "geometry": {"coordinates":[151.024124145,-33.7971382141],"type":"Point"}
}