{
  "type": "Feature",
  "properties": {
    "iso:country":"AU",
    "sg:address":"Unit 6 No.31 Queens Rd",
    "sg:city":"Everton Hills",
    "sg:classifiers":[
        {
            "category":"Professional",
            "subcategory":"Testing Lab",
            "type":"Services"
        }
    ],
    "sg:phone":"+61 7 3353 4911",
    "sg:postcode":"4053",
    "sg:province":"QLD",
    "sg:tags":[
        "soil",
        "investigation"
    ],
    "wof:name":"Geotest Engineering Services Pty Ltd",
    "wof:placetype":"venue"
},
  "geometry": {"coordinates":[152.977416992,-27.3894004822],"type":"Point"}
}