{
  "type": "Feature",
  "properties": {
    "addr:full":"Lvl 1/ 101-111 William St Sydney NSW 2000",
    "addr:housenumber":"/ 101-111",
    "addr:postcode":"2000",
    "addr:street":"William St",
    "iso:country":"AU",
    "sg:address":"Lvl 1/ 101-111 William St",
    "sg:city":"Sydney",
    "sg:classifiers":[
        {
            "category":"Utilities",
            "subcategory":"Recycling",
            "type":"Services"
        }
    ],
    "sg:phone":"+61 2 9331 0433",
    "sg:postcode":"2000",
    "sg:province":"NSW",
    "wof:name":"Visy Closed Loop",
    "wof:placetype":"venue"
},
  "geometry": {"coordinates":[151.21684265100001,-33.8745994568],"type":"Point"}
}