{
  "type": "Feature",
  "properties": {
    "addr:full":"Smashed Health & Fitness Cntr Ducket St Beaudesert QLD 4285",
    "addr:postcode":"4285",
    "addr:street":"St",
    "iso:country":"AU",
    "sg:address":"Smashed Health & Fitness Cntr Ducket St",
    "sg:city":"Beaudesert",
    "sg:classifiers":[
        {
            "category":"Personal",
            "subcategory":"Day Spa",
            "type":"Services"
        }
    ],
    "sg:phone":"+61 410 655 267",
    "sg:postcode":"4285",
    "sg:province":"QLD",
    "wof:name":"Elite Skin Technology",
    "wof:placetype":"venue"
},
  "geometry": {"coordinates":[152.99586500000001,-27.986572],"type":"Point"}
}