{
  "type": "Feature",
  "properties": {
    "addr:full":"Shop 4, 18 River St Maclean NSW 2463",
    "addr:housenumber":"shop;18",
    "addr:postcode":"2463",
    "addr:street":"River St",
    "iso:country":"AU",
    "sg:address":"Shop 4, 18 River St",
    "sg:city":"Maclean",
    "sg:classifiers":[
        {
            "category":"Organizations",
            "subcategory":"Community Association",
            "type":"Services"
        }
    ],
    "sg:phone":"+61 2 6645 4094",
    "sg:postcode":"2463",
    "sg:province":"NSW",
    "sg:tags":[
        "organisation",
        "family",
        "welfare"
    ],
    "wof:name":"MacLean Lower Meals-On-Wheels Inc",
    "wof:placetype":"venue"
},
  "geometry": {"coordinates":[153.20114135700001,-29.4493427277],"type":"Point"}
}