{
  "type": "Feature",
  "properties": {
    "addr:full":"185 Brunker Rd Adamstown NSW 2289",
    "addr:housenumber":"185",
    "addr:postcode":"2289",
    "addr:street":"Brunker Rd",
    "iso:country":"AU",
    "sg:address":"185 Brunker Rd",
    "sg:city":"Adamstown",
    "sg:classifiers":[
        {
            "category":"Health Services",
            "subcategory":"Dentist",
            "type":"Services"
        }
    ],
    "sg:phone":"+61 2 4952 8971",
    "sg:postcode":"2289",
    "sg:province":"NSW",
    "sg:tags":[
        "dental",
        "prosthetist"
    ],
    "wof:name":"R B Salmon",
    "wof:placetype":"venue"
},
  "geometry": {"coordinates":[151.725906372,-32.9349441528],"type":"Point"}
}