{
  "type": "Feature",
  "properties": {
    "iso:country":"AU",
    "sg:address":"4 Stuart St",
    "sg:city":"West Pennant Hills",
    "sg:classifiers":[
        {
            "category":"Sports & Exercise",
            "subcategory":"Playing Field",
            "type":"Entertainment"
        }
    ],
    "sg:phone":"+61 2 9899 8275",
    "sg:postcode":"2125",
    "sg:province":"NSW",
    "sg:tags":[
        "repair",
        "walking",
        "retail",
        "umbrella",
        "stick"
    ],
    "wof:name":"Brella Pty Ltd",
    "wof:placetype":"venue"
},
  "geometry": {"coordinates":[151.04768371599999,-33.7535095215],"type":"Point"}
}