{
  "type": "Feature",
  "properties": {
    "addr:full":"\"Cullarong\" Bishop Rd Ongerup WA 6336",
    "addr:postcode":"6336",
    "addr:street":"Bishop Rd",
    "iso:country":"AU",
    "sg:address":"\"Cullarong\" Bishop Rd",
    "sg:city":"Ongerup",
    "sg:classifiers":[
        {
            "category":"Farming",
            "subcategory":"Farm",
            "type":"Manufacturing & Wholesale Goods"
        }
    ],
    "sg:phone":"+61 8 9828 4030",
    "sg:postcode":"6336",
    "sg:province":"WA",
    "sg:tags":[
        "farmer"
    ],
    "wof:name":"Pope C N",
    "wof:placetype":"venue"
},
  "geometry": {"coordinates":[118.53717804,-33.9036483765],"type":"Point"}
}