{
  "type": "Feature",
  "properties": {
    "addr:full":"1st Floor 643 Murray St West Perth WA 6005",
    "addr:housenumber":"643",
    "addr:postcode":"6005",
    "addr:street":"Murray St",
    "iso:country":"AU",
    "sg:address":"1st Floor 643 Murray St",
    "sg:city":"West Perth",
    "sg:classifiers":[
        {
            "category":"Banks & Credit Unions",
            "subcategory":"Investment Brokerage",
            "type":"Services"
        }
    ],
    "sg:phone":"+61 8 9481 7898",
    "sg:postcode":"6005",
    "sg:province":"WA",
    "sg:tags":[
        "finance",
        "broker"
    ],
    "wof:name":"Agri Finance Co",
    "wof:placetype":"venue"
},
  "geometry": {"coordinates":[115.84496307400001,-31.9484920502],"type":"Point"}
}