{
  "type": "Feature",
  "properties": {
    "addr:full":"119 Dorchester Ave Warwick WA 6024",
    "addr:housenumber":"119",
    "addr:postcode":"6024",
    "addr:street":"Dorchester Ave",
    "iso:country":"AU",
    "sg:address":"119 Dorchester Ave",
    "sg:city":"Warwick",
    "sg:classifiers":[
        {
            "category":"Personal",
            "subcategory":"Beauty Salon",
            "type":"Services"
        }
    ],
    "sg:phone":"+61 8 9448 8906",
    "sg:postcode":"6024",
    "sg:province":"WA",
    "wof:name":"Tricias Nail Design",
    "wof:placetype":"venue"
},
  "geometry": {"coordinates":[115.798973084,-31.8365821838],"type":"Point"}
}