{
  "type": "Feature",
  "properties": {
    "addr:full":"54 Mt Hicks Rd Wynyard TAS 7325",
    "addr:housenumber":"54",
    "addr:postcode":"7325",
    "addr:street":"Mt Hicks Rd",
    "iso:country":"AU",
    "sg:address":"54 Mt Hicks Rd",
    "sg:city":"Wynyard",
    "sg:classifiers":[
        {
            "category":"Building & Trades",
            "subcategory":"Construction",
            "type":"Services"
        }
    ],
    "sg:phone":"+61 438 170 967",
    "sg:postcode":"7325",
    "sg:province":"TAS",
    "sg:tags":[
        "earth",
        "excavating",
        "moving",
        "contractor"
    ],
    "wof:name":"Scott Leonard Contracting",
    "wof:placetype":"venue"
},
  "geometry": {"coordinates":[145.749313,-40.997124],"type":"Point"}
}