{
  "type": "Feature",
  "properties": {
    "addr:full":"101 Ferguson Rd Camp Hill QLD 4152",
    "addr:housenumber":"101",
    "addr:postcode":"4152",
    "addr:street":"Ferguson Rd",
    "iso:country":"AU",
    "sg:address":"101 Ferguson Rd",
    "sg:city":"Camp Hill",
    "sg:classifiers":[
        {
            "category":"Personal",
            "subcategory":"Barber",
            "type":"Services"
        }
    ],
    "sg:phone":"+61 7 3398 1099",
    "sg:postcode":"4152",
    "sg:province":"QLD",
    "wof:name":"Hairdressers Of Camp Hill",
    "wof:placetype":"venue"
},
  "geometry": {"coordinates":[153.078857422,-27.4875164032],"type":"Point"}
}