{
  "type": "Feature",
  "properties": {
    "iso:country":"AU",
    "sg:address":"Ste 1. Lvl 1/ 85 William St",
    "sg:city":"East Sydney",
    "sg:classifiers":[
        {
            "category":"Train Station",
            "subcategory":"Rail",
            "type":"Transportation"
        }
    ],
    "sg:phone":"+61 2 9360 6788",
    "sg:postcode":"2010",
    "sg:province":"NSW",
    "sg:tags":[
        "consultant"
    ],
    "wof:name":"Christopher Stapleton Consulting",
    "wof:placetype":"venue"
},
  "geometry": {"coordinates":[151.21580505399999,-33.8744277954],"type":"Point"}
}