{
  "type": "Feature",
  "properties": {
    "addr:full":"504 Urana Rd Albury NSW 2640",
    "addr:housenumber":"504",
    "addr:postcode":"2640",
    "addr:street":"Urana Rd",
    "iso:country":"AU",
    "sg:address":"504 Urana Rd",
    "sg:city":"Albury",
    "sg:classifiers":[
        {
            "category":"Retail",
            "subcategory":"Repair Shop",
            "type":"Services"
        }
    ],
    "sg:phone":"+61 2 6025 2611",
    "sg:postcode":"2640",
    "sg:province":"NSW",
    "sg:tags":[
        "restorer",
        "repairer",
        "carpet"
    ],
    "wof:name":"Top Class Cleaning Services",
    "wof:placetype":"venue"
},
  "geometry": {"coordinates":[146.902099609,-36.0115776062],"type":"Point"}
}