{
  "type": "Feature",
  "properties": {
    "addr:full":"Shop 34 Stockland Mall Polding St Wetherill Park NSW 2164",
    "addr:housenumber":"shop 34",
    "addr:postcode":"2164",
    "addr:street":"Polding St",
    "iso:country":"AU",
    "sg:address":"Shop 34 Stockland Mall Polding St",
    "sg:city":"Wetherill Park",
    "sg:classifiers":[
        {
            "category":"Shopping",
            "subcategory":"Clothing, Apparel, & Fashions",
            "type":"Retail Goods"
        }
    ],
    "sg:phone":"+61 2 9609 7281",
    "sg:postcode":"2164",
    "sg:province":"NSW",
    "sg:tags":[
        "lady",
        "wear"
    ],
    "wof:name":"Suzanne Grae",
    "wof:placetype":"venue"
},
  "geometry": {"coordinates":[150.9034729,-33.8572120667],"type":"Point"}
}