{
  "type": "Feature",
  "properties": {
    "iso:country":"AU",
    "sg:address":"Shop T 49",
    "sg:city":"Werribee Plaza Werribee",
    "sg:classifiers":[
        {
            "category":"Shopping",
            "subcategory":"Jewelry",
            "type":"Retail Goods"
        }
    ],
    "sg:phone":"+61 3 9749 6378",
    "sg:postcode":"3030",
    "sg:province":"VIC",
    "sg:tags":[
        "jeweller"
    ],
    "wof:name":"Saleras Jewellmasters",
    "wof:placetype":"venue"
},
  "geometry": {"coordinates":[144.659637,-37.903702],"type":"Point"}
}