{
  "type": "Feature",
  "properties": {
    "addr:full":"11 Cross Rd Bedfordale WA 6112",
    "addr:housenumber":"11",
    "addr:postcode":"6112",
    "addr:street":"Cross Rd",
    "iso:country":"AU",
    "sg:address":"11 Cross Rd",
    "sg:city":"Bedfordale",
    "sg:classifiers":[
        {
            "category":"Train Station",
            "subcategory":"Light Rail",
            "type":"Transportation"
        }
    ],
    "sg:phone":"+61 8 9399 3310",
    "sg:postcode":"6112",
    "sg:province":"WA",
    "sg:tags":[
        "survey",
        "traffic"
    ],
    "wof:name":"Traffic Investigations & Safety Services",
    "wof:placetype":"venue"
},
  "geometry": {"coordinates":[116.053222656,-32.1794967651],"type":"Point"}
}