{
  "type": "Feature",
  "properties": {
    "iso:country":"AU",
    "sg:address":"2 Hall Rd",
    "sg:city":"Hornsby",
    "sg:classifiers":[
        {
            "category":"Banks & Credit Unions",
            "subcategory":"Financial Services",
            "type":"Services"
        }
    ],
    "sg:phone":"+61 2 9477 1897",
    "sg:postcode":"2077",
    "sg:province":"NSW",
    "sg:tags":[
        "annuity",
        "rollover",
        "superannuation",
        "consultant"
    ],
    "wof:name":"Sevita Pty Ltd",
    "wof:placetype":"venue"
},
  "geometry": {"coordinates":[151.09695434599999,-33.710849762],"type":"Point"}
}