{
  "type": "Feature",
  "properties": {
    "addr:full":"91 Mulga Rd Oatley NSW 2223",
    "addr:housenumber":"91",
    "addr:postcode":"2223",
    "addr:street":"Mulga Rd",
    "iso:country":"AU",
    "sg:address":"91 Mulga Rd",
    "sg:city":"Oatley",
    "sg:classifiers":[
        {
            "category":"Real Estate",
            "subcategory":"Real Estate Agent",
            "type":"Services"
        }
    ],
    "sg:phone":"+61 2 9570 4777",
    "sg:postcode":"2223",
    "sg:province":"NSW",
    "wof:name":"Raine & Horne Oatley",
    "wof:placetype":"venue"
},
  "geometry": {"coordinates":[151.07437133799999,-33.9801330566],"type":"Point"}
}