{
  "type": "Feature",
  "properties": {
    "iso:country":"AU",
    "sg:address":"Victoria Point Lakeside Shop 7 Bunker Rd",
    "sg:city":"Victoria Point",
    "sg:classifiers":[
        {
            "category":"Shopping",
            "subcategory":"Bicycles & Sporting Goods",
            "type":"Retail Goods"
        }
    ],
    "sg:phone":"+61 7 3820 6182",
    "sg:postcode":"4165",
    "sg:province":"QLD",
    "sg:tags":[
        "chemical",
        "equipment",
        "pool",
        "swimming"
    ],
    "wof:name":"Redlands Pool Service Pty. Ltd.",
    "wof:placetype":"venue"
},
  "geometry": {"coordinates":[153.280197144,-27.5858840942],"type":"Point"}
}