{
  "type": "Feature",
  "properties": {
    "iso:country":"AU",
    "sg:address":"Unit 2 18 Lonsdale St",
    "sg:city":"Braddon",
    "sg:classifiers":[
        {
            "category":"Government",
            "subcategory":"Post Office",
            "type":"Public Place"
        }
    ],
    "sg:phone":"+61 2 6247 4192",
    "sg:postcode":"2612",
    "sg:province":"ACT",
    "sg:tags":[
        "postal"
    ],
    "wof:name":"Braddon Newsagency & Post Office",
    "wof:placetype":"venue"
},
  "geometry": {"coordinates":[149.13287353499999,-35.2737350464],"type":"Point"}
}