{
  "type": "Feature",
  "properties": {
    "addr:full":"Crn Grimshaw & Macorna Streets Watsonia VIC 3087",
    "addr:postcode":"3087",
    "addr:street":"Crn;Streets",
    "iso:country":"AU",
    "sg:address":"Crn Grimshaw & Macorna Streets",
    "sg:city":"Watsonia",
    "sg:classifiers":[
        {
            "category":"Health Services",
            "subcategory":"Health Practitioner",
            "type":"Services"
        }
    ],
    "sg:phone":"+61 414 465 133",
    "sg:postcode":"3087",
    "sg:province":"VIC",
    "sg:tags":[
        "naturopath"
    ],
    "wof:name":"Shirley Tosevski ND",
    "wof:placetype":"venue"
},
  "geometry": {"coordinates":[145.08357238799999,-37.7066497803],"type":"Point"}
}