{
  "type": "Feature",
  "properties": {
    "iso:country":"AU",
    "sg:address":"134- 138 Raglan St",
    "sg:city":"Roma",
    "sg:classifiers":[
        {
            "category":"Professional",
            "type":"Services"
        }
    ],
    "sg:phone":"+61 7 4622 1122",
    "sg:postcode":"4455",
    "sg:province":"QLD",
    "sg:tags":[
        "transport"
    ],
    "wof:name":"Roma Crane Hire & Heavy Haulage",
    "wof:placetype":"venue"
},
  "geometry": {"coordinates":[148.77955627399999,-26.5803775787],"type":"Point"}
}