{
  "type": "Feature",
  "properties": {
    "iso:country":"AU",
    "sg:address":"92 Adelaide St",
    "sg:city":"Raymond Terrace",
    "sg:classifiers":[
        {
            "category":"Travel",
            "subcategory":"Hotels & Motels",
            "type":"Entertainment"
        }
    ],
    "sg:phone":"+61 2 4987 2321",
    "sg:postcode":"2324",
    "sg:province":"NSW",
    "wof:name":"Sleepy Hill Motor Inn",
    "wof:placetype":"venue"
},
  "geometry": {"coordinates":[151.76124572800001,-32.75157547],"type":"Point"}
}