{
  "type": "Feature",
  "properties": {
    "iso:country":"AU",
    "sg:address":"23 Northpoint Ave",
    "sg:city":"Port Lincoln",
    "sg:classifiers":[
        {
            "category":"Insurance",
            "subcategory":"Insurance Agent",
            "type":"Services"
        }
    ],
    "sg:phone":"+61 8 8682 3520",
    "sg:postcode":"5606",
    "sg:province":"SA",
    "sg:tags":[
        "broker"
    ],
    "wof:name":"Wiebrecht K G",
    "wof:placetype":"venue"
},
  "geometry": {"coordinates":[135.852036,-34.728481],"type":"Point"}
}