{
  "type": "Feature",
  "properties": {
    "iso:country":"AU",
    "sg:address":"1 Joffre St",
    "sg:city":"Mowbray",
    "sg:classifiers":[
        {
            "category":"Personal",
            "subcategory":"Beauty Salon",
            "type":"Services"
        }
    ],
    "sg:phone":"+61 3 6326 4561",
    "sg:postcode":"7248",
    "sg:province":"TAS",
    "sg:tags":[
        "wig",
        "hairpiece"
    ],
    "wof:name":"Revelation Hair Skin Nails",
    "wof:placetype":"venue"
},
  "geometry": {"coordinates":[147.131149292,-41.4048194885],"type":"Point"}
}