{
  "type": "Feature",
  "properties": {
    "addr:full":"32 Mark La Waterford West QLD 4133",
    "addr:housenumber":"32",
    "addr:postcode":"4133",
    "addr:street":"Mark La",
    "iso:country":"AU",
    "sg:address":"32 Mark La",
    "sg:city":"Waterford West",
    "sg:classifiers":[
        {
            "category":"Building & Trades",
            "subcategory":"Cleaning & Sanitation",
            "type":"Services"
        }
    ],
    "sg:phone":"+61 417 753 450",
    "sg:postcode":"4133",
    "sg:province":"QLD",
    "sg:tags":[
        "commercial",
        "maintenance"
    ],
    "wof:name":"Di-man Enterprises",
    "wof:placetype":"venue"
},
  "geometry": {"coordinates":[153.11730957,-27.6822509766],"type":"Point"}
}