{
  "type": "Feature",
  "properties": {
    "iso:country":"AU",
    "sg:address":"Shop 9, Willowglen Centre, 837 Ruthven St",
    "sg:city":"Toowoomba South",
    "sg:classifiers":[
        {
            "category":"Shopping",
            "subcategory":"Crafts & Fabrics",
            "type":"Retail Goods"
        }
    ],
    "sg:phone":"+61 7 4687 6888",
    "sg:postcode":"4350",
    "sg:province":"QLD",
    "sg:tags":[
        "supply"
    ],
    "wof:name":"The Scrap N Patch",
    "wof:placetype":"venue"
},
  "geometry": {"coordinates":[151.948181,-27.589878],"type":"Point"}
}