{
  "type": "Feature",
  "properties": {
    "addr:full":"23/ 346- 362 Pennant Hills Rd Carlingford NSW 2118",
    "addr:housenumber":"23 / 346 362",
    "addr:postcode":"2118",
    "addr:street":"Pennant Hills Rd",
    "iso:country":"AU",
    "sg:address":"23/ 346- 362 Pennant Hills Rd",
    "sg:city":"Carlingford",
    "sg:classifiers":[
        {
            "category":"Food & Beverages",
            "subcategory":"Specialty",
            "type":"Retail Goods"
        }
    ],
    "sg:phone":"+61 2 9432 4398",
    "sg:postcode":"2118",
    "sg:province":"NSW",
    "sg:tags":[
        "product",
        "health"
    ],
    "wof:name":"Herbalife Australasia Pty Ltd",
    "wof:placetype":"venue"
},
  "geometry": {"coordinates":[151.051971436,-33.7802963257],"type":"Point"}
}