{
  "type": "Feature",
  "properties": {
    "addr:full":"PO Box 79 Forrestfield WA 6058",
    "addr:postcode":"6058",
    "iso:country":"AU",
    "sg:address":"PO Box 79",
    "sg:city":"Forrestfield",
    "sg:classifiers":[
        {
            "category":"Autos & Motor Vehicles",
            "subcategory":"Auto Supplies",
            "type":"Retail Goods"
        }
    ],
    "sg:phone":"+61 8 9359 3994",
    "sg:postcode":"6058",
    "sg:province":"WA",
    "sg:tags":[
        "oil",
        "spirit"
    ],
    "wof:name":"United Oil WA",
    "wof:placetype":"venue"
},
  "geometry": {"coordinates":[116.00077819800001,-31.9696292877],"type":"Point"}
}