{
  "type": "Feature",
  "properties": {
    "addr:full":"381 Park Rd Regents Park NSW 2143",
    "addr:housenumber":"381",
    "addr:postcode":"2143",
    "addr:street":"Park Rd",
    "iso:country":"AU",
    "sg:address":"381 Park Rd",
    "sg:city":"Regents Park",
    "sg:classifiers":[
        {
            "category":"Retail",
            "subcategory":"Auto Repair",
            "type":"Services"
        }
    ],
    "sg:phone":"+61 2 9738 9200",
    "sg:postcode":"2143",
    "sg:province":"NSW",
    "sg:tags":[
        "repairer",
        "motor",
        "engineer"
    ],
    "wof:name":"Berala Car Care Centre",
    "wof:placetype":"venue"
},
  "geometry": {"coordinates":[151.024200439,-33.8806037903],"type":"Point"}
}