{
  "type": "Feature",
  "properties": {
    "addr:full":"PO Box 568 Penneshaw SA 5222",
    "addr:postcode":"5222",
    "iso:country":"AU",
    "sg:address":"PO Box 568",
    "sg:city":"Penneshaw",
    "sg:classifiers":[
        {
            "category":"Food & Beverages",
            "subcategory":"Groceries & Convenience Stores",
            "type":"Retail Goods"
        }
    ],
    "sg:phone":"+61 8 8553 1260",
    "sg:postcode":"5222",
    "sg:province":"SA",
    "sg:tags":[
        "merchant",
        "egg"
    ],
    "wof:name":"Modra's Free Range Eggs",
    "wof:placetype":"venue"
},
  "geometry": {"coordinates":[137.93669128400001,-35.7182998657],"type":"Point"}
}