{
  "type": "Feature",
  "properties": {
    "addr:full":"742 High St Epping VIC 3076",
    "addr:housenumber":"742",
    "addr:postcode":"3076",
    "addr:street":"High St",
    "iso:country":"AU",
    "sg:address":"742 High St",
    "sg:city":"Epping",
    "sg:classifiers":[
        {
            "category":"Real Estate",
            "subcategory":"Real Estate Agent",
            "type":"Services"
        }
    ],
    "sg:phone":"+61 3 9401 3411",
    "sg:postcode":"3076",
    "sg:province":"VIC",
    "wof:name":"Rescom Property and Service",
    "wof:placetype":"venue"
},
  "geometry": {"coordinates":[145.013183594,-37.8546409607],"type":"Point"}
}