{
  "type": "Feature",
  "properties": {
    "addr:full":"147 Argyle St Hobart TAS 7000",
    "addr:housenumber":"147",
    "addr:postcode":"7000",
    "addr:street":"Argyle St",
    "iso:country":"AU",
    "sg:address":"147 Argyle St",
    "sg:city":"Hobart",
    "sg:classifiers":[
        {
            "category":"Shopping",
            "subcategory":"Clothing, Apparel, & Fashions",
            "type":"Retail Goods"
        }
    ],
    "sg:phone":"+61 3 6231 1882",
    "sg:postcode":"7000",
    "sg:province":"TAS",
    "sg:tags":[
        "recycled",
        "clothing"
    ],
    "wof:name":"Lifeline's Chosen Pieces",
    "wof:placetype":"venue"
},
  "geometry": {"coordinates":[147.32324218799999,-42.8762435913],"type":"Point"}
}