{
  "type": "Feature",
  "properties": {
    "addr:full":"Phillips Rd Berri SA 5343",
    "addr:postcode":"5343",
    "addr:street":"Phillips Rd",
    "iso:country":"AU",
    "sg:address":"Phillips Rd",
    "sg:city":"Berri",
    "sg:classifiers":[
        {
            "category":"Retail",
            "subcategory":"Funeral Services",
            "type":"Services"
        }
    ],
    "sg:phone":"+61 439 812 210",
    "sg:postcode":"5343",
    "sg:province":"SA",
    "sg:tags":[
        "cremation"
    ],
    "wof:name":"Riverland Cremation Services",
    "wof:placetype":"venue"
},
  "geometry": {"coordinates":[140.592926025,-34.2797622681],"type":"Point"}
}