{
  "type": "Feature",
  "properties": {
    "addr:full":"Unit 1, 3 Gosport St Hemmant QLD 4174",
    "addr:housenumber":"3",
    "addr:postcode":"4174",
    "addr:street":"Gosport St",
    "iso:country":"AU",
    "sg:address":"Unit 1, 3 Gosport St",
    "sg:city":"Hemmant",
    "sg:classifiers":[
        {
            "category":"Education",
            "subcategory":"School",
            "type":"Public Place"
        }
    ],
    "sg:phone":"+61 7 3890 7359",
    "sg:postcode":"4174",
    "sg:province":"QLD",
    "sg:tags":[
        "supply"
    ],
    "wof:name":"Eckersley's School Division",
    "wof:placetype":"venue"
},
  "geometry": {"coordinates":[153.12681579599999,-27.4412479401],"type":"Point"}
}