{
  "type": "Feature",
  "properties": {
    "addr:full":"Lot 22 Crows Nest Industrial Estate Crows Nest QLD 4355",
    "addr:postcode":"4355",
    "addr:street":"Nest Industrial",
    "iso:country":"AU",
    "sg:address":"Lot 22 Crows Nest Industrial Estate",
    "sg:city":"Crows Nest",
    "sg:classifiers":[
        {
            "category":"Professional",
            "subcategory":"Engineering",
            "type":"Services"
        }
    ],
    "sg:phone":"+61 7 4698 1822",
    "sg:postcode":"4355",
    "sg:province":"QLD",
    "sg:tags":[
        "engineer"
    ],
    "wof:name":"HMF Engineering",
    "wof:placetype":"venue"
},
  "geometry": {"coordinates":[152.054993,-27.261459],"type":"Point"}
}