{
  "type": "Feature",
  "properties": {
    "addr:full":"20 Tate St West Leederville WA 6007",
    "addr:housenumber":"20",
    "addr:postcode":"6007",
    "addr:street":"Tate St West",
    "iso:country":"AU",
    "sg:address":"20 Tate St",
    "sg:city":"West Leederville",
    "sg:classifiers":[
        {
            "category":"Organizations",
            "subcategory":"Membership Organization",
            "type":"Services"
        }
    ],
    "sg:phone":"+61 8 9380 4979",
    "sg:postcode":"6007",
    "sg:province":"WA",
    "sg:tags":[
        "support",
        "health",
        "organisation"
    ],
    "wof:name":"Australian Pituitary Foundation Ltd",
    "wof:placetype":"venue"
},
  "geometry": {"coordinates":[115.82901001,-31.9420986176],"type":"Point"}
}