{
  "type": "Feature",
  "properties": {
    "addr:full":"3 Webb Rd Loganlea QLD 4131",
    "addr:housenumber":"3",
    "addr:postcode":"4131",
    "addr:street":"Webb Rd",
    "iso:country":"AU",
    "sg:address":"3 Webb Rd",
    "sg:city":"Loganlea",
    "sg:classifiers":[
        {
            "category":"Building & Trades",
            "subcategory":"Cleaning & Sanitation",
            "type":"Services"
        }
    ],
    "sg:phone":"+61 411 559 112",
    "sg:postcode":"4131",
    "sg:province":"QLD",
    "sg:tags":[
        "industrial",
        "commercial",
        "contractor"
    ],
    "wof:name":"Cantrust Cleaning",
    "wof:placetype":"venue"
},
  "geometry": {"coordinates":[153.13238525400001,-27.6777992249],"type":"Point"}
}