{
  "type": "Feature",
  "properties": {
    "addr:full":"Symantec House, Lvl 23, 207 Kent St Sydney NSW 2000",
    "addr:housenumber":"207",
    "addr:postcode":"2000",
    "addr:street":"Kent St",
    "iso:country":"AU",
    "sg:address":"Symantec House, Lvl 23, 207 Kent St",
    "sg:city":"Sydney",
    "sg:classifiers":[
        {
            "category":"Banks & Credit Unions",
            "subcategory":"Investment Brokerage",
            "type":"Services"
        }
    ],
    "sg:phone":"+61 2 9259 0200",
    "sg:postcode":"2000",
    "sg:province":"NSW",
    "wof:name":"Ausbil Dexia Ltd",
    "wof:placetype":"venue"
},
  "geometry": {"coordinates":[151.203857422,-33.863910675],"type":"Point"}
}