{
  "type": "Feature",
  "properties": {
    "addr:full":"Herbert St Boulia QLD 4829",
    "addr:postcode":"4829",
    "addr:street":"Herbert St",
    "iso:country":"AU",
    "sg:address":"Herbert St",
    "sg:city":"Boulia",
    "sg:classifiers":[
        {
            "category":"Travel",
            "subcategory":"Hotels & Motels",
            "type":"Entertainment"
        }
    ],
    "sg:phone":"+61 7 4746 3144",
    "sg:postcode":"4829",
    "sg:province":"QLD",
    "sg:tags":[
        "accommodation"
    ],
    "wof:name":"Australian Hotel",
    "wof:placetype":"venue"
},
  "geometry": {"coordinates":[139.90606700000001,-22.911766],"type":"Point"}
}