{
  "type": "Feature",
  "properties": {
    "iso:country":"AU",
    "sg:address":"PO Box 3720",
    "sg:city":"Caloundra",
    "sg:classifiers":[
        {
            "category":"Professional",
            "subcategory":"Detective & Security Services",
            "type":"Services"
        }
    ],
    "sg:phone":"+61 419 774 650",
    "sg:postcode":"4551",
    "sg:province":"QLD",
    "sg:tags":[
        "consultant",
        "system"
    ],
    "wof:name":"Soundalarms",
    "wof:placetype":"venue"
},
  "geometry": {"coordinates":[153.124755859,-26.7936191559],"type":"Point"}
}