{
  "type": "Feature",
  "properties": {
    "addr:full":"373 Wagga Rd Lavington NSW 2641",
    "addr:housenumber":"373",
    "addr:postcode":"2641",
    "addr:street":"Wagga Rd",
    "iso:country":"AU",
    "sg:address":"373 Wagga Rd",
    "sg:city":"Lavington",
    "sg:classifiers":[
        {
            "category":"Autos & Motor Vehicles",
            "subcategory":"Fuel & Gas Station",
            "type":"Retail Goods"
        }
    ],
    "sg:phone":"+61 2 6040 1311",
    "sg:postcode":"2641",
    "sg:province":"NSW",
    "wof:name":"Caltex",
    "wof:placetype":"venue"
},
  "geometry": {"coordinates":[146.96353149399999,-36.0374450684],"type":"Point"}
}