{
  "type": "Feature",
  "properties": {
    "addr:full":"3 Jellico St Proston QLD 4613",
    "addr:housenumber":"3",
    "addr:postcode":"4613",
    "addr:street":"Jellico St",
    "iso:country":"AU",
    "sg:address":"3 Jellico St",
    "sg:city":"Proston",
    "sg:classifiers":[
        {
            "category":"Building & Trades",
            "subcategory":"Landscaping Services",
            "type":"Services"
        }
    ],
    "sg:phone":"+61 7 4168 9210",
    "sg:postcode":"4613",
    "sg:province":"QLD",
    "sg:tags":[
        "grazier"
    ],
    "wof:name":"Murray T & J E",
    "wof:placetype":"venue"
},
  "geometry": {"coordinates":[151.59954834000001,-26.1596393585],"type":"Point"}
}