{
  "type": "Feature",
  "properties": {
    "addr:full":"112B Charters Towers Rd Hermit Park QLD 4812",
    "addr:housenumber":"112b",
    "addr:postcode":"4812",
    "addr:street":"Charters Towers Rd",
    "iso:country":"AU",
    "sg:address":"112B Charters Towers Rd",
    "sg:city":"Hermit Park",
    "sg:classifiers":[
        {
            "category":"Personal",
            "subcategory":"Beauty Salon",
            "type":"Services"
        }
    ],
    "sg:phone":"+61 7 4772 2211",
    "sg:postcode":"4812",
    "sg:province":"QLD",
    "sg:tags":[
        "hairdresser"
    ],
    "wof:name":"Teddi's Hairdressing & Barber Shop",
    "wof:placetype":"venue"
},
  "geometry": {"coordinates":[146.800735,-19.276768],"type":"Point"}
}