{
  "type": "Feature",
  "properties": {
    "addr:full":"123 Fern St Gerringong NSW 2534",
    "addr:housenumber":"123",
    "addr:postcode":"2534",
    "addr:street":"Fern St",
    "iso:country":"AU",
    "sg:address":"123 Fern St",
    "sg:city":"Gerringong",
    "sg:classifiers":[
        {
            "category":"Food & Beverages",
            "subcategory":"Bakery",
            "type":"Retail Goods"
        }
    ],
    "sg:phone":"+61 2 4234 2311",
    "sg:postcode":"2534",
    "sg:province":"NSW",
    "sg:tags":[
        "baker"
    ],
    "wof:name":"Jocks Bakery & Cafe",
    "wof:placetype":"venue"
},
  "geometry": {"coordinates":[150.827194214,-34.74634552],"type":"Point"}
}