{
  "type": "Feature",
  "properties": {
    "addr:full":"53 Octavia St Mornington VIC 3931",
    "addr:housenumber":"53",
    "addr:postcode":"3931",
    "addr:street":"Octavia St",
    "iso:country":"AU",
    "sg:address":"53 Octavia St",
    "sg:city":"Mornington",
    "sg:classifiers":[
        {
            "category":"Manufacturing",
            "subcategory":"Food",
            "type":"Manufacturing & Wholesale Goods"
        }
    ],
    "sg:phone":"+61 3 5977 2186",
    "sg:postcode":"3931",
    "sg:province":"VIC",
    "sg:tags":[
        "function",
        "catering"
    ],
    "wof:name":"Toms Party Food",
    "wof:placetype":"venue"
},
  "geometry": {"coordinates":[145.03903198200001,-38.2207946777],"type":"Point"}
}