{
  "type": "Feature",
  "properties": {
    "addr:full":"45 Watkin St Newtown NSW 2042",
    "addr:housenumber":"45",
    "addr:postcode":"2042",
    "addr:street":"Watkin St",
    "iso:country":"AU",
    "sg:address":"45 Watkin St",
    "sg:city":"Newtown",
    "sg:classifiers":[
        {
            "category":"Professional",
            "subcategory":"Art Services",
            "type":"Services"
        }
    ],
    "sg:phone":"+61 2 9590 9024",
    "sg:postcode":"2042",
    "sg:province":"NSW",
    "sg:tags":[
        "graphic",
        "designer"
    ],
    "wof:name":"Greendot Design",
    "wof:placetype":"venue"
},
  "geometry": {"coordinates":[151.18348700000001,-33.895393],"type":"Point"}
}