{
  "type": "Feature",
  "properties": {
    "addr:full":"61A Nollamara Shopping Centre Nollamara Ave Nollamara WA 6061",
    "addr:housenumber":"61a",
    "addr:postcode":"6061",
    "addr:street":"Nollamara Shopping;Nollamara Ave",
    "iso:country":"AU",
    "sg:address":"61A Nollamara Shopping Centre Nollamara Ave",
    "sg:city":"Nollamara",
    "sg:classifiers":[
        {
            "category":"Shopping",
            "subcategory":"Clothing, Apparel, & Fashions",
            "type":"Retail Goods"
        }
    ],
    "sg:phone":"+61 8 9349 5372",
    "sg:postcode":"6061",
    "sg:province":"WA",
    "sg:tags":[
        "recycled",
        "clothing"
    ],
    "wof:name":"Vinnies Retail Centres",
    "wof:placetype":"venue"
},
  "geometry": {"coordinates":[115.843658447,-31.880821228],"type":"Point"}
}