{
  "type": "Feature",
  "properties": {
    "iso:country":"AU",
    "sg:address":"Shop 3 158 Graceville Ave",
    "sg:city":"Graceville",
    "sg:classifiers":[
        {
            "category":"Personal",
            "subcategory":"Barber",
            "type":"Services"
        }
    ],
    "sg:phone":"+61 7 3379 7574",
    "sg:postcode":"4075",
    "sg:province":"QLD",
    "wof:name":"Riverside Coiffure",
    "wof:placetype":"venue"
},
  "geometry": {"coordinates":[152.98908996599999,-27.5229568481],"type":"Point"}
}