{
  "type": "Feature",
  "properties": {
    "iso:country":"AU",
    "sg:address":"Cnr Maryborough & George Sts",
    "sg:city":"Bundaberg",
    "sg:classifiers":[
        {
            "category":"Insurance",
            "subcategory":"Insurance Agent",
            "type":"Services"
        }
    ],
    "sg:phone":"+61 7 4153 5366",
    "sg:postcode":"4670",
    "sg:province":"QLD",
    "sg:tags":[
        "broker"
    ],
    "wof:name":"Allen, Rickard & Hatte Insurance Brokers Pty Ltd",
    "wof:placetype":"venue"
},
  "geometry": {"coordinates":[152.34671020499999,-24.8670425415],"type":"Point"}
}