{
  "type": "Feature",
  "properties": {
    "addr:full":"15- 17 Orange Ave Mildura VIC 3500",
    "addr:housenumber":"17",
    "addr:postcode":"3500",
    "addr:street":"Orange Ave",
    "iso:country":"AU",
    "sg:address":"15- 17 Orange Ave",
    "sg:city":"Mildura",
    "sg:classifiers":[
        {
            "category":"Communications",
            "subcategory":"News Services",
            "type":"Services"
        }
    ],
    "sg:phone":"+61 3 5023 3663",
    "sg:postcode":"3500",
    "sg:province":"VIC",
    "sg:tags":[
        "information",
        "tourist",
        "attractions"
    ],
    "wof:name":"Putt Putt Mildura",
    "wof:placetype":"venue"
},
  "geometry": {"coordinates":[142.166213989,-34.185459137],"type":"Point"}
}