{
  "type": "Feature",
  "properties": {
    "iso:country":"AU",
    "sg:address":"165 McKinnon Rd",
    "sg:city":"McKinnon",
    "sg:classifiers":[
        {
            "category":"Personal",
            "subcategory":"Beauty Salon",
            "type":"Services"
        }
    ],
    "sg:phone":"+61 3 9578 6754",
    "sg:postcode":"3204",
    "sg:province":"VIC",
    "wof:name":"Body Magic",
    "wof:placetype":"venue"
},
  "geometry": {"coordinates":[145.037766,-37.910851],"type":"Point"}
}