{
  "type": "Feature",
  "properties": {
    "addr:full":"PO Box 9048 Wyoming NSW 2250",
    "addr:postcode":"2250",
    "iso:country":"AU",
    "sg:address":"PO Box 9048",
    "sg:city":"Wyoming",
    "sg:classifiers":[
        {
            "category":"Building & Trades",
            "subcategory":"Cleaning & Sanitation",
            "type":"Services"
        }
    ],
    "sg:phone":"+61 2 4329 2126",
    "sg:postcode":"2250",
    "sg:province":"NSW",
    "sg:tags":[
        "window"
    ],
    "wof:name":"Squeaky Clean",
    "wof:placetype":"venue"
},
  "geometry": {"coordinates":[151.34925842300001,-33.4094390869],"type":"Point"}
}