{
  "type": "Feature",
  "properties": {
    "addr:full":"74- 76 Industrial Drv Braeside VIC 3195",
    "addr:housenumber":"76",
    "addr:postcode":"3195",
    "addr:street":"Industrial Drv",
    "iso:country":"AU",
    "sg:address":"74- 76 Industrial Drv",
    "sg:city":"Braeside",
    "sg:classifiers":[
        {
            "category":"Building & Trades",
            "subcategory":"Landscaping Services",
            "type":"Services"
        }
    ],
    "sg:phone":"+61 3 9590 9424",
    "sg:postcode":"3195",
    "sg:province":"VIC",
    "sg:tags":[
        "designer",
        "landscape",
        "contractor"
    ],
    "wof:name":"Envirostyle Landscape Design Construction",
    "wof:placetype":"venue"
},
  "geometry": {"coordinates":[145.11256408700001,-38.007106781],"type":"Point"}
}