{
  "type": "Feature",
  "properties": {
    "addr:full":"6 Lime Ave Balwyn North VIC 3104",
    "addr:housenumber":"6",
    "addr:postcode":"3104",
    "addr:street":"Lime Ave",
    "iso:country":"AU",
    "sg:address":"6 Lime Ave",
    "sg:city":"Balwyn North",
    "sg:classifiers":[
        {
            "category":"Professional",
            "subcategory":"Detective & Security Services",
            "type":"Services"
        }
    ],
    "sg:phone":"+61 3 9857 5879",
    "sg:postcode":"3104",
    "sg:province":"VIC",
    "sg:tags":[
        "protective",
        "rustproofing"
    ],
    "wof:name":"Pro-Tec Coatings",
    "wof:placetype":"venue"
},
  "geometry": {"coordinates":[145.10020446799999,-37.7941169739],"type":"Point"}
}