{
  "type": "Feature",
  "properties": {
    "addr:full":"48 B Brunswick Rd Brunswick East VIC 3057",
    "addr:housenumber":"48 b",
    "addr:postcode":"3057",
    "addr:street":"Brunswick Rd",
    "iso:country":"AU",
    "sg:address":"48 B Brunswick Rd",
    "sg:city":"Brunswick East",
    "sg:classifiers":[
        {
            "category":"Food & Beverages",
            "subcategory":"Specialty",
            "type":"Retail Goods"
        }
    ],
    "sg:phone":"+61 3 9387 5279",
    "sg:postcode":"3057",
    "sg:province":"VIC",
    "sg:tags":[
        "product",
        "health"
    ],
    "wof:name":"First Hill Networking",
    "wof:placetype":"venue"
},
  "geometry": {"coordinates":[144.9765625,-37.7789039612],"type":"Point"}
}