{
  "type": "Feature",
  "properties": {
    "addr:full":"184 Boundary Rd Geelong East VIC 3219",
    "addr:housenumber":"184",
    "addr:postcode":"3219",
    "addr:street":"Boundary Rd",
    "iso:country":"AU",
    "sg:address":"184 Boundary Rd",
    "sg:city":"Geelong East",
    "sg:classifiers":[
        {
            "category":"Education",
            "subcategory":"School",
            "type":"Public Place"
        }
    ],
    "sg:phone":"+61 3 5248 4885",
    "sg:postcode":"3219",
    "sg:province":"VIC",
    "sg:tags":[
        "state",
        "except",
        "nsw"
    ],
    "wof:name":"Geelong East Primary School",
    "wof:placetype":"venue"
},
  "geometry": {"coordinates":[144.383255005,-38.17445755],"type":"Point"}
}