{
  "type": "Feature",
  "properties": {
    "iso:country":"AU",
    "sg:address":"274 Shepherds Hill Rd",
    "sg:city":"Eden Hills",
    "sg:classifiers":[
        {
            "category":"Personal",
            "subcategory":"Beauty Salon",
            "type":"Services"
        }
    ],
    "sg:phone":"+61 8 8278 3175",
    "sg:postcode":"5050",
    "sg:province":"SA",
    "sg:tags":[
        "hairdresser"
    ],
    "wof:name":"Hair Ways Hair Designers",
    "wof:placetype":"venue"
},
  "geometry": {"coordinates":[138.60389699999999,-35.026302],"type":"Point"}
}