{
  "type": "Feature",
  "properties": {
    "iso:country":"AU",
    "sg:address":"2- 8 York St",
    "sg:city":"South Melbourne",
    "sg:classifiers":[
        {
            "category":"Building & Trades",
            "subcategory":"Equipment Rental",
            "type":"Services"
        }
    ],
    "sg:phone":"+61 3 9645 5144",
    "sg:postcode":"3205",
    "sg:province":"VIC",
    "sg:tags":[
        "supply",
        "catering"
    ],
    "wof:name":"Macmont Hospitality Supplies",
    "wof:placetype":"venue"
},
  "geometry": {"coordinates":[144.963043,-37.829632],"type":"Point"}
}