{
  "type": "Feature",
  "properties": {
    "addr:full":"10 Terama St Bilgola Plateau NSW 2107",
    "addr:housenumber":"10",
    "addr:postcode":"2107",
    "addr:street":"Terama St",
    "iso:country":"AU",
    "sg:address":"10 Terama St",
    "sg:city":"Bilgola Plateau",
    "sg:classifiers":[
        {
            "category":"Shopping",
            "subcategory":"Stationery & Office Supplies",
            "type":"Retail Goods"
        }
    ],
    "sg:phone":"+61 2 9918 3998",
    "sg:postcode":"2107",
    "sg:province":"NSW",
    "wof:name":"All Computer Supplies (Wholesale) Pty Ltd",
    "wof:placetype":"venue"
},
  "geometry": {"coordinates":[151.31256103499999,-33.6477661133],"type":"Point"}
}