{
  "type": "Feature",
  "properties": {
    "iso:country":"AU",
    "sg:address":"Level 57",
    "sg:city":", Martin Place, MLC Centre Sydney",
    "sg:classifiers":[
        {
            "category":"Organizations",
            "subcategory":"Professional Association",
            "type":"Services"
        }
    ],
    "sg:phone":"+61 1800 632 341",
    "sg:postcode":"2000",
    "sg:province":"NSW",
    "sg:tags":[
        "web",
        "internet"
    ],
    "wof:name":"Vivid Group",
    "wof:placetype":"venue"
},
  "geometry": {"coordinates":[151.210845947,-33.8678855896],"type":"Point"}
}