{
  "type": "Feature",
  "properties": {
    "addr:full":"448 Parramatta Rd Petersham NSW 2049",
    "addr:housenumber":"448",
    "addr:postcode":"2049",
    "addr:street":"Parramatta Rd",
    "iso:country":"AU",
    "sg:address":"448 Parramatta Rd",
    "sg:city":"Petersham",
    "sg:classifiers":[
        {
            "category":"Professional",
            "subcategory":"Accounting & Tax Preparation",
            "type":"Services"
        }
    ],
    "sg:phone":"+61 2 9560 9344",
    "sg:postcode":"2049",
    "sg:province":"NSW",
    "sg:tags":[
        "accountant",
        "auditor"
    ],
    "wof:name":"Con Koufos",
    "wof:placetype":"venue"
},
  "geometry": {"coordinates":[151.15934799999999,-33.888012],"type":"Point"}
}