{
  "type": "Feature",
  "properties": {
    "iso:country":"AU",
    "sg:address":"715 Bessi Creek Rd",
    "sg:city":"Nar Nar Goon North",
    "sg:classifiers":[
        {
            "category":"Home & Garden",
            "subcategory":"Household Appliances",
            "type":"Retail Goods"
        }
    ],
    "sg:phone":"+61 428 396 642",
    "sg:postcode":"3812",
    "sg:province":"VIC",
    "sg:tags":[
        "heating",
        "system"
    ],
    "wof:name":"Home Climate Controllers",
    "wof:placetype":"venue"
},
  "geometry": {"coordinates":[145.557175,-38.009163],"type":"Point"}
}