{
  "type": "Feature",
  "properties": {
    "addr:full":"Shop 10 350 Taylors Rd Delahey VIC 3037",
    "addr:housenumber":"shop 10 350",
    "addr:postcode":"3037",
    "addr:street":"Taylors Rd",
    "iso:country":"AU",
    "sg:address":"Shop 10 350 Taylors Rd",
    "sg:city":"Delahey",
    "sg:classifiers":[
        {
            "category":"Communications",
            "subcategory":"Film & Video Production",
            "type":"Services"
        }
    ],
    "sg:phone":"+61 3 9356 0488",
    "sg:postcode":"3037",
    "sg:province":"VIC",
    "sg:tags":[
        "dvd",
        "library"
    ],
    "wof:name":"Total E Flicks",
    "wof:placetype":"venue"
},
  "geometry": {"coordinates":[144.77032500000001,-37.726089],"type":"Point"}
}