{
  "type": "Feature",
  "properties": {
    "addr:full":"168 Molesworth St Lismore NSW 2480",
    "addr:housenumber":"168",
    "addr:postcode":"2480",
    "addr:street":"Molesworth St",
    "iso:country":"AU",
    "sg:address":"168 Molesworth St",
    "sg:city":"Lismore",
    "sg:classifiers":[
        {
            "category":"Shopping",
            "subcategory":"Clothing, Apparel, & Fashions",
            "type":"Retail Goods"
        }
    ],
    "sg:phone":"+61 2 6621 4591",
    "sg:postcode":"2480",
    "sg:province":"NSW",
    "sg:tags":[
        "lady",
        "wear"
    ],
    "wof:name":"Tahiti Hut",
    "wof:placetype":"venue"
},
  "geometry": {"coordinates":[153.27441406200001,-28.8105583191],"type":"Point"}
}