{
  "type": "Feature",
  "properties": {
    "addr:full":"103 Corio St Geelong VIC 3220",
    "addr:housenumber":"103",
    "addr:postcode":"3220",
    "addr:street":"Corio St",
    "iso:country":"AU",
    "sg:address":"103 Corio St",
    "sg:city":"Geelong",
    "sg:classifiers":[
        {
            "category":"Social Services",
            "subcategory":"Adult Care",
            "type":"Services"
        }
    ],
    "sg:phone":"+61 3 5272 4732",
    "sg:postcode":"3220",
    "sg:province":"VIC",
    "sg:tags":[
        "aged"
    ],
    "wof:name":"City Of Greater Geelong",
    "wof:placetype":"venue"
},
  "geometry": {"coordinates":[144.36506700000001,-38.147182],"type":"Point"}
}