{
  "type": "Feature",
  "properties": {
    "iso:country":"AU",
    "sg:address":"PO Box 2045",
    "sg:city":"South Melbourne",
    "sg:classifiers":[
        {
            "category":"Home & Garden",
            "subcategory":"Building Materials",
            "type":"Retail Goods"
        }
    ],
    "sg:phone":"+61 3 9315 7886",
    "sg:postcode":"8867",
    "sg:province":"VIC",
    "sg:tags":[
        "shutter",
        "roller",
        "grille"
    ],
    "wof:name":"A Southshore Garage Doors",
    "wof:placetype":"venue"
},
  "geometry": {"coordinates":[144.960174561,-37.8345489502],"type":"Point"}
}