{
  "type": "Feature",
  "properties": {
    "iso:country":"AU",
    "sg:address":"41 Knutsford St",
    "sg:city":"Chermside West",
    "sg:classifiers":[
        {
            "category":"Building & Trades",
            "subcategory":"Plumbing",
            "type":"Services"
        }
    ],
    "sg:phone":"+61 7 3359 5138",
    "sg:postcode":"4032",
    "sg:province":"QLD",
    "sg:tags":[
        "plumber",
        "gasfitters"
    ],
    "wof:name":"Ford J & S Plumbing Pty Ltd",
    "wof:placetype":"venue"
},
  "geometry": {"coordinates":[153.01606799999999,-27.387075],"type":"Point"}
}