{
  "type": "Feature",
  "properties": {
    "addr:full":"132 Alcock St Maddington WA 6109",
    "addr:housenumber":"132",
    "addr:postcode":"6109",
    "addr:street":"Alcock St",
    "iso:country":"AU",
    "sg:address":"132 Alcock St",
    "sg:city":"Maddington",
    "sg:classifiers":[
        {
            "category":"Retail",
            "subcategory":"Funeral Services",
            "type":"Services"
        }
    ],
    "sg:phone":"+61 8 9452 0452",
    "sg:postcode":"6109",
    "sg:province":"WA",
    "sg:tags":[
        "director"
    ],
    "wof:name":"Fallen Riders Motor Cycle Funeral Directors",
    "wof:placetype":"venue"
},
  "geometry": {"coordinates":[116.001289368,-32.047618866],"type":"Point"}
}