{
  "type": "Feature",
  "properties": {
    "addr:full":"61 Berwick St Fortitude Valley QLD 4006",
    "addr:housenumber":"61",
    "addr:postcode":"4006",
    "addr:street":"Berwick St",
    "iso:country":"AU",
    "sg:address":"61 Berwick St",
    "sg:city":"Fortitude Valley",
    "sg:classifiers":[
        {
            "category":"Banks & Credit Unions",
            "subcategory":"Investment Brokerage",
            "type":"Services"
        }
    ],
    "sg:phone":"+61 7 3360 8500",
    "sg:postcode":"4006",
    "sg:province":"QLD",
    "sg:tags":[
        "finance",
        "broker"
    ],
    "wof:name":"RPM Rental & Leasing",
    "wof:placetype":"venue"
},
  "geometry": {"coordinates":[153.037384033,-27.4587516785],"type":"Point"}
}