{
  "type": "Feature",
  "properties": {
    "addr:full":"7 Seventh St Granville NSW 2142",
    "addr:housenumber":"7",
    "addr:postcode":"2142",
    "addr:street":"Seventh St",
    "iso:country":"AU",
    "sg:address":"7 Seventh St",
    "sg:city":"Granville",
    "sg:classifiers":[
        {
            "category":"Building & Trades",
            "subcategory":"Plumbing",
            "type":"Services"
        }
    ],
    "sg:phone":"+61 410 405 871",
    "sg:postcode":"2142",
    "sg:province":"NSW",
    "sg:tags":[
        "plumber",
        "gasfitters"
    ],
    "wof:name":"Mr h20 Pty Ltd",
    "wof:placetype":"venue"
},
  "geometry": {"coordinates":[151.01560974099999,-33.8428382874],"type":"Point"}
}