{
  "type": "Feature",
  "properties": {
    "addr:full":"T9B 44 George St Cmplx 97- 107 King St Sydney NSW 2000",
    "addr:housenumber":"44;97 107",
    "addr:postcode":"2000",
    "addr:street":"T9B;George St Cmplx;King St",
    "iso:country":"AU",
    "sg:address":"T9B 44 George St Cmplx 97- 107 King St",
    "sg:city":"Sydney",
    "sg:classifiers":[
        {
            "category":"Shopping",
            "subcategory":"Clothing, Apparel, & Fashions",
            "type":"Retail Goods"
        }
    ],
    "sg:phone":"+61 2 9231 0047",
    "sg:postcode":"2000",
    "sg:province":"NSW",
    "sg:tags":[
        "boutique"
    ],
    "wof:name":"Armani Exchange",
    "wof:placetype":"venue"
},
  "geometry": {"coordinates":[151.20750427199999,-33.8689002991],"type":"Point"}
}