{
  "type": "Feature",
  "properties": {
    "addr:full":"Port Broughton Rd Port Pirie SA 5540",
    "addr:postcode":"5540",
    "addr:street":"Broughton Rd",
    "iso:country":"AU",
    "sg:address":"Port Broughton Rd",
    "sg:city":"Port Pirie",
    "sg:classifiers":[
        {
            "category":"Building & Trades",
            "subcategory":"Construction",
            "type":"Services"
        }
    ],
    "sg:phone":"+61 8 8632 6031",
    "sg:postcode":"5540",
    "sg:province":"SA",
    "sg:tags":[
        "contractor"
    ],
    "wof:name":"Barry Ramsay Constructions Pty Ltd",
    "wof:placetype":"venue"
},
  "geometry": {"coordinates":[137.96635437,-33.2300682068],"type":"Point"}
}