{
  "type": "Feature",
  "properties": {
    "iso:country":"AU",
    "sg:address":"36 Gordon St",
    "sg:city":"Wonthaggi",
    "sg:classifiers":[
        {
            "category":"Building & Trades",
            "subcategory":"Equipment Rental",
            "type":"Services"
        }
    ],
    "sg:phone":"+61 3 5672 4177",
    "sg:postcode":"3995",
    "sg:province":"VIC",
    "sg:tags":[
        "supply",
        "catering"
    ],
    "wof:name":"Gippsland Catering Equipment",
    "wof:placetype":"venue"
},
  "geometry": {"coordinates":[145.590057,-38.591652],"type":"Point"}
}