{
  "type": "Feature",
  "properties": {
    "addr:full":"207 Monbulk Rd Silvan VIC 3795",
    "addr:housenumber":"207",
    "addr:postcode":"3795",
    "addr:street":"Monbulk Rd",
    "iso:country":"AU",
    "sg:address":"207 Monbulk Rd",
    "sg:city":"Silvan",
    "sg:classifiers":[
        {
            "category":"Shopping",
            "subcategory":"Antiques",
            "type":"Retail Goods"
        }
    ],
    "sg:phone":"+61 3 9737 9010",
    "sg:postcode":"3795",
    "sg:province":"VIC",
    "wof:name":"Tulip Antiques",
    "wof:placetype":"venue"
},
  "geometry": {"coordinates":[145.41336059599999,-37.8218002319],"type":"Point"}
}