{
  "type": "Feature",
  "properties": {
    "iso:country":"AU",
    "sg:address":"Shop 1/ 30 Hall",
    "sg:city":"Moonee Ponds",
    "sg:classifiers":[
        {
            "category":"Travel",
            "subcategory":"Travel Agent",
            "type":"Entertainment"
        }
    ],
    "sg:phone":"+61 3 9370 7855",
    "sg:postcode":"3039",
    "sg:province":"VIC",
    "sg:tags":[
        "consultant"
    ],
    "wof:name":"Worldvision Travel Pty Ltd",
    "wof:placetype":"venue"
},
  "geometry": {"coordinates":[144.921326,-37.7658],"type":"Point"}
}