{
  "type": "Feature",
  "properties": {
    "addr:full":"6 Cope St Preston VIC 3072",
    "addr:housenumber":"6",
    "addr:postcode":"3072",
    "addr:street":"Cope St",
    "iso:country":"AU",
    "sg:address":"6 Cope St",
    "sg:city":"Preston",
    "sg:classifiers":[
        {
            "category":"Building & Trades",
            "subcategory":"Equipment Rental",
            "type":"Services"
        }
    ],
    "sg:phone":"+61 409 161 523",
    "sg:postcode":"3072",
    "sg:province":"VIC",
    "sg:tags":[
        "crane",
        "hire"
    ],
    "wof:name":"Formhire Pty Ltd",
    "wof:placetype":"venue"
},
  "geometry": {"coordinates":[145.027954102,-37.7502288818],"type":"Point"}
}