{
  "type": "Feature",
  "properties": {
    "addr:full":"8 Middleton Rd Cromer NSW 2099",
    "addr:housenumber":"8",
    "addr:postcode":"2099",
    "addr:street":"Middleton Rd",
    "iso:country":"AU",
    "sg:address":"8 Middleton Rd",
    "sg:city":"Cromer",
    "sg:classifiers":[
        {
            "category":"Building & Trades",
            "subcategory":"Construction",
            "type":"Services"
        }
    ],
    "sg:phone":"+61 424 855 204",
    "sg:postcode":"2099",
    "sg:province":"NSW",
    "sg:tags":[
        "scaffolding"
    ],
    "wof:name":"AMA Scaffolding Pty Ltd",
    "wof:placetype":"venue"
},
  "geometry": {"coordinates":[151.28109741200001,-33.7350921631],"type":"Point"}
}