{
  "type": "Feature",
  "properties": {
    "addr:full":"69 Duchess St Busselton WA 6280",
    "addr:housenumber":"69",
    "addr:postcode":"6280",
    "addr:street":"Duchess St",
    "iso:country":"AU",
    "sg:address":"69 Duchess St",
    "sg:city":"Busselton",
    "sg:classifiers":[
        {
            "category":"Health Services",
            "subcategory":"Doctor",
            "type":"Services"
        }
    ],
    "sg:phone":"+61 8 9752 4122",
    "sg:postcode":"6280",
    "sg:province":"WA",
    "sg:tags":[
        "medical",
        "practitioner"
    ],
    "wof:name":"DUCHESS MEDICAL PRACTICE",
    "wof:placetype":"venue"
},
  "geometry": {"coordinates":[115.346237183,-33.6483268738],"type":"Point"}
}