{
  "type": "Feature",
  "properties": {
    "addr:full":"10 High St Toowong QLD 4066",
    "addr:housenumber":"10",
    "addr:postcode":"4066",
    "addr:street":"High St",
    "iso:country":"AU",
    "sg:address":"10 High St",
    "sg:city":"Toowong",
    "sg:classifiers":[
        {
            "category":"Food & Beverages",
            "subcategory":"Liquor & Beverages",
            "type":"Retail Goods"
        }
    ],
    "sg:phone":"+61 7 3371 2111",
    "sg:postcode":"4066",
    "sg:province":"QLD",
    "sg:tags":[
        "store"
    ],
    "wof:name":"BWS Liquor Stores",
    "wof:placetype":"venue"
},
  "geometry": {"coordinates":[152.992675781,-27.4863357544],"type":"Point"}
}