{
  "type": "Feature",
  "properties": {
    "iso:country":"AU",
    "sg:address":"67 St John's Ave",
    "sg:city":"Mangerton",
    "sg:classifiers":[
        {
            "category":"Health Services",
            "subcategory":"Dentist",
            "type":"Services"
        }
    ],
    "sg:phone":"+61 2 4225 2525",
    "sg:postcode":"2500",
    "sg:province":"NSW",
    "sg:tags":[
        "technician",
        "dental"
    ],
    "wof:name":"Malcolm McGovern",
    "wof:placetype":"venue"
},
  "geometry": {"coordinates":[150.885345,-34.433838],"type":"Point"}
}