{
  "type": "Feature",
  "properties": {
    "addr:full":"69 Brady Rd Dandenong North VIC 3175",
    "addr:housenumber":"69",
    "addr:postcode":"3175",
    "addr:street":"Brady Rd",
    "iso:country":"AU",
    "sg:address":"69 Brady Rd",
    "sg:city":"Dandenong North",
    "sg:classifiers":[
        {
            "category":"Building & Trades",
            "subcategory":"Construction",
            "type":"Services"
        }
    ],
    "sg:phone":"+61 3 9701 0755",
    "sg:postcode":"3175",
    "sg:province":"VIC",
    "sg:tags":[
        "pool",
        "swimming"
    ],
    "wof:name":"P.J. Pool Plastering",
    "wof:placetype":"venue"
},
  "geometry": {"coordinates":[145.21496582,-37.9541435242],"type":"Point"}
}