{
  "type": "Feature",
  "properties": {
    "iso:country":"AU",
    "sg:address":"Shop 1, Pelican\ufffds Nest Shoppin 149 Colburn Ave",
    "sg:city":"Victoria Point",
    "sg:classifiers":[
        {
            "category":"Real Estate",
            "subcategory":"Real Estate Agent",
            "type":"Services"
        }
    ],
    "sg:phone":"+61 7 3207 9700",
    "sg:postcode":"4165",
    "sg:province":"QLD",
    "wof:name":"Raine & Horne Victoria Point",
    "wof:placetype":"venue"
},
  "geometry": {"coordinates":[153.30661010700001,-27.5865001678],"type":"Point"}
}