{
  "type": "Feature",
  "properties": {
    "iso:country":"AU",
    "sg:address":"Shop 7/ 11 Surfers Ave",
    "sg:city":"Mermaid Beach",
    "sg:classifiers":[
        {
            "category":"Professional",
            "subcategory":"Printing & Photocopies",
            "type":"Services"
        }
    ],
    "sg:phone":"+61 7 5572 5366",
    "sg:postcode":"4218",
    "sg:province":"QLD",
    "sg:tags":[
        "embroidery"
    ],
    "wof:name":"In 2 Sports Embroidery",
    "wof:placetype":"venue"
},
  "geometry": {"coordinates":[153.43208313,-28.0390434265],"type":"Point"}
}