{
  "type": "Feature",
  "properties": {
    "addr:full":"7 Eastern Rd Traralgon VIC 3844",
    "addr:housenumber":"7",
    "addr:postcode":"3844",
    "addr:street":"Eastern Rd",
    "iso:country":"AU",
    "sg:address":"7 Eastern Rd",
    "sg:city":"Traralgon",
    "sg:classifiers":[
        {
            "category":"Wholesale",
            "subcategory":"Machinery & Supplies",
            "type":"Manufacturing & Wholesale Goods"
        }
    ],
    "sg:phone":"+61 3 5174 1700",
    "sg:postcode":"3844",
    "sg:province":"VIC",
    "sg:tags":[
        "equipment",
        "hydraulic"
    ],
    "wof:name":"Valley Hydraulics",
    "wof:placetype":"venue"
},
  "geometry": {"coordinates":[146.562225342,-38.1895141602],"type":"Point"}
}