{
  "type": "Feature",
  "properties": {
    "iso:country":"AU",
    "sg:address":"178 Whitehorse Rd",
    "sg:city":"Nunawading",
    "sg:classifiers":[
        {
            "category":"Home & Garden",
            "subcategory":"Carpets & Floor Coverings",
            "type":"Retail Goods"
        }
    ],
    "sg:phone":"+61 3 9877 5566",
    "sg:postcode":"3131",
    "sg:province":"VIC",
    "sg:tags":[
        "tile",
        "wall"
    ],
    "wof:name":"San Marco Ceramics Pty Ltd",
    "wof:placetype":"venue"
},
  "geometry": {"coordinates":[145.15861511200001,-37.8181037903],"type":"Point"}
}