{
  "type": "Feature",
  "properties": {
    "iso:country":"AU",
    "sg:address":"1310 Lytton Rd",
    "sg:city":"Hemmant",
    "sg:classifiers":[
        {
            "category":"Wholesale",
            "subcategory":"Furniture",
            "type":"Manufacturing & Wholesale Goods"
        }
    ],
    "sg:phone":"+61 7 3390 4011",
    "sg:postcode":"4174",
    "sg:province":"QLD",
    "sg:tags":[
        "wholesaler",
        "mfrs"
    ],
    "wof:name":"Tradway Furniture Pty Ltd",
    "wof:placetype":"venue"
},
  "geometry": {"coordinates":[153.12271118199999,-27.444934845],"type":"Point"}
}