{
  "type": "Feature",
  "properties": {
    "addr:full":"108 - 110 Sunnyholt Rd Blacktown NSW 2148",
    "addr:housenumber":"110",
    "addr:postcode":"2148",
    "addr:street":"Sunnyholt Rd",
    "iso:country":"AU",
    "sg:address":"108 - 110 Sunnyholt Rd",
    "sg:city":"Blacktown",
    "sg:classifiers":[
        {
            "category":"Autos & Motor Vehicles",
            "subcategory":"Automobile Sales",
            "type":"Retail Goods"
        }
    ],
    "sg:phone":"+61 2 9839 9000",
    "sg:postcode":"2148",
    "sg:province":"NSW",
    "sg:tags":[
        "car",
        "new"
    ],
    "wof:name":"Lander Suzuki",
    "wof:placetype":"venue"
},
  "geometry": {"coordinates":[150.914352417,-33.7570724487],"type":"Point"}
}