{
  "type": "Feature",
  "properties": {
    "addr:full":"1 Ramsay St Port Vincent SA 5581",
    "addr:housenumber":"1",
    "addr:postcode":"5581",
    "addr:street":"Ramsay St",
    "iso:country":"AU",
    "sg:address":"1 Ramsay St",
    "sg:city":"Port Vincent",
    "sg:classifiers":[
        {
            "category":"Home & Garden",
            "subcategory":"Building Materials",
            "type":"Retail Goods"
        }
    ],
    "sg:phone":"+61 8 8853 7113",
    "sg:postcode":"5581",
    "sg:province":"SA",
    "sg:tags":[
        "shutter",
        "roller",
        "grille"
    ],
    "wof:name":"York Carpets",
    "wof:placetype":"venue"
},
  "geometry": {"coordinates":[137.861053467,-34.7783508301],"type":"Point"}
}