{
  "type": "Feature",
  "properties": {
    "addr:full":"Upper Level, Griffith Shops, 14 Barker St Griffith ACT 2603",
    "addr:housenumber":"14",
    "addr:postcode":"2603",
    "addr:street":"Barker St",
    "iso:country":"AU",
    "sg:address":"Upper Level, Griffith Shops, 14 Barker St",
    "sg:city":"Griffith",
    "sg:classifiers":[
        {
            "category":"Health Services",
            "subcategory":"Health Practitioner",
            "type":"Services"
        }
    ],
    "sg:phone":"+61 2 6295 0400",
    "sg:postcode":"2603",
    "sg:province":"ACT",
    "sg:tags":[
        "acupuncture"
    ],
    "wof:name":"Smith Wesley",
    "wof:placetype":"venue"
},
  "geometry": {"coordinates":[149.14201355,-35.3278808594],"type":"Point"}
}