{
  "type": "Feature",
  "properties": {
    "iso:country":"AU",
    "sg:address":"25 Rhonda Ave",
    "sg:city":"Willetton",
    "sg:classifiers":[
        {
            "category":"Professional",
            "subcategory":"Printing & Photocopies",
            "type":"Services"
        }
    ],
    "sg:phone":"+61 8 9457 2977",
    "sg:postcode":"6155",
    "sg:province":"WA",
    "sg:tags":[
        "publishing",
        "desktop"
    ],
    "wof:name":"Editing & Design",
    "wof:placetype":"venue"
},
  "geometry": {"coordinates":[115.876488,-32.044571],"type":"Point"}
}