{
  "type": "Feature",
  "properties": {
    "iso:country":"AU",
    "sg:address":"Shop 1/ 72 Florence St",
    "sg:city":"Wynnum",
    "sg:classifiers":[
        {
            "category":"Retail",
            "subcategory":"Laundry & Dry Cleaning",
            "type":"Services"
        }
    ],
    "sg:phone":"+61 7 3348 7272",
    "sg:postcode":"4178",
    "sg:province":"QLD",
    "sg:tags":[
        "manicurist"
    ],
    "wof:name":"Nail Art Designs",
    "wof:placetype":"venue"
},
  "geometry": {"coordinates":[153.17315673799999,-27.4441432953],"type":"Point"}
}