{
  "type": "Feature",
  "properties": {
    "addr:full":"Cnr Westfield & Ypres Rds Westfield WA 6111",
    "addr:postcode":"6111",
    "addr:street":"Cnr Westfield & Ypres Rds",
    "iso:country":"AU",
    "sg:address":"Cnr Westfield & Ypres Rds",
    "sg:city":"Westfield",
    "sg:classifiers":[
        {
            "category":"Food & Beverages",
            "subcategory":"Supermarket",
            "type":"Retail Goods"
        }
    ],
    "sg:phone":"+61 8 9390 9555",
    "sg:postcode":"6111",
    "sg:province":"WA",
    "sg:tags":[
        "grocery",
        "store"
    ],
    "wof:name":"IGA Supermarkets",
    "wof:placetype":"venue"
},
  "geometry": {"coordinates":[116.00124359100001,-32.1200027466],"type":"Point"}
}