{
  "type": "Feature",
  "properties": {
    "addr:full":"8/ 5 Vuko Pl Warriewood NSW 2102",
    "addr:housenumber":"/ 5",
    "addr:postcode":"2102",
    "addr:street":"Vuko Pl",
    "iso:country":"AU",
    "sg:address":"8/ 5 Vuko Pl",
    "sg:city":"Warriewood",
    "sg:classifiers":[
        {
            "category":"Wholesale",
            "subcategory":"Machinery & Supplies",
            "type":"Manufacturing & Wholesale Goods"
        }
    ],
    "sg:phone":"+61 2 9913 8566",
    "sg:postcode":"2102",
    "sg:province":"NSW",
    "sg:tags":[
        "equipment",
        "hydraulic"
    ],
    "wof:name":"International Seal Co Australia Pty Ltd",
    "wof:placetype":"venue"
},
  "geometry": {"coordinates":[151.301727,-33.692806],"type":"Point"}
}