{
  "type": "Feature",
  "properties": {
    "addr:full":"52 North St Richmond VIC 3121",
    "addr:housenumber":"52",
    "addr:postcode":"3121",
    "addr:street":"North St",
    "iso:country":"AU",
    "sg:address":"52 North St",
    "sg:city":"Richmond",
    "sg:classifiers":[
        {
            "category":"Shopping",
            "subcategory":"Beauty & Cosmetics",
            "type":"Retail Goods"
        }
    ],
    "sg:phone":"+61 3 9429 5388",
    "sg:postcode":"3121",
    "sg:province":"VIC",
    "sg:tags":[
        "equipment",
        "salon",
        "supply"
    ],
    "wof:name":"Salonmart",
    "wof:placetype":"venue"
},
  "geometry": {"coordinates":[145.01141357399999,-37.8164710999],"type":"Point"}
}