{
  "type": "Feature",
  "properties": {
    "addr:full":"1/4 227 Leitchs Rd Brendale QLD 4500",
    "addr:housenumber":"/ 4",
    "addr:postcode":"227;4500",
    "addr:street":"Leitchs Rd",
    "iso:country":"AU",
    "sg:address":"1/4 227 Leitchs Rd",
    "sg:city":"Brendale",
    "sg:classifiers":[
        {
            "category":"Manufacturing",
            "subcategory":"Motor Vehicles & Parts",
            "type":"Manufacturing & Wholesale Goods"
        }
    ],
    "sg:phone":"+61 7 3889 9522",
    "sg:postcode":"4500",
    "sg:province":"QLD",
    "sg:tags":[
        "replacement"
    ],
    "wof:name":"Coventry Auto Parts",
    "wof:placetype":"venue"
},
  "geometry": {"coordinates":[152.98051452600001,-27.3218688965],"type":"Point"}
}