{
  "type": "Feature",
  "properties": {
    "addr:full":"Shop 19/26A Lime King St Wharf Sydney NSW 2000",
    "addr:housenumber":"shop 19 / 26a",
    "addr:postcode":"2000",
    "addr:street":"Lime King St",
    "iso:country":"AU",
    "sg:address":"Shop 19/26A Lime King St",
    "sg:city":"Wharf Sydney",
    "sg:classifiers":[
        {
            "category":"Banks & Credit Unions",
            "subcategory":"Financial Services",
            "type":"Services"
        }
    ],
    "sg:phone":"+61 2 9279 2229",
    "sg:postcode":"2000",
    "sg:province":"NSW",
    "sg:tags":[
        "loan",
        "finance",
        "mortgage"
    ],
    "wof:name":"The Deposit Bond Centre",
    "wof:placetype":"venue"
},
  "geometry": {"coordinates":[151.20994567899999,-33.8690834045],"type":"Point"}
}