{
  "type": "Feature",
  "properties": {
    "addr:full":"55 Railway St Corrimal NSW 2518",
    "addr:housenumber":"55",
    "addr:postcode":"2518",
    "addr:street":"Railway St",
    "iso:country":"AU",
    "sg:address":"55 Railway St",
    "sg:city":"Corrimal",
    "sg:classifiers":[
        {
            "category":"Health Services",
            "subcategory":"Health Practitioner",
            "type":"Services"
        }
    ],
    "sg:phone":"+61 2 4285 5016",
    "sg:postcode":"2518",
    "sg:province":"NSW",
    "sg:tags":[
        "physiotherapist"
    ],
    "wof:name":"Mann Timothy W",
    "wof:placetype":"venue"
},
  "geometry": {"coordinates":[150.89982599999999,-34.373592],"type":"Point"}
}