{
  "type": "Feature",
  "properties": {
    "iso:country":"AU",
    "sg:address":"City Square, Level 1, 28-32 Wilson St",
    "sg:city":"Burnie",
    "sg:classifiers":[
        {
            "category":"Banks & Credit Unions",
            "subcategory":"Investment Brokerage",
            "type":"Services"
        }
    ],
    "sg:phone":"+61 3 6432 4706",
    "sg:postcode":"7320",
    "sg:province":"TAS",
    "wof:name":"Oldaker Gerald Financial Services",
    "wof:placetype":"venue"
},
  "geometry": {"coordinates":[145.906448,-41.051453],"type":"Point"}
}