{
  "type": "Feature",
  "properties": {
    "iso:country":"AU",
    "sg:address":"121 Foot St",
    "sg:city":"Frankston",
    "sg:classifiers":[
        {
            "category":"Building & Trades",
            "subcategory":"Landscaping Services",
            "type":"Services"
        }
    ],
    "sg:phone":"+61 3 9783 5738",
    "sg:postcode":"3199",
    "sg:province":"VIC",
    "sg:tags":[
        "designer",
        "landscape",
        "contractor"
    ],
    "wof:name":"Holst David",
    "wof:placetype":"venue"
},
  "geometry": {"coordinates":[145.12689209000001,-38.1666984558],"type":"Point"}
}