{
  "type": "Feature",
  "properties": {
    "iso:country":"AU",
    "sg:address":"Suite 7, Medical Centre 10 Lorraine Ave",
    "sg:city":"Berkeley Vale",
    "sg:classifiers":[
        {
            "category":"Health Services",
            "subcategory":"Dentist",
            "type":"Services"
        }
    ],
    "sg:phone":"+61 2 4388 6377",
    "sg:postcode":"2261",
    "sg:province":"NSW",
    "wof:name":"Hutchison Neil Dr",
    "wof:placetype":"venue"
},
  "geometry": {"coordinates":[151.432495,-33.338757],"type":"Point"}
}