{
  "type": "Feature",
  "properties": {
    "iso:country":"AU",
    "sg:address":"Un 7/ 26 Guinea St",
    "sg:city":"Kogarah",
    "sg:classifiers":[
        {
            "category":"Banks & Credit Unions",
            "subcategory":"Financial Services",
            "type":"Services"
        }
    ],
    "sg:phone":"+61 2 9587 3777",
    "sg:postcode":"2217",
    "sg:province":"NSW",
    "sg:tags":[
        "loan",
        "finance",
        "mortgage"
    ],
    "wof:name":"Sunny Hot Home Loans",
    "wof:placetype":"venue"
},
  "geometry": {"coordinates":[151.129135,-33.963215],"type":"Point"}
}