{
  "type": "Feature",
  "properties": {
    "addr:full":"60 Strelly St Busselton WA 6280",
    "addr:housenumber":"60",
    "addr:postcode":"6280",
    "addr:street":"Strelly St",
    "iso:country":"AU",
    "sg:address":"60 Strelly St",
    "sg:city":"Busselton",
    "sg:classifiers":[
        {
            "category":"Building & Trades",
            "subcategory":"Plumbing",
            "type":"Services"
        }
    ],
    "sg:phone":"+61 8 9752 2224",
    "sg:postcode":"6280",
    "sg:province":"WA",
    "sg:tags":[
        "pump",
        "repairer"
    ],
    "wof:name":"Busselton Pumping Services",
    "wof:placetype":"venue"
},
  "geometry": {"coordinates":[115.35088348399999,-33.6581954956],"type":"Point"}
}