{
  "type": "Feature",
  "properties": {
    "addr:full":"Unit 8/ 8 Metters Pl Wetherill Park NSW 2164",
    "addr:housenumber":"8",
    "addr:postcode":"2164",
    "addr:street":"Metters Pl",
    "iso:country":"AU",
    "sg:address":"Unit 8/ 8 Metters Pl",
    "sg:city":"Wetherill Park",
    "sg:classifiers":[
        {
            "category":"Home & Garden",
            "subcategory":"Building Materials",
            "type":"Retail Goods"
        }
    ],
    "sg:phone":"+61 2 9756 5494",
    "sg:postcode":"2164",
    "sg:province":"NSW",
    "sg:tags":[
        "concrete",
        "additive"
    ],
    "wof:name":"Patterned Concrete Supplies",
    "wof:placetype":"venue"
},
  "geometry": {"coordinates":[150.89401245100001,-33.8475189209],"type":"Point"}
}