{
  "type": "Feature",
  "properties": {
    "addr:full":"123 Burnley St Richmond VIC 3121",
    "addr:housenumber":"123",
    "addr:postcode":"3121",
    "addr:street":"Burnley St",
    "iso:country":"AU",
    "sg:address":"123 Burnley St",
    "sg:city":"Richmond",
    "sg:classifiers":[
        {
            "category":"Fast Food",
            "type":"Food & Drink"
        }
    ],
    "sg:phone":"+61 3 9429 5886",
    "sg:postcode":"3121",
    "sg:province":"VIC",
    "sg:tags":[
        "away",
        "take"
    ],
    "wof:name":"Burnley Take Away",
    "wof:placetype":"venue"
},
  "geometry": {"coordinates":[145.00907898,-37.816242218],"type":"Point"}
}