{
  "type": "Feature",
  "properties": {
    "iso:country":"AU",
    "sg:address":"8/ 57 Robinson St",
    "sg:city":"Dandenong",
    "sg:classifiers":[
        {
            "category":"Health Services",
            "subcategory":"Health Practitioner",
            "type":"Services"
        }
    ],
    "sg:phone":"+61 3 9793 7400",
    "sg:postcode":"3175",
    "sg:province":"VIC",
    "sg:tags":[
        "psychologist"
    ],
    "wof:name":"Kay Angela & Powell Gail",
    "wof:placetype":"venue"
},
  "geometry": {"coordinates":[145.211334228,-37.9844017029],"type":"Point"}
}