{
  "type": "Feature",
  "properties": {
    "addr:full":"5 Jacque Crt Lawnton QLD 4501",
    "addr:housenumber":"5",
    "addr:postcode":"4501",
    "addr:street":"Jacque Crt",
    "iso:country":"AU",
    "sg:address":"5 Jacque Crt",
    "sg:city":"Lawnton",
    "sg:classifiers":[
        {
            "category":"Retail",
            "subcategory":"Driving School",
            "type":"Services"
        }
    ],
    "sg:phone":"+61 1800 681 867",
    "sg:postcode":"4501",
    "sg:province":"QLD",
    "sg:tags":[
        "equipment",
        "pile",
        "contractor"
    ],
    "sg:website":"http://www.pilingcontractors.com.au",
    "wof:name":"Piling Contractors",
    "wof:placetype":"venue"
},
  "geometry": {"coordinates":[152.98971557600001,-27.2866954803],"type":"Point"}
}