{
  "type": "Feature",
  "properties": {
    "iso:country":"AU",
    "sg:address":"Grant St",
    "sg:city":"Goornong",
    "sg:classifiers":[
        {
            "category":"Education",
            "subcategory":"School",
            "type":"Public Place"
        }
    ],
    "sg:phone":"+61 3 5432 2236",
    "sg:postcode":"3557",
    "sg:province":"VIC",
    "sg:tags":[
        "state",
        "except",
        "nsw"
    ],
    "wof:name":"Goornong Primary School",
    "wof:placetype":"venue"
},
  "geometry": {"coordinates":[144.51026916500001,-36.614692688],"type":"Point"}
}