{
  "type": "Feature",
  "properties": {
    "addr:full":"11 Indy Crt Nerang QLD 4211",
    "addr:housenumber":"11",
    "addr:postcode":"4211",
    "addr:street":"Indy Crt",
    "iso:country":"AU",
    "sg:address":"11 Indy Crt",
    "sg:city":"Nerang",
    "sg:classifiers":[
        {
            "category":"Home & Garden",
            "subcategory":"Carpets & Floor Coverings",
            "type":"Retail Goods"
        }
    ],
    "sg:phone":"+61 7 5502 0022",
    "sg:postcode":"4211",
    "sg:province":"QLD",
    "sg:tags":[
        "mattress"
    ],
    "wof:name":"Makin Mattresses",
    "wof:placetype":"venue"
},
  "geometry": {"coordinates":[153.34777832,-28.0108585358],"type":"Point"}
}