{
  "type": "Feature",
  "properties": {
    "iso:country":"AU",
    "sg:address":"14 Hammersly Crt",
    "sg:city":"Sydenham",
    "sg:classifiers":[
        {
            "category":"Building & Trades",
            "subcategory":"Construction",
            "type":"Services"
        }
    ],
    "sg:phone":"+61 3 9390 1668",
    "sg:postcode":"3037",
    "sg:province":"VIC",
    "sg:tags":[
        "contractor"
    ],
    "wof:name":"K Huell Builders",
    "wof:placetype":"venue"
},
  "geometry": {"coordinates":[144.763428,-37.701809],"type":"Point"}
}