{
  "type": "Feature",
  "properties": {
    "iso:country":"AU",
    "sg:address":"24 Lewis St",
    "sg:city":"Epping",
    "sg:classifiers":[
        {
            "category":"Real Estate",
            "subcategory":"Surveying",
            "type":"Services"
        }
    ],
    "sg:phone":"+61 2 9876 1575",
    "sg:postcode":"2121",
    "sg:province":"NSW",
    "sg:tags":[
        "surveyor",
        "land"
    ],
    "wof:name":"Morgan M J",
    "wof:placetype":"venue"
},
  "geometry": {"coordinates":[151.068893433,-33.7757034302],"type":"Point"}
}