{
  "type": "Feature",
  "properties": {
    "addr:full":"131 Main Sth Rd Morphett Vale SA 5162",
    "addr:housenumber":"131",
    "addr:postcode":"5162",
    "addr:street":"Main Sth Rd",
    "iso:country":"AU",
    "sg:address":"131 Main Sth Rd",
    "sg:city":"Morphett Vale",
    "sg:classifiers":[
        {
            "category":"Retail",
            "subcategory":"Car Wash",
            "type":"Services"
        }
    ],
    "sg:phone":"+61 8 8336 3375",
    "sg:postcode":"5162",
    "sg:province":"SA",
    "sg:tags":[
        "truck",
        "cleaning"
    ],
    "wof:name":"BP Superwash",
    "wof:placetype":"venue"
},
  "geometry": {"coordinates":[138.523147583,-35.1233406067],"type":"Point"}
}