{
  "type": "Feature",
  "properties": {
    "addr:full":"5 Greenhill Crt Bunyip VIC 3815",
    "addr:housenumber":"5",
    "addr:postcode":"3815",
    "addr:street":"Greenhill Crt",
    "iso:country":"AU",
    "sg:address":"5 Greenhill Crt",
    "sg:city":"Bunyip",
    "sg:classifiers":[
        {
            "category":"Utilities",
            "subcategory":"Refuse",
            "type":"Services"
        }
    ],
    "sg:phone":"+61 400 557 927",
    "sg:postcode":"3815",
    "sg:province":"VIC",
    "sg:tags":[
        "remover",
        "rubbish"
    ],
    "wof:name":"Warragul Big Bins",
    "wof:placetype":"venue"
},
  "geometry": {"coordinates":[145.727585,-38.088875],"type":"Point"}
}