{
  "type": "Feature",
  "properties": {
    "addr:full":"Shop 5/ 1 Villanova St Wanneroo WA 6065",
    "addr:housenumber":"shop 5 / 1",
    "addr:postcode":"6065",
    "addr:street":"Villanova St",
    "iso:country":"AU",
    "sg:address":"Shop 5/ 1 Villanova St",
    "sg:city":"Wanneroo",
    "sg:classifiers":[
        {
            "category":"Cafe",
            "type":"Food & Drink"
        }
    ],
    "sg:phone":"+61 8 9306 8255",
    "sg:postcode":"6065",
    "sg:province":"WA",
    "wof:name":"Cosmo Cafe",
    "wof:placetype":"venue"
},
  "geometry": {"coordinates":[115.80783081,-31.7806282043],"type":"Point"}
}