{
  "type": "Feature",
  "properties": {
    "addr:full":"31 Kolora Crs Ferny Hills QLD 4055",
    "addr:housenumber":"31",
    "addr:postcode":"4055",
    "addr:street":"Kolora Crs",
    "iso:country":"AU",
    "sg:address":"31 Kolora Crs",
    "sg:city":"Ferny Hills",
    "sg:classifiers":[
        {
            "category":"Retail",
            "subcategory":"Auto Repair",
            "type":"Services"
        }
    ],
    "sg:phone":"+61 7 3351 2270",
    "sg:postcode":"4055",
    "sg:province":"QLD",
    "sg:tags":[
        "electrical"
    ],
    "wof:name":"Arana Auto Electrics",
    "wof:placetype":"venue"
},
  "geometry": {"coordinates":[152.93775939899999,-27.4006195068],"type":"Point"}
}