{
  "type": "Feature",
  "properties": {
    "addr:full":"Shop 14 Warner Village Shopping Centre Warner QLD 4500",
    "addr:housenumber":"shop 14",
    "addr:postcode":"4500",
    "addr:street":"Warner Village",
    "iso:country":"AU",
    "sg:address":"Shop 14",
    "sg:city":"Warner Village Shopping Centre Warner",
    "sg:classifiers":[
        {
            "category":"Shopping",
            "subcategory":"Stationery & Office Supplies",
            "type":"Retail Goods"
        }
    ],
    "sg:phone":"+61 7 3882 1900",
    "sg:postcode":"4500",
    "sg:province":"QLD",
    "wof:name":"Officesmart",
    "wof:placetype":"venue"
},
  "geometry": {"coordinates":[153.00912475600001,-27.3066139221],"type":"Point"}
}