{
  "type": "Feature",
  "properties": {
    "addr:full":"17 Babbage Rd Roseville NSW 2069",
    "addr:housenumber":"17",
    "addr:postcode":"2069",
    "addr:street":"Babbage Rd",
    "iso:country":"AU",
    "sg:address":"17 Babbage Rd",
    "sg:city":"Roseville",
    "sg:classifiers":[
        {
            "category":"Home & Garden",
            "subcategory":"Building Materials",
            "type":"Retail Goods"
        }
    ],
    "sg:phone":"+61 2 9417 7766",
    "sg:postcode":"2069",
    "sg:province":"NSW",
    "sg:tags":[
        "fitting",
        "door"
    ],
    "wof:name":"Doors Best",
    "wof:placetype":"venue"
},
  "geometry": {"coordinates":[151.19529724099999,-33.7785568237],"type":"Point"}
}