{
  "type": "Feature",
  "properties": {
    "iso:country":"AU",
    "sg:address":"362 Crown St",
    "sg:city":"Wollongong",
    "sg:classifiers":[
        {
            "category":"Organizations",
            "subcategory":"Non-profit Organization",
            "type":"Services"
        }
    ],
    "sg:phone":"+61 2 4255 6900",
    "sg:postcode":"2500",
    "sg:province":"NSW",
    "sg:tags":[
        "support",
        "disability",
        "organisation"
    ],
    "wof:name":"Illawarra Society For Crippled Children",
    "wof:placetype":"venue"
},
  "geometry": {"coordinates":[150.880661,-34.425938],"type":"Point"}
}