{
  "type": "Feature",
  "properties": {
    "addr:full":"3 Robinlee Ave Burwood East VIC 3151",
    "addr:housenumber":"3",
    "addr:postcode":"3151",
    "addr:street":"Robinlee Ave",
    "iso:country":"AU",
    "sg:address":"3 Robinlee Ave",
    "sg:city":"Burwood East",
    "sg:classifiers":[
        {
            "category":"Personal",
            "subcategory":"Beauty Salon",
            "type":"Services"
        }
    ],
    "sg:phone":"+61 3 9887 8259",
    "sg:postcode":"3151",
    "sg:province":"VIC",
    "sg:tags":[
        "hairdresser"
    ],
    "wof:name":"Hair Channel No 3",
    "wof:placetype":"venue"
},
  "geometry": {"coordinates":[145.159255981,-37.8462677002],"type":"Point"}
}