{
  "type": "Feature",
  "properties": {
    "addr:full":"PO Box 82 Deception Bay QLD 4508",
    "addr:postcode":"4508",
    "iso:country":"AU",
    "sg:address":"PO Box 82",
    "sg:city":"Deception Bay",
    "sg:classifiers":[
        {
            "category":"Utilities",
            "subcategory":"Electric",
            "type":"Services"
        }
    ],
    "sg:phone":"+61 7 3204 1646",
    "sg:postcode":"4508",
    "sg:province":"QLD",
    "sg:tags":[
        "electrical",
        "contractor"
    ],
    "wof:name":"Bay Area Electrical Systems",
    "wof:placetype":"venue"
},
  "geometry": {"coordinates":[153.01663207999999,-27.1896896362],"type":"Point"}
}