{
  "type": "Feature",
  "properties": {
    "addr:full":"1 Elliott Rd Dandenong VIC 3175",
    "addr:housenumber":"1",
    "addr:postcode":"3175",
    "addr:street":"Elliott Rd",
    "iso:country":"AU",
    "sg:address":"1 Elliott Rd",
    "sg:city":"Dandenong",
    "sg:classifiers":[
        {
            "category":"Retail",
            "subcategory":"Photofinishing",
            "type":"Services"
        }
    ],
    "sg:phone":"+61 3 9791 4433",
    "sg:postcode":"3175",
    "sg:province":"VIC",
    "sg:tags":[
        "refractory"
    ],
    "wof:name":"Radiant Fire Tiles Pty Ltd",
    "wof:placetype":"venue"
},
  "geometry": {"coordinates":[145.21321105999999,-38.0236358643],"type":"Point"}
}