{
  "type": "Feature",
  "properties": {
    "addr:full":"Shop 2a/ 2 VM Arcade Balo St Moree NSW 2400",
    "addr:housenumber":"shop 2a / 2 vm",
    "addr:postcode":"2400",
    "addr:street":"Balo St",
    "iso:country":"AU",
    "sg:address":"Shop 2a/ 2 VM Arcade Balo St",
    "sg:city":"Moree",
    "sg:classifiers":[
        {
            "category":"Health Services",
            "subcategory":"Optometrist",
            "type":"Services"
        }
    ],
    "sg:phone":"+61 2 6752 1753",
    "sg:postcode":"2400",
    "sg:province":"NSW",
    "wof:name":"Ross Cooper & Steven Smith",
    "wof:placetype":"venue"
},
  "geometry": {"coordinates":[149.841598511,-29.4641361237],"type":"Point"}
}