{
  "type": "Feature",
  "properties": {
    "iso:country":"AU",
    "sg:address":"132 Wattle Ave",
    "sg:city":"Carramar",
    "sg:classifiers":[
        {
            "category":"Restaurant",
            "type":"Food & Drink"
        }
    ],
    "sg:phone":"+61 2 9728 2961",
    "sg:postcode":"2163",
    "sg:province":"NSW",
    "wof:name":"Banelao Restaurant",
    "wof:placetype":"venue"
},
  "geometry": {"coordinates":[150.965209961,-33.883972168],"type":"Point"}
}