{
  "type": "Feature",
  "properties": {
    "iso:country":"AU",
    "sg:address":"Cnr Of Victoria Rd & Evans St",
    "sg:city":"Rozelle",
    "sg:classifiers":[
        {
            "category":"Autos & Motor Vehicles",
            "subcategory":"Fuel & Gas Station",
            "type":"Retail Goods"
        }
    ],
    "sg:phone":"+61 2 9810 8494",
    "sg:postcode":"2039",
    "sg:province":"NSW",
    "wof:name":"BP Australia Pty Ltd",
    "wof:placetype":"venue"
},
  "geometry": {"coordinates":[151.169387817,-33.8633422852],"type":"Point"}
}