{
  "type": "Feature",
  "properties": {
    "addr:full":"223 Hawker St Quirindi NSW 2343",
    "addr:housenumber":"223",
    "addr:postcode":"2343",
    "addr:street":"Hawker St",
    "iso:country":"AU",
    "sg:address":"223 Hawker St",
    "sg:city":"Quirindi",
    "sg:classifiers":[
        {
            "category":"Retail",
            "subcategory":"Veterinary Services",
            "type":"Services"
        }
    ],
    "sg:phone":"+61 2 6746 3203",
    "sg:postcode":"2343",
    "sg:province":"NSW",
    "sg:tags":[
        "surgeon"
    ],
    "wof:name":"Timothy McVey",
    "wof:placetype":"venue"
},
  "geometry": {"coordinates":[150.67921447800001,-31.4915790558],"type":"Point"}
}