{
  "type": "Feature",
  "properties": {
    "addr:full":"PO Box 151 Kurri Kurri NSW 2327",
    "addr:postcode":"2327",
    "iso:country":"AU",
    "sg:address":"PO Box 151",
    "sg:city":"Kurri Kurri",
    "sg:classifiers":[
        {
            "category":"Building & Trades",
            "subcategory":"Plumbing",
            "type":"Services"
        }
    ],
    "sg:phone":"+61 2 4936 2002",
    "sg:postcode":"2327",
    "sg:province":"NSW",
    "sg:tags":[
        "plumber",
        "gasfitters"
    ],
    "wof:name":"Steve Boyles Plumbing",
    "wof:placetype":"venue"
},
  "geometry": {"coordinates":[151.481124878,-32.8189888],"type":"Point"}
}