{
  "type": "Feature",
  "properties": {
    "addr:full":"53 Railway St Bomaderry NSW 2541",
    "addr:housenumber":"53",
    "addr:postcode":"2541",
    "addr:street":"Railway St",
    "iso:country":"AU",
    "sg:address":"53 Railway St",
    "sg:city":"Bomaderry",
    "sg:classifiers":[
        {
            "category":"Professional",
            "type":"Services"
        }
    ],
    "sg:phone":"+61 2 4422 6711",
    "sg:postcode":"2541",
    "sg:province":"NSW",
    "sg:tags":[
        "courier"
    ],
    "wof:name":"Kellys Freight Service",
    "wof:placetype":"venue"
},
  "geometry": {"coordinates":[150.612716675,-34.8494262695],"type":"Point"}
}