{
  "type": "Feature",
  "properties": {
    "iso:country":"AU",
    "sg:address":"25 Hospital Rd",
    "sg:city":"Emerald",
    "sg:classifiers":[
        {
            "category":"Shopping",
            "subcategory":"Clothing, Apparel, & Fashions",
            "type":"Retail Goods"
        }
    ],
    "sg:phone":"+61 7 4982 1874",
    "sg:postcode":"4720",
    "sg:province":"QLD",
    "sg:tags":[
        "lady",
        "wear"
    ],
    "wof:name":"The Smart Shop",
    "wof:placetype":"venue"
},
  "geometry": {"coordinates":[148.157303,-23.521198],"type":"Point"}
}