{
  "type": "Feature",
  "properties": {
    "addr:full":"1A William St Singleton NSW 2330",
    "addr:housenumber":"1a",
    "addr:postcode":"2330",
    "addr:street":"William St",
    "iso:country":"AU",
    "sg:address":"1A William St",
    "sg:city":"Singleton",
    "sg:classifiers":[
        {
            "category":"Shopping",
            "type":"Retail Goods"
        }
    ],
    "sg:phone":"+61 2 6571 1237",
    "sg:postcode":"2330",
    "sg:province":"NSW",
    "sg:tags":[
        "agent",
        "stock"
    ],
    "wof:name":"Gordon Fuller & Son Pty Ltd",
    "wof:placetype":"venue"
},
  "geometry": {"coordinates":[151.16902200000001,-32.564259],"type":"Point"}
}