{
  "type": "Feature",
  "properties": {
    "addr:full":"158 Hume St Corowa NSW 2646",
    "addr:housenumber":"158",
    "addr:postcode":"2646",
    "addr:street":"Hume St",
    "iso:country":"AU",
    "sg:address":"158 Hume St",
    "sg:city":"Corowa",
    "sg:classifiers":[
        {
            "category":"Education",
            "subcategory":"School",
            "type":"Public Place"
        }
    ],
    "sg:phone":"+61 2 6033 1535",
    "sg:postcode":"2646",
    "sg:province":"NSW",
    "sg:tags":[
        "state",
        "-",
        "nsw"
    ],
    "wof:name":"Corowa South Public School",
    "wof:placetype":"venue"
},
  "geometry": {"coordinates":[146.37557983400001,-36.0206298828],"type":"Point"}
}