{
  "type": "Feature",
  "properties": {
    "iso:country":"AU",
    "sg:address":"13 George St",
    "sg:city":"Wynyard",
    "sg:classifiers":[
        {
            "category":"Building & Trades",
            "subcategory":"Cleaning & Sanitation",
            "type":"Services"
        }
    ],
    "sg:phone":"+61 419 421 545",
    "sg:postcode":"7325",
    "sg:province":"TAS",
    "sg:tags":[
        "chemical",
        "pressure",
        "steam",
        "contractor"
    ],
    "wof:name":"Billows Wheelie Cleaning",
    "wof:placetype":"venue"
},
  "geometry": {"coordinates":[145.713867,-40.986683],"type":"Point"}
}