{
  "type": "Feature",
  "properties": {
    "addr:full":"Longlands Gap Rd Wondecla QLD 4872",
    "addr:postcode":"4872",
    "addr:street":"Longlands Gap Rd",
    "iso:country":"AU",
    "sg:address":"Longlands Gap Rd",
    "sg:city":"Wondecla",
    "sg:classifiers":[
        {
            "category":"Fast Food",
            "type":"Food & Drink"
        }
    ],
    "sg:phone":"+61 7 4096 2159",
    "sg:postcode":"4872",
    "sg:province":"QLD",
    "sg:tags":[
        "away",
        "take"
    ],
    "wof:name":"Wondecla Roadhouse",
    "wof:placetype":"venue"
},
  "geometry": {"coordinates":[145.1068573,-17.9841003418],"type":"Point"}
}