{
  "type": "Feature",
  "properties": {
    "addr:full":"229 Melbourne Rd Rye VIC 3941",
    "addr:housenumber":"229",
    "addr:postcode":"3941",
    "addr:street":"Melbourne Rd",
    "iso:country":"AU",
    "sg:address":"229 Melbourne Rd",
    "sg:city":"Rye",
    "sg:classifiers":[
        {
            "category":"Building & Trades",
            "subcategory":"Plumbing",
            "type":"Services"
        }
    ],
    "sg:phone":"+61 418 530 698",
    "sg:postcode":"3941",
    "sg:province":"VIC",
    "sg:tags":[
        "plumber",
        "gasfitters"
    ],
    "wof:name":"Peter Allen Plumbing",
    "wof:placetype":"venue"
},
  "geometry": {"coordinates":[144.787765503,-38.3796653748],"type":"Point"}
}