{
  "type": "Feature",
  "properties": {
    "iso:country":"AU",
    "sg:address":"Broad St",
    "sg:city":"Sarina",
    "sg:classifiers":[
        {
            "category":"Travel",
            "subcategory":"Hotels & Motels",
            "type":"Entertainment"
        }
    ],
    "sg:phone":"+61 7 4956 1686",
    "sg:postcode":"4737",
    "sg:province":"QLD",
    "sg:tags":[
        "accommodation"
    ],
    "wof:name":"Sarina Hotel",
    "wof:placetype":"venue"
},
  "geometry": {"coordinates":[149.216522,-21.420662],"type":"Point"}
}