{
  "type": "Feature",
  "properties": {
    "addr:full":"Unit 1, 112 Fison Ave Eagle Farm QLD 4009",
    "addr:housenumber":"112",
    "addr:postcode":"4009",
    "addr:street":"Fison Ave",
    "iso:country":"AU",
    "sg:address":"Unit 1, 112 Fison Ave",
    "sg:city":"Eagle Farm",
    "sg:classifiers":[
        {
            "category":"Personal",
            "subcategory":"Beauty Salon",
            "type":"Services"
        }
    ],
    "sg:phone":"+61 7 3868 4044",
    "sg:postcode":"4009",
    "sg:province":"QLD",
    "sg:tags":[
        "hairdresser"
    ],
    "wof:name":"Procuts Salons H/O",
    "wof:placetype":"venue"
},
  "geometry": {"coordinates":[153.084915161,-27.4347438812],"type":"Point"}
}