{
  "type": "Feature",
  "properties": {
    "iso:country":"AU",
    "sg:address":"Lot 1, Sandalwood Ave",
    "sg:city":"Dalby",
    "sg:classifiers":[
        {
            "category":"Building & Trades",
            "subcategory":"Construction",
            "type":"Services"
        }
    ],
    "sg:phone":"+61 7 4669 6305",
    "sg:postcode":"4405",
    "sg:province":"QLD",
    "sg:tags":[
        "earth",
        "excavating",
        "moving",
        "contractor"
    ],
    "wof:name":"Brook Ray",
    "wof:placetype":"venue"
},
  "geometry": {"coordinates":[151.23423767099999,-27.1802272797],"type":"Point"}
}