{
  "type": "Feature",
  "properties": {
    "addr:full":"Bloomfield St (cnr Princess St) Cleveland QLD 4163",
    "addr:postcode":"4163",
    "addr:street":"Bloomfield St Cnr Princess St",
    "iso:country":"AU",
    "sg:address":"Bloomfield St",
    "sg:city":"(cnr Princess St) Cleveland",
    "sg:classifiers":[
        {
            "category":"Autos & Motor Vehicles",
            "subcategory":"Fuel & Gas Station",
            "type":"Retail Goods"
        }
    ],
    "sg:phone":"+61 7 3286 2662",
    "sg:postcode":"4163",
    "sg:province":"QLD",
    "wof:name":"Shell",
    "wof:placetype":"venue"
},
  "geometry": {"coordinates":[153.267089844,-27.5265235901],"type":"Point"}
}