{
  "type": "Feature",
  "properties": {
    "iso:country":"AU",
    "sg:address":"101 Church St",
    "sg:city":"Mudgee",
    "sg:classifiers":[
        {
            "category":"Travel",
            "subcategory":"Hotels & Motels",
            "type":"Entertainment"
        }
    ],
    "sg:phone":"+61 2 6372 3333",
    "sg:postcode":"2850",
    "sg:province":"NSW",
    "wof:name":"Winning Post Motor Inn",
    "wof:placetype":"venue"
},
  "geometry": {"coordinates":[149.585205,-32.607334],"type":"Point"}
}