{
  "type": "Feature",
  "properties": {
    "iso:country":"AU",
    "sg:address":"32 Little Edward St",
    "sg:city":"Spring Hill",
    "sg:classifiers":[
        {
            "category":"Professional",
            "subcategory":"Printing & Photocopies",
            "type":"Services"
        }
    ],
    "sg:phone":"+61 7 3831 0633",
    "sg:postcode":"4000",
    "sg:province":"QLD",
    "sg:tags":[
        "publishing",
        "desktop"
    ],
    "wof:name":"Atlantic Group Pty Ltd",
    "wof:placetype":"venue"
},
  "geometry": {"coordinates":[153.024093628,-27.4620113373],"type":"Point"}
}