{
  "type": "Feature",
  "properties": {
    "addr:full":"125 Ellsworth Drv Tregear NSW 2770",
    "addr:housenumber":"125",
    "addr:postcode":"2770",
    "addr:street":"Ellsworth Drv",
    "iso:country":"AU",
    "sg:address":"125 Ellsworth Drv",
    "sg:city":"Tregear",
    "sg:classifiers":[
        {
            "category":"Health Services",
            "subcategory":"Doctor",
            "type":"Services"
        }
    ],
    "sg:phone":"+61 2 9628 8411",
    "sg:postcode":"2770",
    "sg:province":"NSW",
    "sg:tags":[
        "medical",
        "practitioner"
    ],
    "wof:name":"Barrett Anthony G & Lorraine A",
    "wof:placetype":"venue"
},
  "geometry": {"coordinates":[150.797317505,-33.7432365417],"type":"Point"}
}