{
  "type": "Feature",
  "properties": {
    "iso:country":"AU",
    "sg:address":"1639 Botany Rd",
    "sg:city":"Banksmeadow",
    "sg:classifiers":[
        {
            "category":"Health Services",
            "subcategory":"Doctor",
            "type":"Services"
        }
    ],
    "sg:phone":"+61 2 9316 9600",
    "sg:postcode":"2019",
    "sg:province":"NSW",
    "sg:tags":[
        "medical",
        "practitioner"
    ],
    "wof:name":"Brajtman I Dr",
    "wof:placetype":"venue"
},
  "geometry": {"coordinates":[151.20608520499999,-33.9562988281],"type":"Point"}
}