{
  "type": "Feature",
  "properties": {
    "iso:country":"AU",
    "sg:address":"57 Oxford Rd",
    "sg:city":"Westmead",
    "sg:classifiers":[
        {
            "category":"Retail",
            "subcategory":"Storage",
            "type":"Services"
        }
    ],
    "sg:phone":"+61 415 879 515",
    "sg:postcode":"2145",
    "sg:province":"NSW",
    "sg:tags":[
        "removal",
        "furniture"
    ],
    "wof:name":"All Removal",
    "wof:placetype":"venue"
},
  "geometry": {"coordinates":[150.982696533,-33.8380699158],"type":"Point"}
}