{
  "type": "Feature",
  "properties": {
    "addr:full":"Unit 1/ 9 Industry St Malaga WA 6090",
    "addr:housenumber":"9",
    "addr:postcode":"6090",
    "addr:street":"Industry St",
    "iso:country":"AU",
    "sg:address":"Unit 1/ 9 Industry St",
    "sg:city":"Malaga",
    "sg:classifiers":[
        {
            "category":"Food & Beverages",
            "subcategory":"Specialty",
            "type":"Retail Goods"
        }
    ],
    "sg:phone":"+61 1800 777 977",
    "sg:postcode":"6090",
    "sg:province":"WA",
    "sg:tags":[
        "ice",
        "supply"
    ],
    "wof:name":"Golden West Ice",
    "wof:placetype":"venue"
},
  "geometry": {"coordinates":[115.89540863000001,-31.8583469391],"type":"Point"}
}