{
  "type": "Feature",
  "properties": {
    "iso:country":"AU",
    "sg:address":"Kawana Nurseries 1483 Peats Ridge Rd",
    "sg:city":"Peats Ridge",
    "sg:classifiers":[
        {
            "category":"Farming",
            "subcategory":"Nursery",
            "type":"Manufacturing & Wholesale Goods"
        }
    ],
    "sg:phone":"+61 2 4373 1186",
    "sg:postcode":"2250",
    "sg:province":"NSW",
    "wof:name":"Slade I N & E G",
    "wof:placetype":"venue"
},
  "geometry": {"coordinates":[151.22969055199999,-33.3454246521],"type":"Point"}
}