{
  "type": "Feature",
  "properties": {
    "addr:full":"20 Bruce St East Maitland NSW 2323",
    "addr:housenumber":"20",
    "addr:postcode":"2323",
    "addr:street":"Bruce St",
    "iso:country":"AU",
    "sg:address":"20 Bruce St",
    "sg:city":"East Maitland",
    "sg:classifiers":[
        {
            "category":"Fast Food",
            "type":"Food & Drink"
        }
    ],
    "sg:phone":"+61 2 4933 2114",
    "sg:postcode":"2323",
    "sg:province":"NSW",
    "sg:tags":[
        "away",
        "take"
    ],
    "wof:name":"Gee Dees Takeaway",
    "wof:placetype":"venue"
},
  "geometry": {"coordinates":[151.597290039,-32.7568283081],"type":"Point"}
}