{
  "type": "Feature",
  "properties": {
    "addr:full":"33a Arthur St Dalby QLD 4405",
    "addr:housenumber":"33a",
    "addr:postcode":"4405",
    "addr:street":"Arthur St",
    "iso:country":"AU",
    "sg:address":"33a Arthur St",
    "sg:city":"Dalby",
    "sg:classifiers":[
        {
            "category":"Building & Trades",
            "subcategory":"Electrical",
            "type":"Services"
        }
    ],
    "sg:phone":"+61 7 4662 2407",
    "sg:postcode":"4405",
    "sg:province":"QLD",
    "sg:tags":[
        "electric",
        "fence"
    ],
    "wof:name":"Bob Laffy Electronics",
    "wof:placetype":"venue"
},
  "geometry": {"coordinates":[151.266357422,-27.1893367767],"type":"Point"}
}