{
  "type": "Feature",
  "properties": {
    "addr:full":"Unit 3/ 7- 9 Underwood Rd Homebush NSW 2140",
    "addr:housenumber":"9",
    "addr:postcode":"2140",
    "addr:street":"Underwood Rd",
    "iso:country":"AU",
    "sg:address":"Unit 3/ 7- 9 Underwood Rd",
    "sg:city":"Homebush",
    "sg:classifiers":[
        {
            "category":"Food & Beverages",
            "subcategory":"Fruits & Vegetables",
            "type":"Retail Goods"
        }
    ],
    "sg:phone":"+61 2 9763 1877",
    "sg:postcode":"2140",
    "sg:province":"NSW",
    "sg:tags":[
        "greengrocer",
        "fruiterer"
    ],
    "wof:name":"Perfection Fresh Australia Pty Ltd",
    "wof:placetype":"venue"
},
  "geometry": {"coordinates":[151.07916259800001,-33.85572052],"type":"Point"}
}