{
  "type": "Feature",
  "properties": {
    "addr:full":"PO Box 2145 Pendle Hill NSW 2145",
    "addr:postcode":"2145",
    "iso:country":"AU",
    "sg:address":"PO Box 2145",
    "sg:city":"Pendle Hill",
    "sg:classifiers":[
        {
            "category":"Building & Trades",
            "subcategory":"Cleaning & Sanitation",
            "type":"Services"
        }
    ],
    "sg:phone":"+61 2 9833 0133",
    "sg:postcode":"2145",
    "sg:province":"NSW",
    "sg:tags":[
        "industrial",
        "commercial",
        "contractor"
    ],
    "wof:name":"ARF Cleaning & Caretaking Pty Ltd",
    "wof:placetype":"venue"
},
  "geometry": {"coordinates":[150.954147339,-33.8062896729],"type":"Point"}
}