{
  "type": "Feature",
  "properties": {
    "addr:full":"Building 38 Lionel St Essendon Airport VIC 3041",
    "addr:housenumber":"38",
    "addr:postcode":"3041",
    "addr:street":"Lionel St",
    "iso:country":"AU",
    "sg:address":"Building 38 Lionel St",
    "sg:city":"Essendon Airport",
    "sg:classifiers":[
        {
            "category":"Food & Beverages",
            "subcategory":"Liquor & Beverages",
            "type":"Retail Goods"
        }
    ],
    "sg:phone":"+61 3 8415 0206",
    "sg:postcode":"3041",
    "sg:province":"VIC",
    "sg:tags":[
        "merchant",
        "spirit",
        "wine"
    ],
    "wof:name":"Fine Wines Of Europe",
    "wof:placetype":"venue"
},
  "geometry": {"coordinates":[144.896728516,-37.7231254578],"type":"Point"}
}