{
  "type": "Feature",
  "properties": {
    "iso:country":"AU",
    "sg:address":"Wilby St",
    "sg:city":"North Star",
    "sg:classifiers":[
        {
            "category":"Social Services",
            "subcategory":"Child Care",
            "type":"Services"
        }
    ],
    "sg:phone":"+61 7 4676 3235",
    "sg:postcode":"2408",
    "sg:province":"NSW",
    "sg:tags":[
        "support",
        "health"
    ],
    "wof:name":"Tharawonga Mobile Resource Unit",
    "wof:placetype":"venue"
},
  "geometry": {"coordinates":[150.39503479000001,-28.9276676178],"type":"Point"}
}