{
  "type": "Feature",
  "properties": {
    "iso:country":"AU",
    "sg:address":"66 Powells Ave",
    "sg:city":"Bendigo",
    "sg:classifiers":[
        {
            "category":"Building & Trades",
            "subcategory":"Plumbing",
            "type":"Services"
        }
    ],
    "sg:phone":"+61 3 5444 4681",
    "sg:postcode":"3550",
    "sg:province":"VIC",
    "sg:tags":[
        "plumber",
        "gasfitters"
    ],
    "sg:website":"http://www.centrestateplumbing.com.au",
    "wof:name":"Centre State Plumbing & Roofing",
    "wof:placetype":"venue"
},
  "geometry": {"coordinates":[144.317428589,-36.7589836121],"type":"Point"}
}