{
  "type": "Feature",
  "properties": {
    "addr:full":"123 Delta St Geebung QLD 4034",
    "addr:housenumber":"123",
    "addr:postcode":"4034",
    "addr:street":"Delta St",
    "iso:country":"AU",
    "sg:address":"123 Delta St",
    "sg:city":"Geebung",
    "sg:classifiers":[
        {
            "category":"Bars & Pubs",
            "subcategory":"Gay Bar",
            "type":"Food & Drink"
        }
    ],
    "sg:phone":"+61 7 3865 7677",
    "sg:postcode":"4034",
    "sg:province":"QLD",
    "sg:tags":[
        "plywood",
        "veneer"
    ],
    "wof:name":"Mister Ply & Wood",
    "wof:placetype":"venue"
},
  "geometry": {"coordinates":[153.05429100000001,-27.366261],"type":"Point"}
}