{
  "type": "Feature",
  "properties": {
    "addr:full":"276 Lefroy Ave Herne Hill WA 6056",
    "addr:housenumber":"276",
    "addr:postcode":"6056",
    "addr:street":"Lefroy Ave",
    "iso:country":"AU",
    "sg:address":"276 Lefroy Ave",
    "sg:city":"Herne Hill",
    "sg:classifiers":[
        {
            "category":"Professional",
            "subcategory":"Computer Services",
            "type":"Services"
        }
    ],
    "sg:phone":"+61 8 9296 1797",
    "sg:postcode":"6056",
    "sg:province":"WA",
    "sg:tags":[
        "consultant",
        "system"
    ],
    "wof:name":"Sharlee Holdings Pty Ltd",
    "wof:placetype":"venue"
},
  "geometry": {"coordinates":[116.027618408,-31.821811676],"type":"Point"}
}