{
  "type": "Feature",
  "properties": {
    "iso:country":"AU",
    "sg:address":"Lot17/ Calder Hwy",
    "sg:city":"Nullawil",
    "sg:classifiers":[
        {
            "category":"Farming",
            "subcategory":"Farm",
            "type":"Manufacturing & Wholesale Goods"
        }
    ],
    "sg:phone":"+61 3 5493 5340",
    "sg:postcode":"3529",
    "sg:province":"VIC",
    "sg:tags":[
        "farmer"
    ],
    "wof:name":"Fawcett J A & C J",
    "wof:placetype":"venue"
},
  "geometry": {"coordinates":[143.17796300000001,-35.853939],"type":"Point"}
}