{
  "type": "Feature",
  "properties": {
    "iso:country":"AU",
    "sg:address":"Unit 5, 10 McElligott Crt",
    "sg:city":"Canning Vale",
    "sg:classifiers":[
        {
            "category":"Autos & Motor Vehicles",
            "subcategory":"Auto Supplies",
            "type":"Retail Goods"
        }
    ],
    "sg:phone":"+61 8 9256 3450",
    "sg:postcode":"6155",
    "sg:province":"WA",
    "sg:tags":[
        "camper-trailers",
        "caravan",
        "equipment"
    ],
    "wof:name":"Challenge Camper Trailers WA",
    "wof:placetype":"venue"
},
  "geometry": {"coordinates":[115.920563,-32.061897],"type":"Point"}
}