{
  "type": "Feature",
  "properties": {
    "addr:full":"Suite 11, 385 Belmore Rd Balwyn North VIC 3104",
    "addr:housenumber":"385",
    "addr:postcode":"3104",
    "addr:street":"Belmore Rd",
    "iso:country":"AU",
    "sg:address":"Suite 11, 385 Belmore Rd",
    "sg:city":"Balwyn North",
    "sg:classifiers":[
        {
            "category":"Professional",
            "type":"Services"
        }
    ],
    "sg:phone":"+61 3 9857 3400",
    "sg:postcode":"3104",
    "sg:province":"VIC",
    "sg:tags":[
        "forwarding",
        "agent",
        "transport"
    ],
    "wof:name":"Advanced Freight Management",
    "wof:placetype":"venue"
},
  "geometry": {"coordinates":[145.101394653,-37.8038978577],"type":"Point"}
}