{
  "type": "Feature",
  "properties": {
    "addr:full":"10 Reginald St Cremorne NSW 2090",
    "addr:housenumber":"10",
    "addr:postcode":"2090",
    "addr:street":"Reginald St",
    "iso:country":"AU",
    "sg:address":"10 Reginald St",
    "sg:city":"Cremorne",
    "sg:classifiers":[
        {
            "category":"Fast Food",
            "type":"Food & Drink"
        }
    ],
    "sg:phone":"+61 2 9953 7556",
    "sg:postcode":"2090",
    "sg:province":"NSW",
    "sg:tags":[
        "away",
        "take"
    ],
    "wof:name":"Kitchen Curries",
    "wof:placetype":"venue"
},
  "geometry": {"coordinates":[151.229415894,-33.8339157104],"type":"Point"}
}