{
  "type": "Feature",
  "properties": {
    "addr:full":"19 Waratah St Kyle Bay NSW 2221",
    "addr:housenumber":"19",
    "addr:postcode":"2221",
    "addr:street":"Waratah St",
    "iso:country":"AU",
    "sg:address":"19 Waratah St",
    "sg:city":"Kyle Bay",
    "sg:classifiers":[
        {
            "category":"Professional",
            "subcategory":"Computer Services",
            "type":"Services"
        }
    ],
    "sg:phone":"+61 2 9547 2741",
    "sg:postcode":"2221",
    "sg:province":"NSW",
    "sg:tags":[
        "consultant",
        "system"
    ],
    "wof:name":"D D M M Computer Solutions",
    "wof:placetype":"venue"
},
  "geometry": {"coordinates":[151.10467529300001,-33.9887657166],"type":"Point"}
}