{
  "type": "Feature",
  "properties": {
    "iso:country":"AU",
    "sg:address":"Rear 886 North Rd",
    "sg:city":"Bentleigh East",
    "sg:classifiers":[
        {
            "category":"Building & Trades",
            "subcategory":"Equipment Rental",
            "type":"Services"
        }
    ],
    "sg:phone":"+61 3 9570 4550",
    "sg:postcode":"3165",
    "sg:province":"VIC",
    "sg:tags":[
        "supply",
        "catering"
    ],
    "wof:name":"Insulbag",
    "wof:placetype":"venue"
},
  "geometry": {"coordinates":[145.061035156,-37.9067802429],"type":"Point"}
}