{
  "type": "Feature",
  "properties": {
    "addr:full":"58 Porter St Prahran VIC 3181",
    "addr:housenumber":"58",
    "addr:postcode":"3181",
    "addr:street":"Porter St",
    "iso:country":"AU",
    "sg:address":"58 Porter St",
    "sg:city":"Prahran",
    "sg:classifiers":[
        {
            "category":"Professional",
            "subcategory":"Printing & Photocopies",
            "type":"Services"
        }
    ],
    "sg:phone":"+61 3 9510 6559",
    "sg:postcode":"3181",
    "sg:province":"VIC",
    "sg:tags":[
        "screen",
        "printer"
    ],
    "sg:website":"http://www.superscreen.com.au",
    "wof:name":"Superscreen",
    "wof:placetype":"venue"
},
  "geometry": {"coordinates":[144.990768433,-37.8466377258],"type":"Point"}
}