{
  "type": "Feature",
  "properties": {
    "iso:country":"AU",
    "sg:address":"3/ 14 Illawong St",
    "sg:city":"Chevron Island",
    "sg:classifiers":[
        {
            "category":"Building & Trades",
            "subcategory":"Cleaning & Sanitation",
            "type":"Services"
        }
    ],
    "sg:phone":"+61 438 920 363",
    "sg:postcode":"4217",
    "sg:province":"QLD",
    "sg:tags":[
        "industrial",
        "commercial",
        "contractor"
    ],
    "wof:name":"Clean Work Contracts",
    "wof:placetype":"venue"
},
  "geometry": {"coordinates":[153.421386719,-27.9969520569],"type":"Point"}
}