{
  "type": "Feature",
  "properties": {
    "addr:full":"37 Nicholson St Balmain NSW 2041",
    "addr:housenumber":"37",
    "addr:postcode":"2041",
    "addr:street":"Nicholson St",
    "iso:country":"AU",
    "sg:address":"37 Nicholson St",
    "sg:city":"Balmain",
    "sg:classifiers":[
        {
            "category":"Home & Garden",
            "subcategory":"Furniture",
            "type":"Retail Goods"
        }
    ],
    "sg:phone":"+61 2 9818 5563",
    "sg:postcode":"2041",
    "sg:province":"NSW",
    "sg:tags":[
        "business"
    ],
    "wof:name":"Emanate Design Pty Ltd",
    "wof:placetype":"venue"
},
  "geometry": {"coordinates":[151.19233700000001,-33.8554],"type":"Point"}
}