{
  "type": "Feature",
  "properties": {
    "iso:country":"AU",
    "sg:address":"U2/ 11 Newton Rd",
    "sg:city":"Wetherill Park",
    "sg:classifiers":[
        {
            "category":"Commercial Area",
            "type":"Public Place"
        }
    ],
    "sg:phone":"+61 2 9756 1220",
    "sg:postcode":"2164",
    "sg:province":"NSW",
    "sg:tags":[
        "heavy",
        "carrier"
    ],
    "wof:name":"Burkes Transport (Bathurst) Pty Ltd",
    "wof:placetype":"venue"
},
  "geometry": {"coordinates":[150.89299011200001,-33.8467597961],"type":"Point"}
}