{
  "type": "Feature",
  "properties": {
    "iso:country":"AU",
    "sg:address":"57 Thomas St",
    "sg:city":"Edgeworth",
    "sg:classifiers":[
        {
            "category":"Utilities",
            "subcategory":"Natural Gas",
            "type":"Services"
        }
    ],
    "sg:phone":"+61 2 4965 8311",
    "sg:postcode":"2285",
    "sg:province":"NSW",
    "sg:tags":[
        "cylinder",
        "testing"
    ],
    "wof:name":"Arrow Automotive & Gas",
    "wof:placetype":"venue"
},
  "geometry": {"coordinates":[151.62652587900001,-32.9253044128],"type":"Point"}
}