{
  "type": "Feature",
  "properties": {
    "iso:country":"AU",
    "sg:address":"43 Brisbane Water Drv",
    "sg:city":"Point Clare",
    "sg:classifiers":[
        {
            "category":"Real Estate",
            "subcategory":"Real Estate Agent",
            "type":"Services"
        }
    ],
    "sg:phone":"+61 2 4323 3133",
    "sg:postcode":"2250",
    "sg:province":"NSW",
    "wof:name":"L.J. Hooker",
    "wof:placetype":"venue"
},
  "geometry": {"coordinates":[151.327728272,-33.4465713501],"type":"Point"}
}