{
  "type": "Feature",
  "properties": {
    "addr:full":"797 Old Cleveland Rd Carina QLD 4152",
    "addr:housenumber":"797",
    "addr:postcode":"4152",
    "addr:street":"Old Cleveland Rd",
    "iso:country":"AU",
    "sg:address":"797 Old Cleveland Rd",
    "sg:city":"Carina",
    "sg:classifiers":[
        {
            "category":"Shopping",
            "subcategory":"Stationery & Office Supplies",
            "type":"Retail Goods"
        }
    ],
    "sg:phone":"+61 7 3843 1666",
    "sg:postcode":"4152",
    "sg:province":"QLD",
    "wof:name":"Carina Stationery Supplies",
    "wof:placetype":"venue"
},
  "geometry": {"coordinates":[153.090576172,-27.4956417084],"type":"Point"}
}