{
  "type": "Feature",
  "properties": {
    "iso:country":"AU",
    "sg:address":"2 Glamis Pl",
    "sg:city":"Melton West",
    "sg:classifiers":[
        {
            "category":"Home & Garden",
            "subcategory":"Carpets & Floor Coverings",
            "type":"Retail Goods"
        }
    ],
    "sg:phone":"+61 419 536 715",
    "sg:postcode":"3337",
    "sg:province":"VIC",
    "sg:tags":[
        "tile",
        "wall",
        "layer"
    ],
    "wof:name":"Ricky's Tiling",
    "wof:placetype":"venue"
},
  "geometry": {"coordinates":[144.566406,-37.674904],"type":"Point"}
}