{
  "type": "Feature",
  "properties": {
    "addr:full":"1/ 190 Belmore Rd Balwyn VIC 3103",
    "addr:housenumber":"/ 190",
    "addr:postcode":"3103",
    "addr:street":"Belmore Rd",
    "iso:country":"AU",
    "sg:address":"1/ 190 Belmore Rd",
    "sg:city":"Balwyn",
    "sg:classifiers":[
        {
            "category":"Insurance",
            "subcategory":"Insurance Agent",
            "type":"Services"
        }
    ],
    "sg:phone":"+61 3 9857 3599",
    "sg:postcode":"3103",
    "sg:province":"VIC",
    "sg:tags":[
        "broker"
    ],
    "wof:name":"Overton Insurance (Brokers) Vic P/L",
    "wof:placetype":"venue"
},
  "geometry": {"coordinates":[145.084182739,-37.8037071228],"type":"Point"}
}