{
  "type": "Feature",
  "properties": {
    "iso:country":"AU",
    "sg:address":"28 Bronze St",
    "sg:city":"Sumner Park",
    "sg:classifiers":[
        {
            "category":"Wholesale",
            "subcategory":"Stationery",
            "type":"Manufacturing & Wholesale Goods"
        }
    ],
    "sg:phone":"+61 7 3376 2377",
    "sg:postcode":"4074",
    "sg:province":"QLD",
    "sg:tags":[
        "mfrg"
    ],
    "wof:name":"Polymark",
    "wof:placetype":"venue"
},
  "geometry": {"coordinates":[152.93650817899999,-27.5636501312],"type":"Point"}
}