{
  "type": "Feature",
  "properties": {
    "addr:full":"414 Sandgate Rd Albion QLD 4010",
    "addr:housenumber":"414",
    "addr:postcode":"4010",
    "addr:street":"Sandgate Rd",
    "iso:country":"AU",
    "sg:address":"414 Sandgate Rd",
    "sg:city":"Albion",
    "sg:classifiers":[
        {
            "category":"Manufacturing",
            "subcategory":"Jewelry",
            "type":"Manufacturing & Wholesale Goods"
        }
    ],
    "sg:phone":"+61 7 3256 0999",
    "sg:postcode":"4010",
    "sg:province":"QLD",
    "sg:tags":[
        "mfrg",
        "jeweller"
    ],
    "wof:name":"K. Bros Jewellers",
    "wof:placetype":"venue"
},
  "geometry": {"coordinates":[153.044265747,-27.4283370972],"type":"Point"}
}