{
  "type": "Feature",
  "properties": {
    "addr:full":"66 Taylor Rd Albion Park NSW 2527",
    "addr:housenumber":"66",
    "addr:postcode":"2527",
    "addr:street":"Taylor Rd",
    "iso:country":"AU",
    "sg:address":"66 Taylor Rd",
    "sg:city":"Albion Park",
    "sg:classifiers":[
        {
            "category":"Banks & Credit Unions",
            "subcategory":"Bank",
            "type":"Services"
        }
    ],
    "sg:phone":"+61 1800 729 633",
    "sg:postcode":"2527",
    "sg:province":"NSW",
    "sg:tags":[
        "broker",
        "mortgage"
    ],
    "wof:name":"Mortgage Reduction Centre",
    "wof:placetype":"venue"
},
  "geometry": {"coordinates":[150.77403259299999,-34.5695037842],"type":"Point"}
}