{
  "type": "Feature",
  "properties": {
    "iso:country":"AU",
    "sg:address":"52 Tudor St",
    "sg:city":"Hamilton",
    "sg:classifiers":[
        {
            "category":"Shopping",
            "subcategory":"Mobile Phones",
            "type":"Retail Goods"
        }
    ],
    "sg:phone":"+61 2 4961 0477",
    "sg:postcode":"2303",
    "sg:province":"NSW",
    "sg:tags":[
        "telephone",
        "accessory"
    ],
    "wof:name":"Phone Sales & Service",
    "wof:placetype":"venue"
},
  "geometry": {"coordinates":[151.747711,-32.924347],"type":"Point"}
}