{
  "type": "Feature",
  "properties": {
    "addr:full":"41 Lawson Crs Thomastown VIC 3074",
    "addr:housenumber":"41",
    "addr:postcode":"3074",
    "addr:street":"Lawson Crs",
    "iso:country":"AU",
    "sg:address":"41 Lawson Crs",
    "sg:city":"Thomastown",
    "sg:classifiers":[
        {
            "category":"Structure",
            "subcategory":"Factory",
            "type":"Public Place"
        }
    ],
    "sg:phone":"+61 3 9469 4082",
    "sg:postcode":"3074",
    "sg:province":"VIC",
    "sg:tags":[
        "seating",
        "system"
    ],
    "wof:name":"Parlap Seating",
    "wof:placetype":"venue"
},
  "geometry": {"coordinates":[145.01148986800001,-37.6832199097],"type":"Point"}
}