{
  "type": "Feature",
  "properties": {
    "addr:full":"PO Box 222 The Entrance NSW 2261",
    "addr:postcode":"2261",
    "iso:country":"AU",
    "sg:address":"PO Box 222",
    "sg:city":"The Entrance",
    "sg:classifiers":[
        {
            "category":"Real Estate",
            "subcategory":"Real Estate Agent",
            "type":"Services"
        }
    ],
    "sg:phone":"+61 412 911 171",
    "sg:postcode":"2261",
    "sg:province":"NSW",
    "wof:name":"All Eights Pty Limited",
    "wof:placetype":"venue"
},
  "geometry": {"coordinates":[151.49662799999999,-33.344341],"type":"Point"}
}