{
  "type": "Feature",
  "properties": {
    "addr:full":"Unit 3, 40 Yarraman Pl Virginia QLD 4014",
    "addr:housenumber":"40",
    "addr:postcode":"4014",
    "addr:street":"Yarraman Pl",
    "iso:country":"AU",
    "sg:address":"Unit 3, 40 Yarraman Pl",
    "sg:city":"Virginia",
    "sg:classifiers":[
        {
            "category":"Building & Trades",
            "subcategory":"Landscaping Services",
            "type":"Services"
        }
    ],
    "sg:phone":"+61 7 3623 8200",
    "sg:postcode":"4014",
    "sg:province":"QLD",
    "sg:tags":[
        "control",
        "weed"
    ],
    "wof:name":"Centrogen Pty Ltd",
    "wof:placetype":"venue"
},
  "geometry": {"coordinates":[153.05914306599999,-27.376329422],"type":"Point"}
}