{
  "type": "Feature",
  "properties": {
    "iso:country":"AU",
    "sg:address":"233 Frederick Rd",
    "sg:city":"Seaton",
    "sg:classifiers":[
        {
            "category":"Shopping",
            "subcategory":"Shoes",
            "type":"Retail Goods"
        }
    ],
    "sg:phone":"+61 8 8353 2130",
    "sg:postcode":"5023",
    "sg:province":"SA",
    "sg:tags":[
        "footwear"
    ],
    "wof:name":"Blue Sheep",
    "wof:placetype":"venue"
},
  "geometry": {"coordinates":[138.505783081,-34.9065437317],"type":"Point"}
}