{
  "type": "Feature",
  "properties": {
    "iso:country":"AU",
    "sg:address":"14 Pinnata Crt",
    "sg:city":"Everton Hills",
    "sg:classifiers":[
        {
            "category":"Professional",
            "subcategory":"Employment Agencies",
            "type":"Services"
        }
    ],
    "sg:phone":"+61 7 3355 0562",
    "sg:postcode":"4053",
    "sg:province":"QLD",
    "sg:tags":[
        "provider",
        "internet"
    ],
    "wof:name":"Advanced Corporate Consultancy",
    "wof:placetype":"venue"
},
  "geometry": {"coordinates":[152.97535705600001,-27.3923873901],"type":"Point"}
}