{
  "type": "Feature",
  "properties": {
    "iso:country":"AU",
    "sg:address":"Cnr Lister & Gager Sts",
    "sg:city":"Sunnybank",
    "sg:classifiers":[
        {
            "category":"Government",
            "subcategory":"City Hall",
            "type":"Public Place"
        }
    ],
    "sg:phone":"+61 7 3403 4233",
    "sg:postcode":"4109",
    "sg:province":"QLD",
    "wof:name":"Sunnybank Hall",
    "wof:placetype":"venue"
},
  "geometry": {"coordinates":[153.06117248499999,-27.5789985657],"type":"Point"}
}