{
  "type": "Feature",
  "properties": {
    "iso:country":"AU",
    "sg:address":"36 Granadilla Drv",
    "sg:city":"Earlville",
    "sg:classifiers":[
        {
            "category":"Utilities",
            "subcategory":"Electric",
            "type":"Services"
        }
    ],
    "sg:phone":"+61 7 4054 3770",
    "sg:postcode":"4870",
    "sg:province":"QLD",
    "sg:tags":[
        "electrical",
        "contractor"
    ],
    "wof:name":"Addie John Electrics",
    "wof:placetype":"venue"
},
  "geometry": {"coordinates":[145.73109435999999,-16.9510955811],"type":"Point"}
}