{
  "type": "Feature",
  "properties": {
    "iso:country":"AU",
    "sg:address":"Shop 104B, Cnr Henry Parry Drv & William St",
    "sg:city":"Gosford",
    "sg:classifiers":[
        {
            "category":"Shopping",
            "subcategory":"Jewelry",
            "type":"Retail Goods"
        }
    ],
    "sg:phone":"+61 2 4323 1877",
    "sg:postcode":"2250",
    "sg:province":"NSW",
    "sg:tags":[
        "jeweller"
    ],
    "wof:name":"Tribal Path",
    "wof:placetype":"venue"
},
  "geometry": {"coordinates":[151.342407227,-33.4260978699],"type":"Point"}
}