{
  "type": "Feature",
  "properties": {
    "iso:country":"AU",
    "sg:address":"Oxford Rd",
    "sg:city":"Ingleburn",
    "sg:classifiers":[
        {
            "category":"Professional",
            "subcategory":"Accounting & Tax Preparation",
            "type":"Services"
        }
    ],
    "sg:phone":"+61 2 9829 3111",
    "sg:postcode":"2565",
    "sg:province":"NSW",
    "sg:tags":[
        "accountant",
        "auditor"
    ],
    "wof:name":"Christian Fox Accountants",
    "wof:placetype":"venue"
},
  "geometry": {"coordinates":[150.86598205600001,-33.9984817505],"type":"Point"}
}