{
  "type": "Feature",
  "properties": {
    "addr:full":"Unit 2, 11- 13 Arizona Rd Charmhaven NSW 2263",
    "addr:housenumber":"11 13",
    "addr:postcode":"2263",
    "addr:street":"Arizona Rd",
    "iso:country":"AU",
    "sg:address":"Unit 2, 11- 13 Arizona Rd",
    "sg:city":"Charmhaven",
    "sg:classifiers":[
        {
            "category":"Wholesale",
            "subcategory":"Electrical",
            "type":"Manufacturing & Wholesale Goods"
        }
    ],
    "sg:phone":"+61 2 4393 3891",
    "sg:postcode":"2263",
    "sg:province":"NSW",
    "sg:tags":[
        "wholesaler",
        "mfrs",
        "accessory"
    ],
    "wof:name":"Cetnaj Pty Ltd",
    "wof:placetype":"venue"
},
  "geometry": {"coordinates":[151.493774,-33.242203],"type":"Point"}
}