{
  "type": "Feature",
  "properties": {
    "addr:full":"340 High St Penrith NSW 2750",
    "addr:housenumber":"340",
    "addr:postcode":"2750",
    "addr:street":"High St",
    "iso:country":"AU",
    "sg:address":"340 High St",
    "sg:city":"Penrith",
    "sg:classifiers":[
        {
            "category":"Real Estate",
            "subcategory":"Real Estate Agent",
            "type":"Services"
        }
    ],
    "sg:phone":"+61 2 4732 3333",
    "sg:postcode":"2750",
    "sg:province":"NSW",
    "wof:name":"Ray White Penrith",
    "wof:placetype":"venue"
},
  "geometry": {"coordinates":[150.91558837900001,-33.8947906494],"type":"Point"}
}