{
  "type": "Feature",
  "properties": {
    "iso:country":"AU",
    "sg:address":"65 Deakin Ave",
    "sg:city":"Mildura",
    "sg:classifiers":[
        {
            "category":"Shopping",
            "subcategory":"Jewelry",
            "type":"Retail Goods"
        }
    ],
    "sg:phone":"+61 3 5023 1028",
    "sg:postcode":"3500",
    "sg:province":"VIC",
    "sg:tags":[
        "jeweller"
    ],
    "wof:name":"Etherington's The Jewellers",
    "wof:placetype":"venue"
},
  "geometry": {"coordinates":[142.161453247,-34.1857185364],"type":"Point"}
}