{
  "type": "Feature",
  "properties": {
    "iso:country":"AU",
    "sg:address":"Sh 1a 9 Westralia St",
    "sg:city":"Stuart Park",
    "sg:classifiers":[
        {
            "category":"Health Services",
            "subcategory":"Dentist",
            "type":"Services"
        }
    ],
    "sg:phone":"+61 8 8981 8113",
    "sg:postcode":"0820",
    "sg:province":"NT",
    "wof:name":"Darwin Tooth Replacement Centre",
    "wof:placetype":"venue"
},
  "geometry": {"coordinates":[130.83203125,-12.4557132721],"type":"Point"}
}