{
  "type": "Feature",
  "properties": {
    "addr:full":"Suite 27 , Commercial Centre, Isle Of Capri QLD 4217",
    "addr:postcode":"4217",
    "iso:country":"AU",
    "sg:address":"Suite 27",
    "sg:city":", Commercial Centre, Isle Of Capri",
    "sg:classifiers":[
        {
            "category":"Professional",
            "subcategory":"Accounting & Tax Preparation",
            "type":"Services"
        }
    ],
    "sg:phone":"+61 7 5538 5099",
    "sg:postcode":"4217",
    "sg:province":"QLD",
    "sg:tags":[
        "accountant",
        "auditor"
    ],
    "wof:name":"Anthony Smith & Company",
    "wof:placetype":"venue"
},
  "geometry": {"coordinates":[153.41133117699999,-27.9702339172],"type":"Point"}
}