{
  "type": "Feature",
  "properties": {
    "addr:full":"143 Newmarket Rd Windsor QLD 4030",
    "addr:housenumber":"143",
    "addr:postcode":"4030",
    "addr:street":"Newmarket Rd",
    "iso:country":"AU",
    "sg:address":"143 Newmarket Rd",
    "sg:city":"Windsor",
    "sg:classifiers":[
        {
            "category":"Autos & Motor Vehicles",
            "subcategory":"Automobile Sales",
            "type":"Retail Goods"
        }
    ],
    "sg:phone":"+61 7 3109 6711",
    "sg:postcode":"4030",
    "sg:province":"QLD",
    "sg:tags":[
        "car",
        "new"
    ],
    "wof:name":"Eagers Windsor",
    "wof:placetype":"venue"
},
  "geometry": {"coordinates":[153.02330000000001,-27.436844],"type":"Point"}
}