{
  "type": "Feature",
  "properties": {
    "addr:full":"21- 23 Tarnard Drv Braeside VIC 3195",
    "addr:housenumber":"23",
    "addr:postcode":"3195",
    "addr:street":"Tarnard Drv",
    "iso:country":"AU",
    "sg:address":"21- 23 Tarnard Drv",
    "sg:city":"Braeside",
    "sg:classifiers":[
        {
            "category":"Manufacturing",
            "subcategory":"Glass & Minerals",
            "type":"Manufacturing & Wholesale Goods"
        }
    ],
    "sg:phone":"+61 3 9587 8777",
    "sg:postcode":"3195",
    "sg:province":"VIC",
    "sg:tags":[
        "merchant",
        "granite",
        "marble"
    ],
    "wof:name":"Doric Marble",
    "wof:placetype":"venue"
},
  "geometry": {"coordinates":[145.111984253,-37.9890632629],"type":"Point"}
}