{
  "type": "Feature",
  "properties": {
    "addr:full":"Fact 21, 14- 26 Audsley St Clayton VIC 3168",
    "addr:housenumber":"21;26",
    "addr:postcode":"3168",
    "addr:street":"Fact;Audsley St",
    "iso:country":"AU",
    "sg:address":"Fact 21, 14- 26 Audsley St",
    "sg:city":"Clayton",
    "sg:classifiers":[
        {
            "category":"Building & Trades",
            "subcategory":"Construction",
            "type":"Services"
        }
    ],
    "sg:phone":"+61 3 9545 5032",
    "sg:postcode":"3168",
    "sg:province":"VIC",
    "sg:tags":[
        "equipment",
        "balancing"
    ],
    "wof:name":"Statewide Driveshaft Services Pty Ltd",
    "wof:placetype":"venue"
},
  "geometry": {"coordinates":[145.124755859,-37.899181366],"type":"Point"}
}