{
  "type": "Feature",
  "properties": {
    "iso:country":"AU",
    "sg:address":"PO Box 40",
    "sg:city":"Park Holme",
    "sg:classifiers":[
        {
            "category":"Manufacturing",
            "subcategory":"Tools & Machinery",
            "type":"Manufacturing & Wholesale Goods"
        }
    ],
    "sg:phone":"+61 8 8295 3364",
    "sg:postcode":"5043",
    "sg:province":"SA",
    "sg:tags":[
        "earth",
        "excavating",
        "moving",
        "equipment"
    ],
    "wof:name":"Dig it With Dingo",
    "wof:placetype":"venue"
},
  "geometry": {"coordinates":[138.556793,-34.990849],"type":"Point"}
}