{
  "type": "Feature",
  "properties": {
    "iso:country":"AU",
    "sg:address":"Shelley Rd",
    "sg:city":"Moruya",
    "sg:classifiers":[
        {
            "category":"Home & Garden",
            "subcategory":"Building Materials",
            "type":"Retail Goods"
        }
    ],
    "sg:phone":"+61 2 4474 4500",
    "sg:postcode":"2537",
    "sg:province":"NSW",
    "sg:tags":[
        "wall",
        "frame",
        "truss",
        "roof"
    ],
    "wof:name":"Truss Steel",
    "wof:placetype":"venue"
},
  "geometry": {"coordinates":[150.08912658700001,-35.8778572083],"type":"Point"}
}