{
  "type": "Feature",
  "properties": {
    "iso:country":"AU",
    "sg:address":"37 Phoenix St",
    "sg:city":"Warragul",
    "sg:classifiers":[
        {
            "category":"Building & Trades",
            "subcategory":"Plumbing",
            "type":"Services"
        }
    ],
    "sg:phone":"+61 3 5623 2326",
    "sg:postcode":"3820",
    "sg:province":"VIC",
    "sg:tags":[
        "plumber",
        "gasfitters"
    ],
    "wof:name":"Heenan J.B. & S.E. Pty Ltd",
    "wof:placetype":"venue"
},
  "geometry": {"coordinates":[145.941864,-38.166073],"type":"Point"}
}