{
  "type": "Feature",
  "properties": {
    "addr:full":"567 Wyndham St Shepparton VIC 3630",
    "addr:housenumber":"567",
    "addr:postcode":"3630",
    "addr:street":"Wyndham St",
    "iso:country":"AU",
    "sg:address":"567 Wyndham St",
    "sg:city":"Shepparton",
    "sg:classifiers":[
        {
            "category":"Health Services",
            "subcategory":"Chiropractor",
            "type":"Services"
        }
    ],
    "sg:phone":"+61 3 5831 7428",
    "sg:postcode":"3630",
    "sg:province":"VIC",
    "wof:name":"Goulburn Valley Chiropractic Clinic",
    "wof:placetype":"venue"
},
  "geometry": {"coordinates":[145.39674377399999,-36.3946037292],"type":"Point"}
}