{
  "type": "Feature",
  "properties": {
    "addr:full":"64 High St Northcote VIC 3070",
    "addr:housenumber":"64",
    "addr:postcode":"3070",
    "addr:street":"High St",
    "iso:country":"AU",
    "sg:address":"64 High St",
    "sg:city":"Northcote",
    "sg:classifiers":[
        {
            "category":"Arts & Performance",
            "subcategory":"Music",
            "type":"Entertainment"
        }
    ],
    "sg:phone":"+61 3 9482 2477",
    "sg:postcode":"3070",
    "sg:province":"VIC",
    "sg:tags":[
        "hi-fi",
        "equipment"
    ],
    "wof:name":"Total Recoil Australia",
    "wof:placetype":"venue"
},
  "geometry": {"coordinates":[144.996948,-37.78072],"type":"Point"}
}