{
  "type": "Feature",
  "properties": {
    "addr:full":"16 Mckenzie Pl Griffith NSW 2680",
    "addr:housenumber":"16",
    "addr:postcode":"2680",
    "addr:street":"Mckenzie Pl",
    "iso:country":"AU",
    "sg:address":"16 Mckenzie Pl",
    "sg:city":"Griffith",
    "sg:classifiers":[
        {
            "category":"Health Services",
            "subcategory":"Health Practitioner",
            "type":"Services"
        }
    ],
    "sg:phone":"+61 2 6962 6386",
    "sg:postcode":"2680",
    "sg:province":"NSW",
    "sg:tags":[
        "pathologist",
        "speech"
    ],
    "wof:name":"Seton Janice Speech Pathologist",
    "wof:placetype":"venue"
},
  "geometry": {"coordinates":[146.061646,-34.285007],"type":"Point"}
}