{
  "type": "Feature",
  "properties": {
    "addr:full":"5 Townsend St Phillip ACT 2606",
    "addr:housenumber":"5",
    "addr:postcode":"2606",
    "addr:street":"Townsend St",
    "iso:country":"AU",
    "sg:address":"5 Townsend St",
    "sg:city":"Phillip",
    "sg:classifiers":[
        {
            "category":"Health Services",
            "subcategory":"Podiatrist",
            "type":"Services"
        }
    ],
    "sg:phone":"+61 2 6282 3119",
    "sg:postcode":"2606",
    "sg:province":"ACT",
    "sg:tags":[
        "cap",
        "hat",
        "renovation",
        "retail"
    ],
    "wof:name":"Saddleworld Canberra",
    "wof:placetype":"venue"
},
  "geometry": {"coordinates":[149.087799072,-35.3510055542],"type":"Point"}
}