{
  "type": "Feature",
  "properties": {
    "addr:full":"Unit 22, Sunshine Homemaker Centre, Cnr Maroochydo Maroochydore QLD 4558",
    "addr:postcode":"4558",
    "addr:street":"Cnr Maroochydo",
    "iso:country":"AU",
    "sg:address":"Unit 22, Sunshine Homemaker Centre, Cnr Maroochydo",
    "sg:city":"Maroochydore",
    "sg:classifiers":[
        {
            "category":"Shopping",
            "subcategory":"Mobile Phones",
            "type":"Retail Goods"
        }
    ],
    "sg:phone":"+61 7 5443 9499",
    "sg:postcode":"4558",
    "sg:province":"QLD",
    "sg:tags":[
        "telephone",
        "accessory"
    ],
    "wof:name":"Strathfield",
    "wof:placetype":"venue"
},
  "geometry": {"coordinates":[153.06849670400001,-26.6588611603],"type":"Point"}
}