{
  "type": "Feature",
  "properties": {
    "addr:full":"Shop 2/ 92 Grimshaw St Greensborough VIC 3088",
    "addr:housenumber":"shop 2 / 92",
    "addr:postcode":"3088",
    "addr:street":"Grimshaw St",
    "iso:country":"AU",
    "sg:address":"Shop 2/ 92 Grimshaw St",
    "sg:city":"Greensborough",
    "sg:classifiers":[
        {
            "category":"Personal",
            "subcategory":"Tanning Parlor",
            "type":"Services"
        }
    ],
    "sg:phone":"+61 3 9434 4595",
    "sg:postcode":"3088",
    "sg:province":"VIC",
    "sg:tags":[
        "solarium"
    ],
    "wof:name":"Sunsation Tanning Studio",
    "wof:placetype":"venue"
},
  "geometry": {"coordinates":[145.10151672399999,-37.7042617798],"type":"Point"}
}