{
  "type": "Feature",
  "properties": {
    "addr:full":"28a Finniss St Marion SA 5043",
    "addr:housenumber":"28a",
    "addr:postcode":"5043",
    "addr:street":"Finniss St",
    "iso:country":"AU",
    "sg:address":"28a Finniss St",
    "sg:city":"Marion",
    "sg:classifiers":[
        {
            "category":"Personal",
            "subcategory":"Beauty Salon",
            "type":"Services"
        }
    ],
    "sg:phone":"+61 8 8298 2796",
    "sg:postcode":"5043",
    "sg:province":"SA",
    "sg:tags":[
        "hairdresser"
    ],
    "wof:name":"The Hair Shoppe",
    "wof:placetype":"venue"
},
  "geometry": {"coordinates":[138.55517599999999,-35.008842],"type":"Point"}
}