{
  "type": "Feature",
  "properties": {
    "iso:country":"AU",
    "sg:address":"Suite 45 Wattletree Rd",
    "sg:city":"Malvern",
    "sg:classifiers":[
        {
            "category":"Health Services",
            "subcategory":"Doctor",
            "type":"Services"
        }
    ],
    "sg:phone":"+61 3 9509 3744",
    "sg:postcode":"3144",
    "sg:province":"VIC",
    "sg:tags":[
        "medical",
        "practitioner"
    ],
    "wof:name":"Stanley Robert M",
    "wof:placetype":"venue"
},
  "geometry": {"coordinates":[145.03526306099999,-37.8632507324],"type":"Point"}
}