{
  "type": "Feature",
  "properties": {
    "iso:country":"AU",
    "sg:address":"16 Bundoora Drv",
    "sg:city":"Karana Downs",
    "sg:classifiers":[
        {
            "category":"Professional",
            "subcategory":"Art Services",
            "type":"Services"
        }
    ],
    "sg:phone":"+61 7 3201 2490",
    "sg:postcode":"4306",
    "sg:province":"QLD",
    "sg:tags":[
        "graphic",
        "designer"
    ],
    "wof:name":"Pacific Designs",
    "wof:placetype":"venue"
},
  "geometry": {"coordinates":[152.80862426799999,-27.5478649139],"type":"Point"}
}