{
  "type": "Feature",
  "properties": {
    "iso:country":"AU",
    "sg:address":"6 Birru Rd",
    "sg:city":"Gosford North",
    "sg:classifiers":[
        {
            "category":"Building & Trades",
            "subcategory":"Construction",
            "type":"Services"
        }
    ],
    "sg:phone":"+61 2 4321 1588",
    "sg:postcode":"2250",
    "sg:province":"NSW",
    "sg:tags":[
        "decking",
        "contractor"
    ],
    "wof:name":"Bali Style.com.au",
    "wof:placetype":"venue"
},
  "geometry": {"coordinates":[151.343994141,-33.4111595154],"type":"Point"}
}