{
  "type": "Feature",
  "properties": {
    "iso:country":"AU",
    "sg:address":"118 Mount St",
    "sg:city":"North Sydney",
    "sg:classifiers":[
        {
            "category":"Insurance",
            "subcategory":"Hazard Insurance",
            "type":"Services"
        }
    ],
    "sg:phone":"+61 2 9391 1111",
    "sg:postcode":"2060",
    "sg:province":"NSW",
    "sg:tags":[
        "fire",
        "accident",
        "marine"
    ],
    "wof:name":"Zurich Australian Insurance Group",
    "wof:placetype":"venue"
},
  "geometry": {"coordinates":[151.20956420900001,-33.8390731812],"type":"Point"}
}