{
  "type": "Feature",
  "properties": {
    "addr:full":"58 Cross St Double Bay NSW 2028",
    "addr:housenumber":"58",
    "addr:postcode":"2028",
    "addr:street":"Cross St",
    "iso:country":"AU",
    "sg:address":"58 Cross St",
    "sg:city":"Double Bay",
    "sg:classifiers":[
        {
            "category":"Health Services",
            "subcategory":"Dentist",
            "type":"Services"
        }
    ],
    "sg:phone":"+61 2 9327 5575",
    "sg:postcode":"2028",
    "sg:province":"NSW",
    "wof:name":"Biscoe Christine Dr",
    "wof:placetype":"venue"
},
  "geometry": {"coordinates":[151.24079895,-33.8754005432],"type":"Point"}
}