{
  "type": "Feature",
  "properties": {
    "iso:country":"AU",
    "sg:address":"4 Bishop St",
    "sg:city":"Port Lincoln",
    "sg:classifiers":[
        {
            "category":"Professional",
            "type":"Services"
        }
    ],
    "sg:phone":"+61 8 8682 5666",
    "sg:postcode":"5606",
    "sg:province":"SA",
    "sg:tags":[
        "auctioneer"
    ],
    "wof:name":"Raine & Horne",
    "wof:placetype":"venue"
},
  "geometry": {"coordinates":[135.863525,-34.723827],"type":"Point"}
}