{
  "type": "Feature",
  "properties": {
    "addr:full":"7b Pioneer Ave Thornleigh NSW 2120",
    "addr:housenumber":"7b",
    "addr:postcode":"2120",
    "addr:street":"Pioneer Ave",
    "iso:country":"AU",
    "sg:address":"7b Pioneer Ave",
    "sg:city":"Thornleigh",
    "sg:classifiers":[
        {
            "category":"Retail",
            "subcategory":"Auto Repair",
            "type":"Services"
        }
    ],
    "sg:phone":"+61 2 9481 7363",
    "sg:postcode":"2120",
    "sg:province":"NSW",
    "sg:tags":[
        "gas",
        "conversion",
        "natural",
        "lp",
        "vehicle"
    ],
    "wof:name":"GASitUP",
    "wof:placetype":"venue"
},
  "geometry": {"coordinates":[151.08375549300001,-33.7244148254],"type":"Point"}
}