{
  "type": "Feature",
  "properties": {
    "iso:country":"AU",
    "sg:address":"120 Sudholtz Rd",
    "sg:city":"Verrierdale",
    "sg:classifiers":[
        {
            "category":"Building & Trades",
            "subcategory":"Landscaping Services",
            "type":"Services"
        }
    ],
    "sg:phone":"+61 7 5449 1796",
    "sg:postcode":"4562",
    "sg:province":"QLD",
    "sg:tags":[
        "control",
        "weed"
    ],
    "wof:name":"Gamble Serina",
    "wof:placetype":"venue"
},
  "geometry": {"coordinates":[152.999725342,-26.4931182861],"type":"Point"}
}