{
  "type": "Feature",
  "properties": {
    "addr:full":"198 Barkley St St Kilda VIC 3182",
    "addr:housenumber":"198",
    "addr:postcode":"3182",
    "addr:street":"Barkley St",
    "iso:country":"AU",
    "sg:address":"198 Barkley St",
    "sg:city":"St Kilda",
    "sg:classifiers":[
        {
            "category":"Fast Food",
            "type":"Food & Drink"
        }
    ],
    "sg:phone":"+61 3 9534 8460",
    "sg:postcode":"3182",
    "sg:province":"VIC",
    "sg:tags":[
        "away",
        "take"
    ],
    "wof:name":"Krua Thai",
    "wof:placetype":"venue"
},
  "geometry": {"coordinates":[144.98089599599999,-37.8697814941],"type":"Point"}
}