{
  "type": "Feature",
  "properties": {
    "iso:country":"AU",
    "sg:address":"56 Carr St",
    "sg:city":"Coogee",
    "sg:classifiers":[
        {
            "category":"Travel",
            "subcategory":"Hotels & Motels",
            "type":"Entertainment"
        }
    ],
    "sg:phone":"+61 2 9315 8388",
    "sg:postcode":"2034",
    "sg:province":"NSW",
    "sg:tags":[
        "accommodation"
    ],
    "wof:name":"Coogee View",
    "wof:placetype":"venue"
},
  "geometry": {"coordinates":[151.25683593799999,-33.9229736328],"type":"Point"}
}