{
  "type": "Feature",
  "properties": {
    "iso:country":"AU",
    "sg:address":"Shop 6 & 7 Matthew Flinders Centre",
    "sg:city":"Augusta",
    "sg:classifiers":[
        {
            "category":"Health Services",
            "subcategory":"Health Practitioner",
            "type":"Services"
        }
    ],
    "sg:phone":"+61 8 9758 0418",
    "sg:postcode":"6290",
    "sg:province":"WA",
    "sg:tags":[
        "naturopath"
    ],
    "wof:name":"Bimaris Health",
    "wof:placetype":"venue"
},
  "geometry": {"coordinates":[115.139793396,-34.2895584106],"type":"Point"}
}