{
  "type": "Feature",
  "properties": {
    "iso:country":"AU",
    "sg:address":"Shp 1044/ 236 Pacific Hwy",
    "sg:city":"Hornsby",
    "sg:classifiers":[
        {
            "category":"Retail",
            "subcategory":"Repair Shop",
            "type":"Services"
        }
    ],
    "sg:phone":"+61 2 9482 9852",
    "sg:postcode":"2077",
    "sg:province":"NSW",
    "sg:tags":[
        "handbag"
    ],
    "wof:name":"Modo Handbags",
    "wof:placetype":"venue"
},
  "geometry": {"coordinates":[151.09779357900001,-33.6981201172],"type":"Point"}
}