{
  "type": "Feature",
  "properties": {
    "iso:country":"AU",
    "sg:address":"1391 Maher Rd",
    "sg:city":"Bonegilla",
    "sg:classifiers":[
        {
            "category":"Retail",
            "subcategory":"Auto Repair",
            "type":"Services"
        }
    ],
    "sg:phone":"+61 2 6020 6396",
    "sg:postcode":"3691",
    "sg:province":"NSW",
    "sg:tags":[
        "beater",
        "painter",
        "panel"
    ],
    "wof:name":"Recoat Spraypainting",
    "wof:placetype":"venue"
},
  "geometry": {"coordinates":[146.89329499999999,-36.113289],"type":"Point"}
}