{
  "type": "Feature",
  "properties": {
    "addr:full":"48 Hibbard Drv Port Macquarie NSW 2444",
    "addr:housenumber":"48",
    "addr:postcode":"2444",
    "addr:street":"Hibbard Drv",
    "iso:country":"AU",
    "sg:address":"48 Hibbard Drv",
    "sg:city":"Port Macquarie",
    "sg:classifiers":[
        {
            "category":"Farming",
            "subcategory":"Livestock Farm",
            "type":"Manufacturing & Wholesale Goods"
        }
    ],
    "sg:phone":"+61 2 6583 5757",
    "sg:postcode":"2444",
    "sg:province":"NSW",
    "sg:tags":[
        "buyer"
    ],
    "wof:name":"Steel J K Pty Ltd",
    "wof:placetype":"venue"
},
  "geometry": {"coordinates":[152.883835,-31.422886],"type":"Point"}
}