{
  "type": "Feature",
  "properties": {
    "addr:full":"35 Manton St Bulimba QLD 4171",
    "addr:housenumber":"35",
    "addr:postcode":"4171",
    "addr:street":"Manton St",
    "iso:country":"AU",
    "sg:address":"35 Manton St",
    "sg:city":"Bulimba",
    "sg:classifiers":[
        {
            "category":"Home & Garden",
            "subcategory":"Building Materials",
            "type":"Retail Goods"
        }
    ],
    "sg:phone":"+61 7 3899 0511",
    "sg:postcode":"4171",
    "sg:province":"QLD",
    "sg:tags":[
        "wall",
        "frame",
        "truss",
        "roof"
    ],
    "wof:name":"Advanced Truss Systems Pty Ltd",
    "wof:placetype":"venue"
},
  "geometry": {"coordinates":[153.05929565400001,-27.4513607025],"type":"Point"}
}