{
  "type": "Feature",
  "properties": {
    "addr:full":"1/ 177 Moray St South Melbourne VIC 3205",
    "addr:housenumber":"/ 177",
    "addr:postcode":"3205",
    "addr:street":"Moray St",
    "iso:country":"AU",
    "sg:address":"1/ 177 Moray St",
    "sg:city":"South Melbourne",
    "sg:classifiers":[
        {
            "category":"Banks & Credit Unions",
            "subcategory":"Financial Services",
            "type":"Services"
        }
    ],
    "sg:phone":"+61 3 9684 4844",
    "sg:postcode":"3205",
    "sg:province":"VIC",
    "sg:tags":[
        "financier"
    ],
    "wof:name":"Onelife Solutions (Aust) Pty Ltd",
    "wof:placetype":"venue"
},
  "geometry": {"coordinates":[144.96301299999999,-37.831779],"type":"Point"}
}