{
  "type": "Feature",
  "properties": {
    "addr:full":"15 Meadows Pl Quinns Rocks WA 6030",
    "addr:housenumber":"15",
    "addr:postcode":"6030",
    "addr:street":"Meadows Pl",
    "iso:country":"AU",
    "sg:address":"15 Meadows Pl",
    "sg:city":"Quinns Rocks",
    "sg:classifiers":[
        {
            "category":"Professional",
            "subcategory":"Art Services",
            "type":"Services"
        }
    ],
    "sg:phone":"+61 409 771 484",
    "sg:postcode":"6030",
    "sg:province":"WA",
    "sg:tags":[
        "decorator",
        "painter"
    ],
    "wof:name":"BJs Painting & Decorating",
    "wof:placetype":"venue"
},
  "geometry": {"coordinates":[115.706016541,-31.6680145264],"type":"Point"}
}