{
  "type": "Feature",
  "properties": {
    "addr:full":"505 Parramatta Rd Leichhardt NSW 2040",
    "addr:housenumber":"505",
    "addr:postcode":"2040",
    "addr:street":"Parramatta Rd",
    "iso:country":"AU",
    "sg:address":"505 Parramatta Rd",
    "sg:city":"Leichhardt",
    "sg:classifiers":[
        {
            "category":"Home & Garden",
            "subcategory":"Carpets & Floor Coverings",
            "type":"Retail Goods"
        }
    ],
    "sg:phone":"+61 2 9518 3593",
    "sg:postcode":"2040",
    "sg:province":"NSW",
    "sg:tags":[
        "wood"
    ],
    "wof:name":"Maxs W. Floors",
    "wof:placetype":"venue"
},
  "geometry": {"coordinates":[151.153549,-33.888744],"type":"Point"}
}