{
  "type": "Feature",
  "properties": {
    "addr:full":"37 Carrington St Queanbeyan ACT 2620",
    "addr:housenumber":"37",
    "addr:postcode":"2620",
    "addr:street":"Carrington St",
    "iso:country":"AU",
    "sg:address":"37 Carrington St",
    "sg:city":"Queanbeyan",
    "sg:classifiers":[
        {
            "category":"Retail",
            "subcategory":"Auto Repair",
            "type":"Services"
        }
    ],
    "sg:phone":"+61 2 6299 1177",
    "sg:postcode":"2620",
    "sg:province":"ACT",
    "sg:tags":[
        "fuel",
        "petrol",
        "injection"
    ],
    "wof:name":"Class Auto Electrics",
    "wof:placetype":"venue"
},
  "geometry": {"coordinates":[149.24110412600001,-35.3397293091],"type":"Point"}
}