{
  "type": "Feature",
  "properties": {
    "addr:full":"Cnr Ingles & Turner Sts Port Melbourne VIC 3207",
    "addr:postcode":"3207",
    "iso:country":"AU",
    "sg:address":"Cnr Ingles & Turner Sts",
    "sg:city":"Port Melbourne",
    "sg:classifiers":[
        {
            "category":"Manufacturing",
            "subcategory":"Motor Vehicles & Parts",
            "type":"Manufacturing & Wholesale Goods"
        }
    ],
    "sg:phone":"+61 3 9864 3535",
    "sg:postcode":"3207",
    "sg:province":"VIC",
    "sg:tags":[
        "replacement"
    ],
    "wof:name":"Volvo",
    "wof:placetype":"venue"
},
  "geometry": {"coordinates":[144.93563800000001,-37.824547],"type":"Point"}
}