{
  "type": "Feature",
  "properties": {
    "iso:country":"AU",
    "sg:address":"71 Marigold St",
    "sg:city":"Revesby",
    "sg:classifiers":[
        {
            "category":"Shopping",
            "subcategory":"Stationery & Office Supplies",
            "type":"Retail Goods"
        }
    ],
    "sg:phone":"+61 2 9792 1922",
    "sg:postcode":"2212",
    "sg:province":"NSW",
    "sg:tags":[
        "equipment",
        "display",
        "exhibition"
    ],
    "wof:name":"Mason Duflex",
    "wof:placetype":"venue"
},
  "geometry": {"coordinates":[150.999512,-33.940186],"type":"Point"}
}