{
  "type": "Feature",
  "properties": {
    "iso:country":"AU",
    "sg:address":"Unit 2 13 Machine Ave",
    "sg:city":"Warana",
    "sg:classifiers":[
        {
            "category":"Retail",
            "subcategory":"Auto Repair",
            "type":"Services"
        }
    ],
    "sg:phone":"+61 7 5493 1388",
    "sg:postcode":"4575",
    "sg:province":"QLD",
    "sg:tags":[
        "beater",
        "painter",
        "panel"
    ],
    "wof:name":"Autoguard Automotive Services",
    "wof:placetype":"venue"
},
  "geometry": {"coordinates":[153.12376399999999,-26.729637],"type":"Point"}
}