{
  "type": "Feature",
  "properties": {
    "addr:full":"Level 2 Macquarie House 169 Macquarie St Parramatta NSW 2150",
    "addr:housenumber":"169",
    "addr:postcode":"2150",
    "addr:street":"Macquarie St",
    "iso:country":"AU",
    "sg:address":"Level 2 Macquarie House 169 Macquarie St",
    "sg:city":"Parramatta",
    "sg:classifiers":[
        {
            "category":"Banks & Credit Unions",
            "subcategory":"Investment Brokerage",
            "type":"Services"
        }
    ],
    "sg:phone":"+61 2 8833 1408",
    "sg:postcode":"2150",
    "sg:province":"NSW",
    "wof:name":"Godfrey Pembroke Financial Consultants",
    "wof:placetype":"venue"
},
  "geometry": {"coordinates":[151.05711364699999,-33.9092903137],"type":"Point"}
}