{
  "type": "Feature",
  "properties": {
    "addr:full":"RSD 1650 Lot 2 Range Rd Willunga SA 5172",
    "addr:housenumber":"2",
    "addr:postcode":"5172",
    "addr:street":"Range Rd",
    "iso:country":"AU",
    "sg:address":"RSD 1650 Lot 2 Range Rd",
    "sg:city":"Willunga",
    "sg:classifiers":[
        {
            "category":"Professional",
            "subcategory":"Art Services",
            "type":"Services"
        }
    ],
    "sg:phone":"+61 419 975 956",
    "sg:postcode":"5172",
    "sg:province":"SA",
    "sg:tags":[
        "decorator",
        "painter"
    ],
    "wof:name":"Bedford Stephen",
    "wof:placetype":"venue"
},
  "geometry": {"coordinates":[138.59585571299999,-35.2743606567],"type":"Point"}
}