{
  "type": "Feature",
  "properties": {
    "iso:country":"AU",
    "sg:address":"25 Belvoir St",
    "sg:city":"Surry Hills",
    "sg:classifiers":[
        {
            "category":"Arts & Performance",
            "subcategory":"Theater",
            "type":"Entertainment"
        }
    ],
    "sg:phone":"+61 2 9699 3444",
    "sg:postcode":"2010",
    "sg:province":"NSW",
    "sg:tags":[
        "theatre"
    ],
    "wof:name":"Company B / Belvoir St Theatre",
    "wof:placetype":"venue"
},
  "geometry": {"coordinates":[151.209472656,-33.8890190125],"type":"Point"}
}