{
  "type": "Feature",
  "properties": {
    "addr:full":"2 McBean St Culcairn NSW 2660",
    "addr:housenumber":"2",
    "addr:postcode":"2660",
    "addr:street":"Mcbean St",
    "iso:country":"AU",
    "sg:address":"2 McBean St",
    "sg:city":"Culcairn",
    "sg:classifiers":[
        {
            "category":"Manufacturing",
            "subcategory":"Wood Products",
            "type":"Manufacturing & Wholesale Goods"
        }
    ],
    "sg:phone":"+61 2 6029 7208",
    "sg:postcode":"2660",
    "sg:province":"NSW",
    "sg:tags":[
        "pallet",
        "platform"
    ],
    "wof:name":"Culcairn Pallets",
    "wof:placetype":"venue"
},
  "geometry": {"coordinates":[147.03414917000001,-35.6612167358],"type":"Point"}
}