{
  "type": "Feature",
  "properties": {
    "iso:country":"AU",
    "sg:address":"Savages Arcade 116 City Rd",
    "sg:city":"Beenleigh",
    "sg:classifiers":[
        {
            "category":"Banks & Credit Unions",
            "subcategory":"Bank",
            "type":"Services"
        }
    ],
    "sg:phone":"+61 7 3287 5377",
    "sg:postcode":"4207",
    "sg:province":"QLD",
    "wof:name":"Bank of Queensland",
    "wof:placetype":"venue"
},
  "geometry": {"coordinates":[153.20220947300001,-27.715970993],"type":"Point"}
}