{
  "type": "Feature",
  "properties": {
    "iso:country":"AU",
    "sg:address":"235 Heaths Rd",
    "sg:city":"Hoppers Crossing",
    "sg:classifiers":[
        {
            "category":"Health Services",
            "subcategory":"Dentist",
            "type":"Services"
        }
    ],
    "sg:phone":"+61 3 9399 8800",
    "sg:postcode":"3029",
    "sg:province":"VIC",
    "wof:name":"Riley McGlade D'Adamo Orthodontics",
    "wof:placetype":"venue"
},
  "geometry": {"coordinates":[144.680817,-37.877487],"type":"Point"}
}