{
  "type": "Feature",
  "properties": {
    "iso:country":"AU",
    "sg:address":"Unit 1/ 5 Bessemer St",
    "sg:city":"Blacktown",
    "sg:classifiers":[
        {
            "category":"Real Estate",
            "subcategory":"Architect",
            "type":"Services"
        }
    ],
    "sg:phone":"+61 2 9831 6244",
    "sg:postcode":"2148",
    "sg:province":"NSW",
    "sg:tags":[
        "fuel",
        "equipment",
        "pump",
        "carburettor"
    ],
    "wof:name":"Carburettor & EFI Service Co. Pty. Ltd.",
    "wof:placetype":"venue"
},
  "geometry": {"coordinates":[150.90826415999999,-33.7571754456],"type":"Point"}
}