{
  "type": "Feature",
  "properties": {
    "addr:full":"1/29A, Innes Rd Greenwich NSW 2065",
    "addr:housenumber":"/ 29a",
    "addr:postcode":"2065",
    "addr:street":"Innes Rd",
    "iso:country":"AU",
    "sg:address":"1/29A, Innes Rd",
    "sg:city":"Greenwich",
    "sg:classifiers":[
        {
            "category":"Professional",
            "subcategory":"Art Services",
            "type":"Services"
        }
    ],
    "sg:phone":"+61 411 584 770",
    "sg:postcode":"2065",
    "sg:province":"NSW",
    "sg:tags":[
        "graphic",
        "designer"
    ],
    "wof:name":"Astro Creative Services",
    "wof:placetype":"venue"
},
  "geometry": {"coordinates":[151.182571411,-33.8223342896],"type":"Point"}
}