{
  "type": "Feature",
  "properties": {
    "addr:full":"Shop 1/ 39 Steele St Devonport TAS 7310",
    "addr:housenumber":"shop 1 / 39",
    "addr:postcode":"7310",
    "addr:street":"Steele St",
    "iso:country":"AU",
    "sg:address":"Shop 1/ 39 Steele St",
    "sg:city":"Devonport",
    "sg:classifiers":[
        {
            "category":"Personal",
            "type":"Services"
        }
    ],
    "sg:phone":"+61 3 6424 8892",
    "sg:postcode":"7310",
    "sg:province":"TAS",
    "sg:tags":[
        "reducing",
        "treatment",
        "weight"
    ],
    "wof:name":"Headway Studio",
    "wof:placetype":"venue"
},
  "geometry": {"coordinates":[146.35952758799999,-41.181388855],"type":"Point"}
}