{
  "type": "Feature",
  "properties": {
    "addr:full":"132/ 149 Pyrmont St Pyrmont NSW 2009",
    "addr:housenumber":"132 / 149",
    "addr:postcode":"2009",
    "addr:street":"Pyrmont St",
    "iso:country":"AU",
    "sg:address":"132/ 149 Pyrmont St",
    "sg:city":"Pyrmont",
    "sg:classifiers":[
        {
            "category":"Shopping",
            "subcategory":"Clothing, Apparel, & Fashions",
            "type":"Retail Goods"
        }
    ],
    "sg:phone":"+61 2 9518 5142",
    "sg:postcode":"2009",
    "sg:province":"NSW",
    "sg:tags":[
        "textile",
        "designer"
    ],
    "wof:name":"Insight Concepts",
    "wof:placetype":"venue"
},
  "geometry": {"coordinates":[151.195709228,-33.8709793091],"type":"Point"}
}