{
  "type": "Feature",
  "properties": {
    "iso:country":"AU",
    "sg:address":"&#034;Art House Design Gallery&#034; Unit 1/ 39 By",
    "sg:city":"(Cnr Byre & Margaret Ave) Somerton Park",
    "sg:classifiers":[
        {
            "category":"Manufacturing",
            "subcategory":"Furniture",
            "type":"Manufacturing & Wholesale Goods"
        }
    ],
    "sg:phone":"+61 8 8376 7771",
    "sg:postcode":"5044",
    "sg:province":"SA",
    "sg:tags":[
        "builder",
        "designer",
        "custom"
    ],
    "wof:name":"Art House Furniture",
    "wof:placetype":"venue"
},
  "geometry": {"coordinates":[138.526184,-34.998066],"type":"Point"}
}