{
  "type": "Feature",
  "properties": {
    "iso:country":"AU",
    "sg:address":"70 Whitbread St",
    "sg:city":"Taree",
    "sg:classifiers":[
        {
            "category":"Home & Garden",
            "subcategory":"Building Materials",
            "type":"Retail Goods"
        }
    ],
    "sg:phone":"+61 2 6552 8888",
    "sg:postcode":"2430",
    "sg:province":"NSW",
    "sg:tags":[
        "supply"
    ],
    "wof:name":"Valley Industries",
    "wof:placetype":"venue"
},
  "geometry": {"coordinates":[152.46151699999999,-31.91313],"type":"Point"}
}