{
  "type": "Feature",
  "properties": {
    "iso:country":"AU",
    "sg:address":"126 Somerville Rd",
    "sg:city":"Yarraville",
    "sg:classifiers":[
        {
            "category":"Wholesale",
            "subcategory":"Electrical",
            "type":"Manufacturing & Wholesale Goods"
        }
    ],
    "sg:phone":"+61 3 9314 6800",
    "sg:postcode":"3013",
    "sg:province":"VIC",
    "sg:tags":[
        "wholesaler"
    ],
    "wof:name":"Middendorp Electric Co Pty Ltd",
    "wof:placetype":"venue"
},
  "geometry": {"coordinates":[144.88705444300001,-37.8130874634],"type":"Point"}
}