{
  "type": "Feature",
  "properties": {
    "addr:full":"138/251 Varsity Pde Varsity Lakes QLD 4226",
    "addr:housenumber":"138 / 251",
    "addr:postcode":"4226",
    "addr:street":"Varsity Pde",
    "iso:country":"AU",
    "sg:address":"138/251 Varsity Pde",
    "sg:city":"Varsity Lakes",
    "sg:classifiers":[
        {
            "category":"Professional",
            "subcategory":"Detective & Security Services",
            "type":"Services"
        }
    ],
    "sg:phone":"+61 411 882 509",
    "sg:postcode":"4226",
    "sg:province":"QLD",
    "sg:tags":[
        "equipment",
        "window",
        "doors"
    ],
    "wof:name":"Safeway Security",
    "wof:placetype":"venue"
},
  "geometry": {"coordinates":[153.41619873100001,-28.0773525238],"type":"Point"}
}