{
  "type": "Feature",
  "properties": {
    "addr:full":"Cnr Anzac Ave & James St Toowoomba QLD 4350",
    "addr:postcode":"4350",
    "addr:street":"Anzac Ave & James St",
    "iso:country":"AU",
    "sg:address":"Cnr Anzac Ave & James St",
    "sg:city":"Toowoomba",
    "sg:classifiers":[
        {
            "category":"Personal",
            "subcategory":"Hair Removal",
            "type":"Services"
        }
    ],
    "sg:phone":"+61 7 4633 0233",
    "sg:postcode":"4350",
    "sg:province":"QLD",
    "sg:website":"http://www.hairfree.com.au",
    "wof:name":"Hair Free Centre",
    "wof:placetype":"venue"
},
  "geometry": {"coordinates":[151.92172199999999,-27.577253],"type":"Point"}
}