{
  "type": "Feature",
  "properties": {
    "iso:country":"AU",
    "sg:address":"70 Kurrawyba Ave",
    "sg:city":"Terrigal",
    "sg:classifiers":[
        {
            "category":"Building & Trades",
            "subcategory":"Construction",
            "type":"Services"
        }
    ],
    "sg:phone":"+61 2 4384 1172",
    "sg:postcode":"2260",
    "sg:province":"NSW",
    "sg:tags":[
        "contractor"
    ],
    "wof:name":"Haven Constructions",
    "wof:placetype":"venue"
},
  "geometry": {"coordinates":[151.44232199999999,-33.452515],"type":"Point"}
}