{
  "type": "Feature",
  "properties": {
    "iso:country":"AU",
    "sg:address":"19 Oakleigh Drv",
    "sg:city":"Mandurah",
    "sg:classifiers":[
        {
            "category":"Social Services",
            "subcategory":"Retirement Home",
            "type":"Services"
        }
    ],
    "sg:phone":"+61 8 9586 4100",
    "sg:postcode":"6210",
    "sg:province":"WA",
    "sg:tags":[
        "village"
    ],
    "wof:name":"Erskine Grove",
    "wof:placetype":"venue"
},
  "geometry": {"coordinates":[115.696068,-32.557697],"type":"Point"}
}