{
  "type": "Feature",
  "properties": {
    "addr:full":"680 Ingham Rd Bohle QLD 4818",
    "addr:housenumber":"680",
    "addr:postcode":"4818",
    "addr:street":"Ingham Rd",
    "iso:country":"AU",
    "sg:address":"680 Ingham Rd",
    "sg:city":"Bohle",
    "sg:classifiers":[
        {
            "category":"Banks & Credit Unions",
            "subcategory":"Financial Services",
            "type":"Services"
        }
    ],
    "sg:phone":"+61 13 72 00",
    "sg:postcode":"4818",
    "sg:province":"QLD",
    "sg:tags":[
        "financier"
    ],
    "wof:name":"Toyota Financial Services",
    "wof:placetype":"venue"
},
  "geometry": {"coordinates":[146.736526,-19.261768],"type":"Point"}
}