{
  "type": "Feature",
  "properties": {
    "iso:country":"AU",
    "sg:address":"275 Adams Rd",
    "sg:city":"Luddenham",
    "sg:classifiers":[
        {
            "category":"Farming",
            "subcategory":"Livestock Farm",
            "type":"Manufacturing & Wholesale Goods"
        }
    ],
    "sg:phone":"+61 2 4773 4257",
    "sg:postcode":"2745",
    "sg:province":"NSW",
    "sg:tags":[
        "agistment"
    ],
    "wof:name":"Harpley L W",
    "wof:placetype":"venue"
},
  "geometry": {"coordinates":[150.71742248499999,-33.8698501587],"type":"Point"}
}