{
  "type": "Feature",
  "properties": {
    "iso:country":"AU",
    "sg:address":"26 Old Creswick Rd",
    "sg:city":"Ballarat",
    "sg:classifiers":[
        {
            "category":"Manufacturing",
            "subcategory":"Paper Products",
            "type":"Manufacturing & Wholesale Goods"
        }
    ],
    "sg:phone":"+61 3 5339 1306",
    "sg:postcode":"3350",
    "sg:province":"VIC",
    "sg:tags":[
        "box",
        "fibre",
        "carton",
        "cardboard"
    ],
    "wof:name":"Bennett-Meyer Packaging",
    "wof:placetype":"venue"
},
  "geometry": {"coordinates":[143.84930399999999,-37.525589],"type":"Point"}
}