{
  "type": "Feature",
  "properties": {
    "addr:full":"76 Paddington St Paddington NSW 2021",
    "addr:housenumber":"76",
    "addr:postcode":"2021",
    "addr:street":"Paddington St",
    "iso:country":"AU",
    "sg:address":"76 Paddington St",
    "sg:city":"Paddington",
    "sg:classifiers":[
        {
            "category":"Arts & Performance",
            "subcategory":"Art Gallery",
            "type":"Entertainment"
        }
    ],
    "sg:phone":"+61 2 9360 9854",
    "sg:postcode":"2021",
    "sg:province":"NSW",
    "wof:name":"Tim Olsen Gallery",
    "wof:placetype":"venue"
},
  "geometry": {"coordinates":[151.23246765100001,-33.8852348328],"type":"Point"}
}