{
  "type": "Feature",
  "properties": {
    "iso:country":"AU",
    "sg:address":"49 Batman St",
    "sg:city":"West Melbourne",
    "sg:classifiers":[
        {
            "category":"Education",
            "subcategory":"Dance Studio",
            "type":"Public Place"
        }
    ],
    "sg:phone":"+61 3 9329 8210",
    "sg:postcode":"3003",
    "sg:province":"VIC",
    "sg:tags":[
        "venue",
        "tuition"
    ],
    "wof:name":"Joining the Chorus",
    "wof:placetype":"venue"
},
  "geometry": {"coordinates":[144.95143127399999,-37.8108978271],"type":"Point"}
}