{
  "type": "Feature",
  "properties": {
    "addr:full":"10 Moira St Goolgowi NSW 2652",
    "addr:housenumber":"10",
    "addr:postcode":"2652",
    "addr:street":"Moira St",
    "iso:country":"AU",
    "sg:address":"10 Moira St",
    "sg:city":"Goolgowi",
    "sg:classifiers":[
        {
            "category":"Farming",
            "subcategory":"Farm & Veterinary Services",
            "type":"Manufacturing & Wholesale Goods"
        }
    ],
    "sg:phone":"+61 2 6965 1227",
    "sg:postcode":"2652",
    "sg:province":"NSW",
    "sg:tags":[
        "contracting"
    ],
    "wof:name":"Acheson Rural Services",
    "wof:placetype":"venue"
},
  "geometry": {"coordinates":[145.70724487300001,-33.9783782959],"type":"Point"}
}