{
  "type": "Feature",
  "properties": {
    "addr:full":"120A Ocean Pde Blue Bay NSW 2261",
    "addr:housenumber":"120a",
    "addr:postcode":"2261",
    "addr:street":"Ocean Pde;Bay",
    "iso:country":"AU",
    "sg:address":"120A Ocean Pde",
    "sg:city":"Blue Bay",
    "sg:classifiers":[
        {
            "category":"Health Services",
            "subcategory":"Doctor",
            "type":"Services"
        }
    ],
    "sg:phone":"+61 2 4333 3040",
    "sg:postcode":"2261",
    "sg:province":"NSW",
    "sg:tags":[
        "medical",
        "practitioner"
    ],
    "wof:name":"Lachs Maria Dr",
    "wof:placetype":"venue"
},
  "geometry": {"coordinates":[151.500519,-33.352459],"type":"Point"}
}