{
  "type": "Feature",
  "properties": {
    "iso:country":"AU",
    "sg:address":"10 Ardena Crt",
    "sg:city":"Bentleigh East",
    "sg:classifiers":[
        {
            "category":"Manufacturing",
            "subcategory":"Motor Vehicles & Parts",
            "type":"Manufacturing & Wholesale Goods"
        }
    ],
    "sg:phone":"+61 3 9563 8267",
    "sg:postcode":"3165",
    "sg:province":"VIC",
    "sg:tags":[
        "replacement"
    ],
    "wof:name":"Autologic",
    "wof:placetype":"venue"
},
  "geometry": {"coordinates":[145.05871582,-37.916519165],"type":"Point"}
}