{
  "type": "Feature",
  "properties": {
    "addr:full":"46-48 Tarandi St Loganholme QLD 4129",
    "addr:housenumber":"46-48",
    "addr:postcode":"4129",
    "addr:street":"Tarandi St",
    "iso:country":"AU",
    "sg:address":"46-48 Tarandi St",
    "sg:city":"Loganholme",
    "sg:classifiers":[
        {
            "category":"Organizations",
            "subcategory":"Professional Association",
            "type":"Services"
        }
    ],
    "sg:phone":"+61 7 3102 1813",
    "sg:postcode":"4129",
    "sg:province":"QLD",
    "sg:tags":[
        "web",
        "internet"
    ],
    "wof:name":"Ocki Industries",
    "wof:placetype":"venue"
},
  "geometry": {"coordinates":[153.182571411,-27.680305481],"type":"Point"}
}