{
  "type": "Feature",
  "properties": {
    "iso:country":"AU",
    "sg:address":"1 Lindeman Ave",
    "sg:city":"Cranbrook",
    "sg:classifiers":[
        {
            "category":"Social Services",
            "subcategory":"Retirement Home",
            "type":"Services"
        }
    ],
    "sg:phone":"+61 7 4725 0533",
    "sg:postcode":"4814",
    "sg:province":"QLD",
    "sg:tags":[
        "village"
    ],
    "wof:name":"Brooklea Lifestyle Village",
    "wof:placetype":"venue"
},
  "geometry": {"coordinates":[146.75753800000001,-19.298862],"type":"Point"}
}