{
  "type": "Feature",
  "properties": {
    "addr:full":"438 Victoria St Darlinghurst NSW 2010",
    "addr:housenumber":"438",
    "addr:postcode":"2010",
    "addr:street":"Victoria St",
    "iso:country":"AU",
    "sg:address":"438 Victoria St",
    "sg:city":"Darlinghurst",
    "sg:classifiers":[
        {
            "category":"Health Services",
            "subcategory":"Doctor",
            "type":"Services"
        }
    ],
    "sg:phone":"+61 2 9332 6822",
    "sg:postcode":"2010",
    "sg:province":"NSW",
    "sg:tags":[
        "medical",
        "practitioner"
    ],
    "wof:name":"Rimmer J Dr",
    "wof:placetype":"venue"
},
  "geometry": {"coordinates":[151.22113037099999,-33.8795280457],"type":"Point"}
}