{
  "type": "Feature",
  "properties": {
    "addr:full":"298 Wyndham St Shepparton VIC 3630",
    "addr:housenumber":"298",
    "addr:postcode":"3630",
    "addr:street":"Wyndham St",
    "iso:country":"AU",
    "sg:address":"298 Wyndham St",
    "sg:city":"Shepparton",
    "sg:classifiers":[
        {
            "category":"Shopping",
            "subcategory":"Party Supplies",
            "type":"Retail Goods"
        }
    ],
    "sg:phone":"+61 3 5821 9046",
    "sg:postcode":"3630",
    "sg:province":"VIC",
    "wof:name":"The Confectionery & Party Shop",
    "wof:placetype":"venue"
},
  "geometry": {"coordinates":[145.39944457999999,-36.3797073364],"type":"Point"}
}