{
  "type": "Feature",
  "properties": {
    "addr:full":"30 Bindera Rd Lambton NSW 2299",
    "addr:housenumber":"30",
    "addr:postcode":"2299",
    "addr:street":"Bindera Rd",
    "iso:country":"AU",
    "sg:address":"30 Bindera Rd",
    "sg:city":"Lambton",
    "sg:classifiers":[
        {
            "category":"Home & Garden",
            "subcategory":"Building Materials",
            "type":"Retail Goods"
        }
    ],
    "sg:phone":"+61 2 4957 1644",
    "sg:postcode":"2299",
    "sg:province":"NSW",
    "sg:tags":[
        "supply"
    ],
    "wof:name":"Mister Ply & Wood",
    "wof:placetype":"venue"
},
  "geometry": {"coordinates":[151.71893310600001,-32.9122924805],"type":"Point"}
}