{
  "type": "Feature",
  "properties": {
    "addr:full":"7 Oleander St Daisy Hill QLD 4127",
    "addr:housenumber":"7",
    "addr:postcode":"4127",
    "addr:street":"Oleander St",
    "iso:country":"AU",
    "sg:address":"7 Oleander St",
    "sg:city":"Daisy Hill",
    "sg:classifiers":[
        {
            "category":"Wholesale",
            "subcategory":"Apparel",
            "type":"Manufacturing & Wholesale Goods"
        }
    ],
    "sg:phone":"+61 7 3299 3184",
    "sg:postcode":"4127",
    "sg:province":"QLD",
    "sg:tags":[
        "wholesaler",
        "mfrs",
        "glove"
    ],
    "wof:name":"ASA Importing",
    "wof:placetype":"venue"
},
  "geometry": {"coordinates":[153.15525817899999,-27.6455917358],"type":"Point"}
}