{
  "type": "Feature",
  "properties": {
    "addr:full":"34 Sheffield Main Rd Spreyton TAS 7310",
    "addr:housenumber":"34",
    "addr:postcode":"7310",
    "addr:street":"Sheffield Main Rd",
    "iso:country":"AU",
    "sg:address":"34 Sheffield Main Rd",
    "sg:city":"Spreyton",
    "sg:classifiers":[
        {
            "category":"Food & Beverages",
            "subcategory":"Fruits & Vegetables",
            "type":"Retail Goods"
        }
    ],
    "sg:phone":"+61 3 6427 2065",
    "sg:postcode":"7310",
    "sg:province":"TAS",
    "sg:tags":[
        "wholesale"
    ],
    "wof:name":"Tasfresh",
    "wof:placetype":"venue"
},
  "geometry": {"coordinates":[146.346237183,-41.224357605],"type":"Point"}
}