{
  "type": "Feature",
  "properties": {
    "addr:full":"1 Upper Blue Mountains St Katoomba NSW 2780",
    "addr:housenumber":"1",
    "addr:postcode":"2780",
    "addr:street":"Upper Blue Mountains St",
    "iso:country":"AU",
    "sg:address":"1 Upper Blue Mountains St",
    "sg:city":"Katoomba",
    "sg:classifiers":[
        {
            "category":"Retail",
            "subcategory":"Veterinary Services",
            "type":"Services"
        }
    ],
    "sg:phone":"+61 434 844 378",
    "sg:postcode":"2780",
    "sg:province":"NSW",
    "sg:tags":[
        "surgeon"
    ],
    "wof:name":"Natural Animal Health Clinic",
    "wof:placetype":"venue"
},
  "geometry": {"coordinates":[150.31053161599999,-33.7118186951],"type":"Point"}
}