{
  "type": "Feature",
  "properties": {
    "addr:full":"62 Lawrence Drv Berwick VIC 3806",
    "addr:housenumber":"62",
    "addr:postcode":"3806",
    "addr:street":"Lawrence Drv",
    "iso:country":"AU",
    "sg:address":"62 Lawrence Drv",
    "sg:city":"Berwick",
    "sg:classifiers":[
        {
            "category":"Banks & Credit Unions",
            "subcategory":"Financial Services",
            "type":"Services"
        }
    ],
    "sg:phone":"+61 3 9796 1170",
    "sg:postcode":"3806",
    "sg:province":"VIC",
    "sg:tags":[
        "loan",
        "finance",
        "mortgage"
    ],
    "wof:name":"Choice Home Loans",
    "wof:placetype":"venue"
},
  "geometry": {"coordinates":[145.335571289,-38.0196647644],"type":"Point"}
}