{
  "type": "Feature",
  "properties": {
    "iso:country":"AU",
    "sg:address":"Cnr Nyrang & Mildura Sts",
    "sg:city":"Fyshwick",
    "sg:classifiers":[
        {
            "category":"Food & Beverages",
            "subcategory":"Liquor & Beverages",
            "type":"Retail Goods"
        }
    ],
    "sg:phone":"+61 2 6239 4290",
    "sg:postcode":"2609",
    "sg:province":"ACT",
    "sg:tags":[
        "merchant",
        "spirit",
        "wine"
    ],
    "wof:name":"Australian Liquor Marketers",
    "wof:placetype":"venue"
},
  "geometry": {"coordinates":[149.15553283700001,-35.3249206543],"type":"Point"}
}