{
  "type": "Feature",
  "properties": {
    "addr:full":"26 Simon St Rockhampton QLD 4702",
    "addr:housenumber":"26",
    "addr:postcode":"4702",
    "addr:street":"Simon St",
    "iso:country":"AU",
    "sg:address":"26 Simon St",
    "sg:city":"Rockhampton",
    "sg:classifiers":[
        {
            "category":"Building & Trades",
            "subcategory":"Construction",
            "type":"Services"
        }
    ],
    "sg:phone":"+61 407 138 189",
    "sg:postcode":"4702",
    "sg:province":"QLD",
    "sg:tags":[
        "contractor"
    ],
    "wof:name":"Barry Window",
    "wof:placetype":"venue"
},
  "geometry": {"coordinates":[150.43182373100001,-25.0342769623],"type":"Point"}
}