{
  "type": "Feature",
  "properties": {
    "iso:country":"AU",
    "sg:address":"351 Beardy St",
    "sg:city":"Armidale",
    "sg:classifiers":[
        {
            "category":"Professional",
            "subcategory":"Engineering",
            "type":"Services"
        }
    ],
    "sg:phone":"+61 2 6772 1699",
    "sg:postcode":"2350",
    "sg:province":"NSW",
    "sg:tags":[
        "diesel",
        "engineer"
    ],
    "wof:name":"John Fowler Automotive Engine Reconditioning Pty Ltd",
    "wof:placetype":"venue"
},
  "geometry": {"coordinates":[151.647613525,-30.508058548],"type":"Point"}
}