{
  "type": "Feature",
  "properties": {
    "addr:full":"17 Boa Vista Rd New Town TAS 7008",
    "addr:postcode":"7008",
    "addr:street":"Boa Vista Rd",
    "iso:country":"AU",
    "sg:address":"17 Boa Vista Rd",
    "sg:city":"New Town",
    "sg:classifiers":[
        {
            "category":"Social Services",
            "type":"Services"
        }
    ],
    "sg:phone":"+61 3 6278 3730",
    "sg:postcode":"7008",
    "sg:province":"TAS",
    "sg:tags":[
        "kinesiology"
    ],
    "wof:name":"Kinesiology Tasmania",
    "wof:placetype":"venue"
},
  "geometry": {"coordinates":[147.31515502900001,-42.8645324707],"type":"Point"}
}