{
  "type": "Feature",
  "properties": {
    "addr:full":"Shop 5, Burleigh Homespace Bermuda St Burleigh Waters QLD 4220",
    "addr:housenumber":"shop 5",
    "addr:postcode":"4220",
    "addr:street":"Burleigh Homespace Bermuda St",
    "iso:country":"AU",
    "sg:address":"Shop 5, Burleigh Homespace Bermuda St",
    "sg:city":"Burleigh Waters",
    "sg:classifiers":[
        {
            "category":"Professional",
            "subcategory":"Art Services",
            "type":"Services"
        }
    ],
    "sg:phone":"+61 7 5520 5755",
    "sg:postcode":"4220",
    "sg:province":"QLD",
    "sg:tags":[
        "interior",
        "designer"
    ],
    "wof:name":"TDR - The Design Road",
    "wof:placetype":"venue"
},
  "geometry": {"coordinates":[153.423553467,-28.0794391632],"type":"Point"}
}