{
  "type": "Feature",
  "properties": {
    "addr:full":"120 Kitchner St Trigg WA 6029",
    "addr:housenumber":"120",
    "addr:postcode":"6029",
    "addr:street":"Kitchner St",
    "iso:country":"AU",
    "sg:address":"120 Kitchner St",
    "sg:city":"Trigg",
    "sg:classifiers":[
        {
            "category":"Professional",
            "subcategory":"Management & Consulting",
            "type":"Services"
        }
    ],
    "sg:phone":"+61 8 9243 7075",
    "sg:postcode":"6029",
    "sg:province":"WA",
    "sg:tags":[
        "consultant",
        "migration"
    ],
    "wof:name":"International Consultants Centre",
    "wof:placetype":"venue"
},
  "geometry": {"coordinates":[115.757789612,-31.873298645],"type":"Point"}
}