{
  "type": "Feature",
  "properties": {
    "addr:full":"Cnr Sharp & Baron Sts Cooma NSW 2630",
    "addr:postcode":"2630",
    "addr:street":"Cnr Sharp & Baron Sts",
    "iso:country":"AU",
    "sg:address":"Cnr Sharp & Baron Sts",
    "sg:city":"Cooma",
    "sg:classifiers":[
        {
            "category":"Autos & Motor Vehicles",
            "subcategory":"Fuel & Gas Station",
            "type":"Retail Goods"
        }
    ],
    "sg:phone":"+61 2 6452 2468",
    "sg:postcode":"2630",
    "sg:province":"NSW",
    "wof:name":"Caltex Australia Petroleum Pty Ltd",
    "wof:placetype":"venue"
},
  "geometry": {"coordinates":[149.13099670400001,-36.2332458496],"type":"Point"}
}