{
  "type": "Feature",
  "properties": {
    "addr:full":"10 Paxton St Springwood QLD 4127",
    "addr:housenumber":"10",
    "addr:postcode":"4127",
    "addr:street":"Paxton St",
    "iso:country":"AU",
    "sg:address":"10 Paxton St",
    "sg:city":"Springwood",
    "sg:classifiers":[
        {
            "category":"Professional",
            "type":"Services"
        }
    ],
    "sg:phone":"+61 7 3208 2100",
    "sg:postcode":"4127",
    "sg:province":"QLD",
    "sg:tags":[
        "industrial",
        "commercial",
        "catering"
    ],
    "sg:website":"http://www.morriscorp.com.au",
    "wof:name":"Morris Corporation (Aust) Pty Ltd",
    "wof:placetype":"venue"
},
  "geometry": {"coordinates":[153.12710571299999,-27.6172332764],"type":"Point"}
}