{
  "type": "Feature",
  "properties": {
    "iso:country":"AU",
    "sg:address":"14 Fraser St",
    "sg:city":"Airport West",
    "sg:classifiers":[
        {
            "category":"Home & Garden",
            "subcategory":"Building Materials",
            "type":"Retail Goods"
        }
    ],
    "sg:phone":"+61 3 9330 3744",
    "sg:postcode":"3042",
    "sg:province":"VIC",
    "sg:tags":[
        "supply"
    ],
    "wof:name":"Airport Post Forming Pty Ltd",
    "wof:placetype":"venue"
},
  "geometry": {"coordinates":[144.88951110799999,-37.7243499756],"type":"Point"}
}