{
  "type": "Feature",
  "properties": {
    "iso:country":"AU",
    "sg:address":"18 Salmon St",
    "sg:city":"Port Melbourne",
    "sg:classifiers":[
        {
            "category":"Shopping",
            "subcategory":"News",
            "type":"Retail Goods"
        }
    ],
    "sg:phone":"+61 3 9245 7373",
    "sg:postcode":"3207",
    "sg:province":"VIC",
    "sg:tags":[
        "magazine",
        "periodical"
    ],
    "wof:name":"Engineering Edge",
    "wof:placetype":"venue"
},
  "geometry": {"coordinates":[144.924896,-37.834003],"type":"Point"}
}