{
  "type": "Feature",
  "properties": {
    "iso:country":"AU",
    "sg:address":"25a Holmes St",
    "sg:city":"Shelley",
    "sg:classifiers":[
        {
            "category":"Professional",
            "subcategory":"Management & Consulting",
            "type":"Services"
        }
    ],
    "sg:phone":"+61 8 9457 0333",
    "sg:postcode":"6148",
    "sg:province":"WA",
    "sg:tags":[
        "consultant",
        "business"
    ],
    "wof:name":"Projects Plus Consulting Services Pty Ltd",
    "wof:placetype":"venue"
},
  "geometry": {"coordinates":[115.884949,-32.029114],"type":"Point"}
}