{
  "type": "Feature",
  "properties": {
    "iso:country":"AU",
    "sg:address":"19 Tandem Ave",
    "sg:city":"Warana",
    "sg:classifiers":[
        {
            "category":"Sports & Exercise",
            "subcategory":"Sports Center",
            "type":"Entertainment"
        }
    ],
    "sg:phone":"+61 7 5493 7999",
    "sg:postcode":"4575",
    "sg:province":"QLD",
    "sg:tags":[
        "ground"
    ],
    "wof:name":"Action Arenas Kawana",
    "wof:placetype":"venue"
},
  "geometry": {"coordinates":[153.12579299999999,-26.728416],"type":"Point"}
}