{
  "type": "Feature",
  "properties": {
    "addr:full":"Shop 31, Bulleen Plaza, 79 - 101 Manningham Rd Bulleen VIC 3105",
    "addr:housenumber":"shop 31;79",
    "addr:postcode":"101;3105",
    "addr:street":"Bulleen Plaza;Manningham Rd",
    "iso:country":"AU",
    "sg:address":"Shop 31, Bulleen Plaza, 79 - 101 Manningham Rd",
    "sg:city":"Bulleen",
    "sg:classifiers":[
        {
            "category":"Manufacturing",
            "subcategory":"Food",
            "type":"Manufacturing & Wholesale Goods"
        }
    ],
    "sg:phone":"+61 3 9852 2066",
    "sg:postcode":"3105",
    "sg:province":"VIC",
    "sg:tags":[
        "product",
        "nut",
        "edible"
    ],
    "wof:name":"Bulleen Fresh Nuts Plaza",
    "wof:placetype":"venue"
},
  "geometry": {"coordinates":[145.09231567399999,-37.7665939331],"type":"Point"}
}