{
  "type": "Feature",
  "properties": {
    "iso:country":"AU",
    "sg:address":"86 Smith St",
    "sg:city":"Naracoorte",
    "sg:classifiers":[
        {
            "category":"Shopping",
            "subcategory":"Jewelry",
            "type":"Retail Goods"
        }
    ],
    "sg:phone":"+61 8 8762 2558",
    "sg:postcode":"5271",
    "sg:province":"SA",
    "sg:tags":[
        "jeweller"
    ],
    "wof:name":"Anthony Moate Jewellers",
    "wof:placetype":"venue"
},
  "geometry": {"coordinates":[140.74176,-36.95623],"type":"Point"}
}