{
  "type": "Feature",
  "properties": {
    "addr:full":"3 Sexton Drv Moresby WA 6530",
    "addr:housenumber":"3",
    "addr:postcode":"6530",
    "addr:street":"Sexton Drv",
    "iso:country":"AU",
    "sg:address":"3 Sexton Drv",
    "sg:city":"Moresby",
    "sg:classifiers":[
        {
            "category":"Utilities",
            "subcategory":"Water",
            "type":"Services"
        }
    ],
    "sg:phone":"+61 418 939 170",
    "sg:postcode":"6530",
    "sg:province":"WA",
    "sg:tags":[
        "hot",
        "system"
    ],
    "wof:name":"Hanson Plumbing & Gas",
    "wof:placetype":"venue"
},
  "geometry": {"coordinates":[114.66079711899999,-28.718296051],"type":"Point"}
}