{
  "type": "Feature",
  "properties": {
    "iso:country":"AU",
    "sg:address":"Level 1, 71 Albany St",
    "sg:city":"Coffs Harbour",
    "sg:classifiers":[
        {
            "category":"Professional",
            "subcategory":"Accounting & Tax Preparation",
            "type":"Services"
        }
    ],
    "sg:phone":"+61 2 6652 8522",
    "sg:postcode":"2450",
    "sg:province":"NSW",
    "sg:tags":[
        "accountant",
        "auditor"
    ],
    "wof:name":"Bartlett Accounting",
    "wof:placetype":"venue"
},
  "geometry": {"coordinates":[153.116287,-30.300774],"type":"Point"}
}