{
  "type": "Feature",
  "properties": {
    "addr:full":"13 Gateway Drv Labrador QLD 4215",
    "addr:housenumber":"13",
    "addr:postcode":"4215",
    "addr:street":"Gateway Drv",
    "iso:country":"AU",
    "sg:address":"13 Gateway Drv",
    "sg:city":"Labrador",
    "sg:classifiers":[
        {
            "category":"Home & Garden",
            "subcategory":"Carpets & Floor Coverings",
            "type":"Retail Goods"
        }
    ],
    "sg:phone":"+61 7 5500 5722",
    "sg:postcode":"4215",
    "sg:province":"QLD",
    "sg:tags":[
        "tile",
        "wall"
    ],
    "sg:website":"http://www.tileandstone.com.au",
    "wof:name":"Tile & Stone Gallery",
    "wof:placetype":"venue"
},
  "geometry": {"coordinates":[153.40838623100001,-27.945930481],"type":"Point"}
}