{
  "type": "Feature",
  "properties": {
    "addr:full":"Shp 20 14-26 Audsley St Clayton South VIC 3169",
    "addr:housenumber":"20",
    "addr:postcode":"14-26;3169",
    "addr:street":"Audsley St",
    "iso:country":"AU",
    "sg:address":"Shp 20 14-26 Audsley St",
    "sg:city":"Clayton South",
    "sg:classifiers":[
        {
            "category":"Shopping",
            "subcategory":"Computers & Home Electronics",
            "type":"Retail Goods"
        }
    ],
    "sg:phone":"+61 3 9562 9881",
    "sg:postcode":"3169",
    "sg:province":"VIC",
    "sg:tags":[
        "equipment",
        "supply"
    ],
    "wof:name":"I T Computer Supermarket",
    "wof:placetype":"venue"
},
  "geometry": {"coordinates":[145.12208557100001,-37.9316177368],"type":"Point"}
}