{
  "type": "Feature",
  "properties": {
    "addr:full":"193 Avoca Drv Green Point NSW 2251",
    "addr:housenumber":"193",
    "addr:postcode":"2251",
    "addr:street":"Avoca Drv",
    "iso:country":"AU",
    "sg:address":"193 Avoca Drv",
    "sg:city":"Green Point",
    "sg:classifiers":[
        {
            "category":"Real Estate",
            "subcategory":"Developer",
            "type":"Services"
        }
    ],
    "sg:phone":"+61 2 4369 7005",
    "sg:postcode":"2251",
    "sg:province":"NSW",
    "sg:tags":[
        "development"
    ],
    "wof:name":"Brian Peterson Real Estate",
    "wof:placetype":"venue"
},
  "geometry": {"coordinates":[151.361602783,-33.4510002136],"type":"Point"}
}