{
  "type": "Feature",
  "properties": {
    "addr:full":"20 Railway Pde Eastwood NSW 2122",
    "addr:housenumber":"20",
    "addr:postcode":"2122",
    "addr:street":"Railway Pde",
    "iso:country":"AU",
    "sg:address":"20 Railway Pde",
    "sg:city":"Eastwood",
    "sg:classifiers":[
        {
            "category":"Fast Food",
            "type":"Food & Drink"
        }
    ],
    "sg:phone":"+61 2 9874 8793",
    "sg:postcode":"2122",
    "sg:province":"NSW",
    "sg:tags":[
        "away",
        "take"
    ],
    "wof:name":"Jack's Gourmet Take Away",
    "wof:placetype":"venue"
},
  "geometry": {"coordinates":[151.082595825,-33.7902641296],"type":"Point"}
}