{
  "type": "Feature",
  "properties": {
    "addr:full":"297 Torrens Rd West Croydon SA 5008",
    "addr:housenumber":"297",
    "addr:postcode":"5008",
    "addr:street":"Torrens Rd",
    "iso:country":"AU",
    "sg:address":"297 Torrens Rd",
    "sg:city":"West Croydon",
    "sg:classifiers":[
        {
            "category":"Personal",
            "subcategory":"Beauty Salon",
            "type":"Services"
        }
    ],
    "sg:phone":"+61 8 8346 2075",
    "sg:postcode":"5008",
    "sg:province":"SA",
    "sg:tags":[
        "hairdresser"
    ],
    "wof:name":"Images Hairstudio",
    "wof:placetype":"venue"
},
  "geometry": {"coordinates":[138.56231700000001,-34.883755],"type":"Point"}
}