{
  "type": "Feature",
  "properties": {
    "addr:full":"597 Ebden St Albury NSW 2640",
    "addr:housenumber":"597",
    "addr:postcode":"2640",
    "addr:street":"Ebden St",
    "iso:country":"AU",
    "sg:address":"597 Ebden St",
    "sg:city":"Albury",
    "sg:classifiers":[
        {
            "category":"Real Estate",
            "subcategory":"Real Estate Agent",
            "type":"Services"
        }
    ],
    "sg:phone":"+61 2 6041 3777",
    "sg:postcode":"2640",
    "sg:province":"NSW",
    "wof:name":"Hutton Barry",
    "wof:placetype":"venue"
},
  "geometry": {"coordinates":[146.90916442899999,-36.0884666443],"type":"Point"}
}