{
  "type": "Feature",
  "properties": {
    "addr:full":"PO Box 195 Mt Lawley WA 6050",
    "addr:postcode":"6050",
    "iso:country":"AU",
    "sg:address":"PO Box 195",
    "sg:city":"Mt Lawley",
    "sg:classifiers":[
        {
            "category":"Building & Trades",
            "subcategory":"Construction",
            "type":"Services"
        }
    ],
    "sg:phone":"+61 418 930 454",
    "sg:postcode":"6050",
    "sg:province":"WA",
    "sg:tags":[
        "plasterboard",
        "plasterer",
        "fixer"
    ],
    "wof:name":"Innaloo Plasterers",
    "wof:placetype":"venue"
},
  "geometry": {"coordinates":[115.870262146,-31.9267730713],"type":"Point"}
}