{
  "type": "Feature",
  "properties": {
    "addr:full":"Unit 2D, Old Creamery La Berry NSW 2535",
    "addr:postcode":"2535",
    "addr:street":"La Berry",
    "iso:country":"AU",
    "sg:address":"Unit 2D, Old Creamery La",
    "sg:city":"Berry",
    "sg:classifiers":[
        {
            "category":"Building & Trades",
            "subcategory":"Construction",
            "type":"Services"
        }
    ],
    "sg:phone":"+61 2 4464 1695",
    "sg:postcode":"2535",
    "sg:province":"NSW",
    "sg:tags":[
        "contractor"
    ],
    "wof:name":"Foxrun Commercial Building Pty Ltd",
    "wof:placetype":"venue"
},
  "geometry": {"coordinates":[150.69612121599999,-34.7813873291],"type":"Point"}
}