{
  "type": "Feature",
  "properties": {
    "iso:country":"AU",
    "sg:address":"320 Ninderry Rd",
    "sg:city":"Yandina",
    "sg:classifiers":[
        {
            "category":"Building & Trades",
            "subcategory":"Construction",
            "type":"Services"
        }
    ],
    "sg:phone":"+61 427 659 781",
    "sg:postcode":"4561",
    "sg:province":"QLD",
    "sg:tags":[
        "earth",
        "excavating",
        "moving",
        "contractor"
    ],
    "wof:name":"Klumps Earthworx",
    "wof:placetype":"venue"
},
  "geometry": {"coordinates":[152.98658752399999,-26.5464134216],"type":"Point"}
}