{
  "type": "Feature",
  "properties": {
    "addr:full":"11 Gateway Drv Labrador QLD 4215",
    "addr:housenumber":"11",
    "addr:postcode":"4215",
    "addr:street":"Gateway Drv",
    "iso:country":"AU",
    "sg:address":"11 Gateway Drv",
    "sg:city":"Labrador",
    "sg:classifiers":[
        {
            "category":"Retail",
            "subcategory":"Auto Repair",
            "type":"Services"
        }
    ],
    "sg:phone":"+61 7 5583 9239",
    "sg:postcode":"4215",
    "sg:province":"QLD",
    "sg:tags":[
        "repairer",
        "motor",
        "engineer"
    ],
    "wof:name":"Grand Motors Toyota",
    "wof:placetype":"venue"
},
  "geometry": {"coordinates":[153.40838623100001,-27.945930481],"type":"Point"}
}