{
  "type": "Feature",
  "properties": {
    "addr:full":"Suite 5/ 186 Main Rd Blackwood SA 5051",
    "addr:housenumber":"/ 186",
    "addr:postcode":"5051",
    "addr:street":"Main Rd",
    "iso:country":"AU",
    "sg:address":"Suite 5/ 186 Main Rd",
    "sg:city":"Blackwood",
    "sg:classifiers":[
        {
            "category":"Professional",
            "subcategory":"Business Services",
            "type":"Services"
        }
    ],
    "sg:phone":"+61 8 8278 6086",
    "sg:postcode":"5051",
    "sg:province":"SA",
    "sg:tags":[
        "drafting"
    ],
    "wof:name":"Simmons Richard",
    "wof:placetype":"venue"
},
  "geometry": {"coordinates":[138.61726400000001,-35.015297],"type":"Point"}
}