{
  "type": "Feature",
  "properties": {
    "iso:country":"AU",
    "sg:address":"5 Benson Drv",
    "sg:city":"Coldstream",
    "sg:classifiers":[
        {
            "category":"Manufacturing",
            "subcategory":"Tools & Machinery",
            "type":"Manufacturing & Wholesale Goods"
        }
    ],
    "sg:phone":"+61 418 375 641",
    "sg:postcode":"3770",
    "sg:province":"VIC",
    "sg:tags":[
        "earth",
        "excavating",
        "moving",
        "equipment"
    ],
    "wof:name":"Buddha Bobcat",
    "wof:placetype":"venue"
},
  "geometry": {"coordinates":[145.353928,-37.698711],"type":"Point"}
}