{
  "type": "Feature",
  "properties": {
    "addr:full":"Duldig Rd Murray Bridge SA 5253",
    "addr:postcode":"5253",
    "addr:street":"Duldig Rd",
    "iso:country":"AU",
    "sg:address":"Duldig Rd",
    "sg:city":"Murray Bridge",
    "sg:classifiers":[
        {
            "category":"Social Services",
            "subcategory":"Retirement Home",
            "type":"Services"
        }
    ],
    "sg:phone":"+61 8 8291 8001",
    "sg:postcode":"5253",
    "sg:province":"SA",
    "sg:tags":[
        "village"
    ],
    "wof:name":"Murray Heights Retirement Village",
    "wof:placetype":"venue"
},
  "geometry": {"coordinates":[139.23646545400001,-35.1343002319],"type":"Point"}
}