{
  "type": "Feature",
  "properties": {
    "addr:full":"PO Box 1139 Cleveland QLD 4163",
    "addr:postcode":"4163",
    "iso:country":"AU",
    "sg:address":"PO Box 1139",
    "sg:city":"Cleveland",
    "sg:classifiers":[
        {
            "category":"Professional",
            "type":"Services"
        }
    ],
    "sg:phone":"+61 7 3821 0126",
    "sg:postcode":"4163",
    "sg:province":"QLD",
    "sg:tags":[
        "transport"
    ],
    "wof:name":"J.A.H. Freightmaster",
    "wof:placetype":"venue"
},
  "geometry": {"coordinates":[153.26710510300001,-27.5265293121],"type":"Point"}
}