{
  "type": "Feature",
  "properties": {
    "addr:full":"79- 81 Wedgewood Rd Hallam VIC 3803",
    "addr:housenumber":"81",
    "addr:postcode":"3803",
    "addr:street":"Wedgewood Rd",
    "iso:country":"AU",
    "sg:address":"79- 81 Wedgewood Rd",
    "sg:city":"Hallam",
    "sg:classifiers":[
        {
            "category":"Manufacturing",
            "subcategory":"Building Materials",
            "type":"Manufacturing & Wholesale Goods"
        }
    ],
    "sg:phone":"+61 3 8795 0900",
    "sg:postcode":"3803",
    "sg:province":"VIC",
    "sg:tags":[
        "stone",
        "product",
        "supply"
    ],
    "wof:name":"Smartstone",
    "wof:placetype":"venue"
},
  "geometry": {"coordinates":[145.257324219,-38.0053672791],"type":"Point"}
}