{
  "type": "Feature",
  "properties": {
    "addr:full":"63 Humber Rd Croydon North VIC 3136",
    "addr:housenumber":"63",
    "addr:postcode":"3136",
    "addr:street":"Humber Rd",
    "iso:country":"AU",
    "sg:address":"63 Humber Rd",
    "sg:city":"Croydon North",
    "sg:classifiers":[
        {
            "category":"Health Services",
            "subcategory":"Health Practitioner",
            "type":"Services"
        }
    ],
    "sg:phone":"+61 3 9727 4855",
    "sg:postcode":"3136",
    "sg:province":"VIC",
    "sg:tags":[
        "consultant",
        "conservation",
        "hearing"
    ],
    "wof:name":"Shelburg Acoustics Pty Ltd",
    "wof:placetype":"venue"
},
  "geometry": {"coordinates":[145.29788207999999,-37.7688598633],"type":"Point"}
}