{
  "type": "Feature",
  "properties": {
    "addr:full":"QIDC Building Suite 2 106 Egerton St Emerald QLD 4720",
    "addr:housenumber":"106",
    "addr:postcode":"4720",
    "addr:street":"Egerton St",
    "iso:country":"AU",
    "sg:address":"QIDC Building Suite 2 106 Egerton St",
    "sg:city":"Emerald",
    "sg:classifiers":[
        {
            "category":"Organizations",
            "subcategory":"Non-profit Organization",
            "type":"Services"
        }
    ],
    "sg:phone":"+61 7 4987 4676",
    "sg:postcode":"4720",
    "sg:province":"QLD",
    "sg:tags":[
        "support",
        "disability",
        "organisation"
    ],
    "wof:name":"Emerald Community Participation Service",
    "wof:placetype":"venue"
},
  "geometry": {"coordinates":[148.15849299999999,-23.524189],"type":"Point"}
}