{
  "type": "Feature",
  "properties": {
    "iso:country":"AU",
    "sg:address":"2 State St",
    "sg:city":"Oakleigh",
    "sg:classifiers":[
        {
            "category":"Building & Trades",
            "subcategory":"Construction",
            "type":"Services"
        }
    ],
    "sg:phone":"+61 3 9562 6688",
    "sg:postcode":"3166",
    "sg:province":"VIC",
    "sg:tags":[
        "contractor"
    ],
    "wof:name":"Michael Vincent Housing Kitchens",
    "wof:placetype":"venue"
},
  "geometry": {"coordinates":[145.10581970199999,-37.9002151489],"type":"Point"}
}