{
  "type": "Feature",
  "properties": {
    "addr:full":"44 Nicholson St Bairnsdale VIC 3875",
    "addr:housenumber":"44",
    "addr:postcode":"3875",
    "addr:street":"Nicholson St",
    "iso:country":"AU",
    "sg:address":"44 Nicholson St",
    "sg:city":"Bairnsdale",
    "sg:classifiers":[
        {
            "category":"Shopping",
            "subcategory":"Clothing, Apparel, & Fashions",
            "type":"Retail Goods"
        }
    ],
    "sg:phone":"+61 3 5152 3171",
    "sg:postcode":"3875",
    "sg:province":"VIC",
    "sg:tags":[
        "lingerie",
        "hosiery",
        "sleepwear"
    ],
    "wof:name":"Aileen Doddrell",
    "wof:placetype":"venue"
},
  "geometry": {"coordinates":[147.629760742,-37.8248023987],"type":"Point"}
}