{
  "type": "Feature",
  "properties": {
    "iso:country":"AU",
    "sg:address":"13 Broderick St",
    "sg:city":"Camperdown",
    "sg:classifiers":[
        {
            "category":"Banks & Credit Unions",
            "subcategory":"Financial Services",
            "type":"Services"
        }
    ],
    "sg:phone":"+61 2 9557 7488",
    "sg:postcode":"2050",
    "sg:province":"NSW",
    "sg:tags":[
        "wholesaler",
        "pencil",
        "pen",
        "mfrs"
    ],
    "wof:name":"Concept Partners",
    "wof:placetype":"venue"
},
  "geometry": {"coordinates":[151.178543,-33.887039],"type":"Point"}
}