{
  "type": "Feature",
  "properties": {
    "addr:full":"367 Settlement Rd Thomastown VIC 3074",
    "addr:housenumber":"367",
    "addr:postcode":"3074",
    "addr:street":"Settlement Rd",
    "iso:country":"AU",
    "sg:address":"367 Settlement Rd",
    "sg:city":"Thomastown",
    "sg:classifiers":[
        {
            "category":"Government",
            "subcategory":"Fire Station",
            "type":"Public Place"
        }
    ],
    "sg:phone":"+61 3 9466 3971",
    "sg:postcode":"3074",
    "sg:province":"VIC",
    "sg:tags":[
        "spring",
        "shock",
        "absorbers",
        "suspension"
    ],
    "wof:name":"Settlement Rd Exhaust Centre",
    "wof:placetype":"venue"
},
  "geometry": {"coordinates":[145.01742553700001,-37.6884613037],"type":"Point"}
}