{
  "type": "Feature",
  "properties": {
    "addr:full":"24 Albion St Warwick QLD 4370",
    "addr:housenumber":"24",
    "addr:postcode":"4370",
    "addr:street":"Albion St",
    "iso:country":"AU",
    "sg:address":"24 Albion St",
    "sg:city":"Warwick",
    "sg:classifiers":[
        {
            "category":"Autos & Motor Vehicles",
            "subcategory":"Auto Supplies",
            "type":"Retail Goods"
        }
    ],
    "sg:phone":"+61 7 4661 1965",
    "sg:postcode":"4370",
    "sg:province":"QLD",
    "sg:tags":[
        "battery",
        "automotive"
    ],
    "wof:name":"Beaurepaires",
    "wof:placetype":"venue"
},
  "geometry": {"coordinates":[152.03587341299999,-28.2121906281],"type":"Point"}
}