{
  "type": "Feature",
  "properties": {
    "addr:full":"1 Firebrace St Horsham VIC 3400",
    "addr:housenumber":"1",
    "addr:postcode":"3400",
    "addr:street":"Firebrace St",
    "iso:country":"AU",
    "sg:address":"1 Firebrace St",
    "sg:city":"Horsham",
    "sg:classifiers":[
        {
            "category":"Building & Trades",
            "subcategory":"Construction",
            "type":"Services"
        }
    ],
    "sg:phone":"+61 3 5381 2490",
    "sg:postcode":"3400",
    "sg:province":"VIC",
    "sg:tags":[
        "window",
        "aluminium"
    ],
    "wof:name":"Dougs Windows & Doors",
    "wof:placetype":"venue"
},
  "geometry": {"coordinates":[142.19985961899999,-36.7118835449],"type":"Point"}
}