{
  "type": "Feature",
  "properties": {
    "iso:country":"AU",
    "sg:address":"Level 13, 215 Adelaide St",
    "sg:city":"Brisbane",
    "sg:classifiers":[
        {
            "category":"Professional",
            "subcategory":"Accounting & Tax Preparation",
            "type":"Services"
        }
    ],
    "sg:phone":"+61 7 3239 4000",
    "sg:postcode":"4000",
    "sg:province":"QLD",
    "sg:tags":[
        "deduction",
        "payroll"
    ],
    "wof:name":"United Group Services Pty Ltd",
    "wof:placetype":"venue"
},
  "geometry": {"coordinates":[153.02769470199999,-27.4665298462],"type":"Point"}
}