{
  "type": "Feature",
  "properties": {
    "iso:country":"AU",
    "sg:address":"173 Cobalt St",
    "sg:city":"Broken Hill",
    "sg:classifiers":[
        {
            "category":"Shopping",
            "subcategory":"Books",
            "type":"Retail Goods"
        }
    ],
    "sg:phone":"+61 8 8087 2200",
    "sg:postcode":"2880",
    "sg:province":"NSW",
    "sg:tags":[
        "wholesaler",
        "canvas",
        "mfrs"
    ],
    "wof:name":"Longhorn Bags &#039;N&#039; Swags",
    "wof:placetype":"venue"
},
  "geometry": {"coordinates":[141.460327148,-31.9575862885],"type":"Point"}
}