{
  "type": "Feature",
  "properties": {
    "addr:full":"Cardiff Crt Cavan SA 5094",
    "addr:postcode":"5094",
    "addr:street":"Cardiff Crt",
    "iso:country":"AU",
    "sg:address":"Cardiff Crt",
    "sg:city":"Cavan",
    "sg:classifiers":[
        {
            "category":"Farming",
            "subcategory":"Nursery",
            "type":"Manufacturing & Wholesale Goods"
        }
    ],
    "sg:phone":"+61 8 8262 7001",
    "sg:postcode":"5094",
    "sg:province":"SA",
    "wof:name":"Palms Of Cavan The",
    "wof:placetype":"venue"
},
  "geometry": {"coordinates":[138.603225708,-34.8264198303],"type":"Point"}
}