{
  "type": "Feature",
  "properties": {
    "addr:full":"75 Guthrie St Osborne Park WA 6017",
    "addr:housenumber":"75",
    "addr:postcode":"6017",
    "addr:street":"Guthrie St",
    "iso:country":"AU",
    "sg:address":"75 Guthrie St",
    "sg:city":"Osborne Park",
    "sg:classifiers":[
        {
            "category":"Shopping",
            "subcategory":"Clothing, Apparel, & Fashions",
            "type":"Retail Goods"
        }
    ],
    "sg:phone":"+61 8 9244 4985",
    "sg:postcode":"6017",
    "sg:province":"WA",
    "sg:tags":[
        "uniform"
    ],
    "wof:name":"Best On Ground",
    "wof:placetype":"venue"
},
  "geometry": {"coordinates":[115.815933227,-31.9059486389],"type":"Point"}
}