{
  "type": "Feature",
  "properties": {
    "addr:full":"88 Palmgrove Rd Avalon NSW 2107",
    "addr:housenumber":"88",
    "addr:postcode":"2107",
    "addr:street":"Palmgrove Rd",
    "iso:country":"AU",
    "sg:address":"88 Palmgrove Rd",
    "sg:city":"Avalon",
    "sg:classifiers":[
        {
            "category":"Professional",
            "subcategory":"Art Services",
            "type":"Services"
        }
    ],
    "sg:phone":"+61 2 9918 0057",
    "sg:postcode":"2107",
    "sg:province":"NSW",
    "sg:tags":[
        "decorator",
        "painter"
    ],
    "wof:name":"Sadrinna Kurt",
    "wof:placetype":"venue"
},
  "geometry": {"coordinates":[151.32052612300001,-33.6377754211],"type":"Point"}
}