{
  "type": "Feature",
  "properties": {
    "addr:full":"49 Audley St Petersham NSW 2049",
    "addr:housenumber":"49",
    "addr:postcode":"2049",
    "addr:street":"Audley St",
    "iso:country":"AU",
    "sg:address":"49 Audley St",
    "sg:city":"Petersham",
    "sg:classifiers":[
        {
            "category":"Utilities",
            "subcategory":"Electric",
            "type":"Services"
        }
    ],
    "sg:phone":"+61 2 9569 9007",
    "sg:postcode":"2049",
    "sg:province":"NSW",
    "sg:tags":[
        "electrical",
        "contractor"
    ],
    "wof:name":"A Kwikfix Electrical Service",
    "wof:placetype":"venue"
},
  "geometry": {"coordinates":[151.15467799999999,-33.897381],"type":"Point"}
}