{
  "type": "Feature",
  "properties": {
    "iso:country":"AU",
    "sg:address":"Lot 23 Dendle St",
    "sg:city":"Grovedale",
    "sg:classifiers":[
        {
            "category":"Wholesale",
            "subcategory":"Electrical",
            "type":"Manufacturing & Wholesale Goods"
        }
    ],
    "sg:phone":"+61 3 5241 1414",
    "sg:postcode":"3216",
    "sg:province":"VIC",
    "sg:tags":[
        "wholesaler"
    ],
    "wof:name":"AWM Electrical",
    "wof:placetype":"venue"
},
  "geometry": {"coordinates":[144.34596252399999,-38.1942253113],"type":"Point"}
}