{
  "type": "Feature",
  "properties": {
    "iso:country":"AU",
    "sg:address":"40 Ebor Ave",
    "sg:city":"Mile End",
    "sg:classifiers":[
        {
            "category":"Health Services",
            "subcategory":"Health Practitioner",
            "type":"Services"
        }
    ],
    "sg:phone":"+61 8 8443 9162",
    "sg:postcode":"5031",
    "sg:province":"SA",
    "sg:tags":[
        "alternative"
    ],
    "wof:name":"Julie Way Seminars",
    "wof:placetype":"venue"
},
  "geometry": {"coordinates":[138.56387329099999,-34.9282302856],"type":"Point"}
}