{
  "type": "Feature",
  "properties": {
    "addr:full":"38 Seaford Rd Seaford VIC 3198",
    "addr:housenumber":"38",
    "addr:postcode":"3198",
    "addr:street":"Seaford Rd",
    "iso:country":"AU",
    "sg:address":"38 Seaford Rd",
    "sg:city":"Seaford",
    "sg:classifiers":[
        {
            "category":"Building & Trades",
            "subcategory":"Plumbing",
            "type":"Services"
        }
    ],
    "sg:phone":"+61 3 9786 3096",
    "sg:postcode":"3198",
    "sg:province":"VIC",
    "sg:tags":[
        "plumber",
        "gasfitters"
    ],
    "wof:name":"Peninsula Plumbing Service",
    "wof:placetype":"venue"
},
  "geometry": {"coordinates":[145.132446289,-38.110824585],"type":"Point"}
}