{
  "type": "Feature",
  "properties": {
    "iso:country":"AU",
    "sg:address":"6 Runic La",
    "sg:city":"Maroubra",
    "sg:classifiers":[
        {
            "category":"Education",
            "subcategory":"School",
            "type":"Public Place"
        }
    ],
    "sg:phone":"+61 2 9349 4877",
    "sg:postcode":"2035",
    "sg:province":"NSW",
    "wof:name":"Mount Sinai College",
    "wof:placetype":"venue"
},
  "geometry": {"coordinates":[151.23646545400001,-33.9353065491],"type":"Point"}
}