{
  "type": "Feature",
  "properties": {
    "addr:full":"67 Perry St Bundaberg North QLD 4670",
    "addr:housenumber":"67",
    "addr:postcode":"4670",
    "addr:street":"Perry St",
    "iso:country":"AU",
    "sg:address":"67 Perry St",
    "sg:city":"Bundaberg North",
    "sg:classifiers":[
        {
            "category":"Retail",
            "subcategory":"Storage",
            "type":"Services"
        }
    ],
    "sg:phone":"+61 7 4152 3655",
    "sg:postcode":"4670",
    "sg:province":"QLD",
    "sg:tags":[
        "equipment",
        "computer",
        "secondhand"
    ],
    "wof:name":"Aztec One Computers",
    "wof:placetype":"venue"
},
  "geometry": {"coordinates":[152.34359741200001,-24.8598957062],"type":"Point"}
}