{
  "type": "Feature",
  "properties": {
    "addr:full":"8 Glendale St Nunawading VIC 3131",
    "addr:housenumber":"8",
    "addr:postcode":"3131",
    "addr:street":"Glendale St",
    "iso:country":"AU",
    "sg:address":"8 Glendale St",
    "sg:city":"Nunawading",
    "sg:classifiers":[
        {
            "category":"Shopping",
            "subcategory":"Party Supplies",
            "type":"Retail Goods"
        }
    ],
    "sg:phone":"+61 3 9877 2722",
    "sg:postcode":"3131",
    "sg:province":"VIC",
    "sg:tags":[
        "selling",
        "plan"
    ],
    "wof:name":"New Horizon Sales",
    "wof:placetype":"venue"
},
  "geometry": {"coordinates":[145.17361450199999,-37.8193817139],"type":"Point"}
}