{
  "type": "Feature",
  "properties": {
    "addr:full":"32 Longueville Rd Lane Cove NSW 2066",
    "addr:housenumber":"32",
    "addr:postcode":"2066",
    "addr:street":"Longueville Rd",
    "iso:country":"AU",
    "sg:address":"32 Longueville Rd",
    "sg:city":"Lane Cove",
    "sg:classifiers":[
        {
            "category":"Retail",
            "subcategory":"Car Wash",
            "type":"Services"
        }
    ],
    "sg:phone":"+61 2 9428 3366",
    "sg:postcode":"2066",
    "sg:province":"NSW",
    "sg:tags":[
        "truck",
        "cleaning"
    ],
    "wof:name":"Ducky's Car Wash & Cafe",
    "wof:placetype":"venue"
},
  "geometry": {"coordinates":[151.17030334500001,-33.8136520386],"type":"Point"}
}