{
  "type": "Feature",
  "properties": {
    "iso:country":"AU",
    "sg:address":"457 Cavendish Rd",
    "sg:city":"Coorparoo",
    "sg:classifiers":[
        {
            "category":"Food & Beverages",
            "subcategory":"Liquor & Beverages",
            "type":"Retail Goods"
        }
    ],
    "sg:phone":"+61 7 3847 6217",
    "sg:postcode":"4151",
    "sg:province":"QLD",
    "sg:tags":[
        "store"
    ],
    "wof:name":"Vintage Cellars",
    "wof:placetype":"venue"
},
  "geometry": {"coordinates":[153.06387329099999,-27.510602951],"type":"Point"}
}