{
  "type": "Feature",
  "properties": {
    "iso:country":"AU",
    "sg:address":"78 McLennan St",
    "sg:city":"Albion",
    "sg:classifiers":[
        {
            "category":"Building & Trades",
            "subcategory":"Cleaning & Sanitation",
            "type":"Services"
        }
    ],
    "sg:phone":"+61 7 3357 7866",
    "sg:postcode":"4010",
    "sg:province":"QLD",
    "sg:tags":[
        "industrial",
        "commercial",
        "contractor"
    ],
    "wof:name":"Chian",
    "wof:placetype":"venue"
},
  "geometry": {"coordinates":[153.037567139,-27.4248943329],"type":"Point"}
}