{
  "type": "Feature",
  "properties": {
    "addr:full":"63 Korong Rd Heidelberg West VIC 3081",
    "addr:housenumber":"63",
    "addr:postcode":"3081",
    "addr:street":"Korong Rd",
    "iso:country":"AU",
    "sg:address":"63 Korong Rd",
    "sg:city":"Heidelberg West",
    "sg:classifiers":[
        {
            "category":"Wholesale",
            "subcategory":"Construction Materials",
            "type":"Manufacturing & Wholesale Goods"
        }
    ],
    "sg:phone":"+61 3 9455 2677",
    "sg:postcode":"3081",
    "sg:province":"VIC",
    "sg:tags":[
        "wholesaler",
        "equipment",
        "bathroom",
        "mfrs",
        "accessory"
    ],
    "wof:name":"Bacini Pty Ltd",
    "wof:placetype":"venue"
},
  "geometry": {"coordinates":[145.047073364,-37.731552124],"type":"Point"}
}