{
  "type": "Feature",
  "properties": {
    "iso:country":"AU",
    "sg:address":"9 Ruse St",
    "sg:city":"Parramatta",
    "sg:classifiers":[
        {
            "category":"Museum",
            "type":"Entertainment"
        }
    ],
    "sg:phone":"+61 2 9635 5655",
    "sg:postcode":"2150",
    "sg:province":"NSW",
    "wof:name":"Experiment Farm Cottage",
    "wof:placetype":"venue"
},
  "geometry": {"coordinates":[151.013214111,-33.8199272156],"type":"Point"}
}