{
  "type": "Feature",
  "properties": {
    "addr:full":"Shed 1 Uki St Yamba NSW 2464",
    "addr:housenumber":"1",
    "addr:postcode":"2464",
    "addr:street":"Uki St",
    "iso:country":"AU",
    "sg:address":"Shed 1 Uki St",
    "sg:city":"Yamba",
    "sg:classifiers":[
        {
            "category":"Retail",
            "subcategory":"Auto Repair",
            "type":"Services"
        }
    ],
    "sg:phone":"+61 2 6646 2374",
    "sg:postcode":"2464",
    "sg:province":"NSW",
    "sg:tags":[
        "muffler",
        "exhaust",
        "system"
    ],
    "wof:name":"Carline Mufflers",
    "wof:placetype":"venue"
},
  "geometry": {"coordinates":[153.34733581500001,-29.4391708374],"type":"Point"}
}