{
  "type": "Feature",
  "properties": {
    "iso:country":"AU",
    "sg:address":"Shop 123",
    "sg:city":"Charlestown Square Charlestown",
    "sg:classifiers":[
        {
            "category":"Banks & Credit Unions",
            "subcategory":"Bank",
            "type":"Services"
        }
    ],
    "sg:phone":"+61 2 4943 9822",
    "sg:postcode":"2290",
    "sg:province":"NSW",
    "wof:name":"St George Bank Ltd",
    "wof:placetype":"venue"
},
  "geometry": {"coordinates":[151.685714722,-32.9541244507],"type":"Point"}
}