{
  "type": "Feature",
  "properties": {
    "iso:country":"AU",
    "sg:address":"15 Bellevue St",
    "sg:city":"Arncliffe",
    "sg:classifiers":[
        {
            "category":"Building & Trades",
            "subcategory":"Construction",
            "type":"Services"
        }
    ],
    "sg:phone":"+61 2 9556 2775",
    "sg:postcode":"2205",
    "sg:province":"NSW",
    "sg:tags":[
        "concrete",
        "contractor"
    ],
    "wof:name":"Borkovich Concrete Services",
    "wof:placetype":"venue"
},
  "geometry": {"coordinates":[151.14953600000001,-33.941193],"type":"Point"}
}