{
  "type": "Feature",
  "properties": {
    "addr:full":"208 William St Northbridge WA 6003",
    "addr:housenumber":"208",
    "addr:postcode":"6003",
    "addr:street":"William St",
    "iso:country":"AU",
    "sg:address":"208 William St",
    "sg:city":"Northbridge",
    "sg:classifiers":[
        {
            "category":"Travel",
            "subcategory":"Travel Agent",
            "type":"Entertainment"
        }
    ],
    "sg:phone":"+61 8 9328 7719",
    "sg:postcode":"6003",
    "sg:province":"WA",
    "sg:tags":[
        "consultant"
    ],
    "wof:name":"Merizzi Travel Service WA",
    "wof:placetype":"venue"
},
  "geometry": {"coordinates":[115.859519959,-31.9490222931],"type":"Point"}
}