{
  "type": "Feature",
  "properties": {
    "iso:country":"AU",
    "sg:address":"Shp 343, Westfield Eastgardens, 152 Bunnerong Rd",
    "sg:city":"Eastgardens",
    "sg:classifiers":[
        {
            "category":"Food & Beverages",
            "subcategory":"Specialty",
            "type":"Retail Goods"
        }
    ],
    "sg:phone":"+61 2 8347 0444",
    "sg:postcode":"2036",
    "sg:province":"NSW",
    "sg:tags":[
        "product",
        "health"
    ],
    "wof:name":"Healthzone",
    "wof:placetype":"venue"
},
  "geometry": {"coordinates":[151.226486206,-33.9449501038],"type":"Point"}
}