{
  "type": "Feature",
  "properties": {
    "iso:country":"AU",
    "sg:address":"919 Mate St",
    "sg:city":"North Albury",
    "sg:classifiers":[
        {
            "category":"Fast Food",
            "type":"Food & Drink"
        }
    ],
    "sg:phone":"+61 2 6025 8674",
    "sg:postcode":"2640",
    "sg:province":"NSW",
    "sg:tags":[
        "away",
        "take"
    ],
    "wof:name":"North Albury Takeaway",
    "wof:placetype":"venue"
},
  "geometry": {"coordinates":[146.93243408199999,-36.0579185486],"type":"Point"}
}