{
  "type": "Feature",
  "properties": {
    "iso:country":"AU",
    "sg:address":"Cnr Tyson St & Pacific Hwy",
    "sg:city":"Grafton",
    "sg:classifiers":[
        {
            "category":"Manufacturing",
            "subcategory":"Tools & Machinery",
            "type":"Manufacturing & Wholesale Goods"
        }
    ],
    "sg:phone":"+61 2 6642 1888",
    "sg:postcode":"2460",
    "sg:province":"NSW",
    "sg:tags":[
        "earth",
        "excavating",
        "moving",
        "equipment"
    ],
    "wof:name":"Gough & Gilmour Holdings Pty Ltd",
    "wof:placetype":"venue"
},
  "geometry": {"coordinates":[152.93020629899999,-29.7162837982],"type":"Point"}
}