{
  "type": "Feature",
  "properties": {
    "addr:full":"Unit 1 / 3 Darkes Rd Dapto West NSW 2530",
    "addr:housenumber":"3",
    "addr:postcode":"2530",
    "addr:street":"Darkes Rd",
    "iso:country":"AU",
    "sg:address":"Unit 1 / 3 Darkes Rd",
    "sg:city":"Dapto West",
    "sg:classifiers":[
        {
            "category":"Manufacturing",
            "subcategory":"Metals",
            "type":"Manufacturing & Wholesale Goods"
        }
    ],
    "sg:phone":"+61 401 769 312",
    "sg:postcode":"2530",
    "sg:province":"NSW",
    "sg:tags":[
        "polisher"
    ],
    "wof:name":"Shine Metal Polishing",
    "wof:placetype":"venue"
},
  "geometry": {"coordinates":[150.76544189399999,-34.478515625],"type":"Point"}
}