{
  "type": "Feature",
  "properties": {
    "addr:full":"73 McEwin Ave Redwood Park SA 5097",
    "addr:housenumber":"73",
    "addr:postcode":"5097",
    "addr:street":"Mcewin Ave",
    "iso:country":"AU",
    "sg:address":"73 McEwin Ave",
    "sg:city":"Redwood Park",
    "sg:classifiers":[
        {
            "category":"Retail",
            "subcategory":"Auto Repair",
            "type":"Services"
        }
    ],
    "sg:phone":"+61 8 8265 5080",
    "sg:postcode":"5097",
    "sg:province":"SA",
    "sg:tags":[
        "body",
        "motor",
        "trimmer"
    ],
    "wof:name":"R & J Trimmers",
    "wof:placetype":"venue"
},
  "geometry": {"coordinates":[138.700271606,-34.8089027405],"type":"Point"}
}