{
  "type": "Feature",
  "properties": {
    "addr:full":"Shop 5, Noosa Wharf, 2 Quamby Place Noosa Heads QLD 4567",
    "addr:housenumber":"shop 5;2",
    "addr:postcode":"4567",
    "addr:street":"Noosa Wharf;Quamby Place",
    "iso:country":"AU",
    "sg:address":"Shop 5, Noosa Wharf, 2 Quamby Place",
    "sg:city":"Noosa Heads",
    "sg:classifiers":[
        {
            "category":"Health Services",
            "subcategory":"Doctor",
            "type":"Services"
        }
    ],
    "sg:phone":"+61 7 5474 8866",
    "sg:postcode":"4567",
    "sg:province":"QLD",
    "sg:tags":[
        "medical",
        "practitioner"
    ],
    "wof:name":"Cozmedics - The Australian Cosmetic Medical Group",
    "wof:placetype":"venue"
},
  "geometry": {"coordinates":[153.078887939,-26.3918266296],"type":"Point"}
}