{
  "type": "Feature",
  "properties": {
    "addr:full":"12 Noyana Ave Grays Point NSW 2232",
    "addr:housenumber":"12",
    "addr:postcode":"2232",
    "addr:street":"Noyana Ave",
    "iso:country":"AU",
    "sg:address":"12 Noyana Ave",
    "sg:city":"Grays Point",
    "sg:classifiers":[
        {
            "category":"Professional",
            "subcategory":"Art Services",
            "type":"Services"
        }
    ],
    "sg:phone":"+61 2 9531 1394",
    "sg:postcode":"2232",
    "sg:province":"NSW",
    "sg:tags":[
        "graphic",
        "designer"
    ],
    "wof:name":"Deej Design",
    "wof:placetype":"venue"
},
  "geometry": {"coordinates":[151.074050903,-34.0605201721],"type":"Point"}
}