{
  "type": "Feature",
  "properties": {
    "addr:full":"GPO Box 199 Brisbane QLD 4001",
    "addr:postcode":"4001",
    "iso:country":"AU",
    "sg:address":"GPO Box 199",
    "sg:city":"Brisbane",
    "sg:classifiers":[
        {
            "category":"Professional",
            "subcategory":"Management & Consulting",
            "type":"Services"
        }
    ],
    "sg:phone":"+61 7 3229 1744",
    "sg:postcode":"4001",
    "sg:province":"QLD",
    "sg:tags":[
        "consultant"
    ],
    "wof:name":"QRMC Risk Management Pty Ltd",
    "wof:placetype":"venue"
},
  "geometry": {"coordinates":[153.06265258799999,-27.4488792419],"type":"Point"}
}