{
  "type": "Feature",
  "properties": {
    "iso:country":"AU",
    "sg:address":"Suite 704, 491 Kent St",
    "sg:city":"Sydney",
    "sg:classifiers":[
        {
            "category":"Professional",
            "subcategory":"Employment Agencies",
            "type":"Services"
        }
    ],
    "sg:phone":"+61 2 9262 9677",
    "sg:postcode":"2000",
    "sg:province":"NSW",
    "wof:name":"Chase Recruitment",
    "wof:placetype":"venue"
},
  "geometry": {"coordinates":[151.20501709000001,-33.8734321594],"type":"Point"}
}