{
  "type": "Feature",
  "properties": {
    "iso:country":"AU",
    "sg:address":"378 Bay St",
    "sg:city":"Port Melbourne",
    "sg:classifiers":[
        {
            "category":"Professional",
            "subcategory":"Accounting & Tax Preparation",
            "type":"Services"
        }
    ],
    "sg:phone":"+61 3 9645 1327",
    "sg:postcode":"3207",
    "sg:province":"VIC",
    "sg:tags":[
        "accountant",
        "auditor"
    ],
    "wof:name":"Barassi & Co",
    "wof:placetype":"venue"
},
  "geometry": {"coordinates":[144.945221,-37.835636],"type":"Point"}
}