{
  "type": "Feature",
  "properties": {
    "iso:country":"AU",
    "sg:address":"109 Hensman St",
    "sg:city":"South Perth",
    "sg:classifiers":[
        {
            "category":"Professional",
            "subcategory":"Art Services",
            "type":"Services"
        }
    ],
    "sg:phone":"+61 8 9367 1368",
    "sg:postcode":"6151",
    "sg:province":"WA",
    "sg:tags":[
        "decorator",
        "painter"
    ],
    "wof:name":"Paintex",
    "wof:placetype":"venue"
},
  "geometry": {"coordinates":[115.864906,-31.985157],"type":"Point"}
}