{
  "type": "Feature",
  "properties": {
    "addr:full":"647 High St Thornbury VIC 3071",
    "addr:housenumber":"647",
    "addr:postcode":"3071",
    "addr:street":"High St",
    "iso:country":"AU",
    "sg:address":"647 High St",
    "sg:city":"Thornbury",
    "sg:classifiers":[
        {
            "category":"Shopping",
            "subcategory":"Pets & Pet Supplies",
            "type":"Retail Goods"
        }
    ],
    "sg:phone":"+61 3 9484 3805",
    "sg:postcode":"3071",
    "sg:province":"VIC",
    "sg:tags":[
        "food"
    ],
    "wof:name":"Salce E & A",
    "wof:placetype":"venue"
},
  "geometry": {"coordinates":[144.99996948200001,-37.7613334656],"type":"Point"}
}