{
  "type": "Feature",
  "properties": {
    "addr:full":"293 Manns Rd Gosford West NSW 2250",
    "addr:housenumber":"293",
    "addr:postcode":"2250",
    "addr:street":"Manns Rd",
    "iso:country":"AU",
    "sg:address":"293 Manns Rd",
    "sg:city":"Gosford West",
    "sg:classifiers":[
        {
            "category":"Home & Garden",
            "subcategory":"Carpets & Floor Coverings",
            "type":"Retail Goods"
        }
    ],
    "sg:phone":"+61 2 4324 5366",
    "sg:postcode":"2250",
    "sg:province":"NSW",
    "sg:tags":[
        "tile",
        "wall"
    ],
    "wof:name":"Amber Group Australia Ltd",
    "wof:placetype":"venue"
},
  "geometry": {"coordinates":[151.31939697300001,-33.4245376587],"type":"Point"}
}