{
  "type": "Feature",
  "properties": {
    "iso:country":"AU",
    "sg:address":"Unit 10 3 Hollylea Rd",
    "sg:city":"Campbelltown",
    "sg:classifiers":[
        {
            "category":"Professional",
            "subcategory":"Printing & Photocopies",
            "type":"Services"
        }
    ],
    "sg:phone":"+61 2 4620 7722",
    "sg:postcode":"2560",
    "sg:province":"NSW",
    "sg:tags":[
        "embroidery"
    ],
    "wof:name":"Print & Press",
    "wof:placetype":"venue"
},
  "geometry": {"coordinates":[150.81658935600001,-34.0640983582],"type":"Point"}
}