{
  "type": "Feature",
  "properties": {
    "addr:full":"Suite 21, Edgecliff Mews, 201 New South Head Rd Edgecliff NSW 2027",
    "addr:housenumber":"201",
    "addr:postcode":"2027",
    "addr:street":"Edgecliff Mews;New South Head Rd",
    "iso:country":"AU",
    "sg:address":"Suite 21, Edgecliff Mews, 201 New South Head Rd",
    "sg:city":"Edgecliff",
    "sg:classifiers":[
        {
            "category":"Health Services",
            "subcategory":"Doctor",
            "type":"Services"
        }
    ],
    "sg:phone":"+61 1300 721 111",
    "sg:postcode":"2027",
    "sg:province":"NSW",
    "sg:tags":[
        "nurse",
        "nursing"
    ],
    "wof:name":"Dial An Angel",
    "wof:placetype":"venue"
},
  "geometry": {"coordinates":[151.24177551299999,-33.8816261292],"type":"Point"}
}