{
  "type": "Feature",
  "properties": {
    "addr:full":"56 Dale St Port Adelaide SA 5015",
    "addr:housenumber":"56",
    "addr:postcode":"5015",
    "addr:street":"Dale St",
    "iso:country":"AU",
    "sg:address":"56 Dale St",
    "sg:city":"Port Adelaide",
    "sg:classifiers":[
        {
            "category":"Banks & Credit Unions",
            "subcategory":"Financial Services",
            "type":"Services"
        }
    ],
    "sg:phone":"+61 8 8447 2766",
    "sg:postcode":"5015",
    "sg:province":"SA",
    "sg:tags":[
        "loan",
        "finance",
        "mortgage"
    ],
    "wof:name":"Wizard",
    "wof:placetype":"venue"
},
  "geometry": {"coordinates":[138.50552368199999,-34.8463935852],"type":"Point"}
}