{
  "type": "Feature",
  "properties": {
    "addr:full":"Santos Stadium 145 Railway Tce Mile End SA 5031",
    "addr:housenumber":"145",
    "addr:postcode":"5031",
    "addr:street":"Railway Tce",
    "iso:country":"AU",
    "sg:address":"Santos Stadium 145 Railway Tce",
    "sg:city":"Mile End",
    "sg:classifiers":[
        {
            "category":"Sports & Exercise",
            "subcategory":"Sports Center",
            "type":"Entertainment"
        }
    ],
    "sg:phone":"+61 8 8152 0355",
    "sg:postcode":"5031",
    "sg:province":"SA",
    "sg:tags":[
        "ground"
    ],
    "wof:name":"Santos Stadium",
    "wof:placetype":"venue"
},
  "geometry": {"coordinates":[138.578033447,-34.9262466431],"type":"Point"}
}