{
  "type": "Feature",
  "properties": {
    "addr:full":"1st Floor, 394 Victoria St Richmond VIC 3121",
    "addr:housenumber":"394",
    "addr:postcode":"3121",
    "addr:street":"Victoria St",
    "iso:country":"AU",
    "sg:address":"1st Floor, 394 Victoria St",
    "sg:city":"Richmond",
    "sg:classifiers":[
        {
            "category":"Manufacturing",
            "subcategory":"Textiles",
            "type":"Manufacturing & Wholesale Goods"
        }
    ],
    "sg:phone":"+61 3 9428 9200",
    "sg:postcode":"3121",
    "sg:province":"VIC",
    "sg:tags":[
        "agent"
    ],
    "wof:name":"Gration Steve Textiles Pty Ltd",
    "wof:placetype":"venue"
},
  "geometry": {"coordinates":[145.00453185999999,-37.8110694885],"type":"Point"}
}