{
  "type": "Feature",
  "properties": {
    "addr:full":"PO Box 254 Kilmore VIC 3764",
    "addr:postcode":"3764",
    "iso:country":"AU",
    "sg:address":"PO Box 254",
    "sg:city":"Kilmore",
    "sg:classifiers":[
        {
            "category":"Banks & Credit Unions",
            "subcategory":"Bureau De Change",
            "type":"Services"
        }
    ],
    "sg:phone":"+61 407 371 332",
    "sg:postcode":"3764",
    "sg:province":"VIC",
    "sg:tags":[
        "repairs",
        "part",
        "appliance",
        "electrical"
    ],
    "wof:name":"Kilmore Appliance Service",
    "wof:placetype":"venue"
},
  "geometry": {"coordinates":[144.94863891599999,-37.3020515442],"type":"Point"}
}