{
  "type": "Feature",
  "properties": {
    "addr:full":"PO Box 2030 High Wycombe WA 6057",
    "addr:postcode":"6057",
    "iso:country":"AU",
    "sg:address":"PO Box 2030",
    "sg:city":"High Wycombe",
    "sg:classifiers":[
        {
            "category":"Social Services",
            "subcategory":"Retirement Home",
            "type":"Services"
        }
    ],
    "sg:phone":"+61 8 9454 6121",
    "sg:postcode":"6057",
    "sg:province":"WA",
    "sg:tags":[
        "environmental",
        "consultant",
        "pollution"
    ],
    "wof:name":"Bacti-Clear Septic Treatments",
    "wof:placetype":"venue"
},
  "geometry": {"coordinates":[116.008079529,-31.9469680786],"type":"Point"}
}