{
  "type": "Feature",
  "properties": {
    "iso:country":"AU",
    "sg:address":"347 Moray St",
    "sg:city":"South Melbourne",
    "sg:classifiers":[
        {
            "category":"Real Estate",
            "subcategory":"Real Estate Agent",
            "type":"Services"
        }
    ],
    "sg:phone":"+61 3 9699 8899",
    "sg:postcode":"3205",
    "sg:province":"VIC",
    "wof:name":"GCK Real Estate",
    "wof:placetype":"venue"
},
  "geometry": {"coordinates":[144.965439,-37.837059],"type":"Point"}
}