{
  "type": "Feature",
  "properties": {
    "addr:full":"7 Bridges St Maroubra NSW 2035",
    "addr:housenumber":"7",
    "addr:postcode":"2035",
    "addr:street":"Bridges St",
    "iso:country":"AU",
    "sg:address":"7 Bridges St",
    "sg:city":"Maroubra",
    "sg:classifiers":[
        {
            "category":"Government",
            "subcategory":"Court House",
            "type":"Public Place"
        }
    ],
    "sg:phone":"+61 2 9314 1580",
    "sg:postcode":"2035",
    "sg:province":"NSW",
    "sg:tags":[
        "personal",
        "marriage",
        "family",
        "counselling"
    ],
    "wof:name":"Centre For Practical Parenting The",
    "wof:placetype":"venue"
},
  "geometry": {"coordinates":[151.252319336,-33.949005127],"type":"Point"}
}