{
  "type": "Feature",
  "properties": {
    "iso:country":"AU",
    "sg:address":"10th Floor 114 Albert Rd",
    "sg:city":"South Melbourne",
    "sg:classifiers":[
        {
            "category":"Structure",
            "subcategory":"Office Building",
            "type":"Public Place"
        }
    ],
    "sg:phone":"+61 3 9693 6400",
    "sg:postcode":"3205",
    "sg:province":"VIC",
    "sg:tags":[
        "serviced"
    ],
    "wof:name":"Phonoffice Services",
    "wof:placetype":"venue"
},
  "geometry": {"coordinates":[144.96992499999999,-37.835842],"type":"Point"}
}