{
  "type": "Feature",
  "properties": {
    "iso:country":"AU",
    "sg:address":"7 Chandos St",
    "sg:city":"Cheltenham",
    "sg:classifiers":[
        {
            "category":"Manufacturing",
            "subcategory":"Building Materials",
            "type":"Manufacturing & Wholesale Goods"
        }
    ],
    "sg:phone":"+61 3 9583 0115",
    "sg:postcode":"3192",
    "sg:province":"VIC",
    "sg:tags":[
        "concrete",
        "product"
    ],
    "wof:name":"Dayton Superior",
    "wof:placetype":"venue"
},
  "geometry": {"coordinates":[145.04124450699999,-37.9574966431],"type":"Point"}
}