{
  "type": "Feature",
  "properties": {
    "addr:full":"Shop 46a The Pine Shopng Cntr KP McGrath Drv & Guineas Creek Rd Elanora QLD 4221",
    "addr:housenumber":"46a",
    "addr:postcode":"4221",
    "addr:street":"The Pine Shopng Cntr;Mcgrath Drv & Guineas Creek Rd",
    "iso:country":"AU",
    "sg:address":"Shop 46a The Pine Shopng Cntr KP McGrath Drv & Guineas Creek Rd",
    "sg:city":"Elanora",
    "sg:classifiers":[
        {
            "category":"Food & Beverages",
            "subcategory":"Liquor & Beverages",
            "type":"Retail Goods"
        }
    ],
    "sg:phone":"+61 7 5598 1691",
    "sg:postcode":"4221",
    "sg:province":"QLD",
    "sg:tags":[
        "store"
    ],
    "wof:name":"BWS Liquor Stores",
    "wof:placetype":"venue"
},
  "geometry": {"coordinates":[153.454177856,-28.1367073059],"type":"Point"}
}