{
  "type": "Feature",
  "properties": {
    "addr:full":"Unit 21B 12-16 Milford St East Victoria Park WA 6101",
    "addr:housenumber":"unit 21b 12-16",
    "addr:postcode":"6101",
    "addr:street":"Milford St",
    "iso:country":"AU",
    "sg:address":"Unit 21B 12-16 Milford St",
    "sg:city":"East Victoria Park",
    "sg:classifiers":[
        {
            "category":"Banks & Credit Unions",
            "subcategory":"Bank",
            "type":"Services"
        }
    ],
    "sg:phone":"+61 408 919 334",
    "sg:postcode":"6101",
    "sg:province":"WA",
    "sg:tags":[
        "leather",
        "cutting",
        "fabric",
        "plastic"
    ],
    "wof:name":"Pats Cutting Service",
    "wof:placetype":"venue"
},
  "geometry": {"coordinates":[115.915428162,-31.9911994934],"type":"Point"}
}