{
  "type": "Feature",
  "properties": {
    "addr:full":"16-22 Dick St Chippendale NSW 2008",
    "addr:housenumber":"16-22",
    "addr:postcode":"2008",
    "addr:street":"Dick St",
    "iso:country":"AU",
    "sg:address":"16-22 Dick St",
    "sg:city":"Chippendale",
    "sg:classifiers":[
        {
            "category":"Manufacturing",
            "subcategory":"Textiles",
            "type":"Manufacturing & Wholesale Goods"
        }
    ],
    "sg:phone":"+61 2 9310 3255",
    "sg:postcode":"2008",
    "sg:province":"NSW",
    "sg:tags":[
        "agent"
    ],
    "wof:name":"Bartlett & Partners (Agencies) Pty Ltd",
    "wof:placetype":"venue"
},
  "geometry": {"coordinates":[151.199142456,-33.8863372803],"type":"Point"}
}