{
  "type": "Feature",
  "properties": {
    "addr:full":"43 Rockingham Beach Rd Rockingham WA 6168",
    "addr:housenumber":"43",
    "addr:postcode":"6168",
    "addr:street":"Rockingham Beach Rd",
    "iso:country":"AU",
    "sg:address":"43 Rockingham Beach Rd",
    "sg:city":"Rockingham",
    "sg:classifiers":[
        {
            "category":"Home & Garden",
            "subcategory":"Kitchen Supply",
            "type":"Retail Goods"
        }
    ],
    "sg:phone":"+61 8 9527 9028",
    "sg:postcode":"6168",
    "sg:province":"WA",
    "sg:tags":[
        "equipment",
        "diving"
    ],
    "wof:name":"Bell Scuba",
    "wof:placetype":"venue"
},
  "geometry": {"coordinates":[115.757622,-32.250061],"type":"Point"}
}