{
  "type": "Feature",
  "properties": {
    "iso:country":"AU",
    "sg:address":"1 Lancaster Ave",
    "sg:city":"Cecil Hills",
    "sg:classifiers":[
        {
            "category":"Health Services",
            "subcategory":"Doctor",
            "type":"Services"
        }
    ],
    "sg:phone":"+61 2 9822 9111",
    "sg:postcode":"2171",
    "sg:province":"NSW",
    "sg:tags":[
        "medical",
        "practitioner"
    ],
    "wof:name":"Aran Sohyel Dr",
    "wof:placetype":"venue"
},
  "geometry": {"coordinates":[150.856323242,-33.8939590454],"type":"Point"}
}