{
  "type": "Feature",
  "properties": {
    "iso:country":"AU",
    "sg:address":"27 Cleveland Crt",
    "sg:city":"Meadow Springs",
    "sg:classifiers":[
        {
            "category":"Manufacturing",
            "subcategory":"Tools & Machinery",
            "type":"Manufacturing & Wholesale Goods"
        }
    ],
    "sg:phone":"+61 8 9581 8891",
    "sg:postcode":"6210",
    "sg:province":"WA",
    "wof:name":"Kenny's Industrial Services",
    "wof:placetype":"venue"
},
  "geometry": {"coordinates":[115.746834,-32.497894],"type":"Point"}
}