{
  "type": "Feature",
  "properties": {
    "iso:country":"AU",
    "sg:address":"Lvl 2, 43 Hardware La",
    "sg:city":"Melbourne",
    "sg:classifiers":[
        {
            "category":"Professional",
            "subcategory":"Employment Agencies",
            "type":"Services"
        }
    ],
    "sg:phone":"+61 3 9670 7733",
    "sg:postcode":"3000",
    "sg:province":"VIC",
    "wof:name":"Extrastaff Recruitment Pty Ltd",
    "wof:placetype":"venue"
},
  "geometry": {"coordinates":[144.96107482900001,-37.8136367798],"type":"Point"}
}