{
  "type": "Feature",
  "properties": {
    "iso:country":"AU",
    "sg:address":"106 Alfred Rd",
    "sg:city":"Chipping Norton",
    "sg:classifiers":[
        {
            "category":"Shopping",
            "subcategory":"Clothing, Apparel, & Fashions",
            "type":"Retail Goods"
        }
    ],
    "sg:phone":"+61 2 9755 4097",
    "sg:postcode":"2170",
    "sg:province":"NSW",
    "sg:tags":[
        "lady",
        "wear"
    ],
    "wof:name":"Growing Concern & Supa Sizes The",
    "wof:placetype":"venue"
},
  "geometry": {"coordinates":[150.95758056599999,-33.9234237671],"type":"Point"}
}