{
  "type": "Feature",
  "properties": {
    "addr:full":"Shop 2, 162 The Entrance Rd Erina NSW 2250",
    "addr:housenumber":"shop 2 162",
    "addr:postcode":"2250",
    "addr:street":"The Entrance Rd",
    "iso:country":"AU",
    "sg:address":"Shop 2, 162 The Entrance Rd",
    "sg:city":"Erina",
    "sg:classifiers":[
        {
            "category":"Shopping",
            "subcategory":"Computers & Home Electronics",
            "type":"Retail Goods"
        }
    ],
    "sg:phone":"+61 2 4365 1000",
    "sg:postcode":"2250",
    "sg:province":"NSW",
    "sg:tags":[
        "equipment",
        "supply"
    ],
    "wof:name":"Inkjet Technologies",
    "wof:placetype":"venue"
},
  "geometry": {"coordinates":[151.384643555,-33.4362258911],"type":"Point"}
}