{
  "type": "Feature",
  "properties": {
    "addr:full":"1360 Ballarto Rd Cranbourne VIC 3977",
    "addr:housenumber":"1360",
    "addr:postcode":"3977",
    "addr:street":"Ballarto Rd",
    "iso:country":"AU",
    "sg:address":"1360 Ballarto Rd",
    "sg:city":"Cranbourne",
    "sg:classifiers":[
        {
            "category":"Wholesale",
            "subcategory":"Plants",
            "type":"Manufacturing & Wholesale Goods"
        }
    ],
    "sg:phone":"+61 3 5996 7020",
    "sg:postcode":"3977",
    "sg:province":"VIC",
    "sg:tags":[
        "florist"
    ],
    "wof:name":"Buncha Flowers",
    "wof:placetype":"venue"
},
  "geometry": {"coordinates":[145.309356689,-38.131477356],"type":"Point"}
}