{
  "type": "Feature",
  "properties": {
    "addr:full":"Unit 8/ 50 Medcalf St Warners Bay NSW 2282",
    "addr:postcode":"2282",
    "addr:street":"50 Medcalf St",
    "iso:country":"AU",
    "sg:address":"Unit 8/ 50 Medcalf St",
    "sg:city":"Warners Bay",
    "sg:classifiers":[
        {
            "category":"Government",
            "subcategory":"Fire Station",
            "type":"Public Place"
        }
    ],
    "sg:phone":"+61 2 4956 5211",
    "sg:postcode":"2282",
    "sg:province":"NSW",
    "sg:tags":[
        "burner",
        "gas",
        "equipment"
    ],
    "wof:name":"A.A. Kilns Pty Ltd",
    "wof:placetype":"venue"
},
  "geometry": {"coordinates":[151.647872925,-32.9665107727],"type":"Point"}
}