{
  "type": "Feature",
  "properties": {
    "addr:full":"Wandearah Rd Port Pirie SA 5540",
    "addr:postcode":"5540",
    "addr:street":"Wandearah Rd",
    "iso:country":"AU",
    "sg:address":"Wandearah Rd",
    "sg:city":"Port Pirie",
    "sg:classifiers":[
        {
            "category":"Education",
            "subcategory":"School",
            "type":"Public Place"
        }
    ],
    "sg:phone":"+61 8 8632 4735",
    "sg:postcode":"5540",
    "sg:province":"SA",
    "wof:name":"St Mark's College Primary",
    "wof:placetype":"venue"
},
  "geometry": {"coordinates":[138.011550903,-33.1855697632],"type":"Point"}
}