{
  "type": "Feature",
  "properties": {
    "iso:country":"AU",
    "sg:address":"95 Montana Rd",
    "sg:city":"Deloraine",
    "sg:classifiers":[
        {
            "category":"Farming",
            "subcategory":"Fish & Marine Products",
            "type":"Manufacturing & Wholesale Goods"
        }
    ],
    "sg:phone":"+61 3 6362 2539",
    "sg:postcode":"7304",
    "sg:province":"TAS",
    "sg:tags":[
        "production",
        "seafood",
        "processing"
    ],
    "wof:name":"Eels Australis Pty Ltd",
    "wof:placetype":"venue"
},
  "geometry": {"coordinates":[146.591156,-41.544418],"type":"Point"}
}