{
  "type": "Feature",
  "properties": {
    "addr:full":"26 Bolton St Wagga Wagga NSW 2650",
    "addr:housenumber":"26",
    "addr:postcode":"2650",
    "addr:street":"Bolton St",
    "iso:country":"AU",
    "sg:address":"26 Bolton St",
    "sg:city":"Wagga Wagga",
    "sg:classifiers":[
        {
            "category":"Building & Trades",
            "subcategory":"Construction",
            "type":"Services"
        }
    ],
    "sg:phone":"+61 2 6931 9315",
    "sg:postcode":"2650",
    "sg:province":"NSW",
    "sg:tags":[
        "tennis court",
        "repair"
    ],
    "wof:name":"Stewarts Tennis Plus",
    "wof:placetype":"venue"
},
  "geometry": {"coordinates":[147.355560303,-35.1145935059],"type":"Point"}
}