{
  "type": "Feature",
  "properties": {
    "addr:full":"Level 6, 68 Grenfell St Adelaide SA 5000",
    "addr:housenumber":"68",
    "addr:postcode":"5000",
    "addr:street":"Grenfell St",
    "iso:country":"AU",
    "sg:address":"Level 6, 68 Grenfell St",
    "sg:city":"Adelaide",
    "sg:classifiers":[
        {
            "category":"Organizations",
            "subcategory":"Professional Association",
            "type":"Services"
        }
    ],
    "sg:phone":"+61 8 8359 2090",
    "sg:postcode":"5000",
    "sg:province":"SA",
    "sg:tags":[
        "organisation",
        "business"
    ],
    "wof:name":"Australian Institute Of Conveyancers SA Division Inc",
    "wof:placetype":"venue"
},
  "geometry": {"coordinates":[138.60220336899999,-34.9240455627],"type":"Point"}
}