{
  "type": "Feature",
  "properties": {
    "addr:full":"Stutehbury St Page ACT 2614",
    "addr:postcode":"2614",
    "addr:street":"St",
    "iso:country":"AU",
    "sg:address":"Stutehbury St",
    "sg:city":"Page",
    "sg:classifiers":[
        {
            "category":"Education",
            "subcategory":"School",
            "type":"Public Place"
        }
    ],
    "sg:phone":"+61 2 6254 2653",
    "sg:postcode":"2614",
    "sg:province":"ACT",
    "wof:name":"St Matthew's Primary",
    "wof:placetype":"venue"
},
  "geometry": {"coordinates":[149.04298400900001,-35.2399215698],"type":"Point"}
}