{
  "type": "Feature",
  "properties": {
    "addr:full":"Royal Children&#039;s Hospital Flemington Rd Parkville VIC 3052",
    "addr:postcode":"3052",
    "addr:street":"S;Flemington Rd",
    "iso:country":"AU",
    "sg:address":"Royal Children&#039;s Hospital Flemington Rd",
    "sg:city":"Parkville",
    "sg:classifiers":[
        {
            "category":"Health Services",
            "subcategory":"Doctor",
            "type":"Services"
        }
    ],
    "sg:phone":"+61 3 9345 5182",
    "sg:postcode":"3052",
    "sg:province":"VIC",
    "sg:tags":[
        "medical",
        "practitioner"
    ],
    "wof:name":"General Medicine",
    "wof:placetype":"venue"
},
  "geometry": {"coordinates":[144.94403076200001,-37.7906112671],"type":"Point"}
}