{
  "type": "Feature",
  "properties": {
    "iso:country":"AU",
    "sg:address":"26 Dudley St",
    "sg:city":"Rydalmere",
    "sg:classifiers":[
        {
            "category":"Professional",
            "subcategory":"Computer Services",
            "type":"Services"
        }
    ],
    "sg:phone":"+61 2 9613 8014",
    "sg:postcode":"2116",
    "sg:province":"NSW",
    "sg:tags":[
        "package",
        "software"
    ],
    "wof:name":"Tametech Pty Ltd",
    "wof:placetype":"venue"
},
  "geometry": {"coordinates":[151.033493042,-33.8628387451],"type":"Point"}
}