{
  "type": "Feature",
  "properties": {
    "addr:full":"PO Box 811 The Junction NSW 2291",
    "addr:postcode":"2291",
    "iso:country":"AU",
    "sg:address":"PO Box 811",
    "sg:city":"The Junction",
    "sg:classifiers":[
        {
            "category":"Building & Trades",
            "subcategory":"Landscaping Services",
            "type":"Services"
        }
    ],
    "sg:phone":"+61 2 4927 5898",
    "sg:postcode":"2291",
    "sg:province":"NSW",
    "sg:tags":[
        "architect",
        "landscape"
    ],
    "wof:name":"Lithos Group Landscape Architects",
    "wof:placetype":"venue"
},
  "geometry": {"coordinates":[151.759887695,-32.9372406006],"type":"Point"}
}