{
  "type": "Feature",
  "properties": {
    "iso:country":"AU",
    "sg:address":"365 Little Collins St",
    "sg:city":"Melbourne",
    "sg:classifiers":[
        {
            "category":"Insurance",
            "subcategory":"Insurance Agent",
            "type":"Services"
        }
    ],
    "sg:phone":"+61 1300 551 969",
    "sg:postcode":"3000",
    "sg:province":"VIC",
    "sg:tags":[
        "broker"
    ],
    "wof:name":"SRG Corporate",
    "wof:placetype":"venue"
},
  "geometry": {"coordinates":[144.96270751899999,-37.8156089783],"type":"Point"}
}