{
  "type": "Feature",
  "properties": {
    "iso:country":"AU",
    "sg:address":"108 Mann St",
    "sg:city":"Gosford",
    "sg:classifiers":[
        {
            "category":"Travel",
            "subcategory":"Hotels & Motels",
            "type":"Entertainment"
        }
    ],
    "sg:phone":"+61 2 4324 1267",
    "sg:postcode":"2250",
    "sg:province":"NSW",
    "sg:tags":[
        "accommodation"
    ],
    "wof:name":"Union Hotel",
    "wof:placetype":"venue"
},
  "geometry": {"coordinates":[151.34175109899999,-33.4266548157],"type":"Point"}
}