{
  "type": "Feature",
  "properties": {
    "iso:country":"AU",
    "sg:address":"18 Naylor St",
    "sg:city":"Carcoar",
    "sg:classifiers":[
        {
            "category":"Shopping",
            "subcategory":"Crafts & Fabrics",
            "type":"Retail Goods"
        }
    ],
    "sg:phone":"+61 2 6367 3173",
    "sg:postcode":"2791",
    "sg:province":"NSW",
    "sg:tags":[
        "supply"
    ],
    "wof:name":"Old Bakery Country Craft",
    "wof:placetype":"venue"
},
  "geometry": {"coordinates":[149.139129639,-33.6118888855],"type":"Point"}
}