{
  "type": "Feature",
  "properties": {
    "addr:full":"77 Shore St West, Cleveland QLD 4163",
    "addr:housenumber":"77",
    "addr:postcode":"4163",
    "addr:street":"Shore St West",
    "iso:country":"AU",
    "sg:address":"77 Shore St",
    "sg:city":"West, Cleveland",
    "sg:classifiers":[
        {
            "category":"Professional",
            "subcategory":"Employment Agencies",
            "type":"Services"
        }
    ],
    "sg:phone":"+61 7 3286 7398",
    "sg:postcode":"4163",
    "sg:province":"QLD",
    "wof:name":"Redlands Recruitment",
    "wof:placetype":"venue"
},
  "geometry": {"coordinates":[153.258300781,-27.5244274139],"type":"Point"}
}