{
  "type": "Feature",
  "properties": {
    "addr:full":"1710 Warburton Hwy Woori Yallock VIC 3139",
    "addr:housenumber":"1710",
    "addr:postcode":"3139",
    "addr:street":"Warburton Hwy",
    "iso:country":"AU",
    "sg:address":"1710 Warburton Hwy",
    "sg:city":"Woori Yallock",
    "sg:classifiers":[
        {
            "category":"Autos & Motor Vehicles",
            "subcategory":"Auto Supplies",
            "type":"Retail Goods"
        }
    ],
    "sg:phone":"+61 3 5964 7220",
    "sg:postcode":"3139",
    "sg:province":"VIC",
    "sg:tags":[
        "tyre"
    ],
    "wof:name":"Bridgestone Schubert Tyre Centre",
    "wof:placetype":"venue"
},
  "geometry": {"coordinates":[145.60627746599999,-37.7795639038],"type":"Point"}
}