{
  "type": "Feature",
  "properties": {
    "iso:country":"AU",
    "sg:address":"17 Marina Vieu Pde",
    "sg:city":"St Huberts Island",
    "sg:classifiers":[
        {
            "category":"Professional",
            "subcategory":"Engineering",
            "type":"Services"
        }
    ],
    "sg:phone":"+61 400 489 968",
    "sg:postcode":"2257",
    "sg:province":"NSW",
    "sg:tags":[
        "consulting",
        "engineer"
    ],
    "wof:name":"Grant Johnston Consulting Engineering",
    "wof:placetype":"venue"
},
  "geometry": {"coordinates":[151.346099853,-33.4945869446],"type":"Point"}
}