{
  "type": "Feature",
  "properties": {
    "addr:full":"Lvl 1/ 934 Mt Alexander Rd Essendon VIC 3040",
    "addr:housenumber":"/ 934",
    "addr:postcode":"3040",
    "addr:street":"Mt Alexander Rd",
    "iso:country":"AU",
    "sg:address":"Lvl 1/ 934 Mt Alexander Rd",
    "sg:city":"Essendon",
    "sg:classifiers":[
        {
            "category":"Social Services",
            "subcategory":"Retirement Home",
            "type":"Services"
        }
    ],
    "sg:phone":"+61 3 9370 1726",
    "sg:postcode":"3040",
    "sg:province":"VIC",
    "sg:tags":[
        "environmental",
        "consultant",
        "pollution"
    ],
    "wof:name":"LRM Global Pty Ltd",
    "wof:placetype":"venue"
},
  "geometry": {"coordinates":[144.91799926799999,-37.7552032471],"type":"Point"}
}