{
  "type": "Feature",
  "properties": {
    "iso:country":"AU",
    "sg:address":"52 Willarong Rd",
    "sg:city":"Caringbah",
    "sg:classifiers":[
        {
            "category":"Education",
            "subcategory":"Music School",
            "type":"Public Place"
        }
    ],
    "sg:phone":"+61 2 9526 7476",
    "sg:postcode":"2229",
    "sg:province":"NSW",
    "sg:tags":[
        "singing",
        "teacher"
    ],
    "wof:name":"Mariette Rups-Donnelly",
    "wof:placetype":"venue"
},
  "geometry": {"coordinates":[151.12261962900001,-34.0299339294],"type":"Point"}
}