{
  "type": "Feature",
  "properties": {
    "addr:full":"ACIS House 107 Quay St Brisbane QLD 4000",
    "addr:housenumber":"107",
    "addr:postcode":"4000",
    "addr:street":"Quay St",
    "iso:country":"AU",
    "sg:address":"ACIS House 107 Quay St",
    "sg:city":"Brisbane",
    "sg:classifiers":[
        {
            "category":"Banks & Credit Unions",
            "subcategory":"Atm",
            "type":"Services"
        }
    ],
    "sg:phone":"+61 1800 773 477",
    "sg:postcode":"4000",
    "sg:province":"QLD",
    "sg:tags":[
        "shelf"
    ],
    "wof:name":"ACIS Pty Ltd",
    "wof:placetype":"venue"
},
  "geometry": {"coordinates":[153.01234435999999,-27.467414856],"type":"Point"}
}