{
  "type": "Feature",
  "properties": {
    "addr:full":"Fctry 4/ 2 Eddy Ave Moama NSW 2731",
    "addr:housenumber":"4 / 2",
    "addr:postcode":"2731",
    "addr:street":"Fctry;Eddy Ave",
    "iso:country":"AU",
    "sg:address":"Fctry 4/ 2 Eddy Ave",
    "sg:city":"Moama",
    "sg:classifiers":[
        {
            "category":"Retail",
            "subcategory":"Auto Repair",
            "type":"Services"
        }
    ],
    "sg:phone":"+61 3 5480 7222",
    "sg:postcode":"2731",
    "sg:province":"NSW",
    "sg:tags":[
        "muffler",
        "exhaust",
        "system"
    ],
    "wof:name":"Moama Welding & Exhaust Centre",
    "wof:placetype":"venue"
},
  "geometry": {"coordinates":[144.77220199999999,-36.109035],"type":"Point"}
}