{
  "type": "Feature",
  "properties": {
    "addr:full":"Unit 5/ 200 Hoxton Park Rd Hoxton Park NSW 2171",
    "addr:housenumber":"/ 200",
    "addr:postcode":"2171",
    "addr:street":"Hoxton Park Rd",
    "iso:country":"AU",
    "sg:address":"Unit 5/ 200 Hoxton Park Rd",
    "sg:city":"Hoxton Park",
    "sg:classifiers":[
        {
            "category":"Building & Trades",
            "subcategory":"Construction",
            "type":"Services"
        }
    ],
    "sg:phone":"+61 412 225 415",
    "sg:postcode":"2171",
    "sg:province":"NSW",
    "sg:tags":[
        "insulation",
        "contractor"
    ],
    "sg:website":"http://www.eurekainsulation.com.au",
    "wof:name":"Eureka Insulation",
    "wof:placetype":"venue"
},
  "geometry": {"coordinates":[150.85234069800001,-33.9256668091],"type":"Point"}
}