{
  "type": "Feature",
  "properties": {
    "iso:country":"AU",
    "sg:address":"481 Port Rd",
    "sg:city":"Croydon",
    "sg:classifiers":[
        {
            "category":"Professional",
            "subcategory":"Accounting & Tax Preparation",
            "type":"Services"
        }
    ],
    "sg:phone":"+61 8 8340 0834",
    "sg:postcode":"5008",
    "sg:province":"SA",
    "sg:tags":[
        "consultant",
        "taxation"
    ],
    "wof:name":"Adelaide Accounting Service",
    "wof:placetype":"venue"
},
  "geometry": {"coordinates":[138.560883,-34.897415],"type":"Point"}
}