{
  "type": "Feature",
  "properties": {
    "addr:full":"481 Port Rd Croydon SA 5008",
    "addr:housenumber":"481",
    "addr:postcode":"5008",
    "addr:street":"Port Rd",
    "iso:country":"AU",
    "sg:address":"481 Port Rd",
    "sg:city":"Croydon",
    "sg:classifiers":[
        {
            "category":"Professional",
            "subcategory":"Accounting & Tax Preparation",
            "type":"Services"
        }
    ],
    "sg:phone":"+61 8 8340 0834",
    "sg:postcode":"5008",
    "sg:province":"SA",
    "sg:tags":[
        "consultant",
        "taxation"
    ],
    "wof:name":"Adelaide Accounting Service",
    "wof:placetype":"venue"
},
  "geometry": {"coordinates":[138.56088299999999,-34.897415],"type":"Point"}
}