{
  "type": "Feature",
  "properties": {
    "addr:full":"7 Hume Pl Mt Colah NSW 2079",
    "addr:housenumber":"7",
    "addr:postcode":"2079",
    "addr:street":"Hume Pl Mt Colah",
    "iso:country":"AU",
    "sg:address":"7 Hume Pl",
    "sg:city":"Mt Colah",
    "sg:classifiers":[
        {
            "category":"Building & Trades",
            "subcategory":"Construction",
            "type":"Services"
        }
    ],
    "sg:phone":"+61 2 9457 8774",
    "sg:postcode":"2079",
    "sg:province":"NSW",
    "sg:tags":[
        "joiner",
        "carpenter"
    ],
    "wof:name":"C.R & L Davis",
    "wof:placetype":"venue"
},
  "geometry": {"coordinates":[151.117675781,-33.6567153931],"type":"Point"}
}