{
  "type": "Feature",
  "properties": {
    "addr:full":"10 Glen St Paddington NSW 2021",
    "addr:housenumber":"10",
    "addr:postcode":"2021",
    "addr:street":"Glen St",
    "iso:country":"AU",
    "sg:address":"10 Glen St",
    "sg:city":"Paddington",
    "sg:classifiers":[
        {
            "category":"Professional",
            "subcategory":"Management & Consulting",
            "type":"Services"
        }
    ],
    "sg:phone":"+61 416 266 216",
    "sg:postcode":"2021",
    "sg:province":"NSW",
    "sg:tags":[
        "consultant"
    ],
    "wof:name":"The Veridian Group Pty Ltd",
    "wof:placetype":"venue"
},
  "geometry": {"coordinates":[151.22750854500001,-33.8807792664],"type":"Point"}
}