{
  "type": "Feature",
  "properties": {
    "iso:country":"AU",
    "sg:address":"Homestead Rd",
    "sg:city":"Mataranka",
    "sg:classifiers":[
        {
            "category":"Travel",
            "subcategory":"Hotels & Motels",
            "type":"Entertainment"
        }
    ],
    "sg:phone":"+61 8 8975 4544",
    "sg:postcode":"0852",
    "sg:province":"NT",
    "wof:name":"Mataranka Homestead Tourist Resort",
    "wof:placetype":"venue"
},
  "geometry": {"coordinates":[133.080856,-14.938445],"type":"Point"}
}