{
  "type": "Feature",
  "properties": {
    "iso:country":"AU",
    "sg:address":"Peterborough Rd",
    "sg:city":"Peterborough",
    "sg:classifiers":[
        {
            "category":"Manufacturing",
            "subcategory":"Printing",
            "type":"Manufacturing & Wholesale Goods"
        }
    ],
    "sg:phone":"+61 428 112 324",
    "sg:postcode":"3270",
    "sg:province":"VIC",
    "sg:tags":[
        "wholesaler",
        "mfrs",
        "greeting",
        "card"
    ],
    "wof:name":"The Card Man",
    "wof:placetype":"venue"
},
  "geometry": {"coordinates":[142.872512817,-38.6027793884],"type":"Point"}
}