{
  "type": "Feature",
  "properties": {
    "addr:full":"The Shunt Off Rd Kernot VIC 3979",
    "addr:postcode":"3979",
    "addr:street":"Off Rd",
    "iso:country":"AU",
    "sg:address":"The Shunt Off Rd",
    "sg:city":"Kernot",
    "sg:classifiers":[
        {
            "category":"Building & Trades",
            "subcategory":"Landscaping Services",
            "type":"Services"
        }
    ],
    "sg:phone":"+61 3 5678 8317",
    "sg:postcode":"3979",
    "sg:province":"VIC",
    "sg:tags":[
        "grazier"
    ],
    "wof:name":"Stewart W F & B",
    "wof:placetype":"venue"
},
  "geometry": {"coordinates":[145.596923828,-38.4267997742],"type":"Point"}
}