{
  "type": "Feature",
  "properties": {
    "addr:full":"PO Box 507 Mt Martha VIC 3934",
    "addr:postcode":"3934",
    "iso:country":"AU",
    "sg:address":"PO Box 507",
    "sg:city":"Mt Martha",
    "sg:classifiers":[
        {
            "category":"Banks & Credit Unions",
            "subcategory":"Financial Services",
            "type":"Services"
        }
    ],
    "sg:phone":"+61 417 153 723",
    "sg:postcode":"3934",
    "sg:province":"VIC",
    "sg:tags":[
        "planning"
    ],
    "wof:name":"Basic Financial Advice",
    "wof:placetype":"venue"
},
  "geometry": {"coordinates":[145.030853272,-38.2737808228],"type":"Point"}
}