{
  "type": "Feature",
  "properties": {
    "addr:full":"38 Dalton St Dubbo NSW 2830",
    "addr:housenumber":"38",
    "addr:postcode":"2830",
    "addr:street":"Dalton St",
    "iso:country":"AU",
    "sg:address":"38 Dalton St",
    "sg:city":"Dubbo",
    "sg:classifiers":[
        {
            "category":"Home & Garden",
            "subcategory":"Carpets & Floor Coverings",
            "type":"Retail Goods"
        }
    ],
    "sg:phone":"+61 2 6882 1627",
    "sg:postcode":"2830",
    "sg:province":"NSW",
    "wof:name":"Orana Floorsanding",
    "wof:placetype":"venue"
},
  "geometry": {"coordinates":[148.60830688499999,-32.266166687],"type":"Point"}
}