{
  "type": "Feature",
  "properties": {
    "iso:country":"AU",
    "sg:address":"234 Berkeley Rd",
    "sg:city":"Unanderra",
    "sg:classifiers":[
        {
            "category":"Professional",
            "type":"Services"
        }
    ],
    "sg:phone":"+61 2 4271 5522",
    "sg:postcode":"2526",
    "sg:province":"NSW",
    "sg:tags":[
        "shop",
        "fitting"
    ],
    "wof:name":"UTJ Interiors",
    "wof:placetype":"venue"
},
  "geometry": {"coordinates":[150.84808349599999,-34.45652771],"type":"Point"}
}