{
  "type": "Feature",
  "properties": {
    "addr:full":"7A Margaret St Yarraman QLD 4614",
    "addr:housenumber":"7a",
    "addr:postcode":"4614",
    "addr:street":"Margaret St",
    "iso:country":"AU",
    "sg:address":"7A Margaret St",
    "sg:city":"Yarraman",
    "sg:classifiers":[
        {
            "category":"Shopping",
            "subcategory":"Clothing, Apparel, & Fashions",
            "type":"Retail Goods"
        }
    ],
    "sg:phone":"+61 7 4163 8000",
    "sg:postcode":"4614",
    "sg:province":"QLD",
    "sg:tags":[
        "recycled",
        "clothing"
    ],
    "wof:name":"Australian Red Cross",
    "wof:placetype":"venue"
},
  "geometry": {"coordinates":[151.980743408,-26.8416423798],"type":"Point"}
}