{
  "type": "Feature",
  "properties": {
    "iso:country":"AU",
    "sg:address":"Shop 7, 6 Little Bramston St",
    "sg:city":"Gladstone",
    "sg:classifiers":[
        {
            "category":"Utilities",
            "subcategory":"Electric",
            "type":"Services"
        }
    ],
    "sg:phone":"+61 7 4972 6883",
    "sg:postcode":"4680",
    "sg:province":"QLD",
    "sg:tags":[
        "electrical",
        "contractor"
    ],
    "wof:name":"Webb T J & K E Electrical",
    "wof:placetype":"venue"
},
  "geometry": {"coordinates":[151.260009766,-23.8440952301],"type":"Point"}
}