{
  "type": "Feature",
  "properties": {
    "iso:country":"AU",
    "sg:address":"96 Monyash Rd",
    "sg:city":"Carine",
    "sg:classifiers":[
        {
            "category":"Insurance",
            "subcategory":"Insurance Agent",
            "type":"Services"
        }
    ],
    "sg:phone":"+61 8 9447 5359",
    "sg:postcode":"6020",
    "sg:province":"WA",
    "wof:name":"Palmer L G",
    "wof:placetype":"venue"
},
  "geometry": {"coordinates":[115.79032135,-31.8555908203],"type":"Point"}
}