{
  "type": "Feature",
  "properties": {
    "addr:full":"14 Helen St Newstead QLD 4006",
    "addr:housenumber":"14",
    "addr:postcode":"4006",
    "addr:street":"Helen St",
    "iso:country":"AU",
    "sg:address":"14 Helen St",
    "sg:city":"Newstead",
    "sg:classifiers":[
        {
            "category":"Shopping",
            "subcategory":"Crafts & Fabrics",
            "type":"Retail Goods"
        }
    ],
    "sg:phone":"+61 7 3257 7500",
    "sg:postcode":"4006",
    "sg:province":"QLD",
    "sg:tags":[
        "florist",
        "supply"
    ],
    "wof:name":"Everts Australia",
    "wof:placetype":"venue"
},
  "geometry": {"coordinates":[153.04606628400001,-27.4532833099],"type":"Point"}
}