{
  "type": "Feature",
  "properties": {
    "iso:country":"AU",
    "sg:address":"32 Hickory St",
    "sg:city":"Dorrigo",
    "sg:classifiers":[
        {
            "category":"Health Services",
            "subcategory":"Health Practitioner",
            "type":"Services"
        }
    ],
    "sg:phone":"+61 2 6657 1097",
    "sg:postcode":"2453",
    "sg:province":"NSW",
    "sg:tags":[
        "acupuncture"
    ],
    "wof:name":"Hartman, Carol",
    "wof:placetype":"venue"
},
  "geometry": {"coordinates":[152.711777,-30.339375],"type":"Point"}
}