{
  "type": "Feature",
  "properties": {
    "iso:country":"AU",
    "sg:address":"8 Berry St",
    "sg:city":"Churchill",
    "sg:classifiers":[
        {
            "category":"Building & Trades",
            "subcategory":"Landscaping Services",
            "type":"Services"
        }
    ],
    "sg:phone":"+61 7 3281 9037",
    "sg:postcode":"4305",
    "sg:province":"QLD",
    "sg:tags":[
        "stump",
        "tree",
        "felling",
        "removal"
    ],
    "wof:name":"Bremer-West Moreton Tree Services",
    "wof:placetype":"venue"
},
  "geometry": {"coordinates":[152.749465942,-27.6441955566],"type":"Point"}
}