{
  "type": "Feature",
  "properties": {
    "addr:full":"Factory 26, 26-28 Roberna St Moorabbin VIC 3189",
    "addr:housenumber":"26-28",
    "addr:postcode":"3189",
    "addr:street":"Roberna St",
    "iso:country":"AU",
    "sg:address":"Factory 26, 26-28 Roberna St",
    "sg:city":"Moorabbin",
    "sg:classifiers":[
        {
            "category":"Wholesale",
            "subcategory":"Machinery & Supplies",
            "type":"Manufacturing & Wholesale Goods"
        }
    ],
    "sg:phone":"+61 3 9532 2300",
    "sg:postcode":"3189",
    "sg:province":"VIC",
    "sg:tags":[
        "bearing",
        "bushing"
    ],
    "wof:name":"Bearing Wholesalers Pty Ltd",
    "wof:placetype":"venue"
},
  "geometry": {"coordinates":[145.06788635300001,-37.9454803467],"type":"Point"}
}