{
  "type": "Feature",
  "properties": {
    "iso:country":"AU",
    "sg:address":"Murray Valley Hwy",
    "sg:city":"Wood Wood",
    "sg:classifiers":[
        {
            "category":"Health Services",
            "subcategory":"Health Practitioner",
            "type":"Services"
        }
    ],
    "sg:phone":"+61 3 5030 5126",
    "sg:postcode":"3596",
    "sg:province":"VIC",
    "sg:tags":[
        "reiki"
    ],
    "wof:name":"Jenny Arblaster",
    "wof:placetype":"venue"
},
  "geometry": {"coordinates":[143.34930419899999,-35.1131401062],"type":"Point"}
}