{
  "type": "Feature",
  "properties": {
    "addr:full":"1 Rose St Manjimup WA 6258",
    "addr:housenumber":"1",
    "addr:postcode":"6258",
    "addr:street":"Rose St",
    "iso:country":"AU",
    "sg:address":"1 Rose St",
    "sg:city":"Manjimup",
    "sg:classifiers":[
        {
            "category":"Wholesale",
            "subcategory":"Machinery & Supplies",
            "type":"Manufacturing & Wholesale Goods"
        }
    ],
    "sg:phone":"+61 8 9771 1351",
    "sg:postcode":"6258",
    "sg:province":"WA",
    "sg:tags":[
        "agricultural"
    ],
    "wof:name":"Transport & Agricultural Sales & Services",
    "wof:placetype":"venue"
},
  "geometry": {"coordinates":[116.14414978000001,-34.2424888611],"type":"Point"}
}