{
  "type": "Feature",
  "properties": {
    "addr:full":"256 Albany Hwy, Centennial Heights Albany WA 6330",
    "addr:housenumber":"256",
    "addr:postcode":"6330",
    "addr:street":"Albany Hwy",
    "iso:country":"AU",
    "sg:address":"256 Albany Hwy, Centennial Heights",
    "sg:city":"Albany",
    "sg:classifiers":[
        {
            "category":"Shopping",
            "subcategory":"Mobile Phones",
            "type":"Retail Goods"
        }
    ],
    "sg:phone":"+61 13 17 60",
    "sg:postcode":"6330",
    "sg:province":"WA",
    "sg:tags":[
        "telephone",
        "accessory"
    ],
    "wof:name":"Battery World",
    "wof:placetype":"venue"
},
  "geometry": {"coordinates":[117.884002685,-35.0174484253],"type":"Point"}
}