{
  "type": "Feature",
  "properties": {
    "addr:full":"Cnr Shepparton & Teddington Rds Burswood WA 6100",
    "addr:postcode":"6100",
    "addr:street":"Cnr",
    "iso:country":"AU",
    "sg:address":"Cnr Shepparton & Teddington Rds",
    "sg:city":"Burswood",
    "sg:classifiers":[
        {
            "category":"Banks & Credit Unions",
            "subcategory":"Atm",
            "type":"Services"
        }
    ],
    "sg:phone":"+61 1800 554 434",
    "sg:postcode":"6100",
    "sg:province":"WA",
    "sg:tags":[
        "box",
        "case",
        "metal"
    ],
    "wof:name":"MW Sheet Metal Pty Ltd",
    "wof:placetype":"venue"
},
  "geometry": {"coordinates":[115.894538879,-31.9679374695],"type":"Point"}
}