{
  "type": "Feature",
  "properties": {
    "addr:full":"6 Castlereagh St Murrumba Downs QLD 4503",
    "addr:housenumber":"6",
    "addr:postcode":"4503",
    "addr:street":"Castlereagh St",
    "iso:country":"AU",
    "sg:address":"6 Castlereagh St",
    "sg:city":"Murrumba Downs",
    "sg:classifiers":[
        {
            "category":"Building & Trades",
            "subcategory":"Equipment Rental",
            "type":"Services"
        }
    ],
    "sg:phone":"+61 412 547 125",
    "sg:postcode":"4503",
    "sg:province":"QLD",
    "sg:tags":[
        "crane",
        "hire"
    ],
    "wof:name":"Jakeman Ian",
    "wof:placetype":"venue"
},
  "geometry": {"coordinates":[153.01556396500001,-27.282793045],"type":"Point"}
}