{
  "type": "Feature",
  "properties": {
    "addr:full":"3 Thorn Crt Shepparton VIC 3630",
    "addr:housenumber":"3",
    "addr:postcode":"3630",
    "addr:street":"Thorn Crt",
    "iso:country":"AU",
    "sg:address":"3 Thorn Crt",
    "sg:city":"Shepparton",
    "sg:classifiers":[
        {
            "category":"Building & Trades",
            "subcategory":"Construction",
            "type":"Services"
        }
    ],
    "sg:phone":"+61 3 5831 2999",
    "sg:postcode":"3630",
    "sg:province":"VIC",
    "sg:tags":[
        "contractor"
    ],
    "wof:name":"DR & ML Robinson Builders",
    "wof:placetype":"venue"
},
  "geometry": {"coordinates":[145.413497925,-36.3619155884],"type":"Point"}
}