{
  "type": "Feature",
  "properties": {
    "addr:full":"909 Cape Clear-Rokewood Rd Illabarook VIC 3351",
    "addr:housenumber":"909",
    "addr:postcode":"3351",
    "addr:street":"Cape Clear-Rokewood Rd",
    "iso:country":"AU",
    "sg:address":"909 Cape Clear-Rokewood Rd",
    "sg:city":"Illabarook",
    "sg:classifiers":[
        {
            "category":"Building & Trades",
            "subcategory":"Construction",
            "type":"Services"
        }
    ],
    "sg:phone":"+61 3 5342 2425",
    "sg:postcode":"3351",
    "sg:province":"VIC",
    "sg:tags":[
        "fencing",
        "contractor"
    ],
    "wof:name":"Legin Fencing",
    "wof:placetype":"venue"
},
  "geometry": {"coordinates":[143.645432,-37.826115],"type":"Point"}
}