{
  "type": "Feature",
  "properties": {
    "addr:full":"147 Mary St Gympie QLD 4570",
    "addr:housenumber":"147",
    "addr:postcode":"4570",
    "addr:street":"Mary St",
    "iso:country":"AU",
    "sg:address":"147 Mary St",
    "sg:city":"Gympie",
    "sg:classifiers":[
        {
            "category":"Shopping",
            "subcategory":"Department Store",
            "type":"Retail Goods"
        }
    ],
    "sg:phone":"+61 7 5482 1822",
    "sg:postcode":"4570",
    "sg:province":"QLD",
    "wof:name":"Wilbrahams",
    "wof:placetype":"venue"
},
  "geometry": {"coordinates":[152.66140747099999,-26.1896057129],"type":"Point"}
}