{
  "type": "Feature",
  "properties": {
    "iso:country":"AU",
    "sg:address":"10 Antill St",
    "sg:city":"Yennora",
    "sg:classifiers":[
        {
            "category":"Retail",
            "subcategory":"Storage",
            "type":"Services"
        }
    ],
    "sg:phone":"+61 2 9632 5088",
    "sg:postcode":"2161",
    "sg:province":"NSW",
    "sg:tags":[
        "removal",
        "furniture"
    ],
    "wof:name":"Pilot Removals",
    "wof:placetype":"venue"
},
  "geometry": {"coordinates":[150.977584839,-33.8635826111],"type":"Point"}
}