{
  "type": "Feature",
  "properties": {
    "addr:full":"255 Pound St Grafton NSW 2460",
    "addr:housenumber":"255",
    "addr:postcode":"2460",
    "addr:street":"Pound St",
    "iso:country":"AU",
    "sg:address":"255 Pound St",
    "sg:city":"Grafton",
    "sg:classifiers":[
        {
            "category":"Organizations",
            "subcategory":"Membership Organization",
            "type":"Services"
        }
    ],
    "sg:phone":"+61 2 6643 3200",
    "sg:postcode":"2460",
    "sg:province":"NSW",
    "sg:tags":[
        "railway"
    ],
    "wof:name":"Pacific National",
    "wof:placetype":"venue"
},
  "geometry": {"coordinates":[152.92405700699999,-29.6825466156],"type":"Point"}
}