{
  "type": "Feature",
  "properties": {
    "addr:full":"Cnr Eramosa Rd East Somerville VIC 3912",
    "addr:postcode":"3912",
    "addr:street":"Cnr Eramosa Rd",
    "iso:country":"AU",
    "sg:address":"Cnr Eramosa Rd",
    "sg:city":"East Somerville",
    "sg:classifiers":[
        {
            "category":"Shopping",
            "subcategory":"Jewelry",
            "type":"Retail Goods"
        }
    ],
    "sg:phone":"+61 3 5977 8637",
    "sg:postcode":"3912",
    "sg:province":"VIC",
    "sg:tags":[
        "jeweller"
    ],
    "wof:name":"All Year Round Accessories",
    "wof:placetype":"venue"
},
  "geometry": {"coordinates":[145.207122803,-38.2238998413],"type":"Point"}
}