{
  "type": "Feature",
  "properties": {
    "addr:full":"74 South Pde Blackburn VIC 3130",
    "addr:housenumber":"74",
    "addr:postcode":"3130",
    "addr:street":"South Pde",
    "iso:country":"AU",
    "sg:address":"74 South Pde",
    "sg:city":"Blackburn",
    "sg:classifiers":[
        {
            "category":"Shopping",
            "subcategory":"Crafts & Fabrics",
            "type":"Retail Goods"
        }
    ],
    "sg:phone":"+61 3 9894 8800",
    "sg:postcode":"3130",
    "sg:province":"VIC",
    "sg:tags":[
        "supply"
    ],
    "wof:name":"Bellbird Paper Arts",
    "wof:placetype":"venue"
},
  "geometry": {"coordinates":[145.15034484899999,-37.820690155],"type":"Point"}
}