{
  "type": "Feature",
  "properties": {
    "addr:full":"521 Nepean Hwy Frankston VIC 3199",
    "addr:housenumber":"521",
    "addr:postcode":"3199",
    "addr:street":"Nepean Hwy",
    "iso:country":"AU",
    "sg:address":"521 Nepean Hwy",
    "sg:city":"Frankston",
    "sg:classifiers":[
        {
            "category":"Autos & Motor Vehicles",
            "subcategory":"Fuel & Gas Station",
            "type":"Retail Goods"
        }
    ],
    "sg:phone":"+61 3 9781 4152",
    "sg:postcode":"3199",
    "sg:province":"VIC",
    "wof:name":"Olivers Hill Service Centre",
    "wof:placetype":"venue"
},
  "geometry": {"coordinates":[145.01173400900001,-37.9090805054],"type":"Point"}
}