{
  "type": "Feature",
  "properties": {
    "addr:full":"Shp 1 Village Shopng Cntr 166 Mona Vale Rd St Ives NSW 2075",
    "addr:housenumber":"1;166",
    "addr:postcode":"2075",
    "addr:street":"Village Shopng Cntr;Mona Vale Rd",
    "iso:country":"AU",
    "sg:address":"Shp 1 Village Shopng Cntr 166 Mona Vale Rd",
    "sg:city":"St Ives",
    "sg:classifiers":[
        {
            "category":"Food & Beverages",
            "subcategory":"Liquor & Beverages",
            "type":"Retail Goods"
        }
    ],
    "sg:phone":"+61 2 9144 6911",
    "sg:postcode":"2075",
    "sg:province":"NSW",
    "sg:tags":[
        "store"
    ],
    "wof:name":"Liquorland",
    "wof:placetype":"venue"
},
  "geometry": {"coordinates":[151.15887451200001,-33.7304878235],"type":"Point"}
}