{
  "type": "Feature",
  "properties": {
    "addr:full":"114 Main St Proserpine QLD 4800",
    "addr:housenumber":"114",
    "addr:postcode":"4800",
    "addr:street":"Main St",
    "iso:country":"AU",
    "sg:address":"114 Main St",
    "sg:city":"Proserpine",
    "sg:classifiers":[
        {
            "category":"Wholesale",
            "subcategory":"Farm Supplies",
            "type":"Manufacturing & Wholesale Goods"
        }
    ],
    "sg:phone":"+61 7 4945 1577",
    "sg:postcode":"4800",
    "sg:province":"QLD",
    "sg:tags":[
        "equipment"
    ],
    "wof:name":"CRT Proserpine Rural",
    "wof:placetype":"venue"
},
  "geometry": {"coordinates":[148.58494567899999,-20.4020633698],"type":"Point"}
}