{
  "type": "Feature",
  "properties": {
    "addr:full":"14 Cambridge St West Leederville WA 6007",
    "addr:housenumber":"14",
    "addr:postcode":"6007",
    "addr:street":"Cambridge St West",
    "iso:country":"AU",
    "sg:address":"14 Cambridge St",
    "sg:city":"West Leederville",
    "sg:classifiers":[
        {
            "category":"Real Estate",
            "subcategory":"Architect",
            "type":"Services"
        }
    ],
    "sg:phone":"+61 8 9381 3022",
    "sg:postcode":"6007",
    "sg:province":"WA",
    "wof:name":"Broderick Michael & Partners",
    "wof:placetype":"venue"
},
  "geometry": {"coordinates":[115.84078979500001,-31.9405231476],"type":"Point"}
}