{
  "type": "Feature",
  "properties": {
    "addr:full":"Shop 40 / Adelaide Arcade Adelaide SA 5000",
    "addr:housenumber":"shop 40 / adelaide arcade",
    "addr:postcode":"5000",
    "iso:country":"AU",
    "sg:address":"Shop 40",
    "sg:city":"/ Adelaide Arcade Adelaide",
    "sg:classifiers":[
        {
            "category":"Personal",
            "subcategory":"Beauty Salon",
            "type":"Services"
        }
    ],
    "sg:phone":"+61 8 8223 5272",
    "sg:postcode":"5000",
    "sg:province":"SA",
    "wof:name":"DEVA The Aveda Concept Salon",
    "wof:placetype":"venue"
},
  "geometry": {"coordinates":[138.60076904300001,-34.9256401062],"type":"Point"}
}