{
  "type": "Feature",
  "properties": {
    "addr:full":"215 Church Rd Taigum QLD 4018",
    "addr:housenumber":"215",
    "addr:postcode":"4018",
    "addr:street":"Church Rd",
    "iso:country":"AU",
    "sg:address":"215 Church Rd",
    "sg:city":"Taigum",
    "sg:classifiers":[
        {
            "category":"Social Services",
            "subcategory":"Child Care",
            "type":"Services"
        }
    ],
    "sg:phone":"+61 7 3865 2677",
    "sg:postcode":"4018",
    "sg:province":"QLD",
    "wof:name":"Tadpoles Early Learning Centres",
    "wof:placetype":"venue"
},
  "geometry": {"coordinates":[153.046707,-27.349039],"type":"Point"}
}