{
  "type": "Feature",
  "properties": {
    "addr:full":"50 Lardner Rd Drouin VIC 3818",
    "addr:housenumber":"50",
    "addr:postcode":"3818",
    "addr:street":"Lardner Rd",
    "iso:country":"AU",
    "sg:address":"50 Lardner Rd",
    "sg:city":"Drouin",
    "sg:classifiers":[
        {
            "category":"Home & Garden",
            "subcategory":"Carpets & Floor Coverings",
            "type":"Retail Goods"
        }
    ],
    "sg:phone":"+61 3 5625 3934",
    "sg:postcode":"3818",
    "sg:province":"VIC",
    "sg:tags":[
        "tile",
        "wall",
        "layer"
    ],
    "wof:name":"Jeff's Floor & Wall Tiling",
    "wof:placetype":"venue"
},
  "geometry": {"coordinates":[145.848648,-38.131603],"type":"Point"}
}