{
  "type": "Feature",
  "properties": {
    "addr:full":"Shop 1040 Westfield Shoppingtown 318 Moggill Road Indooroopilly QLD 4068",
    "addr:housenumber":"1040;318",
    "addr:postcode":"4068",
    "addr:street":"Westfield Shoppingtown;Moggill Road",
    "iso:country":"AU",
    "sg:address":"Shop 1040 Westfield Shoppingtown 318 Moggill Road",
    "sg:city":"Indooroopilly",
    "sg:classifiers":[
        {
            "category":"Personal",
            "subcategory":"Beauty Salon",
            "type":"Services"
        }
    ],
    "sg:phone":"+61 7 3378 9532",
    "sg:postcode":"4068",
    "sg:province":"QLD",
    "sg:tags":[
        "hairdresser"
    ],
    "wof:name":"Price Attack",
    "wof:placetype":"venue"
},
  "geometry": {"coordinates":[152.97247314399999,-27.4977474213],"type":"Point"}
}