{
  "type": "Feature",
  "properties": {
    "addr:full":"PO Box 323 Cherrybrook NSW 2126",
    "addr:postcode":"2126",
    "iso:country":"AU",
    "sg:address":"PO Box 323",
    "sg:city":"Cherrybrook",
    "sg:classifiers":[
        {
            "category":"Arts & Performance",
            "subcategory":"Music",
            "type":"Entertainment"
        }
    ],
    "sg:phone":"+61 412 346 758",
    "sg:postcode":"2126",
    "sg:province":"NSW",
    "sg:tags":[
        "mobile",
        "jockey",
        "disc"
    ],
    "wof:name":"Smash Hits",
    "wof:placetype":"venue"
},
  "geometry": {"coordinates":[151.04136657699999,-33.7210006714],"type":"Point"}
}