{
  "type": "Feature",
  "properties": {
    "addr:full":"68 Lamb St Murgon QLD 4605",
    "addr:housenumber":"68",
    "addr:postcode":"4605",
    "addr:street":"Lamb St",
    "iso:country":"AU",
    "sg:address":"68 Lamb St",
    "sg:city":"Murgon",
    "sg:classifiers":[
        {
            "category":"Fast Food",
            "type":"Food & Drink"
        }
    ],
    "sg:phone":"+61 7 4168 1069",
    "sg:postcode":"4605",
    "sg:province":"QLD",
    "sg:tags":[
        "away",
        "take"
    ],
    "wof:name":"Metro Milk Bar Murgon",
    "wof:placetype":"venue"
},
  "geometry": {"coordinates":[151.941452,-26.241747],"type":"Point"}
}