{
  "type": "Feature",
  "properties": {
    "addr:full":"366 Avoca Drv Avoca NSW 2577",
    "addr:housenumber":"366",
    "addr:postcode":"2577",
    "addr:street":"Avoca Drv",
    "iso:country":"AU",
    "sg:address":"366 Avoca Drv",
    "sg:city":"Avoca",
    "sg:classifiers":[
        {
            "category":"Wholesale",
            "subcategory":"Furniture",
            "type":"Manufacturing & Wholesale Goods"
        }
    ],
    "sg:phone":"+61 2 4368 3009",
    "sg:postcode":"2577",
    "sg:province":"NSW",
    "sg:tags":[
        "wholesaler",
        "mfrs"
    ],
    "wof:name":"Resurrection Collection",
    "wof:placetype":"venue"
},
  "geometry": {"coordinates":[150.479248047,-34.5752410889],"type":"Point"}
}