{
  "type": "Feature",
  "properties": {
    "addr:full":"241 Brisbane Rd Biggera Waters QLD 4216",
    "addr:housenumber":"241",
    "addr:postcode":"4216",
    "addr:street":"Brisbane Rd",
    "iso:country":"AU",
    "sg:address":"241 Brisbane Rd",
    "sg:city":"Biggera Waters",
    "sg:classifiers":[
        {
            "category":"Retail",
            "subcategory":"Auto Rental",
            "type":"Services"
        }
    ],
    "sg:phone":"+61 7 5537 8869",
    "sg:postcode":"4216",
    "sg:province":"QLD",
    "sg:tags":[
        "bus",
        "truck"
    ],
    "wof:name":"BP Biggera Waters",
    "wof:placetype":"venue"
},
  "geometry": {"coordinates":[153.375732422,-27.9313793182],"type":"Point"}
}