{
  "type": "Feature",
  "properties": {
    "iso:country":"AU",
    "sg:address":"277 Abbotsford Rd",
    "sg:city":"Bowen Hills",
    "sg:classifiers":[
        {
            "category":"Autos & Motor Vehicles",
            "subcategory":"Automobile Sales",
            "type":"Retail Goods"
        }
    ],
    "sg:phone":"+61 7 3252 4444",
    "sg:postcode":"4006",
    "sg:province":"QLD",
    "sg:tags":[
        "car",
        "used"
    ],
    "wof:name":"Mayne Motors Warehouse",
    "wof:placetype":"venue"
},
  "geometry": {"coordinates":[153.04096984899999,-27.4356117249],"type":"Point"}
}