{
  "type": "Feature",
  "properties": {
    "addr:full":"4 Ryecroft St Carrara QLD 4211",
    "addr:housenumber":"4",
    "addr:postcode":"4211",
    "addr:street":"Ryecroft St",
    "iso:country":"AU",
    "sg:address":"4 Ryecroft St",
    "sg:city":"Carrara",
    "sg:classifiers":[
        {
            "category":"Manufacturing",
            "subcategory":"Motor Vehicles & Parts",
            "type":"Manufacturing & Wholesale Goods"
        }
    ],
    "sg:phone":"+61 7 5530 3934",
    "sg:postcode":"4211",
    "sg:province":"QLD",
    "sg:tags":[
        "replacement"
    ],
    "wof:name":"Maxi-Drive Engineering",
    "wof:placetype":"venue"
},
  "geometry": {"coordinates":[153.35528564399999,-28.0337276459],"type":"Point"}
}