{
  "type": "Feature",
  "properties": {
    "addr:full":"111- 113 Adelaide St Maryborough QLD 4650",
    "addr:housenumber":"113",
    "addr:postcode":"4650",
    "addr:street":"Adelaide St",
    "iso:country":"AU",
    "sg:address":"111- 113 Adelaide St",
    "sg:city":"Maryborough",
    "sg:classifiers":[
        {
            "category":"Manufacturing",
            "subcategory":"Electronics",
            "type":"Manufacturing & Wholesale Goods"
        }
    ],
    "sg:phone":"+61 7 4121 5520",
    "sg:postcode":"4650",
    "sg:province":"QLD",
    "sg:tags":[
        "oven",
        "microwave"
    ],
    "wof:name":"Bradshaw's Radio-TV Service",
    "wof:placetype":"venue"
},
  "geometry": {"coordinates":[152.700638,-25.539999],"type":"Point"}
}