{
  "type": "Feature",
  "properties": {
    "iso:country":"AU",
    "sg:address":"107 Mountainview Rd",
    "sg:city":"Greensborough",
    "sg:classifiers":[
        {
            "category":"Utilities",
            "subcategory":"Refuse",
            "type":"Services"
        }
    ],
    "sg:phone":"+61 3 9465 9171",
    "sg:postcode":"3088",
    "sg:province":"VIC",
    "sg:tags":[
        "remover",
        "rubbish"
    ],
    "wof:name":"Skip &#039;N&#039; Around Bin Hire",
    "wof:placetype":"venue"
},
  "geometry": {"coordinates":[145.12013244600001,-37.7096481323],"type":"Point"}
}