{
  "type": "Feature",
  "properties": {
    "addr:full":"Unit 3, 131 Broadwood St West Kalgoorlie WA 6430",
    "addr:housenumber":"131",
    "addr:postcode":"6430",
    "addr:street":"Broadwood St West",
    "iso:country":"AU",
    "sg:address":"Unit 3, 131 Broadwood St",
    "sg:city":"West Kalgoorlie",
    "sg:classifiers":[
        {
            "category":"Banks & Credit Unions",
            "subcategory":"Bureau De Change",
            "type":"Services"
        }
    ],
    "sg:phone":"+61 8 9091 1020",
    "sg:postcode":"6430",
    "sg:province":"WA",
    "sg:tags":[
        "equipment",
        "heat",
        "exchange"
    ],
    "wof:name":"COR Engineered Cooling",
    "wof:placetype":"venue"
},
  "geometry": {"coordinates":[121.436569214,-30.7853145599],"type":"Point"}
}