{
  "type": "Feature",
  "properties": {
    "iso:country":"AU",
    "sg:address":"23 Lyall St",
    "sg:city":"South Perth",
    "sg:classifiers":[
        {
            "category":"Professional",
            "subcategory":"Management & Consulting",
            "type":"Services"
        }
    ],
    "sg:phone":"+61 8 9367 9230",
    "sg:postcode":"6151",
    "sg:province":"WA",
    "sg:tags":[
        "consultant"
    ],
    "wof:name":"Argus Research",
    "wof:placetype":"venue"
},
  "geometry": {"coordinates":[115.850838,-31.974451],"type":"Point"}
}