{
  "type": "Feature",
  "properties": {
    "addr:full":"23 Windrush Ave Belrose NSW 2085",
    "addr:housenumber":"23",
    "addr:postcode":"2085",
    "addr:street":"Windrush Ave",
    "iso:country":"AU",
    "sg:address":"23 Windrush Ave",
    "sg:city":"Belrose",
    "sg:classifiers":[
        {
            "category":"Building & Trades",
            "subcategory":"Landscaping Services",
            "type":"Services"
        }
    ],
    "sg:phone":"+61 2 9451 5292",
    "sg:postcode":"2085",
    "sg:province":"NSW",
    "sg:tags":[
        "stump",
        "tree",
        "felling",
        "removal"
    ],
    "wof:name":"Cleancut Tree Service",
    "wof:placetype":"venue"
},
  "geometry": {"coordinates":[151.213012695,-33.729473114],"type":"Point"}
}