{
  "type": "Feature",
  "properties": {
    "addr:full":"104 Ashmore Rd Sorrento QLD 4217",
    "addr:housenumber":"104",
    "addr:postcode":"4217",
    "addr:street":"Ashmore Rd",
    "iso:country":"AU",
    "sg:address":"104 Ashmore Rd",
    "sg:city":"Sorrento",
    "sg:classifiers":[
        {
            "category":"Professional",
            "subcategory":"Business Services",
            "type":"Services"
        }
    ],
    "sg:phone":"+61 7 5538 0250",
    "sg:postcode":"4217",
    "sg:province":"QLD",
    "sg:tags":[
        "drafting"
    ],
    "wof:name":"R & A Drafting",
    "wof:placetype":"venue"
},
  "geometry": {"coordinates":[153.40118408199999,-28.0098152161],"type":"Point"}
}