{
  "type": "Feature",
  "properties": {
    "addr:full":"32 Machinery St Darra QLD 4076",
    "addr:postcode":"4076",
    "addr:street":"St",
    "iso:country":"AU",
    "sg:address":"32 Machinery St",
    "sg:city":"Darra",
    "sg:classifiers":[
        {
            "category":"Banks & Credit Unions",
            "subcategory":"Bureau De Change",
            "type":"Services"
        }
    ],
    "sg:phone":"+61 7 3375 6808",
    "sg:postcode":"4076",
    "sg:province":"QLD",
    "sg:tags":[
        "wheel",
        "industrial"
    ],
    "wof:name":"Bearcat",
    "wof:placetype":"venue"
},
  "geometry": {"coordinates":[152.94813537600001,-27.5769863129],"type":"Point"}
}