{
  "type": "Feature",
  "properties": {
    "addr:full":"37 Bombala St Cooma NSW 2630",
    "addr:housenumber":"37",
    "addr:postcode":"2630",
    "addr:street":"Bombala St",
    "iso:country":"AU",
    "sg:address":"37 Bombala St",
    "sg:city":"Cooma",
    "sg:classifiers":[
        {
            "category":"Health Services",
            "subcategory":"Health Practitioner",
            "type":"Services"
        }
    ],
    "sg:phone":"+61 2 6452 4203",
    "sg:postcode":"2630",
    "sg:province":"NSW",
    "sg:tags":[
        "physiotherapist"
    ],
    "wof:name":"Alison Coles",
    "wof:placetype":"venue"
},
  "geometry": {"coordinates":[149.126586914,-36.2339782715],"type":"Point"}
}