{
  "type": "Feature",
  "properties": {
    "addr:full":"15 Fuller St Seven Hills NSW 2147",
    "addr:housenumber":"15",
    "addr:postcode":"2147",
    "addr:street":"Fuller St",
    "iso:country":"AU",
    "sg:address":"15 Fuller St",
    "sg:city":"Seven Hills",
    "sg:classifiers":[
        {
            "category":"Education",
            "subcategory":"Dance Studio",
            "type":"Public Place"
        }
    ],
    "sg:phone":"+61 2 9631 0893",
    "sg:postcode":"2147",
    "sg:province":"NSW",
    "sg:tags":[
        "venue",
        "tuition"
    ],
    "wof:name":"Abell Ilma School Of Ballroom Dancing",
    "wof:placetype":"venue"
},
  "geometry": {"coordinates":[150.942428589,-33.7820167542],"type":"Point"}
}