{
  "type": "Feature",
  "properties": {
    "addr:full":"6/ 33 East St Daylesford VIC 3460",
    "addr:housenumber":"/ 33",
    "addr:postcode":"3460",
    "addr:street":"East St",
    "iso:country":"AU",
    "sg:address":"6/ 33 East St",
    "sg:city":"Daylesford",
    "sg:classifiers":[
        {
            "category":"Building & Trades",
            "subcategory":"Construction",
            "type":"Services"
        }
    ],
    "sg:phone":"+61 418 539 969",
    "sg:postcode":"3460",
    "sg:province":"VIC",
    "sg:tags":[
        "welding"
    ],
    "wof:name":"Weldon Welding Services",
    "wof:placetype":"venue"
},
  "geometry": {"coordinates":[144.15516662600001,-37.3458824158],"type":"Point"}
}