{
  "type": "Feature",
  "properties": {
    "iso:country":"AU",
    "sg:address":"85 New Canterbury Rd",
    "sg:city":"Petersham",
    "sg:classifiers":[
        {
            "category":"Professional",
            "subcategory":"Computer Services",
            "type":"Services"
        }
    ],
    "sg:phone":"+61 2 9572 6979",
    "sg:postcode":"2049",
    "sg:province":"NSW",
    "sg:tags":[
        "tele-communications",
        "consultant"
    ],
    "wof:name":"Satcom Enterprises",
    "wof:placetype":"venue"
},
  "geometry": {"coordinates":[151.152344,-33.89679],"type":"Point"}
}