{
  "type": "Feature",
  "properties": {
    "iso:country":"AU",
    "sg:address":"Browning St",
    "sg:city":"West End",
    "sg:classifiers":[
        {
            "category":"Government",
            "subcategory":"Customs House",
            "type":"Public Place"
        }
    ],
    "sg:phone":"+61 7 3010 5555",
    "sg:postcode":"4101",
    "sg:province":"QLD",
    "sg:tags":[
        "title",
        "management",
        "stratum"
    ],
    "wof:name":"Stewart Silver King and Burns",
    "wof:placetype":"venue"
},
  "geometry": {"coordinates":[153.014434814,-27.4796657562],"type":"Point"}
}