{
  "type": "Feature",
  "properties": {
    "addr:full":"73 Bay Rd Blue Bay NSW 2261",
    "addr:housenumber":"73",
    "addr:postcode":"2261",
    "addr:street":"Bay Rd",
    "iso:country":"AU",
    "sg:address":"73 Bay Rd",
    "sg:city":"Blue Bay",
    "sg:classifiers":[
        {
            "category":"Fast Food",
            "type":"Food & Drink"
        }
    ],
    "sg:phone":"+61 2 4332 0559",
    "sg:postcode":"2261",
    "sg:province":"NSW",
    "sg:tags":[
        "away",
        "take"
    ],
    "wof:name":"Dolphin Blue Bay Store",
    "wof:placetype":"venue"
},
  "geometry": {"coordinates":[151.49968000000001,-33.35265],"type":"Point"}
}