{
  "type": "Feature",
  "properties": {
    "addr:full":"30 Sands St Bilingurr WA 6725",
    "addr:housenumber":"30",
    "addr:postcode":"6725",
    "addr:street":"Sands St",
    "iso:country":"AU",
    "sg:address":"30 Sands St",
    "sg:city":"Bilingurr",
    "sg:classifiers":[
        {
            "category":"Shopping",
            "subcategory":"Jewelry",
            "type":"Retail Goods"
        }
    ],
    "sg:phone":"+61 8 9193 7441",
    "sg:postcode":"6725",
    "sg:province":"WA",
    "sg:tags":[
        "jeweller"
    ],
    "wof:name":"La Boheme Australian Jewellery",
    "wof:placetype":"venue"
},
  "geometry": {"coordinates":[122.22538757300001,-17.9027481079],"type":"Point"}
}