{
  "type": "Feature",
  "properties": {
    "addr:full":"292 Canterbury Rd Bayswater VIC 3153",
    "addr:housenumber":"292",
    "addr:postcode":"3153",
    "addr:street":"Canterbury Rd",
    "iso:country":"AU",
    "sg:address":"292 Canterbury Rd",
    "sg:city":"Bayswater",
    "sg:classifiers":[
        {
            "category":"Autos & Motor Vehicles",
            "subcategory":"Automobile Sales",
            "type":"Retail Goods"
        }
    ],
    "sg:phone":"+61 3 9729 0022",
    "sg:postcode":"3153",
    "sg:province":"VIC",
    "sg:tags":[
        "car",
        "new"
    ],
    "wof:name":"Knox Star Mercedes",
    "wof:placetype":"venue"
},
  "geometry": {"coordinates":[145.270721436,-37.8315582275],"type":"Point"}
}