{
  "type": "Feature",
  "properties": {
    "addr:full":"58 Grey St Bacchus Marsh VIC 3340",
    "addr:housenumber":"58",
    "addr:postcode":"3340",
    "addr:street":"Grey St",
    "iso:country":"AU",
    "sg:address":"58 Grey St",
    "sg:city":"Bacchus Marsh",
    "sg:classifiers":[
        {
            "category":"Retail",
            "subcategory":"Photofinishing",
            "type":"Services"
        }
    ],
    "sg:phone":"+61 3 5367 2300",
    "sg:postcode":"3340",
    "sg:province":"VIC",
    "sg:tags":[
        "refractory"
    ],
    "wof:name":"Darley Refractories Pty Ltd",
    "wof:placetype":"venue"
},
  "geometry": {"coordinates":[144.43356299999999,-37.658012],"type":"Point"}
}