{
  "type": "Feature",
  "properties": {
    "addr:full":"238 Bunnerong Rd Hillsdale NSW 2036",
    "addr:housenumber":"238",
    "addr:postcode":"2036",
    "addr:street":"Bunnerong Rd",
    "iso:country":"AU",
    "sg:address":"238 Bunnerong Rd",
    "sg:city":"Hillsdale",
    "sg:classifiers":[
        {
            "category":"Communications",
            "type":"Services"
        }
    ],
    "sg:phone":"+61 2 9363 2223",
    "sg:postcode":"2036",
    "sg:province":"NSW",
    "sg:tags":[
        "translation"
    ],
    "wof:name":"Italian Interpreters & Translators",
    "wof:placetype":"venue"
},
  "geometry": {"coordinates":[151.23135375999999,-33.9512405396],"type":"Point"}
}