{
  "type": "Feature",
  "properties": {
    "iso:country":"AU",
    "sg:address":"Shop 4 25 First Ave",
    "sg:city":"Bongaree",
    "sg:classifiers":[
        {
            "category":"Retail",
            "subcategory":"Repair Shop",
            "type":"Services"
        }
    ],
    "sg:phone":"+61 408 000 908",
    "sg:postcode":"4507",
    "sg:province":"QLD",
    "sg:tags":[
        "maintenance",
        "pool",
        "swimming"
    ],
    "wof:name":"Passage Pool Supplies",
    "wof:placetype":"venue"
},
  "geometry": {"coordinates":[153.161087036,-27.0835704803],"type":"Point"}
}