{
  "type": "Feature",
  "properties": {
    "addr:full":"186 Princes Hwy Arncliffe NSW 2205",
    "addr:housenumber":"186",
    "addr:postcode":"2205",
    "addr:street":"Princes Hwy",
    "iso:country":"AU",
    "sg:address":"186 Princes Hwy",
    "sg:city":"Arncliffe",
    "sg:classifiers":[
        {
            "category":"Building & Trades",
            "subcategory":"Construction",
            "type":"Services"
        }
    ],
    "sg:phone":"+61 2 9597 6055",
    "sg:postcode":"2205",
    "sg:province":"NSW",
    "sg:tags":[
        "window",
        "tinting"
    ],
    "wof:name":"Sol-Ace Rockdale Pty Ltd",
    "wof:placetype":"venue"
},
  "geometry": {"coordinates":[151.14593500000001,-33.941109],"type":"Point"}
}