{
  "type": "Feature",
  "properties": {
    "addr:full":"1/ 48 Koobil St Rochedale QLD 4123",
    "addr:housenumber":"/ 48",
    "addr:postcode":"4123",
    "addr:street":"Koobil St",
    "iso:country":"AU",
    "sg:address":"1/ 48 Koobil St",
    "sg:city":"Rochedale",
    "sg:classifiers":[
        {
            "category":"Health Services",
            "subcategory":"Doctor",
            "type":"Services"
        }
    ],
    "sg:phone":"+61 7 3841 1011",
    "sg:postcode":"4123",
    "sg:province":"QLD",
    "sg:tags":[
        "medical",
        "practitioner"
    ],
    "wof:name":"Caird Rosemary Dr",
    "wof:placetype":"venue"
},
  "geometry": {"coordinates":[153.12696838400001,-27.6007575989],"type":"Point"}
}