{
  "type": "Feature",
  "properties": {
    "addr:full":"39 Kingsgrove Rd South Belmore NSW 2192",
    "addr:housenumber":"39",
    "addr:postcode":"2192",
    "addr:street":"Kingsgrove Rd South",
    "iso:country":"AU",
    "sg:address":"39 Kingsgrove Rd",
    "sg:city":"South Belmore",
    "sg:classifiers":[
        {
            "category":"Sports & Exercise",
            "subcategory":"Gym",
            "type":"Entertainment"
        }
    ],
    "sg:phone":"+61 2 9718 4356",
    "sg:postcode":"2192",
    "sg:province":"NSW",
    "sg:tags":[
        "health",
        "fitness"
    ],
    "wof:name":"Ju-Jutsu Wind School",
    "wof:placetype":"venue"
},
  "geometry": {"coordinates":[151.09648100000001,-33.925098],"type":"Point"}
}