{
  "type": "Feature",
  "properties": {
    "addr:full":"PO Box 856 Margaret River WA 6285",
    "addr:postcode":"6285",
    "iso:country":"AU",
    "sg:address":"PO Box 856",
    "sg:city":"Margaret River",
    "sg:classifiers":[
        {
            "category":"Arena",
            "subcategory":"Sports Club",
            "type":"Entertainment"
        }
    ],
    "sg:phone":"+61 8 9757 3850",
    "sg:postcode":"6285",
    "sg:province":"WA",
    "sg:tags":[
        "life",
        "surfing",
        "saving"
    ],
    "wof:name":"Josh Palmateer Surf Academy",
    "wof:placetype":"venue"
},
  "geometry": {"coordinates":[115.073486328,-33.9533615112],"type":"Point"}
}