{
  "type": "Feature",
  "properties": {
    "addr:full":"309 Old Geelong Rd Hoppers Crossing VIC 3029",
    "addr:housenumber":"309",
    "addr:postcode":"3029",
    "addr:street":"Old Geelong Rd",
    "iso:country":"AU",
    "sg:address":"309 Old Geelong Rd",
    "sg:city":"Hoppers Crossing",
    "sg:classifiers":[
        {
            "category":"Retail",
            "subcategory":"Auto Repair",
            "type":"Services"
        }
    ],
    "sg:phone":"+61 3 9748 0400",
    "sg:postcode":"3029",
    "sg:province":"VIC",
    "sg:tags":[
        "wheel",
        "balancing",
        "alignment"
    ],
    "wof:name":"Bridgestone Tyre Centre Hoppers Crossing",
    "wof:placetype":"venue"
},
  "geometry": {"coordinates":[144.72416699999999,-37.87273],"type":"Point"}
}