{
  "type": "Feature",
  "properties": {
    "addr:full":"18 Mellnga Crs Chadstone VIC 3148",
    "addr:housenumber":"18",
    "addr:postcode":"3148",
    "addr:street":"Mellnga Crs",
    "iso:country":"AU",
    "sg:address":"18 Mellnga Crs",
    "sg:city":"Chadstone",
    "sg:classifiers":[
        {
            "category":"Education",
            "subcategory":"Music School",
            "type":"Public Place"
        }
    ],
    "sg:phone":"+61 3 9809 5089",
    "sg:postcode":"3148",
    "sg:province":"VIC",
    "sg:tags":[
        "choir",
        "bands",
        "orchestra"
    ],
    "wof:name":"The Great Pretenders",
    "wof:placetype":"venue"
},
  "geometry": {"coordinates":[145.096893311,-37.881111145],"type":"Point"}
}