{
  "type": "Feature",
  "properties": {
    "addr:full":"U3101/ 21 Mary St Brisbane QLD 4000",
    "addr:housenumber":"/ 21",
    "addr:postcode":"4000",
    "addr:street":"Mary St",
    "iso:country":"AU",
    "sg:address":"U3101/ 21 Mary St",
    "sg:city":"Brisbane",
    "sg:classifiers":[
        {
            "category":"Wholesale",
            "subcategory":"Meat",
            "type":"Manufacturing & Wholesale Goods"
        }
    ],
    "sg:phone":"+61 7 3012 9956",
    "sg:postcode":"4000",
    "sg:province":"QLD",
    "sg:tags":[
        "packing",
        "exporting"
    ],
    "wof:name":"M & N Co",
    "wof:placetype":"venue"
},
  "geometry": {"coordinates":[153.02638244600001,-27.4729442596],"type":"Point"}
}