{
  "type": "Feature",
  "properties": {
    "iso:country":"AU",
    "sg:address":"252 Pitt St",
    "sg:city":"Merrylands",
    "sg:classifiers":[
        {
            "category":"Real Estate",
            "subcategory":"Real Estate Agent",
            "type":"Services"
        }
    ],
    "sg:phone":"+61 2 9682 6666",
    "sg:postcode":"2160",
    "sg:province":"NSW",
    "wof:name":"L J Hooker",
    "wof:placetype":"venue"
},
  "geometry": {"coordinates":[150.991622925,-33.8362083435],"type":"Point"}
}