{
  "type": "Feature",
  "properties": {
    "addr:full":"Level 3, 2- 14 Mountain St Ultimo NSW 2007",
    "addr:housenumber":"2 14",
    "addr:postcode":"2007",
    "addr:street":"Mountain St",
    "iso:country":"AU",
    "sg:address":"Level 3, 2- 14 Mountain St",
    "sg:city":"Ultimo",
    "sg:classifiers":[
        {
            "category":"Professional",
            "subcategory":"Computer Services",
            "type":"Services"
        }
    ],
    "sg:phone":"+61 2 8217 8888",
    "sg:postcode":"2007",
    "sg:province":"NSW",
    "sg:tags":[
        "package",
        "software"
    ],
    "wof:name":"Mobipro",
    "wof:placetype":"venue"
},
  "geometry": {"coordinates":[151.196136475,-33.8814086914],"type":"Point"}
}