{
  "type": "Feature",
  "properties": {
    "addr:full":"Unit 5a, 242 South Pine Rd Enoggera QLD 4051",
    "addr:housenumber":"unit 5a 242",
    "addr:postcode":"4051",
    "addr:street":"South Pine Rd",
    "iso:country":"AU",
    "sg:address":"Unit 5a, 242 South Pine Rd",
    "sg:city":"Enoggera",
    "sg:phone":"+61 411 736 945",
    "sg:postcode":"4051",
    "sg:province":"QLD",
    "wof:name":"Air Filter Services Pty Ltd",
    "wof:placetype":"venue"
},
  "geometry": {"coordinates":[152.994674683,-27.4176387787],"type":"Point"}
}