{
  "type": "Feature",
  "properties": {
    "addr:full":"3 Abbotts Rd Dandenong South VIC 3175",
    "addr:housenumber":"3",
    "addr:postcode":"3175",
    "addr:street":"Abbotts Rd",
    "iso:country":"AU",
    "sg:address":"3 Abbotts Rd",
    "sg:city":"Dandenong South",
    "sg:classifiers":[
        {
            "category":"Home & Garden",
            "subcategory":"Building Materials",
            "type":"Retail Goods"
        }
    ],
    "sg:phone":"+61 3 9706 6600",
    "sg:postcode":"3175",
    "sg:province":"VIC",
    "sg:tags":[
        "fitting",
        "door"
    ],
    "wof:name":"Timberite Building Supplies Pty Ltd",
    "wof:placetype":"venue"
},
  "geometry": {"coordinates":[145.21385192899999,-38.0317230225],"type":"Point"}
}