{
  "type": "Feature",
  "properties": {
    "addr:full":"6 Gladstone Rd Castle Hill NSW 2154",
    "addr:housenumber":"6",
    "addr:postcode":"2154",
    "addr:street":"Gladstone Rd",
    "iso:country":"AU",
    "sg:address":"6 Gladstone Rd",
    "sg:city":"Castle Hill",
    "sg:classifiers":[
        {
            "category":"Communications",
            "subcategory":"Film & Video Production",
            "type":"Services"
        }
    ],
    "sg:phone":"+61 2 9634 2644",
    "sg:postcode":"2154",
    "sg:province":"NSW",
    "sg:tags":[
        "fan",
        "blower"
    ],
    "wof:name":"Mangrovite Transmission Products",
    "wof:placetype":"venue"
},
  "geometry": {"coordinates":[150.977752686,-33.7331314087],"type":"Point"}
}