{
  "type": "Feature",
  "properties": {
    "addr:full":"148 - 150 Port Wakefield Rd Cavan SA 5094",
    "addr:housenumber":"150",
    "addr:postcode":"5094",
    "addr:street":"Port Wakefield Rd",
    "iso:country":"AU",
    "sg:address":"148 - 150 Port Wakefield Rd",
    "sg:city":"Cavan",
    "sg:classifiers":[
        {
            "category":"Building & Trades",
            "subcategory":"Equipment Rental",
            "type":"Services"
        }
    ],
    "sg:phone":"+61 500 504 477",
    "sg:postcode":"5094",
    "sg:province":"SA",
    "sg:tags":[
        "renting",
        "trailer"
    ],
    "wof:name":"Adelaide-Move Yourself Trailer Hire",
    "wof:placetype":"venue"
},
  "geometry": {"coordinates":[138.59861755399999,-34.8263320923],"type":"Point"}
}