{
  "type": "Feature",
  "properties": {
    "addr:full":"Rear17 Birdwood St Sylvania NSW 2224",
    "addr:postcode":"2224",
    "addr:street":"Birdwood St",
    "iso:country":"AU",
    "sg:address":"Rear17 Birdwood St",
    "sg:city":"Sylvania",
    "sg:classifiers":[
        {
            "category":"Health Services",
            "subcategory":"Doctor",
            "type":"Services"
        }
    ],
    "sg:phone":"+61 2 9522 8784",
    "sg:postcode":"2224",
    "sg:province":"NSW",
    "sg:tags":[
        "reflexology"
    ],
    "wof:name":"Host Jeanette Happy Feet",
    "wof:placetype":"venue"
},
  "geometry": {"coordinates":[151.095993042,-34.0087509155],"type":"Point"}
}