{
  "type": "Feature",
  "properties": {
    "addr:full":"1 Crompton Rd Rockingham WA 6168",
    "addr:housenumber":"1",
    "addr:postcode":"6168",
    "addr:street":"Crompton Rd",
    "iso:country":"AU",
    "sg:address":"1 Crompton Rd",
    "sg:city":"Rockingham",
    "sg:classifiers":[
        {
            "category":"Bars & Pubs",
            "subcategory":"Champagne Bar",
            "type":"Food & Drink"
        }
    ],
    "sg:phone":"+61 8 9527 2740",
    "sg:postcode":"6168",
    "sg:province":"WA",
    "sg:tags":[
        "lintel",
        "arch"
    ],
    "wof:name":"Rockingham Angle Irons",
    "wof:placetype":"venue"
},
  "geometry": {"coordinates":[115.767647,-32.274815],"type":"Point"}
}