{
  "type": "Feature",
  "properties": {
    "iso:country":"AU",
    "sg:address":"20 Spinnaker St",
    "sg:city":"Jamboree Heights",
    "sg:classifiers":[
        {
            "category":"Banks & Credit Unions",
            "subcategory":"Atm",
            "type":"Services"
        }
    ],
    "sg:phone":"+61 7 3376 4098",
    "sg:postcode":"4074",
    "sg:province":"QLD",
    "sg:tags":[
        "shelf"
    ],
    "wof:name":"Ace Company Registrations Pty Ltd",
    "wof:placetype":"venue"
},
  "geometry": {"coordinates":[152.93490600600001,-27.5556297302],"type":"Point"}
}