{
  "type": "Feature",
  "properties": {
    "iso:country":"AU",
    "sg:address":"Level 16/ 50 Park Rd",
    "sg:city":"Cabramatta",
    "sg:classifiers":[
        {
            "category":"Health Services",
            "subcategory":"Doctor",
            "type":"Services"
        }
    ],
    "sg:phone":"+61 2 9726 6688",
    "sg:postcode":"2166",
    "sg:province":"NSW",
    "sg:tags":[
        "medical",
        "practitioner"
    ],
    "wof:name":"Vos Medical Centre",
    "wof:placetype":"venue"
},
  "geometry": {"coordinates":[150.93716430699999,-33.8940811157],"type":"Point"}
}