{
  "type": "Feature",
  "properties": {
    "iso:country":"AU",
    "sg:address":"PO Box 5107",
    "sg:city":"Minto",
    "sg:classifiers":[
        {
            "category":"Wholesale",
            "subcategory":"Medical Equipment & Supplies",
            "type":"Manufacturing & Wholesale Goods"
        }
    ],
    "sg:phone":"+61 2 9603 7799",
    "sg:postcode":"2566",
    "sg:province":"NSW",
    "sg:tags":[
        "aid",
        "care",
        "health",
        "home"
    ],
    "wof:name":"Air&#039;N&#039;Lite",
    "wof:placetype":"venue"
},
  "geometry": {"coordinates":[150.84469604500001,-34.0311889648],"type":"Point"}
}