{
  "type": "Feature",
  "properties": {
    "addr:full":"13 - 15 Green St Thomastown VIC 3074",
    "addr:housenumber":"15",
    "addr:postcode":"3074",
    "addr:street":"Green St",
    "iso:country":"AU",
    "sg:address":"13 - 15 Green St",
    "sg:city":"Thomastown",
    "sg:classifiers":[
        {
            "category":"Retail",
            "subcategory":"Event Space",
            "type":"Services"
        }
    ],
    "sg:phone":"+61 3 9466 2113",
    "sg:postcode":"3074",
    "sg:province":"VIC",
    "sg:tags":[
        "venue",
        "reception",
        "wedding"
    ],
    "sg:website":"http://www.greenvillerecept.com.au",
    "wof:name":"Greenville Receptions",
    "wof:placetype":"venue"
},
  "geometry": {"coordinates":[145.03761291500001,-37.6930351257],"type":"Point"}
}