{
  "type": "Feature",
  "properties": {
    "iso:country":"AU",
    "sg:address":"U 2/ 172 Woodburn Rd",
    "sg:city":"Berala",
    "sg:classifiers":[
        {
            "category":"Personal",
            "subcategory":"Beauty Salon",
            "type":"Services"
        }
    ],
    "sg:phone":"+61 2 9643 1158",
    "sg:postcode":"2141",
    "sg:province":"NSW",
    "sg:tags":[
        "hairdresser"
    ],
    "wof:name":"Gina Hair Design",
    "wof:placetype":"venue"
},
  "geometry": {"coordinates":[151.03112793,-33.871723175],"type":"Point"}
}