{
  "type": "Feature",
  "properties": {
    "addr:full":"707 Yiluk St Tom Price WA 6751",
    "addr:housenumber":"707",
    "addr:postcode":"6751",
    "addr:street":"Yiluk St",
    "iso:country":"AU",
    "sg:address":"707 Yiluk St",
    "sg:city":"Tom Price",
    "sg:classifiers":[
        {
            "category":"Personal",
            "type":"Services"
        }
    ],
    "sg:phone":"+61 8 9188 1497",
    "sg:postcode":"6751",
    "sg:province":"WA",
    "sg:tags":[
        "dressmaker"
    ],
    "wof:name":"Tikies Design",
    "wof:placetype":"venue"
},
  "geometry": {"coordinates":[117.79624939,-22.6858272552],"type":"Point"}
}