{
  "type": "Feature",
  "properties": {
    "addr:full":"13 Lindsay St Dennington VIC 3280",
    "addr:housenumber":"13",
    "addr:postcode":"3280",
    "addr:street":"Lindsay St",
    "iso:country":"AU",
    "sg:address":"13 Lindsay St",
    "sg:city":"Dennington",
    "sg:classifiers":[
        {
            "category":"Utilities",
            "subcategory":"Natural Gas",
            "type":"Services"
        }
    ],
    "sg:phone":"+61 3 5562 8587",
    "sg:postcode":"3280",
    "sg:province":"VIC",
    "sg:tags":[
        "solid",
        "plasterer"
    ],
    "wof:name":"Fary Rendering",
    "wof:placetype":"venue"
},
  "geometry": {"coordinates":[142.44340515100001,-38.3569908142],"type":"Point"}
}