{
  "type": "Feature",
  "properties": {
    "iso:country":"AU",
    "sg:address":"220 Franklin St",
    "sg:city":"Adelaide",
    "sg:classifiers":[
        {
            "category":"Professional",
            "subcategory":"Detective & Security Services",
            "type":"Services"
        }
    ],
    "sg:phone":"+61 1300 662 668",
    "sg:postcode":"5000",
    "sg:province":"SA",
    "sg:tags":[
        "investigator"
    ],
    "wof:name":"Chubb Corporate Risk Services",
    "wof:placetype":"venue"
},
  "geometry": {"coordinates":[138.59101867699999,-34.9274749756],"type":"Point"}
}