{
  "type": "Feature",
  "properties": {
    "iso:country":"AU",
    "sg:address":"Shop 9 Cnr Robert & Railway Sts",
    "sg:city":"Mudgeeraba",
    "sg:classifiers":[
        {
            "category":"Personal",
            "subcategory":"Beauty Salon",
            "type":"Services"
        }
    ],
    "sg:phone":"+61 7 5530 4615",
    "sg:postcode":"4213",
    "sg:province":"QLD",
    "sg:tags":[
        "hairdresser"
    ],
    "wof:name":"Whos Who Hairdressing",
    "wof:placetype":"venue"
},
  "geometry": {"coordinates":[153.36459350600001,-28.0756034851],"type":"Point"}
}