{
  "type": "Feature",
  "properties": {
    "addr:full":"205 Barkly St St Kilda VIC 3182",
    "addr:housenumber":"205",
    "addr:postcode":"3182",
    "addr:street":"Barkly St",
    "iso:country":"AU",
    "sg:address":"205 Barkly St",
    "sg:city":"St Kilda",
    "sg:classifiers":[
        {
            "category":"Restaurant",
            "type":"Food & Drink"
        }
    ],
    "sg:phone":"+61 3 9534 5996",
    "sg:postcode":"3182",
    "sg:province":"VIC",
    "wof:name":"Bluecorn",
    "wof:placetype":"venue"
},
  "geometry": {"coordinates":[144.98057556099999,-37.8697395325],"type":"Point"}
}