{
  "type": "Feature",
  "properties": {
    "addr:full":"428 Riversdale Rd Hawthorn East VIC 3123",
    "addr:housenumber":"428",
    "addr:postcode":"3123",
    "addr:street":"Riversdale Rd",
    "iso:country":"AU",
    "sg:address":"428 Riversdale Rd",
    "sg:city":"Hawthorn East",
    "sg:classifiers":[
        {
            "category":"Health Services",
            "subcategory":"Dentist",
            "type":"Services"
        }
    ],
    "sg:phone":"+61 3 9654 4844",
    "sg:postcode":"3123",
    "sg:province":"VIC",
    "wof:name":"Heggie Andrew A C",
    "wof:placetype":"venue"
},
  "geometry": {"coordinates":[145.054779053,-37.8312454224],"type":"Point"}
}