{
  "type": "Feature",
  "properties": {
    "iso:country":"AU",
    "sg:address":"131 Queens Rd",
    "sg:city":"Nudgee",
    "sg:classifiers":[
        {
            "category":"Social Services",
            "subcategory":"Retirement Home",
            "type":"Services"
        }
    ],
    "sg:phone":"+61 7 3260 9555",
    "sg:postcode":"4014",
    "sg:province":"QLD",
    "sg:tags":[
        "village"
    ],
    "wof:name":"Emmaus",
    "wof:placetype":"venue"
},
  "geometry": {"coordinates":[153.09434509299999,-27.3658046722],"type":"Point"}
}