{
  "type": "Feature",
  "properties": {
    "addr:full":"Unit 8/6- 8 McLachlan Ave Artarmon NSW 2064",
    "addr:housenumber":"8",
    "addr:postcode":"2064",
    "addr:street":"Mclachlan Ave",
    "iso:country":"AU",
    "sg:address":"Unit 8/6- 8 McLachlan Ave",
    "sg:city":"Artarmon",
    "sg:classifiers":[
        {
            "category":"Professional",
            "subcategory":"Business Services",
            "type":"Services"
        }
    ],
    "sg:phone":"+61 2 9439 3511",
    "sg:postcode":"2064",
    "sg:province":"NSW",
    "sg:tags":[
        "management",
        "event"
    ],
    "wof:name":"James Gordon Workshop Pty Ltd",
    "wof:placetype":"venue"
},
  "geometry": {"coordinates":[151.181243897,-33.8136672974],"type":"Point"}
}