{
  "type": "Feature",
  "properties": {
    "iso:country":"AU",
    "sg:address":"2297 Point Nepean Rd",
    "sg:city":"Rye",
    "sg:classifiers":[
        {
            "category":"Fast Food",
            "type":"Food & Drink"
        }
    ],
    "sg:phone":"+61 3 5985 8801",
    "sg:postcode":"3941",
    "sg:province":"VIC",
    "sg:tags":[
        "away",
        "take"
    ],
    "wof:name":"King Sushi",
    "wof:placetype":"venue"
},
  "geometry": {"coordinates":[144.825408936,-38.3708076477],"type":"Point"}
}