{
  "type": "Feature",
  "properties": {
    "addr:full":"216 Empire Ave Churchlands WA 6018",
    "addr:housenumber":"216",
    "addr:postcode":"6018",
    "addr:street":"Empire Ave",
    "iso:country":"AU",
    "sg:address":"216 Empire Ave",
    "sg:city":"Churchlands",
    "sg:classifiers":[
        {
            "category":"Education",
            "subcategory":"School",
            "type":"Public Place"
        }
    ],
    "sg:phone":"+61 8 9204 9444",
    "sg:postcode":"6018",
    "sg:province":"WA",
    "sg:tags":[
        "co-educational"
    ],
    "wof:name":"Newman College",
    "wof:placetype":"venue"
},
  "geometry": {"coordinates":[115.783920288,-31.9227676392],"type":"Point"}
}