{
  "type": "Feature",
  "properties": {
    "iso:country":"AU",
    "sg:address":"1 Louth Rd",
    "sg:city":"Cobar",
    "sg:classifiers":[
        {
            "category":"Retail",
            "subcategory":"Auto Rental",
            "type":"Services"
        }
    ],
    "sg:phone":"+61 2 6836 4011",
    "sg:postcode":"2835",
    "sg:province":"NSW",
    "sg:tags":[
        "car",
        "hire",
        "minibus"
    ],
    "wof:name":"Mine Hire Australia Pty Ltd",
    "wof:placetype":"venue"
},
  "geometry": {"coordinates":[145.84019499999999,-31.496782],"type":"Point"}
}