{
  "type": "Feature",
  "properties": {
    "addr:full":"Deakin Business Centre Cnr Eighth St and Lemon Ave Mildura VIC 3500",
    "addr:postcode":"3500",
    "addr:street":"Cnr Eighth St;Ave",
    "iso:country":"AU",
    "sg:address":"Deakin Business Centre Cnr Eighth St and Lemon Ave",
    "sg:city":"Mildura",
    "sg:classifiers":[
        {
            "category":"Health Services",
            "subcategory":"Health Practitioner",
            "type":"Services"
        }
    ],
    "sg:phone":"+61 3 5021 5569",
    "sg:postcode":"3500",
    "sg:province":"VIC",
    "sg:tags":[
        "pathologist",
        "speech"
    ],
    "wof:name":"Linda Phillips",
    "wof:placetype":"venue"
},
  "geometry": {"coordinates":[142.171386719,-34.1923179626],"type":"Point"}
}