{
  "type": "Feature",
  "properties": {
    "addr:full":"3 Charles St Kew VIC 3101",
    "addr:housenumber":"3",
    "addr:postcode":"3101",
    "addr:street":"Charles St",
    "iso:country":"AU",
    "sg:address":"3 Charles St",
    "sg:city":"Kew",
    "sg:classifiers":[
        {
            "category":"Health Services",
            "subcategory":"Doctor",
            "type":"Services"
        }
    ],
    "sg:phone":"+61 3 9818 2263",
    "sg:postcode":"3101",
    "sg:province":"VIC",
    "sg:tags":[
        "medical",
        "practitioner"
    ],
    "wof:name":"Dhillon D C&G S",
    "wof:placetype":"venue"
},
  "geometry": {"coordinates":[145.03370666500001,-37.8137207031],"type":"Point"}
}