{
  "type": "Feature",
  "properties": {
    "addr:full":"PO Box 951 Warwick QLD 4370",
    "addr:postcode":"4370",
    "iso:country":"AU",
    "sg:address":"PO Box 951",
    "sg:city":"Warwick",
    "sg:classifiers":[
        {
            "category":"Building & Trades",
            "subcategory":"Construction",
            "type":"Services"
        }
    ],
    "sg:phone":"+61 418 787 261",
    "sg:postcode":"4370",
    "sg:province":"QLD",
    "sg:tags":[
        "excavation",
        "foundation"
    ],
    "wof:name":"Hardy Rodger & Patricia",
    "wof:placetype":"venue"
},
  "geometry": {"coordinates":[152.03465270999999,-28.2181301117],"type":"Point"}
}