{
  "type": "Feature",
  "properties": {
    "addr:full":"Shop 15,Colonial Arcade,Hay St Port Macquarie NSW 2444",
    "addr:housenumber":"shop 15",
    "addr:postcode":"2444",
    "addr:street":"Colonial Arcade Hay St",
    "iso:country":"AU",
    "sg:address":"Shop 15,Colonial Arcade,Hay St",
    "sg:city":"Port Macquarie",
    "sg:classifiers":[
        {
            "category":"Personal",
            "subcategory":"Beauty Salon",
            "type":"Services"
        }
    ],
    "sg:phone":"+61 2 6583 3741",
    "sg:postcode":"2444",
    "sg:province":"NSW",
    "sg:tags":[
        "hairdresser"
    ],
    "wof:name":"Milans Hairdressing",
    "wof:placetype":"venue"
},
  "geometry": {"coordinates":[152.909515,-31.429291],"type":"Point"}
}