{
  "type": "Feature",
  "properties": {
    "addr:full":"Blair St Broadmeadows VIC 3047",
    "addr:postcode":"3047",
    "addr:street":"Blair St",
    "iso:country":"AU",
    "sg:address":"Blair St",
    "sg:city":"Broadmeadows",
    "sg:classifiers":[
        {
            "category":"Education",
            "subcategory":"School",
            "type":"Public Place"
        }
    ],
    "sg:phone":"+61 3 9309 1988",
    "sg:postcode":"3047",
    "sg:province":"VIC",
    "sg:tags":[
        "state",
        "except",
        "nsw"
    ],
    "wof:name":"Broadmeadows Secondary College",
    "wof:placetype":"venue"
},
  "geometry": {"coordinates":[144.92692565900001,-37.6860351562],"type":"Point"}
}