{
  "type": "Feature",
  "properties": {
    "addr:full":"124 Main St Bairnsdale VIC 3875",
    "addr:housenumber":"124",
    "addr:postcode":"3875",
    "addr:street":"Main St",
    "iso:country":"AU",
    "sg:address":"124 Main St",
    "sg:city":"Bairnsdale",
    "sg:classifiers":[
        {
            "category":"Restaurant",
            "type":"Food & Drink"
        }
    ],
    "sg:phone":"+61 3 5152 3031",
    "sg:postcode":"3875",
    "sg:province":"VIC",
    "wof:name":"Commercial Hotel",
    "wof:placetype":"venue"
},
  "geometry": {"coordinates":[147.827224731,-37.7086296082],"type":"Point"}
}