{
  "type": "Feature",
  "properties": {
    "iso:country":"AU",
    "sg:address":"PO Box 536",
    "sg:city":"Golden Beach",
    "sg:classifiers":[
        {
            "category":"Professional",
            "subcategory":"Computer Services",
            "type":"Services"
        }
    ],
    "sg:phone":"+61 7 5314 1144",
    "sg:postcode":"4551",
    "sg:province":"QLD",
    "sg:tags":[
        "equipment",
        "networking",
        "installation"
    ],
    "wof:name":"Wi-Fi Hot Spot",
    "wof:placetype":"venue"
},
  "geometry": {"coordinates":[153.12013244600001,-26.8203296661],"type":"Point"}
}