{
  "type": "Feature",
  "properties": {
    "addr:full":"Shop 102, Level 1, Westfield Shopngtwn Belconnen ACT 2617",
    "addr:housenumber":"102 level 1",
    "addr:postcode":"2617",
    "addr:street":"Westfield Shopngtwn",
    "iso:country":"AU",
    "sg:address":"Shop 102, Level 1, Westfield Shopngtwn",
    "sg:city":"Belconnen",
    "sg:classifiers":[
        {
            "category":"Shopping",
            "subcategory":"Antiques",
            "type":"Retail Goods"
        }
    ],
    "sg:phone":"+61 2 6253 4723",
    "sg:postcode":"2617",
    "sg:province":"ACT",
    "sg:tags":[
        "collectable",
        "memorabilia"
    ],
    "wof:name":"Sports & Stars",
    "wof:placetype":"venue"
},
  "geometry": {"coordinates":[149.06353759800001,-35.239730835],"type":"Point"}
}