{
  "type": "Feature",
  "properties": {
    "addr:full":"19 The Fell St Thurgoona NSW 2640",
    "addr:housenumber":"19",
    "addr:postcode":"2640",
    "addr:street":"The Fell St",
    "iso:country":"AU",
    "sg:address":"19 The Fell St",
    "sg:city":"Thurgoona",
    "sg:classifiers":[
        {
            "category":"Commercial Area",
            "type":"Public Place"
        }
    ],
    "sg:phone":"+61 417 059 523",
    "sg:postcode":"2640",
    "sg:province":"NSW",
    "sg:tags":[
        "heavy",
        "carrier"
    ],
    "wof:name":"Dawson's Haulage",
    "wof:placetype":"venue"
},
  "geometry": {"coordinates":[146.99371337900001,-36.0482902527],"type":"Point"}
}