{
  "type": "Feature",
  "properties": {
    "addr:full":"4 Burleigh St Toronto West NSW 2283",
    "addr:housenumber":"4",
    "addr:postcode":"2283",
    "addr:street":"Burleigh St",
    "iso:country":"AU",
    "sg:address":"4 Burleigh St",
    "sg:city":"Toronto West",
    "sg:classifiers":[
        {
            "category":"Building & Trades",
            "subcategory":"Construction",
            "type":"Services"
        }
    ],
    "sg:phone":"+61 2 4950 5155",
    "sg:postcode":"2283",
    "sg:province":"NSW",
    "sg:tags":[
        "joinery"
    ],
    "wof:name":"Winstons Kitchens & Joinery",
    "wof:placetype":"venue"
},
  "geometry": {"coordinates":[151.573165894,-33.0023002625],"type":"Point"}
}