{
  "type": "Feature",
  "properties": {
    "addr:full":"31 Boronia Rd Bellevue Hill NSW 2023",
    "addr:housenumber":"31",
    "addr:postcode":"2023",
    "addr:street":"Boronia Rd",
    "iso:country":"AU",
    "sg:address":"31 Boronia Rd",
    "sg:city":"Bellevue Hill",
    "sg:classifiers":[
        {
            "category":"Banks & Credit Unions",
            "subcategory":"Investment Brokerage",
            "type":"Services"
        }
    ],
    "sg:phone":"+61 2 9130 2131",
    "sg:postcode":"2023",
    "sg:province":"NSW",
    "wof:name":"Hecht Peter & Associates",
    "wof:placetype":"venue"
},
  "geometry": {"coordinates":[151.2631073,-33.882270813],"type":"Point"}
}