{
  "type": "Feature",
  "properties": {
    "iso:country":"AU",
    "sg:address":"126 Monaro St",
    "sg:city":"Queanbeyan",
    "sg:classifiers":[
        {
            "category":"Fast Food",
            "type":"Food & Drink"
        }
    ],
    "sg:phone":"+61 2 6297 5441",
    "sg:postcode":"2620",
    "sg:province":"NSW",
    "sg:tags":[
        "away",
        "take"
    ],
    "wof:name":"Georges Pizzaria & Fast Foods",
    "wof:placetype":"venue"
},
  "geometry": {"coordinates":[149.23495483400001,-35.3532600403],"type":"Point"}
}