{
  "type": "Feature",
  "properties": {
    "addr:full":"Shop 2, 41 Pinjarra Rd Mandurah WA 6210",
    "addr:housenumber":"shop;41",
    "addr:postcode":"6210",
    "addr:street":"Pinjarra Rd",
    "iso:country":"AU",
    "sg:address":"Shop 2, 41 Pinjarra Rd",
    "sg:city":"Mandurah",
    "sg:classifiers":[
        {
            "category":"Personal",
            "subcategory":"Tattoo Parlor",
            "type":"Services"
        }
    ],
    "sg:phone":"+61 8 9534 7344",
    "sg:postcode":"6210",
    "sg:province":"WA",
    "sg:tags":[
        "tattooing"
    ],
    "wof:name":"Cold Steel Body Piercing & Accessories",
    "wof:placetype":"venue"
},
  "geometry": {"coordinates":[115.772682,-32.546875],"type":"Point"}
}