{
  "type": "Feature",
  "properties": {
    "addr:full":"110 Illawarra Cres (cnr Marangaroo Drv) Ballajura WA 6066",
    "addr:housenumber":"110",
    "addr:postcode":"6066",
    "addr:street":"Illawarra Cres Cnr Marangaroo Drv",
    "iso:country":"AU",
    "sg:address":"110 Illawarra Cres (cnr Marangaroo Drv)",
    "sg:city":"Ballajura",
    "sg:classifiers":[
        {
            "category":"Retail",
            "subcategory":"Veterinary Services",
            "type":"Services"
        }
    ],
    "sg:phone":"+61 8 9249 6666",
    "sg:postcode":"6066",
    "sg:province":"WA",
    "sg:tags":[
        "surgeon"
    ],
    "wof:name":"Ballajura Veterinary Hospital",
    "wof:placetype":"venue"
},
  "geometry": {"coordinates":[116.133247376,-32.0911560059],"type":"Point"}
}