{
  "type": "Feature",
  "properties": {
    "addr:full":"82 Station St Fairfield VIC 3078",
    "addr:housenumber":"82",
    "addr:postcode":"3078",
    "addr:street":"Station St",
    "iso:country":"AU",
    "sg:address":"82 Station St",
    "sg:city":"Fairfield",
    "sg:classifiers":[
        {
            "category":"Shopping",
            "subcategory":"Gifts & Souvenirs",
            "type":"Retail Goods"
        }
    ],
    "sg:phone":"+61 3 9482 1771",
    "sg:postcode":"3078",
    "sg:province":"VIC",
    "sg:tags":[
        "wrapping"
    ],
    "wof:name":"Roz Standley Designer Bows",
    "wof:placetype":"venue"
},
  "geometry": {"coordinates":[145.01805114699999,-37.778503418],"type":"Point"}
}