{
  "type": "Feature",
  "properties": {
    "addr:full":"62 Pacific Hwy Lake Munmorah NSW 2259",
    "addr:housenumber":"62",
    "addr:postcode":"2259",
    "addr:street":"Pacific Hwy",
    "iso:country":"AU",
    "sg:address":"62 Pacific Hwy",
    "sg:city":"Lake Munmorah",
    "sg:classifiers":[
        {
            "category":"Farming",
            "subcategory":"Farm",
            "type":"Manufacturing & Wholesale Goods"
        }
    ],
    "sg:phone":"+61 2 4399 1500",
    "sg:postcode":"2259",
    "sg:province":"NSW",
    "sg:tags":[
        "farmer"
    ],
    "wof:name":"Pacific Hydroponics Pty Ltd",
    "wof:placetype":"venue"
},
  "geometry": {"coordinates":[151.56605529800001,-33.1901245117],"type":"Point"}
}