{
  "type": "Feature",
  "properties": {
    "addr:full":"113 Smallwood Rd Glenorie NSW 2157",
    "addr:housenumber":"113",
    "addr:postcode":"2157",
    "addr:street":"Smallwood Rd",
    "iso:country":"AU",
    "sg:address":"113 Smallwood Rd",
    "sg:city":"Glenorie",
    "sg:classifiers":[
        {
            "category":"Manufacturing",
            "subcategory":"Building Materials",
            "type":"Manufacturing & Wholesale Goods"
        }
    ],
    "sg:phone":"+61 2 9652 1783",
    "sg:postcode":"2157",
    "sg:province":"NSW",
    "sg:tags":[
        "stone",
        "product",
        "supply"
    ],
    "sg:website":"http://www.sandstonesales.com.au",
    "wof:name":"Sandstone Sales",
    "wof:placetype":"venue"
},
  "geometry": {"coordinates":[150.961791992,-33.5654754639],"type":"Point"}
}