{
  "type": "Feature",
  "properties": {
    "addr:full":"8 Tincogan St Mullumbimby NSW 2482",
    "addr:housenumber":"8",
    "addr:postcode":"2482",
    "addr:street":"Tincogan St",
    "iso:country":"AU",
    "sg:address":"8 Tincogan St",
    "sg:city":"Mullumbimby",
    "sg:classifiers":[
        {
            "category":"Social Services",
            "subcategory":"Child Care",
            "type":"Services"
        }
    ],
    "sg:phone":"+61 2 6684 2164",
    "sg:postcode":"2482",
    "sg:province":"NSW",
    "wof:name":"Cobbers Child Care Centre",
    "wof:placetype":"venue"
},
  "geometry": {"coordinates":[153.49838256800001,-28.5513095856],"type":"Point"}
}