{
  "type": "Feature",
  "properties": {
    "iso:country":"AU",
    "sg:address":"227 A Annangrove Rd",
    "sg:city":"Annangrove",
    "sg:classifiers":[
        {
            "category":"Health Services",
            "subcategory":"Doctor",
            "type":"Services"
        }
    ],
    "sg:phone":"+61 2 9679 2107",
    "sg:postcode":"2156",
    "sg:province":"NSW",
    "sg:tags":[
        "podiatrist"
    ],
    "wof:name":"Hills Foot Clinic",
    "wof:placetype":"venue"
},
  "geometry": {"coordinates":[150.94630432100001,-33.661113739],"type":"Point"}
}