{
  "type": "Feature",
  "properties": {
    "iso:country":"AU",
    "sg:address":"McKenzies Rd",
    "sg:city":"Bass",
    "sg:classifiers":[
        {
            "category":"Farming",
            "subcategory":"Farm",
            "type":"Manufacturing & Wholesale Goods"
        }
    ],
    "sg:phone":"+61 3 5678 2351",
    "sg:postcode":"3991",
    "sg:province":"VIC",
    "sg:tags":[
        "farmer"
    ],
    "wof:name":"Couch K R",
    "wof:placetype":"venue"
},
  "geometry": {"coordinates":[145.500351,-38.455566],"type":"Point"}
}