{
  "type": "Feature",
  "properties": {
    "addr:full":"18 Moonbi St Brendale QLD 4500",
    "addr:housenumber":"18",
    "addr:postcode":"4500",
    "addr:street":"Moonbi St",
    "iso:country":"AU",
    "sg:address":"18 Moonbi St",
    "sg:city":"Brendale",
    "sg:classifiers":[
        {
            "category":"Banks & Credit Unions",
            "subcategory":"Financial Services",
            "type":"Services"
        }
    ],
    "sg:phone":"+61 7 3881 0037",
    "sg:postcode":"4500",
    "sg:province":"QLD",
    "sg:tags":[
        "wholesaler",
        "pencil",
        "pen",
        "mfrs"
    ],
    "wof:name":"Brighter Ideas Pty Ltd",
    "wof:placetype":"venue"
},
  "geometry": {"coordinates":[152.98939514200001,-27.3240623474],"type":"Point"}
}