{
  "type": "Feature",
  "properties": {
    "addr:full":"Cairns Private Hospital 199 Abbott St Cairns QLD 4870",
    "addr:housenumber":"199",
    "addr:postcode":"4870",
    "addr:street":"Abbott St",
    "iso:country":"AU",
    "sg:address":"Cairns Private Hospital 199 Abbott St",
    "sg:city":"Cairns",
    "sg:classifiers":[
        {
            "category":"Health Services",
            "subcategory":"Doctor",
            "type":"Services"
        }
    ],
    "sg:phone":"+61 7 4052 5111",
    "sg:postcode":"4870",
    "sg:province":"QLD",
    "sg:tags":[
        "medical",
        "practitioner"
    ],
    "wof:name":"Splatt D",
    "wof:placetype":"venue"
},
  "geometry": {"coordinates":[145.7787323,-16.9236679077],"type":"Point"}
}