{
  "type": "Feature",
  "properties": {
    "iso:country":"AU",
    "sg:address":"168 Cavendish Rd",
    "sg:city":"Coorparoo",
    "sg:classifiers":[
        {
            "category":"Food & Beverages",
            "subcategory":"Specialty",
            "type":"Retail Goods"
        }
    ],
    "sg:phone":"+61 7 3397 9276",
    "sg:postcode":"4151",
    "sg:province":"QLD",
    "sg:tags":[
        "product",
        "health"
    ],
    "wof:name":"All About Health & Body",
    "wof:placetype":"venue"
},
  "geometry": {"coordinates":[153.05894470199999,-27.4938049316],"type":"Point"}
}