{
  "type": "Feature",
  "properties": {
    "addr:full":"22 Churchill St Dalby QLD 4405",
    "addr:housenumber":"22",
    "addr:postcode":"4405",
    "addr:street":"Churchill St",
    "iso:country":"AU",
    "sg:address":"22 Churchill St",
    "sg:city":"Dalby",
    "sg:classifiers":[
        {
            "category":"Utilities",
            "subcategory":"Electric",
            "type":"Services"
        }
    ],
    "sg:phone":"+61 7 4662 3435",
    "sg:postcode":"4405",
    "sg:province":"QLD",
    "sg:tags":[
        "electrical",
        "contractor"
    ],
    "wof:name":"Condamine Electric Company",
    "wof:placetype":"venue"
},
  "geometry": {"coordinates":[151.242919922,-27.1827106476],"type":"Point"}
}