{
  "type": "Feature",
  "properties": {
    "iso:country":"AU",
    "sg:address":"49 Hope St",
    "sg:city":"North Beach",
    "sg:classifiers":[
        {
            "category":"Home & Garden",
            "subcategory":"Building Materials",
            "type":"Retail Goods"
        }
    ],
    "sg:phone":"+61 417 900 742",
    "sg:postcode":"6020",
    "sg:province":"WA",
    "sg:tags":[
        "concrete",
        "panel",
        "pre-cast"
    ],
    "wof:name":"ALLWEST BUILDING CONTRACTORS",
    "wof:placetype":"venue"
},
  "geometry": {"coordinates":[115.757949829,-31.853471756],"type":"Point"}
}