{
  "type": "Feature",
  "properties": {
    "iso:country":"AU",
    "sg:address":"520 Kessels Rd",
    "sg:city":"MacGregor",
    "sg:classifiers":[
        {
            "category":"Professional",
            "type":"Services"
        }
    ],
    "sg:phone":"+61 7 3343 2499",
    "sg:postcode":"4109",
    "sg:province":"QLD",
    "sg:tags":[
        "auctioneer"
    ],
    "wof:name":"Pacific Auctions Pty Ltd",
    "wof:placetype":"venue"
},
  "geometry": {"coordinates":[153.06953430199999,-27.561296463],"type":"Point"}
}