{
  "type": "Feature",
  "properties": {
    "iso:country":"AU",
    "sg:address":"6 Coleridge Crt",
    "sg:city":"Templestowe",
    "sg:classifiers":[
        {
            "category":"Government",
            "subcategory":"Court House",
            "type":"Public Place"
        }
    ],
    "sg:phone":"+61 3 9842 7786",
    "sg:postcode":"3106",
    "sg:province":"VIC",
    "sg:tags":[
        "personal",
        "marriage",
        "family",
        "counselling"
    ],
    "wof:name":"Frank Luzza",
    "wof:placetype":"venue"
},
  "geometry": {"coordinates":[145.157913208,-37.7675628662],"type":"Point"}
}