{
  "type": "Feature",
  "properties": {
    "addr:full":"17 William St Botany NSW 2019",
    "addr:housenumber":"17",
    "addr:postcode":"2019",
    "addr:street":"William St",
    "iso:country":"AU",
    "sg:address":"17 William St",
    "sg:city":"Botany",
    "sg:classifiers":[
        {
            "category":"Professional",
            "subcategory":"Employment Agencies",
            "type":"Services"
        }
    ],
    "sg:phone":"+61 407 332 036",
    "sg:postcode":"2019",
    "sg:province":"NSW",
    "sg:tags":[
        "entertainer",
        "agent"
    ],
    "wof:name":"Williams James",
    "wof:placetype":"venue"
},
  "geometry": {"coordinates":[151.20477294899999,-33.9464187622],"type":"Point"}
}