{
  "type": "Feature",
  "properties": {
    "iso:country":"AU",
    "sg:address":"Napier St",
    "sg:city":"Renown Park",
    "sg:classifiers":[
        {
            "category":"Education",
            "subcategory":"School",
            "type":"Public Place"
        }
    ],
    "sg:phone":"+61 8 8346 3701",
    "sg:postcode":"5008",
    "sg:province":"SA",
    "sg:tags":[
        "state",
        "except",
        "nsw"
    ],
    "wof:name":"Brompton Primary",
    "wof:placetype":"venue"
},
  "geometry": {"coordinates":[138.58163500000001,-34.894779],"type":"Point"}
}