{
  "type": "Feature",
  "properties": {
    "addr:full":"72 Daniel Ave Globe Derby Park SA 5110",
    "addr:housenumber":"72",
    "addr:postcode":"5110",
    "addr:street":"Daniel Ave",
    "iso:country":"AU",
    "sg:address":"72 Daniel Ave",
    "sg:city":"Globe Derby Park",
    "sg:classifiers":[
        {
            "category":"Building & Trades",
            "subcategory":"Pest Control",
            "type":"Services"
        }
    ],
    "sg:phone":"+61 412 834 165",
    "sg:postcode":"5110",
    "sg:province":"SA",
    "sg:tags":[
        "horse",
        "transport"
    ],
    "wof:name":"Hanns Horse Transport",
    "wof:placetype":"venue"
},
  "geometry": {"coordinates":[138.58863830600001,-34.7895050049],"type":"Point"}
}