{
  "type": "Feature",
  "properties": {
    "iso:country":"AU",
    "sg:address":"Medical Suite 8, Mater Hospital, Jessie St",
    "sg:city":"Rockhampton",
    "sg:classifiers":[
        {
            "category":"Health Services",
            "subcategory":"Doctor",
            "type":"Services"
        }
    ],
    "sg:phone":"+61 7 4923 7630",
    "sg:postcode":"4700",
    "sg:province":"QLD",
    "sg:tags":[
        "medical",
        "practitioner"
    ],
    "wof:name":"Kitchen David",
    "wof:placetype":"venue"
},
  "geometry": {"coordinates":[150.49673461899999,-23.4007301331],"type":"Point"}
}