{
  "type": "Feature",
  "properties": {
    "addr:full":"665 Gardeners Rd Mascot NSW 2020",
    "addr:housenumber":"665",
    "addr:postcode":"2020",
    "addr:street":"Gardeners Rd",
    "iso:country":"AU",
    "sg:address":"665 Gardeners Rd",
    "sg:city":"Mascot",
    "sg:classifiers":[
        {
            "category":"Wholesale",
            "subcategory":"Toys & Hobbies",
            "type":"Manufacturing & Wholesale Goods"
        }
    ],
    "sg:phone":"+61 2 9700 9144",
    "sg:postcode":"2020",
    "sg:province":"NSW",
    "wof:name":"Teddy & Friends",
    "wof:placetype":"venue"
},
  "geometry": {"coordinates":[151.18661499000001,-33.9201583862],"type":"Point"}
}