{
  "type": "Feature",
  "properties": {
    "iso:country":"AU",
    "sg:address":"285 Stud Rd",
    "sg:city":"Wantirna",
    "sg:classifiers":[
        {
            "category":"Health Services",
            "subcategory":"Health Practitioner",
            "type":"Services"
        }
    ],
    "sg:phone":"+61 3 9800 3969",
    "sg:postcode":"3152",
    "sg:province":"VIC",
    "sg:tags":[
        "naturopath"
    ],
    "wof:name":"Knox Chinese Healing & Myotherapy",
    "wof:placetype":"venue"
},
  "geometry": {"coordinates":[145.238372803,-37.8636245728],"type":"Point"}
}