{
  "type": "Feature",
  "properties": {
    "iso:country":"AU",
    "sg:address":"943 Old Northern Rd",
    "sg:city":"Dural",
    "sg:classifiers":[
        {
            "category":"Personal",
            "subcategory":"Beauty Salon",
            "type":"Services"
        }
    ],
    "sg:phone":"+61 2 9651 2929",
    "sg:postcode":"2158",
    "sg:province":"NSW",
    "sg:tags":[
        "hairdresser"
    ],
    "wof:name":"Angelas Hair Upstairs",
    "wof:placetype":"venue"
},
  "geometry": {"coordinates":[151.02696227999999,-33.6773910522],"type":"Point"}
}