{
  "type": "Feature",
  "properties": {
    "addr:full":"39 Regis St Salisbury QLD 4107",
    "addr:housenumber":"39",
    "addr:postcode":"4107",
    "addr:street":"Regis St",
    "iso:country":"AU",
    "sg:address":"39 Regis St",
    "sg:city":"Salisbury",
    "sg:classifiers":[
        {
            "category":"Communications",
            "type":"Services"
        }
    ],
    "sg:phone":"+61 7 3277 8816",
    "sg:postcode":"4107",
    "sg:province":"QLD",
    "sg:tags":[
        "antenna"
    ],
    "wof:name":"Universal TV Antennae Service",
    "wof:placetype":"venue"
},
  "geometry": {"coordinates":[153.033004761,-27.5570087433],"type":"Point"}
}