{
  "type": "Feature",
  "properties": {
    "iso:country":"AU",
    "sg:address":"151 Ingham Rd",
    "sg:city":"West End (Townsville)",
    "sg:classifiers":[
        {
            "category":"Military Area",
            "subcategory":"Air Force Base",
            "type":"Public Place"
        }
    ],
    "sg:phone":"+61 7 4721 5021",
    "sg:postcode":"4810",
    "sg:province":"QLD",
    "sg:tags":[
        "fibre",
        "optic"
    ],
    "wof:name":"Allied Technologies Australia Pty Limited",
    "wof:placetype":"venue"
},
  "geometry": {"coordinates":[146.792114,-19.267185],"type":"Point"}
}