{
  "type": "Feature",
  "properties": {
    "addr:full":"18 Sandilands St Mallanganee NSW 2469",
    "addr:housenumber":"18",
    "addr:postcode":"2469",
    "addr:street":"Sandilands St",
    "iso:country":"AU",
    "sg:address":"18 Sandilands St",
    "sg:city":"Mallanganee",
    "sg:classifiers":[
        {
            "category":"Autos & Motor Vehicles",
            "subcategory":"Automobile Sales",
            "type":"Retail Goods"
        }
    ],
    "sg:phone":"+61 2 6664 5294",
    "sg:postcode":"2469",
    "sg:province":"NSW",
    "sg:tags":[
        "equipment",
        "trailer"
    ],
    "wof:name":"Russler Floats & Trailers",
    "wof:placetype":"venue"
},
  "geometry": {"coordinates":[152.716796875,-28.9063663483],"type":"Point"}
}