{
  "type": "Feature",
  "properties": {
    "addr:full":"47 Oaklands Rd Hazelbrook NSW 2779",
    "addr:housenumber":"47",
    "addr:postcode":"2779",
    "addr:street":"Oaklands Rd",
    "iso:country":"AU",
    "sg:address":"47 Oaklands Rd",
    "sg:city":"Hazelbrook",
    "sg:classifiers":[
        {
            "category":"Utilities",
            "subcategory":"Refuse",
            "type":"Services"
        }
    ],
    "sg:phone":"+61 2 4758 6986",
    "sg:postcode":"2779",
    "sg:province":"NSW",
    "sg:tags":[
        "remover",
        "rubbish"
    ],
    "wof:name":"The Little Tip Truck",
    "wof:placetype":"venue"
},
  "geometry": {"coordinates":[150.45277404800001,-33.7163963318],"type":"Point"}
}