{
  "type": "Feature",
  "properties": {
    "addr:full":"29 Cliff St South Yarra VIC 3141",
    "addr:housenumber":"29",
    "addr:postcode":"3141",
    "addr:street":"Cliff St",
    "iso:country":"AU",
    "sg:address":"29 Cliff St",
    "sg:city":"South Yarra",
    "sg:classifiers":[
        {
            "category":"Health Services",
            "subcategory":"Health Practitioner",
            "type":"Services"
        }
    ],
    "sg:phone":"+61 3 9826 5452",
    "sg:postcode":"3141",
    "sg:province":"VIC",
    "sg:tags":[
        "psychologist"
    ],
    "wof:name":"Midalia Linda",
    "wof:placetype":"venue"
},
  "geometry": {"coordinates":[144.99336242699999,-37.8434524536],"type":"Point"}
}