{
  "type": "Feature",
  "properties": {
    "addr:full":"14 Hasp St Seventeen Mile Rocks QLD 4073",
    "addr:housenumber":"14",
    "addr:postcode":"4073",
    "addr:street":"Hasp St",
    "iso:country":"AU",
    "sg:address":"14 Hasp St",
    "sg:city":"Seventeen Mile Rocks",
    "sg:classifiers":[
        {
            "category":"Building & Trades",
            "subcategory":"Construction",
            "type":"Services"
        }
    ],
    "sg:phone":"+61 7 3279 4011",
    "sg:postcode":"4073",
    "sg:province":"QLD",
    "sg:tags":[
        "fencing",
        "contractor"
    ],
    "wof:name":"Bruce Reid",
    "wof:placetype":"venue"
},
  "geometry": {"coordinates":[152.95521545400001,-27.5445270538],"type":"Point"}
}