{
  "type": "Feature",
  "properties": {
    "iso:country":"AU",
    "sg:address":"Unit 3 150 Frederick St",
    "sg:city":"Welland",
    "sg:classifiers":[
        {
            "category":"Home & Garden",
            "subcategory":"Home Furnishings",
            "type":"Retail Goods"
        }
    ],
    "sg:phone":"+61 8 8340 0272",
    "sg:postcode":"5007",
    "sg:province":"SA",
    "sg:tags":[
        "storage",
        "rack",
        "wine"
    ],
    "wof:name":"Trellis Wineracks",
    "wof:placetype":"venue"
},
  "geometry": {"coordinates":[138.55799865700001,-34.9095535278],"type":"Point"}
}