{
  "type": "Feature",
  "properties": {
    "iso:country":"AU",
    "sg:address":"Floor 5/ 18 Mt Gravatt-Capalaba Rd",
    "sg:city":"Upper Mt Gravatt",
    "sg:classifiers":[
        {
            "category":"Health Services",
            "subcategory":"Health Practitioner",
            "type":"Services"
        }
    ],
    "sg:phone":"+61 7 3343 1677",
    "sg:postcode":"4122",
    "sg:province":"QLD",
    "sg:tags":[
        "psychologist"
    ],
    "wof:name":"Arsenieva Lepa",
    "wof:placetype":"venue"
},
  "geometry": {"coordinates":[153.082229614,-27.5593070984],"type":"Point"}
}