{
  "type": "Feature",
  "properties": {
    "addr:full":"Lvl1/ 72 Barrier St Fyshwick ACT 2609",
    "addr:postcode":"2609",
    "addr:street":"Barrier St",
    "iso:country":"AU",
    "sg:address":"Lvl1/ 72 Barrier St",
    "sg:city":"Fyshwick",
    "sg:classifiers":[
        {
            "category":"Personal",
            "subcategory":"Adult",
            "type":"Services"
        }
    ],
    "sg:phone":"+61 2 6280 6006",
    "sg:postcode":"2609",
    "sg:province":"ACT",
    "sg:tags":[
        "vic",
        "except",
        "state",
        "escort",
        "social",
        "qld"
    ],
    "wof:name":"Tiffanys Palace",
    "wof:placetype":"venue"
},
  "geometry": {"coordinates":[149.17137145999999,-35.3280181885],"type":"Point"}
}