{
  "type": "Feature",
  "properties": {
    "addr:full":"7 Mohr St Tullamarine VIC 3043",
    "addr:housenumber":"7",
    "addr:postcode":"3043",
    "addr:street":"Mohr St",
    "iso:country":"AU",
    "sg:address":"7 Mohr St",
    "sg:city":"Tullamarine",
    "sg:classifiers":[
        {
            "category":"Government",
            "subcategory":"Department Of Motor Vehicles",
            "type":"Public Place"
        }
    ],
    "sg:phone":"+61 3 9334 5881",
    "sg:postcode":"3043",
    "sg:province":"VIC",
    "sg:tags":[
        "wholesaler",
        "mfrs",
        "accessory"
    ],
    "wof:name":"Custom Car Mats of Australia Pty Ltd",
    "wof:placetype":"venue"
},
  "geometry": {"coordinates":[144.86425781200001,-37.7111091614],"type":"Point"}
}