{
  "type": "Feature",
  "properties": {
    "iso:country":"AU",
    "sg:address":"161 Marrickville Rd",
    "sg:city":"Marrickville",
    "sg:classifiers":[
        {
            "category":"Real Estate",
            "subcategory":"Real Estate Agent",
            "type":"Services"
        }
    ],
    "sg:phone":"+61 2 9569 4999",
    "sg:postcode":"2204",
    "sg:province":"NSW",
    "wof:name":"Nelson Peter Real Estate",
    "wof:placetype":"venue"
},
  "geometry": {"coordinates":[151.158936,-33.911583],"type":"Point"}
}