{
  "type": "Feature",
  "properties": {
    "addr:full":"89 Gipps St Broadway QLD 4006",
    "addr:housenumber":"89",
    "addr:postcode":"4006",
    "addr:street":"Gipps St",
    "iso:country":"AU",
    "sg:address":"89 Gipps St",
    "sg:city":"Broadway",
    "sg:classifiers":[
        {
            "category":"Professional",
            "subcategory":"Computer Services",
            "type":"Services"
        }
    ],
    "sg:phone":"+61 7 3252 3225",
    "sg:postcode":"4006",
    "sg:province":"QLD",
    "sg:tags":[
        "package",
        "software"
    ],
    "wof:name":"Micronet Systems",
    "wof:placetype":"venue"
},
  "geometry": {"coordinates":[153.032470703,-27.4584465027],"type":"Point"}
}