{
  "type": "Feature",
  "properties": {
    "iso:country":"AU",
    "sg:address":"Shop 2, 81 Minjungbal Drv",
    "sg:city":"Tweed Heads South",
    "sg:classifiers":[
        {
            "category":"Personal",
            "subcategory":"Beauty Salon",
            "type":"Services"
        }
    ],
    "sg:phone":"+61 7 5524 8233",
    "sg:postcode":"2486",
    "sg:province":"NSW",
    "sg:tags":[
        "hairdresser"
    ],
    "wof:name":"Absolutely Beautiful Day Spa Retreat",
    "wof:placetype":"venue"
},
  "geometry": {"coordinates":[153.543701172,-28.1990661621],"type":"Point"}
}