{
  "type": "Feature",
  "properties": {
    "addr:full":"75 Mullens St Balmain NSW 2041",
    "addr:housenumber":"75",
    "addr:postcode":"2041",
    "addr:street":"Mullens St",
    "iso:country":"AU",
    "sg:address":"75 Mullens St",
    "sg:city":"Balmain",
    "sg:classifiers":[
        {
            "category":"Health Services",
            "subcategory":"Doctor",
            "type":"Services"
        }
    ],
    "sg:phone":"+61 2 9247 3557",
    "sg:postcode":"2041",
    "sg:province":"NSW",
    "sg:tags":[
        "medical",
        "practitioner"
    ],
    "wof:name":"Duke Peter S Dr",
    "wof:placetype":"venue"
},
  "geometry": {"coordinates":[151.17652899999999,-33.861256],"type":"Point"}
}