{
  "type": "Feature",
  "properties": {
    "addr:full":"232 Pacific Hwy Hornsby NSW 2077",
    "addr:housenumber":"232",
    "addr:postcode":"2077",
    "addr:street":"Pacific Hwy",
    "iso:country":"AU",
    "sg:address":"232 Pacific Hwy",
    "sg:city":"Hornsby",
    "sg:classifiers":[
        {
            "category":"Personal",
            "subcategory":"Beauty Salon",
            "type":"Services"
        }
    ],
    "sg:phone":"+61 2 9476 5853",
    "sg:postcode":"2077",
    "sg:province":"NSW",
    "sg:tags":[
        "hairdresser"
    ],
    "wof:name":"Edges Hairdressing",
    "wof:placetype":"venue"
},
  "geometry": {"coordinates":[151.09777832,-33.6981735229],"type":"Point"}
}