{
  "type": "Feature",
  "properties": {
    "addr:full":"80 Taggerty Crs Meadow Heights VIC 3048",
    "addr:housenumber":"80",
    "addr:postcode":"3048",
    "addr:street":"Taggerty Crs",
    "iso:country":"AU",
    "sg:address":"80 Taggerty Crs",
    "sg:city":"Meadow Heights",
    "sg:classifiers":[
        {
            "category":"Retail",
            "subcategory":"Veterinary Services",
            "type":"Services"
        }
    ],
    "sg:phone":"+61 3 9309 3199",
    "sg:postcode":"3048",
    "sg:province":"VIC",
    "sg:tags":[
        "surgeon"
    ],
    "wof:name":"Meadow Heights Veterinary Clinic",
    "wof:placetype":"venue"
},
  "geometry": {"coordinates":[144.825165,-37.717869],"type":"Point"}
}