{
  "type": "Feature",
  "properties": {
    "addr:full":"Unit 1/ 10 Carrick Drv Tullamarine VIC 3043",
    "addr:housenumber":"10",
    "addr:postcode":"3043",
    "addr:street":"Carrick Drv",
    "iso:country":"AU",
    "sg:address":"Unit 1/ 10 Carrick Drv",
    "sg:city":"Tullamarine",
    "sg:classifiers":[
        {
            "category":"Sports & Exercise",
            "subcategory":"Gym",
            "type":"Entertainment"
        }
    ],
    "sg:phone":"+61 3 9338 5640",
    "sg:postcode":"3043",
    "sg:province":"VIC",
    "sg:tags":[
        "personal",
        "trainer",
        "fitness"
    ],
    "wof:name":"Fernwood Women's Health Clubs",
    "wof:placetype":"venue"
},
  "geometry": {"coordinates":[144.88406372099999,-37.7016296387],"type":"Point"}
}