{
  "type": "Feature",
  "properties": {
    "iso:country":"AU",
    "sg:address":"33 Dunbar St",
    "sg:city":"Fraser",
    "sg:classifiers":[
        {
            "category":"Banks & Credit Unions",
            "subcategory":"Investment Brokerage",
            "type":"Services"
        }
    ],
    "sg:phone":"+61 2 6259 2276",
    "sg:postcode":"2615",
    "sg:province":"ACT",
    "sg:tags":[
        "debt",
        "collection"
    ],
    "wof:name":"Maxwell Mercantile Services",
    "wof:placetype":"venue"
},
  "geometry": {"coordinates":[149.03704834000001,-35.1887702942],"type":"Point"}
}