{
  "type": "Feature",
  "properties": {
    "addr:full":"Racecourse Rd Goondiwindi QLD 4390",
    "addr:postcode":"4390",
    "addr:street":"Racecourse Rd",
    "iso:country":"AU",
    "sg:address":"Racecourse Rd",
    "sg:city":"Goondiwindi",
    "sg:classifiers":[
        {
            "category":"Utilities",
            "subcategory":"Telephone",
            "type":"Services"
        }
    ],
    "sg:phone":"+61 7 4671 2353",
    "sg:postcode":"4390",
    "sg:province":"QLD",
    "sg:tags":[
        "equipment",
        "system"
    ],
    "wof:name":"Border T.R.C. Pty Ltd",
    "wof:placetype":"venue"
},
  "geometry": {"coordinates":[150.31414794899999,-28.5372314453],"type":"Point"}
}