{
  "type": "Feature",
  "properties": {
    "addr:full":"44 Gladstone St Toowoomba QLD 4350",
    "addr:housenumber":"44",
    "addr:postcode":"4350",
    "addr:street":"Gladstone St",
    "iso:country":"AU",
    "sg:address":"44 Gladstone St",
    "sg:city":"Toowoomba",
    "sg:classifiers":[
        {
            "category":"Social Services",
            "subcategory":"Child Care",
            "type":"Services"
        }
    ],
    "sg:phone":"+61 7 4632 5284",
    "sg:postcode":"4350",
    "sg:province":"QLD",
    "wof:name":"Kath Dickson Occasional Care Centre",
    "wof:placetype":"venue"
},
  "geometry": {"coordinates":[151.94012499999999,-27.549469],"type":"Point"}
}