{
  "type": "Feature",
  "properties": {
    "addr:full":"Shop 1, 414 Bronte Rd Bronte NSW 2024",
    "addr:housenumber":"shop 1 414",
    "addr:postcode":"2024",
    "addr:street":"Bronte Rd",
    "iso:country":"AU",
    "sg:address":"Shop 1, 414 Bronte Rd",
    "sg:city":"Bronte",
    "sg:classifiers":[
        {
            "category":"Personal",
            "subcategory":"Beauty Salon",
            "type":"Services"
        }
    ],
    "sg:phone":"+61 2 9389 7356",
    "sg:postcode":"2024",
    "sg:province":"NSW",
    "sg:tags":[
        "hairdresser"
    ],
    "wof:name":"Louise of Bronte",
    "wof:placetype":"venue"
},
  "geometry": {"coordinates":[151.2603302,-33.9027862549],"type":"Point"}
}