{
  "type": "Feature",
  "properties": {
    "addr:full":"29a Langhorne St Dandenong VIC 3175",
    "addr:housenumber":"29a",
    "addr:postcode":"3175",
    "addr:street":"Langhorne St",
    "iso:country":"AU",
    "sg:address":"29a Langhorne St",
    "sg:city":"Dandenong",
    "sg:classifiers":[
        {
            "category":"Retail",
            "subcategory":"Laundry & Dry Cleaning",
            "type":"Services"
        }
    ],
    "sg:phone":"+61 3 9792 1066",
    "sg:postcode":"3175",
    "sg:province":"VIC",
    "wof:name":"Dandenong Laundry & Dry Cleaners Pty Ltd",
    "wof:placetype":"venue"
},
  "geometry": {"coordinates":[145.21585082999999,-37.9880027771],"type":"Point"}
}