{
  "type": "Feature",
  "properties": {
    "addr:full":"25 Astrolabe St Red Hill ACT 2603",
    "addr:housenumber":"25",
    "addr:postcode":"2603",
    "addr:street":"Astrolabe St",
    "iso:country":"AU",
    "sg:address":"25 Astrolabe St",
    "sg:city":"Red Hill",
    "sg:classifiers":[
        {
            "category":"Social Services",
            "subcategory":"Child Care",
            "type":"Services"
        }
    ],
    "sg:phone":"+61 2 6232 6433",
    "sg:postcode":"2603",
    "sg:province":"ACT",
    "wof:name":"Red Hill Childcare Centre",
    "wof:placetype":"venue"
},
  "geometry": {"coordinates":[149.13287353499999,-35.3400840759],"type":"Point"}
}