{
  "type": "Feature",
  "properties": {
    "addr:full":"26 Smith Rd Noosaville QLD 4566",
    "addr:housenumber":"26",
    "addr:postcode":"4566",
    "addr:street":"Smith Rd",
    "iso:country":"AU",
    "sg:address":"26 Smith Rd",
    "sg:city":"Noosaville",
    "sg:classifiers":[
        {
            "category":"Retail",
            "subcategory":"Auto Rental",
            "type":"Services"
        }
    ],
    "sg:phone":"+61 416 275 125",
    "sg:postcode":"4566",
    "sg:province":"QLD",
    "sg:tags":[
        "chauffeur",
        "car",
        "hire",
        "driven",
        "limousine"
    ],
    "wof:name":"Abracadabra Limousines",
    "wof:placetype":"venue"
},
  "geometry": {"coordinates":[153.05047607399999,-26.4029693604],"type":"Point"}
}