{
  "type": "Feature",
  "properties": {
    "addr:full":"58 Claudare St Collaroy Plateau NSW 2097",
    "addr:housenumber":"58",
    "addr:postcode":"2097",
    "addr:street":"Claudare St",
    "iso:country":"AU",
    "sg:address":"58 Claudare St",
    "sg:city":"Collaroy Plateau",
    "sg:classifiers":[
        {
            "category":"Utilities",
            "subcategory":"Electric",
            "type":"Services"
        }
    ],
    "sg:phone":"+61 2 9971 5024",
    "sg:postcode":"2097",
    "sg:province":"NSW",
    "sg:tags":[
        "electrical",
        "contractor"
    ],
    "wof:name":"Northside Electric Co",
    "wof:placetype":"venue"
},
  "geometry": {"coordinates":[151.28855895999999,-33.7284164429],"type":"Point"}
}