{
  "type": "Feature",
  "properties": {
    "addr:full":"Shop 5a Glenorchy Cinema Complex Glenorchy TAS 7010",
    "addr:housenumber":"shop 5a",
    "addr:postcode":"7010",
    "iso:country":"AU",
    "sg:address":"Shop 5a Glenorchy Cinema Complex",
    "sg:city":"Glenorchy",
    "sg:classifiers":[
        {
            "category":"Military Area",
            "subcategory":"Air Force Base",
            "type":"Public Place"
        }
    ],
    "sg:phone":"+61 3 6272 6668",
    "sg:postcode":"7010",
    "sg:province":"TAS",
    "sg:tags":[
        "men's",
        "tailor"
    ],
    "wof:name":"Glenorchy Clothing Alterations & Repairs",
    "wof:placetype":"venue"
},
  "geometry": {"coordinates":[147.279754639,-42.8336982727],"type":"Point"}
}