{
  "type": "Feature",
  "properties": {
    "addr:full":"Constellation Drv Ocean Reef WA 6027",
    "addr:postcode":"6027",
    "addr:street":"Constellation Drv",
    "iso:country":"AU",
    "sg:address":"Constellation Drv",
    "sg:city":"Ocean Reef",
    "sg:classifiers":[
        {
            "category":"Health Services",
            "subcategory":"Doctor",
            "type":"Services"
        }
    ],
    "sg:phone":"+61 8 9300 4599",
    "sg:postcode":"6027",
    "sg:province":"WA",
    "sg:tags":[
        "medical",
        "practitioner"
    ],
    "wof:name":"Russell-Smith Belinda Dr",
    "wof:placetype":"venue"
},
  "geometry": {"coordinates":[115.732978821,-31.7506504059],"type":"Point"}
}