{
  "type": "Feature",
  "properties": {
    "addr:full":"Industrial Drv Somerville VIC 3912",
    "addr:postcode":"3912",
    "addr:street":"Industrial Drv",
    "iso:country":"AU",
    "sg:address":"Industrial Drv",
    "sg:city":"Somerville",
    "sg:classifiers":[
        {
            "category":"Utilities",
            "subcategory":"Refuse",
            "type":"Services"
        }
    ],
    "sg:phone":"+61 3 5977 8903",
    "sg:postcode":"3912",
    "sg:province":"VIC",
    "sg:tags":[
        "remover",
        "rubbish"
    ],
    "wof:name":"Better Bin Hire",
    "wof:placetype":"venue"
},
  "geometry": {"coordinates":[145.180511475,-38.2195701599],"type":"Point"}
}