{
  "type": "Feature",
  "properties": {
    "iso:country":"AU",
    "sg:address":"17 Westgate St",
    "sg:city":"Pascoe Vale South",
    "sg:classifiers":[
        {
            "category":"Professional",
            "subcategory":"Employment Agencies",
            "type":"Services"
        }
    ],
    "sg:phone":"+61 3 9354 3563",
    "sg:postcode":"3044",
    "sg:province":"VIC",
    "sg:tags":[
        "theatrical",
        "managers",
        "agent",
        "producer"
    ],
    "wof:name":"Characterland",
    "wof:placetype":"venue"
},
  "geometry": {"coordinates":[144.94241332999999,-37.7376708984],"type":"Point"}
}