{
  "type": "Feature",
  "properties": {
    "iso:country":"AU",
    "sg:address":"101- 105 Main Rd",
    "sg:city":"Lower Plenty",
    "sg:classifiers":[
        {
            "category":"Food & Beverages",
            "subcategory":"Supermarket",
            "type":"Retail Goods"
        }
    ],
    "sg:phone":"+61 3 9435 3287",
    "sg:postcode":"3093",
    "sg:province":"VIC",
    "sg:tags":[
        "grocery",
        "store"
    ],
    "wof:name":"Lower Plenty Cellars, Fine Wines and Gourmet Foods",
    "wof:placetype":"venue"
},
  "geometry": {"coordinates":[145.11312866200001,-37.7270240784],"type":"Point"}
}