{
  "type": "Feature",
  "properties": {
    "addr:full":"3 Madison Rd Canning Vale WA 6155",
    "addr:housenumber":"3",
    "addr:postcode":"6155",
    "addr:street":"Madison Rd",
    "iso:country":"AU",
    "sg:address":"3 Madison Rd",
    "sg:city":"Canning Vale",
    "sg:classifiers":[
        {
            "category":"Utilities",
            "subcategory":"Recycling",
            "type":"Services"
        }
    ],
    "sg:phone":"+61 8 9256 6100",
    "sg:postcode":"6155",
    "sg:province":"WA",
    "wof:name":"Amcor Recycling",
    "wof:placetype":"venue"
},
  "geometry": {"coordinates":[115.927757,-32.058647],"type":"Point"}
}