{
  "type": "Feature",
  "properties": {
    "iso:country":"AU",
    "sg:address":"Rode Shopping Centre Appleby Rd",
    "sg:city":"Stafford Heights",
    "sg:classifiers":[
        {
            "category":"Health Services",
            "subcategory":"Doctor",
            "type":"Services"
        }
    ],
    "sg:phone":"+61 7 3359 6595",
    "sg:postcode":"4053",
    "sg:province":"QLD",
    "sg:tags":[
        "medical",
        "practitioner"
    ],
    "wof:name":"Jabs Dr Rachael",
    "wof:placetype":"venue"
},
  "geometry": {"coordinates":[153.010696411,-27.3950271606],"type":"Point"}
}