{
  "type": "Feature",
  "properties": {
    "addr:full":"7 Porter St Port Lincoln SA 5606",
    "addr:housenumber":"7",
    "addr:postcode":"5606",
    "addr:street":"Porter St",
    "iso:country":"AU",
    "sg:address":"7 Porter St",
    "sg:city":"Port Lincoln",
    "sg:classifiers":[
        {
            "category":"Autos & Motor Vehicles",
            "subcategory":"Motorcycle Sales",
            "type":"Retail Goods"
        }
    ],
    "sg:phone":"+61 8 8682 3122",
    "sg:postcode":"5606",
    "sg:province":"SA",
    "sg:tags":[
        "outboard"
    ],
    "wof:name":"Boat Supplies Pty Ltd",
    "wof:placetype":"venue"
},
  "geometry": {"coordinates":[135.865005,-34.724258],"type":"Point"}
}