{
  "type": "Feature",
  "properties": {
    "addr:full":"1 Torrens St Mitcham SA 5062",
    "addr:housenumber":"1",
    "addr:postcode":"5062",
    "addr:street":"Torrens St",
    "iso:country":"AU",
    "sg:address":"1 Torrens St",
    "sg:city":"Mitcham",
    "sg:classifiers":[
        {
            "category":"Shopping",
            "subcategory":"Crafts & Fabrics",
            "type":"Retail Goods"
        }
    ],
    "sg:phone":"+61 8 8272 4504",
    "sg:postcode":"5062",
    "sg:province":"SA",
    "sg:tags":[
        "supply"
    ],
    "wof:name":"Mitcham Village Art & Crafts Association Incorporated",
    "wof:placetype":"venue"
},
  "geometry": {"coordinates":[138.620635986,-34.9768753052],"type":"Point"}
}