{
  "type": "Feature",
  "properties": {
    "iso:country":"AU",
    "sg:address":"21 Ashby St",
    "sg:city":"Guildford",
    "sg:classifiers":[
        {
            "category":"Manufacturing",
            "subcategory":"Tools & Machinery",
            "type":"Manufacturing & Wholesale Goods"
        }
    ],
    "sg:phone":"+61 2 9892 3425",
    "sg:postcode":"2161",
    "sg:province":"NSW",
    "sg:tags":[
        "toolmaker"
    ],
    "wof:name":"Compact Tooling Pty Ltd",
    "wof:placetype":"venue"
},
  "geometry": {"coordinates":[150.99781799300001,-33.8591461182],"type":"Point"}
}