{
  "type": "Feature",
  "properties": {
    "iso:country":"AU",
    "sg:address":"102 Scotchmer St",
    "sg:city":"Fitzroy North",
    "sg:classifiers":[
        {
            "category":"Retail",
            "subcategory":"Veterinary Services",
            "type":"Services"
        }
    ],
    "sg:phone":"+61 3 9489 2195",
    "sg:postcode":"3068",
    "sg:province":"VIC",
    "sg:tags":[
        "surgeon"
    ],
    "wof:name":"Major Simmone Dr",
    "wof:placetype":"venue"
},
  "geometry": {"coordinates":[144.982513428,-37.7832794189],"type":"Point"}
}