{
  "type": "Feature",
  "properties": {
    "addr:full":"19 Tibouchina St Currimundi QLD 4551",
    "addr:housenumber":"19",
    "addr:postcode":"4551",
    "addr:street":"Tibouchina St",
    "iso:country":"AU",
    "sg:address":"19 Tibouchina St",
    "sg:city":"Currimundi",
    "sg:classifiers":[
        {
            "category":"Health Services",
            "subcategory":"Health Practitioner",
            "type":"Services"
        }
    ],
    "sg:phone":"+61 410 638 073",
    "sg:postcode":"4551",
    "sg:province":"QLD",
    "sg:tags":[
        "alternative"
    ],
    "wof:name":"Millennium Massages",
    "wof:placetype":"venue"
},
  "geometry": {"coordinates":[153.11935424800001,-26.7695960999],"type":"Point"}
}