{
  "type": "Feature",
  "properties": {
    "addr:full":"Suite 1/ 816 Hay St Perth WA 6000",
    "addr:housenumber":"/ 816",
    "addr:postcode":"6000",
    "addr:street":"Hay St",
    "iso:country":"AU",
    "sg:address":"Suite 1/ 816 Hay St",
    "sg:city":"Perth",
    "sg:classifiers":[
        {
            "category":"Real Estate",
            "subcategory":"Architect",
            "type":"Services"
        }
    ],
    "sg:phone":"+61 8 9322 5322",
    "sg:postcode":"6000",
    "sg:province":"WA",
    "wof:name":"Gresley Abas Architects",
    "wof:placetype":"venue"
},
  "geometry": {"coordinates":[115.84956359900001,-31.9512615204],"type":"Point"}
}