{
  "type": "Feature",
  "properties": {
    "addr:full":"13 Burrows St Prospect Vale TAS 7250",
    "addr:housenumber":"13",
    "addr:postcode":"7250",
    "addr:street":"Burrows St",
    "iso:country":"AU",
    "sg:address":"13 Burrows St",
    "sg:city":"Prospect Vale",
    "sg:classifiers":[
        {
            "category":"Building & Trades",
            "subcategory":"Construction",
            "type":"Services"
        }
    ],
    "sg:phone":"+61 3 6344 3364",
    "sg:postcode":"7250",
    "sg:province":"TAS",
    "sg:tags":[
        "earth",
        "excavating",
        "moving",
        "contractor"
    ],
    "wof:name":"Tony Quinn Excavations",
    "wof:placetype":"venue"
},
  "geometry": {"coordinates":[147.127883911,-41.4833946228],"type":"Point"}
}