{
  "type": "Feature",
  "properties": {
    "addr:full":"41 Taylors Rd Croydon VIC 3136",
    "addr:housenumber":"41",
    "addr:postcode":"3136",
    "addr:street":"Taylors Rd",
    "iso:country":"AU",
    "sg:address":"41 Taylors Rd",
    "sg:city":"Croydon",
    "sg:classifiers":[
        {
            "category":"Education",
            "subcategory":"Music School",
            "type":"Public Place"
        }
    ],
    "sg:phone":"+61 3 9725 5337",
    "sg:postcode":"3136",
    "sg:province":"VIC",
    "sg:tags":[
        "therapy",
        "relaxation"
    ],
    "wof:name":"Jacqueline's Beauty Therapy",
    "wof:placetype":"venue"
},
  "geometry": {"coordinates":[145.28276062,-37.8067588806],"type":"Point"}
}