{
  "type": "Feature",
  "properties": {
    "addr:full":"33 Penna Rd Macclesfield SA 5153",
    "addr:housenumber":"33",
    "addr:postcode":"5153",
    "addr:street":"Penna Rd",
    "iso:country":"AU",
    "sg:address":"33 Penna Rd",
    "sg:city":"Macclesfield",
    "sg:classifiers":[
        {
            "category":"Building & Trades",
            "subcategory":"Construction",
            "type":"Services"
        }
    ],
    "sg:phone":"+61 422 137 770",
    "sg:postcode":"5153",
    "sg:province":"SA",
    "sg:tags":[
        "brick",
        "paving"
    ],
    "wof:name":"B.M.L. Sandstone Paving",
    "wof:placetype":"venue"
},
  "geometry": {"coordinates":[138.860595703,-35.1640739441],"type":"Point"}
}