{
  "type": "Feature",
  "properties": {
    "iso:country":"AU",
    "sg:address":"Alma St",
    "sg:city":"Bellerive",
    "sg:classifiers":[
        {
            "category":"Education",
            "subcategory":"School",
            "type":"Public Place"
        }
    ],
    "sg:phone":"+61 3 6244 7288",
    "sg:postcode":"7018",
    "sg:province":"TAS",
    "sg:tags":[
        "co-educational"
    ],
    "wof:name":"Corpus Christi Catholic School",
    "wof:placetype":"venue"
},
  "geometry": {"coordinates":[147.371856689,-42.8717803955],"type":"Point"}
}