{
  "type": "Feature",
  "properties": {
    "addr:full":"Shop 62 Cairns Central Shopping Cntr Cnr McLeod & Spence Streets Cairns QLD 4870",
    "addr:housenumber":"shop 62",
    "addr:postcode":"4870",
    "addr:street":"Cnr",
    "iso:country":"AU",
    "sg:address":"Shop 62 Cairns Central Shopping Cntr Cnr McLeod & Spence Streets",
    "sg:city":"Cairns",
    "sg:classifiers":[
        {
            "category":"Cafe",
            "type":"Food & Drink"
        }
    ],
    "sg:phone":"+61 7 4041 6811",
    "sg:postcode":"4870",
    "sg:province":"QLD",
    "wof:name":"Gloria Jean's Coffees",
    "wof:placetype":"venue"
},
  "geometry": {"coordinates":[145.774200439,-16.9262695312],"type":"Point"}
}