{
  "type": "Feature",
  "properties": {
    "addr:full":"RMB 426 Bridge Town Yornup WA 6256",
    "addr:housenumber":"426",
    "addr:postcode":"6256",
    "addr:street":"Bridge Town",
    "iso:country":"AU",
    "sg:address":"RMB 426 Bridge Town",
    "sg:city":"Yornup",
    "sg:classifiers":[
        {
            "category":"Farming",
            "subcategory":"Farm",
            "type":"Manufacturing & Wholesale Goods"
        }
    ],
    "sg:phone":"+61 8 9761 9026",
    "sg:postcode":"6256",
    "sg:province":"WA",
    "sg:tags":[
        "farmer"
    ],
    "wof:name":"Campbell R W & P R",
    "wof:placetype":"venue"
},
  "geometry": {"coordinates":[116.16957092299999,-34.0550613403],"type":"Point"}
}