{
  "type": "Feature",
  "properties": {
    "iso:country":"AU",
    "sg:address":"54 Elbow St",
    "sg:city":"West Kempsey",
    "sg:classifiers":[
        {
            "category":"Food & Beverages",
            "subcategory":"Bakery",
            "type":"Retail Goods"
        }
    ],
    "sg:phone":"+61 2 6562 1099",
    "sg:postcode":"2440",
    "sg:province":"NSW",
    "sg:tags":[
        "cake",
        "shop",
        "pastry"
    ],
    "wof:name":"Tumblegum Bakehouse And Cafe",
    "wof:placetype":"venue"
},
  "geometry": {"coordinates":[152.829453,-31.08033],"type":"Point"}
}