{
  "type": "Feature",
  "properties": {
    "iso:country":"AU",
    "sg:address":"Epping Plaza Shopping Centre, Cooper St",
    "sg:city":"Epping",
    "sg:classifiers":[
        {
            "category":"Retail",
            "subcategory":"Auto Repair",
            "type":"Services"
        }
    ],
    "sg:phone":"+61 3 9408 3003",
    "sg:postcode":"3076",
    "sg:province":"VIC",
    "sg:tags":[
        "camper-trailers",
        "caravan",
        "servicing"
    ],
    "wof:name":"ABS Auto Brake Service",
    "wof:placetype":"venue"
},
  "geometry": {"coordinates":[145.009490967,-37.6383590698],"type":"Point"}
}