{
  "type": "Feature",
  "properties": {
    "iso:country":"AU",
    "sg:address":"113 Perkins St",
    "sg:city":"South Townsville",
    "sg:classifiers":[
        {
            "category":"Home & Garden",
            "subcategory":"Building Materials",
            "type":"Retail Goods"
        }
    ],
    "sg:phone":"+61 428 647 596",
    "sg:postcode":"4810",
    "sg:province":"QLD",
    "sg:tags":[
        "balustrading"
    ],
    "wof:name":"Ross Island Marine",
    "wof:placetype":"venue"
},
  "geometry": {"coordinates":[146.819687,-19.269747],"type":"Point"}
}