{
  "type": "Feature",
  "properties": {
    "iso:country":"AU",
    "sg:address":"Zielke Ave",
    "sg:city":"Bundaberg",
    "sg:classifiers":[
        {
            "category":"Freight",
            "type":"Transportation"
        }
    ],
    "sg:phone":"+61 7 4159 3444",
    "sg:postcode":"4670",
    "sg:province":"QLD",
    "sg:tags":[
        "transport",
        "refrigerated"
    ],
    "wof:name":"Lindsay Transport",
    "wof:placetype":"venue"
},
  "geometry": {"coordinates":[152.39547729500001,-24.8411235809],"type":"Point"}
}