{
  "type": "Feature",
  "properties": {
    "addr:full":"PO Box 7542 Toowoomba Mail Centre QLD 4352",
    "addr:postcode":"4352",
    "iso:country":"AU",
    "sg:address":"PO Box 7542",
    "sg:city":"Toowoomba Mail Centre",
    "sg:classifiers":[
        {
            "category":"Professional",
            "subcategory":"Business Services",
            "type":"Services"
        }
    ],
    "sg:phone":"+61 405 583 131",
    "sg:postcode":"4352",
    "sg:province":"QLD",
    "sg:tags":[
        "drafting"
    ],
    "wof:name":"Alisco Designs Pty Ltd",
    "wof:placetype":"venue"
},
  "geometry": {"coordinates":[151.59376499999999,-28.363979],"type":"Point"}
}