{
  "type": "Feature",
  "properties": {
    "addr:full":"2- 10 Valley Rd Yallingup WA 6282",
    "addr:housenumber":"10",
    "addr:postcode":"6282",
    "addr:street":"2;Valley Rd",
    "iso:country":"AU",
    "sg:address":"2- 10 Valley Rd",
    "sg:city":"Yallingup",
    "sg:classifiers":[
        {
            "category":"Fast Food",
            "type":"Food & Drink"
        }
    ],
    "sg:phone":"+61 8 9755 2545",
    "sg:postcode":"6282",
    "sg:province":"WA",
    "sg:tags":[
        "away",
        "take"
    ],
    "wof:name":"Surfside Kiosk",
    "wof:placetype":"venue"
},
  "geometry": {"coordinates":[115.02613067599999,-33.6391944885],"type":"Point"}
}