{
  "type": "Feature",
  "properties": {
    "addr:full":"Shp23 Centro 57 Station St Nerang QLD 4211",
    "addr:housenumber":"57",
    "addr:postcode":"4211",
    "addr:street":"Station St",
    "iso:country":"AU",
    "sg:address":"Shp23 Centro 57 Station St",
    "sg:city":"Nerang",
    "sg:classifiers":[
        {
            "category":"Shopping",
            "subcategory":"Bridal",
            "type":"Retail Goods"
        }
    ],
    "sg:phone":"+61 7 5596 4356",
    "sg:postcode":"4211",
    "sg:province":"QLD",
    "sg:tags":[
        "hire",
        "wear"
    ],
    "wof:name":"Tuxedo Junction",
    "wof:placetype":"venue"
},
  "geometry": {"coordinates":[153.339279175,-27.9962673187],"type":"Point"}
}