{
  "type": "Feature",
  "properties": {
    "iso:country":"AU",
    "sg:address":"300 Moorabool St",
    "sg:city":"Geelong",
    "sg:classifiers":[
        {
            "category":"Autos & Motor Vehicles",
            "subcategory":"Automobile Sales",
            "type":"Retail Goods"
        }
    ],
    "sg:phone":"+61 3 5229 9304",
    "sg:postcode":"3220",
    "sg:province":"VIC",
    "sg:tags":[
        "car",
        "used"
    ],
    "wof:name":"Doug Lawson Car Sales",
    "wof:placetype":"venue"
},
  "geometry": {"coordinates":[144.35766599999999,-38.153572],"type":"Point"}
}