{
  "type": "Feature",
  "properties": {
    "addr:full":"16 Byrne St Moyhu VIC 3732",
    "addr:housenumber":"16",
    "addr:postcode":"3732",
    "addr:street":"Byrne St",
    "iso:country":"AU",
    "sg:address":"16 Byrne St",
    "sg:city":"Moyhu",
    "sg:classifiers":[
        {
            "category":"Travel",
            "subcategory":"Hotels & Motels",
            "type":"Entertainment"
        }
    ],
    "sg:phone":"+61 3 5727 9333",
    "sg:postcode":"3732",
    "sg:province":"VIC",
    "sg:tags":[
        "accommodation"
    ],
    "wof:name":"Moyhu Hotel",
    "wof:placetype":"venue"
},
  "geometry": {"coordinates":[146.37884521500001,-36.5767478943],"type":"Point"}
}