{
  "type": "Feature",
  "properties": {
    "addr:full":"28 Davidson St Deniliquin NSW 2710",
    "addr:housenumber":"28",
    "addr:postcode":"2710",
    "addr:street":"Davidson St",
    "iso:country":"AU",
    "sg:address":"28 Davidson St",
    "sg:city":"Deniliquin",
    "sg:classifiers":[
        {
            "category":"Retail",
            "subcategory":"Auto Repair",
            "type":"Services"
        }
    ],
    "sg:phone":"+61 3 5881 2909",
    "sg:postcode":"2710",
    "sg:province":"NSW",
    "sg:tags":[
        "repairer",
        "motor",
        "engineer"
    ],
    "wof:name":"Fred's 4WD Accessories & Service Centre",
    "wof:placetype":"venue"
},
  "geometry": {"coordinates":[144.97006225600001,-35.5282363892],"type":"Point"}
}