{
  "type": "Feature",
  "properties": {
    "iso:country":"AU",
    "sg:address":"PO Box 4247",
    "sg:city":"Alice Springs",
    "sg:classifiers":[
        {
            "category":"Home & Garden",
            "subcategory":"Building Materials",
            "type":"Retail Goods"
        }
    ],
    "sg:phone":"+61 408 890 023",
    "sg:postcode":"0872",
    "sg:province":"NT",
    "sg:tags":[
        "lawn",
        "cutting",
        "maintenance"
    ],
    "wof:name":"Garden Man The",
    "wof:placetype":"venue"
},
  "geometry": {"coordinates":[133.880935669,-23.7033290863],"type":"Point"}
}