{
  "type": "Feature",
  "properties": {
    "addr:full":"Allambie Ave Rosebud VIC 3939",
    "addr:postcode":"3939",
    "addr:street":"Allambie Ave",
    "iso:country":"AU",
    "sg:address":"Allambie Ave",
    "sg:city":"Rosebud",
    "sg:classifiers":[
        {
            "category":"Education",
            "subcategory":"School",
            "type":"Public Place"
        }
    ],
    "sg:phone":"+61 3 5986 4884",
    "sg:postcode":"3939",
    "sg:province":"VIC",
    "sg:tags":[
        "state",
        "except",
        "nsw"
    ],
    "wof:name":"Eastbourne Primary School",
    "wof:placetype":"venue"
},
  "geometry": {"coordinates":[144.88856506400001,-38.3717079163],"type":"Point"}
}