{
  "type": "Feature",
  "properties": {
    "iso:country":"AU",
    "sg:address":"Cnr Ryde & Pittwater Rds",
    "sg:city":"Hunters Hill",
    "sg:classifiers":[
        {
            "category":"Health Services",
            "subcategory":"Dentist",
            "type":"Services"
        }
    ],
    "sg:phone":"+61 2 9817 8944",
    "sg:postcode":"2110",
    "sg:province":"NSW",
    "wof:name":"Dental Lounge",
    "wof:placetype":"venue"
},
  "geometry": {"coordinates":[151.14324951200001,-33.8331756592],"type":"Point"}
}