{
  "type": "Feature",
  "properties": {
    "addr:full":"level 5 203-233 New South Head Rd Edgecliff NSW 2027",
    "addr:housenumber":"203-233",
    "addr:postcode":"2027",
    "addr:street":"New South Head Rd",
    "iso:country":"AU",
    "sg:address":"level 5 203-233 New South Head Rd",
    "sg:city":"Edgecliff",
    "sg:classifiers":[
        {
            "category":"Health Services",
            "subcategory":"Doctor",
            "type":"Services"
        }
    ],
    "sg:phone":"+61 2 9327 2288",
    "sg:postcode":"2027",
    "sg:province":"NSW",
    "sg:tags":[
        "medical",
        "practitioner"
    ],
    "wof:name":"Lucire Yolande Dr",
    "wof:placetype":"venue"
},
  "geometry": {"coordinates":[151.235961914,-33.8788223267],"type":"Point"}
}