{
  "type": "Feature",
  "properties": {
    "iso:country":"AU",
    "sg:address":"41- 45 Myora Rw",
    "sg:city":"Karalee",
    "sg:classifiers":[
        {
            "category":"Professional",
            "subcategory":"Accounting & Tax Preparation",
            "type":"Services"
        }
    ],
    "sg:phone":"+61 7 3294 6574",
    "sg:postcode":"4306",
    "sg:province":"QLD",
    "sg:tags":[
        "consultant",
        "taxation"
    ],
    "wof:name":"Orli Henig & Associates",
    "wof:placetype":"venue"
},
  "geometry": {"coordinates":[152.85798645,-27.5799407959],"type":"Point"}
}