{
  "type": "Feature",
  "properties": {
    "addr:full":"447 Blaxland Rd Ryde NSW 2112",
    "addr:housenumber":"447",
    "addr:postcode":"2112",
    "addr:street":"Blaxland Rd",
    "iso:country":"AU",
    "sg:address":"447 Blaxland Rd",
    "sg:city":"Ryde",
    "sg:classifiers":[
        {
            "category":"Organizations",
            "subcategory":"Professional Association",
            "type":"Services"
        }
    ],
    "sg:phone":"+61 2 8819 6766",
    "sg:postcode":"2112",
    "sg:province":"NSW",
    "sg:tags":[
        "web",
        "internet"
    ],
    "wof:name":"Seeit",
    "wof:placetype":"venue"
},
  "geometry": {"coordinates":[151.09771728499999,-33.7984886169],"type":"Point"}
}