{
  "type": "Feature",
  "properties": {
    "addr:full":"Shop 9 A/B, 78 Station Rd Bethania QLD 4205",
    "addr:housenumber":"shop 9 a / b 78",
    "addr:postcode":"4205",
    "addr:street":"Station Rd",
    "iso:country":"AU",
    "sg:address":"Shop 9 A/B, 78 Station Rd",
    "sg:city":"Bethania",
    "sg:classifiers":[
        {
            "category":"Shopping",
            "subcategory":"Beauty & Cosmetics",
            "type":"Retail Goods"
        }
    ],
    "sg:phone":"+61 7 3805 2738",
    "sg:postcode":"4205",
    "sg:province":"QLD",
    "sg:tags":[
        "container"
    ],
    "wof:name":"Stars Cosmetics",
    "wof:placetype":"venue"
},
  "geometry": {"coordinates":[153.15721130399999,-27.6880168915],"type":"Point"}
}