{
  "type": "Feature",
  "properties": {
    "iso:country":"AU",
    "sg:address":"55 Gordon Rd East",
    "sg:city":"Osborne Park",
    "sg:classifiers":[
        {
            "category":"Professional",
            "subcategory":"Engineering",
            "type":"Services"
        }
    ],
    "sg:phone":"+61 8 9444 3610",
    "sg:postcode":"6017",
    "sg:province":"WA",
    "sg:tags":[
        "engineer"
    ],
    "wof:name":"Smith M H & E V (1983)",
    "wof:placetype":"venue"
},
  "geometry": {"coordinates":[115.823196411,-31.9070262909],"type":"Point"}
}