{
  "type": "Feature",
  "properties": {
    "iso:country":"AU",
    "sg:address":"100 Greenhill Rd",
    "sg:city":"Unley",
    "sg:classifiers":[
        {
            "category":"Professional",
            "subcategory":"Accounting & Tax Preparation",
            "type":"Services"
        }
    ],
    "sg:phone":"+61 8 8373 7388",
    "sg:postcode":"5061",
    "sg:province":"SA",
    "sg:tags":[
        "consultant",
        "taxation"
    ],
    "wof:name":"Rinaldi & Co",
    "wof:placetype":"venue"
},
  "geometry": {"coordinates":[138.60081481899999,-34.9414329529],"type":"Point"}
}