{
  "type": "Feature",
  "properties": {
    "addr:full":"Shop 2/ 297 Bay St Brighton VIC 3186",
    "addr:housenumber":"shop 2 / 297",
    "addr:postcode":"3186",
    "addr:street":"Bay St",
    "iso:country":"AU",
    "sg:address":"Shop 2/ 297 Bay St",
    "sg:city":"Brighton",
    "sg:classifiers":[
        {
            "category":"Shopping",
            "subcategory":"Clothing, Apparel, & Fashions",
            "type":"Retail Goods"
        }
    ],
    "sg:phone":"+61 3 9596 1655",
    "sg:postcode":"3186",
    "sg:province":"VIC",
    "sg:tags":[
        "lady",
        "wear"
    ],
    "wof:name":"Chic Clothing",
    "wof:placetype":"venue"
},
  "geometry": {"coordinates":[145.00209045400001,-37.905330658],"type":"Point"}
}