{
  "type": "Feature",
  "properties": {
    "addr:full":"49 Groom St Hughes ACT 2605",
    "addr:housenumber":"49",
    "addr:postcode":"2605",
    "addr:street":"Groom St",
    "iso:country":"AU",
    "sg:address":"49 Groom St",
    "sg:city":"Hughes",
    "sg:classifiers":[
        {
            "category":"Personal",
            "subcategory":"Hair Removal",
            "type":"Services"
        }
    ],
    "sg:phone":"+61 2 6260 4345",
    "sg:postcode":"2605",
    "sg:province":"ACT",
    "wof:name":"In Essence",
    "wof:placetype":"venue"
},
  "geometry": {"coordinates":[149.091629028,-35.3326416016],"type":"Point"}
}