{
  "type": "Feature",
  "properties": {
    "iso:country":"AU",
    "sg:address":"Unit 16, 23 Mill Point Rd",
    "sg:city":"South Perth",
    "sg:classifiers":[
        {
            "category":"Utilities",
            "subcategory":"Refuse",
            "type":"Services"
        }
    ],
    "sg:phone":"+61 410 324 944",
    "sg:postcode":"6151",
    "sg:province":"WA",
    "sg:tags":[
        "disposal",
        "reduction",
        "waste"
    ],
    "wof:name":"Supa Bins Pty Ltd",
    "wof:placetype":"venue"
},
  "geometry": {"coordinates":[115.847908,-31.966963],"type":"Point"}
}