{
  "type": "Feature",
  "properties": {
    "addr:full":"244 Western Hwy Ararat VIC 3377",
    "addr:housenumber":"244",
    "addr:postcode":"3377",
    "addr:street":"Western Hwy",
    "iso:country":"AU",
    "sg:address":"244 Western Hwy",
    "sg:city":"Ararat",
    "sg:classifiers":[
        {
            "category":"Retail",
            "subcategory":"Auto Repair",
            "type":"Services"
        }
    ],
    "sg:phone":"+61 418 501 027",
    "sg:postcode":"3377",
    "sg:province":"VIC",
    "sg:tags":[
        "bus",
        "truck"
    ],
    "wof:name":"SAS Truck Service",
    "wof:placetype":"venue"
},
  "geometry": {"coordinates":[142.918212891,-37.2643661499],"type":"Point"}
}