{
  "type": "Feature",
  "properties": {
    "addr:full":"69 East St Torrensville SA 5031",
    "addr:housenumber":"69",
    "addr:postcode":"5031",
    "addr:street":"East St",
    "iso:country":"AU",
    "sg:address":"69 East St",
    "sg:city":"Torrensville",
    "sg:classifiers":[
        {
            "category":"Building & Trades",
            "subcategory":"Construction",
            "type":"Services"
        }
    ],
    "sg:phone":"+61 418 700 592",
    "sg:postcode":"5031",
    "sg:province":"SA",
    "sg:tags":[
        "bitumen",
        "paving",
        "asphalt"
    ],
    "wof:name":"Creative Pavements",
    "wof:placetype":"venue"
},
  "geometry": {"coordinates":[138.56182861299999,-34.9172477722],"type":"Point"}
}