{
  "type": "Feature",
  "properties": {
    "addr:full":"35 Ferguson St Williamstown VIC 3016",
    "addr:housenumber":"35",
    "addr:postcode":"3016",
    "addr:street":"Ferguson St",
    "iso:country":"AU",
    "sg:address":"35 Ferguson St",
    "sg:city":"Williamstown",
    "sg:classifiers":[
        {
            "category":"Professional",
            "subcategory":"Accounting & Tax Preparation",
            "type":"Services"
        }
    ],
    "sg:phone":"+61 3 9397 1171",
    "sg:postcode":"3016",
    "sg:province":"VIC",
    "sg:tags":[
        "consultant",
        "taxation"
    ],
    "wof:name":"Williamstown Accounting & Taxation Services",
    "wof:placetype":"venue"
},
  "geometry": {"coordinates":[144.899658203,-37.8593330383],"type":"Point"}
}