{
  "type": "Feature",
  "properties": {
    "iso:country":"AU",
    "sg:address":"202 William St",
    "sg:city":"St Albans",
    "sg:classifiers":[
        {
            "category":"Retail",
            "subcategory":"Auto Repair",
            "type":"Services"
        }
    ],
    "sg:phone":"+61 3 9364 5535",
    "sg:postcode":"3021",
    "sg:province":"VIC",
    "sg:tags":[
        "beater",
        "painter",
        "panel"
    ],
    "wof:name":"Great Body Works",
    "wof:placetype":"venue"
},
  "geometry": {"coordinates":[144.798096,-37.735203],"type":"Point"}
}