{
  "type": "Feature",
  "properties": {
    "iso:country":"AU",
    "sg:address":"67 Ormond Rd",
    "sg:city":"East Geelong",
    "sg:classifiers":[
        {
            "category":"Health Services",
            "subcategory":"Chiropractor",
            "type":"Services"
        }
    ],
    "sg:phone":"+61 3 5229 2297",
    "sg:postcode":"3219",
    "sg:province":"VIC",
    "wof:name":"East Geelong Chiropractic",
    "wof:placetype":"venue"
},
  "geometry": {"coordinates":[144.37579345699999,-38.1591186523],"type":"Point"}
}