{
  "type": "Feature",
  "properties": {
    "iso:country":"AU",
    "sg:address":"427-429 Porter St",
    "sg:city":"Templestowe",
    "sg:classifiers":[
        {
            "category":"Health Services",
            "subcategory":"Doctor",
            "type":"Services"
        }
    ],
    "sg:phone":"+61 3 9846 6022",
    "sg:postcode":"3106",
    "sg:province":"VIC",
    "sg:tags":[
        "medical",
        "practitioner"
    ],
    "wof:name":"McKeever Siobhan Dr",
    "wof:placetype":"venue"
},
  "geometry": {"coordinates":[145.16763305699999,-37.7561225891],"type":"Point"}
}