{
  "type": "Feature",
  "properties": {
    "addr:full":"10 Ord St West Perth WA 6005",
    "addr:housenumber":"10",
    "addr:postcode":"6005",
    "addr:street":"Ord St",
    "iso:country":"AU",
    "sg:address":"10 Ord St",
    "sg:city":"West Perth",
    "sg:classifiers":[
        {
            "category":"Professional",
            "subcategory":"Accounting & Tax Preparation",
            "type":"Services"
        }
    ],
    "sg:phone":"+61 8 9322 2022",
    "sg:postcode":"6005",
    "sg:province":"WA",
    "sg:tags":[
        "accountant",
        "auditor"
    ],
    "wof:name":"Norgard Clohessy",
    "wof:placetype":"venue"
},
  "geometry": {"coordinates":[115.842521667,-31.9512882233],"type":"Point"}
}