{
  "type": "Feature",
  "properties": {
    "addr:full":"68 High St Mansfield VIC 3722",
    "addr:housenumber":"68",
    "addr:postcode":"3722",
    "addr:street":"High St",
    "iso:country":"AU",
    "sg:address":"68 High St",
    "sg:city":"Mansfield",
    "sg:classifiers":[
        {
            "category":"Cafe",
            "type":"Food & Drink"
        }
    ],
    "sg:phone":"+61 3 5779 1404",
    "sg:postcode":"3722",
    "sg:province":"VIC",
    "wof:name":"Mansfield Regional Produce Store",
    "wof:placetype":"venue"
},
  "geometry": {"coordinates":[146.08946227999999,-37.0526161194],"type":"Point"}
}