{
  "type": "Feature",
  "properties": {
    "iso:country":"AU",
    "sg:address":"9 Vintage Lakes Drv",
    "sg:city":"Tweed Heads",
    "sg:classifiers":[
        {
            "category":"Arena",
            "subcategory":"Sports Club",
            "type":"Entertainment"
        }
    ],
    "sg:phone":"+61 1300 552 122",
    "sg:postcode":"2485",
    "sg:province":"NSW",
    "sg:tags":[
        "defence",
        "supply",
        "self",
        "instruction",
        "martial art"
    ],
    "wof:name":"Shim Jang Taekwondo",
    "wof:placetype":"venue"
},
  "geometry": {"coordinates":[153.52256774899999,-28.2099323273],"type":"Point"}
}