{
  "type": "Feature",
  "properties": {
    "addr:full":"13- 15 Station St Wentworthville NSW 2145",
    "addr:housenumber":"15",
    "addr:postcode":"2145",
    "addr:street":"Station St",
    "iso:country":"AU",
    "sg:address":"13- 15 Station St",
    "sg:city":"Wentworthville",
    "sg:classifiers":[
        {
            "category":"Real Estate",
            "subcategory":"Real Estate Agent",
            "type":"Services"
        }
    ],
    "sg:phone":"+61 2 9631 1555",
    "sg:postcode":"2145",
    "sg:province":"NSW",
    "wof:name":"L J Hooker",
    "wof:placetype":"venue"
},
  "geometry": {"coordinates":[150.97213745100001,-33.8075447083],"type":"Point"}
}