{
  "type": "Feature",
  "properties": {
    "addr:full":"65 Vanderlin Drv Casuarina NT 0810",
    "addr:housenumber":"65",
    "addr:postcode":"nt 0810",
    "addr:street":"Vanderlin Drv",
    "iso:country":"AU",
    "sg:address":"65 Vanderlin Drv",
    "sg:city":"Casuarina",
    "sg:classifiers":[
        {
            "category":"Retail",
            "subcategory":"Veterinary Services",
            "type":"Services"
        }
    ],
    "sg:phone":"+61 8 8927 9033",
    "sg:postcode":"0810",
    "sg:province":"NT",
    "sg:tags":[
        "surgeon"
    ],
    "wof:name":"Darwin Veterinary Hospital",
    "wof:placetype":"venue"
},
  "geometry": {"coordinates":[130.88987731899999,-12.3771972656],"type":"Point"}
}