{
  "type": "Feature",
  "properties": {
    "addr:full":"27 Baylis St Wagga Wagga NSW 2650",
    "addr:housenumber":"27",
    "addr:postcode":"2650",
    "addr:street":"Baylis St",
    "iso:country":"AU",
    "sg:address":"27 Baylis St",
    "sg:city":"Wagga Wagga",
    "sg:classifiers":[
        {
            "category":"Banks & Credit Unions",
            "subcategory":"Financial Services",
            "type":"Services"
        }
    ],
    "sg:phone":"+61 2 6971 9666",
    "sg:postcode":"2650",
    "sg:province":"NSW",
    "sg:tags":[
        "advisory",
        "planning",
        "retirement"
    ],
    "wof:name":"Retireinvest",
    "wof:placetype":"venue"
},
  "geometry": {"coordinates":[147.36915588400001,-35.1179695129],"type":"Point"}
}