{
  "type": "Feature",
  "properties": {
    "iso:country":"AU",
    "sg:address":"PO Box 2151",
    "sg:city":"Townsville",
    "sg:classifiers":[
        {
            "category":"Banks & Credit Unions",
            "subcategory":"Bank",
            "type":"Services"
        }
    ],
    "sg:phone":"+61 7 4724 2315",
    "sg:postcode":"4810",
    "sg:province":"QLD",
    "sg:tags":[
        "broker",
        "mortgage"
    ],
    "wof:name":"Toms - The Optimum Mortgage Service",
    "wof:placetype":"venue"
},
  "geometry": {"coordinates":[146.755463,-19.2351],"type":"Point"}
}