{
  "type": "Feature",
  "properties": {
    "iso:country":"AU",
    "sg:address":"20 Alfred St",
    "sg:city":"Gympie",
    "sg:classifiers":[
        {
            "category":"Organizations",
            "subcategory":"Membership Organization",
            "type":"Services"
        }
    ],
    "sg:phone":"+61 7 5482 1212",
    "sg:postcode":"4570",
    "sg:province":"QLD",
    "sg:tags":[
        "support",
        "health",
        "organisation"
    ],
    "wof:name":"Gympie Community Health Centre",
    "wof:placetype":"venue"
},
  "geometry": {"coordinates":[152.65841674800001,-26.1853237152],"type":"Point"}
}