{
  "type": "Feature",
  "properties": {
    "iso:country":"AU",
    "sg:address":"\"Yasamay\" M S 301",
    "sg:city":"Monto",
    "sg:classifiers":[
        {
            "category":"Farming",
            "subcategory":"Farm",
            "type":"Manufacturing & Wholesale Goods"
        }
    ],
    "sg:phone":"+61 7 4166 5283",
    "sg:postcode":"4630",
    "sg:province":"QLD",
    "sg:tags":[
        "farmer"
    ],
    "wof:name":"Baldwin I L",
    "wof:placetype":"venue"
},
  "geometry": {"coordinates":[151.11920165999999,-24.866060257],"type":"Point"}
}