{
  "type": "Feature",
  "properties": {
    "iso:country":"AU",
    "sg:address":"5 Arndt Rd",
    "sg:city":"Pascoe Vale",
    "sg:classifiers":[
        {
            "category":"Home & Garden",
            "subcategory":"Carpets & Floor Coverings",
            "type":"Retail Goods"
        }
    ],
    "sg:phone":"+61 3 9306 9241",
    "sg:postcode":"3044",
    "sg:province":"VIC",
    "sg:tags":[
        "wood"
    ],
    "sg:website":"http://www.borthwickfloors.com.au",
    "wof:name":"A Borthwick & Son Pty. Ltd.",
    "wof:placetype":"venue"
},
  "geometry": {"coordinates":[144.935745239,-37.7212104797],"type":"Point"}
}