{
  "type": "Feature",
  "properties": {
    "addr:full":"247 Pennant Hills Rd Thornleigh NSW 2120",
    "addr:housenumber":"247",
    "addr:postcode":"2120",
    "addr:street":"Pennant Hills Rd",
    "iso:country":"AU",
    "sg:address":"247 Pennant Hills Rd",
    "sg:city":"Thornleigh",
    "sg:classifiers":[
        {
            "category":"Personal",
            "subcategory":"Massage",
            "type":"Services"
        }
    ],
    "sg:phone":"+61 2 9875 4100",
    "sg:postcode":"2120",
    "sg:province":"NSW",
    "sg:tags":[
        "therapy"
    ],
    "wof:name":"Good Life Health & Wellbeing Centre",
    "wof:placetype":"venue"
},
  "geometry": {"coordinates":[151.083084106,-33.7300567627],"type":"Point"}
}