{
  "type": "Feature",
  "properties": {
    "addr:full":"85 Sheridan St Cairns QLD 4870",
    "addr:housenumber":"85",
    "addr:postcode":"4870",
    "addr:street":"Sheridan St",
    "iso:country":"AU",
    "sg:address":"85 Sheridan St",
    "sg:city":"Cairns",
    "sg:classifiers":[
        {
            "category":"Manufacturing",
            "subcategory":"Musical Instruments",
            "type":"Manufacturing & Wholesale Goods"
        }
    ],
    "sg:phone":"+61 7 4051 0372",
    "sg:postcode":"4870",
    "sg:province":"QLD",
    "sg:tags":[
        "repair",
        "maker"
    ],
    "wof:name":"John & Christine Doolen",
    "wof:placetype":"venue"
},
  "geometry": {"coordinates":[145.77171325699999,-16.9216308594],"type":"Point"}
}