{
  "type": "Feature",
  "properties": {
    "iso:country":"AU",
    "sg:address":"Shops 6 & 7, 166 Byrnes St",
    "sg:city":"Mareeba",
    "sg:classifiers":[
        {
            "category":"Personal",
            "subcategory":"Shoe Repair & Shine",
            "type":"Services"
        }
    ],
    "sg:phone":"+61 7 4092 4846",
    "sg:postcode":"4880",
    "sg:province":"QLD",
    "sg:tags":[
        "footwear"
    ],
    "wof:name":"Sonny's Shoe Repairs",
    "wof:placetype":"venue"
},
  "geometry": {"coordinates":[145.42027282699999,-16.9870605469],"type":"Point"}
}