{
  "type": "Feature",
  "properties": {
    "iso:country":"AU",
    "sg:address":"48 Crows Nest Rd",
    "sg:city":"Taree",
    "sg:classifiers":[
        {
            "category":"Manufacturing",
            "subcategory":"Lumber",
            "type":"Manufacturing & Wholesale Goods"
        }
    ],
    "sg:phone":"+61 2 6551 5880",
    "sg:postcode":"2430",
    "sg:province":"NSW",
    "sg:tags":[
        "sawmillers"
    ],
    "wof:name":"Cross & Mcleod Sawmillers",
    "wof:placetype":"venue"
},
  "geometry": {"coordinates":[152.495102,-31.959774],"type":"Point"}
}