{
  "type": "Feature",
  "properties": {
    "iso:country":"AU",
    "sg:address":"PO Box 295",
    "sg:city":"North Beach",
    "sg:classifiers":[
        {
            "category":"Shopping",
            "subcategory":"Musical Instruments",
            "type":"Retail Goods"
        }
    ],
    "sg:phone":"+61 417 920 047",
    "sg:postcode":"6020",
    "sg:province":"WA",
    "sg:tags":[
        "musician",
        "agent"
    ],
    "wof:name":"Jazz Co-Ordination Association Of WA",
    "wof:placetype":"venue"
},
  "geometry": {"coordinates":[115.75567627,-31.8610992432],"type":"Point"}
}