{
  "type": "Feature",
  "properties": {
    "addr:full":"16 Enterprise St Boyne Island QLD 4680",
    "addr:housenumber":"16",
    "addr:postcode":"4680",
    "addr:street":"Enterprise St",
    "iso:country":"AU",
    "sg:address":"16 Enterprise St",
    "sg:city":"Boyne Island",
    "sg:classifiers":[
        {
            "category":"Wholesale",
            "subcategory":"Machinery & Supplies",
            "type":"Manufacturing & Wholesale Goods"
        }
    ],
    "sg:phone":"+61 7 4973 7631",
    "sg:postcode":"4680",
    "sg:province":"QLD",
    "sg:tags":[
        "instrument"
    ],
    "wof:name":"I & C Instrumentation & Electrical",
    "wof:placetype":"venue"
},
  "geometry": {"coordinates":[151.342987061,-23.9597148895],"type":"Point"}
}