{
  "type": "Feature",
  "properties": {
    "iso:country":"AU",
    "sg:address":"320 Kingsgrove Rd",
    "sg:city":"Kingsgrove",
    "sg:classifiers":[
        {
            "category":"Health Services",
            "subcategory":"Doctor",
            "type":"Services"
        }
    ],
    "sg:phone":"+61 2 9519 8056",
    "sg:postcode":"2208",
    "sg:province":"NSW",
    "sg:tags":[
        "medical",
        "practitioner"
    ],
    "wof:name":"Retsas C",
    "wof:placetype":"venue"
},
  "geometry": {"coordinates":[151.101913,-33.943783],"type":"Point"}
}