{
  "type": "Feature",
  "properties": {
    "iso:country":"AU",
    "sg:address":"3 Geelong Crt",
    "sg:city":"Bibra Lake",
    "sg:classifiers":[
        {
            "category":"Manufacturing",
            "subcategory":"Rubber & Plastics",
            "type":"Manufacturing & Wholesale Goods"
        }
    ],
    "sg:phone":"+61 8 9434 5252",
    "sg:postcode":"6163",
    "sg:province":"WA",
    "sg:tags":[
        "moulders"
    ],
    "wof:name":"TCT Manufacturing",
    "wof:placetype":"venue"
},
  "geometry": {"coordinates":[115.802032,-32.10067],"type":"Point"}
}