{
  "type": "Feature",
  "properties": {
    "addr:full":"Mountain Creek Rd Yass NSW 2582",
    "addr:postcode":"2582",
    "addr:street":"Mountain Creek Rd",
    "iso:country":"AU",
    "sg:address":"Mountain Creek Rd",
    "sg:city":"Yass",
    "sg:classifiers":[
        {
            "category":"Manufacturing",
            "subcategory":"Lumber",
            "type":"Manufacturing & Wholesale Goods"
        }
    ],
    "sg:phone":"+61 419 282 549",
    "sg:postcode":"2582",
    "sg:province":"NSW",
    "sg:tags":[
        "sawmillers"
    ],
    "wof:name":"Chris Pollack",
    "wof:placetype":"venue"
},
  "geometry": {"coordinates":[148.834747314,-35.0240058899],"type":"Point"}
}