{
  "type": "Feature",
  "properties": {
    "iso:country":"AU",
    "sg:address":"Shop 5, 135 Coode St",
    "sg:city":"South Perth",
    "sg:classifiers":[
        {
            "category":"Manufacturing",
            "subcategory":"Food",
            "type":"Manufacturing & Wholesale Goods"
        }
    ],
    "sg:phone":"+61 8 9368 4607",
    "sg:postcode":"6151",
    "sg:province":"WA",
    "sg:tags":[
        "function",
        "catering"
    ],
    "wof:name":"Thistle Caterers",
    "wof:placetype":"venue"
},
  "geometry": {"coordinates":[115.863724,-31.981121],"type":"Point"}
}