{
  "type": "Feature",
  "properties": {
    "addr:full":"PO Box 882 Nightcliff Private Boxes NT 0814",
    "addr:postcode":"nt 0814",
    "iso:country":"AU",
    "sg:address":"PO Box 882",
    "sg:city":"Nightcliff Private Boxes",
    "sg:classifiers":[
        {
            "category":"Utilities",
            "subcategory":"Electric",
            "type":"Services"
        }
    ],
    "sg:phone":"+61 8 8985 3372",
    "sg:postcode":"0814",
    "sg:province":"NT",
    "sg:tags":[
        "electrical",
        "contractor"
    ],
    "wof:name":"Prolecs Electrical Pty Ltd",
    "wof:placetype":"venue"
},
  "geometry": {"coordinates":[130.856064,-12.387455],"type":"Point"}
}