{
  "type": "Feature",
  "properties": {
    "iso:country":"AU",
    "sg:address":"20 Sydenham Rd",
    "sg:city":"Norwood",
    "sg:classifiers":[
        {
            "category":"Professional",
            "subcategory":"Research",
            "type":"Services"
        }
    ],
    "sg:phone":"+61 8 8362 8556",
    "sg:postcode":"5067",
    "sg:province":"SA",
    "sg:tags":[
        "market"
    ],
    "wof:name":"Communication & Marketing Research Associates Pty Ltd",
    "wof:placetype":"venue"
},
  "geometry": {"coordinates":[138.62742614699999,-34.9172134399],"type":"Point"}
}