{
  "type": "Feature",
  "properties": {
    "addr:full":"35 Grandeville Drv Mt Waverley VIC 3149",
    "addr:housenumber":"35",
    "addr:postcode":"3149",
    "addr:street":"Grandeville Drv Mt",
    "iso:country":"AU",
    "sg:address":"35 Grandeville Drv",
    "sg:city":"Mt Waverley",
    "sg:classifiers":[
        {
            "category":"Building & Trades",
            "subcategory":"Construction",
            "type":"Services"
        }
    ],
    "sg:phone":"+61 3 9762 3336",
    "sg:postcode":"3149",
    "sg:province":"VIC",
    "sg:tags":[
        "home",
        "air conditioning"
    ],
    "wof:name":"Barry Thomas Air Conditioning",
    "wof:placetype":"venue"
},
  "geometry": {"coordinates":[145.11297607399999,-37.9316062927],"type":"Point"}
}