{
  "type": "Feature",
  "properties": {
    "addr:full":"101 Bulcock St Caloundra QLD 4551",
    "addr:housenumber":"101",
    "addr:postcode":"4551",
    "addr:street":"Bulcock St",
    "iso:country":"AU",
    "sg:address":"101 Bulcock St",
    "sg:city":"Caloundra",
    "sg:classifiers":[
        {
            "category":"Health Services",
            "subcategory":"Health Practitioner",
            "type":"Services"
        }
    ],
    "sg:phone":"+61 7 5491 9116",
    "sg:postcode":"4551",
    "sg:province":"QLD",
    "sg:tags":[
        "physiotherapist"
    ],
    "wof:name":"Mihell Jane",
    "wof:placetype":"venue"
},
  "geometry": {"coordinates":[153.12806701700001,-26.8042945862],"type":"Point"}
}