{
  "type": "Feature",
  "properties": {
    "addr:full":"139 St Johns Rd Glebe NSW 2037",
    "addr:housenumber":"139",
    "addr:postcode":"2037",
    "addr:street":"St Johns Rd",
    "iso:country":"AU",
    "sg:address":"139 St Johns Rd",
    "sg:city":"Glebe",
    "sg:classifiers":[
        {
            "category":"Wholesale",
            "subcategory":"Music Publishers",
            "type":"Manufacturing & Wholesale Goods"
        }
    ],
    "sg:phone":"+61 413 591 989",
    "sg:postcode":"2037",
    "sg:province":"NSW",
    "sg:tags":[
        "wholesaler",
        "dvd",
        "mfrs",
        "cd"
    ],
    "wof:name":"NON Recordings",
    "wof:placetype":"venue"
},
  "geometry": {"coordinates":[151.184356689,-33.8824958801],"type":"Point"}
}