{
  "type": "Feature",
  "properties": {
    "iso:country":"AU",
    "sg:address":"45 Birch St",
    "sg:city":"Bankstown",
    "sg:classifiers":[
        {
            "category":"Personal",
            "subcategory":"Nail Salon",
            "type":"Services"
        }
    ],
    "sg:phone":"+61 2 9791 0122",
    "sg:postcode":"2200",
    "sg:province":"NSW",
    "sg:tags":[
        "foil",
        "printing",
        "stamping"
    ],
    "wof:name":"Ashpole Roy E",
    "wof:placetype":"venue"
},
  "geometry": {"coordinates":[150.998184,-33.917301],"type":"Point"}
}