{
  "type": "Feature",
  "properties": {
    "addr:full":"1 Mulawa St Croydon VIC 3136",
    "addr:housenumber":"1",
    "addr:postcode":"3136",
    "addr:street":"Mulawa St",
    "iso:country":"AU",
    "sg:address":"1 Mulawa St",
    "sg:city":"Croydon",
    "sg:classifiers":[
        {
            "category":"Professional",
            "subcategory":"Secretarial Services",
            "type":"Services"
        }
    ],
    "sg:phone":"+61 3 9725 9880",
    "sg:postcode":"3136",
    "sg:province":"VIC",
    "sg:tags":[
        "typing"
    ],
    "wof:name":"Blue Ribbon Typing Services",
    "wof:placetype":"venue"
},
  "geometry": {"coordinates":[145.28158569300001,-37.7796020508],"type":"Point"}
}