{
  "type": "Feature",
  "properties": {
    "iso:country":"AU",
    "sg:address":"Level 5, 127 York St",
    "sg:city":"Sydney",
    "sg:classifiers":[
        {
            "category":"Shopping",
            "subcategory":"Computers & Home Electronics",
            "type":"Retail Goods"
        }
    ],
    "sg:phone":"+61 2 9264 4910",
    "sg:postcode":"2000",
    "sg:province":"NSW",
    "sg:tags":[
        "equipment",
        "multimedia"
    ],
    "wof:name":"Bold DVD",
    "wof:placetype":"venue"
},
  "geometry": {"coordinates":[151.20623779300001,-33.8717155457],"type":"Point"}
}