{
  "type": "Feature",
  "properties": {
    "iso:country":"AU",
    "sg:address":"30-32 Wreckyn St",
    "sg:city":"North Melbourne",
    "sg:classifiers":[
        {
            "category":"Health Services",
            "subcategory":"Doctor",
            "type":"Services"
        }
    ],
    "sg:phone":"+61 3 9328 1484",
    "sg:postcode":"3051",
    "sg:province":"VIC",
    "sg:tags":[
        "medical",
        "practitioner"
    ],
    "wof:name":"Greenberg Peter & Yvonne",
    "wof:placetype":"venue"
},
  "geometry": {"coordinates":[144.95449829099999,-37.800151825],"type":"Point"}
}