{
  "type": "Feature",
  "properties": {
    "iso:country":"AU",
    "sg:address":"Unit 2 / 3 Landenburg Pl",
    "sg:city":"Greenwich",
    "sg:classifiers":[
        {
            "category":"Professional",
            "subcategory":"Accounting & Tax Preparation",
            "type":"Services"
        }
    ],
    "sg:phone":"+61 2 9439 7147",
    "sg:postcode":"2065",
    "sg:province":"NSW",
    "sg:tags":[
        "consultant",
        "taxation"
    ],
    "wof:name":"HG Accounting & Taxation Services",
    "wof:placetype":"venue"
},
  "geometry": {"coordinates":[151.18511962900001,-33.8367538452],"type":"Point"}
}