{
  "type": "Feature",
  "properties": {
    "addr:full":"3 Macedon Rd Lower Templestowe VIC 3107",
    "addr:postcode":"3107",
    "addr:street":"Macedon Rd",
    "iso:country":"AU",
    "sg:address":"3 Macedon Rd",
    "sg:city":"Lower Templestowe",
    "sg:classifiers":[
        {
            "category":"Professional",
            "subcategory":"Printing & Photocopies",
            "type":"Services"
        }
    ],
    "sg:phone":"+61 3 9850 2147",
    "sg:postcode":"3107",
    "sg:province":"VIC",
    "sg:tags":[
        "photocopying"
    ],
    "wof:name":"Templestowe Photoworks",
    "wof:placetype":"venue"
},
  "geometry": {"coordinates":[145.11213684099999,-37.7732086182],"type":"Point"}
}