{
  "type": "Feature",
  "properties": {
    "addr:full":"49 Norrie Ave Whyalla Norrie SA 5608",
    "addr:housenumber":"49",
    "addr:postcode":"5608",
    "addr:street":"Norrie Ave",
    "iso:country":"AU",
    "sg:address":"49 Norrie Ave",
    "sg:city":"Whyalla Norrie",
    "sg:classifiers":[
        {
            "category":"Fast Food",
            "type":"Food & Drink"
        }
    ],
    "sg:phone":"+61 8 8645 4564",
    "sg:postcode":"5608",
    "sg:province":"SA",
    "sg:tags":[
        "away",
        "take"
    ],
    "wof:name":"Subway Whyalla",
    "wof:placetype":"venue"
},
  "geometry": {"coordinates":[137.551468,-33.037731],"type":"Point"}
}