{
  "type": "Feature",
  "properties": {
    "iso:country":"AU",
    "sg:address":"153 Gordon St",
    "sg:city":"Port Macquarie",
    "sg:classifiers":[
        {
            "category":"Restaurant",
            "type":"Food & Drink"
        }
    ],
    "sg:phone":"+61 2 6583 1766",
    "sg:postcode":"2444",
    "sg:province":"NSW",
    "wof:name":"Chiang Mai Thai Restaurant",
    "wof:placetype":"venue"
},
  "geometry": {"coordinates":[152.901794,-31.43461],"type":"Point"}
}