{
  "type": "Feature",
  "properties": {
    "iso:country":"AU",
    "sg:address":"Lot 2295 & 2296 Warrego Pl",
    "sg:city":"Taylors Lakes",
    "sg:classifiers":[
        {
            "category":"Building & Trades",
            "subcategory":"Construction",
            "type":"Services"
        }
    ],
    "sg:phone":"+61 3 9390 4571",
    "sg:postcode":"3038",
    "sg:province":"VIC",
    "sg:tags":[
        "contractor"
    ],
    "wof:name":"Executive Homes Pty Ltd",
    "wof:placetype":"venue"
},
  "geometry": {"coordinates":[144.782211,-37.689396],"type":"Point"}
}