{
  "type": "Feature",
  "properties": {
    "addr:full":"6 Blaxland Rd Wagga Wagga NSW 2650",
    "addr:housenumber":"6",
    "addr:postcode":"2650",
    "addr:street":"Blaxland Rd",
    "iso:country":"AU",
    "sg:address":"6 Blaxland Rd",
    "sg:city":"Wagga Wagga",
    "sg:classifiers":[
        {
            "category":"Professional",
            "type":"Services"
        }
    ],
    "sg:phone":"+61 2 6921 2804",
    "sg:postcode":"2650",
    "sg:province":"NSW",
    "sg:tags":[
        "transport"
    ],
    "wof:name":"Collins Courier Service",
    "wof:placetype":"venue"
},
  "geometry": {"coordinates":[147.40716552699999,-35.1264839172],"type":"Point"}
}