{
  "type": "Feature",
  "properties": {
    "addr:full":"128 Alison Rd Randwick NSW 2031",
    "addr:housenumber":"128",
    "addr:postcode":"2031",
    "addr:street":"Alison Rd",
    "iso:country":"AU",
    "sg:address":"128 Alison Rd",
    "sg:city":"Randwick",
    "sg:classifiers":[
        {
            "category":"Education",
            "subcategory":"School",
            "type":"Public Place"
        }
    ],
    "sg:phone":"+61 2 9398 5110",
    "sg:postcode":"2031",
    "sg:province":"NSW",
    "sg:tags":[
        "state",
        "-",
        "nsw"
    ],
    "wof:name":"Joseph Varga School The",
    "wof:placetype":"venue"
},
  "geometry": {"coordinates":[151.23704528799999,-33.9120941162],"type":"Point"}
}