{
  "type": "Feature",
  "properties": {
    "iso:country":"AU",
    "sg:address":"41 Sydenham Rd",
    "sg:city":"Norwood",
    "sg:classifiers":[
        {
            "category":"Home & Garden",
            "subcategory":"Furniture",
            "type":"Retail Goods"
        }
    ],
    "sg:phone":"+61 8 8362 9032",
    "sg:postcode":"5067",
    "sg:province":"SA",
    "sg:tags":[
        "business"
    ],
    "wof:name":"Filing Efficiency Centre",
    "wof:placetype":"venue"
},
  "geometry": {"coordinates":[138.627197266,-34.9182891846],"type":"Point"}
}