{
  "type": "Feature",
  "properties": {
    "iso:country":"AU",
    "sg:address":"1 Brygon Creek Rd",
    "sg:city":"Upper Coomera",
    "sg:classifiers":[
        {
            "category":"Social Services",
            "subcategory":"Child Care",
            "type":"Services"
        }
    ],
    "sg:phone":"+61 7 5502 7066",
    "sg:postcode":"4209",
    "sg:province":"QLD",
    "wof:name":"Coomera Kids Ed-U-Care Super Centre",
    "wof:placetype":"venue"
},
  "geometry": {"coordinates":[153.29598999000001,-27.8698482513],"type":"Point"}
}