{
  "type": "Feature",
  "properties": {
    "addr:full":"Level 9, 12 Marine Pde Southport QLD 4215",
    "addr:housenumber":"12",
    "addr:postcode":"4215",
    "addr:street":"Marine Pde",
    "iso:country":"AU",
    "sg:address":"Level 9, 12 Marine Pde",
    "sg:city":"Southport",
    "sg:classifiers":[
        {
            "category":"Government",
            "subcategory":"Court House",
            "type":"Public Place"
        }
    ],
    "sg:phone":"+61 418 995 270",
    "sg:postcode":"4215",
    "sg:province":"QLD",
    "sg:tags":[
        "personal",
        "marriage",
        "family",
        "counselling"
    ],
    "wof:name":"Morris Dr. Laurel",
    "wof:placetype":"venue"
},
  "geometry": {"coordinates":[153.41615295400001,-27.9704322815],"type":"Point"}
}