{
  "type": "Feature",
  "properties": {
    "addr:full":"4 Ramage St Bayswater VIC 3153",
    "addr:housenumber":"4",
    "addr:postcode":"3153",
    "addr:street":"Ramage St",
    "iso:country":"AU",
    "sg:address":"4 Ramage St",
    "sg:city":"Bayswater",
    "sg:classifiers":[
        {
            "category":"Autos & Motor Vehicles",
            "subcategory":"Auto Supplies",
            "type":"Retail Goods"
        }
    ],
    "sg:phone":"+61 3 9729 3300",
    "sg:postcode":"3153",
    "sg:province":"VIC",
    "sg:tags":[
        "transmission",
        "equipment",
        "power"
    ],
    "wof:name":"Brook Hansen",
    "wof:placetype":"venue"
},
  "geometry": {"coordinates":[145.286743164,-37.8419075012],"type":"Point"}
}