{
  "type": "Feature",
  "properties": {
    "iso:country":"AU",
    "sg:address":"6 Weerab Drv",
    "sg:city":"Hallett Cove",
    "sg:classifiers":[
        {
            "category":"Education",
            "subcategory":"Music School",
            "type":"Public Place"
        }
    ],
    "sg:phone":"+61 8 8387 2666",
    "sg:postcode":"5158",
    "sg:province":"SA",
    "sg:tags":[
        "teacher"
    ],
    "wof:name":"Jager Paul",
    "wof:placetype":"venue"
},
  "geometry": {"coordinates":[138.50677490199999,-35.0707359314],"type":"Point"}
}