{
  "type": "Feature",
  "properties": {
    "addr:full":"Baldock Crt Eaglehawk VIC 3556",
    "addr:postcode":"3556",
    "addr:street":"Baldock Crt",
    "iso:country":"AU",
    "sg:address":"Baldock Crt",
    "sg:city":"Eaglehawk",
    "sg:classifiers":[
        {
            "category":"Professional",
            "type":"Services"
        }
    ],
    "sg:phone":"+61 3 5446 1611",
    "sg:postcode":"3556",
    "sg:province":"VIC",
    "sg:tags":[
        "transport"
    ],
    "wof:name":"Coates Transport Water Deliveries",
    "wof:placetype":"venue"
},
  "geometry": {"coordinates":[144.245269775,-36.7251739502],"type":"Point"}
}