{
  "type": "Feature",
  "properties": {
    "addr:full":"78 Kalinga St Ballina NSW 2478",
    "addr:housenumber":"78",
    "addr:postcode":"2478",
    "addr:street":"Kalinga St",
    "iso:country":"AU",
    "sg:address":"78 Kalinga St",
    "sg:city":"Ballina",
    "sg:classifiers":[
        {
            "category":"Autos & Motor Vehicles",
            "subcategory":"Auto Supplies",
            "type":"Retail Goods"
        }
    ],
    "sg:phone":"+61 2 6686 6013",
    "sg:postcode":"2478",
    "sg:province":"NSW",
    "sg:tags":[
        "part",
        "cycles",
        "accessory"
    ],
    "wof:name":"Ballina Bikeworx",
    "wof:placetype":"venue"
},
  "geometry": {"coordinates":[153.5365448,-28.8646030426],"type":"Point"}
}