{
  "type": "Feature",
  "properties": {
    "addr:full":"7 Norton St Wangaratta VIC 3677",
    "addr:housenumber":"7",
    "addr:postcode":"3677",
    "addr:street":"Norton St",
    "iso:country":"AU",
    "sg:address":"7 Norton St",
    "sg:city":"Wangaratta",
    "sg:classifiers":[
        {
            "category":"Professional",
            "subcategory":"Computer Services",
            "type":"Services"
        }
    ],
    "sg:phone":"+61 3 5722 9922",
    "sg:postcode":"3677",
    "sg:province":"VIC",
    "sg:tags":[
        "equipment",
        "networking",
        "installation"
    ],
    "wof:name":"Camdon Communications",
    "wof:placetype":"venue"
},
  "geometry": {"coordinates":[146.31576538100001,-36.3587112427],"type":"Point"}
}