{
  "type": "Feature",
  "properties": {
    "addr:full":"36 Soldiers Rd Jannali NSW 2226",
    "addr:housenumber":"36",
    "addr:postcode":"2226",
    "addr:street":"Soldiers Rd",
    "iso:country":"AU",
    "sg:address":"36 Soldiers Rd",
    "sg:city":"Jannali",
    "sg:classifiers":[
        {
            "category":"Building & Trades",
            "subcategory":"Cleaning & Sanitation",
            "type":"Services"
        }
    ],
    "sg:phone":"+61 2 9589 3937",
    "sg:postcode":"2226",
    "sg:province":"NSW",
    "sg:tags":[
        "window"
    ],
    "wof:name":"fleetmore window cleaning",
    "wof:placetype":"venue"
},
  "geometry": {"coordinates":[151.061965942,-34.0110778809],"type":"Point"}
}