{
  "type": "Feature",
  "properties": {
    "iso:country":"AU",
    "sg:address":"Shop 5/ 191 Waller Rd",
    "sg:city":"Regents Park",
    "sg:classifiers":[
        {
            "category":"Personal",
            "subcategory":"Beauty Salon",
            "type":"Services"
        }
    ],
    "sg:phone":"+61 7 3809 2847",
    "sg:postcode":"4118",
    "sg:province":"QLD",
    "sg:tags":[
        "hairdresser"
    ],
    "wof:name":"Vibrance Hair",
    "wof:placetype":"venue"
},
  "geometry": {"coordinates":[153.05274963400001,-27.6731719971],"type":"Point"}
}