{
  "type": "Feature",
  "properties": {
    "addr:full":"221 East Boundary Rd Bentleigh East VIC 3165",
    "addr:housenumber":"221",
    "addr:postcode":"3165",
    "addr:street":"East Boundary Rd",
    "iso:country":"AU",
    "sg:address":"221 East Boundary Rd",
    "sg:city":"Bentleigh East",
    "sg:classifiers":[
        {
            "category":"Home & Garden",
            "subcategory":"Hardware",
            "type":"Retail Goods"
        }
    ],
    "sg:phone":"+61 1800 335 019",
    "sg:postcode":"3165",
    "sg:province":"VIC",
    "sg:tags":[
        "manufacturer"
    ],
    "wof:name":"Boral Cyclone Ltd",
    "wof:placetype":"venue"
},
  "geometry": {"coordinates":[145.059616089,-37.9170150757],"type":"Point"}
}