{
  "type": "Feature",
  "properties": {
    "addr:full":"14 Jijaws St Sumner Park QLD 4074",
    "addr:housenumber":"14",
    "addr:postcode":"4074",
    "addr:street":"Jijaws St",
    "iso:country":"AU",
    "sg:address":"14 Jijaws St",
    "sg:city":"Sumner Park",
    "sg:classifiers":[
        {
            "category":"Home & Garden",
            "subcategory":"Building Materials",
            "type":"Retail Goods"
        }
    ],
    "sg:phone":"+61 7 3321 9736",
    "sg:postcode":"4074",
    "sg:province":"QLD",
    "sg:tags":[
        "fencing"
    ],
    "wof:name":"Brisbanefencing.com",
    "wof:placetype":"venue"
},
  "geometry": {"coordinates":[152.94012451200001,-27.5648975372],"type":"Point"}
}