{
  "type": "Feature",
  "properties": {
    "addr:full":"11 Lemko Pl Penrith NSW 2750",
    "addr:housenumber":"11",
    "addr:postcode":"2750",
    "addr:street":"Lemko Pl",
    "iso:country":"AU",
    "sg:address":"11 Lemko Pl",
    "sg:city":"Penrith",
    "sg:classifiers":[
        {
            "category":"Retail",
            "subcategory":"Auto Repair",
            "type":"Services"
        }
    ],
    "sg:phone":"+61 2 4722 6200",
    "sg:postcode":"2750",
    "sg:province":"NSW",
    "sg:tags":[
        "body",
        "builder",
        "motor"
    ],
    "wof:name":"Hamelex White",
    "wof:placetype":"venue"
},
  "geometry": {"coordinates":[150.691864014,-33.7365455627],"type":"Point"}
}