{
  "type": "Feature",
  "properties": {
    "addr:full":"34 Princes Hwy Narooma NSW 2546",
    "addr:housenumber":"34",
    "addr:postcode":"2546",
    "addr:street":"Princes Hwy",
    "iso:country":"AU",
    "sg:address":"34 Princes Hwy",
    "sg:city":"Narooma",
    "sg:classifiers":[
        {
            "category":"Banks & Credit Unions",
            "subcategory":"Investment Brokerage",
            "type":"Services"
        }
    ],
    "sg:phone":"+61 2 4476 2222",
    "sg:postcode":"2546",
    "sg:province":"NSW",
    "sg:tags":[
        "management",
        "property"
    ],
    "wof:name":"Ray White Narooma",
    "wof:placetype":"venue"
},
  "geometry": {"coordinates":[150.124603272,-36.2144241333],"type":"Point"}
}