{
  "type": "Feature",
  "properties": {
    "addr:full":"9 Coronation St Mt Waverley VIC 3149",
    "addr:housenumber":"9",
    "addr:postcode":"3149",
    "addr:street":"Coronation St Mt",
    "iso:country":"AU",
    "sg:address":"9 Coronation St",
    "sg:city":"Mt Waverley",
    "sg:classifiers":[
        {
            "category":"Shopping",
            "subcategory":"Crafts & Fabrics",
            "type":"Retail Goods"
        }
    ],
    "sg:phone":"+61 3 9808 1200",
    "sg:postcode":"3149",
    "sg:province":"VIC",
    "sg:tags":[
        "supply"
    ],
    "wof:name":"Adjus-Tap-Mobile",
    "wof:placetype":"venue"
},
  "geometry": {"coordinates":[145.12420654300001,-37.8579368591],"type":"Point"}
}