{
  "type": "Feature",
  "properties": {
    "addr:full":"Shop 5, 161 Horton Pde Maroochydore QLD 4558",
    "addr:housenumber":"shop 5 161",
    "addr:postcode":"4558",
    "addr:street":"Horton Pde",
    "iso:country":"AU",
    "sg:address":"Shop 5, 161 Horton Pde",
    "sg:city":"Maroochydore",
    "sg:classifiers":[
        {
            "category":"Shopping",
            "subcategory":"Computers & Home Electronics",
            "type":"Retail Goods"
        }
    ],
    "sg:phone":"+61 7 5479 1266",
    "sg:postcode":"4558",
    "sg:province":"QLD",
    "sg:tags":[
        "hardware",
        "equipment"
    ],
    "wof:name":"PC Surplus",
    "wof:placetype":"venue"
},
  "geometry": {"coordinates":[153.09111023,-26.6544456482],"type":"Point"}
}