{
  "type": "Feature",
  "properties": {
    "iso:country":"AU",
    "sg:address":"607 Bourke St",
    "sg:city":"Melbourne",
    "sg:classifiers":[
        {
            "category":"Professional",
            "subcategory":"Accounting & Tax Preparation",
            "type":"Services"
        }
    ],
    "sg:phone":"+61 3 9614 4444",
    "sg:postcode":"3000",
    "sg:province":"VIC",
    "sg:tags":[
        "accountant",
        "auditor"
    ],
    "wof:name":"Yeoh Daren",
    "wof:placetype":"venue"
},
  "geometry": {"coordinates":[144.95565795900001,-37.8165397644],"type":"Point"}
}