{
  "type": "Feature",
  "properties": {
    "addr:full":"Unit 6/ 14 Vulcan Rd Canning Vale WA 6155",
    "addr:housenumber":"14",
    "addr:postcode":"6155",
    "addr:street":"Vulcan Rd",
    "iso:country":"AU",
    "sg:address":"Unit 6/ 14 Vulcan Rd",
    "sg:city":"Canning Vale",
    "sg:classifiers":[
        {
            "category":"Retail",
            "subcategory":"Auto Repair",
            "type":"Services"
        }
    ],
    "sg:phone":"+61 8 9456 3311",
    "sg:postcode":"6155",
    "sg:province":"WA",
    "sg:tags":[
        "beater",
        "painter",
        "panel"
    ],
    "sg:website":"http://www.vulcanpanelandpaint.com.au",
    "wof:name":"Vulcan Panel & Paint",
    "wof:placetype":"venue"
},
  "geometry": {"coordinates":[115.92836800000001,-32.057804],"type":"Point"}
}