{
  "type": "Feature",
  "properties": {
    "addr:full":"Shop 3 30 Erindale Rd Balcatta WA 6021",
    "addr:housenumber":"shop;30",
    "addr:postcode":"6021",
    "addr:street":"Erindale Rd",
    "iso:country":"AU",
    "sg:address":"Shop 3 30 Erindale Rd",
    "sg:city":"Balcatta",
    "sg:classifiers":[
        {
            "category":"Retail",
            "subcategory":"Repair Shop",
            "type":"Services"
        }
    ],
    "sg:phone":"+61 8 9344 8611",
    "sg:postcode":"6021",
    "sg:province":"WA",
    "sg:tags":[
        "machine",
        "repairs",
        "part",
        "dryer",
        "washing"
    ],
    "wof:name":"Appliance Parts Centre W.A.",
    "wof:placetype":"venue"
},
  "geometry": {"coordinates":[115.803497315,-31.8671760559],"type":"Point"}
}