{
  "type": "Feature",
  "properties": {
    "addr:full":"25 Green Point Rd Bridgewater TAS 7030",
    "addr:housenumber":"25",
    "addr:postcode":"7030",
    "addr:street":"Green Point Rd",
    "iso:country":"AU",
    "sg:address":"25 Green Point Rd",
    "sg:city":"Bridgewater",
    "sg:classifiers":[
        {
            "category":"Shopping",
            "subcategory":"Clothing, Apparel, & Fashions",
            "type":"Retail Goods"
        }
    ],
    "sg:phone":"+61 3 6263 3550",
    "sg:postcode":"7030",
    "sg:province":"TAS",
    "sg:tags":[
        "recycled",
        "clothing"
    ],
    "wof:name":"The Salvation Army Family Stores",
    "wof:placetype":"venue"
},
  "geometry": {"coordinates":[147.24212646500001,-42.7374801636],"type":"Point"}
}