{
  "type": "Feature",
  "properties": {
    "addr:full":"370 Heaths Rd Werribee VIC 3030",
    "addr:housenumber":"370",
    "addr:postcode":"3030",
    "addr:street":"Heaths Rd",
    "iso:country":"AU",
    "sg:address":"370 Heaths Rd",
    "sg:city":"Werribee",
    "sg:classifiers":[
        {
            "category":"Food & Beverages",
            "subcategory":"Groceries & Convenience Stores",
            "type":"Retail Goods"
        }
    ],
    "sg:phone":"+61 3 9742 7598",
    "sg:postcode":"3030",
    "sg:province":"VIC",
    "wof:name":"Quix Food Stores",
    "wof:placetype":"venue"
},
  "geometry": {"coordinates":[144.666855,-37.875591],"type":"Point"}
}