{
  "type": "Feature",
  "properties": {
    "addr:full":"3 Fourth St Murray Bridge SA 5253",
    "addr:housenumber":"3",
    "addr:postcode":"5253",
    "addr:street":"Fourth St",
    "iso:country":"AU",
    "sg:address":"3 Fourth St",
    "sg:city":"Murray Bridge",
    "sg:classifiers":[
        {
            "category":"Personal",
            "subcategory":"Beauty Salon",
            "type":"Services"
        }
    ],
    "sg:phone":"+61 8 8532 2848",
    "sg:postcode":"5253",
    "sg:province":"SA",
    "sg:tags":[
        "hairdresser"
    ],
    "wof:name":"Tangles Hair Studio",
    "wof:placetype":"venue"
},
  "geometry": {"coordinates":[139.274658203,-35.1177558899],"type":"Point"}
}