{
  "type": "Feature",
  "properties": {
    "addr:full":"421a Smith St Collingwood VIC 3066",
    "addr:housenumber":"421a",
    "addr:postcode":"3066",
    "addr:street":"Smith St",
    "iso:country":"AU",
    "sg:address":"421a Smith St",
    "sg:city":"Collingwood",
    "sg:classifiers":[
        {
            "category":"Cafe",
            "type":"Food & Drink"
        }
    ],
    "sg:phone":"+61 3 9417 2108",
    "sg:postcode":"3066",
    "sg:province":"VIC",
    "wof:name":"Entity Cafe",
    "wof:placetype":"venue"
},
  "geometry": {"coordinates":[144.984573364,-37.7962532043],"type":"Point"}
}