{
  "type": "Feature",
  "properties": {
    "addr:full":"Shop 10/ 211 Buckwell Drv Hassall Grove NSW 2761",
    "addr:housenumber":"shop 10 / 211",
    "addr:postcode":"2761",
    "addr:street":"Buckwell Drv",
    "iso:country":"AU",
    "sg:address":"Shop 10/ 211 Buckwell Drv",
    "sg:city":"Hassall Grove",
    "sg:classifiers":[
        {
            "category":"Food & Beverages",
            "subcategory":"Supermarket",
            "type":"Retail Goods"
        }
    ],
    "sg:phone":"+61 2 9835 6955",
    "sg:postcode":"2761",
    "sg:province":"NSW",
    "sg:tags":[
        "grocery",
        "store"
    ],
    "wof:name":"Hassall Grove Supermarket",
    "wof:placetype":"venue"
},
  "geometry": {"coordinates":[150.83601400000001,-33.735096],"type":"Point"}
}