{
  "type": "Feature",
  "properties": {
    "addr:full":"523- 531 High St Melton VIC 3337",
    "addr:housenumber":"531",
    "addr:postcode":"3337",
    "addr:street":"High St",
    "iso:country":"AU",
    "sg:address":"523- 531 High St",
    "sg:city":"Melton",
    "sg:classifiers":[
        {
            "category":"Food & Beverages",
            "subcategory":"Liquor & Beverages",
            "type":"Retail Goods"
        }
    ],
    "sg:phone":"+61 3 9743 8555",
    "sg:postcode":"3337",
    "sg:province":"VIC",
    "sg:tags":[
        "store"
    ],
    "wof:name":"Safeway Liquor",
    "wof:placetype":"venue"
},
  "geometry": {"coordinates":[144.568558,-37.684155],"type":"Point"}
}