{
  "type": "Feature",
  "properties": {
    "addr:full":"3A Mableton Pl Duncraig WA 6023",
    "addr:housenumber":"3a",
    "addr:postcode":"6023",
    "iso:country":"AU",
    "sg:address":"3A Mableton Pl",
    "sg:city":"Duncraig",
    "sg:classifiers":[
        {
            "category":"Retail",
            "subcategory":"Repair Shop",
            "type":"Services"
        }
    ],
    "sg:phone":"+61 8 9448 8869",
    "sg:postcode":"6023",
    "sg:province":"WA",
    "sg:tags":[
        "maintenance",
        "pool",
        "swimming"
    ],
    "wof:name":"G. & E. Pool Service",
    "wof:placetype":"venue"
},
  "geometry": {"coordinates":[115.778312683,-31.8195419312],"type":"Point"}
}