{
  "type": "Feature",
  "properties": {
    "addr:full":"Shop 6-7, Railway Square, Pacific Hwy Wyong NSW 2259",
    "addr:housenumber":"shop 6-7",
    "addr:postcode":"2259",
    "addr:street":"Railway Square Pacific Hwy",
    "iso:country":"AU",
    "sg:address":"Shop 6-7, Railway Square, Pacific Hwy",
    "sg:city":"Wyong",
    "sg:classifiers":[
        {
            "category":"Education",
            "subcategory":"Special Training",
            "type":"Public Place"
        }
    ],
    "sg:phone":"+61 2 4355 1530",
    "sg:postcode":"2259",
    "sg:province":"NSW",
    "sg:tags":[
        "tuition-educational"
    ],
    "wof:name":"Clever Classroom The",
    "wof:placetype":"venue"
},
  "geometry": {"coordinates":[151.425537109,-33.2829093933],"type":"Point"}
}