{
  "type": "Feature",
  "properties": {
    "addr:full":"Unit 6, 27 Clarice Rd Box Hill VIC 3128",
    "addr:housenumber":"27",
    "addr:postcode":"3128",
    "addr:street":"Clarice Rd",
    "iso:country":"AU",
    "sg:address":"Unit 6, 27 Clarice Rd",
    "sg:city":"Box Hill",
    "sg:classifiers":[
        {
            "category":"Building & Trades",
            "subcategory":"Plumbing",
            "type":"Services"
        }
    ],
    "sg:phone":"+61 3 9897 3851",
    "sg:postcode":"3128",
    "sg:province":"VIC",
    "sg:tags":[
        "fitting",
        "hose",
        "supply"
    ],
    "wof:name":"Sonsbeek Components",
    "wof:placetype":"venue"
},
  "geometry": {"coordinates":[145.134155273,-37.8331756592],"type":"Point"}
}