{
  "type": "Feature",
  "properties": {
    "iso:country":"AU",
    "sg:address":"78 Gunn St",
    "sg:city":"Devonport",
    "sg:classifiers":[
        {
            "category":"Building & Trades",
            "subcategory":"Construction",
            "type":"Services"
        }
    ],
    "sg:phone":"+61 419 331 957",
    "sg:postcode":"7310",
    "sg:province":"TAS",
    "sg:tags":[
        "joinery"
    ],
    "wof:name":"McClymont N & J",
    "wof:placetype":"venue"
},
  "geometry": {"coordinates":[146.35423278799999,-41.1751174927],"type":"Point"}
}