{
  "type": "Feature",
  "properties": {
    "iso:country":"AU",
    "sg:address":"10 Lilac Ave",
    "sg:city":"Orange",
    "sg:classifiers":[
        {
            "category":"Manufacturing",
            "subcategory":"Glass & Minerals",
            "type":"Manufacturing & Wholesale Goods"
        }
    ],
    "sg:phone":"+61 2 6361 9461",
    "sg:postcode":"2800",
    "sg:province":"NSW",
    "sg:tags":[
        "exploration"
    ],
    "wof:name":"Bindi's Geotechnical Services Pty Ltd",
    "wof:placetype":"venue"
},
  "geometry": {"coordinates":[149.07749939000001,-33.2913017273],"type":"Point"}
}