{
  "type": "Feature",
  "properties": {
    "addr:full":"11 Shoring Rd Diggers Rest VIC 3427",
    "addr:housenumber":"11",
    "addr:postcode":"3427",
    "addr:street":"Shoring Rd",
    "iso:country":"AU",
    "sg:address":"11 Shoring Rd",
    "sg:city":"Diggers Rest",
    "sg:classifiers":[
        {
            "category":"Building & Trades",
            "subcategory":"Plumbing",
            "type":"Services"
        }
    ],
    "sg:phone":"+61 418 338 535",
    "sg:postcode":"3427",
    "sg:province":"VIC",
    "sg:tags":[
        "pipe",
        "line",
        "contractor"
    ],
    "wof:name":"Pipeline Support Pty Ltd",
    "wof:placetype":"venue"
},
  "geometry": {"coordinates":[144.712722778,-37.6234321594],"type":"Point"}
}