{
  "type": "Feature",
  "properties": {
    "iso:country":"AU",
    "sg:address":"Zone One, 30 Wises Rd",
    "sg:city":"Maroochydore",
    "sg:classifiers":[
        {
            "category":"Home & Garden",
            "subcategory":"Carpets & Floor Coverings",
            "type":"Retail Goods"
        }
    ],
    "sg:phone":"+61 7 5451 1190",
    "sg:postcode":"4558",
    "sg:province":"QLD",
    "wof:name":"Andersens",
    "wof:placetype":"venue"
},
  "geometry": {"coordinates":[153.07867431599999,-26.6703243256],"type":"Point"}
}