{
  "type": "Feature",
  "properties": {
    "addr:full":"13 Davis Cup Crt Oxenford QLD 4210",
    "addr:housenumber":"13",
    "addr:postcode":"4210",
    "addr:street":"Davis Cup Crt",
    "iso:country":"AU",
    "sg:address":"13 Davis Cup Crt",
    "sg:city":"Oxenford",
    "sg:classifiers":[
        {
            "category":"Home & Garden",
            "subcategory":"Building Materials",
            "type":"Retail Goods"
        }
    ],
    "sg:phone":"+61 432 244 575",
    "sg:postcode":"4210",
    "sg:province":"QLD",
    "sg:tags":[
        "merchant",
        "glass",
        "glazier"
    ],
    "wof:name":"Oxenford Glass",
    "wof:placetype":"venue"
},
  "geometry": {"coordinates":[153.30125427199999,-27.911195755],"type":"Point"}
}