{
  "type": "Feature",
  "properties": {
    "addr:full":"94 Cotham Rd Kew VIC 3101",
    "addr:housenumber":"94",
    "addr:postcode":"3101",
    "addr:street":"Cotham Rd",
    "iso:country":"AU",
    "sg:address":"94 Cotham Rd",
    "sg:city":"Kew",
    "sg:classifiers":[
        {
            "category":"Home & Garden",
            "subcategory":"Furniture",
            "type":"Retail Goods"
        }
    ],
    "sg:phone":"+61 412 288 989",
    "sg:postcode":"3101",
    "sg:province":"VIC",
    "sg:tags":[
        "business"
    ],
    "wof:name":"The Office Chairman",
    "wof:placetype":"venue"
},
  "geometry": {"coordinates":[145.03602600100001,-37.8075675964],"type":"Point"}
}