{
  "type": "Feature",
  "properties": {
    "addr:full":"31 Paynters Rd Wonga Park VIC 3115",
    "addr:housenumber":"31",
    "addr:postcode":"3115",
    "addr:street":"Paynters Rd",
    "iso:country":"AU",
    "sg:address":"31 Paynters Rd",
    "sg:city":"Wonga Park",
    "sg:classifiers":[
        {
            "category":"Building & Trades",
            "subcategory":"Construction",
            "type":"Services"
        }
    ],
    "sg:phone":"+61 3 9722 1797",
    "sg:postcode":"3115",
    "sg:province":"VIC",
    "sg:tags":[
        "contractor"
    ],
    "wof:name":"R.F. & G.E. Clark",
    "wof:placetype":"venue"
},
  "geometry": {"coordinates":[145.280639648,-37.7315216064],"type":"Point"}
}