{
  "type": "Feature",
  "properties": {
    "addr:full":"53 Anembo Ave Summerland Point NSW 2259",
    "addr:housenumber":"53",
    "addr:postcode":"2259",
    "addr:street":"Anembo Ave",
    "iso:country":"AU",
    "sg:address":"53 Anembo Ave",
    "sg:city":"Summerland Point",
    "sg:classifiers":[
        {
            "category":"Home & Garden",
            "subcategory":"Carpets & Floor Coverings",
            "type":"Retail Goods"
        }
    ],
    "sg:phone":"+61 416 112 608",
    "sg:postcode":"2259",
    "sg:province":"NSW",
    "sg:tags":[
        "tile",
        "wall",
        "layer"
    ],
    "wof:name":"Roche N & S",
    "wof:placetype":"venue"
},
  "geometry": {"coordinates":[151.56440734899999,-33.1406364441],"type":"Point"}
}