{
  "type": "Feature",
  "properties": {
    "addr:full":"Kowanyama St Kowanyama QLD 4871",
    "addr:postcode":"4871",
    "addr:street":"Kowanyama St",
    "iso:country":"AU",
    "sg:address":"Kowanyama St",
    "sg:city":"Kowanyama",
    "sg:classifiers":[
        {
            "category":"Education",
            "subcategory":"School",
            "type":"Public Place"
        }
    ],
    "sg:phone":"+61 7 4060 5158",
    "sg:postcode":"4871",
    "sg:province":"QLD",
    "sg:tags":[
        "state",
        "except",
        "nsw"
    ],
    "wof:name":"Kowanyama Primary School",
    "wof:placetype":"venue"
},
  "geometry": {"coordinates":[141.744338989,-15.4824819565],"type":"Point"}
}