{
  "type": "Feature",
  "properties": {
    "iso:country":"AU",
    "sg:address":"375 Argent St",
    "sg:city":"Broken Hill",
    "sg:classifiers":[
        {
            "category":"Personal",
            "subcategory":"Beauty Salon",
            "type":"Services"
        }
    ],
    "sg:phone":"+61 8 8087 9430",
    "sg:postcode":"2880",
    "sg:province":"NSW",
    "sg:tags":[
        "hairdresser"
    ],
    "wof:name":"Nvu Hair",
    "wof:placetype":"venue"
},
  "geometry": {"coordinates":[141.46722412099999,-31.957447052],"type":"Point"}
}