{
  "type": "Feature",
  "properties": {
    "addr:full":"101 Macintosh St Forster NSW 2428",
    "addr:housenumber":"101",
    "addr:postcode":"2428",
    "addr:street":"Macintosh St",
    "iso:country":"AU",
    "sg:address":"101 Macintosh St",
    "sg:city":"Forster",
    "sg:classifiers":[
        {
            "category":"Restaurant",
            "type":"Food & Drink"
        }
    ],
    "sg:phone":"+61 2 6555 5408",
    "sg:postcode":"2428",
    "sg:province":"NSW",
    "wof:name":"Chiang 101 Thai House",
    "wof:placetype":"venue"
},
  "geometry": {"coordinates":[152.514679,-32.191811],"type":"Point"}
}