{
  "type": "Feature",
  "properties": {
    "iso:country":"AU",
    "sg:address":"Ste 208/ 35 Buckingham St",
    "sg:city":"Surry Hills",
    "sg:classifiers":[
        {
            "category":"Organizations",
            "subcategory":"Non-profit Organization",
            "type":"Services"
        }
    ],
    "sg:phone":"+61 2 9657 1796",
    "sg:postcode":"2010",
    "sg:province":"NSW",
    "sg:tags":[
        "support",
        "disability",
        "organisation"
    ],
    "wof:name":"Disability Information & Referral Centre",
    "wof:placetype":"venue"
},
  "geometry": {"coordinates":[151.20736694300001,-33.8871803284],"type":"Point"}
}