{
  "type": "Feature",
  "properties": {
    "iso:country":"AU",
    "sg:address":"U9/ 940 Albany Hwy",
    "sg:city":"East Victoria Park",
    "sg:classifiers":[
        {
            "category":"Real Estate",
            "subcategory":"Developer",
            "type":"Services"
        }
    ],
    "sg:phone":"+61 8 9361 4899",
    "sg:postcode":"6101",
    "sg:province":"WA",
    "sg:tags":[
        "development"
    ],
    "wof:name":"Alan Wilkie Realestate & Business Consultants",
    "wof:placetype":"venue"
},
  "geometry": {"coordinates":[115.906593323,-31.9891090393],"type":"Point"}
}