{
  "type": "Feature",
  "properties": {
    "addr:full":"South Pine Rd Everton Park QLD 4053",
    "addr:postcode":"4053",
    "addr:street":"South Pine Rd",
    "iso:country":"AU",
    "sg:address":"South Pine Rd",
    "sg:city":"Everton Park",
    "sg:classifiers":[
        {
            "category":"Fast Food",
            "type":"Food & Drink"
        }
    ],
    "sg:phone":"+61 7 3355 2097",
    "sg:postcode":"4053",
    "sg:province":"QLD",
    "sg:tags":[
        "away",
        "take"
    ],
    "wof:name":"KFC",
    "wof:placetype":"venue"
},
  "geometry": {"coordinates":[152.99079895,-27.4074687958],"type":"Point"}
}