{
  "type": "Feature",
  "properties": {
    "addr:full":"Level 57, MLC Centre 19 Martin Place Sydney, NSW 2000",
    "addr:housenumber":"19",
    "addr:postcode":"2000",
    "addr:street":"Martin Place",
    "iso:country":"AU",
    "sg:address":"Level 57, MLC Centre 19 Martin Place",
    "sg:city":"Sydney, NSW",
    "sg:classifiers":[
        {
            "category":"Professional",
            "subcategory":"Management & Consulting",
            "type":"Services"
        }
    ],
    "sg:postcode":"2000",
    "sg:tags":[
        "enterprise-2-0",
        "enterprise-profile-management",
        "epm",
        "profiles",
        "software",
        "bpos",
        "microsoft-online-services",
        "telstra",
        "exchange-online",
        "sharepoint-online",
        "livemeeting",
        "ocs",
        "office365",
        "cloud",
        "microsoft",
        "exchange",
        "sharepoint",
        "lync",
        "crm"
    ],
    "sg:website":"http://www.hubone.com",
    "wof:name":"HubOne",
    "wof:placetype":"venue"
},
  "geometry": {"coordinates":[151.29523699999999,-33.760048],"type":"Point"}
}