{
  "type": "Feature",
  "properties": {
    "addr:full":"20 Harper St Abbotsford VIC 3067",
    "addr:housenumber":"20",
    "addr:postcode":"3067",
    "addr:street":"Harper St",
    "iso:country":"AU",
    "sg:address":"20 Harper St",
    "sg:city":"Abbotsford",
    "sg:classifiers":[
        {
            "category":"Manufacturing",
            "subcategory":"Retail Goods",
            "type":"Manufacturing & Wholesale Goods"
        }
    ],
    "sg:phone":"+61 3 9415 8699",
    "sg:postcode":"3067",
    "sg:province":"VIC",
    "sg:tags":[
        "merchant",
        "pump",
        "mfrs"
    ],
    "wof:name":"Interchem Pty Ltd",
    "wof:placetype":"venue"
},
  "geometry": {"coordinates":[144.99887085,-37.8038139343],"type":"Point"}
}