{
  "type": "Feature",
  "properties": {
    "addr:full":"PO Box 3 Cundletown NSW 2430",
    "addr:postcode":"2430",
    "iso:country":"AU",
    "sg:address":"PO Box 3",
    "sg:city":"Cundletown",
    "sg:classifiers":[
        {
            "category":"Home & Garden",
            "subcategory":"Garden Supply",
            "type":"Retail Goods"
        }
    ],
    "sg:phone":"+61 419 655 466",
    "sg:postcode":"2430",
    "sg:province":"NSW",
    "sg:tags":[
        "turf",
        "lawn"
    ],
    "wof:name":"Banksia Turf",
    "wof:placetype":"venue"
},
  "geometry": {"coordinates":[152.51597599999999,-31.897129],"type":"Point"}
}