{
  "type": "Feature",
  "properties": {
    "addr:full":"Unit 4/ 40 Dellamarta Rd Wangara WA 6065",
    "addr:postcode":"6065",
    "addr:street":"40 Dellamarta Rd",
    "iso:country":"AU",
    "sg:address":"Unit 4/ 40 Dellamarta Rd",
    "sg:city":"Wangara",
    "sg:classifiers":[
        {
            "category":"Shopping",
            "subcategory":"Gifts & Souvenirs",
            "type":"Retail Goods"
        }
    ],
    "sg:phone":"+61 8 9408 1396",
    "sg:postcode":"6065",
    "sg:province":"WA",
    "sg:tags":[
        "shop",
        "supply"
    ],
    "wof:name":"Libra Enterprises (WA) Pty Ltd",
    "wof:placetype":"venue"
},
  "geometry": {"coordinates":[115.82386779799999,-31.7911052704],"type":"Point"}
}