{
  "type": "Feature",
  "properties": {
    "iso:country":"AU",
    "sg:address":"9 Mary St",
    "sg:city":"Malanda",
    "sg:classifiers":[
        {
            "category":"Arts & Performance",
            "subcategory":"Art Gallery",
            "type":"Entertainment"
        }
    ],
    "sg:phone":"+61 7 4096 5915",
    "sg:postcode":"4885",
    "sg:province":"QLD",
    "wof:name":"James Baines",
    "wof:placetype":"venue"
},
  "geometry": {"coordinates":[145.59280395499999,-17.3501663208],"type":"Point"}
}