{
  "type": "Feature",
  "properties": {
    "addr:full":"Ferguson La Chatswood NSW 2067",
    "addr:postcode":"2067",
    "iso:country":"AU",
    "sg:address":"Ferguson La",
    "sg:city":"Chatswood",
    "sg:classifiers":[
        {
            "category":"Health Services",
            "subcategory":"Optometrist",
            "type":"Services"
        }
    ],
    "sg:phone":"+61 2 9419 3267",
    "sg:postcode":"2067",
    "sg:province":"NSW",
    "wof:name":"Edgar P, Kangisser M, Wand S",
    "wof:placetype":"venue"
},
  "geometry": {"coordinates":[151.1847229,-33.7952308655],"type":"Point"}
}