{
  "type": "Feature",
  "properties": {
    "addr:full":"773 Pacific Hwy Gordon NSW 2072",
    "addr:housenumber":"773",
    "addr:postcode":"2072",
    "addr:street":"Pacific Hwy",
    "iso:country":"AU",
    "sg:address":"773 Pacific Hwy",
    "sg:city":"Gordon",
    "sg:classifiers":[
        {
            "category":"Banks & Credit Unions",
            "subcategory":"Bank",
            "type":"Services"
        }
    ],
    "sg:phone":"+61 13 33 30",
    "sg:postcode":"2072",
    "sg:province":"NSW",
    "wof:name":"St.George Bank Limited",
    "wof:placetype":"venue"
},
  "geometry": {"coordinates":[151.15266418499999,-33.7549591064],"type":"Point"}
}