{
  "type": "Feature",
  "properties": {
    "iso:country":"AU",
    "sg:address":"Un 2/ 2 Huntingdale Drv",
    "sg:city":"Thornton",
    "sg:classifiers":[
        {
            "category":"Autos & Motor Vehicles",
            "subcategory":"Auto Supplies",
            "type":"Retail Goods"
        }
    ],
    "sg:phone":"+61 2 4966 0590",
    "sg:postcode":"2322",
    "sg:province":"NSW",
    "sg:tags":[
        "wheel",
        "four",
        "equipment",
        "drive",
        "accessory"
    ],
    "wof:name":"J T Engineering",
    "wof:placetype":"venue"
},
  "geometry": {"coordinates":[151.63641357399999,-32.7861480713],"type":"Point"}
}