{
  "type": "Feature",
  "properties": {
    "iso:country":"AU",
    "sg:address":"Shop 1018, Level 1, 318- 322 Moggill Rd",
    "sg:city":"Indooroopilly",
    "sg:classifiers":[
        {
            "category":"Food & Beverages",
            "subcategory":"Liquor & Beverages",
            "type":"Retail Goods"
        }
    ],
    "sg:phone":"+61 7 3878 9700",
    "sg:postcode":"4068",
    "sg:province":"QLD",
    "sg:tags":[
        "store"
    ],
    "wof:name":"Indooroopilly Shoppingtown",
    "wof:placetype":"venue"
},
  "geometry": {"coordinates":[152.97233581500001,-27.4977741241],"type":"Point"}
}