{
  "type": "Feature",
  "properties": {
    "addr:full":"5B Glenelg Ave Mermaid Beach QLD 4218",
    "addr:housenumber":"5b",
    "addr:postcode":"4218",
    "addr:street":"Glenelg Ave",
    "iso:country":"AU",
    "sg:address":"5B Glenelg Ave",
    "sg:city":"Mermaid Beach",
    "sg:classifiers":[
        {
            "category":"Professional",
            "subcategory":"Engineering",
            "type":"Services"
        }
    ],
    "sg:phone":"+61 7 5575 2355",
    "sg:postcode":"4218",
    "sg:province":"QLD",
    "sg:tags":[
        "consulting",
        "engineer"
    ],
    "wof:name":"Grohs Ken Consulting Engineers",
    "wof:placetype":"venue"
},
  "geometry": {"coordinates":[153.43458557100001,-28.0448932648],"type":"Point"}
}