{
  "type": "Feature",
  "properties": {
    "addr:full":"507-515 Victoria St Brunswick West VIC 3055",
    "addr:housenumber":"507-515",
    "addr:postcode":"3055",
    "addr:street":"Victoria St",
    "iso:country":"AU",
    "sg:address":"507-515 Victoria St",
    "sg:city":"Brunswick West",
    "sg:classifiers":[
        {
            "category":"Sports & Exercise",
            "subcategory":"Gym",
            "type":"Entertainment"
        }
    ],
    "sg:phone":"+61 3 9387 2328",
    "sg:postcode":"3055",
    "sg:province":"VIC",
    "sg:tags":[
        "health",
        "fitness"
    ],
    "wof:name":"Fitzys Gym & Squash Centre",
    "wof:placetype":"venue"
},
  "geometry": {"coordinates":[144.945037842,-37.7647972107],"type":"Point"}
}