{
  "type": "Feature",
  "properties": {
    "addr:full":"Unit A10 148 Old Pittwater Rd Brookvale NSW 2100",
    "addr:housenumber":"148",
    "addr:postcode":"2100",
    "addr:street":"Old Pittwater Rd",
    "iso:country":"AU",
    "sg:address":"Unit A10 148 Old Pittwater Rd",
    "sg:city":"Brookvale",
    "sg:classifiers":[
        {
            "category":"Military Area",
            "subcategory":"Air Force Base",
            "type":"Public Place"
        }
    ],
    "sg:phone":"+61 2 9905 6336",
    "sg:postcode":"2100",
    "sg:province":"NSW",
    "sg:tags":[
        "fibre",
        "optic"
    ],
    "wof:name":"Tensor Machinery",
    "wof:placetype":"venue"
},
  "geometry": {"coordinates":[151.26280212399999,-33.7680854797],"type":"Point"}
}