{
  "type": "Feature",
  "properties": {
    "addr:full":"3 Heckenberg Rd Glenorie NSW 2157",
    "addr:housenumber":"3",
    "addr:postcode":"2157",
    "addr:street":"Heckenberg Rd",
    "iso:country":"AU",
    "sg:address":"3 Heckenberg Rd",
    "sg:city":"Glenorie",
    "sg:classifiers":[
        {
            "category":"Building & Trades",
            "subcategory":"Construction",
            "type":"Services"
        }
    ],
    "sg:phone":"+61 2 9652 1927",
    "sg:postcode":"2157",
    "sg:province":"NSW",
    "sg:tags":[
        "contractor"
    ],
    "wof:name":"Michael Shelley",
    "wof:placetype":"venue"
},
  "geometry": {"coordinates":[151.02702331500001,-33.5953330994],"type":"Point"}
}