{
  "type": "Feature",
  "properties": {
    "iso:country":"AU",
    "sg:address":"159 Princes Hwy St",
    "sg:city":"Peters",
    "sg:classifiers":[
        {
            "category":"Wholesale",
            "subcategory":"Furniture",
            "type":"Manufacturing & Wholesale Goods"
        }
    ],
    "sg:phone":"+61 2 9787 7866",
    "sg:postcode":"2044",
    "sg:province":"NSW",
    "sg:tags":[
        "wholesaler",
        "mfrs"
    ],
    "wof:name":"Bandsaw Furniture Manufacturing Pty Ltd",
    "wof:placetype":"venue"
},
  "geometry": {"coordinates":[151.178818,-33.912807],"type":"Point"}
}