{
  "type": "Feature",
  "properties": {
    "addr:full":"22 Murdock St Clayton South VIC 3169",
    "addr:housenumber":"22",
    "addr:postcode":"3169",
    "addr:street":"Murdock St",
    "iso:country":"AU",
    "sg:address":"22 Murdock St",
    "sg:city":"Clayton South",
    "sg:classifiers":[
        {
            "category":"Retail",
            "subcategory":"Auto Repair",
            "type":"Services"
        }
    ],
    "sg:phone":"+61 3 9544 2301",
    "sg:postcode":"3169",
    "sg:province":"VIC",
    "sg:tags":[
        "electrical"
    ],
    "wof:name":"Audimotion",
    "wof:placetype":"venue"
},
  "geometry": {"coordinates":[145.118865967,-37.9335212708],"type":"Point"}
}