{
  "type": "Feature",
  "properties": {
    "iso:country":"AU",
    "sg:address":"41 McLean St",
    "sg:city":"Melville",
    "sg:classifiers":[
        {
            "category":"Professional",
            "subcategory":"Management & Consulting",
            "type":"Services"
        }
    ],
    "sg:phone":"+61 8 9317 2112",
    "sg:postcode":"6156",
    "sg:province":"WA",
    "sg:tags":[
        "consultant"
    ],
    "wof:name":"Thomas International Management Consultants",
    "wof:placetype":"venue"
},
  "geometry": {"coordinates":[115.799889,-32.03986],"type":"Point"}
}