{
  "type": "Feature",
  "properties": {
    "addr:full":"546 Kingsford Smith Drv Hamilton QLD 4007",
    "addr:housenumber":"546",
    "addr:postcode":"4007",
    "addr:street":"Kingsford Smith Drv",
    "iso:country":"AU",
    "sg:address":"546 Kingsford Smith Drv",
    "sg:city":"Hamilton",
    "sg:classifiers":[
        {
            "category":"Travel",
            "subcategory":"Hotels & Motels",
            "type":"Entertainment"
        }
    ],
    "sg:phone":"+61 7 3268 5355",
    "sg:postcode":"4007",
    "sg:province":"QLD",
    "wof:name":"Airport Ascot Motel",
    "wof:placetype":"venue"
},
  "geometry": {"coordinates":[153.06842,-27.438057],"type":"Point"}
}