{
  "type": "Feature",
  "properties": {
    "iso:country":"AU",
    "sg:address":"Fivebough Rd",
    "sg:city":"Leeton",
    "sg:classifiers":[
        {
            "category":"Wholesale",
            "subcategory":"Toys & Hobbies",
            "type":"Manufacturing & Wholesale Goods"
        }
    ],
    "sg:phone":"+61 2 6953 4037",
    "sg:postcode":"2705",
    "sg:province":"NSW",
    "sg:tags":[
        "mfrs"
    ],
    "wof:name":"Keidra Woodworks",
    "wof:placetype":"venue"
},
  "geometry": {"coordinates":[146.427642822,-34.5443763733],"type":"Point"}
}