{
  "type": "Feature",
  "properties": {
    "addr:full":"342 West St Umina NSW 2257",
    "addr:housenumber":"342",
    "addr:postcode":"2257",
    "addr:street":"West St",
    "iso:country":"AU",
    "sg:address":"342 West St",
    "sg:city":"Umina",
    "sg:classifiers":[
        {
            "category":"Food & Beverages",
            "subcategory":"Bakery",
            "type":"Retail Goods"
        }
    ],
    "sg:phone":"+61 2 4342 1422",
    "sg:postcode":"2257",
    "sg:province":"NSW",
    "sg:tags":[
        "baker"
    ],
    "wof:name":"Umina Hot Bread Shop",
    "wof:placetype":"venue"
},
  "geometry": {"coordinates":[151.31756591800001,-33.521396637],"type":"Point"}
}