{
  "type": "Feature",
  "properties": {
    "addr:full":"Shop 5 74 Park Tce Salisbury SA 5108",
    "addr:housenumber":"shop;74",
    "addr:postcode":"5108",
    "addr:street":"Park Tce",
    "iso:country":"AU",
    "sg:address":"Shop 5 74 Park Tce",
    "sg:city":"Salisbury",
    "sg:classifiers":[
        {
            "category":"Professional",
            "subcategory":"Accounting & Tax Preparation",
            "type":"Services"
        }
    ],
    "sg:phone":"+61 1300 123 487",
    "sg:postcode":"5108",
    "sg:province":"SA",
    "sg:tags":[
        "consultant",
        "taxation"
    ],
    "wof:name":"ITP The Income Tax Professionals",
    "wof:placetype":"venue"
},
  "geometry": {"coordinates":[138.64772033700001,-34.7616920471],"type":"Point"}
}