{
  "type": "Feature",
  "properties": {
    "addr:full":"14 Fox St Walgett NSW 2832",
    "addr:housenumber":"14",
    "addr:postcode":"2832",
    "addr:street":"Fox St",
    "iso:country":"AU",
    "sg:address":"14 Fox St",
    "sg:city":"Walgett",
    "sg:classifiers":[
        {
            "category":"Travel",
            "subcategory":"Hotels & Motels",
            "type":"Entertainment"
        }
    ],
    "sg:phone":"+61 2 6828 1355",
    "sg:postcode":"2832",
    "sg:province":"NSW",
    "wof:name":"Walgett Motel",
    "wof:placetype":"venue"
},
  "geometry": {"coordinates":[148.11700439399999,-30.0187835693],"type":"Point"}
}