{
  "type": "Feature",
  "properties": {
    "addr:full":"Suite 6 & 7, 42 Ardross St Applecross WA 6153",
    "addr:housenumber":"&;42",
    "addr:postcode":"6153",
    "addr:street":"7;St",
    "iso:country":"AU",
    "sg:address":"Suite 6 & 7, 42 Ardross St",
    "sg:city":"Applecross",
    "sg:classifiers":[
        {
            "category":"Communications",
            "subcategory":"Film & Video Production",
            "type":"Services"
        }
    ],
    "sg:phone":"+61 8 9316 1466",
    "sg:postcode":"6153",
    "sg:province":"WA",
    "sg:tags":[
        "messaging",
        "voice"
    ],
    "wof:name":"M2 Technolgy Pty Ltd",
    "wof:placetype":"venue"
},
  "geometry": {"coordinates":[115.835342,-32.010784],"type":"Point"}
}