{
  "type": "Feature",
  "properties": {
    "iso:country":"AU",
    "sg:address":"250 Jeffries La",
    "sg:city":"Broadford",
    "sg:classifiers":[
        {
            "category":"Retail",
            "subcategory":"Auto Repair",
            "type":"Services"
        }
    ],
    "sg:phone":"+61 3 5784 1086",
    "sg:postcode":"3658",
    "sg:province":"VIC",
    "sg:tags":[
        "body",
        "motor",
        "trimmer"
    ],
    "wof:name":"Broadford Motor Trimmers",
    "wof:placetype":"venue"
},
  "geometry": {"coordinates":[144.99827575699999,-37.2152366638],"type":"Point"}
}