{
  "type": "Feature",
  "properties": {
    "addr:full":"Shop 420 Bankstown Shopping Square Bankstown NSW 2200",
    "addr:housenumber":"420",
    "addr:postcode":"2200",
    "iso:country":"AU",
    "sg:address":"Shop 420 Bankstown Shopping Square",
    "sg:city":"Bankstown",
    "sg:classifiers":[
        {
            "category":"Shopping",
            "subcategory":"Clothing, Apparel, & Fashions",
            "type":"Retail Goods"
        }
    ],
    "sg:phone":"+61 2 9790 2730",
    "sg:postcode":"2200",
    "sg:province":"NSW",
    "sg:tags":[
        "lady",
        "wear"
    ],
    "wof:name":"Silhouette",
    "wof:placetype":"venue"
},
  "geometry": {"coordinates":[151.034164,-33.914791],"type":"Point"}
}