{
  "type": "Feature",
  "properties": {
    "iso:country":"AU",
    "sg:address":"Unit 2/ 11 Distribution Ave",
    "sg:city":"Nerang",
    "sg:classifiers":[
        {
            "category":"Wholesale",
            "subcategory":"Construction Materials",
            "type":"Manufacturing & Wholesale Goods"
        }
    ],
    "sg:phone":"+61 7 5539 6233",
    "sg:postcode":"4211",
    "sg:province":"QLD",
    "sg:tags":[
        "wholesaler",
        "lighting",
        "mfrs",
        "accessory"
    ],
    "wof:name":"Mick James Electronics",
    "wof:placetype":"venue"
},
  "geometry": {"coordinates":[153.35737609899999,-27.977432251],"type":"Point"}
}