{
  "type": "Feature",
  "properties": {
    "addr:full":"33 Firebrace St Horsham VIC 3400",
    "addr:housenumber":"33",
    "addr:postcode":"3400",
    "addr:street":"Firebrace St",
    "iso:country":"AU",
    "sg:address":"33 Firebrace St",
    "sg:city":"Horsham",
    "sg:classifiers":[
        {
            "category":"Shopping",
            "subcategory":"Clothing, Apparel, & Fashions",
            "type":"Retail Goods"
        }
    ],
    "sg:phone":"+61 3 5381 1351",
    "sg:postcode":"3400",
    "sg:province":"VIC",
    "sg:tags":[
        "lingerie",
        "hosiery",
        "sleepwear"
    ],
    "wof:name":"Horsham Undercover",
    "wof:placetype":"venue"
},
  "geometry": {"coordinates":[142.199905395,-36.7133598328],"type":"Point"}
}