{
  "type": "Feature",
  "properties": {
    "addr:full":"454 Nepean Hwy Frankston VIC 3199",
    "addr:housenumber":"454",
    "addr:postcode":"3199",
    "addr:street":"Nepean Hwy",
    "iso:country":"AU",
    "sg:address":"454 Nepean Hwy",
    "sg:city":"Frankston",
    "sg:classifiers":[
        {
            "category":"Professional",
            "subcategory":"Accounting & Tax Preparation",
            "type":"Services"
        }
    ],
    "sg:phone":"+61 3 9783 6666",
    "sg:postcode":"3199",
    "sg:province":"VIC",
    "sg:tags":[
        "accountant",
        "auditor"
    ],
    "wof:name":"Carr Barnett",
    "wof:placetype":"venue"
},
  "geometry": {"coordinates":[145.12083435100001,-38.1429634094],"type":"Point"}
}