{
  "type": "Feature",
  "properties": {
    "addr:full":"27 Oliver Ave Goonellabah NSW 2480",
    "addr:housenumber":"27",
    "addr:postcode":"2480",
    "addr:street":"Oliver Ave",
    "iso:country":"AU",
    "sg:address":"27 Oliver Ave",
    "sg:city":"Goonellabah",
    "sg:classifiers":[
        {
            "category":"Social Services",
            "subcategory":"Adult Care",
            "type":"Services"
        }
    ],
    "sg:phone":"+61 2 6624 4899",
    "sg:postcode":"2480",
    "sg:province":"NSW",
    "sg:tags":[
        "aged"
    ],
    "wof:name":"Lismore Home Modification & Maintenance",
    "wof:placetype":"venue"
},
  "geometry": {"coordinates":[153.32434082,-28.8242797852],"type":"Point"}
}