{
  "type": "Feature",
  "properties": {
    "addr:full":"159 Lovell St Young NSW 2594",
    "addr:housenumber":"159",
    "addr:postcode":"2594",
    "addr:street":"Lovell St",
    "iso:country":"AU",
    "sg:address":"159 Lovell St",
    "sg:city":"Young",
    "sg:classifiers":[
        {
            "category":"Professional",
            "subcategory":"Engineering",
            "type":"Services"
        }
    ],
    "sg:phone":"+61 2 6382 5655",
    "sg:postcode":"2594",
    "sg:province":"NSW",
    "sg:tags":[
        "engineer"
    ],
    "wof:name":"Robert King, Engineer",
    "wof:placetype":"venue"
},
  "geometry": {"coordinates":[148.28924560600001,-34.3101539612],"type":"Point"}
}