{
  "type": "Feature",
  "properties": {
    "iso:country":"AU",
    "sg:address":"Unit 2/ 20 Booran Rd",
    "sg:city":"Caulfield",
    "sg:classifiers":[
        {
            "category":"Manufacturing",
            "subcategory":"Food",
            "type":"Manufacturing & Wholesale Goods"
        }
    ],
    "sg:phone":"+61 418 304 446",
    "sg:postcode":"3162",
    "sg:province":"VIC",
    "sg:tags":[
        "function",
        "catering"
    ],
    "wof:name":"Sassys Jamaican Kitchen",
    "wof:placetype":"venue"
},
  "geometry": {"coordinates":[145.035842895,-37.8833580017],"type":"Point"}
}