{
  "type": "Feature",
  "properties": {
    "addr:full":"31- 37 Learjet Dr Caboolture QLD 4510",
    "addr:housenumber":"37",
    "addr:postcode":"4510",
    "addr:street":"Learjet Dr",
    "iso:country":"AU",
    "sg:address":"31- 37 Learjet Dr",
    "sg:city":"Caboolture",
    "sg:classifiers":[
        {
            "category":"Autos & Motor Vehicles",
            "subcategory":"Auto Supplies",
            "type":"Retail Goods"
        }
    ],
    "sg:phone":"+61 7 5498 9332",
    "sg:postcode":"4510",
    "sg:province":"QLD",
    "sg:tags":[
        "camper-trailers",
        "caravan",
        "equipment"
    ],
    "sg:website":"http://www.qldcaravancentre.com.au",
    "wof:name":"Qld Caravan Centre",
    "wof:placetype":"venue"
},
  "geometry": {"coordinates":[152.97949199999999,-27.08],"type":"Point"}
}