{
  "type": "Feature",
  "properties": {
    "addr:full":"67 Watkins Rd Baulkham Hills NSW 2153",
    "addr:housenumber":"67",
    "addr:postcode":"2153",
    "addr:street":"Watkins Rd",
    "iso:country":"AU",
    "sg:address":"67 Watkins Rd",
    "sg:city":"Baulkham Hills",
    "sg:classifiers":[
        {
            "category":"Building & Trades",
            "subcategory":"Pest Control",
            "type":"Services"
        }
    ],
    "sg:phone":"+61 2 9639 0447",
    "sg:postcode":"2153",
    "sg:province":"NSW",
    "sg:tags":[
        "controller",
        "automatic"
    ],
    "wof:name":"Automation Applications",
    "wof:placetype":"venue"
},
  "geometry": {"coordinates":[150.98524475100001,-33.7664451599],"type":"Point"}
}