{
  "type": "Feature",
  "properties": {
    "iso:country":"AU",
    "sg:address":"68 Oxford St",
    "sg:city":"Paddington",
    "sg:classifiers":[
        {
            "category":"Shopping",
            "subcategory":"Clothing, Apparel, & Fashions",
            "type":"Retail Goods"
        }
    ],
    "sg:phone":"+61 2 9360 6833",
    "sg:postcode":"2021",
    "sg:province":"NSW",
    "sg:tags":[
        "menswear"
    ],
    "wof:name":"Princeton Brooks",
    "wof:placetype":"venue"
},
  "geometry": {"coordinates":[151.220626831,-33.8827781677],"type":"Point"}
}