{
  "type": "Feature",
  "properties": {
    "addr:full":"93 Railway St Rockdale NSW 2216",
    "addr:housenumber":"93",
    "addr:postcode":"2216",
    "addr:street":"Railway St",
    "iso:country":"AU",
    "sg:address":"93 Railway St",
    "sg:city":"Rockdale",
    "sg:classifiers":[
        {
            "category":"Food & Beverages",
            "subcategory":"Groceries & Convenience Stores",
            "type":"Retail Goods"
        }
    ],
    "sg:phone":"+61 2 9567 7970",
    "sg:postcode":"2216",
    "sg:province":"NSW",
    "wof:name":"Faraj Mini Market",
    "wof:placetype":"venue"
},
  "geometry": {"coordinates":[151.135986,-33.952278],"type":"Point"}
}