{
  "type": "Feature",
  "properties": {
    "addr:full":"125 Clement Drv Karrinyup WA 6018",
    "addr:housenumber":"125",
    "addr:postcode":"6018",
    "addr:street":"Clement Drv",
    "iso:country":"AU",
    "sg:address":"125 Clement Drv",
    "sg:city":"Karrinyup",
    "sg:classifiers":[
        {
            "category":"Manufacturing",
            "subcategory":"Retail Goods",
            "type":"Manufacturing & Wholesale Goods"
        }
    ],
    "sg:phone":"+61 8 9246 4848",
    "sg:postcode":"6018",
    "sg:province":"WA",
    "sg:tags":[
        "merchant",
        "pump",
        "mfrs"
    ],
    "wof:name":"Pumpspec Sales & Service Pty Ltd",
    "wof:placetype":"venue"
},
  "geometry": {"coordinates":[115.77808380099999,-31.8597335815],"type":"Point"}
}