{
  "type": "Feature",
  "properties": {
    "iso:country":"AU",
    "sg:address":"24 Mercedes Drv",
    "sg:city":"Thomastown",
    "sg:classifiers":[
        {
            "category":"Building & Trades",
            "subcategory":"Construction",
            "type":"Services"
        }
    ],
    "sg:phone":"+61 3 9464 1145",
    "sg:postcode":"3074",
    "sg:province":"VIC",
    "sg:tags":[
        "tennis court",
        "repair"
    ],
    "wof:name":"Synthigrass Australia Ltd",
    "wof:placetype":"venue"
},
  "geometry": {"coordinates":[145.042114258,-37.6882095337],"type":"Point"}
}