{
  "type": "Feature",
  "properties": {
    "addr:full":"81 Hunter St Hornsby NSW 2077",
    "addr:housenumber":"81",
    "addr:postcode":"2077",
    "addr:street":"Hunter St",
    "iso:country":"AU",
    "sg:address":"81 Hunter St",
    "sg:city":"Hornsby",
    "sg:classifiers":[
        {
            "category":"Building & Trades",
            "subcategory":"Landscaping Services",
            "type":"Services"
        }
    ],
    "sg:phone":"+61 2 9482 5540",
    "sg:postcode":"2077",
    "sg:province":"NSW",
    "sg:tags":[
        "designer",
        "landscape",
        "contractor"
    ],
    "wof:name":"Integral Landscapes",
    "wof:placetype":"venue"
},
  "geometry": {"coordinates":[151.101104736,-33.7005653381],"type":"Point"}
}