{
  "type": "Feature",
  "properties": {
    "addr:full":"217 Glen Eira Rd St Kilda East VIC 3183",
    "addr:housenumber":"217",
    "addr:postcode":"3183",
    "addr:street":"Glen Eira Rd",
    "iso:country":"AU",
    "sg:address":"217 Glen Eira Rd",
    "sg:city":"St Kilda East",
    "sg:classifiers":[
        {
            "category":"Education",
            "subcategory":"School",
            "type":"Public Place"
        }
    ],
    "sg:phone":"+61 3 9524 6300",
    "sg:postcode":"3183",
    "sg:province":"VIC",
    "sg:tags":[
        "co-educational"
    ],
    "wof:name":"Caulfield Grammar School",
    "wof:placetype":"venue"
},
  "geometry": {"coordinates":[145.003707886,-37.8774642944],"type":"Point"}
}