{
  "type": "Feature",
  "properties": {
    "addr:full":"Gladigau Rd Harrogate SA 5244",
    "addr:postcode":"5244",
    "addr:street":"Gladigau Rd",
    "iso:country":"AU",
    "sg:address":"Gladigau Rd",
    "sg:city":"Harrogate",
    "sg:classifiers":[
        {
            "category":"Retail",
            "subcategory":"Animal Services",
            "type":"Services"
        }
    ],
    "sg:phone":"+61 8 8538 7023",
    "sg:postcode":"5244",
    "sg:province":"SA",
    "sg:tags":[
        "breeder",
        "sheep",
        "stud",
        "cattle"
    ],
    "wof:name":"Redaways Murray Greys",
    "wof:placetype":"venue"
},
  "geometry": {"coordinates":[139.00097656200001,-34.9303245544],"type":"Point"}
}