{
  "type": "Feature",
  "properties": {
    "addr:full":"10 Goulburn St Leanyer NT 0812",
    "addr:housenumber":"10",
    "addr:postcode":"nt 0812",
    "addr:street":"Goulburn St",
    "iso:country":"AU",
    "sg:address":"10 Goulburn St",
    "sg:city":"Leanyer",
    "sg:classifiers":[
        {
            "category":"Personal",
            "subcategory":"Massage",
            "type":"Services"
        }
    ],
    "sg:phone":"+61 8 8945 5092",
    "sg:postcode":"0812",
    "sg:province":"NT",
    "sg:tags":[
        "therapy"
    ],
    "wof:name":"Tracy Baker Massage Therapist",
    "wof:placetype":"venue"
},
  "geometry": {"coordinates":[130.89523299999999,-12.37015],"type":"Point"}
}