{
  "type": "Feature",
  "properties": {
    "iso:country":"AU",
    "sg:address":"265 Peel St",
    "sg:city":"Tamworth",
    "sg:classifiers":[
        {
            "category":"Retail",
            "subcategory":"Event Space",
            "type":"Services"
        }
    ],
    "sg:phone":"+61 2 6766 9522",
    "sg:postcode":"2340",
    "sg:province":"NSW",
    "sg:tags":[
        "function",
        "organiser"
    ],
    "wof:name":"Hogs Breath Cafe",
    "wof:placetype":"venue"
},
  "geometry": {"coordinates":[150.92828369099999,-31.0891265869],"type":"Point"}
}