{
  "type": "Feature",
  "properties": {
    "addr:full":"Cnr Railway & Gordon Sts Ayr QLD 4807",
    "addr:postcode":"4807",
    "addr:street":"Sts",
    "iso:country":"AU",
    "sg:address":"Cnr Railway & Gordon Sts",
    "sg:city":"Ayr",
    "sg:classifiers":[
        {
            "category":"Building & Trades",
            "subcategory":"Pest Control",
            "type":"Services"
        }
    ],
    "sg:phone":"+61 7 4783 5599",
    "sg:postcode":"4807",
    "sg:province":"QLD",
    "sg:tags":[
        "herbicide",
        "insecticides",
        "fungicide"
    ],
    "wof:name":"C R T",
    "wof:placetype":"venue"
},
  "geometry": {"coordinates":[147.399932861,-19.5771808624],"type":"Point"}
}