{
  "type": "Feature",
  "properties": {
    "iso:country":"AU",
    "sg:address":"Piccadilly St",
    "sg:city":"Kalgoorlie",
    "sg:classifiers":[
        {
            "category":"Manufacturing",
            "subcategory":"Chemicals & Compounds",
            "type":"Manufacturing & Wholesale Goods"
        }
    ],
    "sg:phone":"+61 8 9021 8576",
    "sg:postcode":"6430",
    "sg:province":"WA",
    "sg:tags":[
        "explosive"
    ],
    "wof:name":"Dyno Nobel Asia Pacific Ltd",
    "wof:placetype":"venue"
},
  "geometry": {"coordinates":[121.459518433,-30.7491493225],"type":"Point"}
}