{
  "type": "Feature",
  "properties": {
    "addr:full":"Shop 182 Westfield Shopping Cntr Eastgardens NSW 2036",
    "addr:housenumber":"182",
    "addr:postcode":"2036",
    "addr:street":"Westfield Shopping Cntr",
    "iso:country":"AU",
    "sg:address":"Shop 182",
    "sg:city":"Westfield Shopping Cntr Eastgardens",
    "sg:classifiers":[
        {
            "category":"Insurance",
            "subcategory":"Health Insurance",
            "type":"Services"
        }
    ],
    "sg:phone":"+61 13 14 63",
    "sg:postcode":"2036",
    "sg:province":"NSW",
    "wof:name":"NIB Health Funds",
    "wof:placetype":"venue"
},
  "geometry": {"coordinates":[151.22450256400001,-33.9438209534],"type":"Point"}
}