{
  "type": "Feature",
  "properties": {
    "addr:full":"PO Box 4579 North Rocks NSW 2151",
    "addr:postcode":"2151",
    "iso:country":"AU",
    "sg:address":"PO Box 4579",
    "sg:city":"North Rocks",
    "sg:classifiers":[
        {
            "category":"Building & Trades",
            "subcategory":"Plumbing",
            "type":"Services"
        }
    ],
    "sg:phone":"+61 417 239 456",
    "sg:postcode":"2151",
    "sg:province":"NSW",
    "sg:tags":[
        "plumber",
        "gasfitters"
    ],
    "wof:name":"A.N.U. Plumbing Pty Ltd",
    "wof:placetype":"venue"
},
  "geometry": {"coordinates":[151.021286011,-33.7750396729],"type":"Point"}
}