{
  "type": "Feature",
  "properties": {
    "iso:country":"AU",
    "sg:address":"43 Enterprise St",
    "sg:city":"Bohle",
    "sg:classifiers":[
        {
            "category":"Retail",
            "subcategory":"Auto Repair",
            "type":"Services"
        }
    ],
    "sg:phone":"+61 7 4774 7566",
    "sg:postcode":"4818",
    "sg:province":"QLD",
    "sg:tags":[
        "body",
        "builder",
        "motor"
    ],
    "wof:name":"Townsville Body Fabrications",
    "wof:placetype":"venue"
},
  "geometry": {"coordinates":[146.712097,-19.261433],"type":"Point"}
}