{
  "type": "Feature",
  "properties": {
    "addr:full":"3 Gwendoline Ave Bentleigh VIC 3204",
    "addr:housenumber":"3",
    "addr:postcode":"3204",
    "addr:street":"Gwendoline Ave",
    "iso:country":"AU",
    "sg:address":"3 Gwendoline Ave",
    "sg:city":"Bentleigh",
    "sg:classifiers":[
        {
            "category":"Building & Trades",
            "subcategory":"Plumbing",
            "type":"Services"
        }
    ],
    "sg:phone":"+61 417 316 121",
    "sg:postcode":"3204",
    "sg:province":"VIC",
    "sg:tags":[
        "plumber",
        "gasfitters"
    ],
    "wof:name":"Lawrence Phillip",
    "wof:placetype":"venue"
},
  "geometry": {"coordinates":[145.02595500000001,-37.915836],"type":"Point"}
}