{
  "type": "Feature",
  "properties": {
    "addr:full":"U10/ 19 Sherwin Ave Castle Hill NSW 2154",
    "addr:postcode":"2154",
    "addr:street":"/ 19 Sherwin Ave",
    "iso:country":"AU",
    "sg:address":"U10/ 19 Sherwin Ave",
    "sg:city":"Castle Hill",
    "sg:classifiers":[
        {
            "category":"Professional",
            "subcategory":"Computer Services",
            "type":"Services"
        }
    ],
    "sg:phone":"+61 2 8906 1884",
    "sg:postcode":"2154",
    "sg:province":"NSW",
    "sg:tags":[
        "consultant",
        "system"
    ],
    "wof:name":"Hytech Systems",
    "wof:placetype":"venue"
},
  "geometry": {"coordinates":[150.99952697800001,-33.7339324951],"type":"Point"}
}