{
  "type": "Feature",
  "properties": {
    "addr:full":"57 Burnett St Buderim QLD 4556",
    "addr:housenumber":"57",
    "addr:postcode":"4556",
    "addr:street":"Burnett St",
    "iso:country":"AU",
    "sg:address":"57 Burnett St",
    "sg:city":"Buderim",
    "sg:classifiers":[
        {
            "category":"Food & Beverages",
            "subcategory":"Liquor & Beverages",
            "type":"Retail Goods"
        }
    ],
    "sg:phone":"+61 7 5445 3800",
    "sg:postcode":"4556",
    "sg:province":"QLD",
    "sg:tags":[
        "store"
    ],
    "wof:name":"Buderim Tavern",
    "wof:placetype":"venue"
},
  "geometry": {"coordinates":[153.04977417000001,-26.6868171692],"type":"Point"}
}