{
  "type": "Feature",
  "properties": {
    "iso:country":"AU",
    "sg:address":"92 Clavering Rd",
    "sg:city":"Bayswater",
    "sg:classifiers":[
        {
            "category":"Professional",
            "subcategory":"Engineering",
            "type":"Services"
        }
    ],
    "sg:phone":"+61 8 9272 4388",
    "sg:postcode":"6053",
    "sg:province":"WA",
    "sg:tags":[
        "consulting",
        "engineer"
    ],
    "wof:name":"Protection Engineering Pty Ltd",
    "wof:placetype":"venue"
},
  "geometry": {"coordinates":[115.917350769,-31.9125614166],"type":"Point"}
}