{
  "type": "Feature",
  "properties": {
    "addr:full":"16 Blivest St Oxley QLD 4075",
    "addr:housenumber":"16",
    "addr:postcode":"4075",
    "addr:street":"Blivest St",
    "iso:country":"AU",
    "sg:address":"16 Blivest St",
    "sg:city":"Oxley",
    "sg:classifiers":[
        {
            "category":"Building & Trades",
            "subcategory":"Cleaning & Sanitation",
            "type":"Services"
        }
    ],
    "sg:phone":"+61 7 3375 5000",
    "sg:postcode":"4075",
    "sg:province":"QLD",
    "sg:tags":[
        "sweeping",
        "machine"
    ],
    "wof:name":"Materials Handling Pty Ltd",
    "wof:placetype":"venue"
},
  "geometry": {"coordinates":[152.97251892099999,-27.5658035278],"type":"Point"}
}