{
  "type": "Feature",
  "properties": {
    "addr:full":"167- 171 Whitehorse Rd Balwyn VIC 3103",
    "addr:housenumber":"171",
    "addr:postcode":"3103",
    "addr:street":"Whitehorse Rd",
    "iso:country":"AU",
    "sg:address":"167- 171 Whitehorse Rd",
    "sg:city":"Balwyn",
    "sg:classifiers":[
        {
            "category":"Home & Garden",
            "subcategory":"Carpets & Floor Coverings",
            "type":"Retail Goods"
        }
    ],
    "sg:phone":"+61 3 9817 6177",
    "sg:postcode":"3103",
    "sg:province":"VIC",
    "sg:tags":[
        "tile",
        "wall"
    ],
    "sg:website":"http://www.keftonceramics.com.au",
    "wof:name":"Kefton Ceramics",
    "wof:placetype":"venue"
},
  "geometry": {"coordinates":[145.07420349099999,-37.8120956421],"type":"Point"}
}