{
  "type": "Feature",
  "properties": {
    "iso:country":"AU",
    "sg:address":"4 Bruce St",
    "sg:city":"Stanmore",
    "sg:classifiers":[
        {
            "category":"Professional",
            "subcategory":"Management & Consulting",
            "type":"Services"
        }
    ],
    "sg:phone":"+61 2 9500 7664",
    "sg:postcode":"2048",
    "sg:province":"NSW",
    "sg:tags":[
        "consultant",
        "educational"
    ],
    "wof:name":"Home Education Association",
    "wof:placetype":"venue"
},
  "geometry": {"coordinates":[151.161835,-33.891968],"type":"Point"}
}