{
  "type": "Feature",
  "properties": {
    "addr:full":"Shp2/ 35 Ardoss St Applecross WA 6153",
    "addr:postcode":"6153",
    "addr:street":"Ardoss St",
    "iso:country":"AU",
    "sg:address":"Shp2/ 35 Ardoss St",
    "sg:city":"Applecross",
    "sg:classifiers":[
        {
            "category":"Real Estate",
            "subcategory":"Real Estate Agent",
            "type":"Services"
        }
    ],
    "sg:phone":"+61 8 9315 5988",
    "sg:postcode":"6153",
    "sg:province":"WA",
    "wof:name":"Regal Realty Pty Ltd",
    "wof:placetype":"venue"
},
  "geometry": {"coordinates":[115.834541,-32.010151],"type":"Point"}
}