{
  "type": "Feature",
  "properties": {
    "addr:full":"206 High St Prahran VIC 3181",
    "addr:housenumber":"206",
    "addr:postcode":"3181",
    "addr:street":"High St",
    "iso:country":"AU",
    "sg:address":"206 High St",
    "sg:city":"Prahran",
    "sg:classifiers":[
        {
            "category":"Autos & Motor Vehicles",
            "subcategory":"Automobile Sales",
            "type":"Retail Goods"
        }
    ],
    "sg:phone":"+61 3 9510 8833",
    "sg:postcode":"3181",
    "sg:province":"VIC",
    "sg:tags":[
        "car",
        "new"
    ],
    "wof:name":"John Blair Honda",
    "wof:placetype":"venue"
},
  "geometry": {"coordinates":[144.99488830600001,-37.8521652222],"type":"Point"}
}