{
  "type": "Feature",
  "properties": {
    "iso:country":"AU",
    "sg:address":"644 Gympie Rd",
    "sg:city":"Chermside",
    "sg:classifiers":[
        {
            "category":"Travel",
            "subcategory":"Hotels & Motels",
            "type":"Entertainment"
        }
    ],
    "sg:phone":"+61 7 3359 9255",
    "sg:postcode":"4032",
    "sg:province":"QLD",
    "sg:website":"http://www.chermsidemotorinn.com.au",
    "wof:name":"Chermside Motor Inn",
    "wof:placetype":"venue"
},
  "geometry": {"coordinates":[153.031158,-27.390774],"type":"Point"}
}