{
  "type": "Feature",
  "properties": {
    "iso:country":"AU",
    "sg:address":"South Johnstone Rd",
    "sg:city":"Japoonvale",
    "sg:classifiers":[
        {
            "category":"Farming",
            "subcategory":"Farm",
            "type":"Manufacturing & Wholesale Goods"
        }
    ],
    "sg:phone":"+61 7 4065 5159",
    "sg:postcode":"4856",
    "sg:province":"QLD",
    "sg:tags":[
        "farmer"
    ],
    "wof:name":"Rungert H S",
    "wof:placetype":"venue"
},
  "geometry": {"coordinates":[146.01763915999999,-17.619884491],"type":"Point"}
}