{
  "type": "Feature",
  "properties": {
    "addr:full":"Suite 280 4 Young St Neutral Bay NSW 2089",
    "addr:housenumber":"4",
    "addr:postcode":"2089",
    "addr:street":"Young St",
    "iso:country":"AU",
    "sg:address":"Suite 280 4 Young St",
    "sg:city":"Neutral Bay",
    "sg:classifiers":[
        {
            "category":"Professional",
            "subcategory":"Accounting & Tax Preparation",
            "type":"Services"
        }
    ],
    "sg:phone":"+61 432 554 943",
    "sg:postcode":"2089",
    "sg:province":"NSW",
    "sg:tags":[
        "bookkeeping"
    ],
    "wof:name":"S.S. Data Management",
    "wof:placetype":"venue"
},
  "geometry": {"coordinates":[151.22114563,-33.8309020996],"type":"Point"}
}