{
  "type": "Feature",
  "properties": {
    "addr:full":"10 Thompson Rd Bassendean WA 6054",
    "addr:housenumber":"10",
    "addr:postcode":"6054",
    "addr:street":"Thompson Rd",
    "iso:country":"AU",
    "sg:address":"10 Thompson Rd",
    "sg:city":"Bassendean",
    "sg:classifiers":[
        {
            "category":"Home & Garden",
            "subcategory":"Hardware",
            "type":"Retail Goods"
        }
    ],
    "sg:phone":"+61 8 9379 9479",
    "sg:postcode":"6054",
    "sg:province":"WA",
    "sg:tags":[
        "plumber",
        "supply"
    ],
    "wof:name":"Innocare Australia Pty Ltd",
    "wof:placetype":"venue"
},
  "geometry": {"coordinates":[115.955780029,-31.9007377625],"type":"Point"}
}