{
  "type": "Feature",
  "properties": {
    "iso:country":"AU",
    "sg:address":"Mundaring Primary School 855 Stevens St",
    "sg:city":"Mundaring",
    "sg:classifiers":[
        {
            "category":"Education",
            "subcategory":"School",
            "type":"Public Place"
        }
    ],
    "sg:phone":"+61 8 9295 1072",
    "sg:postcode":"6073",
    "sg:province":"WA",
    "sg:tags":[
        "state",
        "except",
        "nsw"
    ],
    "wof:name":"Schools Government (Public)",
    "wof:placetype":"venue"
},
  "geometry": {"coordinates":[116.173202515,-31.8955421448],"type":"Point"}
}