{
  "type": "Feature",
  "properties": {
    "addr:full":"3 Willaring Drv Beckenham WA 6107",
    "addr:housenumber":"3",
    "addr:postcode":"6107",
    "addr:street":"Willaring Drv",
    "iso:country":"AU",
    "sg:address":"3 Willaring Drv",
    "sg:city":"Beckenham",
    "sg:classifiers":[
        {
            "category":"Professional",
            "subcategory":"Art Services",
            "type":"Services"
        }
    ],
    "sg:phone":"+61 8 9350 5108",
    "sg:postcode":"6107",
    "sg:province":"WA",
    "sg:tags":[
        "decorator",
        "painter"
    ],
    "wof:name":"Bob Williams Painting Service",
    "wof:placetype":"venue"
},
  "geometry": {"coordinates":[115.95079040500001,-32.0313796997],"type":"Point"}
}