{
  "type": "Feature",
  "properties": {
    "addr:full":"1 Arthur Summervilles Rd Karalee QLD 4306",
    "addr:housenumber":"1",
    "addr:postcode":"4306",
    "addr:street":"Arthur Summervilles Rd",
    "iso:country":"AU",
    "sg:address":"1 Arthur Summervilles Rd",
    "sg:city":"Karalee",
    "sg:classifiers":[
        {
            "category":"Professional",
            "subcategory":"Art Services",
            "type":"Services"
        }
    ],
    "sg:phone":"+61 413 945 495",
    "sg:postcode":"4306",
    "sg:province":"QLD",
    "sg:tags":[
        "decorator",
        "painter"
    ],
    "wof:name":"TW & VJ Fawcett Painters",
    "wof:placetype":"venue"
},
  "geometry": {"coordinates":[152.83441162099999,-27.5566062927],"type":"Point"}
}