{
  "type": "Feature",
  "properties": {
    "addr:full":"90a Lucinda Ave Wahroonga NSW 2076",
    "addr:housenumber":"90a",
    "addr:postcode":"2076",
    "addr:street":"Lucinda Ave",
    "iso:country":"AU",
    "sg:address":"90a Lucinda Ave",
    "sg:city":"Wahroonga",
    "sg:classifiers":[
        {
            "category":"Professional",
            "subcategory":"Business Services",
            "type":"Services"
        }
    ],
    "sg:phone":"+61 2 9489 3952",
    "sg:postcode":"2076",
    "sg:province":"NSW",
    "sg:tags":[
        "broker"
    ],
    "wof:name":"Wangary Holdings Pty Ltd",
    "wof:placetype":"venue"
},
  "geometry": {"coordinates":[151.10914611800001,-33.7275009155],"type":"Point"}
}