{
  "type": "Feature",
  "properties": {
    "addr:full":"Shop 113 , Level 3 Macquarie Centre North Ryde NSW 2113",
    "addr:housenumber":"113 level 3",
    "addr:postcode":"2113",
    "iso:country":"AU",
    "sg:address":"Shop 113",
    "sg:city":", Level 3 Macquarie Centre North Ryde",
    "sg:classifiers":[
        {
            "category":"Personal",
            "subcategory":"Beauty Salon",
            "type":"Services"
        }
    ],
    "sg:phone":"+61 2 9870 7400",
    "sg:postcode":"2113",
    "sg:province":"NSW",
    "wof:name":"Ella Rouge Beauty",
    "wof:placetype":"venue"
},
  "geometry": {"coordinates":[151.12094116200001,-33.7941093445],"type":"Point"}
}