{
  "type": "Feature",
  "properties": {
    "addr:full":"172 Auburn Rd Hawthorn East VIC 3123",
    "addr:housenumber":"172",
    "addr:postcode":"3123",
    "addr:street":"Auburn Rd",
    "iso:country":"AU",
    "sg:address":"172 Auburn Rd",
    "sg:city":"Hawthorn East",
    "sg:classifiers":[
        {
            "category":"Manufacturing",
            "subcategory":"Musical Instruments",
            "type":"Manufacturing & Wholesale Goods"
        }
    ],
    "sg:phone":"+61 3 9818 4444",
    "sg:postcode":"3123",
    "sg:province":"VIC",
    "sg:tags":[
        "repair",
        "maker"
    ],
    "sg:website":"http://www.violin-world.com",
    "wof:name":"Violin-World",
    "wof:placetype":"venue"
},
  "geometry": {"coordinates":[145.044525147,-37.8243904114],"type":"Point"}
}