{
  "type": "Feature",
  "properties": {
    "addr:full":"332 Hinton Rd Hinton NSW 2321",
    "addr:housenumber":"332",
    "addr:postcode":"2321",
    "addr:street":"Hinton Rd",
    "iso:country":"AU",
    "sg:address":"332 Hinton Rd",
    "sg:city":"Hinton",
    "sg:classifiers":[
        {
            "category":"Personal",
            "subcategory":"Massage",
            "type":"Services"
        }
    ],
    "sg:phone":"+61 2 4930 5224",
    "sg:postcode":"2321",
    "sg:province":"NSW",
    "sg:tags":[
        "therapy"
    ],
    "wof:name":"Meredith Etheridge",
    "wof:placetype":"venue"
},
  "geometry": {"coordinates":[151.64840698200001,-32.7144241333],"type":"Point"}
}