{
  "type": "Feature",
  "properties": {
    "addr:full":"38 Wandoo St Fortitude Valley QLD 4006",
    "addr:housenumber":"38",
    "addr:postcode":"4006",
    "addr:street":"Wandoo St",
    "iso:country":"AU",
    "sg:address":"38 Wandoo St",
    "sg:city":"Fortitude Valley",
    "sg:classifiers":[
        {
            "category":"Manufacturing",
            "subcategory":"Building Materials",
            "type":"Manufacturing & Wholesale Goods"
        }
    ],
    "sg:phone":"+61 7 3252 9699",
    "sg:postcode":"4006",
    "sg:province":"QLD",
    "sg:tags":[
        "stone",
        "product",
        "supply"
    ],
    "wof:name":"Homestone",
    "wof:placetype":"venue"
},
  "geometry": {"coordinates":[153.041137695,-27.4561004639],"type":"Point"}
}