{
  "type": "Feature",
  "properties": {
    "iso:country":"AU",
    "sg:address":"102 Lillyfield Rd",
    "sg:city":"Lilyfield",
    "sg:classifiers":[
        {
            "category":"Building & Trades",
            "subcategory":"Cleaning & Sanitation",
            "type":"Services"
        }
    ],
    "sg:phone":"+61 2 9810 9873",
    "sg:postcode":"2040",
    "sg:province":"NSW",
    "sg:tags":[
        "window"
    ],
    "wof:name":"Mr Gleam",
    "wof:placetype":"venue"
},
  "geometry": {"coordinates":[151.16412399999999,-33.873226],"type":"Point"}
}