{
  "type": "Feature",
  "properties": {
    "addr:full":"930 Little Yarra Rd Three Bridges VIC 3797",
    "addr:housenumber":"930",
    "addr:postcode":"3797",
    "addr:street":"Little Yarra Rd",
    "iso:country":"AU",
    "sg:address":"930 Little Yarra Rd",
    "sg:city":"Three Bridges",
    "sg:classifiers":[
        {
            "category":"Farming",
            "subcategory":"Orchard",
            "type":"Manufacturing & Wholesale Goods"
        }
    ],
    "sg:phone":"+61 3 5966 6206",
    "sg:postcode":"3797",
    "sg:province":"VIC",
    "sg:tags":[
        "pear",
        "apple",
        "grower"
    ],
    "wof:name":"Sanders H & L M",
    "wof:placetype":"venue"
},
  "geometry": {"coordinates":[145.6144104,-37.7825202942],"type":"Point"}
}