{
  "type": "Feature",
  "properties": {
    "addr:full":"1048- 1052 Beaudesert Rd Coopers Plains QLD 4108",
    "addr:housenumber":"1048 1052",
    "addr:postcode":"4108",
    "addr:street":"Beaudesert Rd",
    "iso:country":"AU",
    "sg:address":"1048- 1052 Beaudesert Rd",
    "sg:city":"Coopers Plains",
    "sg:classifiers":[
        {
            "category":"Wholesale",
            "subcategory":"Electrical",
            "type":"Manufacturing & Wholesale Goods"
        }
    ],
    "sg:phone":"+61 7 3844 9144",
    "sg:postcode":"4108",
    "sg:province":"QLD",
    "sg:tags":[
        "control",
        "equipment",
        "switch"
    ],
    "wof:name":"Omron Electronics Pty Ltd",
    "wof:placetype":"venue"
},
  "geometry": {"coordinates":[153.024780273,-27.570772171],"type":"Point"}
}