{
  "type": "Feature",
  "properties": {
    "addr:full":"Warriewood Sq Jackson&#039;s Rd Warriewood NSW 2102",
    "addr:postcode":"2102",
    "addr:street":"Warriewood;S Rd",
    "iso:country":"AU",
    "sg:address":"Warriewood Sq Jackson&#039;s Rd",
    "sg:city":"Warriewood",
    "sg:classifiers":[
        {
            "category":"Personal",
            "subcategory":"Beauty Salon",
            "type":"Services"
        }
    ],
    "sg:phone":"+61 2 9913 3599",
    "sg:postcode":"2102",
    "sg:province":"NSW",
    "sg:tags":[
        "hairdresser"
    ],
    "wof:name":"John Brennan Haircutting Shop",
    "wof:placetype":"venue"
},
  "geometry": {"coordinates":[151.299057,-33.686279],"type":"Point"}
}