{
  "type": "Feature",
  "properties": {
    "addr:full":"1 Penrice Rd Angaston SA 5353",
    "addr:housenumber":"1",
    "addr:postcode":"5353",
    "addr:street":"Penrice Rd",
    "iso:country":"AU",
    "sg:address":"1 Penrice Rd",
    "sg:city":"Angaston",
    "sg:classifiers":[
        {
            "category":"Building & Trades",
            "subcategory":"Construction",
            "type":"Services"
        }
    ],
    "sg:phone":"+61 8 8564 2453",
    "sg:postcode":"5353",
    "sg:province":"SA",
    "sg:tags":[
        "roof"
    ],
    "wof:name":"Barossa Roofing",
    "wof:placetype":"venue"
},
  "geometry": {"coordinates":[139.04527282699999,-34.5007362366],"type":"Point"}
}