{
  "type": "Feature",
  "properties": {
    "iso:country":"AU",
    "sg:address":"340 Bolong Rd",
    "sg:city":"Bomaderry",
    "sg:classifiers":[
        {
            "category":"Manufacturing",
            "subcategory":"Paper Products",
            "type":"Manufacturing & Wholesale Goods"
        }
    ],
    "sg:phone":"+61 2 4421 9511",
    "sg:postcode":"2541",
    "sg:province":"NSW",
    "sg:tags":[
        "wholesaler",
        "mfrs"
    ],
    "wof:name":"Australian Paper - Shoalhaven Mill",
    "wof:placetype":"venue"
},
  "geometry": {"coordinates":[150.60899352999999,-34.856212616],"type":"Point"}
}