{
  "type": "Feature",
  "properties": {
    "addr:full":"100 Eagle St Brisbane QLD 4000",
    "addr:housenumber":"100",
    "addr:postcode":"4000",
    "addr:street":"Eagle St",
    "iso:country":"AU",
    "sg:address":"100 Eagle St",
    "sg:city":"Brisbane",
    "sg:classifiers":[
        {
            "category":"Professional",
            "subcategory":"Management & Consulting",
            "type":"Services"
        }
    ],
    "sg:phone":"+61 7 3117 9599",
    "sg:postcode":"4000",
    "sg:province":"QLD",
    "sg:tags":[
        "consultant",
        "economic"
    ],
    "wof:name":"Marsden Jacob Associates",
    "wof:placetype":"venue"
},
  "geometry": {"coordinates":[153.030059814,-27.4675216675],"type":"Point"}
}