{
  "type": "Feature",
  "properties": {
    "addr:full":"240 Tenth St Mildura VIC 3500",
    "addr:housenumber":"240",
    "addr:postcode":"3500",
    "addr:street":"Tenth St",
    "iso:country":"AU",
    "sg:address":"240 Tenth St",
    "sg:city":"Mildura",
    "sg:classifiers":[
        {
            "category":"Food & Beverages",
            "subcategory":"Groceries & Convenience Stores",
            "type":"Retail Goods"
        }
    ],
    "sg:phone":"+61 3 5023 1575",
    "sg:postcode":"3500",
    "sg:province":"VIC",
    "wof:name":"Westside Valencia",
    "wof:placetype":"venue"
},
  "geometry": {"coordinates":[142.149658203,-34.1798477173],"type":"Point"}
}