{
  "type": "Feature",
  "properties": {
    "addr:full":"105 Barratt St Timboon VIC 3268",
    "addr:housenumber":"105",
    "addr:postcode":"3268",
    "addr:street":"Barratt St",
    "iso:country":"AU",
    "sg:address":"105 Barratt St",
    "sg:city":"Timboon",
    "sg:classifiers":[
        {
            "category":"Retail",
            "subcategory":"Auto Repair",
            "type":"Services"
        }
    ],
    "sg:phone":"+61 3 5598 3081",
    "sg:postcode":"3268",
    "sg:province":"VIC",
    "sg:tags":[
        "beater",
        "painter",
        "panel"
    ],
    "wof:name":"AAA Paint & Panel",
    "wof:placetype":"venue"
},
  "geometry": {"coordinates":[142.97654724099999,-38.4797401428],"type":"Point"}
}