{
  "type": "Feature",
  "properties": {
    "addr:full":"Suite 4 Cnr Fitzroy & Dragon Sts Warwick QLD 4370",
    "addr:housenumber":"cnr",
    "addr:postcode":"4370",
    "iso:country":"AU",
    "sg:address":"Suite 4 Cnr Fitzroy & Dragon Sts",
    "sg:city":"Warwick",
    "sg:classifiers":[
        {
            "category":"Health Services",
            "subcategory":"Health Practitioner",
            "type":"Services"
        }
    ],
    "sg:phone":"+61 400 880 302",
    "sg:postcode":"4370",
    "sg:province":"QLD",
    "sg:tags":[
        "homoeopath"
    ],
    "wof:name":"Rosemary Moulden",
    "wof:placetype":"venue"
},
  "geometry": {"coordinates":[152.02833557100001,-28.2134056091],"type":"Point"}
}