{
  "type": "Feature",
  "properties": {
    "iso:country":"AU",
    "sg:address":"Badger Creek Rd",
    "sg:city":"Badger Creek",
    "sg:classifiers":[
        {
            "category":"Social Services",
            "subcategory":"Child Care",
            "type":"Services"
        }
    ],
    "sg:phone":"+61 3 5962 3522",
    "sg:postcode":"3777",
    "sg:province":"VIC",
    "sg:tags":[
        "support",
        "health"
    ],
    "wof:name":"Maternal & Child Health Centres",
    "wof:placetype":"venue"
},
  "geometry": {"coordinates":[145.54328899999999,-37.686089],"type":"Point"}
}