{
  "type": "Feature",
  "properties": {
    "addr:full":"55 Weidlich Rd Greensborough VIC 3088",
    "addr:housenumber":"55",
    "addr:postcode":"3088",
    "addr:street":"Weidlich Rd",
    "iso:country":"AU",
    "sg:address":"55 Weidlich Rd",
    "sg:city":"Greensborough",
    "sg:classifiers":[
        {
            "category":"Food & Beverages",
            "subcategory":"Groceries & Convenience Stores",
            "type":"Retail Goods"
        }
    ],
    "sg:phone":"+61 3 9434 3470",
    "sg:postcode":"3088",
    "sg:province":"VIC",
    "wof:name":"Elmohamad Ali Milk Bar",
    "wof:placetype":"venue"
},
  "geometry": {"coordinates":[145.131027222,-37.6990318298],"type":"Point"}
}