{
  "type": "Feature",
  "properties": {
    "addr:full":"Marmion Ave Karrinyup WA 6018",
    "addr:postcode":"6018",
    "addr:street":"Marmion Ave",
    "iso:country":"AU",
    "sg:address":"Marmion Ave",
    "sg:city":"Karrinyup",
    "sg:classifiers":[
        {
            "category":"Sports & Exercise",
            "subcategory":"Golf",
            "type":"Entertainment"
        }
    ],
    "sg:phone":"+61 8 9447 7137",
    "sg:postcode":"6018",
    "sg:province":"WA",
    "sg:tags":[
        "club"
    ],
    "wof:name":"Hamersley Golf Course",
    "wof:placetype":"venue"
},
  "geometry": {"coordinates":[115.769142151,-31.8576583862],"type":"Point"}
}