{
  "type": "Feature",
  "properties": {
    "addr:full":"102 Balo St Moree NSW 2400",
    "addr:housenumber":"102",
    "addr:postcode":"2400",
    "addr:street":"Balo St",
    "iso:country":"AU",
    "sg:address":"102 Balo St",
    "sg:city":"Moree",
    "sg:classifiers":[
        {
            "category":"Autos & Motor Vehicles",
            "subcategory":"Automobile Sales",
            "type":"Retail Goods"
        }
    ],
    "sg:phone":"+61 2 6752 6666",
    "sg:postcode":"2400",
    "sg:province":"NSW",
    "sg:tags":[
        "car",
        "used"
    ],
    "wof:name":"Zannes Bros.",
    "wof:placetype":"venue"
},
  "geometry": {"coordinates":[149.84175109899999,-29.4650535583],"type":"Point"}
}