{
  "type": "Feature",
  "properties": {
    "addr:full":"86 Sydenham Rd Doubleview WA 6018",
    "addr:housenumber":"86",
    "addr:postcode":"6018",
    "addr:street":"Sydenham Rd",
    "iso:country":"AU",
    "sg:address":"86 Sydenham Rd",
    "sg:city":"Doubleview",
    "sg:classifiers":[
        {
            "category":"Personal",
            "subcategory":"Beauty Salon",
            "type":"Services"
        }
    ],
    "sg:phone":"+61 8 9244 7882",
    "sg:postcode":"6018",
    "sg:province":"WA",
    "wof:name":"Jeunesse Health & Beauty Clinic WA",
    "wof:placetype":"venue"
},
  "geometry": {"coordinates":[115.785133362,-31.9050960541],"type":"Point"}
}