{
  "type": "Feature",
  "properties": {
    "addr:full":"12 Elizabeth St Hamilton VIC 3300",
    "addr:housenumber":"12",
    "addr:postcode":"3300",
    "addr:street":"Elizabeth St",
    "iso:country":"AU",
    "sg:address":"12 Elizabeth St",
    "sg:city":"Hamilton",
    "sg:classifiers":[
        {
            "category":"Building & Trades",
            "subcategory":"Construction",
            "type":"Services"
        }
    ],
    "sg:phone":"+61 3 5572 1148",
    "sg:postcode":"3300",
    "sg:province":"VIC",
    "sg:tags":[
        "earth",
        "excavating",
        "moving",
        "contractor"
    ],
    "wof:name":"Hamilton Bobcat & Backhoe Service",
    "wof:placetype":"venue"
},
  "geometry": {"coordinates":[142.00776672399999,-37.737033844],"type":"Point"}
}