{
  "type": "Feature",
  "properties": {
    "addr:full":"PO Box 1409 Capalaba QLD 4157",
    "addr:postcode":"4157",
    "iso:country":"AU",
    "sg:address":"PO Box 1409",
    "sg:city":"Capalaba",
    "sg:classifiers":[
        {
            "category":"Professional",
            "subcategory":"Computer Services",
            "type":"Services"
        }
    ],
    "sg:phone":"+61 7 3009 0081",
    "sg:postcode":"4157",
    "sg:province":"QLD",
    "sg:tags":[
        "technical",
        "support"
    ],
    "wof:name":"1st Line Digital",
    "wof:placetype":"venue"
},
  "geometry": {"coordinates":[153.21090698200001,-27.5379695892],"type":"Point"}
}