{
  "type": "Feature",
  "properties": {
    "addr:full":"93 Francis St Richmond NSW 2753",
    "addr:housenumber":"93",
    "addr:postcode":"2753",
    "addr:street":"Francis St",
    "iso:country":"AU",
    "sg:address":"93 Francis St",
    "sg:city":"Richmond",
    "sg:classifiers":[
        {
            "category":"Health Services",
            "subcategory":"Health Practitioner",
            "type":"Services"
        }
    ],
    "sg:phone":"+61 2 4578 3384",
    "sg:postcode":"2753",
    "sg:province":"NSW",
    "sg:tags":[
        "osteopath"
    ],
    "wof:name":"Kate Kuilart",
    "wof:placetype":"venue"
},
  "geometry": {"coordinates":[150.75320434599999,-33.5957832336],"type":"Point"}
}