{
  "type": "Feature",
  "properties": {
    "iso:country":"AU",
    "sg:address":"136 Andersons Creek Rd",
    "sg:city":"Doncaster East",
    "sg:classifiers":[
        {
            "category":"Health Services",
            "subcategory":"Doctor",
            "type":"Services"
        }
    ],
    "sg:phone":"+61 3 9842 4333",
    "sg:postcode":"3109",
    "sg:province":"VIC",
    "sg:tags":[
        "medical",
        "practitioner"
    ],
    "wof:name":"Jarman Frederick (Rick)",
    "wof:placetype":"venue"
},
  "geometry": {"coordinates":[145.17257690400001,-37.765007019],"type":"Point"}
}