{
  "type": "Feature",
  "properties": {
    "addr:full":"Level 1, 459 Toorak Rd Toorak VIC 3142",
    "addr:housenumber":"459",
    "addr:postcode":"3142",
    "addr:street":"Toorak Rd",
    "iso:country":"AU",
    "sg:address":"Level 1, 459 Toorak Rd",
    "sg:city":"Toorak",
    "sg:classifiers":[
        {
            "category":"Professional",
            "subcategory":"Detective & Security Services",
            "type":"Services"
        }
    ],
    "sg:phone":"+61 1300 662 477",
    "sg:postcode":"3142",
    "sg:province":"VIC",
    "sg:tags":[
        "investigator"
    ],
    "wof:name":"Advanced Protective Services - Advanced Detective Services",
    "wof:placetype":"venue"
},
  "geometry": {"coordinates":[145.008102417,-37.8408470154],"type":"Point"}
}