{
  "type": "Feature",
  "properties": {
    "iso:country":"AU",
    "sg:address":"Cnr Bowen & Neil St",
    "sg:city":"Toowoomba City",
    "sg:classifiers":[
        {
            "category":"Professional",
            "subcategory":"Computer Services",
            "type":"Services"
        }
    ],
    "sg:phone":"+61 7 4642 1480",
    "sg:postcode":"4350",
    "sg:province":"QLD",
    "sg:tags":[
        "repairs",
        "upgrade",
        "equipment"
    ],
    "wof:name":"IT Solutions",
    "wof:placetype":"venue"
},
  "geometry": {"coordinates":[151.954056,-27.558409],"type":"Point"}
}