{
  "type": "Feature",
  "properties": {
    "iso:country":"AU",
    "sg:address":"Unit 2/ 19 Rafferty Rd",
    "sg:city":"Mandurah",
    "sg:classifiers":[
        {
            "category":"Retail",
            "subcategory":"Repair Shop",
            "type":"Services"
        }
    ],
    "sg:phone":"+61 8 9535 3244",
    "sg:postcode":"6210",
    "sg:province":"WA",
    "sg:tags":[
        "machine",
        "repairs",
        "part",
        "dryer",
        "washing"
    ],
    "wof:name":"Discount Appliance",
    "wof:placetype":"venue"
},
  "geometry": {"coordinates":[115.747131,-32.51849],"type":"Point"}
}