{
  "type": "Feature",
  "properties": {
    "addr:full":"68 Steven St Redcliffe QLD 4020",
    "addr:housenumber":"68",
    "addr:postcode":"4020",
    "addr:street":"Steven St",
    "iso:country":"AU",
    "sg:address":"68 Steven St",
    "sg:city":"Redcliffe",
    "sg:classifiers":[
        {
            "category":"Professional",
            "subcategory":"Business Services",
            "type":"Services"
        }
    ],
    "sg:phone":"+61 414 551 579",
    "sg:postcode":"4020",
    "sg:province":"QLD",
    "sg:tags":[
        "drafting"
    ],
    "wof:name":"Colin Roe Building Designer",
    "wof:placetype":"venue"
},
  "geometry": {"coordinates":[153.10833700000001,-27.220278],"type":"Point"}
}