{
  "type": "Feature",
  "properties": {
    "addr:full":"47 Elgin St Gunnedah NSW 2380",
    "addr:housenumber":"47",
    "addr:postcode":"2380",
    "addr:street":"Elgin St",
    "iso:country":"AU",
    "sg:address":"47 Elgin St",
    "sg:city":"Gunnedah",
    "sg:classifiers":[
        {
            "category":"Banks & Credit Unions",
            "subcategory":"Financial Services",
            "type":"Services"
        }
    ],
    "sg:phone":"+61 2 6742 2999",
    "sg:postcode":"2380",
    "sg:province":"NSW",
    "sg:tags":[
        "annuity",
        "rollover",
        "superannuation",
        "consultant"
    ],
    "wof:name":"Wayne Cadman Insurances & Financial Planning",
    "wof:placetype":"venue"
},
  "geometry": {"coordinates":[150.25479125999999,-30.9798583984],"type":"Point"}
}