{
  "type": "Feature",
  "properties": {
    "addr:full":"7 Marion St Parramatta NSW 2150",
    "addr:housenumber":"7",
    "addr:postcode":"2150",
    "addr:street":"Marion St",
    "iso:country":"AU",
    "sg:address":"7 Marion St",
    "sg:city":"Parramatta",
    "sg:classifiers":[
        {
            "category":"Autos & Motor Vehicles",
            "subcategory":"Auto Supplies",
            "type":"Retail Goods"
        }
    ],
    "sg:phone":"+61 2 9633 1654",
    "sg:postcode":"2150",
    "sg:province":"NSW",
    "sg:tags":[
        "battery",
        "automotive"
    ],
    "wof:name":"Baileys Neil Auto Electrical Service",
    "wof:placetype":"venue"
},
  "geometry": {"coordinates":[151.03533935600001,-33.8539199829],"type":"Point"}
}