{
  "type": "Feature",
  "properties": {
    "addr:full":"34 Tank St Gladstone QLD 4680",
    "addr:housenumber":"34",
    "addr:postcode":"4680",
    "addr:street":"Tank St",
    "iso:country":"AU",
    "sg:address":"34 Tank St",
    "sg:city":"Gladstone",
    "sg:classifiers":[
        {
            "category":"Real Estate",
            "subcategory":"Real Estate Agent",
            "type":"Services"
        }
    ],
    "sg:phone":"+61 7 4976 3777",
    "sg:postcode":"4680",
    "sg:province":"QLD",
    "wof:name":"PRDnationwide Gladstone",
    "wof:placetype":"venue"
},
  "geometry": {"coordinates":[151.260528564,-23.84815979],"type":"Point"}
}