{
  "type": "Feature",
  "properties": {
    "iso:country":"AU",
    "sg:address":"5 Marina Drv",
    "sg:city":"Patterson Lakes",
    "sg:classifiers":[
        {
            "category":"Sports & Exercise",
            "subcategory":"Ski Resort",
            "type":"Entertainment"
        }
    ],
    "sg:phone":"+61 3 9772 5247",
    "sg:postcode":"3197",
    "sg:province":"VIC",
    "sg:tags":[
        "propelled",
        "jet"
    ],
    "wof:name":"Jetfix",
    "wof:placetype":"venue"
},
  "geometry": {"coordinates":[145.145187378,-38.074131012],"type":"Point"}
}