{
  "type": "Feature",
  "properties": {
    "addr:full":"83 Mornington St Geelong North VIC 3215",
    "addr:housenumber":"83",
    "addr:postcode":"3215",
    "addr:street":"Mornington St",
    "iso:country":"AU",
    "sg:address":"83 Mornington St",
    "sg:city":"Geelong North",
    "sg:classifiers":[
        {
            "category":"Retail",
            "subcategory":"Auto Repair",
            "type":"Services"
        }
    ],
    "sg:phone":"+61 3 5277 0255",
    "sg:postcode":"3215",
    "sg:province":"VIC",
    "sg:tags":[
        "repairer",
        "motor",
        "engineer"
    ],
    "wof:name":"Tom's Automotive Centre",
    "wof:placetype":"venue"
},
  "geometry": {"coordinates":[144.34761047399999,-38.1158714294],"type":"Point"}
}