{
  "type": "Feature",
  "properties": {
    "iso:country":"AU",
    "sg:address":"45 Flinders St",
    "sg:city":"Adelaide",
    "sg:classifiers":[
        {
            "category":"Social Services",
            "subcategory":"Adult Care",
            "type":"Services"
        }
    ],
    "sg:phone":"+61 8 8232 5377",
    "sg:postcode":"5000",
    "sg:province":"SA",
    "sg:tags":[
        "aged"
    ],
    "wof:name":"Aged Rights Advocacy Service",
    "wof:placetype":"venue"
},
  "geometry": {"coordinates":[138.602386475,-34.9271621704],"type":"Point"}
}