{
  "type": "Feature",
  "properties": {
    "addr:full":"62 Smart St Fairfield NSW 2165",
    "addr:housenumber":"62",
    "addr:postcode":"2165",
    "addr:street":"Smart St",
    "iso:country":"AU",
    "sg:address":"62 Smart St",
    "sg:city":"Fairfield",
    "sg:classifiers":[
        {
            "category":"Health Services",
            "subcategory":"Optometrist",
            "type":"Services"
        }
    ],
    "sg:phone":"+61 2 9724 9772",
    "sg:postcode":"2165",
    "sg:province":"NSW",
    "wof:name":"Antonelli Giorgio",
    "wof:placetype":"venue"
},
  "geometry": {"coordinates":[150.95530700699999,-33.8678016663],"type":"Point"}
}