{
  "type": "Feature",
  "properties": {
    "iso:country":"AU",
    "sg:address":"PO Box 281",
    "sg:city":"Salamander Bay",
    "sg:classifiers":[
        {
            "category":"Shopping",
            "subcategory":"Mobile Phones",
            "type":"Retail Goods"
        }
    ],
    "sg:phone":"+61 413 550 713",
    "sg:postcode":"2317",
    "sg:province":"NSW",
    "sg:tags":[
        "telephone",
        "accessory"
    ],
    "wof:name":"Pocknall Industries Car Audio",
    "wof:placetype":"venue"
},
  "geometry": {"coordinates":[152.082092,-32.731091],"type":"Point"}
}