{
  "type": "Feature",
  "properties": {
    "addr:full":"106 West St Toowoomba QLD 4350",
    "addr:housenumber":"106",
    "addr:postcode":"4350",
    "addr:street":"West St",
    "iso:country":"AU",
    "sg:address":"106 West St",
    "sg:city":"Toowoomba",
    "sg:classifiers":[
        {
            "category":"Personal",
            "subcategory":"Beauty Salon",
            "type":"Services"
        }
    ],
    "sg:phone":"+61 7 4638 4299",
    "sg:postcode":"4350",
    "sg:province":"QLD",
    "sg:tags":[
        "wig",
        "hairpiece"
    ],
    "wof:name":"Next Vision Hair",
    "wof:placetype":"venue"
},
  "geometry": {"coordinates":[151.93804900000001,-27.562265],"type":"Point"}
}