{
  "type": "Feature",
  "properties": {
    "iso:country":"AU",
    "sg:address":"106 West St",
    "sg:city":"Toowoomba",
    "sg:classifiers":[
        {
            "category":"Personal",
            "subcategory":"Beauty Salon",
            "type":"Services"
        }
    ],
    "sg:phone":"+61 7 4638 4299",
    "sg:postcode":"4350",
    "sg:province":"QLD",
    "sg:tags":[
        "wig",
        "hairpiece"
    ],
    "wof:name":"Next Vision Hair",
    "wof:placetype":"venue"
},
  "geometry": {"coordinates":[151.938049,-27.562265],"type":"Point"}
}