{
  "type": "Feature",
  "properties": {
    "iso:country":"AU",
    "sg:address":"280 Wickham Rd",
    "sg:city":"Moorabbin",
    "sg:classifiers":[
        {
            "category":"Utilities",
            "subcategory":"Recycling",
            "type":"Services"
        }
    ],
    "sg:phone":"+61 3 9553 4153",
    "sg:postcode":"3189",
    "sg:province":"VIC",
    "wof:name":"General Metal Recycling Pty Ltd",
    "wof:placetype":"venue"
},
  "geometry": {"coordinates":[145.05743408199999,-37.9471130371],"type":"Point"}
}