{
  "type": "Feature",
  "properties": {
    "addr:full":"Cnr Coghlans & Rooneys Rd Warrnambool VIC 3280",
    "addr:postcode":"3280",
    "addr:street":"Cnr Coghlans & Rooneys Rd",
    "iso:country":"AU",
    "sg:address":"Cnr Coghlans & Rooneys Rd",
    "sg:city":"Warrnambool",
    "sg:classifiers":[
        {
            "category":"Manufacturing",
            "subcategory":"Building Materials",
            "type":"Manufacturing & Wholesale Goods"
        }
    ],
    "sg:phone":"+61 3 5561 7111",
    "sg:postcode":"3280",
    "sg:province":"VIC",
    "sg:tags":[
        "concrete",
        "product"
    ],
    "wof:name":"Western District Concrete Pipes & Products",
    "wof:placetype":"venue"
},
  "geometry": {"coordinates":[142.456756592,-38.3516120911],"type":"Point"}
}