{
  "type": "Feature",
  "properties": {
    "addr:full":"58 Katherine Ave Amaroo ACT 2914",
    "addr:housenumber":"58",
    "addr:postcode":"2914",
    "addr:street":"Katherine Ave",
    "iso:country":"AU",
    "sg:address":"58 Katherine Ave",
    "sg:city":"Amaroo",
    "sg:classifiers":[
        {
            "category":"Building & Trades",
            "subcategory":"Construction",
            "type":"Services"
        }
    ],
    "sg:phone":"+61 412 220 893",
    "sg:postcode":"2914",
    "sg:province":"ACT",
    "sg:tags":[
        "contractor"
    ],
    "wof:name":"G & P Corsini",
    "wof:placetype":"venue"
},
  "geometry": {"coordinates":[149.13328552199999,-35.1694717407],"type":"Point"}
}