{
  "type": "Feature",
  "properties": {
    "addr:full":"Unit1 16 Park Rd Milton QLD 4064",
    "addr:housenumber":"16",
    "addr:postcode":"4064",
    "addr:street":"Park Rd",
    "iso:country":"AU",
    "sg:address":"Unit1 16 Park Rd",
    "sg:city":"Milton",
    "sg:classifiers":[
        {
            "category":"Restaurant",
            "type":"Food & Drink"
        }
    ],
    "sg:phone":"+61 7 3367 0144",
    "sg:postcode":"4064",
    "sg:province":"QLD",
    "wof:name":"16th On The Park Restaurant Cafe Bar",
    "wof:placetype":"venue"
},
  "geometry": {"coordinates":[153.00450134299999,-27.4702587128],"type":"Point"}
}