{
  "type": "Feature",
  "properties": {
    "addr:full":"171 Comur St Yass NSW 2582",
    "addr:housenumber":"171",
    "addr:postcode":"2582",
    "addr:street":"Comur St",
    "iso:country":"AU",
    "sg:address":"171 Comur St",
    "sg:city":"Yass",
    "sg:classifiers":[
        {
            "category":"Cafe",
            "type":"Food & Drink"
        }
    ],
    "sg:phone":"+61 2 6226 1336",
    "sg:postcode":"2582",
    "sg:province":"NSW",
    "wof:name":"Liberty Cafe",
    "wof:placetype":"venue"
},
  "geometry": {"coordinates":[148.91253662099999,-34.8437995911],"type":"Point"}
}