{
  "type": "Feature",
  "properties": {
    "iso:country":"AU",
    "sg:address":"Upstairs 181 Keira St",
    "sg:city":"Wollongong",
    "sg:classifiers":[
        {
            "category":"Shopping",
            "subcategory":"Jewelry",
            "type":"Retail Goods"
        }
    ],
    "sg:phone":"+61 2 4226 1944",
    "sg:postcode":"2500",
    "sg:province":"NSW",
    "sg:tags":[
        "jeweller"
    ],
    "wof:name":"J & C Jewellers Gallery",
    "wof:placetype":"venue"
},
  "geometry": {"coordinates":[150.893494,-34.423878],"type":"Point"}
}