{
  "type": "Feature",
  "properties": {
    "addr:full":"2/ 24 Border Drv Mill Park VIC 3082",
    "addr:housenumber":"/ 24",
    "addr:postcode":"3082",
    "addr:street":"Border Drv",
    "iso:country":"AU",
    "sg:address":"2/ 24 Border Drv",
    "sg:city":"Mill Park",
    "sg:classifiers":[
        {
            "category":"Building & Trades",
            "subcategory":"Construction",
            "type":"Services"
        }
    ],
    "sg:phone":"+61 3 9782 5772",
    "sg:postcode":"3082",
    "sg:province":"VIC",
    "sg:tags":[
        "joiner",
        "carpenter"
    ],
    "wof:name":"DNB Constructions",
    "wof:placetype":"venue"
},
  "geometry": {"coordinates":[145.059616089,-37.6504936218],"type":"Point"}
}