{
  "type": "Feature",
  "properties": {
    "addr:full":"40a Wantirna Rd Ringwood VIC 3134",
    "addr:postcode":"3134",
    "addr:street":"Wantirna Rd",
    "iso:country":"AU",
    "sg:address":"40a Wantirna Rd",
    "sg:city":"Ringwood",
    "sg:classifiers":[
        {
            "category":"Professional",
            "subcategory":"Art Services",
            "type":"Services"
        }
    ],
    "sg:phone":"+61 3 9870 4226",
    "sg:postcode":"3134",
    "sg:province":"VIC",
    "sg:tags":[
        "picture",
        "frame",
        "framing"
    ],
    "wof:name":"Cohen Rick & Associates",
    "wof:placetype":"venue"
},
  "geometry": {"coordinates":[145.22714233400001,-37.8206825256],"type":"Point"}
}