{
  "type": "Feature",
  "properties": {
    "addr:full":"21 Hewitts Ave Thirroul NSW 2515",
    "addr:housenumber":"21",
    "addr:postcode":"2515",
    "addr:street":"Hewitts Ave",
    "iso:country":"AU",
    "sg:address":"21 Hewitts Ave",
    "sg:city":"Thirroul",
    "sg:classifiers":[
        {
            "category":"Professional",
            "subcategory":"Art Services",
            "type":"Services"
        }
    ],
    "sg:phone":"+61 2 4268 6855",
    "sg:postcode":"2515",
    "sg:province":"NSW",
    "sg:tags":[
        "graphic",
        "designer"
    ],
    "wof:name":"Website Designers",
    "wof:placetype":"venue"
},
  "geometry": {"coordinates":[150.914658,-34.321083],"type":"Point"}
}