{
  "type": "Feature",
  "properties": {
    "iso:country":"AU",
    "sg:address":"Swanport Plaza 186 Swanport Rd",
    "sg:city":"Murray Bridge",
    "sg:classifiers":[
        {
            "category":"Shopping",
            "subcategory":"Discount & Variety Stores",
            "type":"Retail Goods"
        }
    ],
    "sg:phone":"+61 8 8531 3933",
    "sg:postcode":"5253",
    "sg:province":"SA",
    "sg:tags":[
        "shop",
        "adult"
    ],
    "wof:name":"Afterglow Quality Adult Products",
    "wof:placetype":"venue"
},
  "geometry": {"coordinates":[139.286056519,-35.1480636597],"type":"Point"}
}