{
  "type": "Feature",
  "properties": {
    "addr:full":"189 Boundary Rd Mackay QLD 4740",
    "addr:housenumber":"189",
    "addr:postcode":"4740",
    "addr:street":"Boundary Rd",
    "iso:country":"AU",
    "sg:address":"189 Boundary Rd",
    "sg:city":"Mackay",
    "sg:classifiers":[
        {
            "category":"Manufacturing",
            "subcategory":"Retail Goods",
            "type":"Manufacturing & Wholesale Goods"
        }
    ],
    "sg:phone":"+61 7 4952 8000",
    "sg:postcode":"4740",
    "sg:province":"QLD",
    "sg:tags":[
        "merchant",
        "pump",
        "mfrs"
    ],
    "wof:name":"Paramount Hire",
    "wof:placetype":"venue"
},
  "geometry": {"coordinates":[149.14288300000001,-21.172796],"type":"Point"}
}