{
  "type": "Feature",
  "properties": {
    "iso:country":"AU",
    "sg:address":"Shop/ 2 110 Walker St",
    "sg:city":"North Sydney",
    "sg:classifiers":[
        {
            "category":"Professional",
            "subcategory":"Computer Services",
            "type":"Services"
        }
    ],
    "sg:phone":"+61 2 9929 2868",
    "sg:postcode":"2060",
    "sg:province":"NSW",
    "sg:tags":[
        "equipment",
        "networking",
        "installation"
    ],
    "wof:name":"Digital Star Australia Pty Ltd",
    "wof:placetype":"venue"
},
  "geometry": {"coordinates":[151.208786011,-33.8384933472],"type":"Point"}
}