{
  "type": "Feature",
  "properties": {
    "addr:full":"Indooroopilly Shopping Centre 322 Moggill Rd Indooroopilly QLD 4068",
    "addr:housenumber":"322",
    "addr:postcode":"4068",
    "addr:street":"Moggill Rd",
    "iso:country":"AU",
    "sg:address":"Indooroopilly Shopping Centre 322 Moggill Rd",
    "sg:city":"Indooroopilly",
    "sg:classifiers":[
        {
            "category":"Professional",
            "subcategory":"Accounting & Tax Preparation",
            "type":"Services"
        }
    ],
    "sg:phone":"+61 7 3720 2901",
    "sg:postcode":"4068",
    "sg:province":"QLD",
    "sg:tags":[
        "consultant",
        "taxation"
    ],
    "wof:name":"ITP Income Tax Professionals",
    "wof:placetype":"venue"
},
  "geometry": {"coordinates":[152.97233581500001,-27.4977741241],"type":"Point"}
}