{
  "type": "Feature",
  "properties": {
    "addr:full":"Level 13, 160 Queen St Melbourne VIC 3000",
    "addr:housenumber":"160",
    "addr:postcode":"3000",
    "addr:street":"Queen St",
    "iso:country":"AU",
    "sg:address":"Level 13, 160 Queen St",
    "sg:city":"Melbourne",
    "sg:classifiers":[
        {
            "category":"Community Center",
            "subcategory":"Senior",
            "type":"Public Place"
        }
    ],
    "sg:phone":"+61 1800 002 209",
    "sg:postcode":"3000",
    "sg:province":"VIC",
    "sg:tags":[
        "finance",
        "equity"
    ],
    "wof:name":"Stockwatch Report",
    "wof:placetype":"venue"
},
  "geometry": {"coordinates":[144.96078491200001,-37.8148651123],"type":"Point"}
}