{
  "type": "Feature",
  "properties": {
    "addr:full":"67 Pitt Ave Riverside TAS 7250",
    "addr:housenumber":"67",
    "addr:postcode":"7250",
    "addr:street":"Pitt Ave",
    "iso:country":"AU",
    "sg:address":"67 Pitt Ave",
    "sg:city":"Riverside",
    "sg:classifiers":[
        {
            "category":"Building & Trades",
            "subcategory":"Cleaning & Sanitation",
            "type":"Services"
        }
    ],
    "sg:phone":"+61 3 6327 2925",
    "sg:postcode":"7250",
    "sg:province":"TAS",
    "sg:tags":[
        "cleaner",
        "repairer",
        "roof"
    ],
    "wof:name":"Stagg N G",
    "wof:placetype":"venue"
},
  "geometry": {"coordinates":[147.10289001500001,-41.4266624451],"type":"Point"}
}