{
  "type": "Feature",
  "properties": {
    "addr:full":"19 Old Geelong Rd Hoppers Crossing VIC 3029",
    "addr:housenumber":"19",
    "addr:postcode":"3029",
    "addr:street":"Old Geelong Rd",
    "iso:country":"AU",
    "sg:address":"19 Old Geelong Rd",
    "sg:city":"Hoppers Crossing",
    "sg:classifiers":[
        {
            "category":"Food & Beverages",
            "subcategory":"Liquor & Beverages",
            "type":"Retail Goods"
        }
    ],
    "sg:phone":"+61 3 9749 3952",
    "sg:postcode":"3029",
    "sg:province":"VIC",
    "sg:tags":[
        "store"
    ],
    "wof:name":"Hoppers Crossing Cellars",
    "wof:placetype":"venue"
},
  "geometry": {"coordinates":[144.70013399999999,-37.882912],"type":"Point"}
}