{
  "type": "Feature",
  "properties": {
    "addr:full":"37 Angus Ave Kandos NSW 2848",
    "addr:housenumber":"37",
    "addr:postcode":"2848",
    "addr:street":"Angus Ave",
    "iso:country":"AU",
    "sg:address":"37 Angus Ave",
    "sg:city":"Kandos",
    "sg:classifiers":[
        {
            "category":"Fast Food",
            "type":"Food & Drink"
        }
    ],
    "sg:phone":"+61 2 6379 4180",
    "sg:postcode":"2848",
    "sg:province":"NSW",
    "sg:tags":[
        "away",
        "take"
    ],
    "wof:name":"Clock Stop Cafe",
    "wof:placetype":"venue"
},
  "geometry": {"coordinates":[149.97500600000001,-32.858929],"type":"Point"}
}