{
  "type": "Feature",
  "properties": {
    "addr:full":"268 Macquarie St Dubbo NSW 2830",
    "addr:housenumber":"268",
    "addr:postcode":"2830",
    "addr:street":"Macquarie St",
    "iso:country":"AU",
    "sg:address":"268 Macquarie St",
    "sg:city":"Dubbo",
    "sg:classifiers":[
        {
            "category":"Banks & Credit Unions",
            "subcategory":"Financial Services",
            "type":"Services"
        }
    ],
    "sg:phone":"+61 2 6884 2222",
    "sg:postcode":"2830",
    "sg:province":"NSW",
    "sg:tags":[
        "annuity",
        "rollover",
        "superannuation",
        "consultant"
    ],
    "wof:name":"Dunshea Financial Services",
    "wof:placetype":"venue"
},
  "geometry": {"coordinates":[148.600631714,-32.2518768311],"type":"Point"}
}