{
  "type": "Feature",
  "properties": {
    "addr:full":"182 Beaudesert Rd Moorooka QLD 4105",
    "addr:housenumber":"182",
    "addr:postcode":"4105",
    "addr:street":"Beaudesert Rd",
    "iso:country":"AU",
    "sg:address":"182 Beaudesert Rd",
    "sg:city":"Moorooka",
    "sg:classifiers":[
        {
            "category":"Banks & Credit Unions",
            "subcategory":"Bank",
            "type":"Services"
        }
    ],
    "sg:phone":"+61 13 20 32",
    "sg:postcode":"4105",
    "sg:province":"QLD",
    "wof:name":"Westpac",
    "wof:placetype":"venue"
},
  "geometry": {"coordinates":[153.02496337900001,-27.5326461792],"type":"Point"}
}