{
  "type": "Feature",
  "properties": {
    "addr:full":"149 South Tce Fremantle WA 6160",
    "addr:housenumber":"149",
    "addr:postcode":"6160",
    "addr:street":"South Tce",
    "iso:country":"AU",
    "sg:address":"149 South Tce",
    "sg:city":"Fremantle",
    "sg:classifiers":[
        {
            "category":"Home & Garden",
            "subcategory":"Building Materials",
            "type":"Retail Goods"
        }
    ],
    "sg:phone":"+61 8 9336 2615",
    "sg:postcode":"6160",
    "sg:province":"WA",
    "sg:tags":[
        "merchant",
        "glass",
        "glazier"
    ],
    "sg:website":"http://www.fremantleglass.com.au",
    "wof:name":"Fremantle Glass Pty Ltd",
    "wof:placetype":"venue"
},
  "geometry": {"coordinates":[115.75592,-32.05257],"type":"Point"}
}