{
  "type": "Feature",
  "properties": {
    "iso:country":"AU",
    "sg:address":"1 Wyperfeld Ave",
    "sg:city":"Taylors Lakes",
    "sg:classifiers":[
        {
            "category":"Health Services",
            "subcategory":"Doctor",
            "type":"Services"
        }
    ],
    "sg:phone":"+61 3 9390 2400",
    "sg:postcode":"3038",
    "sg:province":"VIC",
    "sg:tags":[
        "medical",
        "practitioner"
    ],
    "wof:name":"Ooi Richard K M Dr",
    "wof:placetype":"venue"
},
  "geometry": {"coordinates":[144.80371099999999,-37.71146],"type":"Point"}
}