{
  "type": "Feature",
  "properties": {
    "iso:country":"AU",
    "sg:address":"30 Kingsway Ave",
    "sg:city":"Rankin Park",
    "sg:classifiers":[
        {
            "category":"Retail",
            "subcategory":"Storage",
            "type":"Services"
        }
    ],
    "sg:phone":"+61 2 4957 4375",
    "sg:postcode":"2287",
    "sg:province":"NSW",
    "sg:tags":[
        "removal",
        "furniture"
    ],
    "wof:name":"Johns Removals & Storage",
    "wof:placetype":"venue"
},
  "geometry": {"coordinates":[151.68655395499999,-32.9273681641],"type":"Point"}
}