{
  "type": "Feature",
  "properties": {
    "iso:country":"AU",
    "sg:address":"199 Clarendon St",
    "sg:city":"South Melbourne",
    "sg:classifiers":[
        {
            "category":"Retail",
            "subcategory":"Funeral Services",
            "type":"Services"
        }
    ],
    "sg:phone":"+61 3 9690 2200",
    "sg:postcode":"3205",
    "sg:province":"VIC",
    "sg:tags":[
        "director"
    ],
    "wof:name":"McKenzie Roderick",
    "wof:placetype":"venue"
},
  "geometry": {"coordinates":[144.959656,-37.830692],"type":"Point"}
}