{
  "type": "Feature",
  "properties": {
    "iso:country":"AU",
    "sg:address":"63 Elizabeth St",
    "sg:city":"Aitkenvale",
    "sg:classifiers":[
        {
            "category":"Personal",
            "subcategory":"Beauty Salon",
            "type":"Services"
        }
    ],
    "sg:phone":"+61 7 4775 3963",
    "sg:postcode":"4814",
    "sg:province":"QLD",
    "sg:tags":[
        "hairdresser"
    ],
    "wof:name":"Zarnies For Hair",
    "wof:placetype":"venue"
},
  "geometry": {"coordinates":[146.764633,-19.298279],"type":"Point"}
}