{
  "type": "Feature",
  "properties": {
    "addr:full":"U5/ 17 Mosey St Landsdale WA 6065",
    "addr:postcode":"6065",
    "addr:street":"U5 / 17 Mosey St",
    "iso:country":"AU",
    "sg:address":"U5/ 17 Mosey St",
    "sg:city":"Landsdale",
    "sg:classifiers":[
        {
            "category":"Professional",
            "subcategory":"Engineering",
            "type":"Services"
        }
    ],
    "sg:phone":"+61 8 9302 1978",
    "sg:postcode":"6065",
    "sg:province":"WA",
    "sg:tags":[
        "engineer"
    ],
    "wof:name":"Close Tolerance Engineering",
    "wof:placetype":"venue"
},
  "geometry": {"coordinates":[115.84105682400001,-31.8028049469],"type":"Point"}
}