{
  "type": "Feature",
  "properties": {
    "addr:full":"Shop 9, Narangba Valley Shpng Cntr, Young Rd Narangba QLD 4504",
    "addr:housenumber":"shop 9",
    "addr:postcode":"4504",
    "addr:street":"Young Rd",
    "iso:country":"AU",
    "sg:address":"Shop 9, Narangba Valley Shpng Cntr, Young Rd",
    "sg:city":"Narangba",
    "sg:classifiers":[
        {
            "category":"Health Services",
            "subcategory":"Dentist",
            "type":"Services"
        }
    ],
    "sg:phone":"+61 7 3886 7056",
    "sg:postcode":"4504",
    "sg:province":"QLD",
    "wof:name":"Narangba Valley Dental",
    "wof:placetype":"venue"
},
  "geometry": {"coordinates":[152.925582886,-27.1783790588],"type":"Point"}
}