{
  "type": "Feature",
  "properties": {
    "iso:country":"AU",
    "sg:address":"Government Rd",
    "sg:city":"Hahndorf",
    "sg:classifiers":[
        {
            "category":"Building & Trades",
            "subcategory":"Construction",
            "type":"Services"
        }
    ],
    "sg:phone":"+61 8 8388 7547",
    "sg:postcode":"5245",
    "sg:province":"SA",
    "sg:tags":[
        "earth",
        "excavating",
        "moving",
        "contractor"
    ],
    "wof:name":"Coles Earthmoving",
    "wof:placetype":"venue"
},
  "geometry": {"coordinates":[138.809890747,-35.0293006897],"type":"Point"}
}