{
  "type": "Feature",
  "properties": {
    "addr:full":"4 James Crt Miners Rest VIC 3352",
    "addr:housenumber":"4",
    "addr:postcode":"3352",
    "addr:street":"James Crt",
    "iso:country":"AU",
    "sg:address":"4 James Crt",
    "sg:city":"Miners Rest",
    "sg:classifiers":[
        {
            "category":"Home & Garden",
            "subcategory":"Carpets & Floor Coverings",
            "type":"Retail Goods"
        }
    ],
    "sg:phone":"+61 419 101 813",
    "sg:postcode":"3352",
    "sg:province":"VIC",
    "sg:tags":[
        "tile",
        "wall",
        "layer"
    ],
    "wof:name":"A. J. W. Tilers",
    "wof:placetype":"venue"
},
  "geometry": {"coordinates":[143.79676799999999,-37.477642],"type":"Point"}
}