{
  "type": "Feature",
  "properties": {
    "iso:country":"AU",
    "sg:address":"Shop 1/ 164 Yarra St",
    "sg:city":"Warrandyte",
    "sg:classifiers":[
        {
            "category":"Fast Food",
            "type":"Food & Drink"
        }
    ],
    "sg:phone":"+61 3 9844 4144",
    "sg:postcode":"3113",
    "sg:province":"VIC",
    "sg:tags":[
        "away",
        "take"
    ],
    "wof:name":"Seafood By The Yarra",
    "wof:placetype":"venue"
},
  "geometry": {"coordinates":[145.21932983400001,-37.7378921509],"type":"Point"}
}