{
  "type": "Feature",
  "properties": {
    "addr:full":"Unit 3, 22 Oramzi Rd Girraween NSW 2145",
    "addr:housenumber":"22",
    "addr:postcode":"2145",
    "addr:street":"Oramzi Rd",
    "iso:country":"AU",
    "sg:address":"Unit 3, 22 Oramzi Rd",
    "sg:city":"Girraween",
    "sg:classifiers":[
        {
            "category":"Building & Trades",
            "subcategory":"Construction",
            "type":"Services"
        }
    ],
    "sg:phone":"+61 2 9636 9111",
    "sg:postcode":"2145",
    "sg:province":"NSW",
    "sg:tags":[
        "insulation",
        "contractor"
    ],
    "wof:name":"All Weather Insulation",
    "wof:placetype":"venue"
},
  "geometry": {"coordinates":[150.94212341299999,-33.7974586487],"type":"Point"}
}