{
  "type": "Feature",
  "properties": {
    "iso:country":"AU",
    "sg:address":"Standish Ave",
    "sg:city":"Oakhurst",
    "sg:classifiers":[
        {
            "category":"Social Services",
            "subcategory":"Child Care",
            "type":"Services"
        }
    ],
    "sg:phone":"+61 2 9628 1923",
    "sg:postcode":"2761",
    "sg:province":"NSW",
    "sg:tags":[
        "support",
        "health"
    ],
    "wof:name":"Early Childhood Health Centres",
    "wof:placetype":"venue"
},
  "geometry": {"coordinates":[150.82959,-33.740456],"type":"Point"}
}