{
  "type": "Feature",
  "properties": {
    "addr:full":"Shop 75 Mirrabooka Shopng Sq Mirrabooka WA 6061",
    "addr:housenumber":"shop 75",
    "addr:postcode":"6061",
    "addr:street":"Shopng Sq",
    "iso:country":"AU",
    "sg:address":"Shop 75 Mirrabooka Shopng Sq",
    "sg:city":"Mirrabooka",
    "sg:classifiers":[
        {
            "category":"Casinos & Gambling",
            "type":"Entertainment"
        }
    ],
    "sg:phone":"+61 8 9344 6750",
    "sg:postcode":"6061",
    "sg:province":"WA",
    "sg:tags":[
        "lottery",
        "agent"
    ],
    "wof:name":"Jackpot Lottery Centre",
    "wof:placetype":"venue"
},
  "geometry": {"coordinates":[115.85492706300001,-31.853269577],"type":"Point"}
}