{
  "type": "Feature",
  "properties": {
    "addr:full":"Shop 1034 Carindale Shopping Centre Carindale QLD 4152",
    "addr:housenumber":"1034",
    "addr:postcode":"4152",
    "iso:country":"AU",
    "sg:address":"Shop 1034 Carindale Shopping Centre",
    "sg:city":"Carindale",
    "sg:classifiers":[
        {
            "category":"Shopping",
            "subcategory":"Clothing, Apparel, & Fashions",
            "type":"Retail Goods"
        }
    ],
    "sg:phone":"+61 7 3398 9527",
    "sg:postcode":"4152",
    "sg:province":"QLD",
    "sg:tags":[
        "jean"
    ],
    "wof:name":"JeansWest",
    "wof:placetype":"venue"
},
  "geometry": {"coordinates":[153.10345459000001,-27.5023994446],"type":"Point"}
}