{
  "type": "Feature",
  "properties": {
    "iso:country":"AU",
    "sg:address":"330 Old Geelong Rd",
    "sg:city":"Hoppers Crossing",
    "sg:classifiers":[
        {
            "category":"Home & Garden",
            "subcategory":"Hardware",
            "type":"Retail Goods"
        }
    ],
    "sg:phone":"+61 3 9368 9100",
    "sg:postcode":"3029",
    "sg:province":"VIC",
    "sg:tags":[
        "plumber",
        "supply"
    ],
    "wof:name":"Benton's Plumbtec",
    "wof:placetype":"venue"
},
  "geometry": {"coordinates":[144.727386,-37.871143],"type":"Point"}
}