{
  "type": "Feature",
  "properties": {
    "addr:full":"308a Bay Rd Cheltenham VIC 3192",
    "addr:housenumber":"308a",
    "addr:postcode":"3192",
    "addr:street":"Bay Rd",
    "iso:country":"AU",
    "sg:address":"308a Bay Rd",
    "sg:city":"Cheltenham",
    "sg:classifiers":[
        {
            "category":"Professional",
            "subcategory":"Accounting & Tax Preparation",
            "type":"Services"
        }
    ],
    "sg:phone":"+61 3 9583 8066",
    "sg:postcode":"3192",
    "sg:province":"VIC",
    "sg:tags":[
        "accountant",
        "auditor"
    ],
    "wof:name":"Buchanan Ross Pty Ltd",
    "wof:placetype":"venue"
},
  "geometry": {"coordinates":[145.03958129899999,-37.956073761],"type":"Point"}
}