{
  "type": "Feature",
  "properties": {
    "iso:country":"AU",
    "sg:address":"20 Imperial Ave",
    "sg:city":"Sunshine North",
    "sg:classifiers":[
        {
            "category":"Transit Center",
            "subcategory":"Freight",
            "type":"Transportation"
        }
    ],
    "sg:phone":"+61 3 9364 3288",
    "sg:postcode":"3020",
    "sg:province":"VIC",
    "sg:tags":[
        "forklift",
        "truck"
    ],
    "wof:name":"Brooklyn Mechanical Services",
    "wof:placetype":"venue"
},
  "geometry": {"coordinates":[144.83807400000001,-37.755581],"type":"Point"}
}