{
  "type": "Feature",
  "properties": {
    "addr:full":"9 Stuart Rd Dulwich SA 5065",
    "addr:housenumber":"9",
    "addr:postcode":"5065",
    "addr:street":"Stuart Rd",
    "iso:country":"AU",
    "sg:address":"9 Stuart Rd",
    "sg:city":"Dulwich",
    "sg:classifiers":[
        {
            "category":"Health Services",
            "subcategory":"Doctor",
            "type":"Services"
        }
    ],
    "sg:phone":"+61 8 8332 6362",
    "sg:postcode":"5065",
    "sg:province":"SA",
    "sg:tags":[
        "medical",
        "practitioner"
    ],
    "wof:name":"Eastern Suburbs Eye Centre",
    "wof:placetype":"venue"
},
  "geometry": {"coordinates":[138.631515503,-34.9355430603],"type":"Point"}
}