{
  "type": "Feature",
  "properties": {
    "addr:full":"9 Creek Rd Tannum Sands QLD 4680",
    "addr:housenumber":"9",
    "addr:postcode":"4680",
    "addr:street":"Creek Rd",
    "iso:country":"AU",
    "sg:address":"9 Creek Rd",
    "sg:city":"Tannum Sands",
    "sg:classifiers":[
        {
            "category":"Shopping",
            "subcategory":"Music",
            "type":"Retail Goods"
        }
    ],
    "sg:phone":"+61 7 4972 2538",
    "sg:postcode":"4680",
    "sg:province":"QLD",
    "sg:tags":[
        "store"
    ],
    "wof:name":"Gladstone Music Centre",
    "wof:placetype":"venue"
},
  "geometry": {"coordinates":[151.374237061,-23.9532012939],"type":"Point"}
}