{
  "type": "Feature",
  "properties": {
    "iso:country":"AU",
    "sg:address":"Lot 4",
    "sg:city":", Mason Rd, Kwinana Beach",
    "sg:classifiers":[
        {
            "category":"Government",
            "subcategory":"Department Of Motor Vehicles",
            "type":"Public Place"
        }
    ],
    "sg:phone":"+61 8 9439 2362",
    "sg:postcode":"6167",
    "sg:province":"WA",
    "sg:tags":[
        "tank",
        "cleaning"
    ],
    "wof:name":"Tox Free Waste Management Solutions",
    "wof:placetype":"venue"
},
  "geometry": {"coordinates":[115.778137,-32.231857],"type":"Point"}
}