{
  "type": "Feature",
  "properties": {
    "addr:full":"60 Weld St Beaconsfield TAS 7270",
    "addr:housenumber":"60",
    "addr:postcode":"7270",
    "addr:street":"Weld St",
    "iso:country":"AU",
    "sg:address":"60 Weld St",
    "sg:city":"Beaconsfield",
    "sg:classifiers":[
        {
            "category":"Food & Beverages",
            "subcategory":"Supermarket",
            "type":"Retail Goods"
        }
    ],
    "sg:phone":"+61 3 6383 1193",
    "sg:postcode":"7270",
    "sg:province":"TAS",
    "sg:tags":[
        "grocery",
        "store"
    ],
    "wof:name":"Cyns Corner Store",
    "wof:placetype":"venue"
},
  "geometry": {"coordinates":[146.82215881400001,-41.2058906555],"type":"Point"}
}