{
  "type": "Feature",
  "properties": {
    "iso:country":"AU",
    "sg:address":"14-40 Pascoe Vale Road",
    "sg:city":"Moonee Ponds",
    "sg:classifiers":[
        {
            "category":"Health Services",
            "subcategory":"Health Practitioner",
            "type":"Services"
        }
    ],
    "sg:phone":"+61 3 9326 0168",
    "sg:postcode":"3039",
    "sg:province":"VIC",
    "sg:tags":[
        "physiotherapist"
    ],
    "wof:name":"Synergy Health Group",
    "wof:placetype":"venue"
},
  "geometry": {"coordinates":[144.925262,-37.766003],"type":"Point"}
}