{
  "type": "Feature",
  "properties": {
    "iso:country":"AU",
    "sg:address":"16 Wimpole Crs",
    "sg:city":"Bellfield",
    "sg:classifiers":[
        {
            "category":"Professional",
            "subcategory":"Art Services",
            "type":"Services"
        }
    ],
    "sg:phone":"+61 3 9449 1067",
    "sg:postcode":"3081",
    "sg:province":"VIC",
    "sg:tags":[
        "decorator",
        "painter"
    ],
    "wof:name":"Earth Architectural Painting",
    "wof:placetype":"venue"
},
  "geometry": {"coordinates":[145.03782653799999,-37.7502212524],"type":"Point"}
}