{
  "type": "Feature",
  "properties": {
    "iso:country":"AU",
    "sg:address":"5 Egan Pl",
    "sg:city":"Beacon Hill",
    "sg:classifiers":[
        {
            "category":"Professional",
            "subcategory":"Computer Services",
            "type":"Services"
        }
    ],
    "sg:phone":"+61 2 9451 1307",
    "sg:postcode":"2100",
    "sg:province":"NSW",
    "sg:tags":[
        "consultant",
        "system"
    ],
    "wof:name":"E B Consulting Pty Ltd",
    "wof:placetype":"venue"
},
  "geometry": {"coordinates":[151.260986328,-33.7498092651],"type":"Point"}
}