{
  "type": "Feature",
  "properties": {
    "addr:full":"Airport Terminal Southern Cross Drv Ballina NSW 2478",
    "addr:postcode":"2478",
    "addr:street":"Southern Cross Drv",
    "iso:country":"AU",
    "sg:address":"Airport Terminal Southern Cross Drv",
    "sg:city":"Ballina",
    "sg:classifiers":[
        {
            "category":"Airline",
            "type":"Transportation"
        }
    ],
    "sg:phone":"+61 2 6686 8385",
    "sg:postcode":"2478",
    "sg:province":"NSW",
    "sg:tags":[
        "agent"
    ],
    "wof:name":"North Coast Airline Services",
    "wof:placetype":"venue"
},
  "geometry": {"coordinates":[153.55601501500001,-28.8523006439],"type":"Point"}
}