{
  "type": "Feature",
  "properties": {
    "addr:full":"Erldunda Crt Lilydale VIC 3140",
    "addr:postcode":"3140",
    "addr:street":"Erldunda Crt",
    "iso:country":"AU",
    "sg:address":"Erldunda Crt",
    "sg:city":"Lilydale",
    "sg:classifiers":[
        {
            "category":"Education",
            "subcategory":"Kindergarten",
            "type":"Public Place"
        }
    ],
    "sg:phone":"+61 3 9735 0110",
    "sg:postcode":"3140",
    "sg:province":"VIC",
    "sg:tags":[
        "pre-schools"
    ],
    "wof:name":"Lilydale North Pre-School Centre",
    "wof:placetype":"venue"
},
  "geometry": {"coordinates":[145.339355469,-37.7486343384],"type":"Point"}
}