{
  "type": "Feature",
  "properties": {
    "iso:country":"AU",
    "sg:address":"9 Santiago St",
    "sg:city":"Doncaster",
    "sg:classifiers":[
        {
            "category":"Professional",
            "subcategory":"Employment Agencies",
            "type":"Services"
        }
    ],
    "sg:phone":"+61 405 399 684",
    "sg:postcode":"3108",
    "sg:province":"VIC",
    "sg:tags":[
        "entertainer",
        "agent"
    ],
    "wof:name":"Impressive Event Management",
    "wof:placetype":"venue"
},
  "geometry": {"coordinates":[145.11102294899999,-37.7903060913],"type":"Point"}
}