{
  "type": "Feature",
  "properties": {
    "addr:full":"Cnr The Esplanade & Hanlon St Surfers Paradise QLD 4217",
    "addr:postcode":"4217",
    "addr:street":"Cnr The Esplanade & Hanlon St",
    "iso:country":"AU",
    "sg:address":"Cnr The Esplanade & Hanlon St",
    "sg:city":"Surfers Paradise",
    "sg:classifiers":[
        {
            "category":"Arena",
            "subcategory":"Sports Club",
            "type":"Entertainment"
        }
    ],
    "sg:phone":"+61 7 5531 5966",
    "sg:postcode":"4217",
    "sg:province":"QLD",
    "sg:tags":[
        "life",
        "surfing",
        "saving"
    ],
    "wof:name":"Surfers Paradise Surf Life Saving Club",
    "wof:placetype":"venue"
},
  "geometry": {"coordinates":[153.430984497,-28.0007247925],"type":"Point"}
}