{
  "type": "Feature",
  "properties": {
    "addr:full":"Commonwealth Bank Building,377 Anzac Pde Kingsford NSW 2032",
    "addr:housenumber":"377",
    "addr:postcode":"2032",
    "addr:street":"Anzac Pde",
    "iso:country":"AU",
    "sg:address":"Commonwealth Bank Building,377 Anzac Pde",
    "sg:city":"Kingsford",
    "sg:classifiers":[
        {
            "category":"Health Services",
            "subcategory":"Dentist",
            "type":"Services"
        }
    ],
    "sg:phone":"+61 2 9663 3255",
    "sg:postcode":"2032",
    "sg:province":"NSW",
    "sg:tags":[
        "dental",
        "prosthetist"
    ],
    "wof:name":"Calpis Nicholas",
    "wof:placetype":"venue"
},
  "geometry": {"coordinates":[151.22787475600001,-33.9244537354],"type":"Point"}
}