{
  "type": "Feature",
  "properties": {
    "iso:country":"AU",
    "sg:address":"Lvl 1 220 Cambridge St",
    "sg:city":"Wembley",
    "sg:classifiers":[
        {
            "category":"Real Estate",
            "subcategory":"Developer",
            "type":"Services"
        }
    ],
    "sg:phone":"+61 8 9489 6260",
    "sg:postcode":"6014",
    "sg:province":"WA",
    "sg:tags":[
        "development"
    ],
    "wof:name":"Covenant Securities Pty Ltd",
    "wof:placetype":"venue"
},
  "geometry": {"coordinates":[115.82083129900001,-31.9405918121],"type":"Point"}
}