{
  "type": "Feature",
  "properties": {
    "iso:country":"AU",
    "sg:address":"23 Spring Park Rd",
    "sg:city":"Midland",
    "sg:classifiers":[
        {
            "category":"Real Estate",
            "subcategory":"Surveying",
            "type":"Services"
        }
    ],
    "sg:phone":"+61 8 9250 2261",
    "sg:postcode":"6056",
    "sg:province":"WA",
    "sg:tags":[
        "surveyor",
        "land"
    ],
    "wof:name":"Scanlan Surveys Pty Ltd",
    "wof:placetype":"venue"
},
  "geometry": {"coordinates":[116.001731873,-31.8862514496],"type":"Point"}
}