{
  "type": "Feature",
  "properties": {
    "addr:full":"4 Malabar Crt Narre Warren South VIC 3805",
    "addr:housenumber":"4",
    "addr:postcode":"3805",
    "addr:street":"Malabar Crt",
    "iso:country":"AU",
    "sg:address":"4 Malabar Crt",
    "sg:city":"Narre Warren South",
    "sg:classifiers":[
        {
            "category":"Building & Trades",
            "subcategory":"Construction",
            "type":"Services"
        }
    ],
    "sg:phone":"+61 3 8790 6860",
    "sg:postcode":"3805",
    "sg:province":"VIC",
    "sg:tags":[
        "spouting",
        "guttering"
    ],
    "wof:name":"Pronto Roofing",
    "wof:placetype":"venue"
},
  "geometry": {"coordinates":[145.286697,-38.05431],"type":"Point"}
}