{
  "type": "Feature",
  "properties": {
    "addr:full":"Suit 310, 3rd Flr Professional Suites Westfield Miranda NSW 2228",
    "addr:housenumber":"310;flr",
    "addr:postcode":"2228",
    "addr:street":"3Rd",
    "iso:country":"AU",
    "sg:address":"Suit 310, 3rd Flr Professional Suites Westfield",
    "sg:city":"Miranda",
    "sg:classifiers":[
        {
            "category":"Personal",
            "subcategory":"Hair Removal",
            "type":"Services"
        }
    ],
    "sg:phone":"+61 2 9525 7887",
    "sg:postcode":"2228",
    "sg:province":"NSW",
    "wof:name":"Joanne Lea Salon",
    "wof:placetype":"venue"
},
  "geometry": {"coordinates":[151.10809326200001,-34.0387802124],"type":"Point"}
}