{
  "type": "Feature",
  "properties": {
    "iso:country":"AU",
    "sg:address":"14 Mount St",
    "sg:city":"Kew",
    "sg:classifiers":[
        {
            "category":"Taxi",
            "type":"Transportation"
        }
    ],
    "sg:phone":"+61 3 9817 3238",
    "sg:postcode":"3101",
    "sg:province":"VIC",
    "sg:tags":[
        "truck"
    ],
    "wof:name":"Krake Removals",
    "wof:placetype":"venue"
},
  "geometry": {"coordinates":[145.05128479000001,-37.8152618408],"type":"Point"}
}