{
  "type": "Feature",
  "properties": {
    "iso:country":"AU",
    "sg:address":"84 Nicolson Ave",
    "sg:city":"Whyalla Norrie",
    "sg:classifiers":[
        {
            "category":"Organizations",
            "subcategory":"Professional Association",
            "type":"Services"
        }
    ],
    "sg:phone":"+61 8 8645 1448",
    "sg:postcode":"5608",
    "sg:province":"SA",
    "sg:tags":[
        "web",
        "internet"
    ],
    "wof:name":"Affordable Feeds",
    "wof:placetype":"venue"
},
  "geometry": {"coordinates":[137.548157,-33.027935],"type":"Point"}
}