{
  "type": "Feature",
  "properties": {
    "addr:full":"Cnr Gilmore Cres & Hospital Road Garran ACT 2605",
    "addr:postcode":"2605",
    "addr:street":"Cnr Gilmore Cres;Road",
    "iso:country":"AU",
    "sg:address":"Cnr Gilmore Cres & Hospital Road",
    "sg:city":"Garran",
    "sg:classifiers":[
        {
            "category":"Health Services",
            "subcategory":"Doctor",
            "type":"Services"
        }
    ],
    "sg:phone":"+61 2 6222 6668",
    "sg:postcode":"2605",
    "sg:province":"ACT",
    "sg:tags":[
        "medical",
        "practitioner"
    ],
    "wof:name":"Ferguson Alan Dr",
    "wof:placetype":"venue"
},
  "geometry": {"coordinates":[149.108978272,-35.3422012329],"type":"Point"}
}