{
  "type": "Feature",
  "properties": {
    "addr:full":"2A Portrush Rd Payneham SA 5070",
    "addr:housenumber":"2a",
    "addr:postcode":"5070",
    "addr:street":"Portrush Rd",
    "iso:country":"AU",
    "sg:address":"2A Portrush Rd",
    "sg:city":"Payneham",
    "sg:classifiers":[
        {
            "category":"Real Estate",
            "subcategory":"Real Estate Agent",
            "type":"Services"
        }
    ],
    "sg:phone":"+61 8 8362 8008",
    "sg:postcode":"5070",
    "sg:province":"SA",
    "wof:name":"L.J. Hooker",
    "wof:placetype":"venue"
},
  "geometry": {"coordinates":[138.63929748499999,-34.8966178894],"type":"Point"}
}