{
  "type": "Feature",
  "properties": {
    "addr:full":"PO Box 1140 Glenelg South SA 5045",
    "addr:postcode":"5045",
    "iso:country":"AU",
    "sg:address":"PO Box 1140",
    "sg:city":"Glenelg South",
    "sg:classifiers":[
        {
            "category":"Mining & Drilling",
            "type":"Manufacturing & Wholesale Goods"
        }
    ],
    "sg:phone":"+61 418 808 901",
    "sg:postcode":"5045",
    "sg:province":"SA",
    "sg:tags":[
        "boring",
        "contractor"
    ],
    "wof:name":"RaiseBore Australia Pty Ltd",
    "wof:placetype":"venue"
},
  "geometry": {"coordinates":[138.513183594,-34.9854011536],"type":"Point"}
}