{
  "type": "Feature",
  "properties": {
    "iso:country":"AU",
    "sg:address":"Pembroke Rd",
    "sg:city":"Minto",
    "sg:classifiers":[
        {
            "category":"Education",
            "subcategory":"School",
            "type":"Public Place"
        }
    ],
    "sg:phone":"+61 2 9820 1566",
    "sg:postcode":"2566",
    "sg:province":"NSW",
    "sg:tags":[
        "state",
        "-",
        "nsw"
    ],
    "wof:name":"Sarah Redfern High School",
    "wof:placetype":"venue"
},
  "geometry": {"coordinates":[150.84732055699999,-34.0313148499],"type":"Point"}
}