{
  "type": "Feature",
  "properties": {
    "addr:full":"38 Sturt St Cairns QLD 4870",
    "addr:housenumber":"38",
    "addr:postcode":"4870",
    "addr:street":"Sturt St",
    "iso:country":"AU",
    "sg:address":"38 Sturt St",
    "sg:city":"Cairns",
    "sg:classifiers":[
        {
            "category":"Building & Trades",
            "subcategory":"Construction",
            "type":"Services"
        }
    ],
    "sg:phone":"+61 7 4031 3831",
    "sg:postcode":"4870",
    "sg:province":"QLD",
    "sg:tags":[
        "management"
    ],
    "wof:name":"Laing O&#039;Rouke Australia",
    "wof:placetype":"venue"
},
  "geometry": {"coordinates":[145.75338745100001,-16.9370307922],"type":"Point"}
}