{
  "type": "Feature",
  "properties": {
    "addr:full":"333 Yarra Rd Wonga Park VIC 3115",
    "addr:housenumber":"333",
    "addr:postcode":"3115",
    "addr:street":"Yarra Rd",
    "iso:country":"AU",
    "sg:address":"333 Yarra Rd",
    "sg:city":"Wonga Park",
    "sg:classifiers":[
        {
            "category":"Manufacturing",
            "subcategory":"Food",
            "type":"Manufacturing & Wholesale Goods"
        }
    ],
    "sg:phone":"+61 3 9848 5484",
    "sg:postcode":"3115",
    "sg:province":"VIC",
    "sg:tags":[
        "function",
        "catering"
    ],
    "wof:name":"Go For Gold Sizzling Spit Roast",
    "wof:placetype":"venue"
},
  "geometry": {"coordinates":[145.27084350600001,-37.7373695374],"type":"Point"}
}