{
  "type": "Feature",
  "properties": {
    "addr:full":"334 Main St Mornington VIC 3931",
    "addr:housenumber":"334",
    "addr:postcode":"3931",
    "addr:street":"Main St",
    "iso:country":"AU",
    "sg:address":"334 Main St",
    "sg:city":"Mornington",
    "sg:classifiers":[
        {
            "category":"Travel",
            "subcategory":"Hotels & Motels",
            "type":"Entertainment"
        }
    ],
    "sg:phone":"+61 3 5975 3711",
    "sg:postcode":"3931",
    "sg:province":"VIC",
    "wof:name":"Golden Chain Mornington Motel",
    "wof:placetype":"venue"
},
  "geometry": {"coordinates":[145.04312133799999,-38.2264328003],"type":"Point"}
}