{
  "type": "Feature",
  "properties": {
    "addr:full":"PO Box 122 Mansfield QLD 4122",
    "addr:postcode":"4122",
    "iso:country":"AU",
    "sg:address":"PO Box 122",
    "sg:city":"Mansfield",
    "sg:phone":"+61 1300 135 992",
    "sg:postcode":"4122",
    "sg:province":"QLD",
    "wof:name":"WaterBoy Aust",
    "wof:placetype":"venue"
},
  "geometry": {"coordinates":[153.09487915,-27.5326805115],"type":"Point"}
}