{
  "type": "Feature",
  "properties": {
    "iso:country":"AU",
    "sg:address":"5 Dwyer St",
    "sg:city":"Sunshine Beach",
    "sg:classifiers":[
        {
            "category":"Building & Trades",
            "subcategory":"Construction",
            "type":"Services"
        }
    ],
    "sg:phone":"+61 7 5448 0069",
    "sg:postcode":"4567",
    "sg:province":"QLD",
    "sg:tags":[
        "renovation",
        "alterations",
        "extension",
        "contractor"
    ],
    "wof:name":"Sunbuilders",
    "wof:placetype":"venue"
},
  "geometry": {"coordinates":[153.107879639,-26.4035167694],"type":"Point"}
}