{
  "type": "Feature",
  "properties": {
    "addr:full":"3 Fenton Crs Boat Harbour Beach TAS 7321",
    "addr:housenumber":"3",
    "addr:postcode":"7321",
    "addr:street":"Fenton Crs Boat",
    "iso:country":"AU",
    "sg:address":"3 Fenton Crs",
    "sg:city":"Boat Harbour Beach",
    "sg:classifiers":[
        {
            "category":"Organizations",
            "subcategory":"Membership Organization",
            "type":"Services"
        }
    ],
    "sg:phone":"+61 3 6445 1165",
    "sg:postcode":"7321",
    "sg:province":"TAS",
    "sg:tags":[
        "support",
        "health",
        "organisation"
    ],
    "wof:name":"Ochre Health Pty Ltd",
    "wof:placetype":"venue"
},
  "geometry": {"coordinates":[145.11483799999999,-40.838593],"type":"Point"}
}