{
  "type": "Feature",
  "properties": {
    "addr:full":"22 South St Forster NSW 2428",
    "addr:housenumber":"22",
    "addr:postcode":"2428",
    "addr:street":"South St",
    "iso:country":"AU",
    "sg:address":"22 South St",
    "sg:city":"Forster",
    "sg:classifiers":[
        {
            "category":"Health Services",
            "subcategory":"Health Practitioner",
            "type":"Services"
        }
    ],
    "sg:phone":"+61 2 6555 4062",
    "sg:postcode":"2428",
    "sg:province":"NSW",
    "sg:tags":[
        "alternative"
    ],
    "wof:name":"King Paul F. Holistic Massage Practitioner",
    "wof:placetype":"venue"
},
  "geometry": {"coordinates":[152.51460299999999,-32.189209],"type":"Point"}
}