{
  "type": "Feature",
  "properties": {
    "addr:full":"Domestic Terminal 2, Virgin Blue Concourse, Qantas Drv, Syd (Kingsford-Smith) Airpt Mascot NSW 2020",
    "addr:postcode":"2020",
    "addr:street":"Qantas Drv Syd",
    "iso:country":"AU",
    "sg:address":"Domestic Terminal 2, Virgin Blue Concourse, Qantas Drv, Syd (Kingsford-Smith) Airpt",
    "sg:city":"Mascot",
    "sg:classifiers":[
        {
            "category":"Shopping",
            "subcategory":"Mobile Phones",
            "type":"Retail Goods"
        }
    ],
    "sg:phone":"+61 2 9667 1699",
    "sg:postcode":"2020",
    "sg:province":"NSW",
    "sg:tags":[
        "telephone",
        "accessory"
    ],
    "wof:name":"Vodafone Sydney T2",
    "wof:placetype":"venue"
},
  "geometry": {"coordinates":[151.16502380399999,-33.9299888611],"type":"Point"}
}