{
  "type": "Feature",
  "properties": {
    "addr:full":"104 Urana St Wagga Wagga NSW 2650",
    "addr:housenumber":"104",
    "addr:postcode":"2650",
    "addr:street":"Urana St",
    "iso:country":"AU",
    "sg:address":"104 Urana St",
    "sg:city":"Wagga Wagga",
    "sg:classifiers":[
        {
            "category":"Travel",
            "subcategory":"Hotels & Motels",
            "type":"Entertainment"
        }
    ],
    "sg:phone":"+61 439 713 350",
    "sg:postcode":"2650",
    "sg:province":"NSW",
    "wof:name":"Rose Parterre",
    "wof:placetype":"venue"
},
  "geometry": {"coordinates":[147.352005005,-35.126335144],"type":"Point"}
}