{
  "type": "Feature",
  "properties": {
    "addr:full":"14 Duke St Gympie QLD 4570",
    "addr:housenumber":"14",
    "addr:postcode":"4570",
    "addr:street":"Duke St",
    "iso:country":"AU",
    "sg:address":"14 Duke St",
    "sg:city":"Gympie",
    "sg:classifiers":[
        {
            "category":"Food & Beverages",
            "subcategory":"Groceries & Convenience Stores",
            "type":"Retail Goods"
        }
    ],
    "sg:phone":"+61 7 5482 2662",
    "sg:postcode":"4570",
    "sg:province":"QLD",
    "wof:name":"Heilbronn Four Square",
    "wof:placetype":"venue"
},
  "geometry": {"coordinates":[152.657958984,-26.1879615784],"type":"Point"}
}