{
  "type": "Feature",
  "properties": {
    "iso:country":"AU",
    "sg:address":"110 Island Rd",
    "sg:city":"Koo Wee Rup",
    "sg:classifiers":[
        {
            "category":"Farming",
            "subcategory":"Farm",
            "type":"Manufacturing & Wholesale Goods"
        }
    ],
    "sg:phone":"+61 3 5997 1214",
    "sg:postcode":"3981",
    "sg:province":"VIC",
    "sg:tags":[
        "farmer"
    ],
    "wof:name":"De Bona I & H",
    "wof:placetype":"venue"
},
  "geometry": {"coordinates":[145.47085571299999,-38.1668739319],"type":"Point"}
}