{
  "type": "Feature",
  "properties": {
    "addr:full":"603 Riversdale Rd Camberwell VIC 3124",
    "addr:housenumber":"603",
    "addr:postcode":"3124",
    "addr:street":"Riversdale Rd",
    "iso:country":"AU",
    "sg:address":"603 Riversdale Rd",
    "sg:city":"Camberwell",
    "sg:classifiers":[
        {
            "category":"Social Services",
            "subcategory":"Retirement Home",
            "type":"Services"
        }
    ],
    "sg:phone":"+61 3 9804 0455",
    "sg:postcode":"3124",
    "sg:province":"VIC",
    "sg:tags":[
        "village"
    ],
    "wof:name":"Camberwell Manor",
    "wof:placetype":"venue"
},
  "geometry": {"coordinates":[145.06430053700001,-37.8320579529],"type":"Point"}
}