{
  "type": "Feature",
  "properties": {
    "iso:country":"AU",
    "sg:address":"103 Crosby Rd",
    "sg:city":"Albion",
    "sg:classifiers":[
        {
            "category":"Sports & Exercise",
            "subcategory":"Gym",
            "type":"Entertainment"
        }
    ],
    "sg:phone":"+61 408 733 896",
    "sg:postcode":"4010",
    "sg:province":"QLD",
    "sg:tags":[
        "personal",
        "trainer",
        "fitness"
    ],
    "wof:name":"Persistence Personal Training",
    "wof:placetype":"venue"
},
  "geometry": {"coordinates":[153.04826355,-27.4328613281],"type":"Point"}
}