{
  "type": "Feature",
  "properties": {
    "addr:full":"Hillhaven St Moore QLD 4306",
    "addr:postcode":"4306",
    "addr:street":"Hillhaven St",
    "iso:country":"AU",
    "sg:address":"Hillhaven St",
    "sg:city":"Moore",
    "sg:classifiers":[
        {
            "category":"Building & Trades",
            "subcategory":"Landscaping Services",
            "type":"Services"
        }
    ],
    "sg:phone":"+61 7 5424 7236",
    "sg:postcode":"4306",
    "sg:province":"QLD",
    "sg:tags":[
        "grazier"
    ],
    "wof:name":"Davis L R",
    "wof:placetype":"venue"
},
  "geometry": {"coordinates":[151.896575928,-27.5505447388],"type":"Point"}
}