{
  "type": "Feature",
  "properties": {
    "addr:full":"Weller Rd Mountain View VIC 3988",
    "addr:postcode":"3988",
    "addr:street":"Weller Rd",
    "iso:country":"AU",
    "sg:address":"Weller Rd",
    "sg:city":"Mountain View",
    "sg:classifiers":[
        {
            "category":"Farming",
            "subcategory":"Farm",
            "type":"Manufacturing & Wholesale Goods"
        }
    ],
    "sg:phone":"+61 3 5659 7383",
    "sg:postcode":"3988",
    "sg:province":"VIC",
    "sg:tags":[
        "farmer"
    ],
    "wof:name":"Olsen K D",
    "wof:placetype":"venue"
},
  "geometry": {"coordinates":[145.87225341800001,-38.2962760925],"type":"Point"}
}