{
  "type": "Feature",
  "properties": {
    "addr:full":"2 Sybyl St Toowoomba QLD 4350",
    "addr:housenumber":"2",
    "addr:postcode":"4350",
    "addr:street":"Sybyl St",
    "iso:country":"AU",
    "sg:address":"2 Sybyl St",
    "sg:city":"Toowoomba",
    "sg:classifiers":[
        {
            "category":"Building & Trades",
            "subcategory":"Construction",
            "type":"Services"
        }
    ],
    "sg:phone":"+61 7 4635 5215",
    "sg:postcode":"4350",
    "sg:province":"QLD",
    "sg:tags":[
        "mural"
    ],
    "wof:name":"Jon Signs",
    "wof:placetype":"venue"
},
  "geometry": {"coordinates":[151.92820699999999,-27.580208],"type":"Point"}
}