{
  "type": "Feature",
  "properties": {
    "iso:country":"AU",
    "sg:address":"1 Bulliti St",
    "sg:city":"Santa Barbara",
    "sg:classifiers":[
        {
            "category":"Building & Trades",
            "subcategory":"Construction",
            "type":"Services"
        }
    ],
    "sg:phone":"+61 418 714 181",
    "sg:postcode":"4212",
    "sg:province":"QLD",
    "sg:tags":[
        "waterproofing",
        "contractor"
    ],
    "wof:name":"Flexitray Aust",
    "wof:placetype":"venue"
},
  "geometry": {"coordinates":[153.352172852,-27.8562049866],"type":"Point"}
}