{
  "type": "Feature",
  "properties": {
    "addr:full":"15 Hillside Drv Albion Park NSW 2527",
    "addr:housenumber":"15",
    "addr:postcode":"2527",
    "addr:street":"Hillside Drv Albion Park",
    "iso:country":"AU",
    "sg:address":"15 Hillside Drv",
    "sg:city":"Albion Park",
    "sg:classifiers":[
        {
            "category":"Personal",
            "type":"Services"
        }
    ],
    "sg:phone":"+61 2 4257 1828",
    "sg:postcode":"2527",
    "sg:province":"NSW",
    "sg:tags":[
        "dressmaker"
    ],
    "wof:name":"Mirjana Fashions",
    "wof:placetype":"venue"
},
  "geometry": {"coordinates":[150.77101135300001,-34.5803451538],"type":"Point"}
}