{
  "type": "Feature",
  "properties": {
    "iso:country":"AU",
    "sg:address":"Unit 18/ 55 Graham Crt",
    "sg:city":"Hoppers Crossing",
    "sg:classifiers":[
        {
            "category":"Education",
            "subcategory":"Music School",
            "type":"Public Place"
        }
    ],
    "sg:phone":"+61 3 9931 0921",
    "sg:postcode":"3029",
    "sg:province":"VIC",
    "sg:tags":[
        "teacher"
    ],
    "wof:name":"Jamie Redfern Talent Schools Of Australia",
    "wof:placetype":"venue"
},
  "geometry": {"coordinates":[144.729034,-37.872608],"type":"Point"}
}