{
  "type": "Feature",
  "properties": {
    "iso:country":"AU",
    "sg:address":"Clover Hill Drv",
    "sg:city":"Mudgeeraba",
    "sg:classifiers":[
        {
            "category":"Education",
            "subcategory":"School",
            "type":"Public Place"
        }
    ],
    "sg:phone":"+61 7 5559 4111",
    "sg:postcode":"4213",
    "sg:province":"QLD",
    "sg:tags":[
        "state",
        "except",
        "nsw"
    ],
    "wof:name":"Clover Hill Preschool",
    "wof:placetype":"venue"
},
  "geometry": {"coordinates":[153.375274658,-28.090045929],"type":"Point"}
}