{
  "type": "Feature",
  "properties": {
    "addr:full":"Lonsdale St Melbourne VIC 3000",
    "addr:postcode":"3000",
    "addr:street":"Lonsdale St",
    "iso:country":"AU",
    "sg:address":"Lonsdale St",
    "sg:city":"Melbourne",
    "sg:classifiers":[
        {
            "category":"Shopping",
            "subcategory":"Clothing, Apparel, & Fashions",
            "type":"Retail Goods"
        }
    ],
    "sg:phone":"+61 3 9662 3739",
    "sg:postcode":"3000",
    "sg:province":"VIC",
    "sg:tags":[
        "jean"
    ],
    "wof:name":"Just Jeans",
    "wof:placetype":"venue"
},
  "geometry": {"coordinates":[144.97027587900001,-37.8145599365],"type":"Point"}
}