{
  "type": "Feature",
  "properties": {
    "addr:full":"21 Temple Drv Thomastown VIC 3074",
    "addr:housenumber":"21",
    "addr:postcode":"3074",
    "addr:street":"Temple Drv",
    "iso:country":"AU",
    "sg:address":"21 Temple Drv",
    "sg:city":"Thomastown",
    "sg:classifiers":[
        {
            "category":"Donuts",
            "subcategory":"None",
            "type":"Food & Drink"
        }
    ],
    "sg:phone":"+61 3 9465 0166",
    "sg:postcode":"3074",
    "sg:province":"VIC",
    "sg:tags":[
        "die",
        "engraver",
        "sinker"
    ],
    "wof:name":"Milford Astor",
    "wof:placetype":"venue"
},
  "geometry": {"coordinates":[145.01948547399999,-37.6906547546],"type":"Point"}
}