{
  "type": "Feature",
  "properties": {
    "addr:full":"Cnr Mains & Kessels Rds MacGregor QLD 4109",
    "addr:postcode":"4109",
    "addr:street":"Cnr",
    "iso:country":"AU",
    "sg:address":"Cnr Mains & Kessels Rds",
    "sg:city":"MacGregor",
    "sg:classifiers":[
        {
            "category":"Autos & Motor Vehicles",
            "subcategory":"Auto Supplies",
            "type":"Retail Goods"
        }
    ],
    "sg:phone":"+61 7 3420 3111",
    "sg:postcode":"4109",
    "sg:province":"QLD",
    "sg:tags":[
        "tyre"
    ],
    "wof:name":"Quick Fit Tyre Service",
    "wof:placetype":"venue"
},
  "geometry": {"coordinates":[153.06593322800001,-27.5610408783],"type":"Point"}
}