{
  "type": "Feature",
  "properties": {
    "addr:full":"4 Plant Crt Mildura VIC 3500",
    "addr:housenumber":"4",
    "addr:postcode":"3500",
    "addr:street":"Plant Crt",
    "iso:country":"AU",
    "sg:address":"4 Plant Crt",
    "sg:city":"Mildura",
    "sg:classifiers":[
        {
            "category":"Professional",
            "subcategory":"Art Services",
            "type":"Services"
        }
    ],
    "sg:phone":"+61 3 5023 1526",
    "sg:postcode":"3500",
    "sg:province":"VIC",
    "sg:tags":[
        "decorator",
        "painter"
    ],
    "wof:name":"Murphy G V & D M",
    "wof:placetype":"venue"
},
  "geometry": {"coordinates":[142.13685607900001,-34.2043991089],"type":"Point"}
}