{
  "type": "Feature",
  "properties": {
    "addr:full":"Ste4/ 49 Coppin St Richmond VIC 3121",
    "addr:postcode":"3121",
    "addr:street":"Coppin St",
    "iso:country":"AU",
    "sg:address":"Ste4/ 49 Coppin St",
    "sg:city":"Richmond",
    "sg:classifiers":[
        {
            "category":"Professional",
            "subcategory":"Art Services",
            "type":"Services"
        }
    ],
    "sg:phone":"+61 3 9421 5310",
    "sg:postcode":"3121",
    "sg:province":"VIC",
    "sg:tags":[
        "graphic",
        "designer"
    ],
    "wof:name":"Fad Experiment",
    "wof:placetype":"venue"
},
  "geometry": {"coordinates":[145.003814697,-37.8198738098],"type":"Point"}
}