{
  "type": "Feature",
  "properties": {
    "addr:full":"Mansfield Rd Whitfield VIC 3733",
    "addr:postcode":"3733",
    "addr:street":"Mansfield Rd",
    "iso:country":"AU",
    "sg:address":"Mansfield Rd",
    "sg:city":"Whitfield",
    "sg:classifiers":[
        {
            "category":"Education",
            "subcategory":"School",
            "type":"Public Place"
        }
    ],
    "sg:phone":"+61 3 5729 8286",
    "sg:postcode":"3733",
    "sg:province":"VIC",
    "sg:tags":[
        "state",
        "except",
        "nsw"
    ],
    "wof:name":"Whitfield Primary School",
    "wof:placetype":"venue"
},
  "geometry": {"coordinates":[146.41709899899999,-36.7525100708],"type":"Point"}
}