{
  "type": "Feature",
  "properties": {
    "iso:country":"AU",
    "sg:address":"149 Apsley Rd",
    "sg:city":"Willetton",
    "sg:classifiers":[
        {
            "category":"Professional",
            "subcategory":"Business Services",
            "type":"Services"
        }
    ],
    "sg:phone":"+61 8 9457 5579",
    "sg:postcode":"6155",
    "sg:province":"WA",
    "sg:tags":[
        "drafting"
    ],
    "wof:name":"Customcad",
    "wof:placetype":"venue"
},
  "geometry": {"coordinates":[115.890388,-32.048206],"type":"Point"}
}