{
  "type": "Feature",
  "properties": {
    "iso:country":"AU",
    "sg:address":"3- 5 Eddystone Rd",
    "sg:city":"Bexley",
    "sg:classifiers":[
        {
            "category":"Health Services",
            "subcategory":"Nursing And Care Facility",
            "type":"Services"
        }
    ],
    "sg:phone":"+61 2 9150 7701",
    "sg:postcode":"2207",
    "sg:province":"NSW",
    "sg:tags":[
        "home"
    ],
    "wof:name":"Eddystone Nursing Home",
    "wof:placetype":"venue"
},
  "geometry": {"coordinates":[151.11810299999999,-33.949196],"type":"Point"}
}