{
  "type": "Feature",
  "properties": {
    "iso:country":"AU",
    "sg:address":"2 Russell St",
    "sg:city":"Toowoomba",
    "sg:classifiers":[
        {
            "category":"Organizations",
            "subcategory":"Community Association",
            "type":"Services"
        }
    ],
    "sg:phone":"+61 7 4639 6140",
    "sg:postcode":"4350",
    "sg:province":"QLD",
    "sg:tags":[
        "registered",
        "trustee",
        "bankruptcy"
    ],
    "wof:name":"SV Partners",
    "wof:placetype":"venue"
},
  "geometry": {"coordinates":[151.95567299999999,-27.559469],"type":"Point"}
}