{
  "type": "Feature",
  "properties": {
    "addr:full":"Ste 2G1/ 283 Alfred St North Sydney NSW 2060",
    "addr:housenumber":"/ 283",
    "addr:postcode":"2060",
    "addr:street":"Alfred St",
    "iso:country":"AU",
    "sg:address":"Ste 2G1/ 283 Alfred St",
    "sg:city":"North Sydney",
    "sg:classifiers":[
        {
            "category":"Communications",
            "subcategory":"Film & Video Production",
            "type":"Services"
        }
    ],
    "sg:phone":"+61 2 9955 8666",
    "sg:postcode":"2060",
    "sg:province":"NSW",
    "sg:tags":[
        "wholesaler",
        "television",
        "mfrs"
    ],
    "wof:name":"Real ITV",
    "wof:placetype":"venue"
},
  "geometry": {"coordinates":[151.21136474599999,-33.8400726318],"type":"Point"}
}