{
  "type": "Feature",
  "properties": {
    "iso:country":"AU",
    "sg:address":"Inglewood St",
    "sg:city":"Bendigo",
    "sg:classifiers":[
        {
            "category":"Education",
            "subcategory":"School",
            "type":"Public Place"
        }
    ],
    "sg:phone":"+61 3 5443 5353",
    "sg:postcode":"3550",
    "sg:province":"VIC",
    "sg:tags":[
        "state",
        "except",
        "nsw"
    ],
    "wof:name":"Specimen Hill Primary School",
    "wof:placetype":"venue"
},
  "geometry": {"coordinates":[144.249832153,-36.7596549988],"type":"Point"}
}