{
  "type": "Feature",
  "properties": {
    "addr:full":"230 Goondoon St Gladstone QLD 4680",
    "addr:housenumber":"230",
    "addr:postcode":"4680",
    "addr:street":"Goondoon St",
    "iso:country":"AU",
    "sg:address":"230 Goondoon St",
    "sg:city":"Gladstone",
    "sg:classifiers":[
        {
            "category":"Personal",
            "subcategory":"Beauty Salon",
            "type":"Services"
        }
    ],
    "sg:phone":"+61 7 4972 1447",
    "sg:postcode":"4680",
    "sg:province":"QLD",
    "sg:tags":[
        "hairdresser"
    ],
    "wof:name":"Rosette Styles For Hair",
    "wof:placetype":"venue"
},
  "geometry": {"coordinates":[151.26161193900001,-23.8521099091],"type":"Point"}
}