{
  "type": "Feature",
  "properties": {
    "addr:full":"339 Goodwood Rd Cross Roads Kings Park SA 5034",
    "addr:housenumber":"339",
    "addr:postcode":"5034",
    "addr:street":"Goodwood Rd",
    "iso:country":"AU",
    "sg:address":"339 Goodwood Rd Cross Roads",
    "sg:city":"Kings Park",
    "sg:classifiers":[
        {
            "category":"Fast Food",
            "type":"Food & Drink"
        }
    ],
    "sg:phone":"+61 8 8272 9136",
    "sg:postcode":"5034",
    "sg:province":"SA",
    "sg:tags":[
        "away",
        "take"
    ],
    "wof:name":"McDonald's Family Restaurants",
    "wof:placetype":"venue"
},
  "geometry": {"coordinates":[138.590896606,-34.9657516479],"type":"Point"}
}