{
  "type": "Feature",
  "properties": {
    "iso:country":"AU",
    "sg:address":"Cnr Mollison St & Johnson Crt",
    "sg:city":"Kyneton",
    "sg:classifiers":[
        {
            "category":"Farming",
            "subcategory":"Farm & Veterinary Services",
            "type":"Manufacturing & Wholesale Goods"
        }
    ],
    "sg:phone":"+61 3 5422 1381",
    "sg:postcode":"3444",
    "sg:province":"VIC",
    "sg:tags":[
        "irrigation",
        "reticulation",
        "system"
    ],
    "wof:name":"Kyneton Plumbing & Irrigation",
    "wof:placetype":"venue"
},
  "geometry": {"coordinates":[144.45289611800001,-37.2508850098],"type":"Point"}
}