{
  "type": "Feature",
  "properties": {
    "addr:full":"7 Darkan Crt Eltham VIC 3095",
    "addr:housenumber":"7",
    "addr:postcode":"3095",
    "addr:street":"Darkan Crt",
    "iso:country":"AU",
    "sg:address":"7 Darkan Crt",
    "sg:city":"Eltham",
    "sg:classifiers":[
        {
            "category":"Shopping",
            "subcategory":"Musical Instruments",
            "type":"Retail Goods"
        }
    ],
    "sg:phone":"+61 3 9439 3248",
    "sg:postcode":"3095",
    "sg:province":"VIC",
    "sg:tags":[
        "piano",
        "organ"
    ],
    "wof:name":"Speight Piano & Organ Carriers Pty Ltd",
    "wof:placetype":"venue"
},
  "geometry": {"coordinates":[145.172149658,-37.6995773315],"type":"Point"}
}