{
  "type": "Feature",
  "properties": {
    "addr:full":"Shop 1/ 158 Musgrave St North Rockhampton QLD 4701",
    "addr:housenumber":"shop 1 / 158",
    "addr:postcode":"4701",
    "addr:street":"Musgrave St North",
    "iso:country":"AU",
    "sg:address":"Shop 1/ 158 Musgrave St",
    "sg:city":"North Rockhampton",
    "sg:classifiers":[
        {
            "category":"Shopping",
            "subcategory":"Stationery & Office Supplies",
            "type":"Retail Goods"
        }
    ],
    "sg:phone":"+61 7 4923 7705",
    "sg:postcode":"4701",
    "sg:province":"QLD",
    "sg:tags":[
        "typewriter"
    ],
    "wof:name":"Freetech",
    "wof:placetype":"venue"
},
  "geometry": {"coordinates":[150.52281189000001,-23.3639373779],"type":"Point"}
}