{
  "type": "Feature",
  "properties": {
    "addr:full":"12 English St Malanda QLD 4885",
    "addr:housenumber":"12",
    "addr:postcode":"4885",
    "addr:street":"English St",
    "iso:country":"AU",
    "sg:address":"12 English St",
    "sg:city":"Malanda",
    "sg:classifiers":[
        {
            "category":"Farming",
            "subcategory":"Poultry Farm",
            "type":"Manufacturing & Wholesale Goods"
        }
    ],
    "sg:phone":"+61 7 4096 5470",
    "sg:postcode":"4885",
    "sg:province":"QLD",
    "sg:tags":[
        "farmer"
    ],
    "wof:name":"T & J English",
    "wof:placetype":"venue"
},
  "geometry": {"coordinates":[145.59280395499999,-17.3525066376],"type":"Point"}
}