{
  "type": "Feature",
  "properties": {
    "iso:country":"AU",
    "sg:address":"Sunraysia Hwy",
    "sg:city":"Waubra",
    "sg:classifiers":[
        {
            "category":"Food & Beverages",
            "subcategory":"Groceries & Convenience Stores",
            "type":"Retail Goods"
        }
    ],
    "sg:phone":"+61 3 5343 5300",
    "sg:postcode":"3352",
    "sg:province":"VIC",
    "wof:name":"Waubra General Store",
    "wof:placetype":"venue"
},
  "geometry": {"coordinates":[143.65614299999999,-37.367222],"type":"Point"}
}