{
  "type": "Feature",
  "properties": {
    "addr:full":"214 Pulteney St Adelaide SA 5000",
    "addr:housenumber":"214",
    "addr:postcode":"5000",
    "addr:street":"Pulteney St",
    "iso:country":"AU",
    "sg:address":"214 Pulteney St",
    "sg:city":"Adelaide",
    "sg:classifiers":[
        {
            "category":"Real Estate",
            "subcategory":"Architect",
            "type":"Services"
        }
    ],
    "sg:phone":"+61 8 8223 3123",
    "sg:postcode":"5000",
    "sg:province":"SA",
    "wof:name":"Pruszinski Architects Pty Ltd",
    "wof:placetype":"venue"
},
  "geometry": {"coordinates":[138.60609435999999,-34.9270477295],"type":"Point"}
}