{
  "type": "Feature",
  "properties": {
    "iso:country":"AU",
    "sg:address":"U5/ 17",
    "sg:city":"Conquest Way Wangara",
    "sg:classifiers":[
        {
            "category":"Manufacturing",
            "subcategory":"Metals",
            "type":"Manufacturing & Wholesale Goods"
        }
    ],
    "sg:phone":"+61 8 9302 1019",
    "sg:postcode":"6065",
    "sg:province":"WA",
    "sg:tags":[
        "sheet",
        "worker"
    ],
    "wof:name":"NSM Sheet Metal Co",
    "wof:placetype":"venue"
},
  "geometry": {"coordinates":[115.836799622,-31.7994003296],"type":"Point"}
}