{
  "type": "Feature",
  "properties": {
    "addr:full":"Unit 1 / 175 Cheltenham Rd Dandenong VIC 3175",
    "addr:housenumber":"/ 175",
    "addr:postcode":"3175",
    "addr:street":"Cheltenham Rd",
    "iso:country":"AU",
    "sg:address":"Unit 1 / 175 Cheltenham Rd",
    "sg:city":"Dandenong",
    "sg:classifiers":[
        {
            "category":"Shopping",
            "subcategory":"Baby Store",
            "type":"Retail Goods"
        }
    ],
    "sg:phone":"+61 3 9791 7991",
    "sg:postcode":"3175",
    "sg:province":"VIC",
    "sg:tags":[
        "wear"
    ],
    "wof:name":"Nappy Store & More",
    "wof:placetype":"venue"
},
  "geometry": {"coordinates":[145.19383239699999,-37.9917869568],"type":"Point"}
}