{
  "type": "Feature",
  "properties": {
    "addr:full":"110 Swan St Guildford WA 6055",
    "addr:housenumber":"110",
    "addr:postcode":"6055",
    "addr:street":"Swan St",
    "iso:country":"AU",
    "sg:address":"110 Swan St",
    "sg:city":"Guildford",
    "sg:classifiers":[
        {
            "category":"Personal",
            "subcategory":"Beauty Salon",
            "type":"Services"
        }
    ],
    "sg:phone":"+61 8 9279 7888",
    "sg:postcode":"6055",
    "sg:province":"WA",
    "wof:name":"Deep Salon Lifestyle Store",
    "wof:placetype":"venue"
},
  "geometry": {"coordinates":[115.969368,-31.897156],"type":"Point"}
}