{
  "type": "Feature",
  "properties": {
    "addr:full":"Suite 18/ 128 Bowen St Spring Hill QLD 4004",
    "addr:housenumber":"18 / 128",
    "addr:postcode":"4004",
    "addr:street":"Bowen St",
    "iso:country":"AU",
    "sg:address":"Suite 18/ 128 Bowen St",
    "sg:city":"Spring Hill",
    "sg:classifiers":[
        {
            "category":"Real Estate",
            "subcategory":"Real Estate Agent",
            "type":"Services"
        }
    ],
    "sg:phone":"+61 7 3839 4888",
    "sg:postcode":"4004",
    "sg:province":"QLD",
    "wof:name":"Flemming Asset Management",
    "wof:placetype":"venue"
},
  "geometry": {"coordinates":[153.02841186500001,-27.4627170563],"type":"Point"}
}