{
  "type": "Feature",
  "properties": {
    "iso:country":"AU",
    "sg:address":"36 Cary St",
    "sg:city":"Kanwal",
    "sg:classifiers":[
        {
            "category":"Home & Garden",
            "subcategory":"Building Materials",
            "type":"Retail Goods"
        }
    ],
    "sg:phone":"+61 2 4351 1633",
    "sg:postcode":"2259",
    "sg:province":"NSW",
    "sg:tags":[
        "shutter",
        "roller",
        "grille"
    ],
    "wof:name":"Metzen Louvres Pty Ltd",
    "wof:placetype":"venue"
},
  "geometry": {"coordinates":[151.48216247600001,-33.2626190186],"type":"Point"}
}