{
  "type": "Feature",
  "properties": {
    "addr:full":"3/ 3 Dower St Mandurah WA 6210",
    "addr:housenumber":"/ 3",
    "addr:postcode":"6210",
    "addr:street":"Dower St",
    "iso:country":"AU",
    "sg:address":"3/ 3 Dower St",
    "sg:city":"Mandurah",
    "sg:classifiers":[
        {
            "category":"Personal",
            "subcategory":"Beauty Salon",
            "type":"Services"
        }
    ],
    "sg:phone":"+61 8 9586 1088",
    "sg:postcode":"6210",
    "sg:province":"WA",
    "sg:tags":[
        "hairdresser"
    ],
    "wof:name":"Nutz N Co Hair & Beauty Studio",
    "wof:placetype":"venue"
},
  "geometry": {"coordinates":[115.738731,-32.536064],"type":"Point"}
}