{
  "type": "Feature",
  "properties": {
    "addr:full":"342 Charman Rd Cheltenham VIC 3192",
    "addr:housenumber":"342",
    "addr:postcode":"3192",
    "addr:street":"Charman Rd",
    "iso:country":"AU",
    "sg:address":"342 Charman Rd",
    "sg:city":"Cheltenham",
    "sg:classifiers":[
        {
            "category":"Food & Beverages",
            "subcategory":"Fruits & Vegetables",
            "type":"Retail Goods"
        }
    ],
    "sg:phone":"+61 3 9583 6237",
    "sg:postcode":"3192",
    "sg:province":"VIC",
    "sg:tags":[
        "greengrocer",
        "fruiterer"
    ],
    "wof:name":"Charmans Fruits and Blooms",
    "wof:placetype":"venue"
},
  "geometry": {"coordinates":[145.05581665,-37.9657058716],"type":"Point"}
}