{
  "type": "Feature",
  "properties": {
    "addr:full":"Shop 13, 12- 20 Kingston Downs Drv Ocean Grove VIC 3226",
    "addr:housenumber":"shop 13 12 20",
    "addr:postcode":"3226",
    "addr:street":"Kingston Downs Drv",
    "iso:country":"AU",
    "sg:address":"Shop 13, 12- 20 Kingston Downs Drv",
    "sg:city":"Ocean Grove",
    "sg:classifiers":[
        {
            "category":"Travel",
            "subcategory":"Travel Agent",
            "type":"Entertainment"
        }
    ],
    "sg:phone":"+61 3 5256 1888",
    "sg:postcode":"3226",
    "sg:province":"VIC",
    "sg:tags":[
        "consultant"
    ],
    "wof:name":"Harvey World Travel",
    "wof:placetype":"venue"
},
  "geometry": {"coordinates":[144.54728700000001,-38.258514],"type":"Point"}
}