{
  "type": "Feature",
  "properties": {
    "addr:full":"Lot 19 New England Hwy Thornton NSW 2322",
    "addr:postcode":"2322",
    "addr:street":"England Hwy",
    "iso:country":"AU",
    "sg:address":"Lot 19 New England Hwy",
    "sg:city":"Thornton",
    "sg:classifiers":[
        {
            "category":"Home & Garden",
            "subcategory":"Building Materials",
            "type":"Retail Goods"
        }
    ],
    "sg:phone":"+61 2 4964 2271",
    "sg:postcode":"2322",
    "sg:province":"NSW",
    "sg:tags":[
        "retaining",
        "wall"
    ],
    "wof:name":"Ace Retaining Walls",
    "wof:placetype":"venue"
},
  "geometry": {"coordinates":[151.613677978,-32.7769813538],"type":"Point"}
}