{
  "type": "Feature",
  "properties": {
    "iso:country":"AU",
    "sg:address":"131 Canterbury Rd",
    "sg:city":"Canterbury",
    "sg:classifiers":[
        {
            "category":"Professional",
            "subcategory":"Computer Services",
            "type":"Services"
        }
    ],
    "sg:phone":"+61 2 9787 2868",
    "sg:postcode":"2193",
    "sg:province":"NSW",
    "sg:tags":[
        "repairs",
        "upgrade",
        "equipment"
    ],
    "wof:name":"One Group Computers",
    "wof:placetype":"venue"
},
  "geometry": {"coordinates":[151.120728,-33.910957],"type":"Point"}
}