{
  "type": "Feature",
  "properties": {
    "iso:country":"AU",
    "sg:address":"Suite 1, 9A Hindley St",
    "sg:city":"Adelaide",
    "sg:classifiers":[
        {
            "category":"Government",
            "subcategory":"Court House",
            "type":"Public Place"
        }
    ],
    "sg:phone":"+61 1300 788 079",
    "sg:postcode":"5000",
    "sg:province":"SA",
    "sg:tags":[
        "personal",
        "marriage",
        "family",
        "counselling"
    ],
    "sg:website":"http://www.flamedatecoaching.com.au",
    "wof:name":"Flame Date Coaching",
    "wof:placetype":"venue"
},
  "geometry": {"coordinates":[138.59916687,-34.9231414795],"type":"Point"}
}