{
  "type": "Feature",
  "properties": {
    "addr:full":"342 Taylors Rd Delahey VIC 3037",
    "addr:housenumber":"342",
    "addr:postcode":"3037",
    "addr:street":"Taylors Rd",
    "iso:country":"AU",
    "sg:address":"342 Taylors Rd",
    "sg:city":"Delahey",
    "sg:classifiers":[
        {
            "category":"Manufacturing",
            "subcategory":"Tools & Machinery",
            "type":"Manufacturing & Wholesale Goods"
        }
    ],
    "sg:phone":"+61 3 9366 6523",
    "sg:postcode":"3037",
    "sg:province":"VIC",
    "sg:tags":[
        "earth",
        "excavating",
        "moving",
        "equipment"
    ],
    "wof:name":"GELLUX-QAJRU Backhoe Hire",
    "wof:placetype":"venue"
},
  "geometry": {"coordinates":[144.77192700000001,-37.726269],"type":"Point"}
}