{
  "type": "Feature",
  "properties": {
    "iso:country":"AU",
    "sg:address":"85 New Canterbury Rd",
    "sg:city":"Petersham",
    "sg:classifiers":[
        {
            "category":"Professional",
            "subcategory":"Accounting & Tax Preparation",
            "type":"Services"
        }
    ],
    "sg:phone":"+61 2 9560 9422",
    "sg:postcode":"2049",
    "sg:province":"NSW",
    "sg:tags":[
        "accountant",
        "auditor"
    ],
    "wof:name":"Soares Sam Accountant",
    "wof:placetype":"venue"
},
  "geometry": {"coordinates":[151.152344,-33.89679],"type":"Point"}
}