{
  "type": "Feature",
  "properties": {
    "addr:full":"1130 Kingsford Smith Drv Eagle Farm QLD 4009",
    "addr:housenumber":"1130",
    "addr:postcode":"4009",
    "addr:street":"Kingsford Smith Drv",
    "iso:country":"AU",
    "sg:address":"1130 Kingsford Smith Drv",
    "sg:city":"Eagle Farm",
    "sg:classifiers":[
        {
            "category":"Manufacturing",
            "subcategory":"Metals",
            "type":"Manufacturing & Wholesale Goods"
        }
    ],
    "sg:phone":"+61 7 3268 6841",
    "sg:postcode":"4009",
    "sg:province":"QLD",
    "sg:tags":[
        "steel",
        "fabricator",
        "mfrs"
    ],
    "wof:name":"MGM Welding Pty Ltd",
    "wof:placetype":"venue"
},
  "geometry": {"coordinates":[153.09849548299999,-27.4282588959],"type":"Point"}
}