{
  "type": "Feature",
  "properties": {
    "iso:country":"AU",
    "sg:address":"Shed C4 30 Alfred Rd",
    "sg:city":"Chipping Norton",
    "sg:classifiers":[
        {
            "category":"Professional",
            "type":"Services"
        }
    ],
    "sg:phone":"+61 2 9755 4019",
    "sg:postcode":"2170",
    "sg:province":"NSW",
    "sg:tags":[
        "transport"
    ],
    "wof:name":"Coastal Freight Pty Ltd",
    "wof:placetype":"venue"
},
  "geometry": {"coordinates":[150.964767456,-33.9232330322],"type":"Point"}
}