{
  "type": "Feature",
  "properties": {
    "iso:country":"AU",
    "sg:address":"32 Princes St",
    "sg:city":"Watsonia",
    "sg:classifiers":[
        {
            "category":"Building & Trades",
            "subcategory":"Construction",
            "type":"Services"
        }
    ],
    "sg:phone":"+61 3 9435 2778",
    "sg:postcode":"3087",
    "sg:province":"VIC",
    "sg:tags":[
        "plasterboard",
        "plasterer",
        "fixer"
    ],
    "wof:name":"Togher Plasterers",
    "wof:placetype":"venue"
},
  "geometry": {"coordinates":[145.080245972,-37.7059402466],"type":"Point"}
}