{
  "type": "Feature",
  "properties": {
    "addr:full":"44- 52 Johnston St Collingwood VIC 3066",
    "addr:housenumber":"52",
    "addr:postcode":"3066",
    "addr:street":"Johnston St",
    "iso:country":"AU",
    "sg:address":"44- 52 Johnston St",
    "sg:city":"Collingwood",
    "sg:classifiers":[
        {
            "category":"Banks & Credit Unions",
            "subcategory":"Bank",
            "type":"Services"
        }
    ],
    "sg:phone":"+61 3 9419 2122",
    "sg:postcode":"3066",
    "sg:province":"VIC",
    "sg:tags":[
        "castor"
    ],
    "wof:name":"G & R Industrial Products P/L",
    "wof:placetype":"venue"
},
  "geometry": {"coordinates":[144.98643493599999,-37.7990226746],"type":"Point"}
}