{
  "type": "Feature",
  "properties": {
    "iso:country":"AU",
    "sg:address":"46 Gladstone St",
    "sg:city":"Kempsey",
    "sg:classifiers":[
        {
            "category":"Shopping",
            "subcategory":"Bicycles & Sporting Goods",
            "type":"Retail Goods"
        }
    ],
    "sg:phone":"+61 2 6562 1130",
    "sg:postcode":"2440",
    "sg:province":"NSW",
    "sg:tags":[
        "chemical",
        "equipment",
        "pool",
        "swimming"
    ],
    "wof:name":"Aqua-Port",
    "wof:placetype":"venue"
},
  "geometry": {"coordinates":[152.834991,-31.069675],"type":"Point"}
}