{
  "type": "Feature",
  "properties": {
    "addr:full":"Purchase Rd Cherrybrook NSW 2126",
    "addr:postcode":"2126",
    "addr:street":"Purchase Rd",
    "iso:country":"AU",
    "sg:address":"Purchase Rd",
    "sg:city":"Cherrybrook",
    "sg:classifiers":[
        {
            "category":"Education",
            "subcategory":"School",
            "type":"Public Place"
        }
    ],
    "sg:phone":"+61 2 9484 2144",
    "sg:postcode":"2126",
    "sg:province":"NSW",
    "sg:tags":[
        "state",
        "-",
        "nsw"
    ],
    "wof:name":"Cherrybrook Technology High School",
    "wof:placetype":"venue"
},
  "geometry": {"coordinates":[151.03839111299999,-33.7186126709],"type":"Point"}
}