{
  "type": "Feature",
  "properties": {
    "iso:country":"AU",
    "sg:address":"55 Bellbrook Drv",
    "sg:city":"Dandenong North",
    "sg:classifiers":[
        {
            "category":"Professional",
            "subcategory":"Art Services",
            "type":"Services"
        }
    ],
    "sg:phone":"+61 3 9790 1635",
    "sg:postcode":"3175",
    "sg:province":"VIC",
    "sg:tags":[
        "decorator",
        "painter"
    ],
    "wof:name":"Kozlica John",
    "wof:placetype":"venue"
},
  "geometry": {"coordinates":[145.21519470199999,-37.9513816833],"type":"Point"}
}