{
  "type": "Feature",
  "properties": {
    "addr:full":"25 Cleveland St Dianella WA 6059",
    "addr:housenumber":"25",
    "addr:postcode":"6059",
    "addr:street":"Cleveland St",
    "iso:country":"AU",
    "sg:address":"25 Cleveland St",
    "sg:city":"Dianella",
    "sg:classifiers":[
        {
            "category":"Manufacturing",
            "subcategory":"Furniture",
            "type":"Manufacturing & Wholesale Goods"
        }
    ],
    "sg:phone":"+61 8 9272 6922",
    "sg:postcode":"6059",
    "sg:province":"WA",
    "sg:tags":[
        "builder",
        "designer",
        "custom"
    ],
    "wof:name":"Sherwood Design",
    "wof:placetype":"venue"
},
  "geometry": {"coordinates":[115.879066467,-31.9060993195],"type":"Point"}
}