{
  "type": "Feature",
  "properties": {
    "iso:country":"AU",
    "sg:address":"11 Tillock St",
    "sg:city":"Haberfield",
    "sg:classifiers":[
        {
            "category":"Banks & Credit Unions",
            "subcategory":"Bank",
            "type":"Services"
        }
    ],
    "sg:phone":"+61 2 9799 4224",
    "sg:postcode":"2045",
    "sg:province":"NSW",
    "sg:tags":[
        "concrete",
        "reinforcement"
    ],
    "wof:name":"Super Steel Fixing Pty Ltd",
    "wof:placetype":"venue"
},
  "geometry": {"coordinates":[151.14610300000001,-33.876179],"type":"Point"}
}