{
  "type": "Feature",
  "properties": {
    "addr:full":"PO Box 2111 Fortitude Valley Bus Centr QLD 4006",
    "addr:postcode":"4006",
    "iso:country":"AU",
    "sg:address":"PO Box 2111",
    "sg:city":"Fortitude Valley Bus Centr",
    "sg:classifiers":[
        {
            "category":"Education",
            "subcategory":"Junior College",
            "type":"Public Place"
        }
    ],
    "sg:phone":"+61 7 3253 3100",
    "sg:postcode":"4006",
    "sg:province":"QLD",
    "sg:tags":[
        "wholesaler",
        "school",
        "mfrs",
        "uniform"
    ],
    "wof:name":"Ys School Uniforms",
    "wof:placetype":"venue"
},
  "geometry": {"coordinates":[153.039672852,-27.4558525085],"type":"Point"}
}