{
  "type": "Feature",
  "properties": {
    "addr:full":"240 Stamps La Wangaratta VIC 3677",
    "addr:housenumber":"240",
    "addr:postcode":"3677",
    "addr:street":"Stamps La",
    "iso:country":"AU",
    "sg:address":"240 Stamps La",
    "sg:city":"Wangaratta",
    "sg:classifiers":[
        {
            "category":"Professional",
            "subcategory":"Detective & Security Services",
            "type":"Services"
        }
    ],
    "sg:phone":"+61 3 5721 9040",
    "sg:postcode":"3677",
    "sg:province":"VIC",
    "sg:tags":[
        "consultant",
        "system"
    ],
    "wof:name":"Hide Away Safe Co",
    "wof:placetype":"venue"
},
  "geometry": {"coordinates":[146.318527222,-36.3704109192],"type":"Point"}
}