{
  "type": "Feature",
  "properties": {
    "addr:full":"748 High St Prahran VIC 3181",
    "addr:housenumber":"748",
    "addr:postcode":"3181",
    "addr:street":"High St",
    "iso:country":"AU",
    "sg:address":"748 High St",
    "sg:city":"Prahran",
    "sg:classifiers":[
        {
            "category":"Health Services",
            "subcategory":"Health Practitioner",
            "type":"Services"
        }
    ],
    "sg:phone":"+61 3 9576 0373",
    "sg:postcode":"3181",
    "sg:province":"VIC",
    "sg:tags":[
        "psychologist"
    ],
    "wof:name":"Cameron-Grey Heather",
    "wof:placetype":"venue"
},
  "geometry": {"coordinates":[144.999725342,-37.8527030945],"type":"Point"}
}