{
  "type": "Feature",
  "properties": {
    "addr:full":"5 Zeeman St Rochedale South QLD 4123",
    "addr:housenumber":"5",
    "addr:postcode":"4123",
    "addr:street":"Zeeman St",
    "iso:country":"AU",
    "sg:address":"5 Zeeman St",
    "sg:city":"Rochedale South",
    "sg:classifiers":[
        {
            "category":"Food & Beverages",
            "subcategory":"Specialty",
            "type":"Retail Goods"
        }
    ],
    "sg:phone":"+61 1300 720 034",
    "sg:postcode":"4123",
    "sg:province":"QLD",
    "sg:tags":[
        "product",
        "health"
    ],
    "wof:name":"Rapid Nutrition",
    "wof:placetype":"venue"
},
  "geometry": {"coordinates":[153.131713867,-27.5889167786],"type":"Point"}
}