{
  "type": "Feature",
  "properties": {
    "addr:full":"Shop 11 Crossways Shopng Cntr Subiaco WA 6008",
    "addr:housenumber":"shop 11",
    "addr:postcode":"6008",
    "addr:street":"Crossways Shopng Cntr",
    "iso:country":"AU",
    "sg:address":"Shop 11 Crossways Shopng Cntr",
    "sg:city":"Subiaco",
    "sg:classifiers":[
        {
            "category":"Manufacturing",
            "subcategory":"Jewelry",
            "type":"Manufacturing & Wholesale Goods"
        }
    ],
    "sg:phone":"+61 8 9381 9164",
    "sg:postcode":"6008",
    "sg:province":"WA",
    "sg:tags":[
        "mfrg",
        "jeweller"
    ],
    "wof:name":"Jewell-Mend Jewellers",
    "wof:placetype":"venue"
},
  "geometry": {"coordinates":[115.824012756,-31.9468002319],"type":"Point"}
}