{
  "type": "Feature",
  "properties": {
    "iso:country":"AU",
    "sg:address":"2/ 93-103 High St",
    "sg:city":"Preston",
    "sg:classifiers":[
        {
            "category":"Personal",
            "subcategory":"Beauty Salon",
            "type":"Services"
        }
    ],
    "sg:phone":"+61 3 9484 6657",
    "sg:postcode":"3072",
    "sg:province":"VIC",
    "wof:name":"Body Velvet",
    "wof:placetype":"venue"
},
  "geometry": {"coordinates":[145.002807617,-37.7445068359],"type":"Point"}
}