{
  "type": "Feature",
  "properties": {
    "addr:full":"641 Burwood Rd Hawthorn VIC 3122",
    "addr:housenumber":"641",
    "addr:postcode":"3122",
    "addr:street":"Burwood Rd",
    "iso:country":"AU",
    "sg:address":"641 Burwood Rd",
    "sg:city":"Hawthorn",
    "sg:classifiers":[
        {
            "category":"Shopping",
            "subcategory":"Bridal",
            "type":"Retail Goods"
        }
    ],
    "sg:phone":"+61 414 555 877",
    "sg:postcode":"3122",
    "sg:province":"VIC",
    "sg:tags":[
        "hire",
        "wear"
    ],
    "wof:name":"Howe Image Works",
    "wof:placetype":"venue"
},
  "geometry": {"coordinates":[145.04544067399999,-37.8236312866],"type":"Point"}
}