{
  "type": "Feature",
  "properties": {
    "addr:full":"Suite 1, 10- 12 Sherebrooke Blv Woodcroft SA 5162",
    "addr:housenumber":"10 12",
    "addr:postcode":"5162",
    "addr:street":"Sherebrooke Blv",
    "iso:country":"AU",
    "sg:address":"Suite 1, 10- 12 Sherebrooke Blv",
    "sg:city":"Woodcroft",
    "sg:classifiers":[
        {
            "category":"Health Services",
            "subcategory":"Health Practitioner",
            "type":"Services"
        }
    ],
    "sg:phone":"+61 8 8322 6377",
    "sg:postcode":"5162",
    "sg:province":"SA",
    "sg:tags":[
        "physiotherapist"
    ],
    "wof:name":"Suzanne McDougall Physiotherapy",
    "wof:placetype":"venue"
},
  "geometry": {"coordinates":[138.55213928200001,-35.094707489],"type":"Point"}
}