{
  "type": "Feature",
  "properties": {
    "iso:country":"AU",
    "sg:address":"26 Seaview Pde",
    "sg:city":"Palm Beach",
    "sg:classifiers":[
        {
            "category":"Professional",
            "subcategory":"Research",
            "type":"Services"
        }
    ],
    "sg:phone":"+61 7 5533 9199",
    "sg:postcode":"4221",
    "sg:province":"QLD",
    "sg:tags":[
        "market"
    ],
    "wof:name":"Art Union Office Telesellers",
    "wof:placetype":"venue"
},
  "geometry": {"coordinates":[153.461502075,-28.1267585754],"type":"Point"}
}