{
  "type": "Feature",
  "properties": {
    "addr:full":"2/ 18 Sir Laurence Drv Seaford VIC 3198",
    "addr:housenumber":"/ 18",
    "addr:postcode":"3198",
    "addr:street":"Sir Laurence Drv",
    "iso:country":"AU",
    "sg:address":"2/ 18 Sir Laurence Drv",
    "sg:city":"Seaford",
    "sg:classifiers":[
        {
            "category":"Building & Trades",
            "subcategory":"Plumbing",
            "type":"Services"
        }
    ],
    "sg:phone":"+61 3 9773 6222",
    "sg:postcode":"3198",
    "sg:province":"VIC",
    "sg:tags":[
        "plumber",
        "gasfitters"
    ],
    "wof:name":"Bayside Heating and Cooling P/L",
    "wof:placetype":"venue"
},
  "geometry": {"coordinates":[145.14398193400001,-38.1152153015],"type":"Point"}
}