{
  "type": "Feature",
  "properties": {
    "addr:full":"Unit 4, 5 Friesian Cl Sandgate NSW 2304",
    "addr:housenumber":"5",
    "addr:postcode":"2304",
    "addr:street":"Friesian Cl",
    "iso:country":"AU",
    "sg:address":"Unit 4, 5 Friesian Cl",
    "sg:city":"Sandgate",
    "sg:classifiers":[
        {
            "category":"Education",
            "subcategory":"Special Training",
            "type":"Public Place"
        }
    ],
    "sg:phone":"+61 2 4960 9611",
    "sg:postcode":"2304",
    "sg:province":"NSW",
    "sg:tags":[
        "development"
    ],
    "wof:name":"Zokal Safety Training",
    "wof:placetype":"venue"
},
  "geometry": {"coordinates":[151.704711914,-32.8609695435],"type":"Point"}
}