{
  "type": "Feature",
  "properties": {
    "addr:full":"Ogilvie Ave Echuca VIC 3564",
    "addr:postcode":"3564",
    "addr:street":"Ogilvie Ave",
    "iso:country":"AU",
    "sg:address":"Ogilvie Ave",
    "sg:city":"Echuca",
    "sg:classifiers":[
        {
            "category":"Autos & Motor Vehicles",
            "subcategory":"Fuel & Gas Station",
            "type":"Retail Goods"
        }
    ],
    "sg:phone":"+61 3 5482 5655",
    "sg:postcode":"3564",
    "sg:province":"VIC",
    "wof:name":"BP Australia Limited",
    "wof:placetype":"venue"
},
  "geometry": {"coordinates":[144.74734497099999,-36.1404914856],"type":"Point"}
}