{
  "type": "Feature",
  "properties": {
    "iso:country":"AU",
    "sg:address":"140 Dryburgh St",
    "sg:city":"North Melbourne",
    "sg:classifiers":[
        {
            "category":"Professional",
            "subcategory":"Accounting & Tax Preparation",
            "type":"Services"
        }
    ],
    "sg:phone":"+61 3 9329 2570",
    "sg:postcode":"3051",
    "sg:province":"VIC",
    "sg:tags":[
        "distributor",
        "lock",
        "mfrs"
    ],
    "wof:name":"Locksmiths&#039; Supply Co",
    "wof:placetype":"venue"
},
  "geometry": {"coordinates":[144.94371032699999,-37.8032073975],"type":"Point"}
}