{
  "type": "Feature",
  "properties": {
    "iso:country":"AU",
    "sg:address":"Cnr Wyong & Tumbi Creek Rds",
    "sg:city":"Tumbi Umbi",
    "sg:classifiers":[
        {
            "category":"Retail",
            "subcategory":"Auto Repair",
            "type":"Services"
        }
    ],
    "sg:phone":"+61 2 4389 1620",
    "sg:postcode":"2261",
    "sg:province":"NSW",
    "sg:tags":[
        "repairer",
        "motor",
        "engineer"
    ],
    "wof:name":"Wright Col Automotive",
    "wof:placetype":"venue"
},
  "geometry": {"coordinates":[151.449432,-33.362949],"type":"Point"}
}