{
  "type": "Feature",
  "properties": {
    "iso:country":"AU",
    "sg:address":"94 George St",
    "sg:city":"Launceston",
    "sg:classifiers":[
        {
            "category":"Personal",
            "subcategory":"Beauty Salon",
            "type":"Services"
        }
    ],
    "sg:phone":"+61 3 6331 8846",
    "sg:postcode":"7250",
    "sg:province":"TAS",
    "sg:tags":[
        "hairdresser"
    ],
    "wof:name":"Alberto's Salon Of Hairdressing",
    "wof:placetype":"venue"
},
  "geometry": {"coordinates":[147.14030456500001,-41.4362945557],"type":"Point"}
}