{
  "type": "Feature",
  "properties": {
    "iso:country":"AU",
    "sg:address":"84- 86 Parfitt Rd",
    "sg:city":"Wangaratta",
    "sg:classifiers":[
        {
            "category":"Home & Garden",
            "subcategory":"Garden Supply",
            "type":"Retail Goods"
        }
    ],
    "sg:phone":"+61 3 5722 9623",
    "sg:postcode":"3677",
    "sg:province":"VIC",
    "sg:tags":[
        "statuary",
        "fountains",
        "sundial"
    ],
    "wof:name":"Inspired By Style",
    "wof:placetype":"venue"
},
  "geometry": {"coordinates":[146.33738708499999,-36.3460540771],"type":"Point"}
}