{
  "type": "Feature",
  "properties": {
    "iso:country":"AU",
    "sg:address":"40 Burwood Rd",
    "sg:city":"Burwood",
    "sg:classifiers":[
        {
            "category":"Retail",
            "subcategory":"Funeral Services",
            "type":"Services"
        }
    ],
    "sg:phone":"+61 2 9744 2178",
    "sg:postcode":"2134",
    "sg:province":"NSW",
    "sg:tags":[
        "director"
    ],
    "wof:name":"Guardian Funerals",
    "wof:placetype":"venue"
},
  "geometry": {"coordinates":[151.10504150400001,-33.8712730408],"type":"Point"}
}