{
  "type": "Feature",
  "properties": {
    "addr:full":"PO Box 277 Yarraville VIC 3013",
    "addr:postcode":"3013",
    "iso:country":"AU",
    "sg:address":"PO Box 277",
    "sg:city":"Yarraville",
    "sg:classifiers":[
        {
            "category":"Professional",
            "subcategory":"Computer Services",
            "type":"Services"
        }
    ],
    "sg:phone":"+61 3 9315 1332",
    "sg:postcode":"3013",
    "sg:province":"VIC",
    "sg:tags":[
        "consultant",
        "system"
    ],
    "wof:name":"Digital Futures Pty Ltd",
    "wof:placetype":"venue"
},
  "geometry": {"coordinates":[144.882202148,-37.8180885315],"type":"Point"}
}