{
  "type": "Feature",
  "properties": {
    "addr:full":"Level 8 26 Wharf St Brisbane QLD 4000",
    "addr:housenumber":"26",
    "addr:postcode":"4000",
    "addr:street":"Wharf St",
    "iso:country":"AU",
    "sg:address":"Level 8 26 Wharf St",
    "sg:city":"Brisbane",
    "sg:classifiers":[
        {
            "category":"Social Services",
            "subcategory":"Child Care",
            "type":"Services"
        }
    ],
    "sg:phone":"+61 7 3348 7922",
    "sg:postcode":"4000",
    "sg:province":"QLD",
    "sg:tags":[
        "fleet",
        "management"
    ],
    "wof:name":"Streamline Fleet",
    "wof:placetype":"venue"
},
  "geometry": {"coordinates":[153.029693603,-27.4652614594],"type":"Point"}
}