{
  "type": "Feature",
  "properties": {
    "addr:full":"Kindergarten Dakas St Broome WA 6725",
    "addr:postcode":"6725",
    "addr:street":"St",
    "iso:country":"AU",
    "sg:address":"Kindergarten Dakas St",
    "sg:city":"Broome",
    "sg:classifiers":[
        {
            "category":"Education",
            "subcategory":"School",
            "type":"Public Place"
        }
    ],
    "sg:phone":"+61 8 9192 1693",
    "sg:postcode":"6725",
    "sg:province":"WA",
    "wof:name":"St Marys College Broome",
    "wof:placetype":"venue"
},
  "geometry": {"coordinates":[122.22128295900001,-17.9604129791],"type":"Point"}
}