{
  "type": "Feature",
  "properties": {
    "addr:full":"17 - 19 Altree Crt Phillip ACT 2606",
    "addr:housenumber":"19",
    "addr:postcode":"2606",
    "addr:street":"Altree Crt",
    "iso:country":"AU",
    "sg:address":"17 - 19 Altree Crt",
    "sg:city":"Phillip",
    "sg:classifiers":[
        {
            "category":"Shopping",
            "subcategory":"Stationery & Office Supplies",
            "type":"Retail Goods"
        }
    ],
    "sg:phone":"+61 2 6282 6383",
    "sg:postcode":"2606",
    "sg:province":"ACT",
    "sg:tags":[
        "equipment",
        "facsimile"
    ],
    "wof:name":"Office National",
    "wof:placetype":"venue"
},
  "geometry": {"coordinates":[149.08706665,-35.3493995667],"type":"Point"}
}