{
  "type": "Feature",
  "properties": {
    "addr:full":"11 Deal St Mt Hutton NSW 2290",
    "addr:housenumber":"11",
    "addr:postcode":"2290",
    "addr:street":"Deal St",
    "iso:country":"AU",
    "sg:address":"11 Deal St",
    "sg:city":"Mt Hutton",
    "sg:classifiers":[
        {
            "category":"Retail",
            "subcategory":"Repair Shop",
            "type":"Services"
        }
    ],
    "sg:phone":"+61 2 4947 1504",
    "sg:postcode":"2290",
    "sg:province":"NSW",
    "sg:tags":[
        "machine",
        "repairs",
        "part",
        "dryer",
        "washing"
    ],
    "wof:name":"M & R Reynolds",
    "wof:placetype":"venue"
},
  "geometry": {"coordinates":[151.66653442399999,-32.9775543213],"type":"Point"}
}