{
  "type": "Feature",
  "properties": {
    "addr:full":"13a Brook St Sunbury VIC 3429",
    "addr:housenumber":"13a",
    "addr:postcode":"3429",
    "addr:street":"Brook St",
    "iso:country":"AU",
    "sg:address":"13a Brook St",
    "sg:city":"Sunbury",
    "sg:classifiers":[
        {
            "category":"Education",
            "subcategory":"Special Training",
            "type":"Public Place"
        }
    ],
    "sg:phone":"+61 3 9740 8801",
    "sg:postcode":"3429",
    "sg:province":"VIC",
    "sg:tags":[
        "tuition-educational"
    ],
    "wof:name":"Kip McGrath Education Centres",
    "wof:placetype":"venue"
},
  "geometry": {"coordinates":[144.72987365700001,-37.5798072815],"type":"Point"}
}