{
  "type": "Feature",
  "properties": {
    "addr:full":"Shop T321-T322 Erina Fair, Terrigal Drv Erina NSW 2250",
    "addr:postcode":"2250",
    "addr:street":"Terrigal Drv",
    "iso:country":"AU",
    "sg:address":"Shop T321-T322 Erina Fair, Terrigal Drv",
    "sg:city":"Erina",
    "sg:classifiers":[
        {
            "category":"Cafe",
            "type":"Food & Drink"
        }
    ],
    "sg:phone":"+61 2 4365 4695",
    "sg:postcode":"2250",
    "sg:province":"NSW",
    "wof:name":"Starbucks Coffee Company (Australia) Pty Ltd",
    "wof:placetype":"venue"
},
  "geometry": {"coordinates":[151.39523315400001,-33.4345855713],"type":"Point"}
}