{
  "type": "Feature",
  "properties": {
    "addr:full":"8 Cates Ave Waikerie SA 5330",
    "addr:housenumber":"8",
    "addr:postcode":"5330",
    "addr:street":"Cates Ave",
    "iso:country":"AU",
    "sg:address":"8 Cates Ave",
    "sg:city":"Waikerie",
    "sg:classifiers":[
        {
            "category":"Retail",
            "subcategory":"Funeral Services",
            "type":"Services"
        }
    ],
    "sg:phone":"+61 8 8541 2743",
    "sg:postcode":"5330",
    "sg:province":"SA",
    "sg:tags":[
        "director"
    ],
    "wof:name":"Kleemann S A",
    "wof:placetype":"venue"
},
  "geometry": {"coordinates":[139.9815979,-34.1842079163],"type":"Point"}
}