{
  "type": "Feature",
  "properties": {
    "addr:full":"80 March St Richmond NSW 2753",
    "addr:housenumber":"80",
    "addr:postcode":"2753",
    "addr:street":"March St",
    "iso:country":"AU",
    "sg:address":"80 March St",
    "sg:city":"Richmond",
    "sg:classifiers":[
        {
            "category":"Health Services",
            "subcategory":"Dentist",
            "type":"Services"
        }
    ],
    "sg:phone":"+61 2 4588 5070",
    "sg:postcode":"2753",
    "sg:province":"NSW",
    "wof:name":"Gentle Dental Care",
    "wof:placetype":"venue"
},
  "geometry": {"coordinates":[150.752716064,-33.5996818542],"type":"Point"}
}