{
  "type": "Feature",
  "properties": {
    "addr:full":"42- 46 Tarnard Drv Braeside VIC 3195",
    "addr:housenumber":"46",
    "addr:postcode":"3195",
    "addr:street":"Tarnard Drv",
    "iso:country":"AU",
    "sg:address":"42- 46 Tarnard Drv",
    "sg:city":"Braeside",
    "sg:classifiers":[
        {
            "category":"Organizations",
            "subcategory":"Professional Association",
            "type":"Services"
        }
    ],
    "sg:phone":"+61 3 9580 0199",
    "sg:postcode":"3195",
    "sg:province":"VIC",
    "sg:tags":[
        "organisation",
        "business"
    ],
    "wof:name":"Trubilt Fabrications",
    "wof:placetype":"venue"
},
  "geometry": {"coordinates":[145.11408996599999,-37.9895324707],"type":"Point"}
}