{
  "type": "Feature",
  "properties": {
    "addr:full":"Kangarilla Rd Kangarilla SA 5157",
    "addr:postcode":"5157",
    "addr:street":"Kangarilla Rd",
    "iso:country":"AU",
    "sg:address":"Kangarilla Rd",
    "sg:city":"Kangarilla",
    "sg:classifiers":[
        {
            "category":"Mining & Drilling",
            "type":"Manufacturing & Wholesale Goods"
        }
    ],
    "sg:phone":"+61 8 8383 7084",
    "sg:postcode":"5157",
    "sg:province":"SA",
    "sg:tags":[
        "boring",
        "contractor"
    ],
    "wof:name":"Kangarilla Drilling Pty Ltd",
    "wof:placetype":"venue"
},
  "geometry": {"coordinates":[138.66087341299999,-35.1456680298],"type":"Point"}
}