{
  "type": "Feature",
  "properties": {
    "addr:full":"166 Swan St Richmond VIC 3121",
    "addr:housenumber":"166",
    "addr:postcode":"3121",
    "addr:street":"Swan St",
    "iso:country":"AU",
    "sg:address":"166 Swan St",
    "sg:city":"Richmond",
    "sg:classifiers":[
        {
            "category":"Professional",
            "subcategory":"Art Services",
            "type":"Services"
        }
    ],
    "sg:phone":"+61 3 9429 2041",
    "sg:postcode":"3121",
    "sg:province":"VIC",
    "sg:tags":[
        "picture",
        "frame",
        "framing"
    ],
    "wof:name":"Swan St Galleries",
    "wof:placetype":"venue"
},
  "geometry": {"coordinates":[144.99534606899999,-37.8255157471],"type":"Point"}
}