{
  "type": "Feature",
  "properties": {
    "addr:full":"80 Tamar St Ballina NSW 2478",
    "addr:housenumber":"80",
    "addr:postcode":"2478",
    "addr:street":"Tamar St",
    "iso:country":"AU",
    "sg:address":"80 Tamar St",
    "sg:city":"Ballina",
    "sg:classifiers":[
        {
            "category":"Personal",
            "subcategory":"Beauty Salon",
            "type":"Services"
        }
    ],
    "sg:phone":"+61 2 6686 3676",
    "sg:postcode":"2478",
    "sg:province":"NSW",
    "sg:tags":[
        "hairdresser"
    ],
    "wof:name":"Hairmoods",
    "wof:placetype":"venue"
},
  "geometry": {"coordinates":[153.55632019000001,-28.8674297333],"type":"Point"}
}