{
  "type": "Feature",
  "properties": {
    "addr:full":"5 Helwig Ave Montmorency VIC 3094",
    "addr:housenumber":"5",
    "addr:postcode":"3094",
    "addr:street":"Helwig Ave",
    "iso:country":"AU",
    "sg:address":"5 Helwig Ave",
    "sg:city":"Montmorency",
    "sg:classifiers":[
        {
            "category":"Military Area",
            "subcategory":"Coast Guard Base",
            "type":"Public Place"
        }
    ],
    "sg:phone":"+61 419 547 147",
    "sg:postcode":"3094",
    "sg:province":"VIC",
    "sg:tags":[
        "sound",
        "engineer"
    ],
    "wof:name":"The P.A. Sherriff",
    "wof:placetype":"venue"
},
  "geometry": {"coordinates":[145.12498474099999,-37.7244491577],"type":"Point"}
}