{
  "type": "Feature",
  "properties": {
    "addr:full":"PO Box 274 Kapunda SA 5373",
    "addr:postcode":"5373",
    "iso:country":"AU",
    "sg:address":"PO Box 274",
    "sg:city":"Kapunda",
    "sg:classifiers":[
        {
            "category":"Farming",
            "subcategory":"Livestock Farm",
            "type":"Manufacturing & Wholesale Goods"
        }
    ],
    "sg:phone":"+61 8 8566 3028",
    "sg:postcode":"5373",
    "sg:province":"SA",
    "sg:tags":[
        "breeder",
        "horse",
        "stud"
    ],
    "wof:name":"R D Quarter Horses",
    "wof:placetype":"venue"
},
  "geometry": {"coordinates":[138.91636657699999,-34.3394889832],"type":"Point"}
}