{
  "type": "Feature",
  "properties": {
    "addr:full":"U 2/ 11 Victoria Pde Manly NSW 2095",
    "addr:housenumber":"11",
    "addr:postcode":"2095",
    "addr:street":"Victoria Pde",
    "iso:country":"AU",
    "sg:address":"U 2/ 11 Victoria Pde",
    "sg:city":"Manly",
    "sg:classifiers":[
        {
            "category":"Health Services",
            "subcategory":"Health Practitioner",
            "type":"Services"
        }
    ],
    "sg:phone":"+61 2 9976 5466",
    "sg:postcode":"2095",
    "sg:province":"NSW",
    "sg:tags":[
        "naturopath"
    ],
    "wof:name":"Sutherland Kira",
    "wof:placetype":"venue"
},
  "geometry": {"coordinates":[151.28752136200001,-33.7998695374],"type":"Point"}
}