{
  "type": "Feature",
  "properties": {
    "addr:full":"52 Whites Rd Werribee South VIC 3030",
    "addr:housenumber":"52",
    "addr:postcode":"3030",
    "addr:street":"Whites Rd",
    "iso:country":"AU",
    "sg:address":"52 Whites Rd",
    "sg:city":"Werribee South",
    "sg:classifiers":[
        {
            "category":"Food & Beverages",
            "subcategory":"Fruits & Vegetables",
            "type":"Retail Goods"
        }
    ],
    "sg:phone":"+61 3 9742 1408",
    "sg:postcode":"3030",
    "sg:province":"VIC",
    "sg:tags":[
        "grower"
    ],
    "wof:name":"Velisha Brother's F & S",
    "wof:placetype":"venue"
},
  "geometry": {"coordinates":[144.69580099999999,-37.952538],"type":"Point"}
}