{
  "type": "Feature",
  "properties": {
    "addr:full":"9 Gregory St Acacia Ridge QLD 4110",
    "addr:housenumber":"9",
    "addr:postcode":"4110",
    "addr:street":"Gregory St",
    "iso:country":"AU",
    "sg:address":"9 Gregory St",
    "sg:city":"Acacia Ridge",
    "sg:classifiers":[
        {
            "category":"Professional",
            "subcategory":"Accounting & Tax Preparation",
            "type":"Services"
        }
    ],
    "sg:phone":"+61 412 678 506",
    "sg:postcode":"4110",
    "sg:province":"QLD",
    "sg:tags":[
        "bookkeeping"
    ],
    "wof:name":"Titmarsh Terence R",
    "wof:placetype":"venue"
},
  "geometry": {"coordinates":[153.01690673799999,-27.579618454],"type":"Point"}
}