{
  "type": "Feature",
  "properties": {
    "iso:country":"AU",
    "sg:address":"7 Brooker St",
    "sg:city":"Bonython",
    "sg:classifiers":[
        {
            "category":"Shopping",
            "subcategory":"Computers & Home Electronics",
            "type":"Retail Goods"
        }
    ],
    "sg:phone":"+61 402 214 623",
    "sg:postcode":"2905",
    "sg:province":"ACT",
    "sg:tags":[
        "equipment",
        "part",
        "electronic"
    ],
    "wof:name":"Frasers Electronic Repairs",
    "wof:placetype":"venue"
},
  "geometry": {"coordinates":[149.07595825199999,-35.4259681702],"type":"Point"}
}