{
  "type": "Feature",
  "properties": {
    "iso:country":"AU",
    "sg:address":"50 Yuilles Rd",
    "sg:city":"Mornington",
    "sg:classifiers":[
        {
            "category":"Autos & Motor Vehicles",
            "subcategory":"Automobile Sales",
            "type":"Retail Goods"
        }
    ],
    "sg:phone":"+61 3 5976 4177",
    "sg:postcode":"3931",
    "sg:province":"VIC",
    "sg:tags":[
        "car",
        "used"
    ],
    "wof:name":"Peninsula Car Company",
    "wof:placetype":"venue"
},
  "geometry": {"coordinates":[145.04589843799999,-38.230884552],"type":"Point"}
}