{
  "type": "Feature",
  "properties": {
    "iso:country":"AU",
    "sg:address":"45 Central Coast Hwy",
    "sg:city":"Gosford West",
    "sg:classifiers":[
        {
            "category":"Autos & Motor Vehicles",
            "subcategory":"Auto Supplies",
            "type":"Retail Goods"
        }
    ],
    "sg:phone":"+61 2 4322 9155",
    "sg:postcode":"2250",
    "sg:province":"NSW",
    "sg:tags":[
        "accessory"
    ],
    "wof:name":"Stockmans Sheepskin Factory",
    "wof:placetype":"venue"
},
  "geometry": {"coordinates":[151.32734680199999,-33.4264717102],"type":"Point"}
}