{
  "type": "Feature",
  "properties": {
    "addr:full":"25 Colebard St West Archerfield QLD 4108",
    "addr:housenumber":"25",
    "addr:postcode":"4108",
    "addr:street":"Colebard St West",
    "iso:country":"AU",
    "sg:address":"25 Colebard St West",
    "sg:city":"Archerfield",
    "sg:classifiers":[
        {
            "category":"Professional",
            "type":"Services"
        }
    ],
    "sg:phone":"+61 7 3274 5774",
    "sg:postcode":"4108",
    "sg:province":"QLD",
    "sg:tags":[
        "transport"
    ],
    "wof:name":"First Fleet Express",
    "wof:placetype":"venue"
},
  "geometry": {"coordinates":[153.00357055699999,-27.5772418976],"type":"Point"}
}