{
  "type": "Feature",
  "properties": {
    "iso:country":"AU",
    "sg:address":"Lvl 1, 793 George St",
    "sg:city":"Sydney",
    "sg:classifiers":[
        {
            "category":"Health Services",
            "subcategory":"Dentist",
            "type":"Services"
        }
    ],
    "sg:phone":"+61 2 9211 1011",
    "sg:postcode":"2000",
    "sg:province":"NSW",
    "wof:name":"Jacobson, Selwyn Dr",
    "wof:placetype":"venue"
},
  "geometry": {"coordinates":[151.20411682100001,-33.8826179504],"type":"Point"}
}