{
  "type": "Feature",
  "properties": {
    "addr:full":"2 Phillips St Coburg VIC 3058",
    "addr:housenumber":"2",
    "addr:postcode":"3058",
    "addr:street":"Phillips St",
    "iso:country":"AU",
    "sg:address":"2 Phillips St",
    "sg:city":"Coburg",
    "sg:classifiers":[
        {
            "category":"Shopping",
            "subcategory":"Party Supplies",
            "type":"Retail Goods"
        }
    ],
    "sg:phone":"+61 422 465 203",
    "sg:postcode":"3058",
    "sg:province":"VIC",
    "wof:name":"P.A's For Parties",
    "wof:placetype":"venue"
},
  "geometry": {"coordinates":[144.95404052699999,-37.7503738403],"type":"Point"}
}