{
  "type": "Feature",
  "properties": {
    "addr:full":"601 Forest Rd Bexley NSW 2207",
    "addr:housenumber":"601",
    "addr:postcode":"2207",
    "addr:street":"Forest Rd",
    "iso:country":"AU",
    "sg:address":"601 Forest Rd",
    "sg:city":"Bexley",
    "sg:classifiers":[
        {
            "category":"Food & Beverages",
            "subcategory":"Fruits & Vegetables",
            "type":"Retail Goods"
        }
    ],
    "sg:phone":"+61 2 9502 3363",
    "sg:postcode":"2207",
    "sg:province":"NSW",
    "sg:tags":[
        "greengrocer",
        "fruiterer"
    ],
    "wof:name":"All Seasons Fruit Market",
    "wof:placetype":"venue"
},
  "geometry": {"coordinates":[151.11836199999999,-33.956074],"type":"Point"}
}