{
  "type": "Feature",
  "properties": {
    "addr:full":"1 Dora St Marsfield NSW 2122",
    "addr:housenumber":"1",
    "addr:postcode":"2122",
    "addr:street":"Dora St",
    "iso:country":"AU",
    "sg:address":"1 Dora St",
    "sg:city":"Marsfield",
    "sg:classifiers":[
        {
            "category":"Building & Trades",
            "subcategory":"Cleaning & Sanitation",
            "type":"Services"
        }
    ],
    "sg:phone":"+61 400 342 451",
    "sg:postcode":"2122",
    "sg:province":"NSW",
    "sg:tags":[
        "industrial",
        "commercial",
        "contractor"
    ],
    "wof:name":"Philp Karadaghian",
    "wof:placetype":"venue"
},
  "geometry": {"coordinates":[151.11192321799999,-33.7835464478],"type":"Point"}
}