{
  "type": "Feature",
  "properties": {
    "addr:full":"33 Church St Brighton VIC 3186",
    "addr:housenumber":"33",
    "addr:postcode":"3186",
    "addr:street":"Church St",
    "iso:country":"AU",
    "sg:address":"33 Church St",
    "sg:city":"Brighton",
    "sg:classifiers":[
        {
            "category":"Wholesale",
            "subcategory":"Drugs",
            "type":"Manufacturing & Wholesale Goods"
        }
    ],
    "sg:phone":"+61 3 9592 1500",
    "sg:postcode":"3186",
    "sg:province":"VIC",
    "sg:tags":[
        "wholesaler",
        "pharmaceutical",
        "product",
        "mfrs"
    ],
    "wof:name":"Brighton Pharmacy",
    "wof:placetype":"venue"
},
  "geometry": {"coordinates":[144.99380493199999,-37.9131393433],"type":"Point"}
}