{
  "type": "Feature",
  "properties": {
    "addr:full":"Shop 37/ 1 Central Ave Altona Meadows VIC 3028",
    "addr:housenumber":"shop 37 / 1",
    "addr:postcode":"3028",
    "addr:street":"Central Ave",
    "iso:country":"AU",
    "sg:address":"Shop 37/ 1 Central Ave",
    "sg:city":"Altona Meadows",
    "sg:classifiers":[
        {
            "category":"Cafe",
            "type":"Food & Drink"
        }
    ],
    "sg:phone":"+61 3 9315 6189",
    "sg:postcode":"3028",
    "sg:province":"VIC",
    "wof:name":"Central Square Nuts And Sweets",
    "wof:placetype":"venue"
},
  "geometry": {"coordinates":[144.77726699999999,-37.871326],"type":"Point"}
}