{
  "type": "Feature",
  "properties": {
    "addr:full":"300 Cambridge Rd Warrane TAS 7018",
    "addr:housenumber":"300",
    "addr:postcode":"7018",
    "addr:street":"Cambridge Rd",
    "iso:country":"AU",
    "sg:address":"300 Cambridge Rd",
    "sg:city":"Warrane",
    "sg:classifiers":[
        {
            "category":"Industrial Area",
            "type":"Public Place"
        }
    ],
    "sg:phone":"+61 448 443 208",
    "sg:postcode":"7018",
    "sg:province":"TAS",
    "sg:tags":[
        "rural",
        "shed"
    ],
    "wof:name":"Whelan Contracting",
    "wof:placetype":"venue"
},
  "geometry": {"coordinates":[147.39291381800001,-42.8567199707],"type":"Point"}
}