{
  "type": "Feature",
  "properties": {
    "iso:country":"AU",
    "sg:address":"4 Eastbourne St",
    "sg:city":"Chermside West",
    "sg:classifiers":[
        {
            "category":"Home & Garden",
            "subcategory":"Household Appliances",
            "type":"Retail Goods"
        }
    ],
    "sg:phone":"+61 417 715 765",
    "sg:postcode":"4032",
    "sg:province":"QLD",
    "sg:tags":[
        "equipment",
        "gas"
    ],
    "wof:name":"Lyle The Gas Man",
    "wof:placetype":"venue"
},
  "geometry": {"coordinates":[153.01130699999999,-27.390381],"type":"Point"}
}