{
  "type": "Feature",
  "properties": {
    "addr:full":"3/ 12 Strathaird Rd Bundall QLD 4217",
    "addr:housenumber":"/ 12",
    "addr:postcode":"4217",
    "addr:street":"Strathaird Rd",
    "iso:country":"AU",
    "sg:address":"3/ 12 Strathaird Rd",
    "sg:city":"Bundall",
    "sg:classifiers":[
        {
            "category":"Shopping",
            "subcategory":"Bicycles & Sporting Goods",
            "type":"Retail Goods"
        }
    ],
    "sg:phone":"+61 7 5592 3993",
    "sg:postcode":"4217",
    "sg:province":"QLD",
    "sg:tags":[
        "chemical",
        "equipment",
        "pool",
        "swimming"
    ],
    "wof:name":"Poolstore International",
    "wof:placetype":"venue"
},
  "geometry": {"coordinates":[153.40370178200001,-28.0090045929],"type":"Point"}
}