{
  "type": "Feature",
  "properties": {
    "addr:full":"8 Volitans Ave Mt Eliza VIC 3930",
    "addr:housenumber":"8",
    "addr:postcode":"3930",
    "addr:street":"Volitans Ave",
    "iso:country":"AU",
    "sg:address":"8 Volitans Ave",
    "sg:city":"Mt Eliza",
    "sg:classifiers":[
        {
            "category":"Banks & Credit Unions",
            "subcategory":"Financial Services",
            "type":"Services"
        }
    ],
    "sg:phone":"+61 1300 653 795",
    "sg:postcode":"3930",
    "sg:province":"VIC",
    "sg:tags":[
        "loan",
        "finance",
        "mortgage"
    ],
    "wof:name":"My Share",
    "wof:placetype":"venue"
},
  "geometry": {"coordinates":[145.078048706,-38.1940498352],"type":"Point"}
}