{
  "type": "Feature",
  "properties": {
    "iso:country":"AU",
    "sg:address":"Un 4/ 164 G Burwood Rd",
    "sg:city":"Concord",
    "sg:classifiers":[
        {
            "category":"Home & Garden",
            "subcategory":"Carpets & Floor Coverings",
            "type":"Retail Goods"
        }
    ],
    "sg:phone":"+61 2 9744 7989",
    "sg:postcode":"2137",
    "sg:province":"NSW",
    "sg:tags":[
        "tile",
        "wall"
    ],
    "wof:name":"Ossino C & A Indust. Tiling",
    "wof:placetype":"venue"
},
  "geometry": {"coordinates":[151.10980224599999,-33.861038208],"type":"Point"}
}