{
  "type": "Feature",
  "properties": {
    "iso:country":"AU",
    "sg:address":"2 Boundary Rd",
    "sg:city":"Tumut",
    "sg:classifiers":[
        {
            "category":"Freight",
            "type":"Transportation"
        }
    ],
    "sg:phone":"+61 2 6947 9030",
    "sg:postcode":"2720",
    "sg:province":"NSW",
    "sg:tags":[
        "light",
        "carrier"
    ],
    "wof:name":"Tumut Freight Service",
    "wof:placetype":"venue"
},
  "geometry": {"coordinates":[148.207153,-35.2981],"type":"Point"}
}