{
  "type": "Feature",
  "properties": {
    "addr:full":"Roadside Mail Box 2305 Eaglehawk VIC 3556",
    "addr:postcode":"3556",
    "iso:country":"AU",
    "sg:address":"Roadside Mail Box 2305",
    "sg:city":"Eaglehawk",
    "sg:classifiers":[
        {
            "category":"Professional",
            "subcategory":"Art Services",
            "type":"Services"
        }
    ],
    "sg:phone":"+61 3 5436 1548",
    "sg:postcode":"3556",
    "sg:province":"VIC",
    "sg:tags":[
        "decorator",
        "painter"
    ],
    "wof:name":"Tabmow Painting & Decorating",
    "wof:placetype":"venue"
},
  "geometry": {"coordinates":[144.249633789,-36.7074394226],"type":"Point"}
}