{
  "type": "Feature",
  "properties": {
    "iso:country":"AU",
    "sg:address":"Rocky Castle Rd",
    "sg:city":"Coonawarra",
    "sg:classifiers":[
        {
            "category":"Farming",
            "subcategory":"Vineyard",
            "type":"Manufacturing & Wholesale Goods"
        }
    ],
    "sg:phone":"+61 8 8736 3333",
    "sg:postcode":"5263",
    "sg:province":"SA",
    "sg:tags":[
        "winery"
    ],
    "wof:name":"Koonara Management",
    "wof:placetype":"venue"
},
  "geometry": {"coordinates":[140.874283,-37.26495],"type":"Point"}
}