{
  "type": "Feature",
  "properties": {
    "addr:full":"10 Foote St Acacia Ridge QLD 4110",
    "addr:housenumber":"10",
    "addr:postcode":"4110",
    "addr:street":"Foote St",
    "iso:country":"AU",
    "sg:address":"10 Foote St",
    "sg:city":"Acacia Ridge",
    "sg:classifiers":[
        {
            "category":"Health Services",
            "subcategory":"Doctor",
            "type":"Services"
        }
    ],
    "sg:phone":"+61 7 3277 6488",
    "sg:postcode":"4110",
    "sg:province":"QLD",
    "sg:tags":[
        "medical",
        "practitioner"
    ],
    "wof:name":"V T Doan Dang",
    "wof:placetype":"venue"
},
  "geometry": {"coordinates":[153.024368286,-27.5806713104],"type":"Point"}
}