{
  "type": "Feature",
  "properties": {
    "addr:full":"16 Power Crs Port Augusta SA 5700",
    "addr:housenumber":"16",
    "addr:postcode":"5700",
    "addr:street":"Power Crs",
    "iso:country":"AU",
    "sg:address":"16 Power Crs",
    "sg:city":"Port Augusta",
    "sg:classifiers":[
        {
            "category":"Utilities",
            "subcategory":"Water",
            "type":"Services"
        }
    ],
    "sg:phone":"+61 8 8641 0993",
    "sg:postcode":"5700",
    "sg:province":"SA",
    "sg:tags":[
        "hot",
        "system"
    ],
    "wof:name":"Brian Franke Electrical, Refrigeration & Air Conditioning",
    "wof:placetype":"venue"
},
  "geometry": {"coordinates":[137.78460693400001,-32.5366020203],"type":"Point"}
}