{
  "type": "Feature",
  "properties": {
    "iso:country":"AU",
    "sg:address":"Stockland Centre Phillip St",
    "sg:city":"Gladstone",
    "sg:classifiers":[
        {
            "category":"Manufacturing",
            "subcategory":"Jewelry",
            "type":"Manufacturing & Wholesale Goods"
        }
    ],
    "sg:phone":"+61 7 4978 3733",
    "sg:postcode":"4680",
    "sg:province":"QLD",
    "sg:tags":[
        "mfrg",
        "jeweller"
    ],
    "wof:name":"Neville Gregory Leading Edge Jewellers",
    "wof:placetype":"venue"
},
  "geometry": {"coordinates":[151.37464904800001,-23.9533576965],"type":"Point"}
}