{
  "type": "Feature",
  "properties": {
    "addr:full":"287 Charman Rd Cheltenham VIC 3192",
    "addr:housenumber":"287",
    "addr:postcode":"3192",
    "addr:street":"Charman Rd",
    "iso:country":"AU",
    "sg:address":"287 Charman Rd",
    "sg:city":"Cheltenham",
    "sg:classifiers":[
        {
            "category":"Health Services",
            "subcategory":"Optometrist",
            "type":"Services"
        }
    ],
    "sg:phone":"+61 3 9585 0477",
    "sg:postcode":"3192",
    "sg:province":"VIC",
    "wof:name":"Cheltenham Optical Centre",
    "wof:placetype":"venue"
},
  "geometry": {"coordinates":[145.05548095699999,-37.9657402039],"type":"Point"}
}