{
  "type": "Feature",
  "properties": {
    "iso:country":"AU",
    "sg:address":"Locked Bag 7",
    "sg:city":"Beaudesert",
    "sg:classifiers":[
        {
            "category":"Shopping",
            "subcategory":"Party Supplies",
            "type":"Retail Goods"
        }
    ],
    "sg:phone":"+61 7 5543 2107",
    "sg:postcode":"4285",
    "sg:province":"QLD",
    "sg:tags":[
        "selling",
        "plan"
    ],
    "wof:name":"Your Eyes Only",
    "wof:placetype":"venue"
},
  "geometry": {"coordinates":[152.995819,-27.98781],"type":"Point"}
}