{
  "type": "Feature",
  "properties": {
    "addr:full":"14 Gulson St Goulburn NSW 2580",
    "addr:housenumber":"14",
    "addr:postcode":"2580",
    "addr:street":"Gulson St",
    "iso:country":"AU",
    "sg:address":"14 Gulson St",
    "sg:city":"Goulburn",
    "sg:classifiers":[
        {
            "category":"Food & Beverages",
            "subcategory":"Bakery",
            "type":"Retail Goods"
        }
    ],
    "sg:phone":"+61 2 4821 3722",
    "sg:postcode":"2580",
    "sg:province":"NSW",
    "sg:tags":[
        "baker"
    ],
    "wof:name":"Tip Top Bakeries (Canberra)",
    "wof:placetype":"venue"
},
  "geometry": {"coordinates":[149.74566650400001,-34.7281761169],"type":"Point"}
}