{
  "type": "Feature",
  "properties": {
    "addr:full":"Shop 20a Kingsvale Shopping Centre 302 Ross River Aitkenvale QLD 4814",
    "addr:housenumber":"20a;302",
    "addr:postcode":"4814",
    "addr:street":"Kingsvale Shopping",
    "iso:country":"AU",
    "sg:address":"Shop 20a Kingsvale Shopping Centre 302 Ross River",
    "sg:city":"Aitkenvale",
    "sg:classifiers":[
        {
            "category":"Shopping",
            "subcategory":"Clothing, Apparel, & Fashions",
            "type":"Retail Goods"
        }
    ],
    "sg:phone":"+61 7 4725 4180",
    "sg:postcode":"4814",
    "sg:province":"QLD",
    "sg:tags":[
        "lady",
        "wear"
    ],
    "wof:name":"Dress to Impress",
    "wof:placetype":"venue"
},
  "geometry": {"coordinates":[146.76507599999999,-19.297756],"type":"Point"}
}