{
  "type": "Feature",
  "properties": {
    "addr:full":"30 Greenfield Pde Bankstown NSW 2200",
    "addr:housenumber":"30",
    "addr:postcode":"2200",
    "addr:street":"Greenfield Pde",
    "iso:country":"AU",
    "sg:address":"30 Greenfield Pde",
    "sg:city":"Bankstown",
    "sg:classifiers":[
        {
            "category":"Professional",
            "subcategory":"Accounting & Tax Preparation",
            "type":"Services"
        }
    ],
    "sg:phone":"+61 2 9790 1431",
    "sg:postcode":"2200",
    "sg:province":"NSW",
    "sg:tags":[
        "consultant",
        "taxation"
    ],
    "wof:name":"S T Tran & Co",
    "wof:placetype":"venue"
},
  "geometry": {"coordinates":[151.03201300000001,-33.919632],"type":"Point"}
}