{
  "type": "Feature",
  "properties": {
    "addr:full":"16 Yilgarn St Northam WA 6401",
    "addr:housenumber":"16",
    "addr:postcode":"6401",
    "addr:street":"Yilgarn St",
    "iso:country":"AU",
    "sg:address":"16 Yilgarn St",
    "sg:city":"Northam",
    "sg:classifiers":[
        {
            "category":"Wholesale",
            "subcategory":"Farm Supplies",
            "type":"Manufacturing & Wholesale Goods"
        }
    ],
    "sg:phone":"+61 8 9621 2900",
    "sg:postcode":"6401",
    "sg:province":"WA",
    "sg:tags":[
        "equipment"
    ],
    "wof:name":"Landmark",
    "wof:placetype":"venue"
},
  "geometry": {"coordinates":[116.689620972,-31.649143219],"type":"Point"}
}