{
  "type": "Feature",
  "properties": {
    "addr:full":"Westfield Shoppingtown, Macquarie St Liverpool NSW 2170",
    "addr:postcode":"2170",
    "addr:street":"Macquarie St",
    "iso:country":"AU",
    "sg:address":"Westfield Shoppingtown, Macquarie St",
    "sg:city":"Liverpool",
    "sg:classifiers":[
        {
            "category":"Shopping",
            "subcategory":"Mobile Phones",
            "type":"Retail Goods"
        }
    ],
    "sg:phone":"+61 2 9824 3488",
    "sg:postcode":"2170",
    "sg:province":"NSW",
    "sg:tags":[
        "telephone",
        "accessory"
    ],
    "wof:name":"Fone Zone",
    "wof:placetype":"venue"
},
  "geometry": {"coordinates":[150.92414855999999,-33.9189300537],"type":"Point"}
}