{
  "type": "Feature",
  "properties": {
    "iso:country":"AU",
    "sg:address":"467 Guildford Rd",
    "sg:city":"Bayswater",
    "sg:classifiers":[
        {
            "category":"Deli",
            "type":"Food & Drink"
        }
    ],
    "sg:phone":"+61 8 9272 6490",
    "sg:postcode":"6053",
    "sg:province":"WA",
    "sg:tags":[
        "delicatessen"
    ],
    "wof:name":"Slade St Supa Deli",
    "wof:placetype":"venue"
},
  "geometry": {"coordinates":[115.918426514,-31.9243144989],"type":"Point"}
}