{
  "type": "Feature",
  "properties": {
    "addr:full":"Unit 1 9 Church Rd Maddington WA 6109",
    "addr:housenumber":"9",
    "addr:postcode":"6109",
    "addr:street":"Church Rd",
    "iso:country":"AU",
    "sg:address":"Unit 1 9 Church Rd",
    "sg:city":"Maddington",
    "sg:classifiers":[
        {
            "category":"Wholesale",
            "subcategory":"Furniture",
            "type":"Manufacturing & Wholesale Goods"
        }
    ],
    "sg:phone":"+61 8 9459 7715",
    "sg:postcode":"6109",
    "sg:province":"WA",
    "sg:tags":[
        "wholesaler",
        "mfrs"
    ],
    "wof:name":"Doenich Furniture",
    "wof:placetype":"venue"
},
  "geometry": {"coordinates":[115.97982788100001,-32.0468711853],"type":"Point"}
}