{
  "type": "Feature",
  "properties": {
    "addr:full":"RMB 701 Kaniva VIC 3419",
    "addr:postcode":"3419",
    "iso:country":"AU",
    "sg:address":"RMB 701",
    "sg:city":"Kaniva",
    "sg:classifiers":[
        {
            "category":"Farming",
            "subcategory":"Farm",
            "type":"Manufacturing & Wholesale Goods"
        }
    ],
    "sg:phone":"+61 3 5392 2667",
    "sg:postcode":"3419",
    "sg:province":"VIC",
    "sg:tags":[
        "farmer"
    ],
    "wof:name":"Deckert B H & C J",
    "wof:placetype":"venue"
},
  "geometry": {"coordinates":[141.23869323700001,-36.3785514832],"type":"Point"}
}