{
  "type": "Feature",
  "properties": {
    "iso:country":"AU",
    "sg:address":"19 Henderson St",
    "sg:city":"Waikerie",
    "sg:classifiers":[
        {
            "category":"Professional",
            "subcategory":"Detective & Security Services",
            "type":"Services"
        }
    ],
    "sg:phone":"+61 8 8541 2437",
    "sg:postcode":"5330",
    "sg:province":"SA",
    "sg:tags":[
        "equipment",
        "window",
        "doors"
    ],
    "wof:name":"Robs Security Screens",
    "wof:placetype":"venue"
},
  "geometry": {"coordinates":[139.983978272,-34.1782836914],"type":"Point"}
}