{
  "type": "Feature",
  "properties": {
    "addr:full":"57 Rhodes St Hillsdale NSW 2036",
    "addr:housenumber":"57",
    "addr:postcode":"2036",
    "addr:street":"Rhodes St",
    "iso:country":"AU",
    "sg:address":"57 Rhodes St",
    "sg:city":"Hillsdale",
    "sg:classifiers":[
        {
            "category":"Wholesale",
            "subcategory":"Toys & Hobbies",
            "type":"Manufacturing & Wholesale Goods"
        }
    ],
    "sg:phone":"+61 2 9694 1433",
    "sg:postcode":"2036",
    "sg:province":"NSW",
    "wof:name":"Lucky Company Pty Ltd",
    "wof:placetype":"venue"
},
  "geometry": {"coordinates":[151.226730347,-33.9513931274],"type":"Point"}
}