{
  "type": "Feature",
  "properties": {
    "addr:full":"13 Bradpole Rd Elizabeth West SA 5113",
    "addr:housenumber":"13",
    "addr:postcode":"5113",
    "addr:street":"Bradpole Rd",
    "iso:country":"AU",
    "sg:address":"13 Bradpole Rd",
    "sg:city":"Elizabeth West",
    "sg:classifiers":[
        {
            "category":"Manufacturing",
            "subcategory":"Tools & Machinery",
            "type":"Manufacturing & Wholesale Goods"
        }
    ],
    "sg:phone":"+61 8 8287 1499",
    "sg:postcode":"5113",
    "sg:province":"SA",
    "sg:tags":[
        "toolmaker"
    ],
    "wof:name":"Elizabeth Tooling",
    "wof:placetype":"venue"
},
  "geometry": {"coordinates":[138.66575622600001,-34.7073440552],"type":"Point"}
}