{
  "type": "Feature",
  "properties": {
    "addr:full":"73 O'Shannesy St Sunbury VIC 3429",
    "addr:housenumber":"73",
    "addr:postcode":"3429",
    "addr:street":"O'Shannesy St",
    "iso:country":"AU",
    "sg:address":"73 O'Shannesy St",
    "sg:city":"Sunbury",
    "sg:classifiers":[
        {
            "category":"Shopping",
            "subcategory":"Bicycles & Sporting Goods",
            "type":"Retail Goods"
        }
    ],
    "sg:phone":"+61 3 9740 6811",
    "sg:postcode":"3429",
    "sg:province":"VIC",
    "sg:tags":[
        "dance",
        "accessory",
        "wear",
        "supply"
    ],
    "wof:name":"Sunbury Dance & Fabric Shop",
    "wof:placetype":"venue"
},
  "geometry": {"coordinates":[144.7290802,-37.5800704956],"type":"Point"}
}