{
  "type": "Feature",
  "properties": {
    "addr:full":"Shop 1, 235 Peel St Tamworth NSW 2340",
    "addr:housenumber":"shop 1 235",
    "addr:postcode":"2340",
    "addr:street":"Peel St",
    "iso:country":"AU",
    "sg:address":"Shop 1, 235 Peel St",
    "sg:city":"Tamworth",
    "sg:classifiers":[
        {
            "category":"Fast Food",
            "type":"Food & Drink"
        }
    ],
    "sg:phone":"+61 2 6761 2166",
    "sg:postcode":"2340",
    "sg:province":"NSW",
    "sg:tags":[
        "away",
        "take"
    ],
    "wof:name":"Eagle Boys Pizza - Tamworth",
    "wof:placetype":"venue"
},
  "geometry": {"coordinates":[150.92758178700001,-31.0883750916],"type":"Point"}
}