{
  "type": "Feature",
  "properties": {
    "iso:country":"AU",
    "sg:address":"47 Railway Ave",
    "sg:city":"Werribee",
    "sg:classifiers":[
        {
            "category":"Retail",
            "subcategory":"Repair Shop",
            "type":"Services"
        }
    ],
    "sg:phone":"+61 3 9741 5454",
    "sg:postcode":"3030",
    "sg:province":"VIC",
    "sg:tags":[
        "machine",
        "repairs",
        "part",
        "dryer",
        "washing"
    ],
    "wof:name":"Werribee Refrigeration",
    "wof:placetype":"venue"
},
  "geometry": {"coordinates":[144.675949,-37.893078],"type":"Point"}
}