{
  "type": "Feature",
  "properties": {
    "addr:full":"Shop 8, Mt Hawthorn Plaza Mt Hawthorn WA 6016",
    "addr:housenumber":"shop 8",
    "addr:postcode":"6016",
    "addr:street":"Mt Hawthorn Plaza Mt",
    "iso:country":"AU",
    "sg:address":"Shop 8, Mt Hawthorn Plaza",
    "sg:city":"Mt Hawthorn",
    "sg:classifiers":[
        {
            "category":"Communications",
            "subcategory":"Film & Video Production",
            "type":"Services"
        }
    ],
    "sg:phone":"+61 8 9444 0289",
    "sg:postcode":"6016",
    "sg:province":"WA",
    "sg:tags":[
        "dvd",
        "library"
    ],
    "wof:name":"Network Video",
    "wof:placetype":"venue"
},
  "geometry": {"coordinates":[115.837333679,-31.9206905365],"type":"Point"}
}