{
  "type": "Feature",
  "properties": {
    "addr:full":"PO Box 399 Scone NSW 2337",
    "addr:postcode":"2337",
    "iso:country":"AU",
    "sg:address":"PO Box 399",
    "sg:city":"Scone",
    "sg:classifiers":[
        {
            "category":"Building & Trades",
            "subcategory":"Construction",
            "type":"Services"
        }
    ],
    "sg:phone":"+61 418 460 045",
    "sg:postcode":"2337",
    "sg:province":"NSW",
    "sg:tags":[
        "contractor"
    ],
    "wof:name":"John Bingham Building",
    "wof:placetype":"venue"
},
  "geometry": {"coordinates":[150.86781310999999,-32.0457496643],"type":"Point"}
}