{
  "type": "Feature",
  "properties": {
    "iso:country":"AU",
    "sg:address":"Level 1/ 10 Bridge Rd",
    "sg:city":"Stanmore",
    "sg:classifiers":[
        {
            "category":"Building & Trades",
            "subcategory":"Cleaning & Sanitation",
            "type":"Services"
        }
    ],
    "sg:phone":"+61 1300 660 573",
    "sg:postcode":"2048",
    "sg:province":"NSW",
    "sg:tags":[
        "commercial",
        "maintenance"
    ],
    "wof:name":"Advanced Building Technologies Group Pty Ltd",
    "wof:placetype":"venue"
},
  "geometry": {"coordinates":[151.171234,-33.889065],"type":"Point"}
}