{
  "type": "Feature",
  "properties": {
    "addr:full":"28 Blake St Nathalia VIC 3638",
    "addr:housenumber":"28",
    "addr:postcode":"3638",
    "addr:street":"Blake St",
    "iso:country":"AU",
    "sg:address":"28 Blake St",
    "sg:city":"Nathalia",
    "sg:classifiers":[
        {
            "category":"Banks & Credit Unions",
            "subcategory":"Bureau De Change",
            "type":"Services"
        }
    ],
    "sg:phone":"+61 3 5866 2490",
    "sg:postcode":"3638",
    "sg:province":"VIC",
    "sg:tags":[
        "repairs",
        "part",
        "appliance",
        "electrical"
    ],
    "wof:name":"Smith R G & A",
    "wof:placetype":"venue"
},
  "geometry": {"coordinates":[145.20355224599999,-36.058631897],"type":"Point"}
}