{
  "type": "Feature",
  "properties": {
    "addr:full":"Mirrabooka Eualdrie Rd Grenfell NSW 2810",
    "addr:postcode":"2810",
    "addr:street":"Eualdrie Rd",
    "iso:country":"AU",
    "sg:address":"Mirrabooka Eualdrie Rd",
    "sg:city":"Grenfell",
    "sg:classifiers":[
        {
            "category":"Farming",
            "subcategory":"Farm",
            "type":"Manufacturing & Wholesale Goods"
        }
    ],
    "sg:phone":"+61 2 6343 4142",
    "sg:postcode":"2810",
    "sg:province":"NSW",
    "sg:tags":[
        "farmer"
    ],
    "wof:name":"Smith J A & Co",
    "wof:placetype":"venue"
},
  "geometry": {"coordinates":[148.11544799800001,-33.9257202148],"type":"Point"}
}