{
  "type": "Feature",
  "properties": {
    "addr:full":"65 Pimpala Rd Reynella SA 5161",
    "addr:housenumber":"65",
    "addr:postcode":"5161",
    "addr:street":"Pimpala Rd",
    "iso:country":"AU",
    "sg:address":"65 Pimpala Rd",
    "sg:city":"Reynella",
    "sg:classifiers":[
        {
            "category":"Communications",
            "subcategory":"Film & Video Production",
            "type":"Services"
        }
    ],
    "sg:phone":"+61 8 8387 4110",
    "sg:postcode":"5161",
    "sg:province":"SA",
    "sg:tags":[
        "dvd",
        "library"
    ],
    "wof:name":"Civic Video Pty Ltd",
    "wof:placetype":"venue"
},
  "geometry": {"coordinates":[138.53424072300001,-35.1048431396],"type":"Point"}
}