{
  "type": "Feature",
  "properties": {
    "iso:country":"AU",
    "sg:address":"111 Blaxcell St",
    "sg:city":"Granville",
    "sg:classifiers":[
        {
            "category":"Retail",
            "subcategory":"Auto Repair",
            "type":"Services"
        }
    ],
    "sg:phone":"+61 2 9637 3587",
    "sg:postcode":"2142",
    "sg:province":"NSW",
    "sg:tags":[
        "electrical"
    ],
    "wof:name":"T & K Auto Electrical Repairs Pty Ltd",
    "wof:placetype":"venue"
},
  "geometry": {"coordinates":[151.01031494099999,-33.8432235718],"type":"Point"}
}