{
  "type": "Feature",
  "properties": {
    "addr:full":"27 Amberelle Pl Chapel Hill QLD 4069",
    "addr:housenumber":"27",
    "addr:postcode":"4069",
    "addr:street":"Amberelle Pl",
    "iso:country":"AU",
    "sg:address":"27 Amberelle Pl",
    "sg:city":"Chapel Hill",
    "sg:classifiers":[
        {
            "category":"Real Estate",
            "subcategory":"Architect",
            "type":"Services"
        }
    ],
    "sg:phone":"+61 7 3378 9173",
    "sg:postcode":"4069",
    "sg:province":"QLD",
    "wof:name":"Carl Brunskill Architects Pty Ltd",
    "wof:placetype":"venue"
},
  "geometry": {"coordinates":[152.95022582999999,-27.4939975739],"type":"Point"}
}