{
  "type": "Feature",
  "properties": {
    "iso:country":"AU",
    "sg:address":"140 Ashley St",
    "sg:city":"Underdale",
    "sg:classifiers":[
        {
            "category":"Professional",
            "subcategory":"Employment Agencies",
            "type":"Services"
        }
    ],
    "sg:phone":"+61 8 8352 1799",
    "sg:postcode":"5032",
    "sg:province":"SA",
    "sg:tags":[
        "broker",
        "custom"
    ],
    "wof:name":"Gibson Freight Aust Pty Ltd",
    "wof:placetype":"venue"
},
  "geometry": {"coordinates":[138.55065918,-34.9185447693],"type":"Point"}
}