{
  "type": "Feature",
  "properties": {
    "addr:full":"43 Carrington St Adelaide SA 5000",
    "addr:housenumber":"43",
    "addr:postcode":"5000",
    "addr:street":"Carrington St",
    "iso:country":"AU",
    "sg:address":"43 Carrington St",
    "sg:city":"Adelaide",
    "sg:classifiers":[
        {
            "category":"Insurance",
            "subcategory":"Insurance Agent",
            "type":"Services"
        }
    ],
    "sg:phone":"+61 8 8221 6690",
    "sg:postcode":"5000",
    "sg:province":"SA",
    "sg:tags":[
        "broker"
    ],
    "wof:name":"One To One Insurance Solutions Adelaide South",
    "wof:placetype":"venue"
},
  "geometry": {"coordinates":[138.60194397000001,-34.9315567017],"type":"Point"}
}