{
  "type": "Feature",
  "properties": {
    "addr:full":"Shop 10 Hapenny La Katoomba NSW 2780",
    "addr:housenumber":"shop 10",
    "addr:postcode":"2780",
    "addr:street":"Hapenny La",
    "iso:country":"AU",
    "sg:address":"Shop 10 Hapenny La",
    "sg:city":"Katoomba",
    "sg:classifiers":[
        {
            "category":"Shopping",
            "subcategory":"Bicycles & Sporting Goods",
            "type":"Retail Goods"
        }
    ],
    "sg:phone":"+61 2 4782 4159",
    "sg:postcode":"2780",
    "sg:province":"NSW",
    "sg:tags":[
        "dance",
        "accessory",
        "wear",
        "supply"
    ],
    "wof:name":"Kathleen Grace Dancewear",
    "wof:placetype":"venue"
},
  "geometry": {"coordinates":[150.31059265100001,-33.7173042297],"type":"Point"}
}