{
  "type": "Feature",
  "properties": {
    "iso:country":"AU",
    "sg:address":"Staricks Rd",
    "sg:city":"Springton",
    "sg:classifiers":[
        {
            "category":"Farming",
            "subcategory":"Livestock Farm",
            "type":"Manufacturing & Wholesale Goods"
        }
    ],
    "sg:phone":"+61 8 8568 2327",
    "sg:postcode":"5235",
    "sg:province":"SA",
    "sg:tags":[
        "breeder",
        "horse",
        "stud"
    ],
    "wof:name":"Nyongee Farm Warmbloods",
    "wof:placetype":"venue"
},
  "geometry": {"coordinates":[139.08897399899999,-34.705619812],"type":"Point"}
}