{
  "type": "Feature",
  "properties": {
    "addr:full":"38 King St Warwick QLD 4370",
    "addr:housenumber":"38",
    "addr:postcode":"4370",
    "addr:street":"King St",
    "iso:country":"AU",
    "sg:address":"38 King St",
    "sg:city":"Warwick",
    "sg:classifiers":[
        {
            "category":"Professional",
            "subcategory":"Accounting & Tax Preparation",
            "type":"Services"
        }
    ],
    "sg:phone":"+61 7 4661 9773",
    "sg:postcode":"4370",
    "sg:province":"QLD",
    "sg:tags":[
        "bookkeeping"
    ],
    "wof:name":"On Line Services Pty Ltd",
    "wof:placetype":"venue"
},
  "geometry": {"coordinates":[152.033370972,-28.2175636292],"type":"Point"}
}