{
  "type": "Feature",
  "properties": {
    "addr:full":"142 Austin Rd Seaford VIC 3198",
    "addr:housenumber":"142",
    "addr:postcode":"3198",
    "addr:street":"Austin Rd",
    "iso:country":"AU",
    "sg:address":"142 Austin Rd",
    "sg:city":"Seaford",
    "sg:classifiers":[
        {
            "category":"Retail",
            "subcategory":"Self-service Laundry",
            "type":"Services"
        }
    ],
    "sg:phone":"+61 425 769 525",
    "sg:postcode":"3198",
    "sg:province":"VIC",
    "wof:name":"Austin Road Laundrette",
    "wof:placetype":"venue"
},
  "geometry": {"coordinates":[145.14779663100001,-38.1070022583],"type":"Point"}
}