{
  "type": "Feature",
  "properties": {
    "addr:full":"71 Warren Rd Mordialloc VIC 3195",
    "addr:housenumber":"71",
    "addr:postcode":"3195",
    "addr:street":"Warren Rd",
    "iso:country":"AU",
    "sg:address":"71 Warren Rd",
    "sg:city":"Mordialloc",
    "sg:classifiers":[
        {
            "category":"Professional",
            "subcategory":"Computer Services",
            "type":"Services"
        }
    ],
    "sg:phone":"+61 3 9587 4577",
    "sg:postcode":"3195",
    "sg:province":"VIC",
    "sg:tags":[
        "repairs",
        "upgrade",
        "equipment"
    ],
    "sg:website":"http://www.computergiggtechnology.com",
    "wof:name":"Computer Gigg Technology",
    "wof:placetype":"venue"
},
  "geometry": {"coordinates":[145.09211730999999,-37.9951667786],"type":"Point"}
}