{
  "type": "Feature",
  "properties": {
    "iso:country":"AU",
    "sg:address":"2/ 36 Parramatta Rd",
    "sg:city":"Lidcombe",
    "sg:classifiers":[
        {
            "category":"Autos & Motor Vehicles",
            "subcategory":"Auto Supplies",
            "type":"Retail Goods"
        }
    ],
    "sg:phone":"+61 2 9748 7077",
    "sg:postcode":"2141",
    "sg:province":"NSW",
    "sg:tags":[
        "pipe",
        "bending",
        "tube",
        "machinery"
    ],
    "wof:name":"Headland Machinery Pty Ltd",
    "wof:placetype":"venue"
},
  "geometry": {"coordinates":[151.05705261200001,-33.8526802063],"type":"Point"}
}