{
  "type": "Feature",
  "properties": {
    "iso:country":"AU",
    "sg:address":"8 Hinley Ave",
    "sg:city":"Maroochydore",
    "sg:classifiers":[
        {
            "category":"Insurance",
            "subcategory":"Life Insurance",
            "type":"Services"
        }
    ],
    "sg:phone":"+61 7 5443 7433",
    "sg:postcode":"4558",
    "sg:province":"QLD",
    "wof:name":"Ashton Graham H & Associates",
    "wof:placetype":"venue"
},
  "geometry": {"coordinates":[153.084228516,-26.6473484039],"type":"Point"}
}