{
  "type": "Feature",
  "properties": {
    "iso:country":"AU",
    "sg:address":"44 Leatherwood Drv",
    "sg:city":"Arana Hills",
    "sg:classifiers":[
        {
            "category":"Building & Trades",
            "subcategory":"Construction",
            "type":"Services"
        }
    ],
    "sg:phone":"+61 7 3351 1191",
    "sg:postcode":"4054",
    "sg:province":"QLD",
    "sg:tags":[
        "contractor"
    ],
    "wof:name":"Latimer R J & R M",
    "wof:placetype":"venue"
},
  "geometry": {"coordinates":[152.95440673799999,-27.3893527985],"type":"Point"}
}