{
  "type": "Feature",
  "properties": {
    "addr:full":"85 Ridgeway Ave Southport QLD 4215",
    "addr:housenumber":"85",
    "addr:postcode":"4215",
    "addr:street":"Ridgeway Ave",
    "iso:country":"AU",
    "sg:address":"85 Ridgeway Ave",
    "sg:city":"Southport",
    "sg:classifiers":[
        {
            "category":"Professional",
            "subcategory":"Art Services",
            "type":"Services"
        }
    ],
    "sg:phone":"+61 7 5532 7996",
    "sg:postcode":"4215",
    "sg:province":"QLD",
    "sg:tags":[
        "artist"
    ],
    "wof:name":"Muhlberger M",
    "wof:placetype":"venue"
},
  "geometry": {"coordinates":[153.40176391599999,-27.9870071411],"type":"Point"}
}