{
  "type": "Feature",
  "properties": {
    "addr:full":"Level 1, 306 St Vincent St Port Adelaide SA 5015",
    "addr:housenumber":"306",
    "addr:postcode":"5015",
    "addr:street":"St Vincent St",
    "iso:country":"AU",
    "sg:address":"Level 1, 306 St Vincent St",
    "sg:city":"Port Adelaide",
    "sg:classifiers":[
        {
            "category":"Transit Center",
            "subcategory":"Freight",
            "type":"Transportation"
        }
    ],
    "sg:phone":"+61 8 8447 6711",
    "sg:postcode":"5015",
    "sg:province":"SA",
    "sg:tags":[
        "agent",
        "shipping"
    ],
    "wof:name":"McArthur Shipping & Agency Co Pty Ltd The",
    "wof:placetype":"venue"
},
  "geometry": {"coordinates":[138.509277344,-34.8437232971],"type":"Point"}
}