{
  "type": "Feature",
  "properties": {
    "iso:country":"AU",
    "sg:address":"372 Kensington Rd",
    "sg:city":"Erindale",
    "sg:classifiers":[
        {
            "category":"Retail",
            "subcategory":"Auto Repair",
            "type":"Services"
        }
    ],
    "sg:phone":"+61 8 8431 5438",
    "sg:postcode":"5066",
    "sg:province":"SA",
    "sg:tags":[
        "repairer",
        "motor",
        "engineer"
    ],
    "wof:name":"B.P. Erindale Automotive",
    "wof:placetype":"venue"
},
  "geometry": {"coordinates":[138.663604736,-34.9259376526],"type":"Point"}
}