{
  "type": "Feature",
  "properties": {
    "addr:full":"120 Church St Albion Park NSW 2527",
    "addr:housenumber":"120",
    "addr:postcode":"2527",
    "addr:street":"Church St",
    "iso:country":"AU",
    "sg:address":"120 Church St",
    "sg:city":"Albion Park",
    "sg:classifiers":[
        {
            "category":"Education",
            "subcategory":"School",
            "type":"Public Place"
        }
    ],
    "sg:phone":"+61 2 4257 1744",
    "sg:postcode":"2527",
    "sg:province":"NSW",
    "sg:tags":[
        "state",
        "-",
        "nsw"
    ],
    "wof:name":"Albion Park High School",
    "wof:placetype":"venue"
},
  "geometry": {"coordinates":[150.776153564,-34.5757331848],"type":"Point"}
}