{
  "type": "Feature",
  "properties": {
    "addr:full":"57 Clifton St North Rockhampton QLD 4701",
    "addr:housenumber":"57",
    "addr:postcode":"4701",
    "addr:street":"Clifton St North",
    "iso:country":"AU",
    "sg:address":"57 Clifton St",
    "sg:city":"North Rockhampton",
    "sg:classifiers":[
        {
            "category":"Utilities",
            "subcategory":"Fuel Oil & Lpg",
            "type":"Services"
        }
    ],
    "sg:phone":"+61 7 4928 1011",
    "sg:postcode":"4701",
    "sg:province":"QLD",
    "sg:tags":[
        "cooler"
    ],
    "wof:name":"Sheps",
    "wof:placetype":"venue"
},
  "geometry": {"coordinates":[150.52441406200001,-23.3566608429],"type":"Point"}
}