{
  "type": "Feature",
  "properties": {
    "addr:full":"26 Frederick St Ferntree Gully VIC 3156",
    "addr:housenumber":"26",
    "addr:postcode":"3156",
    "addr:street":"Frederick St",
    "iso:country":"AU",
    "sg:address":"26 Frederick St",
    "sg:city":"Ferntree Gully",
    "sg:classifiers":[
        {
            "category":"Retail",
            "subcategory":"Auto Repair",
            "type":"Services"
        }
    ],
    "sg:phone":"+61 3 9758 4042",
    "sg:postcode":"3156",
    "sg:province":"VIC",
    "sg:tags":[
        "repairer",
        "motor",
        "engineer"
    ],
    "wof:name":"Berwick Motor Works",
    "wof:placetype":"venue"
},
  "geometry": {"coordinates":[145.29971313499999,-37.8683509827],"type":"Point"}
}