{
  "type": "Feature",
  "properties": {
    "addr:full":"397 Whitehorse Rd Nunawading VIC 3131",
    "addr:housenumber":"397",
    "addr:postcode":"3131",
    "addr:street":"Whitehorse Rd",
    "iso:country":"AU",
    "sg:address":"397 Whitehorse Rd",
    "sg:city":"Nunawading",
    "sg:classifiers":[
        {
            "category":"Arts & Performance",
            "subcategory":"Theater",
            "type":"Entertainment"
        }
    ],
    "sg:phone":"+61 3 9262 6590",
    "sg:postcode":"3131",
    "sg:province":"VIC",
    "sg:tags":[
        "theatre"
    ],
    "wof:name":"Whitehorse Centre",
    "wof:placetype":"venue"
},
  "geometry": {"coordinates":[145.181442261,-37.8183937073],"type":"Point"}
}