{
  "type": "Feature",
  "properties": {
    "addr:full":"224B Bay St Port Melbourne VIC 3207",
    "addr:housenumber":"224b",
    "addr:postcode":"3207",
    "addr:street":"Bay St",
    "iso:country":"AU",
    "sg:address":"224B Bay St",
    "sg:city":"Port Melbourne",
    "sg:classifiers":[
        {
            "category":"Health Services",
            "subcategory":"Health Practitioner",
            "type":"Services"
        }
    ],
    "sg:phone":"+61 419 992 996",
    "sg:postcode":"3207",
    "sg:province":"VIC",
    "sg:tags":[
        "acupuncture"
    ],
    "wof:name":"Albert Park Traditional Chinese Medicine",
    "wof:placetype":"venue"
},
  "geometry": {"coordinates":[144.94238300000001,-37.838757],"type":"Point"}
}