{
  "type": "Feature",
  "properties": {
    "iso:country":"AU",
    "sg:address":"11 Main Arm Rd",
    "sg:city":"Mullumbimby",
    "sg:classifiers":[
        {
            "category":"Autos & Motor Vehicles",
            "subcategory":"Fuel & Gas Station",
            "type":"Retail Goods"
        }
    ],
    "sg:phone":"+61 2 6684 2394",
    "sg:postcode":"2482",
    "sg:province":"NSW",
    "wof:name":"Frazier P & E Pty Ltd",
    "wof:placetype":"venue"
},
  "geometry": {"coordinates":[153.49346923799999,-28.5468521118],"type":"Point"}
}