{
  "type": "Feature",
  "properties": {
    "iso:country":"AU",
    "sg:address":"Mansfield Shopng Cntr Aminya St",
    "sg:city":"Mansfield",
    "sg:classifiers":[
        {
            "category":"Health Services",
            "subcategory":"Dentist",
            "type":"Services"
        }
    ],
    "sg:phone":"+61 7 3349 7749",
    "sg:postcode":"4122",
    "sg:province":"QLD",
    "wof:name":"Schodel Denis",
    "wof:placetype":"venue"
},
  "geometry": {"coordinates":[153.097900391,-27.539182663],"type":"Point"}
}