{
  "type": "Feature",
  "properties": {
    "addr:full":"712 Burwood Rd Hawthorn East VIC 3123",
    "addr:housenumber":"712",
    "addr:postcode":"3123",
    "addr:street":"Burwood Rd",
    "iso:country":"AU",
    "sg:address":"712 Burwood Rd",
    "sg:city":"Hawthorn East",
    "sg:classifiers":[
        {
            "category":"Banks & Credit Unions",
            "subcategory":"Investment Brokerage",
            "type":"Services"
        }
    ],
    "sg:phone":"+61 411 954 546",
    "sg:postcode":"3123",
    "sg:province":"VIC",
    "sg:tags":[
        "finance",
        "broker"
    ],
    "wof:name":"Bliss Financial Services",
    "wof:placetype":"venue"
},
  "geometry": {"coordinates":[145.04980468799999,-37.8319816589],"type":"Point"}
}