{
  "type": "Feature",
  "properties": {
    "addr:full":"705 Young St Albury NSW 2640",
    "addr:housenumber":"705",
    "addr:postcode":"2640",
    "addr:street":"Young St",
    "iso:country":"AU",
    "sg:address":"705 Young St",
    "sg:city":"Albury",
    "sg:classifiers":[
        {
            "category":"Communications",
            "subcategory":"Film & Video Production",
            "type":"Services"
        }
    ],
    "sg:phone":"+61 2 6021 8736",
    "sg:postcode":"2640",
    "sg:province":"NSW",
    "sg:tags":[
        "cost",
        "estimator"
    ],
    "wof:name":"Padgham & Partners Pty Ltd",
    "wof:placetype":"venue"
},
  "geometry": {"coordinates":[146.925857544,-36.0714263916],"type":"Point"}
}