{
  "type": "Feature",
  "properties": {
    "addr:full":"57 Heatherton Rd Endeavour Hills VIC 3802",
    "addr:housenumber":"57",
    "addr:postcode":"3802",
    "addr:street":"Heatherton Rd",
    "iso:country":"AU",
    "sg:address":"57 Heatherton Rd",
    "sg:city":"Endeavour Hills",
    "sg:classifiers":[
        {
            "category":"Food & Beverages",
            "subcategory":"Bakery",
            "type":"Retail Goods"
        }
    ],
    "sg:phone":"+61 3 9700 4361",
    "sg:postcode":"3802",
    "sg:province":"VIC",
    "sg:tags":[
        "baker"
    ],
    "wof:name":"Lazios",
    "wof:placetype":"venue"
},
  "geometry": {"coordinates":[145.27630615199999,-37.976890564],"type":"Point"}
}