{
  "type": "Feature",
  "properties": {
    "addr:full":"Bay1/ 8 Milligan St Taree NSW 2430",
    "addr:housenumber":"8",
    "addr:postcode":"2430",
    "addr:street":"Milligan St",
    "iso:country":"AU",
    "sg:address":"Bay1/ 8 Milligan St",
    "sg:city":"Taree",
    "sg:classifiers":[
        {
            "category":"Retail",
            "subcategory":"Auto Repair",
            "type":"Services"
        }
    ],
    "sg:phone":"+61 2 6552 4526",
    "sg:postcode":"2430",
    "sg:province":"NSW",
    "sg:tags":[
        "testing",
        "inspection",
        "motor",
        "vehicle"
    ],
    "wof:name":"Taree Mechanical Services",
    "wof:placetype":"venue"
},
  "geometry": {"coordinates":[152.475494,-31.904411],"type":"Point"}
}