{
  "type": "Feature",
  "properties": {
    "addr:full":"12A Fry St Mt Barker SA 5251",
    "addr:housenumber":"12a",
    "addr:postcode":"5251",
    "addr:street":"Fry St Mt",
    "iso:country":"AU",
    "sg:address":"12A Fry St",
    "sg:city":"Mt Barker",
    "sg:classifiers":[
        {
            "category":"Transit Center",
            "subcategory":"Freight",
            "type":"Transportation"
        }
    ],
    "sg:phone":"+61 8 8398 2795",
    "sg:postcode":"5251",
    "sg:province":"SA",
    "sg:tags":[
        "curers",
        "damp",
        "salt",
        "sa"
    ],
    "wof:name":"AntiDamp (S.A.)",
    "wof:placetype":"venue"
},
  "geometry": {"coordinates":[138.84678649899999,-35.0722427368],"type":"Point"}
}