{
  "type": "Feature",
  "properties": {
    "addr:full":"25 Muntz St Wangaratta VIC 3677",
    "addr:housenumber":"25",
    "addr:postcode":"3677",
    "addr:street":"Muntz St",
    "iso:country":"AU",
    "sg:address":"25 Muntz St",
    "sg:city":"Wangaratta",
    "sg:classifiers":[
        {
            "category":"Building & Trades",
            "subcategory":"Equipment Rental",
            "type":"Services"
        }
    ],
    "sg:phone":"+61 3 5721 4519",
    "sg:postcode":"3677",
    "sg:province":"VIC",
    "sg:tags":[
        "fitness"
    ],
    "wof:name":"West End Cycles",
    "wof:placetype":"venue"
},
  "geometry": {"coordinates":[146.30546569800001,-36.3539085388],"type":"Point"}
}