{
  "type": "Feature",
  "properties": {
    "iso:country":"AU",
    "sg:address":"Level 2, 210",
    "sg:city":"Kings Wy South Melbourne",
    "sg:classifiers":[
        {
            "category":"Health Services",
            "subcategory":"Nursing And Care Facility",
            "type":"Services"
        }
    ],
    "sg:phone":"+61 3 8699 3300",
    "sg:postcode":"3205",
    "sg:province":"VIC",
    "sg:tags":[
        "home"
    ],
    "sg:website":"http://www.primelife.com.au",
    "wof:name":"Primelife Corporation",
    "wof:placetype":"venue"
},
  "geometry": {"coordinates":[144.964249,-37.830151],"type":"Point"}
}