{
  "type": "Feature",
  "properties": {
    "iso:country":"AU",
    "sg:address":"Suite 1/ 10 Parkyn Pde",
    "sg:city":"Mooloolaba",
    "sg:classifiers":[
        {
            "category":"Retail",
            "subcategory":"Storage",
            "type":"Services"
        }
    ],
    "sg:phone":"+61 7 5452 5406",
    "sg:postcode":"4557",
    "sg:province":"QLD",
    "sg:tags":[
        "removal",
        "furniture"
    ],
    "wof:name":"Hannan Containerised Furniture Removals",
    "wof:placetype":"venue"
},
  "geometry": {"coordinates":[153.131347656,-26.6841812134],"type":"Point"}
}