{
  "type": "Feature",
  "properties": {
    "addr:full":"Shp32a/ 181 Church St Parramatta NSW 2150",
    "addr:housenumber":"181",
    "addr:postcode":"2150",
    "addr:street":"Church St",
    "iso:country":"AU",
    "sg:address":"Shp32a/ 181 Church St",
    "sg:city":"Parramatta",
    "sg:classifiers":[
        {
            "category":"Professional",
            "subcategory":"Computer Services",
            "type":"Services"
        }
    ],
    "sg:phone":"+61 2 9689 2422",
    "sg:postcode":"2150",
    "sg:province":"NSW",
    "sg:tags":[
        "training"
    ],
    "wof:name":"Ceo Training Pty Ltd",
    "wof:placetype":"venue"
},
  "geometry": {"coordinates":[151.11892700199999,-33.8752441406],"type":"Point"}
}