{
  "type": "Feature",
  "properties": {
    "iso:country":"AU",
    "sg:address":"145 Tolley Rd St",
    "sg:city":"Agnes",
    "sg:classifiers":[
        {
            "category":"Building & Trades",
            "subcategory":"Cleaning & Sanitation",
            "type":"Services"
        }
    ],
    "sg:phone":"+61 8 8264 0404",
    "sg:postcode":"5097",
    "sg:province":"SA",
    "sg:tags":[
        "commercial",
        "maintenance"
    ],
    "wof:name":"Exclusive Property Maintenance & Development",
    "wof:placetype":"venue"
},
  "geometry": {"coordinates":[138.70680236800001,-34.8275413513],"type":"Point"}
}