{
  "type": "Feature",
  "properties": {
    "addr:full":"107 Graham St Wonthaggi VIC 3995",
    "addr:housenumber":"107",
    "addr:postcode":"3995",
    "addr:street":"Graham St",
    "iso:country":"AU",
    "sg:address":"107 Graham St",
    "sg:city":"Wonthaggi",
    "sg:classifiers":[
        {
            "category":"Casinos & Gambling",
            "type":"Entertainment"
        }
    ],
    "sg:phone":"+61 3 5672 4224",
    "sg:postcode":"3995",
    "sg:province":"VIC",
    "sg:tags":[
        "lottery",
        "agent"
    ],
    "wof:name":"Wonthaggi Tattslotto",
    "wof:placetype":"venue"
},
  "geometry": {"coordinates":[145.59446700000001,-38.605728],"type":"Point"}
}