{
  "type": "Feature",
  "properties": {
    "addr:full":"Cnr Limestone & Ainslie Ave Braddon ACT 2612",
    "addr:postcode":"2612",
    "addr:street":"Cnr;Ave",
    "iso:country":"AU",
    "sg:address":"Cnr Limestone & Ainslie Ave",
    "sg:city":"Braddon",
    "sg:classifiers":[
        {
            "category":"Travel",
            "subcategory":"Hotels & Motels",
            "type":"Entertainment"
        }
    ],
    "sg:phone":"+61 2 6248 5511",
    "sg:postcode":"2612",
    "sg:province":"ACT",
    "sg:tags":[
        "accommodation"
    ],
    "wof:name":"Olims Canberra Hotel.",
    "wof:placetype":"venue"
},
  "geometry": {"coordinates":[149.14195251500001,-35.2733726501],"type":"Point"}
}