{
  "type": "Feature",
  "properties": {
    "addr:full":"Ste306/ 77 Dunning Ave Rosebery NSW 2018",
    "addr:housenumber":"77",
    "addr:postcode":"2018",
    "addr:street":"Dunning Ave",
    "iso:country":"AU",
    "sg:address":"Ste306/ 77 Dunning Ave",
    "sg:city":"Rosebery",
    "sg:classifiers":[
        {
            "category":"Real Estate",
            "subcategory":"Architect",
            "type":"Services"
        }
    ],
    "sg:phone":"+61 419 487 283",
    "sg:postcode":"2018",
    "sg:province":"NSW",
    "sg:tags":[
        "building",
        "designer"
    ],
    "wof:name":"Smyth & Smyth Pty Ltd",
    "wof:placetype":"venue"
},
  "geometry": {"coordinates":[151.20278930699999,-33.9152755737],"type":"Point"}
}