{
  "type": "Feature",
  "properties": {
    "addr:full":"6 Vella Drv Sunshine West VIC 3020",
    "addr:housenumber":"6",
    "addr:postcode":"3020",
    "addr:street":"Vella Drv",
    "iso:country":"AU",
    "sg:address":"6 Vella Drv",
    "sg:city":"Sunshine West",
    "sg:classifiers":[
        {
            "category":"Manufacturing",
            "subcategory":"Metals",
            "type":"Manufacturing & Wholesale Goods"
        }
    ],
    "sg:phone":"+61 3 9311 8585",
    "sg:postcode":"3020",
    "sg:province":"VIC",
    "sg:tags":[
        "sheet",
        "worker"
    ],
    "wof:name":"AVS Sheetmetal Pty Ltd",
    "wof:placetype":"venue"
},
  "geometry": {"coordinates":[144.831726,-37.806896],"type":"Point"}
}