{
  "type": "Feature",
  "properties": {
    "iso:country":"AU",
    "sg:address":"8 Gael Crt",
    "sg:city":"Mernda",
    "sg:classifiers":[
        {
            "category":"Shopping",
            "subcategory":"Pets & Pet Supplies",
            "type":"Retail Goods"
        }
    ],
    "sg:phone":"+61 3 9717 3787",
    "sg:postcode":"3754",
    "sg:province":"VIC",
    "sg:tags":[
        "equipment",
        "ceramic"
    ],
    "wof:name":"Vivid Ceramics",
    "wof:placetype":"venue"
},
  "geometry": {"coordinates":[145.104355,-37.589687],"type":"Point"}
}