{
  "type": "Feature",
  "properties": {
    "addr:full":"Level 11/ 6 Oconnell St Sydney NSW 2000",
    "addr:housenumber":"/ 6",
    "addr:postcode":"2000",
    "addr:street":"Oconnell St",
    "iso:country":"AU",
    "sg:address":"Level 11/ 6 Oconnell St",
    "sg:city":"Sydney",
    "sg:classifiers":[
        {
            "category":"Professional",
            "subcategory":"Management & Consulting",
            "type":"Services"
        }
    ],
    "sg:phone":"+61 1300 360 983",
    "sg:postcode":"2000",
    "sg:province":"NSW",
    "sg:tags":[
        "consultant"
    ],
    "wof:name":"3 Finance Pty Ltd",
    "wof:placetype":"venue"
},
  "geometry": {"coordinates":[151.21034240700001,-33.8647460938],"type":"Point"}
}