{
  "type": "Feature",
  "properties": {
    "addr:full":"23 Templeman Pl Midland WA 6056",
    "addr:housenumber":"23",
    "addr:postcode":"6056",
    "addr:street":"Templeman Pl",
    "iso:country":"AU",
    "sg:address":"23 Templeman Pl",
    "sg:city":"Midland",
    "sg:classifiers":[
        {
            "category":"Building & Trades",
            "subcategory":"Construction",
            "type":"Services"
        }
    ],
    "sg:phone":"+61 8 9250 4141",
    "sg:postcode":"6056",
    "sg:province":"WA",
    "sg:tags":[
        "contractor"
    ],
    "wof:name":"Perum Building & Construction Pty Ltd",
    "wof:placetype":"venue"
},
  "geometry": {"coordinates":[116.013183594,-31.8868522644],"type":"Point"}
}