{
  "type": "Feature",
  "properties": {
    "addr:full":"64 Moran St Bendigo VIC 3550",
    "addr:housenumber":"64",
    "addr:postcode":"3550",
    "addr:street":"Moran St",
    "iso:country":"AU",
    "sg:address":"64 Moran St",
    "sg:city":"Bendigo",
    "sg:classifiers":[
        {
            "category":"Home & Garden",
            "subcategory":"Building Materials",
            "type":"Retail Goods"
        }
    ],
    "sg:phone":"+61 3 5443 7612",
    "sg:postcode":"3550",
    "sg:province":"VIC",
    "sg:tags":[
        "merchant",
        "glass",
        "glazier"
    ],
    "wof:name":"Pemro Leadlighting",
    "wof:placetype":"venue"
},
  "geometry": {"coordinates":[144.268234253,-36.7418289185],"type":"Point"}
}