{
  "type": "Feature",
  "properties": {
    "addr:full":"128 Musgrave St North Rockhampton QLD 4701",
    "addr:housenumber":"128",
    "addr:postcode":"4701",
    "addr:street":"Musgrave St North",
    "iso:country":"AU",
    "sg:address":"128 Musgrave St",
    "sg:city":"North Rockhampton",
    "sg:classifiers":[
        {
            "category":"Professional",
            "subcategory":"Computer Services",
            "type":"Services"
        }
    ],
    "sg:phone":"+61 7 4922 2400",
    "sg:postcode":"4701",
    "sg:province":"QLD",
    "sg:tags":[
        "package",
        "software"
    ],
    "wof:name":"Kerr Solutions",
    "wof:placetype":"venue"
},
  "geometry": {"coordinates":[150.522415161,-23.3664264679],"type":"Point"}
}