{
  "type": "Feature",
  "properties": {
    "iso:country":"AU",
    "sg:address":"29 Queen St",
    "sg:city":"Harrisville",
    "sg:classifiers":[
        {
            "category":"Retail",
            "subcategory":"Auto Repair",
            "type":"Services"
        }
    ],
    "sg:phone":"+61 7 5467 1244",
    "sg:postcode":"4307",
    "sg:province":"QLD",
    "sg:tags":[
        "repairer",
        "motor",
        "engineer"
    ],
    "wof:name":"Harrisville Mechanical",
    "wof:placetype":"venue"
},
  "geometry": {"coordinates":[152.66812133799999,-27.8112926483],"type":"Point"}
}