{
  "type": "Feature",
  "properties": {
    "addr:full":"Level 5/ 125 York St Sydney NSW 2000",
    "addr:housenumber":"/ 125",
    "addr:postcode":"2000",
    "addr:street":"York St",
    "iso:country":"AU",
    "sg:address":"Level 5/ 125 York St",
    "sg:city":"Sydney",
    "sg:classifiers":[
        {
            "category":"Manufacturing",
            "subcategory":"Jewelry",
            "type":"Manufacturing & Wholesale Goods"
        }
    ],
    "sg:phone":"+61 2 9283 3998",
    "sg:postcode":"2000",
    "sg:province":"NSW",
    "sg:tags":[
        "mfrg",
        "jeweller"
    ],
    "sg:website":"http://www.pearlautore.com.au",
    "wof:name":"Autore South Sea Pearls",
    "wof:placetype":"venue"
},
  "geometry": {"coordinates":[151.20622253400001,-33.8716278076],"type":"Point"}
}