{
  "type": "Feature",
  "properties": {
    "addr:full":"34 Hicks Rd Kelmscott WA 6111",
    "addr:housenumber":"34",
    "addr:postcode":"6111",
    "addr:street":"Hicks Rd",
    "iso:country":"AU",
    "sg:address":"34 Hicks Rd",
    "sg:city":"Kelmscott",
    "sg:classifiers":[
        {
            "category":"Wholesale",
            "subcategory":"Non-durable Goods",
            "type":"Manufacturing & Wholesale Goods"
        }
    ],
    "sg:phone":"+61 8 9495 1424",
    "sg:postcode":"6111",
    "sg:province":"WA",
    "sg:tags":[
        "wholesaler",
        "craft",
        "mfrs"
    ],
    "wof:name":"Eggshell Artistry Supplies",
    "wof:placetype":"venue"
},
  "geometry": {"coordinates":[116.03417968799999,-32.1267700195],"type":"Point"}
}