{
  "type": "Feature",
  "properties": {
    "addr:full":"447 Mountain Hwy Bayswater VIC 3153",
    "addr:housenumber":"447",
    "addr:postcode":"3153",
    "addr:street":"Mountain Hwy",
    "iso:country":"AU",
    "sg:address":"447 Mountain Hwy",
    "sg:city":"Bayswater",
    "sg:classifiers":[
        {
            "category":"Wholesale",
            "subcategory":"Electrical",
            "type":"Manufacturing & Wholesale Goods"
        }
    ],
    "sg:phone":"+61 3 9729 5511",
    "sg:postcode":"3153",
    "sg:province":"VIC",
    "sg:tags":[
        "wholesaler",
        "mfrs",
        "accessory"
    ],
    "wof:name":"J.S.T Australia Pty Ltd",
    "wof:placetype":"venue"
},
  "geometry": {"coordinates":[145.241989136,-37.8444519043],"type":"Point"}
}