{
  "type": "Feature",
  "properties": {
    "addr:full":"75 Pioneer St Foster VIC 3960",
    "addr:housenumber":"75",
    "addr:postcode":"3960",
    "addr:street":"Pioneer St",
    "iso:country":"AU",
    "sg:address":"75 Pioneer St",
    "sg:city":"Foster",
    "sg:classifiers":[
        {
            "category":"Education",
            "subcategory":"School",
            "type":"Public Place"
        }
    ],
    "sg:phone":"+61 3 5682 2370",
    "sg:postcode":"3960",
    "sg:province":"VIC",
    "sg:tags":[
        "state",
        "except",
        "nsw"
    ],
    "wof:name":"Foster Primary School",
    "wof:placetype":"venue"
},
  "geometry": {"coordinates":[146.202224731,-38.6576347351],"type":"Point"}
}