{
  "type": "Feature",
  "properties": {
    "iso:country":"AU",
    "sg:address":"15 Nicholson St",
    "sg:city":"Bentleigh",
    "sg:classifiers":[
        {
            "category":"Personal",
            "subcategory":"Massage",
            "type":"Services"
        }
    ],
    "sg:phone":"+61 3 9557 7783",
    "sg:postcode":"3204",
    "sg:province":"VIC",
    "sg:tags":[
        "therapy"
    ],
    "wof:name":"Monuina Polynesian Massage",
    "wof:placetype":"venue"
},
  "geometry": {"coordinates":[145.036346,-37.917423],"type":"Point"}
}