{
  "type": "Feature",
  "properties": {
    "iso:country":"AU",
    "sg:address":"1/ 36 Old Cleveland Rd",
    "sg:city":"Capalaba",
    "sg:classifiers":[
        {
            "category":"Real Estate",
            "subcategory":"Real Estate Agent",
            "type":"Services"
        }
    ],
    "sg:phone":"+61 7 3823 5855",
    "sg:postcode":"4157",
    "sg:province":"QLD",
    "wof:name":"HarcourtsRedland/Capalaba",
    "wof:placetype":"venue"
},
  "geometry": {"coordinates":[153.197555542,-27.5210933685],"type":"Point"}
}