{
  "type": "Feature",
  "properties": {
    "iso:country":"AU",
    "sg:address":"69 Petronella Ave",
    "sg:city":"Wheelers Hill",
    "sg:classifiers":[
        {
            "category":"Professional",
            "subcategory":"Engineering",
            "type":"Services"
        }
    ],
    "sg:phone":"+61 412 525 264",
    "sg:postcode":"3150",
    "sg:province":"VIC",
    "sg:tags":[
        "consulting",
        "engineer"
    ],
    "wof:name":"Keller R J & Associates",
    "wof:placetype":"venue"
},
  "geometry": {"coordinates":[145.196212769,-37.9051170349],"type":"Point"}
}