{
  "type": "Feature",
  "properties": {
    "addr:full":"Stockland Townsville, 310-330 Ross Rivers Rd Aitkenvale QLD 4814",
    "addr:housenumber":"310-330",
    "addr:postcode":"4814",
    "addr:street":"Ross Rivers Rd",
    "iso:country":"AU",
    "sg:address":"Stockland Townsville, 310-330 Ross Rivers Rd",
    "sg:city":"Aitkenvale",
    "sg:classifiers":[
        {
            "category":"Shopping",
            "subcategory":"Mobile Phones",
            "type":"Retail Goods"
        }
    ],
    "sg:phone":"+61 7 4725 5488",
    "sg:postcode":"4814",
    "sg:province":"QLD",
    "sg:tags":[
        "telephone",
        "accessory"
    ],
    "wof:name":"Fone Zone.",
    "wof:placetype":"venue"
},
  "geometry": {"coordinates":[146.76196300000001,-19.298431],"type":"Point"}
}