{
  "type": "Feature",
  "properties": {
    "addr:full":"215 Invermay Rd Invermay TAS 7248",
    "addr:housenumber":"215",
    "addr:postcode":"7248",
    "addr:street":"Invermay Rd",
    "iso:country":"AU",
    "sg:address":"215 Invermay Rd",
    "sg:city":"Invermay",
    "sg:classifiers":[
        {
            "category":"Fast Food",
            "type":"Food & Drink"
        }
    ],
    "sg:phone":"+61 3 6326 3777",
    "sg:postcode":"7248",
    "sg:province":"TAS",
    "sg:tags":[
        "away",
        "take"
    ],
    "wof:name":"Bread Bin The",
    "wof:placetype":"venue"
},
  "geometry": {"coordinates":[147.132156372,-41.4095230103],"type":"Point"}
}