{
  "type": "Feature",
  "properties": {
    "iso:country":"AU",
    "sg:address":"PO Box 1692",
    "sg:city":"Werribee",
    "sg:classifiers":[
        {
            "category":"Sports & Exercise",
            "subcategory":"Gym",
            "type":"Entertainment"
        }
    ],
    "sg:phone":"+61 401 906 327",
    "sg:postcode":"3030",
    "sg:province":"VIC",
    "sg:tags":[
        "personal",
        "trainer",
        "fitness"
    ],
    "wof:name":"Physically Fresh",
    "wof:placetype":"venue"
},
  "geometry": {"coordinates":[144.67593400000001,-37.937119],"type":"Point"}
}