{
  "type": "Feature",
  "properties": {
    "addr:full":"35 Maitland Rd Springfield NSW 2250",
    "addr:housenumber":"35",
    "addr:postcode":"2250",
    "addr:street":"Maitland Rd",
    "iso:country":"AU",
    "sg:address":"35 Maitland Rd",
    "sg:city":"Springfield",
    "sg:classifiers":[
        {
            "category":"Autos & Motor Vehicles",
            "subcategory":"Boat Sales",
            "type":"Retail Goods"
        }
    ],
    "sg:phone":"+61 417 427 124",
    "sg:postcode":"2250",
    "sg:province":"NSW",
    "sg:tags":[
        "builder",
        "yacht",
        "repairer"
    ],
    "wof:name":"B.Sett Aluminium",
    "wof:placetype":"venue"
},
  "geometry": {"coordinates":[151.36343383799999,-33.4328842163],"type":"Point"}
}