{
  "type": "Feature",
  "properties": {
    "addr:full":"90 Bayswater Rd Rushcutters Bay NSW 2011",
    "addr:housenumber":"90",
    "addr:postcode":"2011",
    "addr:street":"Bayswater Rd",
    "iso:country":"AU",
    "sg:address":"90 Bayswater Rd",
    "sg:city":"Rushcutters Bay",
    "sg:classifiers":[
        {
            "category":"Fast Food",
            "type":"Food & Drink"
        }
    ],
    "sg:phone":"+61 2 9360 4300",
    "sg:postcode":"2011",
    "sg:province":"NSW",
    "sg:tags":[
        "away",
        "take"
    ],
    "wof:name":"Two Fat Chefs",
    "wof:placetype":"venue"
},
  "geometry": {"coordinates":[151.22825622600001,-33.8761444092],"type":"Point"}
}