{
  "type": "Feature",
  "properties": {
    "iso:country":"AU",
    "sg:address":"PO Box 408",
    "sg:city":"Drysdale",
    "sg:classifiers":[
        {
            "category":"Social Services",
            "subcategory":"Retirement Home",
            "type":"Services"
        }
    ],
    "sg:phone":"+61 3 5251 5412",
    "sg:postcode":"3222",
    "sg:province":"VIC",
    "sg:tags":[
        "life",
        "coaching"
    ],
    "wof:name":"Recipe For Happiness",
    "wof:placetype":"venue"
},
  "geometry": {"coordinates":[144.590103,-38.153461],"type":"Point"}
}