{
  "type": "Feature",
  "properties": {
    "addr:full":"399 Crystal St Broken Hill NSW 2880",
    "addr:housenumber":"399",
    "addr:postcode":"2880",
    "addr:street":"Crystal St",
    "iso:country":"AU",
    "sg:address":"399 Crystal St",
    "sg:city":"Broken Hill",
    "sg:classifiers":[
        {
            "category":"Arena",
            "subcategory":"Sports Club",
            "type":"Entertainment"
        }
    ],
    "sg:phone":"+61 8 8087 7550",
    "sg:postcode":"2880",
    "sg:province":"NSW",
    "sg:tags":[
        "hunt",
        "racing"
    ],
    "wof:name":"St Patrick's Race Club",
    "wof:placetype":"venue"
},
  "geometry": {"coordinates":[141.46856689399999,-31.9581508636],"type":"Point"}
}