{
  "type": "Feature",
  "properties": {
    "addr:full":"56 Strathmore St Kedron QLD 4031",
    "addr:housenumber":"56",
    "addr:postcode":"4031",
    "addr:street":"Strathmore St",
    "iso:country":"AU",
    "sg:address":"56 Strathmore St",
    "sg:city":"Kedron",
    "sg:classifiers":[
        {
            "category":"Education",
            "subcategory":"Music School",
            "type":"Public Place"
        }
    ],
    "sg:phone":"+61 7 3359 3997",
    "sg:postcode":"4031",
    "sg:province":"QLD",
    "sg:tags":[
        "teacher"
    ],
    "wof:name":"Christine Masters",
    "wof:placetype":"venue"
},
  "geometry": {"coordinates":[153.02835099999999,-27.403629],"type":"Point"}
}