{
  "type": "Feature",
  "properties": {
    "iso:country":"AU",
    "sg:address":"456 Swift St",
    "sg:city":"Albury",
    "sg:classifiers":[
        {
            "category":"Health Services",
            "subcategory":"Doctor",
            "type":"Services"
        }
    ],
    "sg:phone":"+61 2 6023 6660",
    "sg:postcode":"2640",
    "sg:province":"NSW",
    "sg:tags":[
        "medical",
        "practitioner"
    ],
    "wof:name":"Merriman Tracey",
    "wof:placetype":"venue"
},
  "geometry": {"coordinates":[146.91633605999999,-36.0787887573],"type":"Point"}
}