{
  "type": "Feature",
  "properties": {
    "iso:country":"AU",
    "sg:address":"67 Leyland St",
    "sg:city":"Garbutt",
    "sg:classifiers":[
        {
            "category":"Utilities",
            "subcategory":"Telephone",
            "type":"Services"
        }
    ],
    "sg:phone":"+61 7 4775 2255",
    "sg:postcode":"4814",
    "sg:province":"QLD",
    "sg:tags":[
        "installation",
        "system",
        "maintenance"
    ],
    "wof:name":"RAM Information Technologies",
    "wof:placetype":"venue"
},
  "geometry": {"coordinates":[146.761047,-19.271269],"type":"Point"}
}