{
  "type": "Feature",
  "properties": {
    "addr:full":"269 Pearcedale Rd Cranbourne South VIC 3977",
    "addr:housenumber":"269",
    "addr:postcode":"3977",
    "addr:street":"Pearcedale Rd",
    "iso:country":"AU",
    "sg:address":"269 Pearcedale Rd",
    "sg:city":"Cranbourne South",
    "sg:classifiers":[
        {
            "category":"Building & Trades",
            "subcategory":"Construction",
            "type":"Services"
        }
    ],
    "sg:phone":"+61 3 9775 7067",
    "sg:postcode":"3977",
    "sg:province":"VIC",
    "sg:tags":[
        "home",
        "air conditioning"
    ],
    "wof:name":"Frankston Plumbing Services",
    "wof:placetype":"venue"
},
  "geometry": {"coordinates":[145.24882507300001,-38.1293144226],"type":"Point"}
}