{
  "type": "Feature",
  "properties": {
    "iso:country":"AU",
    "sg:address":"9 Egmont Rd",
    "sg:city":"Henderson",
    "sg:classifiers":[
        {
            "category":"Communications",
            "subcategory":"Television Station",
            "type":"Services"
        }
    ],
    "sg:phone":"+61 8 9437 3533",
    "sg:postcode":"6166",
    "sg:province":"WA",
    "sg:tags":[
        "screening",
        "machinery",
        "grading"
    ],
    "wof:name":"QMS Engineering Pty Ltd",
    "wof:placetype":"venue"
},
  "geometry": {"coordinates":[115.773819,-32.150673],"type":"Point"}
}