{
  "type": "Feature",
  "properties": {
    "iso:country":"AU",
    "sg:address":"305 Comur St",
    "sg:city":"Yass",
    "sg:classifiers":[
        {
            "category":"Travel",
            "subcategory":"Hotels & Motels",
            "type":"Entertainment"
        }
    ],
    "sg:phone":"+61 2 6226 1300",
    "sg:postcode":"2582",
    "sg:province":"NSW",
    "wof:name":"Hi Way Motor Inn",
    "wof:placetype":"venue"
},
  "geometry": {"coordinates":[148.89584350600001,-34.8095550537],"type":"Point"}
}