{
  "type": "Feature",
  "properties": {
    "iso:country":"AU",
    "sg:address":"205 Main South Rd",
    "sg:city":"Morphett Vale",
    "sg:classifiers":[
        {
            "category":"Sports & Exercise",
            "subcategory":"Sports Center",
            "type":"Entertainment"
        }
    ],
    "sg:phone":"+61 8 8384 1244",
    "sg:postcode":"5162",
    "sg:province":"SA",
    "sg:tags":[
        "ground"
    ],
    "wof:name":"ICA Sportzworx",
    "wof:placetype":"venue"
},
  "geometry": {"coordinates":[138.52331543,-35.1192932129],"type":"Point"}
}