{
  "type": "Feature",
  "properties": {
    "iso:country":"AU",
    "sg:address":"41 Hollingsworth St",
    "sg:city":"North Rockhampton",
    "sg:classifiers":[
        {
            "category":"Home & Garden",
            "subcategory":"Building Materials",
            "type":"Retail Goods"
        }
    ],
    "sg:phone":"+61 7 4922 5599",
    "sg:postcode":"4701",
    "sg:province":"QLD",
    "sg:tags":[
        "tile",
        "roofing"
    ],
    "wof:name":"Alline Roofing Systems",
    "wof:placetype":"venue"
},
  "geometry": {"coordinates":[150.50453185999999,-23.3482112885],"type":"Point"}
}