{
  "type": "Feature",
  "properties": {
    "addr:full":"6 Casuarina St Oak Flats NSW 2529",
    "addr:housenumber":"6",
    "addr:postcode":"2529",
    "addr:street":"Casuarina St Oak Flats",
    "iso:country":"AU",
    "sg:address":"6 Casuarina St",
    "sg:city":"Oak Flats",
    "sg:classifiers":[
        {
            "category":"Commercial Area",
            "type":"Public Place"
        }
    ],
    "sg:phone":"+61 409 562 931",
    "sg:postcode":"2529",
    "sg:province":"NSW",
    "sg:tags":[
        "heavy",
        "carrier"
    ],
    "wof:name":"N & T Johnston Float Hire",
    "wof:placetype":"venue"
},
  "geometry": {"coordinates":[150.80744934099999,-34.5655288696],"type":"Point"}
}