{
  "type": "Feature",
  "properties": {
    "addr:full":"62 Churchhill Ave Subiaco WA 6008",
    "addr:housenumber":"62",
    "addr:postcode":"6008",
    "addr:street":"Churchhill Ave",
    "iso:country":"AU",
    "sg:address":"62 Churchhill Ave",
    "sg:city":"Subiaco",
    "sg:classifiers":[
        {
            "category":"Health Services",
            "subcategory":"Health Practitioner",
            "type":"Services"
        }
    ],
    "sg:phone":"+61 8 9388 2733",
    "sg:postcode":"6008",
    "sg:province":"WA",
    "sg:tags":[
        "psychologist"
    ],
    "wof:name":"Bennett Stephanie",
    "wof:placetype":"venue"
},
  "geometry": {"coordinates":[115.83416748,-31.9478359222],"type":"Point"}
}