{
  "type": "Feature",
  "properties": {
    "addr:full":"140 Blues Point Rd McMahons Point NSW 2060",
    "addr:housenumber":"140",
    "addr:postcode":"2060",
    "addr:street":"Blues Point Rd",
    "iso:country":"AU",
    "sg:address":"140 Blues Point Rd",
    "sg:city":"McMahons Point",
    "sg:classifiers":[
        {
            "category":"Health Services",
            "subcategory":"Doctor",
            "type":"Services"
        }
    ],
    "sg:phone":"+61 2 9929 0458",
    "sg:postcode":"2060",
    "sg:province":"NSW",
    "sg:tags":[
        "medical",
        "practitioner"
    ],
    "wof:name":"Goh C M",
    "wof:placetype":"venue"
},
  "geometry": {"coordinates":[151.204177856,-33.8443832397],"type":"Point"}
}