{
  "type": "Feature",
  "properties": {
    "addr:full":"Unit 7/ 95 Learjet Drv Caboolture QLD 4510",
    "addr:postcode":"4510",
    "addr:street":"95 Learjet Drv",
    "iso:country":"AU",
    "sg:address":"Unit 7/ 95 Learjet Drv",
    "sg:city":"Caboolture",
    "sg:classifiers":[
        {
            "category":"Wholesale",
            "subcategory":"Medical Equipment & Supplies",
            "type":"Manufacturing & Wholesale Goods"
        }
    ],
    "sg:phone":"+61 7 5495 8663",
    "sg:postcode":"4510",
    "sg:province":"QLD",
    "sg:tags":[
        "aid",
        "care",
        "health",
        "home"
    ],
    "wof:name":"Caboolture Wheelchairs",
    "wof:placetype":"venue"
},
  "geometry": {"coordinates":[152.979477,-27.079996],"type":"Point"}
}