{
  "type": "Feature",
  "properties": {
    "iso:country":"AU",
    "sg:address":"26 Mippi Rd",
    "sg:city":"Halls Head",
    "sg:classifiers":[
        {
            "category":"Building & Trades",
            "subcategory":"Construction",
            "type":"Services"
        }
    ],
    "sg:phone":"+61 407 991 979",
    "sg:postcode":"6210",
    "sg:province":"WA",
    "sg:tags":[
        "joiner",
        "carpenter"
    ],
    "wof:name":"Jytah Contracting",
    "wof:placetype":"venue"
},
  "geometry": {"coordinates":[115.696449,-32.528336],"type":"Point"}
}