{
  "type": "Feature",
  "properties": {
    "addr:full":"34/ 7-9 Percy St Auburn NSW 2144",
    "addr:housenumber":"34 / 7-9",
    "addr:postcode":"2144",
    "addr:street":"Percy St",
    "iso:country":"AU",
    "sg:address":"34/ 7-9 Percy St",
    "sg:city":"Auburn",
    "sg:classifiers":[
        {
            "category":"Home & Garden",
            "subcategory":"Furniture",
            "type":"Retail Goods"
        }
    ],
    "sg:phone":"+61 2 9646 1639",
    "sg:postcode":"2144",
    "sg:province":"NSW",
    "sg:tags":[
        "business"
    ],
    "wof:name":"Century Green",
    "wof:placetype":"venue"
},
  "geometry": {"coordinates":[151.03919982900001,-33.850982666],"type":"Point"}
}