{
  "type": "Feature",
  "properties": {
    "addr:full":"2 Stubbin St Belivah QLD 4207",
    "addr:housenumber":"2",
    "addr:postcode":"4207",
    "addr:street":"Stubbin St",
    "iso:country":"AU",
    "sg:address":"2 Stubbin St",
    "sg:city":"Belivah",
    "sg:classifiers":[
        {
            "category":"Social Services",
            "subcategory":"Child Care",
            "type":"Services"
        }
    ],
    "sg:phone":"+61 7 3807 8177",
    "sg:postcode":"4207",
    "sg:province":"QLD",
    "wof:name":"Rosemount Farm Childrens Centre",
    "wof:placetype":"venue"
},
  "geometry": {"coordinates":[153.18569946299999,-27.7572803497],"type":"Point"}
}