{
  "type": "Feature",
  "properties": {
    "addr:full":"421a Church St Richmond VIC 3121",
    "addr:housenumber":"421a",
    "addr:postcode":"3121",
    "addr:street":"Church St",
    "iso:country":"AU",
    "sg:address":"421a Church St",
    "sg:city":"Richmond",
    "sg:classifiers":[
        {
            "category":"Manufacturing",
            "subcategory":"Apparel",
            "type":"Manufacturing & Wholesale Goods"
        }
    ],
    "sg:phone":"+61 3 9429 3433",
    "sg:postcode":"3121",
    "sg:province":"VIC",
    "sg:tags":[
        "makers-up",
        "clothing"
    ],
    "wof:name":"Computer Marker Services",
    "wof:placetype":"venue"
},
  "geometry": {"coordinates":[144.998138428,-37.8254623413],"type":"Point"}
}