{
  "type": "Feature",
  "properties": {
    "iso:country":"AU",
    "sg:address":"226 Mill Rd",
    "sg:city":"Wesley Vale",
    "sg:classifiers":[
        {
            "category":"Professional",
            "subcategory":"Engineering",
            "type":"Services"
        }
    ],
    "sg:phone":"+61 3 6423 7131",
    "sg:postcode":"7307",
    "sg:province":"TAS",
    "sg:tags":[
        "installation",
        "maintenance",
        "engineer"
    ],
    "wof:name":"Silcar Pty Ltd",
    "wof:placetype":"venue"
},
  "geometry": {"coordinates":[146.45001199999999,-41.175884],"type":"Point"}
}