{
  "type": "Feature",
  "properties": {
    "iso:country":"AU",
    "sg:address":"39 Bryants Rd",
    "sg:city":"Loganholme",
    "sg:classifiers":[
        {
            "category":"Food & Beverages",
            "subcategory":"Supermarket",
            "type":"Retail Goods"
        }
    ],
    "sg:phone":"+61 7 3801 5511",
    "sg:postcode":"4129",
    "sg:province":"QLD",
    "sg:tags":[
        "grocery",
        "store"
    ],
    "wof:name":"Foodworks Loganholme",
    "wof:placetype":"venue"
},
  "geometry": {"coordinates":[153.175857544,-27.6629142761],"type":"Point"}
}