{
  "type": "Feature",
  "properties": {
    "iso:country":"AU",
    "sg:address":"21 Governor Phillip Pl",
    "sg:city":"West Pennant Hills",
    "sg:classifiers":[
        {
            "category":"Building & Trades",
            "subcategory":"Construction",
            "type":"Services"
        }
    ],
    "sg:phone":"+61 2 9894 0342",
    "sg:postcode":"2125",
    "sg:province":"NSW",
    "sg:tags":[
        "contractor"
    ],
    "wof:name":"Kemite Pty Ltd",
    "wof:placetype":"venue"
},
  "geometry": {"coordinates":[151.01719665499999,-33.7550621033],"type":"Point"}
}