{
  "type": "Feature",
  "properties": {
    "addr:full":"29 George St The Rocks NSW 2000",
    "addr:housenumber":"29",
    "addr:postcode":"2000",
    "addr:street":"George St",
    "iso:country":"AU",
    "sg:address":"29 George St",
    "sg:city":"The Rocks",
    "sg:classifiers":[
        {
            "category":"Retail",
            "subcategory":"Event Space",
            "type":"Services"
        }
    ],
    "sg:phone":"+61 2 9247 1789",
    "sg:postcode":"2000",
    "sg:province":"NSW",
    "sg:tags":[
        "venue",
        "reception",
        "wedding"
    ],
    "wof:name":"Bounty Wedding Charters",
    "wof:placetype":"venue"
},
  "geometry": {"coordinates":[151.20854187,-33.857421875],"type":"Point"}
}