{
  "type": "Feature",
  "properties": {
    "iso:country":"AU",
    "sg:address":"South Western Hwy",
    "sg:city":"Yornup",
    "sg:classifiers":[
        {
            "category":"Farming",
            "subcategory":"Farm",
            "type":"Manufacturing & Wholesale Goods"
        }
    ],
    "sg:phone":"+61 8 9761 9036",
    "sg:postcode":"6256",
    "sg:province":"WA",
    "sg:tags":[
        "farmer"
    ],
    "wof:name":"Farquhar R & F",
    "wof:placetype":"venue"
},
  "geometry": {"coordinates":[116.16957092299999,-34.0550498962],"type":"Point"}
}