{
  "type": "Feature",
  "properties": {
    "addr:full":"29 Rob Roy St Glen Waverley VIC 3150",
    "addr:housenumber":"29",
    "addr:postcode":"3150",
    "addr:street":"Rob Roy St",
    "iso:country":"AU",
    "sg:address":"29 Rob Roy St",
    "sg:city":"Glen Waverley",
    "sg:classifiers":[
        {
            "category":"Professional",
            "subcategory":"Engineering",
            "type":"Services"
        }
    ],
    "sg:phone":"+61 3 9802 5486",
    "sg:postcode":"3150",
    "sg:province":"VIC",
    "sg:tags":[
        "consulting",
        "engineer"
    ],
    "wof:name":"IH & BE Mudge",
    "wof:placetype":"venue"
},
  "geometry": {"coordinates":[145.15034484899999,-37.88904953],"type":"Point"}
}