{
  "type": "Feature",
  "properties": {
    "addr:full":"L2 541 Blackburn Rd Blackburn VIC 3130",
    "addr:housenumber":"541",
    "addr:postcode":"3130",
    "addr:street":"Blackburn Rd",
    "iso:country":"AU",
    "sg:address":"L2 541 Blackburn Rd",
    "sg:city":"Blackburn",
    "sg:classifiers":[
        {
            "category":"Professional",
            "subcategory":"Employment Agencies",
            "type":"Services"
        }
    ],
    "sg:phone":"+61 3 9550 0851",
    "sg:postcode":"3130",
    "sg:province":"VIC",
    "wof:name":"Dunhill Recruitment",
    "wof:placetype":"venue"
},
  "geometry": {"coordinates":[145.152954102,-37.8202972412],"type":"Point"}
}