{
  "type": "Feature",
  "properties": {
    "addr:full":"226 Malop St Geelong VIC 3220",
    "addr:housenumber":"226",
    "addr:postcode":"3220",
    "addr:street":"Malop St",
    "iso:country":"AU",
    "sg:address":"226 Malop St",
    "sg:city":"Geelong",
    "sg:classifiers":[
        {
            "category":"Banks & Credit Unions",
            "subcategory":"Financial Services",
            "type":"Services"
        }
    ],
    "sg:phone":"+61 3 5222 6755",
    "sg:postcode":"3220",
    "sg:province":"VIC",
    "sg:tags":[
        "planning"
    ],
    "wof:name":"Armour David & Assoc P/L",
    "wof:placetype":"venue"
},
  "geometry": {"coordinates":[144.367142,-38.149117],"type":"Point"}
}