{
  "type": "Feature",
  "properties": {
    "addr:full":"4 Neal Pl Katherine NT 0850",
    "addr:housenumber":"4",
    "addr:postcode":"nt 0850",
    "addr:street":"Neal Pl",
    "iso:country":"AU",
    "sg:address":"4 Neal Pl",
    "sg:city":"Katherine",
    "sg:classifiers":[
        {
            "category":"Taxi",
            "type":"Transportation"
        }
    ],
    "sg:phone":"+61 8 8972 1999",
    "sg:postcode":"0850",
    "sg:province":"NT",
    "sg:tags":[
        "cab"
    ],
    "wof:name":"Katherine Taxis Hire",
    "wof:placetype":"venue"
},
  "geometry": {"coordinates":[132.27984599999999,-14.464932],"type":"Point"}
}