{
  "type": "Feature",
  "properties": {
    "addr:full":"104 Johnston St Fitzroy VIC 3065",
    "addr:housenumber":"104",
    "addr:postcode":"3065",
    "addr:street":"Johnston St",
    "iso:country":"AU",
    "sg:address":"104 Johnston St",
    "sg:city":"Fitzroy",
    "sg:classifiers":[
        {
            "category":"Communications",
            "subcategory":"Film & Video Production",
            "type":"Services"
        }
    ],
    "sg:phone":"+61 3 9417 7644",
    "sg:postcode":"3065",
    "sg:province":"VIC",
    "sg:tags":[
        "information",
        "recorded",
        "telephone"
    ],
    "wof:name":"Image On Line",
    "wof:placetype":"venue"
},
  "geometry": {"coordinates":[144.97784423799999,-37.7983818054],"type":"Point"}
}