{
  "type": "Feature",
  "properties": {
    "iso:country":"AU",
    "sg:address":"71 Princes Hwy",
    "sg:city":"Milton",
    "sg:classifiers":[
        {
            "category":"Manufacturing",
            "subcategory":"Pottery",
            "type":"Manufacturing & Wholesale Goods"
        }
    ],
    "sg:phone":"+61 2 4454 1518",
    "sg:postcode":"2538",
    "sg:province":"NSW",
    "wof:name":"Nulladolla Pottery Group",
    "wof:placetype":"venue"
},
  "geometry": {"coordinates":[150.43490600600001,-35.3155784607],"type":"Point"}
}