{
  "type": "Feature",
  "properties": {
    "addr:full":"146 Burke Rd Malvern East VIC 3145",
    "addr:housenumber":"146",
    "addr:postcode":"3145",
    "addr:street":"Burke Rd",
    "iso:country":"AU",
    "sg:address":"146 Burke Rd",
    "sg:city":"Malvern East",
    "sg:classifiers":[
        {
            "category":"Fast Food",
            "type":"Food & Drink"
        }
    ],
    "sg:phone":"+61 3 9885 3643",
    "sg:postcode":"3145",
    "sg:province":"VIC",
    "sg:tags":[
        "away",
        "take"
    ],
    "wof:name":"Central Park Roast Chicken Bar",
    "wof:placetype":"venue"
},
  "geometry": {"coordinates":[145.05036926299999,-37.8653030396],"type":"Point"}
}