{
  "type": "Feature",
  "properties": {
    "addr:full":"PO Box 844 Endeavour Hills VIC 3802",
    "addr:postcode":"3802",
    "iso:country":"AU",
    "sg:address":"PO Box 844",
    "sg:city":"Endeavour Hills",
    "sg:classifiers":[
        {
            "category":"Retail",
            "subcategory":"Repair Shop",
            "type":"Services"
        }
    ],
    "sg:phone":"+61 419 424 855",
    "sg:postcode":"3802",
    "sg:province":"VIC",
    "sg:tags":[
        "maintenance",
        "pool",
        "swimming"
    ],
    "wof:name":"Able Leak Detection",
    "wof:placetype":"venue"
},
  "geometry": {"coordinates":[145.2762146,-37.9857673645],"type":"Point"}
}