{
  "type": "Feature",
  "properties": {
    "iso:country":"AU",
    "sg:address":"2 Perouse Rd",
    "sg:city":"Randwick",
    "sg:classifiers":[
        {
            "category":"Travel",
            "subcategory":"Hotels & Motels",
            "type":"Entertainment"
        }
    ],
    "sg:phone":"+61 2 9399 3006",
    "sg:postcode":"2031",
    "sg:province":"NSW",
    "sg:tags":[
        "accommodation"
    ],
    "wof:name":"Royal Hotel",
    "wof:placetype":"venue"
},
  "geometry": {"coordinates":[151.24206543,-33.9182548523],"type":"Point"}
}