{
  "type": "Feature",
  "properties": {
    "addr:full":"Top Of Denham St Townsville QLD 4810",
    "addr:postcode":"4810",
    "addr:street":"St",
    "iso:country":"AU",
    "sg:address":"Top Of Denham St",
    "sg:city":"Townsville",
    "sg:classifiers":[
        {
            "category":"Banks & Credit Unions",
            "subcategory":"Investment Brokerage",
            "type":"Services"
        }
    ],
    "sg:phone":"+61 7 4772 6999",
    "sg:postcode":"4810",
    "sg:province":"QLD",
    "sg:tags":[
        "management",
        "property"
    ],
    "wof:name":"Hooker L.J. Townsville",
    "wof:placetype":"venue"
},
  "geometry": {"coordinates":[146.81454500000001,-19.254009],"type":"Point"}
}