{
  "type": "Feature",
  "properties": {
    "addr:full":"27 Kirkaldy St Bathurst NSW 2795",
    "addr:housenumber":"27",
    "addr:postcode":"2795",
    "addr:street":"Kirkaldy St",
    "iso:country":"AU",
    "sg:address":"27 Kirkaldy St",
    "sg:city":"Bathurst",
    "sg:classifiers":[
        {
            "category":"Professional",
            "subcategory":"Engineering",
            "type":"Services"
        }
    ],
    "sg:phone":"+61 2 6332 2388",
    "sg:postcode":"2795",
    "sg:province":"NSW",
    "sg:tags":[
        "engineer"
    ],
    "wof:name":"Lumax Engineering Pty Ltd",
    "wof:placetype":"venue"
},
  "geometry": {"coordinates":[149.55354309099999,-33.5437316895],"type":"Point"}
}