{
  "type": "Feature",
  "properties": {
    "addr:full":"PO Box 79 Cardross VIC 3496",
    "addr:postcode":"3496",
    "iso:country":"AU",
    "sg:address":"PO Box 79",
    "sg:city":"Cardross",
    "sg:classifiers":[
        {
            "category":"Building & Trades",
            "subcategory":"Plumbing",
            "type":"Services"
        }
    ],
    "sg:phone":"+61 3 5024 2095",
    "sg:postcode":"3496",
    "sg:province":"VIC",
    "sg:tags":[
        "drainers"
    ],
    "wof:name":"Sunraysia Drainage Cleaning",
    "wof:placetype":"venue"
},
  "geometry": {"coordinates":[142.104858398,-34.3407592773],"type":"Point"}
}