{
  "type": "Feature",
  "properties": {
    "iso:country":"AU",
    "sg:address":"U2/ 5 Onslow Ave",
    "sg:city":"Elizabeth Bay",
    "sg:classifiers":[
        {
            "category":"Professional",
            "subcategory":"Employment Agencies",
            "type":"Services"
        }
    ],
    "sg:phone":"+61 2 9360 5332",
    "sg:postcode":"2011",
    "sg:province":"NSW",
    "wof:name":"Praxis Australia",
    "wof:placetype":"venue"
},
  "geometry": {"coordinates":[151.22645568900001,-33.8699951172],"type":"Point"}
}