{
  "type": "Feature",
  "properties": {
    "addr:full":"PO Box 2052 Ballarat VIC 3353",
    "addr:postcode":"3353",
    "iso:country":"AU",
    "sg:address":"PO Box 2052",
    "sg:city":"Ballarat",
    "sg:classifiers":[
        {
            "category":"Building & Trades",
            "subcategory":"Landscaping Services",
            "type":"Services"
        }
    ],
    "sg:phone":"+61 3 5368 6678",
    "sg:postcode":"3353",
    "sg:province":"VIC",
    "sg:tags":[
        "firebreak",
        "clearing",
        "land",
        "contractor"
    ],
    "wof:name":"Gerard Styles Treelopping",
    "wof:placetype":"venue"
},
  "geometry": {"coordinates":[143.863708,-37.56332],"type":"Point"}
}