{
  "type": "Feature",
  "properties": {
    "iso:country":"AU",
    "sg:address":"Port Wakefield Rd",
    "sg:city":"Cranbrook",
    "sg:classifiers":[
        {
            "category":"Manufacturing",
            "subcategory":"Tools & Machinery",
            "type":"Manufacturing & Wholesale Goods"
        }
    ],
    "sg:phone":"+61 8 8342 6663",
    "sg:postcode":"6321",
    "sg:province":"WA",
    "sg:tags":[
        "earth",
        "excavating",
        "moving",
        "equipment"
    ],
    "wof:name":"Citystate Machinery",
    "wof:placetype":"venue"
},
  "geometry": {"coordinates":[117.58039856000001,-34.2272415161],"type":"Point"}
}