{
  "type": "Feature",
  "properties": {
    "iso:country":"AU",
    "sg:address":"Cnr Ekibin Rd & Sexton St",
    "sg:city":"Ekibin",
    "sg:classifiers":[
        {
            "category":"Food & Beverages",
            "subcategory":"Supermarket",
            "type":"Retail Goods"
        }
    ],
    "sg:phone":"+61 7 3217 1800",
    "sg:postcode":"4121",
    "sg:province":"QLD",
    "sg:tags":[
        "grocery",
        "store"
    ],
    "wof:name":"727 Stores",
    "wof:placetype":"venue"
},
  "geometry": {"coordinates":[153.038772583,-27.5154666901],"type":"Point"}
}