{
  "type": "Feature",
  "properties": {
    "addr:full":"Shop 19, Chevron Renaissance Surfers Paradise QLD 4217",
    "addr:housenumber":"shop 19",
    "addr:postcode":"4217",
    "addr:street":"Chevron Renaissance",
    "iso:country":"AU",
    "sg:address":"Shop 19, Chevron Renaissance",
    "sg:city":"Surfers Paradise",
    "sg:classifiers":[
        {
            "category":"Shopping",
            "subcategory":"Clothing, Apparel, & Fashions",
            "type":"Retail Goods"
        }
    ],
    "sg:phone":"+61 7 5526 7224",
    "sg:postcode":"4217",
    "sg:province":"QLD",
    "sg:tags":[
        "lady",
        "wear"
    ],
    "wof:name":"Yours International",
    "wof:placetype":"venue"
},
  "geometry": {"coordinates":[153.42675781200001,-27.9907436371],"type":"Point"}
}