{
  "type": "Feature",
  "properties": {
    "addr:full":"100 Old Port Wakefield Rd Two Wells SA 5501",
    "addr:housenumber":"100",
    "addr:postcode":"5501",
    "addr:street":"Old Port Wakefield Rd",
    "iso:country":"AU",
    "sg:address":"100 Old Port Wakefield Rd",
    "sg:city":"Two Wells",
    "sg:classifiers":[
        {
            "category":"Fast Food",
            "type":"Food & Drink"
        }
    ],
    "sg:phone":"+61 8 8520 2436",
    "sg:postcode":"5501",
    "sg:province":"SA",
    "sg:tags":[
        "away",
        "take"
    ],
    "wof:name":"Two Wells Pizza Bar",
    "wof:placetype":"venue"
},
  "geometry": {"coordinates":[138.51466400000001,-34.593758],"type":"Point"}
}