{
  "type": "Feature",
  "properties": {
    "addr:full":"67 Elizabeth St Launceston TAS 7250",
    "addr:housenumber":"67",
    "addr:postcode":"7250",
    "addr:street":"Elizabeth St",
    "iso:country":"AU",
    "sg:address":"67 Elizabeth St",
    "sg:city":"Launceston",
    "sg:classifiers":[
        {
            "category":"Utilities",
            "subcategory":"Electric",
            "type":"Services"
        }
    ],
    "sg:phone":"+61 3 6334 5034",
    "sg:postcode":"7250",
    "sg:province":"TAS",
    "sg:tags":[
        "tube",
        "lamps",
        "globe"
    ],
    "wof:name":"Launceston Lighting Centre",
    "wof:placetype":"venue"
},
  "geometry": {"coordinates":[147.13807678200001,-41.4409484863],"type":"Point"}
}