{
  "type": "Feature",
  "properties": {
    "addr:full":"19 Sutton St Canowindra NSW 2804",
    "addr:housenumber":"19",
    "addr:postcode":"2804",
    "addr:street":"Sutton St",
    "iso:country":"AU",
    "sg:address":"19 Sutton St",
    "sg:city":"Canowindra",
    "sg:classifiers":[
        {
            "category":"Social Services",
            "subcategory":"Child Care",
            "type":"Services"
        }
    ],
    "sg:phone":"+61 408 987 308",
    "sg:postcode":"2804",
    "sg:province":"NSW",
    "sg:tags":[
        "shearer"
    ],
    "wof:name":"Leo Weymouth",
    "wof:placetype":"venue"
},
  "geometry": {"coordinates":[148.66294860799999,-33.5753479004],"type":"Point"}
}