{
  "type": "Feature",
  "properties": {
    "iso:country":"AU",
    "sg:address":"20 A'Beckett St",
    "sg:city":"Prahran East",
    "sg:classifiers":[
        {
            "category":"Professional",
            "subcategory":"Art Services",
            "type":"Services"
        }
    ],
    "sg:phone":"+61 3 9529 2780",
    "sg:postcode":"3181",
    "sg:province":"VIC",
    "sg:tags":[
        "interior",
        "decorator"
    ],
    "wof:name":"Johnston-Miller Design Pty Ltd",
    "wof:placetype":"venue"
},
  "geometry": {"coordinates":[145.00944519000001,-37.8512496948],"type":"Point"}
}