{
  "type": "Feature",
  "properties": {
    "addr:full":"93 Melbourne St North Adelaide SA 5006",
    "addr:housenumber":"93",
    "addr:postcode":"5006",
    "addr:street":"Melbourne St",
    "iso:country":"AU",
    "sg:address":"93 Melbourne St",
    "sg:city":"North Adelaide",
    "sg:classifiers":[
        {
            "category":"Food & Beverages",
            "subcategory":"Liquor & Beverages",
            "type":"Retail Goods"
        }
    ],
    "sg:phone":"+61 8 8267 1533",
    "sg:postcode":"5006",
    "sg:province":"SA",
    "sg:tags":[
        "merchant",
        "spirit",
        "wine"
    ],
    "wof:name":"Melbourne St Wine Cellars",
    "wof:placetype":"venue"
},
  "geometry": {"coordinates":[138.60820007300001,-34.9067382812],"type":"Point"}
}