{
  "type": "Feature",
  "properties": {
    "addr:full":"233 Bridge Rd Forest Lodge NSW 2037",
    "addr:housenumber":"233",
    "addr:postcode":"2037",
    "addr:street":"Bridge Rd",
    "iso:country":"AU",
    "sg:address":"233 Bridge Rd",
    "sg:city":"Forest Lodge",
    "sg:classifiers":[
        {
            "category":"Social Services",
            "subcategory":"Child Care",
            "type":"Services"
        }
    ],
    "sg:phone":"+61 2 9660 4334",
    "sg:postcode":"2037",
    "sg:province":"NSW",
    "wof:name":"F.L.A.S.C.A. (Forest Lodge After School Care Association)",
    "wof:placetype":"venue"
},
  "geometry": {"coordinates":[151.181274414,-33.8827018738],"type":"Point"}
}