{
  "type": "Feature",
  "properties": {
    "addr:full":"1010 Botany Rd Mascot NSW 2020",
    "addr:housenumber":"1010",
    "addr:postcode":"2020",
    "addr:street":"Botany Rd",
    "iso:country":"AU",
    "sg:address":"1010 Botany Rd",
    "sg:city":"Mascot",
    "sg:classifiers":[
        {
            "category":"Manufacturing",
            "subcategory":"Paper Products",
            "type":"Manufacturing & Wholesale Goods"
        }
    ],
    "sg:phone":"+61 2 9667 2502",
    "sg:postcode":"2020",
    "sg:province":"NSW",
    "sg:tags":[
        "metal",
        "non-ferrous",
        "foundry"
    ],
    "sg:website":"http://www.centralfoundry.com.au",
    "wof:name":"Central Foundry P/L",
    "wof:placetype":"venue"
},
  "geometry": {"coordinates":[151.193634033,-33.9332618713],"type":"Point"}
}