{
  "type": "Feature",
  "properties": {
    "iso:country":"AU",
    "sg:address":"51 Beaumont St",
    "sg:city":"Hamilton",
    "sg:classifiers":[
        {
            "category":"Fast Food",
            "type":"Food & Drink"
        }
    ],
    "sg:phone":"+61 2 4965 3300",
    "sg:postcode":"2303",
    "sg:province":"NSW",
    "sg:tags":[
        "away",
        "take"
    ],
    "wof:name":"Cappodocia",
    "wof:placetype":"venue"
},
  "geometry": {"coordinates":[151.74754300000001,-32.921528],"type":"Point"}
}