{
  "type": "Feature",
  "properties": {
    "addr:full":"Shop 107, Cairns Central McLeod St Cairns QLD 4870",
    "addr:housenumber":"107",
    "addr:postcode":"4870",
    "addr:street":"St",
    "iso:country":"AU",
    "sg:address":"Shop 107, Cairns Central McLeod St",
    "sg:city":"Cairns",
    "sg:classifiers":[
        {
            "category":"Shopping",
            "subcategory":"Mobile Phones",
            "type":"Retail Goods"
        }
    ],
    "sg:phone":"+61 7 4041 1111",
    "sg:postcode":"4870",
    "sg:province":"QLD",
    "sg:tags":[
        "telephone",
        "accessory"
    ],
    "wof:name":"Fone Zone",
    "wof:placetype":"venue"
},
  "geometry": {"coordinates":[145.774169922,-16.926197052],"type":"Point"}
}