{
  "type": "Feature",
  "properties": {
    "addr:full":"445 William St Perth WA 6000",
    "addr:housenumber":"445",
    "addr:postcode":"6000",
    "addr:street":"William St",
    "iso:country":"AU",
    "sg:address":"445 William St",
    "sg:city":"Perth",
    "sg:classifiers":[
        {
            "category":"Personal",
            "subcategory":"Beauty Salon",
            "type":"Services"
        }
    ],
    "sg:phone":"+61 8 9328 6570",
    "sg:postcode":"6000",
    "sg:province":"WA",
    "sg:tags":[
        "hairdresser"
    ],
    "wof:name":"House Of Messina",
    "wof:placetype":"venue"
},
  "geometry": {"coordinates":[115.85664367699999,-31.9540557861],"type":"Point"}
}