{
  "type": "Feature",
  "properties": {
    "iso:country":"AU",
    "sg:address":"8 Goorari St",
    "sg:city":"Eight Mile Plains",
    "sg:classifiers":[
        {
            "category":"Home & Garden",
            "subcategory":"Building Materials",
            "type":"Retail Goods"
        }
    ],
    "sg:phone":"+61 7 3841 3157",
    "sg:postcode":"4113",
    "sg:province":"QLD",
    "sg:tags":[
        "merchant",
        "glass",
        "glazier"
    ],
    "sg:website":"http://www.mcautoglass.com.au",
    "wof:name":"M C Autoglass",
    "wof:placetype":"venue"
},
  "geometry": {"coordinates":[153.09674072300001,-27.5701179504],"type":"Point"}
}