{
  "type": "Feature",
  "properties": {
    "iso:country":"AU",
    "sg:address":"38 Mitchell St",
    "sg:city":"Darwin",
    "sg:classifiers":[
        {
            "category":"Real Estate",
            "subcategory":"Real Estate Agent",
            "type":"Services"
        }
    ],
    "sg:phone":"+61 412 613 055",
    "sg:postcode":"0800",
    "sg:province":"NT",
    "wof:name":"Quan Richard",
    "wof:placetype":"venue"
},
  "geometry": {"coordinates":[130.84104919399999,-12.4640693665],"type":"Point"}
}