{
  "type": "Feature",
  "properties": {
    "addr:full":"19 Pechey St Toowoomba QLD 4350",
    "addr:housenumber":"19",
    "addr:postcode":"4350",
    "addr:street":"Pechey St",
    "iso:country":"AU",
    "sg:address":"19 Pechey St",
    "sg:city":"Toowoomba",
    "sg:classifiers":[
        {
            "category":"Autos & Motor Vehicles",
            "subcategory":"Auto Supplies",
            "type":"Retail Goods"
        }
    ],
    "sg:phone":"+61 7 4639 1547",
    "sg:postcode":"4350",
    "sg:province":"QLD",
    "sg:tags":[
        "accessory"
    ],
    "wof:name":"Motogear",
    "wof:placetype":"venue"
},
  "geometry": {"coordinates":[151.94627399999999,-27.572371],"type":"Point"}
}