{
  "type": "Feature",
  "properties": {
    "addr:full":"177 Bondi Rd Bondi NSW 2026",
    "addr:housenumber":"177",
    "addr:postcode":"2026",
    "addr:street":"Bondi Rd",
    "iso:country":"AU",
    "sg:address":"177 Bondi Rd",
    "sg:city":"Bondi",
    "sg:classifiers":[
        {
            "category":"Health Services",
            "subcategory":"Medical Lab",
            "type":"Services"
        }
    ],
    "sg:phone":"+61 2 9389 4929",
    "sg:postcode":"2026",
    "sg:province":"NSW",
    "sg:tags":[
        "laboratory",
        "dental"
    ],
    "wof:name":"A.B. Bondi Dental Laboratories",
    "wof:placetype":"venue"
},
  "geometry": {"coordinates":[151.26449585,-33.8941497803],"type":"Point"}
}