{
  "type": "Feature",
  "properties": {
    "addr:full":"Unit 6/ 9 Hume Rd Smithfield NSW 2164",
    "addr:housenumber":"9",
    "addr:postcode":"2164",
    "addr:street":"Hume Rd",
    "iso:country":"AU",
    "sg:address":"Unit 6/ 9 Hume Rd",
    "sg:city":"Smithfield",
    "sg:classifiers":[
        {
            "category":"Manufacturing",
            "subcategory":"Tools & Machinery",
            "type":"Manufacturing & Wholesale Goods"
        }
    ],
    "sg:phone":"+61 2 9604 2674",
    "sg:postcode":"2164",
    "sg:province":"NSW",
    "sg:tags":[
        "toolmaker"
    ],
    "wof:name":"Tool-Mann Pty Ltd",
    "wof:placetype":"venue"
},
  "geometry": {"coordinates":[150.93063354500001,-33.8366241455],"type":"Point"}
}