{
  "type": "Feature",
  "properties": {
    "iso:country":"AU",
    "sg:address":"25 Khartoum Rd",
    "sg:city":"North Ryde",
    "sg:classifiers":[
        {
            "category":"Social Services",
            "subcategory":"Adult Care",
            "type":"Services"
        }
    ],
    "sg:phone":"+61 2 8875 8900",
    "sg:postcode":"2113",
    "sg:province":"NSW",
    "sg:tags":[
        "disadvantaged",
        "aid",
        "organisation",
        "group"
    ],
    "wof:name":"Parkinson's NSW Inc",
    "wof:placetype":"venue"
},
  "geometry": {"coordinates":[151.1275177,-33.776802063],"type":"Point"}
}