{
  "type": "Feature",
  "properties": {
    "addr:full":"Level 4, 40 Miller St North Sydney NSW 2060",
    "addr:housenumber":"40",
    "addr:postcode":"2060",
    "addr:street":"Miller St",
    "iso:country":"AU",
    "sg:address":"Level 4, 40 Miller St",
    "sg:city":"North Sydney",
    "sg:classifiers":[
        {
            "category":"Parking",
            "type":"Transportation"
        }
    ],
    "sg:phone":"+61 2 9080 8486",
    "sg:postcode":"2060",
    "sg:province":"NSW",
    "wof:name":"Mirvac Parking - Head Office",
    "wof:placetype":"venue"
},
  "geometry": {"coordinates":[151.20639038100001,-33.8403625488],"type":"Point"}
}