{
  "type": "Feature",
  "properties": {
    "iso:country":"AU",
    "sg:address":"16 Banbury Crs",
    "sg:city":"Chipping Norton",
    "sg:classifiers":[
        {
            "category":"Professional",
            "subcategory":"Testing Lab",
            "type":"Services"
        }
    ],
    "sg:phone":"+61 2 9824 2412",
    "sg:postcode":"2170",
    "sg:province":"NSW",
    "sg:tags":[
        "inspection"
    ],
    "wof:name":"VTI Service Pty Ltd",
    "wof:placetype":"venue"
},
  "geometry": {"coordinates":[150.96173095699999,-33.9171600342],"type":"Point"}
}