{
  "type": "Feature",
  "properties": {
    "iso:country":"AU",
    "sg:address":"757 Pacific Hwy",
    "sg:city":"Mt Kuring-gai",
    "sg:classifiers":[
        {
            "category":"Food & Beverages",
            "subcategory":"Supermarket",
            "type":"Retail Goods"
        }
    ],
    "sg:phone":"+61 2 9457 9141",
    "sg:postcode":"2080",
    "sg:province":"NSW",
    "sg:tags":[
        "grocery",
        "store"
    ],
    "wof:name":"Mt Kuring-Gai MFC",
    "wof:placetype":"venue"
},
  "geometry": {"coordinates":[151.13438415499999,-33.6562232971],"type":"Point"}
}