{
  "type": "Feature",
  "properties": {
    "addr:full":"414 Elizabeth St Surry Hills NSW 2010",
    "addr:housenumber":"414",
    "addr:postcode":"2010",
    "addr:street":"Elizabeth St",
    "iso:country":"AU",
    "sg:address":"414 Elizabeth St",
    "sg:city":"Surry Hills",
    "sg:classifiers":[
        {
            "category":"Cafe",
            "type":"Food & Drink"
        }
    ],
    "sg:phone":"+61 2 9281 7105",
    "sg:postcode":"2010",
    "sg:province":"NSW",
    "wof:name":"Cafe 414",
    "wof:placetype":"venue"
},
  "geometry": {"coordinates":[151.20840454099999,-33.8863067627],"type":"Point"}
}