{
  "type": "Feature",
  "properties": {
    "addr:full":"16 Rowan Ave Newstead TAS 7250",
    "addr:housenumber":"16",
    "addr:postcode":"7250",
    "addr:street":"Rowan Ave",
    "iso:country":"AU",
    "sg:address":"16 Rowan Ave",
    "sg:city":"Newstead",
    "sg:classifiers":[
        {
            "category":"Building & Trades",
            "subcategory":"Landscaping Services",
            "type":"Services"
        }
    ],
    "sg:phone":"+61 407 346 003",
    "sg:postcode":"7250",
    "sg:province":"TAS",
    "sg:tags":[
        "designer",
        "landscape",
        "contractor"
    ],
    "wof:name":"Kris Sturmer",
    "wof:placetype":"venue"
},
  "geometry": {"coordinates":[147.161254883,-41.4378242493],"type":"Point"}
}