{
  "type": "Feature",
  "properties": {
    "addr:full":"Shop 80 , Lakehaven Shopping Cntr Lake Haven NSW 2263",
    "addr:housenumber":"shop 80",
    "addr:postcode":"2263",
    "addr:street":"Lakehaven Shopping Cntr Lake",
    "iso:country":"AU",
    "sg:address":"Shop 80",
    "sg:city":", Lakehaven Shopping Cntr Lake Haven",
    "sg:classifiers":[
        {
            "category":"Shopping",
            "subcategory":"Shoes",
            "type":"Retail Goods"
        }
    ],
    "sg:phone":"+61 2 4392 4895",
    "sg:postcode":"2263",
    "sg:province":"NSW",
    "sg:tags":[
        "footwear"
    ],
    "wof:name":"Payless Shoes",
    "wof:placetype":"venue"
},
  "geometry": {"coordinates":[151.500137,-33.243938],"type":"Point"}
}