{
  "type": "Feature",
  "properties": {
    "addr:full":"114 Rankin St Innisfail QLD 4860",
    "addr:housenumber":"114",
    "addr:postcode":"4860",
    "addr:street":"Rankin St",
    "iso:country":"AU",
    "sg:address":"114 Rankin St",
    "sg:city":"Innisfail",
    "sg:classifiers":[
        {
            "category":"Banks & Credit Unions",
            "subcategory":"Investment Brokerage",
            "type":"Services"
        }
    ],
    "sg:phone":"+61 7 4061 1115",
    "sg:postcode":"4860",
    "sg:province":"QLD",
    "sg:tags":[
        "management",
        "property"
    ],
    "wof:name":"Hensler Realty",
    "wof:placetype":"venue"
},
  "geometry": {"coordinates":[146.02961730999999,-17.5203380585],"type":"Point"}
}