{
  "type": "Feature",
  "properties": {
    "addr:full":"544 Pacific Hwy Killara NSW 2071",
    "addr:housenumber":"544",
    "addr:postcode":"2071",
    "addr:street":"Pacific Hwy",
    "iso:country":"AU",
    "sg:address":"544 Pacific Hwy",
    "sg:city":"Killara",
    "sg:classifiers":[
        {
            "category":"Retail",
            "subcategory":"Auto Repair",
            "type":"Services"
        }
    ],
    "sg:phone":"+61 2 9418 1111",
    "sg:postcode":"2071",
    "sg:province":"NSW",
    "sg:tags":[
        "repairer",
        "motor",
        "engineer"
    ],
    "wof:name":"Killara Garage",
    "wof:placetype":"venue"
},
  "geometry": {"coordinates":[151.159912109,-33.769443512],"type":"Point"}
}