{
  "type": "Feature",
  "properties": {
    "addr:full":"45 Kensington Rd Norwood SA 5067",
    "addr:housenumber":"45",
    "addr:postcode":"5067",
    "addr:street":"Kensington Rd",
    "iso:country":"AU",
    "sg:address":"45 Kensington Rd",
    "sg:city":"Norwood",
    "sg:classifiers":[
        {
            "category":"Autos & Motor Vehicles",
            "subcategory":"Auto Supplies",
            "type":"Retail Goods"
        }
    ],
    "sg:phone":"+61 8 8331 3255",
    "sg:postcode":"5067",
    "sg:province":"SA",
    "sg:tags":[
        "camper-trailers",
        "caravan",
        "equipment"
    ],
    "wof:name":"Lifecycle Bicycles",
    "wof:placetype":"venue"
},
  "geometry": {"coordinates":[138.62677001899999,-34.9275779724],"type":"Point"}
}