{
  "type": "Feature",
  "properties": {
    "addr:full":"37 Howards Rd Beverley SA 5009",
    "addr:housenumber":"37",
    "addr:postcode":"5009",
    "addr:street":"Howards Rd",
    "iso:country":"AU",
    "sg:address":"37 Howards Rd",
    "sg:city":"Beverley",
    "sg:classifiers":[
        {
            "category":"Manufacturing",
            "subcategory":"Glass & Minerals",
            "type":"Manufacturing & Wholesale Goods"
        }
    ],
    "sg:phone":"+61 8 8260 4384",
    "sg:postcode":"5009",
    "sg:province":"SA",
    "sg:tags":[
        "merchant",
        "granite",
        "marble"
    ],
    "wof:name":"All State Marble & Granite Pty Ltd",
    "wof:placetype":"venue"
},
  "geometry": {"coordinates":[138.54380798299999,-34.8899536133],"type":"Point"}
}