{
  "type": "Feature",
  "properties": {
    "iso:country":"AU",
    "sg:address":"451 Banna Ave",
    "sg:city":"Griffith",
    "sg:classifiers":[
        {
            "category":"Personal",
            "subcategory":"Beauty Salon",
            "type":"Services"
        }
    ],
    "sg:phone":"+61 2 6962 2925",
    "sg:postcode":"2680",
    "sg:province":"NSW",
    "sg:tags":[
        "hairdresser"
    ],
    "wof:name":"Battaglia Salon",
    "wof:placetype":"venue"
},
  "geometry": {"coordinates":[146.059814,-34.28941],"type":"Point"}
}