{
  "type": "Feature",
  "properties": {
    "addr:full":"451 Banna Ave Griffith NSW 2680",
    "addr:housenumber":"451",
    "addr:postcode":"2680",
    "addr:street":"Banna Ave",
    "iso:country":"AU",
    "sg:address":"451 Banna Ave",
    "sg:city":"Griffith",
    "sg:classifiers":[
        {
            "category":"Personal",
            "subcategory":"Beauty Salon",
            "type":"Services"
        }
    ],
    "sg:phone":"+61 2 6962 2925",
    "sg:postcode":"2680",
    "sg:province":"NSW",
    "sg:tags":[
        "hairdresser"
    ],
    "wof:name":"Battaglia Salon",
    "wof:placetype":"venue"
},
  "geometry": {"coordinates":[146.05981399999999,-34.28941],"type":"Point"}
}