{
  "type": "Feature",
  "properties": {
    "iso:country":"AU",
    "sg:address":"5 Carmody Pl",
    "sg:city":"Bunbury",
    "sg:classifiers":[
        {
            "category":"Internet Cafe",
            "subcategory":"None",
            "type":"Food & Drink"
        }
    ],
    "sg:phone":"+61 8 9791 1254",
    "sg:postcode":"6230",
    "sg:province":"WA",
    "wof:name":"Old Station Coffee Lounge",
    "wof:placetype":"venue"
},
  "geometry": {"coordinates":[115.638542,-33.324444],"type":"Point"}
}