{
  "type": "Feature",
  "properties": {
    "addr:full":"296 Little Lonsdale St Melbourne VIC 3000",
    "addr:housenumber":"296",
    "addr:postcode":"3000",
    "addr:street":"Little Lonsdale St",
    "iso:country":"AU",
    "sg:address":"296 Little Lonsdale St",
    "sg:city":"Melbourne",
    "sg:classifiers":[
        {
            "category":"Shopping",
            "subcategory":"Department Store",
            "type":"Retail Goods"
        }
    ],
    "sg:phone":"+61 3 9670 8112",
    "sg:postcode":"3000",
    "sg:province":"VIC",
    "wof:name":"Yoki&#039;e Clothing",
    "wof:placetype":"venue"
},
  "geometry": {"coordinates":[144.96058654800001,-37.8115196228],"type":"Point"}
}