{
  "type": "Feature",
  "properties": {
    "addr:full":"Shop: 2 265 Castlereagh St Sydney NSW 2000",
    "addr:housenumber":"shop 2 265",
    "addr:postcode":"2000",
    "addr:street":"Castlereagh St",
    "iso:country":"AU",
    "sg:address":"Shop: 2 265 Castlereagh St",
    "sg:city":"Sydney",
    "sg:classifiers":[
        {
            "category":"Fast Food",
            "type":"Food & Drink"
        }
    ],
    "sg:phone":"+61 2 9283 1865",
    "sg:postcode":"2000",
    "sg:province":"NSW",
    "sg:tags":[
        "away",
        "take"
    ],
    "wof:name":"Karvs Take-Away Food",
    "wof:placetype":"venue"
},
  "geometry": {"coordinates":[151.20855712900001,-33.8772392273],"type":"Point"}
}