{
  "type": "Feature",
  "properties": {
    "addr:full":"123 Watsons Rd Glen Waverley VIC 3150",
    "addr:housenumber":"123",
    "addr:postcode":"3150",
    "addr:street":"Watsons Rd",
    "iso:country":"AU",
    "sg:address":"123 Watsons Rd",
    "sg:city":"Glen Waverley",
    "sg:classifiers":[
        {
            "category":"Building & Trades",
            "subcategory":"Construction",
            "type":"Services"
        }
    ],
    "sg:phone":"+61 425 773 708",
    "sg:postcode":"3150",
    "sg:province":"VIC",
    "sg:tags":[
        "plasterboard",
        "plasterer",
        "fixer"
    ],
    "wof:name":"Coventry Plaster",
    "wof:placetype":"venue"
},
  "geometry": {"coordinates":[145.16786193900001,-37.901966095],"type":"Point"}
}