{
  "type": "Feature",
  "properties": {
    "iso:country":"AU",
    "sg:address":"1A/ 352 South St",
    "sg:city":"O'Connor",
    "sg:classifiers":[
        {
            "category":"Autos & Motor Vehicles",
            "subcategory":"Auto Supplies",
            "type":"Retail Goods"
        }
    ],
    "sg:phone":"+61 8 9337 0700",
    "sg:postcode":"6163",
    "sg:province":"WA",
    "sg:tags":[
        "paint",
        "automotive"
    ],
    "wof:name":"Anchor Paint Place",
    "wof:placetype":"venue"
},
  "geometry": {"coordinates":[115.78568300000001,-32.063046],"type":"Point"}
}