{
  "type": "Feature",
  "properties": {
    "addr:full":"Shop 1/ 222 Walker St Bundaberg QLD 4670",
    "addr:housenumber":"shop 1 / 222",
    "addr:postcode":"4670",
    "addr:street":"Walker St",
    "iso:country":"AU",
    "sg:address":"Shop 1/ 222 Walker St",
    "sg:city":"Bundaberg",
    "sg:classifiers":[
        {
            "category":"Sports & Exercise",
            "subcategory":"Gym",
            "type":"Entertainment"
        }
    ],
    "sg:phone":"+61 7 4151 0106",
    "sg:postcode":"4670",
    "sg:province":"QLD",
    "sg:tags":[
        "pilate",
        "method"
    ],
    "wof:name":"Active Physiotherapy Solutions",
    "wof:placetype":"venue"
},
  "geometry": {"coordinates":[152.330810547,-24.8774776459],"type":"Point"}
}