{
  "type": "Feature",
  "properties": {
    "iso:country":"AU",
    "sg:address":"16 Stuart St",
    "sg:city":"Hawthorne",
    "sg:classifiers":[
        {
            "category":"Professional",
            "subcategory":"Employment Agencies",
            "type":"Services"
        }
    ],
    "sg:phone":"+61 7 3899 1382",
    "sg:postcode":"4171",
    "sg:province":"QLD",
    "sg:tags":[
        "entertainer",
        "agent"
    ],
    "wof:name":"A All Amusement Rides, Fetes, Festivals & Hire",
    "wof:placetype":"venue"
},
  "geometry": {"coordinates":[153.058425903,-27.4519329071],"type":"Point"}
}