{
  "type": "Feature",
  "properties": {
    "addr:full":"Shp13/ 357 Redbank Plains Rd Redbank Plains QLD 4301",
    "addr:housenumber":"357",
    "addr:postcode":"4301",
    "addr:street":"Plains Rd",
    "iso:country":"AU",
    "sg:address":"Shp13/ 357 Redbank Plains Rd",
    "sg:city":"Redbank Plains",
    "sg:classifiers":[
        {
            "category":"Cafe",
            "type":"Food & Drink"
        }
    ],
    "sg:phone":"+61 7 3814 1200",
    "sg:postcode":"4301",
    "sg:province":"QLD",
    "wof:name":"Fig Cafe The",
    "wof:placetype":"venue"
},
  "geometry": {"coordinates":[152.87272644000001,-27.6389808655],"type":"Point"}
}