{
  "type": "Feature",
  "properties": {
    "addr:full":"1056 Old Princes Hwy Engadine NSW 2233",
    "addr:housenumber":"1056",
    "addr:postcode":"2233",
    "addr:street":"Old Princes Hwy",
    "iso:country":"AU",
    "sg:address":"1056 Old Princes Hwy",
    "sg:city":"Engadine",
    "sg:classifiers":[
        {
            "category":"Personal",
            "subcategory":"Shoe Repair & Shine",
            "type":"Services"
        }
    ],
    "sg:phone":"+61 2 9520 9027",
    "sg:postcode":"2233",
    "sg:province":"NSW",
    "sg:tags":[
        "footwear"
    ],
    "wof:name":"A & M Zeiden Shoe Repairs",
    "wof:placetype":"venue"
},
  "geometry": {"coordinates":[151.012649536,-34.0659484863],"type":"Point"}
}