{
  "type": "Feature",
  "properties": {
    "iso:country":"AU",
    "sg:address":"42 McRoyle St",
    "sg:city":"Wacol",
    "sg:classifiers":[
        {
            "category":"Farming",
            "subcategory":"Farm & Veterinary Services",
            "type":"Manufacturing & Wholesale Goods"
        }
    ],
    "sg:phone":"+61 7 3879 3350",
    "sg:postcode":"4076",
    "sg:province":"QLD",
    "sg:tags":[
        "seedsman"
    ],
    "wof:name":"Australian Premium Seeds Pty Ltd",
    "wof:placetype":"venue"
},
  "geometry": {"coordinates":[152.93392944300001,-27.5971717834],"type":"Point"}
}