{
  "type": "Feature",
  "properties": {
    "iso:country":"AU",
    "sg:address":"Shop 18 146 b Eighth St",
    "sg:city":"Mildura",
    "sg:classifiers":[
        {
            "category":"Personal",
            "subcategory":"Beauty Salon",
            "type":"Services"
        }
    ],
    "sg:phone":"+61 3 5022 7484",
    "sg:postcode":"3500",
    "sg:province":"VIC",
    "sg:tags":[
        "hairdresser"
    ],
    "wof:name":"Retro Hair",
    "wof:placetype":"venue"
},
  "geometry": {"coordinates":[142.171386719,-34.1923179626],"type":"Point"}
}