{
  "type": "Feature",
  "properties": {
    "addr:full":"Unit 2, 1199 The Horsley Drv Wetherill Park NSW 2164",
    "addr:housenumber":"1199",
    "addr:postcode":"2164",
    "addr:street":"The Horsley Drv",
    "iso:country":"AU",
    "sg:address":"Unit 2, 1199 The Horsley Drv",
    "sg:city":"Wetherill Park",
    "sg:classifiers":[
        {
            "category":"Home & Garden",
            "subcategory":"Hardware",
            "type":"Retail Goods"
        }
    ],
    "sg:phone":"+61 2 9756 5081",
    "sg:postcode":"2164",
    "sg:province":"NSW",
    "sg:tags":[
        "repair",
        "tool",
        "power"
    ],
    "wof:name":"Greater West Powertools Pty Ltd",
    "wof:placetype":"venue"
},
  "geometry": {"coordinates":[150.89210510300001,-33.8474006653],"type":"Point"}
}