{
  "type": "Feature",
  "properties": {
    "addr:full":"127 Dripping Rock Rd Eugowra NSW 2806",
    "addr:housenumber":"127",
    "addr:postcode":"2806",
    "addr:street":"Dripping Rock Rd",
    "iso:country":"AU",
    "sg:address":"127 Dripping Rock Rd",
    "sg:city":"Eugowra",
    "sg:classifiers":[
        {
            "category":"Home & Garden",
            "subcategory":"Carpets & Floor Coverings",
            "type":"Retail Goods"
        }
    ],
    "sg:phone":"+61 427 595 226",
    "sg:postcode":"2806",
    "sg:province":"NSW",
    "sg:tags":[
        "tile",
        "wall"
    ],
    "wof:name":"S&H Tiling",
    "wof:placetype":"venue"
},
  "geometry": {"coordinates":[148.368743897,-33.4269981384],"type":"Point"}
}