{
  "type": "Feature",
  "properties": {
    "addr:full":"5 Winkworth St Cairns QLD 4870",
    "addr:housenumber":"5",
    "addr:postcode":"4870",
    "addr:street":"Winkworth St",
    "iso:country":"AU",
    "sg:address":"5 Winkworth St",
    "sg:city":"Cairns",
    "sg:classifiers":[
        {
            "category":"Professional",
            "subcategory":"Printing & Photocopies",
            "type":"Services"
        }
    ],
    "sg:phone":"+61 7 4031 3553",
    "sg:postcode":"4870",
    "sg:province":"QLD",
    "sg:tags":[
        "equipment",
        "plan"
    ],
    "wof:name":"Ramco",
    "wof:placetype":"venue"
},
  "geometry": {"coordinates":[145.76206970199999,-16.9322280884],"type":"Point"}
}