{
  "type": "Feature",
  "properties": {
    "addr:full":"2 Parkes St Thornleigh NSW 2120",
    "addr:housenumber":"2",
    "addr:postcode":"2120",
    "addr:street":"Parkes St",
    "iso:country":"AU",
    "sg:address":"2 Parkes St",
    "sg:city":"Thornleigh",
    "sg:classifiers":[
        {
            "category":"Professional",
            "subcategory":"Detective & Security Services",
            "type":"Services"
        }
    ],
    "sg:phone":"+61 2 9484 8044",
    "sg:postcode":"2120",
    "sg:province":"NSW",
    "sg:tags":[
        "investigator"
    ],
    "wof:name":"Globe Investigation Services Pty Ltd",
    "wof:placetype":"venue"
},
  "geometry": {"coordinates":[151.08082580600001,-33.7306900024],"type":"Point"}
}