{
  "type": "Feature",
  "properties": {
    "iso:country":"AU",
    "sg:address":"1 Queen Elizabeth Drv",
    "sg:city":"Eatons Hill",
    "sg:classifiers":[
        {
            "category":"Food & Beverages",
            "subcategory":"Liquor & Beverages",
            "type":"Retail Goods"
        }
    ],
    "sg:phone":"+61 7 3264 4816",
    "sg:postcode":"4037",
    "sg:province":"QLD",
    "sg:tags":[
        "store"
    ],
    "wof:name":"Eureka Cellars",
    "wof:placetype":"venue"
},
  "geometry": {"coordinates":[152.951096,-27.336184],"type":"Point"}
}