{
  "type": "Feature",
  "properties": {
    "addr:full":"28A Princep St Bunbury WA 6230",
    "addr:housenumber":"28a",
    "addr:postcode":"6230",
    "addr:street":"Princep St",
    "iso:country":"AU",
    "sg:address":"28A Princep St",
    "sg:city":"Bunbury",
    "sg:classifiers":[
        {
            "category":"Shopping",
            "subcategory":"Music",
            "type":"Retail Goods"
        }
    ],
    "sg:phone":"+61 8 9721 5677",
    "sg:postcode":"6230",
    "sg:province":"WA",
    "sg:tags":[
        "store"
    ],
    "wof:name":"Leading Edge Music",
    "wof:placetype":"venue"
},
  "geometry": {"coordinates":[115.63838199999999,-33.325134],"type":"Point"}
}