{
  "type": "Feature",
  "properties": {
    "iso:country":"AU",
    "sg:address":"7 Rowena St",
    "sg:city":"Kenmore",
    "sg:classifiers":[
        {
            "category":"Social Services",
            "subcategory":"Retirement Home",
            "type":"Services"
        }
    ],
    "sg:phone":"+61 413 351 824",
    "sg:postcode":"4069",
    "sg:province":"QLD",
    "sg:tags":[
        "environmental",
        "consultant",
        "pollution"
    ],
    "wof:name":"Environment Essentials (Qld)",
    "wof:placetype":"venue"
},
  "geometry": {"coordinates":[152.929763794,-27.5189704895],"type":"Point"}
}