{
  "type": "Feature",
  "properties": {
    "iso:country":"AU",
    "sg:address":"10 Ingrid Crt",
    "sg:city":"Herne Hill",
    "sg:phone":"+61 3 5277 3419",
    "sg:postcode":"3218",
    "sg:province":"VIC",
    "wof:name":"Rhino Water Tanks",
    "wof:placetype":"venue"
},
  "geometry": {"coordinates":[144.31771850600001,-38.1349334717],"type":"Point"}
}