{
  "type": "Feature",
  "properties": {
    "iso:country":"AU",
    "sg:address":"4 Paisley St",
    "sg:city":"Footscray",
    "sg:classifiers":[
        {
            "category":"Shopping",
            "subcategory":"Optical Goods",
            "type":"Retail Goods"
        }
    ],
    "sg:phone":"+61 3 9689 8561",
    "sg:postcode":"3011",
    "sg:province":"VIC",
    "sg:tags":[
        "dispenser",
        "prescription"
    ],
    "wof:name":"H Wong Optics",
    "wof:placetype":"venue"
},
  "geometry": {"coordinates":[144.900634766,-37.8008155823],"type":"Point"}
}