{
  "type": "Feature",
  "properties": {
    "iso:country":"AU",
    "sg:address":"4, 8-10 Britton St",
    "sg:city":"Smithfield",
    "sg:classifiers":[
        {
            "category":"Manufacturing",
            "subcategory":"Rubber & Plastics",
            "type":"Manufacturing & Wholesale Goods"
        }
    ],
    "sg:phone":"+61 2 9756 0540",
    "sg:postcode":"2164",
    "sg:province":"NSW",
    "sg:tags":[
        "wholesaler",
        "product",
        "mfrs"
    ],
    "wof:name":"Allied Gaskets Pty Ltd",
    "wof:placetype":"venue"
},
  "geometry": {"coordinates":[150.94505310100001,-33.8449821472],"type":"Point"}
}