{
  "type": "Feature",
  "properties": {
    "addr:full":"112 Cambridge Rd Bellerive TAS 7018",
    "addr:housenumber":"112",
    "addr:postcode":"7018",
    "addr:street":"Cambridge Rd",
    "iso:country":"AU",
    "sg:address":"112 Cambridge Rd",
    "sg:city":"Bellerive",
    "sg:classifiers":[
        {
            "category":"Health Services",
            "subcategory":"Doctor",
            "type":"Services"
        }
    ],
    "sg:phone":"+61 3 6245 0777",
    "sg:postcode":"7018",
    "sg:province":"TAS",
    "sg:tags":[
        "medical",
        "practitioner"
    ],
    "wof:name":"Cambridge Road Surgery",
    "wof:placetype":"venue"
},
  "geometry": {"coordinates":[147.37110900900001,-42.8692779541],"type":"Point"}
}