{
  "type": "Feature",
  "properties": {
    "addr:full":"63 Field St Bowen QLD 4805",
    "addr:housenumber":"63",
    "addr:postcode":"4805",
    "addr:street":"Field St",
    "iso:country":"AU",
    "sg:address":"63 Field St",
    "sg:city":"Bowen",
    "sg:classifiers":[
        {
            "category":"Utilities",
            "subcategory":"Electric",
            "type":"Services"
        }
    ],
    "sg:phone":"+61 418 752 817",
    "sg:postcode":"4805",
    "sg:province":"QLD",
    "sg:tags":[
        "electrical",
        "contractor"
    ],
    "wof:name":"MCO Electrical Pty Ltd",
    "wof:placetype":"venue"
},
  "geometry": {"coordinates":[148.231811523,-19.9823913574],"type":"Point"}
}