{
  "type": "Feature",
  "properties": {
    "addr:full":"7/ 47 Beerwah Pde Beerwah QLD 4519",
    "addr:housenumber":"/ 47",
    "addr:postcode":"4519",
    "addr:street":"Beerwah Pde",
    "iso:country":"AU",
    "sg:address":"7/ 47 Beerwah Pde",
    "sg:city":"Beerwah",
    "sg:classifiers":[
        {
            "category":"Retail",
            "subcategory":"Repair Shop",
            "type":"Services"
        }
    ],
    "sg:phone":"+61 7 5494 0133",
    "sg:postcode":"4519",
    "sg:province":"QLD",
    "sg:tags":[
        "upholsterer"
    ],
    "wof:name":"Campbell's Upholstery",
    "wof:placetype":"venue"
},
  "geometry": {"coordinates":[152.95910599999999,-26.857761],"type":"Point"}
}