{
  "type": "Feature",
  "properties": {
    "addr:full":"Shop 41 Tranmore Pl Killarney Heights NSW 2087",
    "addr:housenumber":"shop 41",
    "addr:postcode":"2087",
    "addr:street":"Tranmore Pl",
    "iso:country":"AU",
    "sg:address":"Shop 41 Tranmore Pl",
    "sg:city":"Killarney Heights",
    "sg:classifiers":[
        {
            "category":"Personal",
            "subcategory":"Beauty Salon",
            "type":"Services"
        }
    ],
    "sg:phone":"+61 2 9453 4023",
    "sg:postcode":"2087",
    "sg:province":"NSW",
    "sg:tags":[
        "hairdresser"
    ],
    "wof:name":"Studio Hair And Makeup",
    "wof:placetype":"venue"
},
  "geometry": {"coordinates":[151.217727661,-33.774974823],"type":"Point"}
}