{
  "type": "Feature",
  "properties": {
    "addr:full":"1/ 84 Madeline St Enfield NSW 2136",
    "addr:housenumber":"/ 84",
    "addr:postcode":"2136",
    "addr:street":"Madeline St",
    "iso:country":"AU",
    "sg:address":"1/ 84 Madeline St",
    "sg:city":"Enfield",
    "sg:classifiers":[
        {
            "category":"Retail",
            "subcategory":"Auto Rental",
            "type":"Services"
        }
    ],
    "sg:phone":"+61 2 9642 3100",
    "sg:postcode":"2136",
    "sg:province":"NSW",
    "sg:tags":[
        "car",
        "hire",
        "minibus"
    ],
    "sg:website":"http://www.hawkesfordscoaches.com.au",
    "wof:name":"Hawkesford's Luxury Coaches",
    "wof:placetype":"venue"
},
  "geometry": {"coordinates":[151.078414917,-33.8990707397],"type":"Point"}
}