{
  "type": "Feature",
  "properties": {
    "addr:full":"PO Box 7262 Duffy ACT 2611",
    "addr:postcode":"2611",
    "iso:country":"AU",
    "sg:address":"PO Box 7262",
    "sg:city":"Duffy",
    "sg:classifiers":[
        {
            "category":"Sports & Exercise",
            "subcategory":"Gym",
            "type":"Entertainment"
        }
    ],
    "sg:phone":"+61 2 6287 2255",
    "sg:postcode":"2611",
    "sg:province":"ACT",
    "sg:tags":[
        "health",
        "fitness"
    ],
    "wof:name":"40 Plus Life Clubs",
    "wof:placetype":"venue"
},
  "geometry": {"coordinates":[149.031692505,-35.3368415833],"type":"Point"}
}