{
  "type": "Feature",
  "properties": {
    "addr:full":"Shop 3 Bargara Central Shopping Centre 699 Bargara Rd Bargara QLD 4670",
    "addr:housenumber":"shop 3;699",
    "addr:postcode":"4670",
    "addr:street":"Bargara Rd",
    "iso:country":"AU",
    "sg:address":"Shop 3 Bargara Central Shopping Centre 699 Bargara Rd",
    "sg:city":"Bargara",
    "sg:classifiers":[
        {
            "category":"Fast Food",
            "type":"Food & Drink"
        }
    ],
    "sg:phone":"+61 7 4159 0400",
    "sg:postcode":"4670",
    "sg:province":"QLD",
    "sg:tags":[
        "away",
        "take"
    ],
    "wof:name":"Bundy Seafood & Takeaway",
    "wof:placetype":"venue"
},
  "geometry": {"coordinates":[152.395263672,-24.8474445343],"type":"Point"}
}