{
  "type": "Feature",
  "properties": {
    "addr:full":"62 Moondine Drv Wembley WA 6014",
    "addr:housenumber":"62",
    "addr:postcode":"6014",
    "addr:street":"Moondine Drv",
    "iso:country":"AU",
    "sg:address":"62 Moondine Drv",
    "sg:city":"Wembley",
    "sg:classifiers":[
        {
            "category":"Shopping",
            "subcategory":"Gifts & Souvenirs",
            "type":"Retail Goods"
        }
    ],
    "sg:phone":"+61 8 9284 0200",
    "sg:postcode":"6014",
    "sg:province":"WA",
    "sg:tags":[
        "shop",
        "supply"
    ],
    "wof:name":"Taylor June Agencies",
    "wof:placetype":"venue"
},
  "geometry": {"coordinates":[115.80979919400001,-31.931230545],"type":"Point"}
}