{
  "type": "Feature",
  "properties": {
    "iso:country":"AU",
    "sg:address":"Unit 1, 8 Pentland Rd",
    "sg:city":"Salisbury South",
    "sg:classifiers":[
        {
            "category":"Professional",
            "subcategory":"Detective & Security Services",
            "type":"Services"
        }
    ],
    "sg:phone":"+61 8 8182 5400",
    "sg:postcode":"5106",
    "sg:province":"SA",
    "sg:tags":[
        "equipment",
        "window",
        "doors"
    ],
    "wof:name":"Drummond Home Security",
    "wof:placetype":"venue"
},
  "geometry": {"coordinates":[138.643234,-34.783726],"type":"Point"}
}