{
  "type": "Feature",
  "properties": {
    "addr:full":"Shape Clinic, Suite 109/ 19A Boundary St Darlinghurst NSW 2010",
    "addr:housenumber":"109 / 19a",
    "addr:postcode":"2010",
    "addr:street":"Boundary St",
    "iso:country":"AU",
    "sg:address":"Shape Clinic, Suite 109/ 19A Boundary St",
    "sg:city":"Darlinghurst",
    "sg:classifiers":[
        {
            "category":"Health Services",
            "subcategory":"Doctor",
            "type":"Services"
        }
    ],
    "sg:phone":"+61 2 8356 2888",
    "sg:postcode":"2010",
    "sg:province":"NSW",
    "sg:tags":[
        "medical",
        "practitioner"
    ],
    "wof:name":"Liew Steven Dr",
    "wof:placetype":"venue"
},
  "geometry": {"coordinates":[151.22529602,-33.878818512],"type":"Point"}
}