{
  "type": "Feature",
  "properties": {
    "addr:full":"182 Settlement Rd Thomastown VIC 3074",
    "addr:housenumber":"182",
    "addr:postcode":"3074",
    "addr:street":"Settlement Rd",
    "iso:country":"AU",
    "sg:address":"182 Settlement Rd",
    "sg:city":"Thomastown",
    "sg:classifiers":[
        {
            "category":"Home & Garden",
            "subcategory":"Carpets & Floor Coverings",
            "type":"Retail Goods"
        }
    ],
    "sg:phone":"+61 3 9466 2866",
    "sg:postcode":"3074",
    "sg:province":"VIC",
    "sg:tags":[
        "flooring",
        "parquet"
    ],
    "wof:name":"Metropolitan Carpets & Tiles Pty Ltd",
    "wof:placetype":"venue"
},
  "geometry": {"coordinates":[145.03811645499999,-37.6941452026],"type":"Point"}
}