{
  "type": "Feature",
  "properties": {
    "iso:country":"AU",
    "sg:address":"24c Ellena St",
    "sg:city":"Maryborough",
    "sg:classifiers":[
        {
            "category":"Autos & Motor Vehicles",
            "subcategory":"Auto Supplies",
            "type":"Retail Goods"
        }
    ],
    "sg:phone":"+61 7 4123 3124",
    "sg:postcode":"4650",
    "sg:province":"QLD",
    "sg:tags":[
        "accessory"
    ],
    "wof:name":"Consec Window Tinting Pty Ltd",
    "wof:placetype":"venue"
},
  "geometry": {"coordinates":[152.70379600000001,-25.541552],"type":"Point"}
}