{
  "type": "Feature",
  "properties": {
    "addr:full":"12 Moore St Austinmer NSW 2515",
    "addr:housenumber":"12",
    "addr:postcode":"2515",
    "addr:street":"Moore St",
    "iso:country":"AU",
    "sg:address":"12 Moore St",
    "sg:city":"Austinmer",
    "sg:classifiers":[
        {
            "category":"Personal",
            "subcategory":"Massage",
            "type":"Services"
        }
    ],
    "sg:phone":"+61 2 4268 0725",
    "sg:postcode":"2515",
    "sg:province":"NSW",
    "sg:tags":[
        "therapy"
    ],
    "wof:name":"Worboys Peter",
    "wof:placetype":"venue"
},
  "geometry": {"coordinates":[150.93298300000001,-34.3074],"type":"Point"}
}