{
  "type": "Feature",
  "properties": {
    "addr:full":"43 Gale St Mortlake NSW 2137",
    "addr:housenumber":"43",
    "addr:postcode":"2137",
    "addr:street":"Gale St",
    "iso:country":"AU",
    "sg:address":"43 Gale St",
    "sg:city":"Mortlake",
    "sg:classifiers":[
        {
            "category":"Education",
            "subcategory":"Kindergarten",
            "type":"Public Place"
        }
    ],
    "sg:phone":"+61 2 9743 3094",
    "sg:postcode":"2137",
    "sg:province":"NSW",
    "sg:tags":[
        "pre-schools"
    ],
    "wof:name":"Adams Lane Pre School",
    "wof:placetype":"venue"
},
  "geometry": {"coordinates":[151.10720825199999,-33.8455581665],"type":"Point"}
}