{
  "type": "Feature",
  "properties": {
    "addr:full":"11/ 15-27 Hutchinson St Surry Hills NSW 2010",
    "addr:housenumber":"11 / 15-27",
    "addr:postcode":"2010",
    "addr:street":"Hutchinson St",
    "iso:country":"AU",
    "sg:address":"11/ 15-27 Hutchinson St",
    "sg:city":"Surry Hills",
    "sg:classifiers":[
        {
            "category":"Shopping",
            "subcategory":"Musical Instruments",
            "type":"Retail Goods"
        }
    ],
    "sg:phone":"+61 412 230 202",
    "sg:postcode":"2010",
    "sg:province":"NSW",
    "sg:tags":[
        "musician",
        "agent"
    ],
    "wof:name":"McAvenna",
    "wof:placetype":"venue"
},
  "geometry": {"coordinates":[151.21713256800001,-33.8851470947],"type":"Point"}
}