{
  "type": "Feature",
  "properties": {
    "addr:full":"6 Meadow Rd Erina NSW 2250",
    "addr:housenumber":"6",
    "addr:postcode":"2250",
    "addr:street":"Meadow Rd",
    "iso:country":"AU",
    "sg:address":"6 Meadow Rd",
    "sg:city":"Erina",
    "sg:classifiers":[
        {
            "category":"Social Services",
            "subcategory":"Child Care",
            "type":"Services"
        }
    ],
    "sg:phone":"+61 2 4323 7701",
    "sg:postcode":"2250",
    "sg:province":"NSW",
    "wof:name":"Central Gardens Child Care Pre School",
    "wof:placetype":"venue"
},
  "geometry": {"coordinates":[151.37750244099999,-33.4325218201],"type":"Point"}
}