{
  "type": "Feature",
  "properties": {
    "addr:full":"48 Orlando Rd Lambton NSW 2299",
    "addr:housenumber":"48",
    "addr:postcode":"2299",
    "addr:street":"Orlando Rd",
    "iso:country":"AU",
    "sg:address":"48 Orlando Rd",
    "sg:city":"Lambton",
    "sg:classifiers":[
        {
            "category":"Building & Trades",
            "subcategory":"Locksmith",
            "type":"Services"
        }
    ],
    "sg:phone":"+61 2 4957 7322",
    "sg:postcode":"2299",
    "sg:province":"NSW",
    "sg:tags":[
        "equipment",
        "operating",
        "door",
        "gate"
    ],
    "wof:name":"Steel-Line Roller Doors",
    "wof:placetype":"venue"
},
  "geometry": {"coordinates":[151.719680786,-32.913646698],"type":"Point"}
}