{
  "type": "Feature",
  "properties": {
    "addr:full":"159 Roma St Brisbane QLD 4000",
    "addr:postcode":"159;4000",
    "addr:street":"Roma St",
    "iso:country":"AU",
    "sg:address":"159 Roma St",
    "sg:city":"Brisbane",
    "sg:classifiers":[
        {
            "category":"Travel",
            "subcategory":"Hotels & Motels",
            "type":"Entertainment"
        }
    ],
    "sg:phone":"+61 7 3238 2222",
    "sg:postcode":"4000",
    "sg:province":"QLD",
    "sg:tags":[
        "accommodation"
    ],
    "wof:name":"Holiday Inn",
    "wof:placetype":"venue"
},
  "geometry": {"coordinates":[153.021484375,-27.4671859741],"type":"Point"}
}