{
  "type": "Feature",
  "properties": {
    "addr:full":"70 Anomaly St Moolap VIC 3221",
    "addr:housenumber":"70",
    "addr:postcode":"3221",
    "addr:street":"Anomaly St",
    "iso:country":"AU",
    "sg:address":"70 Anomaly St",
    "sg:city":"Moolap",
    "sg:classifiers":[
        {
            "category":"Landmark",
            "subcategory":"Scenic View",
            "type":"Public Place"
        }
    ],
    "sg:phone":"+61 3 5248 7000",
    "sg:postcode":"3221",
    "sg:province":"VIC",
    "sg:tags":[
        "staircase",
        "handrail"
    ],
    "sg:website":"http://www.coastalstaircases.com.au",
    "wof:name":"Coastal Staircases",
    "wof:placetype":"venue"
},
  "geometry": {"coordinates":[144.41172800000001,-38.168781],"type":"Point"}
}