{
  "type": "Feature",
  "properties": {
    "iso:country":"AU",
    "sg:address":"26 Kathrynjane Crt",
    "sg:city":"Caboolture",
    "sg:classifiers":[
        {
            "category":"Building & Trades",
            "subcategory":"Construction",
            "type":"Services"
        }
    ],
    "sg:phone":"+61 418 709 702",
    "sg:postcode":"4510",
    "sg:province":"QLD",
    "sg:tags":[
        "contractor"
    ],
    "wof:name":"Keith Vacher Homes",
    "wof:placetype":"venue"
},
  "geometry": {"coordinates":[152.92749,-27.093536],"type":"Point"}
}