{
  "type": "Feature",
  "properties": {
    "iso:country":"AU",
    "sg:address":"11 Wellesley Rd",
    "sg:city":"Ringwood North",
    "sg:classifiers":[
        {
            "category":"Wholesale",
            "subcategory":"Machinery & Supplies",
            "type":"Manufacturing & Wholesale Goods"
        }
    ],
    "sg:phone":"+61 3 9876 1038",
    "sg:postcode":"3134",
    "sg:province":"VIC",
    "sg:tags":[
        "engineer"
    ],
    "wof:name":"Tectool Pty Ltd",
    "wof:placetype":"venue"
},
  "geometry": {"coordinates":[145.23602294899999,-37.7794189453],"type":"Point"}
}