{
  "type": "Feature",
  "properties": {
    "addr:full":"6 Keld Pl Blacktown NSW 2148",
    "addr:housenumber":"6",
    "addr:postcode":"2148",
    "addr:street":"Keld Pl",
    "iso:country":"AU",
    "sg:address":"6 Keld Pl",
    "sg:city":"Blacktown",
    "sg:classifiers":[
        {
            "category":"Health Services",
            "subcategory":"Health Practitioner",
            "type":"Services"
        }
    ],
    "sg:phone":"+61 2 9671 7453",
    "sg:postcode":"2148",
    "sg:province":"NSW",
    "sg:tags":[
        "acupuncture"
    ],
    "wof:name":"Horvath Tibor",
    "wof:placetype":"venue"
},
  "geometry": {"coordinates":[150.899124145,-33.7690582275],"type":"Point"}
}