{
  "type": "Feature",
  "properties": {
    "addr:full":"Shop 23-24 Dapto Shopping Centre Dapto NSW 2530",
    "addr:housenumber":"23-24",
    "addr:postcode":"2530",
    "addr:street":"Dapto",
    "iso:country":"AU",
    "sg:address":"Shop 23-24 Dapto Shopping Centre",
    "sg:city":"Dapto",
    "sg:classifiers":[
        {
            "category":"Shopping",
            "subcategory":"Clothing, Apparel, & Fashions",
            "type":"Retail Goods"
        }
    ],
    "sg:phone":"+61 2 4262 2500",
    "sg:postcode":"2530",
    "sg:province":"NSW",
    "sg:tags":[
        "lady",
        "wear"
    ],
    "wof:name":"Miller's Fashion Club",
    "wof:placetype":"venue"
},
  "geometry": {"coordinates":[150.76550293,-34.4786605835],"type":"Point"}
}