{
  "type": "Feature",
  "properties": {
    "addr:full":"PO Box L 83 Mt Lewis NSW 2190",
    "addr:housenumber":"83",
    "addr:postcode":"2190",
    "addr:street":"Po Box;Mt Lewis",
    "iso:country":"AU",
    "sg:address":"PO Box L 83",
    "sg:city":"Mt Lewis",
    "sg:classifiers":[
        {
            "category":"Bars & Pubs",
            "subcategory":"Nightclub",
            "type":"Food & Drink"
        }
    ],
    "sg:phone":"+61 2 9758 5321",
    "sg:postcode":"2190",
    "sg:province":"NSW",
    "sg:tags":[
        "karaoke"
    ],
    "wof:name":"Karaoke Hire Sydney",
    "wof:placetype":"venue"
},
  "geometry": {"coordinates":[151.05244400000001,-33.918427],"type":"Point"}
}