{
  "type": "Feature",
  "properties": {
    "iso:country":"AU",
    "sg:address":"479 High St",
    "sg:city":"Maitland",
    "sg:classifiers":[
        {
            "category":"Professional",
            "subcategory":"Advertising",
            "type":"Services"
        }
    ],
    "sg:phone":"+61 2 4933 5363",
    "sg:postcode":"2320",
    "sg:province":"NSW",
    "sg:tags":[
        "balloon",
        "novelty"
    ],
    "wof:name":"Maitland Florist",
    "wof:placetype":"venue"
},
  "geometry": {"coordinates":[151.55299377399999,-32.7309379578],"type":"Point"}
}