{
  "type": "Feature",
  "properties": {
    "addr:full":"50 Bald Hills Rd Creswick VIC 3363",
    "addr:housenumber":"50",
    "addr:postcode":"3363",
    "addr:street":"Bald Hills Rd",
    "iso:country":"AU",
    "sg:address":"50 Bald Hills Rd",
    "sg:city":"Creswick",
    "sg:classifiers":[
        {
            "category":"Building & Trades",
            "subcategory":"Construction",
            "type":"Services"
        }
    ],
    "sg:phone":"+61 418 337 313",
    "sg:postcode":"3363",
    "sg:province":"VIC",
    "sg:tags":[
        "contractor"
    ],
    "wof:name":"T. Ryall Building & Commercial Contractors",
    "wof:placetype":"venue"
},
  "geometry": {"coordinates":[143.88601684599999,-37.4249916077],"type":"Point"}
}