{
  "type": "Feature",
  "properties": {
    "addr:full":"77 Howard Rd Padstow NSW 2211",
    "addr:housenumber":"77",
    "addr:postcode":"2211",
    "addr:street":"Howard Rd",
    "iso:country":"AU",
    "sg:address":"77 Howard Rd",
    "sg:city":"Padstow",
    "sg:classifiers":[
        {
            "category":"Real Estate",
            "subcategory":"Real Estate Agent",
            "type":"Services"
        }
    ],
    "sg:phone":"+61 2 9792 3988",
    "sg:postcode":"2211",
    "sg:province":"NSW",
    "wof:name":"Laing + Simmons Padstow",
    "wof:placetype":"venue"
},
  "geometry": {"coordinates":[151.030945,-33.952347],"type":"Point"}
}