{
  "type": "Feature",
  "properties": {
    "iso:country":"AU",
    "sg:address":"26 Spencer St",
    "sg:city":"Bunbury",
    "sg:classifiers":[
        {
            "category":"Professional",
            "subcategory":"Accounting & Tax Preparation",
            "type":"Services"
        }
    ],
    "sg:phone":"+61 8 9721 5422",
    "sg:postcode":"6230",
    "sg:province":"WA",
    "sg:tags":[
        "consultant",
        "taxation"
    ],
    "wof:name":"Eastman & Co",
    "wof:placetype":"venue"
},
  "geometry": {"coordinates":[115.641541,-33.346977],"type":"Point"}
}