{
  "type": "Feature",
  "properties": {
    "addr:full":"4358 Kyogle Rd Wadeville NSW 2474",
    "addr:housenumber":"4358",
    "addr:postcode":"2474",
    "addr:street":"Kyogle Rd",
    "iso:country":"AU",
    "sg:address":"4358 Kyogle Rd",
    "sg:city":"Wadeville",
    "sg:classifiers":[
        {
            "category":"Building & Trades",
            "subcategory":"Construction",
            "type":"Services"
        }
    ],
    "sg:phone":"+61 2 6689 7047",
    "sg:postcode":"2474",
    "sg:province":"NSW",
    "sg:tags":[
        "earth",
        "excavating",
        "moving",
        "contractor"
    ],
    "wof:name":"Nviroscope Pty Ltd",
    "wof:placetype":"venue"
},
  "geometry": {"coordinates":[153.028808594,-28.6050605774],"type":"Point"}
}