{
  "type": "Feature",
  "properties": {
    "addr:full":"71- 73 Turton St East Maitland NSW 2323",
    "addr:housenumber":"73",
    "addr:postcode":"2323",
    "addr:street":"Turton St",
    "iso:country":"AU",
    "sg:address":"71- 73 Turton St",
    "sg:city":"East Maitland",
    "sg:classifiers":[
        {
            "category":"Retail",
            "subcategory":"Auto Repair",
            "type":"Services"
        }
    ],
    "sg:phone":"+61 2 4933 6644",
    "sg:postcode":"2323",
    "sg:province":"NSW",
    "sg:tags":[
        "bus",
        "truck"
    ],
    "wof:name":"Scania Australia Pty Ltd",
    "wof:placetype":"venue"
},
  "geometry": {"coordinates":[151.598510742,-32.7617149353],"type":"Point"}
}