{
  "type": "Feature",
  "properties": {
    "addr:full":"23 Winnifred Rd McGraths Hill NSW 2756",
    "addr:housenumber":"23",
    "addr:postcode":"2756",
    "addr:street":"Winnifred Rd",
    "iso:country":"AU",
    "sg:address":"23 Winnifred Rd",
    "sg:city":"McGraths Hill",
    "sg:classifiers":[
        {
            "category":"Building & Trades",
            "subcategory":"Construction",
            "type":"Services"
        }
    ],
    "sg:phone":"+61 2 4577 2053",
    "sg:postcode":"2756",
    "sg:province":"NSW",
    "sg:tags":[
        "concrete",
        "paving"
    ],
    "wof:name":"Bligh Park Concreting",
    "wof:placetype":"venue"
},
  "geometry": {"coordinates":[150.83909606899999,-33.6105766296],"type":"Point"}
}