{
  "type": "Feature",
  "properties": {
    "addr:full":"9 Stoddarts Rd Warragul VIC 3820",
    "addr:housenumber":"9",
    "addr:postcode":"3820",
    "addr:street":"Stoddarts Rd",
    "iso:country":"AU",
    "sg:address":"9 Stoddarts Rd",
    "sg:city":"Warragul",
    "sg:classifiers":[
        {
            "category":"Wholesale",
            "subcategory":"Office Equipment",
            "type":"Manufacturing & Wholesale Goods"
        }
    ],
    "sg:phone":"+61 3 5622 0135",
    "sg:postcode":"3820",
    "sg:province":"VIC",
    "sg:tags":[
        "nail",
        "nailing"
    ],
    "wof:name":"Waxing & Nails On Stoddarts",
    "wof:placetype":"venue"
},
  "geometry": {"coordinates":[145.94032300000001,-38.141945],"type":"Point"}
}