{
  "type": "Feature",
  "properties": {
    "iso:country":"AU",
    "sg:address":"2/ 427 Oxley Drv",
    "sg:city":"Runaway Bay",
    "sg:classifiers":[
        {
            "category":"Professional",
            "subcategory":"Detective & Security Services",
            "type":"Services"
        }
    ],
    "sg:phone":"+61 413 316 496",
    "sg:postcode":"4216",
    "sg:province":"QLD",
    "sg:tags":[
        "consultant",
        "system"
    ],
    "wof:name":"ASAP Security Services",
    "wof:placetype":"venue"
},
  "geometry": {"coordinates":[153.38771057100001,-27.9209632874],"type":"Point"}
}