{
  "type": "Feature",
  "properties": {
    "iso:country":"AU",
    "sg:address":"71 Deakin Ave",
    "sg:city":"Mildura",
    "sg:classifiers":[
        {
            "category":"Banks & Credit Unions",
            "subcategory":"Investment Brokerage",
            "type":"Services"
        }
    ],
    "sg:phone":"+61 3 5023 5368",
    "sg:postcode":"3500",
    "sg:province":"VIC",
    "sg:tags":[
        "finance",
        "broker"
    ],
    "wof:name":"Mildura Independent Finance Brokers",
    "wof:placetype":"venue"
},
  "geometry": {"coordinates":[142.16122436500001,-34.1859054565],"type":"Point"}
}