{
  "type": "Feature",
  "properties": {
    "addr:full":"88- 90 Malcolm Rd Braeside VIC 3195",
    "addr:housenumber":"90",
    "addr:postcode":"3195",
    "addr:street":"Malcolm Rd",
    "iso:country":"AU",
    "sg:address":"88- 90 Malcolm Rd",
    "sg:city":"Braeside",
    "sg:classifiers":[
        {
            "category":"Manufacturing",
            "subcategory":"Glass & Minerals",
            "type":"Manufacturing & Wholesale Goods"
        }
    ],
    "sg:phone":"+61 3 9580 9746",
    "sg:postcode":"3195",
    "sg:province":"VIC",
    "sg:tags":[
        "repair",
        "fibreglass",
        "product"
    ],
    "wof:name":"Special Patterns (Vic) Pty Ltd",
    "wof:placetype":"venue"
},
  "geometry": {"coordinates":[145.112228394,-38.0012321472],"type":"Point"}
}