{
  "type": "Feature",
  "properties": {
    "iso:country":"AU",
    "sg:address":"2 Dawson St",
    "sg:city":"Naremburn",
    "sg:classifiers":[
        {
            "category":"Professional",
            "subcategory":"Printing & Photocopies",
            "type":"Services"
        }
    ],
    "sg:phone":"+61 2 9439 8244",
    "sg:postcode":"2065",
    "sg:province":"NSW",
    "sg:tags":[
        "trophy"
    ],
    "wof:name":"Australian Glass Trophies & Awards",
    "wof:placetype":"venue"
},
  "geometry": {"coordinates":[151.20866394000001,-33.8164596558],"type":"Point"}
}