{
  "type": "Feature",
  "properties": {
    "addr:full":"228 Commercial St East Mt Gambier SA 5290",
    "addr:housenumber":"228",
    "addr:postcode":"5290",
    "addr:street":"Commercial St East Mt",
    "iso:country":"AU",
    "sg:address":"228 Commercial St",
    "sg:city":"East Mt Gambier",
    "sg:classifiers":[
        {
            "category":"Cafe",
            "type":"Food & Drink"
        }
    ],
    "sg:phone":"+61 8 8724 7800",
    "sg:postcode":"5290",
    "sg:province":"SA",
    "wof:name":"Choices Cafe",
    "wof:placetype":"venue"
},
  "geometry": {"coordinates":[140.79882799999999,-37.834362],"type":"Point"}
}