{
  "type": "Feature",
  "properties": {
    "iso:country":"AU",
    "sg:address":"228 Commercial St",
    "sg:city":"East Mt Gambier",
    "sg:classifiers":[
        {
            "category":"Cafe",
            "type":"Food & Drink"
        }
    ],
    "sg:phone":"+61 8 8724 7800",
    "sg:postcode":"5290",
    "sg:province":"SA",
    "wof:name":"Choices Cafe",
    "wof:placetype":"venue"
},
  "geometry": {"coordinates":[140.798828,-37.834362],"type":"Point"}
}