{
  "type": "Feature",
  "properties": {
    "addr:full":"572- 576 Hay St Perth WA 6000",
    "addr:housenumber":"576",
    "addr:postcode":"6000",
    "addr:street":"Hay St",
    "iso:country":"AU",
    "sg:address":"572- 576 Hay St",
    "sg:city":"Perth",
    "sg:classifiers":[
        {
            "category":"Fast Food",
            "type":"Food & Drink"
        }
    ],
    "sg:phone":"+61 8 9325 2451",
    "sg:postcode":"6000",
    "sg:province":"WA",
    "sg:tags":[
        "away",
        "take"
    ],
    "wof:name":"McDonald's Family Restaurants",
    "wof:placetype":"venue"
},
  "geometry": {"coordinates":[115.85542297400001,-31.9531669617],"type":"Point"}
}