{
  "type": "Feature",
  "properties": {
    "addr:full":"Byng St Orange NSW 2800",
    "addr:postcode":"2800",
    "addr:street":"Byng St",
    "iso:country":"AU",
    "sg:address":"Byng St",
    "sg:city":"Orange",
    "sg:classifiers":[
        {
            "category":"Autos & Motor Vehicles",
            "subcategory":"Auto Supplies",
            "type":"Retail Goods"
        }
    ],
    "sg:phone":"+61 2 6362 5880",
    "sg:postcode":"2800",
    "sg:province":"NSW",
    "sg:tags":[
        "tyre"
    ],
    "wof:name":"Kmart Tyre & Auto Service",
    "wof:placetype":"venue"
},
  "geometry": {"coordinates":[149.09547424300001,-33.2807884216],"type":"Point"}
}