{
  "type": "Feature",
  "properties": {
    "addr:full":"21 Rothon Drv Rochedale QLD 4123",
    "addr:housenumber":"21",
    "addr:postcode":"4123",
    "addr:street":"Rothon Drv",
    "iso:country":"AU",
    "sg:address":"21 Rothon Drv",
    "sg:city":"Rochedale",
    "sg:classifiers":[
        {
            "category":"Professional",
            "subcategory":"Engineering",
            "type":"Services"
        }
    ],
    "sg:phone":"+61 7 3219 0135",
    "sg:postcode":"4123",
    "sg:province":"QLD",
    "sg:tags":[
        "engineer"
    ],
    "wof:name":"Rom Maintenance Services",
    "wof:placetype":"venue"
},
  "geometry": {"coordinates":[153.11369323700001,-27.596452713],"type":"Point"}
}