{
  "type": "Feature",
  "properties": {
    "addr:full":"Channel Rd Dareton NSW 2717",
    "addr:postcode":"2717",
    "addr:street":"Channel Rd",
    "iso:country":"AU",
    "sg:address":"Channel Rd",
    "sg:city":"Dareton",
    "sg:classifiers":[
        {
            "category":"Farming",
            "subcategory":"Berry Farm",
            "type":"Manufacturing & Wholesale Goods"
        }
    ],
    "sg:phone":"+61 3 5027 4538",
    "sg:postcode":"2717",
    "sg:province":"NSW",
    "sg:tags":[
        "fruit",
        "grower"
    ],
    "wof:name":"Webley J",
    "wof:placetype":"venue"
},
  "geometry": {"coordinates":[142.087432861,-34.0725746155],"type":"Point"}
}