{
  "type": "Feature",
  "properties": {
    "iso:country":"AU",
    "sg:address":"12 Antimony St",
    "sg:city":"Carole Park",
    "sg:classifiers":[
        {
            "category":"Manufacturing",
            "subcategory":"Metals",
            "type":"Manufacturing & Wholesale Goods"
        }
    ],
    "sg:phone":"+61 7 3271 6122",
    "sg:postcode":"4300",
    "sg:province":"QLD",
    "sg:tags":[
        "sheet",
        "worker"
    ],
    "wof:name":"Allmet Sheetmetal & Fabrication Pty Ltd",
    "wof:placetype":"venue"
},
  "geometry": {"coordinates":[152.930740356,-27.6135940552],"type":"Point"}
}