{
  "type": "Feature",
  "properties": {
    "addr:full":"291 Kenmore Rd Fig Tree Pocket QLD 4069",
    "addr:housenumber":"291",
    "addr:postcode":"4069",
    "addr:street":"Kenmore Rd",
    "iso:country":"AU",
    "sg:address":"291 Kenmore Rd",
    "sg:city":"Fig Tree Pocket",
    "sg:classifiers":[
        {
            "category":"Health Services",
            "subcategory":"Health Practitioner",
            "type":"Services"
        }
    ],
    "sg:phone":"+61 7 3878 7807",
    "sg:postcode":"4069",
    "sg:province":"QLD",
    "sg:tags":[
        "naturopath"
    ],
    "wof:name":"Bryson Jayne",
    "wof:placetype":"venue"
},
  "geometry": {"coordinates":[152.95359802199999,-27.5259113312],"type":"Point"}
}