{
  "type": "Feature",
  "properties": {
    "addr:full":"217 Buckley St Essendon VIC 3040",
    "addr:housenumber":"217",
    "addr:postcode":"3040",
    "addr:street":"Buckley St",
    "iso:country":"AU",
    "sg:address":"217 Buckley St",
    "sg:city":"Essendon",
    "sg:classifiers":[
        {
            "category":"Home & Garden",
            "subcategory":"Carpets & Floor Coverings",
            "type":"Retail Goods"
        }
    ],
    "sg:phone":"+61 3 9337 9973",
    "sg:postcode":"3040",
    "sg:province":"VIC",
    "sg:tags":[
        "tile",
        "wall"
    ],
    "wof:name":"Pure Design Marble & Granite Pty Ltd",
    "wof:placetype":"venue"
},
  "geometry": {"coordinates":[144.90863037099999,-37.7559547424],"type":"Point"}
}