{
  "type": "Feature",
  "properties": {
    "iso:country":"AU",
    "sg:address":"PO Box 3038",
    "sg:city":"Bassendean DC",
    "sg:classifiers":[
        {
            "category":"Organizations",
            "subcategory":"Membership Organization",
            "type":"Services"
        }
    ],
    "sg:phone":"+61 407 302 200",
    "sg:postcode":"6942",
    "sg:province":"WA",
    "sg:tags":[
        "club",
        "car"
    ],
    "wof:name":"GTR Torana XU1 Car Club Inc",
    "wof:placetype":"venue"
},
  "geometry": {"coordinates":[115.922943115,-31.9122695923],"type":"Point"}
}