{
  "type": "Feature",
  "properties": {
    "addr:full":"15 Bellevue St Surry Hills NSW 2010",
    "addr:housenumber":"15",
    "addr:postcode":"2010",
    "addr:street":"Bellevue St",
    "iso:country":"AU",
    "sg:address":"15 Bellevue St",
    "sg:city":"Surry Hills",
    "sg:classifiers":[
        {
            "category":"Personal",
            "subcategory":"Adult",
            "type":"Services"
        }
    ],
    "sg:phone":"+61 2 9212 4410",
    "sg:postcode":"2010",
    "sg:province":"NSW",
    "sg:tags":[
        "vic",
        "except",
        "state",
        "escort",
        "social",
        "qld"
    ],
    "wof:name":"Lovely",
    "wof:placetype":"venue"
},
  "geometry": {"coordinates":[151.21145629899999,-33.883644104],"type":"Point"}
}