{
  "type": "Feature",
  "properties": {
    "iso:country":"AU",
    "sg:address":"Cnr Lodge & Roseleigh Rds",
    "sg:city":"Wooloowin",
    "sg:classifiers":[
        {
            "category":"Personal",
            "subcategory":"Beauty Salon",
            "type":"Services"
        }
    ],
    "sg:phone":"+61 7 3857 2940",
    "sg:postcode":"4030",
    "sg:province":"QLD",
    "sg:tags":[
        "hairdresser"
    ],
    "wof:name":"Mecca Hair Face Body",
    "wof:placetype":"venue"
},
  "geometry": {"coordinates":[153.04418899999999,-27.41328],"type":"Point"}
}