{
  "type": "Feature",
  "properties": {
    "addr:full":"1214 High St Armadale VIC 3143",
    "addr:housenumber":"1214",
    "addr:postcode":"3143",
    "addr:street":"High St",
    "iso:country":"AU",
    "sg:address":"1214 High St",
    "sg:city":"Armadale",
    "sg:classifiers":[
        {
            "category":"Arts & Performance",
            "subcategory":"Art Gallery",
            "type":"Entertainment"
        }
    ],
    "sg:phone":"+61 3 9500 8511",
    "sg:postcode":"3143",
    "sg:province":"VIC",
    "wof:name":"Metro 5 Gallery",
    "wof:placetype":"venue"
},
  "geometry": {"coordinates":[145.02752685600001,-37.8564987183],"type":"Point"}
}