{
  "type": "Feature",
  "properties": {
    "iso:country":"AU",
    "sg:address":"Cnr Victoria & Lyons Rds",
    "sg:city":"Drummoyne",
    "sg:classifiers":[
        {
            "category":"Real Estate",
            "subcategory":"Real Estate Agent",
            "type":"Services"
        }
    ],
    "sg:phone":"+61 2 9719 8288",
    "sg:postcode":"2047",
    "sg:province":"NSW",
    "wof:name":"Warwick Williams Real Estate",
    "wof:placetype":"venue"
},
  "geometry": {"coordinates":[151.15527299999999,-33.851799],"type":"Point"}
}