{
  "type": "Feature",
  "properties": {
    "iso:country":"AU",
    "sg:address":"36 Nolan Drv",
    "sg:city":"Tura Beach",
    "sg:classifiers":[
        {
            "category":"Real Estate",
            "subcategory":"Surveying",
            "type":"Services"
        }
    ],
    "sg:phone":"+61 2 6495 9242",
    "sg:postcode":"2548",
    "sg:province":"NSW",
    "sg:tags":[
        "surveyor",
        "land"
    ],
    "wof:name":"More & Ryan Surveys",
    "wof:placetype":"venue"
},
  "geometry": {"coordinates":[149.91989135700001,-36.8715324402],"type":"Point"}
}