{
  "type": "Feature",
  "properties": {
    "addr:full":"56 Cabbage Tree La Fairy Meadow NSW 2519",
    "addr:housenumber":"56",
    "addr:postcode":"2519",
    "addr:street":"Cabbage Tree La",
    "iso:country":"AU",
    "sg:address":"56 Cabbage Tree La",
    "sg:city":"Fairy Meadow",
    "sg:classifiers":[
        {
            "category":"Farming",
            "subcategory":"Fish & Marine Products",
            "type":"Manufacturing & Wholesale Goods"
        }
    ],
    "sg:phone":"+61 2 4283 1573",
    "sg:postcode":"2519",
    "sg:province":"NSW",
    "sg:tags":[
        "fisherman"
    ],
    "wof:name":"Musumeci A",
    "wof:placetype":"venue"
},
  "geometry": {"coordinates":[150.88679500000001,-34.396671],"type":"Point"}
}