{
  "type": "Feature",
  "properties": {
    "addr:full":"Unit 14 Level 2, 16 Metroplex Ave Murarrie QLD 4172",
    "addr:housenumber":"16",
    "addr:postcode":"4172",
    "addr:street":"Metroplex Ave",
    "iso:country":"AU",
    "sg:address":"Unit 14 Level 2, 16 Metroplex Ave",
    "sg:city":"Murarrie",
    "sg:classifiers":[
        {
            "category":"Transit Center",
            "subcategory":"Freight",
            "type":"Transportation"
        }
    ],
    "sg:phone":"+61 7 3909 4666",
    "sg:postcode":"4172",
    "sg:province":"QLD",
    "sg:tags":[
        "agent",
        "shipping"
    ],
    "wof:name":"Mediterranean Shipping Co (Aust) Pty Ltd",
    "wof:placetype":"venue"
},
  "geometry": {"coordinates":[153.09918212900001,-27.4549160004],"type":"Point"}
}