{
  "type": "Feature",
  "properties": {
    "iso:country":"AU",
    "sg:address":"Reef St",
    "sg:city":"Gympie",
    "sg:classifiers":[
        {
            "category":"Real Estate",
            "subcategory":"Real Estate Operator",
            "type":"Services"
        }
    ],
    "sg:phone":"+61 7 5453 7233",
    "sg:postcode":"4570",
    "sg:province":"QLD",
    "sg:tags":[
        "concrete",
        "pumping"
    ],
    "wof:name":"Cooloola Concrete Pumping",
    "wof:placetype":"venue"
},
  "geometry": {"coordinates":[152.657440186,-26.1879291534],"type":"Point"}
}