{
  "type": "Feature",
  "properties": {
    "addr:full":"19 Bligh Drv Boambee NSW 2450",
    "addr:housenumber":"19",
    "addr:postcode":"2450",
    "addr:street":"Bligh Drv",
    "iso:country":"AU",
    "sg:address":"19 Bligh Drv",
    "sg:city":"Boambee",
    "sg:classifiers":[
        {
            "category":"Social Services",
            "subcategory":"Retirement Home",
            "type":"Services"
        }
    ],
    "sg:phone":"+61 2 6653 1488",
    "sg:postcode":"2450",
    "sg:province":"NSW",
    "sg:tags":[
        "environmental",
        "consultant",
        "pollution"
    ],
    "wof:name":"Boambee Forestry Services Pty Ltd",
    "wof:placetype":"venue"
},
  "geometry": {"coordinates":[153.07002299999999,-30.334261],"type":"Point"}
}