{
  "type": "Feature",
  "properties": {
    "addr:full":"48 Gaffney St Coburg VIC 3058",
    "addr:housenumber":"48",
    "addr:postcode":"3058",
    "addr:street":"Gaffney St",
    "iso:country":"AU",
    "sg:address":"48 Gaffney St",
    "sg:city":"Coburg",
    "sg:classifiers":[
        {
            "category":"Retail",
            "subcategory":"Repair Shop",
            "type":"Services"
        }
    ],
    "sg:phone":"+61 411 354 355",
    "sg:postcode":"3058",
    "sg:province":"VIC",
    "sg:tags":[
        "machine",
        "repairs",
        "part",
        "dryer",
        "washing"
    ],
    "wof:name":"J R Appliance Service",
    "wof:placetype":"venue"
},
  "geometry": {"coordinates":[144.96141052199999,-37.7334709167],"type":"Point"}
}