{
  "type": "Feature",
  "properties": {
    "addr:full":"174 Ward St North Adelaide SA 5006",
    "addr:housenumber":"174",
    "addr:postcode":"5006",
    "addr:street":"Ward St",
    "iso:country":"AU",
    "sg:address":"174 Ward St",
    "sg:city":"North Adelaide",
    "sg:classifiers":[
        {
            "category":"Health Services",
            "subcategory":"Doctor",
            "type":"Services"
        }
    ],
    "sg:phone":"+61 8 8239 0115",
    "sg:postcode":"5006",
    "sg:province":"SA",
    "sg:tags":[
        "medical",
        "practitioner"
    ],
    "wof:name":"James Katsaros Plastic and Cosmetic Surgery",
    "wof:placetype":"venue"
},
  "geometry": {"coordinates":[138.594802856,-34.9089775085],"type":"Point"}
}