{
  "type": "Feature",
  "properties": {
    "addr:full":"Shop 97/98 Tea Tree Plaza Modbury SA 5092",
    "addr:housenumber":"shop 97 / 98",
    "addr:postcode":"5092",
    "addr:street":"Tea Tree Plaza",
    "iso:country":"AU",
    "sg:address":"Shop 97/98 Tea Tree Plaza",
    "sg:city":"Modbury",
    "sg:classifiers":[
        {
            "category":"Shopping",
            "subcategory":"Antiques",
            "type":"Retail Goods"
        }
    ],
    "sg:phone":"+61 8 8263 1400",
    "sg:postcode":"5092",
    "sg:province":"SA",
    "sg:tags":[
        "collectable",
        "memorabilia"
    ],
    "wof:name":"Superstars & Legends",
    "wof:placetype":"venue"
},
  "geometry": {"coordinates":[138.69236755399999,-34.8331794739],"type":"Point"}
}