{
  "type": "Feature",
  "properties": {
    "addr:full":"Hopkins Rd Eden NSW 2551",
    "addr:postcode":"2551",
    "addr:street":"Hopkins Rd",
    "iso:country":"AU",
    "sg:address":"Hopkins Rd",
    "sg:city":"Eden",
    "sg:classifiers":[
        {
            "category":"Social Services",
            "subcategory":"Adult Care",
            "type":"Services"
        }
    ],
    "sg:phone":"+61 2 6496 3533",
    "sg:postcode":"2551",
    "sg:province":"NSW",
    "sg:tags":[
        "towing"
    ],
    "wof:name":"Griffin -R W & L A Panel Beater",
    "wof:placetype":"venue"
},
  "geometry": {"coordinates":[149.89678955100001,-37.0425376892],"type":"Point"}
}