{
  "type": "Feature",
  "properties": {
    "addr:full":"16 Burns Rd Heathcote NSW 2233",
    "addr:housenumber":"16",
    "addr:postcode":"2233",
    "addr:street":"Burns Rd",
    "iso:country":"AU",
    "sg:address":"16 Burns Rd",
    "sg:city":"Heathcote",
    "sg:classifiers":[
        {
            "category":"Sports & Exercise",
            "subcategory":"Climbing Gym",
            "type":"Entertainment"
        }
    ],
    "sg:phone":"+61 2 9520 8955",
    "sg:postcode":"2233",
    "sg:province":"NSW",
    "sg:tags":[
        "repetition",
        "engineer"
    ],
    "wof:name":"Heathcote Engineering",
    "wof:placetype":"venue"
},
  "geometry": {"coordinates":[150.99632263199999,-34.0973129272],"type":"Point"}
}