{
  "type": "Feature",
  "properties": {
    "addr:full":"Shop 114 Cockle Bay Sussex St Darling Harbour NSW 2000",
    "addr:housenumber":"114",
    "addr:postcode":"2000",
    "addr:street":"Cockle Bay Sussex St",
    "iso:country":"AU",
    "sg:address":"Shop 114 Cockle Bay Sussex St",
    "sg:city":"Darling Harbour",
    "sg:classifiers":[
        {
            "category":"Restaurant",
            "type":"Food & Drink"
        }
    ],
    "sg:phone":"+61 2 9283 3434",
    "sg:postcode":"2000",
    "sg:province":"NSW",
    "wof:name":"Baia San Marco Cafe",
    "wof:placetype":"venue"
},
  "geometry": {"coordinates":[151.20387268100001,-33.8710479736],"type":"Point"}
}