{
  "type": "Feature",
  "properties": {
    "addr:full":"161 Aumuller St Cairns QLD 4870",
    "addr:housenumber":"161",
    "addr:postcode":"4870",
    "addr:street":"Aumuller St",
    "iso:country":"AU",
    "sg:address":"161 Aumuller St",
    "sg:city":"Cairns",
    "sg:classifiers":[
        {
            "category":"Professional",
            "subcategory":"Management & Consulting",
            "type":"Services"
        }
    ],
    "sg:phone":"+61 7 4041 3232",
    "sg:postcode":"4870",
    "sg:province":"QLD",
    "sg:tags":[
        "consultant",
        "educational"
    ],
    "wof:name":"Bill Spooners Coaching Academy",
    "wof:placetype":"venue"
},
  "geometry": {"coordinates":[145.761032105,-16.9336776733],"type":"Point"}
}