{
  "type": "Feature",
  "properties": {
    "iso:country":"AU",
    "sg:address":"Unit 1/ 100 Barwon Tce",
    "sg:city":"Geelong South",
    "sg:classifiers":[
        {
            "category":"Retail",
            "subcategory":"Auto Repair",
            "type":"Services"
        }
    ],
    "sg:phone":"+61 3 5222 7899",
    "sg:postcode":"3220",
    "sg:province":"VIC",
    "sg:tags":[
        "wheel",
        "balancing",
        "alignment"
    ],
    "wof:name":"McCallum Steering & Suspension",
    "wof:placetype":"venue"
},
  "geometry": {"coordinates":[144.368057,-38.171978],"type":"Point"}
}