{
  "type": "Feature",
  "properties": {
    "addr:full":"U32/ 1a Ashley La Westmead NSW 2145",
    "addr:housenumber":"1a",
    "addr:postcode":"2145",
    "addr:street":"/;Ashley La",
    "iso:country":"AU",
    "sg:address":"U32/ 1a Ashley La",
    "sg:city":"Westmead",
    "sg:classifiers":[
        {
            "category":"Health Services",
            "subcategory":"Doctor",
            "type":"Services"
        }
    ],
    "sg:phone":"+61 2 9635 9624",
    "sg:postcode":"2145",
    "sg:province":"NSW",
    "sg:tags":[
        "medical",
        "practitioner"
    ],
    "wof:name":"Felix Chan Dr",
    "wof:placetype":"venue"
},
  "geometry": {"coordinates":[150.98919677699999,-33.8064880371],"type":"Point"}
}