{
  "type": "Feature",
  "properties": {
    "addr:full":"Ten Mile Rd Bundaberg QLD 4670",
    "addr:postcode":"4670",
    "addr:street":"Ten Mile Rd",
    "iso:country":"AU",
    "sg:address":"Ten Mile Rd",
    "sg:city":"Bundaberg",
    "sg:classifiers":[
        {
            "category":"Professional",
            "subcategory":"Art Services",
            "type":"Services"
        }
    ],
    "sg:phone":"+61 7 4159 9192",
    "sg:postcode":"4670",
    "sg:province":"QLD",
    "sg:tags":[
        "decorator",
        "painter"
    ],
    "wof:name":"Martin Walsh",
    "wof:placetype":"venue"
},
  "geometry": {"coordinates":[152.27262878400001,-24.8533039093],"type":"Point"}
}