{
  "type": "Feature",
  "properties": {
    "iso:country":"AU",
    "sg:address":"Shop 5/ 1 Pyrmont Bridge Rd",
    "sg:city":"Pyrmont",
    "sg:classifiers":[
        {
            "category":"Real Estate",
            "subcategory":"Real Estate Agent",
            "type":"Services"
        }
    ],
    "sg:phone":"+61 2 9660 8288",
    "sg:postcode":"2009",
    "sg:province":"NSW",
    "wof:name":"PRDnationwide Pyrmont",
    "wof:placetype":"venue"
},
  "geometry": {"coordinates":[151.19731140100001,-33.8700752258],"type":"Point"}
}