{
  "type": "Feature",
  "properties": {
    "addr:full":"Unit 3, 1 Plasser Crs St Marys NSW 2760",
    "addr:housenumber":"1",
    "addr:postcode":"2760",
    "addr:street":"Plasser Crs",
    "iso:country":"AU",
    "sg:address":"Unit 3, 1 Plasser Crs",
    "sg:city":"St Marys",
    "sg:classifiers":[
        {
            "category":"Manufacturing",
            "subcategory":"Tools & Machinery",
            "type":"Manufacturing & Wholesale Goods"
        }
    ],
    "sg:phone":"+61 2 9833 1678",
    "sg:postcode":"2760",
    "sg:province":"NSW",
    "sg:tags":[
        "toolmaker"
    ],
    "wof:name":"Actif Toolcraft Pty Ltd",
    "wof:placetype":"venue"
},
  "geometry": {"coordinates":[150.77151489299999,-33.7472496033],"type":"Point"}
}