{
  "type": "Feature",
  "properties": {
    "iso:country":"AU",
    "sg:address":"Cnr Read & Gnangara Rds",
    "sg:city":"Waikiki",
    "sg:classifiers":[
        {
            "category":"Food & Beverages",
            "subcategory":"Bakery",
            "type":"Retail Goods"
        }
    ],
    "sg:phone":"+61 8 9592 9012",
    "sg:postcode":"6169",
    "sg:province":"WA",
    "sg:tags":[
        "baker"
    ],
    "wof:name":"Brumby's WA & NT",
    "wof:placetype":"venue"
},
  "geometry": {"coordinates":[115.75295300000001,-32.315533],"type":"Point"}
}