{
  "type": "Feature",
  "properties": {
    "iso:country":"AU",
    "sg:address":"Shop 9, 29 Stockton St",
    "sg:city":"Nelson Bay",
    "sg:classifiers":[
        {
            "category":"Fast Food",
            "type":"Food & Drink"
        }
    ],
    "sg:phone":"+61 2 4984 9599",
    "sg:postcode":"2315",
    "sg:province":"NSW",
    "sg:tags":[
        "away",
        "take"
    ],
    "wof:name":"Eagle Boys Pizza - Nelson Bay",
    "wof:placetype":"venue"
},
  "geometry": {"coordinates":[152.14343299999999,-32.722931],"type":"Point"}
}