{
  "type": "Feature",
  "properties": {
    "addr:full":"24 Donwiller Crs Theodore ACT 2905",
    "addr:housenumber":"24",
    "addr:postcode":"2905",
    "addr:street":"Donwiller Crs",
    "iso:country":"AU",
    "sg:address":"24 Donwiller Crs",
    "sg:city":"Theodore",
    "sg:classifiers":[
        {
            "category":"Building & Trades",
            "subcategory":"Landscaping Services",
            "type":"Services"
        }
    ],
    "sg:phone":"+61 2 6292 0819",
    "sg:postcode":"2905",
    "sg:province":"ACT",
    "sg:tags":[
        "inspection"
    ],
    "wof:name":"Totally Trusted Building Reports",
    "wof:placetype":"venue"
},
  "geometry": {"coordinates":[149.124557495,-35.4470710754],"type":"Point"}
}