{
  "type": "Feature",
  "properties": {
    "addr:full":"Lot 6, Northgate Centre Princes Hwy Fairy Meadow NSW 2519",
    "addr:postcode":"2519",
    "addr:street":"Princes Hwy",
    "iso:country":"AU",
    "sg:address":"Lot 6, Northgate Centre Princes Hwy",
    "sg:city":"Fairy Meadow",
    "sg:classifiers":[
        {
            "category":"Communications",
            "subcategory":"Film & Video Production",
            "type":"Services"
        }
    ],
    "sg:phone":"+61 2 4226 3911",
    "sg:postcode":"2519",
    "sg:province":"NSW",
    "sg:tags":[
        "dvd",
        "library"
    ],
    "wof:name":"Blockbuster",
    "wof:placetype":"venue"
},
  "geometry": {"coordinates":[150.89335600000001,-34.391663],"type":"Point"}
}