{
  "type": "Feature",
  "properties": {
    "addr:full":"94 Commissioner St Cooma NSW 2630",
    "addr:housenumber":"94",
    "addr:postcode":"2630",
    "addr:street":"Commissioner St",
    "iso:country":"AU",
    "sg:address":"94 Commissioner St",
    "sg:city":"Cooma",
    "sg:classifiers":[
        {
            "category":"Travel",
            "subcategory":"Hotels & Motels",
            "type":"Entertainment"
        }
    ],
    "sg:phone":"+61 2 6452 2011",
    "sg:postcode":"2630",
    "sg:province":"NSW",
    "sg:tags":[
        "accommodation"
    ],
    "wof:name":"Dodds Hotel",
    "wof:placetype":"venue"
},
  "geometry": {"coordinates":[149.126663208,-36.236125946],"type":"Point"}
}