{
  "type": "Feature",
  "properties": {
    "iso:country":"AU",
    "sg:address":"16 Main St",
    "sg:city":"Huonville",
    "sg:classifiers":[
        {
            "category":"Health Services",
            "subcategory":"Optometrist",
            "type":"Services"
        }
    ],
    "sg:phone":"+61 3 6264 2095",
    "sg:postcode":"7109",
    "sg:province":"TAS",
    "wof:name":"Harrison Byron",
    "wof:placetype":"venue"
},
  "geometry": {"coordinates":[147.04818725600001,-43.0315513611],"type":"Point"}
}