{
  "type": "Feature",
  "properties": {
    "addr:full":"Francis St Tatura VIC 3616",
    "addr:postcode":"3616",
    "addr:street":"Francis St",
    "iso:country":"AU",
    "sg:address":"Francis St",
    "sg:city":"Tatura",
    "sg:classifiers":[
        {
            "category":"Home & Garden",
            "subcategory":"Building Materials",
            "type":"Retail Goods"
        }
    ],
    "sg:phone":"+61 3 5824 1544",
    "sg:postcode":"3616",
    "sg:province":"VIC",
    "sg:tags":[
        "supply"
    ],
    "wof:name":"Viberts Home Timber & Hardware",
    "wof:placetype":"venue"
},
  "geometry": {"coordinates":[145.22781372099999,-36.4406738281],"type":"Point"}
}