{
  "type": "Feature",
  "properties": {
    "iso:country":"AU",
    "sg:address":"101 Elphinstone St",
    "sg:city":"Rockhampton",
    "sg:classifiers":[
        {
            "category":"Professional",
            "subcategory":"Computer Services",
            "type":"Services"
        }
    ],
    "sg:phone":"+61 414 556 930",
    "sg:postcode":"4700",
    "sg:province":"QLD",
    "sg:tags":[
        "repairs",
        "upgrade",
        "equipment"
    ],
    "wof:name":"Bob Schoevaart's Computer Service",
    "wof:placetype":"venue"
},
  "geometry": {"coordinates":[150.52781677199999,-23.3633308411],"type":"Point"}
}