{
  "type": "Feature",
  "properties": {
    "iso:country":"AU",
    "sg:address":"7 Todea Crt",
    "sg:city":"Duncraig",
    "sg:classifiers":[
        {
            "category":"Banks & Credit Unions",
            "subcategory":"Investment Brokerage",
            "type":"Services"
        }
    ],
    "sg:phone":"+61 8 9448 3332",
    "sg:postcode":"6023",
    "sg:province":"WA",
    "sg:tags":[
        "care",
        "day",
        "family",
        "child"
    ],
    "wof:name":"Maryann Bird Family Day Care",
    "wof:placetype":"venue"
},
  "geometry": {"coordinates":[115.783241272,-31.8436794281],"type":"Point"}
}