{
  "type": "Feature",
  "properties": {
    "iso:country":"AU",
    "sg:address":"17 Hulbert St",
    "sg:city":"South Fremantle",
    "sg:classifiers":[
        {
            "category":"Professional",
            "subcategory":"Secretarial Services",
            "type":"Services"
        }
    ],
    "sg:phone":"+61 8 9336 5780",
    "sg:postcode":"6162",
    "sg:province":"WA",
    "sg:tags":[
        "typing"
    ],
    "wof:name":"A Classic Secretarial Service",
    "wof:placetype":"venue"
},
  "geometry": {"coordinates":[115.755371,-32.075062],"type":"Point"}
}