{
  "type": "Feature",
  "properties": {
    "addr:full":"Unit 8, 151 Hartley Rd Smeaton Grange NSW 2567",
    "addr:housenumber":"151",
    "addr:postcode":"2567",
    "addr:street":"Hartley Rd",
    "iso:country":"AU",
    "sg:address":"Unit 8, 151 Hartley Rd",
    "sg:city":"Smeaton Grange",
    "sg:classifiers":[
        {
            "category":"Retail",
            "subcategory":"Repair Shop",
            "type":"Services"
        }
    ],
    "sg:phone":"+61 2 4648 2052",
    "sg:postcode":"2567",
    "sg:province":"NSW",
    "sg:tags":[
        "upholsterer"
    ],
    "wof:name":"Eberhart Upholstery",
    "wof:placetype":"venue"
},
  "geometry": {"coordinates":[150.75738525400001,-34.0383529663],"type":"Point"}
}