{
  "type": "Feature",
  "properties": {
    "addr:full":"7 Webb Drv Wonthaggi VIC 3995",
    "addr:housenumber":"7",
    "addr:postcode":"3995",
    "addr:street":"Webb Drv",
    "iso:country":"AU",
    "sg:address":"7 Webb Drv",
    "sg:city":"Wonthaggi",
    "sg:classifiers":[
        {
            "category":"Building & Trades",
            "subcategory":"Construction",
            "type":"Services"
        }
    ],
    "sg:phone":"+61 3 5672 3431",
    "sg:postcode":"3995",
    "sg:province":"VIC",
    "sg:tags":[
        "contractor"
    ],
    "wof:name":"DA & RL Thomson",
    "wof:placetype":"venue"
},
  "geometry": {"coordinates":[145.602814,-38.605141],"type":"Point"}
}