{
  "type": "Feature",
  "properties": {
    "addr:full":"150 Greville St Prahran VIC 3181",
    "addr:housenumber":"150",
    "addr:postcode":"3181",
    "addr:street":"Greville St",
    "iso:country":"AU",
    "sg:address":"150 Greville St",
    "sg:city":"Prahran",
    "sg:classifiers":[
        {
            "category":"Personal",
            "subcategory":"Beauty Salon",
            "type":"Services"
        }
    ],
    "sg:phone":"+61 3 9529 7818",
    "sg:postcode":"3181",
    "sg:province":"VIC",
    "sg:tags":[
        "hairdresser"
    ],
    "wof:name":"Lou Salon",
    "wof:placetype":"venue"
},
  "geometry": {"coordinates":[144.99171447800001,-37.8494338989],"type":"Point"}
}