{
  "type": "Feature",
  "properties": {
    "addr:full":"Lvl1/ 120 Greenhill Rd Unley SA 5061",
    "addr:housenumber":"120",
    "addr:postcode":"5061",
    "addr:street":"Greenhill Rd",
    "iso:country":"AU",
    "sg:address":"Lvl1/ 120 Greenhill Rd",
    "sg:city":"Unley",
    "sg:classifiers":[
        {
            "category":"Banks & Credit Unions",
            "subcategory":"Bank",
            "type":"Services"
        }
    ],
    "sg:phone":"+61 8 8373 2229",
    "sg:postcode":"5061",
    "sg:province":"SA",
    "sg:tags":[
        "broker",
        "mortgage"
    ],
    "wof:name":"Gryphon Financial",
    "wof:placetype":"venue"
},
  "geometry": {"coordinates":[138.60307312,-34.9413070679],"type":"Point"}
}