{
  "type": "Feature",
  "properties": {
    "addr:full":"2 Stock Rd Kojonup WA 6395",
    "addr:housenumber":"2",
    "addr:postcode":"6395",
    "addr:street":"Stock Rd",
    "iso:country":"AU",
    "sg:address":"2 Stock Rd",
    "sg:city":"Kojonup",
    "sg:classifiers":[
        {
            "category":"Health Services",
            "subcategory":"Dentist",
            "type":"Services"
        }
    ],
    "sg:phone":"+61 8 9831 1029",
    "sg:postcode":"6395",
    "sg:province":"WA",
    "wof:name":"Walsh J F (Barry)",
    "wof:placetype":"venue"
},
  "geometry": {"coordinates":[117.163497925,-33.8445587158],"type":"Point"}
}