{
  "type": "Feature",
  "properties": {
    "addr:full":"50A Kepler St Warrnambool VIC 3280",
    "addr:housenumber":"50a",
    "addr:postcode":"3280",
    "addr:street":"Kepler St",
    "iso:country":"AU",
    "sg:address":"50A Kepler St",
    "sg:city":"Warrnambool",
    "sg:classifiers":[
        {
            "category":"Shopping",
            "subcategory":"Party Supplies",
            "type":"Retail Goods"
        }
    ],
    "sg:phone":"+61 3 5561 7488",
    "sg:postcode":"3280",
    "sg:province":"VIC",
    "wof:name":"Top Notch Balloons",
    "wof:placetype":"venue"
},
  "geometry": {"coordinates":[142.48106384299999,-38.3833618164],"type":"Point"}
}