{
  "type": "Feature",
  "properties": {
    "addr:full":"108 Albert St Brisbane City QLD 4000",
    "addr:housenumber":"108",
    "addr:postcode":"4000",
    "addr:street":"Albert St",
    "iso:country":"AU",
    "sg:address":"108 Albert St",
    "sg:city":"Brisbane City",
    "sg:classifiers":[
        {
            "category":"Health Services",
            "subcategory":"Doctor",
            "type":"Services"
        }
    ],
    "sg:phone":"+61 7 3012 9500",
    "sg:postcode":"4000",
    "sg:province":"QLD",
    "sg:tags":[
        "medical",
        "practitioner"
    ],
    "wof:name":"City Care Doctors Festival Towers",
    "wof:placetype":"venue"
},
  "geometry": {"coordinates":[153.02719116200001,-27.4718017578],"type":"Point"}
}