{
  "type": "Feature",
  "properties": {
    "addr:full":"129 Edgars Rd Thomastown VIC 3074",
    "addr:housenumber":"129",
    "addr:postcode":"3074",
    "addr:street":"Edgars Rd",
    "iso:country":"AU",
    "sg:address":"129 Edgars Rd",
    "sg:city":"Thomastown",
    "sg:classifiers":[
        {
            "category":"Social Services",
            "subcategory":"Child Care",
            "type":"Services"
        }
    ],
    "sg:phone":"+61 3 9465 8624",
    "sg:postcode":"3074",
    "sg:province":"VIC",
    "wof:name":"Thomastown Child Care Centre",
    "wof:placetype":"venue"
},
  "geometry": {"coordinates":[144.998703003,-37.6818962097],"type":"Point"}
}