{
  "type": "Feature",
  "properties": {
    "addr:full":"167 Elphin Rd Launceston TAS 7250",
    "addr:housenumber":"167",
    "addr:postcode":"7250",
    "addr:street":"Elphin Rd",
    "iso:country":"AU",
    "sg:address":"167 Elphin Rd",
    "sg:city":"Launceston",
    "sg:classifiers":[
        {
            "category":"Wholesale",
            "subcategory":"Drugs",
            "type":"Manufacturing & Wholesale Goods"
        }
    ],
    "sg:phone":"+61 3 6331 5979",
    "sg:postcode":"7250",
    "sg:province":"TAS",
    "sg:tags":[
        "wholesaler",
        "pharmaceutical",
        "product",
        "mfrs"
    ],
    "wof:name":"Lasco Pharmaceuticals",
    "wof:placetype":"venue"
},
  "geometry": {"coordinates":[147.161056519,-41.4414215088],"type":"Point"}
}