{
  "type": "Feature",
  "properties": {
    "iso:country":"AU",
    "sg:address":"18 William St",
    "sg:city":"Condobolin",
    "sg:classifiers":[
        {
            "category":"Professional",
            "subcategory":"Computer Services",
            "type":"Services"
        }
    ],
    "sg:phone":"+61 2 6895 2311",
    "sg:postcode":"2877",
    "sg:province":"NSW",
    "sg:tags":[
        "repairs",
        "upgrade",
        "equipment"
    ],
    "wof:name":"CTC @ Condobolin (Community Technology Centre)",
    "wof:placetype":"venue"
},
  "geometry": {"coordinates":[147.146835,-33.090111],"type":"Point"}
}