{
  "type": "Feature",
  "properties": {
    "iso:country":"AU",
    "sg:address":"PO Box 3125",
    "sg:city":"South Yarra",
    "sg:classifiers":[
        {
            "category":"Industrial Area",
            "type":"Public Place"
        }
    ],
    "sg:phone":"+61 430 090 888",
    "sg:postcode":"3141",
    "sg:province":"VIC",
    "sg:tags":[
        "floor"
    ],
    "wof:name":"National Waterproofing & Industrial Flooring P/L",
    "wof:placetype":"venue"
},
  "geometry": {"coordinates":[144.99111938499999,-37.8378791809],"type":"Point"}
}