{
  "type": "Feature",
  "properties": {
    "addr:full":"Unit 7, 16 Forge St Blacktown NSW 2148",
    "addr:housenumber":"16",
    "addr:postcode":"2148",
    "addr:street":"Forge St",
    "iso:country":"AU",
    "sg:address":"Unit 7, 16 Forge St",
    "sg:city":"Blacktown",
    "sg:classifiers":[
        {
            "category":"Retail",
            "subcategory":"Auto Repair",
            "type":"Services"
        }
    ],
    "sg:phone":"+61 2 9831 5888",
    "sg:postcode":"2148",
    "sg:province":"NSW",
    "sg:tags":[
        "beater",
        "painter",
        "panel"
    ],
    "wof:name":"Dent Blackmagic",
    "wof:placetype":"venue"
},
  "geometry": {"coordinates":[150.90960693400001,-33.7557563782],"type":"Point"}
}