{
  "type": "Feature",
  "properties": {
    "addr:full":"10 Scott St Westbrook QLD 4350",
    "addr:housenumber":"10",
    "addr:postcode":"4350",
    "addr:street":"Scott St",
    "iso:country":"AU",
    "sg:address":"10 Scott St",
    "sg:city":"Westbrook",
    "sg:classifiers":[
        {
            "category":"Building & Trades",
            "subcategory":"Construction",
            "type":"Services"
        }
    ],
    "sg:phone":"+61 413 059 557",
    "sg:postcode":"4350",
    "sg:province":"QLD",
    "sg:tags":[
        "concrete",
        "contractor"
    ],
    "wof:name":"Steger Concreting & Constructions",
    "wof:placetype":"venue"
},
  "geometry": {"coordinates":[151.974457,-27.566097],"type":"Point"}
}