{
  "type": "Feature",
  "properties": {
    "addr:full":"82 Victoria Ave Albert Park VIC 3206",
    "addr:housenumber":"82",
    "addr:postcode":"3206",
    "addr:street":"Victoria Ave",
    "iso:country":"AU",
    "sg:address":"82 Victoria Ave",
    "sg:city":"Albert Park",
    "sg:classifiers":[
        {
            "category":"Professional",
            "subcategory":"Art Services",
            "type":"Services"
        }
    ],
    "sg:phone":"+61 3 9686 3177",
    "sg:postcode":"3206",
    "sg:province":"VIC",
    "sg:tags":[
        "interior",
        "decorator"
    ],
    "wof:name":"Danielle Trippett",
    "wof:placetype":"venue"
},
  "geometry": {"coordinates":[144.95107999999999,-37.844093],"type":"Point"}
}