{
  "type": "Feature",
  "properties": {
    "iso:country":"AU",
    "sg:address":"Edith St",
    "sg:city":"Wynnum",
    "sg:classifiers":[
        {
            "category":"Health Services",
            "subcategory":"Health Practitioner",
            "type":"Services"
        }
    ],
    "sg:phone":"+61 7 3348 4358",
    "sg:postcode":"4178",
    "sg:province":"QLD",
    "sg:tags":[
        "reiki"
    ],
    "wof:name":"Judith Mason - Master Teacher",
    "wof:placetype":"venue"
},
  "geometry": {"coordinates":[153.17463684099999,-27.4440612793],"type":"Point"}
}