{
  "type": "Feature",
  "properties": {
    "addr:full":"124 Beach Rd Christies Beach SA 5165",
    "addr:housenumber":"124",
    "addr:postcode":"5165",
    "addr:street":"Beach Rd",
    "iso:country":"AU",
    "sg:address":"124 Beach Rd",
    "sg:city":"Christies Beach",
    "sg:classifiers":[
        {
            "category":"Food & Beverages",
            "subcategory":"Bakery",
            "type":"Retail Goods"
        }
    ],
    "sg:phone":"+61 8 8384 4510",
    "sg:postcode":"5165",
    "sg:province":"SA",
    "sg:tags":[
        "baker"
    ],
    "wof:name":"Brumby's Bakeries",
    "wof:placetype":"venue"
},
  "geometry": {"coordinates":[138.48402404800001,-35.1389045715],"type":"Point"}
}