{
  "type": "Feature",
  "properties": {
    "addr:full":"Shp 6/ 39- 41 Tamar St Ballina NSW 2478",
    "addr:housenumber":"/;41",
    "addr:postcode":"2478",
    "addr:street":"39;Tamar St",
    "iso:country":"AU",
    "sg:address":"Shp 6/ 39- 41 Tamar St",
    "sg:city":"Ballina",
    "sg:classifiers":[
        {
            "category":"Personal",
            "subcategory":"Beauty Salon",
            "type":"Services"
        }
    ],
    "sg:phone":"+61 2 6686 8486",
    "sg:postcode":"2478",
    "sg:province":"NSW",
    "wof:name":"Frangipani Beauty Spa",
    "wof:placetype":"venue"
},
  "geometry": {"coordinates":[153.56283569300001,-28.8701667786],"type":"Point"}
}