{
  "type": "Feature",
  "properties": {
    "addr:full":"5 Caribbean Drv Scoresby VIC 3179",
    "addr:housenumber":"5",
    "addr:postcode":"3179",
    "addr:street":"Caribbean Drv",
    "iso:country":"AU",
    "sg:address":"5 Caribbean Drv",
    "sg:city":"Scoresby",
    "sg:classifiers":[
        {
            "category":"Wholesale",
            "subcategory":"Stationery",
            "type":"Manufacturing & Wholesale Goods"
        }
    ],
    "sg:phone":"+61 3 9757 4500",
    "sg:postcode":"3179",
    "sg:province":"VIC",
    "sg:tags":[
        "mfrg"
    ],
    "wof:name":"Parker Pen",
    "wof:placetype":"venue"
},
  "geometry": {"coordinates":[145.22085571299999,-37.9022254944],"type":"Point"}
}