{
  "type": "Feature",
  "properties": {
    "iso:country":"AU",
    "sg:address":"94 James St",
    "sg:city":"Toowoomba",
    "sg:classifiers":[
        {
            "category":"Travel",
            "subcategory":"Hotels & Motels",
            "type":"Entertainment"
        }
    ],
    "sg:phone":"+61 7 4632 3099",
    "sg:postcode":"4350",
    "sg:province":"QLD",
    "sg:website":"http://www.countrygardensmotorinn.com.au",
    "wof:name":"Country Gardens Motor Inn",
    "wof:placetype":"venue"
},
  "geometry": {"coordinates":[151.963028,-27.57024],"type":"Point"}
}