{
  "type": "Feature",
  "properties": {
    "addr:full":"94 James St Toowoomba QLD 4350",
    "addr:housenumber":"94",
    "addr:postcode":"4350",
    "addr:street":"James St",
    "iso:country":"AU",
    "sg:address":"94 James St",
    "sg:city":"Toowoomba",
    "sg:classifiers":[
        {
            "category":"Travel",
            "subcategory":"Hotels & Motels",
            "type":"Entertainment"
        }
    ],
    "sg:phone":"+61 7 4632 3099",
    "sg:postcode":"4350",
    "sg:province":"QLD",
    "sg:website":"http://www.countrygardensmotorinn.com.au",
    "wof:name":"Country Gardens Motor Inn",
    "wof:placetype":"venue"
},
  "geometry": {"coordinates":[151.96302800000001,-27.57024],"type":"Point"}
}