{
  "type": "Feature",
  "properties": {
    "addr:full":"Shop 1 Goonellabah Village, Cnr Oliver Ave & Simeoni Drv Goonellabah NSW 2480",
    "addr:housenumber":"shop 1",
    "addr:postcode":"2480",
    "addr:street":"Village Cnr Oliver Ave & Simeoni Drv",
    "iso:country":"AU",
    "sg:address":"Shop 1 Goonellabah Village, Cnr Oliver Ave & Simeoni Drv",
    "sg:city":"Goonellabah",
    "sg:classifiers":[
        {
            "category":"Health Services",
            "subcategory":"Health Practitioner",
            "type":"Services"
        }
    ],
    "sg:phone":"+61 2 6624 2449",
    "sg:postcode":"2480",
    "sg:province":"NSW",
    "sg:tags":[
        "naturopath"
    ],
    "wof:name":"Goonellabah Pharmacy",
    "wof:placetype":"venue"
},
  "geometry": {"coordinates":[153.337615967,-28.8219947815],"type":"Point"}
}