{
  "type": "Feature",
  "properties": {
    "iso:country":"AU",
    "sg:address":"125 Swanston St",
    "sg:city":"Melbourne",
    "sg:classifiers":[
        {
            "category":"Manufacturing",
            "subcategory":"Jewelry",
            "type":"Manufacturing & Wholesale Goods"
        }
    ],
    "sg:phone":"+61 3 9654 1548",
    "sg:postcode":"3000",
    "sg:province":"VIC",
    "sg:tags":[
        "mfrg",
        "jeweller"
    ],
    "wof:name":"R & M Jewellers Pty Ltd",
    "wof:placetype":"venue"
},
  "geometry": {"coordinates":[144.966064453,-37.8147964478],"type":"Point"}
}