{
  "type": "Feature",
  "properties": {
    "addr:full":"17A Brook St Sunbury VIC 3429",
    "addr:housenumber":"17a",
    "addr:postcode":"3429",
    "addr:street":"Brook St",
    "iso:country":"AU",
    "sg:address":"17A Brook St",
    "sg:city":"Sunbury",
    "sg:classifiers":[
        {
            "category":"Food & Beverages",
            "subcategory":"Bakery",
            "type":"Retail Goods"
        }
    ],
    "sg:phone":"+61 3 9740 6844",
    "sg:postcode":"3429",
    "sg:province":"VIC",
    "sg:tags":[
        "cake",
        "shop",
        "pastry"
    ],
    "wof:name":"Ferguson Plarre Bakehouses Pty Ltd",
    "wof:placetype":"venue"
},
  "geometry": {"coordinates":[144.73005676299999,-37.5798835754],"type":"Point"}
}