{
  "type": "Feature",
  "properties": {
    "iso:country":"AU",
    "sg:address":"PO Box 807",
    "sg:city":"Robina Delivery Centre",
    "sg:classifiers":[
        {
            "category":"Building & Trades",
            "subcategory":"Plumbing",
            "type":"Services"
        }
    ],
    "sg:phone":"+61 412 140 488",
    "sg:postcode":"4226",
    "sg:province":"QLD",
    "sg:tags":[
        "plumber",
        "gasfitters"
    ],
    "wof:name":"A D S Plumbing",
    "wof:placetype":"venue"
},
  "geometry": {"coordinates":[153.39210510300001,-28.0869750977],"type":"Point"}
}