{
  "type": "Feature",
  "properties": {
    "addr:full":"511 Barkly St Footscray West VIC 3012",
    "addr:housenumber":"511",
    "addr:postcode":"3012",
    "addr:street":"Barkly St",
    "iso:country":"AU",
    "sg:address":"511 Barkly St",
    "sg:city":"Footscray West",
    "sg:classifiers":[
        {
            "category":"Food & Beverages",
            "subcategory":"Supermarket",
            "type":"Retail Goods"
        }
    ],
    "sg:phone":"+61 3 9687 2117",
    "sg:postcode":"3012",
    "sg:province":"VIC",
    "sg:tags":[
        "grocery",
        "store"
    ],
    "wof:name":"Sims Foodworks",
    "wof:placetype":"venue"
},
  "geometry": {"coordinates":[144.88023376500001,-37.7978286743],"type":"Point"}
}