{
  "type": "Feature",
  "properties": {
    "addr:full":"Lang St Beeac VIC 3251",
    "addr:postcode":"3251",
    "addr:street":"Lang St",
    "iso:country":"AU",
    "sg:address":"Lang St",
    "sg:city":"Beeac",
    "sg:classifiers":[
        {
            "category":"Social Services",
            "subcategory":"Child Care",
            "type":"Services"
        }
    ],
    "sg:phone":"+61 3 5234 6303",
    "sg:postcode":"3251",
    "sg:province":"VIC",
    "sg:tags":[
        "support",
        "health"
    ],
    "wof:name":"Maternal & Child Health Centres",
    "wof:placetype":"venue"
},
  "geometry": {"coordinates":[143.63969399999999,-38.193806],"type":"Point"}
}