{
  "type": "Feature",
  "properties": {
    "iso:country":"AU",
    "sg:address":"93 Rooneys Rd",
    "sg:city":"Warrnambool",
    "sg:classifiers":[
        {
            "category":"Manufacturing",
            "subcategory":"Wood Products",
            "type":"Manufacturing & Wholesale Goods"
        }
    ],
    "sg:phone":"+61 407 336 849",
    "sg:postcode":"3280",
    "sg:province":"VIC",
    "sg:tags":[
        "polisher",
        "french"
    ],
    "wof:name":"South West Timber Coatings Pty Ltd",
    "wof:placetype":"venue"
},
  "geometry": {"coordinates":[142.45472717300001,-38.3630981445],"type":"Point"}
}