{
  "type": "Feature",
  "properties": {
    "iso:country":"AU",
    "sg:address":"28 Binnie St",
    "sg:city":"Brighton East",
    "sg:classifiers":[
        {
            "category":"Building & Trades",
            "subcategory":"Construction",
            "type":"Services"
        }
    ],
    "sg:phone":"+61 418 559 202",
    "sg:postcode":"3187",
    "sg:province":"VIC",
    "sg:tags":[
        "pool",
        "swimming"
    ],
    "wof:name":"Goldfish Pools & Landscapes",
    "wof:placetype":"venue"
},
  "geometry": {"coordinates":[145.00848388700001,-37.9246330261],"type":"Point"}
}