{
  "type": "Feature",
  "properties": {
    "addr:full":"Shop 8, Lot 2 City Plaza Memorial Drive Shellharbour NSW 2529",
    "addr:housenumber":"shop 8 lot",
    "addr:postcode":"2529",
    "addr:street":"Memorial Drive",
    "iso:country":"AU",
    "sg:address":"Shop 8, Lot 2",
    "sg:city":"City Plaza Memorial Drive Shellharbour",
    "sg:classifiers":[
        {
            "category":"Personal",
            "subcategory":"Beauty Salon",
            "type":"Services"
        }
    ],
    "sg:phone":"+61 2 4295 6000",
    "sg:postcode":"2529",
    "sg:province":"NSW",
    "sg:tags":[
        "hairdresser"
    ],
    "wof:name":"Deshanz Hair Stylist",
    "wof:placetype":"venue"
},
  "geometry": {"coordinates":[150.83595275900001,-34.5641212463],"type":"Point"}
}