{
  "type": "Feature",
  "properties": {
    "addr:full":"106 Islander Rd Pialba QLD 4655",
    "addr:housenumber":"106",
    "addr:postcode":"4655",
    "addr:street":"Islander Rd",
    "iso:country":"AU",
    "sg:address":"106 Islander Rd",
    "sg:city":"Pialba",
    "sg:classifiers":[
        {
            "category":"Home & Garden",
            "subcategory":"Hardware",
            "type":"Retail Goods"
        }
    ],
    "sg:phone":"+61 7 4124 2822",
    "sg:postcode":"4655",
    "sg:province":"QLD",
    "sg:tags":[
        "plumber",
        "supply"
    ],
    "wof:name":"Reece Pty Ltd",
    "wof:placetype":"venue"
},
  "geometry": {"coordinates":[152.831467,-25.285175],"type":"Point"}
}