{
  "type": "Feature",
  "properties": {
    "addr:full":"Cnr Wollongong & Maryborough Sts Fyshwick ACT 2609",
    "addr:postcode":"2609",
    "iso:country":"AU",
    "sg:address":"Cnr Wollongong & Maryborough Sts",
    "sg:city":"Fyshwick",
    "sg:classifiers":[
        {
            "category":"Home & Garden",
            "subcategory":"Household Appliances",
            "type":"Retail Goods"
        }
    ],
    "sg:phone":"+61 2 6280 6021",
    "sg:postcode":"2609",
    "sg:province":"ACT",
    "sg:tags":[
        "heating",
        "system"
    ],
    "wof:name":"Burning Log",
    "wof:placetype":"venue"
},
  "geometry": {"coordinates":[149.17758178700001,-35.3275680542],"type":"Point"}
}