{
  "type": "Feature",
  "properties": {
    "iso:country":"AU",
    "sg:address":"Noarlunga Centre David Witton Drv",
    "sg:city":"Noarlunga",
    "sg:classifiers":[
        {
            "category":"Professional",
            "subcategory":"Business Services",
            "type":"Services"
        }
    ],
    "sg:phone":"+61 8 8384 5555",
    "sg:postcode":"5168",
    "sg:province":"SA",
    "sg:tags":[
        "management",
        "event"
    ],
    "wof:name":"AMF Bowling Centres",
    "wof:placetype":"venue"
},
  "geometry": {"coordinates":[138.48785400400001,-35.1429901123],"type":"Point"}
}