{
  "type": "Feature",
  "properties": {
    "iso:country":"AU",
    "sg:address":"176 A Campbell St",
    "sg:city":"Hobart",
    "sg:classifiers":[
        {
            "category":"Real Estate",
            "subcategory":"Architect",
            "type":"Services"
        }
    ],
    "sg:phone":"+61 3 6234 9008",
    "sg:postcode":"7000",
    "sg:province":"TAS",
    "wof:name":"Detlev Geard Architect",
    "wof:placetype":"venue"
},
  "geometry": {"coordinates":[147.321502686,-42.8724555969],"type":"Point"}
}