{
  "type": "Feature",
  "properties": {
    "iso:country":"AU",
    "sg:address":"51 Skotsch Rd",
    "sg:city":"Banjup",
    "sg:classifiers":[
        {
            "category":"Building & Trades",
            "subcategory":"Pest Control",
            "type":"Services"
        }
    ],
    "sg:phone":"+61 8 9397 2033",
    "sg:postcode":"6164",
    "sg:province":"WA",
    "wof:name":"Protector Pest Control",
    "wof:placetype":"venue"
},
  "geometry": {"coordinates":[115.892899,-32.12603],"type":"Point"}
}