{
  "type": "Feature",
  "properties": {
    "addr:full":"Pacific Hwy Beenleigh QLD 4207",
    "addr:postcode":"4207",
    "addr:street":"Pacific Hwy",
    "iso:country":"AU",
    "sg:address":"Pacific Hwy",
    "sg:city":"Beenleigh",
    "sg:classifiers":[
        {
            "category":"Travel",
            "subcategory":"Hotels & Motels",
            "type":"Entertainment"
        }
    ],
    "sg:phone":"+61 7 3287 4666",
    "sg:postcode":"4207",
    "sg:province":"QLD",
    "sg:tags":[
        "pub"
    ],
    "wof:name":"Beenleigh Tavern",
    "wof:placetype":"venue"
},
  "geometry": {"coordinates":[153.20037841800001,-27.7032432556],"type":"Point"}
}