{
  "type": "Feature",
  "properties": {
    "addr:full":"12 St Lawrance Way Rowville VIC 3178",
    "addr:housenumber":"12",
    "addr:postcode":"3178",
    "addr:street":"St Lawrance Way",
    "iso:country":"AU",
    "sg:address":"12 St Lawrance Way",
    "sg:city":"Rowville",
    "sg:classifiers":[
        {
            "category":"Health Services",
            "subcategory":"Doctor",
            "type":"Services"
        }
    ],
    "sg:phone":"+61 3 9764 1617",
    "sg:postcode":"3178",
    "sg:province":"VIC",
    "sg:tags":[
        "medical",
        "practitioner"
    ],
    "wof:name":"Ng Elsa",
    "wof:placetype":"venue"
},
  "geometry": {"coordinates":[145.25779724099999,-37.9137191772],"type":"Point"}
}