{
  "type": "Feature",
  "properties": {
    "addr:full":"85 Bolsover St Rockhampton QLD 4700",
    "addr:housenumber":"85",
    "addr:postcode":"4700",
    "addr:street":"Bolsover St",
    "iso:country":"AU",
    "sg:address":"85 Bolsover St",
    "sg:city":"Rockhampton",
    "sg:classifiers":[
        {
            "category":"Banks & Credit Unions",
            "subcategory":"Financial Services",
            "type":"Services"
        }
    ],
    "sg:phone":"+61 7 4927 6922",
    "sg:postcode":"4700",
    "sg:province":"QLD",
    "sg:tags":[
        "finance",
        "motor",
        "vehicle"
    ],
    "wof:name":"Capitalcorp Financial Services",
    "wof:placetype":"venue"
},
  "geometry": {"coordinates":[150.51910400400001,-23.3878726959],"type":"Point"}
}