{
  "type": "Feature",
  "properties": {
    "addr:full":"319 Lennox St Richmond VIC 3121",
    "addr:housenumber":"319",
    "addr:postcode":"3121",
    "addr:street":"Lennox St",
    "iso:country":"AU",
    "sg:address":"319 Lennox St",
    "sg:city":"Richmond",
    "sg:classifiers":[
        {
            "category":"Shopping",
            "type":"Retail Goods"
        }
    ],
    "sg:phone":"+61 3 9428 8000",
    "sg:postcode":"3121",
    "sg:province":"VIC",
    "sg:tags":[
        "new age",
        "product"
    ],
    "wof:name":"G & J Crystal Harmony",
    "wof:placetype":"venue"
},
  "geometry": {"coordinates":[144.99366760300001,-37.8244285583],"type":"Point"}
}