{
  "type": "Feature",
  "properties": {
    "addr:full":"111 Hume Hwy Cabramatta NSW 2166",
    "addr:housenumber":"111",
    "addr:postcode":"2166",
    "addr:street":"Hume Hwy",
    "iso:country":"AU",
    "sg:address":"111 Hume Hwy",
    "sg:city":"Cabramatta",
    "sg:classifiers":[
        {
            "category":"Autos & Motor Vehicles",
            "subcategory":"Automobile Sales",
            "type":"Retail Goods"
        }
    ],
    "sg:phone":"+61 2 9726 2626",
    "sg:postcode":"2166",
    "sg:province":"NSW",
    "sg:tags":[
        "car",
        "used"
    ],
    "wof:name":"Maureen Motors",
    "wof:placetype":"venue"
},
  "geometry": {"coordinates":[150.95936584500001,-33.8937149048],"type":"Point"}
}