{
  "type": "Feature",
  "properties": {
    "addr:full":"98 St Vincent St Port Adelaide SA 5015",
    "addr:housenumber":"98",
    "addr:postcode":"5015",
    "addr:street":"St Vincent St",
    "iso:country":"AU",
    "sg:address":"98 St Vincent St",
    "sg:city":"Port Adelaide",
    "sg:classifiers":[
        {
            "category":"Shopping",
            "subcategory":"Pets & Pet Supplies",
            "type":"Retail Goods"
        }
    ],
    "sg:phone":"+61 8 8447 5562",
    "sg:postcode":"5015",
    "sg:province":"SA",
    "sg:tags":[
        "food"
    ],
    "wof:name":"Quality Pet Foods",
    "wof:placetype":"venue"
},
  "geometry": {"coordinates":[138.501953125,-34.8451805115],"type":"Point"}
}