{
  "type": "Feature",
  "properties": {
    "iso:country":"AU",
    "sg:address":"3 Dellamarta Rd",
    "sg:city":"Wangara",
    "sg:classifiers":[
        {
            "category":"School Buses",
            "type":"Transportation"
        }
    ],
    "sg:phone":"+61 8 9409 7477",
    "sg:postcode":"6065",
    "sg:province":"WA",
    "sg:tags":[
        "brick"
    ],
    "wof:name":"Boral Besser",
    "wof:placetype":"venue"
},
  "geometry": {"coordinates":[115.813568115,-31.7891845703],"type":"Point"}
}