{
  "type": "Feature",
  "properties": {
    "addr:full":"Embleton Shopping Centre Embleton WA 6062",
    "addr:postcode":"6062",
    "iso:country":"AU",
    "sg:address":"Embleton Shopping Centre",
    "sg:city":"Embleton",
    "sg:classifiers":[
        {
            "category":"Personal",
            "subcategory":"Beauty Salon",
            "type":"Services"
        }
    ],
    "sg:phone":"+61 8 9272 5885",
    "sg:postcode":"6062",
    "sg:province":"WA",
    "sg:tags":[
        "hairdresser"
    ],
    "wof:name":"Absolute Hair Studio",
    "wof:placetype":"venue"
},
  "geometry": {"coordinates":[115.905906677,-31.9091968536],"type":"Point"}
}