{
  "type": "Feature",
  "properties": {
    "addr:full":"Unit 5, 4 Hayley Rd Maddington WA 6109",
    "addr:housenumber":"4",
    "addr:postcode":"6109",
    "addr:street":"Hayley Rd",
    "iso:country":"AU",
    "sg:address":"Unit 5, 4 Hayley Rd",
    "sg:city":"Maddington",
    "sg:classifiers":[
        {
            "category":"Retail",
            "subcategory":"Auto Repair",
            "type":"Services"
        }
    ],
    "sg:phone":"+61 8 9493 4870",
    "sg:postcode":"6109",
    "sg:province":"WA",
    "sg:tags":[
        "beater",
        "painter",
        "panel"
    ],
    "wof:name":"Bayswater Panel Beaters & Spraypainters",
    "wof:placetype":"venue"
},
  "geometry": {"coordinates":[115.9868927,-32.0419692993],"type":"Point"}
}