{
  "type": "Feature",
  "properties": {
    "iso:country":"AU",
    "sg:address":"3- 7 Ferguson St",
    "sg:city":"Abbotsford",
    "sg:classifiers":[
        {
            "category":"Shopping",
            "subcategory":"Clothing, Apparel, & Fashions",
            "type":"Retail Goods"
        }
    ],
    "sg:phone":"+61 3 9419 2299",
    "sg:postcode":"3067",
    "sg:province":"VIC",
    "sg:tags":[
        "textile",
        "designer"
    ],
    "wof:name":"Blackstone Marketing P/L",
    "wof:placetype":"venue"
},
  "geometry": {"coordinates":[144.99229431099999,-37.8090782166],"type":"Point"}
}