{
  "type": "Feature",
  "properties": {
    "addr:full":"7 Witonga Crs Baulkham Hills NSW 2153",
    "addr:housenumber":"7",
    "addr:postcode":"2153",
    "addr:street":"Witonga Crs",
    "iso:country":"AU",
    "sg:address":"7 Witonga Crs",
    "sg:city":"Baulkham Hills",
    "sg:classifiers":[
        {
            "category":"Arena",
            "subcategory":"Sports Club",
            "type":"Entertainment"
        }
    ],
    "sg:phone":"+61 2 9639 0106",
    "sg:postcode":"2153",
    "sg:province":"NSW",
    "sg:tags":[
        "defence",
        "supply",
        "self",
        "instruction",
        "martial art"
    ],
    "wof:name":"Australian Ju-Jitsu Asscn NSW",
    "wof:placetype":"venue"
},
  "geometry": {"coordinates":[150.989624023,-33.7578811646],"type":"Point"}
}