{
  "type": "Feature",
  "properties": {
    "addr:full":"Shop 51/ 64 Southlands Blv Willetton WA 6155",
    "addr:housenumber":"shop 51 / 64",
    "addr:postcode":"6155",
    "addr:street":"Southlands Blv",
    "iso:country":"AU",
    "sg:address":"Shop 51/ 64 Southlands Blv",
    "sg:city":"Willetton",
    "sg:classifiers":[
        {
            "category":"Shopping",
            "subcategory":"Clothing, Apparel, & Fashions",
            "type":"Retail Goods"
        }
    ],
    "sg:phone":"+61 8 9332 0333",
    "sg:postcode":"6155",
    "sg:province":"WA",
    "sg:tags":[
        "jean"
    ],
    "wof:name":"JeansWest",
    "wof:placetype":"venue"
},
  "geometry": {"coordinates":[115.88915299999999,-32.052361],"type":"Point"}
}