{
  "type": "Feature",
  "properties": {
    "iso:country":"AU",
    "sg:address":"18-20 Eileen Rd",
    "sg:city":"Clayton South",
    "sg:classifiers":[
        {
            "category":"Military Area",
            "subcategory":"Coast Guard Base",
            "type":"Public Place"
        }
    ],
    "sg:phone":"+61 3 9547 6025",
    "sg:postcode":"3169",
    "sg:province":"VIC",
    "sg:tags":[
        "vessel",
        "pressure",
        "industrial"
    ],
    "wof:name":"C.P. Engineering Pty. Ltd.",
    "wof:placetype":"venue"
},
  "geometry": {"coordinates":[145.13607788100001,-37.9508666992],"type":"Point"}
}