{
  "type": "Feature",
  "properties": {
    "addr:full":"Collinsville Rd Bowen QLD 4805",
    "addr:postcode":"4805",
    "addr:street":"Collinsville Rd",
    "iso:country":"AU",
    "sg:address":"Collinsville Rd",
    "sg:city":"Bowen",
    "sg:classifiers":[
        {
            "category":"Retail",
            "subcategory":"Auto Repair",
            "type":"Services"
        }
    ],
    "sg:phone":"+61 7 4785 2422",
    "sg:postcode":"4805",
    "sg:province":"QLD",
    "sg:tags":[
        "repairer",
        "motor",
        "engineer"
    ],
    "wof:name":"Brooker Motors",
    "wof:placetype":"venue"
},
  "geometry": {"coordinates":[148.22084045400001,-20.0146598816],"type":"Point"}
}