{
  "type": "Feature",
  "properties": {
    "addr:full":"770 George St Sydney NSW 2000",
    "addr:housenumber":"770",
    "addr:postcode":"2000",
    "addr:street":"George St",
    "iso:country":"AU",
    "sg:address":"770 George St",
    "sg:city":"Sydney",
    "sg:classifiers":[
        {
            "category":"Shopping",
            "subcategory":"Pawn Shop",
            "type":"Retail Goods"
        }
    ],
    "sg:phone":"+61 2 9212 1266",
    "sg:postcode":"2000",
    "sg:province":"NSW",
    "sg:tags":[
        "pawnbroker"
    ],
    "wof:name":"A. Alfa City Loan Office & Super Bargain Centre",
    "wof:placetype":"venue"
},
  "geometry": {"coordinates":[151.20512390100001,-33.8806800842],"type":"Point"}
}