{
  "type": "Feature",
  "properties": {
    "iso:country":"AU",
    "sg:address":"325 Hancock Rd",
    "sg:city":"Fairview Park",
    "sg:classifiers":[
        {
            "category":"Personal",
            "subcategory":"Beauty Salon",
            "type":"Services"
        }
    ],
    "sg:phone":"+61 8 8251 1187",
    "sg:postcode":"5126",
    "sg:province":"SA",
    "sg:tags":[
        "hairdresser"
    ],
    "wof:name":"Roys Family Hair Care",
    "wof:placetype":"venue"
},
  "geometry": {"coordinates":[138.71743774399999,-34.801525116],"type":"Point"}
}