{
  "type": "Feature",
  "properties": {
    "addr:full":"383 Church St North Parramatta NSW 2151",
    "addr:housenumber":"383",
    "addr:postcode":"2151",
    "addr:street":"Church St",
    "iso:country":"AU",
    "sg:address":"383 Church St",
    "sg:city":"North Parramatta",
    "sg:classifiers":[
        {
            "category":"Food & Beverages",
            "subcategory":"Supermarket",
            "type":"Retail Goods"
        }
    ],
    "sg:phone":"+61 2 9630 3871",
    "sg:postcode":"2151",
    "sg:province":"NSW",
    "sg:tags":[
        "grocery",
        "store"
    ],
    "wof:name":"North Parramatta Asian Food Market",
    "wof:placetype":"venue"
},
  "geometry": {"coordinates":[151.00505065900001,-33.8018836975],"type":"Point"}
}