{
  "type": "Feature",
  "properties": {
    "iso:country":"AU",
    "sg:address":"258 Bell St",
    "sg:city":"Coburg",
    "sg:classifiers":[
        {
            "category":"Health Services",
            "subcategory":"Dentist",
            "type":"Services"
        }
    ],
    "sg:phone":"+61 3 9354 3456",
    "sg:postcode":"3058",
    "sg:province":"VIC",
    "wof:name":"Angle House Orthodontics",
    "wof:placetype":"venue"
},
  "geometry": {"coordinates":[144.955245972,-37.7400627136],"type":"Point"}
}