{
  "type": "Feature",
  "properties": {
    "addr:full":"Lot 2, Williams Crt Dubbo NSW 2830",
    "addr:postcode":"2830",
    "addr:street":"Williams Crt",
    "iso:country":"AU",
    "sg:address":"Lot 2, Williams Crt",
    "sg:city":"Dubbo",
    "sg:classifiers":[
        {
            "category":"Building & Trades",
            "subcategory":"Construction",
            "type":"Services"
        }
    ],
    "sg:phone":"+61 2 6882 8111",
    "sg:postcode":"2830",
    "sg:province":"NSW",
    "sg:tags":[
        "fencing",
        "contractor"
    ],
    "wof:name":"ARC Fences",
    "wof:placetype":"venue"
},
  "geometry": {"coordinates":[148.618865967,-32.2335357666],"type":"Point"}
}