{
  "type": "Feature",
  "properties": {
    "iso:country":"AU",
    "sg:address":"145 Booth St",
    "sg:city":"Annandale",
    "sg:classifiers":[
        {
            "category":"Health Services",
            "subcategory":"Health Practitioner",
            "type":"Services"
        }
    ],
    "sg:phone":"+61 2 9552 6288",
    "sg:postcode":"2038",
    "sg:province":"NSW",
    "sg:tags":[
        "acupuncture"
    ],
    "wof:name":"Powderly Kyle",
    "wof:placetype":"venue"
},
  "geometry": {"coordinates":[151.16868591299999,-33.8805770874],"type":"Point"}
}