{
  "type": "Feature",
  "properties": {
    "addr:full":"320 Burwood Hwy Burwood VIC 3125",
    "addr:housenumber":"320",
    "addr:postcode":"3125",
    "addr:street":"Burwood Hwy",
    "iso:country":"AU",
    "sg:address":"320 Burwood Hwy",
    "sg:city":"Burwood",
    "sg:classifiers":[
        {
            "category":"Professional",
            "subcategory":"Art Services",
            "type":"Services"
        }
    ],
    "sg:phone":"+61 3 9808 3310",
    "sg:postcode":"3125",
    "sg:province":"VIC",
    "sg:tags":[
        "decorator",
        "painter"
    ],
    "wof:name":"Graffiti Removals Advisory Service",
    "wof:placetype":"venue"
},
  "geometry": {"coordinates":[145.16310119600001,-37.8543701172],"type":"Point"}
}