{
  "type": "Feature",
  "properties": {
    "addr:full":"1 Noon Drv Yeppoon QLD 4703",
    "addr:housenumber":"1",
    "addr:postcode":"4703",
    "addr:street":"Noon Drv",
    "iso:country":"AU",
    "sg:address":"1 Noon Drv",
    "sg:city":"Yeppoon",
    "sg:classifiers":[
        {
            "category":"Building & Trades",
            "subcategory":"Construction",
            "type":"Services"
        }
    ],
    "sg:phone":"+61 7 4938 3026",
    "sg:postcode":"4703",
    "sg:province":"QLD",
    "sg:tags":[
        "concrete",
        "contractor"
    ],
    "wof:name":"Bulloch Concreting",
    "wof:placetype":"venue"
},
  "geometry": {"coordinates":[150.72909545900001,-23.1147098541],"type":"Point"}
}