{
  "type": "Feature",
  "properties": {
    "addr:full":"39 Kays La Alstonville NSW 2477",
    "addr:housenumber":"39",
    "addr:postcode":"2477",
    "addr:street":"Kays La",
    "iso:country":"AU",
    "sg:address":"39 Kays La",
    "sg:city":"Alstonville",
    "sg:classifiers":[
        {
            "category":"Wholesale",
            "subcategory":"Plants",
            "type":"Manufacturing & Wholesale Goods"
        }
    ],
    "sg:phone":"+61 2 6628 0395",
    "sg:postcode":"2477",
    "sg:province":"NSW",
    "sg:tags":[
        "florist"
    ],
    "wof:name":"Prime Flowers Pty Ltd",
    "wof:placetype":"venue"
},
  "geometry": {"coordinates":[153.475143433,-28.9260387421],"type":"Point"}
}