{
  "type": "Feature",
  "properties": {
    "addr:full":"Shop 3/ 103 Victoria St Gosford East NSW 2250",
    "addr:housenumber":"shop 3 / 103",
    "addr:postcode":"2250",
    "addr:street":"Victoria St",
    "iso:country":"AU",
    "sg:address":"Shop 3/ 103 Victoria St",
    "sg:city":"Gosford East",
    "sg:classifiers":[
        {
            "category":"Shopping",
            "subcategory":"Baby Store",
            "type":"Retail Goods"
        }
    ],
    "sg:phone":"+61 2 4322 9733",
    "sg:postcode":"2250",
    "sg:province":"NSW",
    "sg:tags":[
        "wear"
    ],
    "wof:name":"Heirloom Baby",
    "wof:placetype":"venue"
},
  "geometry": {"coordinates":[151.35319519000001,-33.437046051],"type":"Point"}
}