{
  "type": "Feature",
  "properties": {
    "addr:full":"34 Buckingham St Surry Hills NSW 2010",
    "addr:housenumber":"34",
    "addr:postcode":"2010",
    "addr:street":"Buckingham St",
    "iso:country":"AU",
    "sg:address":"34 Buckingham St",
    "sg:city":"Surry Hills",
    "sg:classifiers":[
        {
            "category":"Arts & Performance",
            "subcategory":"Art Gallery",
            "type":"Entertainment"
        }
    ],
    "sg:phone":"+61 2 9310 1118",
    "sg:postcode":"2010",
    "sg:province":"NSW",
    "wof:name":"New Guinea Gallery",
    "wof:placetype":"venue"
},
  "geometry": {"coordinates":[151.20765685999999,-33.8872413635],"type":"Point"}
}