{
  "type": "Feature",
  "properties": {
    "iso:country":"AU",
    "sg:address":"4 Dandenong St",
    "sg:city":"Dandenong",
    "sg:classifiers":[
        {
            "category":"Community Center",
            "subcategory":"Ethnic",
            "type":"Public Place"
        }
    ],
    "sg:phone":"+61 3 9794 5966",
    "sg:postcode":"3175",
    "sg:province":"VIC",
    "sg:tags":[
        "window",
        "pvc"
    ],
    "wof:name":"Builders Top Choice",
    "wof:placetype":"venue"
},
  "geometry": {"coordinates":[145.199981689,-37.9910049438],"type":"Point"}
}