{
  "type": "Feature",
  "properties": {
    "addr:full":"50 Elizabeth Way Elizabeth SA 5112",
    "addr:housenumber":"50",
    "addr:postcode":"5112",
    "addr:street":"Elizabeth Way",
    "iso:country":"AU",
    "sg:address":"50 Elizabeth Way",
    "sg:city":"Elizabeth",
    "sg:classifiers":[
        {
            "category":"Retail",
            "subcategory":"Event Space",
            "type":"Services"
        }
    ],
    "sg:phone":"+61 8 8255 9000",
    "sg:postcode":"5112",
    "sg:province":"SA",
    "sg:tags":[
        "function",
        "organiser"
    ],
    "wof:name":"Louisiana Tavern",
    "wof:placetype":"venue"
},
  "geometry": {"coordinates":[138.66700744600001,-34.7156982422],"type":"Point"}
}