{
  "type": "Feature",
  "properties": {
    "iso:country":"AU",
    "sg:address":"22 Crown St",
    "sg:city":"Woolloomooloo",
    "sg:classifiers":[
        {
            "category":"Shopping",
            "subcategory":"Bridal",
            "type":"Retail Goods"
        }
    ],
    "sg:phone":"+61 2 9357 7810",
    "sg:postcode":"2011",
    "sg:province":"NSW",
    "sg:tags":[
        "hire",
        "wear"
    ],
    "wof:name":"Karen Willis Holmes - Couture",
    "wof:placetype":"venue"
},
  "geometry": {"coordinates":[151.217041016,-33.8716697693],"type":"Point"}
}