{
  "type": "Feature",
  "properties": {
    "iso:country":"AU",
    "sg:address":"Indooroopilly Shopping Centre, 318-322 Lvl 2, Moggill Rd",
    "sg:city":"Indooroopilly",
    "sg:classifiers":[
        {
            "category":"Shopping",
            "subcategory":"Jewelry",
            "type":"Retail Goods"
        }
    ],
    "sg:phone":"+61 7 3878 3815",
    "sg:postcode":"4068",
    "sg:province":"QLD",
    "sg:tags":[
        "jeweller"
    ],
    "wof:name":"Finesse Fine Jewellery",
    "wof:placetype":"venue"
},
  "geometry": {"coordinates":[152.989044189,-27.4964008331],"type":"Point"}
}