{
  "type": "Feature",
  "properties": {
    "addr:full":"16 Primrose St Ermington NSW 2115",
    "addr:housenumber":"16",
    "addr:postcode":"2115",
    "addr:street":"Primrose St",
    "iso:country":"AU",
    "sg:address":"16 Primrose St",
    "sg:city":"Ermington",
    "sg:classifiers":[
        {
            "category":"Building & Trades",
            "subcategory":"Construction",
            "type":"Services"
        }
    ],
    "sg:phone":"+61 1800 215 080",
    "sg:postcode":"2115",
    "sg:province":"NSW",
    "sg:tags":[
        "contractor"
    ],
    "wof:name":"Medina Homes Pty Ltd",
    "wof:placetype":"venue"
},
  "geometry": {"coordinates":[151.05082702600001,-33.8151283264],"type":"Point"}
}