{
  "type": "Feature",
  "properties": {
    "iso:country":"AU",
    "sg:address":"16 Commerce Ave",
    "sg:city":"Warana",
    "sg:classifiers":[
        {
            "category":"Manufacturing",
            "subcategory":"Furniture",
            "type":"Manufacturing & Wholesale Goods"
        }
    ],
    "sg:phone":"+61 412 731 579",
    "sg:postcode":"4575",
    "sg:province":"QLD",
    "sg:tags":[
        "builder",
        "designer",
        "custom"
    ],
    "wof:name":"Gary O&#039;Neill",
    "wof:placetype":"venue"
},
  "geometry": {"coordinates":[153.12792999999999,-26.728329],"type":"Point"}
}