{
  "type": "Feature",
  "properties": {
    "iso:country":"AU",
    "sg:address":"124 Hutt St",
    "sg:city":"Adelaide",
    "sg:classifiers":[
        {
            "category":"Education",
            "subcategory":"University",
            "type":"Public Place"
        }
    ],
    "sg:phone":"+61 8 8228 3636",
    "sg:postcode":"5000",
    "sg:province":"SA",
    "sg:tags":[
        "college",
        "tertiary"
    ],
    "wof:name":"International College Of Hotel Management",
    "wof:placetype":"venue"
},
  "geometry": {"coordinates":[138.61239624000001,-34.9296417236],"type":"Point"}
}