{
  "type": "Feature",
  "properties": {
    "iso:country":"AU",
    "sg:address":"6a Elvie St",
    "sg:city":"Doncaster East",
    "sg:classifiers":[
        {
            "category":"Professional",
            "subcategory":"Business Services",
            "type":"Services"
        }
    ],
    "sg:phone":"+61 3 9013 0906",
    "sg:postcode":"3109",
    "sg:province":"VIC",
    "sg:tags":[
        "consultant",
        "system"
    ],
    "wof:name":"Lakesview Consulting",
    "wof:placetype":"venue"
},
  "geometry": {"coordinates":[145.16923523,-37.7906494141],"type":"Point"}
}