{
  "type": "Feature",
  "properties": {
    "iso:country":"AU",
    "sg:address":"4 South Rd",
    "sg:city":"Braybrook",
    "sg:classifiers":[
        {
            "category":"Professional",
            "subcategory":"Engineering",
            "type":"Services"
        }
    ],
    "sg:phone":"+61 3 9689 3348",
    "sg:postcode":"3019",
    "sg:province":"VIC",
    "sg:tags":[
        "engineer"
    ],
    "wof:name":"Everlast Steel Products",
    "wof:placetype":"venue"
},
  "geometry": {"coordinates":[144.86213684099999,-37.7924880981],"type":"Point"}
}