{
  "type": "Feature",
  "properties": {
    "addr:full":"18 Fearn Ave Margaret River WA 6285",
    "addr:housenumber":"18",
    "addr:postcode":"6285",
    "addr:street":"Fearn Ave",
    "iso:country":"AU",
    "sg:address":"18 Fearn Ave",
    "sg:city":"Margaret River",
    "sg:classifiers":[
        {
            "category":"Health Services",
            "subcategory":"Doctor",
            "type":"Services"
        }
    ],
    "sg:phone":"+61 8 9758 7411",
    "sg:postcode":"6285",
    "sg:province":"WA",
    "sg:tags":[
        "medical",
        "practitioner"
    ],
    "wof:name":"Fearn House General Practice And Synergy Sports Medicine Margaret River",
    "wof:placetype":"venue"
},
  "geometry": {"coordinates":[115.072410584,-33.9513015747],"type":"Point"}
}