{
  "type": "Feature",
  "properties": {
    "addr:full":"22 Fowler Rd Dandenong South VIC 3175",
    "addr:housenumber":"22",
    "addr:postcode":"3175",
    "addr:street":"Fowler Rd",
    "iso:country":"AU",
    "sg:address":"22 Fowler Rd",
    "sg:city":"Dandenong South",
    "sg:classifiers":[
        {
            "category":"Retail",
            "subcategory":"Auto Repair",
            "type":"Services"
        }
    ],
    "sg:phone":"+61 3 9794 5825",
    "sg:postcode":"3175",
    "sg:province":"VIC",
    "sg:tags":[
        "bus",
        "truck"
    ],
    "wof:name":"Transport Innovators Australia P/L",
    "wof:placetype":"venue"
},
  "geometry": {"coordinates":[145.23292541500001,-38.0066490173],"type":"Point"}
}