{
  "type": "Feature",
  "properties": {
    "addr:full":"280 Sheridan St Cairns North QLD 4870",
    "addr:housenumber":"280",
    "addr:postcode":"4870",
    "addr:street":"Sheridan St",
    "iso:country":"AU",
    "sg:address":"280 Sheridan St",
    "sg:city":"Cairns North",
    "sg:classifiers":[
        {
            "category":"Professional",
            "subcategory":"Engineering",
            "type":"Services"
        }
    ],
    "sg:phone":"+61 7 4051 0288",
    "sg:postcode":"4870",
    "sg:province":"QLD",
    "sg:tags":[
        "consulting",
        "engineer"
    ],
    "wof:name":"Cardno CCS",
    "wof:placetype":"venue"
},
  "geometry": {"coordinates":[145.75894165,-16.9048976898],"type":"Point"}
}