{
  "type": "Feature",
  "properties": {
    "addr:full":"180 Main St Kangaroo Point QLD 4169",
    "addr:housenumber":"180",
    "addr:postcode":"4169",
    "addr:street":"Main St",
    "iso:country":"AU",
    "sg:address":"180 Main St",
    "sg:city":"Kangaroo Point",
    "sg:classifiers":[
        {
            "category":"Manufacturing",
            "subcategory":"Food",
            "type":"Manufacturing & Wholesale Goods"
        }
    ],
    "sg:phone":"+61 7 3895 8311",
    "sg:postcode":"4169",
    "sg:province":"QLD",
    "sg:tags":[
        "function",
        "catering"
    ],
    "wof:name":"Icons Catering",
    "wof:placetype":"venue"
},
  "geometry": {"coordinates":[153.035552978,-27.468914032],"type":"Point"}
}