{
  "type": "Feature",
  "properties": {
    "iso:country":"AU",
    "sg:address":"14 Warwick St",
    "sg:city":"Kaniva",
    "sg:classifiers":[
        {
            "category":"Retail",
            "subcategory":"Laundry & Dry Cleaning",
            "type":"Services"
        }
    ],
    "sg:phone":"+61 3 5392 2833",
    "sg:postcode":"3419",
    "sg:province":"VIC",
    "wof:name":"Dianne's Laundry Service",
    "wof:placetype":"venue"
},
  "geometry": {"coordinates":[141.23887634299999,-36.3728675842],"type":"Point"}
}