{
  "type": "Feature",
  "properties": {
    "addr:full":"4 Sinclair Crt Attwood VIC 3049",
    "addr:housenumber":"4",
    "addr:postcode":"3049",
    "addr:street":"Sinclair Crt",
    "iso:country":"AU",
    "sg:address":"4 Sinclair Crt",
    "sg:city":"Attwood",
    "sg:classifiers":[
        {
            "category":"Professional",
            "subcategory":"Computer Services",
            "type":"Services"
        }
    ],
    "sg:phone":"+61 418 583 042",
    "sg:postcode":"3049",
    "sg:province":"VIC",
    "sg:tags":[
        "repairs",
        "upgrade",
        "equipment"
    ],
    "wof:name":"A B S H Computer Pty Ltd",
    "wof:placetype":"venue"
},
  "geometry": {"coordinates":[144.898132,-37.669178],"type":"Point"}
}