{
  "type": "Feature",
  "properties": {
    "addr:full":"26 Ruse St Osborne Park WA 6017",
    "addr:housenumber":"26",
    "addr:postcode":"6017",
    "addr:street":"Ruse St",
    "iso:country":"AU",
    "sg:address":"26 Ruse St",
    "sg:city":"Osborne Park",
    "sg:classifiers":[
        {
            "category":"Retail",
            "subcategory":"Laundry & Dry Cleaning",
            "type":"Services"
        }
    ],
    "sg:phone":"+61 8 9444 3322",
    "sg:postcode":"6017",
    "sg:province":"WA",
    "sg:tags":[
        "cloth",
        "supply"
    ],
    "wof:name":"New Rag Supplies",
    "wof:placetype":"venue"
},
  "geometry": {"coordinates":[115.815002441,-31.9065570831],"type":"Point"}
}