{
  "type": "Feature",
  "properties": {
    "addr:full":"1- 3 Smith St Collingwood VIC 3066",
    "addr:housenumber":"3",
    "addr:postcode":"3066",
    "addr:street":"Smith St",
    "iso:country":"AU",
    "sg:address":"1- 3 Smith St",
    "sg:city":"Collingwood",
    "sg:classifiers":[
        {
            "category":"Fast Food",
            "type":"Food & Drink"
        }
    ],
    "sg:phone":"+61 3 9416 3366",
    "sg:postcode":"3066",
    "sg:province":"VIC",
    "sg:tags":[
        "away",
        "take"
    ],
    "wof:name":"Pizza Haven",
    "wof:placetype":"venue"
},
  "geometry": {"coordinates":[144.98248290999999,-37.8083992004],"type":"Point"}
}