{
  "type": "Feature",
  "properties": {
    "iso:country":"AU",
    "sg:address":"Law Society Level 1 Cnr Of Farrel & London Circuit",
    "sg:city":"Canberra",
    "sg:classifiers":[
        {
            "category":"Professional",
            "subcategory":"Detective & Security Services",
            "type":"Services"
        }
    ],
    "sg:phone":"+61 2 6230 5038",
    "sg:postcode":"2600",
    "sg:province":"ACT",
    "sg:tags":[
        "equipment",
        "window",
        "doors"
    ],
    "wof:name":"Jim's Security Doors",
    "wof:placetype":"venue"
},
  "geometry": {"coordinates":[149.126953125,-35.284324646],"type":"Point"}
}