{
  "type": "Feature",
  "properties": {
    "addr:full":"68 Oak Rd Kirrawee NSW 2232",
    "addr:housenumber":"68",
    "addr:postcode":"2232",
    "addr:street":"Oak Rd",
    "iso:country":"AU",
    "sg:address":"68 Oak Rd",
    "sg:city":"Kirrawee",
    "sg:classifiers":[
        {
            "category":"Home & Garden",
            "subcategory":"Hardware",
            "type":"Retail Goods"
        }
    ],
    "sg:phone":"+61 2 9521 3711",
    "sg:postcode":"2232",
    "sg:province":"NSW",
    "sg:tags":[
        "plumber",
        "supply"
    ],
    "wof:name":"Reece Pty Ltd",
    "wof:placetype":"venue"
},
  "geometry": {"coordinates":[151.07273864699999,-34.0270881653],"type":"Point"}
}