{
  "type": "Feature",
  "properties": {
    "addr:full":"4 Jetty Rd Old Beach TAS 7017",
    "addr:housenumber":"4",
    "addr:postcode":"7017",
    "addr:street":"Jetty Rd",
    "iso:country":"AU",
    "sg:address":"4 Jetty Rd",
    "sg:city":"Old Beach",
    "sg:classifiers":[
        {
            "category":"Building & Trades",
            "subcategory":"Landscaping Services",
            "type":"Services"
        }
    ],
    "sg:phone":"+61 3 6249 3591",
    "sg:postcode":"7017",
    "sg:province":"TAS",
    "sg:tags":[
        "stump",
        "tree",
        "felling",
        "removal"
    ],
    "wof:name":"Hobart Tree Chipping & Recycling",
    "wof:placetype":"venue"
},
  "geometry": {"coordinates":[147.26826477,-42.7715988159],"type":"Point"}
}