{
  "type": "Feature",
  "properties": {
    "addr:full":"27 Archbold Rd Roseville NSW 2069",
    "addr:housenumber":"27",
    "addr:postcode":"2069",
    "addr:street":"Archbold Rd",
    "iso:country":"AU",
    "sg:address":"27 Archbold Rd",
    "sg:city":"Roseville",
    "sg:classifiers":[
        {
            "category":"Real Estate",
            "subcategory":"Architect",
            "type":"Services"
        }
    ],
    "sg:phone":"+61 2 9417 2707",
    "sg:postcode":"2069",
    "sg:province":"NSW",
    "wof:name":"Meyer Barbara",
    "wof:placetype":"venue"
},
  "geometry": {"coordinates":[151.18717956500001,-33.7811126709],"type":"Point"}
}