{
  "type": "Feature",
  "properties": {
    "addr:full":"134 Grange Rd Allenby Gardens SA 5009",
    "addr:housenumber":"134",
    "addr:postcode":"5009",
    "addr:street":"Grange Rd",
    "iso:country":"AU",
    "sg:address":"134 Grange Rd",
    "sg:city":"Allenby Gardens",
    "sg:classifiers":[
        {
            "category":"Industrial Area",
            "type":"Public Place"
        }
    ],
    "sg:phone":"+61 8 8241 5622",
    "sg:postcode":"5009",
    "sg:province":"SA",
    "sg:tags":[
        "protective",
        "clothing"
    ],
    "wof:name":"Lawrence & Hanson",
    "wof:placetype":"venue"
},
  "geometry": {"coordinates":[138.55355835,-34.9045181274],"type":"Point"}
}