{
  "type": "Feature",
  "properties": {
    "addr:full":"3 Jan St Newton SA 5074",
    "addr:housenumber":"3",
    "addr:postcode":"5074",
    "addr:street":"Jan St",
    "iso:country":"AU",
    "sg:address":"3 Jan St",
    "sg:city":"Newton",
    "sg:classifiers":[
        {
            "category":"Shopping",
            "subcategory":"Clothing, Apparel, & Fashions",
            "type":"Retail Goods"
        }
    ],
    "sg:phone":"+61 8 8337 1822",
    "sg:postcode":"5074",
    "sg:province":"SA",
    "sg:tags":[
        "lady",
        "wear"
    ],
    "wof:name":"Boutique Mon Ami",
    "wof:placetype":"venue"
},
  "geometry": {"coordinates":[138.67326355,-34.8769226074],"type":"Point"}
}