{
  "type": "Feature",
  "properties": {
    "addr:full":"4a Pilkington St Port Hedland WA 6721",
    "addr:housenumber":"4a",
    "addr:postcode":"6721",
    "addr:street":"Pilkington St",
    "iso:country":"AU",
    "sg:address":"4a Pilkington St",
    "sg:city":"Port Hedland",
    "sg:classifiers":[
        {
            "category":"Professional",
            "subcategory":"Employment Agencies",
            "type":"Services"
        }
    ],
    "sg:phone":"+61 418 937 763",
    "sg:postcode":"6721",
    "sg:province":"WA",
    "sg:tags":[
        "entertainer",
        "agent"
    ],
    "wof:name":"Galaxy Promotions",
    "wof:placetype":"venue"
},
  "geometry": {"coordinates":[118.604171753,-20.3100223541],"type":"Point"}
}