{
  "type": "Feature",
  "properties": {
    "addr:full":"Level 2, Cairns Central Apartments Cairns QLD 4870",
    "addr:postcode":"4870",
    "iso:country":"AU",
    "sg:address":"Level 2, Cairns Central Apartments",
    "sg:city":"Cairns",
    "sg:classifiers":[
        {
            "category":"Professional",
            "subcategory":"Employment Agencies",
            "type":"Services"
        }
    ],
    "sg:phone":"+61 13 14 48",
    "sg:postcode":"4870",
    "sg:province":"QLD",
    "sg:tags":[
        "hire",
        "labour",
        "contractor"
    ],
    "wof:name":"Drake",
    "wof:placetype":"venue"
},
  "geometry": {"coordinates":[145.74664306599999,-16.9379043579],"type":"Point"}
}