{
  "type": "Feature",
  "properties": {
    "iso:country":"AU",
    "sg:address":"Unit 3, 62 Keane St",
    "sg:city":"Currajong",
    "sg:classifiers":[
        {
            "category":"Professional",
            "subcategory":"Business Services",
            "type":"Services"
        }
    ],
    "sg:phone":"+61 7 4779 3100",
    "sg:postcode":"4812",
    "sg:province":"QLD",
    "sg:tags":[
        "management",
        "event"
    ],
    "wof:name":"ET Event Management",
    "wof:placetype":"venue"
},
  "geometry": {"coordinates":[146.775543,-19.271448],"type":"Point"}
}