{
  "type": "Feature",
  "properties": {
    "addr:full":"8 Brompton St Alexandra Hills QLD 4161",
    "addr:housenumber":"8",
    "addr:postcode":"4161",
    "addr:street":"Brompton St",
    "iso:country":"AU",
    "sg:address":"8 Brompton St",
    "sg:city":"Alexandra Hills",
    "sg:classifiers":[
        {
            "category":"Food & Beverages",
            "subcategory":"Specialty",
            "type":"Retail Goods"
        }
    ],
    "sg:phone":"+61 7 3824 1519",
    "sg:postcode":"4161",
    "sg:province":"QLD",
    "sg:tags":[
        "product",
        "health"
    ],
    "wof:name":"Herbalife Alexandra Hills",
    "wof:placetype":"venue"
},
  "geometry": {"coordinates":[153.22039794899999,-27.5320072174],"type":"Point"}
}