{
  "type": "Feature",
  "properties": {
    "addr:full":"42 Victoria St Pyramid Hill VIC 3575",
    "addr:housenumber":"42",
    "addr:postcode":"3575",
    "addr:street":"Victoria St",
    "iso:country":"AU",
    "sg:address":"42 Victoria St",
    "sg:city":"Pyramid Hill",
    "sg:classifiers":[
        {
            "category":"Autos & Motor Vehicles",
            "subcategory":"Fuel & Gas Station",
            "type":"Retail Goods"
        }
    ],
    "sg:phone":"+61 3 5455 7214",
    "sg:postcode":"3575",
    "sg:province":"VIC",
    "wof:name":"Pyramid Tyre & Auto",
    "wof:placetype":"venue"
},
  "geometry": {"coordinates":[144.11488342300001,-36.0552215576],"type":"Point"}
}