{
  "type": "Feature",
  "properties": {
    "addr:full":"Shop 3/ 75 Prospect Rd Prospect SA 5082",
    "addr:housenumber":"shop 3 / 75",
    "addr:postcode":"5082",
    "addr:street":"Prospect Rd",
    "iso:country":"AU",
    "sg:address":"Shop 3/ 75 Prospect Rd",
    "sg:city":"Prospect",
    "sg:classifiers":[
        {
            "category":"Personal",
            "subcategory":"Beauty Salon",
            "type":"Services"
        }
    ],
    "sg:phone":"+61 8 8342 0111",
    "sg:postcode":"5082",
    "sg:province":"SA",
    "wof:name":"Beauty Affair",
    "wof:placetype":"venue"
},
  "geometry": {"coordinates":[138.59432983400001,-34.8888626099],"type":"Point"}
}