{
  "type": "Feature",
  "properties": {
    "iso:country":"AU",
    "sg:address":"52 Sutherland Crs",
    "sg:city":"Winthrop",
    "sg:classifiers":[
        {
            "category":"Professional",
            "subcategory":"Computer Services",
            "type":"Services"
        }
    ],
    "sg:phone":"+61 8 9332 9446",
    "sg:postcode":"6150",
    "sg:province":"WA",
    "sg:tags":[
        "consultant",
        "system"
    ],
    "wof:name":"Winthrop Dexterity Consultants",
    "wof:placetype":"venue"
},
  "geometry": {"coordinates":[115.83300800000001,-32.058788],"type":"Point"}
}