{
  "type": "Feature",
  "properties": {
    "iso:country":"AU",
    "sg:address":"133 Womerah Ave",
    "sg:city":"Darlinghurst",
    "sg:classifiers":[
        {
            "category":"Organizations",
            "subcategory":"Professional Association",
            "type":"Services"
        }
    ],
    "sg:phone":"+61 405 096 483",
    "sg:postcode":"2010",
    "sg:province":"NSW",
    "sg:tags":[
        "web",
        "internet"
    ],
    "wof:name":"Craig Longmuir",
    "wof:placetype":"venue"
},
  "geometry": {"coordinates":[151.22315979000001,-33.8781089783],"type":"Point"}
}