{
  "type": "Feature",
  "properties": {
    "addr:full":"49 Quarry Rd Dural NSW 2158",
    "addr:housenumber":"49",
    "addr:postcode":"2158",
    "addr:street":"Quarry Rd",
    "iso:country":"AU",
    "sg:address":"49 Quarry Rd",
    "sg:city":"Dural",
    "sg:classifiers":[
        {
            "category":"Farming",
            "subcategory":"Nursery",
            "type":"Manufacturing & Wholesale Goods"
        }
    ],
    "sg:phone":"+61 2 9651 3199",
    "sg:postcode":"2158",
    "sg:province":"NSW",
    "wof:name":"Bloomin Lot",
    "wof:placetype":"venue"
},
  "geometry": {"coordinates":[151.05099487300001,-33.7006721497],"type":"Point"}
}