{
  "type": "Feature",
  "properties": {
    "addr:full":"76 Leila St Deer Park VIC 3023",
    "addr:housenumber":"76",
    "addr:postcode":"3023",
    "addr:street":"Leila St",
    "iso:country":"AU",
    "sg:address":"76 Leila St",
    "sg:city":"Deer Park",
    "sg:classifiers":[
        {
            "category":"Building & Trades",
            "subcategory":"Construction",
            "type":"Services"
        }
    ],
    "sg:phone":"+61 418 993 134",
    "sg:postcode":"3023",
    "sg:province":"VIC",
    "sg:tags":[
        "window",
        "tinting"
    ],
    "wof:name":"AAA Ozone Tint",
    "wof:placetype":"venue"
},
  "geometry": {"coordinates":[144.76206999999999,-37.766056],"type":"Point"}
}