{
  "type": "Feature",
  "properties": {
    "addr:full":"11 Lapstone Crs Yallambie VIC 3085",
    "addr:housenumber":"11",
    "addr:postcode":"3085",
    "addr:street":"Lapstone Crs",
    "iso:country":"AU",
    "sg:address":"11 Lapstone Crs",
    "sg:city":"Yallambie",
    "sg:classifiers":[
        {
            "category":"Building & Trades",
            "subcategory":"Construction",
            "type":"Services"
        }
    ],
    "sg:phone":"+61 418 358 748",
    "sg:postcode":"3085",
    "sg:province":"VIC",
    "sg:tags":[
        "contractor"
    ],
    "wof:name":"Gande Constructions Pty Ltd",
    "wof:placetype":"venue"
},
  "geometry": {"coordinates":[145.09535217300001,-37.7288017273],"type":"Point"}
}