{
  "type": "Feature",
  "properties": {
    "addr:full":"6- 10 Adelphi Tce Glenelg SA 5045",
    "addr:housenumber":"10",
    "addr:postcode":"5045",
    "addr:street":"6;Adelphi Tce",
    "iso:country":"AU",
    "sg:address":"6- 10",
    "sg:city":"Adelphi Tce Glenelg",
    "sg:classifiers":[
        {
            "category":"Travel",
            "subcategory":"Hotels & Motels",
            "type":"Entertainment"
        }
    ],
    "sg:phone":"+61 8 8350 5199",
    "sg:postcode":"5045",
    "sg:province":"SA",
    "wof:name":"Comfort Inn Haven Marina",
    "wof:placetype":"venue"
},
  "geometry": {"coordinates":[138.51449600000001,-34.974087],"type":"Point"}
}