{
  "type": "Feature",
  "properties": {
    "iso:country":"AU",
    "sg:address":"72b Yerrick Rd",
    "sg:city":"Lakemba",
    "sg:classifiers":[
        {
            "category":"Wholesale",
            "subcategory":"Non-durable Goods",
            "type":"Manufacturing & Wholesale Goods"
        }
    ],
    "sg:phone":"+61 2 9750 7256",
    "sg:postcode":"2195",
    "sg:province":"NSW",
    "sg:tags":[
        "textile"
    ],
    "wof:name":"Muhammed Bilal And Company",
    "wof:placetype":"venue"
},
  "geometry": {"coordinates":[151.076126,-33.910931],"type":"Point"}
}