{
  "type": "Feature",
  "properties": {
    "addr:full":"3/ 61 McLeod St Cairns QLD 4870",
    "addr:housenumber":"/ 61",
    "addr:postcode":"4870",
    "addr:street":"Mcleod St",
    "iso:country":"AU",
    "sg:address":"3/ 61 McLeod St",
    "sg:city":"Cairns",
    "sg:classifiers":[
        {
            "category":"Education",
            "subcategory":"Special Training",
            "type":"Public Place"
        }
    ],
    "sg:phone":"+61 7 4031 0555",
    "sg:postcode":"4870",
    "sg:province":"QLD",
    "sg:tags":[
        "feldenkrais"
    ],
    "wof:name":"Chambers Phillip",
    "wof:placetype":"venue"
},
  "geometry": {"coordinates":[145.768997192,-16.9202709198],"type":"Point"}
}