{
  "type": "Feature",
  "properties": {
    "iso:country":"AU",
    "sg:address":"14 Alderson St",
    "sg:city":"Hume",
    "sg:classifiers":[
        {
            "category":"Retail",
            "subcategory":"Auto Repair",
            "type":"Services"
        }
    ],
    "sg:phone":"+61 2 6260 1311",
    "sg:postcode":"2620",
    "sg:province":"ACT",
    "sg:tags":[
        "automotive",
        "air conditioning"
    ],
    "wof:name":"Valley Auto Electrics",
    "wof:placetype":"venue"
},
  "geometry": {"coordinates":[149.163574219,-35.3935890198],"type":"Point"}
}