{
  "type": "Feature",
  "properties": {
    "addr:full":"343- 349 Mackenzie St Toowoomba QLD 4350",
    "addr:housenumber":"349",
    "addr:postcode":"4350",
    "addr:street":"Mackenzie St",
    "iso:country":"AU",
    "sg:address":"343- 349 Mackenzie St",
    "sg:city":"Toowoomba",
    "sg:classifiers":[
        {
            "category":"Professional",
            "subcategory":"Engineering",
            "type":"Services"
        }
    ],
    "sg:phone":"+61 7 4635 2969",
    "sg:postcode":"4350",
    "sg:province":"QLD",
    "sg:tags":[
        "consulting",
        "engineer"
    ],
    "wof:name":"Creedon & Associates Pty Ltd",
    "wof:placetype":"venue"
},
  "geometry": {"coordinates":[151.96931499999999,-27.596533],"type":"Point"}
}