{
  "type": "Feature",
  "properties": {
    "addr:full":"348 West St Umina Beach NSW 2257",
    "addr:housenumber":"348",
    "addr:postcode":"2257",
    "addr:street":"West St",
    "iso:country":"AU",
    "sg:address":"348 West St",
    "sg:city":"Umina Beach",
    "sg:classifiers":[
        {
            "category":"Real Estate",
            "subcategory":"Real Estate Agent",
            "type":"Services"
        }
    ],
    "sg:phone":"+61 2 4344 1511",
    "sg:postcode":"2257",
    "sg:province":"NSW",
    "wof:name":"Strictly Rentals",
    "wof:placetype":"venue"
},
  "geometry": {"coordinates":[151.31755065900001,-33.521396637],"type":"Point"}
}