{
  "type": "Feature",
  "properties": {
    "iso:country":"AU",
    "sg:address":"Suite 6, 35- 47 Missenden Rd",
    "sg:city":"Camperdown",
    "sg:classifiers":[
        {
            "category":"Health Services",
            "subcategory":"Doctor",
            "type":"Services"
        }
    ],
    "sg:phone":"+61 2 9550 4866",
    "sg:postcode":"2050",
    "sg:province":"NSW",
    "sg:tags":[
        "medical",
        "practitioner"
    ],
    "wof:name":"Lye A",
    "wof:placetype":"venue"
},
  "geometry": {"coordinates":[151.180527,-33.887859],"type":"Point"}
}