{
  "type": "Feature",
  "properties": {
    "iso:country":"AU",
    "sg:address":"7 Bailey Pl",
    "sg:city":"Tura Beach",
    "sg:classifiers":[
        {
            "category":"Professional",
            "subcategory":"Printing & Photocopies",
            "type":"Services"
        }
    ],
    "sg:phone":"+61 2 6495 0183",
    "sg:postcode":"2548",
    "sg:province":"NSW",
    "sg:tags":[
        "publishing",
        "desktop"
    ],
    "wof:name":"Bell's Ready Print",
    "wof:placetype":"venue"
},
  "geometry": {"coordinates":[149.92593383799999,-36.8700256348],"type":"Point"}
}