{
  "type": "Feature",
  "properties": {
    "iso:country":"AU",
    "sg:address":"U4/ 7 Dual Ave",
    "sg:city":"Warana",
    "sg:classifiers":[
        {
            "category":"Building & Trades",
            "subcategory":"Construction",
            "type":"Services"
        }
    ],
    "sg:phone":"+61 7 5437 7340",
    "sg:postcode":"4575",
    "sg:province":"QLD",
    "sg:tags":[
        "contractor"
    ],
    "wof:name":"P J Liebke Building Pty Ltd",
    "wof:placetype":"venue"
},
  "geometry": {"coordinates":[153.123886,-26.728584],"type":"Point"}
}