{
  "type": "Feature",
  "properties": {
    "iso:country":"AU",
    "sg:address":"High & Miebusch Sts",
    "sg:city":"Toowoomba",
    "sg:classifiers":[
        {
            "category":"Autos & Motor Vehicles",
            "subcategory":"Fuel & Gas Station",
            "type":"Retail Goods"
        }
    ],
    "sg:phone":"+61 7 4635 4639",
    "sg:postcode":"4350",
    "sg:province":"QLD",
    "wof:name":"BP Australia Limited",
    "wof:placetype":"venue"
},
  "geometry": {"coordinates":[151.875641,-27.55761],"type":"Point"}
}