{
  "type": "Feature",
  "properties": {
    "addr:full":"Cheviot Rd Moonah West TAS 7009",
    "addr:postcode":"7009",
    "addr:street":"Cheviot Rd",
    "iso:country":"AU",
    "sg:address":"Cheviot Rd",
    "sg:city":"Moonah West",
    "sg:classifiers":[
        {
            "category":"Education",
            "subcategory":"School",
            "type":"Public Place"
        }
    ],
    "sg:phone":"+61 3 6272 1711",
    "sg:postcode":"7009",
    "sg:province":"TAS",
    "sg:tags":[
        "co-educational"
    ],
    "wof:name":"Hilliard Christian School",
    "wof:placetype":"venue"
},
  "geometry": {"coordinates":[147.28384399399999,-42.8519935608],"type":"Point"}
}