{
  "type": "Feature",
  "properties": {
    "addr:full":"Shed 5 / 206 Dyson Rd Lonsdale SA 5160",
    "addr:housenumber":"5 / 206",
    "addr:postcode":"5160",
    "addr:street":"Dyson Rd",
    "iso:country":"AU",
    "sg:address":"Shed 5 / 206 Dyson Rd",
    "sg:city":"Lonsdale",
    "sg:classifiers":[
        {
            "category":"Autos & Motor Vehicles",
            "subcategory":"Motorcycle Sales",
            "type":"Retail Goods"
        }
    ],
    "sg:phone":"+61 427 972 244",
    "sg:postcode":"5160",
    "sg:province":"SA",
    "sg:tags":[
        "part",
        "recyclers",
        "cycle"
    ],
    "wof:name":"Brad's Bikes & Bits",
    "wof:placetype":"venue"
},
  "geometry": {"coordinates":[138.491577148,-35.1174659729],"type":"Point"}
}