{
  "type": "Feature",
  "properties": {
    "addr:full":"3/ 18 Bauhinia St Nightcliff NT 0810",
    "addr:housenumber":"/ 18",
    "addr:postcode":"nt 0810",
    "addr:street":"Bauhinia St",
    "iso:country":"AU",
    "sg:address":"3/ 18 Bauhinia St",
    "sg:city":"Nightcliff",
    "sg:classifiers":[
        {
            "category":"Organizations",
            "subcategory":"Community Association",
            "type":"Services"
        }
    ],
    "sg:phone":"+61 8 8948 5228",
    "sg:postcode":"0810",
    "sg:province":"NT",
    "sg:tags":[
        "organisation",
        "family",
        "welfare"
    ],
    "wof:name":"Alzheimer's Australia NT Inc",
    "wof:placetype":"venue"
},
  "geometry": {"coordinates":[130.85055542000001,-12.3821287155],"type":"Point"}
}