{
  "type": "Feature",
  "properties": {
    "iso:country":"AU",
    "sg:address":"109 Webster St",
    "sg:city":"Ballarat",
    "sg:classifiers":[
        {
            "category":"Retail",
            "subcategory":"Event Space",
            "type":"Services"
        }
    ],
    "sg:phone":"+61 3 5331 8829",
    "sg:postcode":"3350",
    "sg:province":"VIC",
    "sg:tags":[
        "venue",
        "reception",
        "wedding"
    ],
    "wof:name":"Nieder Weisel",
    "wof:placetype":"venue"
},
  "geometry": {"coordinates":[143.84683200000001,-37.55637],"type":"Point"}
}