{
  "type": "Feature",
  "properties": {
    "addr:full":"34 First Ave Sawtell NSW 2452",
    "addr:housenumber":"34",
    "addr:postcode":"2452",
    "addr:street":"First Ave",
    "iso:country":"AU",
    "sg:address":"34 First Ave",
    "sg:city":"Sawtell",
    "sg:classifiers":[
        {
            "category":"Professional",
            "subcategory":"Accounting & Tax Preparation",
            "type":"Services"
        }
    ],
    "sg:phone":"+61 2 6658 3366",
    "sg:postcode":"2452",
    "sg:province":"NSW",
    "sg:tags":[
        "consultant",
        "taxation"
    ],
    "wof:name":"Bale Roger",
    "wof:placetype":"venue"
},
  "geometry": {"coordinates":[153.10067699999999,-30.368593],"type":"Point"}
}