{
  "type": "Feature",
  "properties": {
    "addr:full":"82 Princes Hwy Moruya NSW 2537",
    "addr:housenumber":"82",
    "addr:postcode":"2537",
    "addr:street":"Princes Hwy",
    "iso:country":"AU",
    "sg:address":"82 Princes Hwy",
    "sg:city":"Moruya",
    "sg:classifiers":[
        {
            "category":"Travel",
            "subcategory":"Hotels & Motels",
            "type":"Entertainment"
        }
    ],
    "sg:phone":"+61 2 4474 2722",
    "sg:postcode":"2537",
    "sg:province":"NSW",
    "wof:name":"Motel Luhana",
    "wof:placetype":"venue"
},
  "geometry": {"coordinates":[150.08172607399999,-35.9122009277],"type":"Point"}
}