{
  "type": "Feature",
  "properties": {
    "iso:country":"AU",
    "sg:address":"Parkers Rd",
    "sg:city":"Cloverlea",
    "sg:classifiers":[
        {
            "category":"Retail",
            "subcategory":"Animal Services",
            "type":"Services"
        }
    ],
    "sg:phone":"+61 3 5627 8364",
    "sg:postcode":"3822",
    "sg:province":"VIC",
    "sg:tags":[
        "breeder",
        "sheep",
        "stud",
        "cattle"
    ],
    "wof:name":"Solney Friesian Stud",
    "wof:placetype":"venue"
},
  "geometry": {"coordinates":[146.013916,-38.218575],"type":"Point"}
}