{
  "type": "Feature",
  "properties": {
    "iso:country":"AU",
    "sg:address":"88 Perouse Ave",
    "sg:city":"San Remo",
    "sg:classifiers":[
        {
            "category":"Professional",
            "subcategory":"Art Services",
            "type":"Services"
        }
    ],
    "sg:phone":"+61 2 4390 8505",
    "sg:postcode":"2262",
    "sg:province":"NSW",
    "sg:tags":[
        "decorator",
        "painter"
    ],
    "wof:name":"Ron Fisher",
    "wof:placetype":"venue"
},
  "geometry": {"coordinates":[151.526535,-33.212234],"type":"Point"}
}