{
  "type": "Feature",
  "properties": {
    "addr:full":"19 Burns Bay Rd Lane Cove NSW 2066",
    "addr:housenumber":"19",
    "addr:postcode":"2066",
    "addr:street":"Burns Bay Rd",
    "iso:country":"AU",
    "sg:address":"19 Burns Bay Rd",
    "sg:city":"Lane Cove",
    "sg:classifiers":[
        {
            "category":"Fast Food",
            "type":"Food & Drink"
        }
    ],
    "sg:phone":"+61 2 9427 1818",
    "sg:postcode":"2066",
    "sg:province":"NSW",
    "sg:tags":[
        "away",
        "take"
    ],
    "wof:name":"Tow Yin Sunny's Kitchen",
    "wof:placetype":"venue"
},
  "geometry": {"coordinates":[151.169067383,-33.8144416809],"type":"Point"}
}