{
  "type": "Feature",
  "properties": {
    "iso:country":"AU",
    "sg:address":"15 Haskings St",
    "sg:city":"Caboolture",
    "sg:classifiers":[
        {
            "category":"Health Services",
            "subcategory":"Doctor",
            "type":"Services"
        }
    ],
    "sg:phone":"+61 7 5492 5188",
    "sg:postcode":"4510",
    "sg:province":"QLD",
    "sg:tags":[
        "medical",
        "practitioner"
    ],
    "wof:name":"Herd, C L J",
    "wof:placetype":"venue"
},
  "geometry": {"coordinates":[152.950378,-27.083071],"type":"Point"}
}