{
  "type": "Feature",
  "properties": {
    "addr:full":"110 Lakes Rd Mandurah WA 6210",
    "addr:housenumber":"110",
    "addr:postcode":"6210",
    "addr:street":"Lakes Rd",
    "iso:country":"AU",
    "sg:address":"110 Lakes Rd",
    "sg:city":"Mandurah",
    "sg:classifiers":[
        {
            "category":"Health Services",
            "subcategory":"Doctor",
            "type":"Services"
        }
    ],
    "sg:phone":"+61 8 9531 8331",
    "sg:postcode":"6210",
    "sg:province":"WA",
    "sg:tags":[
        "medical",
        "practitioner"
    ],
    "wof:name":"Imaging The South",
    "wof:placetype":"venue"
},
  "geometry": {"coordinates":[115.81997699999999,-32.510883],"type":"Point"}
}