{
  "type": "Feature",
  "properties": {
    "addr:full":"466 Geelong Rd West Footscray VIC 3012",
    "addr:housenumber":"466",
    "addr:postcode":"3012",
    "addr:street":"Geelong Rd",
    "iso:country":"AU",
    "sg:address":"466 Geelong Rd",
    "sg:city":"West Footscray",
    "sg:classifiers":[
        {
            "category":"Autos & Motor Vehicles",
            "subcategory":"Auto Supplies",
            "type":"Retail Goods"
        }
    ],
    "sg:phone":"+61 3 9314 7878",
    "sg:postcode":"3012",
    "sg:province":"VIC",
    "sg:tags":[
        "tyre"
    ],
    "wof:name":"Pit Stop Tyres",
    "wof:placetype":"venue"
},
  "geometry": {"coordinates":[144.86343383799999,-37.8124847412],"type":"Point"}
}