{
  "type": "Feature",
  "properties": {
    "addr:full":"Unit 29/ 48 Moondine Drv Wembley WA 6014",
    "addr:housenumber":"/ 48",
    "addr:postcode":"6014",
    "addr:street":"Moondine Drv",
    "iso:country":"AU",
    "sg:address":"Unit 29/ 48 Moondine Drv",
    "sg:city":"Wembley",
    "sg:classifiers":[
        {
            "category":"Professional",
            "subcategory":"Art Services",
            "type":"Services"
        }
    ],
    "sg:phone":"+61 415 058 073",
    "sg:postcode":"6014",
    "sg:province":"WA",
    "sg:tags":[
        "commercial",
        "artist"
    ],
    "wof:name":"PR Simulations",
    "wof:placetype":"venue"
},
  "geometry": {"coordinates":[115.810943603,-31.9288463593],"type":"Point"}
}