{
  "type": "Feature",
  "properties": {
    "addr:full":"97 Upper Heidelberg Rd Ivanhoe VIC 3079",
    "addr:housenumber":"97",
    "addr:postcode":"3079",
    "addr:street":"Upper Heidelberg Rd",
    "iso:country":"AU",
    "sg:address":"97 Upper Heidelberg Rd",
    "sg:city":"Ivanhoe",
    "sg:classifiers":[
        {
            "category":"Shopping",
            "subcategory":"Clothing, Apparel, & Fashions",
            "type":"Retail Goods"
        }
    ],
    "sg:phone":"+61 3 9497 1009",
    "sg:postcode":"3079",
    "sg:province":"VIC",
    "sg:tags":[
        "lady",
        "wear"
    ],
    "wof:name":"Roxanne Fashions",
    "wof:placetype":"venue"
},
  "geometry": {"coordinates":[145.041549683,-37.7692756653],"type":"Point"}
}