{
  "type": "Feature",
  "properties": {
    "addr:full":"94B Commercial St West Mt Gambier SA 5290",
    "addr:housenumber":"94b",
    "addr:postcode":"5290",
    "addr:street":"Commercial St West",
    "iso:country":"AU",
    "sg:address":"94B Commercial St West",
    "sg:city":"Mt Gambier",
    "sg:classifiers":[
        {
            "category":"Retail",
            "subcategory":"Auto Repair",
            "type":"Services"
        }
    ],
    "sg:phone":"+61 8 8723 1365",
    "sg:postcode":"5290",
    "sg:province":"SA",
    "sg:tags":[
        "repairer",
        "motor",
        "engineer"
    ],
    "wof:name":"Peter Rogers Auto Repairs",
    "wof:placetype":"venue"
},
  "geometry": {"coordinates":[140.775406,-37.826546],"type":"Point"}
}