{
  "type": "Feature",
  "properties": {
    "iso:country":"AU",
    "sg:address":"3 Lithgow St",
    "sg:city":"Fyshwick",
    "sg:classifiers":[
        {
            "category":"Building & Trades",
            "subcategory":"Plumbing",
            "type":"Services"
        }
    ],
    "sg:phone":"+61 2 6280 4833",
    "sg:postcode":"2609",
    "sg:province":"ACT",
    "sg:tags":[
        "sink"
    ],
    "wof:name":"Fiori",
    "wof:placetype":"venue"
},
  "geometry": {"coordinates":[149.16346740700001,-35.3304786682],"type":"Point"}
}