{
  "type": "Feature",
  "properties": {
    "addr:full":"17 Maryvale Ave Liverpool NSW 2170",
    "addr:housenumber":"17",
    "addr:postcode":"2170",
    "addr:street":"Maryvale Ave",
    "iso:country":"AU",
    "sg:address":"17 Maryvale Ave",
    "sg:city":"Liverpool",
    "sg:classifiers":[
        {
            "category":"Personal",
            "subcategory":"Beauty Salon",
            "type":"Services"
        }
    ],
    "sg:phone":"+61 2 9822 7151",
    "sg:postcode":"2170",
    "sg:province":"NSW",
    "wof:name":"Beyond Healing",
    "wof:placetype":"venue"
},
  "geometry": {"coordinates":[150.904174805,-33.9236488342],"type":"Point"}
}