{
  "type": "Feature",
  "properties": {
    "addr:full":"U3/ 35 Cessna Drv Caboolture QLD 4510",
    "addr:housenumber":"35",
    "addr:postcode":"4510",
    "addr:street":"U3 /;Cessna Drv",
    "iso:country":"AU",
    "sg:address":"U3/ 35 Cessna Drv",
    "sg:city":"Caboolture",
    "sg:classifiers":[
        {
            "category":"Wholesale",
            "subcategory":"Machinery & Supplies",
            "type":"Manufacturing & Wholesale Goods"
        }
    ],
    "sg:phone":"+61 7 5428 1314",
    "sg:postcode":"4510",
    "sg:province":"QLD",
    "sg:tags":[
        "equipment",
        "welding"
    ],
    "wof:name":"The Welding Shed",
    "wof:placetype":"venue"
},
  "geometry": {"coordinates":[152.98594700000001,-27.085272],"type":"Point"}
}