{
  "type": "Feature",
  "properties": {
    "addr:full":"240 macauley St Albury NSW 2640",
    "addr:housenumber":"240",
    "addr:postcode":"2640",
    "addr:street":"Macauley St",
    "iso:country":"AU",
    "sg:address":"240 macauley St",
    "sg:city":"Albury",
    "sg:classifiers":[
        {
            "category":"Home & Garden",
            "subcategory":"Building Materials",
            "type":"Retail Goods"
        }
    ],
    "sg:phone":"+61 2 6041 3633",
    "sg:postcode":"2640",
    "sg:province":"NSW",
    "sg:tags":[
        "insulation"
    ],
    "wof:name":"Incelite Insulation",
    "wof:placetype":"venue"
},
  "geometry": {"coordinates":[146.919265747,-36.0952301025],"type":"Point"}
}