{
  "type": "Feature",
  "properties": {
    "iso:country":"AU",
    "sg:address":"521 Main St",
    "sg:city":"Bairnsdale",
    "sg:classifiers":[
        {
            "category":"Wholesale",
            "subcategory":"Machinery & Supplies",
            "type":"Manufacturing & Wholesale Goods"
        }
    ],
    "sg:phone":"+61 3 5153 1555",
    "sg:postcode":"3875",
    "sg:province":"VIC",
    "sg:tags":[
        "bearing",
        "bushing"
    ],
    "wof:name":"B.J-Bearings Pty Ltd",
    "wof:placetype":"venue"
},
  "geometry": {"coordinates":[147.827224731,-37.7086296082],"type":"Point"}
}