{
  "type": "Feature",
  "properties": {
    "addr:full":"5 Jedda Pl Mona Vale NSW 2103",
    "addr:housenumber":"5",
    "addr:postcode":"2103",
    "addr:street":"Jedda Pl",
    "iso:country":"AU",
    "sg:address":"5 Jedda Pl",
    "sg:city":"Mona Vale",
    "sg:classifiers":[
        {
            "category":"Social Services",
            "subcategory":"Adult Care",
            "type":"Services"
        }
    ],
    "sg:phone":"+61 2 9970 8339",
    "sg:postcode":"2103",
    "sg:province":"NSW",
    "sg:tags":[
        "towing"
    ],
    "wof:name":"M.R. Towing",
    "wof:placetype":"venue"
},
  "geometry": {"coordinates":[151.30752563499999,-33.6713752747],"type":"Point"}
}