{
  "type": "Feature",
  "properties": {
    "addr:full":"21 Welsford St Shepparton VIC 3630",
    "addr:housenumber":"21",
    "addr:postcode":"3630",
    "addr:street":"Welsford St",
    "iso:country":"AU",
    "sg:address":"21 Welsford St",
    "sg:city":"Shepparton",
    "sg:classifiers":[
        {
            "category":"Government",
            "subcategory":"Court House",
            "type":"Public Place"
        }
    ],
    "sg:phone":"+61 3 5823 7000",
    "sg:postcode":"3630",
    "sg:province":"VIC",
    "sg:tags":[
        "personal",
        "marriage",
        "family",
        "counselling"
    ],
    "wof:name":"Goulburn Valley Family Care Inc.",
    "wof:placetype":"venue"
},
  "geometry": {"coordinates":[145.39878845199999,-36.3751869202],"type":"Point"}
}