{
  "type": "Feature",
  "properties": {
    "addr:full":"2/ 121 Barker St Casino NSW 2470",
    "addr:housenumber":"/ 121",
    "addr:postcode":"2470",
    "addr:street":"Barker St",
    "iso:country":"AU",
    "sg:address":"2/ 121 Barker St",
    "sg:city":"Casino",
    "sg:classifiers":[
        {
            "category":"Professional",
            "subcategory":"Employment Agencies",
            "type":"Services"
        }
    ],
    "sg:phone":"+61 2 6662 3720",
    "sg:postcode":"2470",
    "sg:province":"NSW",
    "wof:name":"Wesley Uniting Employment",
    "wof:placetype":"venue"
},
  "geometry": {"coordinates":[153.04745483400001,-28.8649692535],"type":"Point"}
}