{
  "type": "Feature",
  "properties": {
    "iso:country":"AU",
    "sg:address":"59 Davies Rd",
    "sg:city":"Claremont",
    "sg:classifiers":[
        {
            "category":"Personal",
            "subcategory":"Skin Care",
            "type":"Services"
        }
    ],
    "sg:phone":"+61 8 9284 6565",
    "sg:postcode":"6010",
    "sg:province":"WA",
    "sg:tags":[
        "merchant",
        "hide"
    ],
    "wof:name":"Wardright Trading Pty Ltd",
    "wof:placetype":"venue"
},
  "geometry": {"coordinates":[115.781478882,-31.9764137268],"type":"Point"}
}