{
  "type": "Feature",
  "properties": {
    "addr:full":"25 Kirkwood Rd Eaglehawk VIC 3556",
    "addr:housenumber":"25",
    "addr:postcode":"3556",
    "addr:street":"Kirkwood Rd",
    "iso:country":"AU",
    "sg:address":"25 Kirkwood Rd",
    "sg:city":"Eaglehawk",
    "sg:classifiers":[
        {
            "category":"Professional",
            "subcategory":"Secretarial Services",
            "type":"Services"
        }
    ],
    "sg:phone":"+61 3 5446 2279",
    "sg:postcode":"3556",
    "sg:province":"VIC",
    "sg:tags":[
        "typing"
    ],
    "wof:name":"Katie's Secretarial Services",
    "wof:placetype":"venue"
},
  "geometry": {"coordinates":[144.250244141,-36.7135734558],"type":"Point"}
}