{
  "type": "Feature",
  "properties": {
    "addr:full":"Suite 2, 163 Canning Hwy East Fremantle WA 6158",
    "addr:housenumber":"163",
    "addr:postcode":"6158",
    "addr:street":"Canning Hwy",
    "iso:country":"AU",
    "sg:address":"Suite 2, 163 Canning Hwy",
    "sg:city":"East Fremantle",
    "sg:classifiers":[
        {
            "category":"Banks & Credit Unions",
            "subcategory":"Financial Services",
            "type":"Services"
        }
    ],
    "sg:phone":"+61 8 9339 0922",
    "sg:postcode":"6158",
    "sg:province":"WA",
    "sg:tags":[
        "planning"
    ],
    "wof:name":"Genesys Wealth Advisers",
    "wof:placetype":"venue"
},
  "geometry": {"coordinates":[115.765472,-32.041046],"type":"Point"}
}