{
  "type": "Feature",
  "properties": {
    "addr:full":"286 Harborne St Glendalough WA 6016",
    "addr:housenumber":"286",
    "addr:postcode":"6016",
    "addr:street":"Harborne St",
    "iso:country":"AU",
    "sg:address":"286 Harborne St",
    "sg:city":"Glendalough",
    "sg:classifiers":[
        {
            "category":"Health Services",
            "subcategory":"Dentist",
            "type":"Services"
        }
    ],
    "sg:phone":"+61 8 9242 4677",
    "sg:postcode":"6016",
    "sg:province":"WA",
    "wof:name":"Harborne Dental",
    "wof:placetype":"venue"
},
  "geometry": {"coordinates":[115.81993866000001,-31.9194717407],"type":"Point"}
}