{
  "type": "Feature",
  "properties": {
    "addr:full":"17 Palmer Rd Richmond VIC 3121",
    "addr:housenumber":"17",
    "addr:postcode":"3121",
    "addr:street":"Palmer Rd",
    "iso:country":"AU",
    "sg:address":"17 Palmer Rd",
    "sg:city":"Richmond",
    "sg:classifiers":[
        {
            "category":"Manufacturing",
            "subcategory":"Textiles",
            "type":"Manufacturing & Wholesale Goods"
        }
    ],
    "sg:phone":"+61 3 9428 9311",
    "sg:postcode":"3121",
    "sg:province":"VIC",
    "sg:tags":[
        "fibre"
    ],
    "wof:name":"K J Textiles Pty Ltd",
    "wof:placetype":"venue"
},
  "geometry": {"coordinates":[145.00474548299999,-37.818649292],"type":"Point"}
}