{
  "type": "Feature",
  "properties": {
    "iso:country":"AU",
    "sg:address":"22 Carnarvon St",
    "sg:city":"Broome",
    "sg:classifiers":[
        {
            "category":"Arts & Performance",
            "subcategory":"Art Gallery",
            "type":"Entertainment"
        }
    ],
    "sg:phone":"+61 8 9193 5633",
    "sg:postcode":"6725",
    "sg:province":"WA",
    "wof:name":"Old Broome Lockup Gallery",
    "wof:placetype":"venue"
},
  "geometry": {"coordinates":[122.24369812,-17.9537467957],"type":"Point"}
}