{
  "type": "Feature",
  "properties": {
    "addr:full":"16 James St Burleigh Heads QLD 4220",
    "addr:housenumber":"16",
    "addr:postcode":"4220",
    "addr:street":"James St",
    "iso:country":"AU",
    "sg:address":"16 James St",
    "sg:city":"Burleigh Heads",
    "sg:classifiers":[
        {
            "category":"Travel",
            "subcategory":"Travel Agent",
            "type":"Entertainment"
        }
    ],
    "sg:phone":"+61 13 18 66",
    "sg:postcode":"4220",
    "sg:province":"QLD",
    "sg:tags":[
        "consultant"
    ],
    "wof:name":"Flight Centre",
    "wof:placetype":"venue"
},
  "geometry": {"coordinates":[153.45112609899999,-28.0894546509],"type":"Point"}
}