{
  "type": "Feature",
  "properties": {
    "iso:country":"AU",
    "sg:address":"Unit 2/ 17 Hargraves Pl",
    "sg:city":"Wetherill Park",
    "sg:classifiers":[
        {
            "category":"Retail",
            "subcategory":"Auto Repair",
            "type":"Services"
        }
    ],
    "sg:phone":"+61 2 9756 2515",
    "sg:postcode":"2164",
    "sg:province":"NSW",
    "sg:tags":[
        "electrical"
    ],
    "wof:name":"Greenaway Auto Electrical Service",
    "wof:placetype":"venue"
},
  "geometry": {"coordinates":[150.89768981899999,-33.8426094055],"type":"Point"}
}