{
  "type": "Feature",
  "properties": {
    "iso:country":"AU",
    "sg:address":"Eucalyptus Drv",
    "sg:city":"Macquarie Fields",
    "sg:classifiers":[
        {
            "category":"Education",
            "subcategory":"School",
            "type":"Public Place"
        }
    ],
    "sg:phone":"+61 2 9605 4391",
    "sg:postcode":"2564",
    "sg:province":"NSW",
    "sg:tags":[
        "state",
        "-",
        "nsw"
    ],
    "wof:name":"Guise Public School",
    "wof:placetype":"venue"
},
  "geometry": {"coordinates":[150.896118164,-33.9864463806],"type":"Point"}
}