{
  "type": "Feature",
  "properties": {
    "iso:country":"AU",
    "sg:address":"Puddledock Rd",
    "sg:city":"Armidale",
    "sg:classifiers":[
        {
            "category":"Professional",
            "subcategory":"Computer Services",
            "type":"Services"
        }
    ],
    "sg:phone":"+61 2 6772 9037",
    "sg:postcode":"2350",
    "sg:province":"NSW",
    "sg:tags":[
        "equipment",
        "networking",
        "installation"
    ],
    "wof:name":"New England Data & Aerial Solutions",
    "wof:placetype":"venue"
},
  "geometry": {"coordinates":[151.684356689,-30.4633407593],"type":"Point"}
}