{
  "type": "Feature",
  "properties": {
    "addr:full":"6 Highview Ave Manly Vale NSW 2093",
    "addr:housenumber":"6",
    "addr:postcode":"2093",
    "addr:street":"Highview Ave",
    "iso:country":"AU",
    "sg:address":"6 Highview Ave",
    "sg:city":"Manly Vale",
    "sg:classifiers":[
        {
            "category":"Education",
            "subcategory":"Special Training",
            "type":"Public Place"
        }
    ],
    "sg:phone":"+61 2 9948 8417",
    "sg:postcode":"2093",
    "sg:province":"NSW",
    "sg:tags":[
        "development"
    ],
    "wof:name":"Cupitt Faulkner Group, The",
    "wof:placetype":"venue"
},
  "geometry": {"coordinates":[151.264892578,-33.7857246399],"type":"Point"}
}