{
  "type": "Feature",
  "properties": {
    "addr:full":"166 Shellharbour Rd Kemblawarra NSW 2505",
    "addr:housenumber":"166",
    "addr:postcode":"2505",
    "addr:street":"Shellharbour Rd",
    "iso:country":"AU",
    "sg:address":"166 Shellharbour Rd",
    "sg:city":"Kemblawarra",
    "sg:classifiers":[
        {
            "category":"Banks & Credit Unions",
            "subcategory":"Investment Brokerage",
            "type":"Services"
        }
    ],
    "sg:phone":"+61 2 4274 4858",
    "sg:postcode":"2505",
    "sg:province":"NSW",
    "sg:tags":[
        "radiator",
        "motor"
    ],
    "wof:name":"Illawarra Radiators",
    "wof:placetype":"venue"
},
  "geometry": {"coordinates":[150.893021,-34.492619],"type":"Point"}
}