{
  "type": "Feature",
  "properties": {
    "addr:full":"675 Burwood Rd Hawthorn East VIC 3123",
    "addr:housenumber":"675",
    "addr:postcode":"3123",
    "addr:street":"Burwood Rd",
    "iso:country":"AU",
    "sg:address":"675 Burwood Rd",
    "sg:city":"Hawthorn East",
    "sg:classifiers":[
        {
            "category":"Banks & Credit Unions",
            "subcategory":"Bank",
            "type":"Services"
        }
    ],
    "sg:phone":"+61 13 13 14",
    "sg:postcode":"3123",
    "sg:province":"VIC",
    "wof:name":"ANZ",
    "wof:placetype":"venue"
},
  "geometry": {"coordinates":[145.046630859,-37.8237762451],"type":"Point"}
}