{
  "type": "Feature",
  "properties": {
    "addr:full":"39 Barker St Casino NSW 2470",
    "addr:housenumber":"39",
    "addr:postcode":"2470",
    "addr:street":"Barker St",
    "iso:country":"AU",
    "sg:address":"39 Barker St",
    "sg:city":"Casino",
    "sg:classifiers":[
        {
            "category":"Organizations",
            "subcategory":"Non-profit Organization",
            "type":"Services"
        }
    ],
    "sg:phone":"+61 2 6662 2333",
    "sg:postcode":"2470",
    "sg:province":"NSW",
    "sg:tags":[
        "support",
        "disability",
        "organisation"
    ],
    "wof:name":"On-Focus Inc",
    "wof:placetype":"venue"
},
  "geometry": {"coordinates":[153.04620361299999,-28.8647842407],"type":"Point"}
}