{
  "type": "Feature",
  "properties": {
    "iso:country":"AU",
    "sg:address":"Unit 4, 16 Dalton St",
    "sg:city":"Mittagong",
    "sg:classifiers":[
        {
            "category":"Retail",
            "subcategory":"Laundry & Dry Cleaning",
            "type":"Services"
        }
    ],
    "sg:phone":"+61 2 4872 1242",
    "sg:postcode":"2575",
    "sg:province":"NSW",
    "sg:tags":[
        "wholesaler",
        "underclothing",
        "mfrs"
    ],
    "wof:name":"Reflex Sports Pty Ltd",
    "wof:placetype":"venue"
},
  "geometry": {"coordinates":[150.432983398,-34.4526367188],"type":"Point"}
}