{
  "type": "Feature",
  "properties": {
    "iso:country":"AU",
    "sg:address":"Unit 10, 63 Marina Blv",
    "sg:city":"Cullen Bay",
    "sg:classifiers":[
        {
            "category":"Professional",
            "subcategory":"Business Services",
            "type":"Services"
        }
    ],
    "sg:phone":"+61 8 8941 5122",
    "sg:postcode":"0820",
    "sg:province":"NT",
    "sg:tags":[
        "fashion",
        "agent"
    ],
    "wof:name":"Australian Image Company",
    "wof:placetype":"venue"
},
  "geometry": {"coordinates":[130.821365356,-12.4509496689],"type":"Point"}
}