{
  "type": "Feature",
  "properties": {
    "iso:country":"AU",
    "sg:address":"119 Delta St",
    "sg:city":"Geebung",
    "sg:classifiers":[
        {
            "category":"Shopping",
            "subcategory":"Crafts & Fabrics",
            "type":"Retail Goods"
        }
    ],
    "sg:phone":"+61 7 3265 2544",
    "sg:postcode":"4034",
    "sg:province":"QLD",
    "sg:tags":[
        "synthetic",
        "canvas",
        "product"
    ],
    "wof:name":"Sun N' Surf International Tent Manufacturers",
    "wof:placetype":"venue"
},
  "geometry": {"coordinates":[153.054016,-27.366385],"type":"Point"}
}