{
  "type": "Feature",
  "properties": {
    "iso:country":"AU",
    "sg:address":"Unit 3/ 43 Forbes St",
    "sg:city":"Hawthorne",
    "sg:classifiers":[
        {
            "category":"Personal",
            "type":"Services"
        }
    ],
    "sg:phone":"+61 422 246 096",
    "sg:postcode":"4171",
    "sg:province":"QLD",
    "sg:tags":[
        "gift"
    ],
    "wof:name":"Boutique Gifts",
    "wof:placetype":"venue"
},
  "geometry": {"coordinates":[153.062332153,-27.4667568207],"type":"Point"}
}