{
  "type": "Feature",
  "properties": {
    "iso:country":"AU",
    "sg:address":"46- 48 Wagawn St",
    "sg:city":"Tugun",
    "sg:classifiers":[
        {
            "category":"Retail",
            "subcategory":"Auto Rental",
            "type":"Services"
        }
    ],
    "sg:phone":"+61 7 5534 5899",
    "sg:postcode":"4224",
    "sg:province":"QLD",
    "sg:tags":[
        "car",
        "hire",
        "minibus"
    ],
    "wof:name":"Rolo Rent-A-Car",
    "wof:placetype":"venue"
},
  "geometry": {"coordinates":[153.49101257300001,-28.140914917],"type":"Point"}
}