{
  "type": "Feature",
  "properties": {
    "addr:full":"Unit 26, 45 Deakin St Kangaroo Point QLD 4169",
    "addr:housenumber":"45",
    "addr:postcode":"4169",
    "addr:street":"Deakin St",
    "iso:country":"AU",
    "sg:address":"Unit 26, 45 Deakin St",
    "sg:city":"Kangaroo Point",
    "sg:classifiers":[
        {
            "category":"Wholesale",
            "subcategory":"Construction Materials",
            "type":"Manufacturing & Wholesale Goods"
        }
    ],
    "sg:phone":"+61 417 753 442",
    "sg:postcode":"4169",
    "sg:province":"QLD",
    "sg:tags":[
        "wholesaler",
        "lighting",
        "mfrs",
        "accessory"
    ],
    "wof:name":"Corsair Trading Pty Ltd",
    "wof:placetype":"venue"
},
  "geometry": {"coordinates":[153.036209106,-27.471162796],"type":"Point"}
}