{
  "type": "Feature",
  "properties": {
    "addr:full":"75 Tyers La Keysborough VIC 3173",
    "addr:housenumber":"75",
    "addr:postcode":"3173",
    "addr:street":"Tyers La",
    "iso:country":"AU",
    "sg:address":"75 Tyers La",
    "sg:city":"Keysborough",
    "sg:classifiers":[
        {
            "category":"Building & Trades",
            "subcategory":"Equipment Rental",
            "type":"Services"
        }
    ],
    "sg:phone":"+61 3 9701 5321",
    "sg:postcode":"3173",
    "sg:province":"VIC",
    "sg:tags":[
        "party",
        "hire"
    ],
    "wof:name":"Bee Cool Coolroom",
    "wof:placetype":"venue"
},
  "geometry": {"coordinates":[145.16679382300001,-38.007976532],"type":"Point"}
}