{
  "type": "Feature",
  "properties": {
    "addr:full":"20 Dandarangan St Moora WA 6510",
    "addr:housenumber":"20",
    "addr:postcode":"6510",
    "addr:street":"Dandarangan St",
    "iso:country":"AU",
    "sg:address":"20 Dandarangan St",
    "sg:city":"Moora",
    "sg:classifiers":[
        {
            "category":"Food & Beverages",
            "subcategory":"Liquor & Beverages",
            "type":"Retail Goods"
        }
    ],
    "sg:phone":"+61 8 9651 1380",
    "sg:postcode":"6510",
    "sg:province":"WA",
    "sg:tags":[
        "store"
    ],
    "wof:name":"Cellarbrations",
    "wof:placetype":"venue"
},
  "geometry": {"coordinates":[116.006844,-30.639011],"type":"Point"}
}