{
  "type": "Feature",
  "properties": {
    "addr:full":"14 Edison Drv Golden Grove SA 5125",
    "addr:housenumber":"14",
    "addr:postcode":"5125",
    "addr:street":"Edison Drv",
    "iso:country":"AU",
    "sg:address":"14 Edison Drv",
    "sg:city":"Golden Grove",
    "sg:classifiers":[
        {
            "category":"Wholesale",
            "subcategory":"Machinery & Supplies",
            "type":"Manufacturing & Wholesale Goods"
        }
    ],
    "sg:phone":"+61 8 8251 7344",
    "sg:postcode":"5125",
    "sg:province":"SA",
    "sg:tags":[
        "equipment",
        "hydraulic"
    ],
    "wof:name":"G & R Hydraulics Pty Ltd",
    "wof:placetype":"venue"
},
  "geometry": {"coordinates":[138.71196,-34.790741],"type":"Point"}
}