{
  "type": "Feature",
  "properties": {
    "addr:full":"323 Prospect Rd Blair Athol SA 5084",
    "addr:housenumber":"323",
    "addr:postcode":"5084",
    "addr:street":"Prospect Rd",
    "iso:country":"AU",
    "sg:address":"323 Prospect Rd",
    "sg:city":"Blair Athol",
    "sg:classifiers":[
        {
            "category":"Personal",
            "subcategory":"Beauty Salon",
            "type":"Services"
        }
    ],
    "sg:phone":"+61 8 8262 2864",
    "sg:postcode":"5084",
    "sg:province":"SA",
    "sg:tags":[
        "hairdresser"
    ],
    "wof:name":"Blair Athol Hair Design",
    "wof:placetype":"venue"
},
  "geometry": {"coordinates":[138.59280395499999,-34.8662910461],"type":"Point"}
}