{
  "type": "Feature",
  "properties": {
    "addr:full":"95 Unley Rd Unley SA 5061",
    "addr:housenumber":"95",
    "addr:postcode":"5061",
    "addr:street":"Unley Rd",
    "iso:country":"AU",
    "sg:address":"95 Unley Rd",
    "sg:city":"Unley",
    "sg:classifiers":[
        {
            "category":"Professional",
            "subcategory":"Art Services",
            "type":"Services"
        }
    ],
    "sg:phone":"+61 8 8272 2232",
    "sg:postcode":"5061",
    "sg:province":"SA",
    "wof:name":"A P Bond Art Dealer",
    "wof:placetype":"venue"
},
  "geometry": {"coordinates":[138.607345581,-34.9472541809],"type":"Point"}
}