{
  "type": "Feature",
  "properties": {
    "iso:country":"AU",
    "sg:address":"Shop 6/ 32 Mountjoy Pde",
    "sg:city":"Lorne",
    "sg:classifiers":[
        {
            "category":"Shopping",
            "subcategory":"Clothing, Apparel, & Fashions",
            "type":"Retail Goods"
        }
    ],
    "sg:phone":"+61 3 5289 2977",
    "sg:postcode":"3232",
    "sg:province":"VIC",
    "sg:tags":[
        "lady",
        "wear"
    ],
    "wof:name":"Blue Illusion Australia",
    "wof:placetype":"venue"
},
  "geometry": {"coordinates":[143.974335,-38.537487],"type":"Point"}
}