{
  "type": "Feature",
  "properties": {
    "iso:country":"AU",
    "sg:address":"Shop 33",
    "sg:city":"Lemongrove Shopping Centre Chatswood",
    "sg:classifiers":[
        {
            "category":"Personal",
            "subcategory":"Beauty Salon",
            "type":"Services"
        }
    ],
    "sg:phone":"+61 2 9411 5748",
    "sg:postcode":"2067",
    "sg:province":"NSW",
    "sg:tags":[
        "hairdresser"
    ],
    "wof:name":"Jozos Hairdressing",
    "wof:placetype":"venue"
},
  "geometry": {"coordinates":[151.18385314899999,-33.7960700989],"type":"Point"}
}