{
  "type": "Feature",
  "properties": {
    "addr:full":"Mt Macedon Rd Mt Macedon VIC 3441",
    "addr:postcode":"3441",
    "addr:street":"Macedon Rd",
    "iso:country":"AU",
    "sg:address":"Mt Macedon Rd",
    "sg:city":"Mt Macedon",
    "sg:classifiers":[
        {
            "category":"Sports & Exercise",
            "subcategory":"Golf",
            "type":"Entertainment"
        }
    ],
    "sg:phone":"+61 3 5426 1650",
    "sg:postcode":"3441",
    "sg:province":"VIC",
    "sg:tags":[
        "club"
    ],
    "wof:name":"Mt Macedon Golf Club",
    "wof:placetype":"venue"
},
  "geometry": {"coordinates":[144.59375,-37.3917236328],"type":"Point"}
}