{
  "type": "Feature",
  "properties": {
    "iso:country":"AU",
    "sg:address":"89 Bussell Hwy",
    "sg:city":"Busselton",
    "sg:classifiers":[
        {
            "category":"Retail",
            "subcategory":"Veterinary Services",
            "type":"Services"
        }
    ],
    "sg:phone":"+61 8 9754 4422",
    "sg:postcode":"6280",
    "sg:province":"WA",
    "sg:tags":[
        "surgeon"
    ],
    "wof:name":"Geovet Veterinary Hospital",
    "wof:placetype":"venue"
},
  "geometry": {"coordinates":[115.33152008099999,-33.6547393799],"type":"Point"}
}