{
  "type": "Feature",
  "properties": {
    "iso:country":"AU",
    "sg:address":"Old Port Wakefield Rd",
    "sg:city":"Virginia",
    "sg:classifiers":[
        {
            "category":"Health Services",
            "subcategory":"Health Practitioner",
            "type":"Services"
        }
    ],
    "sg:phone":"+61 8 8380 9145",
    "sg:postcode":"5120",
    "sg:province":"SA",
    "sg:tags":[
        "physiotherapist"
    ],
    "wof:name":"Neil Mowbray",
    "wof:placetype":"venue"
},
  "geometry": {"coordinates":[138.560836792,-34.6675376892],"type":"Point"}
}