{
  "type": "Feature",
  "properties": {
    "addr:full":"Shp1/ 271 Military Rd Cremorne NSW 2090",
    "addr:housenumber":"271",
    "addr:postcode":"2090",
    "addr:street":"Military Rd",
    "iso:country":"AU",
    "sg:address":"Shp1/ 271 Military Rd",
    "sg:city":"Cremorne",
    "sg:classifiers":[
        {
            "category":"Cafe",
            "type":"Food & Drink"
        }
    ],
    "sg:phone":"+61 2 9904 0409",
    "sg:postcode":"2090",
    "sg:province":"NSW",
    "wof:name":"Jet Black Cafe",
    "wof:placetype":"venue"
},
  "geometry": {"coordinates":[151.228683472,-33.8290138245],"type":"Point"}
}