{
  "type": "Feature",
  "properties": {
    "addr:full":"65 Burnett St Buderim QLD 4556",
    "addr:housenumber":"65",
    "addr:postcode":"4556",
    "addr:street":"Burnett St",
    "iso:country":"AU",
    "sg:address":"65 Burnett St",
    "sg:city":"Buderim",
    "sg:classifiers":[
        {
            "category":"Social Services",
            "type":"Services"
        }
    ],
    "sg:phone":"+61 7 5476 6899",
    "sg:postcode":"4556",
    "sg:province":"QLD",
    "sg:tags":[
        "disabled",
        "person",
        "equipment"
    ],
    "wof:name":"Automated Disability Access Systems",
    "wof:placetype":"venue"
},
  "geometry": {"coordinates":[153.04934692399999,-26.687297821],"type":"Point"}
}