{
  "type": "Feature",
  "properties": {
    "addr:full":"PO Box 38 Inglewood SA 5133",
    "addr:postcode":"5133",
    "iso:country":"AU",
    "sg:address":"PO Box 38",
    "sg:city":"Inglewood",
    "sg:classifiers":[
        {
            "category":"Home & Garden",
            "subcategory":"Building Materials",
            "type":"Retail Goods"
        }
    ],
    "sg:phone":"+61 400 620 621",
    "sg:postcode":"5133",
    "sg:province":"SA",
    "sg:tags":[
        "fitting",
        "door"
    ],
    "wof:name":"Power Gate Automation",
    "wof:placetype":"venue"
},
  "geometry": {"coordinates":[138.791183472,-34.8022003174],"type":"Point"}
}