{
  "type": "Feature",
  "properties": {
    "addr:full":"60 Goldie St Wynyard TAS 7325",
    "addr:housenumber":"60",
    "addr:postcode":"7325",
    "addr:street":"Goldie St",
    "iso:country":"AU",
    "sg:address":"60 Goldie St",
    "sg:city":"Wynyard",
    "sg:classifiers":[
        {
            "category":"Banks & Credit Unions",
            "subcategory":"Financial Services",
            "type":"Services"
        }
    ],
    "sg:phone":"+61 3 6443 8215",
    "sg:postcode":"7325",
    "sg:province":"TAS",
    "sg:tags":[
        "building",
        "society"
    ],
    "wof:name":"B&E Ltd",
    "wof:placetype":"venue"
},
  "geometry": {"coordinates":[145.72886700000001,-40.988979],"type":"Point"}
}