{
  "type": "Feature",
  "properties": {
    "addr:full":"349 Coronation Drv Milton QLD 4064",
    "addr:housenumber":"349",
    "addr:postcode":"4064",
    "addr:street":"Coronation Drv",
    "iso:country":"AU",
    "sg:address":"349 Coronation Drv",
    "sg:city":"Milton",
    "sg:classifiers":[
        {
            "category":"Government",
            "subcategory":"Fire Station",
            "type":"Public Place"
        }
    ],
    "sg:phone":"+61 7 3377 0811",
    "sg:postcode":"4064",
    "sg:province":"QLD",
    "sg:tags":[
        "equipment",
        "protection",
        "consultant"
    ],
    "wof:name":"Total Fire Protection",
    "wof:placetype":"venue"
},
  "geometry": {"coordinates":[153.00291442899999,-27.4751014709],"type":"Point"}
}