{
  "type": "Feature",
  "properties": {
    "iso:country":"AU",
    "sg:address":"65 The Boulevarde",
    "sg:city":"Toronto",
    "sg:classifiers":[
        {
            "category":"Real Estate",
            "subcategory":"Architect",
            "type":"Services"
        }
    ],
    "sg:phone":"+61 2 4959 4797",
    "sg:postcode":"2283",
    "sg:province":"NSW",
    "sg:tags":[
        "building",
        "designer"
    ],
    "wof:name":"David Cooper Building Design",
    "wof:placetype":"venue"
},
  "geometry": {"coordinates":[151.5965271,-33.0059738159],"type":"Point"}
}