{
  "type": "Feature",
  "properties": {
    "iso:country":"AU",
    "sg:address":"14 Vale St",
    "sg:city":"Flinders",
    "sg:classifiers":[
        {
            "category":"Home & Garden",
            "subcategory":"Carpets & Floor Coverings",
            "type":"Retail Goods"
        }
    ],
    "sg:phone":"+61 3 5989 0017",
    "sg:postcode":"3929",
    "sg:province":"VIC",
    "sg:tags":[
        "layer",
        "planner"
    ],
    "wof:name":"The Human Factor Consulting Services Pty Ltd",
    "wof:placetype":"venue"
},
  "geometry": {"coordinates":[145.00660705600001,-38.4783630371],"type":"Point"}
}