{
  "type": "Feature",
  "properties": {
    "addr:full":"151 Industrial Rd Oak Flats NSW 2529",
    "addr:housenumber":"151",
    "addr:postcode":"2529",
    "addr:street":"Industrial Rd",
    "iso:country":"AU",
    "sg:address":"151 Industrial Rd",
    "sg:city":"Oak Flats",
    "sg:classifiers":[
        {
            "category":"Mining & Drilling",
            "type":"Manufacturing & Wholesale Goods"
        }
    ],
    "sg:phone":"+61 2 4256 1177",
    "sg:postcode":"2529",
    "sg:province":"NSW",
    "sg:tags":[
        "equipment",
        "quarrying",
        "supply"
    ],
    "wof:name":"Mining Repair",
    "wof:placetype":"venue"
},
  "geometry": {"coordinates":[150.804153442,-34.5649604797],"type":"Point"}
}