{
  "type": "Feature",
  "properties": {
    "addr:full":"Unit 4 4A Hollylea Rd Campbelltown NSW 2560",
    "addr:housenumber":"4a",
    "addr:postcode":"2560",
    "addr:street":"Hollylea Rd",
    "iso:country":"AU",
    "sg:address":"Unit 4 4A Hollylea Rd",
    "sg:city":"Campbelltown",
    "sg:classifiers":[
        {
            "category":"Manufacturing",
            "subcategory":"Motor Vehicles & Parts",
            "type":"Manufacturing & Wholesale Goods"
        }
    ],
    "sg:phone":"+61 2 4625 0720",
    "sg:postcode":"2560",
    "sg:province":"NSW",
    "sg:tags":[
        "replacement"
    ],
    "wof:name":"Len Voss Automatics",
    "wof:placetype":"venue"
},
  "geometry": {"coordinates":[150.827926636,-34.0504722595],"type":"Point"}
}