{
  "type": "Feature",
  "properties": {
    "addr:full":"LifeCare Kingsway Dental Hepburn Rd Landsdale WA 6065",
    "addr:postcode":"6065",
    "addr:street":"Hepburn Rd",
    "iso:country":"AU",
    "sg:address":"LifeCare Kingsway Dental Hepburn Rd",
    "sg:city":"Landsdale",
    "sg:classifiers":[
        {
            "category":"Health Services",
            "subcategory":"Dentist",
            "type":"Services"
        }
    ],
    "sg:phone":"+61 8 9409 3619",
    "sg:postcode":"6065",
    "sg:province":"WA",
    "wof:name":"Barcham W Ross Dr",
    "wof:placetype":"venue"
},
  "geometry": {"coordinates":[115.86859893800001,-31.8209400177],"type":"Point"}
}