{
  "type": "Feature",
  "properties": {
    "addr:full":"Shop 3 The Stroll 41 Smart St Fairfield NSW 2165",
    "addr:housenumber":"shop 3;41",
    "addr:postcode":"2165",
    "addr:street":"The Stroll;Smart St",
    "iso:country":"AU",
    "sg:address":"Shop 3 The Stroll 41 Smart St",
    "sg:city":"Fairfield",
    "sg:classifiers":[
        {
            "category":"Shopping",
            "subcategory":"Music",
            "type":"Retail Goods"
        }
    ],
    "sg:phone":"+61 2 9727 3621",
    "sg:postcode":"2165",
    "sg:province":"NSW",
    "sg:tags":[
        "store"
    ],
    "wof:name":"Leading Edge Music",
    "wof:placetype":"venue"
},
  "geometry": {"coordinates":[150.953216553,-33.8656311035],"type":"Point"}
}