{
  "type": "Feature",
  "properties": {
    "addr:full":"Suite 105 109 Alexander St Crows Nest NSW 2065",
    "addr:housenumber":"109",
    "addr:postcode":"2065",
    "addr:street":"Alexander St",
    "iso:country":"AU",
    "sg:address":"Suite 105 109 Alexander St",
    "sg:city":"Crows Nest",
    "sg:classifiers":[
        {
            "category":"Organizations",
            "subcategory":"Community Association",
            "type":"Services"
        }
    ],
    "sg:phone":"+61 2 9439 1399",
    "sg:postcode":"2065",
    "sg:province":"NSW",
    "sg:tags":[
        "organisation",
        "family",
        "welfare"
    ],
    "wof:name":"Community Housing Lower North Shore",
    "wof:placetype":"venue"
},
  "geometry": {"coordinates":[151.202636719,-33.8253135681],"type":"Point"}
}