{
  "type": "Feature",
  "properties": {
    "iso:country":"AU",
    "sg:address":"Shp 3/ 14 Terminus St",
    "sg:city":"Castle Hill",
    "sg:classifiers":[
        {
            "category":"Fast Food",
            "type":"Food & Drink"
        }
    ],
    "sg:phone":"+61 2 9899 7572",
    "sg:postcode":"2154",
    "sg:province":"NSW",
    "sg:tags":[
        "away",
        "take"
    ],
    "wof:name":"Craving Kebabs",
    "wof:placetype":"venue"
},
  "geometry": {"coordinates":[151.00601196299999,-33.7335777283],"type":"Point"}
}