{
  "type": "Feature",
  "properties": {
    "addr:full":"Great Lakes Campus The Northern Parkway St Tuncurry NSW 2428",
    "addr:postcode":"2428",
    "addr:street":"Northern Parkway St",
    "iso:country":"AU",
    "sg:address":"Great Lakes Campus The Northern Parkway St",
    "sg:city":"Tuncurry",
    "sg:classifiers":[
        {
            "category":"Education",
            "subcategory":"Special Training",
            "type":"Public Place"
        }
    ],
    "sg:phone":"+61 2 6555 0600",
    "sg:postcode":"2428",
    "sg:province":"NSW",
    "sg:tags":[
        "development"
    ],
    "wof:name":"TAFE NSW - North Coast Institute",
    "wof:placetype":"venue"
},
  "geometry": {"coordinates":[152.53431699999999,-32.21175],"type":"Point"}
}