{
  "type": "Feature",
  "properties": {
    "addr:full":"51 Dundas Pl Albert Park VIC 3206",
    "addr:housenumber":"51",
    "addr:postcode":"3206",
    "addr:street":"Dundas Pl",
    "iso:country":"AU",
    "sg:address":"51 Dundas Pl",
    "sg:city":"Albert Park",
    "sg:classifiers":[
        {
            "category":"Health Services",
            "subcategory":"Doctor",
            "type":"Services"
        }
    ],
    "sg:phone":"+61 3 9699 8044",
    "sg:postcode":"3206",
    "sg:province":"VIC",
    "sg:tags":[
        "medical",
        "practitioner"
    ],
    "wof:name":"Conroy Ewa Dr",
    "wof:placetype":"venue"
},
  "geometry": {"coordinates":[144.95716899999999,-37.841393],"type":"Point"}
}