{
  "type": "Feature",
  "properties": {
    "iso:country":"AU",
    "sg:address":"Gwydir Hwy",
    "sg:city":"Glen Innes",
    "sg:classifiers":[
        {
            "category":"Manufacturing",
            "subcategory":"Glass & Minerals",
            "type":"Manufacturing & Wholesale Goods"
        }
    ],
    "sg:phone":"+61 2 6732 3588",
    "sg:postcode":"2370",
    "sg:province":"NSW",
    "sg:tags":[
        "exploration"
    ],
    "wof:name":"Nunan T J & P V Pty Ltd",
    "wof:placetype":"venue"
},
  "geometry": {"coordinates":[151.73333740199999,-29.7348918915],"type":"Point"}
}