{
  "type": "Feature",
  "properties": {
    "addr:full":"375a Bayswater Rd Bayswater VIC 3153",
    "addr:housenumber":"375a",
    "addr:postcode":"3153",
    "addr:street":"Bayswater Rd",
    "iso:country":"AU",
    "sg:address":"375a Bayswater Rd",
    "sg:city":"Bayswater",
    "sg:classifiers":[
        {
            "category":"Autos & Motor Vehicles",
            "subcategory":"Automobile Sales",
            "type":"Retail Goods"
        }
    ],
    "sg:phone":"+61 3 9720 9388",
    "sg:postcode":"3153",
    "sg:province":"VIC",
    "sg:tags":[
        "car",
        "used"
    ],
    "wof:name":"Deluxe Motor Vehicles",
    "wof:placetype":"venue"
},
  "geometry": {"coordinates":[145.27143859899999,-37.8357315063],"type":"Point"}
}