{
  "type": "Feature",
  "properties": {
    "addr:full":"41a Oxford St Ingleburn NSW 2565",
    "addr:housenumber":"41a",
    "addr:postcode":"2565",
    "addr:street":"Oxford St",
    "iso:country":"AU",
    "sg:address":"41a Oxford St",
    "sg:city":"Ingleburn",
    "sg:classifiers":[
        {
            "category":"Personal",
            "subcategory":"Beauty Salon",
            "type":"Services"
        }
    ],
    "sg:phone":"+61 2 9605 2844",
    "sg:postcode":"2565",
    "sg:province":"NSW",
    "sg:tags":[
        "hairdresser"
    ],
    "wof:name":"La Boum Hair Salon",
    "wof:placetype":"venue"
},
  "geometry": {"coordinates":[150.866622925,-33.9991035461],"type":"Point"}
}