{
  "type": "Feature",
  "properties": {
    "iso:country":"AU",
    "sg:address":"5-9 Day St",
    "sg:city":"Lidcombe",
    "sg:classifiers":[
        {
            "category":"Autos & Motor Vehicles",
            "subcategory":"Automobile Sales",
            "type":"Retail Goods"
        }
    ],
    "sg:phone":"+61 2 9737 0406",
    "sg:postcode":"2141",
    "sg:province":"NSW",
    "sg:tags":[
        "car",
        "used"
    ],
    "wof:name":"Jeff Rogers Wholesale Cars",
    "wof:placetype":"venue"
},
  "geometry": {"coordinates":[151.05003356899999,-33.8491134644],"type":"Point"}
}