{
  "type": "Feature",
  "properties": {
    "addr:full":"34 McLachlan St Darwin NT 0800",
    "addr:housenumber":"34",
    "addr:postcode":"nt 0800",
    "addr:street":"Mclachlan St",
    "iso:country":"AU",
    "sg:address":"34 McLachlan St",
    "sg:city":"Darwin",
    "sg:classifiers":[
        {
            "category":"Social Services",
            "subcategory":"Retirement Home",
            "type":"Services"
        }
    ],
    "sg:phone":"+61 8 8982 4800",
    "sg:postcode":"0800",
    "sg:province":"NT",
    "sg:tags":[
        "environmental",
        "consultant",
        "pollution"
    ],
    "wof:name":"Sinclair Knight Merz",
    "wof:placetype":"venue"
},
  "geometry": {"coordinates":[130.83970642099999,-12.4577188492],"type":"Point"}
}