{
  "type": "Feature",
  "properties": {
    "iso:country":"AU",
    "sg:address":"97 Robinson Rd",
    "sg:city":"Geebung",
    "sg:classifiers":[
        {
            "category":"Building & Trades",
            "subcategory":"Construction",
            "type":"Services"
        }
    ],
    "sg:phone":"+61 7 3265 3099",
    "sg:postcode":"4034",
    "sg:province":"QLD",
    "sg:tags":[
        "tennis court",
        "repair"
    ],
    "wof:name":"Cyclone Fencing",
    "wof:placetype":"venue"
},
  "geometry": {"coordinates":[153.05685399999999,-27.36964],"type":"Point"}
}