{
  "type": "Feature",
  "properties": {
    "iso:country":"AU",
    "sg:address":"4 Gregory St",
    "sg:city":"Broome",
    "sg:classifiers":[
        {
            "category":"Professional",
            "subcategory":"Art Services",
            "type":"Services"
        }
    ],
    "sg:phone":"+61 8 9193 6426",
    "sg:postcode":"6725",
    "sg:province":"WA",
    "sg:tags":[
        "picture",
        "frame",
        "framing"
    ],
    "wof:name":"Acacia Picture Framing",
    "wof:placetype":"venue"
},
  "geometry": {"coordinates":[122.22328186,-17.9664382935],"type":"Point"}
}