{
  "type": "Feature",
  "properties": {
    "addr:full":"Lvl E/ 42 Upper Heidelberg Rd Ivanhoe VIC 3079",
    "addr:housenumber":"/ 42",
    "addr:postcode":"3079",
    "addr:street":"Upper Heidelberg Rd",
    "iso:country":"AU",
    "sg:address":"Lvl E/ 42 Upper Heidelberg Rd",
    "sg:city":"Ivanhoe",
    "sg:classifiers":[
        {
            "category":"Health Services",
            "subcategory":"Doctor",
            "type":"Services"
        }
    ],
    "sg:phone":"+61 3 9499 1200",
    "sg:postcode":"3079",
    "sg:province":"VIC",
    "sg:tags":[
        "nurse",
        "nursing"
    ],
    "wof:name":"Sequel Home Based Care",
    "wof:placetype":"venue"
},
  "geometry": {"coordinates":[145.04377746599999,-37.7687988281],"type":"Point"}
}