{
  "type": "Feature",
  "properties": {
    "addr:full":"20 Violet St Eagle Farm QLD 4009",
    "addr:housenumber":"20",
    "addr:postcode":"4009",
    "addr:street":"Violet St",
    "iso:country":"AU",
    "sg:address":"20 Violet St",
    "sg:city":"Eagle Farm",
    "sg:classifiers":[
        {
            "category":"Home & Garden",
            "subcategory":"Furniture",
            "type":"Retail Goods"
        }
    ],
    "sg:phone":"+61 7 3868 1477",
    "sg:postcode":"4009",
    "sg:province":"QLD",
    "sg:tags":[
        "business"
    ],
    "wof:name":"Add'n Office Fitouts",
    "wof:placetype":"venue"
},
  "geometry": {"coordinates":[153.091629028,-27.4308357239],"type":"Point"}
}