{
  "type": "Feature",
  "properties": {
    "addr:full":"Landfill Site Ranford Rd Canning Vale WA 6155",
    "addr:postcode":"6155",
    "addr:street":"Ranford Rd",
    "iso:country":"AU",
    "sg:address":"Landfill Site Ranford Rd",
    "sg:city":"Canning Vale",
    "sg:classifiers":[
        {
            "category":"Home & Garden",
            "subcategory":"Garden Supply",
            "type":"Retail Goods"
        }
    ],
    "sg:phone":"+61 419 935 282",
    "sg:postcode":"6155",
    "sg:province":"WA",
    "sg:tags":[
        "landscape"
    ],
    "wof:name":"Soils Aint Soils",
    "wof:placetype":"venue"
},
  "geometry": {"coordinates":[115.9226,-32.091831],"type":"Point"}
}