{
  "type": "Feature",
  "properties": {
    "addr:full":"Building 7, 21 Northumberland St Collingwood VIC 3066",
    "addr:housenumber":"21",
    "addr:postcode":"3066",
    "addr:street":"Northumberland St",
    "iso:country":"AU",
    "sg:address":"Building 7, 21 Northumberland St",
    "sg:city":"Collingwood",
    "sg:classifiers":[
        {
            "category":"Professional",
            "subcategory":"Printing & Photocopies",
            "type":"Services"
        }
    ],
    "sg:phone":"+61 3 9419 7177",
    "sg:postcode":"3066",
    "sg:province":"VIC",
    "sg:tags":[
        "publishing",
        "desktop"
    ],
    "wof:name":"E-Brochures",
    "wof:placetype":"venue"
},
  "geometry": {"coordinates":[144.986785889,-37.807510376],"type":"Point"}
}