{
  "type": "Feature",
  "properties": {
    "iso:country":"AU",
    "sg:address":"Rutland Ave",
    "sg:city":"Mt Eliza",
    "sg:classifiers":[
        {
            "category":"Personal",
            "subcategory":"Massage",
            "type":"Services"
        }
    ],
    "sg:phone":"+61 3 9787 8024",
    "sg:postcode":"3930",
    "sg:province":"VIC",
    "sg:tags":[
        "therapy"
    ],
    "wof:name":"Klos Terri",
    "wof:placetype":"venue"
},
  "geometry": {"coordinates":[145.08541870100001,-38.1902770996],"type":"Point"}
}