{
  "type": "Feature",
  "properties": {
    "iso:country":"AU",
    "sg:address":"106 Flinders St",
    "sg:city":"Adelaide",
    "sg:classifiers":[
        {
            "category":"Education",
            "subcategory":"Special Training",
            "type":"Public Place"
        }
    ],
    "sg:phone":"+61 1300 887 246",
    "sg:postcode":"5000",
    "sg:province":"SA",
    "sg:tags":[
        "development"
    ],
    "wof:name":"Archer College",
    "wof:placetype":"venue"
},
  "geometry": {"coordinates":[138.60415649399999,-34.9268035889],"type":"Point"}
}