{
  "type": "Feature",
  "properties": {
    "addr:full":"7/ 129 Robinson Rd Geebung QLD 4034",
    "addr:housenumber":"/ 129",
    "addr:postcode":"4034",
    "addr:street":"Robinson Rd",
    "iso:country":"AU",
    "sg:address":"7/ 129 Robinson Rd",
    "sg:city":"Geebung",
    "sg:classifiers":[
        {
            "category":"Home & Garden",
            "subcategory":"Carpets & Floor Coverings",
            "type":"Retail Goods"
        }
    ],
    "sg:phone":"+61 7 3865 8457",
    "sg:postcode":"4034",
    "sg:province":"QLD",
    "sg:tags":[
        "material",
        "waterproofing"
    ],
    "sg:website":"http://www.bayset.com.au",
    "wof:name":"Bayset Waterproofing Supplies",
    "wof:placetype":"venue"
},
  "geometry": {"coordinates":[153.05549600000001,-27.369349],"type":"Point"}
}