{
  "type": "Feature",
  "properties": {
    "addr:full":"29 Vaux St Cowra NSW 2794",
    "addr:housenumber":"29",
    "addr:postcode":"2794",
    "addr:street":"Vaux St",
    "iso:country":"AU",
    "sg:address":"29 Vaux St",
    "sg:city":"Cowra",
    "sg:classifiers":[
        {
            "category":"Banks & Credit Unions",
            "subcategory":"Financial Services",
            "type":"Services"
        }
    ],
    "sg:phone":"+61 2 6342 1661",
    "sg:postcode":"2794",
    "sg:province":"NSW",
    "sg:tags":[
        "annuity",
        "rollover",
        "superannuation",
        "consultant"
    ],
    "wof:name":"Martin Williams",
    "wof:placetype":"venue"
},
  "geometry": {"coordinates":[148.691864014,-33.8369789124],"type":"Point"}
}