{
  "type": "Feature",
  "properties": {
    "addr:full":"Cnr Glebe Point Rd & Broadway Glebe NSW 2037",
    "addr:postcode":"2037",
    "addr:street":"Cnr Glebe Point Rd & Broadway",
    "iso:country":"AU",
    "sg:address":"Cnr Glebe Point Rd & Broadway",
    "sg:city":"Glebe",
    "sg:classifiers":[
        {
            "category":"Professional",
            "subcategory":"Computer Services",
            "type":"Services"
        }
    ],
    "sg:phone":"+61 2 8586 1111",
    "sg:postcode":"2037",
    "sg:province":"NSW",
    "sg:tags":[
        "repairs",
        "upgrade",
        "equipment"
    ],
    "wof:name":"AppleCentre Broadway",
    "wof:placetype":"venue"
},
  "geometry": {"coordinates":[151.18496704099999,-33.8771972656],"type":"Point"}
}