{
  "type": "Feature",
  "properties": {
    "addr:full":"Wellington St Perth WA 6000",
    "addr:postcode":"6000",
    "addr:street":"Wellington St",
    "iso:country":"AU",
    "sg:address":"Wellington St",
    "sg:city":"Perth",
    "sg:classifiers":[
        {
            "category":"Real Estate",
            "subcategory":"Real Estate Services",
            "type":"Services"
        }
    ],
    "sg:phone":"+61 8 9226 1155",
    "sg:postcode":"6000",
    "sg:province":"WA",
    "sg:tags":[
        "consultant",
        "property"
    ],
    "wof:name":"The Barclay MIS Group Pty Ltd",
    "wof:placetype":"venue"
},
  "geometry": {"coordinates":[115.85492706300001,-31.9502372742],"type":"Point"}
}