{
  "type": "Feature",
  "properties": {
    "addr:full":"30 Binary St Yatala QLD 4207",
    "addr:housenumber":"30",
    "addr:postcode":"4207",
    "addr:street":"Binary St",
    "iso:country":"AU",
    "sg:address":"30 Binary St",
    "sg:city":"Yatala",
    "sg:classifiers":[
        {
            "category":"Manufacturing",
            "subcategory":"Petroleum Products",
            "type":"Manufacturing & Wholesale Goods"
        }
    ],
    "sg:phone":"+61 7 3382 7742",
    "sg:postcode":"4207",
    "sg:province":"QLD",
    "sg:tags":[
        "polystyrene"
    ],
    "sg:website":"http://www.nrggreenboard.com",
    "wof:name":"NRG Building Systems",
    "wof:placetype":"venue"
},
  "geometry": {"coordinates":[153.23348999000001,-27.7579345703],"type":"Point"}
}