{
  "type": "Feature",
  "properties": {
    "addr:full":"182 Hume Hwy Lansvale NSW 2166",
    "addr:housenumber":"182",
    "addr:postcode":"2166",
    "addr:street":"Hume Hwy",
    "iso:country":"AU",
    "sg:address":"182 Hume Hwy",
    "sg:city":"Lansvale",
    "sg:classifiers":[
        {
            "category":"Autos & Motor Vehicles",
            "subcategory":"Automobile Sales",
            "type":"Retail Goods"
        }
    ],
    "sg:phone":"+61 2 9754 2929",
    "sg:postcode":"2166",
    "sg:province":"NSW",
    "sg:tags":[
        "car",
        "used"
    ],
    "wof:name":"Tiger Motors",
    "wof:placetype":"venue"
},
  "geometry": {"coordinates":[150.955169678,-33.8958625793],"type":"Point"}
}