{
  "type": "Feature",
  "properties": {
    "addr:full":"60 Mill St Redland Bay QLD 4165",
    "addr:housenumber":"60",
    "addr:postcode":"4165",
    "addr:street":"Mill St",
    "iso:country":"AU",
    "sg:address":"60 Mill St",
    "sg:city":"Redland Bay",
    "sg:classifiers":[
        {
            "category":"Home & Garden",
            "subcategory":"Building Materials",
            "type":"Retail Goods"
        }
    ],
    "sg:phone":"+61 7 3829 3907",
    "sg:postcode":"4165",
    "sg:province":"QLD",
    "sg:tags":[
        "skylight"
    ],
    "wof:name":"Doyles Skylights & Vebtilations",
    "wof:placetype":"venue"
},
  "geometry": {"coordinates":[153.298629761,-27.6097126007],"type":"Point"}
}