{
  "type": "Feature",
  "properties": {
    "iso:country":"AU",
    "sg:address":"918 High St",
    "sg:city":"Reservoir",
    "sg:classifiers":[
        {
            "category":"Restaurant",
            "type":"Food & Drink"
        }
    ],
    "sg:phone":"+61 3 9470 3915",
    "sg:postcode":"3073",
    "sg:province":"VIC",
    "sg:tags":[
        "pizza"
    ],
    "wof:name":"Ballerinis Pizza & Pasta Restaurant",
    "wof:placetype":"venue"
},
  "geometry": {"coordinates":[145.007446289,-37.7179031372],"type":"Point"}
}