{
  "type": "Feature",
  "properties": {
    "addr:full":"11 Rossiter Ave Roxburgh Park VIC 3064",
    "addr:housenumber":"11",
    "addr:postcode":"3064",
    "addr:street":"Rossiter Ave",
    "iso:country":"AU",
    "sg:address":"11 Rossiter Ave",
    "sg:city":"Roxburgh Park",
    "sg:classifiers":[
        {
            "category":"Wholesale",
            "subcategory":"Medical Equipment & Supplies",
            "type":"Manufacturing & Wholesale Goods"
        }
    ],
    "sg:phone":"+61 3 9308 9660",
    "sg:postcode":"3064",
    "sg:province":"VIC",
    "sg:tags":[
        "aid",
        "care",
        "health",
        "home"
    ],
    "wof:name":"Southern Star Senior Care Pty Ltd",
    "wof:placetype":"venue"
},
  "geometry": {"coordinates":[144.926345825,-37.6378822327],"type":"Point"}
}