{
  "type": "Feature",
  "properties": {
    "addr:full":"110 Cliftonville Rd Maroota South NSW 2756",
    "addr:housenumber":"110",
    "addr:postcode":"2756",
    "addr:street":"Cliftonville Rd",
    "iso:country":"AU",
    "sg:address":"110 Cliftonville Rd",
    "sg:city":"Maroota South",
    "sg:classifiers":[
        {
            "category":"Building & Trades",
            "subcategory":"Landscaping Services",
            "type":"Services"
        }
    ],
    "sg:phone":"+61 418 478 826",
    "sg:postcode":"2756",
    "sg:province":"NSW",
    "sg:tags":[
        "gardener"
    ],
    "wof:name":"Swanes Garden Care & Landscape",
    "wof:placetype":"venue"
},
  "geometry": {"coordinates":[150.95533752399999,-33.5308761597],"type":"Point"}
}