{
  "type": "Feature",
  "properties": {
    "addr:full":"15 Kallista-Emerald Rd Kallista VIC 3791",
    "addr:housenumber":"15",
    "addr:postcode":"3791",
    "addr:street":"Kallista-Emerald Rd",
    "iso:country":"AU",
    "sg:address":"15 Kallista-Emerald Rd",
    "sg:city":"Kallista",
    "sg:classifiers":[
        {
            "category":"Building & Trades",
            "subcategory":"Construction",
            "type":"Services"
        }
    ],
    "sg:phone":"+61 418 355 139",
    "sg:postcode":"3791",
    "sg:province":"VIC",
    "sg:tags":[
        "earth",
        "excavating",
        "moving",
        "contractor"
    ],
    "wof:name":"Roy Garbutt Excavations",
    "wof:placetype":"venue"
},
  "geometry": {"coordinates":[145.37986755399999,-37.8861732483],"type":"Point"}
}