{
  "type": "Feature",
  "properties": {
    "addr:full":"110 Poinciana Ave Tewantin QLD 4565",
    "addr:housenumber":"110",
    "addr:postcode":"4565",
    "addr:street":"Poinciana Ave",
    "iso:country":"AU",
    "sg:address":"110 Poinciana Ave",
    "sg:city":"Tewantin",
    "sg:classifiers":[
        {
            "category":"Shopping",
            "subcategory":"Crafts & Fabrics",
            "type":"Retail Goods"
        }
    ],
    "sg:phone":"+61 7 5474 2911",
    "sg:postcode":"4565",
    "sg:province":"QLD",
    "sg:tags":[
        "wool",
        "knitting",
        "accessory"
    ],
    "wof:name":"Tewantin Wool Craft & Fabrics",
    "wof:placetype":"venue"
},
  "geometry": {"coordinates":[153.03887939399999,-26.3916072845],"type":"Point"}
}