{
  "type": "Feature",
  "properties": {
    "iso:country":"AU",
    "sg:address":"2 Murray St",
    "sg:city":"Kerang",
    "sg:classifiers":[
        {
            "category":"Education",
            "subcategory":"Kindergarten",
            "type":"Public Place"
        }
    ],
    "sg:phone":"+61 3 5452 1929",
    "sg:postcode":"3579",
    "sg:province":"VIC",
    "sg:tags":[
        "pre-schools"
    ],
    "wof:name":"Kerang & District Preschool Inc",
    "wof:placetype":"venue"
},
  "geometry": {"coordinates":[143.91438293499999,-35.7306938171],"type":"Point"}
}