{
  "type": "Feature",
  "properties": {
    "addr:full":"17 Bankswood Crt Camira QLD 4300",
    "addr:housenumber":"17",
    "addr:postcode":"4300",
    "addr:street":"Bankswood Crt",
    "iso:country":"AU",
    "sg:address":"17 Bankswood Crt",
    "sg:city":"Camira",
    "sg:classifiers":[
        {
            "category":"Retail",
            "subcategory":"Funeral Services",
            "type":"Services"
        }
    ],
    "sg:phone":"+61 7 3437 8543",
    "sg:postcode":"4300",
    "sg:province":"QLD",
    "sg:tags":[
        "supply"
    ],
    "wof:name":"Stainless Memorials",
    "wof:placetype":"venue"
},
  "geometry": {"coordinates":[152.92584228499999,-27.6493263245],"type":"Point"}
}