{
  "type": "Feature",
  "properties": {
    "iso:country":"AU",
    "sg:address":"221 Queen St",
    "sg:city":"Melbourne",
    "sg:classifiers":[
        {
            "category":"Banks & Credit Unions",
            "subcategory":"Investment Brokerage",
            "type":"Services"
        }
    ],
    "sg:phone":"+61 1300 300 208",
    "sg:postcode":"3000",
    "sg:province":"VIC",
    "sg:tags":[
        "finance",
        "broker"
    ],
    "wof:name":"Melbourne & All Suburbs Conveyancing",
    "wof:placetype":"venue"
},
  "geometry": {"coordinates":[144.95985412600001,-37.813457489],"type":"Point"}
}