{
  "type": "Feature",
  "properties": {
    "addr:full":"Level 6/ 176 Wellingto Pde East Melbourne VIC 3002",
    "addr:housenumber":"/ 176",
    "addr:postcode":"3002",
    "addr:street":"Wellingto Pde",
    "iso:country":"AU",
    "sg:address":"Level 6/ 176 Wellingto Pde",
    "sg:city":"East Melbourne",
    "sg:classifiers":[
        {
            "category":"Organizations",
            "subcategory":"Professional Association",
            "type":"Services"
        }
    ],
    "sg:phone":"+61 3 8412 7600",
    "sg:postcode":"3002",
    "sg:province":"VIC",
    "sg:tags":[
        "web",
        "internet"
    ],
    "wof:name":"iBase Global Pty Ltd",
    "wof:placetype":"venue"
},
  "geometry": {"coordinates":[144.98342895499999,-37.8159637451],"type":"Point"}
}