{
  "type": "Feature",
  "properties": {
    "addr:full":"100 Commonwealth St Surry Hills NSW 2010",
    "addr:housenumber":"100",
    "addr:postcode":"2010",
    "addr:street":"Commonwealth St",
    "iso:country":"AU",
    "sg:address":"100 Commonwealth St",
    "sg:city":"Surry Hills",
    "sg:classifiers":[
        {
            "category":"Shopping",
            "subcategory":"Music",
            "type":"Retail Goods"
        }
    ],
    "sg:phone":"+61 2 9211 1700",
    "sg:postcode":"2010",
    "sg:province":"NSW",
    "sg:tags":[
        "instrument",
        "musical"
    ],
    "wof:name":"Billy Hyde Drumcraft",
    "wof:placetype":"venue"
},
  "geometry": {"coordinates":[151.21107482900001,-33.8803672791],"type":"Point"}
}