{
  "type": "Feature",
  "properties": {
    "addr:full":"13 Bellbowrie Park Bellbowrie St Port Macquarie NSW 2444",
    "addr:housenumber":"13",
    "addr:postcode":"2444",
    "addr:street":"Bellbowrie Park Bellbowrie St",
    "iso:country":"AU",
    "sg:address":"13 Bellbowrie Park Bellbowrie St",
    "sg:city":"Port Macquarie",
    "sg:classifiers":[
        {
            "category":"Shopping",
            "subcategory":"Party Supplies",
            "type":"Retail Goods"
        }
    ],
    "sg:phone":"+61 2 6583 2121",
    "sg:postcode":"2444",
    "sg:province":"NSW",
    "wof:name":"Balmoor Distributors",
    "wof:placetype":"venue"
},
  "geometry": {"coordinates":[152.89125100000001,-31.429485],"type":"Point"}
}