{
  "type": "Feature",
  "properties": {
    "addr:full":"61 Coghlan Rd Subiaco East WA 6008",
    "addr:housenumber":"61",
    "addr:postcode":"6008",
    "addr:street":"Coghlan Rd;East",
    "iso:country":"AU",
    "sg:address":"61 Coghlan Rd",
    "sg:city":"Subiaco East",
    "sg:classifiers":[
        {
            "category":"Health Services",
            "subcategory":"Health Practitioner",
            "type":"Services"
        }
    ],
    "sg:phone":"+61 8 9381 6166",
    "sg:postcode":"6008",
    "sg:province":"WA",
    "sg:tags":[
        "physiotherapist"
    ],
    "wof:name":"Helen Potter",
    "wof:placetype":"venue"
},
  "geometry": {"coordinates":[115.833129883,-31.947675705],"type":"Point"}
}