{
  "type": "Feature",
  "properties": {
    "addr:full":"26 Pear St Redland Bay QLD 4165",
    "addr:housenumber":"26",
    "addr:postcode":"4165",
    "addr:street":"Pear St",
    "iso:country":"AU",
    "sg:address":"26 Pear St",
    "sg:city":"Redland Bay",
    "sg:classifiers":[
        {
            "category":"Professional",
            "subcategory":"Engineering",
            "type":"Services"
        }
    ],
    "sg:phone":"+61 7 3206 8064",
    "sg:postcode":"4165",
    "sg:province":"QLD",
    "sg:tags":[
        "electrical",
        "engineer"
    ],
    "wof:name":"Liva Electric",
    "wof:placetype":"venue"
},
  "geometry": {"coordinates":[153.31463623100001,-27.6722507477],"type":"Point"}
}