{
  "type": "Feature",
  "properties": {
    "addr:full":"Cnr Mitchell Drv & Garnett Rd Green Hills NSW 2323",
    "addr:postcode":"2323",
    "addr:street":"Cnr Mitchell Drv & Garnett Rd",
    "iso:country":"AU",
    "sg:address":"Cnr Mitchell Drv & Garnett Rd",
    "sg:city":"Green Hills",
    "sg:classifiers":[
        {
            "category":"Education",
            "subcategory":"Vocational School",
            "type":"Public Place"
        }
    ],
    "sg:phone":"+61 2 4934 8111",
    "sg:postcode":"2323",
    "sg:province":"NSW",
    "sg:tags":[
        "beauty"
    ],
    "wof:name":"Australian College Of Beauty Therapy (NSW)",
    "wof:placetype":"venue"
},
  "geometry": {"coordinates":[151.58665466299999,-32.7614974976],"type":"Point"}
}