{
  "type": "Feature",
  "properties": {
    "addr:full":"9 Campbell Way Bunbury WA 6230",
    "addr:housenumber":"9",
    "addr:postcode":"6230",
    "addr:street":"Campbell Way",
    "iso:country":"AU",
    "sg:address":"9 Campbell Way",
    "sg:city":"Bunbury",
    "sg:classifiers":[
        {
            "category":"Retail",
            "subcategory":"Auto Repair",
            "type":"Services"
        }
    ],
    "sg:phone":"+61 8 9726 0408",
    "sg:postcode":"6230",
    "sg:province":"WA",
    "sg:tags":[
        "bus",
        "truck"
    ],
    "wof:name":"G-Mac Equipment",
    "wof:placetype":"venue"
},
  "geometry": {"coordinates":[115.678513,-33.354626],"type":"Point"}
}