{
  "type": "Feature",
  "properties": {
    "iso:country":"AU",
    "sg:address":"20 Lavarack St",
    "sg:city":"Melton South",
    "sg:classifiers":[
        {
            "category":"Professional",
            "subcategory":"Accounting & Tax Preparation",
            "type":"Services"
        }
    ],
    "sg:phone":"+61 3 9743 3919",
    "sg:postcode":"3338",
    "sg:province":"VIC",
    "sg:tags":[
        "consultant",
        "taxation"
    ],
    "wof:name":"South Melton Taxation Consultants",
    "wof:placetype":"venue"
},
  "geometry": {"coordinates":[144.57806400000001,-37.707874],"type":"Point"}
}