{
  "type": "Feature",
  "properties": {
    "iso:country":"AU",
    "sg:address":"74 Landor Rd",
    "sg:city":"Barden Ridge",
    "sg:classifiers":[
        {
            "category":"Building & Trades",
            "subcategory":"Construction",
            "type":"Services"
        }
    ],
    "sg:phone":"+61 418 219 196",
    "sg:postcode":"2234",
    "sg:province":"NSW",
    "sg:tags":[
        "concrete",
        "treatment",
        "repair"
    ],
    "wof:name":"Custom Concrete Resurfacing",
    "wof:placetype":"venue"
},
  "geometry": {"coordinates":[151.013183594,-34.0280799866],"type":"Point"}
}