{
  "type": "Feature",
  "properties": {
    "addr:full":"40 Anderson Rd Concord NSW 2137",
    "addr:housenumber":"40",
    "addr:postcode":"2137",
    "addr:street":"Anderson Rd",
    "iso:country":"AU",
    "sg:address":"40 Anderson Rd",
    "sg:city":"Concord",
    "sg:classifiers":[
        {
            "category":"Home & Garden",
            "subcategory":"Carpets & Floor Coverings",
            "type":"Retail Goods"
        }
    ],
    "sg:phone":"+61 2 9736 1656",
    "sg:postcode":"2137",
    "sg:province":"NSW",
    "sg:tags":[
        "tile",
        "wall",
        "layer"
    ],
    "wof:name":"Rateni M",
    "wof:placetype":"venue"
},
  "geometry": {"coordinates":[151.10552978499999,-33.8492279053],"type":"Point"}
}