{
  "type": "Feature",
  "properties": {
    "iso:country":"AU",
    "sg:address":"522A Henley Beach Rd",
    "sg:city":"Fulham",
    "sg:classifiers":[
        {
            "category":"Personal",
            "subcategory":"Tanning Parlor",
            "type":"Services"
        }
    ],
    "sg:phone":"+61 8 8353 8988",
    "sg:postcode":"5024",
    "sg:province":"SA",
    "sg:tags":[
        "solarium"
    ],
    "wof:name":"Waxstar",
    "wof:placetype":"venue"
},
  "geometry": {"coordinates":[138.516815186,-34.9262084961],"type":"Point"}
}