{
  "type": "Feature",
  "properties": {
    "addr:full":"27 Brighton Rd Sandgate QLD 4017",
    "addr:housenumber":"27",
    "addr:postcode":"4017",
    "addr:street":"Brighton Rd",
    "iso:country":"AU",
    "sg:address":"27 Brighton Rd",
    "sg:city":"Sandgate",
    "sg:classifiers":[
        {
            "category":"Real Estate",
            "subcategory":"Real Estate Agent",
            "type":"Services"
        }
    ],
    "sg:phone":"+61 7 3269 0944",
    "sg:postcode":"4017",
    "sg:province":"QLD",
    "wof:name":"Sandgate Real Estate",
    "wof:placetype":"venue"
},
  "geometry": {"coordinates":[153.06968689000001,-27.3199138641],"type":"Point"}
}