{
  "type": "Feature",
  "properties": {
    "addr:full":"20 Larch St Tallebudgera QLD 4228",
    "addr:housenumber":"20",
    "addr:postcode":"4228",
    "addr:street":"Larch St",
    "iso:country":"AU",
    "sg:address":"20 Larch St",
    "sg:city":"Tallebudgera",
    "sg:classifiers":[
        {
            "category":"Personal",
            "subcategory":"Beauty Salon",
            "type":"Services"
        }
    ],
    "sg:phone":"+61 402 833 718",
    "sg:postcode":"4228",
    "sg:province":"QLD",
    "sg:tags":[
        "hairdresser"
    ],
    "wof:name":"Moov&#039;en Scissors",
    "wof:placetype":"venue"
},
  "geometry": {"coordinates":[153.43475341800001,-28.1251544952],"type":"Point"}
}