{
  "type": "Feature",
  "properties": {
    "addr:full":"160 Hamersley Rd Subiaco WA 6008",
    "addr:housenumber":"160",
    "addr:postcode":"6008",
    "addr:street":"Hamersley Rd",
    "iso:country":"AU",
    "sg:address":"160 Hamersley Rd",
    "sg:city":"Subiaco",
    "sg:classifiers":[
        {
            "category":"Social Services",
            "subcategory":"Child Care",
            "type":"Services"
        }
    ],
    "sg:phone":"+61 8 9381 8962",
    "sg:postcode":"6008",
    "sg:province":"WA",
    "wof:name":"Subiaco Children's Centre",
    "wof:placetype":"venue"
},
  "geometry": {"coordinates":[115.821899414,-31.9522380829],"type":"Point"}
}