{
  "type": "Feature",
  "properties": {
    "iso:country":"AU",
    "sg:address":"14 Main South Rd",
    "sg:city":"Morphett Vale",
    "sg:classifiers":[
        {
            "category":"Personal",
            "type":"Services"
        }
    ],
    "sg:phone":"+61 8 8326 9390",
    "sg:postcode":"5162",
    "sg:province":"SA",
    "sg:tags":[
        "gift"
    ],
    "wof:name":"Abundance Flowers & Baskets",
    "wof:placetype":"venue"
},
  "geometry": {"coordinates":[138.52331543,-35.1256561279],"type":"Point"}
}