{
  "type": "Feature",
  "properties": {
    "addr:full":"82 Acland St St Kilda VIC 3182",
    "addr:housenumber":"82",
    "addr:postcode":"3182",
    "addr:street":"Acland St",
    "iso:country":"AU",
    "sg:address":"82 Acland St",
    "sg:city":"St Kilda",
    "sg:classifiers":[
        {
            "category":"Communications",
            "subcategory":"News Services",
            "type":"Services"
        }
    ],
    "sg:phone":"+61 3 9534 8856",
    "sg:postcode":"3182",
    "sg:province":"VIC",
    "sg:tags":[
        "information",
        "tourist",
        "attractions"
    ],
    "wof:name":"Southbound Australia Pty Ltd",
    "wof:placetype":"venue"
},
  "geometry": {"coordinates":[144.97877502399999,-37.8672981262],"type":"Point"}
}