{
  "type": "Feature",
  "properties": {
    "iso:country":"AU",
    "sg:address":"44 Camden Crt",
    "sg:city":"Helensvale",
    "sg:classifiers":[
        {
            "category":"Professional",
            "subcategory":"Accounting & Tax Preparation",
            "type":"Services"
        }
    ],
    "sg:phone":"+61 7 5519 4999",
    "sg:postcode":"4212",
    "sg:province":"QLD",
    "sg:tags":[
        "accountant",
        "auditor"
    ],
    "wof:name":"Cga Accountants Pty Ltd",
    "wof:placetype":"venue"
},
  "geometry": {"coordinates":[153.325775147,-27.9069843292],"type":"Point"}
}