{
  "type": "Feature",
  "properties": {
    "iso:country":"AU",
    "sg:address":"Ground Floor, Queen Victoria Building, George St",
    "sg:city":"Sydney",
    "sg:classifiers":[
        {
            "category":"Shopping",
            "subcategory":"Jewelry",
            "type":"Retail Goods"
        }
    ],
    "sg:phone":"+61 2 9267 7974",
    "sg:postcode":"2000",
    "sg:province":"NSW",
    "sg:tags":[
        "jeweller"
    ],
    "sg:website":"http://www.mondial.com.au",
    "wof:name":"Mondial Neuman",
    "wof:placetype":"venue"
},
  "geometry": {"coordinates":[151.206954956,-33.8691902161],"type":"Point"}
}