{
  "type": "Feature",
  "properties": {
    "addr:full":"3 Rooksby St Gladstone QLD 4680",
    "addr:housenumber":"3",
    "addr:postcode":"4680",
    "addr:street":"Rooksby St",
    "iso:country":"AU",
    "sg:address":"3 Rooksby St",
    "sg:city":"Gladstone",
    "sg:classifiers":[
        {
            "category":"Autos & Motor Vehicles",
            "subcategory":"Boat Sales",
            "type":"Retail Goods"
        }
    ],
    "sg:phone":"+61 7 4972 3343",
    "sg:postcode":"4680",
    "sg:province":"QLD",
    "sg:tags":[
        "equipment",
        "yacht"
    ],
    "wof:name":"Gladstone Sailing Specialists",
    "wof:placetype":"venue"
},
  "geometry": {"coordinates":[151.24411010700001,-23.8367919922],"type":"Point"}
}