{
  "type": "Feature",
  "properties": {
    "iso:country":"AU",
    "sg:address":"62 Brougham St",
    "sg:city":"Eltham",
    "sg:classifiers":[
        {
            "category":"Cafe",
            "type":"Food & Drink"
        }
    ],
    "sg:phone":"+61 3 9431 6622",
    "sg:postcode":"3095",
    "sg:province":"VIC",
    "wof:name":"Lilies On Brougham Pty Ltd",
    "wof:placetype":"venue"
},
  "geometry": {"coordinates":[145.14488220199999,-37.7226524353],"type":"Point"}
}