{
  "type": "Feature",
  "properties": {
    "iso:country":"AU",
    "sg:address":"12d Ryelane St",
    "sg:city":"Maddington",
    "sg:classifiers":[
        {
            "category":"Retail",
            "subcategory":"Laundry & Dry Cleaning",
            "type":"Services"
        }
    ],
    "sg:phone":"+61 8 9459 0663",
    "sg:postcode":"6109",
    "sg:province":"WA",
    "wof:name":"Snowco",
    "wof:placetype":"venue"
},
  "geometry": {"coordinates":[115.98925781200001,-32.0424499512],"type":"Point"}
}