{
  "type": "Feature",
  "properties": {
    "addr:full":"105 Kooyong Rd Rivervale WA 6103",
    "addr:housenumber":"105",
    "addr:postcode":"6103",
    "addr:street":"Kooyong Rd",
    "iso:country":"AU",
    "sg:address":"105 Kooyong Rd",
    "sg:city":"Rivervale",
    "sg:classifiers":[
        {
            "category":"Health Services",
            "subcategory":"Health Practitioner",
            "type":"Services"
        }
    ],
    "sg:phone":"+61 8 9362 3887",
    "sg:postcode":"6103",
    "sg:province":"WA",
    "sg:tags":[
        "osteopath"
    ],
    "wof:name":"Gajek Andre",
    "wof:placetype":"venue"
},
  "geometry": {"coordinates":[115.914230347,-31.9618473053],"type":"Point"}
}