{
  "type": "Feature",
  "properties": {
    "iso:country":"AU",
    "sg:address":"Gardner St",
    "sg:city":"Toogoolawah",
    "sg:classifiers":[
        {
            "category":"Education",
            "subcategory":"School",
            "type":"Public Place"
        }
    ],
    "sg:phone":"+61 7 5423 4125",
    "sg:postcode":"4313",
    "sg:province":"QLD",
    "sg:tags":[
        "state",
        "except",
        "nsw"
    ],
    "wof:name":"Toogoolawah Preschool",
    "wof:placetype":"venue"
},
  "geometry": {"coordinates":[152.379394531,-27.0906600952],"type":"Point"}
}