{
  "type": "Feature",
  "properties": {
    "addr:full":"Shed 7, Cnr Geoffrey & Bronwyn Sts Caloundra QLD 4551",
    "addr:housenumber":"7",
    "addr:postcode":"4551",
    "addr:street":"Cnr Geoffrey & Bronwyn Sts",
    "iso:country":"AU",
    "sg:address":"Shed 7, Cnr Geoffrey & Bronwyn Sts",
    "sg:city":"Caloundra",
    "sg:classifiers":[
        {
            "category":"Professional",
            "subcategory":"Detective & Security Services",
            "type":"Services"
        }
    ],
    "sg:phone":"+61 7 5492 7730",
    "sg:postcode":"4551",
    "sg:province":"QLD",
    "sg:tags":[
        "equipment",
        "window",
        "doors"
    ],
    "wof:name":"AA Coast & Hinterland Screens",
    "wof:placetype":"venue"
},
  "geometry": {"coordinates":[153.11094665499999,-26.7950534821],"type":"Point"}
}