{
  "type": "Feature",
  "properties": {
    "addr:full":"7 Southseas Pl Patterson Lakes VIC 3197",
    "addr:housenumber":"7",
    "addr:postcode":"3197",
    "addr:street":"Southseas Pl",
    "iso:country":"AU",
    "sg:address":"7 Southseas Pl",
    "sg:city":"Patterson Lakes",
    "sg:classifiers":[
        {
            "category":"Building & Trades",
            "subcategory":"Construction",
            "type":"Services"
        }
    ],
    "sg:phone":"+61 1300 650 360",
    "sg:postcode":"3197",
    "sg:province":"VIC",
    "sg:tags":[
        "concrete",
        "paving"
    ],
    "wof:name":"Concrete Facelift",
    "wof:placetype":"venue"
},
  "geometry": {"coordinates":[145.13995361299999,-38.0669975281],"type":"Point"}
}