{
  "type": "Feature",
  "properties": {
    "addr:full":"1 / 1 Enterprise Cl Gosford West NSW 2250",
    "addr:housenumber":"/ 1",
    "addr:postcode":"2250",
    "addr:street":"Enterprise Cl Gosford West",
    "iso:country":"AU",
    "sg:address":"1",
    "sg:city":"/ 1 Enterprise Cl Gosford West",
    "sg:classifiers":[
        {
            "category":"Building & Trades",
            "subcategory":"Plumbing",
            "type":"Services"
        }
    ],
    "sg:phone":"+61 2 4324 4106",
    "sg:postcode":"2250",
    "sg:province":"NSW",
    "sg:tags":[
        "plumber",
        "gasfitters"
    ],
    "wof:name":"Hot Water Maintenance",
    "wof:placetype":"venue"
},
  "geometry": {"coordinates":[151.38217163100001,-33.3467674255],"type":"Point"}
}