{
  "type": "Feature",
  "properties": {
    "addr:full":"Suite 24, Level 24 213 North Albany St Gosford NSW 2250",
    "addr:housenumber":"213",
    "addr:postcode":"2250",
    "addr:street":"North Albany St",
    "iso:country":"AU",
    "sg:address":"Suite 24, Level 24 213 North Albany St",
    "sg:city":"Gosford",
    "sg:classifiers":[
        {
            "category":"Health Services",
            "subcategory":"Doctor",
            "type":"Services"
        }
    ],
    "sg:phone":"+61 2 4325 0980",
    "sg:postcode":"2250",
    "sg:province":"NSW",
    "sg:tags":[
        "medical",
        "practitioner"
    ],
    "wof:name":"Quinn Frank Dr",
    "wof:placetype":"venue"
},
  "geometry": {"coordinates":[151.346832275,-33.4269714355],"type":"Point"}
}