{
  "type": "Feature",
  "properties": {
    "iso:country":"AU",
    "sg:address":"Lvl 4/ 91 Phillip St",
    "sg:city":"Parramatta",
    "sg:classifiers":[
        {
            "category":"Professional",
            "subcategory":"Computer Services",
            "type":"Services"
        }
    ],
    "sg:phone":"+61 2 9893 9255",
    "sg:postcode":"2124",
    "sg:province":"NSW",
    "sg:tags":[
        "consultant",
        "system"
    ],
    "wof:name":"Realtime Business Solutions Pty Ltd",
    "wof:placetype":"venue"
},
  "geometry": {"coordinates":[150.964447022,-33.8522224426],"type":"Point"}
}