{
  "type": "Feature",
  "properties": {
    "iso:country":"AU",
    "sg:address":"13 Kerribee Pl",
    "sg:city":"Carlingford",
    "sg:classifiers":[
        {
            "category":"Health Services",
            "subcategory":"Doctor",
            "type":"Services"
        }
    ],
    "sg:phone":"+61 2 9871 7101",
    "sg:postcode":"2118",
    "sg:province":"NSW",
    "sg:tags":[
        "nurse",
        "nursing"
    ],
    "wof:name":"Parramatta Region Home Nursing Service",
    "wof:placetype":"venue"
},
  "geometry": {"coordinates":[151.04629516599999,-33.7604789734],"type":"Point"}
}