{
  "type": "Feature",
  "properties": {
    "addr:full":"16 Seaforth Rd Shoalwater WA 6169",
    "addr:housenumber":"16",
    "addr:postcode":"6169",
    "addr:street":"Seaforth Rd",
    "iso:country":"AU",
    "sg:address":"16 Seaforth Rd",
    "sg:city":"Shoalwater",
    "sg:classifiers":[
        {
            "category":"Professional",
            "subcategory":"Business Services",
            "type":"Services"
        }
    ],
    "sg:phone":"+61 8 9528 7085",
    "sg:postcode":"6169",
    "sg:province":"WA",
    "sg:tags":[
        "drafting"
    ],
    "wof:name":"Crowther Building Design and Drafting",
    "wof:placetype":"venue"
},
  "geometry": {"coordinates":[115.70649,-32.302479],"type":"Point"}
}