{
  "type": "Feature",
  "properties": {
    "addr:full":"11 Malbanda Ave Para Vista SA 5093",
    "addr:housenumber":"11",
    "addr:postcode":"5093",
    "addr:street":"Malbanda Ave",
    "iso:country":"AU",
    "sg:address":"11 Malbanda Ave",
    "sg:city":"Para Vista",
    "sg:classifiers":[
        {
            "category":"Building & Trades",
            "subcategory":"Cleaning & Sanitation",
            "type":"Services"
        }
    ],
    "sg:phone":"+61 8 8264 1554",
    "sg:postcode":"5093",
    "sg:province":"SA",
    "sg:tags":[
        "cleaner",
        "repairer",
        "roof"
    ],
    "wof:name":"Peter Nicholls Pty Ltd",
    "wof:placetype":"venue"
},
  "geometry": {"coordinates":[138.659866333,-34.8318252563],"type":"Point"}
}