{
  "type": "Feature",
  "properties": {
    "addr:full":"17 Kedron Park Rd Wooloowin QLD 4030",
    "addr:housenumber":"17",
    "addr:postcode":"4030",
    "addr:street":"Kedron Park Rd",
    "iso:country":"AU",
    "sg:address":"17 Kedron Park Rd",
    "sg:city":"Wooloowin",
    "sg:classifiers":[
        {
            "category":"Professional",
            "subcategory":"Art Services",
            "type":"Services"
        }
    ],
    "sg:phone":"+61 7 3357 7681",
    "sg:postcode":"4030",
    "sg:province":"QLD",
    "sg:tags":[
        "picture",
        "frame",
        "framing"
    ],
    "wof:name":"1hrFraming",
    "wof:placetype":"venue"
},
  "geometry": {"coordinates":[153.040695,-27.421432],"type":"Point"}
}