{
  "type": "Feature",
  "properties": {
    "addr:full":"93 Collins St Hobart TAS 7000",
    "addr:housenumber":"93",
    "addr:postcode":"7000",
    "addr:street":"Collins St",
    "iso:country":"AU",
    "sg:address":"93 Collins St",
    "sg:city":"Hobart",
    "sg:classifiers":[
        {
            "category":"Health Services",
            "subcategory":"Doctor",
            "type":"Services"
        }
    ],
    "sg:phone":"+61 3 6231 3003",
    "sg:postcode":"7000",
    "sg:province":"TAS",
    "sg:tags":[
        "medical",
        "practitioner"
    ],
    "wof:name":"Ward-MacCana Helen",
    "wof:placetype":"venue"
},
  "geometry": {"coordinates":[147.32754516599999,-42.882976532],"type":"Point"}
}