{
  "type": "Feature",
  "properties": {
    "addr:full":"122 Blackstone Rd Booval QLD 4304",
    "addr:housenumber":"122",
    "addr:postcode":"4304",
    "addr:street":"Blackstone Rd",
    "iso:country":"AU",
    "sg:address":"122 Blackstone Rd",
    "sg:city":"Booval",
    "sg:classifiers":[
        {
            "category":"Shopping",
            "subcategory":"Party Supplies",
            "type":"Retail Goods"
        }
    ],
    "sg:phone":"+61 7 3812 1974",
    "sg:postcode":"4304",
    "sg:province":"QLD",
    "wof:name":"Denmans Party Hire",
    "wof:placetype":"venue"
},
  "geometry": {"coordinates":[152.78785705600001,-27.6212062836],"type":"Point"}
}