{
  "type": "Feature",
  "properties": {
    "iso:country":"AU",
    "sg:address":"529- 535 High St",
    "sg:city":"Northcote",
    "sg:classifiers":[
        {
            "category":"Education",
            "subcategory":"Music School",
            "type":"Public Place"
        }
    ],
    "sg:phone":"+61 3 9482 5550",
    "sg:postcode":"3070",
    "sg:province":"VIC",
    "sg:tags":[
        "teacher"
    ],
    "wof:name":"Drumtek",
    "wof:placetype":"venue"
},
  "geometry": {"coordinates":[144.99945099999999,-37.764374],"type":"Point"}
}