{
  "type": "Feature",
  "properties": {
    "iso:country":"AU",
    "sg:address":"101 Melville St",
    "sg:city":"Numurkah",
    "sg:classifiers":[
        {
            "category":"Farming",
            "subcategory":"Farm & Veterinary Services",
            "type":"Manufacturing & Wholesale Goods"
        }
    ],
    "sg:phone":"+61 3 5862 1849",
    "sg:postcode":"3636",
    "sg:province":"VIC",
    "sg:tags":[
        "irrigation",
        "reticulation",
        "system"
    ],
    "wof:name":"Plumbing Numurkah",
    "wof:placetype":"venue"
},
  "geometry": {"coordinates":[145.4425354,-36.092540741],"type":"Point"}
}