{
  "type": "Feature",
  "properties": {
    "addr:full":"Suite 503, 12 Century Circuit Baulkham Hills NSW 2153",
    "addr:postcode":"2153",
    "addr:street":"Century Circuit",
    "iso:country":"AU",
    "sg:address":"Suite 503, 12 Century Circuit",
    "sg:city":"Baulkham Hills",
    "sg:classifiers":[
        {
            "category":"Professional",
            "subcategory":"Employment Agencies",
            "type":"Services"
        }
    ],
    "sg:phone":"+61 2 8853 4111",
    "sg:postcode":"2153",
    "sg:province":"NSW",
    "sg:website":"http://www.norwestrecruitment.com.au",
    "wof:name":"Norwest Recruitment",
    "wof:placetype":"venue"
},
  "geometry": {"coordinates":[150.96238708499999,-33.7338676453],"type":"Point"}
}