{
  "type": "Feature",
  "properties": {
    "iso:country":"AU",
    "sg:address":"434 Montague Rd",
    "sg:city":"Modbury North",
    "sg:classifiers":[
        {
            "category":"Banks & Credit Unions",
            "subcategory":"Financial Services",
            "type":"Services"
        }
    ],
    "sg:phone":"+61 8 8395 3270",
    "sg:postcode":"5092",
    "sg:province":"SA",
    "sg:tags":[
        "loan",
        "finance",
        "mortgage"
    ],
    "wof:name":"Sovereign Integrated Finance Pty Ltd",
    "wof:placetype":"venue"
},
  "geometry": {"coordinates":[138.672607422,-34.8287582397],"type":"Point"}
}