{
  "type": "Feature",
  "properties": {
    "iso:country":"AU",
    "sg:address":"2 Culworth Ave",
    "sg:city":"Killara",
    "sg:classifiers":[
        {
            "category":"Health Services",
            "subcategory":"Health Practitioner",
            "type":"Services"
        }
    ],
    "sg:phone":"+61 2 9498 7792",
    "sg:postcode":"2071",
    "sg:province":"NSW",
    "sg:tags":[
        "alternative"
    ],
    "wof:name":"Feldenkrais Method",
    "wof:placetype":"venue"
},
  "geometry": {"coordinates":[151.16339111299999,-33.7683372498],"type":"Point"}
}