{
  "type": "Feature",
  "properties": {
    "iso:country":"AU",
    "sg:address":"137 Eighth St",
    "sg:city":"Mildura",
    "sg:classifiers":[
        {
            "category":"Fast Food",
            "type":"Food & Drink"
        }
    ],
    "sg:phone":"+61 3 5023 1361",
    "sg:postcode":"3500",
    "sg:province":"VIC",
    "sg:tags":[
        "away",
        "take"
    ],
    "wof:name":"Hydr-8",
    "wof:placetype":"venue"
},
  "geometry": {"coordinates":[142.16169738799999,-34.1844139099],"type":"Point"}
}