{
  "type": "Feature",
  "properties": {
    "addr:full":"49 Ulick St Merewether NSW 2291",
    "addr:housenumber":"49",
    "addr:postcode":"2291",
    "addr:street":"Ulick St",
    "iso:country":"AU",
    "sg:address":"49 Ulick St",
    "sg:city":"Merewether",
    "sg:classifiers":[
        {
            "category":"Organizations",
            "subcategory":"Professional Association",
            "type":"Services"
        }
    ],
    "sg:phone":"+61 2 4963 4111",
    "sg:postcode":"2291",
    "sg:province":"NSW",
    "sg:tags":[
        "web",
        "internet"
    ],
    "wof:name":"Stickybeek. com.au",
    "wof:placetype":"venue"
},
  "geometry": {"coordinates":[151.73713684099999,-32.9374465942],"type":"Point"}
}