{
  "type": "Feature",
  "properties": {
    "addr:full":"Neville St Bovell WA 6280",
    "addr:postcode":"6280",
    "addr:street":"Neville St",
    "iso:country":"AU",
    "sg:address":"Neville St",
    "sg:city":"Bovell",
    "sg:classifiers":[
        {
            "category":"Professional",
            "type":"Services"
        }
    ],
    "sg:phone":"+61 8 9752 3195",
    "sg:postcode":"6280",
    "sg:province":"WA",
    "sg:tags":[
        "transport"
    ],
    "wof:name":"Sands Fridge Lines",
    "wof:placetype":"venue"
},
  "geometry": {"coordinates":[115.346702576,-33.6643791199],"type":"Point"}
}