{
  "type": "Feature",
  "properties": {
    "iso:country":"AU",
    "sg:address":"Ste 4/ 286 High St",
    "sg:city":"Penrith",
    "sg:classifiers":[
        {
            "category":"Professional",
            "subcategory":"Accounting & Tax Preparation",
            "type":"Services"
        }
    ],
    "sg:phone":"+61 2 4721 8552",
    "sg:postcode":"2750",
    "sg:province":"NSW",
    "sg:tags":[
        "accountant",
        "auditor"
    ],
    "wof:name":"Berger Piepers Chartered Accountants",
    "wof:placetype":"venue"
},
  "geometry": {"coordinates":[150.91560363799999,-33.8947219849],"type":"Point"}
}