{
  "type": "Feature",
  "properties": {
    "addr:full":"U3/ 78 Kitchener Pde Bankstown NSW 2200",
    "addr:housenumber":"78",
    "addr:postcode":"2200",
    "addr:street":"U3 /;Kitchener Pde",
    "iso:country":"AU",
    "sg:address":"U3/ 78 Kitchener Pde",
    "sg:city":"Bankstown",
    "sg:classifiers":[
        {
            "category":"Health Services",
            "subcategory":"Chiropractor",
            "type":"Services"
        }
    ],
    "sg:phone":"+61 2 9791 1671",
    "sg:postcode":"2200",
    "sg:province":"NSW",
    "wof:name":"Sabena Najim",
    "wof:placetype":"venue"
},
  "geometry": {"coordinates":[151.03312700000001,-33.913624],"type":"Point"}
}