{
  "type": "Feature",
  "properties": {
    "iso:country":"AU",
    "sg:address":"93 Barrett Drv",
    "sg:city":"Alice Springs",
    "sg:classifiers":[
        {
            "category":"Retail",
            "subcategory":"Event Space",
            "type":"Services"
        }
    ],
    "sg:phone":"+61 8 8950 0200",
    "sg:postcode":"0870",
    "sg:province":"NT",
    "sg:tags":[
        "function",
        "organiser"
    ],
    "wof:name":"Alice Springs Convention Centre",
    "wof:placetype":"venue"
},
  "geometry": {"coordinates":[133.88081359899999,-23.7100105286],"type":"Point"}
}