{
  "type": "Feature",
  "properties": {
    "addr:full":"25 Stokes St Lane Cove NSW 2066",
    "addr:housenumber":"25",
    "addr:postcode":"2066",
    "addr:street":"Stokes St",
    "iso:country":"AU",
    "sg:address":"25 Stokes St",
    "sg:city":"Lane Cove",
    "sg:classifiers":[
        {
            "category":"Social Services",
            "subcategory":"Child Care",
            "type":"Services"
        }
    ],
    "sg:phone":"+61 2 9427 1841",
    "sg:postcode":"2066",
    "sg:province":"NSW",
    "sg:tags":[
        "palliative"
    ],
    "wof:name":"Home & Community Care Program (HACC)",
    "wof:placetype":"venue"
},
  "geometry": {"coordinates":[151.174758911,-33.8090286255],"type":"Point"}
}