{
  "type": "Feature",
  "properties": {
    "addr:full":"10 Goulburn St Cheltenham VIC 3192",
    "addr:housenumber":"10",
    "addr:postcode":"3192",
    "addr:street":"Goulburn St",
    "iso:country":"AU",
    "sg:address":"10 Goulburn St",
    "sg:city":"Cheltenham",
    "sg:classifiers":[
        {
            "category":"Professional",
            "subcategory":"Accounting & Tax Preparation",
            "type":"Services"
        }
    ],
    "sg:phone":"+61 3 9585 0141",
    "sg:postcode":"3192",
    "sg:province":"VIC",
    "sg:tags":[
        "accountant",
        "auditor"
    ],
    "wof:name":"Wilson Neil D",
    "wof:placetype":"venue"
},
  "geometry": {"coordinates":[145.05909729000001,-37.9635772705],"type":"Point"}
}