{
  "type": "Feature",
  "properties": {
    "addr:full":"40 Mathew Crs Burpengary QLD 4505",
    "addr:housenumber":"40",
    "addr:postcode":"4505",
    "addr:street":"Mathew Crs",
    "iso:country":"AU",
    "sg:address":"40 Mathew Crs",
    "sg:city":"Burpengary",
    "sg:classifiers":[
        {
            "category":"Farming",
            "subcategory":"Livestock Farm",
            "type":"Manufacturing & Wholesale Goods"
        }
    ],
    "sg:phone":"+61 7 3888 3411",
    "sg:postcode":"4505",
    "sg:province":"QLD",
    "sg:tags":[
        "breeder",
        "horse",
        "stud"
    ],
    "wof:name":"Carramar Paint Horse Stud",
    "wof:placetype":"venue"
},
  "geometry": {"coordinates":[152.9921875,-27.1472892761],"type":"Point"}
}