{
  "type": "Feature",
  "properties": {
    "iso:country":"AU",
    "sg:address":"Shp2/ 3 Zillman Rd",
    "sg:city":"Hendra",
    "sg:classifiers":[
        {
            "category":"Retail",
            "subcategory":"Repair Shop",
            "type":"Services"
        }
    ],
    "sg:phone":"+61 7 3268 5883",
    "sg:postcode":"4011",
    "sg:province":"QLD",
    "sg:tags":[
        "mending",
        "clothing",
        "alteration"
    ],
    "wof:name":"Oi Wah Hui Clothing Alterations & Ironing",
    "wof:placetype":"venue"
},
  "geometry": {"coordinates":[153.063583,-27.422705],"type":"Point"}
}