{
  "type": "Feature",
  "properties": {
    "addr:full":"712 Anzac Hwy Glenelg SA 5045",
    "addr:housenumber":"712",
    "addr:postcode":"5045",
    "addr:street":"Anzac Hwy",
    "iso:country":"AU",
    "sg:address":"712 Anzac Hwy",
    "sg:city":"Glenelg",
    "sg:classifiers":[
        {
            "category":"Health Services",
            "subcategory":"Health Practitioner",
            "type":"Services"
        }
    ],
    "sg:phone":"+61 8 8295 1294",
    "sg:postcode":"5045",
    "sg:province":"SA",
    "sg:tags":[
        "physiotherapist"
    ],
    "wof:name":"Jones Helen",
    "wof:placetype":"venue"
},
  "geometry": {"coordinates":[138.51641799999999,-34.976688],"type":"Point"}
}