{
  "type": "Feature",
  "properties": {
    "addr:full":"59a Newline Rd Eagleton NSW 2324",
    "addr:housenumber":"59a",
    "addr:postcode":"2324",
    "addr:street":"Newline Rd",
    "iso:country":"AU",
    "sg:address":"59a Newline Rd",
    "sg:city":"Eagleton",
    "sg:classifiers":[
        {
            "category":"Wholesale",
            "subcategory":"Machinery & Supplies",
            "type":"Manufacturing & Wholesale Goods"
        }
    ],
    "sg:phone":"+61 2 4988 6542",
    "sg:postcode":"2324",
    "sg:province":"NSW",
    "sg:tags":[
        "process",
        "instrument",
        "control"
    ],
    "wof:name":"REM Controls Pty Ltd",
    "wof:placetype":"venue"
},
  "geometry": {"coordinates":[151.757080078,-32.7011413574],"type":"Point"}
}