{
  "type": "Feature",
  "properties": {
    "addr:full":"Mandurah Forum Mandurah WA 6210",
    "addr:postcode":"6210",
    "iso:country":"AU",
    "sg:address":"Mandurah Forum",
    "sg:city":"Mandurah",
    "sg:classifiers":[
        {
            "category":"Autos & Motor Vehicles",
            "subcategory":"Auto Supplies",
            "type":"Retail Goods"
        }
    ],
    "sg:phone":"+61 8 9581 2242",
    "sg:postcode":"6210",
    "sg:province":"WA",
    "sg:tags":[
        "tyre"
    ],
    "wof:name":"Kmart Tyre & Auto Service",
    "wof:placetype":"venue"
},
  "geometry": {"coordinates":[115.74091300000001,-32.536026],"type":"Point"}
}