{
  "type": "Feature",
  "properties": {
    "iso:country":"AU",
    "sg:address":"Shop 18 Langwarin Plaza 385 Cranbourne Rd",
    "sg:city":"Langwarrin",
    "sg:classifiers":[
        {
            "category":"Communications",
            "subcategory":"Film & Video Production",
            "type":"Services"
        }
    ],
    "sg:phone":"+61 3 9775 8000",
    "sg:postcode":"3910",
    "sg:province":"VIC",
    "sg:tags":[
        "dvd",
        "library"
    ],
    "wof:name":"Blockbuster",
    "wof:placetype":"venue"
},
  "geometry": {"coordinates":[145.198486328,-38.1478652954],"type":"Point"}
}