{
  "type": "Feature",
  "properties": {
    "addr:full":"928 North East Rd Modbury SA 5092",
    "addr:housenumber":"928",
    "addr:postcode":"5092",
    "addr:street":"North East Rd",
    "iso:country":"AU",
    "sg:address":"928 North East Rd",
    "sg:city":"Modbury",
    "sg:classifiers":[
        {
            "category":"Real Estate",
            "subcategory":"Real Estate Agent",
            "type":"Services"
        }
    ],
    "sg:phone":"+61 8 8395 7733",
    "sg:postcode":"5092",
    "sg:province":"SA",
    "wof:name":"Real Estate Partners",
    "wof:placetype":"venue"
},
  "geometry": {"coordinates":[138.68391418499999,-34.8330841064],"type":"Point"}
}