{
  "type": "Feature",
  "properties": {
    "addr:full":"14 Eden Ave Croydon Park NSW 2133",
    "addr:housenumber":"14",
    "addr:postcode":"2133",
    "addr:street":"Eden Ave",
    "iso:country":"AU",
    "sg:address":"14 Eden Ave",
    "sg:city":"Croydon Park",
    "sg:classifiers":[
        {
            "category":"Professional",
            "subcategory":"Art Services",
            "type":"Services"
        }
    ],
    "sg:phone":"+61 2 9745 3755",
    "sg:postcode":"2133",
    "sg:province":"NSW",
    "sg:tags":[
        "decorator",
        "painter"
    ],
    "wof:name":"Dec-Art Painting Co",
    "wof:placetype":"venue"
},
  "geometry": {"coordinates":[151.098144531,-33.8987503052],"type":"Point"}
}