{
  "type": "Feature",
  "properties": {
    "addr:full":"10 Cook Hwy Craiglie QLD 4871",
    "addr:housenumber":"10",
    "addr:postcode":"4871",
    "addr:street":"Cook Hwy",
    "iso:country":"AU",
    "sg:address":"10 Cook Hwy",
    "sg:city":"Craiglie",
    "sg:classifiers":[
        {
            "category":"Autos & Motor Vehicles",
            "subcategory":"Fuel & Gas Station",
            "type":"Retail Goods"
        }
    ],
    "sg:phone":"+61 7 4098 5588",
    "sg:postcode":"4871",
    "sg:province":"QLD",
    "wof:name":"Shell Port Douglas",
    "wof:placetype":"venue"
},
  "geometry": {"coordinates":[145.56617736800001,-16.658197403],"type":"Point"}
}