{
  "type": "Feature",
  "properties": {
    "addr:full":"2 6 Corby Ave Concord NSW 2137",
    "addr:housenumber":"6",
    "addr:postcode":"2137",
    "addr:street":"Corby Ave",
    "iso:country":"AU",
    "sg:address":"2 6 Corby Ave",
    "sg:city":"Concord",
    "sg:classifiers":[
        {
            "category":"Building & Trades",
            "subcategory":"Construction",
            "type":"Services"
        }
    ],
    "sg:phone":"+61 401 919 793",
    "sg:postcode":"2137",
    "sg:province":"NSW",
    "sg:tags":[
        "rendering",
        "cement"
    ],
    "wof:name":"Aus Pioneer co",
    "wof:placetype":"venue"
},
  "geometry": {"coordinates":[151.11111450199999,-33.8616867065],"type":"Point"}
}