{
  "type": "Feature",
  "properties": {
    "addr:full":"PO Box 6080 Lake Munmorah NSW 2259",
    "addr:postcode":"2259",
    "iso:country":"AU",
    "sg:address":"PO Box 6080",
    "sg:city":"Lake Munmorah",
    "sg:classifiers":[
        {
            "category":"Building & Trades",
            "subcategory":"Construction",
            "type":"Services"
        }
    ],
    "sg:phone":"+61 2 4955 7394",
    "sg:postcode":"2259",
    "sg:province":"NSW",
    "sg:tags":[
        "contractor"
    ],
    "wof:name":"Tolmark Homes Pty Ltd",
    "wof:placetype":"venue"
},
  "geometry": {"coordinates":[151.48101806599999,-33.1748428345],"type":"Point"}
}