{
  "type": "Feature",
  "properties": {
    "addr:full":"100 A Nelson Rd Box Hill North VIC 3129",
    "addr:housenumber":"100 a",
    "addr:postcode":"3129",
    "addr:street":"Nelson Rd",
    "iso:country":"AU",
    "sg:address":"100 A Nelson Rd",
    "sg:city":"Box Hill North",
    "sg:classifiers":[
        {
            "category":"Arts & Performance",
            "subcategory":"Music",
            "type":"Entertainment"
        }
    ],
    "sg:phone":"+61 3 9890 5939",
    "sg:postcode":"3129",
    "sg:province":"VIC",
    "sg:tags":[
        "mobile",
        "jockey",
        "disc"
    ],
    "wof:name":"Tectonic Entertainment",
    "wof:placetype":"venue"
},
  "geometry": {"coordinates":[145.126861572,-37.7974510193],"type":"Point"}
}