{
  "type": "Feature",
  "properties": {
    "iso:country":"AU",
    "sg:address":"Fleetwood Drv",
    "sg:city":"Narre Warren",
    "sg:classifiers":[
        {
            "category":"Education",
            "subcategory":"School",
            "type":"Public Place"
        }
    ],
    "sg:phone":"+61 3 9705 2281",
    "sg:postcode":"3805",
    "sg:province":"VIC",
    "sg:tags":[
        "state",
        "except",
        "nsw"
    ],
    "wof:name":"Hallam Valley Primary",
    "wof:placetype":"venue"
},
  "geometry": {"coordinates":[145.304596,-38.038731],"type":"Point"}
}