{
  "type": "Feature",
  "properties": {
    "iso:country":"AU",
    "sg:address":"Shop 6 Heritage Shopping Village Progress Rd",
    "sg:city":"Burpengary",
    "sg:classifiers":[
        {
            "category":"Health Services",
            "subcategory":"Health Practitioner",
            "type":"Services"
        }
    ],
    "sg:phone":"+61 7 3888 5866",
    "sg:postcode":"4505",
    "sg:province":"QLD",
    "sg:tags":[
        "physiotherapist"
    ],
    "wof:name":"Saville Diana",
    "wof:placetype":"venue"
},
  "geometry": {"coordinates":[152.976119995,-27.1531486511],"type":"Point"}
}