{
  "type": "Feature",
  "properties": {
    "iso:country":"AU",
    "sg:address":"319 Plummer St",
    "sg:city":"Port Melbourne",
    "sg:classifiers":[
        {
            "category":"Retail",
            "subcategory":"Storage",
            "type":"Services"
        }
    ],
    "sg:phone":"+61 3 9676 9989",
    "sg:postcode":"3207",
    "sg:province":"VIC",
    "wof:name":"Budget Self Storage",
    "wof:placetype":"venue"
},
  "geometry": {"coordinates":[144.919342,-37.833622],"type":"Point"}
}