{
  "type": "Feature",
  "properties": {
    "addr:full":"380 Sanctuary Rd Loch Sport VIC 3851",
    "addr:housenumber":"380",
    "addr:postcode":"3851",
    "addr:street":"Sanctuary Rd",
    "iso:country":"AU",
    "sg:address":"380 Sanctuary Rd",
    "sg:city":"Loch Sport",
    "sg:classifiers":[
        {
            "category":"Home & Garden",
            "subcategory":"Garden Supply",
            "type":"Retail Goods"
        }
    ],
    "sg:phone":"+61 3 5146 0513",
    "sg:postcode":"3851",
    "sg:province":"VIC",
    "sg:tags":[
        "equipment"
    ],
    "wof:name":"Loch Sport Garden Supplies",
    "wof:placetype":"venue"
},
  "geometry": {"coordinates":[147.582199097,-38.0485076904],"type":"Point"}
}