{
  "type": "Feature",
  "properties": {
    "addr:full":"50 Beaufort Rd Terrigal NSW 2260",
    "addr:housenumber":"50",
    "addr:postcode":"2260",
    "addr:street":"Beaufort Rd",
    "iso:country":"AU",
    "sg:address":"50 Beaufort Rd",
    "sg:city":"Terrigal",
    "sg:classifiers":[
        {
            "category":"Building & Trades",
            "subcategory":"Cleaning & Sanitation",
            "type":"Services"
        }
    ],
    "sg:phone":"+61 2 4384 3978",
    "sg:postcode":"2260",
    "sg:province":"NSW",
    "sg:tags":[
        "cleaner",
        "repairer",
        "roof"
    ],
    "wof:name":"Montgomery Plumbing Services",
    "wof:placetype":"venue"
},
  "geometry": {"coordinates":[151.432571,-33.43222],"type":"Point"}
}