{
  "type": "Feature",
  "properties": {
    "addr:full":"14- 17 Dansu Crt Hallam VIC 3803",
    "addr:housenumber":"17",
    "addr:postcode":"3803",
    "addr:street":"Dansu Crt",
    "iso:country":"AU",
    "sg:address":"14- 17 Dansu Crt",
    "sg:city":"Hallam",
    "sg:classifiers":[
        {
            "category":"Communications",
            "subcategory":"Television Station",
            "type":"Services"
        }
    ],
    "sg:phone":"+61 1800 032 984",
    "sg:postcode":"3803",
    "sg:province":"VIC",
    "sg:tags":[
        "wholesaler",
        "wire",
        "mfrs",
        "electric",
        "cable"
    ],
    "wof:name":"Edward Keller Australia Pty Ltd",
    "wof:placetype":"venue"
},
  "geometry": {"coordinates":[145.254760742,-38.0074462891],"type":"Point"}
}