{
  "type": "Feature",
  "properties": {
    "iso:country":"AU",
    "sg:address":"66 Emmerson St",
    "sg:city":"North Perth",
    "sg:classifiers":[
        {
            "category":"Real Estate",
            "subcategory":"Real Estate Agent",
            "type":"Services"
        }
    ],
    "sg:phone":"+61 419 491 070",
    "sg:postcode":"6006",
    "sg:province":"WA",
    "wof:name":"Popic Joseph",
    "wof:placetype":"venue"
},
  "geometry": {"coordinates":[115.847579956,-31.9344997406],"type":"Point"}
}