{
  "type": "Feature",
  "properties": {
    "iso:country":"AU",
    "sg:address":"3825 Lavers Hill Rd",
    "sg:city":"Kennedy's Creek",
    "sg:classifiers":[
        {
            "category":"Building & Trades",
            "subcategory":"Construction",
            "type":"Services"
        }
    ],
    "sg:phone":"+61 3 5238 3210",
    "sg:postcode":"3239",
    "sg:province":"VIC",
    "sg:tags":[
        "earth",
        "excavating",
        "moving",
        "contractor"
    ],
    "wof:name":"Kennedy's Creek Earthmoving",
    "wof:placetype":"venue"
},
  "geometry": {"coordinates":[143.427521,-38.582909],"type":"Point"}
}