{
  "type": "Feature",
  "properties": {
    "addr:full":"Suite 3, 24 Albert Rd South Melbourne VIC 3205",
    "addr:housenumber":"24",
    "addr:postcode":"3205",
    "addr:street":"Albert Rd",
    "iso:country":"AU",
    "sg:address":"Suite 3, 24 Albert Rd",
    "sg:city":"South Melbourne",
    "sg:classifiers":[
        {
            "category":"Professional",
            "subcategory":"Employment Agencies",
            "type":"Services"
        }
    ],
    "sg:phone":"+61 419 113 447",
    "sg:postcode":"3205",
    "sg:province":"VIC",
    "sg:tags":[
        "model"
    ],
    "wof:name":"Chic Productions - Model Edge",
    "wof:placetype":"venue"
},
  "geometry": {"coordinates":[144.97155799999999,-37.83326],"type":"Point"}
}