{
  "type": "Feature",
  "properties": {
    "addr:full":"Main St Currie TAS 7256",
    "addr:postcode":"7256",
    "addr:street":"Main St",
    "iso:country":"AU",
    "sg:address":"Main St",
    "sg:city":"Currie",
    "sg:classifiers":[
        {
            "category":"Food & Beverages",
            "subcategory":"Supermarket",
            "type":"Retail Goods"
        }
    ],
    "sg:phone":"+61 3 6462 1244",
    "sg:postcode":"7256",
    "sg:province":"TAS",
    "sg:tags":[
        "grocery",
        "store"
    ],
    "wof:name":"King Island IGA Everyday",
    "wof:placetype":"venue"
},
  "geometry": {"coordinates":[143.85075378400001,-39.930896759],"type":"Point"}
}