{
  "type": "Feature",
  "properties": {
    "addr:full":"94 Robinson Rd (East) Virginia QLD 4014",
    "addr:housenumber":"94",
    "addr:postcode":"4014",
    "addr:street":"Robinson Rd East",
    "iso:country":"AU",
    "sg:address":"94 Robinson Rd",
    "sg:city":"(East) Virginia",
    "sg:classifiers":[
        {
            "category":"Insurance",
            "subcategory":"Hazard Insurance",
            "type":"Services"
        }
    ],
    "sg:phone":"+61 13 11 55",
    "sg:postcode":"4014",
    "sg:province":"QLD",
    "sg:tags":[
        "motor",
        "vehicle"
    ],
    "wof:name":"Suncorp",
    "wof:placetype":"venue"
},
  "geometry": {"coordinates":[153.05755615199999,-27.3699874878],"type":"Point"}
}