{
  "type": "Feature",
  "properties": {
    "addr:full":"Unit 5, Oak Flats Trade Centre 9 Industrial Rd Oak Flats NSW 2529",
    "addr:housenumber":"9",
    "addr:postcode":"2529",
    "addr:street":"Industrial Rd",
    "iso:country":"AU",
    "sg:address":"Unit 5, Oak Flats Trade Centre 9 Industrial Rd",
    "sg:city":"Oak Flats",
    "sg:classifiers":[
        {
            "category":"Professional",
            "subcategory":"Detective & Security Services",
            "type":"Services"
        }
    ],
    "sg:phone":"+61 2 4256 6679",
    "sg:postcode":"2529",
    "sg:province":"NSW",
    "sg:tags":[
        "equipment",
        "window",
        "doors"
    ],
    "wof:name":"Leisure Coast Security Doors & Screens",
    "wof:placetype":"venue"
},
  "geometry": {"coordinates":[150.812957764,-34.5689659119],"type":"Point"}
}