{
  "type": "Feature",
  "properties": {
    "addr:full":"9 Carmyle Ave Toorak VIC 3142",
    "addr:housenumber":"9",
    "addr:postcode":"3142",
    "addr:street":"Carmyle Ave",
    "iso:country":"AU",
    "sg:address":"9 Carmyle Ave",
    "sg:city":"Toorak",
    "sg:classifiers":[
        {
            "category":"Health Services",
            "subcategory":"Doctor",
            "type":"Services"
        }
    ],
    "sg:phone":"+61 3 9822 4212",
    "sg:postcode":"3142",
    "sg:province":"VIC",
    "sg:tags":[
        "medical",
        "practitioner"
    ],
    "wof:name":"Gunter David",
    "wof:placetype":"venue"
},
  "geometry": {"coordinates":[145.02273559599999,-37.8498764038],"type":"Point"}
}