{
  "type": "Feature",
  "properties": {
    "iso:country":"AU",
    "sg:address":"103 Smith St",
    "sg:city":"Kempsey",
    "sg:classifiers":[
        {
            "category":"Home & Garden",
            "subcategory":"Household Appliances",
            "type":"Retail Goods"
        }
    ],
    "sg:phone":"+61 2 6562 4505",
    "sg:postcode":"2440",
    "sg:province":"NSW",
    "sg:tags":[
        "equipment",
        "gas"
    ],
    "wof:name":"Hi Speed Auto Gas Pty Ltd",
    "wof:placetype":"venue"
},
  "geometry": {"coordinates":[152.842651,-31.077978],"type":"Point"}
}