{
  "type": "Feature",
  "properties": {
    "iso:country":"AU",
    "sg:address":"2/ 25 Flinders St",
    "sg:city":"Lawson",
    "sg:classifiers":[
        {
            "category":"Wholesale",
            "subcategory":"Electrical",
            "type":"Manufacturing & Wholesale Goods"
        }
    ],
    "sg:phone":"+61 2 4759 1146",
    "sg:postcode":"2783",
    "sg:province":"NSW",
    "sg:tags":[
        "wholesaler"
    ],
    "wof:name":"Harlech Trading Co.",
    "wof:placetype":"venue"
},
  "geometry": {"coordinates":[150.4400177,-33.7256889343],"type":"Point"}
}