{
  "type": "Feature",
  "properties": {
    "addr:full":"420 Main Rd Gembrook VIC 3783",
    "addr:housenumber":"420",
    "addr:postcode":"3783",
    "addr:street":"Main Rd",
    "iso:country":"AU",
    "sg:address":"420 Main Rd",
    "sg:city":"Gembrook",
    "sg:classifiers":[
        {
            "category":"Utilities",
            "subcategory":"Refuse",
            "type":"Services"
        }
    ],
    "sg:phone":"+61 3 5968 1222",
    "sg:postcode":"3783",
    "sg:province":"VIC",
    "sg:tags":[
        "remover",
        "rubbish"
    ],
    "wof:name":"Ranges Bin Hire",
    "wof:placetype":"venue"
},
  "geometry": {"coordinates":[145.551987,-37.952675],"type":"Point"}
}