{
  "type": "Feature",
  "properties": {
    "iso:country":"AU",
    "sg:address":"5 Camp St",
    "sg:city":"Bright",
    "sg:classifiers":[
        {
            "category":"Professional",
            "subcategory":"Accounting & Tax Preparation",
            "type":"Services"
        }
    ],
    "sg:phone":"+61 3 5755 5105",
    "sg:postcode":"3741",
    "sg:province":"VIC",
    "sg:tags":[
        "accountant",
        "auditor"
    ],
    "wof:name":"Bright Accounting",
    "wof:placetype":"venue"
},
  "geometry": {"coordinates":[146.96212800000001,-36.727486],"type":"Point"}
}