{
  "type": "Feature",
  "properties": {
    "iso:country":"AU",
    "sg:address":"4 Plane St",
    "sg:city":"Lucindale",
    "sg:classifiers":[
        {
            "category":"Home & Garden",
            "subcategory":"Furniture",
            "type":"Retail Goods"
        }
    ],
    "sg:phone":"+61 8 8766 2063",
    "sg:postcode":"5272",
    "sg:province":"SA",
    "sg:tags":[
        "outdoor"
    ],
    "wof:name":"Smiley's Garden Furniture",
    "wof:placetype":"venue"
},
  "geometry": {"coordinates":[140.368073,-36.969212],"type":"Point"}
}