{
  "type": "Feature",
  "properties": {
    "iso:country":"AU",
    "sg:address":"277 Little Lonsdale St",
    "sg:city":"Melbourne",
    "sg:classifiers":[
        {
            "category":"Shopping",
            "subcategory":"Clothing, Apparel, & Fashions",
            "type":"Retail Goods"
        }
    ],
    "sg:phone":"+61 3 9671 4545",
    "sg:postcode":"3000",
    "sg:province":"VIC",
    "sg:tags":[
        "accessory"
    ],
    "wof:name":"Catherine Manuell Design",
    "wof:placetype":"venue"
},
  "geometry": {"coordinates":[144.96359252900001,-37.8109130859],"type":"Point"}
}