{
  "type": "Feature",
  "properties": {
    "addr:full":"Ft 4 6 Rosedale Ave Glen Huntly VIC 3163",
    "addr:housenumber":"6",
    "addr:postcode":"3163",
    "addr:street":"Ft;Rosedale Ave",
    "iso:country":"AU",
    "sg:address":"Ft 4 6 Rosedale Ave",
    "sg:city":"Glen Huntly",
    "sg:classifiers":[
        {
            "category":"Building & Trades",
            "subcategory":"Construction",
            "type":"Services"
        }
    ],
    "sg:phone":"+61 418 428 595",
    "sg:postcode":"3163",
    "sg:province":"VIC",
    "sg:tags":[
        "plasterboard",
        "plasterer",
        "fixer"
    ],
    "wof:name":"A.I.M. Quality Plastering",
    "wof:placetype":"venue"
},
  "geometry": {"coordinates":[145.04315185600001,-37.890789032],"type":"Point"}
}