{
  "type": "Feature",
  "properties": {
    "iso:country":"AU",
    "sg:address":"59a Woodville Rd",
    "sg:city":"Woodville",
    "sg:classifiers":[
        {
            "category":"Fast Food",
            "type":"Food & Drink"
        }
    ],
    "sg:phone":"+61 8 8345 5871",
    "sg:postcode":"5011",
    "sg:province":"SA",
    "sg:tags":[
        "away",
        "take"
    ],
    "wof:name":"Woodville Expresso Snack Bar",
    "wof:placetype":"venue"
},
  "geometry": {"coordinates":[138.536865234,-34.8787689209],"type":"Point"}
}