{
  "type": "Feature",
  "properties": {
    "addr:full":"Unit 5/ 1 Hotham Gr Elsternwick VIC 3185",
    "addr:housenumber":"1",
    "addr:postcode":"3185",
    "addr:street":"Hotham Gr",
    "iso:country":"AU",
    "sg:address":"Unit 5/ 1 Hotham Gr",
    "sg:city":"Elsternwick",
    "sg:classifiers":[
        {
            "category":"Professional",
            "subcategory":"Art Services",
            "type":"Services"
        }
    ],
    "sg:phone":"+61 407 545 590",
    "sg:postcode":"3185",
    "sg:province":"VIC",
    "sg:tags":[
        "decorator",
        "painter"
    ],
    "wof:name":"Terry Kavanagh",
    "wof:placetype":"venue"
},
  "geometry": {"coordinates":[144.995162964,-37.8798294067],"type":"Point"}
}