{
  "type": "Feature",
  "properties": {
    "addr:full":"27 Gladstone St Warragul VIC 3820",
    "addr:housenumber":"27",
    "addr:postcode":"3820",
    "addr:street":"Gladstone St",
    "iso:country":"AU",
    "sg:address":"27 Gladstone St",
    "sg:city":"Warragul",
    "sg:classifiers":[
        {
            "category":"Building & Trades",
            "subcategory":"Construction",
            "type":"Services"
        }
    ],
    "sg:phone":"+61 438 502 459",
    "sg:postcode":"3820",
    "sg:province":"VIC",
    "sg:tags":[
        "insulation",
        "contractor"
    ],
    "wof:name":"Warragul Insulation",
    "wof:placetype":"venue"
},
  "geometry": {"coordinates":[145.93554700000001,-38.163456],"type":"Point"}
}