{
  "type": "Feature",
  "properties": {
    "addr:full":"287 Victoria Rd Marrickville NSW 2204",
    "addr:housenumber":"287",
    "addr:postcode":"2204",
    "addr:street":"Victoria Rd",
    "iso:country":"AU",
    "sg:address":"287 Victoria Rd",
    "sg:city":"Marrickville",
    "sg:classifiers":[
        {
            "category":"Professional",
            "subcategory":"Accounting & Tax Preparation",
            "type":"Services"
        }
    ],
    "sg:phone":"+61 2 9560 7411",
    "sg:postcode":"2204",
    "sg:province":"NSW",
    "sg:tags":[
        "accountant",
        "auditor"
    ],
    "wof:name":"Arapidis E",
    "wof:placetype":"venue"
},
  "geometry": {"coordinates":[151.160507,-33.911613],"type":"Point"}
}