{
  "type": "Feature",
  "properties": {
    "addr:full":"17 River Rd Horsham VIC 3400",
    "addr:housenumber":"17",
    "addr:postcode":"3400",
    "addr:street":"River Rd",
    "iso:country":"AU",
    "sg:address":"17 River Rd",
    "sg:city":"Horsham",
    "sg:classifiers":[
        {
            "category":"Social Services",
            "subcategory":"Retirement Home",
            "type":"Services"
        }
    ],
    "sg:phone":"+61 3 5382 4105",
    "sg:postcode":"3400",
    "sg:province":"VIC",
    "sg:tags":[
        "village"
    ],
    "wof:name":"Village Life",
    "wof:placetype":"venue"
},
  "geometry": {"coordinates":[142.202224731,-36.7253417969],"type":"Point"}
}