{
  "type": "Feature",
  "properties": {
    "iso:country":"AU",
    "sg:address":"310 Smythes Rd",
    "sg:city":"Delacombe",
    "sg:classifiers":[
        {
            "category":"Donuts",
            "subcategory":"None",
            "type":"Food & Drink"
        }
    ],
    "sg:phone":"+61 3 5336 1481",
    "sg:postcode":"3356",
    "sg:province":"VIC",
    "sg:tags":[
        "die",
        "engraver",
        "sinker"
    ],
    "wof:name":"Spencer Engraving",
    "wof:placetype":"venue"
},
  "geometry": {"coordinates":[143.824539,-37.587509],"type":"Point"}
}