{
  "type": "Feature",
  "properties": {
    "addr:full":"Shop 5 122 Hothlyn Drv Craigieburn VIC 3064",
    "addr:housenumber":"shop 5",
    "addr:postcode":"122;3064",
    "addr:street":"Hothlyn Drv",
    "iso:country":"AU",
    "sg:address":"Shop 5 122 Hothlyn Drv",
    "sg:city":"Craigieburn",
    "sg:classifiers":[
        {
            "category":"Food & Beverages",
            "subcategory":"Groceries & Convenience Stores",
            "type":"Retail Goods"
        }
    ],
    "sg:phone":"+61 3 9305 5470",
    "sg:postcode":"3064",
    "sg:province":"VIC",
    "wof:name":"Hothlyn Drive Food Store",
    "wof:placetype":"venue"
},
  "geometry": {"coordinates":[144.93348693900001,-37.610786438],"type":"Point"}
}