{
  "type": "Feature",
  "properties": {
    "addr:full":"52 Kokoda St Darra QLD 4076",
    "addr:housenumber":"52",
    "addr:postcode":"4076",
    "addr:street":"Kokoda St",
    "iso:country":"AU",
    "sg:address":"52 Kokoda St",
    "sg:city":"Darra",
    "sg:classifiers":[
        {
            "category":"Building & Trades",
            "subcategory":"Landscaping Services",
            "type":"Services"
        }
    ],
    "sg:phone":"+61 7 3271 2390",
    "sg:postcode":"4076",
    "sg:province":"QLD",
    "sg:tags":[
        "designer",
        "landscape",
        "contractor"
    ],
    "wof:name":"A O&#039;Keefe Landscaping",
    "wof:placetype":"venue"
},
  "geometry": {"coordinates":[152.940216064,-27.5774478912],"type":"Point"}
}