{
  "type": "Feature",
  "properties": {
    "addr:full":"14 Layland St St James WA 6102",
    "addr:housenumber":"14",
    "addr:postcode":"6102",
    "addr:street":"Layland St",
    "iso:country":"AU",
    "sg:address":"14 Layland St St",
    "sg:city":"James",
    "sg:classifiers":[
        {
            "category":"Building & Trades",
            "subcategory":"Cleaning & Sanitation",
            "type":"Services"
        }
    ],
    "sg:phone":"+61 419 841 071",
    "sg:postcode":"6102",
    "sg:province":"WA",
    "sg:tags":[
        "industrial",
        "commercial",
        "contractor"
    ],
    "wof:name":"Clean Rite Property Services",
    "wof:placetype":"venue"
},
  "geometry": {"coordinates":[115.906326294,-32.0026664734],"type":"Point"}
}