{
  "type": "Feature",
  "properties": {
    "iso:country":"AU",
    "sg:address":"300 Severin St",
    "sg:city":"Cairns",
    "sg:classifiers":[
        {
            "category":"Shopping",
            "subcategory":"Beauty & Cosmetics",
            "type":"Retail Goods"
        }
    ],
    "sg:phone":"+61 7 4031 5511",
    "sg:postcode":"4870",
    "sg:province":"QLD",
    "sg:tags":[
        "equipment",
        "salon",
        "supply"
    ],
    "wof:name":"ProHair Pty Ltd",
    "wof:placetype":"venue"
},
  "geometry": {"coordinates":[145.76565551799999,-16.9261646271],"type":"Point"}
}