{
  "type": "Feature",
  "properties": {
    "addr:full":"Adil Rd Mareeba QLD 4880",
    "addr:postcode":"4880",
    "addr:street":"Adil Rd",
    "iso:country":"AU",
    "sg:address":"Adil Rd",
    "sg:city":"Mareeba",
    "sg:classifiers":[
        {
            "category":"Farming",
            "subcategory":"Farm",
            "type":"Manufacturing & Wholesale Goods"
        }
    ],
    "sg:phone":"+61 7 4092 1784",
    "sg:postcode":"4880",
    "sg:province":"QLD",
    "sg:tags":[
        "farmer"
    ],
    "wof:name":"Adil A",
    "wof:placetype":"venue"
},
  "geometry": {"coordinates":[145.41192626899999,-16.9648475647],"type":"Point"}
}