{
  "type": "Feature",
  "properties": {
    "iso:country":"AU",
    "sg:address":"Tooth St",
    "sg:city":"Nobby",
    "sg:classifiers":[
        {
            "category":"Travel",
            "subcategory":"Hotels & Motels",
            "type":"Entertainment"
        }
    ],
    "sg:phone":"+61 7 4696 3211",
    "sg:postcode":"4360",
    "sg:province":"QLD",
    "wof:name":"Rudds Pub",
    "wof:placetype":"venue"
},
  "geometry": {"coordinates":[151.90345764200001,-27.8519973755],"type":"Point"}
}