{
  "type": "Feature",
  "properties": {
    "iso:country":"AU",
    "sg:address":"Unit 1 7 Veronica St",
    "sg:city":"Capalaba",
    "sg:classifiers":[
        {
            "category":"Wholesale",
            "subcategory":"Painting Supplies",
            "type":"Manufacturing & Wholesale Goods"
        }
    ],
    "sg:phone":"+61 7 3245 1628",
    "sg:postcode":"4157",
    "sg:province":"QLD",
    "sg:tags":[
        "product",
        "cleaning"
    ],
    "wof:name":"All Beaut Cleaning & Maintenance",
    "wof:placetype":"venue"
},
  "geometry": {"coordinates":[153.19850158700001,-27.5282592773],"type":"Point"}
}