{
  "type": "Feature",
  "properties": {
    "addr:full":"25 Lindsay Pl Dubbo NSW 2830",
    "addr:housenumber":"25",
    "addr:postcode":"2830",
    "addr:street":"Lindsay Pl",
    "iso:country":"AU",
    "sg:address":"25 Lindsay Pl",
    "sg:city":"Dubbo",
    "sg:classifiers":[
        {
            "category":"Personal",
            "type":"Services"
        }
    ],
    "sg:phone":"+61 2 6882 7915",
    "sg:postcode":"2830",
    "sg:province":"NSW",
    "sg:tags":[
        "dressmaker"
    ],
    "wof:name":"J. Pittin",
    "wof:placetype":"venue"
},
  "geometry": {"coordinates":[148.627685547,-32.2447280884],"type":"Point"}
}