{
  "type": "Feature",
  "properties": {
    "addr:full":"Unit 2/ 11 Reliance Drv Tuggerah NSW 2259",
    "addr:housenumber":"11",
    "addr:postcode":"2259",
    "addr:street":"Reliance Drv",
    "iso:country":"AU",
    "sg:address":"Unit 2/ 11 Reliance Drv",
    "sg:city":"Tuggerah",
    "sg:classifiers":[
        {
            "category":"Wholesale",
            "subcategory":"Painting Supplies",
            "type":"Manufacturing & Wholesale Goods"
        }
    ],
    "sg:phone":"+61 2 4353 3220",
    "sg:postcode":"2259",
    "sg:province":"NSW",
    "sg:tags":[
        "product",
        "cleaning"
    ],
    "wof:name":"Elite Cleaning & Packaging Supplies",
    "wof:placetype":"venue"
},
  "geometry": {"coordinates":[151.41966247600001,-33.3162994385],"type":"Point"}
}