{
  "type": "Feature",
  "properties": {
    "addr:full":"222 Swallow Drv Erskine Park NSW 2759",
    "addr:housenumber":"222",
    "addr:postcode":"2759",
    "addr:street":"Swallow Drv",
    "iso:country":"AU",
    "sg:address":"222 Swallow Drv",
    "sg:city":"Erskine Park",
    "sg:classifiers":[
        {
            "category":"Health Services",
            "subcategory":"Health Practitioner",
            "type":"Services"
        }
    ],
    "sg:phone":"+61 2 9834 4395",
    "sg:postcode":"2759",
    "sg:province":"NSW",
    "sg:tags":[
        "physiotherapist"
    ],
    "wof:name":"Bonovas,Con",
    "wof:placetype":"venue"
},
  "geometry": {"coordinates":[150.80506897000001,-33.8001785278],"type":"Point"}
}