{
  "type": "Feature",
  "properties": {
    "addr:full":"56 Burke St Malvern East VIC 3145",
    "addr:housenumber":"56",
    "addr:postcode":"3145",
    "addr:street":"Burke St",
    "iso:country":"AU",
    "sg:address":"56 Burke St",
    "sg:city":"Malvern East",
    "sg:classifiers":[
        {
            "category":"Social Services",
            "subcategory":"Adult Care",
            "type":"Services"
        }
    ],
    "sg:phone":"+61 3 9571 2828",
    "sg:postcode":"3145",
    "sg:province":"VIC",
    "sg:tags":[
        "aged"
    ],
    "wof:name":"MECWA Day Centres For Frail Aged & Disabled",
    "wof:placetype":"venue"
},
  "geometry": {"coordinates":[145.048904419,-37.8731231689],"type":"Point"}
}