{
  "type": "Feature",
  "properties": {
    "addr:full":"26 Kevin Ave Ferntree Gully VIC 3156",
    "addr:housenumber":"26",
    "addr:postcode":"3156",
    "addr:street":"Kevin Ave",
    "iso:country":"AU",
    "sg:address":"26 Kevin Ave",
    "sg:city":"Ferntree Gully",
    "sg:classifiers":[
        {
            "category":"Retail",
            "subcategory":"Auto Repair",
            "type":"Services"
        }
    ],
    "sg:phone":"+61 3 9758 2544",
    "sg:postcode":"3156",
    "sg:province":"VIC",
    "sg:tags":[
        "beater",
        "painter",
        "panel"
    ],
    "wof:name":"Milsome Panels",
    "wof:placetype":"venue"
},
  "geometry": {"coordinates":[145.28228759800001,-37.8874893188],"type":"Point"}
}