{
  "type": "Feature",
  "properties": {
    "addr:full":"16 Old Gunnedah Rd Narrabri NSW 2390",
    "addr:housenumber":"16",
    "addr:postcode":"2390",
    "addr:street":"Old Gunnedah Rd",
    "iso:country":"AU",
    "sg:address":"16 Old Gunnedah Rd",
    "sg:city":"Narrabri",
    "sg:classifiers":[
        {
            "category":"Taxi",
            "type":"Transportation"
        }
    ],
    "sg:phone":"+61 2 6792 2552",
    "sg:postcode":"2390",
    "sg:province":"NSW",
    "sg:tags":[
        "cab"
    ],
    "wof:name":"Narrabri Radio Cabs",
    "wof:placetype":"venue"
},
  "geometry": {"coordinates":[149.78918457,-30.3356132507],"type":"Point"}
}