{
  "type": "Feature",
  "properties": {
    "addr:full":"Cnr Newmarket Rd & Cox St Windsor QLD 4030",
    "addr:postcode":"4030",
    "addr:street":"Cnr Newmarket Rd & Cox St",
    "iso:country":"AU",
    "sg:address":"Cnr Newmarket Rd & Cox St",
    "sg:city":"Windsor",
    "sg:classifiers":[
        {
            "category":"Retail",
            "subcategory":"Auto Repair",
            "type":"Services"
        }
    ],
    "sg:phone":"+61 7 3357 1555",
    "sg:postcode":"4030",
    "sg:province":"QLD",
    "sg:tags":[
        "engine",
        "reconditioning"
    ],
    "wof:name":"Power Brakes & Engineering",
    "wof:placetype":"venue"
},
  "geometry": {"coordinates":[153.02858000000001,-27.437695],"type":"Point"}
}