{
  "type": "Feature",
  "properties": {
    "addr:full":"49 Aberdeen St Scone NSW 2337",
    "addr:housenumber":"49",
    "addr:postcode":"2337",
    "addr:street":"Aberdeen St",
    "iso:country":"AU",
    "sg:address":"49 Aberdeen St",
    "sg:city":"Scone",
    "sg:classifiers":[
        {
            "category":"Arena",
            "subcategory":"Sports Club",
            "type":"Entertainment"
        }
    ],
    "sg:phone":"+61 2 6545 1091",
    "sg:postcode":"2337",
    "sg:province":"NSW",
    "sg:tags":[
        "union",
        "rugby"
    ],
    "wof:name":"Scone Rugby Union Club The",
    "wof:placetype":"venue"
},
  "geometry": {"coordinates":[150.86068725600001,-32.04662323],"type":"Point"}
}