{
  "type": "Feature",
  "properties": {
    "addr:full":"5 Carlsson Pl Hope Valley SA 5090",
    "addr:housenumber":"5",
    "addr:postcode":"5090",
    "addr:street":"Carlsson Pl",
    "iso:country":"AU",
    "sg:address":"5 Carlsson Pl",
    "sg:city":"Hope Valley",
    "sg:classifiers":[
        {
            "category":"Professional",
            "subcategory":"Engineering",
            "type":"Services"
        }
    ],
    "sg:phone":"+61 429 805 118",
    "sg:postcode":"5090",
    "sg:province":"SA",
    "sg:tags":[
        "electronic",
        "engineer"
    ],
    "wof:name":"Associated Electronic Services Pty Ltd",
    "wof:placetype":"venue"
},
  "geometry": {"coordinates":[138.68927001899999,-34.8459701538],"type":"Point"}
}