{
  "type": "Feature",
  "properties": {
    "addr:full":"Unit 1 11 Manning St South Brisbane QLD 4101",
    "addr:housenumber":"11",
    "addr:postcode":"4101",
    "addr:street":"Manning St",
    "iso:country":"AU",
    "sg:address":"Unit 1 11 Manning St",
    "sg:city":"South Brisbane",
    "sg:classifiers":[
        {
            "category":"Banks & Credit Unions",
            "subcategory":"Financial Services",
            "type":"Services"
        }
    ],
    "sg:phone":"+61 1300 551 755",
    "sg:postcode":"4101",
    "sg:province":"QLD",
    "sg:tags":[
        "planning"
    ],
    "wof:name":"Batten Finacial Services",
    "wof:placetype":"venue"
},
  "geometry": {"coordinates":[153.013916016,-27.4753227234],"type":"Point"}
}