{
  "type": "Feature",
  "properties": {
    "iso:country":"AU",
    "sg:address":"7 Weatherburn Way",
    "sg:city":"Kardinya",
    "sg:classifiers":[
        {
            "category":"Structure",
            "subcategory":"Building",
            "type":"Public Place"
        }
    ],
    "sg:phone":"+61 1800 777 847",
    "sg:postcode":"6163",
    "sg:province":"WA",
    "sg:tags":[
        "sail",
        "shade"
    ],
    "sg:website":"http://www.shadesail.com.au/yp.html",
    "wof:name":"Shade & Sail Innovations",
    "wof:placetype":"venue"
},
  "geometry": {"coordinates":[115.804688,-32.061852],"type":"Point"}
}