{
  "type": "Feature",
  "properties": {
    "iso:country":"AU",
    "sg:address":"22 Salisbury Hwy",
    "sg:city":"Salisbury",
    "sg:classifiers":[
        {
            "category":"Real Estate",
            "subcategory":"Real Estate Agent",
            "type":"Services"
        }
    ],
    "sg:phone":"+61 8 8250 7000",
    "sg:postcode":"5108",
    "sg:province":"SA",
    "wof:name":"Northern Property World",
    "wof:placetype":"venue"
},
  "geometry": {"coordinates":[138.64663696299999,-34.7566490173],"type":"Point"}
}