{
  "type": "Feature",
  "properties": {
    "addr:full":"391 Lt Bourke St Melbourne VIC 3000",
    "addr:housenumber":"391",
    "addr:postcode":"3000",
    "addr:street":"Lt Bourke St",
    "iso:country":"AU",
    "sg:address":"391 Lt Bourke St",
    "sg:city":"Melbourne",
    "sg:classifiers":[
        {
            "category":"Shopping",
            "subcategory":"Pawn Shop",
            "type":"Retail Goods"
        }
    ],
    "sg:phone":"+61 3 9670 0560",
    "sg:postcode":"3000",
    "sg:province":"VIC",
    "sg:tags":[
        "pawnbroker"
    ],
    "wof:name":"Camera Lane",
    "wof:placetype":"venue"
},
  "geometry": {"coordinates":[144.969192505,-37.8124732971],"type":"Point"}
}