{
  "type": "Feature",
  "properties": {
    "iso:country":"AU",
    "sg:address":"PO Box 7398",
    "sg:city":"MC Garbutt",
    "sg:classifiers":[
        {
            "category":"Building & Trades",
            "subcategory":"Construction",
            "type":"Services"
        }
    ],
    "sg:phone":"+61 7 4779 2626",
    "sg:postcode":"4814",
    "sg:province":"QLD",
    "sg:tags":[
        "contractor"
    ],
    "wof:name":"Trojan Homes",
    "wof:placetype":"venue"
},
  "geometry": {"coordinates":[146.783768,-19.26436],"type":"Point"}
}