{
  "type": "Feature",
  "properties": {
    "addr:full":"Norseman Hwy Esperance WA 6450",
    "addr:postcode":"6450",
    "addr:street":"Norseman Hwy",
    "iso:country":"AU",
    "sg:address":"Norseman Hwy",
    "sg:city":"Esperance",
    "sg:classifiers":[
        {
            "category":"Wholesale",
            "subcategory":"Meat",
            "type":"Manufacturing & Wholesale Goods"
        }
    ],
    "sg:phone":"+61 8 9076 1245",
    "sg:postcode":"6450",
    "sg:province":"WA",
    "sg:tags":[
        "abattoir"
    ],
    "wof:name":"Shark Lake Meat Works",
    "wof:placetype":"venue"
},
  "geometry": {"coordinates":[121.89927673299999,-33.852771759],"type":"Point"}
}