{
  "type": "Feature",
  "properties": {
    "iso:country":"AU",
    "sg:address":"207 Para Rd",
    "sg:city":"Montmorency",
    "sg:classifiers":[
        {
            "category":"Manufacturing",
            "subcategory":"Tools & Machinery",
            "type":"Manufacturing & Wholesale Goods"
        }
    ],
    "sg:phone":"+61 3 9431 7300",
    "sg:postcode":"3094",
    "sg:province":"VIC",
    "sg:tags":[
        "toolmaker"
    ],
    "wof:name":"Lovitt Technologies Australia Pty Ltd",
    "wof:placetype":"venue"
},
  "geometry": {"coordinates":[145.110671997,-37.7076301575],"type":"Point"}
}