{
  "type": "Feature",
  "properties": {
    "iso:country":"AU",
    "sg:address":"53 Torrance Crs",
    "sg:city":"Quakers Hill",
    "sg:classifiers":[
        {
            "category":"Building & Trades",
            "subcategory":"Construction",
            "type":"Services"
        }
    ],
    "sg:phone":"+61 2 9626 0515",
    "sg:postcode":"2763",
    "sg:province":"NSW",
    "sg:tags":[
        "concrete",
        "contractor"
    ],
    "wof:name":"A & M Mattarelli Pty Ltd",
    "wof:placetype":"venue"
},
  "geometry": {"coordinates":[150.88661193900001,-33.7264213562],"type":"Point"}
}