{
  "type": "Feature",
  "properties": {
    "iso:country":"AU",
    "sg:address":"Cnr Hutton & Howe Sts",
    "sg:city":"Osborne Park",
    "sg:classifiers":[
        {
            "category":"Autos & Motor Vehicles",
            "subcategory":"Auto Supplies",
            "type":"Retail Goods"
        }
    ],
    "sg:phone":"+61 8 9444 1122",
    "sg:postcode":"6017",
    "sg:province":"WA",
    "sg:tags":[
        "tyre"
    ],
    "wof:name":"Ian Diffen World Of Tyres & Mufflers",
    "wof:placetype":"venue"
},
  "geometry": {"coordinates":[115.817733765,-31.9038505554],"type":"Point"}
}