{
  "type": "Feature",
  "properties": {
    "iso:country":"AU",
    "sg:address":"Unit 12 17-19 Boundary St",
    "sg:city":"Parramatta",
    "sg:classifiers":[
        {
            "category":"Manufacturing",
            "subcategory":"Metals",
            "type":"Manufacturing & Wholesale Goods"
        }
    ],
    "sg:phone":"+61 2 9633 1289",
    "sg:postcode":"2150",
    "sg:province":"NSW",
    "sg:tags":[
        "titanium"
    ],
    "wof:name":"Grand Prix Products",
    "wof:placetype":"venue"
},
  "geometry": {"coordinates":[150.998504639,-33.8256378174],"type":"Point"}
}