{
  "type": "Feature",
  "properties": {
    "addr:full":"9 Lincoln Rd Croydon VIC 3136",
    "addr:housenumber":"9",
    "addr:postcode":"3136",
    "addr:street":"Lincoln Rd",
    "iso:country":"AU",
    "sg:address":"9 Lincoln Rd",
    "sg:city":"Croydon",
    "sg:classifiers":[
        {
            "category":"Government",
            "subcategory":"Court House",
            "type":"Public Place"
        }
    ],
    "sg:phone":"+61 3 9725 0124",
    "sg:postcode":"3136",
    "sg:province":"VIC",
    "sg:tags":[
        "personal",
        "marriage",
        "family",
        "counselling"
    ],
    "wof:name":"Heart to Heart Counselling Service",
    "wof:placetype":"venue"
},
  "geometry": {"coordinates":[145.28715515100001,-37.7870025635],"type":"Point"}
}