{
  "type": "Feature",
  "properties": {
    "addr:full":"19 Helios St Shailer Park QLD 4128",
    "addr:housenumber":"19",
    "addr:postcode":"4128",
    "addr:street":"Helios St",
    "iso:country":"AU",
    "sg:address":"19 Helios St",
    "sg:city":"Shailer Park",
    "sg:classifiers":[
        {
            "category":"Arena",
            "subcategory":"Sports Club",
            "type":"Entertainment"
        }
    ],
    "sg:phone":"+61 419 791 356",
    "sg:postcode":"4128",
    "sg:province":"QLD",
    "sg:tags":[
        "organisation",
        "sporting"
    ],
    "wof:name":"Universities Rugby League Qld",
    "wof:placetype":"venue"
},
  "geometry": {"coordinates":[153.175018311,-27.6552753448],"type":"Point"}
}