{
  "type": "Feature",
  "properties": {
    "iso:country":"AU",
    "sg:address":"93 Batman Ave",
    "sg:city":"Shepparton",
    "sg:classifiers":[
        {
            "category":"Personal",
            "subcategory":"Massage",
            "type":"Services"
        }
    ],
    "sg:phone":"+61 3 5822 0449",
    "sg:postcode":"3630",
    "sg:province":"VIC",
    "sg:tags":[
        "therapy"
    ],
    "wof:name":"Aloomba Massage Centre",
    "wof:placetype":"venue"
},
  "geometry": {"coordinates":[145.38130188,-36.3581047058],"type":"Point"}
}