{
  "type": "Feature",
  "properties": {
    "addr:full":"43 Wyong St Keilor East VIC 3033",
    "addr:housenumber":"43",
    "addr:postcode":"3033",
    "addr:street":"Wyong St",
    "iso:country":"AU",
    "sg:address":"43 Wyong St",
    "sg:city":"Keilor East",
    "sg:classifiers":[
        {
            "category":"Food & Beverages",
            "subcategory":"Fruits & Vegetables",
            "type":"Retail Goods"
        }
    ],
    "sg:phone":"+61 3 9336 2925",
    "sg:postcode":"3033",
    "sg:province":"VIC",
    "sg:tags":[
        "greengrocer",
        "fruiterer"
    ],
    "wof:name":"Centreway Fruit & Veg",
    "wof:placetype":"venue"
},
  "geometry": {"coordinates":[144.86601300000001,-37.732933],"type":"Point"}
}