{
  "type": "Feature",
  "properties": {
    "addr:full":"29 Rafter Crs Abbotsbury NSW 2176",
    "addr:housenumber":"29",
    "addr:postcode":"2176",
    "addr:street":"Rafter Crs",
    "iso:country":"AU",
    "sg:address":"29 Rafter Crs",
    "sg:city":"Abbotsbury",
    "sg:classifiers":[
        {
            "category":"Retail",
            "subcategory":"Auto Rental",
            "type":"Services"
        }
    ],
    "sg:phone":"+61 2 9822 0082",
    "sg:postcode":"2176",
    "sg:province":"NSW",
    "sg:tags":[
        "car",
        "wedding"
    ],
    "wof:name":"Amore Limousines",
    "wof:placetype":"venue"
},
  "geometry": {"coordinates":[150.86752319300001,-33.873008728],"type":"Point"}
}