{
  "type": "Feature",
  "properties": {
    "iso:country":"AU",
    "sg:address":"\"Corinya\" Riverside Drv",
    "sg:city":"Kalgan",
    "sg:classifiers":[
        {
            "category":"Farming",
            "subcategory":"Farm",
            "type":"Manufacturing & Wholesale Goods"
        }
    ],
    "sg:phone":"+61 8 9846 4290",
    "sg:postcode":"6330",
    "sg:province":"WA",
    "sg:tags":[
        "farmer"
    ],
    "wof:name":"James B A & L D",
    "wof:placetype":"venue"
},
  "geometry": {"coordinates":[117.999443054,-34.9053916931],"type":"Point"}
}