{
  "type": "Feature",
  "properties": {
    "iso:country":"AU",
    "sg:address":"Shop 7/ 20-26 Addison St",
    "sg:city":"Shellharbour",
    "sg:classifiers":[
        {
            "category":"Cafe",
            "type":"Food & Drink"
        }
    ],
    "sg:phone":"+61 2 4296 1233",
    "sg:postcode":"2529",
    "sg:province":"NSW",
    "wof:name":"Maritz Cafe",
    "wof:placetype":"venue"
},
  "geometry": {"coordinates":[150.867431641,-34.5793533325],"type":"Point"}
}