{
  "type": "Feature",
  "properties": {
    "addr:full":"1st Floor, 8 Gregory Tce Alice Springs NT 0870",
    "addr:housenumber":"8",
    "addr:postcode":"nt 0870",
    "addr:street":"Gregory Tce",
    "iso:country":"AU",
    "sg:address":"1st Floor, 8",
    "sg:city":"Gregory Tce Alice Springs",
    "sg:classifiers":[
        {
            "category":"Structure",
            "subcategory":"Office Building",
            "type":"Public Place"
        }
    ],
    "sg:phone":"+61 8 8950 8100",
    "sg:postcode":"0870",
    "sg:province":"NT",
    "sg:tags":[
        "serviced"
    ],
    "wof:name":"Allice Springs Busines Centre",
    "wof:placetype":"venue"
},
  "geometry": {"coordinates":[133.85372924800001,-23.7290496826],"type":"Point"}
}