{
  "type": "Feature",
  "properties": {
    "addr:full":"4-8 Geenaway St Bulleen VIC 3105",
    "addr:housenumber":"4-8",
    "addr:postcode":"3105",
    "addr:street":"Geenaway St",
    "iso:country":"AU",
    "sg:address":"4-8 Geenaway St",
    "sg:city":"Bulleen",
    "sg:classifiers":[
        {
            "category":"Military Area",
            "subcategory":"Army Base",
            "type":"Public Place"
        }
    ],
    "sg:phone":"+61 1800 880 155",
    "sg:postcode":"3105",
    "sg:province":"VIC",
    "sg:tags":[
        "wholesaler",
        "clutch",
        "brake",
        "mfrs",
        "equipment"
    ],
    "wof:name":"Rotors & Drums Australia Pty Ltd",
    "wof:placetype":"venue"
},
  "geometry": {"coordinates":[145.08277893100001,-37.7610359192],"type":"Point"}
}