{
  "type": "Feature",
  "properties": {
    "addr:full":"16 Ronald Ave Narraweena NSW 2099",
    "addr:housenumber":"16",
    "addr:postcode":"2099",
    "addr:street":"Ronald Ave",
    "iso:country":"AU",
    "sg:address":"16 Ronald Ave",
    "sg:city":"Narraweena",
    "sg:classifiers":[
        {
            "category":"Building & Trades",
            "subcategory":"Construction",
            "type":"Services"
        }
    ],
    "sg:phone":"+61 2 9972 0596",
    "sg:postcode":"2099",
    "sg:province":"NSW",
    "sg:tags":[
        "equipment",
        "system",
        "automation"
    ],
    "wof:name":"Alsinger Intergration Pty Ltd",
    "wof:placetype":"venue"
},
  "geometry": {"coordinates":[151.27149963400001,-33.7482070923],"type":"Point"}
}