{
  "type": "Feature",
  "properties": {
    "addr:full":"Suite 17, 91- 93 Macleay St Potts Point NSW 2011",
    "addr:housenumber":"91 93",
    "addr:postcode":"2011",
    "addr:street":"Macleay St",
    "iso:country":"AU",
    "sg:address":"Suite 17, 91- 93 Macleay St",
    "sg:city":"Potts Point",
    "sg:classifiers":[
        {
            "category":"Travel",
            "subcategory":"Travel Agent",
            "type":"Entertainment"
        }
    ],
    "sg:phone":"+61 2 9361 3201",
    "sg:postcode":"2011",
    "sg:province":"NSW",
    "sg:tags":[
        "consultant"
    ],
    "wof:name":"Intermedia Travel Consultant (NSW) Pty Ltd",
    "wof:placetype":"venue"
},
  "geometry": {"coordinates":[151.225006103,-33.8714981079],"type":"Point"}
}