{
  "type": "Feature",
  "properties": {
    "addr:full":"85 Lindsay St Hamilton NSW 2303",
    "addr:housenumber":"85",
    "addr:postcode":"2303",
    "addr:street":"Lindsay St",
    "iso:country":"AU",
    "sg:address":"85 Lindsay St",
    "sg:city":"Hamilton",
    "sg:classifiers":[
        {
            "category":"Personal",
            "type":"Services"
        }
    ],
    "sg:phone":"+61 2 4969 6868",
    "sg:postcode":"2303",
    "sg:province":"NSW",
    "sg:tags":[
        "reducing",
        "treatment",
        "weight"
    ],
    "wof:name":"Hamilton Natural Therapies Centre",
    "wof:placetype":"venue"
},
  "geometry": {"coordinates":[151.74594099999999,-32.921799],"type":"Point"}
}