{
  "type": "Feature",
  "properties": {
    "addr:full":"Balmoral Rd Cavendish VIC 3314",
    "addr:postcode":"3314",
    "addr:street":"Balmoral Rd",
    "iso:country":"AU",
    "sg:address":"Balmoral Rd",
    "sg:city":"Cavendish",
    "sg:classifiers":[
        {
            "category":"Building & Trades",
            "subcategory":"Construction",
            "type":"Services"
        }
    ],
    "sg:phone":"+61 3 5574 2376",
    "sg:postcode":"3314",
    "sg:province":"VIC",
    "sg:tags":[
        "contractor"
    ],
    "wof:name":"Hearn G N",
    "wof:placetype":"venue"
},
  "geometry": {"coordinates":[142.03903198200001,-37.5272293091],"type":"Point"}
}