{
  "type": "Feature",
  "properties": {
    "iso:country":"AU",
    "sg:address":"1 Farr St & Corner Sydenham Rd",
    "sg:city":"Marrickville",
    "sg:classifiers":[
        {
            "category":"Banks & Credit Unions",
            "subcategory":"Bureau De Change",
            "type":"Services"
        }
    ],
    "sg:phone":"+61 2 9568 2233",
    "sg:postcode":"2204",
    "sg:province":"NSW",
    "sg:tags":[
        "supply",
        "equipment",
        "beating",
        "panel"
    ],
    "wof:name":"Autorobot Distributors",
    "wof:placetype":"venue"
},
  "geometry": {"coordinates":[151.15986599999999,-33.908318],"type":"Point"}
}