{
  "type": "Feature",
  "properties": {
    "addr:full":"228 Madagascar Drv Kings Park NSW 2148",
    "addr:housenumber":"228",
    "addr:postcode":"2148",
    "addr:street":"Madagascar Drv",
    "iso:country":"AU",
    "sg:address":"228 Madagascar Drv",
    "sg:city":"Kings Park",
    "sg:classifiers":[
        {
            "category":"Utilities",
            "subcategory":"Electric",
            "type":"Services"
        }
    ],
    "sg:phone":"+61 412 313 531",
    "sg:postcode":"2148",
    "sg:province":"NSW",
    "sg:tags":[
        "electrical",
        "contractor"
    ],
    "wof:name":"Hammer Electrical Pty Ltd",
    "wof:placetype":"venue"
},
  "geometry": {"coordinates":[150.915527344,-33.7432098389],"type":"Point"}
}