{
  "type": "Feature",
  "properties": {
    "addr:full":"224 Renmark Ave Renmark SA 5341",
    "addr:housenumber":"224",
    "addr:postcode":"5341",
    "addr:street":"Renmark Ave",
    "iso:country":"AU",
    "sg:address":"224 Renmark Ave",
    "sg:city":"Renmark",
    "sg:classifiers":[
        {
            "category":"Shopping",
            "type":"Retail Goods"
        }
    ],
    "sg:phone":"+61 8 8586 6988",
    "sg:postcode":"5341",
    "sg:province":"SA",
    "sg:tags":[
        "equipment",
        "safety",
        "accessory"
    ],
    "wof:name":"Daves Work N&#039; Safety Gear",
    "wof:placetype":"venue"
},
  "geometry": {"coordinates":[140.74325561500001,-34.1766586304],"type":"Point"}
}