{
  "type": "Feature",
  "properties": {
    "addr:full":"Suite 8, 56 Creaney Drv Kingsley WA 6026",
    "addr:housenumber":"56",
    "addr:postcode":"6026",
    "addr:street":"Creaney Drv",
    "iso:country":"AU",
    "sg:address":"Suite 8, 56 Creaney Drv",
    "sg:city":"Kingsley",
    "sg:classifiers":[
        {
            "category":"Professional",
            "subcategory":"Accounting & Tax Preparation",
            "type":"Services"
        }
    ],
    "sg:phone":"+61 8 9409 5550",
    "sg:postcode":"6026",
    "sg:province":"WA",
    "sg:tags":[
        "consultant",
        "taxation"
    ],
    "wof:name":"Graeme Hughes",
    "wof:placetype":"venue"
},
  "geometry": {"coordinates":[115.790412903,-31.8077640533],"type":"Point"}
}