{
  "type": "Feature",
  "properties": {
    "addr:full":"1/27 Humphries Rd St Johns Park NSW 2176",
    "addr:housenumber":"/ 27",
    "addr:postcode":"2176",
    "addr:street":"Humphries Rd",
    "iso:country":"AU",
    "sg:address":"1/27 Humphries Rd St",
    "sg:city":"Johns Park",
    "sg:classifiers":[
        {
            "category":"Health Services",
            "subcategory":"Doctor",
            "type":"Services"
        }
    ],
    "sg:phone":"+61 2 9822 0473",
    "sg:postcode":"2176",
    "sg:province":"NSW",
    "sg:tags":[
        "medical",
        "practitioner"
    ],
    "wof:name":"Cumberland Imaging",
    "wof:placetype":"venue"
},
  "geometry": {"coordinates":[150.90184020999999,-33.8892402649],"type":"Point"}
}