{
  "type": "Feature",
  "properties": {
    "addr:full":"87 Osborne Rd Mitchelton QLD 4053",
    "addr:housenumber":"87",
    "addr:postcode":"4053",
    "addr:street":"Osborne Rd",
    "iso:country":"AU",
    "sg:address":"87 Osborne Rd",
    "sg:city":"Mitchelton",
    "sg:classifiers":[
        {
            "category":"Professional",
            "subcategory":"Employment Agencies",
            "type":"Services"
        }
    ],
    "sg:phone":"+61 7 3354 6600",
    "sg:postcode":"4053",
    "sg:province":"QLD",
    "wof:name":"Sarina Russo Job Access",
    "wof:placetype":"venue"
},
  "geometry": {"coordinates":[152.977615356,-27.410572052],"type":"Point"}
}