{
  "type": "Feature",
  "properties": {
    "addr:full":"Alfred St Largs Bay SA 5016",
    "addr:postcode":"5016",
    "addr:street":"Alfred St",
    "iso:country":"AU",
    "sg:address":"Alfred St",
    "sg:city":"Largs Bay",
    "sg:classifiers":[
        {
            "category":"Home & Garden",
            "subcategory":"Carpets & Floor Coverings",
            "type":"Retail Goods"
        }
    ],
    "sg:phone":"+61 432 402 795",
    "sg:postcode":"5016",
    "sg:province":"SA",
    "sg:tags":[
        "tile",
        "wall",
        "layer"
    ],
    "wof:name":"Nick's Professional Ceramics",
    "wof:placetype":"venue"
},
  "geometry": {"coordinates":[138.499603272,-34.828250885],"type":"Point"}
}