{
  "type": "Feature",
  "properties": {
    "addr:full":"39- 41 Alexander Ave Taren Point NSW 2229",
    "addr:housenumber":"41",
    "addr:postcode":"2229",
    "addr:street":"Alexander Ave",
    "iso:country":"AU",
    "sg:address":"39- 41 Alexander Ave",
    "sg:city":"Taren Point",
    "sg:classifiers":[
        {
            "category":"Bus Stop",
            "subcategory":"None",
            "type":"Transportation"
        }
    ],
    "sg:phone":"+61 2 9540 2355",
    "sg:postcode":"2229",
    "sg:province":"NSW",
    "sg:tags":[
        "pipe",
        "fitting",
        "metal"
    ],
    "wof:name":"Caman Engineering International Pty Ltd",
    "wof:placetype":"venue"
},
  "geometry": {"coordinates":[151.123703003,-34.0218086243],"type":"Point"}
}