{
  "type": "Feature",
  "properties": {
    "addr:full":"2 Poplar St Wonthaggi VIC 3995",
    "addr:housenumber":"2",
    "addr:postcode":"3995",
    "addr:street":"Poplar St",
    "iso:country":"AU",
    "sg:address":"2 Poplar St",
    "sg:city":"Wonthaggi",
    "sg:classifiers":[
        {
            "category":"Building & Trades",
            "subcategory":"Construction",
            "type":"Services"
        }
    ],
    "sg:phone":"+61 3 5672 2338",
    "sg:postcode":"3995",
    "sg:province":"VIC",
    "sg:tags":[
        "concrete",
        "contractor"
    ],
    "wof:name":"John Lee",
    "wof:placetype":"venue"
},
  "geometry": {"coordinates":[145.59245300000001,-38.600449],"type":"Point"}
}