{
  "type": "Feature",
  "properties": {
    "addr:full":"29 Trumpeter St Battery Point TAS 7004",
    "addr:housenumber":"29",
    "addr:postcode":"7004",
    "addr:street":"Trumpeter St",
    "iso:country":"AU",
    "sg:address":"29 Trumpeter St",
    "sg:city":"Battery Point",
    "sg:classifiers":[
        {
            "category":"Travel",
            "subcategory":"Hotels & Motels",
            "type":"Entertainment"
        }
    ],
    "sg:phone":"+61 3 6223 5551",
    "sg:postcode":"7004",
    "sg:province":"TAS",
    "sg:tags":[
        "accommodation"
    ],
    "wof:name":"Shipwrights Arms Hotel",
    "wof:placetype":"venue"
},
  "geometry": {"coordinates":[147.33502197300001,-42.890914917],"type":"Point"}
}