{
  "type": "Feature",
  "properties": {
    "addr:full":"1 Castle Crt Tugun QLD 4224",
    "addr:housenumber":"1",
    "addr:postcode":"4224",
    "addr:street":"Castle Crt",
    "iso:country":"AU",
    "sg:address":"1 Castle Crt",
    "sg:city":"Tugun",
    "sg:classifiers":[
        {
            "category":"Building & Trades",
            "subcategory":"Construction",
            "type":"Services"
        }
    ],
    "sg:phone":"+61 418 453 577",
    "sg:postcode":"4224",
    "sg:province":"QLD",
    "sg:tags":[
        "plasterboard",
        "plasterer",
        "fixer"
    ],
    "wof:name":"Mahoney Peter G",
    "wof:placetype":"venue"
},
  "geometry": {"coordinates":[153.49345398,-28.1509056091],"type":"Point"}
}