{
  "type": "Feature",
  "properties": {
    "iso:country":"AU",
    "sg:address":"21 Nyah Rd",
    "sg:city":"Swan Hill",
    "sg:classifiers":[
        {
            "category":"Autos & Motor Vehicles",
            "subcategory":"Boat Sales",
            "type":"Retail Goods"
        }
    ],
    "sg:phone":"+61 3 5032 4770",
    "sg:postcode":"3585",
    "sg:province":"VIC",
    "sg:tags":[
        "yacht"
    ],
    "wof:name":"Hunter Marine Boat Builders and Motorcycles",
    "wof:placetype":"venue"
},
  "geometry": {"coordinates":[143.553909,-35.328243],"type":"Point"}
}