{
  "type": "Feature",
  "properties": {
    "iso:country":"AU",
    "sg:address":"2 Station St",
    "sg:city":"Dundas",
    "sg:classifiers":[
        {
            "category":"Shopping",
            "subcategory":"Stationery & Office Supplies",
            "type":"Retail Goods"
        }
    ],
    "sg:phone":"+61 2 9638 1869",
    "sg:postcode":"2117",
    "sg:province":"NSW",
    "wof:name":"Officesmart",
    "wof:placetype":"venue"
},
  "geometry": {"coordinates":[151.03361511200001,-33.8050804138],"type":"Point"}
}