{
  "type": "Feature",
  "properties": {
    "addr:full":"316 Bay St Port Melbourne VIC 3207",
    "addr:housenumber":"316",
    "addr:postcode":"3207",
    "addr:street":"Bay St",
    "iso:country":"AU",
    "sg:address":"316 Bay St",
    "sg:city":"Port Melbourne",
    "sg:classifiers":[
        {
            "category":"Travel",
            "subcategory":"Hotels & Motels",
            "type":"Entertainment"
        }
    ],
    "sg:phone":"+61 3 9645 4070",
    "sg:postcode":"3207",
    "sg:province":"VIC",
    "sg:tags":[
        "pub"
    ],
    "wof:name":"Chequers Inn Hotel",
    "wof:placetype":"venue"
},
  "geometry": {"coordinates":[144.94407699999999,-37.83691],"type":"Point"}
}