{
  "type": "Feature",
  "properties": {
    "addr:full":"160 High St Preston VIC 3072",
    "addr:housenumber":"160",
    "addr:postcode":"3072",
    "addr:street":"High St",
    "iso:country":"AU",
    "sg:address":"160 High St",
    "sg:city":"Preston",
    "sg:classifiers":[
        {
            "category":"Retail",
            "subcategory":"Auto Repair",
            "type":"Services"
        }
    ],
    "sg:phone":"+61 3 9484 6260",
    "sg:postcode":"3072",
    "sg:province":"VIC",
    "sg:tags":[
        "camper-trailers",
        "caravan",
        "servicing"
    ],
    "wof:name":"ABS Auto Brake Service",
    "wof:placetype":"venue"
},
  "geometry": {"coordinates":[145.002853394,-37.7462539673],"type":"Point"}
}