{
  "type": "Feature",
  "properties": {
    "addr:full":"434 Boronia Rd Wantirna South VIC 3152",
    "addr:housenumber":"434",
    "addr:postcode":"3152",
    "addr:street":"Boronia Rd",
    "iso:country":"AU",
    "sg:address":"434 Boronia Rd",
    "sg:city":"Wantirna South",
    "sg:classifiers":[
        {
            "category":"Building & Trades",
            "subcategory":"Construction",
            "type":"Services"
        }
    ],
    "sg:phone":"+61 3 9801 2923",
    "sg:postcode":"3152",
    "sg:province":"VIC",
    "sg:tags":[
        "polishing",
        "sanding",
        "floor"
    ],
    "wof:name":"Hillcrest Floor Surfacing",
    "wof:placetype":"venue"
},
  "geometry": {"coordinates":[145.250732422,-37.85546875],"type":"Point"}
}