{
  "type": "Feature",
  "properties": {
    "addr:full":"Lilydale Industrial Park 121 Beresford Rd Lilydale VIC 3140",
    "addr:housenumber":"121",
    "addr:postcode":"3140",
    "addr:street":"Beresford Rd",
    "iso:country":"AU",
    "sg:address":"Lilydale Industrial Park 121 Beresford Rd",
    "sg:city":"Lilydale",
    "sg:classifiers":[
        {
            "category":"Building & Trades",
            "subcategory":"Plumbing",
            "type":"Services"
        }
    ],
    "sg:phone":"+61 3 9739 5358",
    "sg:postcode":"3140",
    "sg:province":"VIC",
    "sg:tags":[
        "pump",
        "repairer"
    ],
    "wof:name":"Lilydale Electric Motors",
    "wof:placetype":"venue"
},
  "geometry": {"coordinates":[145.349517822,-37.7510604858],"type":"Point"}
}