{
  "type": "Feature",
  "properties": {
    "iso:country":"AU",
    "sg:address":"Austral Publich School, Edmonson Road",
    "sg:city":"Austral",
    "sg:classifiers":[
        {
            "category":"Arts & Performance",
            "subcategory":"Dance",
            "type":"Entertainment"
        }
    ],
    "sg:phone":"+61 438 224 019",
    "sg:postcode":"2171",
    "sg:province":"NSW",
    "sg:tags":[
        "theatrical",
        "ballet",
        "tuition"
    ],
    "wof:name":"Cindys Dance Studio",
    "wof:placetype":"venue"
},
  "geometry": {"coordinates":[150.846237183,-33.9284286499],"type":"Point"}
}