{
  "type": "Feature",
  "properties": {
    "addr:full":"321 Albany Creek Rd Bridgeman Downs QLD 4035",
    "addr:housenumber":"321",
    "addr:postcode":"4035",
    "addr:street":"Albany Creek Rd",
    "iso:country":"AU",
    "sg:address":"321 Albany Creek Rd",
    "sg:city":"Bridgeman Downs",
    "sg:classifiers":[
        {
            "category":"Government",
            "subcategory":"Post Office",
            "type":"Public Place"
        }
    ],
    "sg:phone":"+61 7 3863 3299",
    "sg:postcode":"4035",
    "sg:province":"QLD",
    "sg:tags":[
        "yoga"
    ],
    "wof:name":"Hot-Oz-Yoga",
    "wof:placetype":"venue"
},
  "geometry": {"coordinates":[152.996613,-27.355963],"type":"Point"}
}