{
  "type": "Feature",
  "properties": {
    "addr:full":"64 Nairana Drv Marayong NSW 2148",
    "addr:housenumber":"64",
    "addr:postcode":"2148",
    "addr:street":"Nairana Drv",
    "iso:country":"AU",
    "sg:address":"64 Nairana Drv",
    "sg:city":"Marayong",
    "sg:classifiers":[
        {
            "category":"Professional",
            "type":"Services"
        }
    ],
    "sg:phone":"+61 2 9837 1331",
    "sg:postcode":"2148",
    "sg:province":"NSW",
    "sg:tags":[
        "transport"
    ],
    "wof:name":"Watson D G Transport Pty Ltd",
    "wof:placetype":"venue"
},
  "geometry": {"coordinates":[150.89353942899999,-33.743812561],"type":"Point"}
}