{
  "type": "Feature",
  "properties": {
    "addr:full":"56 Prindiville Drv Wangara WA 6065",
    "addr:housenumber":"56",
    "addr:postcode":"6065",
    "addr:street":"Prindiville Drv",
    "iso:country":"AU",
    "sg:address":"56 Prindiville Drv",
    "sg:city":"Wangara",
    "sg:classifiers":[
        {
            "category":"Food & Beverages",
            "subcategory":"Groceries & Convenience Stores",
            "type":"Retail Goods"
        }
    ],
    "sg:phone":"+61 8 9409 4822",
    "sg:postcode":"6065",
    "sg:province":"WA",
    "wof:name":"Weigh &#039;n Pay Pty Ltd",
    "wof:placetype":"venue"
},
  "geometry": {"coordinates":[115.82611846899999,-31.791519165],"type":"Point"}
}