{
  "type": "Feature",
  "properties": {
    "addr:full":"3 Yallambee Rd Berowra NSW 2081",
    "addr:housenumber":"3",
    "addr:postcode":"2081",
    "addr:street":"Yallambee Rd",
    "iso:country":"AU",
    "sg:address":"3 Yallambee Rd",
    "sg:city":"Berowra",
    "sg:classifiers":[
        {
            "category":"Building & Trades",
            "subcategory":"Construction",
            "type":"Services"
        }
    ],
    "sg:phone":"+61 2 9456 7567",
    "sg:postcode":"2081",
    "sg:province":"NSW",
    "sg:tags":[
        "concrete",
        "contractor"
    ],
    "wof:name":"Aston & Bourke Pty Ltd",
    "wof:placetype":"venue"
},
  "geometry": {"coordinates":[151.14651489299999,-33.6280021667],"type":"Point"}
}