{
  "type": "Feature",
  "properties": {
    "addr:full":"Shop 6 114 Hoare St Manunda QLD 4870",
    "addr:housenumber":"shop 6",
    "addr:postcode":"114;4870",
    "addr:street":"Hoare St",
    "iso:country":"AU",
    "sg:address":"Shop 6 114 Hoare St",
    "sg:city":"Manunda",
    "sg:classifiers":[
        {
            "category":"Health Services",
            "subcategory":"Doctor",
            "type":"Services"
        }
    ],
    "sg:phone":"+61 7 4053 3399",
    "sg:postcode":"4870",
    "sg:province":"QLD",
    "sg:tags":[
        "medical",
        "practitioner"
    ],
    "wof:name":"Dewhurst, Dr Tim",
    "wof:placetype":"venue"
},
  "geometry": {"coordinates":[145.745605469,-16.923116684],"type":"Point"}
}