{
  "type": "Feature",
  "properties": {
    "iso:country":"AU",
    "sg:address":"PO Box 156",
    "sg:city":"Daw Park",
    "sg:classifiers":[
        {
            "category":"Professional",
            "type":"Services"
        }
    ],
    "sg:phone":"+61 8 8276 1868",
    "sg:postcode":"5041",
    "sg:province":"SA",
    "sg:tags":[
        "control",
        "equipment",
        "traffic"
    ],
    "wof:name":"Futura",
    "wof:placetype":"venue"
},
  "geometry": {"coordinates":[138.587463,-34.979698],"type":"Point"}
}