{
  "type": "Feature",
  "properties": {
    "addr:full":"181 March St Orange NSW 2800",
    "addr:housenumber":"181",
    "addr:postcode":"2800",
    "addr:street":"March St",
    "iso:country":"AU",
    "sg:address":"181 March St",
    "sg:city":"Orange",
    "sg:classifiers":[
        {
            "category":"Professional",
            "subcategory":"Engineering",
            "type":"Services"
        }
    ],
    "sg:phone":"+61 2 6362 6675",
    "sg:postcode":"2800",
    "sg:province":"NSW",
    "sg:tags":[
        "engineer"
    ],
    "wof:name":"Central Western Bearing & Engineering Suppliers",
    "wof:placetype":"venue"
},
  "geometry": {"coordinates":[149.10856628400001,-33.2804718018],"type":"Point"}
}