{
  "type": "Feature",
  "properties": {
    "iso:country":"AU",
    "sg:address":"4b Campbell Crs",
    "sg:city":"Terrigal",
    "sg:classifiers":[
        {
            "category":"Personal",
            "subcategory":"Beauty Salon",
            "type":"Services"
        }
    ],
    "sg:phone":"+61 2 4385 3445",
    "sg:postcode":"2260",
    "sg:province":"NSW",
    "sg:tags":[
        "hairdresser"
    ],
    "wof:name":"Dowds Judy Hair Studio",
    "wof:placetype":"venue"
},
  "geometry": {"coordinates":[151.445709,-33.4478],"type":"Point"}
}