{
  "type": "Feature",
  "properties": {
    "addr:full":"16 Colonial Drv Lawnton QLD 4501",
    "addr:housenumber":"16",
    "addr:postcode":"4501",
    "addr:street":"Colonial Drv",
    "iso:country":"AU",
    "sg:address":"16 Colonial Drv",
    "sg:city":"Lawnton",
    "sg:classifiers":[
        {
            "category":"Retail",
            "subcategory":"Auto Rental",
            "type":"Services"
        }
    ],
    "sg:phone":"+61 419 711 668",
    "sg:postcode":"4501",
    "sg:province":"QLD",
    "sg:tags":[
        "chauffeur",
        "car",
        "hire",
        "driven",
        "limousine"
    ],
    "wof:name":"Home James Limousine Service",
    "wof:placetype":"venue"
},
  "geometry": {"coordinates":[152.960845947,-27.2835025787],"type":"Point"}
}