{
  "type": "Feature",
  "properties": {
    "iso:country":"AU",
    "sg:address":"73 Lock Rd",
    "sg:city":"Rhyll",
    "sg:classifiers":[
        {
            "category":"Autos & Motor Vehicles",
            "subcategory":"Auto Supplies",
            "type":"Retail Goods"
        }
    ],
    "sg:phone":"+61 3 5956 9195",
    "sg:postcode":"3923",
    "sg:province":"VIC",
    "sg:tags":[
        "part",
        "cycles",
        "accessory"
    ],
    "wof:name":"Phillip Island Motorcycle Repairs",
    "wof:placetype":"venue"
},
  "geometry": {"coordinates":[145.30055236800001,-38.4634742737],"type":"Point"}
}