{
  "type": "Feature",
  "properties": {
    "addr:full":"Unit 1/ 27 Ace Crs Tuggerah NSW 2259",
    "addr:housenumber":"27",
    "addr:postcode":"2259",
    "addr:street":"Ace Crs",
    "iso:country":"AU",
    "sg:address":"Unit 1/ 27 Ace Crs",
    "sg:city":"Tuggerah",
    "sg:classifiers":[
        {
            "category":"Government",
            "subcategory":"Fire Station",
            "type":"Public Place"
        }
    ],
    "sg:phone":"+61 2 4352 2808",
    "sg:postcode":"2259",
    "sg:province":"NSW",
    "sg:tags":[
        "equipment",
        "protection",
        "consultant"
    ],
    "wof:name":"Fire & Security",
    "wof:placetype":"venue"
},
  "geometry": {"coordinates":[151.420410156,-33.3050003052],"type":"Point"}
}