{
  "type": "Feature",
  "properties": {
    "addr:full":"19 Tyack St Toowoomba City QLD 4350",
    "addr:housenumber":"19",
    "addr:postcode":"4350",
    "addr:street":"Tyack St",
    "iso:country":"AU",
    "sg:address":"19 Tyack St",
    "sg:city":"Toowoomba City",
    "sg:classifiers":[
        {
            "category":"Shopping",
            "subcategory":"Bridal",
            "type":"Retail Goods"
        }
    ],
    "sg:phone":"+61 7 4633 1374",
    "sg:postcode":"4350",
    "sg:province":"QLD",
    "sg:tags":[
        "hire",
        "wear"
    ],
    "wof:name":"Linda Trigg - Bridal Designer",
    "wof:placetype":"venue"
},
  "geometry": {"coordinates":[151.93057300000001,-27.547915],"type":"Point"}
}