{
  "type": "Feature",
  "properties": {
    "iso:country":"AU",
    "sg:address":"9 Trout St",
    "sg:city":"Ashgrove",
    "sg:classifiers":[
        {
            "category":"Health Services",
            "subcategory":"Dentist",
            "type":"Services"
        }
    ],
    "sg:phone":"+61 7 3366 0220",
    "sg:postcode":"4060",
    "sg:province":"QLD",
    "wof:name":"Allstar Orthodontics",
    "wof:placetype":"venue"
},
  "geometry": {"coordinates":[152.99092102,-27.4457492828],"type":"Point"}
}