{
  "type": "Feature",
  "properties": {
    "addr:full":"23 Errand St Kelvin Grove QLD 4059",
    "addr:housenumber":"23",
    "addr:postcode":"4059",
    "addr:street":"Errand St",
    "iso:country":"AU",
    "sg:address":"23 Errand St",
    "sg:city":"Kelvin Grove",
    "sg:classifiers":[
        {
            "category":"Banks & Credit Unions",
            "subcategory":"Bank",
            "type":"Services"
        }
    ],
    "sg:phone":"+61 7 3356 8132",
    "sg:postcode":"4059",
    "sg:province":"QLD",
    "sg:tags":[
        "broker",
        "mortgage"
    ],
    "wof:name":"National Finance Corporation",
    "wof:placetype":"venue"
},
  "geometry": {"coordinates":[153.005615234,-27.4453392029],"type":"Point"}
}