{
  "type": "Feature",
  "properties": {
    "addr:full":"39 Correys Ave Concord NSW 2137",
    "addr:housenumber":"39",
    "addr:postcode":"2137",
    "addr:street":"Correys Ave",
    "iso:country":"AU",
    "sg:address":"39 Correys Ave",
    "sg:city":"Concord",
    "sg:classifiers":[
        {
            "category":"Shopping",
            "subcategory":"Stationery & Office Supplies",
            "type":"Retail Goods"
        }
    ],
    "sg:phone":"+61 2 9743 3459",
    "sg:postcode":"2137",
    "sg:province":"NSW",
    "sg:tags":[
        "packaging",
        "equipment",
        "sealing",
        "filling"
    ],
    "wof:name":"Arpon Pty Ltd",
    "wof:placetype":"venue"
},
  "geometry": {"coordinates":[151.09957885700001,-33.8537216187],"type":"Point"}
}