{
  "type": "Feature",
  "properties": {
    "addr:full":"PO Box 136 Torrensville Plaza SA 5031",
    "addr:postcode":"5031",
    "iso:country":"AU",
    "sg:address":"PO Box 136",
    "sg:city":"Torrensville Plaza",
    "sg:classifiers":[
        {
            "category":"Social Services",
            "subcategory":"Job Training",
            "type":"Services"
        }
    ],
    "sg:phone":"+61 408 599 993",
    "sg:postcode":"5031",
    "sg:province":"SA",
    "sg:tags":[
        "interpreter"
    ],
    "wof:name":"A & Z Global Services",
    "wof:placetype":"venue"
},
  "geometry": {"coordinates":[138.55938720699999,-34.9241485596],"type":"Point"}
}