{
  "type": "Feature",
  "properties": {
    "iso:country":"AU",
    "sg:address":"50 Cribb St",
    "sg:city":"Milton",
    "sg:classifiers":[
        {
            "category":"Arts & Performance",
            "subcategory":"Music",
            "type":"Entertainment"
        }
    ],
    "sg:phone":"+61 7 3367 1045",
    "sg:postcode":"4064",
    "sg:province":"QLD",
    "sg:tags":[
        "mobile",
        "jockey",
        "disc"
    ],
    "wof:name":"Nightlife Music Video",
    "wof:placetype":"venue"
},
  "geometry": {"coordinates":[153.00743102999999,-27.4685993195],"type":"Point"}
}