{
  "type": "Feature",
  "properties": {
    "iso:country":"AU",
    "sg:address":"22 First Ave",
    "sg:city":"Maroochydore",
    "sg:classifiers":[
        {
            "category":"Recreation",
            "subcategory":"Fishing",
            "type":"Entertainment"
        }
    ],
    "sg:phone":"+61 7 5443 2714",
    "sg:postcode":"4558",
    "sg:province":"QLD",
    "sg:tags":[
        "bait"
    ],
    "wof:name":"Maroochydore Fishing World",
    "wof:placetype":"venue"
},
  "geometry": {"coordinates":[153.09312439000001,-26.6555900574],"type":"Point"}
}