{
  "type": "Feature",
  "properties": {
    "iso:country":"AU",
    "sg:address":"18 Bergonia St",
    "sg:city":"Mona Vale",
    "sg:classifiers":[
        {
            "category":"Building & Trades",
            "subcategory":"Landscaping Services",
            "type":"Services"
        }
    ],
    "sg:phone":"+61 402 066 655",
    "sg:postcode":"2103",
    "sg:province":"NSW",
    "sg:tags":[
        "stump",
        "tree",
        "felling",
        "removal"
    ],
    "wof:name":"Acacia Tree Service",
    "wof:placetype":"venue"
},
  "geometry": {"coordinates":[151.294723511,-33.6753005981],"type":"Point"}
}