{
  "type": "Feature",
  "properties": {
    "addr:full":"195 Parramatta Rd Annandale NSW 2038",
    "addr:housenumber":"195",
    "addr:postcode":"2038",
    "addr:street":"Parramatta Rd",
    "iso:country":"AU",
    "sg:address":"195 Parramatta Rd",
    "sg:city":"Annandale",
    "sg:classifiers":[
        {
            "category":"Real Estate",
            "subcategory":"Real Estate Services",
            "type":"Services"
        }
    ],
    "sg:phone":"+61 2 9569 4888",
    "sg:postcode":"2038",
    "sg:province":"NSW",
    "sg:tags":[
        "valuer"
    ],
    "wof:name":"Callagher Estate Agents",
    "wof:placetype":"venue"
},
  "geometry": {"coordinates":[151.16441345199999,-33.8880615234],"type":"Point"}
}