{
  "type": "Feature",
  "properties": {
    "addr:full":"Horne St Sunbury VIC 3429",
    "addr:postcode":"3429",
    "addr:street":"Horne St",
    "iso:country":"AU",
    "sg:address":"Horne St",
    "sg:city":"Sunbury",
    "sg:classifiers":[
        {
            "category":"Autos & Motor Vehicles",
            "subcategory":"Fuel & Gas Station",
            "type":"Retail Goods"
        }
    ],
    "sg:phone":"+61 3 9740 7830",
    "sg:postcode":"3429",
    "sg:province":"VIC",
    "wof:name":"Plus Petrol",
    "wof:placetype":"venue"
},
  "geometry": {"coordinates":[144.725875855,-37.5795974731],"type":"Point"}
}