{
  "type": "Feature",
  "properties": {
    "iso:country":"AU",
    "sg:address":"3/15 Fullarton Rd",
    "sg:city":"Niddrie",
    "sg:classifiers":[
        {
            "category":"Personal",
            "subcategory":"Beauty Salon",
            "type":"Services"
        }
    ],
    "sg:phone":"+61 412 417 065",
    "sg:postcode":"3042",
    "sg:province":"VIC",
    "wof:name":"Jo's Skin & Body Boutique",
    "wof:placetype":"venue"
},
  "geometry": {"coordinates":[144.88018798799999,-37.7318992615],"type":"Point"}
}