{
  "type": "Feature",
  "properties": {
    "addr:full":"46 Kennedy St Castlemaine VIC 3450",
    "addr:housenumber":"46",
    "addr:postcode":"3450",
    "addr:street":"Kennedy St",
    "iso:country":"AU",
    "sg:address":"46 Kennedy St",
    "sg:city":"Castlemaine",
    "sg:classifiers":[
        {
            "category":"Real Estate",
            "subcategory":"Real Estate Agent",
            "type":"Services"
        }
    ],
    "sg:phone":"+61 3 5472 2154",
    "sg:postcode":"3450",
    "sg:province":"VIC",
    "sg:tags":[
        "handyman's",
        "equipment",
        "hire",
        "builders",
        "contractor"
    ],
    "wof:name":"Castlemaine Hire Service",
    "wof:placetype":"venue"
},
  "geometry": {"coordinates":[144.21502685600001,-37.0616035461],"type":"Point"}
}