{
  "type": "Feature",
  "properties": {
    "iso:country":"AU",
    "sg:address":"Level 5, 395 Collins St",
    "sg:city":"Melbourne",
    "sg:classifiers":[
        {
            "category":"Organizations",
            "subcategory":"Non-profit Organization",
            "type":"Services"
        }
    ],
    "sg:phone":"+61 3 8610 9100",
    "sg:postcode":"3000",
    "sg:province":"VIC",
    "sg:tags":[
        "environmental",
        "organisation",
        "conservation"
    ],
    "wof:name":"Bush Heritage Australia",
    "wof:placetype":"venue"
},
  "geometry": {"coordinates":[144.961425781,-37.8171043396],"type":"Point"}
}