{
  "type": "Feature",
  "properties": {
    "iso:country":"AU",
    "sg:address":"2 Evelyn Crt",
    "sg:city":"Dingley",
    "sg:classifiers":[
        {
            "category":"Organizations",
            "subcategory":"Community Association",
            "type":"Services"
        }
    ],
    "sg:phone":"+61 417 232 686",
    "sg:postcode":"3172",
    "sg:province":"VIC",
    "sg:tags":[
        "shiatsu",
        "therapy"
    ],
    "wof:name":"Wellington W F",
    "wof:placetype":"venue"
},
  "geometry": {"coordinates":[145.12843322800001,-37.9678192139],"type":"Point"}
}