{
  "type": "Feature",
  "properties": {
    "addr:full":"7 Ashley La Westmead NSW 2145",
    "addr:housenumber":"7",
    "addr:postcode":"2145",
    "addr:street":"Ashley La",
    "iso:country":"AU",
    "sg:address":"7 Ashley La",
    "sg:city":"Westmead",
    "sg:classifiers":[
        {
            "category":"Organizations",
            "subcategory":"Professional Association",
            "type":"Services"
        }
    ],
    "sg:phone":"+61 2 8833 3000",
    "sg:postcode":"2145",
    "sg:province":"NSW",
    "sg:tags":[
        "organisation",
        "business"
    ],
    "wof:name":"Skin & Cancer Foundation Of NSW",
    "wof:placetype":"venue"
},
  "geometry": {"coordinates":[150.98919677699999,-33.8064880371],"type":"Point"}
}