{
  "type": "Feature",
  "properties": {
    "iso:country":"AU",
    "sg:address":"253 High St",
    "sg:city":"Shepparton",
    "sg:classifiers":[
        {
            "category":"Banks & Credit Unions",
            "subcategory":"Investment Brokerage",
            "type":"Services"
        }
    ],
    "sg:phone":"+61 3 5831 3522",
    "sg:postcode":"3630",
    "sg:province":"VIC",
    "sg:tags":[
        "equipment",
        "spray",
        "painting",
        "supply"
    ],
    "wof:name":"B Bs Paint Centre Pty Ltd",
    "wof:placetype":"venue"
},
  "geometry": {"coordinates":[145.406646728,-36.3819084167],"type":"Point"}
}