{
  "type": "Feature",
  "properties": {
    "addr:full":"12 Heather St Gympie QLD 4570",
    "addr:housenumber":"12",
    "addr:postcode":"4570",
    "addr:street":"Heather St",
    "iso:country":"AU",
    "sg:address":"12 Heather St",
    "sg:city":"Gympie",
    "sg:classifiers":[
        {
            "category":"Professional",
            "subcategory":"Business Services",
            "type":"Services"
        }
    ],
    "sg:phone":"+61 7 5482 5087",
    "sg:postcode":"4570",
    "sg:province":"QLD",
    "sg:tags":[
        "drafting"
    ],
    "wof:name":"Cooloola Drafting",
    "wof:placetype":"venue"
},
  "geometry": {"coordinates":[152.648529053,-26.2095775604],"type":"Point"}
}