{
  "type": "Feature",
  "properties": {
    "addr:full":"Lot 6 Industrial Ave Mt Isa QLD 4825",
    "addr:postcode":"4825",
    "addr:street":"Industrial Ave",
    "iso:country":"AU",
    "sg:address":"Lot 6 Industrial Ave",
    "sg:city":"Mt Isa",
    "sg:classifiers":[
        {
            "category":"Manufacturing",
            "subcategory":"Metals",
            "type":"Manufacturing & Wholesale Goods"
        }
    ],
    "sg:phone":"+61 7 4743 8484",
    "sg:postcode":"4825",
    "sg:province":"QLD",
    "sg:tags":[
        "metallurgist"
    ],
    "wof:name":"Amdel Laboratories Ltd",
    "wof:placetype":"venue"
},
  "geometry": {"coordinates":[139.50254799999999,-20.699867],"type":"Point"}
}