{
  "type": "Feature",
  "properties": {
    "addr:full":"4 Warren Crt Tanunda SA 5352",
    "addr:housenumber":"4",
    "addr:postcode":"5352",
    "addr:street":"Warren Crt",
    "iso:country":"AU",
    "sg:address":"4 Warren Crt",
    "sg:city":"Tanunda",
    "sg:classifiers":[
        {
            "category":"Personal",
            "type":"Services"
        }
    ],
    "sg:phone":"+61 409 869 517",
    "sg:postcode":"5352",
    "sg:province":"SA",
    "sg:tags":[
        "dressmaker"
    ],
    "wof:name":"Cottles Park Couture",
    "wof:placetype":"venue"
},
  "geometry": {"coordinates":[138.96571350100001,-34.5239143372],"type":"Point"}
}