{
  "type": "Feature",
  "properties": {
    "iso:country":"AU",
    "sg:address":"Loft 1, 50- 54 Ann St",
    "sg:city":"Surry Hills",
    "sg:classifiers":[
        {
            "category":"Real Estate",
            "subcategory":"Architect",
            "type":"Services"
        }
    ],
    "sg:phone":"+61 2 9211 0626",
    "sg:postcode":"2010",
    "sg:province":"NSW",
    "wof:name":"Dale Jones-Evans Pty Ltd",
    "wof:placetype":"venue"
},
  "geometry": {"coordinates":[151.21266174300001,-33.8821372986],"type":"Point"}
}