{
  "type": "Feature",
  "properties": {
    "addr:full":"150 Clarendon St South Melbourne VIC 3205",
    "addr:housenumber":"150",
    "addr:postcode":"3205",
    "addr:street":"Clarendon St",
    "iso:country":"AU",
    "sg:address":"150 Clarendon St",
    "sg:city":"South Melbourne",
    "sg:classifiers":[
        {
            "category":"Retail",
            "subcategory":"Car Wash",
            "type":"Services"
        }
    ],
    "sg:phone":"+61 3 9686 8222",
    "sg:postcode":"3205",
    "sg:province":"VIC",
    "sg:tags":[
        "truck",
        "cleaning"
    ],
    "wof:name":"Blue Planet Hand Car Wash & Detailing Salon",
    "wof:placetype":"venue"
},
  "geometry": {"coordinates":[144.96270799999999,-37.835869],"type":"Point"}
}