{
  "type": "Feature",
  "properties": {
    "iso:country":"AU",
    "sg:address":"14 Como St",
    "sg:city":"Alphington",
    "sg:classifiers":[
        {
            "category":"Health Services",
            "subcategory":"Nursing And Care Facility",
            "type":"Services"
        }
    ],
    "sg:phone":"+61 3 9497 2027",
    "sg:postcode":"3078",
    "sg:province":"VIC",
    "sg:tags":[
        "home"
    ],
    "wof:name":"Latrobe Private Nursing Home",
    "wof:placetype":"venue"
},
  "geometry": {"coordinates":[145.033493042,-37.782119751],"type":"Point"}
}