{
  "type": "Feature",
  "properties": {
    "addr:full":"1 Cooke St Bunbury WA 6230",
    "addr:housenumber":"1",
    "addr:postcode":"6230",
    "addr:street":"Cooke St",
    "iso:country":"AU",
    "sg:address":"1 Cooke St",
    "sg:city":"Bunbury",
    "sg:classifiers":[
        {
            "category":"Home & Garden",
            "subcategory":"Kitchen Supply",
            "type":"Retail Goods"
        }
    ],
    "sg:phone":"+61 417 932 208",
    "sg:postcode":"6230",
    "sg:province":"WA",
    "sg:tags":[
        "sharpening"
    ],
    "wof:name":"Tonkin N R Surgical Instrument Services",
    "wof:placetype":"venue"
},
  "geometry": {"coordinates":[115.62460299999999,-33.353069],"type":"Point"}
}