{
  "type": "Feature",
  "properties": {
    "iso:country":"AU",
    "sg:address":"PO Box 1456",
    "sg:city":"Albany DC",
    "sg:classifiers":[
        {
            "category":"Building & Trades",
            "subcategory":"Landscaping Services",
            "type":"Services"
        }
    ],
    "sg:phone":"+61 8 9841 2279",
    "sg:postcode":"6331",
    "sg:province":"WA",
    "sg:tags":[
        "firebreak",
        "clearing",
        "land",
        "contractor"
    ],
    "wof:name":"Bill Gibbs Excavations & Earthmoving",
    "wof:placetype":"venue"
},
  "geometry": {"coordinates":[117.859283447,-35.0605697632],"type":"Point"}
}