{
  "type": "Feature",
  "properties": {
    "addr:full":"11 Warrenwood Ave Hoppers Crossing VIC 3029",
    "addr:housenumber":"11",
    "addr:postcode":"3029",
    "addr:street":"Warrenwood Ave",
    "iso:country":"AU",
    "sg:address":"11 Warrenwood Ave",
    "sg:city":"Hoppers Crossing",
    "sg:classifiers":[
        {
            "category":"Shopping",
            "subcategory":"Crafts & Fabrics",
            "type":"Retail Goods"
        }
    ],
    "sg:phone":"+61 3 9749 1363",
    "sg:postcode":"3029",
    "sg:province":"VIC",
    "sg:tags":[
        "synthetic",
        "canvas",
        "product"
    ],
    "wof:name":"Hoppers Crossing Upholstery & Canvas",
    "wof:placetype":"venue"
},
  "geometry": {"coordinates":[144.69554099999999,-37.879757],"type":"Point"}
}