{
  "type": "Feature",
  "properties": {
    "addr:full":"153 Ramsay St Haberfield NSW 2045",
    "addr:housenumber":"153",
    "addr:postcode":"2045",
    "addr:street":"Ramsay St",
    "iso:country":"AU",
    "sg:address":"153 Ramsay St",
    "sg:city":"Haberfield",
    "sg:classifiers":[
        {
            "category":"Food & Beverages",
            "subcategory":"Bakery",
            "type":"Retail Goods"
        }
    ],
    "sg:phone":"+61 2 9797 7715",
    "sg:postcode":"2045",
    "sg:province":"NSW",
    "sg:tags":[
        "baker"
    ],
    "wof:name":"Haberfield Bakery Pty Ltd",
    "wof:placetype":"venue"
},
  "geometry": {"coordinates":[151.13874799999999,-33.880123],"type":"Point"}
}