{
  "type": "Feature",
  "properties": {
    "iso:country":"AU",
    "sg:address":"683 83-93 Dalmeny Ave Rosebery, NSW",
    "sg:classifiers":[
        {
            "category":"Professional",
            "subcategory":"Computer Services",
            "type":"Services"
        }
    ],
    "sg:postcode":"2018",
    "sg:tags":[
        "hosted-software-timesheet-management"
    ],
    "sg:website":"http://www.beyondng.com",
    "wof:name":"Beyond NG",
    "wof:placetype":"venue"
},
  "geometry": {"coordinates":[151.210048,-33.916323],"type":"Point"}
}