{
  "type": "Feature",
  "properties": {
    "iso:country":"AU",
    "sg:address":"13 Eddy St",
    "sg:city":"Kiama",
    "sg:classifiers":[
        {
            "category":"Health Services",
            "subcategory":"Doctor",
            "type":"Services"
        }
    ],
    "sg:phone":"+61 2 4232 2011",
    "sg:postcode":"2533",
    "sg:province":"NSW",
    "sg:tags":[
        "medical",
        "practitioner"
    ],
    "wof:name":"South Coast Dermatology",
    "wof:placetype":"venue"
},
  "geometry": {"coordinates":[150.85153198200001,-34.6772422791],"type":"Point"}
}