{
  "type": "Feature",
  "properties": {
    "iso:country":"AU",
    "sg:address":"484a The Entrance Rd",
    "sg:city":"Erina Heights",
    "sg:classifiers":[
        {
            "category":"Personal",
            "subcategory":"Beauty Salon",
            "type":"Services"
        }
    ],
    "sg:phone":"+61 2 4365 5999",
    "sg:postcode":"2260",
    "sg:province":"NSW",
    "wof:name":"Ellysian Beauty Skin Therapy Centre",
    "wof:placetype":"venue"
},
  "geometry": {"coordinates":[151.41214,-33.426113],"type":"Point"}
}