{
  "type": "Feature",
  "properties": {
    "iso:country":"AU",
    "sg:address":"6 Fennell St",
    "sg:city":"Parramatta",
    "sg:classifiers":[
        {
            "category":"Banks & Credit Unions",
            "subcategory":"Financial Services",
            "type":"Services"
        }
    ],
    "sg:phone":"+61 2 9890 8098",
    "sg:postcode":"2150",
    "sg:province":"NSW",
    "sg:tags":[
        "financier"
    ],
    "wof:name":"Cawarra Factors Pty Ltd",
    "wof:placetype":"venue"
},
  "geometry": {"coordinates":[151.00793457,-33.8057632446],"type":"Point"}
}