{
  "type": "Feature",
  "properties": {
    "addr:full":"29a Redcliffe Pde Redcliffe QLD 4020",
    "addr:housenumber":"29a",
    "addr:postcode":"4020",
    "addr:street":"Redcliffe Pde",
    "iso:country":"AU",
    "sg:address":"29a Redcliffe Pde",
    "sg:city":"Redcliffe",
    "sg:classifiers":[
        {
            "category":"Real Estate",
            "subcategory":"Real Estate Agent",
            "type":"Services"
        }
    ],
    "sg:phone":"+61 7 3283 1333",
    "sg:postcode":"4020",
    "sg:province":"QLD",
    "wof:name":"Century 21 Warlters & Partners",
    "wof:placetype":"venue"
},
  "geometry": {"coordinates":[153.11535599999999,-27.228456],"type":"Point"}
}