{
  "type": "Feature",
  "properties": {
    "iso:country":"AU",
    "sg:address":"139 Unley Rd",
    "sg:city":"Unley",
    "sg:classifiers":[
        {
            "category":"Professional",
            "type":"Services"
        }
    ],
    "sg:phone":"+61 8 8373 4699",
    "sg:postcode":"5061",
    "sg:province":"SA",
    "sg:tags":[
        "industrial",
        "commercial",
        "catering"
    ],
    "wof:name":"Serves You Right!",
    "wof:placetype":"venue"
},
  "geometry": {"coordinates":[138.607498169,-34.9488868713],"type":"Point"}
}