{
  "type": "Feature",
  "properties": {
    "addr:full":"21- 23 Thomas Mitchell Drv Muswellbrook NSW 2333",
    "addr:housenumber":"23",
    "addr:postcode":"2333",
    "addr:street":"Thomas Mitchell Drv",
    "iso:country":"AU",
    "sg:address":"21- 23 Thomas Mitchell Drv",
    "sg:city":"Muswellbrook",
    "sg:classifiers":[
        {
            "category":"Manufacturing",
            "subcategory":"Tools & Machinery",
            "type":"Manufacturing & Wholesale Goods"
        }
    ],
    "sg:phone":"+61 2 6541 1149",
    "sg:postcode":"2333",
    "sg:province":"NSW",
    "sg:tags":[
        "earth",
        "excavating",
        "moving",
        "equipment"
    ],
    "wof:name":"LeTourneau Sales & Service Australia Pty Ltd",
    "wof:placetype":"venue"
},
  "geometry": {"coordinates":[150.87640380900001,-32.3067207336],"type":"Point"}
}