{
  "type": "Feature",
  "properties": {
    "addr:full":"Cnr of 79 Wambo & Durah Street Chinchilla QLD 4413",
    "addr:postcode":"4413",
    "addr:street":"Street",
    "iso:country":"AU",
    "sg:address":"Cnr of 79 Wambo & Durah Street",
    "sg:city":"Chinchilla",
    "sg:classifiers":[
        {
            "category":"Communications",
            "subcategory":"Film & Video Production",
            "type":"Services"
        }
    ],
    "sg:phone":"+61 7 4662 8438",
    "sg:postcode":"4413",
    "sg:province":"QLD",
    "sg:tags":[
        "dvd",
        "library"
    ],
    "wof:name":"Network Videos-Chinchilla",
    "wof:placetype":"venue"
},
  "geometry": {"coordinates":[150.63751220699999,-26.7329521179],"type":"Point"}
}