{
  "type": "Feature",
  "properties": {
    "addr:full":"179 Bungarribee Rd Blacktown NSW 2148",
    "addr:housenumber":"179",
    "addr:postcode":"2148",
    "addr:street":"Bungarribee Rd",
    "iso:country":"AU",
    "sg:address":"179 Bungarribee Rd",
    "sg:city":"Blacktown",
    "sg:classifiers":[
        {
            "category":"Fast Food",
            "type":"Food & Drink"
        }
    ],
    "sg:phone":"+61 2 9831 7354",
    "sg:postcode":"2148",
    "sg:province":"NSW",
    "sg:tags":[
        "away",
        "take"
    ],
    "wof:name":"Chan Mow Mini Mart",
    "wof:placetype":"venue"
},
  "geometry": {"coordinates":[150.89935302699999,-33.7761611938],"type":"Point"}
}