{
  "type": "Feature",
  "properties": {
    "iso:country":"AU",
    "sg:address":"167 Dowling St",
    "sg:city":"Dungog",
    "sg:classifiers":[
        {
            "category":"Travel",
            "subcategory":"Hotels & Motels",
            "type":"Entertainment"
        }
    ],
    "sg:phone":"+61 2 4992 1547",
    "sg:postcode":"2420",
    "sg:province":"NSW",
    "wof:name":"Dungog Tall Timbers Motel",
    "wof:placetype":"venue"
},
  "geometry": {"coordinates":[151.757645,-32.400898],"type":"Point"}
}