{
  "type": "Feature",
  "properties": {
    "iso:country":"AU",
    "sg:address":"380 St Kilda Rd",
    "sg:city":"Melbourne",
    "sg:classifiers":[
        {
            "category":"Organizations",
            "subcategory":"Professional Association",
            "type":"Services"
        }
    ],
    "sg:phone":"+61 3 9280 0111",
    "sg:postcode":"3004",
    "sg:province":"VIC",
    "sg:tags":[
        "organisation",
        "business"
    ],
    "wof:name":"Boiler & Pressure Vessel Manufacturers Association Of Australia Inc.",
    "wof:placetype":"venue"
},
  "geometry": {"coordinates":[144.97140502900001,-37.8321914673],"type":"Point"}
}