{
  "type": "Feature",
  "properties": {
    "iso:country":"AU",
    "sg:address":"416 Stuart Hwy",
    "sg:city":"Winnellie",
    "sg:classifiers":[
        {
            "category":"Home & Garden",
            "subcategory":"Hardware",
            "type":"Retail Goods"
        }
    ],
    "sg:phone":"+61 8 8947 0287",
    "sg:postcode":"0820",
    "sg:province":"NT",
    "sg:tags":[
        "generating",
        "set",
        "generator"
    ],
    "wof:name":"Askensmith Pty Ltd",
    "wof:placetype":"venue"
},
  "geometry": {"coordinates":[130.87657165499999,-12.4253997803],"type":"Point"}
}