{
  "type": "Feature",
  "properties": {
    "iso:country":"AU",
    "sg:address":"Shop 2, 95 Princes Hwy",
    "sg:city":"Ulladulla",
    "sg:classifiers":[
        {
            "category":"Shopping",
            "subcategory":"Jewelry",
            "type":"Retail Goods"
        }
    ],
    "sg:phone":"+61 2 4455 1251",
    "sg:postcode":"2539",
    "sg:province":"NSW",
    "sg:tags":[
        "jeweller"
    ],
    "wof:name":"Jewellery Plus Ulladulla",
    "wof:placetype":"venue"
},
  "geometry": {"coordinates":[150.475463867,-35.3511276245],"type":"Point"}
}