{
  "type": "Feature",
  "properties": {
    "addr:full":"PO Box 37 Branxton NSW 2335",
    "addr:postcode":"2335",
    "iso:country":"AU",
    "sg:address":"PO Box 37",
    "sg:city":"Branxton",
    "sg:classifiers":[
        {
            "category":"Train Station",
            "subcategory":"Rail",
            "type":"Transportation"
        }
    ],
    "sg:phone":"+61 2 4932 5086",
    "sg:postcode":"2335",
    "sg:province":"NSW",
    "sg:tags":[
        "rolling",
        "railway",
        "tramway",
        "stock"
    ],
    "wof:name":"Hunter Valley Railway Museum Trust",
    "wof:placetype":"venue"
},
  "geometry": {"coordinates":[151.3515625,-32.655960083],"type":"Point"}
}