{
  "type": "Feature",
  "properties": {
    "addr:full":"13 Maxine Drv Greensborough VIC 3088",
    "addr:housenumber":"13",
    "addr:postcode":"3088",
    "addr:street":"Maxine Drv",
    "iso:country":"AU",
    "sg:address":"13 Maxine Drv",
    "sg:city":"Greensborough",
    "sg:classifiers":[
        {
            "category":"Real Estate",
            "subcategory":"Surveying",
            "type":"Services"
        }
    ],
    "sg:phone":"+61 3 9434 5769",
    "sg:postcode":"3088",
    "sg:province":"VIC",
    "sg:tags":[
        "building",
        "surveyor"
    ],
    "wof:name":"Integrated Permits & Inspections",
    "wof:placetype":"venue"
},
  "geometry": {"coordinates":[145.13223266599999,-37.6881256104],"type":"Point"}
}