{
  "type": "Feature",
  "properties": {
    "iso:country":"AU",
    "sg:address":"Dandaloo Canyonleigh Rd",
    "sg:city":"Sutton Forest",
    "sg:classifiers":[
        {
            "category":"Health Services",
            "subcategory":"Doctor",
            "type":"Services"
        }
    ],
    "sg:phone":"+61 2 4878 9141",
    "sg:postcode":"2577",
    "sg:province":"NSW",
    "sg:tags":[
        "medical",
        "practitioner"
    ],
    "wof:name":"Walsh J W",
    "wof:placetype":"venue"
},
  "geometry": {"coordinates":[150.24839782699999,-34.586151123],"type":"Point"}
}