{
  "type": "Feature",
  "properties": {
    "addr:full":"169 Northcote St Kurri Kurri NSW 2327",
    "addr:housenumber":"169",
    "addr:postcode":"2327",
    "addr:street":"Northcote St",
    "iso:country":"AU",
    "sg:address":"169 Northcote St",
    "sg:city":"Kurri Kurri",
    "sg:classifiers":[
        {
            "category":"Organizations",
            "subcategory":"Community Association",
            "type":"Services"
        }
    ],
    "sg:phone":"+61 2 4937 2138",
    "sg:postcode":"2327",
    "sg:province":"NSW",
    "sg:tags":[
        "organisation",
        "family",
        "welfare"
    ],
    "wof:name":"Meals On Wheels",
    "wof:placetype":"venue"
},
  "geometry": {"coordinates":[151.466995239,-32.8153190613],"type":"Point"}
}