{
  "type": "Feature",
  "properties": {
    "addr:full":"Shop 5, Cnr Mamre Rd & Great Western Hwy St Marys NSW 2760",
    "addr:housenumber":"shop 5 cnr",
    "addr:postcode":"2760",
    "addr:street":"Mamre Rd & Great Western Hwy",
    "iso:country":"AU",
    "sg:address":"Shop 5, Cnr Mamre Rd & Great Western Hwy",
    "sg:city":"St Marys",
    "sg:classifiers":[
        {
            "category":"Health Services",
            "subcategory":"Doctor",
            "type":"Services"
        }
    ],
    "sg:phone":"+61 2 9833 2680",
    "sg:postcode":"2760",
    "sg:province":"NSW",
    "sg:tags":[
        "medical",
        "practitioner"
    ],
    "wof:name":"SDS Pathology",
    "wof:placetype":"venue"
},
  "geometry": {"coordinates":[150.77349853499999,-33.7701263428],"type":"Point"}
}