{
  "type": "Feature",
  "properties": {
    "iso:country":"AU",
    "sg:address":"210 Fisher Rd",
    "sg:city":"Cromer",
    "sg:classifiers":[
        {
            "category":"Utilities",
            "subcategory":"Electric",
            "type":"Services"
        }
    ],
    "sg:phone":"+61 438 207 870",
    "sg:postcode":"2099",
    "sg:province":"NSW",
    "sg:tags":[
        "electrical",
        "contractor"
    ],
    "wof:name":"Ajwires Electrical",
    "wof:placetype":"venue"
},
  "geometry": {"coordinates":[151.279907227,-33.7378082275],"type":"Point"}
}