{
  "type": "Feature",
  "properties": {
    "iso:country":"AU",
    "sg:address":"11 Shaw Pl",
    "sg:city":"Mt Nasura",
    "sg:classifiers":[
        {
            "category":"Professional",
            "subcategory":"Accounting & Tax Preparation",
            "type":"Services"
        }
    ],
    "sg:phone":"+61 8 9390 6316",
    "sg:postcode":"6112",
    "sg:province":"WA",
    "sg:tags":[
        "accountant",
        "auditor"
    ],
    "wof:name":"Dugmore G.C. & Associates",
    "wof:placetype":"venue"
},
  "geometry": {"coordinates":[116.03112793,-32.1316223145],"type":"Point"}
}