{
  "type": "Feature",
  "properties": {
    "addr:full":"1331 North East Rd Tea Tree Gully SA 5091",
    "addr:housenumber":"1331",
    "addr:postcode":"5091",
    "addr:street":"North East Rd Tea Tree",
    "iso:country":"AU",
    "sg:address":"1331 North East Rd",
    "sg:city":"Tea Tree Gully",
    "sg:classifiers":[
        {
            "category":"Health Services",
            "subcategory":"Doctor",
            "type":"Services"
        }
    ],
    "sg:phone":"+61 8 8264 2300",
    "sg:postcode":"5091",
    "sg:province":"SA",
    "sg:tags":[
        "medical",
        "practitioner"
    ],
    "wof:name":"Millington R M",
    "wof:placetype":"venue"
},
  "geometry": {"coordinates":[138.728912353,-34.8207778931],"type":"Point"}
}