{
  "type": "Feature",
  "properties": {
    "iso:country":"AU",
    "sg:address":"Belvedere Gulgong Rd",
    "sg:city":"Gulgong",
    "sg:classifiers":[
        {
            "category":"Shopping",
            "subcategory":"Crafts & Fabrics",
            "type":"Retail Goods"
        }
    ],
    "sg:phone":"+61 2 6375 9617",
    "sg:postcode":"2852",
    "sg:province":"NSW",
    "sg:tags":[
        "wool",
        "classers"
    ],
    "wof:name":"Bourke K A",
    "wof:placetype":"venue"
},
  "geometry": {"coordinates":[149.529404,-32.36274],"type":"Point"}
}