{
  "type": "Feature",
  "properties": {
    "addr:full":"11 Pauli Crt Warner QLD 4500",
    "addr:housenumber":"11",
    "addr:postcode":"4500",
    "addr:street":"Pauli Crt",
    "iso:country":"AU",
    "sg:address":"11 Pauli Crt",
    "sg:city":"Warner",
    "sg:classifiers":[
        {
            "category":"Professional",
            "subcategory":"Business Services",
            "type":"Services"
        }
    ],
    "sg:phone":"+61 7 3264 3200",
    "sg:postcode":"4500",
    "sg:province":"QLD",
    "sg:tags":[
        "drafting"
    ],
    "wof:name":"Perkins B & C Services",
    "wof:placetype":"venue"
},
  "geometry": {"coordinates":[152.94720459000001,-27.324754715],"type":"Point"}
}