{
  "type": "Feature",
  "properties": {
    "iso:country":"AU",
    "sg:address":"Unit 10 202-208 Glen Osmond Rd",
    "sg:city":"Fullarton",
    "sg:classifiers":[
        {
            "category":"Professional",
            "subcategory":"Printing & Photocopies",
            "type":"Services"
        }
    ],
    "sg:phone":"+61 8 8338 2211",
    "sg:postcode":"5063",
    "sg:province":"SA",
    "sg:tags":[
        "equipment",
        "plan"
    ],
    "wof:name":"Spectra Building Designers",
    "wof:placetype":"venue"
},
  "geometry": {"coordinates":[138.62950134299999,-34.9489784241],"type":"Point"}
}