{
  "type": "Feature",
  "properties": {
    "iso:country":"AU",
    "sg:address":"11 Mount Erin Crs",
    "sg:city":"Frankston",
    "sg:classifiers":[
        {
            "category":"Building & Trades",
            "subcategory":"Construction",
            "type":"Services"
        }
    ],
    "sg:phone":"+61 407 800 995",
    "sg:postcode":"3199",
    "sg:province":"VIC",
    "sg:tags":[
        "joiner",
        "carpenter"
    ],
    "wof:name":"Plumb Level Constructions",
    "wof:placetype":"venue"
},
  "geometry": {"coordinates":[145.32432556099999,-37.8735275269],"type":"Point"}
}