{
  "type": "Feature",
  "properties": {
    "addr:full":"317 Macdonnell Rd Clontarf QLD 4019",
    "addr:housenumber":"317",
    "addr:postcode":"4019",
    "addr:street":"Macdonnell Rd",
    "iso:country":"AU",
    "sg:address":"317 Macdonnell Rd",
    "sg:city":"Clontarf",
    "sg:classifiers":[
        {
            "category":"Retail",
            "subcategory":"Auto Repair",
            "type":"Services"
        }
    ],
    "sg:phone":"+61 7 3283 2290",
    "sg:postcode":"4019",
    "sg:province":"QLD",
    "sg:tags":[
        "repairer",
        "motor",
        "engineer"
    ],
    "wof:name":"Kipparing Service Centre",
    "wof:placetype":"venue"
},
  "geometry": {"coordinates":[153.08229064899999,-27.2338790894],"type":"Point"}
}