{
  "type": "Feature",
  "properties": {
    "addr:full":"35-43 Wangaratta St Richmond VIC 3121",
    "addr:housenumber":"35-43",
    "addr:postcode":"3121",
    "addr:street":"Wangaratta St",
    "iso:country":"AU",
    "sg:address":"35-43 Wangaratta St",
    "sg:city":"Richmond",
    "sg:classifiers":[
        {
            "category":"Shopping",
            "subcategory":"Clothing, Apparel, & Fashions",
            "type":"Retail Goods"
        }
    ],
    "sg:phone":"+61 3 9429 8055",
    "sg:postcode":"3121",
    "sg:province":"VIC",
    "sg:tags":[
        "lady",
        "wear"
    ],
    "wof:name":"Meredith Australia Pty Ltd",
    "wof:placetype":"venue"
},
  "geometry": {"coordinates":[144.99261474599999,-37.8241844177],"type":"Point"}
}