{
  "type": "Feature",
  "properties": {
    "addr:full":"8 Hampshire Ave West Pymble NSW 2073",
    "addr:housenumber":"8",
    "addr:postcode":"2073",
    "addr:street":"Hampshire Ave",
    "iso:country":"AU",
    "sg:address":"8 Hampshire Ave",
    "sg:city":"West Pymble",
    "sg:classifiers":[
        {
            "category":"Building & Trades",
            "subcategory":"Cleaning & Sanitation",
            "type":"Services"
        }
    ],
    "sg:phone":"+61 402 405 266",
    "sg:postcode":"2073",
    "sg:province":"NSW",
    "sg:tags":[
        "industrial",
        "commercial",
        "contractor"
    ],
    "wof:name":"Gardners Cleaning Pty Ltd",
    "wof:placetype":"venue"
},
  "geometry": {"coordinates":[151.13223266599999,-33.7708625793],"type":"Point"}
}