{
  "type": "Feature",
  "properties": {
    "addr:full":"12/ 19 Birmingham Ave Villawood NSW 2163",
    "addr:housenumber":"12 / 19",
    "addr:postcode":"2163",
    "addr:street":"Birmingham Ave",
    "iso:country":"AU",
    "sg:address":"12/ 19 Birmingham Ave",
    "sg:city":"Villawood",
    "sg:classifiers":[
        {
            "category":"Building & Trades",
            "subcategory":"Equipment Rental",
            "type":"Services"
        }
    ],
    "sg:phone":"+61 2 9724 1522",
    "sg:postcode":"2163",
    "sg:province":"NSW",
    "sg:tags":[
        "supply",
        "catering"
    ],
    "wof:name":"Paragon PBS P/L",
    "wof:placetype":"venue"
},
  "geometry": {"coordinates":[150.98667907699999,-33.87682724],"type":"Point"}
}