{
  "type": "Feature",
  "properties": {
    "iso:country":"AU",
    "sg:address":"18 Oborn Rd",
    "sg:city":"Mt Barker",
    "sg:classifiers":[
        {
            "category":"Home & Garden",
            "subcategory":"Building Materials",
            "type":"Retail Goods"
        }
    ],
    "sg:phone":"+61 8 8391 0499",
    "sg:postcode":"5251",
    "sg:province":"SA",
    "sg:tags":[
        "fencing"
    ],
    "wof:name":"Mt Barker Steel",
    "wof:placetype":"venue"
},
  "geometry": {"coordinates":[138.874267578,-35.0796318054],"type":"Point"}
}