{
  "type": "Feature",
  "properties": {
    "addr:full":"5 Florida Drv Landsdale WA 6065",
    "addr:housenumber":"5",
    "addr:postcode":"6065",
    "addr:street":"Florida Drv",
    "iso:country":"AU",
    "sg:address":"5 Florida Drv",
    "sg:city":"Landsdale",
    "sg:classifiers":[
        {
            "category":"Personal",
            "subcategory":"Beauty Salon",
            "type":"Services"
        }
    ],
    "sg:phone":"+61 8 9302 5737",
    "sg:postcode":"6065",
    "sg:province":"WA",
    "sg:tags":[
        "hair",
        "wedding"
    ],
    "wof:name":"Total Brides",
    "wof:placetype":"venue"
},
  "geometry": {"coordinates":[115.855873108,-31.8202152252],"type":"Point"}
}