{
  "type": "Feature",
  "properties": {
    "iso:country":"AU",
    "sg:address":"1 Rugby St",
    "sg:city":"Pasadena",
    "sg:classifiers":[
        {
            "category":"Building & Trades",
            "subcategory":"Construction",
            "type":"Services"
        }
    ],
    "sg:phone":"+61 8 8277 9471",
    "sg:postcode":"5042",
    "sg:province":"SA",
    "sg:tags":[
        "contractor"
    ],
    "wof:name":"G & Z Goddard Constructions",
    "wof:placetype":"venue"
},
  "geometry": {"coordinates":[138.582993,-35.00032],"type":"Point"}
}