{
  "type": "Feature",
  "properties": {
    "iso:country":"AU",
    "sg:address":"Suite 4 188 Mulgrave Rd",
    "sg:city":"Westcourt",
    "sg:classifiers":[
        {
            "category":"Professional",
            "subcategory":"Employment Agencies",
            "type":"Services"
        }
    ],
    "sg:phone":"+61 7 4044 2666",
    "sg:postcode":"4870",
    "sg:province":"QLD",
    "wof:name":"IPA Personnel Pty Ltd",
    "wof:placetype":"venue"
},
  "geometry": {"coordinates":[145.75164794899999,-16.9359817505],"type":"Point"}
}