{
  "type": "Feature",
  "properties": {
    "addr:full":"Level 14, 145 Eagle St Brisbane QLD 4000",
    "addr:housenumber":"145",
    "addr:postcode":"4000",
    "addr:street":"Eagle St",
    "iso:country":"AU",
    "sg:address":"Level 14, 145 Eagle St",
    "sg:city":"Brisbane",
    "sg:classifiers":[
        {
            "category":"Professional",
            "subcategory":"Accounting & Tax Preparation",
            "type":"Services"
        }
    ],
    "sg:phone":"+61 7 3333 9800",
    "sg:postcode":"4000",
    "sg:province":"QLD",
    "sg:tags":[
        "accountant",
        "auditor"
    ],
    "wof:name":"McGrathNicol",
    "wof:placetype":"venue"
},
  "geometry": {"coordinates":[153.03030395499999,-27.4665985107],"type":"Point"}
}