{
  "type": "Feature",
  "properties": {
    "addr:full":"34 Cottesmore St Fig Tree Pocket QLD 4069",
    "addr:housenumber":"34",
    "addr:postcode":"4069",
    "addr:street":"Cottesmore St",
    "iso:country":"AU",
    "sg:address":"34 Cottesmore St",
    "sg:city":"Fig Tree Pocket",
    "sg:classifiers":[
        {
            "category":"Real Estate",
            "subcategory":"Architect",
            "type":"Services"
        }
    ],
    "sg:phone":"+61 7 3378 5441",
    "sg:postcode":"4069",
    "sg:province":"QLD",
    "wof:name":"Leslie James Architects Pty Ltd",
    "wof:placetype":"venue"
},
  "geometry": {"coordinates":[152.958221436,-27.5185813904],"type":"Point"}
}