{
  "type": "Feature",
  "properties": {
    "addr:full":"693 Albany Hwy East Victoria Park WA 6101",
    "addr:housenumber":"693",
    "addr:postcode":"6101",
    "addr:street":"Albany Hwy",
    "iso:country":"AU",
    "sg:address":"693 Albany Hwy",
    "sg:city":"East Victoria Park",
    "sg:classifiers":[
        {
            "category":"Health Services",
            "subcategory":"Dentist",
            "type":"Services"
        }
    ],
    "sg:phone":"+61 8 9361 8973",
    "sg:postcode":"6101",
    "sg:province":"WA",
    "wof:name":"Ten F S",
    "wof:placetype":"venue"
},
  "geometry": {"coordinates":[115.90090179400001,-31.9815120697],"type":"Point"}
}