{
  "type": "Feature",
  "properties": {
    "addr:full":"22 Irvine St Kingsford NSW 2032",
    "addr:housenumber":"22",
    "addr:postcode":"2032",
    "addr:street":"Irvine St",
    "iso:country":"AU",
    "sg:address":"22 Irvine St",
    "sg:city":"Kingsford",
    "sg:classifiers":[
        {
            "category":"Utilities",
            "subcategory":"Water",
            "type":"Services"
        }
    ],
    "sg:phone":"+61 2 9344 5388",
    "sg:postcode":"2032",
    "sg:province":"NSW",
    "sg:tags":[
        "hot",
        "system"
    ],
    "wof:name":"Fitzgerald Mark",
    "wof:placetype":"venue"
},
  "geometry": {"coordinates":[151.23382568400001,-33.9304466248],"type":"Point"}
}