{
  "type": "Feature",
  "properties": {
    "addr:full":"47 Coronation Drv Innisfail QLD 4860",
    "addr:housenumber":"47",
    "addr:postcode":"4860",
    "addr:street":"Coronation Drv",
    "iso:country":"AU",
    "sg:address":"47 Coronation Drv",
    "sg:city":"Innisfail",
    "sg:classifiers":[
        {
            "category":"Personal",
            "subcategory":"Massage",
            "type":"Services"
        }
    ],
    "sg:phone":"+61 7 4061 2557",
    "sg:postcode":"4860",
    "sg:province":"QLD",
    "sg:tags":[
        "therapy"
    ],
    "wof:name":"Energetics Australia",
    "wof:placetype":"venue"
},
  "geometry": {"coordinates":[146.032073975,-17.5319271088],"type":"Point"}
}