{
  "type": "Feature",
  "properties": {
    "addr:full":"7 Endeavour Drv Port Adelaide SA 5015",
    "addr:housenumber":"7",
    "addr:postcode":"5015",
    "addr:street":"Endeavour Drv",
    "iso:country":"AU",
    "sg:address":"7 Endeavour Drv",
    "sg:city":"Port Adelaide",
    "sg:classifiers":[
        {
            "category":"Retail",
            "subcategory":"Repair Shop",
            "type":"Services"
        }
    ],
    "sg:phone":"+61 1300 884 405",
    "sg:postcode":"5015",
    "sg:province":"SA",
    "sg:tags":[
        "restorer",
        "repairer",
        "carpet"
    ],
    "wof:name":"Chem-Dry Professionals",
    "wof:placetype":"venue"
},
  "geometry": {"coordinates":[138.50471496599999,-34.854675293],"type":"Point"}
}