{
  "type": "Feature",
  "properties": {
    "addr:full":"218 Prospect Rd Prospect SA 5082",
    "addr:housenumber":"218",
    "addr:postcode":"5082",
    "addr:street":"Prospect Rd",
    "iso:country":"AU",
    "sg:address":"218 Prospect Rd",
    "sg:city":"Prospect",
    "sg:classifiers":[
        {
            "category":"Shopping",
            "subcategory":"Party Supplies",
            "type":"Retail Goods"
        }
    ],
    "sg:phone":"+61 403 505 015",
    "sg:postcode":"5082",
    "sg:province":"SA",
    "sg:tags":[
        "children's"
    ],
    "wof:name":"The Enchanted Palace",
    "wof:placetype":"venue"
},
  "geometry": {"coordinates":[138.59332275400001,-34.8789215088],"type":"Point"}
}