{
  "type": "Feature",
  "properties": {
    "iso:country":"AU",
    "sg:address":"Level 1, 84 Pitt St",
    "sg:city":"Sydney",
    "sg:classifiers":[
        {
            "category":"Professional",
            "subcategory":"Management & Consulting",
            "type":"Services"
        }
    ],
    "sg:phone":"+61 2 9299 4107",
    "sg:postcode":"2000",
    "sg:province":"NSW",
    "sg:tags":[
        "consultant",
        "economic"
    ],
    "wof:name":"Syneca Consulting",
    "wof:placetype":"venue"
},
  "geometry": {"coordinates":[151.208709717,-33.8666687012],"type":"Point"}
}