{
  "type": "Feature",
  "properties": {
    "iso:country":"AU",
    "sg:address":"756 Zillmere Rd",
    "sg:city":"Aspley",
    "sg:classifiers":[
        {
            "category":"Health Services",
            "subcategory":"Doctor",
            "type":"Services"
        }
    ],
    "sg:phone":"+61 7 3263 8282",
    "sg:postcode":"4034",
    "sg:province":"QLD",
    "sg:tags":[
        "medical",
        "practitioner"
    ],
    "wof:name":"Tan H H",
    "wof:placetype":"venue"
},
  "geometry": {"coordinates":[153.020737,-27.356859],"type":"Point"}
}