{
  "type": "Feature",
  "properties": {
    "addr:full":"7 Noble St Kewdale WA 6105",
    "addr:housenumber":"7",
    "addr:postcode":"6105",
    "addr:street":"Noble St",
    "iso:country":"AU",
    "sg:address":"7 Noble St",
    "sg:city":"Kewdale",
    "sg:classifiers":[
        {
            "category":"Manufacturing",
            "subcategory":"Motor Vehicles & Parts",
            "type":"Manufacturing & Wholesale Goods"
        }
    ],
    "sg:phone":"+61 8 9353 3533",
    "sg:postcode":"6105",
    "sg:province":"WA",
    "sg:tags":[
        "engine",
        "equipment",
        "diesel"
    ],
    "wof:name":"R Moore & Sons",
    "wof:placetype":"venue"
},
  "geometry": {"coordinates":[115.95108795199999,-31.9787483215],"type":"Point"}
}