{
  "type": "Feature",
  "properties": {
    "addr:full":"Shp 1/ 256 Church St Richmond VIC 3121",
    "addr:housenumber":"/ 256",
    "addr:postcode":"3121",
    "addr:street":"Church St",
    "iso:country":"AU",
    "sg:address":"Shp 1/ 256 Church St",
    "sg:city":"Richmond",
    "sg:classifiers":[
        {
            "category":"Home & Garden",
            "subcategory":"Carpets & Floor Coverings",
            "type":"Retail Goods"
        }
    ],
    "sg:phone":"+61 3 9429 9844",
    "sg:postcode":"3121",
    "sg:province":"VIC",
    "sg:tags":[
        "wholesaler",
        "tie",
        "mfrs",
        "scarf"
    ],
    "wof:name":"Tie N Things",
    "wof:placetype":"venue"
},
  "geometry": {"coordinates":[144.99896240199999,-37.8188591003],"type":"Point"}
}