{
  "type": "Feature",
  "properties": {
    "addr:full":"11 Eastbourne Rd Darling Point NSW 2027",
    "addr:housenumber":"11",
    "addr:postcode":"2027",
    "addr:street":"Eastbourne Rd",
    "iso:country":"AU",
    "sg:address":"11 Eastbourne Rd",
    "sg:city":"Darling Point",
    "sg:classifiers":[
        {
            "category":"Health Services",
            "subcategory":"Doctor",
            "type":"Services"
        }
    ],
    "sg:phone":"+61 2 9326 1271",
    "sg:postcode":"2027",
    "sg:province":"NSW",
    "sg:tags":[
        "medical",
        "practitioner"
    ],
    "wof:name":"Mayne Peter G",
    "wof:placetype":"venue"
},
  "geometry": {"coordinates":[151.239334106,-33.8728218079],"type":"Point"}
}