{
  "type": "Feature",
  "properties": {
    "addr:full":"PO Box 18 Botany NSW 2019",
    "addr:postcode":"2019",
    "iso:country":"AU",
    "sg:address":"PO Box 18",
    "sg:city":"Botany",
    "sg:classifiers":[
        {
            "category":"Professional",
            "type":"Services"
        }
    ],
    "sg:phone":"+61 2 9316 4653",
    "sg:postcode":"2019",
    "sg:province":"NSW",
    "sg:tags":[
        "transport"
    ],
    "wof:name":"AKH Transport Pty Ltd",
    "wof:placetype":"venue"
},
  "geometry": {"coordinates":[151.203567505,-33.9508285522],"type":"Point"}
}