{
  "type": "Feature",
  "properties": {
    "addr:full":"26 Hutchinson St St Peters NSW 2044",
    "addr:housenumber":"26",
    "addr:postcode":"2044",
    "addr:street":"Hutchinson St",
    "iso:country":"AU",
    "sg:address":"26 Hutchinson St",
    "sg:city":"St Peters",
    "sg:classifiers":[
        {
            "category":"Wholesale",
            "subcategory":"Apparel",
            "type":"Manufacturing & Wholesale Goods"
        }
    ],
    "sg:phone":"+61 2 9550 3834",
    "sg:postcode":"2044",
    "sg:province":"NSW",
    "sg:tags":[
        "wholesaler",
        "mfrs",
        "dress"
    ],
    "wof:name":"Brownland Pty Ltd",
    "wof:placetype":"venue"
},
  "geometry": {"coordinates":[151.17898600000001,-33.91011],"type":"Point"}
}