{
  "type": "Feature",
  "properties": {
    "iso:country":"AU",
    "sg:address":"1- 7 Felspar St",
    "sg:city":"Welshpool",
    "sg:classifiers":[
        {
            "category":"Utilities",
            "subcategory":"Refuse",
            "type":"Services"
        }
    ],
    "sg:phone":"+61 8 9356 5737",
    "sg:postcode":"6106",
    "sg:province":"WA",
    "sg:tags":[
        "incinerator"
    ],
    "wof:name":"Incinerator Sales & Service",
    "wof:placetype":"venue"
},
  "geometry": {"coordinates":[115.970077515,-32.0015487671],"type":"Point"}
}