{
  "type": "Feature",
  "properties": {
    "addr:full":"33 Carmel Crs Kariong NSW 2250",
    "addr:housenumber":"33",
    "addr:postcode":"2250",
    "addr:street":"Carmel Crs",
    "iso:country":"AU",
    "sg:address":"33 Carmel Crs",
    "sg:city":"Kariong",
    "sg:classifiers":[
        {
            "category":"Professional",
            "subcategory":"Accounting & Tax Preparation",
            "type":"Services"
        }
    ],
    "sg:phone":"+61 2 4340 4182",
    "sg:postcode":"2250",
    "sg:province":"NSW",
    "sg:tags":[
        "accountant",
        "auditor"
    ],
    "wof:name":"Bentley Joel",
    "wof:placetype":"venue"
},
  "geometry": {"coordinates":[151.29620361299999,-33.438331604],"type":"Point"}
}