{
  "type": "Feature",
  "properties": {
    "addr:full":"Coronation Place, 4/10 Benson Street, Toowong QLD 4066",
    "addr:housenumber":"/ 10",
    "addr:postcode":"4066",
    "addr:street":"Coronation;Benson Street",
    "iso:country":"AU",
    "sg:address":"Coronation Place, 4/10 Benson Street,",
    "sg:city":"Toowong",
    "sg:classifiers":[
        {
            "category":"Health Services",
            "subcategory":"Doctor",
            "type":"Services"
        }
    ],
    "sg:phone":"+61 1300 722 242",
    "sg:postcode":"4066",
    "sg:province":"QLD",
    "sg:tags":[
        "podiatrist"
    ],
    "wof:name":"Australian Podiatry Association (QLD) Pty Ltd.",
    "wof:placetype":"venue"
},
  "geometry": {"coordinates":[152.99359130900001,-27.4855175018],"type":"Point"}
}