{
  "type": "Feature",
  "properties": {
    "addr:full":"111 Monaro St Queanbeyan NSW 2620",
    "addr:housenumber":"111",
    "addr:postcode":"2620",
    "addr:street":"Monaro St",
    "iso:country":"AU",
    "sg:address":"111 Monaro St",
    "sg:city":"Queanbeyan",
    "sg:classifiers":[
        {
            "category":"Cafe",
            "type":"Food & Drink"
        }
    ],
    "sg:phone":"+61 2 6297 1335",
    "sg:postcode":"2620",
    "sg:province":"NSW",
    "wof:name":"Central Cafe",
    "wof:placetype":"venue"
},
  "geometry": {"coordinates":[149.23455810600001,-35.3530273438],"type":"Point"}
}