{
  "type": "Feature",
  "properties": {
    "addr:full":"96 Rowan St Wangaratta VIC 3678",
    "addr:housenumber":"96",
    "addr:postcode":"3678",
    "addr:street":"Rowan St",
    "iso:country":"AU",
    "sg:address":"96 Rowan St",
    "sg:city":"Wangaratta",
    "sg:classifiers":[
        {
            "category":"Health Services",
            "subcategory":"Health Practitioner",
            "type":"Services"
        }
    ],
    "sg:phone":"+61 3 5722 2589",
    "sg:postcode":"3678",
    "sg:province":"VIC",
    "sg:tags":[
        "psychologist"
    ],
    "wof:name":"Hume Psychology And Consulting Services",
    "wof:placetype":"venue"
},
  "geometry": {"coordinates":[146.31483459500001,-36.3510322571],"type":"Point"}
}