{
  "type": "Feature",
  "properties": {
    "addr:full":"5 A Lansdowne Crs West Hobart TAS 7000",
    "addr:housenumber":"5 a",
    "addr:postcode":"7000",
    "addr:street":"Lansdowne Crs",
    "iso:country":"AU",
    "sg:address":"5 A Lansdowne Crs",
    "sg:city":"West Hobart",
    "sg:classifiers":[
        {
            "category":"Professional",
            "subcategory":"Art Services",
            "type":"Services"
        }
    ],
    "sg:phone":"+61 3 6231 2757",
    "sg:postcode":"7000",
    "sg:province":"TAS",
    "sg:tags":[
        "interior",
        "decorator"
    ],
    "wof:name":"Hobart Interiors",
    "wof:placetype":"venue"
},
  "geometry": {"coordinates":[147.31132507300001,-42.8765106201],"type":"Point"}
}