{
  "type": "Feature",
  "properties": {
    "addr:full":"1295 North East Rd Tea Tree Gully SA 5091",
    "addr:housenumber":"1295",
    "addr:postcode":"5091",
    "addr:street":"North East Rd Tea Tree",
    "iso:country":"AU",
    "sg:address":"1295 North East Rd",
    "sg:city":"Tea Tree Gully",
    "sg:classifiers":[
        {
            "category":"Personal",
            "subcategory":"Massage",
            "type":"Services"
        }
    ],
    "sg:phone":"+61 8 8396 4884",
    "sg:postcode":"5091",
    "sg:province":"SA",
    "sg:tags":[
        "therapy"
    ],
    "wof:name":"Christopher Bazzica",
    "wof:placetype":"venue"
},
  "geometry": {"coordinates":[138.72889709500001,-34.8207740784],"type":"Point"}
}