{
  "type": "Feature",
  "properties": {
    "addr:full":"2a Swan St Revesby NSW 2212",
    "addr:housenumber":"2a",
    "addr:postcode":"2212",
    "addr:street":"Swan St",
    "iso:country":"AU",
    "sg:address":"2a Swan St",
    "sg:city":"Revesby",
    "sg:classifiers":[
        {
            "category":"Personal",
            "subcategory":"Beauty Salon",
            "type":"Services"
        }
    ],
    "sg:phone":"+61 2 9773 0287",
    "sg:postcode":"2212",
    "sg:province":"NSW",
    "sg:tags":[
        "hairdresser"
    ],
    "wof:name":"Nicole's Cuts & Curls",
    "wof:placetype":"venue"
},
  "geometry": {"coordinates":[151.01272599999999,-33.949554],"type":"Point"}
}