{
  "type": "Feature",
  "properties": {
    "iso:country":"AU",
    "sg:address":"74 Bridge Rd",
    "sg:city":"Richmond",
    "sg:classifiers":[
        {
            "category":"Shopping",
            "subcategory":"Clothing, Apparel, & Fashions",
            "type":"Retail Goods"
        }
    ],
    "sg:phone":"+61 3 9428 6833",
    "sg:postcode":"3121",
    "sg:province":"VIC",
    "sg:tags":[
        "jean"
    ],
    "wof:name":"Easy Tiger",
    "wof:placetype":"venue"
},
  "geometry": {"coordinates":[144.992462158,-37.8179397583],"type":"Point"}
}