{
  "type": "Feature",
  "properties": {
    "addr:full":"Palmer St Orange NSW 2800",
    "addr:postcode":"2800",
    "addr:street":"Palmer St",
    "iso:country":"AU",
    "sg:address":"Palmer St",
    "sg:city":"Orange",
    "sg:classifiers":[
        {
            "category":"Sports & Exercise",
            "subcategory":"Sports Center",
            "type":"Entertainment"
        }
    ],
    "sg:phone":"+61 2 6362 9811",
    "sg:postcode":"2800",
    "sg:province":"NSW",
    "sg:tags":[
        "coach",
        "tennis"
    ],
    "wof:name":"Totally Tennis Indoor Centre",
    "wof:placetype":"venue"
},
  "geometry": {"coordinates":[149.10737609899999,-33.2911987305],"type":"Point"}
}