{
  "type": "Feature",
  "properties": {
    "addr:full":"\"Greenwood Grove\" 125 Ervins Rd Mt Moriac VIC 3240",
    "addr:housenumber":"125",
    "addr:postcode":"3240",
    "addr:street":"Ervins Rd Mt Moriac",
    "iso:country":"AU",
    "sg:address":"\"Greenwood Grove\" 125 Ervins Rd",
    "sg:city":"Mt Moriac",
    "sg:classifiers":[
        {
            "category":"Farming",
            "subcategory":"Farm",
            "type":"Manufacturing & Wholesale Goods"
        }
    ],
    "sg:phone":"+61 3 5266 1253",
    "sg:postcode":"3240",
    "sg:province":"VIC",
    "sg:tags":[
        "farmer"
    ],
    "wof:name":"Chalmers B A",
    "wof:placetype":"venue"
},
  "geometry": {"coordinates":[144.18690490700001,-38.230884552],"type":"Point"}
}