{
  "type": "Feature",
  "properties": {
    "addr:full":"Unit 8 251 Ferry Rd Southport QLD 4215",
    "addr:housenumber":"251",
    "addr:postcode":"4215",
    "addr:street":"Ferry Rd",
    "iso:country":"AU",
    "sg:address":"Unit 8 251 Ferry Rd",
    "sg:city":"Southport",
    "sg:classifiers":[
        {
            "category":"Health Services",
            "subcategory":"Doctor",
            "type":"Services"
        }
    ],
    "sg:phone":"+61 7 5532 6928",
    "sg:postcode":"4215",
    "sg:province":"QLD",
    "sg:tags":[
        "medical",
        "practitioner"
    ],
    "wof:name":"White Robert Dr",
    "wof:placetype":"venue"
},
  "geometry": {"coordinates":[153.41261291500001,-27.9917697906],"type":"Point"}
}