{
  "type": "Feature",
  "properties": {
    "addr:full":"26 Bourke St Tamworth NSW 2340",
    "addr:housenumber":"26",
    "addr:postcode":"2340",
    "addr:street":"Bourke St",
    "iso:country":"AU",
    "sg:address":"26 Bourke St",
    "sg:city":"Tamworth",
    "sg:classifiers":[
        {
            "category":"Health Services",
            "subcategory":"Dentist",
            "type":"Services"
        }
    ],
    "sg:phone":"+61 2 6766 2316",
    "sg:postcode":"2340",
    "sg:province":"NSW",
    "wof:name":"Broadbent N J, Massey S J, Wise R J & Allan.D",
    "wof:placetype":"venue"
},
  "geometry": {"coordinates":[150.92913818400001,-31.0874061584],"type":"Point"}
}