{
  "type": "Feature",
  "properties": {
    "addr:full":"18 Peel St Walgett NSW 2832",
    "addr:housenumber":"18",
    "addr:postcode":"2832",
    "addr:street":"Peel St",
    "iso:country":"AU",
    "sg:address":"18 Peel St",
    "sg:city":"Walgett",
    "sg:classifiers":[
        {
            "category":"Taxi",
            "type":"Transportation"
        }
    ],
    "sg:phone":"+61 2 6828 1801",
    "sg:postcode":"2832",
    "sg:province":"NSW",
    "sg:tags":[
        "cab"
    ],
    "wof:name":"Walgett Radio Taxis",
    "wof:placetype":"venue"
},
  "geometry": {"coordinates":[148.11451721200001,-30.018995285],"type":"Point"}
}