{
  "type": "Feature",
  "properties": {
    "addr:full":"PO Box 167 Evans Head NSW 2473",
    "addr:postcode":"2473",
    "iso:country":"AU",
    "sg:address":"PO Box 167",
    "sg:city":"Evans Head",
    "sg:classifiers":[
        {
            "category":"Building & Trades",
            "subcategory":"Plumbing",
            "type":"Services"
        }
    ],
    "sg:phone":"+61 427 485 178",
    "sg:postcode":"2473",
    "sg:province":"NSW",
    "sg:tags":[
        "plumber",
        "gasfitters"
    ],
    "wof:name":"Plumbers New South Wales",
    "wof:placetype":"venue"
},
  "geometry": {"coordinates":[153.426055908,-29.1095695496],"type":"Point"}
}