{
  "type": "Feature",
  "properties": {
    "addr:full":"Cnr Corbusier & Balcatta Rds Balcatta WA 6021",
    "addr:postcode":"6021",
    "addr:street":"Cnr Corbusier & Balcatta Rds",
    "iso:country":"AU",
    "sg:address":"Cnr Corbusier & Balcatta Rds",
    "sg:city":"Balcatta",
    "sg:classifiers":[
        {
            "category":"Shopping",
            "subcategory":"Stationery & Office Supplies",
            "type":"Retail Goods"
        }
    ],
    "sg:phone":"+61 8 9240 5992",
    "sg:postcode":"6021",
    "sg:province":"WA",
    "wof:name":"Office National Balcatta",
    "wof:placetype":"venue"
},
  "geometry": {"coordinates":[115.81381225600001,-31.8622932434],"type":"Point"}
}