{
  "type": "Feature",
  "properties": {
    "addr:full":"17 Everley Rd Chester Hill NSW 2162",
    "addr:housenumber":"17",
    "addr:postcode":"2162",
    "addr:street":"Everley Rd",
    "iso:country":"AU",
    "sg:address":"17 Everley Rd",
    "sg:city":"Chester Hill",
    "sg:classifiers":[
        {
            "category":"Professional",
            "type":"Services"
        }
    ],
    "sg:phone":"+61 13 38 08",
    "sg:postcode":"2162",
    "sg:province":"NSW",
    "sg:tags":[
        "courier"
    ],
    "wof:name":"Parceline",
    "wof:placetype":"venue"
},
  "geometry": {"coordinates":[151.009887695,-33.8702545166],"type":"Point"}
}