{
  "type": "Feature",
  "properties": {
    "iso:country":"AU",
    "sg:address":"63 Butcher St",
    "sg:city":"Bendigo",
    "sg:classifiers":[
        {
            "category":"Social Services",
            "subcategory":"Child Care",
            "type":"Services"
        }
    ],
    "sg:phone":"+61 3 5443 7628",
    "sg:postcode":"3550",
    "sg:province":"VIC",
    "sg:tags":[
        "childbirth"
    ],
    "wof:name":"Central Victorian Midwifery Group Practice",
    "wof:placetype":"venue"
},
  "geometry": {"coordinates":[144.32142639200001,-36.7766532898],"type":"Point"}
}