{
  "type": "Feature",
  "properties": {
    "addr:full":"95 Sutton St Echuca VIC 3564",
    "addr:housenumber":"95",
    "addr:postcode":"3564",
    "addr:street":"Sutton St",
    "iso:country":"AU",
    "sg:address":"95 Sutton St",
    "sg:city":"Echuca",
    "sg:classifiers":[
        {
            "category":"Home & Garden",
            "subcategory":"Carpets & Floor Coverings",
            "type":"Retail Goods"
        }
    ],
    "sg:phone":"+61 3 5482 2691",
    "sg:postcode":"3564",
    "sg:province":"VIC",
    "sg:tags":[
        "tile",
        "wall",
        "layer"
    ],
    "wof:name":"Rosenow Russell",
    "wof:placetype":"venue"
},
  "geometry": {"coordinates":[144.759643555,-36.1291351318],"type":"Point"}
}