{
  "type": "Feature",
  "properties": {
    "iso:country":"AU",
    "sg:address":"Campbell St",
    "sg:city":"Birchip",
    "sg:classifiers":[
        {
            "category":"Education",
            "subcategory":"School",
            "type":"Public Place"
        }
    ],
    "sg:phone":"+61 3 5492 2553",
    "sg:postcode":"3483",
    "sg:province":"VIC",
    "sg:tags":[
        "state",
        "except",
        "nsw"
    ],
    "wof:name":"Birchip P-12 School",
    "wof:placetype":"venue"
},
  "geometry": {"coordinates":[142.91653442399999,-35.9839820862],"type":"Point"}
}