{
  "type": "Feature",
  "properties": {
    "addr:full":"35 Fermony Ave Northam WA 6401",
    "addr:housenumber":"35",
    "addr:postcode":"6401",
    "addr:street":"Fermony Ave",
    "iso:country":"AU",
    "sg:address":"35 Fermony Ave",
    "sg:city":"Northam",
    "sg:classifiers":[
        {
            "category":"Professional",
            "subcategory":"Art Services",
            "type":"Services"
        }
    ],
    "sg:phone":"+61 8 9622 3571",
    "sg:postcode":"6401",
    "sg:province":"WA",
    "sg:tags":[
        "decorator",
        "painter"
    ],
    "wof:name":"G.W.Y. Painting Service",
    "wof:placetype":"venue"
},
  "geometry": {"coordinates":[116.679489136,-31.6577262878],"type":"Point"}
}