{
  "type": "Feature",
  "properties": {
    "addr:full":"126 Andrews Rd Penrith NSW 2750",
    "addr:housenumber":"126",
    "addr:postcode":"2750",
    "addr:street":"Andrews Rd",
    "iso:country":"AU",
    "sg:address":"126 Andrews Rd",
    "sg:city":"Penrith",
    "sg:classifiers":[
        {
            "category":"Manufacturing",
            "subcategory":"Chemicals & Compounds",
            "type":"Manufacturing & Wholesale Goods"
        }
    ],
    "sg:phone":"+61 1800 112 113",
    "sg:postcode":"2750",
    "sg:province":"NSW",
    "sg:tags":[
        "industrial"
    ],
    "wof:name":"Inchem",
    "wof:placetype":"venue"
},
  "geometry": {"coordinates":[150.70350647000001,-33.7312355042],"type":"Point"}
}