{
  "type": "Feature",
  "properties": {
    "addr:full":"Cnr Kildare & Doonside Rds Doonside NSW 2767",
    "addr:postcode":"2767",
    "addr:street":"Cnr Kildare & Doonside Rds",
    "iso:country":"AU",
    "sg:address":"Cnr Kildare & Doonside Rds",
    "sg:city":"Doonside",
    "sg:classifiers":[
        {
            "category":"Autos & Motor Vehicles",
            "subcategory":"Fuel & Gas Station",
            "type":"Retail Goods"
        }
    ],
    "sg:phone":"+61 2 9621 4395",
    "sg:postcode":"2767",
    "sg:province":"NSW",
    "wof:name":"Saab Petroleum",
    "wof:placetype":"venue"
},
  "geometry": {"coordinates":[150.87034606899999,-33.7651901245],"type":"Point"}
}