{
  "type": "Feature",
  "properties": {
    "iso:country":"AU",
    "sg:address":"Keith Hall971 River Drv (via Ballina)",
    "sg:city":"Ballina",
    "sg:classifiers":[
        {
            "category":"Travel",
            "subcategory":"Travel Agent",
            "type":"Entertainment"
        }
    ],
    "sg:phone":"+61 2 6686 2047",
    "sg:postcode":"2478",
    "sg:province":"NSW",
    "sg:tags":[
        "tour",
        "holiday",
        "adventure"
    ],
    "wof:name":"A John Felsch Stretch Limousines",
    "wof:placetype":"venue"
},
  "geometry": {"coordinates":[153.52981567399999,-28.8953952789],"type":"Point"}
}