{
  "type": "Feature",
  "properties": {
    "addr:full":"44 Newland Ave Marino SA 5049",
    "addr:housenumber":"44",
    "addr:postcode":"5049",
    "addr:street":"Newland Ave",
    "iso:country":"AU",
    "sg:address":"44 Newland Ave",
    "sg:city":"Marino",
    "sg:classifiers":[
        {
            "category":"Government",
            "subcategory":"City Hall",
            "type":"Public Place"
        }
    ],
    "sg:phone":"+61 8 8298 8277",
    "sg:postcode":"5049",
    "sg:province":"SA",
    "wof:name":"Marino Community Hall",
    "wof:placetype":"venue"
},
  "geometry": {"coordinates":[138.51664700000001,-35.043346],"type":"Point"}
}