{
  "type": "Feature",
  "properties": {
    "addr:full":"PO Box 1216 Moorabbin VIC 3189",
    "addr:postcode":"3189",
    "iso:country":"AU",
    "sg:address":"PO Box 1216",
    "sg:city":"Moorabbin",
    "sg:classifiers":[
        {
            "category":"Shopping",
            "subcategory":"Clothing, Apparel, & Fashions",
            "type":"Retail Goods"
        }
    ],
    "sg:phone":"+61 3 9557 7273",
    "sg:postcode":"3189",
    "sg:province":"VIC",
    "sg:tags":[
        "lady",
        "wear"
    ],
    "wof:name":"Jamil",
    "wof:placetype":"venue"
},
  "geometry": {"coordinates":[145.05694580100001,-37.9414215088],"type":"Point"}
}