{
  "type": "Feature",
  "properties": {
    "iso:country":"AU",
    "sg:address":"170 Matthew Flinders Drv",
    "sg:city":"Yeppoon",
    "sg:classifiers":[
        {
            "category":"Recreation",
            "type":"Entertainment"
        }
    ],
    "sg:phone":"+61 7 4938 4805",
    "sg:postcode":"4703",
    "sg:province":"QLD",
    "sg:tags":[
        "supply",
        "outdoor",
        "adventure",
        "activity"
    ],
    "wof:name":"Yeppoon Outdoor Recreation Centre",
    "wof:placetype":"venue"
},
  "geometry": {"coordinates":[150.762405395,-23.1492519379],"type":"Point"}
}