{
  "type": "Feature",
  "properties": {
    "iso:country":"AU",
    "sg:address":"Cnr Dandenong & Warrigal Rds",
    "sg:city":"Oakleigh",
    "sg:classifiers":[
        {
            "category":"Health Services",
            "subcategory":"Doctor",
            "type":"Services"
        }
    ],
    "sg:phone":"+61 3 9569 7099",
    "sg:postcode":"3166",
    "sg:province":"VIC",
    "sg:tags":[
        "medical",
        "practitioner"
    ],
    "wof:name":"Adriatic Furniture",
    "wof:placetype":"venue"
},
  "geometry": {"coordinates":[145.089935303,-37.8929138184],"type":"Point"}
}