{
  "type": "Feature",
  "properties": {
    "addr:full":"32/ 6a Grandstand Pde Zetland NSW 2017",
    "addr:housenumber":"32 / 6a",
    "addr:postcode":"2017",
    "addr:street":"Grandstand Pde",
    "iso:country":"AU",
    "sg:address":"32/ 6a Grandstand Pde",
    "sg:city":"Zetland",
    "sg:classifiers":[
        {
            "category":"Government",
            "subcategory":"Customs House",
            "type":"Public Place"
        }
    ],
    "sg:phone":"+61 2 9662 6000",
    "sg:postcode":"2017",
    "sg:province":"NSW",
    "sg:tags":[
        "title",
        "management",
        "stratum"
    ],
    "wof:name":"Eastern Strata Management",
    "wof:placetype":"venue"
},
  "geometry": {"coordinates":[151.20933532699999,-33.9069137573],"type":"Point"}
}