{
  "type": "Feature",
  "properties": {
    "addr:full":"PO Box 586 Everton Park QLD 4053",
    "addr:postcode":"4053",
    "iso:country":"AU",
    "sg:address":"PO Box 586",
    "sg:city":"Everton Park",
    "sg:classifiers":[
        {
            "category":"Food & Beverages",
            "subcategory":"Specialty",
            "type":"Retail Goods"
        }
    ],
    "sg:phone":"+61 7 3311 4693",
    "sg:postcode":"4053",
    "sg:province":"QLD",
    "sg:tags":[
        "delicacy"
    ],
    "wof:name":"Kaffir Gourmet Shop On Line",
    "wof:placetype":"venue"
},
  "geometry": {"coordinates":[152.98692321799999,-27.3994598389],"type":"Point"}
}