{
  "type": "Feature",
  "properties": {
    "iso:country":"AU",
    "sg:address":"113 Galvin St",
    "sg:city":"South Launceston",
    "sg:classifiers":[
        {
            "category":"Food & Beverages",
            "subcategory":"Fruits & Vegetables",
            "type":"Retail Goods"
        }
    ],
    "sg:phone":"+61 3 6344 4433",
    "sg:postcode":"7249",
    "sg:province":"TAS",
    "sg:tags":[
        "wholesale"
    ],
    "wof:name":"Freshline Marketing",
    "wof:placetype":"venue"
},
  "geometry": {"coordinates":[147.142700195,-41.4500846863],"type":"Point"}
}