{
  "type": "Feature",
  "properties": {
    "addr:full":"3 Valli Pl Bendigo VIC 3550",
    "addr:housenumber":"3",
    "addr:postcode":"3550",
    "addr:street":"Valli Pl",
    "iso:country":"AU",
    "sg:address":"3 Valli Pl",
    "sg:city":"Bendigo",
    "sg:classifiers":[
        {
            "category":"Building & Trades",
            "subcategory":"Construction",
            "type":"Services"
        }
    ],
    "sg:phone":"+61 419 515 399",
    "sg:postcode":"3550",
    "sg:province":"VIC",
    "sg:tags":[
        "welding"
    ],
    "wof:name":"Kris McCarthy",
    "wof:placetype":"venue"
},
  "geometry": {"coordinates":[144.30099487300001,-36.751083374],"type":"Point"}
}