{
  "type": "Feature",
  "properties": {
    "addr:full":"258 Keilor Rd Essendon North VIC 3041",
    "addr:housenumber":"258",
    "addr:postcode":"3041",
    "addr:street":"Keilor Rd",
    "iso:country":"AU",
    "sg:address":"258 Keilor Rd",
    "sg:city":"Essendon North",
    "sg:classifiers":[
        {
            "category":"Health Services",
            "subcategory":"Dentist",
            "type":"Services"
        }
    ],
    "sg:phone":"+61 3 9379 8314",
    "sg:postcode":"3041",
    "sg:province":"VIC",
    "wof:name":"Gardner-Berry Dale Dr",
    "wof:placetype":"venue"
},
  "geometry": {"coordinates":[144.89695739699999,-37.7389640808],"type":"Point"}
}