{
  "type": "Feature",
  "properties": {
    "addr:full":"471 Vulture St East Brisbane QLD 4169",
    "addr:housenumber":"471",
    "addr:postcode":"4169",
    "addr:street":"Vulture St",
    "iso:country":"AU",
    "sg:address":"471 Vulture St",
    "sg:city":"East Brisbane",
    "sg:classifiers":[
        {
            "category":"Communications",
            "subcategory":"Film & Video Production",
            "type":"Services"
        }
    ],
    "sg:phone":"+61 7 3895 8418",
    "sg:postcode":"4169",
    "sg:province":"QLD",
    "sg:tags":[
        "television",
        "system",
        "circuit",
        "closed"
    ],
    "wof:name":"Veelock Pty Ltd",
    "wof:placetype":"venue"
},
  "geometry": {"coordinates":[153.04164123499999,-27.4855136871],"type":"Point"}
}