{
  "type": "Feature",
  "properties": {
    "addr:full":"115 Highbury Rd Burwood VIC 3125",
    "addr:housenumber":"115",
    "addr:postcode":"3125",
    "addr:street":"Highbury Rd",
    "iso:country":"AU",
    "sg:address":"115 Highbury Rd",
    "sg:city":"Burwood",
    "sg:classifiers":[
        {
            "category":"Arts & Performance",
            "subcategory":"Art Gallery",
            "type":"Entertainment"
        }
    ],
    "sg:phone":"+61 3 9888 8225",
    "sg:postcode":"3125",
    "sg:province":"VIC",
    "wof:name":"Creative Art Conservation",
    "wof:placetype":"venue"
},
  "geometry": {"coordinates":[145.10682678200001,-37.8545417786],"type":"Point"}
}