{
  "type": "Feature",
  "properties": {
    "addr:full":"Shop 3088A Westfield Shopping Cntr Parramatta NSW 2150",
    "addr:housenumber":"3088a",
    "addr:postcode":"2150",
    "addr:street":"Westfield Shopping Cntr",
    "iso:country":"AU",
    "sg:address":"Shop 3088A Westfield Shopping Cntr",
    "sg:city":"Parramatta",
    "sg:classifiers":[
        {
            "category":"Banks & Credit Unions",
            "subcategory":"Bureau De Change",
            "type":"Services"
        }
    ],
    "sg:phone":"+61 2 9891 6244",
    "sg:postcode":"2150",
    "sg:province":"NSW",
    "sg:tags":[
        "currency",
        "exchange",
        "foreign"
    ],
    "wof:name":"UAE Exchange",
    "wof:placetype":"venue"
},
  "geometry": {"coordinates":[151.00668335,-33.81483078],"type":"Point"}
}