{
  "type": "Feature",
  "properties": {
    "addr:full":"39 Murray St Tanunda SA 5352",
    "addr:housenumber":"39",
    "addr:postcode":"5352",
    "addr:street":"Murray St",
    "iso:country":"AU",
    "sg:address":"39 Murray St",
    "sg:city":"Tanunda",
    "sg:classifiers":[
        {
            "category":"Banks & Credit Unions",
            "subcategory":"Bureau De Change",
            "type":"Services"
        }
    ],
    "sg:phone":"+61 8 8563 0402",
    "sg:postcode":"5352",
    "sg:province":"SA",
    "sg:tags":[
        "motorised",
        "scooter"
    ],
    "wof:name":"Strength Motorcycles Pty Ltd",
    "wof:placetype":"venue"
},
  "geometry": {"coordinates":[138.96934509299999,-34.5168380737],"type":"Point"}
}