{
  "type": "Feature",
  "properties": {
    "addr:full":"6a Diggers Drv Tanilba Bay NSW 2319",
    "addr:postcode":"2319",
    "addr:street":"Diggers Drv",
    "iso:country":"AU",
    "sg:address":"6a Diggers Drv",
    "sg:city":"Tanilba Bay",
    "sg:classifiers":[
        {
            "category":"Utilities",
            "subcategory":"Electric",
            "type":"Services"
        }
    ],
    "sg:phone":"+61 408 493 605",
    "sg:postcode":"2319",
    "sg:province":"NSW",
    "sg:tags":[
        "electrical",
        "contractor"
    ],
    "wof:name":"Tanilba Bay Electrical Services",
    "wof:placetype":"venue"
},
  "geometry": {"coordinates":[151.99852000000001,-32.728168],"type":"Point"}
}