{
  "type": "Feature",
  "properties": {
    "addr:full":"2 Irene Pl Beldon WA 6027",
    "addr:housenumber":"2",
    "addr:postcode":"6027",
    "addr:street":"Irene Pl",
    "iso:country":"AU",
    "sg:address":"2 Irene Pl",
    "sg:city":"Beldon",
    "sg:classifiers":[
        {
            "category":"Utilities",
            "subcategory":"Electric",
            "type":"Services"
        }
    ],
    "sg:phone":"+61 411 697 930",
    "sg:postcode":"6027",
    "sg:province":"WA",
    "sg:tags":[
        "electrical",
        "contractor"
    ],
    "wof:name":"Challenge Electrical Services",
    "wof:placetype":"venue"
},
  "geometry": {"coordinates":[115.764198303,-31.7771492004],"type":"Point"}
}