{
  "type": "Feature",
  "properties": {
    "addr:full":"56b Gormanston Rd Moonah TAS 7009",
    "addr:housenumber":"56b",
    "addr:postcode":"7009",
    "addr:street":"Gormanston Rd",
    "iso:country":"AU",
    "sg:address":"56b Gormanston Rd",
    "sg:city":"Moonah",
    "sg:classifiers":[
        {
            "category":"Autos & Motor Vehicles",
            "subcategory":"Automobile Sales",
            "type":"Retail Goods"
        }
    ],
    "sg:phone":"+61 3 6273 8533",
    "sg:postcode":"7009",
    "sg:province":"TAS",
    "sg:tags":[
        "car",
        "used"
    ],
    "wof:name":"Tilford Trade Clearance Centre",
    "wof:placetype":"venue"
},
  "geometry": {"coordinates":[147.29835510300001,-42.8429298401],"type":"Point"}
}