{
  "type": "Feature",
  "properties": {
    "addr:full":"24 Heath St Lonsdale SA 5160",
    "addr:housenumber":"24",
    "addr:postcode":"5160",
    "addr:street":"Heath St",
    "iso:country":"AU",
    "sg:address":"24 Heath St",
    "sg:city":"Lonsdale",
    "sg:classifiers":[
        {
            "category":"Professional",
            "subcategory":"Engineering",
            "type":"Services"
        }
    ],
    "sg:phone":"+61 8 8326 3155",
    "sg:postcode":"5160",
    "sg:province":"SA",
    "sg:tags":[
        "engineer"
    ],
    "wof:name":"Wellsun Engineering Pty Ltd",
    "wof:placetype":"venue"
},
  "geometry": {"coordinates":[138.49827575699999,-35.1104011536],"type":"Point"}
}