{
  "type": "Feature",
  "properties": {
    "iso:country":"AU",
    "sg:address":"185 River St",
    "sg:city":"Ballina",
    "sg:classifiers":[
        {
            "category":"Sports & Exercise",
            "subcategory":"Gym",
            "type":"Entertainment"
        }
    ],
    "sg:phone":"+61 2 6686 9010",
    "sg:postcode":"2478",
    "sg:province":"NSW",
    "sg:tags":[
        "health",
        "fitness"
    ],
    "wof:name":"Intershape Ladies Exercise Studio",
    "wof:placetype":"venue"
},
  "geometry": {"coordinates":[153.55877685600001,-28.8696556091],"type":"Point"}
}