{
  "type": "Feature",
  "properties": {
    "addr:full":"Unit 7/ 72 Percival Rd Smithfield NSW 2164",
    "addr:housenumber":"72",
    "addr:postcode":"2164",
    "addr:street":"Percival Rd",
    "iso:country":"AU",
    "sg:address":"Unit 7/ 72 Percival Rd",
    "sg:city":"Smithfield",
    "sg:classifiers":[
        {
            "category":"Autos & Motor Vehicles",
            "subcategory":"Boat Sales",
            "type":"Retail Goods"
        }
    ],
    "sg:phone":"+61 2 9729 0040",
    "sg:postcode":"2164",
    "sg:province":"NSW",
    "sg:tags":[
        "yacht"
    ],
    "wof:name":"Projet Ski Marine",
    "wof:placetype":"venue"
},
  "geometry": {"coordinates":[150.95028686500001,-33.8412094116],"type":"Point"}
}