{
  "type": "Feature",
  "properties": {
    "addr:full":"14 Henderson St Waikerie SA 5330",
    "addr:housenumber":"14",
    "addr:postcode":"5330",
    "addr:street":"Henderson St",
    "iso:country":"AU",
    "sg:address":"14 Henderson St",
    "sg:city":"Waikerie",
    "sg:classifiers":[
        {
            "category":"Building & Trades",
            "subcategory":"Construction",
            "type":"Services"
        }
    ],
    "sg:phone":"+61 8 8541 3587",
    "sg:postcode":"5330",
    "sg:province":"SA",
    "sg:tags":[
        "renovation",
        "alterations",
        "extension",
        "contractor"
    ],
    "wof:name":"Waikerie Building Services",
    "wof:placetype":"venue"
},
  "geometry": {"coordinates":[139.98394775400001,-34.1782341003],"type":"Point"}
}