{
  "type": "Feature",
  "properties": {
    "addr:full":"45- 47 Rawson St Epping NSW 2121",
    "addr:housenumber":"47",
    "addr:postcode":"2121",
    "addr:street":"Rawson St",
    "iso:country":"AU",
    "sg:address":"45- 47 Rawson St",
    "sg:city":"Epping",
    "sg:classifiers":[
        {
            "category":"Retail",
            "subcategory":"Event Space",
            "type":"Services"
        }
    ],
    "sg:phone":"+61 2 9876 4357",
    "sg:postcode":"2121",
    "sg:province":"NSW",
    "sg:tags":[
        "venue",
        "reception",
        "wedding"
    ],
    "wof:name":"The Epping Club",
    "wof:placetype":"venue"
},
  "geometry": {"coordinates":[151.08076477,-33.7732124329],"type":"Point"}
}