{
  "type": "Feature",
  "properties": {
    "addr:full":"41 Russ Layton Drv Emerald QLD 4720",
    "addr:housenumber":"41",
    "addr:postcode":"4720",
    "addr:street":"Russ Layton Drv",
    "iso:country":"AU",
    "sg:address":"41 Russ Layton Drv",
    "sg:city":"Emerald",
    "sg:classifiers":[
        {
            "category":"Building & Trades",
            "subcategory":"Construction",
            "type":"Services"
        }
    ],
    "sg:phone":"+61 7 4982 3108",
    "sg:postcode":"4720",
    "sg:province":"QLD",
    "sg:tags":[
        "concrete",
        "paving"
    ],
    "wof:name":"Bid-Lo Concretors",
    "wof:placetype":"venue"
},
  "geometry": {"coordinates":[148.1474,-23.534527],"type":"Point"}
}