{
  "type": "Feature",
  "properties": {
    "iso:country":"AU",
    "sg:address":"Shop 12 Honour Ave",
    "sg:city":"Wyndham Vale",
    "sg:classifiers":[
        {
            "category":"Food & Beverages",
            "subcategory":"Liquor & Beverages",
            "type":"Retail Goods"
        }
    ],
    "sg:phone":"+61 3 9974 0222",
    "sg:postcode":"3024",
    "sg:province":"VIC",
    "sg:tags":[
        "store"
    ],
    "wof:name":"Wyndham Vale Cellars",
    "wof:placetype":"venue"
},
  "geometry": {"coordinates":[144.624619,-37.891167],"type":"Point"}
}