{
  "type": "Feature",
  "properties": {
    "addr:full":"57 Saints Rd Salisbury Plain SA 5109",
    "addr:housenumber":"57",
    "addr:postcode":"5109",
    "addr:street":"Saints Rd",
    "iso:country":"AU",
    "sg:address":"57 Saints Rd",
    "sg:city":"Salisbury Plain",
    "sg:classifiers":[
        {
            "category":"Autos & Motor Vehicles",
            "subcategory":"Auto Supplies",
            "type":"Retail Goods"
        }
    ],
    "sg:phone":"+61 8 8250 0191",
    "sg:postcode":"5109",
    "sg:province":"SA",
    "sg:tags":[
        "tyre"
    ],
    "wof:name":"Saints Tyre & Auto",
    "wof:placetype":"venue"
},
  "geometry": {"coordinates":[138.66510009800001,-34.7637443542],"type":"Point"}
}