{
  "type": "Feature",
  "properties": {
    "addr:full":"4 Taylor St Maroubra NSW 2035",
    "addr:housenumber":"4",
    "addr:postcode":"2035",
    "addr:street":"Taylor St",
    "iso:country":"AU",
    "sg:address":"4 Taylor St",
    "sg:city":"Maroubra",
    "sg:classifiers":[
        {
            "category":"Shopping",
            "subcategory":"Computers & Home Electronics",
            "type":"Retail Goods"
        }
    ],
    "sg:phone":"+61 2 9349 7309",
    "sg:postcode":"2035",
    "sg:province":"NSW",
    "sg:tags":[
        "hardware",
        "equipment"
    ],
    "wof:name":"QPID Technology Pty Ltd",
    "wof:placetype":"venue"
},
  "geometry": {"coordinates":[151.230300903,-33.9446105957],"type":"Point"}
}