{
  "type": "Feature",
  "properties": {
    "addr:full":"Unit 2/ 25 Industrial Rd Unanderra NSW 2526",
    "addr:housenumber":"25",
    "addr:postcode":"2526",
    "addr:street":"Industrial Rd",
    "iso:country":"AU",
    "sg:address":"Unit 2/ 25 Industrial Rd",
    "sg:city":"Unanderra",
    "sg:classifiers":[
        {
            "category":"Utilities",
            "type":"Services"
        }
    ],
    "sg:phone":"+61 2 4272 7344",
    "sg:postcode":"2526",
    "sg:province":"NSW",
    "sg:tags":[
        "refrigeration",
        "industrial",
        "commercial",
        "retail"
    ],
    "wof:name":"ADL Services Pty Ltd",
    "wof:placetype":"venue"
},
  "geometry": {"coordinates":[150.85737609899999,-34.4643745422],"type":"Point"}
}