{
  "type": "Feature",
  "properties": {
    "addr:full":"239 Barwon Heads Rd Marshall VIC 3216",
    "addr:housenumber":"239",
    "addr:postcode":"3216",
    "addr:street":"Barwon Heads Rd",
    "iso:country":"AU",
    "sg:address":"239 Barwon Heads Rd",
    "sg:city":"Marshall",
    "sg:classifiers":[
        {
            "category":"Personal",
            "subcategory":"Beauty Salon",
            "type":"Services"
        }
    ],
    "sg:phone":"+61 3 5244 5367",
    "sg:postcode":"3216",
    "sg:province":"VIC",
    "wof:name":"house of toft",
    "wof:placetype":"venue"
},
  "geometry": {"coordinates":[144.355926514,-38.1878395081],"type":"Point"}
}