{
  "type": "Feature",
  "properties": {
    "iso:country":"AU",
    "sg:address":"59 Carefree Rd",
    "sg:city":"Picton",
    "sg:classifiers":[
        {
            "category":"Banks & Credit Unions",
            "subcategory":"Financial Services",
            "type":"Services"
        }
    ],
    "sg:phone":"+61 2 9970 6861",
    "sg:postcode":"2571",
    "sg:province":"NSW",
    "sg:tags":[
        "loan",
        "finance",
        "mortgage"
    ],
    "wof:name":"Choice Home Loans",
    "wof:placetype":"venue"
},
  "geometry": {"coordinates":[150.611495972,-34.1690788269],"type":"Point"}
}