{
  "type": "Feature",
  "properties": {
    "iso:country":"AU",
    "sg:address":"18 Douglas Park Drv",
    "sg:city":"Wilton",
    "sg:classifiers":[
        {
            "category":"Education",
            "subcategory":"Kindergarten",
            "type":"Public Place"
        }
    ],
    "sg:phone":"+61 2 4630 8106",
    "sg:postcode":"2571",
    "sg:province":"NSW",
    "sg:tags":[
        "pre-schools"
    ],
    "wof:name":"Cath's Kindy",
    "wof:placetype":"venue"
},
  "geometry": {"coordinates":[150.72950744600001,-34.2359542847],"type":"Point"}
}