{
  "type": "Feature",
  "properties": {
    "iso:country":"AU",
    "sg:address":"22 Jetty Ave",
    "sg:city":"Charmhaven",
    "sg:classifiers":[
        {
            "category":"Manufacturing",
            "subcategory":"Chemicals & Compounds",
            "type":"Manufacturing & Wholesale Goods"
        }
    ],
    "sg:phone":"+61 2 4393 5244",
    "sg:postcode":"2263",
    "sg:province":"NSW",
    "sg:tags":[
        "oil",
        "recovery",
        "dispersal",
        "spill"
    ],
    "wof:name":"Colnar Distribution",
    "wof:placetype":"venue"
},
  "geometry": {"coordinates":[151.505234,-33.233929],"type":"Point"}
}