{
  "type": "Feature",
  "properties": {
    "iso:country":"AU",
    "sg:address":"PO Box 1270",
    "sg:city":"Innisfail",
    "sg:classifiers":[
        {
            "category":"Building & Trades",
            "subcategory":"Construction",
            "type":"Services"
        }
    ],
    "sg:phone":"+61 7 4065 4783",
    "sg:postcode":"4860",
    "sg:province":"QLD",
    "sg:tags":[
        "earth",
        "excavating",
        "moving",
        "contractor"
    ],
    "wof:name":"Alumno Pty Ltd",
    "wof:placetype":"venue"
},
  "geometry": {"coordinates":[146.028244019,-17.5247402191],"type":"Point"}
}