{
  "type": "Feature",
  "properties": {
    "iso:country":"AU",
    "sg:address":"170 Upper Dawson Rd",
    "sg:city":"Rockhampton",
    "sg:classifiers":[
        {
            "category":"Education",
            "subcategory":"School",
            "type":"Public Place"
        }
    ],
    "sg:phone":"+61 7 4927 5994",
    "sg:postcode":"4700",
    "sg:province":"QLD",
    "wof:name":"St Peter's School",
    "wof:placetype":"venue"
},
  "geometry": {"coordinates":[150.50091552699999,-23.3998184204],"type":"Point"}
}