{
  "type": "Feature",
  "properties": {
    "addr:full":"PO Box 9213 Wyee NSW 2259",
    "addr:postcode":"2259",
    "iso:country":"AU",
    "sg:address":"PO Box 9213",
    "sg:city":"Wyee",
    "sg:classifiers":[
        {
            "category":"Commercial Area",
            "type":"Public Place"
        }
    ],
    "sg:phone":"+61 2 4973 6044",
    "sg:postcode":"2259",
    "sg:province":"NSW",
    "sg:tags":[
        "heavy",
        "carrier"
    ],
    "wof:name":"Toveety Pty Ltd",
    "wof:placetype":"venue"
},
  "geometry": {"coordinates":[151.48171997099999,-33.1759185791],"type":"Point"}
}