{
  "type": "Feature",
  "properties": {
    "addr:full":"1/ 101 Great Western Hwy Emu Plains NSW 2750",
    "addr:housenumber":"/ 101",
    "addr:postcode":"2750",
    "addr:street":"Great Western Hwy",
    "iso:country":"AU",
    "sg:address":"1/ 101 Great Western Hwy",
    "sg:city":"Emu Plains",
    "sg:classifiers":[
        {
            "category":"Health Services",
            "subcategory":"Doctor",
            "type":"Services"
        }
    ],
    "sg:phone":"+61 2 4735 6239",
    "sg:postcode":"2750",
    "sg:province":"NSW",
    "sg:tags":[
        "medical",
        "practitioner"
    ],
    "wof:name":"Southern Cross Medical Centre",
    "wof:placetype":"venue"
},
  "geometry": {"coordinates":[150.673171997,-33.7466049194],"type":"Point"}
}