{
  "type": "Feature",
  "properties": {
    "iso:country":"AU",
    "sg:address":"39 Torrens Rd",
    "sg:city":"Riverton",
    "sg:classifiers":[
        {
            "category":"Deli",
            "type":"Food & Drink"
        }
    ],
    "sg:phone":"+61 8 8847 2072",
    "sg:postcode":"5412",
    "sg:province":"SA",
    "sg:tags":[
        "delicatessen"
    ],
    "wof:name":"Riverton Deli",
    "wof:placetype":"venue"
},
  "geometry": {"coordinates":[138.74729919399999,-34.1593856812],"type":"Point"}
}