{
  "type": "Feature",
  "properties": {
    "addr:full":"1 Langford Ave Mitcham VIC 3132",
    "addr:housenumber":"1",
    "addr:postcode":"3132",
    "addr:street":"Langford Ave",
    "iso:country":"AU",
    "sg:address":"1 Langford Ave",
    "sg:city":"Mitcham",
    "sg:classifiers":[
        {
            "category":"Professional",
            "subcategory":"Art Services",
            "type":"Services"
        }
    ],
    "sg:phone":"+61 3 9874 3962",
    "sg:postcode":"3132",
    "sg:province":"VIC",
    "sg:tags":[
        "graphic",
        "designer"
    ],
    "wof:name":"Glenn Ball Designs Pty Ltd",
    "wof:placetype":"venue"
},
  "geometry": {"coordinates":[145.20083618199999,-37.8290481567],"type":"Point"}
}