{
  "type": "Feature",
  "properties": {
    "addr:full":"89 Arcadia Ave Gymea Bay NSW 2227",
    "addr:housenumber":"89",
    "addr:postcode":"2227",
    "addr:street":"Arcadia Ave",
    "iso:country":"AU",
    "sg:address":"89 Arcadia Ave",
    "sg:city":"Gymea Bay",
    "sg:classifiers":[
        {
            "category":"Building & Trades",
            "subcategory":"Construction",
            "type":"Services"
        }
    ],
    "sg:phone":"+61 2 9525 2135",
    "sg:postcode":"2227",
    "sg:province":"NSW",
    "sg:tags":[
        "joiner",
        "carpenter"
    ],
    "wof:name":"MBK CARPENTRY & MAINTENANCE P/L",
    "wof:placetype":"venue"
},
  "geometry": {"coordinates":[151.07960510300001,-34.0528335571],"type":"Point"}
}