{
  "type": "Feature",
  "properties": {
    "addr:full":"139 Beach Rd Christies Beach SA 5165",
    "addr:housenumber":"139",
    "addr:postcode":"5165",
    "addr:street":"Beach Rd",
    "iso:country":"AU",
    "sg:address":"139 Beach Rd",
    "sg:city":"Christies Beach",
    "sg:classifiers":[
        {
            "category":"Government",
            "subcategory":"Fire Station",
            "type":"Public Place"
        }
    ],
    "sg:phone":"+61 8 8326 3921",
    "sg:postcode":"5165",
    "sg:province":"SA",
    "sg:tags":[
        "spring",
        "shock",
        "absorbers",
        "suspension"
    ],
    "wof:name":"Suspension Professionals",
    "wof:placetype":"venue"
},
  "geometry": {"coordinates":[138.48515319800001,-35.1386032104],"type":"Point"}
}