{
  "type": "Feature",
  "properties": {
    "addr:full":"13 Eccles St Ermington NSW 2115",
    "addr:housenumber":"13",
    "addr:postcode":"2115",
    "addr:street":"Eccles St",
    "iso:country":"AU",
    "sg:address":"13 Eccles St",
    "sg:city":"Ermington",
    "sg:classifiers":[
        {
            "category":"Professional",
            "subcategory":"Computer Services",
            "type":"Services"
        }
    ],
    "sg:phone":"+61 500 522 779",
    "sg:postcode":"2115",
    "sg:province":"NSW",
    "sg:tags":[
        "consultant",
        "system"
    ],
    "wof:name":"BC Database",
    "wof:placetype":"venue"
},
  "geometry": {"coordinates":[151.05564880399999,-33.8090286255],"type":"Point"}
}