{
  "type": "Feature",
  "properties": {
    "iso:country":"AU",
    "sg:address":"168-172 Brisbane St",
    "sg:city":"Dubbo",
    "sg:classifiers":[
        {
            "category":"Health Services",
            "subcategory":"Doctor",
            "type":"Services"
        }
    ],
    "sg:phone":"+61 2 6841 0750",
    "sg:postcode":"2830",
    "sg:province":"NSW",
    "sg:tags":[
        "medical",
        "practitioner"
    ],
    "wof:name":"Dubbo Nuclear Medicine & Echocardiography",
    "wof:placetype":"venue"
},
  "geometry": {"coordinates":[148.603683472,-32.2488136292],"type":"Point"}
}