{
  "type": "Feature",
  "properties": {
    "iso:country":"AU",
    "sg:address":"Lipson St",
    "sg:city":"Port Adelaide",
    "sg:classifiers":[
        {
            "category":"Retail",
            "subcategory":"Event Space",
            "type":"Services"
        }
    ],
    "sg:phone":"+61 8 8341 1690",
    "sg:postcode":"5015",
    "sg:province":"SA",
    "sg:tags":[
        "function",
        "organiser"
    ],
    "wof:name":"National Railway Museum",
    "wof:placetype":"venue"
},
  "geometry": {"coordinates":[138.50633239699999,-34.8434638977],"type":"Point"}
}