{
  "type": "Feature",
  "properties": {
    "addr:full":"2/4 Dale St Mt Martha VIC 3934",
    "addr:housenumber":"/ 4",
    "addr:postcode":"3934",
    "addr:street":"Dale St Mt Martha",
    "iso:country":"AU",
    "sg:address":"2/4 Dale St",
    "sg:city":"Mt Martha",
    "sg:classifiers":[
        {
            "category":"Building & Trades",
            "subcategory":"Construction",
            "type":"Services"
        }
    ],
    "sg:phone":"+61 431 824 435",
    "sg:postcode":"3934",
    "sg:province":"VIC",
    "sg:tags":[
        "fencing",
        "contractor"
    ],
    "wof:name":"Freeman Fencing",
    "wof:placetype":"venue"
},
  "geometry": {"coordinates":[145.05711364699999,-38.2513618469],"type":"Point"}
}