{
  "type": "Feature",
  "properties": {
    "addr:full":"32 Edward St Wagga Wagga NSW 2650",
    "addr:housenumber":"32",
    "addr:postcode":"2650",
    "addr:street":"Edward St",
    "iso:country":"AU",
    "sg:address":"32 Edward St",
    "sg:city":"Wagga Wagga",
    "sg:classifiers":[
        {
            "category":"Building & Trades",
            "subcategory":"Construction",
            "type":"Services"
        }
    ],
    "sg:phone":"+61 13 63 60",
    "sg:postcode":"2650",
    "sg:province":"NSW",
    "sg:tags":[
        "window",
        "tinting"
    ],
    "wof:name":"Tint.a.Car",
    "wof:placetype":"venue"
},
  "geometry": {"coordinates":[147.375656128,-35.1198692322],"type":"Point"}
}