{
  "type": "Feature",
  "properties": {
    "iso:country":"AU",
    "sg:address":"18 McCulloch St",
    "sg:city":"Mackay",
    "sg:classifiers":[
        {
            "category":"Banks & Credit Unions",
            "subcategory":"Investment Brokerage",
            "type":"Services"
        }
    ],
    "sg:phone":"+61 7 4953 4623",
    "sg:postcode":"4740",
    "sg:province":"QLD",
    "sg:tags":[
        "radiator",
        "motor"
    ],
    "wof:name":"North Mackay Radiators",
    "wof:placetype":"venue"
},
  "geometry": {"coordinates":[149.195618,-21.11891],"type":"Point"}
}