{
  "type": "Feature",
  "properties": {
    "addr:full":"Stuart St Newport NSW 2106",
    "addr:postcode":"2106",
    "addr:street":"Stuart St",
    "iso:country":"AU",
    "sg:address":"Stuart St",
    "sg:city":"Newport",
    "sg:classifiers":[
        {
            "category":"Education",
            "subcategory":"School",
            "type":"Public Place"
        }
    ],
    "sg:phone":"+61 2 9999 3588",
    "sg:postcode":"2106",
    "sg:province":"NSW",
    "sg:tags":[
        "state",
        "-",
        "nsw"
    ],
    "wof:name":"Newport Public School",
    "wof:placetype":"venue"
},
  "geometry": {"coordinates":[151.312744141,-33.6591033936],"type":"Point"}
}