{
  "type": "Feature",
  "properties": {
    "addr:full":"95 Victoria St Bunbury WA 6230",
    "addr:housenumber":"95",
    "addr:postcode":"6230",
    "addr:street":"Victoria St",
    "iso:country":"AU",
    "sg:address":"95 Victoria St",
    "sg:city":"Bunbury",
    "sg:classifiers":[
        {
            "category":"Cafe",
            "type":"Food & Drink"
        }
    ],
    "sg:phone":"+61 8 9791 4064",
    "sg:postcode":"6230",
    "sg:province":"WA",
    "wof:name":"Gelare Ice Cream Cafe",
    "wof:placetype":"venue"
},
  "geometry": {"coordinates":[115.63681800000001,-33.324024],"type":"Point"}
}