{
  "type": "Feature",
  "properties": {
    "iso:country":"AU",
    "sg:address":"27 Andrew St",
    "sg:city":"Ringwood",
    "sg:classifiers":[
        {
            "category":"Building & Trades",
            "subcategory":"Construction",
            "type":"Services"
        }
    ],
    "sg:phone":"+61 3 9870 3708",
    "sg:postcode":"3134",
    "sg:province":"VIC",
    "sg:tags":[
        "renovation",
        "alterations",
        "extension",
        "contractor"
    ],
    "wof:name":"Exelle Home Improvements",
    "wof:placetype":"venue"
},
  "geometry": {"coordinates":[145.22215270999999,-37.8093605042],"type":"Point"}
}