{
  "type": "Feature",
  "properties": {
    "iso:country":"AU",
    "sg:address":"74b The Entrance Rd",
    "sg:city":"The Entrance",
    "sg:classifiers":[
        {
            "category":"Personal",
            "subcategory":"Tattoo Parlor",
            "type":"Services"
        }
    ],
    "sg:phone":"+61 2 4332 5002",
    "sg:postcode":"2261",
    "sg:province":"NSW",
    "sg:tags":[
        "tattooing"
    ],
    "wof:name":"Skin Circus Tattooing & Body Piercing",
    "wof:placetype":"venue"
},
  "geometry": {"coordinates":[151.49818400000001,-33.341358],"type":"Point"}
}