{
  "type": "Feature",
  "properties": {
    "iso:country":"AU",
    "sg:address":"103 Raubers Rd",
    "sg:city":"Northgate",
    "sg:classifiers":[
        {
            "category":"Manufacturing",
            "subcategory":"Metals",
            "type":"Manufacturing & Wholesale Goods"
        }
    ],
    "sg:phone":"+61 7 3622 9505",
    "sg:postcode":"4013",
    "sg:province":"QLD",
    "sg:tags":[
        "wholesaler",
        "aluminium",
        "mfrs"
    ],
    "wof:name":"Smorgon Steel",
    "wof:placetype":"venue"
},
  "geometry": {"coordinates":[153.085494995,-27.3934459686],"type":"Point"}
}