{
  "type": "Feature",
  "properties": {
    "iso:country":"AU",
    "sg:address":"70 Don Rd",
    "sg:city":"Devonport",
    "sg:classifiers":[
        {
            "category":"Fast Food",
            "type":"Food & Drink"
        }
    ],
    "sg:phone":"+61 3 6424 1032",
    "sg:postcode":"7310",
    "sg:province":"TAS",
    "sg:tags":[
        "away",
        "take"
    ],
    "wof:name":"Belly's Takeaway",
    "wof:placetype":"venue"
},
  "geometry": {"coordinates":[146.33206176799999,-41.1808433533],"type":"Point"}
}