{
  "type": "Feature",
  "properties": {
    "addr:full":"200 Sheepways Rd Kongwak VIC 3951",
    "addr:housenumber":"200",
    "addr:postcode":"3951",
    "addr:street":"Sheepways Rd",
    "iso:country":"AU",
    "sg:address":"200 Sheepways Rd",
    "sg:city":"Kongwak",
    "sg:classifiers":[
        {
            "category":"Farming",
            "subcategory":"Farm",
            "type":"Manufacturing & Wholesale Goods"
        }
    ],
    "sg:phone":"+61 3 5657 4255",
    "sg:postcode":"3951",
    "sg:province":"VIC",
    "sg:tags":[
        "farmer"
    ],
    "wof:name":"Brown Bill & Joy",
    "wof:placetype":"venue"
},
  "geometry": {"coordinates":[145.67713928200001,-38.4888954163],"type":"Point"}
}