{
  "type": "Feature",
  "properties": {
    "addr:full":"11 Yakaloo Crs Forresters Beach NSW 2260",
    "addr:housenumber":"11",
    "addr:postcode":"2260",
    "addr:street":"Yakaloo Crs",
    "iso:country":"AU",
    "sg:address":"11 Yakaloo Crs",
    "sg:city":"Forresters Beach",
    "sg:classifiers":[
        {
            "category":"Health Services",
            "subcategory":"Health Practitioner",
            "type":"Services"
        }
    ],
    "sg:phone":"+61 409 916 467",
    "sg:postcode":"2260",
    "sg:province":"NSW",
    "sg:tags":[
        "physiotherapist"
    ],
    "wof:name":"Rodney Ingram Mobile Physiotherapy",
    "wof:placetype":"venue"
},
  "geometry": {"coordinates":[151.46456900000001,-33.406319],"type":"Point"}
}