{
  "type": "Feature",
  "properties": {
    "iso:country":"AU",
    "sg:address":"1/ 499 St. Kilda Rd",
    "sg:city":"Melbourne",
    "sg:classifiers":[
        {
            "category":"Professional",
            "subcategory":"Management & Consulting",
            "type":"Services"
        }
    ],
    "sg:phone":"+61 3 9861 4066",
    "sg:postcode":"3004",
    "sg:province":"VIC",
    "sg:tags":[
        "consultant",
        "industrial",
        "relation"
    ],
    "wof:name":"Michael P Rahilly",
    "wof:placetype":"venue"
},
  "geometry": {"coordinates":[144.97836303700001,-37.8428039551],"type":"Point"}
}