{
  "type": "Feature",
  "properties": {
    "iso:country":"AU",
    "sg:address":"2/ 23 Central Drv",
    "sg:city":"Andrews",
    "sg:classifiers":[
        {
            "category":"Communications",
            "subcategory":"Film & Video Production",
            "type":"Services"
        }
    ],
    "sg:phone":"+61 7 5593 6700",
    "sg:postcode":"4220",
    "sg:province":"QLD",
    "sg:tags":[
        "shutter",
        "window",
        "roller"
    ],
    "wof:name":"Aluminium Roller Shields",
    "wof:placetype":"venue"
},
  "geometry": {"coordinates":[153.424224853,-28.1057434082],"type":"Point"}
}