{
  "type": "Feature",
  "properties": {
    "iso:country":"AU",
    "sg:address":"11 Kennedy St",
    "sg:city":"Kingston",
    "sg:classifiers":[
        {
            "category":"Shopping",
            "subcategory":"Clothing, Apparel, & Fashions",
            "type":"Retail Goods"
        }
    ],
    "sg:phone":"+61 2 6232 6361",
    "sg:postcode":"2604",
    "sg:province":"ACT",
    "sg:tags":[
        "lady",
        "wear"
    ],
    "wof:name":"Bellissima On Kennedy",
    "wof:placetype":"venue"
},
  "geometry": {"coordinates":[149.140457153,-35.3162193298],"type":"Point"}
}