{
  "type": "Feature",
  "properties": {
    "iso:country":"AU",
    "sg:address":"50 Steere St",
    "sg:city":"Collie",
    "sg:classifiers":[
        {
            "category":"Retail",
            "subcategory":"Auto Repair",
            "type":"Services"
        }
    ],
    "sg:phone":"+61 8 9734 7704",
    "sg:postcode":"6225",
    "sg:province":"WA",
    "sg:tags":[
        "body",
        "motor",
        "trimmer"
    ],
    "wof:name":"Dashboard Exchange",
    "wof:placetype":"venue"
},
  "geometry": {"coordinates":[116.155418,-33.35815],"type":"Point"}
}