{
  "type": "Feature",
  "properties": {
    "iso:country":"AU",
    "sg:address":"7/ 58 Gerard St",
    "sg:city":"Cremorne",
    "sg:classifiers":[
        {
            "category":"Professional",
            "subcategory":"Art Services",
            "type":"Services"
        }
    ],
    "sg:phone":"+61 414 704 467",
    "sg:postcode":"2090",
    "sg:province":"NSW",
    "sg:tags":[
        "interior",
        "decorator"
    ],
    "wof:name":"Interiors Plus",
    "wof:placetype":"venue"
},
  "geometry": {"coordinates":[151.22862243599999,-33.8272018433],"type":"Point"}
}