{
  "type": "Feature",
  "properties": {
    "addr:full":"269 Pacific Hwy Artarmon NSW 2064",
    "addr:housenumber":"269",
    "addr:postcode":"2064",
    "addr:street":"Pacific Hwy",
    "iso:country":"AU",
    "sg:address":"269 Pacific Hwy",
    "sg:city":"Artarmon",
    "sg:classifiers":[
        {
            "category":"Shopping",
            "subcategory":"Mobile Phones",
            "type":"Retail Goods"
        }
    ],
    "sg:phone":"+61 2 9428 2200",
    "sg:postcode":"2064",
    "sg:province":"NSW",
    "sg:tags":[
        "telephone",
        "accessory"
    ],
    "wof:name":"Full Power Technology Pty Ltd",
    "wof:placetype":"venue"
},
  "geometry": {"coordinates":[151.183425903,-33.8187103271],"type":"Point"}
}