{
  "type": "Feature",
  "properties": {
    "addr:full":"434 Crown St West Wollongong NSW 2500",
    "addr:housenumber":"434",
    "addr:postcode":"2500",
    "addr:street":"Crown St West",
    "iso:country":"AU",
    "sg:address":"434 Crown St",
    "sg:city":"West Wollongong",
    "sg:classifiers":[
        {
            "category":"Retail",
            "subcategory":"Auto Repair",
            "type":"Services"
        }
    ],
    "sg:phone":"+61 2 4228 5955",
    "sg:postcode":"2500",
    "sg:province":"NSW",
    "sg:tags":[
        "repairer",
        "motor",
        "engineer"
    ],
    "wof:name":"BP West Wollongong S&G Auto Repairs",
    "wof:placetype":"venue"
},
  "geometry": {"coordinates":[150.87335200000001,-34.425156],"type":"Point"}
}