{
  "type": "Feature",
  "properties": {
    "addr:full":"64 Station St Wentworthville NSW 2145",
    "addr:housenumber":"64",
    "addr:postcode":"2145",
    "addr:street":"Station St",
    "iso:country":"AU",
    "sg:address":"64 Station St",
    "sg:city":"Wentworthville",
    "sg:classifiers":[
        {
            "category":"Communications",
            "subcategory":"Film & Video Production",
            "type":"Services"
        }
    ],
    "sg:phone":"+61 2 9636 5843",
    "sg:postcode":"2145",
    "sg:province":"NSW",
    "sg:tags":[
        "dvd",
        "library"
    ],
    "wof:name":"Video Ezy",
    "wof:placetype":"venue"
},
  "geometry": {"coordinates":[150.97201538100001,-33.8087005615],"type":"Point"}
}