{
  "type": "Feature",
  "properties": {
    "iso:country":"AU",
    "sg:address":"90 Ryland Rd",
    "sg:city":"Rapid Creek",
    "sg:classifiers":[
        {
            "category":"Professional",
            "subcategory":"Art Services",
            "type":"Services"
        }
    ],
    "sg:phone":"+61 8 8985 1888",
    "sg:postcode":"0810",
    "sg:province":"NT",
    "sg:tags":[
        "graphic",
        "designer"
    ],
    "wof:name":"Niblock Publishing",
    "wof:placetype":"venue"
},
  "geometry": {"coordinates":[130.86076355,-12.3847675323],"type":"Point"}
}