{
  "type": "Feature",
  "properties": {
    "iso:country":"AU",
    "sg:address":"Shp 1a/ 25 Curlewis St",
    "sg:city":"Bondi",
    "sg:classifiers":[
        {
            "category":"Health Services",
            "subcategory":"Health Practitioner",
            "type":"Services"
        }
    ],
    "sg:phone":"+61 2 9300 0111",
    "sg:postcode":"2026",
    "sg:province":"NSW",
    "sg:tags":[
        "pathologist",
        "speech"
    ],
    "wof:name":"Sydney Speech Pathology And Occupational Therapy",
    "wof:placetype":"venue"
},
  "geometry": {"coordinates":[151.26905822800001,-33.8856315613],"type":"Point"}
}