{
  "type": "Feature",
  "properties": {
    "addr:full":"32 Faithfull St Goulburn NSW 2580",
    "addr:housenumber":"32",
    "addr:postcode":"2580",
    "addr:street":"Faithfull St",
    "iso:country":"AU",
    "sg:address":"32 Faithfull St",
    "sg:city":"Goulburn",
    "sg:classifiers":[
        {
            "category":"Building & Trades",
            "subcategory":"Construction",
            "type":"Services"
        }
    ],
    "sg:phone":"+61 2 4821 4417",
    "sg:postcode":"2580",
    "sg:province":"NSW",
    "sg:tags":[
        "contractor"
    ],
    "wof:name":"Winterton Peter",
    "wof:placetype":"venue"
},
  "geometry": {"coordinates":[149.70623779300001,-34.7582817078],"type":"Point"}
}