{
  "type": "Feature",
  "properties": {
    "addr:full":"Cnr Christine Ave & Bermuda St Burleigh Waters QLD 4220",
    "addr:postcode":"4220",
    "addr:street":"Christine Ave & Bermuda St",
    "iso:country":"AU",
    "sg:address":"Cnr Christine Ave & Bermuda St",
    "sg:city":"Burleigh Waters",
    "sg:classifiers":[
        {
            "category":"Autos & Motor Vehicles",
            "subcategory":"Fuel & Gas Station",
            "type":"Retail Goods"
        }
    ],
    "sg:phone":"+61 7 5576 3622",
    "sg:postcode":"4220",
    "sg:province":"QLD",
    "wof:name":"Shell Select Burleigh Waters",
    "wof:placetype":"venue"
},
  "geometry": {"coordinates":[153.43406677199999,-28.0801677704],"type":"Point"}
}