{
  "type": "Feature",
  "properties": {
    "addr:full":"PO Box 2082 Claremont North WA 6010",
    "addr:postcode":"6010",
    "iso:country":"AU",
    "sg:address":"PO Box 2082",
    "sg:city":"Claremont North",
    "sg:classifiers":[
        {
            "category":"Banks & Credit Unions",
            "subcategory":"Financial Services",
            "type":"Services"
        }
    ],
    "sg:phone":"+61 8 9287 2526",
    "sg:postcode":"6010",
    "sg:province":"WA",
    "sg:tags":[
        "settlement",
        "nt",
        "agent",
        "wa"
    ],
    "wof:name":"Mt Claremont Settlements",
    "wof:placetype":"venue"
},
  "geometry": {"coordinates":[115.78241729699999,-31.9855003357],"type":"Point"}
}