{
  "type": "Feature",
  "properties": {
    "addr:full":"Tuggeranong Markets Athlon Drv Tuggeranong ACT 2900",
    "addr:postcode":"2900",
    "addr:street":"Athlon Drv",
    "iso:country":"AU",
    "sg:address":"Tuggeranong Markets Athlon Drv",
    "sg:city":"Tuggeranong",
    "sg:classifiers":[
        {
            "category":"Fast Food",
            "type":"Food & Drink"
        }
    ],
    "sg:phone":"+61 2 6293 2697",
    "sg:postcode":"2900",
    "sg:province":"ACT",
    "sg:tags":[
        "away",
        "take"
    ],
    "wof:name":"Viet Kitchen",
    "wof:placetype":"venue"
},
  "geometry": {"coordinates":[149.065795898,-35.4151611328],"type":"Point"}
}