{
  "type": "Feature",
  "properties": {
    "addr:full":"Unit 5, 221- 223 O&#039;Riordan Strs Mascot NSW 2020",
    "addr:housenumber":"221 223 o",
    "addr:postcode":"2020",
    "addr:street":"Riordan Strs",
    "iso:country":"AU",
    "sg:address":"Unit 5, 221- 223",
    "sg:city":"O&#039;Riordan Strs Mascot",
    "sg:classifiers":[
        {
            "category":"Professional",
            "subcategory":"Detective & Security Services",
            "type":"Services"
        }
    ],
    "sg:phone":"+61 2 8338 8599",
    "sg:postcode":"2020",
    "sg:province":"NSW",
    "sg:tags":[
        "consultant",
        "system"
    ],
    "wof:name":"All Night Security",
    "wof:placetype":"venue"
},
  "geometry": {"coordinates":[151.19451904300001,-33.9301681519],"type":"Point"}
}