{
  "type": "Feature",
  "properties": {
    "addr:full":"26 Parry St Charleville QLD 4470",
    "addr:housenumber":"26",
    "addr:postcode":"4470",
    "addr:street":"Parry St",
    "iso:country":"AU",
    "sg:address":"26 Parry St",
    "sg:city":"Charleville",
    "sg:classifiers":[
        {
            "category":"Home & Garden",
            "subcategory":"Carpets & Floor Coverings",
            "type":"Retail Goods"
        }
    ],
    "sg:phone":"+61 7 4654 7341",
    "sg:postcode":"4470",
    "sg:province":"QLD",
    "sg:tags":[
        "tile",
        "wall",
        "layer"
    ],
    "wof:name":"Charleville Constructions & Tiles",
    "wof:placetype":"venue"
},
  "geometry": {"coordinates":[146.24830627399999,-26.401763916],"type":"Point"}
}