{
  "type": "Feature",
  "properties": {
    "addr:full":"23 Nelson St Woolgoolga NSW 2456",
    "addr:housenumber":"23",
    "addr:postcode":"2456",
    "addr:street":"Nelson St",
    "iso:country":"AU",
    "sg:address":"23 Nelson St",
    "sg:city":"Woolgoolga",
    "sg:classifiers":[
        {
            "category":"Professional",
            "subcategory":"Management & Consulting",
            "type":"Services"
        }
    ],
    "sg:phone":"+61 410 335 135",
    "sg:postcode":"2456",
    "sg:province":"NSW",
    "sg:tags":[
        "project"
    ],
    "wof:name":"Zachary Morgan Edwards",
    "wof:placetype":"venue"
},
  "geometry": {"coordinates":[153.20152300000001,-30.11367],"type":"Point"}
}