{
  "type": "Feature",
  "properties": {
    "addr:full":"83- 87 Beenleigh Redland Bay Rd Loganholme QLD 4129",
    "addr:housenumber":"87",
    "addr:postcode":"4129",
    "addr:street":"Beenleigh Redland Bay Rd",
    "iso:country":"AU",
    "sg:address":"83- 87 Beenleigh Redland Bay Rd",
    "sg:city":"Loganholme",
    "sg:classifiers":[
        {
            "category":"Retail",
            "subcategory":"Repair Shop",
            "type":"Services"
        }
    ],
    "sg:phone":"+61 7 3806 2853",
    "sg:postcode":"4129",
    "sg:province":"QLD",
    "sg:tags":[
        "maintenance",
        "pool",
        "swimming"
    ],
    "wof:name":"Blakeway Mark",
    "wof:placetype":"venue"
},
  "geometry": {"coordinates":[153.19392395,-27.6710071564],"type":"Point"}
}