{
  "type": "Feature",
  "properties": {
    "iso:country":"AU",
    "sg:address":"2/ 3 Male St",
    "sg:city":"Brighton",
    "sg:classifiers":[
        {
            "category":"Banks & Credit Unions",
            "subcategory":"Financial Services",
            "type":"Services"
        }
    ],
    "sg:phone":"+61 3 9593 3280",
    "sg:postcode":"3186",
    "sg:province":"VIC",
    "sg:tags":[
        "planning"
    ],
    "wof:name":"Custodian Wealth Builders",
    "wof:placetype":"venue"
},
  "geometry": {"coordinates":[144.99588012699999,-37.9163322449],"type":"Point"}
}