{
  "type": "Feature",
  "properties": {
    "addr:full":"Shop 6, Village Walk 489-493 Toorak Rd Toorak VIC 3142",
    "addr:housenumber":"shop 6",
    "addr:postcode":"489-493;3142",
    "addr:street":"Village Walk;Toorak Rd",
    "iso:country":"AU",
    "sg:address":"Shop 6, Village Walk 489-493 Toorak Rd",
    "sg:city":"Toorak",
    "sg:classifiers":[
        {
            "category":"Health Services",
            "subcategory":"Optometrist",
            "type":"Services"
        }
    ],
    "sg:phone":"+61 3 9827 6256",
    "sg:postcode":"3142",
    "sg:province":"VIC",
    "wof:name":"Trak Spex",
    "wof:placetype":"venue"
},
  "geometry": {"coordinates":[145.00944519000001,-37.8409996033],"type":"Point"}
}