{
  "type": "Feature",
  "properties": {
    "addr:full":"98 Lavender St Inala QLD 4077",
    "addr:housenumber":"98",
    "addr:postcode":"4077",
    "addr:street":"Lavender St",
    "iso:country":"AU",
    "sg:address":"98 Lavender St",
    "sg:city":"Inala",
    "sg:classifiers":[
        {
            "category":"Professional",
            "subcategory":"Business Services",
            "type":"Services"
        }
    ],
    "sg:phone":"+61 403 745 164",
    "sg:postcode":"4077",
    "sg:province":"QLD",
    "sg:tags":[
        "drafting"
    ],
    "wof:name":"Andrew Northcott Drafting",
    "wof:placetype":"venue"
},
  "geometry": {"coordinates":[152.97210693400001,-27.5912570953],"type":"Point"}
}