{
  "type": "Feature",
  "properties": {
    "addr:full":"Unit 1/ 11 Alloa St Maddington WA 6109",
    "addr:postcode":"6109",
    "addr:street":"11 Alloa St",
    "iso:country":"AU",
    "sg:address":"Unit 1/ 11 Alloa St",
    "sg:city":"Maddington",
    "sg:classifiers":[
        {
            "category":"Conference Center",
            "type":"Public Place"
        }
    ],
    "sg:phone":"+61 8 9493 5133",
    "sg:postcode":"6109",
    "sg:province":"WA",
    "sg:tags":[
        "dryer",
        "electric",
        "hand"
    ],
    "wof:name":"Barretts Architectural Products",
    "wof:placetype":"venue"
},
  "geometry": {"coordinates":[115.98445892300001,-32.044883728],"type":"Point"}
}