{
  "type": "Feature",
  "properties": {
    "iso:country":"AU",
    "sg:address":"301 Koroit St",
    "sg:city":"Warrnambool",
    "sg:classifiers":[
        {
            "category":"Building & Trades",
            "subcategory":"Construction",
            "type":"Services"
        }
    ],
    "sg:phone":"+61 438 615 469",
    "sg:postcode":"3280",
    "sg:province":"VIC",
    "sg:tags":[
        "plasterboard",
        "plasterer",
        "fixer"
    ],
    "wof:name":"PM & SM Fleming Plastering",
    "wof:placetype":"venue"
},
  "geometry": {"coordinates":[142.47251892099999,-38.3787536621],"type":"Point"}
}