{
  "type": "Feature",
  "properties": {
    "addr:full":"Lot 101 Gawler Rd & Mayes Rd Virginia SA 5120",
    "addr:postcode":"5120",
    "addr:street":"Gawler Rd & Mayes Rd",
    "iso:country":"AU",
    "sg:address":"Lot 101 Gawler Rd & Mayes Rd",
    "sg:city":"Virginia",
    "sg:classifiers":[
        {
            "category":"Utilities",
            "subcategory":"Fuel Oil & Lpg",
            "type":"Services"
        }
    ],
    "sg:phone":"+61 8 8380 8386",
    "sg:postcode":"5120",
    "sg:province":"SA",
    "sg:tags":[
        "charcoal"
    ],
    "wof:name":"Charcoala Australia",
    "wof:placetype":"venue"
},
  "geometry": {"coordinates":[138.568084717,-34.6543121338],"type":"Point"}
}