{
  "type": "Feature",
  "properties": {
    "addr:full":"99 Douglas St Thursday Island QLD 4875",
    "addr:housenumber":"99",
    "addr:postcode":"4875",
    "addr:street":"Douglas St",
    "iso:country":"AU",
    "sg:address":"99 Douglas St",
    "sg:city":"Thursday Island",
    "sg:classifiers":[
        {
            "category":"Organizations",
            "subcategory":"Community Association",
            "type":"Services"
        }
    ],
    "sg:phone":"+61 7 4069 1663",
    "sg:postcode":"4875",
    "sg:province":"QLD",
    "sg:tags":[
        "organisation",
        "family",
        "welfare"
    ],
    "wof:name":"Mura Kosker Sorority Inc",
    "wof:placetype":"venue"
},
  "geometry": {"coordinates":[142.21932983400001,-10.5836553574],"type":"Point"}
}