{
  "type": "Feature",
  "properties": {
    "addr:full":"Sports Inhury Centre, 44 Connells Point Rd South Hurstville NSW 2221",
    "addr:housenumber":"44",
    "addr:postcode":"2221",
    "addr:street":"Connells Point Rd",
    "iso:country":"AU",
    "sg:address":"Sports Inhury Centre, 44 Connells Point Rd",
    "sg:city":"South Hurstville",
    "sg:classifiers":[
        {
            "category":"Health Services",
            "subcategory":"Health Practitioner",
            "type":"Services"
        }
    ],
    "sg:phone":"+61 2 9546 6052",
    "sg:postcode":"2221",
    "sg:province":"NSW",
    "sg:tags":[
        "physiotherapist"
    ],
    "sg:website":"http://www.physiotherapy.asn.au",
    "wof:name":"South Hurtsville Physiotherapy",
    "wof:placetype":"venue"
},
  "geometry": {"coordinates":[151.10534668,-33.9771995544],"type":"Point"}
}