{
  "type": "Feature",
  "properties": {
    "iso:country":"AU",
    "sg:address":"Shop 14 Crowne Plz",
    "sg:city":"Terrigal",
    "sg:classifiers":[
        {
            "category":"Shopping",
            "subcategory":"Clothing, Apparel, & Fashions",
            "type":"Retail Goods"
        }
    ],
    "sg:phone":"+61 2 4385 1025",
    "sg:postcode":"2260",
    "sg:province":"NSW",
    "sg:tags":[
        "boutique"
    ],
    "wof:name":"Sommas On Sea",
    "wof:placetype":"venue"
},
  "geometry": {"coordinates":[151.445709,-33.4478],"type":"Point"}
}