{
  "type": "Feature",
  "properties": {
    "iso:country":"AU",
    "sg:address":"32- 40 King St",
    "sg:city":"Warrawong",
    "sg:classifiers":[
        {
            "category":"Restaurant",
            "type":"Food & Drink"
        }
    ],
    "sg:phone":"+61 2 4274 1584",
    "sg:postcode":"2502",
    "sg:province":"NSW",
    "wof:name":"Dragon Fountain Chinese Restaurant",
    "wof:placetype":"venue"
},
  "geometry": {"coordinates":[150.887299,-34.483593],"type":"Point"}
}