{
  "type": "Feature",
  "properties": {
    "iso:country":"AU",
    "sg:address":"Lot 201 Goobar St",
    "sg:city":"Narrabri",
    "sg:classifiers":[
        {
            "category":"Wholesale",
            "subcategory":"Machinery & Supplies",
            "type":"Manufacturing & Wholesale Goods"
        }
    ],
    "sg:phone":"+61 2 6792 4213",
    "sg:postcode":"2390",
    "sg:province":"NSW",
    "sg:tags":[
        "agricultural"
    ],
    "wof:name":"Harold B Davis",
    "wof:placetype":"venue"
},
  "geometry": {"coordinates":[149.749603272,-30.3352870941],"type":"Point"}
}