{
  "type": "Feature",
  "properties": {
    "addr:full":"52 Cumberland Drv Maribyrnong VIC 3032",
    "addr:housenumber":"52",
    "addr:postcode":"3032",
    "addr:street":"Cumberland Drv",
    "iso:country":"AU",
    "sg:address":"52 Cumberland Drv",
    "sg:city":"Maribyrnong",
    "sg:classifiers":[
        {
            "category":"Building & Trades",
            "subcategory":"Construction",
            "type":"Services"
        }
    ],
    "sg:phone":"+61 3 9318 1044",
    "sg:postcode":"3032",
    "sg:province":"VIC",
    "sg:tags":[
        "contractor"
    ],
    "wof:name":"Homes By Chisolm",
    "wof:placetype":"venue"
},
  "geometry": {"coordinates":[144.90046699999999,-37.787415],"type":"Point"}
}