{
  "type": "Feature",
  "properties": {
    "iso:country":"AU",
    "sg:address":"Ground Floor, 62 Colin St",
    "sg:city":"West Perth",
    "sg:classifiers":[
        {
            "category":"Manufacturing",
            "subcategory":"Glass & Minerals",
            "type":"Manufacturing & Wholesale Goods"
        }
    ],
    "sg:phone":"+61 8 9442 2200",
    "sg:postcode":"6005",
    "sg:province":"WA",
    "sg:tags":[
        "exploration"
    ],
    "wof:name":"Regis Resources NL",
    "wof:placetype":"venue"
},
  "geometry": {"coordinates":[115.84220886200001,-31.9489479065],"type":"Point"}
}