{
  "type": "Feature",
  "properties": {
    "addr:full":"5 Windemere Ave Dubbo NSW 2830",
    "addr:housenumber":"5",
    "addr:postcode":"2830",
    "addr:street":"Windemere Ave",
    "iso:country":"AU",
    "sg:address":"5 Windemere Ave",
    "sg:city":"Dubbo",
    "sg:classifiers":[
        {
            "category":"Shopping",
            "subcategory":"Crafts & Fabrics",
            "type":"Retail Goods"
        }
    ],
    "sg:phone":"+61 2 6882 0828",
    "sg:postcode":"2830",
    "sg:province":"NSW",
    "sg:tags":[
        "wool",
        "classers"
    ],
    "wof:name":"John McLean",
    "wof:placetype":"venue"
},
  "geometry": {"coordinates":[148.655563355,-32.2481498718],"type":"Point"}
}