{
  "type": "Feature",
  "properties": {
    "addr:full":"135b Flora St Sutherland NSW 2232",
    "addr:housenumber":"135b",
    "addr:postcode":"2232",
    "addr:street":"Flora St",
    "iso:country":"AU",
    "sg:address":"135b Flora St",
    "sg:city":"Sutherland",
    "sg:classifiers":[
        {
            "category":"Personal",
            "subcategory":"Beauty Salon",
            "type":"Services"
        }
    ],
    "sg:phone":"+61 2 9542 4565",
    "sg:postcode":"2232",
    "sg:province":"NSW",
    "sg:tags":[
        "hairdresser"
    ],
    "wof:name":"Snip Snap Hair Design",
    "wof:placetype":"venue"
},
  "geometry": {"coordinates":[151.05856323200001,-34.0317764282],"type":"Point"}
}