{
  "type": "Feature",
  "properties": {
    "iso:country":"AU",
    "sg:address":"Factory Unit 6/ 18 Leighton Pl",
    "sg:city":"Hornsby",
    "sg:classifiers":[
        {
            "category":"Communications",
            "subcategory":"Film & Video Production",
            "type":"Services"
        }
    ],
    "sg:phone":"+61 2 9476 3157",
    "sg:postcode":"2077",
    "sg:province":"NSW",
    "sg:tags":[
        "mirror"
    ],
    "wof:name":"Hornsby Framing",
    "wof:placetype":"venue"
},
  "geometry": {"coordinates":[151.11370849599999,-33.6958999634],"type":"Point"}
}