{
  "type": "Feature",
  "properties": {
    "iso:country":"AU",
    "sg:address":"End of Braford Drv",
    "sg:city":"Bonville",
    "sg:classifiers":[
        {
            "category":"Farming",
            "subcategory":"Nursery",
            "type":"Manufacturing & Wholesale Goods"
        }
    ],
    "sg:phone":"+61 2 6653 4899",
    "sg:postcode":"2441",
    "sg:province":"NSW",
    "wof:name":"Bonville Valley Nursery & Botanic Garden",
    "wof:placetype":"venue"
},
  "geometry": {"coordinates":[153.031387,-30.368095],"type":"Point"}
}