{
  "type": "Feature",
  "properties": {
    "iso:country":"AU",
    "sg:address":"Suite 1A, 68 Jessica Blv",
    "sg:city":"Minyama",
    "sg:classifiers":[
        {
            "category":"Personal",
            "subcategory":"Hair Removal",
            "type":"Services"
        }
    ],
    "sg:phone":"+61 7 5477 6233",
    "sg:postcode":"4575",
    "sg:province":"QLD",
    "wof:name":"Queensland Laser Hair Removal Clinic",
    "wof:placetype":"venue"
},
  "geometry": {"coordinates":[153.124054,-26.698994],"type":"Point"}
}