{
  "type": "Feature",
  "properties": {
    "addr:full":"21 Hicks St Charters Towers QLD 4820",
    "addr:housenumber":"21",
    "addr:postcode":"4820",
    "addr:street":"Hicks St",
    "iso:country":"AU",
    "sg:address":"21 Hicks St",
    "sg:city":"Charters Towers",
    "sg:classifiers":[
        {
            "category":"Personal",
            "subcategory":"Beauty Salon",
            "type":"Services"
        }
    ],
    "sg:phone":"+61 7 4787 4977",
    "sg:postcode":"4820",
    "sg:province":"QLD",
    "sg:tags":[
        "hairdresser"
    ],
    "wof:name":"Cal's Hair Studio",
    "wof:placetype":"venue"
},
  "geometry": {"coordinates":[146.26246599999999,-20.060867],"type":"Point"}
}