{
  "type": "Feature",
  "properties": {
    "addr:full":"Bridge St Murray Bridge SA 5253",
    "addr:postcode":"5253",
    "addr:street":"Bridge St",
    "iso:country":"AU",
    "sg:address":"Bridge St",
    "sg:city":"Murray Bridge",
    "sg:classifiers":[
        {
            "category":"Organizations",
            "subcategory":"Non-profit Organization",
            "type":"Services"
        }
    ],
    "sg:phone":"+61 8 8531 0710",
    "sg:postcode":"5253",
    "sg:province":"SA",
    "sg:tags":[
        "environmental",
        "organisation",
        "conservation"
    ],
    "wof:name":"Murraywatch",
    "wof:placetype":"venue"
},
  "geometry": {"coordinates":[139.282150269,-35.1134796143],"type":"Point"}
}