{
  "type": "Feature",
  "properties": {
    "addr:full":"9 Grex Ave Minchinbury NSW 2770",
    "addr:housenumber":"9",
    "addr:postcode":"2770",
    "addr:street":"Grex Ave",
    "iso:country":"AU",
    "sg:address":"9 Grex Ave",
    "sg:city":"Minchinbury",
    "sg:classifiers":[
        {
            "category":"Manufacturing",
            "subcategory":"Tools & Machinery",
            "type":"Manufacturing & Wholesale Goods"
        }
    ],
    "sg:phone":"+61 2 9677 9011",
    "sg:postcode":"2770",
    "sg:province":"NSW",
    "sg:tags":[
        "earth",
        "excavating",
        "moving",
        "equipment"
    ],
    "wof:name":"Ditchwitch Australia P/L",
    "wof:placetype":"venue"
},
  "geometry": {"coordinates":[150.817260742,-33.7835617065],"type":"Point"}
}