{
  "type": "Feature",
  "properties": {
    "addr:full":"3 Port Wakefield Rd Waterloo Corner SA 5110",
    "addr:housenumber":"3",
    "addr:postcode":"5110",
    "addr:street":"Port Wakefield Rd",
    "iso:country":"AU",
    "sg:address":"3 Port Wakefield Rd",
    "sg:city":"Waterloo Corner",
    "sg:classifiers":[
        {
            "category":"Food & Beverages",
            "subcategory":"Fruits & Vegetables",
            "type":"Retail Goods"
        }
    ],
    "sg:phone":"+61 8 8280 8899",
    "sg:postcode":"5110",
    "sg:province":"SA",
    "sg:tags":[
        "grower"
    ],
    "wof:name":"T & L Veges",
    "wof:placetype":"venue"
},
  "geometry": {"coordinates":[138.58691406200001,-34.746383667],"type":"Point"}
}