{
  "type": "Feature",
  "properties": {
    "addr:full":"Darlinghurst Public School, Cnr Liverpool St & Bar Darlinghurst NSW 2010",
    "addr:postcode":"2010",
    "addr:street":"Cnr Liverpool St &",
    "iso:country":"AU",
    "sg:address":"Darlinghurst Public School, Cnr Liverpool St & Bar",
    "sg:city":"Darlinghurst",
    "sg:classifiers":[
        {
            "category":"Organizations",
            "subcategory":"Professional Association",
            "type":"Services"
        }
    ],
    "sg:phone":"+61 2 9331 6920",
    "sg:postcode":"2010",
    "sg:province":"NSW",
    "sg:tags":[
        "organisation",
        "business"
    ],
    "wof:name":"Australian Society of Orthodontists Inc",
    "wof:placetype":"venue"
},
  "geometry": {"coordinates":[151.220535278,-33.8781356812],"type":"Point"}
}