{
  "type": "Feature",
  "properties": {
    "addr:full":"Lot 1 Newry Rd Maffra VIC 3860",
    "addr:postcode":"3860",
    "addr:street":"Newry Rd",
    "iso:country":"AU",
    "sg:address":"Lot 1 Newry Rd",
    "sg:city":"Maffra",
    "sg:classifiers":[
        {
            "category":"Manufacturing",
            "subcategory":"Motor Vehicles & Parts",
            "type":"Manufacturing & Wholesale Goods"
        }
    ],
    "sg:phone":"+61 3 5141 1866",
    "sg:postcode":"3860",
    "sg:province":"VIC",
    "sg:tags":[
        "replacement"
    ],
    "wof:name":"Strut Lift",
    "wof:placetype":"venue"
},
  "geometry": {"coordinates":[146.955932617,-37.9315681458],"type":"Point"}
}