{
  "type": "Feature",
  "properties": {
    "iso:country":"AU",
    "sg:address":"Unit 3 & 4",
    "sg:city":", 4 O&#039;Hart Cl Charmhaven",
    "sg:classifiers":[
        {
            "category":"Wholesale",
            "subcategory":"Machinery & Supplies",
            "type":"Manufacturing & Wholesale Goods"
        }
    ],
    "sg:phone":"+61 2 4392 4477",
    "sg:postcode":"2263",
    "sg:province":"NSW",
    "sg:tags":[
        "equipment",
        "welding"
    ],
    "wof:name":"Linde Gas Pty. Ltd.",
    "wof:placetype":"venue"
},
  "geometry": {"coordinates":[151.50839199999999,-33.23679],"type":"Point"}
}