{
  "type": "Feature",
  "properties": {
    "addr:full":"Peak Downs Hwy Ooralea QLD 4740",
    "addr:postcode":"4740",
    "addr:street":"Downs Hwy",
    "iso:country":"AU",
    "sg:address":"Peak Downs Hwy",
    "sg:city":"Ooralea",
    "sg:classifiers":[
        {
            "category":"Home & Garden",
            "subcategory":"Garden Supply",
            "type":"Retail Goods"
        }
    ],
    "sg:phone":"+61 7 4952 2466",
    "sg:postcode":"4740",
    "sg:province":"QLD",
    "sg:tags":[
        "fertilizer"
    ],
    "wof:name":"Grow Force Australia Ltd",
    "wof:placetype":"venue"
},
  "geometry": {"coordinates":[149.147018,-21.165936],"type":"Point"}
}