{
  "type": "Feature",
  "properties": {
    "addr:full":"PO Box 43 Annandale NSW 2038",
    "addr:postcode":"2038",
    "iso:country":"AU",
    "sg:address":"PO Box 43",
    "sg:city":"Annandale",
    "sg:classifiers":[
        {
            "category":"Professional",
            "subcategory":"Printing & Photocopies",
            "type":"Services"
        }
    ],
    "sg:phone":"+61 2 9572 6788",
    "sg:postcode":"2038",
    "sg:province":"NSW",
    "sg:tags":[
        "textile",
        "clothing"
    ],
    "wof:name":"Ribboprint",
    "wof:placetype":"venue"
},
  "geometry": {"coordinates":[151.169723511,-33.8796691895],"type":"Point"}
}