{
  "type": "Feature",
  "properties": {
    "iso:country":"AU",
    "sg:address":"PO Box 53",
    "sg:city":"Balaklava",
    "sg:classifiers":[
        {
            "category":"Farming",
            "subcategory":"Farm",
            "type":"Manufacturing & Wholesale Goods"
        }
    ],
    "sg:phone":"+61 8 8862 1139",
    "sg:postcode":"5461",
    "sg:province":"SA",
    "sg:tags":[
        "farmer"
    ],
    "wof:name":"Zerk M F & L L",
    "wof:placetype":"venue"
},
  "geometry": {"coordinates":[138.41090399999999,-34.1455],"type":"Point"}
}