{
  "type": "Feature",
  "properties": {
    "addr:full":"56 Croston Rd Engadine NSW 2233",
    "addr:housenumber":"56",
    "addr:postcode":"2233",
    "addr:street":"Croston Rd",
    "iso:country":"AU",
    "sg:address":"56 Croston Rd",
    "sg:city":"Engadine",
    "sg:classifiers":[
        {
            "category":"Utilities",
            "subcategory":"Natural Gas",
            "type":"Services"
        }
    ],
    "sg:phone":"+61 2 9520 9440",
    "sg:postcode":"2233",
    "sg:province":"NSW",
    "sg:tags":[
        "hose",
        "reel",
        "cable"
    ],
    "wof:name":"Moore S & C Pty Ltd",
    "wof:placetype":"venue"
},
  "geometry": {"coordinates":[151.03196716299999,-34.0422363281],"type":"Point"}
}