{
  "type": "Feature",
  "properties": {
    "addr:full":"Sodium St Narangba QLD 4504",
    "addr:postcode":"4504",
    "addr:street":"St",
    "iso:country":"AU",
    "sg:address":"Sodium St",
    "sg:city":"Narangba",
    "sg:classifiers":[
        {
            "category":"Manufacturing",
            "subcategory":"Metals",
            "type":"Manufacturing & Wholesale Goods"
        }
    ],
    "sg:phone":"+61 7 3897 0840",
    "sg:postcode":"4504",
    "sg:province":"QLD",
    "sg:tags":[
        "fabricator",
        "aluminium"
    ],
    "wof:name":"G.James Glass & Aluminium",
    "wof:placetype":"venue"
},
  "geometry": {"coordinates":[152.98696899399999,-27.1980400085],"type":"Point"}
}