{
  "type": "Feature",
  "properties": {
    "addr:full":"269 Brighton Rd Somerton Park SA 5044",
    "addr:housenumber":"269",
    "addr:postcode":"5044",
    "addr:street":"Brighton Rd",
    "iso:country":"AU",
    "sg:address":"269 Brighton Rd",
    "sg:city":"Somerton Park",
    "sg:classifiers":[
        {
            "category":"Real Estate",
            "subcategory":"Architect",
            "type":"Services"
        }
    ],
    "sg:phone":"+61 8 8376 8888",
    "sg:postcode":"5044",
    "sg:province":"SA",
    "wof:name":"Folland Panozzo Architects",
    "wof:placetype":"venue"
},
  "geometry": {"coordinates":[138.5215,-34.999512],"type":"Point"}
}