{
  "type": "Feature",
  "properties": {
    "addr:full":"310 Bridge Rd Richmond VIC 3121",
    "addr:housenumber":"310",
    "addr:postcode":"3121",
    "addr:street":"Bridge Rd",
    "iso:country":"AU",
    "sg:address":"310 Bridge Rd",
    "sg:city":"Richmond",
    "sg:classifiers":[
        {
            "category":"Food & Beverages",
            "subcategory":"Groceries & Convenience Stores",
            "type":"Retail Goods"
        }
    ],
    "sg:phone":"+61 3 9429 4221",
    "sg:postcode":"3121",
    "sg:province":"VIC",
    "wof:name":"Select 7",
    "wof:placetype":"venue"
},
  "geometry": {"coordinates":[145.00161743199999,-37.8189277649],"type":"Point"}
}