{
  "type": "Feature",
  "properties": {
    "addr:full":"390 Pacific Hwy Belmont NSW 2280",
    "addr:housenumber":"390",
    "addr:postcode":"2280",
    "addr:street":"Pacific Hwy",
    "iso:country":"AU",
    "sg:address":"390 Pacific Hwy",
    "sg:city":"Belmont",
    "sg:classifiers":[
        {
            "category":"Retail",
            "subcategory":"Auto Rental",
            "type":"Services"
        }
    ],
    "sg:phone":"+61 2 4947 9999",
    "sg:postcode":"2280",
    "sg:province":"NSW",
    "sg:tags":[
        "camper-trailers",
        "caravan",
        "hire"
    ],
    "wof:name":"Five Star Campers",
    "wof:placetype":"venue"
},
  "geometry": {"coordinates":[151.663208008,-33.0238647461],"type":"Point"}
}