{
  "type": "Feature",
  "properties": {
    "addr:full":"Shop 19, 659 Young St Albury NSW 2640",
    "addr:housenumber":"shop 19 659",
    "addr:postcode":"2640",
    "addr:street":"Young St",
    "iso:country":"AU",
    "sg:address":"Shop 19, 659 Young St",
    "sg:city":"Albury",
    "sg:classifiers":[
        {
            "category":"Education",
            "subcategory":"Vocational School",
            "type":"Public Place"
        }
    ],
    "sg:phone":"+61 414 691 652",
    "sg:postcode":"2640",
    "sg:province":"NSW",
    "sg:tags":[
        "cake",
        "decorating",
        "decorator"
    ],
    "wof:name":"Nicky's Cakes",
    "wof:placetype":"venue"
},
  "geometry": {"coordinates":[146.92576599099999,-36.0718727112],"type":"Point"}
}