{
  "type": "Feature",
  "properties": {
    "addr:full":"Lot 11 Barlee St Busselton WA 6280",
    "addr:postcode":"6280",
    "addr:street":"St",
    "iso:country":"AU",
    "sg:address":"Lot 11 Barlee St",
    "sg:city":"Busselton",
    "sg:classifiers":[
        {
            "category":"Home & Garden",
            "subcategory":"Hardware",
            "type":"Retail Goods"
        }
    ],
    "sg:phone":"+61 8 9754 2008",
    "sg:postcode":"6280",
    "sg:province":"WA",
    "sg:tags":[
        "plumber",
        "supply"
    ],
    "wof:name":"Reece Pty. Ltd.",
    "wof:placetype":"venue"
},
  "geometry": {"coordinates":[115.34425354,-33.6603355408],"type":"Point"}
}