{
  "type": "Feature",
  "properties": {
    "iso:country":"AU",
    "sg:address":"10 Goldsmith Drv",
    "sg:city":"Noarlunga Downs",
    "sg:classifiers":[
        {
            "category":"Retail",
            "subcategory":"Auto Repair",
            "type":"Services"
        }
    ],
    "sg:phone":"+61 8 8326 3433",
    "sg:postcode":"5168",
    "sg:province":"SA",
    "sg:tags":[
        "clutch",
        "brake"
    ],
    "wof:name":"Bridgestone Tyre Centre",
    "wof:placetype":"venue"
},
  "geometry": {"coordinates":[138.48841857900001,-35.1431007385],"type":"Point"}
}