{
  "type": "Feature",
  "properties": {
    "addr:full":"Un 57/ 19 Banchory Crt Carindale QLD 4152",
    "addr:housenumber":"/ 19",
    "addr:postcode":"4152",
    "addr:street":"Banchory Crt",
    "iso:country":"AU",
    "sg:address":"Un 57/ 19 Banchory Crt",
    "sg:city":"Carindale",
    "sg:classifiers":[
        {
            "category":"Retail",
            "subcategory":"Storage",
            "type":"Services"
        }
    ],
    "sg:phone":"+61 7 3398 8585",
    "sg:postcode":"4152",
    "sg:province":"QLD",
    "sg:tags":[
        "shelving",
        "system"
    ],
    "wof:name":"The Storage Space Company",
    "wof:placetype":"venue"
},
  "geometry": {"coordinates":[153.10421752900001,-27.5020542145],"type":"Point"}
}