{
  "type": "Feature",
  "properties": {
    "addr:full":"163 Dawkins Rd Lewiston SA 5501",
    "addr:housenumber":"163",
    "addr:postcode":"5501",
    "addr:street":"Dawkins Rd",
    "iso:country":"AU",
    "sg:address":"163 Dawkins Rd",
    "sg:city":"Lewiston",
    "sg:classifiers":[
        {
            "category":"Farming",
            "subcategory":"Farm & Veterinary Services",
            "type":"Manufacturing & Wholesale Goods"
        }
    ],
    "sg:phone":"+61 427 076 948",
    "sg:postcode":"5501",
    "sg:province":"SA",
    "sg:tags":[
        "blacksmith",
        "farrier"
    ],
    "wof:name":"R J & C A Oldenbeuving",
    "wof:placetype":"venue"
},
  "geometry": {"coordinates":[138.62437399999999,-34.611275],"type":"Point"}
}