{
  "type": "Feature",
  "properties": {
    "addr:full":"24 Maida Ave Sunshine North VIC 3020",
    "addr:housenumber":"24",
    "addr:postcode":"3020",
    "addr:street":"Maida Ave",
    "iso:country":"AU",
    "sg:address":"24 Maida Ave",
    "sg:city":"Sunshine North",
    "sg:classifiers":[
        {
            "category":"Retail",
            "subcategory":"Laundry & Dry Cleaning",
            "type":"Services"
        }
    ],
    "sg:phone":"+61 3 9364 4268",
    "sg:postcode":"3020",
    "sg:province":"VIC",
    "sg:tags":[
        "ironing"
    ],
    "wof:name":"HTH Pressing",
    "wof:placetype":"venue"
},
  "geometry": {"coordinates":[144.8349,-37.755821],"type":"Point"}
}