{
  "type": "Feature",
  "properties": {
    "iso:country":"AU",
    "sg:address":"24 Baillie St",
    "sg:city":"Lismore",
    "sg:classifiers":[
        {
            "category":"Professional",
            "subcategory":"Art Services",
            "type":"Services"
        }
    ],
    "sg:phone":"+61 2 6621 5875",
    "sg:postcode":"2480",
    "sg:province":"NSW",
    "sg:tags":[
        "decorator",
        "painter"
    ],
    "wof:name":"Marbelous",
    "wof:placetype":"venue"
},
  "geometry": {"coordinates":[153.27593994099999,-28.8035202026],"type":"Point"}
}