{
  "type": "Feature",
  "properties": {
    "iso:country":"AU",
    "sg:address":"70 Francis Rd",
    "sg:city":"Wingfield",
    "sg:classifiers":[
        {
            "category":"Commercial Area",
            "type":"Public Place"
        }
    ],
    "sg:phone":"+61 8 8268 1311",
    "sg:postcode":"5013",
    "sg:province":"SA",
    "sg:tags":[
        "heavy",
        "carrier"
    ],
    "wof:name":"James Contract Supplies Pty Ltd",
    "wof:placetype":"venue"
},
  "geometry": {"coordinates":[138.55108642600001,-34.8456306458],"type":"Point"}
}