{
  "type": "Feature",
  "properties": {
    "iso:country":"AU",
    "sg:address":"118 Hume St",
    "sg:city":"Wodonga",
    "sg:classifiers":[
        {
            "category":"Health Services",
            "subcategory":"Doctor",
            "type":"Services"
        }
    ],
    "sg:phone":"+61 2 6024 5577",
    "sg:postcode":"3690",
    "sg:province":"VIC",
    "sg:tags":[
        "podiatrist"
    ],
    "wof:name":"Amys Podiatry Clinic",
    "wof:placetype":"venue"
},
  "geometry": {"coordinates":[146.88575744600001,-36.1246871948],"type":"Point"}
}