{
  "type": "Feature",
  "properties": {
    "iso:country":"AU",
    "sg:address":"327 High St",
    "sg:city":"Ashburton",
    "sg:classifiers":[
        {
            "category":"Health Services",
            "subcategory":"Doctor",
            "type":"Services"
        }
    ],
    "sg:phone":"+61 3 9885 0950",
    "sg:postcode":"3147",
    "sg:province":"VIC",
    "sg:tags":[
        "medical",
        "practitioner"
    ],
    "wof:name":"Permezel S.W.G.",
    "wof:placetype":"venue"
},
  "geometry": {"coordinates":[145.08482360799999,-37.8638687134],"type":"Point"}
}