{
  "type": "Feature",
  "properties": {
    "addr:full":"3 Bass St Queanbeyan NSW 2620",
    "addr:housenumber":"3",
    "addr:postcode":"2620",
    "addr:street":"Bass St",
    "iso:country":"AU",
    "sg:address":"3 Bass St",
    "sg:city":"Queanbeyan",
    "sg:classifiers":[
        {
            "category":"Retail",
            "subcategory":"Repair Shop",
            "type":"Services"
        }
    ],
    "sg:phone":"+61 2 6298 1640",
    "sg:postcode":"2620",
    "sg:province":"NSW",
    "sg:tags":[
        "restorer",
        "repairer",
        "carpet"
    ],
    "wof:name":"Q Commercial Carpets",
    "wof:placetype":"venue"
},
  "geometry": {"coordinates":[149.24591064399999,-35.3350639343],"type":"Point"}
}