{
  "type": "Feature",
  "properties": {
    "iso:country":"AU",
    "sg:address":"307 Bellerine St",
    "sg:city":"Geelong South",
    "sg:classifiers":[
        {
            "category":"Retail",
            "subcategory":"Auto Repair",
            "type":"Services"
        }
    ],
    "sg:phone":"+61 3 5223 1872",
    "sg:postcode":"3220",
    "sg:province":"VIC",
    "sg:tags":[
        "repairer",
        "motor",
        "engineer"
    ],
    "wof:name":"Singh's Automotive",
    "wof:placetype":"venue"
},
  "geometry": {"coordinates":[144.358932,-38.163872],"type":"Point"}
}