{
  "type": "Feature",
  "properties": {
    "addr:full":"121a Percy St Portland VIC 3305",
    "addr:housenumber":"121a",
    "addr:postcode":"3305",
    "addr:street":"Percy St",
    "iso:country":"AU",
    "sg:address":"121a Percy St",
    "sg:city":"Portland",
    "sg:classifiers":[
        {
            "category":"Communications",
            "subcategory":"Film & Video Production",
            "type":"Services"
        }
    ],
    "sg:phone":"+61 3 5523 2978",
    "sg:postcode":"3305",
    "sg:province":"VIC",
    "sg:tags":[
        "dvd",
        "library"
    ],
    "wof:name":"Family Videoland",
    "wof:placetype":"venue"
},
  "geometry": {"coordinates":[141.60395813,-38.3450164795],"type":"Point"}
}