{
  "type": "Feature",
  "properties": {
    "iso:country":"AU",
    "sg:address":"Jacaranda Ave",
    "sg:city":"Caboolture South",
    "sg:classifiers":[
        {
            "category":"Health Services",
            "subcategory":"Dentist",
            "type":"Services"
        }
    ],
    "sg:phone":"+61 7 5498 9088",
    "sg:postcode":"4510",
    "sg:province":"QLD",
    "sg:tags":[
        "dental",
        "prosthetist"
    ],
    "wof:name":"David Larment Denture Clinics",
    "wof:placetype":"venue"
},
  "geometry": {"coordinates":[152.949905,-27.095922],"type":"Point"}
}