{
  "type": "Feature",
  "properties": {
    "addr:full":"Blackjack Rd Charters Towers QLD 4820",
    "addr:postcode":"4820",
    "addr:street":"Blackjack Rd",
    "iso:country":"AU",
    "sg:address":"Blackjack Rd",
    "sg:city":"Charters Towers",
    "sg:classifiers":[
        {
            "category":"Building & Trades",
            "subcategory":"Construction",
            "type":"Services"
        }
    ],
    "sg:phone":"+61 428 872 668",
    "sg:postcode":"4820",
    "sg:province":"QLD",
    "sg:tags":[
        "earth",
        "excavating",
        "moving",
        "contractor"
    ],
    "wof:name":"Boyd Evans Backhoe Hire",
    "wof:placetype":"venue"
},
  "geometry": {"coordinates":[146.22877500000001,-20.109455],"type":"Point"}
}