{
  "type": "Feature",
  "properties": {
    "iso:country":"AU",
    "sg:address":"200 Seymore St",
    "sg:city":"Sandgate",
    "sg:classifiers":[
        {
            "category":"Real Estate",
            "subcategory":"Real Estate Agent",
            "type":"Services"
        }
    ],
    "sg:phone":"+61 7 3869 0953",
    "sg:postcode":"4017",
    "sg:province":"QLD",
    "wof:name":"Jim McKeering Real Estate",
    "wof:placetype":"venue"
},
  "geometry": {"coordinates":[153.070236206,-27.3208713531],"type":"Point"}
}