{
  "type": "Feature",
  "properties": {
    "iso:country":"AU",
    "sg:address":"Suite 7/ 101 Collins Rd",
    "sg:city":"Willetton",
    "sg:classifiers":[
        {
            "category":"Banks & Credit Unions",
            "subcategory":"Bank",
            "type":"Services"
        }
    ],
    "sg:phone":"+61 8 9259 5626",
    "sg:postcode":"6155",
    "sg:province":"WA",
    "sg:tags":[
        "broker",
        "mortgage"
    ],
    "wof:name":"Home Loan Solutions",
    "wof:placetype":"venue"
},
  "geometry": {"coordinates":[115.89475299999999,-32.055218],"type":"Point"}
}