{
  "type": "Feature",
  "properties": {
    "addr:full":"West St Eden NSW 2551",
    "addr:postcode":"2551",
    "addr:street":"West St",
    "iso:country":"AU",
    "sg:address":"West St",
    "sg:city":"Eden",
    "sg:classifiers":[
        {
            "category":"Professional",
            "subcategory":"Computer Services",
            "type":"Services"
        }
    ],
    "sg:phone":"+61 2 6496 2501",
    "sg:postcode":"2551",
    "sg:province":"NSW",
    "sg:tags":[
        "training"
    ],
    "wof:name":"Skelton Peter",
    "wof:placetype":"venue"
},
  "geometry": {"coordinates":[149.897216797,-37.0562400818],"type":"Point"}
}