{
  "type": "Feature",
  "properties": {
    "addr:full":"Roe Rd Karlgarin Hill WA 6358",
    "addr:postcode":"6358",
    "addr:street":"Roe Rd Karlgarin Hill",
    "iso:country":"AU",
    "sg:address":"Roe Rd",
    "sg:city":"Karlgarin Hill",
    "sg:classifiers":[
        {
            "category":"Farming",
            "subcategory":"Farm",
            "type":"Manufacturing & Wholesale Goods"
        }
    ],
    "sg:phone":"+61 8 9889 6030",
    "sg:postcode":"6358",
    "sg:province":"WA",
    "sg:tags":[
        "farmer"
    ],
    "wof:name":"Richter P R & F E",
    "wof:placetype":"venue"
},
  "geometry": {"coordinates":[118.576752,-32.357388],"type":"Point"}
}