{
  "type": "Feature",
  "properties": {
    "iso:country":"AU",
    "sg:address":"Lovely Banks Rd",
    "sg:city":"Colebrook",
    "sg:phone":"+61 3 6259 7176",
    "sg:postcode":"7027",
    "sg:province":"TAS",
    "wof:name":"Tassie Concrete Tanks",
    "wof:placetype":"venue"
},
  "geometry": {"coordinates":[147.325119019,-42.4911384583],"type":"Point"}
}