{
  "type": "Feature",
  "properties": {
    "iso:country":"AU",
    "sg:address":"358 Cambridge St",
    "sg:city":"Wembley",
    "sg:classifiers":[
        {
            "category":"Banks & Credit Unions",
            "subcategory":"Investment Brokerage",
            "type":"Services"
        }
    ],
    "sg:phone":"+61 8 9287 1980",
    "sg:postcode":"6014",
    "sg:province":"WA",
    "sg:tags":[
        "finance",
        "broker"
    ],
    "wof:name":"Premium Private Finance WA Pty Ltd",
    "wof:placetype":"venue"
},
  "geometry": {"coordinates":[115.81012725799999,-31.9408855438],"type":"Point"}
}