{
  "type": "Feature",
  "properties": {
    "iso:country":"AU",
    "sg:address":"North Avoca Pde",
    "sg:city":"North Avoca",
    "sg:classifiers":[
        {
            "category":"Arena",
            "subcategory":"Sports Club",
            "type":"Entertainment"
        }
    ],
    "sg:phone":"+61 2 4384 3607",
    "sg:postcode":"2260",
    "sg:province":"NSW",
    "sg:tags":[
        "life",
        "surfing",
        "saving"
    ],
    "wof:name":"North Avoca Beach Surf Life Saving Club",
    "wof:placetype":"venue"
},
  "geometry": {"coordinates":[151.438568,-33.457874],"type":"Point"}
}