{
  "type": "Feature",
  "properties": {
    "iso:country":"AU",
    "sg:address":"Suite 407 RPA Medical Centre 100 Carillon Ave",
    "sg:city":"Newtown",
    "sg:classifiers":[
        {
            "category":"Health Services",
            "subcategory":"Doctor",
            "type":"Services"
        }
    ],
    "sg:phone":"+61 2 9516 3456",
    "sg:postcode":"2042",
    "sg:province":"NSW",
    "sg:tags":[
        "medical",
        "practitioner"
    ],
    "wof:name":"Central Sydney Cardiology",
    "wof:placetype":"venue"
},
  "geometry": {"coordinates":[151.18330399999999,-33.891499],"type":"Point"}
}