{
  "type": "Feature",
  "properties": {
    "addr:full":"383- 387 Dorset Rd Croydon VIC 3136",
    "addr:housenumber":"387",
    "addr:postcode":"3136",
    "addr:street":"Dorset Rd",
    "iso:country":"AU",
    "sg:address":"383- 387 Dorset Rd",
    "sg:city":"Croydon",
    "sg:classifiers":[
        {
            "category":"Health Services",
            "subcategory":"Health Practitioner",
            "type":"Services"
        }
    ],
    "sg:phone":"+61 3 9885 8961",
    "sg:postcode":"3136",
    "sg:province":"VIC",
    "sg:tags":[
        "physiotherapist"
    ],
    "wof:name":"Wigg Andrew",
    "wof:placetype":"venue"
},
  "geometry": {"coordinates":[145.28868102999999,-37.8067703247],"type":"Point"}
}