{
  "type": "Feature",
  "properties": {
    "addr:full":"145 Davey St Hobart TAS 7000",
    "addr:housenumber":"145",
    "addr:postcode":"7000",
    "addr:street":"Davey St",
    "iso:country":"AU",
    "sg:address":"145 Davey St",
    "sg:city":"Hobart",
    "sg:classifiers":[
        {
            "category":"Professional",
            "subcategory":"Printing & Photocopies",
            "type":"Services"
        }
    ],
    "sg:phone":"+61 3 6231 1145",
    "sg:postcode":"7000",
    "sg:province":"TAS",
    "sg:tags":[
        "laminating"
    ],
    "wof:name":"Pumpkin Prints",
    "wof:placetype":"venue"
},
  "geometry": {"coordinates":[147.32232665999999,-42.8900032043],"type":"Point"}
}