{
  "type": "Feature",
  "properties": {
    "iso:country":"AU",
    "sg:address":"103 Munro St",
    "sg:city":"Babinda",
    "sg:classifiers":[
        {
            "category":"Fast Food",
            "type":"Food & Drink"
        }
    ],
    "sg:phone":"+61 7 4067 1465",
    "sg:postcode":"4861",
    "sg:province":"QLD",
    "sg:tags":[
        "away",
        "take"
    ],
    "wof:name":"Munchies Cafe Babinda",
    "wof:placetype":"venue"
},
  "geometry": {"coordinates":[145.921142578,-17.3440265656],"type":"Point"}
}