{
  "type": "Feature",
  "properties": {
    "addr:full":"98 High St Tenterfield NSW 2372",
    "addr:housenumber":"98",
    "addr:postcode":"2372",
    "addr:street":"High St",
    "iso:country":"AU",
    "sg:address":"98 High St",
    "sg:city":"Tenterfield",
    "sg:classifiers":[
        {
            "category":"Professional",
            "subcategory":"Accounting & Tax Preparation",
            "type":"Services"
        }
    ],
    "sg:phone":"+61 2 6736 5383",
    "sg:postcode":"2372",
    "sg:province":"NSW",
    "sg:tags":[
        "consultant",
        "taxation"
    ],
    "wof:name":"Lyn Gower",
    "wof:placetype":"venue"
},
  "geometry": {"coordinates":[152.01829528799999,-29.0531730652],"type":"Point"}
}