{
  "type": "Feature",
  "properties": {
    "iso:country":"AU",
    "sg:address":"8 Prospect St",
    "sg:city":"Mackay",
    "sg:classifiers":[
        {
            "category":"Retail",
            "subcategory":"Auto Repair",
            "type":"Services"
        }
    ],
    "sg:phone":"+61 7 4957 7482",
    "sg:postcode":"4740",
    "sg:province":"QLD",
    "sg:tags":[
        "clutch",
        "brake"
    ],
    "wof:name":"South Mackay Brake & Alignment Centre",
    "wof:placetype":"venue"
},
  "geometry": {"coordinates":[149.189392,-21.149155],"type":"Point"}
}