{
  "type": "Feature",
  "properties": {
    "addr:full":"218 Eumungerie Rd Narromine NSW 2821",
    "addr:housenumber":"218",
    "addr:postcode":"2821",
    "addr:street":"Eumungerie Rd",
    "iso:country":"AU",
    "sg:address":"218 Eumungerie Rd",
    "sg:city":"Narromine",
    "sg:classifiers":[
        {
            "category":"Farming",
            "subcategory":"Farm & Veterinary Services",
            "type":"Manufacturing & Wholesale Goods"
        }
    ],
    "sg:phone":"+61 2 6889 1144",
    "sg:postcode":"2821",
    "sg:province":"NSW",
    "sg:tags":[
        "seedsman"
    ],
    "wof:name":"Enza Zaden (Australia) Pty Ltd",
    "wof:placetype":"venue"
},
  "geometry": {"coordinates":[148.24449157699999,-32.2355308533],"type":"Point"}
}