{
  "type": "Feature",
  "properties": {
    "iso:country":"AU",
    "sg:address":"U6/ 25 Dellamarta Rd",
    "sg:city":"Wangara",
    "sg:classifiers":[
        {
            "category":"Professional",
            "subcategory":"Engineering",
            "type":"Services"
        }
    ],
    "sg:phone":"+61 8 9309 2333",
    "sg:postcode":"6065",
    "sg:province":"WA",
    "sg:tags":[
        "manufacturing",
        "engineer"
    ],
    "wof:name":"Westenge",
    "wof:placetype":"venue"
},
  "geometry": {"coordinates":[115.818328857,-31.788772583],"type":"Point"}
}