{
  "type": "Feature",
  "properties": {
    "iso:country":"AU",
    "sg:address":"22 Britton St",
    "sg:city":"Smithfield",
    "sg:classifiers":[
        {
            "category":"Retail",
            "subcategory":"Auto Repair",
            "type":"Services"
        }
    ],
    "sg:phone":"+61 2 9604 4582",
    "sg:postcode":"2164",
    "sg:province":"NSW",
    "sg:tags":[
        "body",
        "builder",
        "motor"
    ],
    "wof:name":"Hadleys Hearses",
    "wof:placetype":"venue"
},
  "geometry": {"coordinates":[150.94541931099999,-33.8436851501],"type":"Point"}
}