{
  "type": "Feature",
  "properties": {
    "iso:country":"AU",
    "sg:address":"Cnr Chapel St & Dandenong Rd",
    "sg:city":"Windsor",
    "sg:classifiers":[
        {
            "category":"Health Services",
            "subcategory":"Doctor",
            "type":"Services"
        }
    ],
    "sg:phone":"+61 3 9510 7888",
    "sg:postcode":"3181",
    "sg:province":"VIC",
    "sg:tags":[
        "medical",
        "practitioner"
    ],
    "wof:name":"Khera: Param S Dr",
    "wof:placetype":"venue"
},
  "geometry": {"coordinates":[144.992553711,-37.8561820984],"type":"Point"}
}