{
  "type": "Feature",
  "properties": {
    "iso:country":"AU",
    "sg:address":"32 Boronia Ave",
    "sg:city":"Epping",
    "sg:classifiers":[
        {
            "category":"Real Estate",
            "subcategory":"Real Estate Agent",
            "type":"Services"
        }
    ],
    "sg:phone":"+61 2 9869 4151",
    "sg:postcode":"2121",
    "sg:province":"NSW",
    "wof:name":"Millennium Residential Management",
    "wof:placetype":"venue"
},
  "geometry": {"coordinates":[151.07142639200001,-33.7762069702],"type":"Point"}
}