{
  "type": "Feature",
  "properties": {
    "iso:country":"AU",
    "sg:address":"621 Glenhuntly Rd",
    "sg:city":"Caulfield",
    "sg:classifiers":[
        {
            "category":"Shopping",
            "subcategory":"Clothing, Apparel, & Fashions",
            "type":"Retail Goods"
        }
    ],
    "sg:phone":"+61 3 9523 9838",
    "sg:postcode":"3162",
    "sg:province":"VIC",
    "sg:tags":[
        "lady",
        "wear"
    ],
    "wof:name":"Worn To Be Wild",
    "wof:placetype":"venue"
},
  "geometry": {"coordinates":[145.01530456500001,-37.8859214783],"type":"Point"}
}