{
  "type": "Feature",
  "properties": {
    "addr:full":"218 Beaconsfield-Emerald Rd Beaconsfield VIC 3807",
    "addr:housenumber":"218",
    "addr:postcode":"3807",
    "addr:street":"Beaconsfield-Emerald Rd",
    "iso:country":"AU",
    "sg:address":"218 Beaconsfield-Emerald Rd",
    "sg:city":"Beaconsfield",
    "sg:classifiers":[
        {
            "category":"Parking",
            "subcategory":"Lot",
            "type":"Transportation"
        }
    ],
    "sg:phone":"+61 3 9707 1411",
    "sg:postcode":"3807",
    "sg:province":"VIC",
    "sg:tags":[
        "vegetable",
        "packing",
        "fruit",
        "pack"
    ],
    "wof:name":"Addamo Fresh Pty Ltd",
    "wof:placetype":"venue"
},
  "geometry": {"coordinates":[145.379302978,-38.027469635],"type":"Point"}
}