{
  "type": "Feature",
  "properties": {
    "iso:country":"AU",
    "sg:address":"17 Haymer Crt",
    "sg:city":"Braeside",
    "sg:classifiers":[
        {
            "category":"Manufacturing",
            "subcategory":"Tools & Machinery",
            "type":"Manufacturing & Wholesale Goods"
        }
    ],
    "sg:phone":"+61 3 9587 4571",
    "sg:postcode":"3195",
    "sg:province":"VIC",
    "sg:tags":[
        "earth",
        "excavating",
        "moving",
        "equipment"
    ],
    "wof:name":"Flt Wholesale Pty Ltd",
    "wof:placetype":"venue"
},
  "geometry": {"coordinates":[145.10450744600001,-38.0106048584],"type":"Point"}
}