{
  "type": "Feature",
  "properties": {
    "addr:full":"152 Nielson St Lismore NSW 2480",
    "addr:housenumber":"152",
    "addr:postcode":"2480",
    "addr:street":"Nielson St",
    "iso:country":"AU",
    "sg:address":"152 Nielson St",
    "sg:city":"Lismore",
    "sg:classifiers":[
        {
            "category":"Education",
            "subcategory":"School",
            "type":"Public Place"
        }
    ],
    "sg:phone":"+61 2 6621 3363",
    "sg:postcode":"2480",
    "sg:province":"NSW",
    "sg:tags":[
        "state",
        "-",
        "nsw"
    ],
    "wof:name":"Wyrallah Road Public",
    "wof:placetype":"venue"
},
  "geometry": {"coordinates":[153.292724609,-28.8295078278],"type":"Point"}
}