{
  "type": "Feature",
  "properties": {
    "iso:country":"AU",
    "sg:address":"Shp 1/52 Rooty Hill Rd (North)",
    "sg:city":"Rooty Hill",
    "sg:classifiers":[
        {
            "category":"Real Estate",
            "subcategory":"Real Estate Agent",
            "type":"Services"
        }
    ],
    "sg:phone":"+61 2 9832 4000",
    "sg:postcode":"2766",
    "sg:province":"NSW",
    "wof:name":"Starr Partners Pty Ltd",
    "wof:placetype":"venue"
},
  "geometry": {"coordinates":[150.84257507300001,-33.7695426941],"type":"Point"}
}