{
  "type": "Feature",
  "properties": {
    "iso:country":"AU",
    "sg:address":"239 Beach St",
    "sg:city":"Frankston",
    "sg:classifiers":[
        {
            "category":"Retail",
            "subcategory":"Repair Shop",
            "type":"Services"
        }
    ],
    "sg:phone":"+61 3 8790 8633",
    "sg:postcode":"3199",
    "sg:province":"VIC",
    "sg:tags":[
        "machine",
        "repairs",
        "part",
        "dryer",
        "washing"
    ],
    "wof:name":"Peninsula Appliance Parts Pty Ltd",
    "wof:placetype":"venue"
},
  "geometry": {"coordinates":[145.14523315400001,-38.1483192444],"type":"Point"}
}