{
  "type": "Feature",
  "properties": {
    "addr:full":"14b Dee Rd Millgrove VIC 3799",
    "addr:housenumber":"14b",
    "addr:postcode":"3799",
    "addr:street":"Dee Rd",
    "iso:country":"AU",
    "sg:address":"14b Dee Rd",
    "sg:city":"Millgrove",
    "sg:classifiers":[
        {
            "category":"Professional",
            "subcategory":"Art Services",
            "type":"Services"
        }
    ],
    "sg:phone":"+61 3 5966 2438",
    "sg:postcode":"3799",
    "sg:province":"VIC",
    "sg:tags":[
        "artist"
    ],
    "wof:name":"McFadyen K C",
    "wof:placetype":"venue"
},
  "geometry": {"coordinates":[145.653762817,-37.7519378662],"type":"Point"}
}