{
  "type": "Feature",
  "properties": {
    "iso:country":"AU",
    "sg:address":"13a Napier St",
    "sg:city":"Condobolin",
    "sg:classifiers":[
        {
            "category":"Education",
            "subcategory":"School",
            "type":"Public Place"
        }
    ],
    "sg:phone":"+61 2 6895 2204",
    "sg:postcode":"2877",
    "sg:province":"NSW",
    "wof:name":"St Josephs School",
    "wof:placetype":"venue"
},
  "geometry": {"coordinates":[147.146515,-33.08506],"type":"Point"}
}