{
  "type": "Feature",
  "properties": {
    "addr:full":"75 Lacey Rd Carseldine QLD 4034",
    "addr:housenumber":"75",
    "addr:postcode":"4034",
    "addr:street":"Lacey Rd",
    "iso:country":"AU",
    "sg:address":"75 Lacey Rd",
    "sg:city":"Carseldine",
    "sg:classifiers":[
        {
            "category":"Building & Trades",
            "subcategory":"Construction",
            "type":"Services"
        }
    ],
    "sg:phone":"+61 7 3263 8350",
    "sg:postcode":"4034",
    "sg:province":"QLD",
    "sg:tags":[
        "roof"
    ],
    "wof:name":"Virginia Timbers & Trusses",
    "wof:placetype":"venue"
},
  "geometry": {"coordinates":[153.015152,-27.340931],"type":"Point"}
}