{
  "type": "Feature",
  "properties": {
    "addr:full":"4 New England Drv Woodcroft SA 5162",
    "addr:housenumber":"4",
    "addr:postcode":"5162",
    "addr:street":"New England Drv",
    "iso:country":"AU",
    "sg:address":"4 New England Drv",
    "sg:city":"Woodcroft",
    "sg:classifiers":[
        {
            "category":"Health Services",
            "subcategory":"Doctor",
            "type":"Services"
        }
    ],
    "sg:phone":"+61 8 8378 6910",
    "sg:postcode":"5162",
    "sg:province":"SA",
    "sg:tags":[
        "occupational",
        "safety"
    ],
    "wof:name":"I K Agencies",
    "wof:placetype":"venue"
},
  "geometry": {"coordinates":[138.54750060999999,-35.0976676941],"type":"Point"}
}