{
  "type": "Feature",
  "properties": {
    "addr:full":"3 Layton Crt Mill Park VIC 3082",
    "addr:housenumber":"3",
    "addr:postcode":"3082",
    "addr:street":"Layton Crt",
    "iso:country":"AU",
    "sg:address":"3 Layton Crt",
    "sg:city":"Mill Park",
    "sg:classifiers":[
        {
            "category":"Building & Trades",
            "subcategory":"Construction",
            "type":"Services"
        }
    ],
    "sg:phone":"+61 419 323 450",
    "sg:postcode":"3082",
    "sg:province":"VIC",
    "sg:tags":[
        "fencing",
        "contractor"
    ],
    "wof:name":"D.A.C Fencing",
    "wof:placetype":"venue"
},
  "geometry": {"coordinates":[145.05320739699999,-37.6729011536],"type":"Point"}
}