{
  "type": "Feature",
  "properties": {
    "addr:full":"55 Southpine Rd Brendale QLD 4500",
    "addr:housenumber":"55",
    "addr:postcode":"4500",
    "addr:street":"Southpine Rd",
    "iso:country":"AU",
    "sg:address":"55 Southpine Rd",
    "sg:city":"Brendale",
    "sg:classifiers":[
        {
            "category":"Autos & Motor Vehicles",
            "subcategory":"Automobile Sales",
            "type":"Retail Goods"
        }
    ],
    "sg:phone":"+61 7 3000 8000",
    "sg:postcode":"4500",
    "sg:province":"QLD",
    "sg:tags":[
        "car",
        "new"
    ],
    "wof:name":"Torque Toyota",
    "wof:placetype":"venue"
},
  "geometry": {"coordinates":[153.00845336899999,-27.317440033],"type":"Point"}
}