{
  "type": "Feature",
  "properties": {
    "iso:country":"AU",
    "sg:address":"Penrose Rd",
    "sg:city":"Cooinda Penrose",
    "sg:classifiers":[
        {
            "category":"Farming",
            "subcategory":"Berry Farm",
            "type":"Manufacturing & Wholesale Goods"
        }
    ],
    "sg:phone":"+61 2 4884 4336",
    "sg:postcode":"2579",
    "sg:province":"NSW",
    "sg:tags":[
        "fruit",
        "grower"
    ],
    "wof:name":"Penrose Berry Farm",
    "wof:placetype":"venue"
},
  "geometry": {"coordinates":[150.223022461,-34.6686859131],"type":"Point"}
}