{
  "type": "Feature",
  "properties": {
    "iso:country":"AU",
    "sg:address":"123 Aphrasia St",
    "sg:city":"Geelong",
    "sg:classifiers":[
        {
            "category":"Professional",
            "subcategory":"Engineering",
            "type":"Services"
        }
    ],
    "sg:phone":"+61 3 5221 3505",
    "sg:postcode":"3220",
    "sg:province":"VIC",
    "sg:tags":[
        "engineer"
    ],
    "wof:name":"Carr Engineered Equipment",
    "wof:placetype":"venue"
},
  "geometry": {"coordinates":[144.333542,-38.149773],"type":"Point"}
}