{
  "type": "Feature",
  "properties": {
    "addr:full":"134 Brewer Rd Bentleigh VIC 3204",
    "addr:housenumber":"134",
    "addr:postcode":"3204",
    "addr:street":"Brewer Rd",
    "iso:country":"AU",
    "sg:address":"134 Brewer Rd",
    "sg:city":"Bentleigh",
    "sg:classifiers":[
        {
            "category":"Social Services",
            "subcategory":"Child Care",
            "type":"Services"
        }
    ],
    "sg:phone":"+61 3 9557 1705",
    "sg:postcode":"3204",
    "sg:province":"VIC",
    "wof:name":"Bentleigh Family & Child Care Co-Operative Ltd",
    "wof:placetype":"venue"
},
  "geometry": {"coordinates":[145.03924599999999,-37.922478],"type":"Point"}
}