{
  "type": "Feature",
  "properties": {
    "iso:country":"AU",
    "sg:address":"90 Henty St",
    "sg:city":"Reservoir",
    "sg:classifiers":[
        {
            "category":"Home & Garden",
            "subcategory":"Building Materials",
            "type":"Retail Goods"
        }
    ],
    "sg:phone":"+61 3 9460 1773",
    "sg:postcode":"3073",
    "sg:province":"VIC",
    "sg:tags":[
        "decorative",
        "coating"
    ],
    "wof:name":"Mural Texture Manufacturers",
    "wof:placetype":"venue"
},
  "geometry": {"coordinates":[144.98793029800001,-37.717464447],"type":"Point"}
}