{
  "type": "Feature",
  "properties": {
    "iso:country":"AU",
    "sg:address":"234 Deakin Ave",
    "sg:city":"Mildura",
    "sg:classifiers":[
        {
            "category":"Banks & Credit Unions",
            "subcategory":"Investment Brokerage",
            "type":"Services"
        }
    ],
    "sg:phone":"+61 3 5022 7062",
    "sg:postcode":"3500",
    "sg:province":"VIC",
    "sg:tags":[
        "share",
        "broker",
        "stock"
    ],
    "wof:name":"Bridges Personal Investment Services",
    "wof:placetype":"venue"
},
  "geometry": {"coordinates":[142.15219116200001,-34.1941261292],"type":"Point"}
}