{
  "type": "Feature",
  "properties": {
    "addr:full":"100 Memorial Drv Eumundi QLD 4562",
    "addr:housenumber":"100",
    "addr:postcode":"4562",
    "addr:street":"Memorial Drv",
    "iso:country":"AU",
    "sg:address":"100 Memorial Drv",
    "sg:city":"Eumundi",
    "sg:classifiers":[
        {
            "category":"Wholesale",
            "subcategory":"Meat",
            "type":"Manufacturing & Wholesale Goods"
        }
    ],
    "sg:phone":"+61 7 5442 8244",
    "sg:postcode":"4562",
    "sg:province":"QLD",
    "sg:tags":[
        "abattoir"
    ],
    "wof:name":"Grays Slaughter Yards-Office",
    "wof:placetype":"venue"
},
  "geometry": {"coordinates":[152.950927734,-26.4752902985],"type":"Point"}
}