{
  "type": "Feature",
  "properties": {
    "iso:country":"AU",
    "sg:address":"13 A Landon St",
    "sg:city":"Fairfield East",
    "sg:classifiers":[
        {
            "category":"Building & Trades",
            "subcategory":"Construction",
            "type":"Services"
        }
    ],
    "sg:phone":"+61 2 9723 0169",
    "sg:postcode":"2165",
    "sg:province":"NSW",
    "sg:tags":[
        "fencing",
        "contractor"
    ],
    "wof:name":"Lauofo Fencing",
    "wof:placetype":"venue"
},
  "geometry": {"coordinates":[150.96954345699999,-33.8737602234],"type":"Point"}
}