{
  "type": "Feature",
  "properties": {
    "addr:full":"Surrey Downs Shopping Centre Golden Grove Rd Surrey Downs SA 5126",
    "addr:postcode":"5126",
    "addr:street":"Golden Grove Rd",
    "iso:country":"AU",
    "sg:address":"Surrey Downs Shopping Centre Golden Grove Rd",
    "sg:city":"Surrey Downs",
    "sg:classifiers":[
        {
            "category":"Personal",
            "subcategory":"Beauty Salon",
            "type":"Services"
        }
    ],
    "sg:phone":"+61 8 8251 4094",
    "sg:postcode":"5126",
    "sg:province":"SA",
    "sg:tags":[
        "hairdresser"
    ],
    "wof:name":"Hotcuts Hair & Beauty",
    "wof:placetype":"venue"
},
  "geometry": {"coordinates":[138.70463562,-34.8024253845],"type":"Point"}
}