{
  "type": "Feature",
  "properties": {
    "iso:country":"AU",
    "sg:address":"42 Mackley St",
    "sg:city":"Garbutt",
    "sg:classifiers":[
        {
            "category":"Manufacturing",
            "subcategory":"Tools & Machinery",
            "type":"Manufacturing & Wholesale Goods"
        }
    ],
    "sg:phone":"+61 7 4781 0222",
    "sg:postcode":"4814",
    "sg:province":"QLD",
    "sg:tags":[
        "earth",
        "excavating",
        "moving",
        "equipment"
    ],
    "wof:name":"Geographe",
    "wof:placetype":"venue"
},
  "geometry": {"coordinates":[146.767609,-19.27],"type":"Point"}
}