{
  "type": "Feature",
  "properties": {
    "addr:full":"109 Drummond St Carlton VIC 3053",
    "addr:housenumber":"109",
    "addr:postcode":"3053",
    "addr:street":"Drummond St",
    "iso:country":"AU",
    "sg:address":"109 Drummond St",
    "sg:city":"Carlton",
    "sg:classifiers":[
        {
            "category":"Professional",
            "subcategory":"Printing & Photocopies",
            "type":"Services"
        }
    ],
    "sg:phone":"+61 3 9662 2522",
    "sg:postcode":"3053",
    "sg:province":"VIC",
    "sg:tags":[
        "publishing",
        "desktop"
    ],
    "sg:website":"http://www.zoomdigital.com.au",
    "wof:name":"Zoom Digital Print Centre",
    "wof:placetype":"venue"
},
  "geometry": {"coordinates":[144.96766662600001,-37.804107666],"type":"Point"}
}