{
  "type": "Feature",
  "properties": {
    "addr:full":"271 Gooch St Thornbury VIC 3071",
    "addr:housenumber":"271",
    "addr:postcode":"3071",
    "addr:street":"Gooch St",
    "iso:country":"AU",
    "sg:address":"271 Gooch St",
    "sg:city":"Thornbury",
    "sg:classifiers":[
        {
            "category":"Building & Trades",
            "subcategory":"Plumbing",
            "type":"Services"
        }
    ],
    "sg:phone":"+61 3 9484 1260",
    "sg:postcode":"3071",
    "sg:province":"VIC",
    "sg:tags":[
        "plumber",
        "gasfitters"
    ],
    "wof:name":"Consolidated Plumbing",
    "wof:placetype":"venue"
},
  "geometry": {"coordinates":[145.02244567899999,-37.7600669861],"type":"Point"}
}