{
  "type": "Feature",
  "properties": {
    "addr:full":"21 Myamba Pde Surfside NSW 2536",
    "addr:housenumber":"21",
    "addr:postcode":"2536",
    "addr:street":"Myamba Pde",
    "iso:country":"AU",
    "sg:address":"21 Myamba Pde",
    "sg:city":"Surfside",
    "sg:classifiers":[
        {
            "category":"Retail",
            "subcategory":"Storage",
            "type":"Services"
        }
    ],
    "sg:phone":"+61 2 4472 5649",
    "sg:postcode":"2536",
    "sg:province":"NSW",
    "wof:name":"PR & DA O&#039;Brien",
    "wof:placetype":"venue"
},
  "geometry": {"coordinates":[150.19691467300001,-35.7011413574],"type":"Point"}
}