{
  "type": "Feature",
  "properties": {
    "addr:full":"34 McPherson St Banksmeadow NSW 2019",
    "addr:housenumber":"34",
    "addr:postcode":"2019",
    "addr:street":"Mcpherson St",
    "iso:country":"AU",
    "sg:address":"34 McPherson St",
    "sg:city":"Banksmeadow",
    "sg:classifiers":[
        {
            "category":"Landmark",
            "subcategory":"City Walls",
            "type":"Public Place"
        }
    ],
    "sg:phone":"+61 2 9666 6817",
    "sg:postcode":"2019",
    "sg:province":"NSW",
    "sg:tags":[
        "facing",
        "hard"
    ],
    "wof:name":"Trakell Welding & Engineering Pty Ltd",
    "wof:placetype":"venue"
},
  "geometry": {"coordinates":[151.21810913100001,-33.9585342407],"type":"Point"}
}