{
  "type": "Feature",
  "properties": {
    "addr:full":"Unit 3B, 90 Bourke Rd Alexandria NSW 2015",
    "addr:housenumber":"unit 3b 90",
    "addr:postcode":"2015",
    "addr:street":"Bourke Rd",
    "iso:country":"AU",
    "sg:address":"Unit 3B, 90 Bourke Rd",
    "sg:city":"Alexandria",
    "sg:classifiers":[
        {
            "category":"Professional",
            "type":"Services"
        }
    ],
    "sg:phone":"+61 2 8399 2844",
    "sg:postcode":"2015",
    "sg:province":"NSW",
    "sg:tags":[
        "auctioneer"
    ],
    "wof:name":"D & D Auctions & Consignment Centre",
    "wof:placetype":"venue"
},
  "geometry": {"coordinates":[151.195220947,-33.9108734131],"type":"Point"}
}