{
  "type": "Feature",
  "properties": {
    "addr:full":"181 Murray Ave Renmark SA 5341",
    "addr:housenumber":"181",
    "addr:postcode":"5341",
    "addr:street":"Murray Ave",
    "iso:country":"AU",
    "sg:address":"181 Murray Ave",
    "sg:city":"Renmark",
    "sg:classifiers":[
        {
            "category":"Fast Food",
            "type":"Food & Drink"
        }
    ],
    "sg:phone":"+61 8 8586 6349",
    "sg:postcode":"5341",
    "sg:province":"SA",
    "sg:tags":[
        "away",
        "take"
    ],
    "wof:name":"Big Bite Take Away",
    "wof:placetype":"venue"
},
  "geometry": {"coordinates":[140.750274658,-34.173084259],"type":"Point"}
}