{
  "type": "Feature",
  "properties": {
    "addr:full":"330 Railway Pde Carlton NSW 2218",
    "addr:housenumber":"330",
    "addr:postcode":"2218",
    "addr:street":"Railway Pde",
    "iso:country":"AU",
    "sg:address":"330 Railway Pde",
    "sg:city":"Carlton",
    "sg:classifiers":[
        {
            "category":"Real Estate",
            "subcategory":"Real Estate Agent",
            "type":"Services"
        }
    ],
    "sg:phone":"+61 2 9553 8191",
    "sg:postcode":"2218",
    "sg:province":"NSW",
    "wof:name":"Global Professionals Real Estate",
    "wof:placetype":"venue"
},
  "geometry": {"coordinates":[151.123199,-33.968891],"type":"Point"}
}