{
  "type": "Feature",
  "properties": {
    "iso:country":"AU",
    "sg:address":"52 Hilldale Drv",
    "sg:city":"Bolwarra Heights",
    "sg:classifiers":[
        {
            "category":"Professional",
            "subcategory":"Secretarial Services",
            "type":"Services"
        }
    ],
    "sg:phone":"+61 2 4930 0020",
    "sg:postcode":"2320",
    "sg:province":"NSW",
    "sg:tags":[
        "typing"
    ],
    "wof:name":"Champagne Secretarial Services",
    "wof:placetype":"venue"
},
  "geometry": {"coordinates":[151.582931519,-32.6908988953],"type":"Point"}
}