{
  "type": "Feature",
  "properties": {
    "iso:country":"AU",
    "sg:address":"103 Bassett St",
    "sg:city":"Hurstville",
    "sg:classifiers":[
        {
            "category":"Manufacturing",
            "subcategory":"Chemicals & Compounds",
            "type":"Manufacturing & Wholesale Goods"
        }
    ],
    "sg:phone":"+61 2 9579 6255",
    "sg:postcode":"2220",
    "sg:province":"NSW",
    "sg:tags":[
        "electroplating"
    ],
    "wof:name":"Illawarra Plating Works",
    "wof:placetype":"venue"
},
  "geometry": {"coordinates":[151.0884552,-33.9568252563],"type":"Point"}
}