{
  "type": "Feature",
  "properties": {
    "addr:full":"431 Liverpool St Darlinghurst NSW 2010",
    "addr:housenumber":"431",
    "addr:postcode":"2010",
    "addr:street":"Liverpool St",
    "iso:country":"AU",
    "sg:address":"431 Liverpool St",
    "sg:city":"Darlinghurst",
    "sg:classifiers":[
        {
            "category":"Real Estate",
            "subcategory":"Real Estate Agent",
            "type":"Services"
        }
    ],
    "sg:phone":"+61 2 9360 1311",
    "sg:postcode":"2010",
    "sg:province":"NSW",
    "wof:name":"Raine & Horne",
    "wof:placetype":"venue"
},
  "geometry": {"coordinates":[151.22271728499999,-33.8786621094],"type":"Point"}
}