{
  "type": "Feature",
  "properties": {
    "addr:full":"9 Church St Terrigal NSW 2260",
    "addr:housenumber":"9",
    "addr:postcode":"2260",
    "addr:street":"Church St",
    "iso:country":"AU",
    "sg:address":"9 Church St",
    "sg:city":"Terrigal",
    "sg:classifiers":[
        {
            "category":"Health Services",
            "subcategory":"Doctor",
            "type":"Services"
        }
    ],
    "sg:phone":"+61 2 4384 4383",
    "sg:postcode":"2260",
    "sg:province":"NSW",
    "sg:tags":[
        "medical",
        "practitioner"
    ],
    "wof:name":"Mayne Laverty Pathology Collection Centres",
    "wof:placetype":"venue"
},
  "geometry": {"coordinates":[151.444061,-33.447498],"type":"Point"}
}