{
  "type": "Feature",
  "properties": {
    "addr:full":"Suite 5, 31- 41 Kiora Rd Miranda NSW 2228",
    "addr:housenumber":"31 41",
    "addr:postcode":"2228",
    "addr:street":"Kiora Rd",
    "iso:country":"AU",
    "sg:address":"Suite 5, 31- 41 Kiora Rd",
    "sg:city":"Miranda",
    "sg:classifiers":[
        {
            "category":"Education",
            "subcategory":"Special Training",
            "type":"Public Place"
        }
    ],
    "sg:phone":"+61 2 9531 6222",
    "sg:postcode":"2228",
    "sg:province":"NSW",
    "sg:tags":[
        "tuition-educational"
    ],
    "wof:name":"MCP Education Centre",
    "wof:placetype":"venue"
},
  "geometry": {"coordinates":[151.10227966299999,-34.0339813232],"type":"Point"}
}