{
  "type": "Feature",
  "properties": {
    "addr:full":"PO Box 273 Abbotsford VIC 3067",
    "addr:postcode":"3067",
    "iso:country":"AU",
    "sg:address":"PO Box 273",
    "sg:city":"Abbotsford",
    "sg:classifiers":[
        {
            "category":"Professional",
            "subcategory":"Art Services",
            "type":"Services"
        }
    ],
    "sg:phone":"+61 422 416 488",
    "sg:postcode":"3067",
    "sg:province":"VIC",
    "sg:tags":[
        "picture",
        "frame",
        "framing"
    ],
    "wof:name":"Professional Art Installations",
    "wof:placetype":"venue"
},
  "geometry": {"coordinates":[145.00360107399999,-37.8037185669],"type":"Point"}
}