{
  "type": "Feature",
  "properties": {
    "addr:full":"281 Botany St Kingsford NSW 2032",
    "addr:housenumber":"281",
    "addr:postcode":"2032",
    "addr:street":"Botany St",
    "iso:country":"AU",
    "sg:address":"281 Botany St",
    "sg:city":"Kingsford",
    "sg:classifiers":[
        {
            "category":"Social Services",
            "type":"Services"
        }
    ],
    "sg:phone":"+61 2 9315 5704",
    "sg:postcode":"2032",
    "sg:province":"NSW",
    "sg:tags":[
        "kinesiology"
    ],
    "wof:name":"International Institute of Kinesiology Australia",
    "wof:placetype":"venue"
},
  "geometry": {"coordinates":[151.23190307600001,-33.9305801392],"type":"Point"}
}