{
  "type": "Feature",
  "properties": {
    "addr:full":"62 Macarthur St Griffith NSW 2680",
    "addr:housenumber":"62",
    "addr:postcode":"2680",
    "addr:street":"Macarthur St",
    "iso:country":"AU",
    "sg:address":"62 Macarthur St",
    "sg:city":"Griffith",
    "sg:classifiers":[
        {
            "category":"Farming",
            "subcategory":"Farm & Veterinary Services",
            "type":"Manufacturing & Wholesale Goods"
        }
    ],
    "sg:phone":"+61 2 6962 4223",
    "sg:postcode":"2680",
    "sg:province":"NSW",
    "sg:tags":[
        "shearing",
        "contractor"
    ],
    "wof:name":"Dickie J C & R J",
    "wof:placetype":"venue"
},
  "geometry": {"coordinates":[146.05470299999999,-34.281071],"type":"Point"}
}