{
  "type": "Feature",
  "properties": {
    "addr:full":"154 Gympie Rd Maryborough QLD 4650",
    "addr:housenumber":"154",
    "addr:postcode":"4650",
    "addr:street":"Gympie Rd",
    "iso:country":"AU",
    "sg:address":"154 Gympie Rd",
    "sg:city":"Maryborough",
    "sg:classifiers":[
        {
            "category":"Autos & Motor Vehicles",
            "subcategory":"Fuel & Gas Station",
            "type":"Retail Goods"
        }
    ],
    "sg:phone":"+61 7 4121 0355",
    "sg:postcode":"4650",
    "sg:province":"QLD",
    "wof:name":"Ned Kellys Service Station",
    "wof:placetype":"venue"
},
  "geometry": {"coordinates":[152.68168600000001,-25.546227],"type":"Point"}
}