{
  "type": "Feature",
  "properties": {
    "addr:full":"20 Irwin Rd Elimbah QLD 4516",
    "addr:housenumber":"20",
    "addr:postcode":"4516",
    "addr:street":"Irwin Rd",
    "iso:country":"AU",
    "sg:address":"20 Irwin Rd",
    "sg:city":"Elimbah",
    "sg:classifiers":[
        {
            "category":"Building & Trades",
            "subcategory":"Plumbing",
            "type":"Services"
        }
    ],
    "sg:phone":"+61 417 791 514",
    "sg:postcode":"4516",
    "sg:province":"QLD",
    "sg:tags":[
        "drainers"
    ],
    "wof:name":"P & K Drain Cleaners",
    "wof:placetype":"venue"
},
  "geometry": {"coordinates":[152.95640599999999,-27.022331],"type":"Point"}
}