{
  "type": "Feature",
  "properties": {
    "addr:full":"Shop 2- 3 Junction Rd Mossman QLD 4873",
    "addr:housenumber":"shop;3",
    "addr:postcode":"4873",
    "addr:street":"Junction Rd",
    "iso:country":"AU",
    "sg:address":"Shop 2- 3 Junction Rd",
    "sg:city":"Mossman",
    "sg:classifiers":[
        {
            "category":"Shopping",
            "subcategory":"Pets & Pet Supplies",
            "type":"Retail Goods"
        }
    ],
    "sg:phone":"+61 7 4098 2137",
    "sg:postcode":"4873",
    "sg:province":"QLD",
    "sg:tags":[
        "food"
    ],
    "wof:name":"Pet & Produce Pantry",
    "wof:placetype":"venue"
},
  "geometry": {"coordinates":[145.37503051799999,-16.456785202],"type":"Point"}
}