{
  "type": "Feature",
  "properties": {
    "iso:country":"AU",
    "sg:address":"6 Dicameron Crt",
    "sg:city":"Thornlands",
    "sg:classifiers":[
        {
            "category":"Building & Trades",
            "subcategory":"Landscaping Services",
            "type":"Services"
        }
    ],
    "sg:phone":"+61 7 3206 3528",
    "sg:postcode":"4164",
    "sg:province":"QLD",
    "sg:tags":[
        "designer",
        "landscape",
        "contractor"
    ],
    "wof:name":"Thornlandscapes",
    "wof:placetype":"venue"
},
  "geometry": {"coordinates":[153.25584411599999,-27.564453125],"type":"Point"}
}