{
  "type": "Feature",
  "properties": {
    "addr:full":"PO Box 196 Boyup Brook WA 6244",
    "addr:postcode":"6244",
    "iso:country":"AU",
    "sg:address":"PO Box 196",
    "sg:city":"Boyup Brook",
    "sg:classifiers":[
        {
            "category":"Building & Trades",
            "subcategory":"Construction",
            "type":"Services"
        }
    ],
    "sg:phone":"+61 8 9765 1810",
    "sg:postcode":"6244",
    "sg:province":"WA",
    "sg:tags":[
        "earth",
        "excavating",
        "moving",
        "contractor"
    ],
    "wof:name":"Chapman JF & DN",
    "wof:placetype":"venue"
},
  "geometry": {"coordinates":[116.388328552,-33.8355484009],"type":"Point"}
}