{
  "type": "Feature",
  "properties": {
    "iso:country":"AU",
    "sg:address":"Shp5/ 2 Fielding St",
    "sg:city":"Collaroy",
    "sg:classifiers":[
        {
            "category":"Food & Beverages",
            "subcategory":"Bakery",
            "type":"Retail Goods"
        }
    ],
    "sg:phone":"+61 2 9971 4056",
    "sg:postcode":"2097",
    "sg:province":"NSW",
    "sg:tags":[
        "cake",
        "shop",
        "pastry"
    ],
    "wof:name":"Pattiserie De Collaroy",
    "wof:placetype":"venue"
},
  "geometry": {"coordinates":[151.30044555699999,-33.7309455872],"type":"Point"}
}