{
  "type": "Feature",
  "properties": {
    "addr:full":"91 Turton Rd Waratah NSW 2298",
    "addr:housenumber":"91",
    "addr:postcode":"2298",
    "addr:street":"Turton Rd",
    "iso:country":"AU",
    "sg:address":"91 Turton Rd",
    "sg:city":"Waratah",
    "sg:classifiers":[
        {
            "category":"Fast Food",
            "type":"Food & Drink"
        }
    ],
    "sg:phone":"+61 2 4968 8318",
    "sg:postcode":"2298",
    "sg:province":"NSW",
    "sg:tags":[
        "away",
        "take"
    ],
    "wof:name":"Red Rooster",
    "wof:placetype":"venue"
},
  "geometry": {"coordinates":[151.727096558,-32.9080200195],"type":"Point"}
}