{
  "type": "Feature",
  "properties": {
    "iso:country":"AU",
    "sg:address":"12 Bachmann St",
    "sg:city":"Chermside West",
    "sg:classifiers":[
        {
            "category":"Retail",
            "subcategory":"Auto Rental",
            "type":"Services"
        }
    ],
    "sg:phone":"+61 7 3256 4136",
    "sg:postcode":"4032",
    "sg:province":"QLD",
    "sg:tags":[
        "car",
        "hire",
        "minibus"
    ],
    "wof:name":"Cut Rate Car Rentals",
    "wof:placetype":"venue"
},
  "geometry": {"coordinates":[153.020493,-27.386204],"type":"Point"}
}