{
  "type": "Feature",
  "properties": {
    "addr:full":"13 Glencoe St Bendigo VIC 3550",
    "addr:housenumber":"13",
    "addr:postcode":"3550",
    "addr:street":"Glencoe St",
    "iso:country":"AU",
    "sg:address":"13 Glencoe St",
    "sg:city":"Bendigo",
    "sg:classifiers":[
        {
            "category":"Home & Garden",
            "subcategory":"Hardware",
            "type":"Retail Goods"
        }
    ],
    "sg:phone":"+61 3 5443 6550",
    "sg:postcode":"3550",
    "sg:province":"VIC",
    "sg:tags":[
        "woodworking",
        "machinery"
    ],
    "wof:name":"Procraft",
    "wof:placetype":"venue"
},
  "geometry": {"coordinates":[144.29612731899999,-36.764995575],"type":"Point"}
}