{
  "type": "Feature",
  "properties": {
    "addr:full":"144 Olsen Ave Arundel QLD 4214",
    "addr:housenumber":"144",
    "addr:postcode":"4214",
    "addr:street":"Olsen Ave",
    "iso:country":"AU",
    "sg:address":"144 Olsen Ave",
    "sg:city":"Arundel",
    "sg:classifiers":[
        {
            "category":"Real Estate",
            "subcategory":"Real Estate Agent",
            "type":"Services"
        }
    ],
    "sg:phone":"+61 7 5594 7788",
    "sg:postcode":"4214",
    "sg:province":"QLD",
    "wof:name":"Century 21 Clifton Delaney",
    "wof:placetype":"venue"
},
  "geometry": {"coordinates":[153.38050842300001,-27.9571857452],"type":"Point"}
}