{
  "type": "Feature",
  "properties": {
    "addr:full":"19 Chapman Pl Eagle Farm QLD 4009",
    "addr:housenumber":"19",
    "addr:postcode":"4009",
    "addr:street":"Chapman Pl",
    "iso:country":"AU",
    "sg:address":"19 Chapman Pl",
    "sg:city":"Eagle Farm",
    "sg:classifiers":[
        {
            "category":"Professional",
            "type":"Services"
        }
    ],
    "sg:phone":"+61 7 3121 1700",
    "sg:postcode":"4009",
    "sg:province":"QLD",
    "sg:tags":[
        "forwarding",
        "agent",
        "transport"
    ],
    "wof:name":"Sadleirs International",
    "wof:placetype":"venue"
},
  "geometry": {"coordinates":[153.099243164,-27.4329872131],"type":"Point"}
}