{
  "type": "Feature",
  "properties": {
    "addr:full":"21 Station St Bowral NSW 2576",
    "addr:housenumber":"21",
    "addr:postcode":"2576",
    "addr:street":"Station St",
    "iso:country":"AU",
    "sg:address":"21 Station St",
    "sg:city":"Bowral",
    "sg:classifiers":[
        {
            "category":"Real Estate",
            "subcategory":"Real Estate Services",
            "type":"Services"
        }
    ],
    "sg:phone":"+61 2 4861 4444",
    "sg:postcode":"2576",
    "sg:province":"NSW",
    "sg:tags":[
        "auctioneer"
    ],
    "wof:name":"Raine & Horne Bowral",
    "wof:placetype":"venue"
},
  "geometry": {"coordinates":[150.41644287099999,-34.4794502258],"type":"Point"}
}