{
  "type": "Feature",
  "properties": {
    "addr:full":"Shp1/ 130 Anzac Pde Kensington NSW 2033",
    "addr:housenumber":"130",
    "addr:postcode":"2033",
    "addr:street":"Anzac Pde",
    "iso:country":"AU",
    "sg:address":"Shp1/ 130 Anzac Pde",
    "sg:city":"Kensington",
    "sg:classifiers":[
        {
            "category":"Restaurant",
            "type":"Food & Drink"
        }
    ],
    "sg:phone":"+61 2 9697 0040",
    "sg:postcode":"2033",
    "sg:province":"NSW",
    "wof:name":"Curry Beans",
    "wof:placetype":"venue"
},
  "geometry": {"coordinates":[151.22297699999999,-33.910633],"type":"Point"}
}