{
  "type": "Feature",
  "properties": {
    "addr:full":"PO Box 2446 North Parramatta NSW 2151",
    "addr:postcode":"2151",
    "iso:country":"AU",
    "sg:address":"PO Box 2446",
    "sg:city":"North Parramatta",
    "sg:classifiers":[
        {
            "category":"Shopping",
            "subcategory":"Mobile Phones",
            "type":"Retail Goods"
        }
    ],
    "sg:phone":"+61 414 310 101",
    "sg:postcode":"2151",
    "sg:province":"NSW",
    "sg:tags":[
        "telephone",
        "accessory"
    ],
    "wof:name":"Advanced Cellular International",
    "wof:placetype":"venue"
},
  "geometry": {"coordinates":[151.010131836,-33.7986602783],"type":"Point"}
}