{
  "type": "Feature",
  "properties": {
    "iso:country":"AU",
    "sg:address":"8 McGregor St",
    "sg:city":"Toowoomba",
    "sg:classifiers":[
        {
            "category":"Shopping",
            "subcategory":"Stationery & Office Supplies",
            "type":"Retail Goods"
        }
    ],
    "sg:phone":"+61 7 4633 4888",
    "sg:postcode":"4350",
    "sg:province":"QLD",
    "sg:tags":[
        "equipment",
        "badge",
        "making"
    ],
    "wof:name":"B.B. Badges",
    "wof:placetype":"venue"
},
  "geometry": {"coordinates":[151.92453,-27.550079],"type":"Point"}
}