{
  "type": "Feature",
  "properties": {
    "iso:country":"AU",
    "sg:address":"office 2 14 Kay Ave",
    "sg:city":"Berri",
    "sg:classifiers":[
        {
            "category":"Health Services",
            "subcategory":"Chiropractor",
            "type":"Services"
        }
    ],
    "sg:phone":"+61 8 8582 3272",
    "sg:postcode":"5343",
    "sg:province":"SA",
    "wof:name":"Berri Family Chiropractic Centre",
    "wof:placetype":"venue"
},
  "geometry": {"coordinates":[140.603912353,-34.2840957642],"type":"Point"}
}