{
  "type": "Feature",
  "properties": {
    "iso:country":"AU",
    "sg:address":"80 Antimony St",
    "sg:city":"Carole Park",
    "sg:classifiers":[
        {
            "category":"Retail",
            "subcategory":"Auto Repair",
            "type":"Services"
        }
    ],
    "sg:phone":"+61 7 3271 3031",
    "sg:postcode":"4300",
    "sg:province":"QLD",
    "sg:tags":[
        "recapping",
        "repairing",
        "retreading",
        "tyre"
    ],
    "wof:name":"Austread Tyres Pty Ltd",
    "wof:placetype":"venue"
},
  "geometry": {"coordinates":[152.93751525900001,-27.619512558],"type":"Point"}
}