{
  "type": "Feature",
  "properties": {
    "addr:full":"12 Queen St Rutherford NSW 2320",
    "addr:housenumber":"12",
    "addr:postcode":"2320",
    "addr:street":"Queen St",
    "iso:country":"AU",
    "sg:address":"12 Queen St",
    "sg:city":"Rutherford",
    "sg:classifiers":[
        {
            "category":"Personal",
            "type":"Services"
        }
    ],
    "sg:phone":"+61 2 4932 5276",
    "sg:postcode":"2320",
    "sg:province":"NSW",
    "sg:tags":[
        "wallpapering",
        "wallcovering"
    ],
    "wof:name":"Dunn P J & P A",
    "wof:placetype":"venue"
},
  "geometry": {"coordinates":[151.53712463400001,-32.7187347412],"type":"Point"}
}