{
  "type": "Feature",
  "properties": {
    "iso:country":"AU",
    "sg:address":"6-8 Kayleigh Drv",
    "sg:city":"Maroochydore",
    "sg:classifiers":[
        {
            "category":"Home & Garden",
            "subcategory":"Carpets & Floor Coverings",
            "type":"Retail Goods"
        }
    ],
    "sg:phone":"+61 7 5479 2344",
    "sg:postcode":"4558",
    "sg:province":"QLD",
    "sg:tags":[
        "wood"
    ],
    "wof:name":"Direct Line Timbers",
    "wof:placetype":"venue"
},
  "geometry": {"coordinates":[153.09039306599999,-26.6701431274],"type":"Point"}
}