{
  "type": "Feature",
  "properties": {
    "addr:full":"106 Richmond Rd Keswick SA 5035",
    "addr:housenumber":"106",
    "addr:postcode":"5035",
    "addr:street":"Richmond Rd",
    "iso:country":"AU",
    "sg:address":"106 Richmond Rd",
    "sg:city":"Keswick",
    "sg:classifiers":[
        {
            "category":"Landmark",
            "subcategory":"Fountain",
            "type":"Public Place"
        }
    ],
    "sg:phone":"+61 8 8297 9022",
    "sg:postcode":"5035",
    "sg:province":"SA",
    "sg:tags":[
        "wholesaler",
        "spring",
        "mfrs"
    ],
    "wof:name":"Pedders Suspension",
    "wof:placetype":"venue"
},
  "geometry": {"coordinates":[138.572555542,-34.9421615601],"type":"Point"}
}