{
  "type": "Feature",
  "properties": {
    "iso:country":"AU",
    "sg:address":"4 Second Ave",
    "sg:city":"Canley Vale",
    "sg:classifiers":[
        {
            "category":"Building & Trades",
            "subcategory":"Cleaning & Sanitation",
            "type":"Services"
        }
    ],
    "sg:phone":"+61 2 9755 7313",
    "sg:postcode":"2166",
    "sg:province":"NSW",
    "sg:tags":[
        "industrial",
        "commercial",
        "contractor"
    ],
    "wof:name":"Diamond Cleaning",
    "wof:placetype":"venue"
},
  "geometry": {"coordinates":[150.94549560600001,-33.8865394592],"type":"Point"}
}