{
  "type": "Feature",
  "properties": {
    "addr:full":"Level 1 125 Grey St Albany WA 6330",
    "addr:housenumber":"125",
    "addr:postcode":"6330",
    "addr:street":"Grey St",
    "iso:country":"AU",
    "sg:address":"Level 1 125 Grey St",
    "sg:city":"Albany",
    "sg:classifiers":[
        {
            "category":"Banks & Credit Unions",
            "subcategory":"Investment Brokerage",
            "type":"Services"
        }
    ],
    "sg:phone":"+61 8 9842 6690",
    "sg:postcode":"6330",
    "sg:province":"WA",
    "sg:tags":[
        "finance",
        "broker"
    ],
    "wof:name":"Albany Home Loans",
    "wof:placetype":"venue"
},
  "geometry": {"coordinates":[117.884307861,-35.023979187],"type":"Point"}
}