{
  "type": "Feature",
  "properties": {
    "iso:country":"AU",
    "sg:address":"PO Box 549",
    "sg:city":"Paddington",
    "sg:classifiers":[
        {
            "category":"Shopping",
            "subcategory":"Mobile Phones",
            "type":"Retail Goods"
        }
    ],
    "sg:phone":"+61 1800 008 068",
    "sg:postcode":"4064",
    "sg:province":"QLD",
    "sg:tags":[
        "telephone",
        "accessory"
    ],
    "sg:website":"http://www.futurecom.com.au",
    "wof:name":"Future Communication Solutions",
    "wof:placetype":"venue"
},
  "geometry": {"coordinates":[153.007736206,-27.4666595459],"type":"Point"}
}