{
  "type": "Feature",
  "properties": {
    "iso:country":"AU",
    "sg:address":"5 Morse Pl",
    "sg:city":"Morley",
    "sg:classifiers":[
        {
            "category":"Professional",
            "subcategory":"Employment Agencies",
            "type":"Services"
        }
    ],
    "sg:phone":"+61 419 911 080",
    "sg:postcode":"6062",
    "sg:province":"WA",
    "sg:tags":[
        "entertainer",
        "agent"
    ],
    "wof:name":"Lip Service",
    "wof:placetype":"venue"
},
  "geometry": {"coordinates":[115.925971985,-31.8867473602],"type":"Point"}
}