{
  "type": "Feature",
  "properties": {
    "addr:full":"27 View St Chatswood NSW 2067",
    "addr:housenumber":"27",
    "addr:postcode":"2067",
    "addr:street":"View St",
    "iso:country":"AU",
    "sg:address":"27 View St",
    "sg:city":"Chatswood",
    "sg:classifiers":[
        {
            "category":"Building & Trades",
            "subcategory":"Construction",
            "type":"Services"
        }
    ],
    "sg:phone":"+61 418 288 354",
    "sg:postcode":"2067",
    "sg:province":"NSW",
    "sg:tags":[
        "stonework",
        "stone",
        "mason"
    ],
    "wof:name":"Stone Concepts",
    "wof:placetype":"venue"
},
  "geometry": {"coordinates":[151.17837524399999,-33.7937545776],"type":"Point"}
}