{
  "type": "Feature",
  "properties": {
    "addr:full":"136 Pringle Ave Belrose NSW 2085",
    "addr:housenumber":"136",
    "addr:postcode":"2085",
    "addr:street":"Pringle Ave",
    "iso:country":"AU",
    "sg:address":"136 Pringle Ave",
    "sg:city":"Belrose",
    "sg:classifiers":[
        {
            "category":"Building & Trades",
            "subcategory":"Cleaning & Sanitation",
            "type":"Services"
        }
    ],
    "sg:phone":"+61 2 9451 7685",
    "sg:postcode":"2085",
    "sg:province":"NSW",
    "sg:tags":[
        "industrial",
        "commercial",
        "contractor"
    ],
    "wof:name":"Alken Services Pty Ltd",
    "wof:placetype":"venue"
},
  "geometry": {"coordinates":[151.21548461899999,-33.7305793762],"type":"Point"}
}