{
  "type": "Feature",
  "properties": {
    "addr:full":"547 Kessels Rd MacGregor QLD 4109",
    "addr:housenumber":"547",
    "addr:postcode":"4109",
    "addr:street":"Kessels Rd",
    "iso:country":"AU",
    "sg:address":"547 Kessels Rd",
    "sg:city":"MacGregor",
    "sg:classifiers":[
        {
            "category":"Building & Trades",
            "subcategory":"Construction",
            "type":"Services"
        }
    ],
    "sg:phone":"+61 7 3343 8800",
    "sg:postcode":"4109",
    "sg:province":"QLD",
    "sg:tags":[
        "window",
        "tinting"
    ],
    "wof:name":"Tint-A-Car/Tint-A-Glass",
    "wof:placetype":"venue"
},
  "geometry": {"coordinates":[153.06959533700001,-27.5617160797],"type":"Point"}
}