{
  "type": "Feature",
  "properties": {
    "addr:full":"25 Myers St Geelong VIC 3220",
    "addr:housenumber":"25",
    "addr:postcode":"3220",
    "addr:street":"Myers St",
    "iso:country":"AU",
    "sg:address":"25 Myers St",
    "sg:city":"Geelong",
    "sg:classifiers":[
        {
            "category":"Retail",
            "subcategory":"Funeral Services",
            "type":"Services"
        }
    ],
    "sg:phone":"+61 3 5222 3688",
    "sg:postcode":"3220",
    "sg:province":"VIC",
    "sg:tags":[
        "director"
    ],
    "sg:website":"http://www.kingsaustralia.com.au",
    "wof:name":"Kings Funeral Service",
    "wof:placetype":"venue"
},
  "geometry": {"coordinates":[144.354415894,-38.149936676],"type":"Point"}
}