{
  "type": "Feature",
  "properties": {
    "iso:country":"AU",
    "sg:address":"10 Gillen Crt",
    "sg:city":"Padbury",
    "sg:classifiers":[
        {
            "category":"Autos & Motor Vehicles",
            "subcategory":"Automobile Sales",
            "type":"Retail Goods"
        }
    ],
    "sg:phone":"+61 8 9401 1542",
    "sg:postcode":"6025",
    "sg:province":"WA",
    "sg:tags":[
        "car",
        "used"
    ],
    "wof:name":"Barnett G R",
    "wof:placetype":"venue"
},
  "geometry": {"coordinates":[115.760299683,-31.8025417328],"type":"Point"}
}