{
  "type": "Feature",
  "properties": {
    "iso:country":"AU",
    "sg:address":"14 Wilson St",
    "sg:city":"Kalgoorlie",
    "sg:classifiers":[
        {
            "category":"Banks & Credit Unions",
            "subcategory":"Bank",
            "type":"Services"
        }
    ],
    "sg:phone":"+61 8 9091 4544",
    "sg:postcode":"6430",
    "sg:province":"WA",
    "sg:tags":[
        "equipment",
        "sale",
        "point"
    ],
    "wof:name":"Online Business Equipment",
    "wof:placetype":"venue"
},
  "geometry": {"coordinates":[121.468727112,-30.7479953766],"type":"Point"}
}