{
  "type": "Feature",
  "properties": {
    "iso:country":"AU",
    "sg:address":"Suite 22/Level 3 25 Walters Drv",
    "sg:city":"Osborne Park",
    "sg:classifiers":[
        {
            "category":"Organizations",
            "subcategory":"Professional Association",
            "type":"Services"
        }
    ],
    "sg:phone":"+61 8 9446 6411",
    "sg:postcode":"6017",
    "sg:province":"WA",
    "sg:tags":[
        "web",
        "internet"
    ],
    "wof:name":"Himladeon Pty Ltd",
    "wof:placetype":"venue"
},
  "geometry": {"coordinates":[115.80911254900001,-31.9092922211],"type":"Point"}
}