{
  "type": "Feature",
  "properties": {
    "addr:full":"Cnr Edinburgh & Allenby Rds Lilydale VIC 3140",
    "addr:postcode":"3140",
    "addr:street":"Cnr",
    "iso:country":"AU",
    "sg:address":"Cnr Edinburgh & Allenby Rds",
    "sg:city":"Lilydale",
    "sg:classifiers":[
        {
            "category":"Education",
            "subcategory":"School",
            "type":"Public Place"
        }
    ],
    "sg:phone":"+61 3 9728 8833",
    "sg:postcode":"3140",
    "sg:province":"VIC",
    "sg:tags":[
        "co-educational"
    ],
    "wof:name":"Edinburgh Adventist Primary School",
    "wof:placetype":"venue"
},
  "geometry": {"coordinates":[145.35084533700001,-37.777961731],"type":"Point"}
}