{
  "type": "Feature",
  "properties": {
    "addr:full":"Suite 5 Aralia St Shopping Complex 66 Aralia St Nightcliff NT 0810",
    "addr:housenumber":"66",
    "addr:postcode":"nt 0810",
    "addr:street":"Aralia St;Aralia St",
    "iso:country":"AU",
    "sg:address":"Suite 5 Aralia St Shopping Complex 66 Aralia St",
    "sg:city":"Nightcliff",
    "sg:classifiers":[
        {
            "category":"Health Services",
            "subcategory":"Doctor",
            "type":"Services"
        }
    ],
    "sg:phone":"+61 8 8985 3754",
    "sg:postcode":"0810",
    "sg:province":"NT",
    "sg:tags":[
        "medical",
        "practitioner"
    ],
    "wof:name":"Ramdoss C G",
    "wof:placetype":"venue"
},
  "geometry": {"coordinates":[130.849685669,-12.3790082932],"type":"Point"}
}