{
  "type": "Feature",
  "properties": {
    "addr:full":"Unit 2/ 1 Station St Subiaco WA 6008",
    "addr:housenumber":"1",
    "addr:postcode":"6008",
    "addr:street":"Station St",
    "iso:country":"AU",
    "sg:address":"Unit 2/ 1 Station St",
    "sg:city":"Subiaco",
    "sg:classifiers":[
        {
            "category":"Professional",
            "subcategory":"Computer Services",
            "type":"Services"
        }
    ],
    "sg:phone":"+61 1300 485 627",
    "sg:postcode":"6008",
    "sg:province":"WA",
    "sg:tags":[
        "training"
    ],
    "wof:name":"Hands On Computer Training International",
    "wof:placetype":"venue"
},
  "geometry": {"coordinates":[115.822937012,-31.9418983459],"type":"Point"}
}