{
  "type": "Feature",
  "properties": {
    "addr:full":"9 Hearty St Blackburn South VIC 3130",
    "addr:housenumber":"9",
    "addr:postcode":"3130",
    "addr:street":"Hearty St",
    "iso:country":"AU",
    "sg:address":"9 Hearty St",
    "sg:city":"Blackburn South",
    "sg:classifiers":[
        {
            "category":"Personal",
            "subcategory":"Beauty Salon",
            "type":"Services"
        }
    ],
    "sg:phone":"+61 3 9877 2416",
    "sg:postcode":"3130",
    "sg:province":"VIC",
    "wof:name":"Rejuvenate",
    "wof:placetype":"venue"
},
  "geometry": {"coordinates":[145.15330505399999,-37.8404159546],"type":"Point"}
}