{
  "type": "Feature",
  "properties": {
    "iso:country":"AU",
    "sg:address":"Shop 3 150 Kelletts Rd",
    "sg:city":"Rowville",
    "sg:classifiers":[
        {
            "category":"Fast Food",
            "type":"Food & Drink"
        }
    ],
    "sg:phone":"+61 3 9753 4207",
    "sg:postcode":"3178",
    "sg:province":"VIC",
    "sg:tags":[
        "away",
        "take"
    ],
    "wof:name":"Kelletts Charcoal Chicken",
    "wof:placetype":"venue"
},
  "geometry": {"coordinates":[145.257415772,-37.9132537842],"type":"Point"}
}