{
  "type": "Feature",
  "properties": {
    "iso:country":"AU",
    "sg:address":"14 Yabtree St",
    "sg:city":"Wagga Wagga",
    "sg:classifiers":[
        {
            "category":"Health Services",
            "subcategory":"Doctor",
            "type":"Services"
        }
    ],
    "sg:phone":"+61 2 6938 6492",
    "sg:postcode":"2650",
    "sg:province":"NSW",
    "sg:tags":[
        "medical",
        "practitioner"
    ],
    "wof:name":"Sexual Health Clinic",
    "wof:placetype":"venue"
},
  "geometry": {"coordinates":[147.35829162600001,-35.1185951233],"type":"Point"}
}