{
  "type": "Feature",
  "properties": {
    "iso:country":"AU",
    "sg:address":"Lvl 2, 35 Astor Tce",
    "sg:city":"Spring Hill",
    "sg:classifiers":[
        {
            "category":"Health Services",
            "subcategory":"Health Practitioner",
            "type":"Services"
        }
    ],
    "sg:phone":"+61 7 3833 6735",
    "sg:postcode":"4000",
    "sg:province":"QLD",
    "sg:tags":[
        "psychotherapist"
    ],
    "sg:website":"http://www.hypnotherapyqueensland.com",
    "wof:name":"Peter McMahon",
    "wof:placetype":"venue"
},
  "geometry": {"coordinates":[153.025634766,-27.4637088776],"type":"Point"}
}