{
  "type": "Feature",
  "properties": {
    "iso:country":"AU",
    "sg:address":"11 Rider St",
    "sg:city":"Seacombe Gardens",
    "sg:classifiers":[
        {
            "category":"Retail",
            "subcategory":"Auto Repair",
            "type":"Services"
        }
    ],
    "sg:phone":"+61 8 8358 3535",
    "sg:postcode":"5047",
    "sg:province":"SA",
    "sg:tags":[
        "repairer",
        "motor",
        "engineer"
    ],
    "wof:name":"Al's Chevy Garage",
    "wof:placetype":"venue"
},
  "geometry": {"coordinates":[138.545944,-35.022728],"type":"Point"}
}