{
  "type": "Feature",
  "properties": {
    "iso:country":"AU",
    "sg:address":"312 Pease St",
    "sg:city":"Edge Hill",
    "sg:classifiers":[
        {
            "category":"Building & Trades",
            "subcategory":"Landscaping Services",
            "type":"Services"
        }
    ],
    "sg:phone":"+61 7 4032 2131",
    "sg:postcode":"4870",
    "sg:province":"QLD",
    "sg:tags":[
        "architect",
        "landscape"
    ],
    "wof:name":"GGI Landscape Architects",
    "wof:placetype":"venue"
},
  "geometry": {"coordinates":[145.74232482900001,-16.9008636475],"type":"Point"}
}