{
  "type": "Feature",
  "properties": {
    "iso:country":"AU",
    "sg:address":"26 Dower St",
    "sg:city":"Mandurah",
    "sg:classifiers":[
        {
            "category":"Professional",
            "subcategory":"Accounting & Tax Preparation",
            "type":"Services"
        }
    ],
    "sg:phone":"+61 8 9535 1093",
    "sg:postcode":"6210",
    "sg:province":"WA",
    "sg:tags":[
        "consultant",
        "taxation"
    ],
    "wof:name":"Kaye L Preen & Associates",
    "wof:placetype":"venue"
},
  "geometry": {"coordinates":[115.73944899999999,-32.531277],"type":"Point"}
}