{
  "type": "Feature",
  "properties": {
    "addr:full":"PO Box 212 Kyneton VIC 3444",
    "addr:postcode":"3444",
    "iso:country":"AU",
    "sg:address":"PO Box 212",
    "sg:city":"Kyneton",
    "sg:classifiers":[
        {
            "category":"Building & Trades",
            "subcategory":"Construction",
            "type":"Services"
        }
    ],
    "sg:phone":"+61 3 5422 3081",
    "sg:postcode":"3444",
    "sg:province":"VIC",
    "sg:tags":[
        "excavation",
        "foundation"
    ],
    "wof:name":"Boyers Excavations",
    "wof:placetype":"venue"
},
  "geometry": {"coordinates":[144.456954956,-37.2511405945],"type":"Point"}
}