{
  "type": "Feature",
  "properties": {
    "addr:full":"Level 2 TCG Centre 80 Mitchell St Darwin NT 0801",
    "addr:housenumber":"80",
    "addr:postcode":"nt 0801",
    "addr:street":"Mitchell St",
    "iso:country":"AU",
    "sg:address":"Level 2 TCG Centre 80 Mitchell St",
    "sg:city":"Darwin",
    "sg:classifiers":[
        {
            "category":"Professional",
            "subcategory":"Engineering",
            "type":"Services"
        }
    ],
    "sg:phone":"+61 8 8981 7500",
    "sg:postcode":"0801",
    "sg:province":"NT",
    "sg:tags":[
        "consulting",
        "engineer"
    ],
    "wof:name":"Qantec McWilliam Consulting Engineers",
    "wof:placetype":"venue"
},
  "geometry": {"coordinates":[130.837432861,-12.4605512619],"type":"Point"}
}