{
  "type": "Feature",
  "properties": {
    "iso:country":"AU",
    "sg:address":"Northern Ave",
    "sg:city":"Moorabbin",
    "sg:classifiers":[
        {
            "category":"Professional",
            "subcategory":"Detective & Security Services",
            "type":"Services"
        }
    ],
    "sg:phone":"+61 3 9580 7644",
    "sg:postcode":"3189",
    "sg:province":"VIC",
    "sg:tags":[
        "distributor",
        "aircraft",
        "mfrs"
    ],
    "wof:name":"Aviall Australia Pty Ltd",
    "wof:placetype":"venue"
},
  "geometry": {"coordinates":[145.01821899399999,-37.9021911621],"type":"Point"}
}