{
  "type": "Feature",
  "properties": {
    "addr:full":"Shp 8/ 37 Benjamin Way Belconnen ACT 2617",
    "addr:housenumber":"/ 37",
    "addr:postcode":"2617",
    "addr:street":"Benjamin Way",
    "iso:country":"AU",
    "sg:address":"Shp 8/ 37",
    "sg:city":"Benjamin Way Belconnen",
    "sg:classifiers":[
        {
            "category":"Shopping",
            "subcategory":"Bridal",
            "type":"Retail Goods"
        }
    ],
    "sg:phone":"+61 2 6251 3557",
    "sg:postcode":"2617",
    "sg:province":"ACT",
    "sg:tags":[
        "hire",
        "wear"
    ],
    "wof:name":"Ferrari Formal Wear Belconnen",
    "wof:placetype":"venue"
},
  "geometry": {"coordinates":[149.0677948,-35.2405891418],"type":"Point"}
}