{
  "type": "Feature",
  "properties": {
    "addr:full":"199 Canterbury Rd Bankstown NSW 2200",
    "addr:housenumber":"199",
    "addr:postcode":"2200",
    "addr:street":"Canterbury Rd",
    "iso:country":"AU",
    "sg:address":"199 Canterbury Rd",
    "sg:city":"Bankstown",
    "sg:classifiers":[
        {
            "category":"Food & Beverages",
            "subcategory":"Meat & Fish",
            "type":"Retail Goods"
        }
    ],
    "sg:phone":"+61 2 9790 6677",
    "sg:postcode":"2200",
    "sg:province":"NSW",
    "sg:tags":[
        "seafood"
    ],
    "wof:name":"Popiye Seafood",
    "wof:placetype":"venue"
},
  "geometry": {"coordinates":[151.026016,-33.934032],"type":"Point"}
}