{
  "type": "Feature",
  "properties": {
    "iso:country":"AU",
    "sg:address":"27 Loader St",
    "sg:city":"Glynde",
    "sg:classifiers":[
        {
            "category":"Building & Trades",
            "subcategory":"Plumbing",
            "type":"Services"
        }
    ],
    "sg:phone":"+61 408 082 702",
    "sg:postcode":"5070",
    "sg:province":"SA",
    "sg:tags":[
        "plumber",
        "gasfitters"
    ],
    "wof:name":"Icolaro Tony Plumbing",
    "wof:placetype":"venue"
},
  "geometry": {"coordinates":[138.65208435100001,-34.9000816345],"type":"Point"}
}