{
  "type": "Feature",
  "properties": {
    "addr:full":"172a Dora St Dora Creek NSW 2264",
    "addr:housenumber":"172a",
    "addr:postcode":"2264",
    "addr:street":"Dora St Dora",
    "iso:country":"AU",
    "sg:address":"172a Dora St",
    "sg:city":"Dora Creek",
    "sg:classifiers":[
        {
            "category":"Health Services",
            "subcategory":"Health Practitioner",
            "type":"Services"
        }
    ],
    "sg:phone":"+61 2 4973 4170",
    "sg:postcode":"2264",
    "sg:province":"NSW",
    "sg:tags":[
        "bowen",
        "therapy"
    ],
    "wof:name":"Bowen Therapy",
    "wof:placetype":"venue"
},
  "geometry": {"coordinates":[151.51324500000001,-33.087238],"type":"Point"}
}