{
  "type": "Feature",
  "properties": {
    "addr:full":"Unit 10, 50 Chadderton St Lansvale NSW 2166",
    "addr:housenumber":"50",
    "addr:postcode":"2166",
    "addr:street":"Chadderton St",
    "iso:country":"AU",
    "sg:address":"Unit 10, 50 Chadderton St",
    "sg:city":"Lansvale",
    "sg:classifiers":[
        {
            "category":"Professional",
            "subcategory":"Engineering",
            "type":"Services"
        }
    ],
    "sg:phone":"+61 2 9727 3157",
    "sg:postcode":"2166",
    "sg:province":"NSW",
    "sg:tags":[
        "engineer"
    ],
    "wof:name":"Roadways Industry Pty Ltd",
    "wof:placetype":"venue"
},
  "geometry": {"coordinates":[150.956573486,-33.8937606812],"type":"Point"}
}