{
  "type": "Feature",
  "properties": {
    "iso:country":"AU",
    "sg:address":"100 Gertrude St",
    "sg:city":"Geraldton",
    "sg:classifiers":[
        {
            "category":"Retail",
            "subcategory":"Auto Repair",
            "type":"Services"
        }
    ],
    "sg:phone":"+61 419 969 908",
    "sg:postcode":"6530",
    "sg:province":"WA",
    "sg:tags":[
        "repairer",
        "motor",
        "engineer"
    ],
    "wof:name":"M & J Mobile Lube",
    "wof:placetype":"venue"
},
  "geometry": {"coordinates":[114.619049072,-28.7858543396],"type":"Point"}
}