{
  "type": "Feature",
  "properties": {
    "iso:country":"AU",
    "sg:address":"18 Reginald Ave",
    "sg:city":"Belmore",
    "sg:classifiers":[
        {
            "category":"Utilities",
            "subcategory":"Refuse",
            "type":"Services"
        }
    ],
    "sg:phone":"+61 2 9787 9467",
    "sg:postcode":"2192",
    "sg:province":"NSW",
    "sg:tags":[
        "remover",
        "rubbish"
    ],
    "wof:name":"Gabriel Rubbish Removal",
    "wof:placetype":"venue"
},
  "geometry": {"coordinates":[151.092896,-33.920792],"type":"Point"}
}