{
  "type": "Feature",
  "properties": {
    "iso:country":"AU",
    "sg:address":"26 Thompson St",
    "sg:city":"Ormond",
    "sg:classifiers":[
        {
            "category":"Building & Trades",
            "subcategory":"Construction",
            "type":"Services"
        }
    ],
    "sg:phone":"+61 408 869 542",
    "sg:postcode":"3204",
    "sg:province":"VIC",
    "sg:tags":[
        "brick",
        "paving"
    ],
    "wof:name":"Earthen Landscapes & Paving",
    "wof:placetype":"venue"
},
  "geometry": {"coordinates":[145.02829,-37.904079],"type":"Point"}
}