{
  "type": "Feature",
  "properties": {
    "iso:country":"AU",
    "sg:address":"Ste 7/ 250 Pitt St",
    "sg:city":"Sydney",
    "sg:classifiers":[
        {
            "category":"Shopping",
            "subcategory":"Shoes",
            "type":"Retail Goods"
        }
    ],
    "sg:phone":"+61 2 9264 4747",
    "sg:postcode":"2000",
    "sg:province":"NSW",
    "sg:tags":[
        "footwear"
    ],
    "wof:name":"Birkenstock Soul",
    "wof:placetype":"venue"
},
  "geometry": {"coordinates":[151.20828247099999,-33.8728370667],"type":"Point"}
}