{
  "type": "Feature",
  "properties": {
    "addr:full":"9 Showers St Preston VIC 3072",
    "addr:housenumber":"9",
    "addr:postcode":"3072",
    "addr:street":"Showers St",
    "iso:country":"AU",
    "sg:address":"9 Showers St",
    "sg:city":"Preston",
    "sg:classifiers":[
        {
            "category":"Retail",
            "subcategory":"Auto Repair",
            "type":"Services"
        }
    ],
    "sg:phone":"+61 3 9484 3847",
    "sg:postcode":"3072",
    "sg:province":"VIC",
    "sg:tags":[
        "beater",
        "painter",
        "panel"
    ],
    "wof:name":"Franknaz Collision Centre",
    "wof:placetype":"venue"
},
  "geometry": {"coordinates":[145.00106811500001,-37.7487411499],"type":"Point"}
}