{
  "type": "Feature",
  "properties": {
    "addr:full":"42 Nissan Drv Dandenong VIC 3175",
    "addr:postcode":"3175",
    "addr:street":"Nissan Drv",
    "iso:country":"AU",
    "sg:address":"42 Nissan Drv",
    "sg:city":"Dandenong",
    "sg:classifiers":[
        {
            "category":"Professional",
            "type":"Services"
        }
    ],
    "sg:phone":"+61 3 9791 9577",
    "sg:postcode":"3175",
    "sg:province":"VIC",
    "sg:tags":[
        "forwarding",
        "agent",
        "transport"
    ],
    "wof:name":"M & S MacDermid Transport Pty Ltd",
    "wof:placetype":"venue"
},
  "geometry": {"coordinates":[145.218948364,-38.021446228],"type":"Point"}
}