{
  "type": "Feature",
  "properties": {
    "addr:full":"Suite 12 Studio 2 Fitzgerald Ave Springwood QLD 4127",
    "addr:housenumber":"2",
    "addr:postcode":"4127",
    "addr:street":"Fitzgerald Ave",
    "iso:country":"AU",
    "sg:address":"Suite 12 Studio 2 Fitzgerald Ave",
    "sg:city":"Springwood",
    "sg:classifiers":[
        {
            "category":"Health Services",
            "subcategory":"Health Practitioner",
            "type":"Services"
        }
    ],
    "sg:phone":"+61 7 3208 0512",
    "sg:postcode":"4127",
    "sg:province":"QLD",
    "sg:tags":[
        "naturopath"
    ],
    "wof:name":"Donelly Sandra",
    "wof:placetype":"venue"
},
  "geometry": {"coordinates":[153.126220703,-27.6121501923],"type":"Point"}
}