{
  "type": "Feature",
  "properties": {
    "iso:country":"AU",
    "sg:address":"180 Mary St",
    "sg:city":"Gympie",
    "sg:classifiers":[
        {
            "category":"Retail",
            "subcategory":"Repair Shop",
            "type":"Services"
        }
    ],
    "sg:phone":"+61 7 5482 2558",
    "sg:postcode":"4570",
    "sg:province":"QLD",
    "sg:tags":[
        "machine",
        "sewing"
    ],
    "wof:name":"Cooloola Sewing Machines",
    "wof:placetype":"venue"
},
  "geometry": {"coordinates":[152.660522461,-26.1895523071],"type":"Point"}
}