{
  "type": "Feature",
  "properties": {
    "iso:country":"AU",
    "sg:address":"116/A Dangar St",
    "sg:city":"Armidale",
    "sg:classifiers":[
        {
            "category":"Professional",
            "subcategory":"Art Services",
            "type":"Services"
        }
    ],
    "sg:phone":"+61 2 6772 6967",
    "sg:postcode":"2350",
    "sg:province":"NSW",
    "sg:tags":[
        "interior",
        "decorator"
    ],
    "wof:name":"White Ivy Design",
    "wof:placetype":"venue"
},
  "geometry": {"coordinates":[151.66131591800001,-30.5241508484],"type":"Point"}
}