{
  "type": "Feature",
  "properties": {
    "addr:full":"Sunnyholt Rd Blacktown NSW 2148",
    "addr:postcode":"2148",
    "addr:street":"Sunnyholt Rd",
    "iso:country":"AU",
    "sg:address":"Sunnyholt Rd",
    "sg:city":"Blacktown",
    "sg:classifiers":[
        {
            "category":"Education",
            "subcategory":"School",
            "type":"Public Place"
        }
    ],
    "sg:phone":"+61 2 9622 2968",
    "sg:postcode":"2148",
    "sg:province":"NSW",
    "sg:tags":[
        "state",
        "-",
        "nsw"
    ],
    "wof:name":"Blacktown North Public School",
    "wof:placetype":"venue"
},
  "geometry": {"coordinates":[150.91163635300001,-33.7718315125],"type":"Point"}
}