{
  "type": "Feature",
  "properties": {
    "addr:full":"4 Wood St Bendigo VIC 3550",
    "addr:housenumber":"4",
    "addr:postcode":"3550",
    "addr:street":"Wood St",
    "iso:country":"AU",
    "sg:address":"4 Wood St",
    "sg:city":"Bendigo",
    "sg:classifiers":[
        {
            "category":"Autos & Motor Vehicles",
            "subcategory":"Auto Supplies",
            "type":"Retail Goods"
        }
    ],
    "sg:phone":"+61 3 5444 1545",
    "sg:postcode":"3550",
    "sg:province":"VIC",
    "sg:tags":[
        "tyre"
    ],
    "wof:name":"Bendigo Tyre Centre",
    "wof:placetype":"venue"
},
  "geometry": {"coordinates":[144.267211914,-36.7402534485],"type":"Point"}
}