{
  "type": "Feature",
  "properties": {
    "addr:full":"3/ 371 Scarborough Beach Rd Innaloo WA 6018",
    "addr:housenumber":"/ 371",
    "addr:postcode":"6018",
    "addr:street":"Scarborough Beach Rd",
    "iso:country":"AU",
    "sg:address":"3/ 371 Scarborough Beach Rd",
    "sg:city":"Innaloo",
    "sg:classifiers":[
        {
            "category":"Retail",
            "subcategory":"Veterinary Services",
            "type":"Services"
        }
    ],
    "sg:phone":"+61 8 9244 7707",
    "sg:postcode":"6018",
    "sg:province":"WA",
    "sg:tags":[
        "surgeon"
    ],
    "wof:name":"Total Vet Care",
    "wof:placetype":"venue"
},
  "geometry": {"coordinates":[115.79624176,-31.9023532867],"type":"Point"}
}