{
  "type": "Feature",
  "properties": {
    "iso:country":"AU",
    "sg:address":"6 Ornella Ave",
    "sg:city":"Glendenning",
    "sg:classifiers":[
        {
            "category":"Social Services",
            "subcategory":"Child Care",
            "type":"Services"
        }
    ],
    "sg:phone":"+61 2 9832 9055",
    "sg:postcode":"2761",
    "sg:province":"NSW",
    "wof:name":"J J's Long Day Care Centre",
    "wof:placetype":"venue"
},
  "geometry": {"coordinates":[150.851425,-33.742428],"type":"Point"}
}