{
  "type": "Feature",
  "properties": {
    "addr:full":"Unit 3 28 Frobisher St Osborne Park WA 6017",
    "addr:housenumber":"28",
    "addr:postcode":"6017",
    "addr:street":"Frobisher St",
    "iso:country":"AU",
    "sg:address":"Unit 3 28 Frobisher St",
    "sg:city":"Osborne Park",
    "sg:classifiers":[
        {
            "category":"Retail",
            "subcategory":"Auto Repair",
            "type":"Services"
        }
    ],
    "sg:phone":"+61 8 9242 1892",
    "sg:postcode":"6017",
    "sg:province":"WA",
    "sg:tags":[
        "repairer",
        "motor",
        "engineer"
    ],
    "wof:name":"Seabird Mechanical Repairers",
    "wof:placetype":"venue"
},
  "geometry": {"coordinates":[115.81955719,-31.9109172821],"type":"Point"}
}