{
  "type": "Feature",
  "properties": {
    "addr:full":"488 Springvale Rd (Cnr Hawthorn St) Nunawading VIC 3131",
    "addr:housenumber":"488",
    "addr:postcode":"3131",
    "addr:street":"Springvale Rd Cnr Hawthorn St",
    "iso:country":"AU",
    "sg:address":"488 Springvale Rd",
    "sg:city":"(Cnr Hawthorn St) Nunawading",
    "sg:classifiers":[
        {
            "category":"Autos & Motor Vehicles",
            "subcategory":"Fuel & Gas Station",
            "type":"Retail Goods"
        }
    ],
    "sg:phone":"+61 3 9886 5244",
    "sg:postcode":"3131",
    "sg:province":"VIC",
    "wof:name":"Quix Food Stores",
    "wof:placetype":"venue"
},
  "geometry": {"coordinates":[145.170196533,-37.848236084],"type":"Point"}
}