{
  "type": "Feature",
  "properties": {
    "iso:country":"AU",
    "sg:address":"7 Rutherford St",
    "sg:city":"Swan Hill",
    "sg:classifiers":[
        {
            "category":"Manufacturing",
            "subcategory":"Textiles",
            "type":"Manufacturing & Wholesale Goods"
        }
    ],
    "sg:phone":"+61 3 5033 2200",
    "sg:postcode":"3585",
    "sg:province":"VIC",
    "sg:tags":[
        "knitted",
        "woven",
        "fabric"
    ],
    "wof:name":"Miss Sampson's Drapery",
    "wof:placetype":"venue"
},
  "geometry": {"coordinates":[143.561996,-35.34296],"type":"Point"}
}