{
  "type": "Feature",
  "properties": {
    "addr:full":"71 Richardson St Port Hedland WA 6721",
    "addr:housenumber":"71",
    "addr:postcode":"6721",
    "addr:street":"Richardson St",
    "iso:country":"AU",
    "sg:address":"71 Richardson St",
    "sg:city":"Port Hedland",
    "sg:classifiers":[
        {
            "category":"Transit Center",
            "subcategory":"Freight",
            "type":"Transportation"
        }
    ],
    "sg:phone":"+61 8 9173 1604",
    "sg:postcode":"6721",
    "sg:province":"WA",
    "sg:tags":[
        "ship",
        "provedores"
    ],
    "wof:name":"Sealanes",
    "wof:placetype":"venue"
},
  "geometry": {"coordinates":[118.574783325,-20.3119945526],"type":"Point"}
}