{
  "type": "Feature",
  "properties": {
    "addr:full":"481 Princess Hwy Rockdale NSW 2216",
    "addr:housenumber":"481",
    "addr:postcode":"2216",
    "addr:street":"Princess Hwy",
    "iso:country":"AU",
    "sg:address":"481 Princess Hwy",
    "sg:city":"Rockdale",
    "sg:classifiers":[
        {
            "category":"Banks & Credit Unions",
            "subcategory":"Bank",
            "type":"Services"
        }
    ],
    "sg:phone":"+61 13 13 14",
    "sg:postcode":"2216",
    "sg:province":"NSW",
    "wof:name":"ANZ",
    "wof:placetype":"venue"
},
  "geometry": {"coordinates":[151.13795500000001,-33.95174],"type":"Point"}
}