{
  "type": "Feature",
  "properties": {
    "addr:full":"372 Hoddle St Clifton Hill VIC 3068",
    "addr:housenumber":"372",
    "addr:postcode":"3068",
    "addr:street":"Hoddle St",
    "iso:country":"AU",
    "sg:address":"372 Hoddle St",
    "sg:city":"Clifton Hill",
    "sg:classifiers":[
        {
            "category":"Professional",
            "type":"Services"
        }
    ],
    "sg:phone":"+61 3 9403 3555",
    "sg:postcode":"3068",
    "sg:province":"VIC",
    "sg:tags":[
        "shop",
        "fitting"
    ],
    "wof:name":"Australasian Shopfitting Co Pty Ltd",
    "wof:placetype":"venue"
},
  "geometry": {"coordinates":[144.994232178,-37.7939414978],"type":"Point"}
}