{
  "type": "Feature",
  "properties": {
    "iso:country":"AU",
    "sg:address":"21 Hoskins St",
    "sg:city":"Moss Vale",
    "sg:classifiers":[
        {
            "category":"Building & Trades",
            "subcategory":"Cleaning & Sanitation",
            "type":"Services"
        }
    ],
    "sg:phone":"+61 411 033 249",
    "sg:postcode":"2577",
    "sg:province":"NSW",
    "sg:tags":[
        "chemical",
        "pressure",
        "steam",
        "contractor"
    ],
    "wof:name":"Clean Auto Works The",
    "wof:placetype":"venue"
},
  "geometry": {"coordinates":[150.377075195,-34.5438957214],"type":"Point"}
}