{
  "type": "Feature",
  "properties": {
    "iso:country":"AU",
    "sg:address":"7 Fourteenth St",
    "sg:city":"Warragamba",
    "sg:classifiers":[
        {
            "category":"Fast Food",
            "type":"Food & Drink"
        }
    ],
    "sg:phone":"+61 2 4774 1072",
    "sg:postcode":"2752",
    "sg:province":"NSW",
    "sg:tags":[
        "away",
        "take"
    ],
    "wof:name":"Skippy's Food Bar & Cafe",
    "wof:placetype":"venue"
},
  "geometry": {"coordinates":[150.604003906,-33.8909645081],"type":"Point"}
}