{
  "type": "Feature",
  "properties": {
    "iso:country":"AU",
    "sg:address":"8 Grange Drv",
    "sg:city":"Cooloongup",
    "sg:classifiers":[
        {
            "category":"Personal",
            "subcategory":"Massage",
            "type":"Services"
        }
    ],
    "sg:phone":"+61 439 307 260",
    "sg:postcode":"6168",
    "sg:province":"WA",
    "sg:tags":[
        "therapy"
    ],
    "wof:name":"Therapeutic Touch",
    "wof:placetype":"venue"
},
  "geometry": {"coordinates":[115.762772,-32.294708],"type":"Point"}
}