{
  "type": "Feature",
  "properties": {
    "iso:country":"AU",
    "sg:address":"151 Union St",
    "sg:city":"Windsor",
    "sg:classifiers":[
        {
            "category":"Health Services",
            "subcategory":"Health Practitioner",
            "type":"Services"
        }
    ],
    "sg:phone":"+61 3 9807 2066",
    "sg:postcode":"3181",
    "sg:province":"VIC",
    "sg:tags":[
        "homoeopath"
    ],
    "wof:name":"Goodfield Mary",
    "wof:placetype":"venue"
},
  "geometry": {"coordinates":[144.99220275900001,-37.8547134399],"type":"Point"}
}