{
  "type": "Feature",
  "properties": {
    "iso:country":"AU",
    "sg:address":"7 Robert St",
    "sg:city":"Atherton",
    "sg:classifiers":[
        {
            "category":"Professional",
            "subcategory":"Computer Services",
            "type":"Services"
        }
    ],
    "sg:phone":"+61 7 4091 1899",
    "sg:postcode":"4883",
    "sg:province":"QLD",
    "sg:tags":[
        "training"
    ],
    "wof:name":"TPCR Computer Solutions",
    "wof:placetype":"venue"
},
  "geometry": {"coordinates":[145.47557067899999,-17.2686138153],"type":"Point"}
}