{
  "type": "Feature",
  "properties": {
    "addr:full":"9 Woodlands Ave Sassafras VIC 3787",
    "addr:housenumber":"9",
    "addr:postcode":"3787",
    "addr:street":"Woodlands Ave",
    "iso:country":"AU",
    "sg:address":"9 Woodlands Ave",
    "sg:city":"Sassafras",
    "sg:classifiers":[
        {
            "category":"Professional",
            "subcategory":"Art Services",
            "type":"Services"
        }
    ],
    "sg:phone":"+61 412 348 326",
    "sg:postcode":"3787",
    "sg:province":"VIC",
    "sg:tags":[
        "decorator",
        "painter"
    ],
    "wof:name":"Red Rose Painting",
    "wof:placetype":"venue"
},
  "geometry": {"coordinates":[145.354218,-37.865746],"type":"Point"}
}