{
  "type": "Feature",
  "properties": {
    "addr:full":"16 Jura Pl Seven Hills NSW 2147",
    "addr:housenumber":"16",
    "addr:postcode":"2147",
    "addr:street":"Jura Pl",
    "iso:country":"AU",
    "sg:address":"16 Jura Pl",
    "sg:city":"Seven Hills",
    "sg:classifiers":[
        {
            "category":"Building & Trades",
            "subcategory":"Plumbing",
            "type":"Services"
        }
    ],
    "sg:phone":"+61 2 9621 3865",
    "sg:postcode":"2147",
    "sg:province":"NSW",
    "sg:tags":[
        "plumber",
        "gasfitters"
    ],
    "wof:name":"A J Brock Plumbing Services",
    "wof:placetype":"venue"
},
  "geometry": {"coordinates":[150.92385864299999,-33.7890625],"type":"Point"}
}