{
  "type": "Feature",
  "properties": {
    "addr:full":"1 Jannalli Rd Dubbo NSW 2830",
    "addr:housenumber":"1",
    "addr:postcode":"2830",
    "addr:street":"Jannalli Rd",
    "iso:country":"AU",
    "sg:address":"1 Jannalli Rd",
    "sg:city":"Dubbo",
    "sg:classifiers":[
        {
            "category":"Retail",
            "subcategory":"Storage",
            "type":"Services"
        }
    ],
    "sg:phone":"+61 2 6882 1264",
    "sg:postcode":"2830",
    "sg:province":"NSW",
    "wof:name":"Dubbo Storage & Warehousing",
    "wof:placetype":"venue"
},
  "geometry": {"coordinates":[148.582199097,-32.2413482666],"type":"Point"}
}