{
  "type": "Feature",
  "properties": {
    "iso:country":"AU",
    "sg:address":"18 Hazelhurst St",
    "sg:city":"Kewdale",
    "sg:classifiers":[
        {
            "category":"Home & Garden",
            "subcategory":"Garden Supply",
            "type":"Retail Goods"
        }
    ],
    "sg:phone":"+61 8 9353 2534",
    "sg:postcode":"6105",
    "sg:province":"WA",
    "sg:tags":[
        "shadecloth"
    ],
    "wof:name":"UDA Pty Ltd",
    "wof:placetype":"venue"
},
  "geometry": {"coordinates":[115.956108093,-31.9720191956],"type":"Point"}
}