{
  "type": "Feature",
  "properties": {
    "iso:country":"AU",
    "sg:address":"8/ 3 Trotters La",
    "sg:city":"Prospect",
    "sg:classifiers":[
        {
            "category":"Retail",
            "subcategory":"Repair Shop",
            "type":"Services"
        }
    ],
    "sg:phone":"+61 419 507 803",
    "sg:postcode":"7250",
    "sg:province":"TAS",
    "sg:tags":[
        "windscreen"
    ],
    "wof:name":"Precision Windscreens & Autoglass",
    "wof:placetype":"venue"
},
  "geometry": {"coordinates":[147.16734314000001,-41.4506225586],"type":"Point"}
}