{
  "type": "Feature",
  "properties": {
    "iso:country":"AU",
    "sg:address":"29 Robertson St",
    "sg:city":"Naracoorte",
    "sg:classifiers":[
        {
            "category":"Health Services",
            "subcategory":"Dentist",
            "type":"Services"
        }
    ],
    "sg:phone":"+61 8 8762 2777",
    "sg:postcode":"5271",
    "sg:province":"SA",
    "sg:tags":[
        "technician",
        "dental"
    ],
    "wof:name":"Wight Fred D",
    "wof:placetype":"venue"
},
  "geometry": {"coordinates":[140.74290500000001,-36.956383],"type":"Point"}
}