{
  "type": "Feature",
  "properties": {
    "addr:full":"Gundagai St Adelong NSW 2729",
    "addr:postcode":"2729",
    "addr:street":"Gundagai St",
    "iso:country":"AU",
    "sg:address":"Gundagai St",
    "sg:city":"Adelong",
    "sg:classifiers":[
        {
            "category":"Education",
            "subcategory":"School",
            "type":"Public Place"
        }
    ],
    "sg:phone":"+61 2 6946 2170",
    "sg:postcode":"2729",
    "sg:province":"NSW",
    "wof:name":"St. Joseph's School",
    "wof:placetype":"venue"
},
  "geometry": {"coordinates":[148.06573499999999,-35.312653],"type":"Point"}
}