{
  "type": "Feature",
  "properties": {
    "iso:country":"AU",
    "sg:address":"240 Victoria Ave",
    "sg:city":"Chatswood",
    "sg:classifiers":[
        {
            "category":"Health Services",
            "subcategory":"Doctor",
            "type":"Services"
        }
    ],
    "sg:phone":"+61 2 9411 5224",
    "sg:postcode":"2067",
    "sg:province":"NSW",
    "sg:tags":[
        "medical",
        "practitioner"
    ],
    "wof:name":"Macquarie Pathology Services Pty Ltd",
    "wof:placetype":"venue"
},
  "geometry": {"coordinates":[151.18887329099999,-33.7946434021],"type":"Point"}
}