{
  "type": "Feature",
  "properties": {
    "addr:full":"1 Lions Park Drv Yatala QLD 4207",
    "addr:housenumber":"1",
    "addr:postcode":"4207",
    "addr:street":"Lions Park Drv",
    "iso:country":"AU",
    "sg:address":"1 Lions Park Drv",
    "sg:city":"Yatala",
    "sg:classifiers":[
        {
            "category":"Autos & Motor Vehicles",
            "subcategory":"Automobile Sales",
            "type":"Retail Goods"
        }
    ],
    "sg:phone":"+61 7 3807 2544",
    "sg:postcode":"4207",
    "sg:province":"QLD",
    "sg:tags":[
        "equipment",
        "trailer"
    ],
    "wof:name":"Dryden Trailers Pty Ltd",
    "wof:placetype":"venue"
},
  "geometry": {"coordinates":[153.23097229000001,-27.7423858643],"type":"Point"}
}