{
  "type": "Feature",
  "properties": {
    "iso:country":"AU",
    "sg:address":"PO Box 334",
    "sg:city":"Diamond Creek",
    "sg:classifiers":[
        {
            "category":"Utilities",
            "subcategory":"Electric",
            "type":"Services"
        }
    ],
    "sg:phone":"+61 418 320 532",
    "sg:postcode":"3089",
    "sg:province":"VIC",
    "sg:tags":[
        "electrical",
        "contractor"
    ],
    "wof:name":"Elco Electrical Contractors",
    "wof:placetype":"venue"
},
  "geometry": {"coordinates":[145.15799,-37.674252],"type":"Point"}
}