{
  "type": "Feature",
  "properties": {
    "addr:full":"825 Phillips Rd Byford WA 6122",
    "addr:housenumber":"825",
    "addr:postcode":"6122",
    "addr:street":"Phillips Rd",
    "iso:country":"AU",
    "sg:address":"825 Phillips Rd",
    "sg:city":"Byford",
    "sg:classifiers":[
        {
            "category":"Real Estate",
            "subcategory":"Real Estate Agent",
            "type":"Services"
        }
    ],
    "sg:phone":"+61 8 9525 1735",
    "sg:postcode":"6122",
    "sg:province":"WA",
    "wof:name":"Charles Orlando",
    "wof:placetype":"venue"
},
  "geometry": {"coordinates":[116.051872253,-32.233165741],"type":"Point"}
}