{
  "type": "Feature",
  "properties": {
    "addr:full":"Victor Drv Pialba QLD 4655",
    "addr:postcode":"4655",
    "addr:street":"Victor Drv",
    "iso:country":"AU",
    "sg:address":"Victor Drv",
    "sg:city":"Pialba",
    "sg:classifiers":[
        {
            "category":"Arena",
            "subcategory":"Sports Club",
            "type":"Entertainment"
        }
    ],
    "sg:phone":"+61 7 4124 7233",
    "sg:postcode":"4655",
    "sg:province":"QLD",
    "sg:tags":[
        "organisation",
        "sporting"
    ],
    "wof:name":"Sunfish (Qld) Fraser Coast Branch Inc.",
    "wof:placetype":"venue"
},
  "geometry": {"coordinates":[152.83764600000001,-25.305544],"type":"Point"}
}