{
  "type": "Feature",
  "properties": {
    "iso:country":"AU",
    "sg:address":"PO Box 359",
    "sg:city":"Albany",
    "sg:classifiers":[
        {
            "category":"Retail",
            "subcategory":"Repair Shop",
            "type":"Services"
        }
    ],
    "sg:phone":"+61 418 958 889",
    "sg:postcode":"6330",
    "sg:province":"WA",
    "sg:tags":[
        "windscreen"
    ],
    "wof:name":"Kandoo Windscreens",
    "wof:placetype":"venue"
},
  "geometry": {"coordinates":[117.94029998800001,-34.8903007507],"type":"Point"}
}