{
  "type": "Feature",
  "properties": {
    "addr:full":"434 Stafford Rd Stafford QLD 4053",
    "addr:housenumber":"434",
    "addr:postcode":"4053",
    "addr:street":"Stafford Rd",
    "iso:country":"AU",
    "sg:address":"434 Stafford Rd",
    "sg:city":"Stafford",
    "sg:classifiers":[
        {
            "category":"Retail",
            "subcategory":"Auto Repair",
            "type":"Services"
        }
    ],
    "sg:phone":"+61 7 3856 2999",
    "sg:postcode":"4053",
    "sg:province":"QLD",
    "sg:tags":[
        "repairer",
        "motor",
        "engineer"
    ],
    "wof:name":"Kmart Tyre & Auto Service",
    "wof:placetype":"venue"
},
  "geometry": {"coordinates":[153.0105896,-27.4097309113],"type":"Point"}
}