{
  "type": "Feature",
  "properties": {
    "iso:country":"AU",
    "sg:address":"83 Jocelyn St",
    "sg:city":"Chester Hill",
    "sg:classifiers":[
        {
            "category":"Social Services",
            "subcategory":"Retirement Home",
            "type":"Services"
        }
    ],
    "sg:phone":"+61 2 9645 9500",
    "sg:postcode":"2162",
    "sg:province":"NSW",
    "sg:tags":[
        "village"
    ],
    "wof:name":"Chester Hill Village",
    "wof:placetype":"venue"
},
  "geometry": {"coordinates":[150.99848938,-33.8885574341],"type":"Point"}
}