{
  "type": "Feature",
  "properties": {
    "addr:full":"28 Pritchard St Manjimup WA 6258",
    "addr:housenumber":"28",
    "addr:postcode":"6258",
    "addr:street":"Pritchard St",
    "iso:country":"AU",
    "sg:address":"28 Pritchard St",
    "sg:city":"Manjimup",
    "sg:classifiers":[
        {
            "category":"Utilities",
            "subcategory":"Electric",
            "type":"Services"
        }
    ],
    "sg:phone":"+61 8 9771 1768",
    "sg:postcode":"6258",
    "sg:province":"WA",
    "sg:tags":[
        "electrical",
        "contractor"
    ],
    "wof:name":"South West Electrics",
    "wof:placetype":"venue"
},
  "geometry": {"coordinates":[116.13941192599999,-34.2481384277],"type":"Point"}
}