{
  "type": "Feature",
  "properties": {
    "addr:full":"854 South Rd Edwardstown SA 5039",
    "addr:housenumber":"854",
    "addr:postcode":"5039",
    "addr:street":"South Rd",
    "iso:country":"AU",
    "sg:address":"854 South Rd",
    "sg:city":"Edwardstown",
    "sg:classifiers":[
        {
            "category":"Building & Trades",
            "subcategory":"Equipment Rental",
            "type":"Services"
        }
    ],
    "sg:phone":"+61 8 8371 2117",
    "sg:postcode":"5039",
    "sg:province":"SA",
    "sg:tags":[
        "party",
        "hire"
    ],
    "wof:name":"Renniks Events",
    "wof:placetype":"venue"
},
  "geometry": {"coordinates":[138.57455444300001,-34.991481781],"type":"Point"}
}