{
  "type": "Feature",
  "properties": {
    "addr:full":"46 Main St Minlaton SA 5575",
    "addr:housenumber":"46",
    "addr:postcode":"5575",
    "addr:street":"Main St",
    "iso:country":"AU",
    "sg:address":"46 Main St",
    "sg:city":"Minlaton",
    "sg:classifiers":[
        {
            "category":"Shopping",
            "subcategory":"Shoes",
            "type":"Retail Goods"
        }
    ],
    "sg:phone":"+61 8 8853 2383",
    "sg:postcode":"5575",
    "sg:province":"SA",
    "sg:tags":[
        "footwear"
    ],
    "wof:name":"McMahon I J & C S",
    "wof:placetype":"venue"
},
  "geometry": {"coordinates":[137.59489440900001,-34.7730712891],"type":"Point"}
}