{
  "type": "Feature",
  "properties": {
    "addr:full":"16 Monique Drv Langwarrin VIC 3910",
    "addr:housenumber":"16",
    "addr:postcode":"3910",
    "addr:street":"Monique Drv",
    "iso:country":"AU",
    "sg:address":"16 Monique Drv",
    "sg:city":"Langwarrin",
    "sg:classifiers":[
        {
            "category":"Building & Trades",
            "subcategory":"Pest Control",
            "type":"Services"
        }
    ],
    "sg:phone":"+61 1300 367 731",
    "sg:postcode":"3910",
    "sg:province":"VIC",
    "wof:name":"Termiteforce Pest Control",
    "wof:placetype":"venue"
},
  "geometry": {"coordinates":[145.206207275,-38.1578636169],"type":"Point"}
}