{
  "type": "Feature",
  "properties": {
    "iso:country":"AU",
    "sg:address":"19 Washington Ave",
    "sg:city":"Cromer",
    "sg:classifiers":[
        {
            "category":"Utilities",
            "subcategory":"Electric",
            "type":"Services"
        }
    ],
    "sg:phone":"+61 414 704 034",
    "sg:postcode":"2099",
    "sg:province":"NSW",
    "sg:tags":[
        "electrical",
        "contractor"
    ],
    "wof:name":"J & K Electrical",
    "wof:placetype":"venue"
},
  "geometry": {"coordinates":[151.27474975600001,-33.7344055176],"type":"Point"}
}