{
  "type": "Feature",
  "properties": {
    "addr:full":"1129 Pittwater Rd Collaroy NSW 2097",
    "addr:housenumber":"1129",
    "addr:postcode":"2097",
    "addr:street":"Pittwater Rd",
    "iso:country":"AU",
    "sg:address":"1129 Pittwater Rd",
    "sg:city":"Collaroy",
    "sg:classifiers":[
        {
            "category":"Real Estate",
            "subcategory":"Real Estate Agent",
            "type":"Services"
        }
    ],
    "sg:phone":"+61 2 9981 2133",
    "sg:postcode":"2097",
    "sg:province":"NSW",
    "wof:name":"Elders Real Estate Collaroy",
    "wof:placetype":"venue"
},
  "geometry": {"coordinates":[151.30079650900001,-33.7316513062],"type":"Point"}
}