{
  "type": "Feature",
  "properties": {
    "iso:country":"AU",
    "sg:address":"99 Fifth Ave",
    "sg:city":"Windsor",
    "sg:classifiers":[
        {
            "category":"Mining & Drilling",
            "type":"Manufacturing & Wholesale Goods"
        }
    ],
    "sg:phone":"+61 7 3857 7552",
    "sg:postcode":"4030",
    "sg:province":"QLD",
    "sg:tags":[
        "geologist"
    ],
    "wof:name":"Elliott Mark Dr",
    "wof:placetype":"venue"
},
  "geometry": {"coordinates":[153.02432300000001,-27.432795],"type":"Point"}
}