{
  "type": "Feature",
  "properties": {
    "addr:full":"340 Keilor Rd Niddrie VIC 3042",
    "addr:housenumber":"340",
    "addr:postcode":"3042",
    "addr:street":"Keilor Rd",
    "iso:country":"AU",
    "sg:address":"340 Keilor Rd",
    "sg:city":"Niddrie",
    "sg:classifiers":[
        {
            "category":"Education",
            "subcategory":"Vocational School",
            "type":"Public Place"
        }
    ],
    "sg:phone":"+61 3 9374 2622",
    "sg:postcode":"3042",
    "sg:province":"VIC",
    "sg:tags":[
        "cake",
        "decorating",
        "decorator"
    ],
    "wof:name":"Ferguson Plarre Bakehouses Pty Ltd",
    "wof:placetype":"venue"
},
  "geometry": {"coordinates":[144.891357422,-37.7367630005],"type":"Point"}
}