{
  "type": "Feature",
  "properties": {
    "addr:full":"705 Mt Alexander Rd Moonee Ponds VIC 3039",
    "addr:housenumber":"705",
    "addr:postcode":"3039",
    "addr:street":"Mt Alexander Rd",
    "iso:country":"AU",
    "sg:address":"705 Mt Alexander Rd",
    "sg:city":"Moonee Ponds",
    "sg:classifiers":[
        {
            "category":"Health Services",
            "subcategory":"Dentist",
            "type":"Services"
        }
    ],
    "sg:phone":"+61 3 9370 9988",
    "sg:postcode":"3039",
    "sg:province":"VIC",
    "wof:name":"Michaels Marta Dr",
    "wof:placetype":"venue"
},
  "geometry": {"coordinates":[144.92280600000001,-37.764111],"type":"Point"}
}