{
  "type": "Feature",
  "properties": {
    "addr:full":"19 Rosedale St Coopers Plains QLD 4108",
    "addr:housenumber":"19",
    "addr:postcode":"4108",
    "addr:street":"Rosedale St",
    "iso:country":"AU",
    "sg:address":"19 Rosedale St",
    "sg:city":"Coopers Plains",
    "sg:classifiers":[
        {
            "category":"Insurance",
            "subcategory":"Insurance Agent",
            "type":"Services"
        }
    ],
    "sg:phone":"+61 7 3344 3899",
    "sg:postcode":"4108",
    "sg:province":"QLD",
    "sg:tags":[
        "broker"
    ],
    "sg:website":"http://www.eastwestinsurance.com.au",
    "wof:name":"East West Insurance Brokers Pty Ltd",
    "wof:placetype":"venue"
},
  "geometry": {"coordinates":[153.035354614,-27.5690956116],"type":"Point"}
}