{
  "type": "Feature",
  "properties": {
    "addr:full":"20 Queen St Campbelltown NSW 2560",
    "addr:housenumber":"20",
    "addr:postcode":"2560",
    "addr:street":"Queen St",
    "iso:country":"AU",
    "sg:address":"20 Queen St",
    "sg:city":"Campbelltown",
    "sg:classifiers":[
        {
            "category":"Travel",
            "subcategory":"Hotels & Motels",
            "type":"Entertainment"
        }
    ],
    "sg:phone":"+61 2 4625 2345",
    "sg:postcode":"2560",
    "sg:province":"NSW",
    "wof:name":"Campbelltown Colonial Motor Inn",
    "wof:placetype":"venue"
},
  "geometry": {"coordinates":[150.82196044899999,-34.05809021],"type":"Point"}
}