{
  "type": "Feature",
  "properties": {
    "iso:country":"AU",
    "sg:address":"90 Watton St",
    "sg:city":"Werribee",
    "sg:classifiers":[
        {
            "category":"Shopping",
            "subcategory":"Music",
            "type":"Retail Goods"
        }
    ],
    "sg:phone":"+61 3 9731 1255",
    "sg:postcode":"3030",
    "sg:province":"VIC",
    "sg:tags":[
        "instrument",
        "musical"
    ],
    "wof:name":"Underground Music",
    "wof:placetype":"venue"
},
  "geometry": {"coordinates":[144.65773,-37.903111],"type":"Point"}
}