{
  "type": "Feature",
  "properties": {
    "iso:country":"AU",
    "sg:address":"60 Lennox St",
    "sg:city":"Newtown",
    "sg:classifiers":[
        {
            "category":"Social Services",
            "subcategory":"Child Care",
            "type":"Services"
        }
    ],
    "sg:phone":"+61 2 9557 1548",
    "sg:postcode":"2042",
    "sg:province":"NSW",
    "sg:tags":[
        "support",
        "health"
    ],
    "wof:name":"Early Childhood Health Centres",
    "wof:placetype":"venue"
},
  "geometry": {"coordinates":[151.179123,-33.895782],"type":"Point"}
}