{
  "type": "Feature",
  "properties": {
    "addr:full":"Constellation Drv Beaumaris WA 6065",
    "addr:postcode":"6065",
    "addr:street":"Constellation Drv",
    "iso:country":"AU",
    "sg:address":"Constellation Drv",
    "sg:city":"Beaumaris",
    "sg:classifiers":[
        {
            "category":"Health Services",
            "subcategory":"Health Practitioner",
            "type":"Services"
        }
    ],
    "sg:phone":"+61 8 9300 4844",
    "sg:postcode":"6065",
    "sg:province":"WA",
    "sg:tags":[
        "physiotherapist"
    ],
    "wof:name":"Beaumaris Physiotherapy",
    "wof:placetype":"venue"
},
  "geometry": {"coordinates":[115.731201172,-31.7437705994],"type":"Point"}
}