{
  "type": "Feature",
  "properties": {
    "addr:full":"PO Box 140 Keilor VIC 3036",
    "addr:postcode":"3036",
    "iso:country":"AU",
    "sg:address":"PO Box 140",
    "sg:city":"Keilor",
    "sg:classifiers":[
        {
            "category":"Wholesale",
            "subcategory":"Non-durable Goods",
            "type":"Manufacturing & Wholesale Goods"
        }
    ],
    "sg:phone":"+61 1800 666 880",
    "sg:postcode":"3036",
    "sg:province":"VIC",
    "sg:tags":[
        "wholesaler",
        "mfrs",
        "cosmetic"
    ],
    "wof:name":"Mirenesse Cosmetiques.",
    "wof:placetype":"venue"
},
  "geometry": {"coordinates":[144.830963,-37.717381],"type":"Point"}
}