{
  "type": "Feature",
  "properties": {
    "addr:full":"16/ 2 Emilton Ave St Kilda VIC 3182",
    "addr:housenumber":"16 / 2",
    "addr:postcode":"3182",
    "addr:street":"Emilton Ave",
    "iso:country":"AU",
    "sg:address":"16/ 2 Emilton Ave St",
    "sg:city":"Kilda",
    "sg:classifiers":[
        {
            "category":"Professional",
            "subcategory":"Art Services",
            "type":"Services"
        }
    ],
    "sg:phone":"+61 417 814 387",
    "sg:postcode":"3182",
    "sg:province":"VIC",
    "sg:tags":[
        "graphic",
        "designer"
    ],
    "wof:name":"Chris Dear",
    "wof:placetype":"venue"
},
  "geometry": {"coordinates":[144.981964111,-37.8622817993],"type":"Point"}
}