{
  "type": "Feature",
  "properties": {
    "addr:full":"422- 426 Peel St Tamworth NSW 2340",
    "addr:housenumber":"426",
    "addr:postcode":"2340",
    "addr:street":"Peel St",
    "iso:country":"AU",
    "sg:address":"422- 426 Peel St",
    "sg:city":"Tamworth",
    "sg:classifiers":[
        {
            "category":"Wholesale",
            "subcategory":"Medical Equipment & Supplies",
            "type":"Manufacturing & Wholesale Goods"
        }
    ],
    "sg:phone":"+61 13 17 97",
    "sg:postcode":"2340",
    "sg:province":"NSW",
    "sg:tags":[
        "aids",
        "hearing"
    ],
    "wof:name":"Australian Hearing",
    "wof:placetype":"venue"
},
  "geometry": {"coordinates":[150.93222045900001,-31.0929870605],"type":"Point"}
}