{
  "type": "Feature",
  "properties": {
    "addr:full":"834 Sandgate Rd Clayfield QLD 4011",
    "addr:housenumber":"834",
    "addr:postcode":"4011",
    "addr:street":"Sandgate Rd",
    "iso:country":"AU",
    "sg:address":"834 Sandgate Rd",
    "sg:city":"Clayfield",
    "sg:classifiers":[
        {
            "category":"Fast Food",
            "type":"Food & Drink"
        }
    ],
    "sg:phone":"+61 7 3262 1154",
    "sg:postcode":"4011",
    "sg:province":"QLD",
    "sg:tags":[
        "away",
        "take"
    ],
    "wof:name":"KFC",
    "wof:placetype":"venue"
},
  "geometry": {"coordinates":[153.05830399999999,-27.415356],"type":"Point"}
}