{
  "type": "Feature",
  "properties": {
    "addr:full":"52- 70 Centre Dandenong Rd Dingley Village VIC 3172",
    "addr:housenumber":"70",
    "addr:postcode":"3172",
    "addr:street":"Centre Dandenong Rd",
    "iso:country":"AU",
    "sg:address":"52- 70 Centre Dandenong Rd",
    "sg:city":"Dingley Village",
    "sg:classifiers":[
        {
            "category":"Social Services",
            "subcategory":"Retirement Home",
            "type":"Services"
        }
    ],
    "sg:phone":"+61 3 9558 3322",
    "sg:postcode":"3172",
    "sg:province":"VIC",
    "sg:tags":[
        "village"
    ],
    "wof:name":"Greenwood Village Mews",
    "wof:placetype":"venue"
},
  "geometry": {"coordinates":[145.138397217,-37.9872932434],"type":"Point"}
}