{
  "type": "Feature",
  "properties": {
    "addr:full":"Main St Murwillumbah NSW 2484",
    "addr:postcode":"2484",
    "addr:street":"Main St",
    "iso:country":"AU",
    "sg:address":"Main St",
    "sg:city":"Murwillumbah",
    "sg:classifiers":[
        {
            "category":"Education",
            "subcategory":"Special Training",
            "type":"Public Place"
        }
    ],
    "sg:phone":"+61 2 6672 5955",
    "sg:postcode":"2484",
    "sg:province":"NSW",
    "sg:tags":[
        "development"
    ],
    "wof:name":"Murwillumbah Job Club",
    "wof:placetype":"venue"
},
  "geometry": {"coordinates":[153.40342712399999,-28.3228321075],"type":"Point"}
}