{
  "type": "Feature",
  "properties": {
    "iso:country":"AU",
    "sg:address":"Shp 7, Parkside Plaza, Cnr Charles St & Bamford Lane",
    "sg:city":"Kirwan",
    "sg:classifiers":[
        {
            "category":"Shopping",
            "subcategory":"Stationery & Office Supplies",
            "type":"Retail Goods"
        }
    ],
    "sg:phone":"+61 7 4723 4821",
    "sg:postcode":"4817",
    "sg:province":"QLD",
    "wof:name":"Stationery Werks",
    "wof:placetype":"venue"
},
  "geometry": {"coordinates":[146.735153,-19.303686],"type":"Point"}
}