{
  "type": "Feature",
  "properties": {
    "addr:full":"117 Murray St Pyrmont NSW 2009",
    "addr:housenumber":"117",
    "addr:postcode":"2009",
    "addr:street":"Murray St",
    "iso:country":"AU",
    "sg:address":"117 Murray St",
    "sg:city":"Pyrmont",
    "sg:classifiers":[
        {
            "category":"Real Estate",
            "subcategory":"Developer",
            "type":"Services"
        }
    ],
    "sg:phone":"+61 2 9518 9160",
    "sg:postcode":"2009",
    "sg:province":"NSW",
    "sg:tags":[
        "development"
    ],
    "wof:name":"Beljen Developments Pty Ltd",
    "wof:placetype":"venue"
},
  "geometry": {"coordinates":[151.19723510700001,-33.8722610474],"type":"Point"}
}