{
  "type": "Feature",
  "properties": {
    "addr:full":"17 Famechon Crs Modbury North SA 5092",
    "addr:housenumber":"17",
    "addr:postcode":"5092",
    "addr:street":"Famechon Crs",
    "iso:country":"AU",
    "sg:address":"17 Famechon Crs",
    "sg:city":"Modbury North",
    "sg:classifiers":[
        {
            "category":"Social Services",
            "subcategory":"Child Care",
            "type":"Services"
        }
    ],
    "sg:phone":"+61 8 8395 8577",
    "sg:postcode":"5092",
    "sg:province":"SA",
    "wof:name":"Blue Skies Child Care Centre",
    "wof:placetype":"venue"
},
  "geometry": {"coordinates":[138.69236755399999,-34.8331794739],"type":"Point"}
}