{
  "type": "Feature",
  "properties": {
    "addr:full":"Albert St Osborne Park WA 6017",
    "addr:postcode":"6017",
    "addr:street":"Albert St",
    "iso:country":"AU",
    "sg:address":"Albert St",
    "sg:city":"Osborne Park",
    "sg:classifiers":[
        {
            "category":"Education",
            "subcategory":"School",
            "type":"Public Place"
        }
    ],
    "sg:phone":"+61 8 9349 2737",
    "sg:postcode":"6017",
    "sg:province":"WA",
    "sg:tags":[
        "state",
        "except",
        "nsw"
    ],
    "wof:name":"Osborne Primary School",
    "wof:placetype":"venue"
},
  "geometry": {"coordinates":[115.825576782,-31.9032115936],"type":"Point"}
}