{
  "type": "Feature",
  "properties": {
    "iso:country":"AU",
    "sg:address":"37 Wilson St",
    "sg:city":"Burnie",
    "sg:classifiers":[
        {
            "category":"Shopping",
            "subcategory":"Hobbies, Toys, & Games",
            "type":"Retail Goods"
        }
    ],
    "sg:phone":"+61 3 6431 6616",
    "sg:postcode":"7320",
    "sg:province":"TAS",
    "sg:tags":[
        "stamp"
    ],
    "wof:name":"Collector's Corner",
    "wof:placetype":"venue"
},
  "geometry": {"coordinates":[145.906769,-41.051544],"type":"Point"}
}