{
  "type": "Feature",
  "properties": {
    "addr:full":"2 Rolland Crt Endeavour Hills VIC 3802",
    "addr:housenumber":"2",
    "addr:postcode":"3802",
    "addr:street":"Rolland Crt",
    "iso:country":"AU",
    "sg:address":"2 Rolland Crt",
    "sg:city":"Endeavour Hills",
    "sg:classifiers":[
        {
            "category":"Utilities",
            "subcategory":"Electric",
            "type":"Services"
        }
    ],
    "sg:phone":"+61 412 527 576",
    "sg:postcode":"3802",
    "sg:province":"VIC",
    "sg:tags":[
        "electrical",
        "contractor"
    ],
    "wof:name":"John Hiller",
    "wof:placetype":"venue"
},
  "geometry": {"coordinates":[145.264038086,-37.9834289551],"type":"Point"}
}