{
  "type": "Feature",
  "properties": {
    "iso:country":"AU",
    "sg:address":"32 Eighth St",
    "sg:city":"Mildura",
    "sg:classifiers":[
        {
            "category":"Manufacturing",
            "subcategory":"Motor Vehicles & Parts",
            "type":"Manufacturing & Wholesale Goods"
        }
    ],
    "sg:phone":"+61 3 5021 1712",
    "sg:postcode":"3500",
    "sg:province":"VIC",
    "sg:tags":[
        "engine",
        "equipment",
        "diesel"
    ],
    "wof:name":"G & P Engine Reconditioners & Spare Parts",
    "wof:placetype":"venue"
},
  "geometry": {"coordinates":[142.17123413100001,-34.1919975281],"type":"Point"}
}