{
  "type": "Feature",
  "properties": {
    "addr:full":"Macquarie St Wallsend NSW 2287",
    "addr:postcode":"2287",
    "addr:street":"Macquarie St",
    "iso:country":"AU",
    "sg:address":"Macquarie St",
    "sg:city":"Wallsend",
    "sg:classifiers":[
        {
            "category":"Education",
            "subcategory":"School",
            "type":"Public Place"
        }
    ],
    "sg:phone":"+61 2 4951 1811",
    "sg:postcode":"2287",
    "sg:province":"NSW",
    "sg:tags":[
        "state",
        "-",
        "nsw"
    ],
    "wof:name":"Callaghan College- Wallsend",
    "wof:placetype":"venue"
},
  "geometry": {"coordinates":[151.664154053,-32.9008483887],"type":"Point"}
}