{
  "type": "Feature",
  "properties": {
    "addr:full":"3 Hogan St Ballina NSW 2478",
    "addr:housenumber":"3",
    "addr:postcode":"2478",
    "addr:street":"Hogan St",
    "iso:country":"AU",
    "sg:address":"3 Hogan St",
    "sg:city":"Ballina",
    "sg:classifiers":[
        {
            "category":"Building & Trades",
            "subcategory":"Plumbing",
            "type":"Services"
        }
    ],
    "sg:phone":"+61 2 6681 1003",
    "sg:postcode":"2478",
    "sg:province":"NSW",
    "sg:tags":[
        "tool",
        "air",
        "accessory",
        "supply"
    ],
    "wof:name":"Air Tool Sales & Service",
    "wof:placetype":"venue"
},
  "geometry": {"coordinates":[153.56272888199999,-28.8569850922],"type":"Point"}
}