{
  "type": "Feature",
  "properties": {
    "iso:country":"AU",
    "sg:address":"35 Avenell St",
    "sg:city":"Wishart",
    "sg:classifiers":[
        {
            "category":"Professional",
            "subcategory":"Accounting & Tax Preparation",
            "type":"Services"
        }
    ],
    "sg:phone":"+61 7 3849 2911",
    "sg:postcode":"4122",
    "sg:province":"QLD",
    "sg:tags":[
        "consultant",
        "taxation"
    ],
    "wof:name":"Bergmans Tax Accounting",
    "wof:placetype":"venue"
},
  "geometry": {"coordinates":[153.09620666500001,-27.5516242981],"type":"Point"}
}