{
  "type": "Feature",
  "properties": {
    "addr:full":"18 Wareemba St Five Dock NSW 2046",
    "addr:housenumber":"18",
    "addr:postcode":"2046",
    "addr:street":"Wareemba St",
    "iso:country":"AU",
    "sg:address":"18 Wareemba St",
    "sg:city":"Five Dock",
    "sg:classifiers":[
        {
            "category":"Retail",
            "subcategory":"Driving School",
            "type":"Services"
        }
    ],
    "sg:phone":"+61 418 223 620",
    "sg:postcode":"2046",
    "sg:province":"NSW",
    "wof:name":"United Driving School",
    "wof:placetype":"venue"
},
  "geometry": {"coordinates":[151.13566599999999,-33.856148],"type":"Point"}
}