{
  "type": "Feature",
  "properties": {
    "addr:full":"1/ 51 Eastern Rd Browns Plains QLD 4118",
    "addr:housenumber":"/ 51",
    "addr:postcode":"4118",
    "addr:street":"Eastern Rd",
    "iso:country":"AU",
    "sg:address":"1/ 51 Eastern Rd",
    "sg:city":"Browns Plains",
    "sg:classifiers":[
        {
            "category":"Retail",
            "subcategory":"Auto Repair",
            "type":"Services"
        }
    ],
    "sg:phone":"+61 7 3800 3709",
    "sg:postcode":"4118",
    "sg:province":"QLD",
    "sg:tags":[
        "repairer",
        "motor",
        "engineer"
    ],
    "wof:name":"Matt Stocker Automotives",
    "wof:placetype":"venue"
},
  "geometry": {"coordinates":[153.047897339,-27.664434433],"type":"Point"}
}