{
  "type": "Feature",
  "properties": {
    "iso:country":"AU",
    "sg:address":"139 Fitzgerald St",
    "sg:city":"Northam",
    "sg:classifiers":[
        {
            "category":"Professional",
            "subcategory":"Employment Agencies",
            "type":"Services"
        }
    ],
    "sg:phone":"+61 8 9622 3500",
    "sg:postcode":"6401",
    "sg:province":"WA",
    "wof:name":"MAX Employment",
    "wof:placetype":"venue"
},
  "geometry": {"coordinates":[116.672813416,-31.6526546478],"type":"Point"}
}