{
  "type": "Feature",
  "properties": {
    "addr:full":"37 Cross Rd Kingswood SA 5062",
    "addr:housenumber":"37",
    "addr:postcode":"5062",
    "addr:street":"Cross Rd",
    "iso:country":"AU",
    "sg:address":"37 Cross Rd",
    "sg:city":"Kingswood",
    "sg:classifiers":[
        {
            "category":"Health Services",
            "subcategory":"Nursing And Care Facility",
            "type":"Services"
        }
    ],
    "sg:phone":"+61 8 8271 6085",
    "sg:postcode":"5062",
    "sg:province":"SA",
    "sg:tags":[
        "home"
    ],
    "wof:name":"Abbingdon Private Nursing Home",
    "wof:placetype":"venue"
},
  "geometry": {"coordinates":[138.612747192,-34.9654197693],"type":"Point"}
}