{
  "type": "Feature",
  "properties": {
    "addr:full":"189 Matcham Rd Matcham NSW 2250",
    "addr:housenumber":"189",
    "addr:postcode":"2250",
    "addr:street":"Matcham Rd",
    "iso:country":"AU",
    "sg:address":"189 Matcham Rd",
    "sg:city":"Matcham",
    "sg:classifiers":[
        {
            "category":"Arts & Performance",
            "subcategory":"Art Gallery",
            "type":"Entertainment"
        }
    ],
    "sg:phone":"+61 2 4367 5645",
    "sg:postcode":"2250",
    "sg:province":"NSW",
    "sg:tags":[
        "aboriginal",
        "craft"
    ],
    "wof:name":"Gundooee",
    "wof:placetype":"venue"
},
  "geometry": {"coordinates":[151.42318725600001,-33.4142723083],"type":"Point"}
}