{
  "type": "Feature",
  "properties": {
    "iso:country":"AU",
    "sg:address":"94 Maitland St",
    "sg:city":"Bingara",
    "sg:classifiers":[
        {
            "category":"Health Services",
            "subcategory":"Doctor",
            "type":"Services"
        }
    ],
    "sg:phone":"+61 2 6724 1900",
    "sg:postcode":"2404",
    "sg:province":"NSW",
    "sg:tags":[
        "medical",
        "practitioner"
    ],
    "wof:name":"Wearne Neil Dr",
    "wof:placetype":"venue"
},
  "geometry": {"coordinates":[150.572265625,-29.8702640533],"type":"Point"}
}