{
  "type": "Feature",
  "properties": {
    "iso:country":"AU",
    "sg:address":"Thompson Rd Clinic",
    "sg:city":"Cranbourne",
    "sg:classifiers":[
        {
            "category":"Health Services",
            "subcategory":"Doctor",
            "type":"Services"
        }
    ],
    "sg:phone":"+61 3 5996 9000",
    "sg:postcode":"3977",
    "sg:province":"VIC",
    "sg:tags":[
        "medical",
        "practitioner"
    ],
    "wof:name":"Desouza Michael",
    "wof:placetype":"venue"
},
  "geometry": {"coordinates":[145.191238403,-38.0715713501],"type":"Point"}
}