{
  "type": "Feature",
  "properties": {
    "addr:full":"Unit 1, 219 William St Kalgoorlie WA 6430",
    "addr:housenumber":"219",
    "addr:postcode":"6430",
    "addr:street":"William St",
    "iso:country":"AU",
    "sg:address":"Unit 1, 219 William St",
    "sg:city":"Kalgoorlie",
    "sg:classifiers":[
        {
            "category":"Wholesale",
            "subcategory":"Machinery & Supplies",
            "type":"Manufacturing & Wholesale Goods"
        }
    ],
    "sg:phone":"+61 8 9022 8144",
    "sg:postcode":"6430",
    "sg:province":"WA",
    "sg:tags":[
        "equipment",
        "hydraulic"
    ],
    "wof:name":"Alfagomma Australia Pty Ltd",
    "wof:placetype":"venue"
},
  "geometry": {"coordinates":[121.43636322,-30.778263092],"type":"Point"}
}