{
  "type": "Feature",
  "properties": {
    "addr:full":"27 Chapple St Gladstone QLD 4680",
    "addr:housenumber":"27",
    "addr:postcode":"4680",
    "addr:street":"Chapple St",
    "iso:country":"AU",
    "sg:address":"27 Chapple St",
    "sg:city":"Gladstone",
    "sg:classifiers":[
        {
            "category":"Taxi",
            "type":"Transportation"
        }
    ],
    "sg:phone":"+61 13 10 08",
    "sg:postcode":"4680",
    "sg:province":"QLD",
    "sg:tags":[
        "cab"
    ],
    "wof:name":"Blue & White Taxis (Gladstone) Pty.Ltd.",
    "wof:placetype":"venue"
},
  "geometry": {"coordinates":[151.240524292,-23.8425960541],"type":"Point"}
}