{
  "type": "Feature",
  "properties": {
    "iso:country":"AU",
    "sg:address":"81 Lygon St",
    "sg:city":"Brunswick East",
    "sg:classifiers":[
        {
            "category":"Shopping",
            "subcategory":"Music",
            "type":"Retail Goods"
        }
    ],
    "sg:phone":"+61 3 9387 2470",
    "sg:postcode":"3057",
    "sg:province":"VIC",
    "sg:tags":[
        "store"
    ],
    "wof:name":"Arkitekt Records",
    "wof:placetype":"venue"
},
  "geometry": {"coordinates":[144.970779419,-37.7764320374],"type":"Point"}
}