{
  "type": "Feature",
  "properties": {
    "iso:country":"AU",
    "sg:address":"73 Marion St",
    "sg:city":"Unley",
    "sg:classifiers":[
        {
            "category":"Education",
            "subcategory":"Kindergarten",
            "type":"Public Place"
        }
    ],
    "sg:phone":"+61 8 8271 3429",
    "sg:postcode":"5061",
    "sg:province":"SA",
    "sg:tags":[
        "pre-schools"
    ],
    "wof:name":"Unley Mothercraft Nursery & Kindergarten",
    "wof:placetype":"venue"
},
  "geometry": {"coordinates":[138.60963439899999,-34.9483795166],"type":"Point"}
}