{
  "type": "Feature",
  "properties": {
    "addr:full":"28 Greenhill Rd Wayville SA 5034",
    "addr:housenumber":"28",
    "addr:postcode":"5034",
    "addr:street":"Greenhill Rd",
    "iso:country":"AU",
    "sg:address":"28 Greenhill Rd",
    "sg:city":"Wayville",
    "sg:classifiers":[
        {
            "category":"Health Services",
            "subcategory":"Health Practitioner",
            "type":"Services"
        }
    ],
    "sg:phone":"+61 8 8274 2101",
    "sg:postcode":"5034",
    "sg:province":"SA",
    "sg:tags":[
        "physiotherapist"
    ],
    "wof:name":"Fuller Richard",
    "wof:placetype":"venue"
},
  "geometry": {"coordinates":[138.58840942399999,-34.9421005249],"type":"Point"}
}