{
  "type": "Feature",
  "properties": {
    "addr:full":"35 Shakespeare St Alpha QLD 4724",
    "addr:housenumber":"35",
    "addr:postcode":"4724",
    "addr:street":"Shakespeare St",
    "iso:country":"AU",
    "sg:address":"35 Shakespeare St",
    "sg:city":"Alpha",
    "sg:classifiers":[
        {
            "category":"Travel",
            "subcategory":"Hotels & Motels",
            "type":"Entertainment"
        }
    ],
    "sg:phone":"+61 7 4985 1523",
    "sg:postcode":"4724",
    "sg:province":"QLD",
    "sg:tags":[
        "accommodation"
    ],
    "wof:name":"Criterion Hotel",
    "wof:placetype":"venue"
},
  "geometry": {"coordinates":[146.63836669899999,-23.6486721039],"type":"Point"}
}