{
  "type": "Feature",
  "properties": {
    "addr:full":"7 Miller Ave Ashfield NSW 2131",
    "addr:housenumber":"7",
    "addr:postcode":"2131",
    "addr:street":"Miller Ave",
    "iso:country":"AU",
    "sg:address":"7 Miller Ave",
    "sg:city":"Ashfield",
    "sg:classifiers":[
        {
            "category":"Home & Garden",
            "subcategory":"Building Materials",
            "type":"Retail Goods"
        }
    ],
    "sg:phone":"+61 2 9799 5030",
    "sg:postcode":"2131",
    "sg:province":"NSW",
    "sg:tags":[
        "lawn",
        "cutting",
        "maintenance"
    ],
    "wof:name":"Gordon Latham",
    "wof:placetype":"venue"
},
  "geometry": {"coordinates":[151.122024536,-33.887714386],"type":"Point"}
}