{
  "type": "Feature",
  "properties": {
    "addr:full":"73 Mount St Perth WA 6000",
    "addr:housenumber":"73",
    "addr:postcode":"6000",
    "addr:street":"Mount St",
    "iso:country":"AU",
    "sg:address":"73 Mount St",
    "sg:city":"Perth",
    "sg:classifiers":[
        {
            "category":"Professional",
            "subcategory":"Art Services",
            "type":"Services"
        }
    ],
    "sg:phone":"+61 8 9226 0139",
    "sg:postcode":"6000",
    "sg:province":"WA",
    "wof:name":"Rogers Wendy",
    "wof:placetype":"venue"
},
  "geometry": {"coordinates":[115.845680237,-31.9547691345],"type":"Point"}
}