{
  "type": "Feature",
  "properties": {
    "iso:country":"AU",
    "sg:address":"GPO Box 2700",
    "sg:city":"Canberra",
    "sg:classifiers":[
        {
            "category":"Professional",
            "subcategory":"Employment Agencies",
            "type":"Services"
        }
    ],
    "sg:phone":"+61 2 6275 0750",
    "sg:postcode":"2601",
    "sg:province":"ACT",
    "wof:name":"Wizard Information Services Pty Limited",
    "wof:placetype":"venue"
},
  "geometry": {"coordinates":[149.111816406,-35.2768592834],"type":"Point"}
}