{
  "type": "Feature",
  "properties": {
    "iso:country":"AU",
    "sg:address":"Shp1&2/ 33 High St",
    "sg:city":"Cranbourne",
    "sg:classifiers":[
        {
            "category":"Food & Beverages",
            "subcategory":"Supermarket",
            "type":"Retail Goods"
        }
    ],
    "sg:phone":"+61 3 5996 1722",
    "sg:postcode":"3977",
    "sg:province":"VIC",
    "sg:tags":[
        "grocery",
        "store"
    ],
    "wof:name":"Araliya Food Corner",
    "wof:placetype":"venue"
},
  "geometry": {"coordinates":[145.28269958499999,-38.112247467],"type":"Point"}
}