{
  "type": "Feature",
  "properties": {
    "addr:full":"64 Herbert St Rockdale NSW 2216",
    "addr:housenumber":"64",
    "addr:postcode":"2216",
    "addr:street":"Herbert St",
    "iso:country":"AU",
    "sg:address":"64 Herbert St",
    "sg:city":"Rockdale",
    "sg:classifiers":[
        {
            "category":"Professional",
            "subcategory":"Employment Agencies",
            "type":"Services"
        }
    ],
    "sg:phone":"+61 2 9567 9757",
    "sg:postcode":"2216",
    "sg:province":"NSW",
    "sg:tags":[
        "entertainer",
        "agent"
    ],
    "wof:name":"Fisher Creative Entertainment Pty Ltd",
    "wof:placetype":"venue"
},
  "geometry": {"coordinates":[151.13136299999999,-33.947968],"type":"Point"}
}