{
  "type": "Feature",
  "properties": {
    "addr:full":"PO Box 4764 North Rocks NSW 2151",
    "addr:postcode":"2151",
    "iso:country":"AU",
    "sg:address":"PO Box 4764",
    "sg:city":"North Rocks",
    "sg:classifiers":[
        {
            "category":"Professional",
            "subcategory":"Detective & Security Services",
            "type":"Services"
        }
    ],
    "sg:phone":"+61 411 326 436",
    "sg:postcode":"2151",
    "sg:province":"NSW",
    "sg:tags":[
        "investigator"
    ],
    "wof:name":"Enquiry Investigators",
    "wof:placetype":"venue"
},
  "geometry": {"coordinates":[151.021286011,-33.7750396729],"type":"Point"}
}