{
  "type": "Feature",
  "properties": {
    "iso:country":"AU",
    "sg:address":"Lvl 2/ 1 Balmoral St",
    "sg:city":"Frankston",
    "sg:classifiers":[
        {
            "category":"Travel",
            "subcategory":"Travel Agent",
            "type":"Entertainment"
        }
    ],
    "sg:phone":"+61 3 8781 1170",
    "sg:postcode":"3199",
    "sg:province":"VIC",
    "sg:tags":[
        "consultant"
    ],
    "wof:name":"The Europe Shop",
    "wof:placetype":"venue"
},
  "geometry": {"coordinates":[145.15461730999999,-38.1803321838],"type":"Point"}
}