{
  "type": "Feature",
  "properties": {
    "iso:country":"AU",
    "sg:address":"96 Limestone St",
    "sg:city":"Enoggera",
    "sg:classifiers":[
        {
            "category":"Shopping",
            "subcategory":"Bicycles & Sporting Goods",
            "type":"Retail Goods"
        }
    ],
    "sg:phone":"+61 7 3281 0255",
    "sg:postcode":"4051",
    "sg:province":"QLD",
    "sg:tags":[
        "chemical",
        "equipment",
        "pool",
        "swimming"
    ],
    "wof:name":"Swimart Ipswich",
    "wof:placetype":"venue"
},
  "geometry": {"coordinates":[152.99020385700001,-27.4223403931],"type":"Point"}
}