{
  "type": "Feature",
  "properties": {
    "addr:full":"1 Barossa St (cnr Alexander Drv) Highland Park QLD 4211",
    "addr:housenumber":"1",
    "addr:postcode":"4211",
    "addr:street":"Barossa St Cnr Alexander Drv",
    "iso:country":"AU",
    "sg:address":"1 Barossa St (cnr Alexander Drv)",
    "sg:city":"Highland Park",
    "sg:classifiers":[
        {
            "category":"Health Services",
            "subcategory":"Dentist",
            "type":"Services"
        }
    ],
    "sg:phone":"+61 7 5527 4200",
    "sg:postcode":"4211",
    "sg:province":"QLD",
    "wof:name":"Cook Dr Damian",
    "wof:placetype":"venue"
},
  "geometry": {"coordinates":[153.34620666500001,-28.0161857605],"type":"Point"}
}