{
  "type": "Feature",
  "properties": {
    "addr:full":"22 Edward St Orange NSW 2800",
    "addr:housenumber":"22",
    "addr:postcode":"2800",
    "addr:street":"Edward St",
    "iso:country":"AU",
    "sg:address":"22 Edward St",
    "sg:city":"Orange",
    "sg:classifiers":[
        {
            "category":"Building & Trades",
            "subcategory":"Construction",
            "type":"Services"
        }
    ],
    "sg:phone":"+61 2 6362 1111",
    "sg:postcode":"2800",
    "sg:province":"NSW",
    "sg:tags":[
        "welding"
    ],
    "wof:name":"Midstate Metals Pty Ltd",
    "wof:placetype":"venue"
},
  "geometry": {"coordinates":[149.10488891599999,-33.2931175232],"type":"Point"}
}