{
  "type": "Feature",
  "properties": {
    "addr:full":"33 Mulyan St Como NSW 2226",
    "addr:housenumber":"33",
    "addr:postcode":"2226",
    "addr:street":"Mulyan St",
    "iso:country":"AU",
    "sg:address":"33 Mulyan St",
    "sg:city":"Como",
    "sg:classifiers":[
        {
            "category":"Building & Trades",
            "subcategory":"Construction",
            "type":"Services"
        }
    ],
    "sg:phone":"+61 415 979 245",
    "sg:postcode":"2226",
    "sg:province":"NSW",
    "sg:tags":[
        "plasterboard",
        "plasterer",
        "fixer"
    ],
    "wof:name":"Southside Gyprocking Services",
    "wof:placetype":"venue"
},
  "geometry": {"coordinates":[151.06364440900001,-34.0023078918],"type":"Point"}
}