{
  "type": "Feature",
  "properties": {
    "addr:full":"10 David Muir St Slade Point QLD 4740",
    "addr:housenumber":"10",
    "addr:postcode":"4740",
    "addr:street":"David Muir St",
    "iso:country":"AU",
    "sg:address":"10 David Muir St",
    "sg:city":"Slade Point",
    "sg:classifiers":[
        {
            "category":"Utilities",
            "subcategory":"Water",
            "type":"Services"
        }
    ],
    "sg:phone":"+61 7 4955 2177",
    "sg:postcode":"4740",
    "sg:province":"QLD",
    "sg:tags":[
        "equipment",
        "treatment"
    ],
    "wof:name":"Envirokleen Solutions Pty Ltd",
    "wof:placetype":"venue"
},
  "geometry": {"coordinates":[149.18261699999999,-21.123739],"type":"Point"}
}