{
  "type": "Feature",
  "properties": {
    "addr:full":"79 High St Mansfield VIC 3722",
    "addr:housenumber":"79",
    "addr:postcode":"3722",
    "addr:street":"High St",
    "iso:country":"AU",
    "sg:address":"79 High St",
    "sg:city":"Mansfield",
    "sg:classifiers":[
        {
            "category":"Wholesale",
            "subcategory":"Medical Equipment & Supplies",
            "type":"Manufacturing & Wholesale Goods"
        }
    ],
    "sg:phone":"+61 3 5775 2028",
    "sg:postcode":"3722",
    "sg:province":"VIC",
    "sg:tags":[
        "aid",
        "care",
        "health",
        "home"
    ],
    "wof:name":"Eisner's Guardian Pharmacy",
    "wof:placetype":"venue"
},
  "geometry": {"coordinates":[146.08888244600001,-37.0520439148],"type":"Point"}
}