{
  "type": "Feature",
  "properties": {
    "iso:country":"AU",
    "sg:address":"Unit 4, Building 2 , Lot 3, Morris Road West",
    "sg:city":"Rothwell",
    "sg:classifiers":[
        {
            "category":"Utilities",
            "subcategory":"Electric",
            "type":"Services"
        }
    ],
    "sg:phone":"+61 7 3204 1544",
    "sg:postcode":"4022",
    "sg:province":"QLD",
    "sg:tags":[
        "electrical",
        "contractor"
    ],
    "wof:name":"Aquarius Electrical Services Pty Ltd",
    "wof:placetype":"venue"
},
  "geometry": {"coordinates":[153.044983,-27.211966],"type":"Point"}
}