{
  "type": "Feature",
  "properties": {
    "addr:full":"7/ 5 Edelmaier St Bayswater VIC 3153",
    "addr:housenumber":"/ 5",
    "addr:postcode":"3153",
    "addr:street":"Edelmaier St",
    "iso:country":"AU",
    "sg:address":"7/ 5 Edelmaier St",
    "sg:city":"Bayswater",
    "sg:classifiers":[
        {
            "category":"Professional",
            "subcategory":"Engineering",
            "type":"Services"
        }
    ],
    "sg:phone":"+61 3 9720 2405",
    "sg:postcode":"3153",
    "sg:province":"VIC",
    "sg:tags":[
        "engineer"
    ],
    "wof:name":"Proficient Engineering",
    "wof:placetype":"venue"
},
  "geometry": {"coordinates":[145.27464294399999,-37.8467407227],"type":"Point"}
}