{
  "type": "Feature",
  "properties": {
    "addr:full":"114 Wembley Rd Woodridge QLD 4114",
    "addr:housenumber":"114",
    "addr:postcode":"4114",
    "addr:street":"Wembley Rd",
    "iso:country":"AU",
    "sg:address":"114 Wembley Rd",
    "sg:city":"Woodridge",
    "sg:classifiers":[
        {
            "category":"Communications",
            "subcategory":"Film & Video Production",
            "type":"Services"
        }
    ],
    "sg:phone":"+61 7 3808 8700",
    "sg:postcode":"4114",
    "sg:province":"QLD",
    "sg:tags":[
        "dvd",
        "library"
    ],
    "wof:name":"Video Ezy",
    "wof:placetype":"venue"
},
  "geometry": {"coordinates":[153.10496520999999,-27.641456604],"type":"Point"}
}