{
  "type": "Feature",
  "properties": {
    "addr:full":"39 Kookaburra St Dalby QLD 4405",
    "addr:housenumber":"39",
    "addr:postcode":"4405",
    "addr:street":"Kookaburra St",
    "iso:country":"AU",
    "sg:address":"39 Kookaburra St",
    "sg:city":"Dalby",
    "sg:classifiers":[
        {
            "category":"Farming",
            "subcategory":"Farm",
            "type":"Manufacturing & Wholesale Goods"
        }
    ],
    "sg:phone":"+61 7 4662 3487",
    "sg:postcode":"4405",
    "sg:province":"QLD",
    "sg:tags":[
        "farmer"
    ],
    "wof:name":"Frizzell M B & R M",
    "wof:placetype":"venue"
},
  "geometry": {"coordinates":[151.27244567899999,-27.1698493958],"type":"Point"}
}