{
  "type": "Feature",
  "properties": {
    "iso:country":"AU",
    "sg:address":"Lvl 1/ 456 Latrobe St",
    "sg:city":"West Melbourne",
    "sg:classifiers":[
        {
            "category":"Personal",
            "subcategory":"Beauty Salon",
            "type":"Services"
        }
    ],
    "sg:phone":"+61 3 9329 1050",
    "sg:postcode":"3003",
    "sg:province":"VIC",
    "sg:tags":[
        "hairdresser"
    ],
    "wof:name":"Mbc Hair & Beauty",
    "wof:placetype":"venue"
},
  "geometry": {"coordinates":[144.93093872099999,-37.8105697632],"type":"Point"}
}