{
  "type": "Feature",
  "properties": {
    "iso:country":"AU",
    "sg:address":"Laurel St",
    "sg:city":"Enoggera",
    "sg:classifiers":[
        {
            "category":"Education",
            "subcategory":"School",
            "type":"Public Place"
        }
    ],
    "sg:phone":"+61 7 3354 1428",
    "sg:postcode":"4051",
    "sg:province":"QLD",
    "sg:tags":[
        "state",
        "except",
        "nsw"
    ],
    "wof:name":"Enoggera State Preschool",
    "wof:placetype":"venue"
},
  "geometry": {"coordinates":[152.99296569800001,-27.4162540436],"type":"Point"}
}