{
  "type": "Feature",
  "properties": {
    "addr:full":"11 Richland Rd Newton SA 5074",
    "addr:housenumber":"11",
    "addr:postcode":"5074",
    "addr:street":"Richland Rd",
    "iso:country":"AU",
    "sg:address":"11 Richland Rd",
    "sg:city":"Newton",
    "sg:classifiers":[
        {
            "category":"Professional",
            "subcategory":"Secretarial Services",
            "type":"Services"
        }
    ],
    "sg:phone":"+61 8 8365 2451",
    "sg:postcode":"5074",
    "sg:province":"SA",
    "sg:tags":[
        "typing"
    ],
    "wof:name":"Hooper M J & D S",
    "wof:placetype":"venue"
},
  "geometry": {"coordinates":[138.68232727,-34.885017395],"type":"Point"}
}