{
  "type": "Feature",
  "properties": {
    "addr:full":"151 Pottery Rd Lenah Valley TAS 7008",
    "addr:housenumber":"151",
    "addr:postcode":"7008",
    "addr:street":"Pottery Rd",
    "iso:country":"AU",
    "sg:address":"151 Pottery Rd",
    "sg:city":"Lenah Valley",
    "sg:classifiers":[
        {
            "category":"Building & Trades",
            "subcategory":"Landscaping Services",
            "type":"Services"
        }
    ],
    "sg:phone":"+61 418 177 650",
    "sg:postcode":"7008",
    "sg:province":"TAS",
    "sg:tags":[
        "stump",
        "tree",
        "felling",
        "removal"
    ],
    "wof:name":"Campbells Tree Service",
    "wof:placetype":"venue"
},
  "geometry": {"coordinates":[147.281784058,-42.8736839294],"type":"Point"}
}