{
  "type": "Feature",
  "properties": {
    "addr:full":"154 Lime Ave Mildura VIC 3500",
    "addr:housenumber":"154",
    "addr:postcode":"3500",
    "addr:street":"Lime Ave",
    "iso:country":"AU",
    "sg:address":"154 Lime Ave",
    "sg:city":"Mildura",
    "sg:classifiers":[
        {
            "category":"Health Services",
            "subcategory":"Health Practitioner",
            "type":"Services"
        }
    ],
    "sg:phone":"+61 3 5023 5122",
    "sg:postcode":"3500",
    "sg:province":"VIC",
    "sg:tags":[
        "acupuncture"
    ],
    "wof:name":"Dr Bob Meyer",
    "wof:placetype":"venue"
},
  "geometry": {"coordinates":[142.15583801299999,-34.1873817444],"type":"Point"}
}