{
  "type": "Feature",
  "properties": {
    "addr:full":"45 Thompson Ave Cowes VIC 3922",
    "addr:housenumber":"45",
    "addr:postcode":"3922",
    "addr:street":"Thompson Ave",
    "iso:country":"AU",
    "sg:address":"45 Thompson Ave",
    "sg:city":"Cowes",
    "sg:classifiers":[
        {
            "category":"Shopping",
            "subcategory":"Clothing, Apparel, & Fashions",
            "type":"Retail Goods"
        }
    ],
    "sg:phone":"+61 3 5952 3877",
    "sg:postcode":"3922",
    "sg:province":"VIC",
    "sg:tags":[
        "lady",
        "wear"
    ],
    "wof:name":"Beach Chums",
    "wof:placetype":"venue"
},
  "geometry": {"coordinates":[145.23916625999999,-38.4496879578],"type":"Point"}
}