{
  "type": "Feature",
  "properties": {
    "addr:full":"386 St Kilda Rd St Kilda VIC 3182",
    "addr:housenumber":"386",
    "addr:postcode":"3182",
    "addr:street":"St Kilda Rd",
    "iso:country":"AU",
    "sg:address":"386 St Kilda Rd",
    "sg:city":"St Kilda",
    "sg:classifiers":[
        {
            "category":"Arts & Performance",
            "subcategory":"Music",
            "type":"Entertainment"
        }
    ],
    "sg:phone":"+61 3 9525 3044",
    "sg:postcode":"3182",
    "sg:province":"VIC",
    "sg:tags":[
        "mobile",
        "jockey",
        "disc"
    ],
    "wof:name":"Aerotechnics Australia",
    "wof:placetype":"venue"
},
  "geometry": {"coordinates":[144.986938477,-37.8670196533],"type":"Point"}
}