{
  "type": "Feature",
  "properties": {
    "addr:full":"787 High St Thornbury VIC 3071",
    "addr:housenumber":"787",
    "addr:postcode":"3071",
    "addr:street":"High St",
    "iso:country":"AU",
    "sg:address":"787 High St",
    "sg:city":"Thornbury",
    "sg:classifiers":[
        {
            "category":"Personal",
            "subcategory":"Beauty Salon",
            "type":"Services"
        }
    ],
    "sg:phone":"+61 3 9484 1032",
    "sg:postcode":"3071",
    "sg:province":"VIC",
    "sg:tags":[
        "hairdresser"
    ],
    "wof:name":"Omorfia Ladies & Gents",
    "wof:placetype":"venue"
},
  "geometry": {"coordinates":[145.000732422,-37.7568206787],"type":"Point"}
}