{
  "type": "Feature",
  "properties": {
    "addr:full":"1 Park St Belconnen ACT 2617",
    "addr:housenumber":"1",
    "addr:postcode":"2617",
    "addr:street":"Park St",
    "iso:country":"AU",
    "sg:address":"1 Park St",
    "sg:city":"Belconnen",
    "sg:classifiers":[
        {
            "category":"Retail",
            "subcategory":"Auto Repair",
            "type":"Services"
        }
    ],
    "sg:phone":"+61 2 6253 1396",
    "sg:postcode":"2617",
    "sg:province":"ACT",
    "sg:tags":[
        "repairer",
        "motor",
        "engineer"
    ],
    "wof:name":"Carco Exhaust & Automotive",
    "wof:placetype":"venue"
},
  "geometry": {"coordinates":[149.061004639,-35.2433929443],"type":"Point"}
}