{
  "type": "Feature",
  "properties": {
    "addr:full":"29 Bight Reefs Rd Singleton WA 6175",
    "addr:housenumber":"29",
    "addr:postcode":"6175",
    "addr:street":"Bight Reefs Rd",
    "iso:country":"AU",
    "sg:address":"29 Bight Reefs Rd",
    "sg:city":"Singleton",
    "sg:classifiers":[
        {
            "category":"Education",
            "subcategory":"Vocational School",
            "type":"Public Place"
        }
    ],
    "sg:phone":"+61 8 9537 1268",
    "sg:postcode":"6175",
    "sg:province":"WA",
    "sg:tags":[
        "finishing",
        "modelling"
    ],
    "wof:name":"Mystique Modelling Academy",
    "wof:placetype":"venue"
},
  "geometry": {"coordinates":[115.75299099999999,-32.451702],"type":"Point"}
}