{
  "type": "Feature",
  "properties": {
    "addr:full":"13 Lyon Park Rd North Ryde NSW 2113",
    "addr:housenumber":"13",
    "addr:postcode":"2113",
    "addr:street":"Lyon Park Rd",
    "iso:country":"AU",
    "sg:address":"13 Lyon Park Rd",
    "sg:city":"North Ryde",
    "sg:classifiers":[
        {
            "category":"Wholesale",
            "subcategory":"Drugs",
            "type":"Manufacturing & Wholesale Goods"
        }
    ],
    "sg:phone":"+61 2 9889 0500",
    "sg:postcode":"2113",
    "sg:province":"NSW",
    "sg:tags":[
        "wholesaler",
        "pharmaceutical",
        "product",
        "mfrs"
    ],
    "wof:name":"Omnicare Clinical Research Pty Ltd",
    "wof:placetype":"venue"
},
  "geometry": {"coordinates":[151.119049072,-33.7850532532],"type":"Point"}
}