{
  "type": "Feature",
  "properties": {
    "iso:country":"AU",
    "sg:address":"Unit 22/ 38-46 South St",
    "sg:city":"Rydalmere",
    "sg:classifiers":[
        {
            "category":"Communications",
            "type":"Services"
        }
    ],
    "sg:phone":"+61 2 9898 1733",
    "sg:postcode":"2116",
    "sg:province":"NSW",
    "sg:tags":[
        "data"
    ],
    "wof:name":"Pacom Bell",
    "wof:placetype":"venue"
},
  "geometry": {"coordinates":[151.01080322300001,-33.8342208862],"type":"Point"}
}