{
  "type": "Feature",
  "properties": {
    "iso:country":"AU",
    "sg:address":"1/ 71 Albany St",
    "sg:city":"Coffs Harbour",
    "sg:classifiers":[
        {
            "category":"Health Services",
            "subcategory":"Health Practitioner",
            "type":"Services"
        }
    ],
    "sg:phone":"+61 2 6651 5811",
    "sg:postcode":"2450",
    "sg:province":"NSW",
    "sg:tags":[
        "psychologist"
    ],
    "wof:name":"Marshell Denise",
    "wof:placetype":"venue"
},
  "geometry": {"coordinates":[153.116287,-30.300774],"type":"Point"}
}