{
  "type": "Feature",
  "properties": {
    "iso:country":"AU",
    "sg:address":"34 Norman St",
    "sg:city":"Wooloowin",
    "sg:classifiers":[
        {
            "category":"Health Services",
            "subcategory":"Health Practitioner",
            "type":"Services"
        }
    ],
    "sg:phone":"+61 7 3857 1219",
    "sg:postcode":"4030",
    "sg:province":"QLD",
    "sg:tags":[
        "physiotherapist"
    ],
    "wof:name":"Beeley Helen",
    "wof:placetype":"venue"
},
  "geometry": {"coordinates":[153.03784200000001,-27.418274],"type":"Point"}
}