{
  "type": "Feature",
  "properties": {
    "addr:full":"Unit 5/ 310 Edgeware Rd Newtown NSW 2042",
    "addr:housenumber":"/ 310",
    "addr:postcode":"2042",
    "addr:street":"Edgeware Rd",
    "iso:country":"AU",
    "sg:address":"Unit 5/ 310 Edgeware Rd",
    "sg:city":"Newtown",
    "sg:classifiers":[
        {
            "category":"Building & Trades",
            "subcategory":"Construction",
            "type":"Services"
        }
    ],
    "sg:phone":"+61 411 480 771",
    "sg:postcode":"2042",
    "sg:province":"NSW",
    "sg:tags":[
        "polishing",
        "sanding",
        "floor"
    ],
    "wof:name":"A.S.A.P. Floor Sanding",
    "wof:placetype":"venue"
},
  "geometry": {"coordinates":[151.17465200000001,-33.907349],"type":"Point"}
}