{
  "type": "Feature",
  "properties": {
    "addr:full":"1a Ely St Athol Park SA 5012",
    "addr:housenumber":"1a",
    "addr:postcode":"5012",
    "addr:street":"Ely St",
    "iso:country":"AU",
    "sg:address":"1a Ely St",
    "sg:city":"Athol Park",
    "sg:phone":"+61 8 8240 0022",
    "sg:postcode":"5012",
    "sg:province":"SA",
    "wof:name":"Aussie Tanks",
    "wof:placetype":"venue"
},
  "geometry": {"coordinates":[138.54090881400001,-34.8580856323],"type":"Point"}
}