{
  "type": "Feature",
  "properties": {
    "iso:country":"AU",
    "sg:address":"Salloom St",
    "sg:city":"Gin Gin",
    "sg:classifiers":[
        {
            "category":"Banks & Credit Unions",
            "subcategory":"Investment Brokerage",
            "type":"Services"
        }
    ],
    "sg:phone":"+61 7 4157 2099",
    "sg:postcode":"4671",
    "sg:province":"QLD",
    "sg:tags":[
        "radiator",
        "motor"
    ],
    "wof:name":"Gin Gin Mechanical & Radiator Repairs",
    "wof:placetype":"venue"
},
  "geometry": {"coordinates":[151.965057,-24.994165],"type":"Point"}
}