{
  "type": "Feature",
  "properties": {
    "addr:full":"2145 Frankston-Flinders Rd Hastings VIC 3915",
    "addr:housenumber":"2145",
    "addr:postcode":"3915",
    "addr:street":"Frankston-Flinders Rd",
    "iso:country":"AU",
    "sg:address":"2145 Frankston-Flinders Rd",
    "sg:city":"Hastings",
    "sg:classifiers":[
        {
            "category":"Wholesale",
            "subcategory":"Metals & Minerals",
            "type":"Manufacturing & Wholesale Goods"
        }
    ],
    "sg:phone":"+61 3 5979 1425",
    "sg:postcode":"3915",
    "sg:province":"VIC",
    "sg:tags":[
        "steel",
        "merchant"
    ],
    "wof:name":"K & K Steel Building Supplies",
    "wof:placetype":"venue"
},
  "geometry": {"coordinates":[145.18347168,-38.3123931885],"type":"Point"}
}