{
  "type": "Feature",
  "properties": {
    "addr:full":"Roadside Mail Box 3075 Traralgon VIC 3844",
    "addr:postcode":"3844",
    "iso:country":"AU",
    "sg:address":"Roadside Mail Box 3075",
    "sg:city":"Traralgon",
    "sg:classifiers":[
        {
            "category":"Professional",
            "subcategory":"Employment Agencies",
            "type":"Services"
        }
    ],
    "sg:phone":"+61 409 233 121",
    "sg:postcode":"3844",
    "sg:province":"VIC",
    "sg:tags":[
        "entertainer",
        "agent"
    ],
    "wof:name":"PASH",
    "wof:placetype":"venue"
},
  "geometry": {"coordinates":[146.53814697300001,-38.1949501038],"type":"Point"}
}