{
  "type": "Feature",
  "properties": {
    "addr:full":"Lvl8/ 87 Wickham Tce Spring Hill QLD 4000",
    "addr:housenumber":"87",
    "addr:postcode":"4000",
    "addr:street":"Wickham Tce",
    "iso:country":"AU",
    "sg:address":"Lvl8/ 87",
    "sg:city":"Wickham Tce Spring Hill",
    "sg:classifiers":[
        {
            "category":"Banks & Credit Unions",
            "subcategory":"Financial Services",
            "type":"Services"
        }
    ],
    "sg:phone":"+61 7 3832 2319",
    "sg:postcode":"4000",
    "sg:province":"QLD",
    "sg:tags":[
        "planning"
    ],
    "wof:name":"Calbridge Investment Management",
    "wof:placetype":"venue"
},
  "geometry": {"coordinates":[153.02684020999999,-27.4644565582],"type":"Point"}
}