{
  "type": "Feature",
  "properties": {
    "iso:country":"AU",
    "sg:address":"Lot 75 Industrial Estate",
    "sg:city":"Nhulunbuy",
    "sg:classifiers":[
        {
            "category":"Recreation",
            "subcategory":"Boat Charter",
            "type":"Entertainment"
        }
    ],
    "sg:phone":"+61 8 8987 3181",
    "sg:postcode":"0881",
    "sg:province":"NT",
    "wof:name":"Arnhem Boat Hire",
    "wof:placetype":"venue"
},
  "geometry": {"coordinates":[136.78602599999999,-12.18588],"type":"Point"}
}