{
  "type": "Feature",
  "properties": {
    "addr:full":"439 -447 Cleveland-Redland Bay Rd Victoria Point QLD 4165",
    "addr:housenumber":"-447",
    "addr:postcode":"4165",
    "addr:street":"Cleveland-Redland Bay Rd",
    "iso:country":"AU",
    "sg:address":"439 -447 Cleveland-Redland Bay Rd",
    "sg:city":"Victoria Point",
    "sg:classifiers":[
        {
            "category":"Autos & Motor Vehicles",
            "subcategory":"Fuel & Gas Station",
            "type":"Retail Goods"
        }
    ],
    "sg:phone":"+61 7 3207 9671",
    "sg:postcode":"4165",
    "sg:province":"QLD",
    "wof:name":"Quix Food Stores",
    "wof:placetype":"venue"
},
  "geometry": {"coordinates":[153.283599853,-27.5913066864],"type":"Point"}
}