{
  "type": "Feature",
  "properties": {
    "addr:full":"Alexandra St Hunters Hill NSW 2110",
    "addr:postcode":"2110",
    "addr:street":"Alexandra St",
    "iso:country":"AU",
    "sg:address":"Alexandra St",
    "sg:city":"Hunters Hill",
    "sg:classifiers":[
        {
            "category":"Education",
            "subcategory":"School",
            "type":"Public Place"
        }
    ],
    "sg:phone":"+61 2 9816 4404",
    "sg:postcode":"2110",
    "sg:province":"NSW",
    "sg:tags":[
        "state",
        "-",
        "nsw"
    ],
    "wof:name":"Hunters Hill Public School",
    "wof:placetype":"venue"
},
  "geometry": {"coordinates":[151.15487670900001,-33.8348999023],"type":"Point"}
}