{
  "type": "Feature",
  "properties": {
    "addr:full":"6 Braeside St Wahroonga NSW 2076",
    "addr:housenumber":"6",
    "addr:postcode":"2076",
    "addr:street":"Braeside St",
    "iso:country":"AU",
    "sg:address":"6 Braeside St",
    "sg:city":"Wahroonga",
    "sg:classifiers":[
        {
            "category":"Professional",
            "subcategory":"Computer Services",
            "type":"Services"
        }
    ],
    "sg:phone":"+61 1300 660 288",
    "sg:postcode":"2076",
    "sg:province":"NSW",
    "sg:tags":[
        "equipment",
        "networking",
        "installation"
    ],
    "wof:name":"Geeks 2 U",
    "wof:placetype":"venue"
},
  "geometry": {"coordinates":[151.122116089,-33.7120094299],"type":"Point"}
}