{
  "type": "Feature",
  "properties": {
    "addr:full":"15 Holly St O'Halloran Hill SA 5158",
    "addr:housenumber":"15",
    "addr:postcode":"5158",
    "addr:street":"Holly St O'Halloran",
    "iso:country":"AU",
    "sg:address":"15 Holly St",
    "sg:city":"O'Halloran Hill",
    "sg:classifiers":[
        {
            "category":"Health Services",
            "subcategory":"Health Practitioner",
            "type":"Services"
        }
    ],
    "sg:phone":"+61 8 8381 8571",
    "sg:postcode":"5158",
    "sg:province":"SA",
    "sg:tags":[
        "naturopath"
    ],
    "wof:name":"Chivers Dorothy",
    "wof:placetype":"venue"
},
  "geometry": {"coordinates":[138.55874633799999,-35.0626869202],"type":"Point"}
}