{
  "type": "Feature",
  "properties": {
    "addr:full":"246 New Line Rd Dural NSW 2158",
    "addr:housenumber":"246",
    "addr:postcode":"2158",
    "addr:street":"New Line Rd",
    "iso:country":"AU",
    "sg:address":"246 New Line Rd",
    "sg:city":"Dural",
    "sg:classifiers":[
        {
            "category":"Building & Trades",
            "subcategory":"Cleaning & Sanitation",
            "type":"Services"
        }
    ],
    "sg:phone":"+61 2 9651 1536",
    "sg:postcode":"2158",
    "sg:province":"NSW",
    "sg:tags":[
        "tank",
        "septic"
    ],
    "wof:name":"Southern Cross Laboratories (Actizyme)",
    "wof:placetype":"venue"
},
  "geometry": {"coordinates":[151.03053283700001,-33.6961975098],"type":"Point"}
}