{
  "type": "Feature",
  "properties": {
    "iso:country":"AU",
    "sg:address":"U 5/ 244 Horsley Rd",
    "sg:city":"Milperra",
    "sg:classifiers":[
        {
            "category":"Professional",
            "subcategory":"Printing & Photocopies",
            "type":"Services"
        }
    ],
    "sg:phone":"+61 2 9792 2218",
    "sg:postcode":"2214",
    "sg:province":"NSW",
    "sg:tags":[
        "screen",
        "printer"
    ],
    "wof:name":"Design-A-Mite",
    "wof:placetype":"venue"
},
  "geometry": {"coordinates":[150.994064,-33.944221],"type":"Point"}
}