{
  "type": "Feature",
  "properties": {
    "addr:full":"10 Thompson St Bowen Hills QLD 4006",
    "addr:housenumber":"10",
    "addr:postcode":"4006",
    "addr:street":"Thompson St",
    "iso:country":"AU",
    "sg:address":"10 Thompson St",
    "sg:city":"Bowen Hills",
    "sg:classifiers":[
        {
            "category":"Retail",
            "subcategory":"Auto Repair",
            "type":"Services"
        }
    ],
    "sg:phone":"+61 7 3252 9050",
    "sg:postcode":"4006",
    "sg:province":"QLD",
    "sg:tags":[
        "automotive",
        "air conditioning"
    ],
    "wof:name":"Jayair",
    "wof:placetype":"venue"
},
  "geometry": {"coordinates":[153.04022216800001,-27.4419784546],"type":"Point"}
}