{
  "type": "Feature",
  "properties": {
    "addr:full":"Shop 2, 79 Waratah Ave Dalkeith WA 6009",
    "addr:housenumber":"shop;79",
    "addr:postcode":"6009",
    "addr:street":"Waratah Ave",
    "iso:country":"AU",
    "sg:address":"Shop 2, 79 Waratah Ave",
    "sg:city":"Dalkeith",
    "sg:classifiers":[
        {
            "category":"Personal",
            "subcategory":"Beauty Salon",
            "type":"Services"
        }
    ],
    "sg:phone":"+61 8 9386 5491",
    "sg:postcode":"6009",
    "sg:province":"WA",
    "sg:tags":[
        "hairdresser"
    ],
    "wof:name":"Mirage Hairdressers",
    "wof:placetype":"venue"
},
  "geometry": {"coordinates":[115.7985,-31.994621],"type":"Point"}
}