{
  "type": "Feature",
  "properties": {
    "addr:full":"Boud Ave Perth Airport WA 6105",
    "addr:postcode":"6105",
    "addr:street":"Boud Ave",
    "iso:country":"AU",
    "sg:address":"Boud Ave",
    "sg:city":"Perth Airport",
    "sg:classifiers":[
        {
            "category":"Professional",
            "type":"Services"
        }
    ],
    "sg:phone":"+61 13 23 45",
    "sg:postcode":"6105",
    "sg:province":"WA",
    "sg:tags":[
        "transport"
    ],
    "wof:name":"Star Track Express",
    "wof:placetype":"venue"
},
  "geometry": {"coordinates":[115.957107544,-31.9367618561],"type":"Point"}
}