{
  "type": "Feature",
  "properties": {
    "iso:country":"AU",
    "sg:address":"Holm Park Rd",
    "sg:city":"Beaconsfield",
    "sg:classifiers":[
        {
            "category":"Home & Garden",
            "subcategory":"Garden Supply",
            "type":"Retail Goods"
        }
    ],
    "sg:phone":"+61 408 338 883",
    "sg:postcode":"3807",
    "sg:province":"VIC",
    "sg:tags":[
        "equipment"
    ],
    "wof:name":"Mulch Maker Pty Ltd",
    "wof:placetype":"venue"
},
  "geometry": {"coordinates":[145.37562560999999,-38.0389404297],"type":"Point"}
}