{
  "type": "Feature",
  "properties": {
    "addr:full":"Wyatt Park Wyatt Ave Belrose NSW 2085",
    "addr:postcode":"2085",
    "addr:street":"Wyatt Ave",
    "iso:country":"AU",
    "sg:address":"Wyatt Park Wyatt Ave",
    "sg:city":"Belrose",
    "sg:classifiers":[
        {
            "category":"Sports & Exercise",
            "subcategory":"Sports Center",
            "type":"Entertainment"
        }
    ],
    "sg:phone":"+61 412 261 689",
    "sg:postcode":"2085",
    "sg:province":"NSW",
    "sg:tags":[
        "coach",
        "tennis"
    ],
    "wof:name":"Smith's Tennis School ( Belrose )",
    "wof:placetype":"venue"
},
  "geometry": {"coordinates":[151.21682739299999,-33.722328186],"type":"Point"}
}