{
  "type": "Feature",
  "properties": {
    "iso:country":"AU",
    "sg:address":"57 McHarg Rd",
    "sg:city":"Happy Valley",
    "sg:classifiers":[
        {
            "category":"Building & Trades",
            "subcategory":"Construction",
            "type":"Services"
        }
    ],
    "sg:phone":"+61 8 8381 8846",
    "sg:postcode":"5159",
    "sg:province":"SA",
    "sg:tags":[
        "window",
        "aluminium"
    ],
    "wof:name":"Allen Gary",
    "wof:placetype":"venue"
},
  "geometry": {"coordinates":[138.589767456,-35.0914840698],"type":"Point"}
}