{
  "type": "Feature",
  "properties": {
    "iso:country":"AU",
    "sg:address":"5- 15 Epsom Rd",
    "sg:city":"Rosebery",
    "sg:classifiers":[
        {
            "category":"Shopping",
            "subcategory":"Stationery & Office Supplies",
            "type":"Retail Goods"
        }
    ],
    "sg:phone":"+61 1300 788 299",
    "sg:postcode":"2018",
    "sg:province":"NSW",
    "sg:tags":[
        "packaging",
        "equipment",
        "sealing",
        "filling"
    ],
    "wof:name":"Global Food Equipment",
    "wof:placetype":"venue"
},
  "geometry": {"coordinates":[151.202957153,-33.9103775024],"type":"Point"}
}