{
  "type": "Feature",
  "properties": {
    "addr:full":"531 Burke Road, Camberwell VIC 3124",
    "addr:housenumber":"531",
    "addr:postcode":"3124",
    "addr:street":"Burke Road",
    "iso:country":"AU",
    "sg:address":"531 Burke Road,",
    "sg:city":"Camberwell",
    "sg:classifiers":[
        {
            "category":"Home & Garden",
            "subcategory":"Carpets & Floor Coverings",
            "type":"Retail Goods"
        }
    ],
    "sg:phone":"+61 3 9822 7787",
    "sg:postcode":"3124",
    "sg:province":"VIC",
    "sg:tags":[
        "material",
        "waterproofing"
    ],
    "wof:name":"The Waterstop Shop",
    "wof:placetype":"venue"
},
  "geometry": {"coordinates":[145.054153442,-37.8439064026],"type":"Point"}
}