{
  "type": "Feature",
  "properties": {
    "iso:country":"AU",
    "sg:address":"Forster Cape Hawke Community Medical Centre Cnr Breckenridge & South Sts",
    "sg:city":"Forster",
    "sg:classifiers":[
        {
            "category":"Health Services",
            "subcategory":"Doctor",
            "type":"Services"
        }
    ],
    "sg:phone":"+61 2 6554 7129",
    "sg:postcode":"2428",
    "sg:province":"NSW",
    "sg:tags":[
        "medical",
        "practitioner"
    ],
    "wof:name":"Mayne Laverty Pathology Collection Centres",
    "wof:placetype":"venue"
},
  "geometry": {"coordinates":[152.51496900000001,-32.186188],"type":"Point"}
}