{
  "type": "Feature",
  "properties": {
    "iso:country":"AU",
    "sg:address":"203 Power St",
    "sg:city":"Glendenning",
    "sg:classifiers":[
        {
            "category":"Wholesale",
            "subcategory":"Construction Materials",
            "type":"Manufacturing & Wholesale Goods"
        }
    ],
    "sg:phone":"+61 2 9839 1111",
    "sg:postcode":"2761",
    "sg:province":"NSW",
    "sg:tags":[
        "protective",
        "coating"
    ],
    "wof:name":"The Valspar (Aust) Corp Pty. Limited",
    "wof:placetype":"venue"
},
  "geometry": {"coordinates":[150.84806800000001,-33.75256],"type":"Point"}
}