{
  "type": "Feature",
  "properties": {
    "addr:full":"45 Fairy St Bell Post Hill VIC 3215",
    "addr:housenumber":"45",
    "addr:postcode":"3215",
    "addr:street":"Fairy St",
    "iso:country":"AU",
    "sg:address":"45 Fairy St",
    "sg:city":"Bell Post Hill",
    "sg:classifiers":[
        {
            "category":"Health Services",
            "subcategory":"Doctor",
            "type":"Services"
        }
    ],
    "sg:phone":"+61 3 5278 1122",
    "sg:postcode":"3215",
    "sg:province":"VIC",
    "sg:tags":[
        "medical",
        "practitioner"
    ],
    "wof:name":"Pape A M",
    "wof:placetype":"venue"
},
  "geometry": {"coordinates":[144.32797241200001,-38.1039962769],"type":"Point"}
}