{
  "type": "Feature",
  "properties": {
    "addr:full":"25-27 Dickson St Mt Waverley VIC 3149",
    "addr:housenumber":"25-27",
    "addr:postcode":"3149",
    "addr:street":"Dickson St Mt",
    "iso:country":"AU",
    "sg:address":"25-27 Dickson St",
    "sg:city":"Mt Waverley",
    "sg:classifiers":[
        {
            "category":"Health Services",
            "subcategory":"Doctor",
            "type":"Services"
        }
    ],
    "sg:phone":"+61 3 9807 7007",
    "sg:postcode":"3149",
    "sg:province":"VIC",
    "sg:tags":[
        "medical",
        "practitioner"
    ],
    "wof:name":"Dickson Street Medical Centre",
    "wof:placetype":"venue"
},
  "geometry": {"coordinates":[145.11146545400001,-37.8901672363],"type":"Point"}
}