{
  "type": "Feature",
  "properties": {
    "addr:full":"16 Victoria Crs St Albans VIC 3021",
    "addr:housenumber":"16",
    "addr:postcode":"3021",
    "addr:street":"Victoria Crs",
    "iso:country":"AU",
    "sg:address":"16 Victoria Crs",
    "sg:city":"St Albans",
    "sg:classifiers":[
        {
            "category":"Professional",
            "subcategory":"Employment Agencies",
            "type":"Services"
        }
    ],
    "sg:phone":"+61 3 9367 5204",
    "sg:postcode":"3021",
    "sg:province":"VIC",
    "wof:name":"A.M.E.S. Employment Services",
    "wof:placetype":"venue"
},
  "geometry": {"coordinates":[144.800217,-37.744259],"type":"Point"}
}