{
  "type": "Feature",
  "properties": {
    "iso:country":"AU",
    "sg:address":"43 Amulet St",
    "sg:city":"Portsmith",
    "sg:classifiers":[
        {
            "category":"Retail",
            "subcategory":"Event Space",
            "type":"Services"
        }
    ],
    "sg:phone":"+61 7 4035 2700",
    "sg:postcode":"4870",
    "sg:province":"QLD",
    "sg:tags":[
        "function",
        "organiser"
    ],
    "wof:name":"QRI Cairns Licensed Club",
    "wof:placetype":"venue"
},
  "geometry": {"coordinates":[145.71661376899999,-16.8993663788],"type":"Point"}
}