{
  "type": "Feature",
  "properties": {
    "addr:full":"1 Chester Hill Rd Chester Hill NSW 2162",
    "addr:housenumber":"1",
    "addr:postcode":"2162",
    "addr:street":"Chester Hill Rd",
    "iso:country":"AU",
    "sg:address":"1 Chester Hill Rd",
    "sg:city":"Chester Hill",
    "sg:classifiers":[
        {
            "category":"Shopping",
            "subcategory":"Pawn Shop",
            "type":"Retail Goods"
        }
    ],
    "sg:phone":"+61 2 9645 1098",
    "sg:postcode":"2162",
    "sg:province":"NSW",
    "sg:tags":[
        "pawnbroker"
    ],
    "wof:name":"Chester Hill Pawnbroker",
    "wof:placetype":"venue"
},
  "geometry": {"coordinates":[151.000762939,-33.8831977844],"type":"Point"}
}