{
  "type": "Feature",
  "properties": {
    "addr:full":"695 Sandgate Rd Clayfield QLD 4011",
    "addr:housenumber":"695",
    "addr:postcode":"4011",
    "addr:street":"Sandgate Rd",
    "iso:country":"AU",
    "sg:address":"695 Sandgate Rd",
    "sg:city":"Clayfield",
    "sg:classifiers":[
        {
            "category":"Banks & Credit Unions",
            "subcategory":"Investment Brokerage",
            "type":"Services"
        }
    ],
    "sg:phone":"+61 7 3262 4433",
    "sg:postcode":"4011",
    "sg:province":"QLD",
    "sg:tags":[
        "management",
        "property"
    ],
    "wof:name":"Clayfield Unit Centre",
    "wof:placetype":"venue"
},
  "geometry": {"coordinates":[153.054565,-27.419502],"type":"Point"}
}