{
  "type": "Feature",
  "properties": {
    "addr:full":"Ste13 Lvl 10 Evan Thomson Bldg 24 Chasely St Auchenflower QLD 4066",
    "addr:housenumber":"10;24",
    "addr:postcode":"4066",
    "addr:street":"Evan;Chasely St",
    "iso:country":"AU",
    "sg:address":"Ste13 Lvl 10 Evan Thomson Bldg 24 Chasely St",
    "sg:city":"Auchenflower",
    "sg:classifiers":[
        {
            "category":"Health Services",
            "subcategory":"Doctor",
            "type":"Services"
        }
    ],
    "sg:phone":"+61 7 3871 2277",
    "sg:postcode":"4066",
    "sg:province":"QLD",
    "sg:tags":[
        "medical",
        "practitioner"
    ],
    "wof:name":"Adib Reza Dr",
    "wof:placetype":"venue"
},
  "geometry": {"coordinates":[152.998046875,-27.4772014618],"type":"Point"}
}