{
  "type": "Feature",
  "properties": {
    "iso:country":"AU",
    "sg:address":"Shp 1/ 194 Goulburn St",
    "sg:city":"Surry Hills",
    "sg:classifiers":[
        {
            "category":"Cafe",
            "type":"Food & Drink"
        }
    ],
    "sg:phone":"+61 2 9264 6804",
    "sg:postcode":"2010",
    "sg:province":"NSW",
    "wof:name":"Cafe 194",
    "wof:placetype":"venue"
},
  "geometry": {"coordinates":[151.21368408199999,-33.8793258667],"type":"Point"}
}