{
  "type": "Feature",
  "properties": {
    "iso:country":"AU",
    "sg:address":"16 Lyons Drv",
    "sg:city":"Selby",
    "sg:classifiers":[
        {
            "category":"Social Services",
            "subcategory":"Retirement Home",
            "type":"Services"
        }
    ],
    "sg:phone":"+61 3 9754 6024",
    "sg:postcode":"3159",
    "sg:province":"VIC",
    "sg:tags":[
        "accommodation",
        "special"
    ],
    "wof:name":"Selby Court Supportive Residential Care",
    "wof:placetype":"venue"
},
  "geometry": {"coordinates":[145.37103271500001,-37.914100647],"type":"Point"}
}