{
  "type": "Feature",
  "properties": {
    "addr:full":"128 Barkly St Brunswick East VIC 3057",
    "addr:housenumber":"128",
    "addr:postcode":"3057",
    "addr:street":"Barkly St",
    "iso:country":"AU",
    "sg:address":"128 Barkly St",
    "sg:city":"Brunswick East",
    "sg:classifiers":[
        {
            "category":"Wholesale",
            "subcategory":"Photographic Equipment",
            "type":"Manufacturing & Wholesale Goods"
        }
    ],
    "sg:phone":"+61 3 9381 1455",
    "sg:postcode":"3057",
    "sg:province":"VIC",
    "sg:tags":[
        "wholesaler",
        "mfrs",
        "supply"
    ],
    "wof:name":"B.C.S. Photographics & Video",
    "wof:placetype":"venue"
},
  "geometry": {"coordinates":[144.9715271,-37.7774276733],"type":"Point"}
}