{
  "type": "Feature",
  "properties": {
    "iso:country":"AU",
    "sg:address":"1/ 25 Central Rd",
    "sg:city":"Port Macquarie",
    "sg:classifiers":[
        {
            "category":"Bars & Pubs",
            "subcategory":"Lounge",
            "type":"Food & Drink"
        }
    ],
    "sg:phone":"+61 2 6581 1855",
    "sg:postcode":"2444",
    "sg:province":"NSW",
    "sg:tags":[
        "water",
        "filter",
        "drinking"
    ],
    "wof:name":"Barry's Handyland",
    "wof:placetype":"venue"
},
  "geometry": {"coordinates":[152.893295,-31.448105],"type":"Point"}
}