{
  "type": "Feature",
  "properties": {
    "addr:full":"5 Martin St Nerang QLD 4211",
    "addr:housenumber":"5",
    "addr:postcode":"4211",
    "addr:street":"Martin St",
    "iso:country":"AU",
    "sg:address":"5 Martin St",
    "sg:city":"Nerang",
    "sg:classifiers":[
        {
            "category":"Building & Trades",
            "subcategory":"Plumbing",
            "type":"Services"
        }
    ],
    "sg:phone":"+61 7 5578 1046",
    "sg:postcode":"4211",
    "sg:province":"QLD",
    "sg:tags":[
        "plumber",
        "gasfitters"
    ],
    "wof:name":"Pete The Plumber Nerang",
    "wof:placetype":"venue"
},
  "geometry": {"coordinates":[153.33494567899999,-27.9868602753],"type":"Point"}
}