{
  "type": "Feature",
  "properties": {
    "addr:full":"Room 16 Paddington Market 261 Given Tce Paddington QLD 4064",
    "addr:housenumber":"261",
    "addr:postcode":"4064",
    "addr:street":"Given Tce",
    "iso:country":"AU",
    "sg:address":"Room 16 Paddington Market 261",
    "sg:city":"Given Tce Paddington",
    "sg:classifiers":[
        {
            "category":"Health Services",
            "subcategory":"Dentist",
            "type":"Services"
        }
    ],
    "sg:phone":"+61 7 3369 2340",
    "sg:postcode":"4064",
    "sg:province":"QLD",
    "wof:name":"Renton Ian P",
    "wof:placetype":"venue"
},
  "geometry": {"coordinates":[153.00668335,-27.4619503021],"type":"Point"}
}