{
  "type": "Feature",
  "properties": {
    "iso:country":"AU",
    "sg:address":"Level 10, 157 Walker St",
    "sg:city":"North Sydney",
    "sg:classifiers":[
        {
            "category":"Banks & Credit Unions",
            "subcategory":"Bureau De Change",
            "type":"Services"
        }
    ],
    "sg:phone":"+61 2 8912 2323",
    "sg:postcode":"2060",
    "sg:province":"NSW",
    "sg:tags":[
        "card"
    ],
    "wof:name":"MyCard Credit Cards",
    "wof:placetype":"venue"
},
  "geometry": {"coordinates":[151.20930480999999,-33.8374290466],"type":"Point"}
}