{
  "type": "Feature",
  "properties": {
    "addr:full":"Building A, 4 Moreton Rd Minto Heights NSW 2566",
    "addr:housenumber":"4",
    "addr:postcode":"2566",
    "addr:street":"Moreton Rd",
    "iso:country":"AU",
    "sg:address":"Building A, 4 Moreton Rd",
    "sg:city":"Minto Heights",
    "sg:classifiers":[
        {
            "category":"Communications",
            "type":"Services"
        }
    ],
    "sg:phone":"+61 2 9820 2635",
    "sg:postcode":"2566",
    "sg:province":"NSW",
    "sg:tags":[
        "equipment",
        "satellite"
    ],
    "wof:name":"Antenna Engineering International",
    "wof:placetype":"venue"
},
  "geometry": {"coordinates":[150.87515258799999,-34.0373039246],"type":"Point"}
}