{
  "type": "Feature",
  "properties": {
    "iso:country":"AU",
    "sg:address":"8 Miriam St",
    "sg:city":"Caulfield",
    "sg:classifiers":[
        {
            "category":"Building & Trades",
            "subcategory":"Construction",
            "type":"Services"
        }
    ],
    "sg:phone":"+61 3 9571 1035",
    "sg:postcode":"3162",
    "sg:province":"VIC",
    "sg:tags":[
        "contractor"
    ],
    "wof:name":"Taylaoak Pty Ltd Builders & Designers",
    "wof:placetype":"venue"
},
  "geometry": {"coordinates":[145.03594970699999,-37.8848648071],"type":"Point"}
}