{
  "type": "Feature",
  "properties": {
    "addr:full":"3 Francis Hollis Drv Tathra NSW 2550",
    "addr:housenumber":"3",
    "addr:postcode":"2550",
    "addr:street":"Francis Hollis Drv",
    "iso:country":"AU",
    "sg:address":"3 Francis Hollis Drv",
    "sg:city":"Tathra",
    "sg:classifiers":[
        {
            "category":"Building & Trades",
            "subcategory":"Construction",
            "type":"Services"
        }
    ],
    "sg:phone":"+61 2 6494 4313",
    "sg:postcode":"2550",
    "sg:province":"NSW",
    "sg:tags":[
        "concrete",
        "contractor"
    ],
    "wof:name":"M.J. Denning Concreting",
    "wof:placetype":"venue"
},
  "geometry": {"coordinates":[149.97508239699999,-36.7247238159],"type":"Point"}
}