{
  "type": "Feature",
  "properties": {
    "addr:full":"Lucca Rd Wyong North NSW 2259",
    "addr:postcode":"2259",
    "addr:street":"Lucca Rd",
    "iso:country":"AU",
    "sg:address":"Lucca Rd",
    "sg:city":"Wyong North",
    "sg:classifiers":[
        {
            "category":"Freight",
            "type":"Transportation"
        }
    ],
    "sg:phone":"+61 1800 800 042",
    "sg:postcode":"2259",
    "sg:province":"NSW",
    "sg:tags":[
        "cargo",
        "container"
    ],
    "wof:name":"Betta Storage Containers",
    "wof:placetype":"venue"
},
  "geometry": {"coordinates":[151.41911315900001,-33.3097610474],"type":"Point"}
}