{
  "type": "Feature",
  "properties": {
    "addr:full":"Windsor Rd Northmead NSW 2152",
    "addr:postcode":"2152",
    "addr:street":"Windsor Rd",
    "iso:country":"AU",
    "sg:address":"Windsor Rd",
    "sg:city":"Northmead",
    "sg:classifiers":[
        {
            "category":"Fast Food",
            "type":"Food & Drink"
        }
    ],
    "sg:phone":"+61 2 9683 4615",
    "sg:postcode":"2152",
    "sg:province":"NSW",
    "sg:tags":[
        "away",
        "take"
    ],
    "wof:name":"Hill Ocean Seafood",
    "wof:placetype":"venue"
},
  "geometry": {"coordinates":[150.996185303,-33.7838401794],"type":"Point"}
}