{
  "type": "Feature",
  "properties": {
    "iso:country":"AU",
    "sg:address":"18 Kaybrook Crt",
    "sg:city":"Oakleigh South",
    "sg:classifiers":[
        {
            "category":"Personal",
            "subcategory":"Massage",
            "type":"Services"
        }
    ],
    "sg:phone":"+61 3 9544 6469",
    "sg:postcode":"3167",
    "sg:province":"VIC",
    "sg:tags":[
        "therapy"
    ],
    "wof:name":"Rook Rosemary",
    "wof:placetype":"venue"
},
  "geometry": {"coordinates":[145.108032227,-37.9235610962],"type":"Point"}
}