{
  "type": "Feature",
  "properties": {
    "iso:country":"AU",
    "sg:address":"Boggy Creek Rd",
    "sg:city":"Myrrhee",
    "sg:classifiers":[
        {
            "category":"Farming",
            "subcategory":"Farm",
            "type":"Manufacturing & Wholesale Goods"
        }
    ],
    "sg:phone":"+61 3 5729 7518",
    "sg:postcode":"3732",
    "sg:province":"VIC",
    "sg:tags":[
        "farmer"
    ],
    "wof:name":"Earp A L",
    "wof:placetype":"venue"
},
  "geometry": {"coordinates":[146.32443237300001,-36.7222595215],"type":"Point"}
}