{
  "type": "Feature",
  "properties": {
    "addr:full":"6 Hillside St Springvale VIC 3171",
    "addr:housenumber":"6",
    "addr:postcode":"3171",
    "addr:street":"Hillside St",
    "iso:country":"AU",
    "sg:address":"6 Hillside St",
    "sg:city":"Springvale",
    "sg:classifiers":[
        {
            "category":"Professional",
            "subcategory":"Engineering",
            "type":"Services"
        }
    ],
    "sg:phone":"+61 3 9546 2786",
    "sg:postcode":"3171",
    "sg:province":"VIC",
    "sg:tags":[
        "engineer",
        "structural"
    ],
    "wof:name":"Galijan Engineers Pty Ltd",
    "wof:placetype":"venue"
},
  "geometry": {"coordinates":[145.16546630900001,-37.9403648376],"type":"Point"}
}