{
  "type": "Feature",
  "properties": {
    "iso:country":"AU",
    "sg:address":"33/ 532 Canterbury Rd",
    "sg:city":"Campsie",
    "sg:classifiers":[
        {
            "category":"Health Services",
            "subcategory":"Doctor",
            "type":"Services"
        }
    ],
    "sg:phone":"+61 2 9797 7438",
    "sg:postcode":"2194",
    "sg:province":"NSW",
    "sg:tags":[
        "medical",
        "practitioner"
    ],
    "wof:name":"Claxton Robert C",
    "wof:placetype":"venue"
},
  "geometry": {"coordinates":[151.09910600000001,-33.920555],"type":"Point"}
}