{
  "type": "Feature",
  "properties": {
    "addr:full":"Level 1/ 3 Hodgson St Fitzroy VIC 3065",
    "addr:housenumber":"/ 3",
    "addr:postcode":"3065",
    "addr:street":"Hodgson St",
    "iso:country":"AU",
    "sg:address":"Level 1/ 3 Hodgson St",
    "sg:city":"Fitzroy",
    "sg:classifiers":[
        {
            "category":"Education",
            "subcategory":"Dance Studio",
            "type":"Public Place"
        }
    ],
    "sg:phone":"+61 3 9417 6072",
    "sg:postcode":"3065",
    "sg:province":"VIC",
    "sg:tags":[
        "venue",
        "tuition"
    ],
    "wof:name":"Dance Cats",
    "wof:placetype":"venue"
},
  "geometry": {"coordinates":[144.98326110799999,-37.8018188477],"type":"Point"}
}