{
  "type": "Feature",
  "properties": {
    "iso:country":"AU",
    "sg:address":"14 Pettit St",
    "sg:city":"Norlane",
    "sg:classifiers":[
        {
            "category":"Retail",
            "subcategory":"Storage",
            "type":"Services"
        }
    ],
    "sg:phone":"+61 3 5278 7825",
    "sg:postcode":"3214",
    "sg:province":"VIC",
    "sg:tags":[
        "removal",
        "furniture"
    ],
    "wof:name":"Quick & Reliable Removals",
    "wof:placetype":"venue"
},
  "geometry": {"coordinates":[144.358551025,-38.0977668762],"type":"Point"}
}