{
  "type": "Feature",
  "properties": {
    "iso:country":"AU",
    "sg:address":"185 Harbour Drv",
    "sg:city":"Coffs Harbour",
    "sg:classifiers":[
        {
            "category":"Health Services",
            "subcategory":"Dentist",
            "type":"Services"
        }
    ],
    "sg:phone":"+61 2 6652 2733",
    "sg:postcode":"2450",
    "sg:province":"NSW",
    "wof:name":"Harbour Drive Dental",
    "wof:placetype":"venue"
},
  "geometry": {"coordinates":[153.11734,-30.298359],"type":"Point"}
}