{
  "type": "Feature",
  "properties": {
    "iso:country":"AU",
    "sg:address":"1 Cooney St",
    "sg:city":"Ipswich",
    "sg:classifiers":[
        {
            "category":"Wholesale",
            "subcategory":"Farm Supplies",
            "type":"Manufacturing & Wholesale Goods"
        }
    ],
    "sg:phone":"+61 7 3281 5878",
    "sg:postcode":"4305",
    "sg:province":"QLD",
    "sg:tags":[
        "equipment"
    ],
    "wof:name":"Hughes Welding & Fabrications",
    "wof:placetype":"venue"
},
  "geometry": {"coordinates":[152.75717163100001,-27.6329994202],"type":"Point"}
}