{
  "type": "Feature",
  "properties": {
    "addr:full":"87A Thomas Mitchell Drv Wodonga NSW 3690",
    "addr:housenumber":"87a",
    "addr:postcode":"3690",
    "addr:street":"Thomas Mitchell Drv",
    "iso:country":"AU",
    "sg:address":"87A Thomas Mitchell Drv",
    "sg:city":"Wodonga",
    "sg:classifiers":[
        {
            "category":"Building & Trades",
            "subcategory":"Construction",
            "type":"Services"
        }
    ],
    "sg:phone":"+61 2 6056 1077",
    "sg:postcode":"3690",
    "sg:province":"NSW",
    "sg:tags":[
        "joinery"
    ],
    "wof:name":"B & B Joinery",
    "wof:placetype":"venue"
},
  "geometry": {"coordinates":[146.903076172,-36.1338844299],"type":"Point"}
}