{
  "type": "Feature",
  "properties": {
    "iso:country":"AU",
    "sg:address":"6 Watkin St",
    "sg:city":"Rockdale",
    "sg:classifiers":[
        {
            "category":"Real Estate",
            "subcategory":"Real Estate Agent",
            "type":"Services"
        }
    ],
    "sg:phone":"+61 2 9556 1155",
    "sg:postcode":"2216",
    "sg:province":"NSW",
    "sg:tags":[
        "export"
    ],
    "wof:name":"Express Padala",
    "wof:placetype":"venue"
},
  "geometry": {"coordinates":[151.13324,-33.95219],"type":"Point"}
}