{
  "type": "Feature",
  "properties": {
    "addr:full":"191 Marion St Leichhardt NSW 2040",
    "addr:housenumber":"191",
    "addr:postcode":"2040",
    "addr:street":"Marion St",
    "iso:country":"AU",
    "sg:address":"191 Marion St",
    "sg:city":"Leichhardt",
    "sg:classifiers":[
        {
            "category":"Personal",
            "subcategory":"Adult",
            "type":"Services"
        }
    ],
    "sg:phone":"+61 2 9560 4333",
    "sg:postcode":"2040",
    "sg:province":"NSW",
    "sg:tags":[
        "vic",
        "except",
        "state",
        "escort",
        "social",
        "qld"
    ],
    "wof:name":"Studio 191 Of Leichhardt",
    "wof:placetype":"venue"
},
  "geometry": {"coordinates":[151.14828499999999,-33.88406],"type":"Point"}
}