{
  "type": "Feature",
  "properties": {
    "addr:full":"1st Floor 87 The Terrace Ocean Grove VIC 3226",
    "addr:housenumber":"87",
    "addr:postcode":"3226",
    "addr:street":"The Terrace",
    "iso:country":"AU",
    "sg:address":"1st Floor 87 The Terrace",
    "sg:city":"Ocean Grove",
    "sg:classifiers":[
        {
            "category":"Education",
            "subcategory":"Music School",
            "type":"Public Place"
        }
    ],
    "sg:phone":"+61 3 5256 1056",
    "sg:postcode":"3226",
    "sg:province":"VIC",
    "sg:tags":[
        "teacher"
    ],
    "wof:name":"Ocean Grove Music Centre",
    "wof:placetype":"venue"
},
  "geometry": {"coordinates":[144.52380400000001,-38.267723],"type":"Point"}
}