{
  "type": "Feature",
  "properties": {
    "iso:country":"AU",
    "sg:address":"Shop 5, 83- 89 Lytton Rd",
    "sg:city":"East Brisbane",
    "sg:classifiers":[
        {
            "category":"Food & Beverages",
            "subcategory":"Liquor & Beverages",
            "type":"Retail Goods"
        }
    ],
    "sg:phone":"+61 7 3217 4611",
    "sg:postcode":"4169",
    "sg:province":"QLD",
    "sg:tags":[
        "store"
    ],
    "wof:name":"Story Bridge Cellars",
    "wof:placetype":"venue"
},
  "geometry": {"coordinates":[153.045196533,-27.4796199799],"type":"Point"}
}