{
  "type": "Feature",
  "properties": {
    "addr:full":"60 Wilkie St Yeerongpilly QLD 4105",
    "addr:housenumber":"60",
    "addr:postcode":"4105",
    "addr:street":"Wilkie St",
    "iso:country":"AU",
    "sg:address":"60 Wilkie St",
    "sg:city":"Yeerongpilly",
    "sg:classifiers":[
        {
            "category":"Fast Food",
            "type":"Food & Drink"
        }
    ],
    "sg:phone":"+61 7 3848 5111",
    "sg:postcode":"4105",
    "sg:province":"QLD",
    "sg:tags":[
        "away",
        "take"
    ],
    "wof:name":"Railway Snack Bar The",
    "wof:placetype":"venue"
},
  "geometry": {"coordinates":[153.01449585,-27.5249786377],"type":"Point"}
}