{
  "type": "Feature",
  "properties": {
    "iso:country":"AU",
    "sg:address":"410 West Botany St",
    "sg:city":"Rockdale",
    "sg:classifiers":[
        {
            "category":"Retail",
            "subcategory":"Auto Repair",
            "type":"Services"
        }
    ],
    "sg:phone":"+61 2 9597 6078",
    "sg:postcode":"2216",
    "sg:province":"NSW",
    "sg:tags":[
        "repairer",
        "motor",
        "engineer"
    ],
    "wof:name":"Botany Bay Auto Repairs",
    "wof:placetype":"venue"
},
  "geometry": {"coordinates":[151.1465,-33.958408],"type":"Point"}
}