{
  "type": "Feature",
  "properties": {
    "addr:full":"5 Cambridge Ave Narraweena NSW 2099",
    "addr:housenumber":"5",
    "addr:postcode":"2099",
    "addr:street":"Cambridge Ave",
    "iso:country":"AU",
    "sg:address":"5 Cambridge Ave",
    "sg:city":"Narraweena",
    "sg:classifiers":[
        {
            "category":"Organizations",
            "subcategory":"Membership Organization",
            "type":"Services"
        }
    ],
    "sg:phone":"+61 2 9401 4315",
    "sg:postcode":"2099",
    "sg:province":"NSW",
    "sg:tags":[
        "club",
        "car"
    ],
    "wof:name":"Manly Warringgah Sporting Car Club",
    "wof:placetype":"venue"
},
  "geometry": {"coordinates":[151.27793884299999,-33.7449150085],"type":"Point"}
}