{
  "type": "Feature",
  "properties": {
    "addr:full":"158 Martin St Brighton VIC 3186",
    "addr:housenumber":"158",
    "addr:postcode":"3186",
    "addr:street":"Martin St",
    "iso:country":"AU",
    "sg:address":"158 Martin St",
    "sg:city":"Brighton",
    "sg:classifiers":[
        {
            "category":"Building & Trades",
            "subcategory":"Locksmith",
            "type":"Services"
        }
    ],
    "sg:phone":"+61 3 9596 5700",
    "sg:postcode":"3186",
    "sg:province":"VIC",
    "sg:tags":[
        "lock"
    ],
    "wof:name":"F & R Payne & Son Pty Ltd",
    "wof:placetype":"venue"
},
  "geometry": {"coordinates":[145.00486755399999,-37.8976211548],"type":"Point"}
}