{
  "type": "Feature",
  "properties": {
    "addr:full":"61 Woodview Ave Lisarow NSW 2250",
    "addr:housenumber":"61",
    "addr:postcode":"2250",
    "addr:street":"Woodview Ave",
    "iso:country":"AU",
    "sg:address":"61 Woodview Ave",
    "sg:city":"Lisarow",
    "sg:classifiers":[
        {
            "category":"Banks & Credit Unions",
            "subcategory":"Bank",
            "type":"Services"
        }
    ],
    "sg:phone":"+61 2 4362 8600",
    "sg:postcode":"2250",
    "sg:province":"NSW",
    "sg:tags":[
        "broker",
        "mortgage"
    ],
    "wof:name":"Woodview Home Loans & Finance",
    "wof:placetype":"venue"
},
  "geometry": {"coordinates":[151.382614136,-33.3786239624],"type":"Point"}
}