{
  "type": "Feature",
  "properties": {
    "addr:full":"PO Box 1199 Toowoomba QLD 4350",
    "addr:postcode":"4350",
    "iso:country":"AU",
    "sg:address":"PO Box 1199",
    "sg:city":"Toowoomba",
    "sg:classifiers":[
        {
            "category":"Professional",
            "subcategory":"Detective & Security Services",
            "type":"Services"
        }
    ],
    "sg:phone":"+61 1300 790 442",
    "sg:postcode":"4350",
    "sg:province":"QLD",
    "sg:tags":[
        "guard",
        "patrol"
    ],
    "wof:name":"Lombard Security Group",
    "wof:placetype":"venue"
},
  "geometry": {"coordinates":[151.92219499999999,-27.569708],"type":"Point"}
}