{
  "type": "Feature",
  "properties": {
    "iso:country":"AU",
    "sg:address":"30 Church St",
    "sg:city":"Mudgee",
    "sg:classifiers":[
        {
            "category":"Shopping",
            "subcategory":"Clothing, Apparel, & Fashions",
            "type":"Retail Goods"
        }
    ],
    "sg:phone":"+61 2 6372 3694",
    "sg:postcode":"2850",
    "sg:province":"NSW",
    "sg:tags":[
        "lady",
        "wear"
    ],
    "wof:name":"Rockmans Stores Pty Limited",
    "wof:placetype":"venue"
},
  "geometry": {"coordinates":[149.585403,-32.606232],"type":"Point"}
}