{
  "type": "Feature",
  "properties": {
    "iso:country":"AU",
    "sg:address":"281 Boorowa St",
    "sg:city":"Young",
    "sg:classifiers":[
        {
            "category":"Retail",
            "subcategory":"Auto Repair",
            "type":"Services"
        }
    ],
    "sg:phone":"+61 2 6382 1774",
    "sg:postcode":"2594",
    "sg:province":"NSW",
    "sg:tags":[
        "electrical"
    ],
    "wof:name":"Moncrieff Allan",
    "wof:placetype":"venue"
},
  "geometry": {"coordinates":[148.285766602,-34.3097839355],"type":"Point"}
}