{
  "type": "Feature",
  "properties": {
    "iso:country":"AU",
    "sg:address":"181 Maroubra Rd",
    "sg:city":"Maroubra",
    "sg:classifiers":[
        {
            "category":"Banks & Credit Unions",
            "subcategory":"Investment Brokerage",
            "type":"Services"
        }
    ],
    "sg:phone":"+61 2 9344 5333",
    "sg:postcode":"2035",
    "sg:province":"NSW",
    "sg:tags":[
        "management",
        "property"
    ],
    "wof:name":"MG Strata & BMC Management",
    "wof:placetype":"venue"
},
  "geometry": {"coordinates":[151.23776245100001,-33.9415054321],"type":"Point"}
}