{
  "type": "Feature",
  "properties": {
    "addr:full":"Shop 140A, Level 3 Westfield Shoppingtown Belconnen ACT 2617",
    "addr:housenumber":"140a level 3",
    "addr:postcode":"2617",
    "addr:street":"Westfield Shoppingtown",
    "iso:country":"AU",
    "sg:address":"Shop 140A, Level 3",
    "sg:city":"Westfield Shoppingtown Belconnen",
    "sg:classifiers":[
        {
            "category":"Insurance",
            "subcategory":"Health Insurance",
            "type":"Services"
        }
    ],
    "sg:phone":"+61 2 6251 3610",
    "sg:postcode":"2617",
    "sg:province":"ACT",
    "wof:name":"NIB Health Funds Limited",
    "wof:placetype":"venue"
},
  "geometry": {"coordinates":[149.06663513199999,-35.2382316589],"type":"Point"}
}