{
  "type": "Feature",
  "properties": {
    "iso:country":"AU",
    "sg:address":"147 Sydney Rd",
    "sg:city":"Brunswick",
    "sg:classifiers":[
        {
            "category":"Arts & Performance",
            "subcategory":"Art Gallery",
            "type":"Entertainment"
        }
    ],
    "sg:phone":"+61 3 9387 9800",
    "sg:postcode":"3056",
    "sg:province":"VIC",
    "wof:name":"The Art of Mother Love",
    "wof:placetype":"venue"
},
  "geometry": {"coordinates":[144.96078491200001,-37.7739257812],"type":"Point"}
}