{
  "type": "Feature",
  "properties": {
    "iso:country":"AU",
    "sg:address":"195 Mount St",
    "sg:city":"Burnie",
    "sg:classifiers":[
        {
            "category":"Food & Beverages",
            "subcategory":"Liquor & Beverages",
            "type":"Retail Goods"
        }
    ],
    "sg:phone":"+61 3 6432 2636",
    "sg:postcode":"7320",
    "sg:province":"TAS",
    "sg:tags":[
        "store"
    ],
    "wof:name":"BWS Liquor Stores",
    "wof:placetype":"venue"
},
  "geometry": {"coordinates":[145.90121500000001,-41.069946],"type":"Point"}
}