{
  "type": "Feature",
  "properties": {
    "iso:country":"AU",
    "sg:address":"Anzac Ave",
    "sg:city":"Seymour",
    "sg:classifiers":[
        {
            "category":"Autos & Motor Vehicles",
            "subcategory":"Fuel & Gas Station",
            "type":"Retail Goods"
        }
    ],
    "sg:phone":"+61 3 5792 4334",
    "sg:postcode":"3660",
    "sg:province":"VIC",
    "wof:name":"BP Australia Limited",
    "wof:placetype":"venue"
},
  "geometry": {"coordinates":[145.135055542,-37.0252456665],"type":"Point"}
}