{
  "type": "Feature",
  "properties": {
    "addr:full":"2 / 475 Gympie Rd Strathpine QLD 4500",
    "addr:housenumber":"/ 475",
    "addr:postcode":"4500",
    "addr:street":"Gympie Rd",
    "iso:country":"AU",
    "sg:address":"2 / 475 Gympie Rd",
    "sg:city":"Strathpine",
    "sg:classifiers":[
        {
            "category":"Health Services",
            "subcategory":"Health Practitioner",
            "type":"Services"
        }
    ],
    "sg:phone":"+61 404 496 253",
    "sg:postcode":"4500",
    "sg:province":"QLD",
    "sg:tags":[
        "psychologist"
    ],
    "wof:name":"Glyn Spaulding (MAPS)",
    "wof:placetype":"venue"
},
  "geometry": {"coordinates":[152.988845825,-27.3023986816],"type":"Point"}
}