{
  "type": "Feature",
  "properties": {
    "iso:country":"AU",
    "sg:address":"Suite 36, 123 Acland St",
    "sg:city":"St Kilda",
    "sg:classifiers":[
        {
            "category":"Sports & Exercise",
            "subcategory":"Gym",
            "type":"Entertainment"
        }
    ],
    "sg:phone":"+61 403 889 519",
    "sg:postcode":"3182",
    "sg:province":"VIC",
    "sg:tags":[
        "personal",
        "trainer",
        "fitness"
    ],
    "wof:name":"Instant Results",
    "wof:placetype":"venue"
},
  "geometry": {"coordinates":[144.979644775,-37.868637085],"type":"Point"}
}