{
  "type": "Feature",
  "properties": {
    "addr:full":"10 Hinde St Southport QLD 4215",
    "addr:housenumber":"10",
    "addr:postcode":"4215",
    "addr:street":"Hinde St",
    "iso:country":"AU",
    "sg:address":"10 Hinde St",
    "sg:city":"Southport",
    "sg:classifiers":[
        {
            "category":"Autos & Motor Vehicles",
            "subcategory":"Automobile Sales",
            "type":"Retail Goods"
        }
    ],
    "sg:phone":"+61 7 5591 9009",
    "sg:postcode":"4215",
    "sg:province":"QLD",
    "sg:tags":[
        "car",
        "used"
    ],
    "wof:name":"The Auto Centre",
    "wof:placetype":"venue"
},
  "geometry": {"coordinates":[153.38807678200001,-27.9789085388],"type":"Point"}
}