{
  "type": "Feature",
  "properties": {
    "addr:full":"Chilcott St Inglewood QLD 4387",
    "addr:postcode":"4387",
    "addr:street":"Chilcott St",
    "iso:country":"AU",
    "sg:address":"Chilcott St",
    "sg:city":"Inglewood",
    "sg:classifiers":[
        {
            "category":"Education",
            "subcategory":"School",
            "type":"Public Place"
        }
    ],
    "sg:phone":"+61 7 4652 0125",
    "sg:postcode":"4387",
    "sg:province":"QLD",
    "sg:tags":[
        "state",
        "except",
        "nsw"
    ],
    "wof:name":"Inglewood Preschool",
    "wof:placetype":"venue"
},
  "geometry": {"coordinates":[151.07780500000001,-28.416943],"type":"Point"}
}