{
  "type": "Feature",
  "properties": {
    "addr:full":"21 Mitchell Ave Warrandyte VIC 3113",
    "addr:housenumber":"21",
    "addr:postcode":"3113",
    "addr:street":"Mitchell Ave",
    "iso:country":"AU",
    "sg:address":"21 Mitchell Ave",
    "sg:city":"Warrandyte",
    "sg:classifiers":[
        {
            "category":"Food & Beverages",
            "subcategory":"Specialty",
            "type":"Retail Goods"
        }
    ],
    "sg:phone":"+61 3 9844 3130",
    "sg:postcode":"3113",
    "sg:province":"VIC",
    "sg:tags":[
        "product",
        "health"
    ],
    "wof:name":"Australian Lavender Essentials",
    "wof:placetype":"venue"
},
  "geometry": {"coordinates":[145.22381591800001,-37.7388114929],"type":"Point"}
}