{
  "type": "Feature",
  "properties": {
    "iso:country":"AU",
    "sg:address":"U2/ 44 Brighton St",
    "sg:city":"Bundeena",
    "sg:classifiers":[
        {
            "category":"Cafe",
            "type":"Food & Drink"
        }
    ],
    "sg:phone":"+61 2 9527 3731",
    "sg:postcode":"2230",
    "sg:province":"NSW",
    "wof:name":"The Fringe Cafe & Bundeena Visitor Centre",
    "wof:placetype":"venue"
},
  "geometry": {"coordinates":[151.15130615199999,-34.0855484009],"type":"Point"}
}