{
  "type": "Feature",
  "properties": {
    "addr:full":"62 Industrial Ave Toowoomba QLD 4350",
    "addr:housenumber":"62",
    "addr:postcode":"4350",
    "addr:street":"Industrial Ave",
    "iso:country":"AU",
    "sg:address":"62 Industrial Ave",
    "sg:city":"Toowoomba",
    "sg:classifiers":[
        {
            "category":"Communications",
            "subcategory":"Television Station",
            "type":"Services"
        }
    ],
    "sg:phone":"+61 7 4634 5311",
    "sg:postcode":"4350",
    "sg:province":"QLD",
    "sg:tags":[
        "screening",
        "machinery",
        "grading"
    ],
    "wof:name":"Condamine Wellscreens",
    "wof:placetype":"venue"
},
  "geometry": {"coordinates":[151.905914,-27.543427],"type":"Point"}
}