{
  "type": "Feature",
  "properties": {
    "addr:full":"272 Sturt St Townsville QLD 4810",
    "addr:housenumber":"272",
    "addr:postcode":"4810",
    "addr:street":"Sturt St",
    "iso:country":"AU",
    "sg:address":"272 Sturt St",
    "sg:city":"Townsville",
    "sg:classifiers":[
        {
            "category":"Professional",
            "subcategory":"Business Services",
            "type":"Services"
        }
    ],
    "sg:phone":"+61 7 4724 0492",
    "sg:postcode":"4810",
    "sg:province":"QLD",
    "sg:tags":[
        "record",
        "management",
        "storage"
    ],
    "wof:name":"Queensland Micrographics",
    "wof:placetype":"venue"
},
  "geometry": {"coordinates":[146.81346099999999,-19.262243],"type":"Point"}
}