{
  "type": "Feature",
  "properties": {
    "addr:full":"2 Emperor Pl Forestville NSW 2087",
    "addr:housenumber":"2",
    "addr:postcode":"2087",
    "addr:street":"Emperor Pl",
    "iso:country":"AU",
    "sg:address":"2 Emperor Pl",
    "sg:city":"Forestville",
    "sg:classifiers":[
        {
            "category":"Education",
            "subcategory":"School",
            "type":"Public Place"
        }
    ],
    "sg:phone":"+61 2 9975 2491",
    "sg:postcode":"2087",
    "sg:province":"NSW",
    "sg:tags":[
        "supply"
    ],
    "wof:name":"Science Supply Associates Pty Ltd",
    "wof:placetype":"venue"
},
  "geometry": {"coordinates":[151.21995544399999,-33.7578773499],"type":"Point"}
}