{
  "type": "Feature",
  "properties": {
    "iso:country":"AU",
    "sg:address":"34 Spencer St",
    "sg:city":"Bunbury",
    "sg:classifiers":[
        {
            "category":"Autos & Motor Vehicles",
            "subcategory":"Automobile Sales",
            "type":"Retail Goods"
        }
    ],
    "sg:phone":"+61 8 9721 3644",
    "sg:postcode":"6230",
    "sg:province":"WA",
    "sg:tags":[
        "car",
        "new"
    ],
    "wof:name":"Toyota",
    "wof:placetype":"venue"
},
  "geometry": {"coordinates":[115.641548,-33.346935],"type":"Point"}
}