{
  "type": "Feature",
  "properties": {
    "iso:country":"AU",
    "sg:address":"3 Saint Clements St",
    "sg:city":"Blair Athol",
    "sg:classifiers":[
        {
            "category":"Arts & Performance",
            "subcategory":"Music",
            "type":"Entertainment"
        }
    ],
    "sg:phone":"+61 411 864 895",
    "sg:postcode":"5084",
    "sg:province":"SA",
    "sg:tags":[
        "mobile",
        "jockey",
        "disc"
    ],
    "wof:name":"Sound Force DJ's",
    "wof:placetype":"venue"
},
  "geometry": {"coordinates":[138.60064697300001,-34.8664131165],"type":"Point"}
}