{
  "type": "Feature",
  "properties": {
    "addr:full":"Old Creswick Rd Ballarat VIC 3350",
    "addr:postcode":"3350",
    "addr:street":"Old Creswick Rd",
    "iso:country":"AU",
    "sg:address":"Old Creswick Rd",
    "sg:city":"Ballarat",
    "sg:classifiers":[
        {
            "category":"Building & Trades",
            "subcategory":"Construction",
            "type":"Services"
        }
    ],
    "sg:phone":"+61 3 5339 2099",
    "sg:postcode":"3350",
    "sg:province":"VIC",
    "sg:tags":[
        "industrial",
        "commercial",
        "air conditioning"
    ],
    "wof:name":"B & E Trevena & Sons",
    "wof:placetype":"venue"
},
  "geometry": {"coordinates":[143.84930399999999,-37.525589],"type":"Point"}
}