{
  "type": "Feature",
  "properties": {
    "addr:full":"2/ 606 Sherwood Rd Sherwood QLD 4075",
    "addr:housenumber":"/ 606",
    "addr:postcode":"4075",
    "addr:street":"Sherwood Rd",
    "iso:country":"AU",
    "sg:address":"2/ 606 Sherwood Rd",
    "sg:city":"Sherwood",
    "sg:classifiers":[
        {
            "category":"Health Services",
            "subcategory":"Health Practitioner",
            "type":"Services"
        }
    ],
    "sg:phone":"+61 7 3716 0445",
    "sg:postcode":"4075",
    "sg:province":"QLD",
    "sg:tags":[
        "psychologist"
    ],
    "wof:name":"Childpsych Psychology Practice",
    "wof:placetype":"venue"
},
  "geometry": {"coordinates":[152.98126220699999,-27.5320358276],"type":"Point"}
}