{
  "type": "Feature",
  "properties": {
    "addr:full":"7 Lincoln St Minto NSW 2566",
    "addr:housenumber":"7",
    "addr:postcode":"2566",
    "addr:street":"Lincoln St",
    "iso:country":"AU",
    "sg:address":"7 Lincoln St",
    "sg:city":"Minto",
    "sg:classifiers":[
        {
            "category":"Professional",
            "subcategory":"Accounting & Tax Preparation",
            "type":"Services"
        }
    ],
    "sg:phone":"+61 2 9820 1000",
    "sg:postcode":"2566",
    "sg:province":"NSW",
    "sg:tags":[
        "consultant",
        "taxation"
    ],
    "wof:name":"Gage W.A. & Co.",
    "wof:placetype":"venue"
},
  "geometry": {"coordinates":[150.84111023,-34.0265846252],"type":"Point"}
}