{
  "type": "Feature",
  "properties": {
    "iso:country":"AU",
    "sg:address":"Cnr Pacific Hwy and Henry Parry Drv",
    "sg:city":"Gosford North",
    "sg:classifiers":[
        {
            "category":"Travel",
            "subcategory":"Hotels & Motels",
            "type":"Entertainment"
        }
    ],
    "sg:phone":"+61 2 4324 4366",
    "sg:postcode":"2250",
    "sg:province":"NSW",
    "wof:name":"Bermuda Motor Inn",
    "wof:placetype":"venue"
},
  "geometry": {"coordinates":[151.35012817399999,-33.4089775085],"type":"Point"}
}