{
  "type": "Feature",
  "properties": {
    "addr:full":"11 David St Lobethal SA 5241",
    "addr:housenumber":"11",
    "addr:postcode":"5241",
    "addr:street":"David St",
    "iso:country":"AU",
    "sg:address":"11 David St",
    "sg:city":"Lobethal",
    "sg:classifiers":[
        {
            "category":"Government",
            "subcategory":"Post Office",
            "type":"Public Place"
        }
    ],
    "sg:phone":"+61 8 8389 6498",
    "sg:postcode":"5241",
    "sg:province":"SA",
    "sg:tags":[
        "equipment",
        "hole",
        "contractor"
    ],
    "wof:name":"Post Hole Drilling & Fencing Services Pty Ltd",
    "wof:placetype":"venue"
},
  "geometry": {"coordinates":[138.87789917000001,-34.9004554749],"type":"Point"}
}