{
  "type": "Feature",
  "properties": {
    "addr:full":"8/70 Cenniennal Crt Byron Bay NSW 2481",
    "addr:housenumber":"/ 70",
    "addr:postcode":"2481",
    "addr:street":"Cenniennal Crt",
    "iso:country":"AU",
    "sg:address":"8/70 Cenniennal Crt",
    "sg:city":"Byron Bay",
    "sg:classifiers":[
        {
            "category":"Juice Bar",
            "subcategory":"None",
            "type":"Food & Drink"
        }
    ],
    "sg:phone":"+61 2 6680 9433",
    "sg:postcode":"2481",
    "sg:province":"NSW",
    "sg:tags":[
        "merchant",
        "fruit",
        "processor"
    ],
    "wof:name":"Ginger Necktar Drink Co. Pty Ltd",
    "wof:placetype":"venue"
},
  "geometry": {"coordinates":[153.57896423299999,-28.6370677948],"type":"Point"}
}