{
  "type": "Feature",
  "properties": {
    "addr:full":"Level 1/ 369 Centre Rd Bentleigh VIC 3204",
    "addr:housenumber":"/ 369",
    "addr:postcode":"3204",
    "addr:street":"Centre Rd",
    "iso:country":"AU",
    "sg:address":"Level 1/ 369 Centre Rd",
    "sg:city":"Bentleigh",
    "sg:classifiers":[
        {
            "category":"Health Services",
            "subcategory":"Medical Lab",
            "type":"Services"
        }
    ],
    "sg:phone":"+61 3 9557 9259",
    "sg:postcode":"3204",
    "sg:province":"VIC",
    "sg:tags":[
        "laboratory",
        "dental"
    ],
    "wof:name":"Orthex Orthodontics",
    "wof:placetype":"venue"
},
  "geometry": {"coordinates":[145.03706399999999,-37.918098],"type":"Point"}
}