{
  "type": "Feature",
  "properties": {
    "addr:full":"601 High St Penrith NSW 2750",
    "addr:housenumber":"601",
    "addr:postcode":"2750",
    "addr:street":"High St",
    "iso:country":"AU",
    "sg:address":"601 High St",
    "sg:city":"Penrith",
    "sg:classifiers":[
        {
            "category":"Conference Center",
            "type":"Public Place"
        }
    ],
    "sg:phone":"+61 2 4732 7891",
    "sg:postcode":"2750",
    "sg:province":"NSW",
    "sg:tags":[
        "venue",
        "convention"
    ],
    "wof:name":"Penrith City Library",
    "wof:placetype":"venue"
},
  "geometry": {"coordinates":[150.915527344,-33.8951301575],"type":"Point"}
}