{
  "type": "Feature",
  "properties": {
    "addr:full":"Lot 23 Chifley St Metford NSW 2323",
    "addr:postcode":"2323",
    "addr:street":"Chifley St",
    "iso:country":"AU",
    "sg:address":"Lot 23 Chifley St",
    "sg:city":"Metford",
    "sg:classifiers":[
        {
            "category":"Home & Garden",
            "subcategory":"Hardware",
            "type":"Retail Goods"
        }
    ],
    "sg:phone":"+61 2 4933 2878",
    "sg:postcode":"2323",
    "sg:province":"NSW",
    "sg:tags":[
        "plumber",
        "supply"
    ],
    "wof:name":"Tradelink Plumbing Centres",
    "wof:placetype":"venue"
},
  "geometry": {"coordinates":[151.596832275,-32.7603187561],"type":"Point"}
}