{
  "type": "Feature",
  "properties": {
    "addr:full":"13/ 50 Margaret St Sydney NSW 2000",
    "addr:housenumber":"13 / 50",
    "addr:postcode":"2000",
    "addr:street":"Margaret St",
    "iso:country":"AU",
    "sg:address":"13/ 50 Margaret St",
    "sg:city":"Sydney",
    "sg:classifiers":[
        {
            "category":"Banks & Credit Unions",
            "subcategory":"Investment Brokerage",
            "type":"Services"
        }
    ],
    "sg:phone":"+61 2 8234 1800",
    "sg:postcode":"2000",
    "sg:province":"NSW",
    "wof:name":"Becton Property Group",
    "wof:placetype":"venue"
},
  "geometry": {"coordinates":[151.207122803,-33.8651199341],"type":"Point"}
}