{
  "type": "Feature",
  "properties": {
    "iso:country":"AU",
    "sg:address":"372 Norton St",
    "sg:city":"Leichhardt",
    "sg:classifiers":[
        {
            "category":"Building & Trades",
            "subcategory":"Construction",
            "type":"Services"
        }
    ],
    "sg:phone":"+61 2 9572 6166",
    "sg:postcode":"2040",
    "sg:province":"NSW",
    "sg:tags":[
        "home",
        "air conditioning"
    ],
    "wof:name":"Keeley Air Conditioning Pty Ltd",
    "wof:placetype":"venue"
},
  "geometry": {"coordinates":[151.155853,-33.874409],"type":"Point"}
}