{
  "type": "Feature",
  "properties": {
    "addr:full":"1/ 12 Wharf St Forster NSW 2428",
    "addr:housenumber":"/ 12",
    "addr:postcode":"2428",
    "addr:street":"Wharf St",
    "iso:country":"AU",
    "sg:address":"1/ 12 Wharf St",
    "sg:city":"Forster",
    "sg:classifiers":[
        {
            "category":"Health Services",
            "subcategory":"Optometrist",
            "type":"Services"
        }
    ],
    "sg:phone":"+61 2 6554 7817",
    "sg:postcode":"2428",
    "sg:province":"NSW",
    "wof:name":"Eyecare Plus Optometrists",
    "wof:placetype":"venue"
},
  "geometry": {"coordinates":[152.51049800000001,-32.180138],"type":"Point"}
}