{
  "type": "Feature",
  "properties": {
    "addr:full":"33 Higginbotham Rd Gladesville NSW 2111",
    "addr:housenumber":"33",
    "addr:postcode":"2111",
    "addr:street":"Higginbotham Rd",
    "iso:country":"AU",
    "sg:address":"33 Higginbotham Rd",
    "sg:city":"Gladesville",
    "sg:classifiers":[
        {
            "category":"Shopping",
            "subcategory":"Mobile Phones",
            "type":"Retail Goods"
        }
    ],
    "sg:phone":"+61 2 9807 1444",
    "sg:postcode":"2111",
    "sg:province":"NSW",
    "sg:tags":[
        "battery",
        "equipment",
        "charging"
    ],
    "wof:name":"Avtronics (Australia) Pty Ltd",
    "wof:placetype":"venue"
},
  "geometry": {"coordinates":[151.12399292000001,-33.8167533875],"type":"Point"}
}