{
  "type": "Feature",
  "properties": {
    "iso:country":"AU",
    "sg:address":"18 Alfred Rd",
    "sg:city":"Chipping Norton",
    "sg:classifiers":[
        {
            "category":"Shopping",
            "subcategory":"Optical Goods",
            "type":"Retail Goods"
        }
    ],
    "sg:phone":"+61 2 9755 1155",
    "sg:postcode":"2170",
    "sg:province":"NSW",
    "sg:tags":[
        "supply"
    ],
    "wof:name":"Visionlab Pty Ltd",
    "wof:placetype":"venue"
},
  "geometry": {"coordinates":[150.96629333499999,-33.9231948853],"type":"Point"}
}