{
  "type": "Feature",
  "properties": {
    "addr:full":"1032 Doncaster Rd Doncaster East VIC 3109",
    "addr:housenumber":"1032",
    "addr:postcode":"3109",
    "addr:street":"Doncaster Rd",
    "iso:country":"AU",
    "sg:address":"1032 Doncaster Rd",
    "sg:city":"Doncaster East",
    "sg:classifiers":[
        {
            "category":"Health Services",
            "subcategory":"Health Practitioner",
            "type":"Services"
        }
    ],
    "sg:phone":"+61 3 9841 0155",
    "sg:postcode":"3109",
    "sg:province":"VIC",
    "sg:tags":[
        "psychologist"
    ],
    "wof:name":"Goergen Ann Ryan",
    "wof:placetype":"venue"
},
  "geometry": {"coordinates":[145.162597656,-37.7894134521],"type":"Point"}
}