{
  "type": "Feature",
  "properties": {
    "addr:full":"Montague Rd Ingle Farm SA 5098",
    "addr:postcode":"5098",
    "addr:street":"Montague Rd",
    "iso:country":"AU",
    "sg:address":"Montague Rd",
    "sg:city":"Ingle Farm",
    "sg:classifiers":[
        {
            "category":"Wholesale",
            "subcategory":"Medical Equipment & Supplies",
            "type":"Manufacturing & Wholesale Goods"
        }
    ],
    "sg:phone":"+61 8 8264 5893",
    "sg:postcode":"5098",
    "sg:province":"SA",
    "sg:tags":[
        "aids",
        "hearing"
    ],
    "wof:name":"Hearing Life",
    "wof:placetype":"venue"
},
  "geometry": {"coordinates":[138.650756836,-34.828704834],"type":"Point"}
}