{
  "type": "Feature",
  "properties": {
    "addr:full":"11 Courtney Ave Cranbourne North VIC 3977",
    "addr:housenumber":"11",
    "addr:postcode":"3977",
    "addr:street":"Courtney Ave",
    "iso:country":"AU",
    "sg:address":"11 Courtney Ave",
    "sg:city":"Cranbourne North",
    "sg:classifiers":[
        {
            "category":"Professional",
            "type":"Services"
        }
    ],
    "sg:phone":"+61 405 780 196",
    "sg:postcode":"3977",
    "sg:province":"VIC",
    "sg:tags":[
        "shop",
        "fitting"
    ],
    "wof:name":"C.S.M Pty Ltd",
    "wof:placetype":"venue"
},
  "geometry": {"coordinates":[145.274993897,-38.0773735046],"type":"Point"}
}