{
  "type": "Feature",
  "properties": {
    "iso:country":"AU",
    "sg:address":"31 Logan Reserve Rd",
    "sg:city":"Waterford West",
    "sg:classifiers":[
        {
            "category":"Professional",
            "subcategory":"Employment Agencies",
            "type":"Services"
        }
    ],
    "sg:phone":"+61 7 3299 7821",
    "sg:postcode":"4133",
    "sg:province":"QLD",
    "sg:tags":[
        "entertainer",
        "agent"
    ],
    "wof:name":"Top Class Entertainment",
    "wof:placetype":"venue"
},
  "geometry": {"coordinates":[153.120697022,-27.6843090057],"type":"Point"}
}