{
  "type": "Feature",
  "properties": {
    "addr:full":"23 Colong Pl Wagga Wagga NSW 2650",
    "addr:housenumber":"23",
    "addr:postcode":"2650",
    "addr:street":"Colong Pl",
    "iso:country":"AU",
    "sg:address":"23 Colong Pl",
    "sg:city":"Wagga Wagga",
    "sg:classifiers":[
        {
            "category":"Building & Trades",
            "subcategory":"Construction",
            "type":"Services"
        }
    ],
    "sg:phone":"+61 2 6921 1406",
    "sg:postcode":"2650",
    "sg:province":"NSW",
    "sg:tags":[
        "contractor"
    ],
    "wof:name":"Harvey Cec",
    "wof:placetype":"venue"
},
  "geometry": {"coordinates":[147.37905883799999,-35.1299476624],"type":"Point"}
}