{
  "type": "Feature",
  "properties": {
    "addr:full":"3 Lyons Crt Mentone VIC 3194",
    "addr:housenumber":"3",
    "addr:postcode":"3194",
    "addr:street":"Lyons Crt",
    "iso:country":"AU",
    "sg:address":"3 Lyons Crt",
    "sg:city":"Mentone",
    "sg:classifiers":[
        {
            "category":"Social Services",
            "subcategory":"Job Training",
            "type":"Services"
        }
    ],
    "sg:phone":"+61 3 9584 4343",
    "sg:postcode":"3194",
    "sg:province":"VIC",
    "sg:tags":[
        "interpreter"
    ],
    "wof:name":"Japanese Interpreting & Tour Guiding Services",
    "wof:placetype":"venue"
},
  "geometry": {"coordinates":[145.077758789,-37.9811859131],"type":"Point"}
}