{
  "type": "Feature",
  "properties": {
    "addr:full":"Shp 114 Charlestown Shopping Cntr Charlestown NSW 2290",
    "addr:housenumber":"114",
    "addr:postcode":"2290",
    "addr:street":"Charlestown Shopping Cntr",
    "iso:country":"AU",
    "sg:address":"Shp 114",
    "sg:city":"Charlestown Shopping Cntr Charlestown",
    "sg:classifiers":[
        {
            "category":"Shopping",
            "subcategory":"Clothing, Apparel, & Fashions",
            "type":"Retail Goods"
        }
    ],
    "sg:phone":"+61 2 4943 3277",
    "sg:postcode":"2290",
    "sg:province":"NSW",
    "sg:tags":[
        "jean"
    ],
    "wof:name":"Just Jeans Pty Ltd",
    "wof:placetype":"venue"
},
  "geometry": {"coordinates":[151.68569946299999,-32.9541778564],"type":"Point"}
}