{
  "type": "Feature",
  "properties": {
    "iso:country":"AU",
    "sg:address":"4 Marlin St",
    "sg:city":"Boondall",
    "sg:classifiers":[
        {
            "category":"Utilities",
            "subcategory":"Electric",
            "type":"Services"
        }
    ],
    "sg:phone":"+61 7 3265 7081",
    "sg:postcode":"4034",
    "sg:province":"QLD",
    "sg:tags":[
        "electrical",
        "contractor"
    ],
    "wof:name":"Meikle A",
    "wof:placetype":"venue"
},
  "geometry": {"coordinates":[153.05509900000001,-27.348261],"type":"Point"}
}