{
  "type": "Feature",
  "properties": {
    "iso:country":"AU",
    "sg:address":"10 Carrington Rd",
    "sg:city":"Marrickville",
    "sg:classifiers":[
        {
            "category":"Shopping",
            "subcategory":"Clothing, Apparel, & Fashions",
            "type":"Retail Goods"
        }
    ],
    "sg:phone":"+61 1300 888 739",
    "sg:postcode":"2204",
    "sg:province":"NSW",
    "sg:tags":[
        "lingerie",
        "hosiery",
        "sleepwear"
    ],
    "wof:name":"Adult Sex Toys",
    "wof:placetype":"venue"
},
  "geometry": {"coordinates":[151.156906,-33.917988],"type":"Point"}
}