{
  "type": "Feature",
  "properties": {
    "addr:full":"9 Sarah St Mascot NSW 2020",
    "addr:housenumber":"9",
    "addr:postcode":"2020",
    "addr:street":"Sarah St",
    "iso:country":"AU",
    "sg:address":"9 Sarah St",
    "sg:city":"Mascot",
    "sg:classifiers":[
        {
            "category":"Banks & Credit Unions",
            "subcategory":"Bureau De Change",
            "type":"Services"
        }
    ],
    "sg:phone":"+61 2 8338 9888",
    "sg:postcode":"2020",
    "sg:province":"NSW",
    "sg:tags":[
        "control",
        "consultant",
        "vibration"
    ],
    "wof:name":"Acoustic Logic Consultancy",
    "wof:placetype":"venue"
},
  "geometry": {"coordinates":[151.18585205100001,-33.9300346375],"type":"Point"}
}