{
  "type": "Feature",
  "properties": {
    "addr:full":"Cairns Private Hospital 144 Lake St Cairns QLD 4870",
    "addr:housenumber":"144",
    "addr:postcode":"4870",
    "addr:street":"Lake St",
    "iso:country":"AU",
    "sg:address":"Cairns Private Hospital 144 Lake St",
    "sg:city":"Cairns",
    "sg:classifiers":[
        {
            "category":"Health Services",
            "subcategory":"Doctor",
            "type":"Services"
        }
    ],
    "sg:phone":"+61 7 4052 5230",
    "sg:postcode":"4870",
    "sg:province":"QLD",
    "sg:tags":[
        "medical",
        "practitioner"
    ],
    "wof:name":"Ling J S",
    "wof:placetype":"venue"
},
  "geometry": {"coordinates":[145.771682739,-16.9173984528],"type":"Point"}
}