{
  "type": "Feature",
  "properties": {
    "iso:country":"AU",
    "sg:address":"PO Box 230",
    "sg:city":"Marengo",
    "sg:classifiers":[
        {
            "category":"Building & Trades",
            "subcategory":"Cleaning & Sanitation",
            "type":"Services"
        }
    ],
    "sg:phone":"+61 439 378 616",
    "sg:postcode":"3233",
    "sg:province":"VIC",
    "sg:tags":[
        "window"
    ],
    "wof:name":"Crystal Windows",
    "wof:placetype":"venue"
},
  "geometry": {"coordinates":[143.66261291500001,-38.7765884399],"type":"Point"}
}