{
  "type": "Feature",
  "properties": {
    "addr:full":"Greenshields Rd Drouin VIC 3818",
    "addr:postcode":"3818",
    "addr:street":"Greenshields Rd",
    "iso:country":"AU",
    "sg:address":"Greenshields Rd",
    "sg:city":"Drouin",
    "sg:classifiers":[
        {
            "category":"Farming",
            "subcategory":"Farm",
            "type":"Manufacturing & Wholesale Goods"
        }
    ],
    "sg:phone":"+61 3 5625 1141",
    "sg:postcode":"3818",
    "sg:province":"VIC",
    "sg:tags":[
        "farmer"
    ],
    "wof:name":"Wilms L & M",
    "wof:placetype":"venue"
},
  "geometry": {"coordinates":[145.868729,-38.1698],"type":"Point"}
}