{
  "type": "Feature",
  "properties": {
    "iso:country":"AU",
    "sg:address":"195 Mill Rd",
    "sg:city":"Lara",
    "sg:classifiers":[
        {
            "category":"Farming",
            "subcategory":"Nursery",
            "type":"Manufacturing & Wholesale Goods"
        }
    ],
    "sg:phone":"+61 3 5282 3670",
    "sg:postcode":"3212",
    "sg:province":"VIC",
    "wof:name":"Dacol Wholesale Nursery",
    "wof:placetype":"venue"
},
  "geometry": {"coordinates":[144.434692383,-38.0054397583],"type":"Point"}
}