{
  "type": "Feature",
  "properties": {
    "iso:country":"AU",
    "sg:address":"47 Gregory Rd",
    "sg:city":"Leppington",
    "sg:classifiers":[
        {
            "category":"Professional",
            "subcategory":"Art Services",
            "type":"Services"
        }
    ],
    "sg:phone":"+61 2 9606 4019",
    "sg:postcode":"2171",
    "sg:province":"NSW",
    "sg:tags":[
        "decorator",
        "painter"
    ],
    "wof:name":"Granada Painting Services Pty Ltd",
    "wof:placetype":"venue"
},
  "geometry": {"coordinates":[150.76187133799999,-33.9607772827],"type":"Point"}
}