{
  "type": "Feature",
  "properties": {
    "addr:full":"Office8/ 90 John St Cabramatta NSW 2166",
    "addr:housenumber":"90",
    "addr:postcode":"2166",
    "addr:street":"John St",
    "iso:country":"AU",
    "sg:address":"Office8/ 90 John St",
    "sg:city":"Cabramatta",
    "sg:classifiers":[
        {
            "category":"Professional",
            "subcategory":"Accounting & Tax Preparation",
            "type":"Services"
        }
    ],
    "sg:phone":"+61 2 9727 9898",
    "sg:postcode":"2166",
    "sg:province":"NSW",
    "sg:tags":[
        "consultant",
        "taxation"
    ],
    "wof:name":"Total Finance Corporation",
    "wof:placetype":"venue"
},
  "geometry": {"coordinates":[150.934127808,-33.8949432373],"type":"Point"}
}