{
  "type": "Feature",
  "properties": {
    "addr:full":"19 Kent St Busselton WA 6280",
    "addr:housenumber":"19",
    "addr:postcode":"6280",
    "addr:street":"Kent St",
    "iso:country":"AU",
    "sg:address":"19 Kent St",
    "sg:city":"Busselton",
    "sg:classifiers":[
        {
            "category":"Social Services",
            "subcategory":"Child Care",
            "type":"Services"
        }
    ],
    "sg:phone":"+61 8 9752 1935",
    "sg:postcode":"6280",
    "sg:province":"WA",
    "sg:tags":[
        "support",
        "health"
    ],
    "wof:name":"Child Health Services",
    "wof:placetype":"venue"
},
  "geometry": {"coordinates":[115.339118958,-33.6507263184],"type":"Point"}
}