{
  "type": "Feature",
  "properties": {
    "iso:country":"AU",
    "sg:address":"5 John St",
    "sg:city":"Warners Bay",
    "sg:classifiers":[
        {
            "category":"Food & Beverages",
            "subcategory":"Liquor & Beverages",
            "type":"Retail Goods"
        }
    ],
    "sg:phone":"+61 2 4947 1126",
    "sg:postcode":"2282",
    "sg:province":"NSW",
    "sg:tags":[
        "store"
    ],
    "wof:name":"Warners Bay Hotel Bottlemart",
    "wof:placetype":"venue"
},
  "geometry": {"coordinates":[151.64533996599999,-32.9739189148],"type":"Point"}
}