{
  "type": "Feature",
  "properties": {
    "addr:full":"18 Jarrah St Wodonga VIC 3690",
    "addr:housenumber":"18",
    "addr:postcode":"3690",
    "addr:street":"Jarrah St",
    "iso:country":"AU",
    "sg:address":"18 Jarrah St",
    "sg:city":"Wodonga",
    "sg:classifiers":[
        {
            "category":"Personal",
            "subcategory":"Beauty Salon",
            "type":"Services"
        }
    ],
    "sg:phone":"+61 2 6024 1212",
    "sg:postcode":"3690",
    "sg:province":"VIC",
    "sg:tags":[
        "hairdresser"
    ],
    "wof:name":"Beauty Bowl The",
    "wof:placetype":"venue"
},
  "geometry": {"coordinates":[146.882080078,-36.1390075684],"type":"Point"}
}