{
  "type": "Feature",
  "properties": {
    "iso:country":"AU",
    "sg:address":"147 High Rd",
    "sg:city":"Willetton",
    "sg:classifiers":[
        {
            "category":"Personal",
            "subcategory":"Skin Care",
            "type":"Services"
        }
    ],
    "sg:phone":"+61 8 9457 0400",
    "sg:postcode":"6155",
    "sg:province":"WA",
    "sg:tags":[
        "hair",
        "product"
    ],
    "wof:name":"Lush Hair",
    "wof:placetype":"venue"
},
  "geometry": {"coordinates":[115.88102000000001,-32.038834],"type":"Point"}
}