{
  "type": "Feature",
  "properties": {
    "addr:full":"PO Box 8104 Burwood Heights VIC 3151",
    "addr:postcode":"3151",
    "iso:country":"AU",
    "sg:address":"PO Box 8104",
    "sg:city":"Burwood Heights",
    "sg:classifiers":[
        {
            "category":"Utilities",
            "subcategory":"Electric",
            "type":"Services"
        }
    ],
    "sg:phone":"+61 418 992 555",
    "sg:postcode":"3151",
    "sg:province":"VIC",
    "sg:tags":[
        "electrical",
        "contractor"
    ],
    "wof:name":"Hi-Power Electrics",
    "wof:placetype":"venue"
},
  "geometry": {"coordinates":[145.133102417,-37.8542900085],"type":"Point"}
}