{
  "type": "Feature",
  "properties": {
    "addr:full":"65b Wilgarning St Stafford Heights QLD 4053",
    "addr:housenumber":"65b",
    "addr:postcode":"4053",
    "addr:street":"Wilgarning St",
    "iso:country":"AU",
    "sg:address":"65b Wilgarning St",
    "sg:city":"Stafford Heights",
    "sg:classifiers":[
        {
            "category":"Professional",
            "subcategory":"Employment Agencies",
            "type":"Services"
        }
    ],
    "sg:phone":"+61 7 3359 5453",
    "sg:postcode":"4053",
    "sg:province":"QLD",
    "sg:tags":[
        "occupational",
        "therapist"
    ],
    "wof:name":"Kellie Clayton Occupational Therapists",
    "wof:placetype":"venue"
},
  "geometry": {"coordinates":[153.015167236,-27.4017791748],"type":"Point"}
}