{
  "type": "Feature",
  "properties": {
    "addr:full":"31 Keats St Byron Bay NSW 2481",
    "addr:housenumber":"31",
    "addr:postcode":"2481",
    "addr:street":"Keats St",
    "iso:country":"AU",
    "sg:address":"31 Keats St",
    "sg:city":"Byron Bay",
    "sg:classifiers":[
        {
            "category":"Real Estate",
            "subcategory":"Architect",
            "type":"Services"
        }
    ],
    "sg:phone":"+61 2 6685 5199",
    "sg:postcode":"2481",
    "sg:province":"NSW",
    "sg:tags":[
        "building",
        "designer"
    ],
    "wof:name":"David Challis & Associates",
    "wof:placetype":"venue"
},
  "geometry": {"coordinates":[153.578857422,-28.6370677948],"type":"Point"}
}