{
  "type": "Feature",
  "properties": {
    "addr:full":"First Ave Home Hill QLD 4806",
    "addr:postcode":"4806",
    "addr:street":"First Ave;Hill",
    "iso:country":"AU",
    "sg:address":"First Ave",
    "sg:city":"Home Hill",
    "sg:classifiers":[
        {
            "category":"Home & Garden",
            "subcategory":"Garden Supply",
            "type":"Retail Goods"
        }
    ],
    "sg:phone":"+61 7 4782 1555",
    "sg:postcode":"4806",
    "sg:province":"QLD",
    "sg:tags":[
        "fertilizer"
    ],
    "wof:name":"Burdekin Agricultural and Application Services",
    "wof:placetype":"venue"
},
  "geometry": {"coordinates":[147.41166687,-19.670923233],"type":"Point"}
}