{
  "type": "Feature",
  "properties": {
    "addr:full":"14 Patullos Rd Lara VIC 3212",
    "addr:housenumber":"14",
    "addr:postcode":"3212",
    "addr:street":"Patullos Rd",
    "iso:country":"AU",
    "sg:address":"14 Patullos Rd",
    "sg:city":"Lara",
    "sg:classifiers":[
        {
            "category":"Personal",
            "subcategory":"Beauty Salon",
            "type":"Services"
        }
    ],
    "sg:phone":"+61 3 5282 4240",
    "sg:postcode":"3212",
    "sg:province":"VIC",
    "sg:tags":[
        "hairdresser"
    ],
    "wof:name":"Acorns Hair & Beauty",
    "wof:placetype":"venue"
},
  "geometry": {"coordinates":[144.39581298799999,-38.0227775574],"type":"Point"}
}