{
  "type": "Feature",
  "properties": {
    "addr:full":"19 Lisa Pl Coolaroo VIC 3048",
    "addr:housenumber":"19",
    "addr:postcode":"3048",
    "addr:street":"Lisa Pl",
    "iso:country":"AU",
    "sg:address":"19 Lisa Pl",
    "sg:city":"Coolaroo",
    "sg:classifiers":[
        {
            "category":"Home & Garden",
            "subcategory":"Furniture",
            "type":"Retail Goods"
        }
    ],
    "sg:phone":"+61 3 9302 4454",
    "sg:postcode":"3048",
    "sg:province":"VIC",
    "sg:tags":[
        "outdoor"
    ],
    "wof:name":"Turendav Australia Pty Ltd",
    "wof:placetype":"venue"
},
  "geometry": {"coordinates":[144.94094799999999,-37.655663],"type":"Point"}
}