{
  "type": "Feature",
  "properties": {
    "iso:country":"AU",
    "sg:address":"737 Military Rd",
    "sg:city":"Mosman",
    "sg:classifiers":[
        {
            "category":"Shopping",
            "subcategory":"Clothing, Apparel, & Fashions",
            "type":"Retail Goods"
        }
    ],
    "sg:phone":"+61 2 9960 8784",
    "sg:postcode":"2088",
    "sg:province":"NSW",
    "sg:tags":[
        "lady",
        "wear"
    ],
    "wof:name":"Eco -D",
    "wof:placetype":"venue"
},
  "geometry": {"coordinates":[151.243896484,-33.8287086487],"type":"Point"}
}