{
  "type": "Feature",
  "properties": {
    "addr:full":"2 Dover Pl Melton West VIC 3337",
    "addr:housenumber":"2",
    "addr:postcode":"3337",
    "addr:street":"Dover Pl",
    "iso:country":"AU",
    "sg:address":"2 Dover Pl",
    "sg:city":"Melton West",
    "sg:classifiers":[
        {
            "category":"Arena",
            "subcategory":"Sports Club",
            "type":"Entertainment"
        }
    ],
    "sg:phone":"+61 3 9747 3511",
    "sg:postcode":"3337",
    "sg:province":"VIC",
    "sg:tags":[
        "organisation",
        "sporting"
    ],
    "wof:name":"Downunder Sports Management",
    "wof:placetype":"venue"
},
  "geometry": {"coordinates":[144.567825,-37.674664],"type":"Point"}
}