{
  "type": "Feature",
  "properties": {
    "addr:full":"Unit 5 22 Gibberd Rd Balcatta WA 6021",
    "addr:housenumber":"22",
    "addr:postcode":"6021",
    "addr:street":"Gibberd Rd",
    "iso:country":"AU",
    "sg:address":"Unit 5 22 Gibberd Rd",
    "sg:city":"Balcatta",
    "sg:classifiers":[
        {
            "category":"Building & Trades",
            "subcategory":"Construction",
            "type":"Services"
        }
    ],
    "sg:phone":"+61 8 9240 7400",
    "sg:postcode":"6021",
    "sg:province":"WA",
    "sg:tags":[
        "industrial",
        "commercial",
        "air conditioning"
    ],
    "wof:name":"West Australia Mechanical Services Pty Ltd",
    "wof:placetype":"venue"
},
  "geometry": {"coordinates":[115.812538147,-31.8647708893],"type":"Point"}
}