{
  "type": "Feature",
  "properties": {
    "iso:country":"AU",
    "sg:address":"8 Angelina Ave",
    "sg:city":"Glenella",
    "sg:classifiers":[
        {
            "category":"Building & Trades",
            "subcategory":"Construction",
            "type":"Services"
        }
    ],
    "sg:phone":"+61 412 776 692",
    "sg:postcode":"4740",
    "sg:province":"QLD",
    "sg:tags":[
        "contractor"
    ],
    "wof:name":"Moohin T & J H Bricklaying Pty Ltd",
    "wof:placetype":"venue"
},
  "geometry": {"coordinates":[149.154312,-21.130884],"type":"Point"}
}