{
  "type": "Feature",
  "properties": {
    "addr:full":"Cnr Laidlaw Drv & Sutton St Delacombe VIC 3356",
    "addr:postcode":"3356",
    "addr:street":"Cnr Laidlaw Drv & Sutton St",
    "iso:country":"AU",
    "sg:address":"Cnr Laidlaw Drv & Sutton St",
    "sg:city":"Delacombe",
    "sg:classifiers":[
        {
            "category":"Retail",
            "subcategory":"Auto Repair",
            "type":"Services"
        }
    ],
    "sg:phone":"+61 3 5336 1514",
    "sg:postcode":"3356",
    "sg:province":"VIC",
    "sg:tags":[
        "repairer",
        "motor",
        "engineer"
    ],
    "wof:name":"Quick's Automotive & LPG Services",
    "wof:placetype":"venue"
},
  "geometry": {"coordinates":[143.82879600000001,-37.572372],"type":"Point"}
}