{
  "type": "Feature",
  "properties": {
    "iso:country":"AU",
    "sg:address":"3 Harper Ave",
    "sg:city":"Beechworth",
    "sg:classifiers":[
        {
            "category":"Wholesale",
            "subcategory":"Farm Supplies",
            "type":"Manufacturing & Wholesale Goods"
        }
    ],
    "sg:phone":"+61 3 5728 1613",
    "sg:postcode":"3747",
    "sg:province":"VIC",
    "sg:tags":[
        "equipment"
    ],
    "wof:name":"Beechworths Plumbing Plus Rural Supplies",
    "wof:placetype":"venue"
},
  "geometry": {"coordinates":[146.68705700000001,-36.363941],"type":"Point"}
}