{
  "type": "Feature",
  "properties": {
    "iso:country":"AU",
    "sg:address":"586 Glenferrie Rd",
    "sg:city":"Hawthorn",
    "sg:classifiers":[
        {
            "category":"Education",
            "subcategory":"Kindergarten",
            "type":"Public Place"
        }
    ],
    "sg:phone":"+61 3 9819 2326",
    "sg:postcode":"3122",
    "sg:province":"VIC",
    "sg:tags":[
        "pre-schools"
    ],
    "wof:name":"Glenferrie Early Childhood Centre",
    "wof:placetype":"venue"
},
  "geometry": {"coordinates":[145.03504943900001,-37.8251571655],"type":"Point"}
}