{
  "type": "Feature",
  "properties": {
    "addr:full":"22 Catalina Rd Palmerston NT 0830",
    "addr:housenumber":"22",
    "addr:postcode":"nt 0830",
    "addr:street":"Catalina Rd",
    "iso:country":"AU",
    "sg:address":"22 Catalina Rd",
    "sg:city":"Palmerston",
    "sg:classifiers":[
        {
            "category":"Real Estate",
            "subcategory":"Real Estate Operator",
            "type":"Services"
        }
    ],
    "sg:phone":"+61 8 8932 7878",
    "sg:postcode":"0830",
    "sg:province":"NT",
    "sg:tags":[
        "concrete",
        "pumping"
    ],
    "wof:name":"Concrete Pumpers & Sprayers N.T.",
    "wof:placetype":"venue"
},
  "geometry": {"coordinates":[130.961884,-12.502508],"type":"Point"}
}