{
  "type": "Feature",
  "properties": {
    "iso:country":"AU",
    "sg:address":"Shop 6 303 Shute Harbour Rd",
    "sg:city":"Airlie Beach",
    "sg:classifiers":[
        {
            "category":"Organizations",
            "subcategory":"Labor Organization",
            "type":"Services"
        }
    ],
    "sg:phone":"+61 7 4946 6335",
    "sg:postcode":"4802",
    "sg:province":"QLD",
    "sg:tags":[
        "union"
    ],
    "wof:name":"Australian Workers&#039; Union",
    "wof:placetype":"venue"
},
  "geometry": {"coordinates":[148.72108459500001,-20.2697238922],"type":"Point"}
}