{
  "type": "Feature",
  "properties": {
    "iso:country":"AU",
    "sg:address":"21 Lyons St North",
    "sg:city":"Ballarat",
    "sg:classifiers":[
        {
            "category":"Personal",
            "type":"Services"
        }
    ],
    "sg:phone":"+61 3 5333 4916",
    "sg:postcode":"3353",
    "sg:province":"VIC",
    "sg:tags":[
        "career",
        "counselling"
    ],
    "wof:name":"Murphy Margot MAPS",
    "wof:placetype":"venue"
},
  "geometry": {"coordinates":[143.85197400000001,-37.559826],"type":"Point"}
}