{
  "type": "Feature",
  "properties": {
    "addr:full":"14 England St Dandenong VIC 3175",
    "addr:housenumber":"14",
    "addr:postcode":"3175",
    "addr:street":"England St",
    "iso:country":"AU",
    "sg:address":"14 England St",
    "sg:city":"Dandenong",
    "sg:classifiers":[
        {
            "category":"Utilities",
            "subcategory":"Natural Gas",
            "type":"Services"
        }
    ],
    "sg:phone":"+61 3 9706 8844",
    "sg:postcode":"3175",
    "sg:province":"VIC",
    "sg:tags":[
        "hose",
        "reel",
        "cable"
    ],
    "wof:name":"Conductix Insul-8",
    "wof:placetype":"venue"
},
  "geometry": {"coordinates":[145.219314575,-38.0298080444],"type":"Point"}
}