{
  "type": "Feature",
  "properties": {
    "iso:country":"AU",
    "sg:address":"32 Lisgar St",
    "sg:city":"Virginia",
    "sg:classifiers":[
        {
            "category":"Wholesale",
            "subcategory":"Medical Equipment & Supplies",
            "type":"Manufacturing & Wholesale Goods"
        }
    ],
    "sg:phone":"+61 7 3256 3388",
    "sg:postcode":"4014",
    "sg:province":"QLD",
    "sg:tags":[
        "aid",
        "care",
        "health",
        "home"
    ],
    "wof:name":"Lifecare Furniture Pty Ltd",
    "wof:placetype":"venue"
},
  "geometry": {"coordinates":[153.05706787099999,-27.3717651367],"type":"Point"}
}