{
  "type": "Feature",
  "properties": {
    "addr:full":"4/ 17 Orion St Lismore NSW 2480",
    "addr:housenumber":"/ 17",
    "addr:postcode":"2480",
    "addr:street":"Orion St",
    "iso:country":"AU",
    "sg:address":"4/ 17 Orion St",
    "sg:city":"Lismore",
    "sg:classifiers":[
        {
            "category":"Health Services",
            "subcategory":"Dentist",
            "type":"Services"
        }
    ],
    "sg:phone":"+61 2 6621 8250",
    "sg:postcode":"2480",
    "sg:province":"NSW",
    "wof:name":"Standish Paul & Geard Frederick J",
    "wof:placetype":"venue"
},
  "geometry": {"coordinates":[153.28202819800001,-28.8044528961],"type":"Point"}
}