{
  "type": "Feature",
  "properties": {
    "addr:full":"110 Church St Parramatta NSW 2150",
    "addr:housenumber":"110",
    "addr:postcode":"2150",
    "addr:street":"Church St",
    "iso:country":"AU",
    "sg:address":"110 Church St",
    "sg:city":"Parramatta",
    "sg:classifiers":[
        {
            "category":"Food & Beverages",
            "subcategory":"Specialty",
            "type":"Retail Goods"
        }
    ],
    "sg:phone":"+61 2 9687 1205",
    "sg:postcode":"2150",
    "sg:province":"NSW",
    "sg:tags":[
        "delicacy"
    ],
    "wof:name":"Sing Kee Asian Grocery Store",
    "wof:placetype":"venue"
},
  "geometry": {"coordinates":[151.097930908,-33.8215408325],"type":"Point"}
}