{
  "type": "Feature",
  "properties": {
    "addr:full":"27 Ann St Salisbury SA 5108",
    "addr:housenumber":"27",
    "addr:postcode":"5108",
    "addr:street":"Ann St",
    "iso:country":"AU",
    "sg:address":"27 Ann St",
    "sg:city":"Salisbury",
    "sg:classifiers":[
        {
            "category":"Social Services",
            "subcategory":"Child Care",
            "type":"Services"
        }
    ],
    "sg:phone":"+61 8 8281 4148",
    "sg:postcode":"5108",
    "sg:province":"SA",
    "wof:name":"Oasis Child Care Centre Inc",
    "wof:placetype":"venue"
},
  "geometry": {"coordinates":[138.64825439399999,-34.7627792358],"type":"Point"}
}