{
  "type": "Feature",
  "properties": {
    "addr:full":"Level 1, 559 Military Rd Mosman NSW 2088",
    "addr:housenumber":"559",
    "addr:postcode":"2088",
    "addr:street":"Military Rd",
    "iso:country":"AU",
    "sg:address":"Level 1, 559 Military Rd",
    "sg:city":"Mosman",
    "sg:classifiers":[
        {
            "category":"Professional",
            "subcategory":"Computer Services",
            "type":"Services"
        }
    ],
    "sg:phone":"+61 2 9960 5005",
    "sg:postcode":"2088",
    "sg:province":"NSW",
    "sg:tags":[
        "repairs",
        "upgrade",
        "equipment"
    ],
    "wof:name":"STC System Express",
    "wof:placetype":"venue"
},
  "geometry": {"coordinates":[151.24090576200001,-33.8246459961],"type":"Point"}
}