{
  "type": "Feature",
  "properties": {
    "addr:full":"5 Wattletree Rd Armadale VIC 3143",
    "addr:housenumber":"5",
    "addr:postcode":"3143",
    "addr:street":"Wattletree Rd",
    "iso:country":"AU",
    "sg:address":"5 Wattletree Rd",
    "sg:city":"Armadale",
    "sg:classifiers":[
        {
            "category":"Travel",
            "subcategory":"Hostel",
            "type":"Entertainment"
        }
    ],
    "sg:phone":"+61 3 9509 9804",
    "sg:postcode":"3143",
    "sg:province":"VIC",
    "sg:tags":[
        "home"
    ],
    "wof:name":"Glenloch Homes For The Elderly Inc",
    "wof:placetype":"venue"
},
  "geometry": {"coordinates":[145.016387939,-37.8606796265],"type":"Point"}
}