{
  "type": "Feature",
  "properties": {
    "addr:full":"Pearce Rd Nambour QLD 4560",
    "addr:postcode":"4560",
    "addr:street":"Pearce Rd",
    "iso:country":"AU",
    "sg:address":"Pearce Rd",
    "sg:city":"Nambour",
    "sg:classifiers":[
        {
            "category":"Farming",
            "subcategory":"Farm",
            "type":"Manufacturing & Wholesale Goods"
        }
    ],
    "sg:phone":"+61 7 5446 6268",
    "sg:postcode":"4560",
    "sg:province":"QLD",
    "sg:tags":[
        "farmer"
    ],
    "wof:name":"Page G A & S J",
    "wof:placetype":"venue"
},
  "geometry": {"coordinates":[153.00758361800001,-26.5812187195],"type":"Point"}
}