{
  "type": "Feature",
  "properties": {
    "addr:full":"98 - 104 Riversdale Rd Hawthorn VIC 3122",
    "addr:housenumber":"104",
    "addr:postcode":"3122",
    "addr:street":"98;Riversdale Rd",
    "iso:country":"AU",
    "sg:address":"98 - 104 Riversdale Rd",
    "sg:city":"Hawthorn",
    "sg:classifiers":[
        {
            "category":"Organizations",
            "subcategory":"Membership Organization",
            "type":"Services"
        }
    ],
    "sg:phone":"+61 1800 100 500",
    "sg:postcode":"3122",
    "sg:province":"VIC",
    "sg:tags":[
        "support",
        "health",
        "organisation"
    ],
    "wof:name":"Alzheimers Australia Vic - National Dementia Helpline",
    "wof:placetype":"venue"
},
  "geometry": {"coordinates":[145.035324097,-37.8289489746],"type":"Point"}
}