{
  "type": "Feature",
  "properties": {
    "iso:country":"AU",
    "sg:address":"8 Armstrong North St",
    "sg:city":"Ballarat",
    "sg:classifiers":[
        {
            "category":"Food & Beverages",
            "subcategory":"Bakery",
            "type":"Retail Goods"
        }
    ],
    "sg:phone":"+61 3 5332 8172",
    "sg:postcode":"3350",
    "sg:province":"VIC",
    "sg:tags":[
        "baker"
    ],
    "wof:name":"Bread Basket The",
    "wof:placetype":"venue"
},
  "geometry": {"coordinates":[143.856567,-37.561222],"type":"Point"}
}