{
  "type": "Feature",
  "properties": {
    "addr:full":"433 Williamstown Rd Port Melbourne VIC 3207",
    "addr:housenumber":"433",
    "addr:postcode":"3207",
    "addr:street":"Williamstown Rd",
    "iso:country":"AU",
    "sg:address":"433 Williamstown Rd",
    "sg:city":"Port Melbourne",
    "sg:classifiers":[
        {
            "category":"Retail",
            "subcategory":"Auto Repair",
            "type":"Services"
        }
    ],
    "sg:phone":"+61 3 9646 3362",
    "sg:postcode":"3207",
    "sg:province":"VIC",
    "sg:tags":[
        "testing",
        "inspection",
        "motor",
        "vehicle"
    ],
    "wof:name":"Road Safety Inspections Pty Ltd",
    "wof:placetype":"venue"
},
  "geometry": {"coordinates":[144.93353300000001,-37.833202],"type":"Point"}
}