{
  "type": "Feature",
  "properties": {
    "iso:country":"AU",
    "sg:address":"Bussell Hwy",
    "sg:city":"Stratham",
    "sg:classifiers":[
        {
            "category":"Shopping",
            "subcategory":"Crafts & Fabrics",
            "type":"Retail Goods"
        }
    ],
    "sg:phone":"+61 8 9795 9974",
    "sg:postcode":"6237",
    "sg:province":"WA",
    "sg:tags":[
        "supply"
    ],
    "wof:name":"Earth & Fire Pottery",
    "wof:placetype":"venue"
},
  "geometry": {"coordinates":[115.593857,-33.471256],"type":"Point"}
}