{
  "type": "Feature",
  "properties": {
    "addr:full":"16 Counsel Rd Coolbellup WA 6163",
    "addr:housenumber":"16",
    "addr:postcode":"6163",
    "addr:street":"Counsel Rd",
    "iso:country":"AU",
    "sg:address":"16 Counsel Rd",
    "sg:city":"Coolbellup",
    "sg:classifiers":[
        {
            "category":"Professional",
            "type":"Services"
        }
    ],
    "sg:phone":"+61 417 969 864",
    "sg:postcode":"6163",
    "sg:province":"WA",
    "sg:tags":[
        "transport"
    ],
    "wof:name":"VI Transport Pty Ltd",
    "wof:placetype":"venue"
},
  "geometry": {"coordinates":[115.79856100000001,-32.08025],"type":"Point"}
}