{
  "type": "Feature",
  "properties": {
    "addr:full":"118 Riviera Ave Terrigal NSW 2260",
    "addr:housenumber":"118",
    "addr:postcode":"2260",
    "addr:street":"Riviera Ave",
    "iso:country":"AU",
    "sg:address":"118 Riviera Ave",
    "sg:city":"Terrigal",
    "sg:classifiers":[
        {
            "category":"Professional",
            "subcategory":"Engineering",
            "type":"Services"
        }
    ],
    "sg:phone":"+61 2 4384 4317",
    "sg:postcode":"2260",
    "sg:province":"NSW",
    "sg:tags":[
        "civil",
        "engineer"
    ],
    "wof:name":"Byrne G G",
    "wof:placetype":"venue"
},
  "geometry": {"coordinates":[151.43957499999999,-33.44606],"type":"Point"}
}