{
  "type": "Feature",
  "properties": {
    "addr:full":"527 Hampton St Hampton VIC 3188",
    "addr:housenumber":"527",
    "addr:postcode":"3188",
    "addr:street":"Hampton St",
    "iso:country":"AU",
    "sg:address":"527 Hampton St",
    "sg:city":"Hampton",
    "sg:classifiers":[
        {
            "category":"Health Services",
            "subcategory":"Medical Lab",
            "type":"Services"
        }
    ],
    "sg:phone":"+61 3 9521 0299",
    "sg:postcode":"3188",
    "sg:province":"VIC",
    "sg:tags":[
        "laboratory",
        "dental"
    ],
    "wof:name":"Smile Works The",
    "wof:placetype":"venue"
},
  "geometry": {"coordinates":[145.00340270999999,-37.9316215515],"type":"Point"}
}