{
  "type": "Feature",
  "properties": {
    "iso:country":"AU",
    "sg:address":"188 Carlisle St",
    "sg:city":"St Kilda",
    "sg:classifiers":[
        {
            "category":"Shopping",
            "subcategory":"Shoes",
            "type":"Retail Goods"
        }
    ],
    "sg:phone":"+61 3 9534 5099",
    "sg:postcode":"3182",
    "sg:province":"VIC",
    "sg:tags":[
        "footwear"
    ],
    "wof:name":"Bella Shoes Pty Ltd",
    "wof:placetype":"venue"
},
  "geometry": {"coordinates":[144.99049377399999,-37.8682136536],"type":"Point"}
}