{
  "type": "Feature",
  "properties": {
    "addr:full":"26 Nimmo St Middle Park VIC 3206",
    "addr:housenumber":"26",
    "addr:postcode":"3206",
    "addr:street":"Nimmo St",
    "iso:country":"AU",
    "sg:address":"26 Nimmo St",
    "sg:city":"Middle Park",
    "sg:classifiers":[
        {
            "category":"Building & Trades",
            "subcategory":"Locksmith",
            "type":"Services"
        }
    ],
    "sg:phone":"+61 419 523 199",
    "sg:postcode":"3206",
    "sg:province":"VIC",
    "sg:tags":[
        "steeplejack"
    ],
    "wof:name":"UTM Rigging",
    "wof:placetype":"venue"
},
  "geometry": {"coordinates":[144.96246300000001,-37.849632],"type":"Point"}
}