{
  "type": "Feature",
  "properties": {
    "addr:full":"Grevillea St Byron Bay NSW 2481",
    "addr:postcode":"2481",
    "addr:street":"Grevillea St",
    "iso:country":"AU",
    "sg:address":"Grevillea St",
    "sg:city":"Byron Bay",
    "sg:classifiers":[
        {
            "category":"Autos & Motor Vehicles",
            "subcategory":"Auto Supplies",
            "type":"Retail Goods"
        }
    ],
    "sg:phone":"+61 2 6685 6685",
    "sg:postcode":"2481",
    "sg:province":"NSW",
    "sg:tags":[
        "accessory"
    ],
    "wof:name":"Byron Bay Motor Wreckers",
    "wof:placetype":"venue"
},
  "geometry": {"coordinates":[153.58392334000001,-28.6368637085],"type":"Point"}
}