{
  "type": "Feature",
  "properties": {
    "iso:country":"AU",
    "sg:address":"413 Victoria St",
    "sg:city":"Wetherill Park",
    "sg:classifiers":[
        {
            "category":"Professional",
            "type":"Services"
        }
    ],
    "sg:phone":"+61 2 9756 3080",
    "sg:postcode":"2164",
    "sg:province":"NSW",
    "sg:tags":[
        "packaging",
        "filling",
        "assembling"
    ],
    "wof:name":"Klausen Contract Processing",
    "wof:placetype":"venue"
},
  "geometry": {"coordinates":[150.89581298799999,-33.8449821472],"type":"Point"}
}