{
  "type": "Feature",
  "properties": {
    "addr:full":"7 Sturt St Ballarat VIC 3350",
    "addr:housenumber":"7",
    "addr:postcode":"3350",
    "addr:street":"Sturt St",
    "iso:country":"AU",
    "sg:address":"7 Sturt St",
    "sg:city":"Ballarat",
    "sg:classifiers":[
        {
            "category":"Health Services",
            "subcategory":"Health Practitioner",
            "type":"Services"
        }
    ],
    "sg:phone":"+61 3 5331 5316",
    "sg:postcode":"3350",
    "sg:province":"VIC",
    "sg:tags":[
        "naturopath"
    ],
    "wof:name":"Jasmine Setchell",
    "wof:placetype":"venue"
},
  "geometry": {"coordinates":[143.85884100000001,-37.562397],"type":"Point"}
}