{
  "type": "Feature",
  "properties": {
    "iso:country":"AU",
    "sg:address":"Commercial Rd",
    "sg:city":"Morwell",
    "sg:classifiers":[
        {
            "category":"Education",
            "subcategory":"School",
            "type":"Public Place"
        }
    ],
    "sg:phone":"+61 3 5134 2329",
    "sg:postcode":"3840",
    "sg:province":"VIC",
    "sg:tags":[
        "state",
        "except",
        "nsw"
    ],
    "wof:name":"Morwell Primary School",
    "wof:placetype":"venue"
},
  "geometry": {"coordinates":[146.40997314399999,-38.2407341003],"type":"Point"}
}