{
  "type": "Feature",
  "properties": {
    "addr:full":"118 Wolseley Rd Oakville NSW 2765",
    "addr:housenumber":"118",
    "addr:postcode":"2765",
    "addr:street":"Wolseley Rd",
    "iso:country":"AU",
    "sg:address":"118 Wolseley Rd",
    "sg:city":"Oakville",
    "sg:classifiers":[
        {
            "category":"Education",
            "subcategory":"School",
            "type":"Public Place"
        }
    ],
    "sg:phone":"+61 2 4572 3633",
    "sg:postcode":"2765",
    "sg:province":"NSW",
    "sg:tags":[
        "co-educational"
    ],
    "wof:name":"Arndell College",
    "wof:placetype":"venue"
},
  "geometry": {"coordinates":[150.85153198200001,-33.620426178],"type":"Point"}
}