{
  "type": "Feature",
  "properties": {
    "addr:full":"30 Duntroon St Brendale QLD 4500",
    "addr:housenumber":"30",
    "addr:postcode":"4500",
    "addr:street":"Duntroon St",
    "iso:country":"AU",
    "sg:address":"30 Duntroon St",
    "sg:city":"Brendale",
    "sg:classifiers":[
        {
            "category":"Food & Beverages",
            "subcategory":"Specialty",
            "type":"Retail Goods"
        }
    ],
    "sg:phone":"+61 7 3881 0810",
    "sg:postcode":"4500",
    "sg:province":"QLD",
    "sg:tags":[
        "product",
        "health"
    ],
    "wof:name":"Ellen Jay Health & Beauty",
    "wof:placetype":"venue"
},
  "geometry": {"coordinates":[152.98333740199999,-27.3214244843],"type":"Point"}
}