{
  "type": "Feature",
  "properties": {
    "addr:full":"Lot 23 Pulman Pl Emu Plains NSW 2750",
    "addr:postcode":"2750",
    "addr:street":"Pl",
    "iso:country":"AU",
    "sg:address":"Lot 23 Pulman Pl",
    "sg:city":"Emu Plains",
    "sg:classifiers":[
        {
            "category":"Building & Trades",
            "subcategory":"Equipment Rental",
            "type":"Services"
        }
    ],
    "sg:phone":"+61 2 4729 0856",
    "sg:postcode":"2750",
    "sg:province":"NSW",
    "sg:tags":[
        "crane",
        "hire"
    ],
    "wof:name":"Schreiterer Transport Pty Ltd",
    "wof:placetype":"venue"
},
  "geometry": {"coordinates":[150.65473938,-33.746307373],"type":"Point"}
}