{
  "type": "Feature",
  "properties": {
    "addr:full":"11 Myrtle St Watsonia VIC 3087",
    "addr:housenumber":"11",
    "addr:postcode":"3087",
    "addr:street":"Myrtle St",
    "iso:country":"AU",
    "sg:address":"11 Myrtle St",
    "sg:city":"Watsonia",
    "sg:classifiers":[
        {
            "category":"Home & Garden",
            "subcategory":"Home Furnishings",
            "type":"Retail Goods"
        }
    ],
    "sg:phone":"+61 3 9434 0600",
    "sg:postcode":"3087",
    "sg:province":"VIC",
    "sg:tags":[
        "storage",
        "rack",
        "wine"
    ],
    "wof:name":"Winehaus Cellar Design & Construction",
    "wof:placetype":"venue"
},
  "geometry": {"coordinates":[145.088943481,-37.6987228394],"type":"Point"}
}