{
  "type": "Feature",
  "properties": {
    "addr:full":"Cnr Grants Gully & Miller Rds Clarendon SA 5157",
    "addr:postcode":"5157",
    "addr:street":"Grants",
    "iso:country":"AU",
    "sg:address":"Cnr Grants Gully & Miller Rds",
    "sg:city":"Clarendon",
    "sg:classifiers":[
        {
            "category":"Retail",
            "subcategory":"Event Space",
            "type":"Services"
        }
    ],
    "sg:phone":"+61 8 8383 6166",
    "sg:postcode":"5157",
    "sg:province":"SA",
    "sg:tags":[
        "venue",
        "reception",
        "wedding"
    ],
    "wof:name":"The Old Clarendon Inn",
    "wof:placetype":"venue"
},
  "geometry": {"coordinates":[138.63027954099999,-35.1099967957],"type":"Point"}
}