{
  "type": "Feature",
  "properties": {
    "iso:country":"AU",
    "sg:address":"150 Davey St",
    "sg:city":"Hobart",
    "sg:classifiers":[
        {
            "category":"Professional",
            "subcategory":"Computer Services",
            "type":"Services"
        }
    ],
    "sg:phone":"+61 3 6224 0937",
    "sg:postcode":"7000",
    "sg:province":"TAS",
    "sg:tags":[
        "package",
        "software"
    ],
    "wof:name":"Axsys",
    "wof:placetype":"venue"
},
  "geometry": {"coordinates":[147.324752808,-42.8884849548],"type":"Point"}
}