{
  "type": "Feature",
  "properties": {
    "addr:full":"221 Albany Hwy Victoria Park WA 6100",
    "addr:housenumber":"221",
    "addr:postcode":"6100",
    "addr:street":"Albany Hwy Victoria",
    "iso:country":"AU",
    "sg:address":"221 Albany Hwy",
    "sg:city":"Victoria Park",
    "sg:classifiers":[
        {
            "category":"Recreation",
            "subcategory":"Fishing",
            "type":"Entertainment"
        }
    ],
    "sg:phone":"+61 8 9355 0575",
    "sg:postcode":"6100",
    "sg:province":"WA",
    "sg:tags":[
        "tackle"
    ],
    "wof:name":"Anglers Fishing World",
    "wof:placetype":"venue"
},
  "geometry": {"coordinates":[115.892883301,-31.9709339142],"type":"Point"}
}