{
  "type": "Feature",
  "properties": {
    "iso:country":"AU",
    "sg:address":"Cnr Mill & Wilson Sts",
    "sg:city":"Mossman",
    "sg:classifiers":[
        {
            "category":"Retail",
            "subcategory":"Auto Repair",
            "type":"Services"
        }
    ],
    "sg:phone":"+61 7 4098 1502",
    "sg:postcode":"4873",
    "sg:province":"QLD",
    "sg:tags":[
        "clutch",
        "brake"
    ],
    "wof:name":"Goodyear Auto Service Centre",
    "wof:placetype":"venue"
},
  "geometry": {"coordinates":[145.37440490700001,-16.4591617584],"type":"Point"}
}