{
  "type": "Feature",
  "properties": {
    "addr:full":"Unit 3- 177 Beavers Rd Northcote VIC 3070",
    "addr:housenumber":"177",
    "addr:postcode":"3070",
    "addr:street":"Beavers Rd",
    "iso:country":"AU",
    "sg:address":"Unit 3- 177 Beavers Rd",
    "sg:city":"Northcote",
    "sg:classifiers":[
        {
            "category":"Wholesale",
            "subcategory":"Music Publishers",
            "type":"Manufacturing & Wholesale Goods"
        }
    ],
    "sg:phone":"+61 3 9482 3873",
    "sg:postcode":"3070",
    "sg:province":"VIC",
    "sg:tags":[
        "wholesaler",
        "dvd",
        "mfrs",
        "cd"
    ],
    "wof:name":"Shock Film & DVD",
    "wof:placetype":"venue"
},
  "geometry": {"coordinates":[144.98613,-37.765373],"type":"Point"}
}