{
  "type": "Feature",
  "properties": {
    "addr:full":"Shop 1/ 31 MacLaurin Ave East Hills NSW 2213",
    "addr:housenumber":"shop 1 / 31",
    "addr:postcode":"2213",
    "addr:street":"Maclaurin Ave",
    "iso:country":"AU",
    "sg:address":"Shop 1/ 31 MacLaurin Ave",
    "sg:city":"East Hills",
    "sg:classifiers":[
        {
            "category":"Personal",
            "subcategory":"Beauty Salon",
            "type":"Services"
        }
    ],
    "sg:phone":"+61 2 9772 1220",
    "sg:postcode":"2213",
    "sg:province":"NSW",
    "wof:name":"Elegance in Beauty",
    "wof:placetype":"venue"
},
  "geometry": {"coordinates":[150.984467,-33.962696],"type":"Point"}
}