{
  "type": "Feature",
  "properties": {
    "iso:country":"AU",
    "sg:address":"90 Payne St",
    "sg:city":"Auchenflower",
    "sg:classifiers":[
        {
            "category":"Health Services",
            "subcategory":"Health Practitioner",
            "type":"Services"
        }
    ],
    "sg:phone":"+61 7 3876 8666",
    "sg:postcode":"4066",
    "sg:province":"QLD",
    "sg:tags":[
        "physiotherapist"
    ],
    "wof:name":"Lilley Kathleen-Physiotherapy Inservices",
    "wof:placetype":"venue"
},
  "geometry": {"coordinates":[152.99070739699999,-27.4696178436],"type":"Point"}
}