{
  "type": "Feature",
  "properties": {
    "addr:full":"22 Ainsbury Pde Clarkson WA 6030",
    "addr:housenumber":"22",
    "addr:postcode":"6030",
    "addr:street":"Ainsbury Pde",
    "iso:country":"AU",
    "sg:address":"22 Ainsbury Pde",
    "sg:city":"Clarkson",
    "sg:classifiers":[
        {
            "category":"Social Services",
            "subcategory":"Child Care",
            "type":"Services"
        }
    ],
    "sg:phone":"+61 8 9305 7307",
    "sg:postcode":"6030",
    "sg:province":"WA",
    "wof:name":"Clarkson Child Care",
    "wof:placetype":"venue"
},
  "geometry": {"coordinates":[115.716186523,-31.6796112061],"type":"Point"}
}