{
  "type": "Feature",
  "properties": {
    "addr:full":"32 School Rd Stafford QLD 4053",
    "addr:housenumber":"32",
    "addr:postcode":"4053",
    "addr:street":"School Rd",
    "iso:country":"AU",
    "sg:address":"32 School Rd",
    "sg:city":"Stafford",
    "sg:classifiers":[
        {
            "category":"Utilities",
            "subcategory":"Electric",
            "type":"Services"
        }
    ],
    "sg:phone":"+61 414 759 766",
    "sg:postcode":"4053",
    "sg:province":"QLD",
    "sg:tags":[
        "electrical",
        "contractor"
    ],
    "wof:name":"Bob Wrench Electrical",
    "wof:placetype":"venue"
},
  "geometry": {"coordinates":[153.01759338400001,-27.409538269],"type":"Point"}
}