{
  "type": "Feature",
  "properties": {
    "iso:country":"AU",
    "sg:address":"Shop 4/ 58 Capella St",
    "sg:city":"Clermont",
    "sg:classifiers":[
        {
            "category":"Health Services",
            "subcategory":"Health Practitioner",
            "type":"Services"
        }
    ],
    "sg:phone":"+61 7 4983 1888",
    "sg:postcode":"4721",
    "sg:province":"QLD",
    "sg:tags":[
        "bowen",
        "therapy"
    ],
    "wof:name":"Qi Dharma",
    "wof:placetype":"venue"
},
  "geometry": {"coordinates":[147.64051818900001,-22.8237915039],"type":"Point"}
}