{
  "type": "Feature",
  "properties": {
    "addr:full":"451 High St Preston VIC 3072",
    "addr:housenumber":"451",
    "addr:postcode":"3072",
    "addr:street":"High St",
    "iso:country":"AU",
    "sg:address":"451 High St",
    "sg:city":"Preston",
    "sg:classifiers":[
        {
            "category":"Food & Beverages",
            "subcategory":"Bakery",
            "type":"Retail Goods"
        }
    ],
    "sg:phone":"+61 3 9478 2324",
    "sg:postcode":"3072",
    "sg:province":"VIC",
    "sg:tags":[
        "cake",
        "shop",
        "pastry"
    ],
    "wof:name":"Herberts Pies",
    "wof:placetype":"venue"
},
  "geometry": {"coordinates":[145.00372314399999,-37.7386779785],"type":"Point"}
}