{
  "type": "Feature",
  "properties": {
    "addr:full":"Cnr Porter St & Ashmole Rd Redcliffe QLD 4020",
    "addr:postcode":"4020",
    "addr:street":"Cnr Porter St & Ashmole Rd",
    "iso:country":"AU",
    "sg:address":"Cnr Porter St & Ashmole Rd",
    "sg:city":"Redcliffe",
    "sg:classifiers":[
        {
            "category":"Food & Beverages",
            "subcategory":"Bakery",
            "type":"Retail Goods"
        }
    ],
    "sg:phone":"+61 7 3880 0011",
    "sg:postcode":"4020",
    "sg:province":"QLD",
    "sg:tags":[
        "baker"
    ],
    "wof:name":"Porter Street Bakery",
    "wof:placetype":"venue"
},
  "geometry": {"coordinates":[153.107224,-27.22217],"type":"Point"}
}