{
  "type": "Feature",
  "properties": {
    "iso:country":"AU",
    "sg:address":"Shop 2/ 53 Burnett St",
    "sg:city":"Buderim",
    "sg:classifiers":[
        {
            "category":"Shopping",
            "subcategory":"Hobbies, Toys, & Games",
            "type":"Retail Goods"
        }
    ],
    "sg:phone":"+61 7 5456 4200",
    "sg:postcode":"4556",
    "sg:province":"QLD",
    "sg:tags":[
        "stamp"
    ],
    "wof:name":"Badgers Books",
    "wof:placetype":"venue"
},
  "geometry": {"coordinates":[153.04997253400001,-26.6865768433],"type":"Point"}
}