{
  "type": "Feature",
  "properties": {
    "addr:full":"DPWS White St Dubbo NSW 2830",
    "addr:postcode":"2830",
    "addr:street":"White St",
    "iso:country":"AU",
    "sg:address":"DPWS White St",
    "sg:city":"Dubbo",
    "sg:classifiers":[
        {
            "category":"Real Estate",
            "subcategory":"Real Estate Services",
            "type":"Services"
        }
    ],
    "sg:phone":"+61 2 6885 9323",
    "sg:postcode":"2830",
    "sg:province":"NSW",
    "sg:tags":[
        "valuer"
    ],
    "wof:name":"State Valuation Office",
    "wof:placetype":"venue"
},
  "geometry": {"coordinates":[148.618682861,-32.2418861389],"type":"Point"}
}