{
  "type": "Feature",
  "properties": {
    "iso:country":"AU",
    "sg:address":"39 Urawa Rd",
    "sg:city":"Duncraig",
    "sg:classifiers":[
        {
            "category":"Home & Garden",
            "subcategory":"Building Materials",
            "type":"Retail Goods"
        }
    ],
    "sg:phone":"+61 400 215 335",
    "sg:postcode":"6023",
    "sg:province":"WA",
    "sg:tags":[
        "lawn",
        "cutting",
        "maintenance"
    ],
    "wof:name":"JPs Lawn Mowing",
    "wof:placetype":"venue"
},
  "geometry": {"coordinates":[115.764633179,-31.8284740448],"type":"Point"}
}