{
  "type": "Feature",
  "properties": {
    "addr:full":"18 Patullos Rd Lara VIC 3212",
    "addr:housenumber":"18",
    "addr:postcode":"3212",
    "addr:street":"Patullos Rd",
    "iso:country":"AU",
    "sg:address":"18 Patullos Rd",
    "sg:city":"Lara",
    "sg:classifiers":[
        {
            "category":"Fast Food",
            "type":"Food & Drink"
        }
    ],
    "sg:phone":"+61 3 5282 2992",
    "sg:postcode":"3212",
    "sg:province":"VIC",
    "sg:tags":[
        "away",
        "take"
    ],
    "wof:name":"Sixways Fish N Chips",
    "wof:placetype":"venue"
},
  "geometry": {"coordinates":[144.395385742,-38.0227279663],"type":"Point"}
}