{
  "type": "Feature",
  "properties": {
    "addr:full":"3/ 191 Chester Pass Rd Albany WA 6330",
    "addr:housenumber":"/ 191",
    "addr:postcode":"6330",
    "addr:street":"Chester Pass Rd",
    "iso:country":"AU",
    "sg:address":"3/ 191 Chester Pass Rd",
    "sg:city":"Albany",
    "sg:classifiers":[
        {
            "category":"Banks & Credit Unions",
            "subcategory":"Investment Brokerage",
            "type":"Services"
        }
    ],
    "sg:phone":"+61 8 9842 8581",
    "sg:postcode":"6330",
    "sg:province":"WA",
    "wof:name":"Timbercorp",
    "wof:placetype":"venue"
},
  "geometry": {"coordinates":[117.875770569,-34.9880447388],"type":"Point"}
}