{
  "type": "Feature",
  "properties": {
    "iso:country":"AU",
    "sg:address":"62 Alexander St",
    "sg:city":"Surat",
    "sg:classifiers":[
        {
            "category":"Autos & Motor Vehicles",
            "subcategory":"Auto Supplies",
            "type":"Retail Goods"
        }
    ],
    "sg:phone":"+61 458 265 505",
    "sg:postcode":"4417",
    "sg:province":"QLD",
    "sg:tags":[
        "tyre"
    ],
    "wof:name":"Surat Tyre Service",
    "wof:placetype":"venue"
},
  "geometry": {"coordinates":[149.067504883,-27.1587638855],"type":"Point"}
}