{
  "type": "Feature",
  "properties": {
    "addr:full":"245 Learmonth Rd Wendouree VIC 3355",
    "addr:housenumber":"245",
    "addr:postcode":"3355",
    "addr:street":"Learmonth Rd",
    "iso:country":"AU",
    "sg:address":"245 Learmonth Rd",
    "sg:city":"Wendouree",
    "sg:classifiers":[
        {
            "category":"Professional",
            "subcategory":"Detective & Security Services",
            "type":"Services"
        }
    ],
    "sg:phone":"+61 3 5339 1056",
    "sg:postcode":"3355",
    "sg:province":"VIC",
    "sg:tags":[
        "equipment",
        "window",
        "doors"
    ],
    "wof:name":"Dart J & G",
    "wof:placetype":"venue"
},
  "geometry": {"coordinates":[143.81231700000001,-37.528526],"type":"Point"}
}