{
  "type": "Feature",
  "properties": {
    "addr:full":"Shop 73 , Burnside Shopping Village Glenside SA 5065",
    "addr:housenumber":"shop 73",
    "addr:postcode":"5065",
    "addr:street":"Burnside Shopping",
    "iso:country":"AU",
    "sg:address":"Shop 73",
    "sg:city":", Burnside Shopping Village Glenside",
    "sg:classifiers":[
        {
            "category":"Shopping",
            "subcategory":"Shoes",
            "type":"Retail Goods"
        }
    ],
    "sg:phone":"+61 8 8338 1863",
    "sg:postcode":"5065",
    "sg:province":"SA",
    "sg:tags":[
        "footwear"
    ],
    "wof:name":"Betts Kids Shoes",
    "wof:placetype":"venue"
},
  "geometry": {"coordinates":[138.642654419,-34.9418182373],"type":"Point"}
}