{
  "type": "Feature",
  "properties": {
    "iso:country":"AU",
    "sg:address":"98 Renown Ave",
    "sg:city":"Punchbowl",
    "sg:classifiers":[
        {
            "category":"Retail",
            "subcategory":"Driving School",
            "type":"Services"
        }
    ],
    "sg:phone":"+61 417 656 115",
    "sg:postcode":"2196",
    "sg:province":"NSW",
    "wof:name":"John Kelly Driving School",
    "wof:placetype":"venue"
},
  "geometry": {"coordinates":[151.068237,-33.930077],"type":"Point"}
}