{
  "type": "Feature",
  "properties": {
    "iso:country":"AU",
    "sg:address":"25 Nobility St",
    "sg:city":"Moolap",
    "sg:classifiers":[
        {
            "category":"Building & Trades",
            "subcategory":"Construction",
            "type":"Services"
        }
    ],
    "sg:phone":"+61 3 5248 5777",
    "sg:postcode":"3221",
    "sg:province":"VIC",
    "sg:tags":[
        "contractor"
    ],
    "wof:name":"Rogers M.J.",
    "wof:placetype":"venue"
},
  "geometry": {"coordinates":[144.41149899999999,-38.165695],"type":"Point"}
}