{
  "type": "Feature",
  "properties": {
    "addr:full":"4 Tinsey Crt Caboolture QLD 4510",
    "addr:housenumber":"4",
    "addr:postcode":"4510",
    "addr:street":"Tinsey Crt",
    "iso:country":"AU",
    "sg:address":"4 Tinsey Crt",
    "sg:city":"Caboolture",
    "sg:classifiers":[
        {
            "category":"Education",
            "subcategory":"Special Training",
            "type":"Public Place"
        }
    ],
    "sg:phone":"+61 7 5499 4488",
    "sg:postcode":"4510",
    "sg:province":"QLD",
    "sg:tags":[
        "tuition-educational"
    ],
    "wof:name":"Action Coaching",
    "wof:placetype":"venue"
},
  "geometry": {"coordinates":[152.96778900000001,-27.081312],"type":"Point"}
}