{
  "type": "Feature",
  "properties": {
    "addr:full":"5 Station St Frankston VIC 3199",
    "addr:housenumber":"5",
    "addr:postcode":"3199",
    "addr:street":"Station St",
    "iso:country":"AU",
    "sg:address":"5 Station St",
    "sg:city":"Frankston",
    "sg:classifiers":[
        {
            "category":"Personal",
            "subcategory":"Beauty Salon",
            "type":"Services"
        }
    ],
    "sg:phone":"+61 3 9781 0841",
    "sg:postcode":"3199",
    "sg:province":"VIC",
    "wof:name":"Heaven On Earth Day Spa",
    "wof:placetype":"venue"
},
  "geometry": {"coordinates":[145.12512207,-38.143119812],"type":"Point"}
}