{
  "type": "Feature",
  "properties": {
    "addr:full":"PO Box 51 Hillarys WA 6025",
    "addr:postcode":"6025",
    "iso:country":"AU",
    "sg:address":"PO Box 51",
    "sg:city":"Hillarys",
    "sg:classifiers":[
        {
            "category":"Professional",
            "subcategory":"Employment Agencies",
            "type":"Services"
        }
    ],
    "sg:phone":"+61 8 9305 6701",
    "sg:postcode":"6025",
    "sg:province":"WA",
    "sg:tags":[
        "provider",
        "internet"
    ],
    "wof:name":"Internet Advisory Services",
    "wof:placetype":"venue"
},
  "geometry": {"coordinates":[115.74561309800001,-31.8076992035],"type":"Point"}
}