{
  "type": "Feature",
  "properties": {
    "addr:full":"107 Oxford Ave Bankstown NSW 2200",
    "addr:housenumber":"107",
    "addr:postcode":"2200",
    "addr:street":"Oxford Ave",
    "iso:country":"AU",
    "sg:address":"107 Oxford Ave",
    "sg:city":"Bankstown",
    "sg:classifiers":[
        {
            "category":"Building & Trades",
            "subcategory":"Construction",
            "type":"Services"
        }
    ],
    "sg:phone":"+61 2 9796 2296",
    "sg:postcode":"2200",
    "sg:province":"NSW",
    "sg:tags":[
        "concrete",
        "contractor"
    ],
    "wof:name":"RA Building Construction Pty Ltd",
    "wof:placetype":"venue"
},
  "geometry": {"coordinates":[151.02500900000001,-33.925243],"type":"Point"}
}