{
  "type": "Feature",
  "properties": {
    "addr:full":"8 Yarraga Pl Yowie Bay NSW 2228",
    "addr:housenumber":"8",
    "addr:postcode":"2228",
    "addr:street":"Yarraga Pl",
    "iso:country":"AU",
    "sg:address":"8 Yarraga Pl",
    "sg:city":"Yowie Bay",
    "sg:classifiers":[
        {
            "category":"Health Services",
            "subcategory":"Doctor",
            "type":"Services"
        }
    ],
    "sg:phone":"+61 2 9526 2250",
    "sg:postcode":"2228",
    "sg:province":"NSW",
    "sg:tags":[
        "medical",
        "practitioner"
    ],
    "wof:name":"Prabhakar K N",
    "wof:placetype":"venue"
},
  "geometry": {"coordinates":[151.107696533,-34.046459198],"type":"Point"}
}