{
  "type": "Feature",
  "properties": {
    "iso:country":"AU",
    "sg:address":"PO Box 485",
    "sg:city":"Neutral Bay",
    "sg:classifiers":[
        {
            "category":"Personal",
            "type":"Services"
        }
    ],
    "sg:phone":"+61 2 9960 5115",
    "sg:postcode":"2089",
    "sg:province":"NSW",
    "sg:tags":[
        "introduction",
        "social"
    ],
    "wof:name":"Julianna Robertson & Friends",
    "wof:placetype":"venue"
},
  "geometry": {"coordinates":[151.21998596200001,-33.8306503296],"type":"Point"}
}