{
  "type": "Feature",
  "properties": {
    "addr:full":"146- 148 Lords Pl Orange NSW 2800",
    "addr:housenumber":"148",
    "addr:postcode":"2800",
    "addr:street":"Lords Pl",
    "iso:country":"AU",
    "sg:address":"146- 148 Lords Pl",
    "sg:city":"Orange",
    "sg:classifiers":[
        {
            "category":"Professional",
            "subcategory":"Accounting & Tax Preparation",
            "type":"Services"
        }
    ],
    "sg:phone":"+61 2 6362 1933",
    "sg:postcode":"2800",
    "sg:province":"NSW",
    "sg:tags":[
        "consultant",
        "taxation"
    ],
    "wof:name":"WHK Todd & Niven",
    "wof:placetype":"venue"
},
  "geometry": {"coordinates":[149.10081481899999,-33.2848358154],"type":"Point"}
}