{
  "type": "Feature",
  "properties": {
    "iso:country":"AU",
    "sg:address":"Level 11, 221 St",
    "sg:city":"Georges Tce Perth",
    "sg:classifiers":[
        {
            "category":"Professional",
            "subcategory":"Engineering",
            "type":"Services"
        }
    ],
    "sg:phone":"+61 8 9481 8222",
    "sg:postcode":"6000",
    "sg:province":"WA",
    "sg:tags":[
        "consulting",
        "engineer"
    ],
    "wof:name":"J P Kenny Pty Ltd",
    "wof:placetype":"venue"
},
  "geometry": {"coordinates":[115.851867676,-31.9532966614],"type":"Point"}
}