{
  "type": "Feature",
  "properties": {
    "iso:country":"AU",
    "sg:address":"35 Gillies St",
    "sg:city":"Benalla",
    "sg:classifiers":[
        {
            "category":"Farming",
            "subcategory":"Farm & Veterinary Services",
            "type":"Manufacturing & Wholesale Goods"
        }
    ],
    "sg:phone":"+61 3 5762 5288",
    "sg:postcode":"3672",
    "sg:province":"VIC",
    "sg:tags":[
        "seedsman"
    ],
    "wof:name":"Smyth Seeds",
    "wof:placetype":"venue"
},
  "geometry": {"coordinates":[145.987259,-36.539265],"type":"Point"}
}