{
  "type": "Feature",
  "properties": {
    "addr:full":"4 Crossley St Melbourne VIC 3000",
    "addr:housenumber":"4",
    "addr:postcode":"3000",
    "addr:street":"Crossley St",
    "iso:country":"AU",
    "sg:address":"4 Crossley St",
    "sg:city":"Melbourne",
    "sg:classifiers":[
        {
            "category":"Shopping",
            "subcategory":"Jewelry",
            "type":"Retail Goods"
        }
    ],
    "sg:phone":"+61 3 9662 9446",
    "sg:postcode":"3000",
    "sg:province":"VIC",
    "sg:tags":[
        "jeweller"
    ],
    "wof:name":"Gallery Funaki",
    "wof:placetype":"venue"
},
  "geometry": {"coordinates":[144.97142028799999,-37.8116798401],"type":"Point"}
}