{
  "type": "Feature",
  "properties": {
    "addr:full":"Shop8 George St Plz Corner George & Moore Streets Liverpool NSW 2170",
    "addr:postcode":"2170",
    "addr:street":"George St Plz Corner George & Moore Streets",
    "iso:country":"AU",
    "sg:address":"Shop8 George St Plz Corner George & Moore Streets",
    "sg:city":"Liverpool",
    "sg:classifiers":[
        {
            "category":"Shopping",
            "subcategory":"Discount & Variety Stores",
            "type":"Retail Goods"
        }
    ],
    "sg:phone":"+61 2 9601 7664",
    "sg:postcode":"2170",
    "sg:province":"NSW",
    "sg:tags":[
        "shop",
        "adult"
    ],
    "wof:name":"Adult XXX City",
    "wof:placetype":"venue"
},
  "geometry": {"coordinates":[150.926437378,-33.915473938],"type":"Point"}
}