{
  "type": "Feature",
  "properties": {
    "addr:full":"PO Box 1557 Sale VIC 3853",
    "addr:postcode":"3853",
    "iso:country":"AU",
    "sg:address":"PO Box 1557",
    "sg:city":"Sale",
    "sg:classifiers":[
        {
            "category":"Sports & Exercise",
            "subcategory":"Gym",
            "type":"Entertainment"
        }
    ],
    "sg:phone":"+61 427 719 150",
    "sg:postcode":"3853",
    "sg:province":"VIC",
    "sg:tags":[
        "personal",
        "trainer",
        "fitness"
    ],
    "wof:name":"The Fitness Formula",
    "wof:placetype":"venue"
},
  "geometry": {"coordinates":[147.06842040999999,-38.1093482971],"type":"Point"}
}