{
  "type": "Feature",
  "properties": {
    "iso:country":"AU",
    "sg:address":"27 Alsop Drv",
    "sg:city":"Winchelsea",
    "sg:classifiers":[
        {
            "category":"Retail",
            "subcategory":"Auto Repair",
            "type":"Services"
        }
    ],
    "sg:phone":"+61 3 5267 2150",
    "sg:postcode":"3241",
    "sg:province":"VIC",
    "sg:tags":[
        "engine",
        "reconditioning"
    ],
    "wof:name":"Engine Worx",
    "wof:placetype":"venue"
},
  "geometry": {"coordinates":[143.97633361800001,-38.2447891235],"type":"Point"}
}