{
  "type": "Feature",
  "properties": {
    "addr:full":"74 Boundary St West End (Brisbane) QLD 4101",
    "addr:housenumber":"74",
    "addr:postcode":"4101",
    "addr:street":"Boundary St",
    "iso:country":"AU",
    "sg:address":"74 Boundary St",
    "sg:city":"West End (Brisbane)",
    "sg:classifiers":[
        {
            "category":"Shopping",
            "subcategory":"Jewelry",
            "type":"Retail Goods"
        }
    ],
    "sg:phone":"+61 7 3844 4498",
    "sg:postcode":"4101",
    "sg:province":"QLD",
    "sg:tags":[
        "jeweller"
    ],
    "wof:name":"West End Jewellers Australia Pty Ltd",
    "wof:placetype":"venue"
},
  "geometry": {"coordinates":[153.012817383,-27.4776802063],"type":"Point"}
}