{
  "type": "Feature",
  "properties": {
    "addr:full":"1 Garden Pl Maroubra Junction NSW 2035",
    "addr:housenumber":"1",
    "addr:postcode":"2035",
    "addr:street":"Garden Pl",
    "iso:country":"AU",
    "sg:address":"1 Garden Pl",
    "sg:city":"Maroubra Junction",
    "sg:classifiers":[
        {
            "category":"Organizations",
            "subcategory":"Community Association",
            "type":"Services"
        }
    ],
    "sg:phone":"+61 2 9314 2166",
    "sg:postcode":"2035",
    "sg:province":"NSW",
    "sg:tags":[
        "organisation",
        "family",
        "welfare"
    ],
    "wof:name":"Salvation Army Family Welfare Centres",
    "wof:placetype":"venue"
},
  "geometry": {"coordinates":[151.20643615700001,-33.9285011292],"type":"Point"}
}