{
  "type": "Feature",
  "properties": {
    "addr:full":"84 Charters Towers Rd Townsville QLD 4810",
    "addr:housenumber":"84",
    "addr:postcode":"4810",
    "addr:street":"Charters Towers Rd",
    "iso:country":"AU",
    "sg:address":"84 Charters Towers Rd",
    "sg:city":"Townsville",
    "sg:classifiers":[
        {
            "category":"Building & Trades",
            "subcategory":"Construction",
            "type":"Services"
        }
    ],
    "sg:phone":"+61 7 4772 2822",
    "sg:postcode":"4810",
    "sg:province":"QLD",
    "sg:tags":[
        "contractor"
    ],
    "wof:name":"Glenwood Homes",
    "wof:placetype":"venue"
},
  "geometry": {"coordinates":[146.80186499999999,-19.275024],"type":"Point"}
}