{
  "type": "Feature",
  "properties": {
    "addr:full":"12 Cowper St Hawthorn East VIC 3123",
    "addr:housenumber":"12",
    "addr:postcode":"3123",
    "addr:street":"Cowper St",
    "iso:country":"AU",
    "sg:address":"12 Cowper St",
    "sg:city":"Hawthorn East",
    "sg:classifiers":[
        {
            "category":"Health Services",
            "subcategory":"Health Practitioner",
            "type":"Services"
        }
    ],
    "sg:phone":"+61 3 9882 7727",
    "sg:postcode":"3123",
    "sg:province":"VIC",
    "sg:tags":[
        "technique",
        "alexander"
    ],
    "wof:name":"Alexander Technique Australian Society Of Teachers Of The (Austat)",
    "wof:placetype":"venue"
},
  "geometry": {"coordinates":[145.055587769,-37.8183326721],"type":"Point"}
}