{
  "type": "Feature",
  "properties": {
    "addr:full":"22 Smallacombe St Tara QLD 4421",
    "addr:housenumber":"22",
    "addr:postcode":"4421",
    "addr:street":"Smallacombe St",
    "iso:country":"AU",
    "sg:address":"22 Smallacombe St",
    "sg:city":"Tara",
    "sg:classifiers":[
        {
            "category":"Building & Trades",
            "subcategory":"Construction",
            "type":"Services"
        }
    ],
    "sg:phone":"+61 7 4669 4053",
    "sg:postcode":"4421",
    "sg:province":"QLD",
    "sg:tags":[
        "concrete",
        "contractor"
    ],
    "wof:name":"Hiles Concreting Services",
    "wof:placetype":"venue"
},
  "geometry": {"coordinates":[150.460662842,-27.2786102295],"type":"Point"}
}