{
  "type": "Feature",
  "properties": {
    "addr:full":"186 Seaford Rd Seaford VIC 3198",
    "addr:housenumber":"186",
    "addr:postcode":"3198",
    "addr:street":"Seaford Rd",
    "iso:country":"AU",
    "sg:address":"186 Seaford Rd",
    "sg:city":"Seaford",
    "sg:classifiers":[
        {
            "category":"Education",
            "subcategory":"Kindergarten",
            "type":"Public Place"
        }
    ],
    "sg:phone":"+61 3 9782 4880",
    "sg:postcode":"3198",
    "sg:province":"VIC",
    "sg:tags":[
        "pre-schools"
    ],
    "wof:name":"D.B.'s Child Care & Kindergarten",
    "wof:placetype":"venue"
},
  "geometry": {"coordinates":[145.147750855,-38.111289978],"type":"Point"}
}