{
  "type": "Feature",
  "properties": {
    "iso:country":"AU",
    "sg:address":"59 Dendy St",
    "sg:city":"Brighton",
    "sg:classifiers":[
        {
            "category":"Health Services",
            "subcategory":"Doctor",
            "type":"Services"
        }
    ],
    "sg:phone":"+61 3 9593 2888",
    "sg:postcode":"3186",
    "sg:province":"VIC",
    "sg:tags":[
        "medical",
        "practitioner"
    ],
    "wof:name":"Breidahl Alan",
    "wof:placetype":"venue"
},
  "geometry": {"coordinates":[144.99807739299999,-37.9198379517],"type":"Point"}
}