{
  "type": "Feature",
  "properties": {
    "addr:full":"601 Pinjarra Rd Mandurah WA 6210",
    "addr:housenumber":"601",
    "addr:postcode":"6210",
    "addr:street":"Pinjarra Rd",
    "iso:country":"AU",
    "sg:address":"601 Pinjarra Rd",
    "sg:city":"Mandurah",
    "sg:classifiers":[
        {
            "category":"Government",
            "subcategory":"Customs House",
            "type":"Public Place"
        }
    ],
    "sg:phone":"+61 8 9581 4482",
    "sg:postcode":"6210",
    "sg:province":"WA",
    "sg:tags":[
        "title",
        "management",
        "stratum"
    ],
    "wof:name":"Riverglades Resort",
    "wof:placetype":"venue"
},
  "geometry": {"coordinates":[115.770889,-32.546013],"type":"Point"}
}