{
  "type": "Feature",
  "properties": {
    "addr:full":"Factory 1/23- 25 Brighton Rd Dandenong VIC 3175",
    "addr:housenumber":"/;25",
    "addr:postcode":"3175",
    "addr:street":"23;Brighton Rd",
    "iso:country":"AU",
    "sg:address":"Factory 1/23- 25 Brighton Rd",
    "sg:city":"Dandenong",
    "sg:classifiers":[
        {
            "category":"Government",
            "subcategory":"Fire Station",
            "type":"Public Place"
        }
    ],
    "sg:phone":"+61 3 9794 7665",
    "sg:postcode":"3175",
    "sg:province":"VIC",
    "sg:tags":[
        "spring",
        "shock",
        "absorbers",
        "suspension"
    ],
    "wof:name":"Mr Muffler Shockers",
    "wof:placetype":"venue"
},
  "geometry": {"coordinates":[145.20106506400001,-37.9900016785],"type":"Point"}
}