{
  "type": "Feature",
  "properties": {
    "addr:full":"1st Floor 75 Rosstown Rd Carnegie VIC 3163",
    "addr:housenumber":"75",
    "addr:postcode":"3163",
    "addr:street":"Rosstown Rd",
    "iso:country":"AU",
    "sg:address":"1st Floor 75 Rosstown Rd",
    "sg:city":"Carnegie",
    "sg:classifiers":[
        {
            "category":"Personal",
            "type":"Services"
        }
    ],
    "sg:phone":"+61 3 9571 8151",
    "sg:postcode":"3163",
    "sg:province":"VIC",
    "sg:tags":[
        "introduction",
        "social"
    ],
    "wof:name":"Father Glover Happiness For Life",
    "wof:placetype":"venue"
},
  "geometry": {"coordinates":[145.05752563499999,-37.8862533569],"type":"Point"}
}