{
  "type": "Feature",
  "properties": {
    "addr:full":"Shop 31, Belmont Forum Cnr Belmont Ave & Wright St Cloverdale WA 6105",
    "addr:housenumber":"shop 31",
    "addr:postcode":"6105",
    "addr:street":"Belmont Forum Cnr Belmont Ave & Wright St",
    "iso:country":"AU",
    "sg:address":"Shop 31, Belmont Forum Cnr Belmont Ave & Wright St",
    "sg:city":"Cloverdale",
    "sg:classifiers":[
        {
            "category":"Personal",
            "subcategory":"Beauty Salon",
            "type":"Services"
        }
    ],
    "sg:phone":"+61 8 9277 6933",
    "sg:postcode":"6105",
    "sg:province":"WA",
    "sg:tags":[
        "hairdresser"
    ],
    "wof:name":"Price Attack",
    "wof:placetype":"venue"
},
  "geometry": {"coordinates":[115.93450164799999,-31.9653282166],"type":"Point"}
}