{
  "type": "Feature",
  "properties": {
    "addr:full":"122 Armstrong St Ballarat North VIC 3350",
    "addr:housenumber":"122",
    "addr:postcode":"3350",
    "addr:street":"Armstrong St",
    "iso:country":"AU",
    "sg:address":"122 Armstrong St",
    "sg:city":"Ballarat North",
    "sg:classifiers":[
        {
            "category":"Real Estate",
            "subcategory":"Architect",
            "type":"Services"
        }
    ],
    "sg:phone":"+61 3 5331 4333",
    "sg:postcode":"3350",
    "sg:province":"VIC",
    "sg:tags":[
        "building",
        "designer"
    ],
    "wof:name":"Stephen Green & Associates Pty Ltd",
    "wof:placetype":"venue"
},
  "geometry": {"coordinates":[143.855423,-37.565403],"type":"Point"}
}