{
  "type": "Feature",
  "properties": {
    "addr:full":"10 Kestrel Crs Peregian Beach QLD 4573",
    "addr:housenumber":"10",
    "addr:postcode":"4573",
    "addr:street":"Kestrel Crs",
    "iso:country":"AU",
    "sg:address":"10 Kestrel Crs",
    "sg:city":"Peregian Beach",
    "sg:classifiers":[
        {
            "category":"Professional",
            "subcategory":"Printing & Photocopies",
            "type":"Services"
        }
    ],
    "sg:phone":"+61 7 5471 3389",
    "sg:postcode":"4573",
    "sg:province":"QLD",
    "sg:tags":[
        "publishing",
        "desktop"
    ],
    "wof:name":"Coast Creative",
    "wof:placetype":"venue"
},
  "geometry": {"coordinates":[153.095215,-26.47817],"type":"Point"}
}