{
  "type": "Feature",
  "properties": {
    "addr:full":"2 Clements St Guildford NSW 2161",
    "addr:housenumber":"2",
    "addr:postcode":"2161",
    "addr:street":"Clements St",
    "iso:country":"AU",
    "sg:address":"2 Clements St",
    "sg:city":"Guildford",
    "sg:classifiers":[
        {
            "category":"Building & Trades",
            "subcategory":"Construction",
            "type":"Services"
        }
    ],
    "sg:phone":"+61 2 9681 1676",
    "sg:postcode":"2161",
    "sg:province":"NSW",
    "sg:tags":[
        "contractor"
    ],
    "wof:name":"Len Stephens",
    "wof:placetype":"venue"
},
  "geometry": {"coordinates":[150.977386475,-33.8581542969],"type":"Point"}
}