{
  "type": "Feature",
  "properties": {
    "addr:full":"2 Damask Pl Niddrie VIC 3042",
    "addr:housenumber":"2",
    "addr:postcode":"3042",
    "addr:street":"Damask Pl",
    "iso:country":"AU",
    "sg:address":"2 Damask Pl",
    "sg:city":"Niddrie",
    "sg:classifiers":[
        {
            "category":"Utilities",
            "subcategory":"Electric",
            "type":"Services"
        }
    ],
    "sg:phone":"+61 3 9331 2554",
    "sg:postcode":"3042",
    "sg:province":"VIC",
    "sg:tags":[
        "electrical",
        "contractor"
    ],
    "wof:name":"S. Baxter Electrical Services",
    "wof:placetype":"venue"
},
  "geometry": {"coordinates":[144.88194274899999,-37.746673584],"type":"Point"}
}