{
  "type": "Feature",
  "properties": {
    "addr:full":"145A New Town Rd New Town TAS 7008",
    "addr:housenumber":"145a",
    "addr:postcode":"7008",
    "addr:street":"New Town Rd",
    "iso:country":"AU",
    "sg:address":"145A New Town Rd",
    "sg:city":"New Town",
    "sg:classifiers":[
        {
            "category":"Professional",
            "subcategory":"Accounting & Tax Preparation",
            "type":"Services"
        }
    ],
    "sg:phone":"+61 3 6278 1303",
    "sg:postcode":"7008",
    "sg:province":"TAS",
    "sg:tags":[
        "jukebox"
    ],
    "wof:name":"B & M Coin Amusements",
    "wof:placetype":"venue"
},
  "geometry": {"coordinates":[147.30586242699999,-42.859375],"type":"Point"}
}