{
  "type": "Feature",
  "properties": {
    "iso:country":"AU",
    "sg:address":"446 Elizabeth St",
    "sg:city":"North Hobart",
    "sg:classifiers":[
        {
            "category":"Government",
            "subcategory":"Court House",
            "type":"Public Place"
        }
    ],
    "sg:phone":"+61 3 6231 9022",
    "sg:postcode":"7000",
    "sg:province":"TAS",
    "sg:tags":[
        "personal",
        "marriage",
        "family",
        "counselling"
    ],
    "wof:name":"Reconnect (Family Reconnection Service)",
    "wof:placetype":"venue"
},
  "geometry": {"coordinates":[147.311676025,-42.8704376221],"type":"Point"}
}