{
  "type": "Feature",
  "properties": {
    "iso:country":"AU",
    "sg:address":"135- 157 Watton St",
    "sg:city":"Werribee",
    "sg:classifiers":[
        {
            "category":"Food & Beverages",
            "subcategory":"Liquor & Beverages",
            "type":"Retail Goods"
        }
    ],
    "sg:phone":"+61 3 9741 6006",
    "sg:postcode":"3030",
    "sg:province":"VIC",
    "sg:tags":[
        "store"
    ],
    "wof:name":"Liquorland",
    "wof:placetype":"venue"
},
  "geometry": {"coordinates":[144.658463,-37.903027],"type":"Point"}
}