{
  "type": "Feature",
  "properties": {
    "addr:full":"31 Redesdale Rd Kyneton VIC 3444",
    "addr:housenumber":"31",
    "addr:postcode":"3444",
    "addr:street":"Redesdale Rd",
    "iso:country":"AU",
    "sg:address":"31 Redesdale Rd",
    "sg:city":"Kyneton",
    "sg:classifiers":[
        {
            "category":"Utilities",
            "subcategory":"Electric",
            "type":"Services"
        }
    ],
    "sg:phone":"+61 3 5422 2182",
    "sg:postcode":"3444",
    "sg:province":"VIC",
    "sg:tags":[
        "electrical",
        "contractor"
    ],
    "wof:name":"Macedon Ranges Electrics",
    "wof:placetype":"venue"
},
  "geometry": {"coordinates":[144.45338439899999,-37.2349052429],"type":"Point"}
}