{
  "type": "Feature",
  "properties": {
    "addr:full":"Cnr Main Drv & Commerce Ave Warana QLD 4575",
    "addr:postcode":"4575",
    "addr:street":"Cnr Main Drv & Commerce Ave",
    "iso:country":"AU",
    "sg:address":"Cnr Main Drv & Commerce Ave",
    "sg:city":"Warana",
    "sg:classifiers":[
        {
            "category":"Banks & Credit Unions",
            "subcategory":"Bureau De Change",
            "type":"Services"
        }
    ],
    "sg:phone":"+61 7 5493 2088",
    "sg:postcode":"4575",
    "sg:province":"QLD",
    "sg:tags":[
        "supply",
        "equipment",
        "beating",
        "panel"
    ],
    "wof:name":"Queensland Paint Supplies (Sunshine Coast)",
    "wof:placetype":"venue"
},
  "geometry": {"coordinates":[153.12806699999999,-26.729326],"type":"Point"}
}