{
  "type": "Feature",
  "properties": {
    "addr:full":"406 Scarborough Beach Rd Osborne Park WA 6017",
    "addr:housenumber":"406",
    "addr:postcode":"6017",
    "addr:street":"Scarborough Beach Rd",
    "iso:country":"AU",
    "sg:address":"406 Scarborough Beach Rd",
    "sg:city":"Osborne Park",
    "sg:classifiers":[
        {
            "category":"Home & Garden",
            "subcategory":"Carpets & Floor Coverings",
            "type":"Retail Goods"
        }
    ],
    "sg:phone":"+61 8 9242 1533",
    "sg:postcode":"6017",
    "sg:province":"WA",
    "sg:tags":[
        "tile",
        "wall"
    ],
    "wof:name":"Osborne Ceramic Centre",
    "wof:placetype":"venue"
},
  "geometry": {"coordinates":[115.81376648,-31.9098510742],"type":"Point"}
}