{
  "type": "Feature",
  "properties": {
    "addr:full":"64 York St Sydney NSW 2000",
    "addr:housenumber":"64",
    "addr:postcode":"2000",
    "addr:street":"York St",
    "iso:country":"AU",
    "sg:address":"64 York St",
    "sg:city":"Sydney",
    "sg:classifiers":[
        {
            "category":"Airline",
            "type":"Transportation"
        }
    ],
    "sg:phone":"+61 2 9244 2317",
    "sg:postcode":"2000",
    "sg:province":"NSW",
    "sg:tags":[
        "agent"
    ],
    "wof:name":"Alaska Airlines",
    "wof:placetype":"venue"
},
  "geometry": {"coordinates":[151.20639038100001,-33.8702278137],"type":"Point"}
}