{
  "type": "Feature",
  "properties": {
    "iso:country":"AU",
    "sg:address":"Shop 5 / 74 Kembla St",
    "sg:city":"Wollongong",
    "sg:classifiers":[
        {
            "category":"Banks & Credit Unions",
            "subcategory":"Financial Services",
            "type":"Services"
        }
    ],
    "sg:phone":"+61 2 4229 5455",
    "sg:postcode":"2500",
    "sg:province":"NSW",
    "sg:tags":[
        "loan",
        "finance",
        "mortgage"
    ],
    "wof:name":"RAMS Home Loans",
    "wof:placetype":"venue"
},
  "geometry": {"coordinates":[150.897324,-34.425243],"type":"Point"}
}