{
  "type": "Feature",
  "properties": {
    "addr:full":"32 Perrin Pl Salisbury QLD 4107",
    "addr:housenumber":"32",
    "addr:postcode":"4107",
    "addr:street":"Perrin Pl",
    "iso:country":"AU",
    "sg:address":"32 Perrin Pl",
    "sg:city":"Salisbury",
    "sg:classifiers":[
        {
            "category":"Manufacturing",
            "subcategory":"Electronics",
            "type":"Manufacturing & Wholesale Goods"
        }
    ],
    "sg:phone":"+61 7 3875 0400",
    "sg:postcode":"4107",
    "sg:province":"QLD",
    "sg:tags":[
        "wholesaler",
        "equipment",
        "part",
        "mfrs",
        "refrigeration"
    ],
    "wof:name":"Actrol Parts",
    "wof:placetype":"venue"
},
  "geometry": {"coordinates":[153.03118896500001,-27.5598945618],"type":"Point"}
}