{
  "type": "Feature",
  "properties": {
    "addr:full":"31 Dwyer St Wy Yung VIC 3875",
    "addr:housenumber":"31",
    "addr:postcode":"3875",
    "addr:street":"Dwyer St",
    "iso:country":"AU",
    "sg:address":"31 Dwyer St",
    "sg:city":"Wy Yung",
    "sg:classifiers":[
        {
            "category":"Building & Trades",
            "subcategory":"Plumbing",
            "type":"Services"
        }
    ],
    "sg:phone":"+61 406 784 017",
    "sg:postcode":"3875",
    "sg:province":"VIC",
    "sg:tags":[
        "plumber",
        "gasfitters"
    ],
    "wof:name":"Kris Brodribb Plumber & Gasfitter",
    "wof:placetype":"venue"
},
  "geometry": {"coordinates":[147.616134644,-37.8051948547],"type":"Point"}
}