{
  "type": "Feature",
  "properties": {
    "iso:country":"AU",
    "sg:address":"61 Epping Ave",
    "sg:city":"Eastwood",
    "sg:classifiers":[
        {
            "category":"Manufacturing",
            "subcategory":"Food",
            "type":"Manufacturing & Wholesale Goods"
        }
    ],
    "sg:phone":"+61 409 365 360",
    "sg:postcode":"2122",
    "sg:province":"NSW",
    "sg:tags":[
        "function",
        "catering"
    ],
    "wof:name":"Good Food By Bernadette",
    "wof:placetype":"venue"
},
  "geometry": {"coordinates":[151.07539367699999,-33.7826385498],"type":"Point"}
}