{
  "type": "Feature",
  "properties": {
    "iso:country":"AU",
    "sg:address":"Oleo Rd",
    "sg:city":"Yallunda Flat",
    "sg:classifiers":[
        {
            "category":"Farming",
            "subcategory":"Farm",
            "type":"Manufacturing & Wholesale Goods"
        }
    ],
    "sg:phone":"+61 8 8688 5006",
    "sg:postcode":"5607",
    "sg:province":"SA",
    "sg:tags":[
        "farmer"
    ],
    "wof:name":"Piper Bros A & K",
    "wof:placetype":"venue"
},
  "geometry": {"coordinates":[135.812271,-34.347542],"type":"Point"}
}