{
  "type": "Feature",
  "properties": {
    "addr:full":"McIvor River Rd Cooktown QLD 4895",
    "addr:postcode":"4895",
    "addr:street":"River Rd",
    "iso:country":"AU",
    "sg:address":"McIvor River Rd",
    "sg:city":"Cooktown",
    "sg:classifiers":[
        {
            "category":"Food & Beverages",
            "subcategory":"Groceries & Convenience Stores",
            "type":"Retail Goods"
        }
    ],
    "sg:phone":"+61 7 4069 5142",
    "sg:postcode":"4895",
    "sg:province":"QLD",
    "wof:name":"Marton Store",
    "wof:placetype":"venue"
},
  "geometry": {"coordinates":[145.249237061,-15.4774303436],"type":"Point"}
}