{
  "type": "Feature",
  "properties": {
    "iso:country":"AU",
    "sg:address":"5 Cunninggham St",
    "sg:city":"Moorebank",
    "sg:classifiers":[
        {
            "category":"Retail",
            "subcategory":"Auto Repair",
            "type":"Services"
        }
    ],
    "sg:phone":"+61 2 9600 9463",
    "sg:postcode":"2170",
    "sg:province":"NSW",
    "sg:tags":[
        "body",
        "builder",
        "motor"
    ],
    "wof:name":"Baker & Priem Tray Bodies",
    "wof:placetype":"venue"
},
  "geometry": {"coordinates":[150.937942505,-33.9343719482],"type":"Point"}
}