{
  "type": "Feature",
  "properties": {
    "addr:full":"165 Kingsford Smith Drv Melba ACT 2615",
    "addr:housenumber":"165",
    "addr:postcode":"2615",
    "addr:street":"Kingsford Smith Drv",
    "iso:country":"AU",
    "sg:address":"165 Kingsford Smith Drv",
    "sg:city":"Melba",
    "sg:classifiers":[
        {
            "category":"Banks & Credit Unions",
            "subcategory":"Financial Services",
            "type":"Services"
        }
    ],
    "sg:phone":"+61 2 6259 7099",
    "sg:postcode":"2615",
    "sg:province":"ACT",
    "sg:tags":[
        "financier"
    ],
    "wof:name":"Braddon John Management Pty Ltd",
    "wof:placetype":"venue"
},
  "geometry": {"coordinates":[149.059814453,-35.2030944824],"type":"Point"}
}