{
  "type": "Feature",
  "properties": {
    "addr:full":"138 Emu Bay Rd Deloraine TAS 7304",
    "addr:housenumber":"138",
    "addr:postcode":"7304",
    "addr:street":"Emu Bay Rd",
    "iso:country":"AU",
    "sg:address":"138 Emu Bay Rd",
    "sg:city":"Deloraine",
    "sg:classifiers":[
        {
            "category":"Building & Trades",
            "subcategory":"Equipment Rental",
            "type":"Services"
        }
    ],
    "sg:phone":"+61 3 6362 2377",
    "sg:postcode":"7304",
    "sg:province":"TAS",
    "sg:tags":[
        "crane",
        "hire"
    ],
    "wof:name":"Huett's Crane Hire",
    "wof:placetype":"venue"
},
  "geometry": {"coordinates":[146.64415,-41.521652],"type":"Point"}
}