{
  "type": "Feature",
  "properties": {
    "addr:full":"31a Churchill Park Drv Invermay TAS 7248",
    "addr:housenumber":"31a",
    "addr:postcode":"7248",
    "addr:street":"Churchill Park Drv",
    "iso:country":"AU",
    "sg:address":"31a Churchill Park Drv",
    "sg:city":"Invermay",
    "sg:classifiers":[
        {
            "category":"Food & Beverages",
            "subcategory":"Bakery",
            "type":"Retail Goods"
        }
    ],
    "sg:phone":"+61 3 6334 1100",
    "sg:postcode":"7248",
    "sg:province":"TAS",
    "sg:tags":[
        "baker"
    ],
    "wof:name":"Betta Pies",
    "wof:placetype":"venue"
},
  "geometry": {"coordinates":[147.1434021,-41.4176254272],"type":"Point"}
}