{
  "type": "Feature",
  "properties": {
    "addr:full":"54 McEvoy St Waterloo NSW 2017",
    "addr:housenumber":"54",
    "addr:postcode":"2017",
    "addr:street":"Mcevoy St",
    "iso:country":"AU",
    "sg:address":"54 McEvoy St",
    "sg:city":"Waterloo",
    "sg:classifiers":[
        {
            "category":"Manufacturing",
            "subcategory":"Printing",
            "type":"Manufacturing & Wholesale Goods"
        }
    ],
    "sg:phone":"+61 2 9319 4032",
    "sg:postcode":"2017",
    "sg:province":"NSW",
    "sg:tags":[
        "wholesaler",
        "mfrs",
        "greeting",
        "card"
    ],
    "wof:name":"Greeting Times",
    "wof:placetype":"venue"
},
  "geometry": {"coordinates":[151.20135498100001,-33.9015579224],"type":"Point"}
}