{
  "type": "Feature",
  "properties": {
    "addr:full":"Suite 7, Camden Village Court, 180 -186 Argyle Street Camden NSW 2570",
    "addr:housenumber":"180 -186",
    "addr:postcode":"2570",
    "addr:street":"Village;Argyle Street",
    "iso:country":"AU",
    "sg:address":"Suite 7, Camden Village Court, 180",
    "sg:city":"-186 Argyle Street Camden",
    "sg:classifiers":[
        {
            "category":"Professional",
            "subcategory":"Accounting & Tax Preparation",
            "type":"Services"
        }
    ],
    "sg:phone":"+61 2 4655 9247",
    "sg:postcode":"2570",
    "sg:province":"NSW",
    "sg:tags":[
        "consultant",
        "taxation"
    ],
    "wof:name":"Wards Accounting Group",
    "wof:placetype":"venue"
},
  "geometry": {"coordinates":[150.69380188,-34.0555648804],"type":"Point"}
}