{
  "type": "Feature",
  "properties": {
    "addr:full":"39 Farmers Ave Boddington WA 6390",
    "addr:housenumber":"39",
    "addr:postcode":"6390",
    "addr:street":"Farmers Ave",
    "iso:country":"AU",
    "sg:address":"39 Farmers Ave",
    "sg:city":"Boddington",
    "sg:classifiers":[
        {
            "category":"Retail",
            "subcategory":"Auto Repair",
            "type":"Services"
        }
    ],
    "sg:phone":"+61 8 9883 8206",
    "sg:postcode":"6390",
    "sg:province":"WA",
    "sg:tags":[
        "repairer",
        "motor",
        "engineer"
    ],
    "wof:name":"R B H Mechanical Services Pty Ltd",
    "wof:placetype":"venue"
},
  "geometry": {"coordinates":[116.458862305,-32.8087615967],"type":"Point"}
}