{
  "type": "Feature",
  "properties": {
    "addr:full":"Townsville Rd Ingham QLD 4850",
    "addr:postcode":"4850",
    "addr:street":"Townsville Rd",
    "iso:country":"AU",
    "sg:address":"Townsville Rd",
    "sg:city":"Ingham",
    "sg:classifiers":[
        {
            "category":"Autos & Motor Vehicles",
            "subcategory":"Fuel & Gas Station",
            "type":"Retail Goods"
        }
    ],
    "sg:phone":"+61 7 4776 3342",
    "sg:postcode":"4850",
    "sg:province":"QLD",
    "wof:name":"Andys Roadhouse",
    "wof:placetype":"venue"
},
  "geometry": {"coordinates":[146.154586792,-18.6509418488],"type":"Point"}
}