{
  "type": "Feature",
  "properties": {
    "addr:full":"Unit 2, 5 Elswick Pl Coffs Harbour NSW 2450",
    "addr:housenumber":"5",
    "addr:postcode":"2450",
    "addr:street":"Elswick Pl",
    "iso:country":"AU",
    "sg:address":"Unit 2, 5 Elswick Pl",
    "sg:city":"Coffs Harbour",
    "sg:classifiers":[
        {
            "category":"Wholesale",
            "subcategory":"Machinery & Supplies",
            "type":"Manufacturing & Wholesale Goods"
        }
    ],
    "sg:phone":"+61 2 6658 0599",
    "sg:postcode":"2450",
    "sg:province":"NSW",
    "sg:tags":[
        "equipment",
        "rustproofing"
    ],
    "wof:name":"Lanocote",
    "wof:placetype":"venue"
},
  "geometry": {"coordinates":[153.089035,-30.315544],"type":"Point"}
}