{
  "type": "Feature",
  "properties": {
    "addr:full":"172 Burwood Rd Hawthorn VIC 3122",
    "addr:housenumber":"172",
    "addr:postcode":"3122",
    "addr:street":"Burwood Rd",
    "iso:country":"AU",
    "sg:address":"172 Burwood Rd",
    "sg:city":"Hawthorn",
    "sg:classifiers":[
        {
            "category":"Professional",
            "subcategory":"Computer Services",
            "type":"Services"
        }
    ],
    "sg:phone":"+61 3 9819 2500",
    "sg:postcode":"3122",
    "sg:province":"VIC",
    "sg:tags":[
        "tele-communications",
        "consultant"
    ],
    "wof:name":"Talking Concepts",
    "wof:placetype":"venue"
},
  "geometry": {"coordinates":[145.028442383,-37.8219108582],"type":"Point"}
}