{
  "type": "Feature",
  "properties": {
    "iso:country":"AU",
    "sg:address":"PO Box 4605",
    "sg:city":"Knox City Centre",
    "sg:classifiers":[
        {
            "category":"Wholesale",
            "subcategory":"Painting Supplies",
            "type":"Manufacturing & Wholesale Goods"
        }
    ],
    "sg:phone":"+61 3 9801 8940",
    "sg:postcode":"3152",
    "sg:province":"VIC",
    "sg:tags":[
        "product",
        "cleaning"
    ],
    "wof:name":"Eastpoint Cleaning Supplies",
    "wof:placetype":"venue"
},
  "geometry": {"coordinates":[145.24118042000001,-37.8691291809],"type":"Point"}
}