{
  "type": "Feature",
  "properties": {
    "addr:full":"52 Buckingham St Surry Hills NSW 2010",
    "addr:housenumber":"52",
    "addr:postcode":"2010",
    "addr:street":"Buckingham St",
    "iso:country":"AU",
    "sg:address":"52 Buckingham St",
    "sg:city":"Surry Hills",
    "sg:classifiers":[
        {
            "category":"Organizations",
            "subcategory":"Labor Organization",
            "type":"Services"
        }
    ],
    "sg:phone":"+61 2 9698 2178",
    "sg:postcode":"2010",
    "sg:province":"NSW",
    "sg:tags":[
        "union"
    ],
    "wof:name":"Australian Institute Of Marine & Power Engineers",
    "wof:placetype":"venue"
},
  "geometry": {"coordinates":[151.20755004899999,-33.8877868652],"type":"Point"}
}