{
  "type": "Feature",
  "properties": {
    "addr:full":"68 Centre St South Casino NSW 2470",
    "addr:housenumber":"68",
    "addr:postcode":"2470",
    "addr:street":"Centre St South Casino",
    "iso:country":"AU",
    "sg:address":"68 Centre St",
    "sg:city":"South Casino",
    "sg:classifiers":[
        {
            "category":"Travel",
            "subcategory":"Hotels & Motels",
            "type":"Entertainment"
        }
    ],
    "sg:phone":"+61 2 6662 1110",
    "sg:postcode":"2470",
    "sg:province":"NSW",
    "sg:tags":[
        "pub"
    ],
    "wof:name":"Charcoal Inn",
    "wof:placetype":"venue"
},
  "geometry": {"coordinates":[153.04745483400001,-28.8560276031],"type":"Point"}
}