{
  "type": "Feature",
  "properties": {
    "iso:country":"AU",
    "sg:address":"39 Lawson St",
    "sg:city":"Sans Souci",
    "sg:classifiers":[
        {
            "category":"Autos & Motor Vehicles",
            "subcategory":"Boat Sales",
            "type":"Retail Goods"
        }
    ],
    "sg:phone":"+61 403 827 478",
    "sg:postcode":"2219",
    "sg:province":"NSW",
    "sg:tags":[
        "builder",
        "yacht",
        "repairer"
    ],
    "wof:name":"Armstrong Boatworks",
    "wof:placetype":"venue"
},
  "geometry": {"coordinates":[151.129364,-33.998775],"type":"Point"}
}