{
  "type": "Feature",
  "properties": {
    "addr:full":"7 Beck St Dernancourt SA 5075",
    "addr:housenumber":"7",
    "addr:postcode":"5075",
    "addr:street":"Beck St",
    "iso:country":"AU",
    "sg:address":"7 Beck St",
    "sg:city":"Dernancourt",
    "sg:classifiers":[
        {
            "category":"Utilities",
            "subcategory":"Natural Gas",
            "type":"Services"
        }
    ],
    "sg:phone":"+61 8 8261 6197",
    "sg:postcode":"5075",
    "sg:province":"SA",
    "sg:tags":[
        "solid",
        "plasterer"
    ],
    "wof:name":"Adelaide Plastering Contractors",
    "wof:placetype":"venue"
},
  "geometry": {"coordinates":[138.66990661599999,-34.8589744568],"type":"Point"}
}