{
  "type": "Feature",
  "properties": {
    "addr:full":"33 Hackney Rd Hackney SA 5069",
    "addr:housenumber":"33",
    "addr:postcode":"5069",
    "addr:street":"Hackney Rd",
    "iso:country":"AU",
    "sg:address":"33 Hackney Rd",
    "sg:city":"Hackney",
    "sg:classifiers":[
        {
            "category":"Health Services",
            "subcategory":"Doctor",
            "type":"Services"
        }
    ],
    "sg:phone":"+61 8 8363 0833",
    "sg:postcode":"5069",
    "sg:province":"SA",
    "sg:tags":[
        "medical",
        "practitioner"
    ],
    "wof:name":"Tham S K",
    "wof:placetype":"venue"
},
  "geometry": {"coordinates":[138.61480712900001,-34.9169616699],"type":"Point"}
}