{
  "type": "Feature",
  "properties": {
    "iso:country":"AU",
    "sg:address":"9 Thorn St",
    "sg:city":"Toronto",
    "sg:classifiers":[
        {
            "category":"Organizations",
            "subcategory":"Community Association",
            "type":"Services"
        }
    ],
    "sg:phone":"+61 2 4959 6980",
    "sg:postcode":"2283",
    "sg:province":"NSW",
    "sg:tags":[
        "organisation",
        "family",
        "welfare"
    ],
    "wof:name":"Westlakes Community Transport Association Incorporated",
    "wof:placetype":"venue"
},
  "geometry": {"coordinates":[151.592285156,-33.0118331909],"type":"Point"}
}