{
  "type": "Feature",
  "properties": {
    "addr:full":"445 High St Maitland NSW 2320",
    "addr:housenumber":"445",
    "addr:postcode":"2320",
    "addr:street":"High St",
    "iso:country":"AU",
    "sg:address":"445 High St",
    "sg:city":"Maitland",
    "sg:classifiers":[
        {
            "category":"Real Estate",
            "subcategory":"Real Estate Agent",
            "type":"Services"
        }
    ],
    "sg:phone":"+61 2 4933 6600",
    "sg:postcode":"2320",
    "sg:province":"NSW",
    "wof:name":"Idstein J.P. & Co. Pty Ltd",
    "wof:placetype":"venue"
},
  "geometry": {"coordinates":[151.55430602999999,-32.7319068909],"type":"Point"}
}