{
  "type": "Feature",
  "properties": {
    "addr:full":"952 Mt Alexander Rd Essendon VIC 3040",
    "addr:housenumber":"952",
    "addr:postcode":"3040",
    "addr:street":"Mt Alexander Rd",
    "iso:country":"AU",
    "sg:address":"952 Mt Alexander Rd",
    "sg:city":"Essendon",
    "sg:classifiers":[
        {
            "category":"Professional",
            "subcategory":"Art Services",
            "type":"Services"
        }
    ],
    "sg:phone":"+61 3 9372 9288",
    "sg:postcode":"3040",
    "sg:province":"VIC",
    "sg:tags":[
        "interior",
        "decorator"
    ],
    "wof:name":"Moonee Furnishings Pty Ltd",
    "wof:placetype":"venue"
},
  "geometry": {"coordinates":[144.917312622,-37.7540931702],"type":"Point"}
}