{
  "type": "Feature",
  "properties": {
    "addr:full":"24 Darnick St Underwood QLD 4119",
    "addr:housenumber":"24",
    "addr:postcode":"4119",
    "addr:street":"Darnick St",
    "iso:country":"AU",
    "sg:address":"24 Darnick St",
    "sg:city":"Underwood",
    "sg:classifiers":[
        {
            "category":"Wholesale",
            "subcategory":"Machinery & Supplies",
            "type":"Manufacturing & Wholesale Goods"
        }
    ],
    "sg:phone":"+61 7 3341 5222",
    "sg:postcode":"4119",
    "sg:province":"QLD",
    "sg:tags":[
        "electroplating"
    ],
    "wof:name":"Helios Electroheat Pty Ltd",
    "wof:placetype":"venue"
},
  "geometry": {"coordinates":[153.11236572300001,-27.6064605713],"type":"Point"}
}