{
  "type": "Feature",
  "properties": {
    "addr:full":"30A Brewer Rd Bentleigh VIC 3204",
    "addr:housenumber":"30a",
    "addr:postcode":"3204",
    "addr:street":"Brewer Rd",
    "iso:country":"AU",
    "sg:address":"30A Brewer Rd",
    "sg:city":"Bentleigh",
    "sg:classifiers":[
        {
            "category":"Building & Trades",
            "subcategory":"Construction",
            "type":"Services"
        }
    ],
    "sg:phone":"+61 3 9576 5511",
    "sg:postcode":"3204",
    "sg:province":"VIC",
    "sg:tags":[
        "pool",
        "swimming"
    ],
    "wof:name":"Brighton Pools Spas & Landscaping",
    "wof:placetype":"venue"
},
  "geometry": {"coordinates":[145.026566,-37.920944],"type":"Point"}
}