{
  "type": "Feature",
  "properties": {
    "addr:full":"2 Jacana Ave Bribie Island QLD 4507",
    "addr:housenumber":"2",
    "addr:postcode":"4507",
    "addr:street":"Jacana Ave Bribie",
    "iso:country":"AU",
    "sg:address":"2 Jacana Ave",
    "sg:city":"Bribie Island",
    "sg:classifiers":[
        {
            "category":"Real Estate",
            "subcategory":"Real Estate Agent",
            "type":"Services"
        }
    ],
    "sg:phone":"+61 7 3408 2700",
    "sg:postcode":"4507",
    "sg:province":"QLD",
    "wof:name":"Bribie Ocean Beach Realty",
    "wof:placetype":"venue"
},
  "geometry": {"coordinates":[153.20271301299999,-27.0699272156],"type":"Point"}
}