{
  "type": "Feature",
  "properties": {
    "addr:full":"3 Bottlebrush Drv Mill Park VIC 3082",
    "addr:housenumber":"3",
    "addr:postcode":"3082",
    "addr:street":"Bottlebrush Drv",
    "iso:country":"AU",
    "sg:address":"3 Bottlebrush Drv",
    "sg:city":"Mill Park",
    "sg:classifiers":[
        {
            "category":"Building & Trades",
            "subcategory":"Construction",
            "type":"Services"
        }
    ],
    "sg:phone":"+61 419 517 319",
    "sg:postcode":"3082",
    "sg:province":"VIC",
    "sg:tags":[
        "contractor"
    ],
    "wof:name":"Kama Homes",
    "wof:placetype":"venue"
},
  "geometry": {"coordinates":[145.074829102,-37.6616172791],"type":"Point"}
}