{
  "type": "Feature",
  "properties": {
    "addr:full":"343 Fenlon Ave North Rockhampton QLD 4701",
    "addr:housenumber":"343",
    "addr:postcode":"4701",
    "addr:street":"Fenlon Ave North",
    "iso:country":"AU",
    "sg:address":"343 Fenlon Ave",
    "sg:city":"North Rockhampton",
    "sg:classifiers":[
        {
            "category":"Utilities",
            "subcategory":"Electric",
            "type":"Services"
        }
    ],
    "sg:phone":"+61 7 4926 1141",
    "sg:postcode":"4701",
    "sg:province":"QLD",
    "sg:tags":[
        "electrical",
        "contractor"
    ],
    "wof:name":"Rowland K & L Electrical",
    "wof:placetype":"venue"
},
  "geometry": {"coordinates":[150.54539489699999,-23.3525218964],"type":"Point"}
}