{
  "type": "Feature",
  "properties": {
    "iso:country":"AU",
    "sg:address":"175 Stanley St",
    "sg:city":"West Melbourne",
    "sg:classifiers":[
        {
            "category":"Professional",
            "subcategory":"Employment Agencies",
            "type":"Services"
        }
    ],
    "sg:phone":"+61 3 9600 9122",
    "sg:postcode":"3003",
    "sg:province":"VIC",
    "sg:tags":[
        "vic",
        "escort"
    ],
    "wof:name":"Thirty Something Escorts",
    "wof:placetype":"venue"
},
  "geometry": {"coordinates":[144.94642639200001,-37.8100204468],"type":"Point"}
}