{
  "type": "Feature",
  "properties": {
    "addr:full":"15/ 222 Headland Rd Dee Why NSW 2099",
    "addr:housenumber":"15 / 222",
    "addr:postcode":"2099",
    "addr:street":"Headland Rd",
    "iso:country":"AU",
    "sg:address":"15/ 222 Headland Rd",
    "sg:city":"Dee Why",
    "sg:classifiers":[
        {
            "category":"Retail",
            "subcategory":"Auto Repair",
            "type":"Services"
        }
    ],
    "sg:phone":"+61 2 9905 1455",
    "sg:postcode":"2099",
    "sg:province":"NSW",
    "sg:tags":[
        "repairer",
        "motor",
        "engineer"
    ],
    "wof:name":"Autohaus Hamilton Pty Ltd",
    "wof:placetype":"venue"
},
  "geometry": {"coordinates":[151.282150269,-33.7599182129],"type":"Point"}
}