{
  "type": "Feature",
  "properties": {
    "addr:full":"15 Calder St Geelong West VIC 3218",
    "addr:housenumber":"15",
    "addr:postcode":"3218",
    "addr:street":"Calder St",
    "iso:country":"AU",
    "sg:address":"15 Calder St",
    "sg:city":"Geelong West",
    "sg:classifiers":[
        {
            "category":"Wholesale",
            "subcategory":"Scrap",
            "type":"Manufacturing & Wholesale Goods"
        }
    ],
    "sg:phone":"+61 3 5224 2566",
    "sg:postcode":"3218",
    "sg:province":"VIC",
    "sg:tags":[
        "merchant",
        "metal"
    ],
    "wof:name":"A-Class Towing",
    "wof:placetype":"venue"
},
  "geometry": {"coordinates":[144.33419799800001,-38.1442985535],"type":"Point"}
}