{
  "type": "Feature",
  "properties": {
    "iso:country":"AU",
    "sg:address":"11 Benson Crt",
    "sg:city":"Riverside",
    "sg:classifiers":[
        {
            "category":"Manufacturing",
            "subcategory":"Glass & Minerals",
            "type":"Manufacturing & Wholesale Goods"
        }
    ],
    "sg:phone":"+61 409 974 605",
    "sg:postcode":"7250",
    "sg:province":"TAS",
    "sg:tags":[
        "stained"
    ],
    "wof:name":"Abraham Glass",
    "wof:placetype":"venue"
},
  "geometry": {"coordinates":[147.11978149399999,-41.4323005676],"type":"Point"}
}