{
  "type": "Feature",
  "properties": {
    "addr:full":"PO Box 3361 Norman Park QLD 4170",
    "addr:postcode":"4170",
    "iso:country":"AU",
    "sg:address":"PO Box 3361",
    "sg:city":"Norman Park",
    "sg:classifiers":[
        {
            "category":"Utilities",
            "subcategory":"Mobile Phone",
            "type":"Services"
        }
    ],
    "sg:phone":"+61 414 305 314",
    "sg:postcode":"4170",
    "sg:province":"QLD",
    "sg:tags":[
        "repair",
        "telephone"
    ],
    "wof:name":"A1 LCD Mobile Phone Repairs",
    "wof:placetype":"venue"
},
  "geometry": {"coordinates":[153.05592346200001,-27.4741001129],"type":"Point"}
}