{
  "type": "Feature",
  "properties": {
    "addr:full":"Purves Rd Arthurs Seat VIC 3936",
    "addr:postcode":"3936",
    "addr:street":"Purves Rd",
    "iso:country":"AU",
    "sg:address":"Purves Rd",
    "sg:city":"Arthurs Seat",
    "sg:classifiers":[
        {
            "category":"Farming",
            "subcategory":"Livestock Farm",
            "type":"Manufacturing & Wholesale Goods"
        }
    ],
    "sg:phone":"+61 3 5989 2766",
    "sg:postcode":"3936",
    "sg:province":"VIC",
    "sg:tags":[
        "agistment"
    ],
    "wof:name":"Arthur's Seat Riding Schools",
    "wof:placetype":"venue"
},
  "geometry": {"coordinates":[144.950271606,-38.3550872803],"type":"Point"}
}