{
  "type": "Feature",
  "properties": {
    "addr:full":"93 Gilbert St Latrobe TAS 7307",
    "addr:housenumber":"93",
    "addr:postcode":"7307",
    "addr:street":"Gilbert St",
    "iso:country":"AU",
    "sg:address":"93 Gilbert St",
    "sg:city":"Latrobe",
    "sg:classifiers":[
        {
            "category":"Shopping",
            "subcategory":"Antiques",
            "type":"Retail Goods"
        }
    ],
    "sg:phone":"+61 3 6426 1006",
    "sg:postcode":"7307",
    "sg:province":"TAS",
    "wof:name":"Bells Parade Antiques",
    "wof:placetype":"venue"
},
  "geometry": {"coordinates":[146.41023300000001,-41.235241],"type":"Point"}
}