{
  "type": "Feature",
  "properties": {
    "addr:full":"31a Victoria St Ulverstone TAS 7315",
    "addr:housenumber":"31a",
    "addr:postcode":"7315",
    "addr:street":"Victoria St",
    "iso:country":"AU",
    "sg:address":"31a Victoria St",
    "sg:city":"Ulverstone",
    "sg:classifiers":[
        {
            "category":"Manufacturing",
            "subcategory":"Signs",
            "type":"Manufacturing & Wholesale Goods"
        }
    ],
    "sg:phone":"+61 407 300 322",
    "sg:postcode":"7315",
    "sg:province":"TAS",
    "sg:tags":[
        "traffic",
        "safety"
    ],
    "wof:name":"Max Deverell Signs",
    "wof:placetype":"venue"
},
  "geometry": {"coordinates":[146.16685485799999,-41.154384613],"type":"Point"}
}