{
  "type": "Feature",
  "properties": {
    "addr:full":"Shop 1, 729 The Entrance Rd Wamberal NSW 2260",
    "addr:housenumber":"shop 1 729",
    "addr:postcode":"2260",
    "addr:street":"The Entrance Rd",
    "iso:country":"AU",
    "sg:address":"Shop 1, 729 The Entrance Rd",
    "sg:city":"Wamberal",
    "sg:classifiers":[
        {
            "category":"Personal",
            "subcategory":"Beauty Salon",
            "type":"Services"
        }
    ],
    "sg:phone":"+61 2 4384 3307",
    "sg:postcode":"2260",
    "sg:province":"NSW",
    "wof:name":"Flawless Beauty",
    "wof:placetype":"venue"
},
  "geometry": {"coordinates":[151.43847700000001,-33.422611],"type":"Point"}
}