{
  "type": "Feature",
  "properties": {
    "iso:country":"AU",
    "sg:address":"19 Hereford St",
    "sg:city":"Berkeley Vale",
    "sg:classifiers":[
        {
            "category":"Utilities",
            "subcategory":"Refuse",
            "type":"Services"
        }
    ],
    "sg:phone":"+61 2 4389 2094",
    "sg:postcode":"2261",
    "sg:province":"NSW",
    "sg:tags":[
        "incinerator"
    ],
    "wof:name":"Universal Incinerators Australia",
    "wof:placetype":"venue"
},
  "geometry": {"coordinates":[151.424866,-33.325237],"type":"Point"}
}