{
  "type": "Feature",
  "properties": {
    "iso:country":"AU",
    "sg:address":"33 Little Bridge St",
    "sg:city":"Ballarat",
    "sg:classifiers":[
        {
            "category":"Banks & Credit Unions",
            "subcategory":"Financial Services",
            "type":"Services"
        }
    ],
    "sg:phone":"+61 3 5333 3255",
    "sg:postcode":"3350",
    "sg:province":"VIC",
    "sg:tags":[
        "financier"
    ],
    "wof:name":"City Finance Loans & Cash Solutions",
    "wof:placetype":"venue"
},
  "geometry": {"coordinates":[143.861526,-37.563072],"type":"Point"}
}