{
  "type": "Feature",
  "properties": {
    "addr:full":"42 Lovel St Katoomba NSW 2780",
    "addr:housenumber":"42",
    "addr:postcode":"2780",
    "addr:street":"Lovel St",
    "iso:country":"AU",
    "sg:address":"42 Lovel St",
    "sg:city":"Katoomba",
    "sg:classifiers":[
        {
            "category":"Professional",
            "subcategory":"Art Services",
            "type":"Services"
        }
    ],
    "sg:phone":"+61 2 4782 5889",
    "sg:postcode":"2780",
    "sg:province":"NSW",
    "sg:tags":[
        "interior",
        "decorator"
    ],
    "wof:name":"Q Interiors & Antiques",
    "wof:placetype":"venue"
},
  "geometry": {"coordinates":[150.31993102999999,-33.7136917114],"type":"Point"}
}