{
  "type": "Feature",
  "properties": {
    "addr:full":"2/ 4 Iron Bark Cl Warabrook NSW 2304",
    "addr:housenumber":"/ 4",
    "addr:postcode":"2304",
    "addr:street":"Iron Bark Cl",
    "iso:country":"AU",
    "sg:address":"2/ 4",
    "sg:city":"Iron Bark Cl Warabrook",
    "sg:classifiers":[
        {
            "category":"Communications",
            "type":"Services"
        }
    ],
    "sg:phone":"+61 2 4968 9577",
    "sg:postcode":"2304",
    "sg:province":"NSW",
    "sg:tags":[
        "data"
    ],
    "wof:name":"Phoenix Contact Pty Ltd",
    "wof:placetype":"venue"
},
  "geometry": {"coordinates":[151.71446227999999,-32.8858909607],"type":"Point"}
}