{
  "type": "Feature",
  "properties": {
    "addr:full":"3 Glen Eira Ave Ripponlea VIC 3185",
    "addr:housenumber":"3",
    "addr:postcode":"3185",
    "addr:street":"Glen;Ave",
    "iso:country":"AU",
    "sg:address":"3 Glen Eira Ave",
    "sg:city":"Ripponlea",
    "sg:classifiers":[
        {
            "category":"Personal",
            "subcategory":"Massage",
            "type":"Services"
        }
    ],
    "sg:phone":"+61 3 9523 9592",
    "sg:postcode":"3185",
    "sg:province":"VIC",
    "sg:tags":[
        "therapy"
    ],
    "wof:name":"Michelle Sergas",
    "wof:placetype":"venue"
},
  "geometry": {"coordinates":[144.99554443400001,-37.8761520386],"type":"Point"}
}