{
  "type": "Feature",
  "properties": {
    "addr:full":"Unit 4, 205 Stirling Hwy Claremont WA 6010",
    "addr:housenumber":"205",
    "addr:postcode":"6010",
    "addr:street":"Stirling Hwy",
    "iso:country":"AU",
    "sg:address":"Unit 4, 205 Stirling Hwy",
    "sg:city":"Claremont",
    "sg:classifiers":[
        {
            "category":"Home & Garden",
            "subcategory":"Furniture",
            "type":"Retail Goods"
        }
    ],
    "sg:phone":"+61 8 9384 6628",
    "sg:postcode":"6010",
    "sg:province":"WA",
    "sg:tags":[
        "outdoor"
    ],
    "wof:name":"True North Furniture",
    "wof:placetype":"venue"
},
  "geometry": {"coordinates":[115.788391113,-31.9819793701],"type":"Point"}
}