{
  "type": "Feature",
  "properties": {
    "iso:country":"AU",
    "sg:address":"20 Kitchener St",
    "sg:city":"Coorparoo",
    "sg:classifiers":[
        {
            "category":"Real Estate",
            "subcategory":"Real Estate Agent",
            "type":"Services"
        }
    ],
    "sg:phone":"+61 422 126 007",
    "sg:postcode":"4151",
    "sg:province":"QLD",
    "wof:name":"Vicinity Realty",
    "wof:placetype":"venue"
},
  "geometry": {"coordinates":[153.059616089,-27.4928264618],"type":"Point"}
}