{
  "type": "Feature",
  "properties": {
    "addr:full":"459 Penshurst St East Roseville NSW 2069",
    "addr:housenumber":"459",
    "addr:postcode":"2069",
    "addr:street":"Penshurst St",
    "iso:country":"AU",
    "sg:address":"459 Penshurst St",
    "sg:city":"East Roseville",
    "sg:classifiers":[
        {
            "category":"Sports & Exercise",
            "subcategory":"Ski Slope",
            "type":"Entertainment"
        }
    ],
    "sg:phone":"+61 2 9417 8688",
    "sg:postcode":"2069",
    "sg:province":"NSW",
    "sg:tags":[
        "equipment",
        "hire",
        "retail",
        "snow"
    ],
    "wof:name":"A Ark Ski Shop",
    "wof:placetype":"venue"
},
  "geometry": {"coordinates":[151.191772461,-33.7837677002],"type":"Point"}
}