{
  "type": "Feature",
  "properties": {
    "addr:full":"457 Chapel St South Yarra VIC 3141",
    "addr:housenumber":"457",
    "addr:postcode":"3141",
    "addr:street":"Chapel St",
    "iso:country":"AU",
    "sg:address":"457 Chapel St",
    "sg:city":"South Yarra",
    "sg:classifiers":[
        {
            "category":"Shopping",
            "subcategory":"Clothing, Apparel, & Fashions",
            "type":"Retail Goods"
        }
    ],
    "sg:phone":"+61 3 9827 6233",
    "sg:postcode":"3141",
    "sg:province":"VIC",
    "sg:tags":[
        "jean"
    ],
    "wof:name":"GASP Jeans",
    "wof:placetype":"venue"
},
  "geometry": {"coordinates":[144.994598389,-37.843711853],"type":"Point"}
}