{
  "type": "Feature",
  "properties": {
    "addr:full":"32 Willoughby St Milsons Point NSW 2061",
    "addr:housenumber":"32",
    "addr:postcode":"2061",
    "addr:street":"Willoughby St",
    "iso:country":"AU",
    "sg:address":"32 Willoughby St",
    "sg:city":"Milsons Point",
    "sg:classifiers":[
        {
            "category":"Real Estate",
            "subcategory":"Architect",
            "type":"Services"
        }
    ],
    "sg:phone":"+61 2 9954 4404",
    "sg:postcode":"2061",
    "sg:province":"NSW",
    "wof:name":"Chappelow & Associates Pty Ltd",
    "wof:placetype":"venue"
},
  "geometry": {"coordinates":[151.213012695,-33.8451766968],"type":"Point"}
}