{
  "type": "Feature",
  "properties": {
    "iso:country":"AU",
    "sg:address":"126 Moore St",
    "sg:city":"Hurstville",
    "sg:classifiers":[
        {
            "category":"Communications",
            "type":"Services"
        }
    ],
    "sg:phone":"+61 2 9594 5990",
    "sg:postcode":"2220",
    "sg:province":"NSW",
    "sg:tags":[
        "translation"
    ],
    "wof:name":"Active Language Solutions",
    "wof:placetype":"venue"
},
  "geometry": {"coordinates":[151.10003662099999,-33.9565658569],"type":"Point"}
}