{
  "type": "Feature",
  "properties": {
    "addr:full":"27 Barraclough Crs Monash ACT 2904",
    "addr:housenumber":"27",
    "addr:postcode":"2904",
    "addr:street":"Barraclough Crs",
    "iso:country":"AU",
    "sg:address":"27 Barraclough Crs",
    "sg:city":"Monash",
    "sg:classifiers":[
        {
            "category":"Health Services",
            "subcategory":"Doctor",
            "type":"Services"
        }
    ],
    "sg:phone":"+61 2 6291 0266",
    "sg:postcode":"2904",
    "sg:province":"ACT",
    "sg:tags":[
        "medical",
        "practitioner"
    ],
    "wof:name":"Brown J V",
    "wof:placetype":"venue"
},
  "geometry": {"coordinates":[149.092254639,-35.4151611328],"type":"Point"}
}