{
  "type": "Feature",
  "properties": {
    "addr:full":"4 Yalumba St Thornlands QLD 4164",
    "addr:housenumber":"4",
    "addr:postcode":"4164",
    "addr:street":"Yalumba St",
    "iso:country":"AU",
    "sg:address":"4 Yalumba St",
    "sg:city":"Thornlands",
    "sg:classifiers":[
        {
            "category":"Retail",
            "subcategory":"Repair Shop",
            "type":"Services"
        }
    ],
    "sg:phone":"+61 7 3206 1217",
    "sg:postcode":"4164",
    "sg:province":"QLD",
    "sg:tags":[
        "maintenance",
        "pool",
        "swimming"
    ],
    "wof:name":"Pool Tech",
    "wof:placetype":"venue"
},
  "geometry": {"coordinates":[153.25508117699999,-27.5600299835],"type":"Point"}
}