{
  "type": "Feature",
  "properties": {
    "iso:country":"AU",
    "sg:address":"19a Highett St",
    "sg:city":"Mansfield",
    "sg:classifiers":[
        {
            "category":"Shopping",
            "subcategory":"Clothing, Apparel, & Fashions",
            "type":"Retail Goods"
        }
    ],
    "sg:phone":"+61 3 5775 1057",
    "sg:postcode":"3722",
    "sg:province":"VIC",
    "sg:tags":[
        "lady",
        "wear"
    ],
    "wof:name":"Jabeta Creations",
    "wof:placetype":"venue"
},
  "geometry": {"coordinates":[146.087982178,-37.0513381958],"type":"Point"}
}