{
  "type": "Feature",
  "properties": {
    "addr:full":"601 Glebe Rd Adamstown NSW 2289",
    "addr:housenumber":"601",
    "addr:postcode":"2289",
    "addr:street":"Glebe Rd",
    "iso:country":"AU",
    "sg:address":"601 Glebe Rd",
    "sg:city":"Adamstown",
    "sg:classifiers":[
        {
            "category":"Shopping",
            "subcategory":"Clothing, Apparel, & Fashions",
            "type":"Retail Goods"
        }
    ],
    "sg:phone":"+61 2 4956 3838",
    "sg:postcode":"2289",
    "sg:province":"NSW",
    "sg:tags":[
        "lady",
        "wear"
    ],
    "wof:name":"Ellexa",
    "wof:placetype":"venue"
},
  "geometry": {"coordinates":[151.725662231,-32.9343185425],"type":"Point"}
}