{
  "type": "Feature",
  "properties": {
    "addr:full":"Fctry 2/ 25 Onslow Ave Campbellfield VIC 3061",
    "addr:housenumber":"2 / 25",
    "addr:postcode":"3061",
    "addr:street":"Fctry;Onslow Ave",
    "iso:country":"AU",
    "sg:address":"Fctry 2/ 25 Onslow Ave",
    "sg:city":"Campbellfield",
    "sg:classifiers":[
        {
            "category":"Autos & Motor Vehicles",
            "subcategory":"Auto Supplies",
            "type":"Retail Goods"
        }
    ],
    "sg:phone":"+61 403 047 748",
    "sg:postcode":"3061",
    "sg:province":"VIC",
    "sg:tags":[
        "electric"
    ],
    "wof:name":"Electric Motor & Geared Sales Pty Ltd",
    "wof:placetype":"venue"
},
  "geometry": {"coordinates":[144.96463012699999,-37.6875610352],"type":"Point"}
}