{
  "type": "Feature",
  "properties": {
    "addr:full":"80 Main St Penguin TAS 7316",
    "addr:housenumber":"80",
    "addr:postcode":"7316",
    "addr:street":"Main St",
    "iso:country":"AU",
    "sg:address":"80 Main St",
    "sg:city":"Penguin",
    "sg:classifiers":[
        {
            "category":"Government",
            "subcategory":"Post Office",
            "type":"Public Place"
        }
    ],
    "sg:phone":"+61 3 6437 2307",
    "sg:postcode":"7316",
    "sg:province":"TAS",
    "sg:tags":[
        "postal"
    ],
    "wof:name":"Australia Post",
    "wof:placetype":"venue"
},
  "geometry": {"coordinates":[146.0728302,-41.1139030457],"type":"Point"}
}