{
  "type": "Feature",
  "properties": {
    "iso:country":"AU",
    "sg:address":"Suite 1, 1-15 Rosebery Ave",
    "sg:city":"Rosebery",
    "sg:classifiers":[
        {
            "category":"Shopping",
            "subcategory":"Stationery & Office Supplies",
            "type":"Retail Goods"
        }
    ],
    "sg:phone":"+61 2 8345 6700",
    "sg:postcode":"2018",
    "sg:province":"NSW",
    "sg:tags":[
        "packaging",
        "material"
    ],
    "wof:name":"Alto Packaging Limited",
    "wof:placetype":"venue"
},
  "geometry": {"coordinates":[151.20735168499999,-33.9147911072],"type":"Point"}
}