{
  "type": "Feature",
  "properties": {
    "addr:full":"13 Arthur St Ballarat VIC 3350",
    "addr:housenumber":"13",
    "addr:postcode":"3350",
    "addr:street":"Arthur St",
    "iso:country":"AU",
    "sg:address":"13 Arthur St",
    "sg:city":"Ballarat",
    "sg:classifiers":[
        {
            "category":"Professional",
            "type":"Services"
        }
    ],
    "sg:phone":"+61 419 542 655",
    "sg:postcode":"3350",
    "sg:province":"VIC",
    "sg:tags":[
        "courier"
    ],
    "wof:name":"Rusty's Couriers",
    "wof:placetype":"venue"
},
  "geometry": {"coordinates":[143.81466699999999,-37.556759],"type":"Point"}
}