{
  "type": "Feature",
  "properties": {
    "iso:country":"AU",
    "sg:address":"13 Arthur St",
    "sg:city":"Ballarat",
    "sg:classifiers":[
        {
            "category":"Professional",
            "type":"Services"
        }
    ],
    "sg:phone":"+61 419 542 655",
    "sg:postcode":"3350",
    "sg:province":"VIC",
    "sg:tags":[
        "courier"
    ],
    "wof:name":"Rusty's Couriers",
    "wof:placetype":"venue"
},
  "geometry": {"coordinates":[143.814667,-37.556759],"type":"Point"}
}