{
  "type": "Feature",
  "properties": {
    "addr:full":"Shop 8 78 Brisbane St Ipswich QLD 4305",
    "addr:housenumber":"shop;78",
    "addr:postcode":"4305",
    "addr:street":"Brisbane St",
    "iso:country":"AU",
    "sg:address":"Shop 8 78 Brisbane St",
    "sg:city":"Ipswich",
    "sg:classifiers":[
        {
            "category":"Personal",
            "subcategory":"Beauty Salon",
            "type":"Services"
        }
    ],
    "sg:phone":"+61 7 3281 3923",
    "sg:postcode":"4305",
    "sg:province":"QLD",
    "sg:tags":[
        "hairdresser"
    ],
    "wof:name":"Louella's Hair Studio",
    "wof:placetype":"venue"
},
  "geometry": {"coordinates":[152.76071167000001,-27.614654541],"type":"Point"}
}