{
  "type": "Feature",
  "properties": {
    "addr:full":"5 Cambro Rd Clayton VIC 3168",
    "addr:housenumber":"5",
    "addr:postcode":"3168",
    "addr:street":"Cambro Rd",
    "iso:country":"AU",
    "sg:address":"5 Cambro Rd",
    "sg:city":"Clayton",
    "sg:classifiers":[
        {
            "category":"Freight",
            "type":"Transportation"
        }
    ],
    "sg:phone":"+61 412 156 702",
    "sg:postcode":"3168",
    "sg:province":"VIC",
    "sg:tags":[
        "car",
        "carrier",
        "transporting"
    ],
    "wof:name":"Bullys Car Freight Service",
    "wof:placetype":"venue"
},
  "geometry": {"coordinates":[145.14213562,-37.9172286987],"type":"Point"}
}