{
  "type": "Feature",
  "properties": {
    "addr:full":"Kingaroy St Kingaroy QLD 4610",
    "addr:postcode":"4610",
    "addr:street":"Kingaroy St",
    "iso:country":"AU",
    "sg:address":"Kingaroy St",
    "sg:city":"Kingaroy",
    "sg:classifiers":[
        {
            "category":"Autos & Motor Vehicles",
            "subcategory":"Fuel & Gas Station",
            "type":"Retail Goods"
        }
    ],
    "sg:phone":"+61 7 4162 1928",
    "sg:postcode":"4610",
    "sg:province":"QLD",
    "wof:name":"BP Australia Limited",
    "wof:placetype":"venue"
},
  "geometry": {"coordinates":[151.83883667000001,-26.5438289642],"type":"Point"}
}