{
  "type": "Feature",
  "properties": {
    "addr:full":"Picola North Rd Picola VIC 3639",
    "addr:postcode":"3639",
    "addr:street":"North Rd",
    "iso:country":"AU",
    "sg:address":"Picola North Rd",
    "sg:city":"Picola",
    "sg:classifiers":[
        {
            "category":"Arena",
            "subcategory":"Sports Club",
            "type":"Entertainment"
        }
    ],
    "sg:phone":"+61 3 5869 1370",
    "sg:postcode":"3639",
    "sg:province":"VIC",
    "sg:tags":[
        "australian",
        "football",
        "rule"
    ],
    "wof:name":"Picola United Football Club",
    "wof:placetype":"venue"
},
  "geometry": {"coordinates":[145.10890197800001,-35.9984855652],"type":"Point"}
}