{
  "type": "Feature",
  "properties": {
    "addr:full":"14 Fisher St Belmont WA 6104",
    "addr:housenumber":"14",
    "addr:postcode":"6104",
    "addr:street":"Fisher St",
    "iso:country":"AU",
    "sg:address":"14 Fisher St",
    "sg:city":"Belmont",
    "sg:classifiers":[
        {
            "category":"Home & Garden",
            "subcategory":"Garden Supply",
            "type":"Retail Goods"
        }
    ],
    "sg:phone":"+61 8 9277 9377",
    "sg:postcode":"6104",
    "sg:province":"WA",
    "sg:tags":[
        "equipment"
    ],
    "wof:name":"Padstow Grange Distributors",
    "wof:placetype":"venue"
},
  "geometry": {"coordinates":[115.933288574,-31.9562664032],"type":"Point"}
}