{
  "type": "Feature",
  "properties": {
    "iso:country":"AU",
    "sg:address":"PO Box 1004",
    "sg:city":"Meadowbank",
    "sg:classifiers":[
        {
            "category":"Banks & Credit Unions",
            "subcategory":"Investment Brokerage",
            "type":"Services"
        }
    ],
    "sg:phone":"+61 2 9808 6242",
    "sg:postcode":"2114",
    "sg:province":"NSW",
    "sg:tags":[
        "debt",
        "collection"
    ],
    "wof:name":"Commercial Debt Recovery Solutions",
    "wof:placetype":"venue"
},
  "geometry": {"coordinates":[151.09100341800001,-33.8160209656],"type":"Point"}
}