{
  "type": "Feature",
  "properties": {
    "iso:country":"AU",
    "sg:address":"432 Rocky Point Rd",
    "sg:city":"Sans Souci",
    "sg:classifiers":[
        {
            "category":"Health Services",
            "subcategory":"Chiropractor",
            "type":"Services"
        }
    ],
    "sg:phone":"+61 2 9529 4008",
    "sg:postcode":"2219",
    "sg:province":"NSW",
    "wof:name":"Moodie Leon & Leanne",
    "wof:placetype":"venue"
},
  "geometry": {"coordinates":[151.134506,-33.988667],"type":"Point"}
}