{
  "type": "Feature",
  "properties": {
    "iso:country":"AU",
    "sg:address":"39 Gregory St",
    "sg:city":"Cloncurry",
    "sg:classifiers":[
        {
            "category":"Commercial Area",
            "type":"Public Place"
        }
    ],
    "sg:phone":"+61 7 4742 1331",
    "sg:postcode":"4824",
    "sg:province":"QLD",
    "sg:tags":[
        "heavy",
        "carrier"
    ],
    "wof:name":"Davis H G & Co",
    "wof:placetype":"venue"
},
  "geometry": {"coordinates":[140.506592,-20.703087],"type":"Point"}
}