{
  "type": "Feature",
  "properties": {
    "iso:country":"AU",
    "sg:address":"Braeside Rd",
    "sg:city":"Greystanes",
    "sg:classifiers":[
        {
            "category":"Education",
            "subcategory":"School",
            "type":"Public Place"
        }
    ],
    "sg:phone":"+61 2 9631 1500",
    "sg:postcode":"2145",
    "sg:province":"NSW",
    "wof:name":"Our Lady Queen of Peace School",
    "wof:placetype":"venue"
},
  "geometry": {"coordinates":[150.95439148,-33.8190879822],"type":"Point"}
}