{
  "type": "Feature",
  "properties": {
    "addr:full":"Boomi Creek Rd Woodenbong NSW 2476",
    "addr:postcode":"2476",
    "addr:street":"Creek Rd",
    "iso:country":"AU",
    "sg:address":"Boomi Creek Rd",
    "sg:city":"Woodenbong",
    "sg:classifiers":[
        {
            "category":"Farming",
            "subcategory":"Farm",
            "type":"Manufacturing & Wholesale Goods"
        }
    ],
    "sg:phone":"+61 2 6635 1258",
    "sg:postcode":"2476",
    "sg:province":"NSW",
    "sg:tags":[
        "farmer"
    ],
    "wof:name":"Walker N O",
    "wof:placetype":"venue"
},
  "geometry": {"coordinates":[152.61863708499999,-28.3996658325],"type":"Point"}
}