{
  "type": "Feature",
  "properties": {
    "addr:full":"356 Torrens Rd Kilkenny SA 5009",
    "addr:housenumber":"356",
    "addr:postcode":"5009",
    "addr:street":"Torrens Rd",
    "iso:country":"AU",
    "sg:address":"356 Torrens Rd",
    "sg:city":"Kilkenny",
    "sg:classifiers":[
        {
            "category":"Retail",
            "subcategory":"Auto Repair",
            "type":"Services"
        }
    ],
    "sg:phone":"+61 8 8268 7303",
    "sg:postcode":"5009",
    "sg:province":"SA",
    "sg:tags":[
        "car",
        "restoration",
        "supply"
    ],
    "wof:name":"Marque Restoration & Motor Repair",
    "wof:placetype":"venue"
},
  "geometry": {"coordinates":[138.55751037600001,-34.88048172],"type":"Point"}
}