{
  "type": "Feature",
  "properties": {
    "addr:full":"Ste 3/ 318 Pakington St Newtown VIC 3220",
    "addr:housenumber":"/ 318",
    "addr:postcode":"3220",
    "addr:street":"Pakington St",
    "iso:country":"AU",
    "sg:address":"Ste 3/ 318 Pakington St",
    "sg:city":"Newtown",
    "sg:classifiers":[
        {
            "category":"Farming",
            "subcategory":"Farm & Veterinary Services",
            "type":"Manufacturing & Wholesale Goods"
        }
    ],
    "sg:phone":"+61 3 5229 0566",
    "sg:postcode":"3220",
    "sg:province":"VIC",
    "sg:tags":[
        "agricultural",
        "advisory"
    ],
    "wof:name":"Southern Farming Systems",
    "wof:placetype":"venue"
},
  "geometry": {"coordinates":[144.34562700000001,-38.155666],"type":"Point"}
}