{
  "type": "Feature",
  "properties": {
    "iso:country":"AU",
    "sg:address":"14 Cremzow Rd",
    "sg:city":"Brendale",
    "sg:classifiers":[
        {
            "category":"Health Services",
            "subcategory":"Doctor",
            "type":"Services"
        }
    ],
    "sg:phone":"+61 7 3881 1881",
    "sg:postcode":"4500",
    "sg:province":"QLD",
    "sg:tags":[
        "medical",
        "practitioner"
    ],
    "wof:name":"Collins Dr Raymond",
    "wof:placetype":"venue"
},
  "geometry": {"coordinates":[152.983444214,-27.3175735474],"type":"Point"}
}