{
  "type": "Feature",
  "properties": {
    "addr:full":"69 Pendeen Rd Albany WA 6330",
    "addr:housenumber":"69",
    "addr:postcode":"6330",
    "addr:street":"Pendeen Rd",
    "iso:country":"AU",
    "sg:address":"69 Pendeen Rd",
    "sg:city":"Albany",
    "sg:classifiers":[
        {
            "category":"Autos & Motor Vehicles",
            "subcategory":"Automobile Sales",
            "type":"Retail Goods"
        }
    ],
    "sg:phone":"+61 8 9844 3883",
    "sg:postcode":"6330",
    "sg:province":"WA",
    "sg:tags":[
        "equipment",
        "trailer"
    ],
    "wof:name":"Allroad Motor Body Builders",
    "wof:placetype":"venue"
},
  "geometry": {"coordinates":[117.891273498,-34.9572601318],"type":"Point"}
}