{
  "type": "Feature",
  "properties": {
    "iso:country":"AU",
    "sg:address":"Shop 19 Windsor Town Cntr Kable St",
    "sg:city":"Windsor",
    "sg:classifiers":[
        {
            "category":"Retail",
            "subcategory":"Laundry & Dry Cleaning",
            "type":"Services"
        }
    ],
    "sg:phone":"+61 2 4577 2584",
    "sg:postcode":"2756",
    "sg:province":"NSW",
    "wof:name":"Windsor Laundry Services",
    "wof:placetype":"venue"
},
  "geometry": {"coordinates":[150.821868897,-33.6063919067],"type":"Point"}
}