{
  "type": "Feature",
  "properties": {
    "addr:full":"33 Ewing St Murwillumbah NSW 2484",
    "addr:housenumber":"33",
    "addr:postcode":"2484",
    "addr:street":"Ewing St",
    "iso:country":"AU",
    "sg:address":"33 Ewing St",
    "sg:city":"Murwillumbah",
    "sg:classifiers":[
        {
            "category":"Food & Beverages",
            "subcategory":"Groceries & Convenience Stores",
            "type":"Retail Goods"
        }
    ],
    "sg:phone":"+61 2 6672 5285",
    "sg:postcode":"2484",
    "sg:province":"NSW",
    "wof:name":"Hospital Shop The",
    "wof:placetype":"venue"
},
  "geometry": {"coordinates":[153.395553589,-28.3242340088],"type":"Point"}
}