{
  "type": "Feature",
  "properties": {
    "addr:full":"312 Marrickville Rd Marrickville NSW 2204",
    "addr:housenumber":"312",
    "addr:postcode":"2204",
    "addr:street":"Marrickville Rd",
    "iso:country":"AU",
    "sg:address":"312 Marrickville Rd",
    "sg:city":"Marrickville",
    "sg:classifiers":[
        {
            "category":"Health Services",
            "subcategory":"Doctor",
            "type":"Services"
        }
    ],
    "sg:phone":"+61 2 9569 7222",
    "sg:postcode":"2204",
    "sg:province":"NSW",
    "sg:tags":[
        "medical",
        "practitioner"
    ],
    "wof:name":"Foundation Marrickville Medical Practice",
    "wof:placetype":"venue"
},
  "geometry": {"coordinates":[151.15564000000001,-33.91032],"type":"Point"}
}