{
  "type": "Feature",
  "properties": {
    "addr:full":"11 Amaroo St Bonnyrigg NSW 2177",
    "addr:housenumber":"11",
    "addr:postcode":"2177",
    "addr:street":"Amaroo St",
    "iso:country":"AU",
    "sg:address":"11 Amaroo St",
    "sg:city":"Bonnyrigg",
    "sg:classifiers":[
        {
            "category":"Home & Garden",
            "subcategory":"Home Furnishings",
            "type":"Retail Goods"
        }
    ],
    "sg:phone":"+61 402 243 597",
    "sg:postcode":"2177",
    "sg:province":"NSW",
    "sg:tags":[
        "shower",
        "screen"
    ],
    "wof:name":"Sydney Shower Installations",
    "wof:placetype":"venue"
},
  "geometry": {"coordinates":[150.890167236,-33.8994216919],"type":"Point"}
}