{
  "type": "Feature",
  "properties": {
    "addr:full":"47 Amaroo St Wagga Wagga NSW 2650",
    "addr:housenumber":"47",
    "addr:postcode":"2650",
    "addr:street":"Amaroo St",
    "iso:country":"AU",
    "sg:address":"47 Amaroo St",
    "sg:city":"Wagga Wagga",
    "sg:classifiers":[
        {
            "category":"Professional",
            "subcategory":"Business Services",
            "type":"Services"
        }
    ],
    "sg:phone":"+61 412 694 069",
    "sg:postcode":"2650",
    "sg:province":"NSW",
    "sg:tags":[
        "broker"
    ],
    "wof:name":"Peter Campbell Real Estate",
    "wof:placetype":"venue"
},
  "geometry": {"coordinates":[147.36399841299999,-35.1516494751],"type":"Point"}
}