{
  "type": "Feature",
  "properties": {
    "addr:full":"80 Gehrig La Oxley VIC 3678",
    "addr:housenumber":"80",
    "addr:postcode":"3678",
    "addr:street":"Gehrig La Oxley",
    "iso:country":"AU",
    "sg:address":"80 Gehrig La",
    "sg:city":"Oxley",
    "sg:classifiers":[
        {
            "category":"Farming",
            "subcategory":"Vineyard",
            "type":"Manufacturing & Wholesale Goods"
        }
    ],
    "sg:phone":"+61 3 5727 3395",
    "sg:postcode":"3678",
    "sg:province":"VIC",
    "sg:tags":[
        "winery"
    ],
    "wof:name":"Gehrig John Wines",
    "wof:placetype":"venue"
},
  "geometry": {"coordinates":[146.38238525400001,-36.4550704956],"type":"Point"}
}