{
  "type": "Feature",
  "properties": {
    "addr:full":"81 Overland Drv Edens Landing QLD 4207",
    "addr:housenumber":"81",
    "addr:postcode":"4207",
    "addr:street":"Overland Drv",
    "iso:country":"AU",
    "sg:address":"81 Overland Drv",
    "sg:city":"Edens Landing",
    "sg:classifiers":[
        {
            "category":"Health Services",
            "subcategory":"Health Practitioner",
            "type":"Services"
        }
    ],
    "sg:phone":"+61 7 3805 1132",
    "sg:postcode":"4207",
    "sg:province":"QLD",
    "sg:tags":[
        "naturopath"
    ],
    "wof:name":"Nutrition 4 You",
    "wof:placetype":"venue"
},
  "geometry": {"coordinates":[153.16348266599999,-27.7060966492],"type":"Point"}
}