{
  "type": "Feature",
  "properties": {
    "addr:full":"214 Macquarie St Liverpool NSW 2170",
    "addr:housenumber":"214",
    "addr:postcode":"2170",
    "addr:street":"Macquarie St",
    "iso:country":"AU",
    "sg:address":"214 Macquarie St",
    "sg:city":"Liverpool",
    "sg:classifiers":[
        {
            "category":"Travel",
            "subcategory":"Hotels & Motels",
            "type":"Entertainment"
        }
    ],
    "sg:phone":"+61 2 9602 0086",
    "sg:postcode":"2170",
    "sg:province":"NSW",
    "sg:tags":[
        "pub"
    ],
    "wof:name":"Liverpool Hotel",
    "wof:placetype":"venue"
},
  "geometry": {"coordinates":[150.92385864299999,-33.9226989746],"type":"Point"}
}