{
  "type": "Feature",
  "properties": {
    "addr:full":"11 Elizabeth St Kenilworth QLD 4574",
    "addr:housenumber":"11",
    "addr:postcode":"4574",
    "addr:street":"Elizabeth St",
    "iso:country":"AU",
    "sg:address":"11 Elizabeth St",
    "sg:city":"Kenilworth",
    "sg:classifiers":[
        {
            "category":"Cafe",
            "type":"Food & Drink"
        }
    ],
    "sg:phone":"+61 7 5446 0025",
    "sg:postcode":"4574",
    "sg:province":"QLD",
    "wof:name":"Nanna McGinn's Coffee Shop",
    "wof:placetype":"venue"
},
  "geometry": {"coordinates":[152.727341,-26.595402],"type":"Point"}
}