{
  "type": "Feature",
  "properties": {
    "addr:full":"745 Heatherton Rd Springvale VIC 3171",
    "addr:housenumber":"745",
    "addr:postcode":"3171",
    "addr:street":"Heatherton Rd",
    "iso:country":"AU",
    "sg:address":"745 Heatherton Rd",
    "sg:city":"Springvale",
    "sg:classifiers":[
        {
            "category":"Food & Beverages",
            "subcategory":"Groceries & Convenience Stores",
            "type":"Retail Goods"
        }
    ],
    "sg:phone":"+61 3 9558 5522",
    "sg:postcode":"3171",
    "sg:province":"VIC",
    "wof:name":"Springvale Convenience Store",
    "wof:placetype":"venue"
},
  "geometry": {"coordinates":[145.14736938499999,-37.9616470337],"type":"Point"}
}