{
  "type": "Feature",
  "properties": {
    "addr:full":"39 Haverfield St Echuca VIC 3564",
    "addr:housenumber":"39",
    "addr:postcode":"3564",
    "addr:street":"Haverfield St",
    "iso:country":"AU",
    "sg:address":"39 Haverfield St",
    "sg:city":"Echuca",
    "sg:classifiers":[
        {
            "category":"Food & Beverages",
            "subcategory":"Supermarket",
            "type":"Retail Goods"
        }
    ],
    "sg:phone":"+61 3 5482 1348",
    "sg:postcode":"3564",
    "sg:province":"VIC",
    "sg:tags":[
        "grocery",
        "store"
    ],
    "wof:name":"Grays Friendly Grocers",
    "wof:placetype":"venue"
},
  "geometry": {"coordinates":[144.74641418499999,-36.1403999329],"type":"Point"}
}