{
  "type": "Feature",
  "properties": {
    "iso:country":"AU",
    "sg:address":"Paradise Rd",
    "sg:city":"Slacks Creek",
    "sg:classifiers":[
        {
            "category":"Education",
            "subcategory":"School",
            "type":"Public Place"
        }
    ],
    "sg:phone":"+61 7 3489 2333",
    "sg:postcode":"4127",
    "sg:province":"QLD",
    "sg:tags":[
        "state",
        "except",
        "nsw"
    ],
    "wof:name":"Mabel Park High",
    "wof:placetype":"venue"
},
  "geometry": {"coordinates":[153.12635803200001,-27.639547348],"type":"Point"}
}