{
  "type": "Feature",
  "properties": {
    "addr:full":"31 Whitehead St Blairgowrie VIC 3942",
    "addr:housenumber":"31",
    "addr:postcode":"3942",
    "addr:street":"Whitehead St",
    "iso:country":"AU",
    "sg:address":"31 Whitehead St",
    "sg:city":"Blairgowrie",
    "sg:classifiers":[
        {
            "category":"Building & Trades",
            "subcategory":"Plumbing",
            "type":"Services"
        }
    ],
    "sg:phone":"+61 3 5988 9922",
    "sg:postcode":"3942",
    "sg:province":"VIC",
    "sg:tags":[
        "plumber",
        "gasfitters"
    ],
    "wof:name":"Taylor G & J",
    "wof:placetype":"venue"
},
  "geometry": {"coordinates":[144.771652222,-38.3643798828],"type":"Point"}
}