{
  "type": "Feature",
  "properties": {
    "iso:country":"AU",
    "sg:address":"5 Keith St",
    "sg:city":"Lindfield",
    "sg:classifiers":[
        {
            "category":"Mining & Drilling",
            "type":"Manufacturing & Wholesale Goods"
        }
    ],
    "sg:phone":"+61 2 9415 6820",
    "sg:postcode":"2070",
    "sg:province":"NSW",
    "sg:tags":[
        "geologist"
    ],
    "wof:name":"Geo-Sydney",
    "wof:placetype":"venue"
},
  "geometry": {"coordinates":[151.17694091800001,-33.7769966125],"type":"Point"}
}