{
  "type": "Feature",
  "properties": {
    "iso:country":"AU",
    "sg:address":"3b Philips Crs",
    "sg:city":"Hendon",
    "sg:classifiers":[
        {
            "category":"Structure",
            "subcategory":"Building",
            "type":"Public Place"
        }
    ],
    "sg:phone":"+61 8 8243 1085",
    "sg:postcode":"5014",
    "sg:province":"SA",
    "sg:tags":[
        "sail",
        "shade"
    ],
    "wof:name":"Shade Craftsman",
    "wof:placetype":"venue"
},
  "geometry": {"coordinates":[138.513946533,-34.8669090271],"type":"Point"}
}