{
  "type": "Feature",
  "properties": {
    "addr:full":"131 Marsh St Armidale NSW 2350",
    "addr:housenumber":"131",
    "addr:postcode":"2350",
    "addr:street":"Marsh St",
    "iso:country":"AU",
    "sg:address":"131 Marsh St",
    "sg:city":"Armidale",
    "sg:classifiers":[
        {
            "category":"Fast Food",
            "type":"Food & Drink"
        }
    ],
    "sg:phone":"+61 2 6771 1622",
    "sg:postcode":"2350",
    "sg:province":"NSW",
    "sg:tags":[
        "away",
        "take"
    ],
    "wof:name":"McDonald's Family Restaurants",
    "wof:placetype":"venue"
},
  "geometry": {"coordinates":[151.66633605999999,-30.5217666626],"type":"Point"}
}