{
  "type": "Feature",
  "properties": {
    "addr:full":"350 Bryces Rd Berry NSW 2535",
    "addr:housenumber":"350",
    "addr:postcode":"2535",
    "addr:street":"Bryces Rd",
    "iso:country":"AU",
    "sg:address":"350 Bryces Rd",
    "sg:city":"Berry",
    "sg:classifiers":[
        {
            "category":"Building & Trades",
            "subcategory":"Cleaning & Sanitation",
            "type":"Services"
        }
    ],
    "sg:phone":"+61 2 4464 1752",
    "sg:postcode":"2535",
    "sg:province":"NSW",
    "sg:tags":[
        "window"
    ],
    "wof:name":"Shoalhaven Premium Cleaning Service",
    "wof:placetype":"venue"
},
  "geometry": {"coordinates":[150.70933532699999,-34.8292694092],"type":"Point"}
}