{
  "type": "Feature",
  "properties": {
    "iso:country":"AU",
    "sg:address":"PO Box 328",
    "sg:city":"Oaklands Park",
    "sg:classifiers":[
        {
            "category":"Food & Beverages",
            "subcategory":"Specialty",
            "type":"Retail Goods"
        }
    ],
    "sg:phone":"+61 8 8346 0611",
    "sg:postcode":"5046",
    "sg:province":"SA",
    "sg:tags":[
        "ice",
        "supply"
    ],
    "wof:name":"Trend Ice",
    "wof:placetype":"venue"
},
  "geometry": {"coordinates":[138.54599,-35.01244],"type":"Point"}
}