{
  "type": "Feature",
  "properties": {
    "addr:full":"Kellett St Nelson VIC 3292",
    "addr:postcode":"3292",
    "addr:street":"Kellett St",
    "iso:country":"AU",
    "sg:address":"Kellett St",
    "sg:city":"Nelson",
    "sg:classifiers":[
        {
            "category":"Travel",
            "subcategory":"Hotels & Motels",
            "type":"Entertainment"
        }
    ],
    "sg:phone":"+61 8 8738 4011",
    "sg:postcode":"3292",
    "sg:province":"VIC",
    "sg:tags":[
        "accommodation"
    ],
    "wof:name":"Nelson Hotel",
    "wof:placetype":"venue"
},
  "geometry": {"coordinates":[141.01037600000001,-38.049007],"type":"Point"}
}