{
  "type": "Feature",
  "properties": {
    "iso:country":"AU",
    "sg:address":"Bruce Hwy",
    "sg:city":"Stuart",
    "sg:classifiers":[
        {
            "category":"Wholesale",
            "subcategory":"Meat",
            "type":"Manufacturing & Wholesale Goods"
        }
    ],
    "sg:phone":"+61 7 4720 8000",
    "sg:postcode":"4811",
    "sg:province":"QLD",
    "sg:tags":[
        "abattoir"
    ],
    "wof:name":"Australia Meat Holdings Pty Limited",
    "wof:placetype":"venue"
},
  "geometry": {"coordinates":[146.83938599999999,-19.324133],"type":"Point"}
}