{
  "type": "Feature",
  "properties": {
    "iso:country":"AU",
    "sg:address":"292 Brisbane St",
    "sg:city":"West Ipswich",
    "sg:classifiers":[
        {
            "category":"Wholesale",
            "subcategory":"Machinery & Supplies",
            "type":"Manufacturing & Wholesale Goods"
        }
    ],
    "sg:phone":"+61 7 3281 2500",
    "sg:postcode":"4305",
    "sg:province":"QLD",
    "sg:tags":[
        "engineer"
    ],
    "wof:name":"J Blackwood & Son Ltd",
    "wof:placetype":"venue"
},
  "geometry": {"coordinates":[152.748214722,-27.6219425201],"type":"Point"}
}