{
  "type": "Feature",
  "properties": {
    "addr:full":"449 Bridge Rd Richmond VIC 3121",
    "addr:housenumber":"449",
    "addr:postcode":"3121",
    "addr:street":"Bridge Rd",
    "iso:country":"AU",
    "sg:address":"449 Bridge Rd",
    "sg:city":"Richmond",
    "sg:classifiers":[
        {
            "category":"Social Services",
            "subcategory":"Adult Care",
            "type":"Services"
        }
    ],
    "sg:phone":"+61 3 9427 7700",
    "sg:postcode":"3121",
    "sg:province":"VIC",
    "sg:tags":[
        "towing"
    ],
    "wof:name":"Stateline Towing & Roadside Service Pty Ltd",
    "wof:placetype":"venue"
},
  "geometry": {"coordinates":[145.005584717,-37.819065094],"type":"Point"}
}