{
  "type": "Feature",
  "properties": {
    "addr:full":"26D Daws Rd Ascot Park SA 5043",
    "addr:housenumber":"26d",
    "addr:postcode":"5043",
    "addr:street":"Daws Rd",
    "iso:country":"AU",
    "sg:address":"26D Daws Rd",
    "sg:city":"Ascot Park",
    "sg:classifiers":[
        {
            "category":"Personal",
            "subcategory":"Beauty Salon",
            "type":"Services"
        }
    ],
    "sg:phone":"+61 8 8299 0016",
    "sg:postcode":"5043",
    "sg:province":"SA",
    "wof:name":"Nail-a-holics",
    "wof:placetype":"venue"
},
  "geometry": {"coordinates":[138.56542999999999,-34.993095],"type":"Point"}
}