{
  "type": "Feature",
  "properties": {
    "addr:full":"Thompson Ave Cowes VIC 3922",
    "addr:postcode":"3922",
    "addr:street":"Thompson Ave",
    "iso:country":"AU",
    "sg:address":"Thompson Ave",
    "sg:city":"Cowes",
    "sg:classifiers":[
        {
            "category":"Food & Beverages",
            "subcategory":"Supermarket",
            "type":"Retail Goods"
        }
    ],
    "sg:phone":"+61 3 5952 3765",
    "sg:postcode":"3922",
    "sg:province":"VIC",
    "sg:tags":[
        "grocery",
        "store"
    ],
    "wof:name":"Island Supermarket",
    "wof:placetype":"venue"
},
  "geometry": {"coordinates":[145.23898315400001,-38.45652771],"type":"Point"}
}