{
  "type": "Feature",
  "properties": {
    "addr:full":"11 Vilna Crs Hackham West SA 5163",
    "addr:housenumber":"11",
    "addr:postcode":"5163",
    "addr:street":"Vilna Crs",
    "iso:country":"AU",
    "sg:address":"11 Vilna Crs",
    "sg:city":"Hackham West",
    "sg:classifiers":[
        {
            "category":"Retail",
            "subcategory":"Storage",
            "type":"Services"
        }
    ],
    "sg:phone":"+61 402 559 777",
    "sg:postcode":"5163",
    "sg:province":"SA",
    "sg:tags":[
        "removal",
        "furniture"
    ],
    "wof:name":"AA ADaz's Removals & Storage",
    "wof:placetype":"venue"
},
  "geometry": {"coordinates":[138.51512145999999,-35.1371994019],"type":"Point"}
}