{
  "type": "Feature",
  "properties": {
    "addr:full":"27a Cadell St Goolwa SA 5214",
    "addr:housenumber":"27a",
    "addr:postcode":"5214",
    "addr:street":"Cadell St",
    "iso:country":"AU",
    "sg:address":"27a Cadell St",
    "sg:city":"Goolwa",
    "sg:classifiers":[
        {
            "category":"Retail",
            "subcategory":"Veterinary Services",
            "type":"Services"
        }
    ],
    "sg:phone":"+61 8 8555 5690",
    "sg:postcode":"5214",
    "sg:province":"SA",
    "sg:tags":[
        "surgeon"
    ],
    "wof:name":"Strathalbyn Veterinary Clinic",
    "wof:placetype":"venue"
},
  "geometry": {"coordinates":[138.780426025,-35.4992103577],"type":"Point"}
}