{
  "type": "Feature",
  "properties": {
    "iso:country":"AU",
    "sg:address":"Ground Floor 276 Pitt St",
    "sg:city":"Sydney",
    "sg:classifiers":[
        {
            "category":"Airline",
            "type":"Transportation"
        }
    ],
    "sg:phone":"+61 1300 658 572",
    "sg:postcode":"2000",
    "sg:province":"NSW",
    "sg:tags":[
        "agent"
    ],
    "wof:name":"Air Mauritius Ltd",
    "wof:placetype":"venue"
},
  "geometry": {"coordinates":[151.20820617699999,-33.8738594055],"type":"Point"}
}