{
  "type": "Feature",
  "properties": {
    "addr:full":"55 Yandilla St Pittsworth QLD 4356",
    "addr:housenumber":"55",
    "addr:postcode":"4356",
    "addr:street":"Yandilla St",
    "iso:country":"AU",
    "sg:address":"55 Yandilla St",
    "sg:city":"Pittsworth",
    "sg:classifiers":[
        {
            "category":"Personal",
            "type":"Services"
        }
    ],
    "sg:phone":"+61 7 4693 1877",
    "sg:postcode":"4356",
    "sg:province":"QLD",
    "sg:tags":[
        "gift"
    ],
    "wof:name":"Cain's Gift Store",
    "wof:placetype":"venue"
},
  "geometry": {"coordinates":[151.63591,-27.715374],"type":"Point"}
}