{
  "type": "Feature",
  "properties": {
    "addr:full":"777 Great Northern Hwy Herne Hill WA 6056",
    "addr:housenumber":"777",
    "addr:postcode":"6056",
    "addr:street":"Great Northern Hwy",
    "iso:country":"AU",
    "sg:address":"777 Great Northern Hwy",
    "sg:city":"Herne Hill",
    "sg:classifiers":[
        {
            "category":"Casinos & Gambling",
            "type":"Entertainment"
        }
    ],
    "sg:phone":"+61 8 9296 4427",
    "sg:postcode":"6056",
    "sg:province":"WA",
    "sg:tags":[
        "lottery",
        "agent"
    ],
    "wof:name":"Herne Hill Village Lottery Centre",
    "wof:placetype":"venue"
},
  "geometry": {"coordinates":[116.01701355,-31.8243427277],"type":"Point"}
}