{
  "type": "Feature",
  "properties": {
    "addr:full":"Shop 45 Warriewood Shopping Square Warriewood NSW 2102",
    "addr:housenumber":"shop 45",
    "addr:postcode":"2102",
    "addr:street":"Shopping",
    "iso:country":"AU",
    "sg:address":"Shop 45 Warriewood Shopping Square",
    "sg:city":"Warriewood",
    "sg:classifiers":[
        {
            "category":"Shopping",
            "subcategory":"Clothing, Apparel, & Fashions",
            "type":"Retail Goods"
        }
    ],
    "sg:phone":"+61 2 9970 8425",
    "sg:postcode":"2102",
    "sg:province":"NSW",
    "sg:tags":[
        "lady",
        "wear"
    ],
    "wof:name":"Sussan",
    "wof:placetype":"venue"
},
  "geometry": {"coordinates":[151.299454,-33.686592],"type":"Point"}
}