{
  "type": "Feature",
  "properties": {
    "addr:full":"40 Bruce St Heyfield VIC 3858",
    "addr:housenumber":"40",
    "addr:postcode":"3858",
    "addr:street":"Bruce St",
    "iso:country":"AU",
    "sg:address":"40 Bruce St",
    "sg:city":"Heyfield",
    "sg:classifiers":[
        {
            "category":"Building & Trades",
            "subcategory":"Construction",
            "type":"Services"
        }
    ],
    "sg:phone":"+61 3 5148 3151",
    "sg:postcode":"3858",
    "sg:province":"VIC",
    "sg:tags":[
        "contractor"
    ],
    "wof:name":"Jega Constructions Pty Ltd",
    "wof:placetype":"venue"
},
  "geometry": {"coordinates":[146.791015625,-37.9784622192],"type":"Point"}
}