{
  "type": "Feature",
  "properties": {
    "addr:full":"5 Hettwer Crt Victoria Point QLD 4165",
    "addr:housenumber":"5",
    "addr:postcode":"4165",
    "addr:street":"Hettwer Crt",
    "iso:country":"AU",
    "sg:address":"5 Hettwer Crt",
    "sg:city":"Victoria Point",
    "sg:classifiers":[
        {
            "category":"Health Services",
            "subcategory":"Doctor",
            "type":"Services"
        }
    ],
    "sg:phone":"+61 7 3820 9935",
    "sg:postcode":"4165",
    "sg:province":"QLD",
    "sg:tags":[
        "medical",
        "practitioner"
    ],
    "wof:name":"Global Medical Transcription Services",
    "wof:placetype":"venue"
},
  "geometry": {"coordinates":[153.29570007300001,-27.5903053284],"type":"Point"}
}