{
  "type": "Feature",
  "properties": {
    "addr:full":"Shop 6- 7, 30-32 McAdams Sq Croydon Hills VIC 3136",
    "addr:housenumber":"shop;7 30-32",
    "addr:postcode":"3136",
    "addr:street":"Mcadams Sq",
    "iso:country":"AU",
    "sg:address":"Shop 6- 7, 30-32 McAdams Sq",
    "sg:city":"Croydon Hills",
    "sg:classifiers":[
        {
            "category":"Personal",
            "subcategory":"Beauty Salon",
            "type":"Services"
        }
    ],
    "sg:phone":"+61 3 9723 4332",
    "sg:postcode":"3136",
    "sg:province":"VIC",
    "wof:name":"Aqua Beauty Bar",
    "wof:placetype":"venue"
},
  "geometry": {"coordinates":[145.26855468799999,-37.783405304],"type":"Point"}
}