{
  "type": "Feature",
  "properties": {
    "iso:country":"AU",
    "sg:address":"40 Patterson La",
    "sg:city":"Young",
    "sg:classifiers":[
        {
            "category":"Utilities",
            "subcategory":"Refuse",
            "type":"Services"
        }
    ],
    "sg:phone":"+61 2 6382 3609",
    "sg:postcode":"2594",
    "sg:province":"NSW",
    "sg:tags":[
        "disposal",
        "reduction",
        "waste"
    ],
    "wof:name":"Young - Elite Waste Services",
    "wof:placetype":"venue"
},
  "geometry": {"coordinates":[148.31123352,-34.2680625916],"type":"Point"}
}