{
  "type": "Feature",
  "properties": {
    "addr:full":"Cnr Wellington & Howick Sts Launceston TAS 7250",
    "addr:postcode":"7250",
    "addr:street":"Cnr Wellington &",
    "iso:country":"AU",
    "sg:address":"Cnr Wellington & Howick Sts",
    "sg:city":"Launceston",
    "sg:classifiers":[
        {
            "category":"Autos & Motor Vehicles",
            "subcategory":"Auto Supplies",
            "type":"Retail Goods"
        }
    ],
    "sg:phone":"+61 3 6334 0766",
    "sg:postcode":"7250",
    "sg:province":"TAS",
    "sg:tags":[
        "tyre"
    ],
    "wof:name":"Bob Jane Launceston",
    "wof:placetype":"venue"
},
  "geometry": {"coordinates":[147.13923645,-41.445930481],"type":"Point"}
}