{
  "type": "Feature",
  "properties": {
    "addr:full":"33 Pemberton St Botany NSW 2019",
    "addr:housenumber":"33",
    "addr:postcode":"2019",
    "addr:street":"Pemberton St",
    "iso:country":"AU",
    "sg:address":"33 Pemberton St",
    "sg:city":"Botany",
    "sg:classifiers":[
        {
            "category":"Building & Trades",
            "subcategory":"Construction",
            "type":"Services"
        }
    ],
    "sg:phone":"+61 2 9700 1114",
    "sg:postcode":"2019",
    "sg:province":"NSW",
    "sg:tags":[
        "joinery"
    ],
    "wof:name":"Competitive Joinery Pty Ltd",
    "wof:placetype":"venue"
},
  "geometry": {"coordinates":[151.203216553,-33.9509544373],"type":"Point"}
}