{
  "type": "Feature",
  "properties": {
    "iso:country":"AU",
    "sg:address":"206 Henley Beach Rd",
    "sg:city":"Torrensville",
    "sg:classifiers":[
        {
            "category":"Structure",
            "subcategory":"Tunnel",
            "type":"Public Place"
        }
    ],
    "sg:phone":"+61 8 8443 9901",
    "sg:postcode":"5031",
    "sg:province":"SA",
    "sg:tags":[
        "cleaner",
        "industrial",
        "vacuum"
    ],
    "wof:name":"Electron Ducted Vacuum Systems",
    "wof:placetype":"venue"
},
  "geometry": {"coordinates":[138.55865478499999,-34.9240531921],"type":"Point"}
}