{
  "type": "Feature",
  "properties": {
    "addr:full":"Shop 31 a Shellhabour Square Shellharbour NSW 2529",
    "addr:housenumber":"shop 31 a",
    "addr:postcode":"2529",
    "addr:street":"Shellhabour Square",
    "iso:country":"AU",
    "sg:address":"Shop 31",
    "sg:city":"a Shellhabour Square Shellharbour",
    "sg:classifiers":[
        {
            "category":"Shopping",
            "subcategory":"Baby Store",
            "type":"Retail Goods"
        }
    ],
    "sg:phone":"+61 2 4297 6649",
    "sg:postcode":"2529",
    "sg:province":"NSW",
    "sg:tags":[
        "wear"
    ],
    "wof:name":"Bo Peep Baby Boutique",
    "wof:placetype":"venue"
},
  "geometry": {"coordinates":[150.86412048299999,-34.5756912231],"type":"Point"}
}