{
  "type": "Feature",
  "properties": {
    "iso:country":"AU",
    "sg:address":"31 Gunnedah Rd",
    "sg:city":"Tamworth",
    "sg:classifiers":[
        {
            "category":"Utilities",
            "subcategory":"Recycling",
            "type":"Services"
        }
    ],
    "sg:phone":"+61 2 6762 2193",
    "sg:postcode":"2340",
    "sg:province":"NSW",
    "wof:name":"K O R",
    "wof:placetype":"venue"
},
  "geometry": {"coordinates":[150.906005859,-31.0970020294],"type":"Point"}
}