{
  "type": "Feature",
  "properties": {
    "iso:country":"AU",
    "sg:address":"16 Grey Gum Rd",
    "sg:city":"Taree",
    "sg:classifiers":[
        {
            "category":"Commercial Area",
            "type":"Public Place"
        }
    ],
    "sg:phone":"+61 2 6552 1845",
    "sg:postcode":"2430",
    "sg:province":"NSW",
    "sg:tags":[
        "heavy",
        "carrier"
    ],
    "wof:name":"Bourkes Transport Industries Pty Ltd",
    "wof:placetype":"venue"
},
  "geometry": {"coordinates":[152.45146199999999,-31.895943],"type":"Point"}
}