{
  "type": "Feature",
  "properties": {
    "iso:country":"AU",
    "sg:address":"Shp 6306 Aquatic Drv",
    "sg:city":"Maribyrnong",
    "sg:classifiers":[
        {
            "category":"Food & Beverages",
            "subcategory":"Fruits & Vegetables",
            "type":"Retail Goods"
        }
    ],
    "sg:phone":"+61 3 9318 6276",
    "sg:postcode":"3032",
    "sg:province":"VIC",
    "sg:tags":[
        "greengrocer",
        "fruiterer"
    ],
    "wof:name":"Fresh @ Highpoint Fruit & Veg",
    "wof:placetype":"venue"
},
  "geometry": {"coordinates":[144.889603,-37.776188],"type":"Point"}
}