{
  "type": "Feature",
  "properties": {
    "iso:country":"AU",
    "sg:address":"Brewery St",
    "sg:city":"Inverell",
    "sg:classifiers":[
        {
            "category":"Sports & Exercise",
            "subcategory":"Sports Center",
            "type":"Entertainment"
        }
    ],
    "sg:phone":"+61 2 6722 2281",
    "sg:postcode":"2360",
    "sg:province":"NSW",
    "sg:tags":[
        "ground"
    ],
    "wof:name":"Inverell Squash Centre",
    "wof:placetype":"venue"
},
  "geometry": {"coordinates":[151.13487243599999,-29.7799053192],"type":"Point"}
}