{
  "type": "Feature",
  "properties": {
    "iso:country":"AU",
    "sg:address":"1 Olsen St",
    "sg:city":"Frankston",
    "sg:classifiers":[
        {
            "category":"Retail",
            "subcategory":"Repair Shop",
            "type":"Services"
        }
    ],
    "sg:phone":"+61 3 9783 9844",
    "sg:postcode":"3199",
    "sg:province":"VIC",
    "sg:tags":[
        "cleaner",
        "part",
        "vacuum"
    ],
    "wof:name":"Godfreys",
    "wof:placetype":"venue"
},
  "geometry": {"coordinates":[145.12315368599999,-38.1412506104],"type":"Point"}
}