{
  "type": "Feature",
  "properties": {
    "addr:full":"Unit 6, 53 Norfolk Rd Marion SA 5043",
    "addr:housenumber":"53",
    "addr:postcode":"5043",
    "addr:street":"Norfolk Rd",
    "iso:country":"AU",
    "sg:address":"Unit 6, 53 Norfolk Rd",
    "sg:city":"Marion",
    "sg:classifiers":[
        {
            "category":"Retail",
            "subcategory":"Auto Repair",
            "type":"Services"
        }
    ],
    "sg:phone":"+61 8 8377 1016",
    "sg:postcode":"5043",
    "sg:province":"SA",
    "sg:tags":[
        "repairer",
        "motor",
        "engineer"
    ],
    "wof:name":"Tacho Automotive Repairs & Servicing",
    "wof:placetype":"venue"
},
  "geometry": {"coordinates":[138.55676299999999,-35.013618],"type":"Point"}
}