{
  "type": "Feature",
  "properties": {
    "addr:full":"65 Arthur St Roma QLD 4455",
    "addr:housenumber":"65",
    "addr:postcode":"4455",
    "addr:street":"Arthur St",
    "iso:country":"AU",
    "sg:address":"65 Arthur St",
    "sg:city":"Roma",
    "sg:classifiers":[
        {
            "category":"Organizations",
            "subcategory":"Community Association",
            "type":"Services"
        }
    ],
    "sg:phone":"+61 7 4622 5250",
    "sg:postcode":"4455",
    "sg:province":"QLD",
    "sg:tags":[
        "organisation",
        "family",
        "welfare"
    ],
    "wof:name":"Global Care",
    "wof:placetype":"venue"
},
  "geometry": {"coordinates":[148.789596558,-26.5708694458],"type":"Point"}
}