{
  "type": "Feature",
  "properties": {
    "iso:country":"AU",
    "sg:address":"11 Kembla St",
    "sg:city":"Fyshwick",
    "sg:classifiers":[
        {
            "category":"Retail",
            "subcategory":"Storage",
            "type":"Services"
        }
    ],
    "sg:phone":"+61 2 6280 6222",
    "sg:postcode":"2609",
    "sg:province":"ACT",
    "sg:tags":[
        "shelving",
        "system"
    ],
    "wof:name":"Rak-A-Van Shelving",
    "wof:placetype":"venue"
},
  "geometry": {"coordinates":[149.178131103,-35.3253479004],"type":"Point"}
}