{
  "type": "Feature",
  "properties": {
    "addr:full":"45 Tulip St Violet Town VIC 3669",
    "addr:housenumber":"45",
    "addr:postcode":"3669",
    "addr:street":"Tulip St",
    "iso:country":"AU",
    "sg:address":"45 Tulip St",
    "sg:city":"Violet Town",
    "sg:classifiers":[
        {
            "category":"Farming",
            "subcategory":"Farm & Veterinary Services",
            "type":"Manufacturing & Wholesale Goods"
        }
    ],
    "sg:phone":"+61 3 5798 1898",
    "sg:postcode":"3669",
    "sg:province":"VIC",
    "sg:tags":[
        "shearing",
        "contractor"
    ],
    "wof:name":"Shear Excellence",
    "wof:placetype":"venue"
},
  "geometry": {"coordinates":[145.71588134800001,-36.6343536377],"type":"Point"}
}