{
  "type": "Feature",
  "properties": {
    "addr:full":"130 Ziegenfusz Rd Thornlands QLD 4164",
    "addr:housenumber":"130",
    "addr:postcode":"4164",
    "addr:street":"Ziegenfusz Rd",
    "iso:country":"AU",
    "sg:address":"130 Ziegenfusz Rd",
    "sg:city":"Thornlands",
    "sg:classifiers":[
        {
            "category":"Building & Trades",
            "subcategory":"Landscaping Services",
            "type":"Services"
        }
    ],
    "sg:phone":"+61 418 787 704",
    "sg:postcode":"4164",
    "sg:province":"QLD",
    "sg:tags":[
        "designer",
        "landscape",
        "contractor"
    ],
    "wof:name":"A Affordable Bobcat Hire",
    "wof:placetype":"venue"
},
  "geometry": {"coordinates":[153.254959106,-27.5629653931],"type":"Point"}
}