{
  "type": "Feature",
  "properties": {
    "addr:full":"100 Main St Croydon VIC 3136",
    "addr:housenumber":"100",
    "addr:postcode":"3136",
    "addr:street":"Main St",
    "iso:country":"AU",
    "sg:address":"100 Main St",
    "sg:city":"Croydon",
    "sg:classifiers":[
        {
            "category":"Health Services",
            "subcategory":"Optometrist",
            "type":"Services"
        }
    ],
    "sg:phone":"+61 3 9725 7633",
    "sg:postcode":"3136",
    "sg:province":"VIC",
    "wof:name":"OPSM",
    "wof:placetype":"venue"
},
  "geometry": {"coordinates":[145.280807495,-37.7980880737],"type":"Point"}
}