{
  "type": "Feature",
  "properties": {
    "iso:country":"AU",
    "sg:address":"136 Daws Rd",
    "sg:city":"Melrose Park",
    "sg:classifiers":[
        {
            "category":"Government",
            "subcategory":"Fire Station",
            "type":"Public Place"
        }
    ],
    "sg:phone":"+61 8 8276 7655",
    "sg:postcode":"5039",
    "sg:province":"SA",
    "sg:tags":[
        "equipment",
        "protection",
        "consultant"
    ],
    "wof:name":"Sandvik Mining And Construction Adelaide Ltd",
    "wof:placetype":"venue"
},
  "geometry": {"coordinates":[138.578735352,-34.9924468994],"type":"Point"}
}