{
  "type": "Feature",
  "properties": {
    "addr:full":"Shop 11 York Town Sq Launceston TAS 7250",
    "addr:housenumber":"shop 11",
    "addr:postcode":"7250",
    "addr:street":"York Town Sq",
    "iso:country":"AU",
    "sg:address":"Shop 11",
    "sg:city":"York Town Sq Launceston",
    "sg:classifiers":[
        {
            "category":"Personal",
            "subcategory":"Nail Salon",
            "type":"Services"
        }
    ],
    "sg:phone":"+61 3 6331 0010",
    "sg:postcode":"7250",
    "sg:province":"TAS",
    "sg:tags":[
        "artificial"
    ],
    "wof:name":"Da Vinci",
    "wof:placetype":"venue"
},
  "geometry": {"coordinates":[147.14088439899999,-41.4353675842],"type":"Point"}
}