{
  "type": "Feature",
  "properties": {
    "addr:full":"45 Finlay St Bridgewater TAS 7030",
    "addr:housenumber":"45",
    "addr:postcode":"7030",
    "addr:street":"Finlay St",
    "iso:country":"AU",
    "sg:address":"45 Finlay St",
    "sg:city":"Bridgewater",
    "sg:classifiers":[
        {
            "category":"Home & Garden",
            "subcategory":"Building Materials",
            "type":"Retail Goods"
        }
    ],
    "sg:phone":"+61 3 6263 5260",
    "sg:postcode":"7030",
    "sg:province":"TAS",
    "sg:tags":[
        "lawn",
        "cutting",
        "maintenance"
    ],
    "wof:name":"Gregs Mowing Service",
    "wof:placetype":"venue"
},
  "geometry": {"coordinates":[147.23197937,-42.7367782593],"type":"Point"}
}