{
  "type": "Feature",
  "properties": {
    "addr:full":"Pimpala Shopping Centre Shop 4/27 Main South Rd Reynella SA 5161",
    "addr:housenumber":"shop 4 / 27",
    "addr:postcode":"5161",
    "addr:street":"Main South Rd",
    "iso:country":"AU",
    "sg:address":"Pimpala Shopping Centre Shop 4/27 Main South Rd",
    "sg:city":"Reynella",
    "sg:classifiers":[
        {
            "category":"Shopping",
            "subcategory":"Pets & Pet Supplies",
            "type":"Retail Goods"
        }
    ],
    "sg:phone":"+61 8 8322 5717",
    "sg:postcode":"5161",
    "sg:province":"SA",
    "sg:tags":[
        "food"
    ],
    "wof:name":"Pets Pantry",
    "wof:placetype":"venue"
},
  "geometry": {"coordinates":[138.53123474099999,-35.1006469727],"type":"Point"}
}