{
  "type": "Feature",
  "properties": {
    "iso:country":"AU",
    "sg:address":"945 Burke Rd",
    "sg:city":"Camberwell",
    "sg:classifiers":[
        {
            "category":"Shopping",
            "subcategory":"Bridal",
            "type":"Retail Goods"
        }
    ],
    "sg:phone":"+61 3 9882 1575",
    "sg:postcode":"3124",
    "sg:province":"VIC",
    "sg:tags":[
        "hire",
        "wear"
    ],
    "wof:name":"Dickory Dock (Aust) Pty Ltd",
    "wof:placetype":"venue"
},
  "geometry": {"coordinates":[145.057739258,-37.8250694275],"type":"Point"}
}