{
  "type": "Feature",
  "properties": {
    "addr:full":"491 Hume Hwy Yagoona NSW 2199",
    "addr:housenumber":"491",
    "addr:postcode":"2199",
    "addr:street":"Hume Hwy",
    "iso:country":"AU",
    "sg:address":"491 Hume Hwy",
    "sg:city":"Yagoona",
    "sg:classifiers":[
        {
            "category":"Professional",
            "subcategory":"Computer Services",
            "type":"Services"
        }
    ],
    "sg:phone":"+61 2 9796 4849",
    "sg:postcode":"2199",
    "sg:province":"NSW",
    "sg:tags":[
        "consultant",
        "system"
    ],
    "wof:name":"First In It Consulting",
    "wof:placetype":"venue"
},
  "geometry": {"coordinates":[151.022583,-33.907341],"type":"Point"}
}