{
  "type": "Feature",
  "properties": {
    "addr:full":"293 Broadway St Reservoir VIC 3073",
    "addr:housenumber":"293",
    "addr:postcode":"3073",
    "addr:street":"Broadway St",
    "iso:country":"AU",
    "sg:address":"293 Broadway St",
    "sg:city":"Reservoir",
    "sg:classifiers":[
        {
            "category":"Food & Beverages",
            "subcategory":"Bakery",
            "type":"Retail Goods"
        }
    ],
    "sg:phone":"+61 3 9462 5200",
    "sg:postcode":"3073",
    "sg:province":"VIC",
    "sg:tags":[
        "baker"
    ],
    "wof:name":"NTVi Bakery",
    "wof:placetype":"venue"
},
  "geometry": {"coordinates":[145.00860595699999,-37.7169418335],"type":"Point"}
}