{
  "type": "Feature",
  "properties": {
    "iso:country":"AU",
    "sg:address":"PO Box 990",
    "sg:city":"Bowen",
    "sg:classifiers":[
        {
            "category":"Building & Trades",
            "subcategory":"Equipment Rental",
            "type":"Services"
        }
    ],
    "sg:phone":"+61 428 488 153",
    "sg:postcode":"4805",
    "sg:province":"QLD",
    "sg:tags":[
        "crane",
        "hire"
    ],
    "wof:name":"Bowen Crane Hire",
    "wof:placetype":"venue"
},
  "geometry": {"coordinates":[148.22084045400001,-20.0146598816],"type":"Point"}
}