{
  "type": "Feature",
  "properties": {
    "addr:full":"Shop 11 Pick &#039;n&#039; Pay Hypermarket, Albany Aspley QLD 4034",
    "addr:housenumber":"shop 11",
    "addr:postcode":"4034",
    "iso:country":"AU",
    "sg:address":"Shop 11 Pick &#039;n&#039; Pay Hypermarket, Albany",
    "sg:city":"Aspley",
    "sg:classifiers":[
        {
            "category":"Shopping",
            "type":"Retail Goods"
        }
    ],
    "sg:phone":"+61 7 3263 4277",
    "sg:postcode":"4034",
    "sg:province":"QLD",
    "sg:tags":[
        "repair",
        "travel"
    ],
    "wof:name":"Colorado Bag Co. Stores",
    "wof:placetype":"venue"
},
  "geometry": {"coordinates":[153.01719700000001,-27.365219],"type":"Point"}
}