{
  "type": "Feature",
  "properties": {
    "iso:country":"AU",
    "sg:address":"Grnd Flr, 4 High St",
    "sg:city":"Cranbourne",
    "sg:classifiers":[
        {
            "category":"Banks & Credit Unions",
            "subcategory":"Financial Services",
            "type":"Services"
        }
    ],
    "sg:phone":"+61 3 5996 4900",
    "sg:postcode":"3977",
    "sg:province":"VIC",
    "sg:tags":[
        "loan",
        "finance",
        "mortgage"
    ],
    "wof:name":"Wizard",
    "wof:placetype":"venue"
},
  "geometry": {"coordinates":[145.28367614699999,-38.1087608337],"type":"Point"}
}