{
  "type": "Feature",
  "properties": {
    "addr:full":"6 King Drv Horsham VIC 3400",
    "addr:housenumber":"6",
    "addr:postcode":"3400",
    "addr:street":"King Drv",
    "iso:country":"AU",
    "sg:address":"6 King Drv",
    "sg:city":"Horsham",
    "sg:classifiers":[
        {
            "category":"Wholesale",
            "subcategory":"Furniture",
            "type":"Manufacturing & Wholesale Goods"
        }
    ],
    "sg:phone":"+61 3 5381 1404",
    "sg:postcode":"3400",
    "sg:province":"VIC",
    "sg:tags":[
        "wholesaler",
        "mfrs"
    ],
    "wof:name":"Oscar Furniture Pty Ltd",
    "wof:placetype":"venue"
},
  "geometry": {"coordinates":[142.194702148,-36.735168457],"type":"Point"}
}