{
  "type": "Feature",
  "properties": {
    "addr:full":"Studio 1/29 Wellington Road Mt Barker SA 5251",
    "addr:housenumber":"29",
    "addr:postcode":"5251",
    "addr:street":"Wellington Road",
    "iso:country":"AU",
    "sg:address":"Studio 1/29 Wellington Road",
    "sg:city":"Mt Barker",
    "sg:classifiers":[
        {
            "category":"Health Services",
            "subcategory":"Health Practitioner",
            "type":"Services"
        }
    ],
    "sg:phone":"+61 8 8391 1212",
    "sg:postcode":"5251",
    "sg:province":"SA",
    "sg:tags":[
        "physiotherapist"
    ],
    "wof:name":"Hunt Sheree & Associates",
    "wof:placetype":"venue"
},
  "geometry": {"coordinates":[138.86627197300001,-35.0797271729],"type":"Point"}
}