{
  "type": "Feature",
  "properties": {
    "addr:full":"Gabon St Stafford QLD 4053",
    "addr:postcode":"4053",
    "addr:street":"Gabon St",
    "iso:country":"AU",
    "sg:address":"Gabon St",
    "sg:city":"Stafford",
    "sg:classifiers":[
        {
            "category":"Education",
            "subcategory":"Special Training",
            "type":"Public Place"
        }
    ],
    "sg:phone":"+61 7 3256 4021",
    "sg:postcode":"4053",
    "sg:province":"QLD",
    "sg:tags":[
        "drama",
        "speech",
        "speaking",
        "tuition"
    ],
    "wof:name":"Johns Melissa",
    "wof:placetype":"venue"
},
  "geometry": {"coordinates":[153.01057434099999,-27.4050674438],"type":"Point"}
}