{
  "type": "Feature",
  "properties": {
    "addr:full":"391 Commercial Rd Moana SA 5169",
    "addr:housenumber":"391",
    "addr:postcode":"5169",
    "addr:street":"Commercial Rd",
    "iso:country":"AU",
    "sg:address":"391 Commercial Rd",
    "sg:city":"Moana",
    "sg:classifiers":[
        {
            "category":"Building & Trades",
            "subcategory":"Construction",
            "type":"Services"
        }
    ],
    "sg:phone":"+61 8 8386 1111",
    "sg:postcode":"5169",
    "sg:province":"SA",
    "sg:tags":[
        "bitumen",
        "paving",
        "asphalt"
    ],
    "wof:name":"Care Constructions",
    "wof:placetype":"venue"
},
  "geometry": {"coordinates":[138.477752686,-35.195854187],"type":"Point"}
}