{
  "type": "Feature",
  "properties": {
    "addr:full":"16 Grand Plaza Drv Browns Plains QLD 4118",
    "addr:housenumber":"16",
    "addr:postcode":"4118",
    "addr:street":"Grand Plaza Drv",
    "iso:country":"AU",
    "sg:address":"16 Grand Plaza Drv",
    "sg:city":"Browns Plains",
    "sg:classifiers":[
        {
            "category":"Retail",
            "subcategory":"Car Wash",
            "type":"Services"
        }
    ],
    "sg:phone":"+61 7 3809 2022",
    "sg:postcode":"4118",
    "sg:province":"QLD",
    "sg:tags":[
        "truck",
        "cleaning"
    ],
    "wof:name":"Oasis Car Wash Pty Ltd",
    "wof:placetype":"venue"
},
  "geometry": {"coordinates":[153.03775024399999,-27.6644439697],"type":"Point"}
}