{
  "type": "Feature",
  "properties": {
    "addr:full":"30 Prospect St Fortitude Valley QLD 4006",
    "addr:housenumber":"30",
    "addr:postcode":"4006",
    "addr:street":"Prospect St",
    "iso:country":"AU",
    "sg:address":"30 Prospect St",
    "sg:city":"Fortitude Valley",
    "sg:classifiers":[
        {
            "category":"Professional",
            "subcategory":"Business Services",
            "type":"Services"
        }
    ],
    "sg:phone":"+61 7 3252 2666",
    "sg:postcode":"4006",
    "sg:province":"QLD",
    "sg:tags":[
        "small",
        "advisory"
    ],
    "wof:name":"Liquor & Gaming Specialists Pty Ltd",
    "wof:placetype":"venue"
},
  "geometry": {"coordinates":[153.03826904300001,-27.4509811401],"type":"Point"}
}