{
  "type": "Feature",
  "properties": {
    "addr:full":"21 Ryan Ave Singleton NSW 2330",
    "addr:housenumber":"21",
    "addr:postcode":"2330",
    "addr:street":"Ryan Ave",
    "iso:country":"AU",
    "sg:address":"21 Ryan Ave",
    "sg:city":"Singleton",
    "sg:classifiers":[
        {
            "category":"Cinema",
            "subcategory":"Movie Theater",
            "type":"Entertainment"
        }
    ],
    "sg:phone":"+61 2 6571 5253",
    "sg:postcode":"2330",
    "sg:province":"NSW",
    "wof:name":"Rose Point Cinemas",
    "wof:placetype":"venue"
},
  "geometry": {"coordinates":[151.163284,-32.568653],"type":"Point"}
}