{
  "type": "Feature",
  "properties": {
    "addr:full":"45 Exhibition St McKinnon VIC 3204",
    "addr:housenumber":"45",
    "addr:postcode":"3204",
    "addr:street":"Exhibition St",
    "iso:country":"AU",
    "sg:address":"45 Exhibition St",
    "sg:city":"McKinnon",
    "sg:classifiers":[
        {
            "category":"Building & Trades",
            "subcategory":"Construction",
            "type":"Services"
        }
    ],
    "sg:phone":"+61 411 616 129",
    "sg:postcode":"3204",
    "sg:province":"VIC",
    "sg:tags":[
        "joiner",
        "carpenter"
    ],
    "wof:name":"B M J Complete Carpentry Pty Ltd",
    "wof:placetype":"venue"
},
  "geometry": {"coordinates":[145.03694200000001,-37.912449],"type":"Point"}
}