{
  "type": "Feature",
  "properties": {
    "iso:country":"AU",
    "sg:address":"65 Herron Crs",
    "sg:city":"Latham",
    "sg:classifiers":[
        {
            "category":"Utilities",
            "subcategory":"Refuse",
            "type":"Services"
        }
    ],
    "sg:phone":"+61 2 6254 0671",
    "sg:postcode":"2615",
    "sg:province":"ACT",
    "sg:tags":[
        "remover",
        "rubbish"
    ],
    "wof:name":"Herron Cleaning Services",
    "wof:placetype":"venue"
},
  "geometry": {"coordinates":[149.03184509299999,-35.219039917],"type":"Point"}
}