{
  "type": "Feature",
  "properties": {
    "addr:full":"29 Erskine St Macquarie ACT 2614",
    "addr:housenumber":"29",
    "addr:postcode":"2614",
    "addr:street":"Erskine St",
    "iso:country":"AU",
    "sg:address":"29 Erskine St",
    "sg:city":"Macquarie",
    "sg:classifiers":[
        {
            "category":"Professional",
            "subcategory":"Management & Consulting",
            "type":"Services"
        }
    ],
    "sg:phone":"+61 1800 888 789",
    "sg:postcode":"2614",
    "sg:province":"ACT",
    "sg:tags":[
        "consultant",
        "migration"
    ],
    "wof:name":"Greg Bowler & Associates Pty Ltd",
    "wof:placetype":"venue"
},
  "geometry": {"coordinates":[149.05781555199999,-35.2511482239],"type":"Point"}
}