{
  "type": "Feature",
  "properties": {
    "iso:country":"AU",
    "sg:address":"Level 19, 323 Castlereagh St",
    "sg:city":"Sydney",
    "sg:classifiers":[
        {
            "category":"Professional",
            "subcategory":"Employment Agencies",
            "type":"Services"
        }
    ],
    "sg:phone":"+61 2 9281 1111",
    "sg:postcode":"2000",
    "sg:province":"NSW",
    "sg:tags":[
        "provider",
        "internet"
    ],
    "wof:name":"Dot Communications Internet Services Pty Ltd",
    "wof:placetype":"venue"
},
  "geometry": {"coordinates":[151.20829773,-33.8797225952],"type":"Point"}
}