{
  "type": "Feature",
  "properties": {
    "addr:full":"59 Ferguson St Brighton TAS 7030",
    "addr:housenumber":"59",
    "addr:postcode":"7030",
    "addr:street":"Ferguson St",
    "iso:country":"AU",
    "sg:address":"59 Ferguson St",
    "sg:city":"Brighton",
    "sg:classifiers":[
        {
            "category":"Wholesale",
            "subcategory":"Farm Supplies",
            "type":"Manufacturing & Wholesale Goods"
        }
    ],
    "sg:phone":"+61 3 6268 1285",
    "sg:postcode":"7030",
    "sg:province":"TAS",
    "sg:tags":[
        "equipment"
    ],
    "wof:name":"Fehlberg's Produce",
    "wof:placetype":"venue"
},
  "geometry": {"coordinates":[147.22874450699999,-42.6952896118],"type":"Point"}
}