{
  "type": "Feature",
  "properties": {
    "iso:country":"AU",
    "sg:address":"79 Boat Harbour Drv",
    "sg:city":"Pialba",
    "sg:classifiers":[
        {
            "category":"Travel",
            "subcategory":"Travel Agent",
            "type":"Entertainment"
        }
    ],
    "sg:phone":"+61 7 4124 2222",
    "sg:postcode":"4655",
    "sg:province":"QLD",
    "sg:tags":[
        "consultant"
    ],
    "wof:name":"Travelworld",
    "wof:placetype":"venue"
},
  "geometry": {"coordinates":[152.837555,-25.2904],"type":"Point"}
}