{
  "type": "Feature",
  "properties": {
    "addr:full":"35 Blaxland Rd Macquarie Hills NSW 2285",
    "addr:housenumber":"35",
    "addr:postcode":"2285",
    "addr:street":"Blaxland Rd",
    "iso:country":"AU",
    "sg:address":"35 Blaxland Rd",
    "sg:city":"Macquarie Hills",
    "sg:classifiers":[
        {
            "category":"Health Services",
            "subcategory":"Health Practitioner",
            "type":"Services"
        }
    ],
    "sg:phone":"+61 2 4956 9129",
    "sg:postcode":"2285",
    "sg:province":"NSW",
    "sg:tags":[
        "physiotherapist"
    ],
    "wof:name":"Aldavilla Physiotherapy",
    "wof:placetype":"venue"
},
  "geometry": {"coordinates":[151.65162658700001,-32.9574241638],"type":"Point"}
}