{
  "type": "Feature",
  "properties": {
    "iso:country":"AU",
    "sg:address":"PO Box 356",
    "sg:city":"Goulburn",
    "sg:classifiers":[
        {
            "category":"Building & Trades",
            "subcategory":"Landscaping Services",
            "type":"Services"
        }
    ],
    "sg:phone":"+61 438 932 965",
    "sg:postcode":"2580",
    "sg:province":"NSW",
    "sg:tags":[
        "consultant"
    ],
    "wof:name":"Asset Building Consultants Pty Ltd.",
    "wof:placetype":"venue"
},
  "geometry": {"coordinates":[149.716262817,-34.7571792603],"type":"Point"}
}