{
  "type": "Feature",
  "properties": {
    "addr:full":"36 Wagtail Drv Regency Downs QLD 4341",
    "addr:housenumber":"36",
    "addr:postcode":"4341",
    "addr:street":"Wagtail Drv",
    "iso:country":"AU",
    "sg:address":"36 Wagtail Drv",
    "sg:city":"Regency Downs",
    "sg:classifiers":[
        {
            "category":"Home & Garden",
            "subcategory":"Kitchen Supply",
            "type":"Retail Goods"
        }
    ],
    "sg:phone":"+61 427 716 689",
    "sg:postcode":"4341",
    "sg:province":"QLD",
    "sg:tags":[
        "sharpening"
    ],
    "wof:name":"Terry Barling",
    "wof:placetype":"venue"
},
  "geometry": {"coordinates":[152.441894531,-27.5244998932],"type":"Point"}
}