{
  "type": "Feature",
  "properties": {
    "addr:full":"Corner South Rd & Glasgow St Wingfield SA 5013",
    "addr:postcode":"5013",
    "addr:street":"South Rd & Glasgow St",
    "iso:country":"AU",
    "sg:address":"Corner South Rd & Glasgow St",
    "sg:city":"Wingfield",
    "sg:classifiers":[
        {
            "category":"Home & Garden",
            "subcategory":"Kitchen Supply",
            "type":"Retail Goods"
        }
    ],
    "sg:phone":"+61 1800 724 172",
    "sg:postcode":"5013",
    "sg:province":"SA",
    "sg:tags":[
        "traffic",
        "equipment",
        "safety",
        "road"
    ],
    "wof:name":"Armco Civil Products Pty Ltd",
    "wof:placetype":"venue"
},
  "geometry": {"coordinates":[138.564453125,-34.8483848572],"type":"Point"}
}