{
  "type": "Feature",
  "properties": {
    "addr:full":"27 Anderson Drv Tarro NSW 2322",
    "addr:housenumber":"27",
    "addr:postcode":"2322",
    "addr:street":"Anderson Drv",
    "iso:country":"AU",
    "sg:address":"27 Anderson Drv",
    "sg:city":"Tarro",
    "sg:classifiers":[
        {
            "category":"Banks & Credit Unions",
            "subcategory":"Financial Services",
            "type":"Services"
        }
    ],
    "sg:phone":"+61 2 4966 4785",
    "sg:postcode":"2322",
    "sg:province":"NSW",
    "sg:tags":[
        "planning"
    ],
    "wof:name":"Charlestown Financial Services Pty Ltd",
    "wof:placetype":"venue"
},
  "geometry": {"coordinates":[151.66644287099999,-32.8097076416],"type":"Point"}
}