{
  "type": "Feature",
  "properties": {
    "iso:country":"AU",
    "sg:address":"Shop 4, 76-78 Bathurst St",
    "sg:city":"Liverpool",
    "sg:classifiers":[
        {
            "category":"Personal",
            "subcategory":"Tanning Parlor",
            "type":"Services"
        }
    ],
    "sg:phone":"+61 2 9821 4484",
    "sg:postcode":"2170",
    "sg:province":"NSW",
    "sg:tags":[
        "solarium"
    ],
    "wof:name":"Oasis Tanning Centre Pty Ltd",
    "wof:placetype":"venue"
},
  "geometry": {"coordinates":[150.921188355,-33.9236717224],"type":"Point"}
}