{
  "type": "Feature",
  "properties": {
    "addr:full":"PO Box 250 Landsborough QLD 4550",
    "addr:postcode":"4550",
    "iso:country":"AU",
    "sg:address":"PO Box 250",
    "sg:city":"Landsborough",
    "sg:classifiers":[
        {
            "category":"Professional",
            "subcategory":"Research",
            "type":"Services"
        }
    ],
    "sg:phone":"+61 7 5439 9993",
    "sg:postcode":"4550",
    "sg:province":"QLD",
    "sg:tags":[
        "market"
    ],
    "wof:name":"The Secret Shopper Mystery Shoppers",
    "wof:placetype":"venue"
},
  "geometry": {"coordinates":[152.96539306599999,-26.8091907501],"type":"Point"}
}