{
  "type": "Feature",
  "properties": {
    "addr:full":"60 Kolora Rd Heidelberg West VIC 3081",
    "addr:housenumber":"60",
    "addr:postcode":"3081",
    "addr:street":"Kolora Rd",
    "iso:country":"AU",
    "sg:address":"60 Kolora Rd",
    "sg:city":"Heidelberg West",
    "sg:classifiers":[
        {
            "category":"Professional",
            "type":"Services"
        }
    ],
    "sg:phone":"+61 3 9459 2333",
    "sg:postcode":"3081",
    "sg:province":"VIC",
    "sg:tags":[
        "packaging",
        "filling",
        "assembling"
    ],
    "wof:name":"CSW Technologies",
    "wof:placetype":"venue"
},
  "geometry": {"coordinates":[145.045974731,-37.7328567505],"type":"Point"}
}