{
  "type": "Feature",
  "properties": {
    "addr:full":"26 Dividend St Mansfield QLD 4122",
    "addr:housenumber":"26",
    "addr:postcode":"4122",
    "addr:street":"Dividend St",
    "iso:country":"AU",
    "sg:address":"26 Dividend St",
    "sg:city":"Mansfield",
    "sg:classifiers":[
        {
            "category":"Manufacturing",
            "subcategory":"Tools & Machinery",
            "type":"Manufacturing & Wholesale Goods"
        }
    ],
    "sg:phone":"+61 7 3849 1553",
    "sg:postcode":"4122",
    "sg:province":"QLD",
    "sg:tags":[
        "earth",
        "excavating",
        "moving",
        "equipment"
    ],
    "wof:name":"Avant Mini Loaders (Qld)",
    "wof:placetype":"venue"
},
  "geometry": {"coordinates":[153.10392761200001,-27.5314254761],"type":"Point"}
}