{
  "type": "Feature",
  "properties": {
    "addr:full":"2/ 87 Webster Rd Stafford QLD 4053",
    "addr:housenumber":"/ 87",
    "addr:postcode":"4053",
    "addr:street":"Webster Rd",
    "iso:country":"AU",
    "sg:address":"2/ 87 Webster Rd",
    "sg:city":"Stafford",
    "sg:classifiers":[
        {
            "category":"Wholesale",
            "subcategory":"Electrical",
            "type":"Manufacturing & Wholesale Goods"
        }
    ],
    "sg:phone":"+61 7 3552 7600",
    "sg:postcode":"4053",
    "sg:province":"QLD",
    "sg:tags":[
        "wholesaler"
    ],
    "wof:name":"Cetnaj",
    "wof:placetype":"venue"
},
  "geometry": {"coordinates":[153.01626586899999,-27.4153842926],"type":"Point"}
}