{
  "type": "Feature",
  "properties": {
    "addr:full":"Shop 19 Centrepoint Plaza Bulcock St Caloundra Caloundra QLD 4551",
    "addr:housenumber":"shop 19",
    "addr:postcode":"4551",
    "addr:street":"Centrepoint Plaza Bulcock St",
    "iso:country":"AU",
    "sg:address":"Shop 19 Centrepoint Plaza Bulcock St Caloundra",
    "sg:city":"Caloundra",
    "sg:classifiers":[
        {
            "category":"Health Services",
            "subcategory":"Health Practitioner",
            "type":"Services"
        }
    ],
    "sg:phone":"+61 7 5438 0688",
    "sg:postcode":"4551",
    "sg:province":"QLD",
    "sg:tags":[
        "bowen",
        "therapy"
    ],
    "wof:name":"Marilyn Boulton",
    "wof:placetype":"venue"
},
  "geometry": {"coordinates":[153.12538147000001,-26.8044376373],"type":"Point"}
}