{
  "type": "Feature",
  "properties": {
    "addr:full":"3/ 24 Chester St Oakleigh VIC 3166",
    "addr:housenumber":"/ 24",
    "addr:postcode":"3166",
    "addr:street":"Chester St",
    "iso:country":"AU",
    "sg:address":"3/ 24 Chester St",
    "sg:city":"Oakleigh",
    "sg:classifiers":[
        {
            "category":"Professional",
            "subcategory":"Employment Agencies",
            "type":"Services"
        }
    ],
    "sg:phone":"+61 3 9563 4407",
    "sg:postcode":"3166",
    "sg:province":"VIC",
    "wof:name":"Job Futures",
    "wof:placetype":"venue"
},
  "geometry": {"coordinates":[145.09068298299999,-37.8996582031],"type":"Point"}
}