{
  "type": "Feature",
  "properties": {
    "addr:full":"9 Wetherill St South Lidcombe NSW 2141",
    "addr:housenumber":"9",
    "addr:postcode":"2141",
    "addr:street":"Wetherill St South",
    "iso:country":"AU",
    "sg:address":"9 Wetherill St South",
    "sg:city":"Lidcombe",
    "sg:classifiers":[
        {
            "category":"Manufacturing",
            "subcategory":"Glass & Minerals",
            "type":"Manufacturing & Wholesale Goods"
        }
    ],
    "sg:phone":"+61 416 248 439",
    "sg:postcode":"2141",
    "sg:province":"NSW",
    "sg:tags":[
        "merchant",
        "granite",
        "marble"
    ],
    "wof:name":"Decoreno Pty Ltd",
    "wof:placetype":"venue"
},
  "geometry": {"coordinates":[151.04493713400001,-33.8454475403],"type":"Point"}
}