{
  "type": "Feature",
  "properties": {
    "addr:full":"19 Massey St Gladesville NSW 1675",
    "addr:housenumber":"19",
    "addr:postcode":"1675",
    "addr:street":"Massey St",
    "iso:country":"AU",
    "sg:address":"19 Massey St",
    "sg:city":"Gladesville",
    "sg:classifiers":[
        {
            "category":"Real Estate",
            "subcategory":"Surveying",
            "type":"Services"
        }
    ],
    "sg:phone":"+61 2 9879 6077",
    "sg:postcode":"1675",
    "sg:province":"NSW",
    "sg:tags":[
        "surveyor",
        "land"
    ],
    "wof:name":"Lockley Land Title Solutions",
    "wof:placetype":"venue"
},
  "geometry": {"coordinates":[151.128662109,-33.8302612305],"type":"Point"}
}