{
  "type": "Feature",
  "properties": {
    "iso:country":"AU",
    "sg:address":"22 - 24 Mitchell St",
    "sg:city":"Wodonga",
    "sg:classifiers":[
        {
            "category":"Education",
            "subcategory":"School",
            "type":"Public Place"
        }
    ],
    "sg:phone":"+61 2 6024 1600",
    "sg:postcode":"3690",
    "sg:province":"VIC",
    "sg:tags":[
        "state",
        "-",
        "nsw"
    ],
    "wof:name":"Wodonga Middle Years College",
    "wof:placetype":"venue"
},
  "geometry": {"coordinates":[146.89064025900001,-36.1297187805],"type":"Point"}
}