{
  "type": "Feature",
  "properties": {
    "addr:full":"193 Sydney Rd Coburg VIC 3058",
    "addr:housenumber":"193",
    "addr:postcode":"3058",
    "addr:street":"Sydney Rd",
    "iso:country":"AU",
    "sg:address":"193 Sydney Rd",
    "sg:city":"Coburg",
    "sg:classifiers":[
        {
            "category":"Manufacturing",
            "subcategory":"Soap",
            "type":"Manufacturing & Wholesale Goods"
        }
    ],
    "sg:phone":"+61 3 9383 2646",
    "sg:postcode":"3058",
    "sg:province":"VIC",
    "sg:tags":[
        "detergent"
    ],
    "wof:name":"Crystalwhite Detergents Pty Ltd",
    "wof:placetype":"venue"
},
  "geometry": {"coordinates":[144.964935303,-37.7498931885],"type":"Point"}
}