{
  "type": "Feature",
  "properties": {
    "iso:country":"AU",
    "sg:address":"791 Glenhuntly Rd",
    "sg:city":"Caulfield South",
    "sg:classifiers":[
        {
            "category":"Fast Food",
            "type":"Food & Drink"
        }
    ],
    "sg:phone":"+61 3 9523 8473",
    "sg:postcode":"3162",
    "sg:province":"VIC",
    "sg:tags":[
        "away",
        "take"
    ],
    "wof:name":"Chooks Corner",
    "wof:placetype":"venue"
},
  "geometry": {"coordinates":[145.021774292,-37.8867225647],"type":"Point"}
}