{
  "type": "Feature",
  "properties": {
    "addr:full":"15 Alice St Atherton QLD 4883",
    "addr:housenumber":"15",
    "addr:postcode":"4883",
    "addr:street":"Alice St",
    "iso:country":"AU",
    "sg:address":"15 Alice St",
    "sg:city":"Atherton",
    "sg:classifiers":[
        {
            "category":"Health Services",
            "subcategory":"Doctor",
            "type":"Services"
        }
    ],
    "sg:phone":"+61 7 4091 3122",
    "sg:postcode":"4883",
    "sg:province":"QLD",
    "sg:tags":[
        "medical",
        "practitioner"
    ],
    "wof:name":"Alice Street Medical Centre",
    "wof:placetype":"venue"
},
  "geometry": {"coordinates":[145.47914123499999,-17.264837265],"type":"Point"}
}