{
  "type": "Feature",
  "properties": {
    "addr:full":"Croudace St Lambton NSW 2299",
    "addr:postcode":"2299",
    "addr:street":"St",
    "iso:country":"AU",
    "sg:address":"Croudace St",
    "sg:city":"Lambton",
    "sg:classifiers":[
        {
            "category":"Education",
            "subcategory":"School",
            "type":"Public Place"
        }
    ],
    "sg:phone":"+61 2 4957 1667",
    "sg:postcode":"2299",
    "sg:province":"NSW",
    "sg:tags":[
        "state",
        "-",
        "nsw"
    ],
    "wof:name":"Lambton Primary",
    "wof:placetype":"venue"
},
  "geometry": {"coordinates":[151.705154419,-32.910194397],"type":"Point"}
}