{
  "type": "Feature",
  "properties": {
    "addr:full":"Shop 3 9 El Alemein Rd Port Augusta SA 5700",
    "addr:housenumber":"shop;9",
    "addr:postcode":"5700",
    "addr:street":"El Alemein Rd",
    "iso:country":"AU",
    "sg:address":"Shop 3 9 El Alemein Rd",
    "sg:city":"Port Augusta",
    "sg:classifiers":[
        {
            "category":"Shopping",
            "subcategory":"Clothing, Apparel, & Fashions",
            "type":"Retail Goods"
        }
    ],
    "sg:phone":"+61 8 8641 1511",
    "sg:postcode":"5700",
    "sg:province":"SA",
    "sg:tags":[
        "sportswear"
    ],
    "wof:name":"Mark Hanlon Sportscene",
    "wof:placetype":"venue"
},
  "geometry": {"coordinates":[137.76036071799999,-32.4911460876],"type":"Point"}
}