{
  "type": "Feature",
  "properties": {
    "addr:full":"246 Botany Rd Alexandria NSW 2015",
    "addr:housenumber":"246",
    "addr:postcode":"2015",
    "addr:street":"Botany Rd",
    "iso:country":"AU",
    "sg:address":"246 Botany Rd",
    "sg:city":"Alexandria",
    "sg:classifiers":[
        {
            "category":"Travel",
            "subcategory":"Hotels & Motels",
            "type":"Entertainment"
        }
    ],
    "sg:phone":"+61 2 9698 2832",
    "sg:postcode":"2015",
    "sg:province":"NSW",
    "sg:tags":[
        "accommodation"
    ],
    "wof:name":"Glenroy Hotel",
    "wof:placetype":"venue"
},
  "geometry": {"coordinates":[151.20150756800001,-33.9024887085],"type":"Point"}
}