{
  "type": "Feature",
  "properties": {
    "addr:full":"43 Brodie St Rydalmere NSW 2116",
    "addr:housenumber":"43",
    "addr:postcode":"2116",
    "addr:street":"Brodie St",
    "iso:country":"AU",
    "sg:address":"43 Brodie St",
    "sg:city":"Rydalmere",
    "sg:classifiers":[
        {
            "category":"Utilities",
            "type":"Services"
        }
    ],
    "sg:phone":"+61 2 9684 2022",
    "sg:postcode":"2116",
    "sg:province":"NSW",
    "sg:tags":[
        "refrigeration",
        "industrial",
        "commercial",
        "retail"
    ],
    "wof:name":"Artisan Food Equipment",
    "wof:placetype":"venue"
},
  "geometry": {"coordinates":[151.01846313499999,-33.901008606],"type":"Point"}
}