{
  "type": "Feature",
  "properties": {
    "addr:full":"Bi-Lo Centre Kelly St Scone NSW 2337",
    "addr:postcode":"2337",
    "addr:street":"Kelly St",
    "iso:country":"AU",
    "sg:address":"Bi-Lo Centre Kelly St",
    "sg:city":"Scone",
    "sg:classifiers":[
        {
            "category":"Food & Beverages",
            "subcategory":"Liquor & Beverages",
            "type":"Retail Goods"
        }
    ],
    "sg:phone":"+61 2 6545 1025",
    "sg:postcode":"2337",
    "sg:province":"NSW",
    "sg:tags":[
        "merchant",
        "spirit",
        "wine"
    ],
    "wof:name":"Scone Cellars",
    "wof:placetype":"venue"
},
  "geometry": {"coordinates":[150.86782836899999,-32.0457382202],"type":"Point"}
}