{
  "type": "Feature",
  "properties": {
    "iso:country":"AU",
    "sg:address":"33 Smith St",
    "sg:city":"North Hobart",
    "sg:classifiers":[
        {
            "category":"Professional",
            "type":"Services"
        }
    ],
    "sg:phone":"+61 3 6231 9331",
    "sg:postcode":"7000",
    "sg:province":"TAS",
    "sg:tags":[
        "marine",
        "contractor"
    ],
    "wof:name":"ASD Contractors",
    "wof:placetype":"venue"
},
  "geometry": {"coordinates":[147.31893920900001,-42.8720436096],"type":"Point"}
}