{
  "type": "Feature",
  "properties": {
    "iso:country":"AU",
    "sg:address":"West Brisbane Clinic 114",
    "sg:city":"Enoggera Tce Paddington",
    "sg:classifiers":[
        {
            "category":"Health Services",
            "subcategory":"Health Practitioner",
            "type":"Services"
        }
    ],
    "sg:phone":"+61 7 3369 3922",
    "sg:postcode":"4064",
    "sg:province":"QLD",
    "sg:tags":[
        "dietitian"
    ],
    "wof:name":"Kate Di Prima",
    "wof:placetype":"venue"
},
  "geometry": {"coordinates":[153.001464844,-27.4572563171],"type":"Point"}
}