{
  "type": "Feature",
  "properties": {
    "iso:country":"AU",
    "sg:address":"1180 Centre Rd",
    "sg:city":"Clayton South",
    "sg:classifiers":[
        {
            "category":"Health Services",
            "subcategory":"Health Practitioner",
            "type":"Services"
        }
    ],
    "sg:phone":"+61 3 9544 2220",
    "sg:postcode":"3169",
    "sg:province":"VIC",
    "sg:tags":[
        "physiotherapist"
    ],
    "wof:name":"Greg Varigos Physiotherapy & Sports Medicine Clinic",
    "wof:placetype":"venue"
},
  "geometry": {"coordinates":[145.10426330600001,-37.9268188477],"type":"Point"}
}