{
  "type": "Feature",
  "properties": {
    "addr:full":"245 Warners Bay Rd Mt Hutton NSW 2290",
    "addr:housenumber":"245",
    "addr:postcode":"2290",
    "addr:street":"Warners Bay Rd",
    "iso:country":"AU",
    "sg:address":"245 Warners Bay Rd",
    "sg:city":"Mt Hutton",
    "sg:classifiers":[
        {
            "category":"Education",
            "subcategory":"Special Training",
            "type":"Public Place"
        }
    ],
    "sg:phone":"+61 2 4948 8933",
    "sg:postcode":"2290",
    "sg:province":"NSW",
    "sg:tags":[
        "tuition-educational"
    ],
    "wof:name":"Top Tuition",
    "wof:placetype":"venue"
},
  "geometry": {"coordinates":[151.66867065400001,-32.9816398621],"type":"Point"}
}