{
  "type": "Feature",
  "properties": {
    "addr:full":"3 Deepdale St Dandenong VIC 3175",
    "addr:housenumber":"3",
    "addr:postcode":"3175",
    "addr:street":"Deepdale St",
    "iso:country":"AU",
    "sg:address":"3 Deepdale St",
    "sg:city":"Dandenong",
    "sg:classifiers":[
        {
            "category":"Autos & Motor Vehicles",
            "subcategory":"Recreational Vehicle Sales",
            "type":"Retail Goods"
        }
    ],
    "sg:phone":"+61 3 9792 2977",
    "sg:postcode":"3175",
    "sg:province":"VIC",
    "sg:tags":[
        "industrial",
        "sewing",
        "contractor"
    ],
    "wof:name":"Abicat",
    "wof:placetype":"venue"
},
  "geometry": {"coordinates":[145.21157836899999,-38.0004692078],"type":"Point"}
}