{
  "type": "Feature",
  "properties": {
    "addr:full":"355 Stannix Park Rd Ebenezer NSW 2756",
    "addr:housenumber":"355",
    "addr:postcode":"2756",
    "addr:street":"Stannix Park Rd",
    "iso:country":"AU",
    "sg:address":"355 Stannix Park Rd",
    "sg:city":"Ebenezer",
    "sg:classifiers":[
        {
            "category":"Shopping Center",
            "type":"Public Place"
        }
    ],
    "sg:phone":"+61 2 4579 8333",
    "sg:postcode":"2756",
    "sg:province":"NSW",
    "sg:tags":[
        "spawn",
        "supplier",
        "mushroom"
    ],
    "wof:name":"Grange Growing Solutions Pty Ltd",
    "wof:placetype":"venue"
},
  "geometry": {"coordinates":[150.860961914,-33.5340232849],"type":"Point"}
}