{
  "type": "Feature",
  "properties": {
    "addr:full":"25 Main St Greensborough VIC 3088",
    "addr:housenumber":"25",
    "addr:postcode":"3088",
    "addr:street":"Main St",
    "iso:country":"AU",
    "sg:address":"25 Main St",
    "sg:city":"Greensborough",
    "sg:classifiers":[
        {
            "category":"Shopping",
            "subcategory":"Clothing, Apparel, & Fashions",
            "type":"Retail Goods"
        }
    ],
    "sg:phone":"+61 3 9432 3418",
    "sg:postcode":"3088",
    "sg:province":"VIC",
    "sg:tags":[
        "lady",
        "wear"
    ],
    "wof:name":"Sussan Corporation (Aust) Pty Ltd",
    "wof:placetype":"venue"
},
  "geometry": {"coordinates":[145.103393555,-37.7037506104],"type":"Point"}
}