{
  "type": "Feature",
  "properties": {
    "addr:full":"39b Munibung Rd Cardiff NSW 2285",
    "addr:housenumber":"39b",
    "addr:postcode":"2285",
    "addr:street":"Munibung Rd",
    "iso:country":"AU",
    "sg:address":"39b Munibung Rd",
    "sg:city":"Cardiff",
    "sg:classifiers":[
        {
            "category":"Autos & Motor Vehicles",
            "subcategory":"Boat Sales",
            "type":"Retail Goods"
        }
    ],
    "sg:phone":"+61 2 4956 8522",
    "sg:postcode":"2285",
    "sg:province":"NSW",
    "sg:tags":[
        "builder",
        "yacht",
        "repairer"
    ],
    "wof:name":"Bluewater Cruising Yachts Pty Ltd",
    "wof:placetype":"venue"
},
  "geometry": {"coordinates":[151.65034484899999,-32.9429931641],"type":"Point"}
}