{
  "type": "Feature",
  "properties": {
    "addr:full":"Lomas La Nulkaba NSW 2325",
    "addr:postcode":"2325",
    "addr:street":"Lomas",
    "iso:country":"AU",
    "sg:address":"Lomas La",
    "sg:city":"Nulkaba",
    "sg:classifiers":[
        {
            "category":"Shopping",
            "subcategory":"Hobbies, Toys, & Games",
            "type":"Retail Goods"
        }
    ],
    "sg:phone":"+61 2 4990 3055",
    "sg:postcode":"2325",
    "sg:province":"NSW",
    "sg:tags":[
        "farmer"
    ],
    "wof:name":"Glen Doone Ostrich Enterprise",
    "wof:placetype":"venue"
},
  "geometry": {"coordinates":[151.35943603499999,-32.7947425842],"type":"Point"}
}