{
  "type": "Feature",
  "properties": {
    "addr:full":"79 Gheringhap St Geelong VIC 3220",
    "addr:housenumber":"79",
    "addr:postcode":"3220",
    "addr:street":"Gheringhap St",
    "iso:country":"AU",
    "sg:address":"79 Gheringhap St",
    "sg:city":"Geelong",
    "sg:classifiers":[
        {
            "category":"Professional",
            "subcategory":"Accounting & Tax Preparation",
            "type":"Services"
        }
    ],
    "sg:phone":"+61 3 5222 4522",
    "sg:postcode":"3220",
    "sg:province":"VIC",
    "sg:tags":[
        "consultant",
        "taxation"
    ],
    "wof:name":"West Carr & Harvey",
    "wof:placetype":"venue"
},
  "geometry": {"coordinates":[144.356583,-38.150532],"type":"Point"}
}