{
  "type": "Feature",
  "properties": {
    "addr:full":"31 Bourke St Mentone VIC 3194",
    "addr:housenumber":"31",
    "addr:postcode":"3194",
    "addr:street":"Bourke St",
    "iso:country":"AU",
    "sg:address":"31 Bourke St",
    "sg:city":"Mentone",
    "sg:classifiers":[
        {
            "category":"Building & Trades",
            "subcategory":"Cleaning & Sanitation",
            "type":"Services"
        }
    ],
    "sg:phone":"+61 419 151 394",
    "sg:postcode":"3194",
    "sg:province":"VIC",
    "sg:tags":[
        "cleaner",
        "repairer",
        "roof"
    ],
    "wof:name":"Melbourne Steel Roofing",
    "wof:placetype":"venue"
},
  "geometry": {"coordinates":[145.056396484,-37.9744033813],"type":"Point"}
}