{
  "type": "Feature",
  "properties": {
    "iso:country":"AU",
    "sg:address":"587 High St",
    "sg:city":"Northcote",
    "sg:classifiers":[
        {
            "category":"Professional",
            "subcategory":"Computer Services",
            "type":"Services"
        }
    ],
    "sg:phone":"+61 3 9482 2727",
    "sg:postcode":"3070",
    "sg:province":"VIC",
    "sg:tags":[
        "repairs",
        "upgrade",
        "equipment"
    ],
    "wof:name":"Croxton Computer Centre",
    "wof:placetype":"venue"
},
  "geometry": {"coordinates":[144.999695,-37.762978],"type":"Point"}
}