{
  "type": "Feature",
  "properties": {
    "addr:full":"53 Morehead St Bungalow QLD 4870",
    "addr:housenumber":"53",
    "addr:postcode":"4870",
    "addr:street":"Morehead St",
    "iso:country":"AU",
    "sg:address":"53 Morehead St",
    "sg:city":"Bungalow",
    "sg:classifiers":[
        {
            "category":"Retail",
            "subcategory":"Auto Repair",
            "type":"Services"
        }
    ],
    "sg:phone":"+61 7 4035 4307",
    "sg:postcode":"4870",
    "sg:province":"QLD",
    "sg:tags":[
        "clutch",
        "brake"
    ],
    "wof:name":"Brake Cylinder Reconditioners",
    "wof:placetype":"venue"
},
  "geometry": {"coordinates":[145.76063537600001,-16.938249588],"type":"Point"}
}