{
  "type": "Feature",
  "properties": {
    "iso:country":"AU",
    "sg:address":"101 Newmarket Rd",
    "sg:city":"Windsor",
    "sg:classifiers":[
        {
            "category":"Shopping",
            "subcategory":"Computers & Home Electronics",
            "type":"Retail Goods"
        }
    ],
    "sg:phone":"+61 7 3357 9999",
    "sg:postcode":"4030",
    "sg:province":"QLD",
    "sg:tags":[
        "hardware",
        "equipment"
    ],
    "wof:name":"Caribiner Av Services",
    "wof:placetype":"venue"
},
  "geometry": {"coordinates":[153.024719,-27.436983],"type":"Point"}
}