{
  "type": "Feature",
  "properties": {
    "addr:full":"208 Sturt St Ballarat VIC 3350",
    "addr:housenumber":"208",
    "addr:postcode":"3350",
    "addr:street":"Sturt St",
    "iso:country":"AU",
    "sg:address":"208 Sturt St",
    "sg:city":"Ballarat",
    "sg:classifiers":[
        {
            "category":"Shopping",
            "type":"Retail Goods"
        }
    ],
    "sg:phone":"+61 3 5331 3672",
    "sg:postcode":"3350",
    "sg:province":"VIC",
    "sg:tags":[
        "repair",
        "travel"
    ],
    "wof:name":"Snowgum",
    "wof:placetype":"venue"
},
  "geometry": {"coordinates":[143.856979,-37.561554],"type":"Point"}
}