{
  "type": "Feature",
  "properties": {
    "addr:full":"5a Levanswell Rd Moorabbin VIC 3189",
    "addr:housenumber":"5a",
    "addr:postcode":"3189",
    "addr:street":"Levanswell Rd",
    "iso:country":"AU",
    "sg:address":"5a Levanswell Rd",
    "sg:city":"Moorabbin",
    "sg:classifiers":[
        {
            "category":"Building & Trades",
            "subcategory":"Construction",
            "type":"Services"
        }
    ],
    "sg:phone":"+61 3 9555 4083",
    "sg:postcode":"3189",
    "sg:province":"VIC",
    "sg:tags":[
        "equipment",
        "balancing"
    ],
    "wof:name":"Berryman Balancing Centre",
    "wof:placetype":"venue"
},
  "geometry": {"coordinates":[145.06137085,-37.9440689087],"type":"Point"}
}