{
  "type": "Feature",
  "properties": {
    "iso:country":"AU",
    "sg:address":"Lygon Crt 360 Lygon St",
    "sg:city":"Carlton",
    "sg:classifiers":[
        {
            "category":"Food & Beverages",
            "subcategory":"Liquor & Beverages",
            "type":"Retail Goods"
        }
    ],
    "sg:phone":"+61 3 9347 9850",
    "sg:postcode":"3053",
    "sg:province":"VIC",
    "sg:tags":[
        "store"
    ],
    "wof:name":"Harvest Liquor Group",
    "wof:placetype":"venue"
},
  "geometry": {"coordinates":[144.96754455600001,-37.7981987],"type":"Point"}
}