{
  "type": "Feature",
  "properties": {
    "addr:full":"Wilson St Horsham VIC 3400",
    "addr:postcode":"3400",
    "addr:street":"Wilson St",
    "iso:country":"AU",
    "sg:address":"Wilson St",
    "sg:city":"Horsham",
    "sg:classifiers":[
        {
            "category":"Autos & Motor Vehicles",
            "subcategory":"Fuel & Gas Station",
            "type":"Retail Goods"
        }
    ],
    "sg:phone":"+61 3 5382 4260",
    "sg:postcode":"3400",
    "sg:province":"VIC",
    "wof:name":"BP Australia Limited",
    "wof:placetype":"venue"
},
  "geometry": {"coordinates":[142.19648742699999,-36.7166404724],"type":"Point"}
}