{
  "type": "Feature",
  "properties": {
    "iso:country":"AU",
    "sg:address":"Lot 223 Davo Crt",
    "sg:city":"Burleigh Gardens",
    "sg:classifiers":[
        {
            "category":"Manufacturing",
            "subcategory":"Metals",
            "type":"Manufacturing & Wholesale Goods"
        }
    ],
    "sg:phone":"+61 7 5593 8433",
    "sg:postcode":"4220",
    "sg:province":"QLD",
    "sg:tags":[
        "sheet",
        "worker"
    ],
    "wof:name":"1st Class Sheet Metal",
    "wof:placetype":"venue"
},
  "geometry": {"coordinates":[153.41616821299999,-28.1045284271],"type":"Point"}
}