{
  "type": "Feature",
  "properties": {
    "addr:full":"272 Ross River Rd Aitkenvale QLD 4814",
    "addr:housenumber":"272",
    "addr:postcode":"4814",
    "addr:street":"Ross River Rd",
    "iso:country":"AU",
    "sg:address":"272 Ross River Rd",
    "sg:city":"Aitkenvale",
    "sg:classifiers":[
        {
            "category":"Real Estate",
            "subcategory":"Real Estate Agent",
            "type":"Services"
        }
    ],
    "sg:phone":"+61 7 4779 7900",
    "sg:postcode":"4814",
    "sg:province":"QLD",
    "wof:name":"Riverside Realty",
    "wof:placetype":"venue"
},
  "geometry": {"coordinates":[146.76771500000001,-19.297165],"type":"Point"}
}