{
  "type": "Feature",
  "properties": {
    "addr:full":"509b Burwood Hwy Vermont VIC 3133",
    "addr:housenumber":"509b",
    "addr:postcode":"3133",
    "addr:street":"Burwood Hwy",
    "iso:country":"AU",
    "sg:address":"509b Burwood Hwy",
    "sg:city":"Vermont",
    "sg:classifiers":[
        {
            "category":"Health Services",
            "subcategory":"Doctor",
            "type":"Services"
        }
    ],
    "sg:phone":"+61 3 9886 4644",
    "sg:postcode":"3133",
    "sg:province":"VIC",
    "sg:tags":[
        "medical",
        "practitioner"
    ],
    "wof:name":"Jigau Constantin Dr",
    "wof:placetype":"venue"
},
  "geometry": {"coordinates":[145.18327331500001,-37.8563041687],"type":"Point"}
}