{
  "type": "Feature",
  "properties": {
    "addr:full":"Shop 2 4 Rupert Ave Bedford Park SA 5042",
    "addr:housenumber":"shop;4",
    "addr:postcode":"5042",
    "addr:street":"Rupert Ave",
    "iso:country":"AU",
    "sg:address":"Shop 2 4 Rupert Ave",
    "sg:city":"Bedford Park",
    "sg:classifiers":[
        {
            "category":"Retail",
            "subcategory":"Repair Shop",
            "type":"Services"
        }
    ],
    "sg:phone":"+61 8 8277 5666",
    "sg:postcode":"5042",
    "sg:province":"SA",
    "sg:tags":[
        "machine",
        "repairs",
        "part",
        "dryer",
        "washing"
    ],
    "wof:name":"Flagstaff Electrical",
    "wof:placetype":"venue"
},
  "geometry": {"coordinates":[138.537216,-35.002754],"type":"Point"}
}