{
  "type": "Feature",
  "properties": {
    "iso:country":"AU",
    "sg:address":"Oakenden Rd",
    "sg:city":"Oakenden",
    "sg:classifiers":[
        {
            "category":"Farming",
            "subcategory":"Farm",
            "type":"Manufacturing & Wholesale Goods"
        }
    ],
    "sg:phone":"+61 7 4959 7277",
    "sg:postcode":"4741",
    "sg:province":"QLD",
    "sg:tags":[
        "farmer"
    ],
    "wof:name":"Harris R J & J M",
    "wof:placetype":"venue"
},
  "geometry": {"coordinates":[149.01416,-21.296892],"type":"Point"}
}