{
  "type": "Feature",
  "properties": {
    "addr:full":"Shop 62, Arbour Avenue, Riverwalk, Robina QLD 4226",
    "addr:housenumber":"shop 62",
    "addr:postcode":"4226",
    "addr:street":"Arbour Avenue",
    "iso:country":"AU",
    "sg:address":"Shop 62, Arbour Avenue, Riverwalk,",
    "sg:city":"Robina",
    "sg:classifiers":[
        {
            "category":"Personal",
            "subcategory":"Beauty Salon",
            "type":"Services"
        }
    ],
    "sg:phone":"+61 7 5578 7888",
    "sg:postcode":"4226",
    "sg:province":"QLD",
    "sg:tags":[
        "hairdresser"
    ],
    "wof:name":"Michael W Barber - Hair - Beauty",
    "wof:placetype":"venue"
},
  "geometry": {"coordinates":[153.38200378400001,-28.0783596039],"type":"Point"}
}