{
  "type": "Feature",
  "properties": {
    "iso:country":"AU",
    "sg:address":"49 Best St",
    "sg:city":"Devonport",
    "sg:classifiers":[
        {
            "category":"Arena",
            "subcategory":"Sports Club",
            "type":"Entertainment"
        }
    ],
    "sg:phone":"+61 3 6423 4548",
    "sg:postcode":"7310",
    "sg:province":"TAS",
    "sg:tags":[
        "organisation",
        "sporting"
    ],
    "wof:name":"Devonport Triathlon Association",
    "wof:placetype":"venue"
},
  "geometry": {"coordinates":[146.35644531200001,-41.1778411865],"type":"Point"}
}