{
  "type": "Feature",
  "properties": {
    "iso:country":"AU",
    "sg:address":"86 Rathmines St",
    "sg:city":"Fairfield",
    "sg:classifiers":[
        {
            "category":"Shopping",
            "subcategory":"Computers & Home Electronics",
            "type":"Retail Goods"
        }
    ],
    "sg:phone":"+61 3 9481 7271",
    "sg:postcode":"3078",
    "sg:province":"VIC",
    "sg:tags":[
        "equipment",
        "multimedia"
    ],
    "wof:name":"PixelAnimations",
    "wof:placetype":"venue"
},
  "geometry": {"coordinates":[145.01596069300001,-37.7771949768],"type":"Point"}
}