{
  "type": "Feature",
  "properties": {
    "addr:full":"Education Ave Palmer SA 5237",
    "addr:postcode":"5237",
    "addr:street":"Education Ave",
    "iso:country":"AU",
    "sg:address":"Education Ave",
    "sg:city":"Palmer",
    "sg:classifiers":[
        {
            "category":"Education",
            "subcategory":"School",
            "type":"Public Place"
        }
    ],
    "sg:phone":"+61 8 8569 4050",
    "sg:postcode":"5237",
    "sg:province":"SA",
    "sg:tags":[
        "state",
        "except",
        "nsw"
    ],
    "wof:name":"Palmer Primary School",
    "wof:placetype":"venue"
},
  "geometry": {"coordinates":[139.160354614,-34.8536605835],"type":"Point"}
}