{
  "type": "Feature",
  "properties": {
    "iso:country":"AU",
    "sg:address":"52 Scarborough St",
    "sg:city":"Monterey",
    "sg:classifiers":[
        {
            "category":"Building & Trades",
            "subcategory":"Landscaping Services",
            "type":"Services"
        }
    ],
    "sg:phone":"+61 2 9587 9268",
    "sg:postcode":"2217",
    "sg:province":"NSW",
    "sg:tags":[
        "control",
        "weed"
    ],
    "wof:name":"All Seasons Pest Control",
    "wof:placetype":"venue"
},
  "geometry": {"coordinates":[151.14645400000001,-33.975014],"type":"Point"}
}