{
  "type": "Feature",
  "properties": {
    "addr:full":"322 Wellington St South Launceston TAS 7249",
    "addr:housenumber":"322",
    "addr:postcode":"7249",
    "addr:street":"Wellington St",
    "iso:country":"AU",
    "sg:address":"322 Wellington St",
    "sg:city":"South Launceston",
    "sg:classifiers":[
        {
            "category":"Health Services",
            "subcategory":"Doctor",
            "type":"Services"
        }
    ],
    "sg:phone":"+61 3 6343 0033",
    "sg:postcode":"7249",
    "sg:province":"TAS",
    "sg:tags":[
        "medical",
        "practitioner"
    ],
    "wof:name":"Siejka S J",
    "wof:placetype":"venue"
},
  "geometry": {"coordinates":[147.148071289,-41.4578361511],"type":"Point"}
}