{
  "type": "Feature",
  "properties": {
    "addr:full":"Shop 501,Prahran Market Commercial Rd South Yarra VIC 3141",
    "addr:housenumber":"501",
    "addr:postcode":"3141",
    "addr:street":"Commercial Rd",
    "iso:country":"AU",
    "sg:address":"Shop 501,Prahran Market Commercial Rd",
    "sg:city":"South Yarra",
    "sg:classifiers":[
        {
            "category":"Manufacturing",
            "subcategory":"Food",
            "type":"Manufacturing & Wholesale Goods"
        }
    ],
    "sg:phone":"+61 3 9824 2822",
    "sg:postcode":"3141",
    "sg:province":"VIC",
    "sg:tags":[
        "function",
        "catering"
    ],
    "wof:name":"O2GO Catering & Events",
    "wof:placetype":"venue"
},
  "geometry": {"coordinates":[144.989044189,-37.8461914062],"type":"Point"}
}