{
  "type": "Feature",
  "properties": {
    "addr:full":"69 Stephenson St Richmond VIC 3121",
    "addr:housenumber":"69",
    "addr:postcode":"3121",
    "addr:street":"Stephenson St",
    "iso:country":"AU",
    "sg:address":"69 Stephenson St",
    "sg:city":"Richmond",
    "sg:classifiers":[
        {
            "category":"Retail",
            "subcategory":"Auto Repair",
            "type":"Services"
        }
    ],
    "sg:phone":"+61 3 9429 2871",
    "sg:postcode":"3121",
    "sg:province":"VIC",
    "sg:tags":[
        "repairer",
        "motor",
        "engineer"
    ],
    "wof:name":"Naylor Auto Repairs",
    "wof:placetype":"venue"
},
  "geometry": {"coordinates":[144.993682861,-37.8288269043],"type":"Point"}
}