{
  "type": "Feature",
  "properties": {
    "iso:country":"AU",
    "sg:address":"17 William St",
    "sg:city":"Bellingen",
    "sg:classifiers":[
        {
            "category":"Professional",
            "subcategory":"Accounting & Tax Preparation",
            "type":"Services"
        }
    ],
    "sg:phone":"+61 2 6655 1977",
    "sg:postcode":"2454",
    "sg:province":"NSW",
    "sg:tags":[
        "consultant",
        "taxation"
    ],
    "wof:name":"Koops Martin Accountants",
    "wof:placetype":"venue"
},
  "geometry": {"coordinates":[152.895645,-30.452608],"type":"Point"}
}