{
  "type": "Feature",
  "properties": {
    "addr:full":"616 Park Rd Park Orchards VIC 3114",
    "addr:housenumber":"616",
    "addr:postcode":"3114",
    "addr:street":"Park Rd",
    "iso:country":"AU",
    "sg:address":"616 Park Rd",
    "sg:city":"Park Orchards",
    "sg:classifiers":[
        {
            "category":"Health Services",
            "subcategory":"Health Practitioner",
            "type":"Services"
        }
    ],
    "sg:phone":"+61 3 9876 1964",
    "sg:postcode":"3114",
    "sg:province":"VIC",
    "sg:tags":[
        "physiotherapist"
    ],
    "wof:name":"Park Orchards Physiotherapy",
    "wof:placetype":"venue"
},
  "geometry": {"coordinates":[145.218475342,-37.7791976929],"type":"Point"}
}