{
  "type": "Feature",
  "properties": {
    "addr:full":"Bruce Hwy Mt Larcom QLD 4695",
    "addr:postcode":"4695",
    "addr:street":"Bruce Hwy Mt Larcom",
    "iso:country":"AU",
    "sg:address":"Bruce Hwy",
    "sg:city":"Mt Larcom",
    "sg:classifiers":[
        {
            "category":"Autos & Motor Vehicles",
            "subcategory":"Fuel & Gas Station",
            "type":"Retail Goods"
        }
    ],
    "sg:phone":"+61 7 4975 1287",
    "sg:postcode":"4695",
    "sg:province":"QLD",
    "wof:name":"Shell Roadhouse Mount Larcom",
    "wof:placetype":"venue"
},
  "geometry": {"coordinates":[150.978515625,-23.809047699],"type":"Point"}
}