{
  "type": "Feature",
  "properties": {
    "iso:country":"AU",
    "sg:address":"PO Box 100",
    "sg:city":"Cottesloe",
    "sg:classifiers":[
        {
            "category":"Professional",
            "subcategory":"Accounting & Tax Preparation",
            "type":"Services"
        }
    ],
    "sg:phone":"+61 8 9385 0073",
    "sg:postcode":"6011",
    "sg:province":"WA",
    "sg:tags":[
        "accountant",
        "auditor"
    ],
    "wof:name":"Instantax North Coast",
    "wof:placetype":"venue"
},
  "geometry": {"coordinates":[115.757278442,-31.996049881],"type":"Point"}
}