{
  "type": "Feature",
  "properties": {
    "addr:full":"98 Surrey St Darlinghurst NSW 2010",
    "addr:housenumber":"98",
    "addr:postcode":"2010",
    "addr:street":"Surrey St",
    "iso:country":"AU",
    "sg:address":"98 Surrey St",
    "sg:city":"Darlinghurst",
    "sg:classifiers":[
        {
            "category":"Professional",
            "subcategory":"Employment Agencies",
            "type":"Services"
        }
    ],
    "sg:phone":"+61 2 9357 7722",
    "sg:postcode":"2010",
    "sg:province":"NSW",
    "sg:tags":[
        "entertainer",
        "agent"
    ],
    "wof:name":"Little BIG Music",
    "wof:placetype":"venue"
},
  "geometry": {"coordinates":[151.22250366200001,-33.8776702881],"type":"Point"}
}