{
  "type": "Feature",
  "properties": {
    "iso:country":"AU",
    "sg:address":"U5/ 59 Glen Iris Rd",
    "sg:city":"Glen Iris",
    "sg:classifiers":[
        {
            "category":"Building & Trades",
            "subcategory":"Landscaping Services",
            "type":"Services"
        }
    ],
    "sg:phone":"+61 437 174 446",
    "sg:postcode":"3146",
    "sg:province":"VIC",
    "sg:tags":[
        "designer",
        "landscape",
        "contractor"
    ],
    "wof:name":"Champion Landscapes",
    "wof:placetype":"venue"
},
  "geometry": {"coordinates":[145.06849670400001,-37.8486366272],"type":"Point"}
}