{
  "type": "Feature",
  "properties": {
    "addr:full":"6 Derinya St Mornington TAS 7018",
    "addr:housenumber":"6",
    "addr:postcode":"7018",
    "addr:street":"Derinya St",
    "iso:country":"AU",
    "sg:address":"6 Derinya St",
    "sg:city":"Mornington",
    "sg:classifiers":[
        {
            "category":"Arts & Performance",
            "subcategory":"Dance",
            "type":"Entertainment"
        }
    ],
    "sg:phone":"+61 407 070 509",
    "sg:postcode":"7018",
    "sg:province":"TAS",
    "sg:tags":[
        "theatrical",
        "ballet",
        "tuition"
    ],
    "wof:name":"Eastern Shore School Of Dance",
    "wof:placetype":"venue"
},
  "geometry": {"coordinates":[147.387252808,-42.8599357605],"type":"Point"}
}