{
  "type": "Feature",
  "properties": {
    "addr:full":"Suite 7-9, 88 Mountain St Broadway NSW 2007",
    "addr:housenumber":"88",
    "addr:postcode":"2007",
    "addr:street":"Mountain St",
    "iso:country":"AU",
    "sg:address":"Suite 7-9, 88 Mountain St",
    "sg:city":"Broadway",
    "sg:classifiers":[
        {
            "category":"Health Services",
            "subcategory":"Doctor",
            "type":"Services"
        }
    ],
    "sg:phone":"+61 2 9212 4445",
    "sg:postcode":"2007",
    "sg:province":"NSW",
    "sg:tags":[
        "medical",
        "practitioner"
    ],
    "wof:name":"Mindcare Centre",
    "wof:placetype":"venue"
},
  "geometry": {"coordinates":[151.19657898,-33.8838577271],"type":"Point"}
}