{
  "type": "Feature",
  "properties": {
    "addr:full":"103 Hampton Rd Fremantle WA 6160",
    "addr:housenumber":"103",
    "addr:postcode":"6160",
    "addr:street":"Hampton Rd",
    "iso:country":"AU",
    "sg:address":"103 Hampton Rd",
    "sg:city":"Fremantle",
    "sg:classifiers":[
        {
            "category":"Retail",
            "subcategory":"Auto Repair",
            "type":"Services"
        }
    ],
    "sg:phone":"+61 8 9335 1516",
    "sg:postcode":"6160",
    "sg:province":"WA",
    "sg:tags":[
        "electrical"
    ],
    "wof:name":"Deering Autronics",
    "wof:placetype":"venue"
},
  "geometry": {"coordinates":[115.75630200000001,-32.05917],"type":"Point"}
}