{
  "type": "Feature",
  "properties": {
    "iso:country":"AU",
    "sg:address":"Shp 12/ 3 Cottonwood Pl",
    "sg:city":"Oxenford",
    "sg:classifiers":[
        {
            "category":"Personal",
            "subcategory":"Beauty Salon",
            "type":"Services"
        }
    ],
    "sg:phone":"+61 7 5556 0860",
    "sg:postcode":"4210",
    "sg:province":"QLD",
    "sg:tags":[
        "hairdresser"
    ],
    "wof:name":"Rumours Style Centre",
    "wof:placetype":"venue"
},
  "geometry": {"coordinates":[153.311965942,-27.8915309906],"type":"Point"}
}