{
  "type": "Feature",
  "properties": {
    "iso:country":"AU",
    "sg:address":"U6, 26 Hector St",
    "sg:city":"West, Osborne Park",
    "sg:classifiers":[
        {
            "category":"Banks & Credit Unions",
            "subcategory":"Atm",
            "type":"Services"
        }
    ],
    "sg:phone":"+61 8 9204 4544",
    "sg:postcode":"6017",
    "sg:province":"WA",
    "sg:tags":[
        "wholesaler",
        "mfrs",
        "envelope"
    ],
    "wof:name":"Any Envelopes",
    "wof:placetype":"venue"
},
  "geometry": {"coordinates":[115.81407165500001,-31.8990840912],"type":"Point"}
}