{
  "type": "Feature",
  "properties": {
    "addr:full":"1902 Mount Mee Rd Ocean View QLD 4521",
    "addr:housenumber":"1902",
    "addr:postcode":"4521",
    "addr:street":"Mount Mee Rd",
    "iso:country":"AU",
    "sg:address":"1902 Mount Mee Rd",
    "sg:city":"Ocean View",
    "sg:classifiers":[
        {
            "category":"Wholesale",
            "subcategory":"Painting Supplies",
            "type":"Manufacturing & Wholesale Goods"
        }
    ],
    "sg:phone":"+61 7 5498 2288",
    "sg:postcode":"4521",
    "sg:province":"QLD",
    "sg:tags":[
        "product",
        "cleaning"
    ],
    "wof:name":"Swipe Australia Pty Ltd",
    "wof:placetype":"venue"
},
  "geometry": {"coordinates":[152.80497700000001,-27.12966],"type":"Point"}
}