{
  "type": "Feature",
  "properties": {
    "iso:country":"AU",
    "sg:address":"3/ 3 Ralph Black Drv",
    "sg:city":"North Wollongong",
    "sg:classifiers":[
        {
            "category":"Manufacturing",
            "subcategory":"Glass & Minerals",
            "type":"Manufacturing & Wholesale Goods"
        }
    ],
    "sg:phone":"+61 2 4228 9593",
    "sg:postcode":"2500",
    "sg:province":"NSW",
    "sg:tags":[
        "merchant",
        "granite",
        "marble"
    ],
    "wof:name":"Southern Marble & Granite",
    "wof:placetype":"venue"
},
  "geometry": {"coordinates":[150.893967,-34.406525],"type":"Point"}
}