{
  "type": "Feature",
  "properties": {
    "iso:country":"AU",
    "sg:address":"349 Deepfield Rd",
    "sg:city":"Catherine Field",
    "sg:classifiers":[
        {
            "category":"Commercial Area",
            "type":"Public Place"
        }
    ],
    "sg:phone":"+61 2 9606 5758",
    "sg:postcode":"2171",
    "sg:province":"NSW",
    "sg:tags":[
        "heavy",
        "carrier"
    ],
    "wof:name":"Jaz Transport Pty Ltd",
    "wof:placetype":"venue"
},
  "geometry": {"coordinates":[150.846237183,-33.9284286499],"type":"Point"}
}