{
  "type": "Feature",
  "properties": {
    "addr:full":"79a Jetty Rd Brighton SA 5048",
    "addr:housenumber":"79a",
    "addr:postcode":"5048",
    "addr:street":"Jetty Rd",
    "iso:country":"AU",
    "sg:address":"79a Jetty Rd",
    "sg:city":"Brighton",
    "sg:classifiers":[
        {
            "category":"Personal",
            "subcategory":"Beauty Salon",
            "type":"Services"
        }
    ],
    "sg:phone":"+61 8 8298 7622",
    "sg:postcode":"5048",
    "sg:province":"SA",
    "sg:tags":[
        "hairdresser"
    ],
    "wof:name":"Manhattan Haircutters",
    "wof:placetype":"venue"
},
  "geometry": {"coordinates":[138.515579,-35.017429],"type":"Point"}
}