{
  "type": "Feature",
  "properties": {
    "addr:full":"29 Harvester Ave Sunshine North VIC 3020",
    "addr:housenumber":"29",
    "addr:postcode":"3020",
    "addr:street":"Harvester Ave",
    "iso:country":"AU",
    "sg:address":"29 Harvester Ave",
    "sg:city":"Sunshine North",
    "sg:classifiers":[
        {
            "category":"Manufacturing",
            "subcategory":"Glass & Minerals",
            "type":"Manufacturing & Wholesale Goods"
        }
    ],
    "sg:phone":"+61 3 9364 8892",
    "sg:postcode":"3020",
    "sg:province":"VIC",
    "sg:tags":[
        "merchant",
        "granite",
        "marble"
    ],
    "wof:name":"Baron Forge Pty Ltd",
    "wof:placetype":"venue"
},
  "geometry": {"coordinates":[144.836456,-37.76041],"type":"Point"}
}