{
  "type": "Feature",
  "properties": {
    "addr:full":"PO Box 791 Sunshine VIC 3020",
    "addr:postcode":"3020",
    "iso:country":"AU",
    "sg:address":"PO Box 791",
    "sg:city":"Sunshine",
    "sg:classifiers":[
        {
            "category":"Utilities",
            "subcategory":"Fuel Oil & Lpg",
            "type":"Services"
        }
    ],
    "sg:phone":"+61 1300 555 878",
    "sg:postcode":"3020",
    "sg:province":"VIC",
    "sg:tags":[
        "heating"
    ],
    "wof:name":"Roy Wood Petroleum",
    "wof:placetype":"venue"
},
  "geometry": {"coordinates":[144.832458,-37.787601],"type":"Point"}
}