{
  "type": "Feature",
  "properties": {
    "addr:full":"107 Douglas Pde Williamstown VIC 3016",
    "addr:housenumber":"107",
    "addr:postcode":"3016",
    "addr:street":"Douglas Pde",
    "iso:country":"AU",
    "sg:address":"107 Douglas Pde",
    "sg:city":"Williamstown",
    "sg:classifiers":[
        {
            "category":"Organizations",
            "subcategory":"Professional Association",
            "type":"Services"
        }
    ],
    "sg:phone":"+61 3 9646 6311",
    "sg:postcode":"3016",
    "sg:province":"VIC",
    "sg:tags":[
        "organisation",
        "business"
    ],
    "wof:name":"A S I S International Australian Chapter",
    "wof:placetype":"venue"
},
  "geometry": {"coordinates":[144.89729309099999,-37.8552894592],"type":"Point"}
}