{
  "type": "Feature",
  "properties": {
    "addr:full":"PO Box 356 Cooroy QLD 4563",
    "addr:postcode":"4563",
    "iso:country":"AU",
    "sg:address":"PO Box 356",
    "sg:city":"Cooroy",
    "sg:classifiers":[
        {
            "category":"Building & Trades",
            "subcategory":"Construction",
            "type":"Services"
        }
    ],
    "sg:phone":"+61 407 395 410",
    "sg:postcode":"4563",
    "sg:province":"QLD",
    "sg:tags":[
        "earth",
        "excavating",
        "moving",
        "contractor"
    ],
    "wof:name":"Cronin Excavations",
    "wof:placetype":"venue"
},
  "geometry": {"coordinates":[152.890335083,-26.4106693268],"type":"Point"}
}