{
  "type": "Feature",
  "properties": {
    "addr:full":"Level 2/ 76 Kings Park Rd West Perth WA 6005",
    "addr:housenumber":"/ 76",
    "addr:postcode":"6005",
    "addr:street":"Kings Park Rd",
    "iso:country":"AU",
    "sg:address":"Level 2/ 76 Kings Park Rd",
    "sg:city":"West Perth",
    "sg:classifiers":[
        {
            "category":"Professional",
            "subcategory":"Accounting & Tax Preparation",
            "type":"Services"
        }
    ],
    "sg:phone":"+61 8 9322 6600",
    "sg:postcode":"6005",
    "sg:province":"WA",
    "sg:tags":[
        "consultant",
        "taxation"
    ],
    "wof:name":"Marshall Michael Chartered Accountants",
    "wof:placetype":"venue"
},
  "geometry": {"coordinates":[115.833892822,-31.950422287],"type":"Point"}
}