{
  "type": "Feature",
  "properties": {
    "addr:full":"3 Gillian St Springvale South VIC 3172",
    "addr:housenumber":"3",
    "addr:postcode":"3172",
    "addr:street":"Gillian St",
    "iso:country":"AU",
    "sg:address":"3 Gillian St",
    "sg:city":"Springvale South",
    "sg:classifiers":[
        {
            "category":"Education",
            "subcategory":"Kindergarten",
            "type":"Public Place"
        }
    ],
    "sg:phone":"+61 3 9546 8382",
    "sg:postcode":"3172",
    "sg:province":"VIC",
    "sg:tags":[
        "pre-schools"
    ],
    "wof:name":"Darren Reserve Kindergarten",
    "wof:placetype":"venue"
},
  "geometry": {"coordinates":[145.155151367,-37.9811058044],"type":"Point"}
}