{
  "type": "Feature",
  "properties": {
    "addr:full":"573 Freemans Drv Cooranbong NSW 2265",
    "addr:housenumber":"573",
    "addr:postcode":"2265",
    "addr:street":"Freemans Drv",
    "iso:country":"AU",
    "sg:address":"573 Freemans Drv",
    "sg:city":"Cooranbong",
    "sg:classifiers":[
        {
            "category":"Government",
            "subcategory":"Court House",
            "type":"Public Place"
        }
    ],
    "sg:phone":"+61 2 9517 2098",
    "sg:postcode":"2265",
    "sg:province":"NSW",
    "sg:tags":[
        "personal",
        "marriage",
        "family",
        "counselling"
    ],
    "wof:name":"Rody Myers",
    "wof:placetype":"venue"
},
  "geometry": {"coordinates":[151.46951300000001,-33.065067],"type":"Point"}
}