{
  "type": "Feature",
  "properties": {
    "iso:country":"AU",
    "sg:address":"Unit 5/ 12 Keona Crt",
    "sg:city":"Coffs Harbour",
    "sg:classifiers":[
        {
            "category":"Building & Trades",
            "subcategory":"Pest Control",
            "type":"Services"
        }
    ],
    "sg:phone":"+61 2 6651 5533",
    "sg:postcode":"2450",
    "sg:province":"NSW",
    "wof:name":"Termguard (Northern NSW) Pty Ltd",
    "wof:placetype":"venue"
},
  "geometry": {"coordinates":[153.091415,-30.312115],"type":"Point"}
}