{
  "type": "Feature",
  "properties": {
    "iso:country":"AU",
    "sg:address":"185 MacMillan St",
    "sg:city":"Ayr",
    "sg:classifiers":[
        {
            "category":"Building & Trades",
            "subcategory":"Construction",
            "type":"Services"
        }
    ],
    "sg:phone":"+61 7 4783 1940",
    "sg:postcode":"4807",
    "sg:province":"QLD",
    "sg:tags":[
        "earth",
        "excavating",
        "moving",
        "contractor"
    ],
    "wof:name":"Spataro's Bobcat & Mini Loads",
    "wof:placetype":"venue"
},
  "geometry": {"coordinates":[147.400512695,-19.5833263397],"type":"Point"}
}