{
  "type": "Feature",
  "properties": {
    "addr:full":"69-81 Garden Rd Clayton VIC 3168",
    "addr:housenumber":"69-81",
    "addr:postcode":"3168",
    "addr:street":"Garden Rd",
    "iso:country":"AU",
    "sg:address":"69-81 Garden Rd",
    "sg:city":"Clayton",
    "sg:classifiers":[
        {
            "category":"Wholesale",
            "subcategory":"Apparel",
            "type":"Manufacturing & Wholesale Goods"
        }
    ],
    "sg:phone":"+61 3 9547 9144",
    "sg:postcode":"3168",
    "sg:province":"VIC",
    "sg:tags":[
        "wholesaler",
        "mfrs",
        "silo"
    ],
    "wof:name":"Riband Steel Pty Ltd",
    "wof:placetype":"venue"
},
  "geometry": {"coordinates":[145.14553832999999,-37.9243507385],"type":"Point"}
}