{
  "type": "Feature",
  "properties": {
    "iso:country":"AU",
    "sg:address":"116 Grove Rd",
    "sg:city":"Glenorchy",
    "sg:classifiers":[
        {
            "category":"Manufacturing",
            "subcategory":"Metals",
            "type":"Manufacturing & Wholesale Goods"
        }
    ],
    "sg:phone":"+61 3 6273 2161",
    "sg:postcode":"7010",
    "sg:province":"TAS",
    "sg:tags":[
        "wholesaler",
        "aluminium",
        "mfrs"
    ],
    "wof:name":"Capral Smart Aluminium Centre",
    "wof:placetype":"venue"
},
  "geometry": {"coordinates":[147.26988220199999,-42.8292388916],"type":"Point"}
}