{
  "type": "Feature",
  "properties": {
    "addr:full":"9/ 443 Golden Four Drv Tugun QLD 4224",
    "addr:housenumber":"/ 443",
    "addr:postcode":"4224",
    "addr:street":"Golden Four Drv",
    "iso:country":"AU",
    "sg:address":"9/ 443 Golden Four Drv",
    "sg:city":"Tugun",
    "sg:classifiers":[
        {
            "category":"Building & Trades",
            "subcategory":"Landscaping Services",
            "type":"Services"
        }
    ],
    "sg:phone":"+61 7 5559 5028",
    "sg:postcode":"4224",
    "sg:province":"QLD",
    "sg:tags":[
        "architect",
        "landscape"
    ],
    "wof:name":"Environmental Design Group",
    "wof:placetype":"venue"
},
  "geometry": {"coordinates":[153.49482727,-28.1433982849],"type":"Point"}
}