{
  "type": "Feature",
  "properties": {
    "iso:country":"AU",
    "sg:address":"PO Box 2154",
    "sg:city":"Launceston",
    "sg:classifiers":[
        {
            "category":"Social Services",
            "subcategory":"Retirement Home",
            "type":"Services"
        }
    ],
    "sg:phone":"+61 3 6326 6343",
    "sg:postcode":"7250",
    "sg:province":"TAS",
    "sg:tags":[
        "accommodation",
        "special"
    ],
    "wof:name":"Abbeyfield Society(Launceston)Inc",
    "wof:placetype":"venue"
},
  "geometry": {"coordinates":[147.138504028,-41.4452018738],"type":"Point"}
}