{
  "type": "Feature",
  "properties": {
    "addr:full":"Robina East Quay 34- 36 Glenferrie Drv Robina QLD 4226",
    "addr:housenumber":"34 36",
    "addr:postcode":"4226",
    "addr:street":"East Quay;Glenferrie Drv",
    "iso:country":"AU",
    "sg:address":"Robina East Quay 34- 36 Glenferrie Drv",
    "sg:city":"Robina",
    "sg:classifiers":[
        {
            "category":"Real Estate",
            "subcategory":"Architect",
            "type":"Services"
        }
    ],
    "sg:phone":"+61 7 5562 0666",
    "sg:postcode":"4226",
    "sg:province":"QLD",
    "sg:tags":[
        "building",
        "designer"
    ],
    "wof:name":"Griffith Alan (Architect) Pty Ltd",
    "wof:placetype":"venue"
},
  "geometry": {"coordinates":[153.40196227999999,-28.064289093],"type":"Point"}
}