{
  "type": "Feature",
  "properties": {
    "addr:full":"PO Box 85 Lindisfarne TAS 7015",
    "addr:postcode":"7015",
    "iso:country":"AU",
    "sg:address":"PO Box 85",
    "sg:city":"Lindisfarne",
    "sg:classifiers":[
        {
            "category":"Shopping",
            "subcategory":"Hobbies, Toys, & Games",
            "type":"Retail Goods"
        }
    ],
    "sg:phone":"+61 3 6249 5069",
    "sg:postcode":"7015",
    "sg:province":"TAS",
    "sg:tags":[
        "stamp"
    ],
    "wof:name":"Gio Stamps",
    "wof:placetype":"venue"
},
  "geometry": {"coordinates":[147.36045837399999,-42.8469581604],"type":"Point"}
}