{
  "type": "Feature",
  "properties": {
    "addr:full":"2 Wendover Ave Norlane VIC 3214",
    "addr:housenumber":"2",
    "addr:postcode":"3214",
    "addr:street":"Wendover Ave",
    "iso:country":"AU",
    "sg:address":"2 Wendover Ave",
    "sg:city":"Norlane",
    "sg:classifiers":[
        {
            "category":"Social Services",
            "subcategory":"Adult Care",
            "type":"Services"
        }
    ],
    "sg:phone":"+61 3 5278 2198",
    "sg:postcode":"3214",
    "sg:province":"VIC",
    "sg:tags":[
        "aged"
    ],
    "wof:name":"Dorothy Thomson Day Centre",
    "wof:placetype":"venue"
},
  "geometry": {"coordinates":[144.35691833499999,-38.0922546387],"type":"Point"}
}