{
  "type": "Feature",
  "properties": {
    "iso:country":"AU",
    "sg:address":"26 Kembla Way",
    "sg:city":"Willetton",
    "sg:classifiers":[
        {
            "category":"Building & Trades",
            "subcategory":"Construction",
            "type":"Services"
        }
    ],
    "sg:phone":"+61 8 9457 9293",
    "sg:postcode":"6155",
    "sg:province":"WA",
    "sg:tags":[
        "renovation",
        "alterations",
        "extension",
        "contractor"
    ],
    "sg:website":"http://www.buildwest.com.au",
    "wof:name":"Build West",
    "wof:placetype":"venue"
},
  "geometry": {"coordinates":[115.88723,-32.041573],"type":"Point"}
}