{
  "type": "Feature",
  "properties": {
    "addr:full":"PO Box 921 Cronulla NSW 2230",
    "addr:postcode":"2230",
    "iso:country":"AU",
    "sg:address":"PO Box 921",
    "sg:city":"Cronulla",
    "sg:classifiers":[
        {
            "category":"Education",
            "subcategory":"Special Training",
            "type":"Public Place"
        }
    ],
    "sg:phone":"+61 2 9527 0959",
    "sg:postcode":"2230",
    "sg:province":"NSW",
    "sg:tags":[
        "development"
    ],
    "wof:name":"Competency International (Australia) Pty Ltd",
    "wof:placetype":"venue"
},
  "geometry": {"coordinates":[151.153366089,-34.055229187],"type":"Point"}
}