{
  "type": "Feature",
  "properties": {
    "addr:full":"43 Roberts St Bayswater WA 6053",
    "addr:housenumber":"43",
    "addr:postcode":"6053",
    "addr:street":"Roberts St",
    "iso:country":"AU",
    "sg:address":"43 Roberts St",
    "sg:city":"Bayswater",
    "sg:classifiers":[
        {
            "category":"Home & Garden",
            "subcategory":"Furniture",
            "type":"Retail Goods"
        }
    ],
    "sg:phone":"+61 8 9471 1700",
    "sg:postcode":"6053",
    "sg:province":"WA",
    "sg:tags":[
        "business"
    ],
    "wof:name":"Anton Philippe Design Con.",
    "wof:placetype":"venue"
},
  "geometry": {"coordinates":[115.912071228,-31.9231853485],"type":"Point"}
}