{
  "type": "Feature",
  "properties": {
    "iso:country":"AU",
    "sg:address":"Kulja Rd",
    "sg:city":"Jingymia",
    "sg:classifiers":[
        {
            "category":"Farming",
            "subcategory":"Farm",
            "type":"Manufacturing & Wholesale Goods"
        }
    ],
    "sg:phone":"+61 8 9684 4027",
    "sg:postcode":"6613",
    "sg:province":"WA",
    "sg:tags":[
        "farmer"
    ],
    "wof:name":"Westlund GB & SL",
    "wof:placetype":"venue"
},
  "geometry": {"coordinates":[116.568000794,-29.9594097137],"type":"Point"}
}