{
  "type": "Feature",
  "properties": {
    "addr:full":"87 Kororoit Creek Rd Williamstown VIC 3016",
    "addr:housenumber":"87",
    "addr:postcode":"3016",
    "addr:street":"Kororoit Creek Rd",
    "iso:country":"AU",
    "sg:address":"87 Kororoit Creek Rd",
    "sg:city":"Williamstown",
    "sg:classifiers":[
        {
            "category":"Social Services",
            "subcategory":"Child Care",
            "type":"Services"
        }
    ],
    "sg:phone":"+61 3 9397 8244",
    "sg:postcode":"3016",
    "sg:province":"VIC",
    "wof:name":"The Range Childrens Centre",
    "wof:placetype":"venue"
},
  "geometry": {"coordinates":[144.88119506800001,-37.8573532104],"type":"Point"}
}