{
  "type": "Feature",
  "properties": {
    "addr:full":"17 Whinham St Fitzroy SA 5082",
    "addr:housenumber":"17",
    "addr:postcode":"5082",
    "addr:street":"Whinham St",
    "iso:country":"AU",
    "sg:address":"17 Whinham St",
    "sg:city":"Fitzroy",
    "sg:classifiers":[
        {
            "category":"Wholesale",
            "subcategory":"Machinery & Supplies",
            "type":"Manufacturing & Wholesale Goods"
        }
    ],
    "sg:phone":"+61 8 8269 1561",
    "sg:postcode":"5082",
    "sg:province":"SA",
    "sg:tags":[
        "instrument"
    ],
    "wof:name":"T & M Instruments Pty Ltd",
    "wof:placetype":"venue"
},
  "geometry": {"coordinates":[138.588378906,-34.8959922791],"type":"Point"}
}