{
  "type": "Feature",
  "properties": {
    "addr:full":"22 Strangeways St Curtin ACT 2605",
    "addr:housenumber":"22",
    "addr:postcode":"2605",
    "addr:street":"Strangeways St",
    "iso:country":"AU",
    "sg:address":"22 Strangeways St",
    "sg:city":"Curtin",
    "sg:classifiers":[
        {
            "category":"Building & Trades",
            "subcategory":"Construction",
            "type":"Services"
        }
    ],
    "sg:phone":"+61 2 6285 4999",
    "sg:postcode":"2605",
    "sg:province":"ACT",
    "sg:tags":[
        "management"
    ],
    "wof:name":"Asset Technologies Pty Ltd",
    "wof:placetype":"venue"
},
  "geometry": {"coordinates":[149.08206176799999,-35.3246803284],"type":"Point"}
}