{
  "type": "Feature",
  "properties": {
    "iso:country":"AU",
    "sg:address":"12 Langmore La",
    "sg:city":"Berwick",
    "sg:classifiers":[
        {
            "category":"Professional",
            "subcategory":"Accounting & Tax Preparation",
            "type":"Services"
        }
    ],
    "sg:phone":"+61 3 9707 2677",
    "sg:postcode":"3806",
    "sg:province":"VIC",
    "sg:tags":[
        "accountant",
        "auditor"
    ],
    "wof:name":"RJ Ryan Partners",
    "wof:placetype":"venue"
},
  "geometry": {"coordinates":[145.34506225600001,-38.0332221985],"type":"Point"}
}