{
  "type": "Feature",
  "properties": {
    "addr:full":"102 Queen St Busselton WA 6280",
    "addr:housenumber":"102",
    "addr:postcode":"6280",
    "addr:street":"Queen St",
    "iso:country":"AU",
    "sg:address":"102 Queen St",
    "sg:city":"Busselton",
    "sg:classifiers":[
        {
            "category":"Professional",
            "subcategory":"Accounting & Tax Preparation",
            "type":"Services"
        }
    ],
    "sg:phone":"+61 8 9752 4633",
    "sg:postcode":"6280",
    "sg:province":"WA",
    "sg:tags":[
        "consultant",
        "taxation"
    ],
    "wof:name":"H&R Block",
    "wof:placetype":"venue"
},
  "geometry": {"coordinates":[115.34491729699999,-33.6517944336],"type":"Point"}
}