{
  "type": "Feature",
  "properties": {
    "addr:full":"Goulburn Valley Hwy Numurkah VIC 3636",
    "addr:postcode":"3636",
    "addr:street":"Valley Hwy",
    "iso:country":"AU",
    "sg:address":"Goulburn Valley Hwy",
    "sg:city":"Numurkah",
    "sg:classifiers":[
        {
            "category":"Shopping",
            "subcategory":"Stationery & Office Supplies",
            "type":"Retail Goods"
        }
    ],
    "sg:phone":"+61 3 5862 1784",
    "sg:postcode":"3636",
    "sg:province":"VIC",
    "sg:tags":[
        "equipment",
        "dairy"
    ],
    "wof:name":"Numurkah Refrigeration",
    "wof:placetype":"venue"
},
  "geometry": {"coordinates":[145.43177795400001,-36.0883102417],"type":"Point"}
}