{
  "type": "Feature",
  "properties": {
    "addr:full":"600 Malvern Rd Malvern VIC 3144",
    "addr:housenumber":"600",
    "addr:postcode":"3144",
    "addr:street":"Malvern Rd",
    "iso:country":"AU",
    "sg:address":"600 Malvern Rd",
    "sg:city":"Malvern",
    "sg:classifiers":[
        {
            "category":"Utilities",
            "subcategory":"Refuse",
            "type":"Services"
        }
    ],
    "sg:phone":"+61 1300 675 477",
    "sg:postcode":"3144",
    "sg:province":"VIC",
    "sg:tags":[
        "remover",
        "rubbish"
    ],
    "wof:name":"Mobile Skips",
    "wof:placetype":"venue"
},
  "geometry": {"coordinates":[145.03805542000001,-37.8526725769],"type":"Point"}
}