{
  "type": "Feature",
  "properties": {
    "addr:full":"205 Byron St Inverell NSW 2360",
    "addr:housenumber":"205",
    "addr:postcode":"2360",
    "addr:street":"Byron St",
    "iso:country":"AU",
    "sg:address":"205 Byron St",
    "sg:city":"Inverell",
    "sg:classifiers":[
        {
            "category":"Autos & Motor Vehicles",
            "subcategory":"Auto Supplies",
            "type":"Retail Goods"
        }
    ],
    "sg:phone":"+61 2 6722 3035",
    "sg:postcode":"2360",
    "sg:province":"NSW",
    "sg:tags":[
        "tyre"
    ],
    "wof:name":"Inverell Tyre Service",
    "wof:placetype":"venue"
},
  "geometry": {"coordinates":[151.116622925,-29.7703495026],"type":"Point"}
}