{
  "type": "Feature",
  "properties": {
    "iso:country":"AU",
    "sg:address":"49 Miles St",
    "sg:city":"Mt Isa",
    "sg:classifiers":[
        {
            "category":"Education",
            "subcategory":"School",
            "type":"Public Place"
        }
    ],
    "sg:phone":"+61 7 4743 5768",
    "sg:postcode":"4825",
    "sg:province":"QLD",
    "sg:tags":[
        "state",
        "except",
        "nsw"
    ],
    "wof:name":"Mount Isa Central Preschool",
    "wof:placetype":"venue"
},
  "geometry": {"coordinates":[139.497375,-20.707319],"type":"Point"}
}