{
  "type": "Feature",
  "properties": {
    "addr:full":"66 Boorea St Blaxland NSW 2774",
    "addr:housenumber":"66",
    "addr:postcode":"2774",
    "addr:street":"Boorea St",
    "iso:country":"AU",
    "sg:address":"66 Boorea St",
    "sg:city":"Blaxland",
    "sg:classifiers":[
        {
            "category":"Retail",
            "subcategory":"Repair Shop",
            "type":"Services"
        }
    ],
    "sg:phone":"+61 2 4739 8192",
    "sg:postcode":"2774",
    "sg:province":"NSW",
    "sg:tags":[
        "machine",
        "repairs",
        "part",
        "dryer",
        "washing"
    ],
    "wof:name":"NBM Appliances",
    "wof:placetype":"venue"
},
  "geometry": {"coordinates":[150.61892700199999,-33.7443237305],"type":"Point"}
}