{
  "type": "Feature",
  "properties": {
    "addr:full":"Ste 1 Lvl 5, 187 Macquarie St Sydney NSW 2000",
    "addr:housenumber":"187",
    "addr:postcode":"2000",
    "addr:street":"Macquarie St",
    "iso:country":"AU",
    "sg:address":"Ste 1 Lvl 5, 187 Macquarie St",
    "sg:city":"Sydney",
    "sg:classifiers":[
        {
            "category":"Health Services",
            "subcategory":"Chiropractor",
            "type":"Services"
        }
    ],
    "sg:phone":"+61 2 9232 8840",
    "sg:postcode":"2000",
    "sg:province":"NSW",
    "wof:name":"Bablis Peter",
    "wof:placetype":"venue"
},
  "geometry": {"coordinates":[151.21217346200001,-33.8671836853],"type":"Point"}
}