{
  "type": "Feature",
  "properties": {
    "iso:country":"AU",
    "sg:address":"31 Edith St",
    "sg:city":"Innisfail",
    "sg:classifiers":[
        {
            "category":"Shopping",
            "subcategory":"Computers & Home Electronics",
            "type":"Retail Goods"
        }
    ],
    "sg:phone":"+61 7 4061 6600",
    "sg:postcode":"4860",
    "sg:province":"QLD",
    "sg:tags":[
        "hi-fi",
        "equipment"
    ],
    "wof:name":"Innisfail Sound & Communications",
    "wof:placetype":"venue"
},
  "geometry": {"coordinates":[146.02899169899999,-17.5244941711],"type":"Point"}
}