{
  "type": "Feature",
  "properties": {
    "iso:country":"AU",
    "sg:address":"Rosenthal Motors Pty Ltd, 13 Vaughan Tce",
    "sg:city":"Berri",
    "sg:classifiers":[
        {
            "category":"Insurance",
            "subcategory":"Hazard Insurance",
            "type":"Services"
        }
    ],
    "sg:phone":"+61 8 8582 1200",
    "sg:postcode":"5343",
    "sg:province":"SA",
    "sg:tags":[
        "fire",
        "accident",
        "marine"
    ],
    "wof:name":"SGIC",
    "wof:placetype":"venue"
},
  "geometry": {"coordinates":[140.60078430199999,-34.2843208313],"type":"Point"}
}