{
  "type": "Feature",
  "properties": {
    "addr:full":"2 Von Nida Crt Rowville VIC 3178",
    "addr:housenumber":"2",
    "addr:postcode":"3178",
    "addr:street":"Von Nida Crt",
    "iso:country":"AU",
    "sg:address":"2 Von Nida Crt",
    "sg:city":"Rowville",
    "sg:classifiers":[
        {
            "category":"Professional",
            "subcategory":"Accounting & Tax Preparation",
            "type":"Services"
        }
    ],
    "sg:phone":"+61 3 9764 4437",
    "sg:postcode":"3178",
    "sg:province":"VIC",
    "sg:tags":[
        "accountant",
        "auditor"
    ],
    "wof:name":"Henry Liew & Associates",
    "wof:placetype":"venue"
},
  "geometry": {"coordinates":[145.24252319300001,-37.9359436035],"type":"Point"}
}