{
  "type": "Feature",
  "properties": {
    "addr:full":"Rear of 96 Aberdeen St Albany WA 6330",
    "addr:housenumber":"rear of 96",
    "addr:postcode":"6330",
    "addr:street":"Aberdeen St",
    "iso:country":"AU",
    "sg:address":"Rear of 96 Aberdeen St",
    "sg:city":"Albany",
    "sg:classifiers":[
        {
            "category":"Health Services",
            "subcategory":"Doctor",
            "type":"Services"
        }
    ],
    "sg:phone":"+61 8 9842 9836",
    "sg:postcode":"6330",
    "sg:province":"WA",
    "sg:tags":[
        "occupational",
        "safety"
    ],
    "wof:name":"Advanced Personnel Management",
    "wof:placetype":"venue"
},
  "geometry": {"coordinates":[117.88524627699999,-35.0223236084],"type":"Point"}
}