{
  "type": "Feature",
  "properties": {
    "addr:full":"Shp 1/ 46 Duke St Sunshine Beach QLD 4567",
    "addr:housenumber":"/ 46",
    "addr:postcode":"4567",
    "addr:street":"Duke St",
    "iso:country":"AU",
    "sg:address":"Shp 1/ 46 Duke St",
    "sg:city":"Sunshine Beach",
    "sg:classifiers":[
        {
            "category":"Food & Beverages",
            "subcategory":"Bakery",
            "type":"Retail Goods"
        }
    ],
    "sg:phone":"+61 7 5447 5256",
    "sg:postcode":"4567",
    "sg:province":"QLD",
    "sg:tags":[
        "baker"
    ],
    "wof:name":"Beach Bakery",
    "wof:placetype":"venue"
},
  "geometry": {"coordinates":[153.11050415,-26.4058475494],"type":"Point"}
}