{
  "type": "Feature",
  "properties": {
    "addr:full":"182 Island Point Rd St Georges Basin NSW 2540",
    "addr:housenumber":"182",
    "addr:postcode":"2540",
    "addr:street":"Island Point Rd",
    "iso:country":"AU",
    "sg:address":"182 Island Point Rd",
    "sg:city":"St Georges Basin",
    "sg:classifiers":[
        {
            "category":"Building & Trades",
            "subcategory":"Construction",
            "type":"Services"
        }
    ],
    "sg:phone":"+61 2 4443 4246",
    "sg:postcode":"2540",
    "sg:province":"NSW",
    "sg:tags":[
        "plasterboard",
        "plasterer",
        "fixer"
    ],
    "wof:name":"Bay & Basin Plastering",
    "wof:placetype":"venue"
},
  "geometry": {"coordinates":[150.59872436500001,-35.0869407654],"type":"Point"}
}