{
  "type": "Feature",
  "properties": {
    "addr:full":"1 Berry St East Melbourne VIC 3002",
    "addr:housenumber":"1",
    "addr:postcode":"3002",
    "addr:street":"Berry St",
    "iso:country":"AU",
    "sg:address":"1 Berry St",
    "sg:city":"East Melbourne",
    "sg:classifiers":[
        {
            "category":"Organizations",
            "subcategory":"Community Association",
            "type":"Services"
        }
    ],
    "sg:phone":"+61 3 9429 9266",
    "sg:postcode":"3002",
    "sg:province":"VIC",
    "sg:tags":[
        "organisation",
        "family",
        "welfare"
    ],
    "wof:name":"Berry Street Victoria",
    "wof:placetype":"venue"
},
  "geometry": {"coordinates":[144.988372803,-37.8191566467],"type":"Point"}
}