{
  "type": "Feature",
  "properties": {
    "iso:country":"AU",
    "sg:address":"ShpA49/ 840 Wellington St",
    "sg:city":"West Perth",
    "sg:classifiers":[
        {
            "category":"Shopping",
            "subcategory":"Clothing, Apparel, & Fashions",
            "type":"Retail Goods"
        }
    ],
    "sg:phone":"+61 8 9226 2699",
    "sg:postcode":"6005",
    "sg:province":"WA",
    "sg:tags":[
        "lady",
        "wear"
    ],
    "wof:name":"Roads",
    "wof:placetype":"venue"
},
  "geometry": {"coordinates":[115.847587585,-31.9475536346],"type":"Point"}
}