{
  "type": "Feature",
  "properties": {
    "addr:full":"36/ 40 Gerard St Cremorne NSW 2090",
    "addr:housenumber":"36 / 40",
    "addr:postcode":"2090",
    "addr:street":"Gerard St",
    "iso:country":"AU",
    "sg:address":"36/ 40 Gerard St",
    "sg:city":"Cremorne",
    "sg:classifiers":[
        {
            "category":"Health Services",
            "subcategory":"Health Practitioner",
            "type":"Services"
        }
    ],
    "sg:phone":"+61 2 9904 1953",
    "sg:postcode":"2090",
    "sg:province":"NSW",
    "sg:tags":[
        "homoeopath"
    ],
    "wof:name":"Parker Susan",
    "wof:placetype":"venue"
},
  "geometry": {"coordinates":[151.227462769,-33.8277626038],"type":"Point"}
}