{
  "type": "Feature",
  "properties": {
    "addr:full":"Shop 2/ 18 Farrell St Yandina QLD 4561",
    "addr:housenumber":"shop 2 / 18",
    "addr:postcode":"4561",
    "addr:street":"Farrell St",
    "iso:country":"AU",
    "sg:address":"Shop 2/ 18 Farrell St",
    "sg:city":"Yandina",
    "sg:classifiers":[
        {
            "category":"Retail",
            "subcategory":"Veterinary Services",
            "type":"Services"
        }
    ],
    "sg:phone":"+61 7 5441 3022",
    "sg:postcode":"4561",
    "sg:province":"QLD",
    "sg:tags":[
        "surgeon"
    ],
    "wof:name":"Central Nambour Veterinary Services",
    "wof:placetype":"venue"
},
  "geometry": {"coordinates":[152.95639038100001,-26.5611553192],"type":"Point"}
}