{
  "type": "Feature",
  "properties": {
    "addr:full":"23 Burbanks Elbow Wanneroo WA 6065",
    "addr:housenumber":"23",
    "addr:postcode":"6065",
    "addr:street":"Burbanks Elbow",
    "iso:country":"AU",
    "sg:address":"23 Burbanks Elbow",
    "sg:city":"Wanneroo",
    "sg:classifiers":[
        {
            "category":"Building & Trades",
            "subcategory":"Cleaning & Sanitation",
            "type":"Services"
        }
    ],
    "sg:phone":"+61 402 724 910",
    "sg:postcode":"6065",
    "sg:province":"WA",
    "sg:tags":[
        "window"
    ],
    "wof:name":"Rhino Clean",
    "wof:placetype":"venue"
},
  "geometry": {"coordinates":[115.814277649,-31.7493362427],"type":"Point"}
}