{
  "type": "Feature",
  "properties": {
    "addr:full":"10 -18 Lensworth St Coopers Plains QLD 4108",
    "addr:housenumber":"-18",
    "addr:postcode":"4108",
    "addr:street":"Lensworth St",
    "iso:country":"AU",
    "sg:address":"10 -18 Lensworth St",
    "sg:city":"Coopers Plains",
    "sg:classifiers":[
        {
            "category":"Professional",
            "subcategory":"Detective & Security Services",
            "type":"Services"
        }
    ],
    "sg:phone":"+61 1300 764 438",
    "sg:postcode":"4108",
    "sg:province":"QLD",
    "sg:tags":[
        "consultant",
        "system"
    ],
    "wof:name":"Academy Of Security & Training The",
    "wof:placetype":"venue"
},
  "geometry": {"coordinates":[153.035766602,-27.5728664398],"type":"Point"}
}