{
  "type": "Feature",
  "properties": {
    "addr:full":"U 8/ 63 Macgregor Tce Bardon QLD 4065",
    "addr:housenumber":"63",
    "addr:postcode":"4065",
    "addr:street":"Macgregor Tce Bardon",
    "iso:country":"AU",
    "sg:address":"U 8/ 63",
    "sg:city":"Macgregor Tce Bardon",
    "sg:classifiers":[
        {
            "category":"Social Services",
            "subcategory":"Child Care",
            "type":"Services"
        }
    ],
    "sg:phone":"+61 7 3369 0122",
    "sg:postcode":"4065",
    "sg:province":"QLD",
    "wof:name":"First Choice Child Care Management",
    "wof:placetype":"venue"
},
  "geometry": {"coordinates":[152.987594605,-27.4580230713],"type":"Point"}
}