{
  "type": "Feature",
  "properties": {
    "iso:country":"AU",
    "sg:address":"150 Palmerin St",
    "sg:city":"Warwick",
    "sg:classifiers":[
        {
            "category":"Health Services",
            "subcategory":"Dentist",
            "type":"Services"
        }
    ],
    "sg:phone":"+61 7 4661 1070",
    "sg:postcode":"4370",
    "sg:province":"QLD",
    "wof:name":"Timothy Williams DR",
    "wof:placetype":"venue"
},
  "geometry": {"coordinates":[152.032104492,-28.219789505],"type":"Point"}
}