{
  "type": "Feature",
  "properties": {
    "addr:full":"Shop 1, 60 Russell St Morley WA 6062",
    "addr:housenumber":"shop;60",
    "addr:postcode":"6062",
    "addr:street":"Russell St",
    "iso:country":"AU",
    "sg:address":"Shop 1, 60 Russell St",
    "sg:city":"Morley",
    "sg:classifiers":[
        {
            "category":"Fast Food",
            "type":"Food & Drink"
        }
    ],
    "sg:phone":"+61 8 9276 3344",
    "sg:postcode":"6062",
    "sg:province":"WA",
    "sg:tags":[
        "away",
        "take"
    ],
    "wof:name":"Nando's Flame Grilled Chicken",
    "wof:placetype":"venue"
},
  "geometry": {"coordinates":[115.89531707800001,-31.8968505859],"type":"Point"}
}