{
  "type": "Feature",
  "properties": {
    "addr:full":"16 Lakeview Ave West Lakes SA 5021",
    "addr:housenumber":"16",
    "addr:postcode":"5021",
    "addr:street":"Lakeview Ave",
    "iso:country":"AU",
    "sg:address":"16 Lakeview Ave",
    "sg:city":"West Lakes",
    "sg:classifiers":[
        {
            "category":"Building & Trades",
            "subcategory":"Plumbing",
            "type":"Services"
        }
    ],
    "sg:phone":"+61 417 360 589",
    "sg:postcode":"5021",
    "sg:province":"SA",
    "sg:tags":[
        "plumber",
        "gasfitters"
    ],
    "wof:name":"C & H Vecchio",
    "wof:placetype":"venue"
},
  "geometry": {"coordinates":[138.49525451700001,-34.8668861389],"type":"Point"}
}