{
  "type": "Feature",
  "properties": {
    "addr:full":"88 Portland St Croydon Park NSW 2133",
    "addr:housenumber":"88",
    "addr:postcode":"2133",
    "addr:street":"Portland St",
    "iso:country":"AU",
    "sg:address":"88 Portland St",
    "sg:city":"Croydon Park",
    "sg:classifiers":[
        {
            "category":"Real Estate",
            "subcategory":"Real Estate Agent",
            "type":"Services"
        }
    ],
    "sg:phone":"+61 2 9642 2143",
    "sg:postcode":"2133",
    "sg:province":"NSW",
    "sg:tags":[
        "handyman's",
        "equipment",
        "hire",
        "builders",
        "contractor"
    ],
    "wof:name":"Toddo Plant Hire",
    "wof:placetype":"venue"
},
  "geometry": {"coordinates":[151.09362793,-33.8981628418],"type":"Point"}
}