{
  "type": "Feature",
  "properties": {
    "addr:full":"Unit 9, 3 Reserve St West Ryde NSW 2114",
    "addr:housenumber":"3",
    "addr:postcode":"2114",
    "addr:street":"Reserve St",
    "iso:country":"AU",
    "sg:address":"Unit 9, 3 Reserve St",
    "sg:city":"West Ryde",
    "sg:classifiers":[
        {
            "category":"Health Services",
            "subcategory":"Doctor",
            "type":"Services"
        }
    ],
    "sg:phone":"+61 2 9804 7779",
    "sg:postcode":"2114",
    "sg:province":"NSW",
    "sg:tags":[
        "medical",
        "practitioner"
    ],
    "wof:name":"Haddad J Dr",
    "wof:placetype":"venue"
},
  "geometry": {"coordinates":[151.08912658700001,-33.8059082031],"type":"Point"}
}