{
  "type": "Feature",
  "properties": {
    "iso:country":"AU",
    "sg:address":"PO Box 5246",
    "sg:city":"Mackay Mail Centre",
    "sg:classifiers":[
        {
            "category":"Utilities",
            "subcategory":"Refuse",
            "type":"Services"
        }
    ],
    "sg:phone":"+61 7 4959 2911",
    "sg:postcode":"4741",
    "sg:province":"QLD",
    "sg:tags":[
        "remover",
        "rubbish"
    ],
    "wof:name":"All Mackay Garden Tidy",
    "wof:placetype":"venue"
},
  "geometry": {"coordinates":[148.339584,-21.01993],"type":"Point"}
}