{
  "type": "Feature",
  "properties": {
    "iso:country":"AU",
    "sg:address":"Greenwood Plaza 36 Blue St",
    "sg:city":"North Sydney",
    "sg:classifiers":[
        {
            "category":"Food & Beverages",
            "subcategory":"Fruits & Vegetables",
            "type":"Retail Goods"
        }
    ],
    "sg:phone":"+61 2 9957 3933",
    "sg:postcode":"2060",
    "sg:province":"NSW",
    "sg:tags":[
        "greengrocer",
        "fruiterer"
    ],
    "wof:name":"North Sydney Fresh Pty Ltd",
    "wof:placetype":"venue"
},
  "geometry": {"coordinates":[151.207855225,-33.8408737183],"type":"Point"}
}