{
  "type": "Feature",
  "properties": {
    "iso:country":"AU",
    "sg:address":"16-30 Eveleigh St",
    "sg:city":"Redfern",
    "sg:classifiers":[
        {
            "category":"Communications",
            "subcategory":"Film & Video Production",
            "type":"Services"
        }
    ],
    "sg:phone":"+61 2 9699 2422",
    "sg:postcode":"2016",
    "sg:province":"NSW",
    "sg:tags":[
        "services",
        "equipment",
        "microfilming",
        "supply"
    ],
    "wof:name":"Tuscan Industries",
    "wof:placetype":"venue"
},
  "geometry": {"coordinates":[151.19981384299999,-33.8894920349],"type":"Point"}
}