{
  "type": "Feature",
  "properties": {
    "iso:country":"AU",
    "sg:address":"Shop 6, 1613 Ocean Drv",
    "sg:city":"Lake Cathie",
    "sg:classifiers":[
        {
            "category":"Real Estate",
            "subcategory":"Real Estate Agent",
            "type":"Services"
        }
    ],
    "sg:phone":"+61 2 6585 4600",
    "sg:postcode":"2445",
    "sg:province":"NSW",
    "wof:name":"Settlement First National",
    "wof:placetype":"venue"
},
  "geometry": {"coordinates":[152.85476700000001,-31.552298],"type":"Point"}
}