{
  "type": "Feature",
  "properties": {
    "iso:country":"AU",
    "sg:address":"58 Ormond St",
    "sg:city":"Paddington",
    "sg:classifiers":[
        {
            "category":"Professional",
            "subcategory":"Employment Agencies",
            "type":"Services"
        }
    ],
    "sg:phone":"+61 2 9331 6969",
    "sg:postcode":"2021",
    "sg:province":"NSW",
    "sg:tags":[
        "model"
    ],
    "wof:name":"Elite Model Management Australia",
    "wof:placetype":"venue"
},
  "geometry": {"coordinates":[151.22662353499999,-33.8833236694],"type":"Point"}
}