{
  "type": "Feature",
  "properties": {
    "addr:full":"9 Gladstone St Hobart TAS 7000",
    "addr:housenumber":"9",
    "addr:postcode":"7000",
    "addr:street":"Gladstone St",
    "iso:country":"AU",
    "sg:address":"9 Gladstone St",
    "sg:city":"Hobart",
    "sg:classifiers":[
        {
            "category":"Personal",
            "subcategory":"Massage",
            "type":"Services"
        }
    ],
    "sg:phone":"+61 3 6223 3121",
    "sg:postcode":"7000",
    "sg:province":"TAS",
    "sg:tags":[
        "therapy"
    ],
    "wof:name":"Massage On Gladstone",
    "wof:placetype":"venue"
},
  "geometry": {"coordinates":[147.33013915999999,-42.887096405],"type":"Point"}
}