{
  "type": "Feature",
  "properties": {
    "iso:country":"AU",
    "sg:address":"20 Chapel St",
    "sg:city":"North Adelaide",
    "sg:classifiers":[
        {
            "category":"Retail",
            "subcategory":"Self-service Laundry",
            "type":"Services"
        }
    ],
    "sg:phone":"+61 8 8239 0985",
    "sg:postcode":"5006",
    "sg:province":"SA",
    "wof:name":"Village Wash House The",
    "wof:placetype":"venue"
},
  "geometry": {"coordinates":[138.595336914,-34.9064941406],"type":"Point"}
}