{
  "type": "Feature",
  "properties": {
    "addr:full":"4 Baldwin St Erskineville NSW 2043",
    "addr:housenumber":"4",
    "addr:postcode":"2043",
    "addr:street":"Baldwin St",
    "iso:country":"AU",
    "sg:address":"4 Baldwin St",
    "sg:city":"Erskineville",
    "sg:classifiers":[
        {
            "category":"Professional",
            "subcategory":"Art Services",
            "type":"Services"
        }
    ],
    "sg:phone":"+61 2 9517 1469",
    "sg:postcode":"2043",
    "sg:province":"NSW",
    "sg:tags":[
        "decorator",
        "painter"
    ],
    "wof:name":"Livingstone Flynn Painters and Decorators",
    "wof:placetype":"venue"
},
  "geometry": {"coordinates":[151.183243,-33.898857],"type":"Point"}
}