{
  "type": "Feature",
  "properties": {
    "iso:country":"AU",
    "sg:address":"24 Robin Crt",
    "sg:city":"Lindisfarne",
    "sg:classifiers":[
        {
            "category":"Personal",
            "type":"Services"
        }
    ],
    "sg:phone":"+61 409 976 394",
    "sg:postcode":"7015",
    "sg:province":"TAS",
    "sg:tags":[
        "career",
        "counselling"
    ],
    "wof:name":"Creese Management Solutions",
    "wof:placetype":"venue"
},
  "geometry": {"coordinates":[147.36781310999999,-42.8436126709],"type":"Point"}
}