{
  "type": "Feature",
  "properties": {
    "addr:full":"156 Wangee Rd Greenacre NSW 2190",
    "addr:housenumber":"156",
    "addr:postcode":"2190",
    "addr:street":"Wangee Rd",
    "iso:country":"AU",
    "sg:address":"156 Wangee Rd",
    "sg:city":"Greenacre",
    "sg:classifiers":[
        {
            "category":"Food & Beverages",
            "subcategory":"Supermarket",
            "type":"Retail Goods"
        }
    ],
    "sg:phone":"+61 2 9759 4956",
    "sg:postcode":"2190",
    "sg:province":"NSW",
    "sg:tags":[
        "grocery",
        "store"
    ],
    "wof:name":"Criniti F",
    "wof:placetype":"venue"
},
  "geometry": {"coordinates":[151.06852699999999,-33.910423],"type":"Point"}
}