{
  "type": "Feature",
  "properties": {
    "iso:country":"AU",
    "sg:address":"3/ 39 Mather Rd",
    "sg:city":"Neerabup",
    "sg:classifiers":[
        {
            "category":"Building & Trades",
            "subcategory":"Construction",
            "type":"Services"
        }
    ],
    "sg:phone":"+61 8 9305 2056",
    "sg:postcode":"6031",
    "sg:province":"WA",
    "sg:tags":[
        "welding"
    ],
    "wof:name":"Mobile West Coast Welding",
    "wof:placetype":"venue"
},
  "geometry": {"coordinates":[115.788803101,-31.6845989227],"type":"Point"}
}