{
  "type": "Feature",
  "properties": {
    "addr:full":"28 Blair St Moama VIC 2731",
    "addr:housenumber":"28",
    "addr:postcode":"2731",
    "addr:street":"Blair St",
    "iso:country":"AU",
    "sg:address":"28 Blair St",
    "sg:city":"Moama",
    "sg:classifiers":[
        {
            "category":"Professional",
            "subcategory":"Art Services",
            "type":"Services"
        }
    ],
    "sg:phone":"+61 409 944 379",
    "sg:postcode":"2731",
    "sg:province":"VIC",
    "sg:tags":[
        "decorator",
        "painter"
    ],
    "wof:name":"Matt Carroll Painting & Decorating",
    "wof:placetype":"venue"
},
  "geometry": {"coordinates":[144.77220199999999,-36.109035],"type":"Point"}
}