{
  "type": "Feature",
  "properties": {
    "addr:full":"4 Dixon St Royal Park SA 5014",
    "addr:housenumber":"4",
    "addr:postcode":"5014",
    "addr:street":"Dixon St",
    "iso:country":"AU",
    "sg:address":"4 Dixon St",
    "sg:city":"Royal Park",
    "sg:classifiers":[
        {
            "category":"Building & Trades",
            "subcategory":"Plumbing",
            "type":"Services"
        }
    ],
    "sg:phone":"+61 8 8447 2308",
    "sg:postcode":"5014",
    "sg:province":"SA",
    "sg:tags":[
        "plumber",
        "gasfitters"
    ],
    "wof:name":"Fisher Brian & Son Pty Ltd",
    "wof:placetype":"venue"
},
  "geometry": {"coordinates":[138.51182556099999,-34.8669052124],"type":"Point"}
}