{
  "type": "Feature",
  "properties": {
    "addr:full":"552 Barkly St West Footscray VIC 3012",
    "addr:housenumber":"552",
    "addr:postcode":"3012",
    "addr:street":"Barkly St",
    "iso:country":"AU",
    "sg:address":"552 Barkly St",
    "sg:city":"West Footscray",
    "sg:classifiers":[
        {
            "category":"Personal",
            "subcategory":"Beauty Salon",
            "type":"Services"
        }
    ],
    "sg:phone":"+61 3 9687 1662",
    "sg:postcode":"3012",
    "sg:province":"VIC",
    "sg:tags":[
        "hairdresser"
    ],
    "wof:name":"Yen Trang Hair Design",
    "wof:placetype":"venue"
},
  "geometry": {"coordinates":[144.87867736800001,-37.7974052429],"type":"Point"}
}