{
  "type": "Feature",
  "properties": {
    "iso:country":"AU",
    "sg:address":"65 Sanger St",
    "sg:city":"Corowa",
    "sg:classifiers":[
        {
            "category":"Banks & Credit Unions",
            "subcategory":"Bank",
            "type":"Services"
        }
    ],
    "sg:phone":"+61 13 20 32",
    "sg:postcode":"2646",
    "sg:province":"NSW",
    "wof:name":"Westpac",
    "wof:placetype":"venue"
},
  "geometry": {"coordinates":[146.39134216299999,-35.9949874878],"type":"Point"}
}