{
  "type": "Feature",
  "properties": {
    "addr:full":"Unit 9, 195 Landsborough Ave Scarborough QLD 4020",
    "addr:housenumber":"195",
    "addr:postcode":"4020",
    "addr:street":"Landsborough Ave",
    "iso:country":"AU",
    "sg:address":"Unit 9, 195 Landsborough Ave",
    "sg:city":"Scarborough",
    "sg:classifiers":[
        {
            "category":"Health Services",
            "subcategory":"Health Practitioner",
            "type":"Services"
        }
    ],
    "sg:phone":"+61 7 3203 4016",
    "sg:postcode":"4020",
    "sg:province":"QLD",
    "sg:tags":[
        "psychologist"
    ],
    "wof:name":"Blackwood Marilyn",
    "wof:placetype":"venue"
},
  "geometry": {"coordinates":[153.11440999999999,-27.204018],"type":"Point"}
}