{
  "type": "Feature",
  "properties": {
    "iso:country":"AU",
    "sg:address":"140 Geldart Rd",
    "sg:city":"Chandler",
    "sg:classifiers":[
        {
            "category":"Building & Trades",
            "subcategory":"Construction",
            "type":"Services"
        }
    ],
    "sg:phone":"+61 7 3390 1013",
    "sg:postcode":"4155",
    "sg:province":"QLD",
    "sg:tags":[
        "renovation",
        "alterations",
        "extension",
        "contractor"
    ],
    "wof:name":"Hoffie R & L Maintenance Services",
    "wof:placetype":"venue"
},
  "geometry": {"coordinates":[153.15826415999999,-27.5194149017],"type":"Point"}
}