{
  "type": "Feature",
  "properties": {
    "addr:full":"Flat 5- 44 Kororoit Ck Williamstown VIC 3016",
    "addr:housenumber":"44",
    "addr:postcode":"3016",
    "addr:street":"Kororoit",
    "iso:country":"AU",
    "sg:address":"Flat 5- 44 Kororoit Ck",
    "sg:city":"Williamstown",
    "sg:classifiers":[
        {
            "category":"Personal",
            "subcategory":"Massage",
            "type":"Services"
        }
    ],
    "sg:phone":"+61 3 9397 1685",
    "sg:postcode":"3016",
    "sg:province":"VIC",
    "sg:tags":[
        "therapy"
    ],
    "wof:name":"Kivinen Lorraine",
    "wof:placetype":"venue"
},
  "geometry": {"coordinates":[144.885620117,-37.8572883606],"type":"Point"}
}