{
  "type": "Feature",
  "properties": {
    "iso:country":"AU",
    "sg:address":"3 Arnold Ave",
    "sg:city":"Camden",
    "sg:classifiers":[
        {
            "category":"Building & Trades",
            "subcategory":"Pest Control",
            "type":"Services"
        }
    ],
    "sg:phone":"+61 2 4655 8110",
    "sg:postcode":"2570",
    "sg:province":"NSW",
    "wof:name":"I & A Pest Management Pty. Ltd.",
    "wof:placetype":"venue"
},
  "geometry": {"coordinates":[150.698165894,-34.0909118652],"type":"Point"}
}