{
  "type": "Feature",
  "properties": {
    "addr:full":"159 Edith St Innisfail QLD 4860",
    "addr:housenumber":"159",
    "addr:postcode":"4860",
    "addr:street":"Edith St",
    "iso:country":"AU",
    "sg:address":"159 Edith St",
    "sg:city":"Innisfail",
    "sg:classifiers":[
        {
            "category":"Utilities",
            "subcategory":"Electric",
            "type":"Services"
        }
    ],
    "sg:phone":"+61 7 4061 1524",
    "sg:postcode":"4860",
    "sg:province":"QLD",
    "sg:tags":[
        "electrical",
        "contractor"
    ],
    "wof:name":"Johnstone River Electrics",
    "wof:placetype":"venue"
},
  "geometry": {"coordinates":[146.02024841299999,-17.5238819122],"type":"Point"}
}