{
  "type": "Feature",
  "properties": {
    "addr:full":"216 Ryrie St Geelong VIC 3220",
    "addr:housenumber":"216",
    "addr:postcode":"3220",
    "addr:street":"Ryrie St",
    "iso:country":"AU",
    "sg:address":"216 Ryrie St",
    "sg:city":"Geelong",
    "sg:classifiers":[
        {
            "category":"Ice Cream",
            "type":"Food & Drink"
        }
    ],
    "sg:phone":"+61 3 5222 5536",
    "sg:postcode":"3220",
    "sg:province":"VIC",
    "sg:tags":[
        "retail"
    ],
    "wof:name":"Baskin-Robbins",
    "wof:placetype":"venue"
},
  "geometry": {"coordinates":[144.36140399999999,-38.149929],"type":"Point"}
}