{
  "type": "Feature",
  "properties": {
    "iso:country":"AU",
    "sg:address":"Unit 2/ 60 Machinery St",
    "sg:city":"Darra",
    "sg:classifiers":[
        {
            "category":"Wholesale",
            "subcategory":"Machinery & Supplies",
            "type":"Manufacturing & Wholesale Goods"
        }
    ],
    "sg:phone":"+61 7 3375 1612",
    "sg:postcode":"4076",
    "sg:province":"QLD",
    "sg:tags":[
        "engineer"
    ],
    "wof:name":"Hydraulink Fluid Connectors",
    "wof:placetype":"venue"
},
  "geometry": {"coordinates":[152.94874572800001,-27.5762004852],"type":"Point"}
}