{
  "type": "Feature",
  "properties": {
    "iso:country":"AU",
    "sg:address":"Level 5, Export House, 22 Pitt St",
    "sg:city":"Sydney",
    "sg:classifiers":[
        {
            "category":"Insurance",
            "subcategory":"Insurance Agent",
            "type":"Services"
        }
    ],
    "sg:phone":"+61 13 25 19",
    "sg:postcode":"2000",
    "sg:province":"NSW",
    "sg:tags":[
        "credit"
    ],
    "wof:name":"atradius#",
    "wof:placetype":"venue"
},
  "geometry": {"coordinates":[151.20932006800001,-33.8620605469],"type":"Point"}
}