{
  "type": "Feature",
  "properties": {
    "iso:country":"AU",
    "sg:address":"Woolcock St",
    "sg:city":"Garbutt",
    "sg:classifiers":[
        {
            "category":"Freight",
            "type":"Transportation"
        }
    ],
    "sg:phone":"+61 7 4728 2206",
    "sg:postcode":"4814",
    "sg:province":"QLD",
    "sg:tags":[
        "light",
        "carrier"
    ],
    "wof:name":"Signature Transport Services",
    "wof:placetype":"venue"
},
  "geometry": {"coordinates":[146.782639,-19.270138],"type":"Point"}
}