{
  "type": "Feature",
  "properties": {
    "addr:full":"Lightfoot St Mont Albert VIC 3127",
    "addr:postcode":"3127",
    "addr:street":"Lightfoot St",
    "iso:country":"AU",
    "sg:address":"Lightfoot St",
    "sg:city":"Mont Albert",
    "sg:classifiers":[
        {
            "category":"Manufacturing",
            "subcategory":"Glass & Minerals",
            "type":"Manufacturing & Wholesale Goods"
        }
    ],
    "sg:phone":"+61 3 9836 4336",
    "sg:postcode":"3127",
    "sg:province":"VIC",
    "sg:tags":[
        "merchant",
        "granite",
        "marble"
    ],
    "wof:name":"Accent On Fireplaces",
    "wof:placetype":"venue"
},
  "geometry": {"coordinates":[145.10496520999999,-37.8132286072],"type":"Point"}
}