{
  "type": "Feature",
  "properties": {
    "iso:country":"AU",
    "sg:address":"Level 2 181 Fitzroy St St",
    "sg:city":"Kilda",
    "sg:classifiers":[
        {
            "category":"Banks & Credit Unions",
            "subcategory":"Atm",
            "type":"Services"
        }
    ],
    "sg:phone":"+61 3 9536 7444",
    "sg:postcode":"3182",
    "sg:province":"VIC",
    "sg:tags":[
        "premium",
        "insurance",
        "finance"
    ],
    "wof:name":"Pacific Premium Funding",
    "wof:placetype":"venue"
},
  "geometry": {"coordinates":[144.981323242,-37.8575973511],"type":"Point"}
}