{
  "type": "Feature",
  "properties": {
    "addr:full":"Unit 11 23 Murphy St Launceston TAS 7250",
    "addr:housenumber":"23",
    "addr:postcode":"7250",
    "addr:street":"Murphy St",
    "iso:country":"AU",
    "sg:address":"Unit 11 23 Murphy St",
    "sg:city":"Launceston",
    "sg:classifiers":[
        {
            "category":"Professional",
            "type":"Services"
        }
    ],
    "sg:phone":"+61 3 6331 9666",
    "sg:postcode":"7250",
    "sg:province":"TAS",
    "sg:tags":[
        "buyer",
        "merchant",
        "wool"
    ],
    "wof:name":"Conn Wool Pty Ltd",
    "wof:placetype":"venue"
},
  "geometry": {"coordinates":[147.12522888199999,-41.4251556396],"type":"Point"}
}