{
  "type": "Feature",
  "properties": {
    "iso:country":"AU",
    "sg:address":"Lvl 1, 123 Maling Rd",
    "sg:city":"Canterbury",
    "sg:classifiers":[
        {
            "category":"Health Services",
            "subcategory":"Health Practitioner",
            "type":"Services"
        }
    ],
    "sg:phone":"+61 3 9830 7797",
    "sg:postcode":"3126",
    "sg:province":"VIC",
    "sg:tags":[
        "psychologist"
    ],
    "wof:name":"Message John",
    "wof:placetype":"venue"
},
  "geometry": {"coordinates":[145.081542969,-37.824760437],"type":"Point"}
}