{
  "type": "Feature",
  "properties": {
    "addr:full":"Cnr Cormack & Plymouth Rds Wingfield SA 5013",
    "addr:postcode":"5013",
    "addr:street":"Cnr",
    "iso:country":"AU",
    "sg:address":"Cnr Cormack & Plymouth Rds",
    "sg:city":"Wingfield",
    "sg:classifiers":[
        {
            "category":"Freight",
            "type":"Transportation"
        }
    ],
    "sg:phone":"+61 8 8345 1800",
    "sg:postcode":"5013",
    "sg:province":"SA",
    "sg:tags":[
        "light",
        "carrier"
    ],
    "wof:name":"Northern Kope Parcel Express",
    "wof:placetype":"venue"
},
  "geometry": {"coordinates":[138.563964844,-34.8405456543],"type":"Point"}
}