{
  "type": "Feature",
  "properties": {
    "addr:full":"PO Box 148 Nobby Beach QLD 4218",
    "addr:postcode":"4218",
    "iso:country":"AU",
    "sg:address":"PO Box 148",
    "sg:city":"Nobby Beach",
    "sg:classifiers":[
        {
            "category":"Building & Trades",
            "subcategory":"Construction",
            "type":"Services"
        }
    ],
    "sg:phone":"+61 405 106 605",
    "sg:postcode":"4218",
    "sg:province":"QLD",
    "sg:tags":[
        "home",
        "air conditioning"
    ],
    "wof:name":"Express Air Conditioning Services",
    "wof:placetype":"venue"
},
  "geometry": {"coordinates":[153.438262939,-28.0588607788],"type":"Point"}
}