{
  "type": "Feature",
  "properties": {
    "addr:full":"314 Station St Lalor VIC 3075",
    "addr:housenumber":"314",
    "addr:postcode":"3075",
    "addr:street":"Station St",
    "iso:country":"AU",
    "sg:address":"314 Station St",
    "sg:city":"Lalor",
    "sg:classifiers":[
        {
            "category":"Food & Beverages",
            "subcategory":"Bakery",
            "type":"Retail Goods"
        }
    ],
    "sg:phone":"+61 3 9465 3419",
    "sg:postcode":"3075",
    "sg:province":"VIC",
    "sg:tags":[
        "cake",
        "shop",
        "pastry"
    ],
    "wof:name":"Cake Box",
    "wof:placetype":"venue"
},
  "geometry": {"coordinates":[145.020141602,-37.766040802],"type":"Point"}
}