{
  "type": "Feature",
  "properties": {
    "iso:country":"AU",
    "sg:address":"26-30 Tedder Ave",
    "sg:city":"Main Beach",
    "sg:classifiers":[
        {
            "category":"Professional",
            "subcategory":"Art Services",
            "type":"Services"
        }
    ],
    "sg:phone":"+61 7 5532 6327",
    "sg:postcode":"4217",
    "sg:province":"QLD",
    "sg:tags":[
        "product",
        "industrial",
        "designer"
    ],
    "wof:name":"3Di Design",
    "wof:placetype":"venue"
},
  "geometry": {"coordinates":[153.42500305199999,-27.9781932831],"type":"Point"}
}