{
  "type": "Feature",
  "properties": {
    "addr:full":"Blairs Rd Bundaberg QLD 4670",
    "addr:postcode":"4670",
    "addr:street":"Blairs Rd",
    "iso:country":"AU",
    "sg:address":"Blairs Rd",
    "sg:city":"Bundaberg",
    "sg:classifiers":[
        {
            "category":"Professional",
            "subcategory":"Printing & Photocopies",
            "type":"Services"
        }
    ],
    "sg:phone":"+61 7 4159 9068",
    "sg:postcode":"4670",
    "sg:province":"QLD",
    "sg:tags":[
        "trophy"
    ],
    "wof:name":"Hoofprints Show Ribbons",
    "wof:placetype":"venue"
},
  "geometry": {"coordinates":[152.27345275900001,-24.8498535156],"type":"Point"}
}