{
  "type": "Feature",
  "properties": {
    "addr:full":"677 New Cleveland Rd Gumdale QLD 4154",
    "addr:housenumber":"677",
    "addr:postcode":"4154",
    "addr:street":"New Cleveland Rd",
    "iso:country":"AU",
    "sg:address":"677 New Cleveland Rd",
    "sg:city":"Gumdale",
    "sg:classifiers":[
        {
            "category":"Education",
            "subcategory":"School",
            "type":"Public Place"
        }
    ],
    "sg:phone":"+61 7 3902 8383",
    "sg:postcode":"4154",
    "sg:province":"QLD",
    "sg:tags":[
        "state",
        "except",
        "nsw"
    ],
    "wof:name":"Gumdale Preschool",
    "wof:placetype":"venue"
},
  "geometry": {"coordinates":[153.15213012699999,-27.4908046722],"type":"Point"}
}