{
  "type": "Feature",
  "properties": {
    "addr:full":"316 Hanson Rd Wingfield SA 5013",
    "addr:housenumber":"316",
    "addr:postcode":"5013",
    "addr:street":"Hanson Rd",
    "iso:country":"AU",
    "sg:address":"316 Hanson Rd",
    "sg:city":"Wingfield",
    "sg:classifiers":[
        {
            "category":"Wholesale",
            "subcategory":"Auto Parts",
            "type":"Manufacturing & Wholesale Goods"
        }
    ],
    "sg:phone":"+61 8 8268 5571",
    "sg:postcode":"5013",
    "sg:province":"SA",
    "sg:tags":[
        "recyclers"
    ],
    "wof:name":"Costless Auto Wreckers",
    "wof:placetype":"venue"
},
  "geometry": {"coordinates":[138.54666137699999,-34.8470954895],"type":"Point"}
}