{
  "type": "Feature",
  "properties": {
    "iso:country":"AU",
    "sg:address":"3 Murray Rd",
    "sg:city":"Frenchman Bay",
    "sg:classifiers":[
        {
            "category":"Food & Beverages",
            "subcategory":"Meat & Fish",
            "type":"Retail Goods"
        }
    ],
    "sg:phone":"+61 8 9844 4000",
    "sg:postcode":"6330",
    "sg:province":"WA",
    "sg:tags":[
        "aquaculture"
    ],
    "wof:name":"Great Southern Marine Hatcheries",
    "wof:placetype":"venue"
},
  "geometry": {"coordinates":[117.963012695,-35.0953140259],"type":"Point"}
}