{
  "type": "Feature",
  "properties": {
    "addr:full":"118 South Pine Rd Brendale QLD 4500",
    "addr:housenumber":"118",
    "addr:postcode":"4500",
    "addr:street":"South Pine Rd",
    "iso:country":"AU",
    "sg:address":"118 South Pine Rd",
    "sg:city":"Brendale",
    "sg:classifiers":[
        {
            "category":"Industrial Area",
            "type":"Public Place"
        }
    ],
    "sg:phone":"+61 7 3480 1653",
    "sg:postcode":"4500",
    "sg:province":"QLD",
    "sg:tags":[
        "rural",
        "shed"
    ],
    "wof:name":"ASI Building Systems",
    "wof:placetype":"venue"
},
  "geometry": {"coordinates":[152.982147217,-27.3266239166],"type":"Point"}
}