{
  "type": "Feature",
  "properties": {
    "addr:full":"74 Williamstown Rd Footscray West VIC 3012",
    "addr:housenumber":"74",
    "addr:postcode":"3012",
    "addr:street":"Williamstown Rd",
    "iso:country":"AU",
    "sg:address":"74 Williamstown Rd",
    "sg:city":"Footscray West",
    "sg:classifiers":[
        {
            "category":"Banks & Credit Unions",
            "subcategory":"Financial Services",
            "type":"Services"
        }
    ],
    "sg:phone":"+61 3 9689 5200",
    "sg:postcode":"3012",
    "sg:province":"VIC",
    "sg:tags":[
        "planning"
    ],
    "wof:name":"Christopher Cashia & Associates",
    "wof:placetype":"venue"
},
  "geometry": {"coordinates":[144.88444519000001,-37.8068122864],"type":"Point"}
}