{
  "type": "Feature",
  "properties": {
    "addr:full":"Unit 37/ 640- 680 Geelong Rd Brooklyn VIC 3025",
    "addr:housenumber":"/",
    "addr:postcode":"680;3025",
    "addr:street":"Geelong Rd",
    "iso:country":"AU",
    "sg:address":"Unit 37/ 640- 680 Geelong Rd",
    "sg:city":"Brooklyn",
    "sg:classifiers":[
        {
            "category":"Utilities",
            "subcategory":"Cable",
            "type":"Services"
        }
    ],
    "sg:phone":"+61 3 9316 1000",
    "sg:postcode":"3025",
    "sg:province":"VIC",
    "sg:tags":[
        "equipment",
        "meters"
    ],
    "wof:name":"Skilltech Consulting Services Pty Ltd",
    "wof:placetype":"venue"
},
  "geometry": {"coordinates":[144.837997,-37.820152],"type":"Point"}
}