{
  "type": "Feature",
  "properties": {
    "iso:country":"AU",
    "sg:address":"72 Napier St",
    "sg:city":"Deniliquin",
    "sg:classifiers":[
        {
            "category":"Retail",
            "subcategory":"Auto Repair",
            "type":"Services"
        }
    ],
    "sg:phone":"+61 3 5881 1747",
    "sg:postcode":"2710",
    "sg:province":"VIC",
    "sg:tags":[
        "repairer",
        "motor",
        "engineer"
    ],
    "wof:name":"Lehman B & C Mechanical Repairs",
    "wof:placetype":"venue"
},
  "geometry": {"coordinates":[144.95941162099999,-35.5310401917],"type":"Point"}
}