{
  "type": "Feature",
  "properties": {
    "iso:country":"AU",
    "sg:address":"126 Napoleon St",
    "sg:city":"Eltham",
    "sg:classifiers":[
        {
            "category":"Manufacturing",
            "subcategory":"Tools & Machinery",
            "type":"Manufacturing & Wholesale Goods"
        }
    ],
    "sg:phone":"+61 3 9439 0089",
    "sg:postcode":"3095",
    "sg:province":"VIC",
    "sg:tags":[
        "manufactured",
        "specially",
        "designed"
    ],
    "wof:name":"Angel Design ( Aus) pty ltd",
    "wof:placetype":"venue"
},
  "geometry": {"coordinates":[145.15211486800001,-37.7243995667],"type":"Point"}
}