{
  "type": "Feature",
  "properties": {
    "addr:full":"593- 595 Blackburn Rd Notting Hill VIC 3168",
    "addr:housenumber":"595",
    "addr:postcode":"3168",
    "addr:street":"Blackburn Rd",
    "iso:country":"AU",
    "sg:address":"593- 595 Blackburn Rd",
    "sg:city":"Notting Hill",
    "sg:classifiers":[
        {
            "category":"Utilities",
            "subcategory":"Telephone",
            "type":"Services"
        }
    ],
    "sg:phone":"+61 3 9590 1000",
    "sg:postcode":"3168",
    "sg:province":"VIC",
    "sg:tags":[
        "equipment",
        "system"
    ],
    "wof:name":"Nortel Networks Australia Pty. Ltd.",
    "wof:placetype":"venue"
},
  "geometry": {"coordinates":[145.142303467,-37.9040298462],"type":"Point"}
}