{
  "type": "Feature",
  "properties": {
    "iso:country":"AU",
    "sg:address":"29 Grimwade Crs",
    "sg:city":"Frankston",
    "sg:classifiers":[
        {
            "category":"Wholesale",
            "subcategory":"Machinery & Supplies",
            "type":"Manufacturing & Wholesale Goods"
        }
    ],
    "sg:phone":"+61 1800 817 135",
    "sg:postcode":"3199",
    "sg:province":"VIC",
    "sg:tags":[
        "process",
        "instrument",
        "control"
    ],
    "wof:name":"Vega Australia Pty Ltd",
    "wof:placetype":"venue"
},
  "geometry": {"coordinates":[145.00411987300001,-37.7022476196],"type":"Point"}
}