{
  "type": "Feature",
  "properties": {
    "addr:full":"Level 3 / 358 Lonsdale St Melbourne VIC 3000",
    "addr:housenumber":"/ 358",
    "addr:postcode":"3000",
    "addr:street":"Lonsdale St",
    "iso:country":"AU",
    "sg:address":"Level 3 / 358 Lonsdale St",
    "sg:city":"Melbourne",
    "sg:classifiers":[
        {
            "category":"Real Estate",
            "subcategory":"Architect",
            "type":"Services"
        }
    ],
    "sg:phone":"+61 1300 855 766",
    "sg:postcode":"3000",
    "sg:province":"VIC",
    "wof:name":"David Moore Architect",
    "wof:placetype":"venue"
},
  "geometry": {"coordinates":[144.96473693900001,-37.8172607422],"type":"Point"}
}