{
  "type": "Feature",
  "properties": {
    "addr:full":"302 Wardell St Enoggera QLD 4051",
    "addr:housenumber":"302",
    "addr:postcode":"4051",
    "addr:street":"Wardell St",
    "iso:country":"AU",
    "sg:address":"302 Wardell St",
    "sg:city":"Enoggera",
    "sg:classifiers":[
        {
            "category":"Health Services",
            "subcategory":"Health Practitioner",
            "type":"Services"
        }
    ],
    "sg:phone":"+61 7 3855 5900",
    "sg:postcode":"4051",
    "sg:province":"QLD",
    "sg:tags":[
        "physiotherapist"
    ],
    "wof:name":"Box Robyn Dr",
    "wof:placetype":"venue"
},
  "geometry": {"coordinates":[152.99037170400001,-27.4237174988],"type":"Point"}
}