{
  "type": "Feature",
  "properties": {
    "addr:full":"170 Bardon Ave Miami QLD 4220",
    "addr:housenumber":"170",
    "addr:postcode":"4220",
    "addr:street":"Bardon Ave",
    "iso:country":"AU",
    "sg:address":"170 Bardon Ave",
    "sg:city":"Miami",
    "sg:classifiers":[
        {
            "category":"Social Services",
            "subcategory":"Retirement Home",
            "type":"Services"
        }
    ],
    "sg:phone":"+61 7 5535 3327",
    "sg:postcode":"4220",
    "sg:province":"QLD",
    "sg:tags":[
        "village"
    ],
    "wof:name":"Miami Village",
    "wof:placetype":"venue"
},
  "geometry": {"coordinates":[153.42536926299999,-28.0682659149],"type":"Point"}
}