{
  "type": "Feature",
  "properties": {
    "addr:full":"7 Westside Ave Port Melbourne VIC 3207",
    "addr:housenumber":"7",
    "addr:postcode":"3207",
    "addr:street":"Westside Ave",
    "iso:country":"AU",
    "sg:address":"7 Westside Ave",
    "sg:city":"Port Melbourne",
    "sg:classifiers":[
        {
            "category":"Professional",
            "subcategory":"Computer Services",
            "type":"Services"
        }
    ],
    "sg:phone":"+61 1300 275 472",
    "sg:postcode":"3207",
    "sg:province":"VIC",
    "sg:tags":[
        "tele-communications",
        "consultant"
    ],
    "wof:name":"Blitz Telecom (Australia) Pty Ltd",
    "wof:placetype":"venue"
},
  "geometry": {"coordinates":[144.91784699999999,-37.82198],"type":"Point"}
}