{
  "type": "Feature",
  "properties": {
    "iso:country":"AU",
    "sg:address":"407 Gosport St",
    "sg:city":"Moree",
    "sg:classifiers":[
        {
            "category":"Wholesale",
            "subcategory":"Farm Supplies",
            "type":"Manufacturing & Wholesale Goods"
        }
    ],
    "sg:phone":"+61 2 6752 5300",
    "sg:postcode":"2400",
    "sg:province":"NSW",
    "sg:tags":[
        "equipment"
    ],
    "wof:name":"B & W Rural Pty Ltd",
    "wof:placetype":"venue"
},
  "geometry": {"coordinates":[149.847366333,-29.4778614044],"type":"Point"}
}