{
  "type": "Feature",
  "properties": {
    "addr:full":"5 Healthscope Crt Mildura VIC 3500",
    "addr:housenumber":"5",
    "addr:postcode":"3500",
    "addr:street":"Healthscope Crt",
    "iso:country":"AU",
    "sg:address":"5 Healthscope Crt",
    "sg:city":"Mildura",
    "sg:classifiers":[
        {
            "category":"Health Services",
            "subcategory":"Doctor",
            "type":"Services"
        }
    ],
    "sg:phone":"+61 3 5051 2405",
    "sg:postcode":"3500",
    "sg:province":"VIC",
    "sg:tags":[
        "medical",
        "practitioner"
    ],
    "wof:name":"Petrucco M",
    "wof:placetype":"venue"
},
  "geometry": {"coordinates":[142.154098511,-34.2107391357],"type":"Point"}
}