{
  "type": "Feature",
  "properties": {
    "addr:full":"115 Boat Harbour Drv Pialba QLD 4655",
    "addr:housenumber":"115",
    "addr:postcode":"4655",
    "addr:street":"Boat Harbour Drv",
    "iso:country":"AU",
    "sg:address":"115 Boat Harbour Drv",
    "sg:city":"Pialba",
    "sg:classifiers":[
        {
            "category":"Travel",
            "subcategory":"Hotels & Motels",
            "type":"Entertainment"
        }
    ],
    "sg:phone":"+61 7 4124 4222",
    "sg:postcode":"4655",
    "sg:province":"QLD",
    "sg:tags":[
        "accommodation"
    ],
    "wof:name":"Big Can Liquor Barn (Giants)",
    "wof:placetype":"venue"
},
  "geometry": {"coordinates":[152.841553,-25.288782],"type":"Point"}
}