{
  "type": "Feature",
  "properties": {
    "iso:country":"AU",
    "sg:address":"Cnr Strickland Rd & Beischer St",
    "sg:city":"Bendigo",
    "sg:classifiers":[
        {
            "category":"Home & Garden",
            "subcategory":"Household Appliances",
            "type":"Retail Goods"
        }
    ],
    "sg:phone":"+61 3 5442 1655",
    "sg:postcode":"3550",
    "sg:province":"VIC",
    "sg:tags":[
        "heating",
        "system"
    ],
    "wof:name":"McCaig Air Conditioning",
    "wof:placetype":"venue"
},
  "geometry": {"coordinates":[144.29603576700001,-36.7509155273],"type":"Point"}
}