{
  "type": "Feature",
  "properties": {
    "addr:full":"PO Box 426 Frenchs Forest NSW 1640",
    "addr:postcode":"1640",
    "iso:country":"AU",
    "sg:address":"PO Box 426",
    "sg:city":"Frenchs Forest",
    "sg:classifiers":[
        {
            "category":"Mining & Drilling",
            "type":"Manufacturing & Wholesale Goods"
        }
    ],
    "sg:phone":"+61 2 9905 8188",
    "sg:postcode":"1640",
    "sg:province":"NSW",
    "sg:tags":[
        "boring",
        "contractor"
    ],
    "wof:name":"Diacore Pty Ltd",
    "wof:placetype":"venue"
},
  "geometry": {"coordinates":[151.22604370100001,-33.7509613037],"type":"Point"}
}