{
  "type": "Feature",
  "properties": {
    "addr:full":"81 Wilsons Rd Newcomb VIC 3219",
    "addr:housenumber":"81",
    "addr:postcode":"3219",
    "addr:street":"Wilsons Rd",
    "iso:country":"AU",
    "sg:address":"81 Wilsons Rd",
    "sg:city":"Newcomb",
    "sg:classifiers":[
        {
            "category":"Education",
            "subcategory":"School",
            "type":"Public Place"
        }
    ],
    "sg:phone":"+61 3 5248 1093",
    "sg:postcode":"3219",
    "sg:province":"VIC",
    "sg:tags":[
        "co-educational"
    ],
    "wof:name":"Christ The King School",
    "wof:placetype":"venue"
},
  "geometry": {"coordinates":[144.39242553700001,-38.1662788391],"type":"Point"}
}