{
  "type": "Feature",
  "properties": {
    "addr:full":"Somerset Sports College, 131 Dundas St West Ormiston QLD 4160",
    "addr:housenumber":"131",
    "addr:postcode":"4160",
    "addr:street":"Dundas St West",
    "iso:country":"AU",
    "sg:address":"Somerset Sports College, 131 Dundas St West",
    "sg:city":"Ormiston",
    "sg:classifiers":[
        {
            "category":"Health Services",
            "subcategory":"Health Practitioner",
            "type":"Services"
        }
    ],
    "sg:phone":"+61 422 570 745",
    "sg:postcode":"4160",
    "sg:province":"QLD",
    "sg:tags":[
        "physiotherapist"
    ],
    "wof:name":"Ormiston College",
    "wof:placetype":"venue"
},
  "geometry": {"coordinates":[153.24562072800001,-27.5151939392],"type":"Point"}
}