{
  "type": "Feature",
  "properties": {
    "iso:country":"AU",
    "sg:address":"PO Box 235",
    "sg:city":"Carina",
    "sg:classifiers":[
        {
            "category":"Education",
            "subcategory":"Special Training",
            "type":"Public Place"
        }
    ],
    "sg:phone":"+61 7 3398 8832",
    "sg:postcode":"4152",
    "sg:province":"QLD",
    "sg:tags":[
        "development"
    ],
    "wof:name":"Courage To Speak",
    "wof:placetype":"venue"
},
  "geometry": {"coordinates":[153.07696533199999,-27.50041008],"type":"Point"}
}