{
  "type": "Feature",
  "properties": {
    "iso:country":"AU",
    "sg:address":"Waterloo Corner Rd",
    "sg:city":"Salisbury North",
    "sg:classifiers":[
        {
            "category":"Fast Food",
            "type":"Food & Drink"
        }
    ],
    "sg:phone":"+61 8 8258 1325",
    "sg:postcode":"5108",
    "sg:province":"SA",
    "sg:tags":[
        "away",
        "take"
    ],
    "wof:name":"Chicken Cave",
    "wof:placetype":"venue"
},
  "geometry": {"coordinates":[138.622848511,-34.7508621216],"type":"Point"}
}