{
  "type": "Feature",
  "properties": {
    "addr:full":"65A Fyans St Geelong VIC 3220",
    "addr:housenumber":"65a",
    "addr:postcode":"3220",
    "addr:street":"Fyans St",
    "iso:country":"AU",
    "sg:address":"65A Fyans St",
    "sg:city":"Geelong",
    "sg:classifiers":[
        {
            "category":"Home & Garden",
            "subcategory":"Building Materials",
            "type":"Retail Goods"
        }
    ],
    "sg:phone":"+61 412 436 278",
    "sg:postcode":"3220",
    "sg:province":"VIC",
    "sg:tags":[
        "lawn",
        "cutting",
        "maintenance"
    ],
    "wof:name":"Sister Act",
    "wof:placetype":"venue"
},
  "geometry": {"coordinates":[144.355896,-38.162003],"type":"Point"}
}