{
  "type": "Feature",
  "properties": {
    "addr:full":"Reynolds Rd Belmont VIC 3216",
    "addr:postcode":"3216",
    "addr:street":"Reynolds Rd",
    "iso:country":"AU",
    "sg:address":"Reynolds Rd",
    "sg:city":"Belmont",
    "sg:classifiers":[
        {
            "category":"Shopping",
            "subcategory":"Party Supplies",
            "type":"Retail Goods"
        }
    ],
    "sg:phone":"+61 3 5241 2200",
    "sg:postcode":"3216",
    "sg:province":"VIC",
    "sg:tags":[
        "children's"
    ],
    "wof:name":"Geelong Bowling Lanes",
    "wof:placetype":"venue"
},
  "geometry": {"coordinates":[144.32701110799999,-38.1777305603],"type":"Point"}
}