{
  "type": "Feature",
  "properties": {
    "iso:country":"AU",
    "sg:address":"12 Kemp St",
    "sg:city":"Wallsend",
    "sg:classifiers":[
        {
            "category":"Health Services",
            "subcategory":"Health Practitioner",
            "type":"Services"
        }
    ],
    "sg:phone":"+61 2 4951 2199",
    "sg:postcode":"2287",
    "sg:province":"NSW",
    "sg:tags":[
        "physiotherapist"
    ],
    "wof:name":"Karen James Physio",
    "wof:placetype":"venue"
},
  "geometry": {"coordinates":[151.670455933,-32.9021148682],"type":"Point"}
}