{
  "type": "Feature",
  "properties": {
    "addr:full":"39 Cypress St Torquay QLD 4655",
    "addr:housenumber":"39",
    "addr:postcode":"4655",
    "addr:street":"Cypress St",
    "iso:country":"AU",
    "sg:address":"39 Cypress St",
    "sg:city":"Torquay",
    "sg:classifiers":[
        {
            "category":"Health Services",
            "subcategory":"Health Practitioner",
            "type":"Services"
        }
    ],
    "sg:phone":"+61 7 4125 4218",
    "sg:postcode":"4655",
    "sg:province":"QLD",
    "sg:tags":[
        "bowen",
        "therapy"
    ],
    "wof:name":"Absolute Bowen Therapy Clinic",
    "wof:placetype":"venue"
},
  "geometry": {"coordinates":[152.87623600000001,-25.284748],"type":"Point"}
}