{
  "type": "Feature",
  "properties": {
    "addr:full":"Cnr Stuart Ave & Fordholm Rd Hampton Park VIC 3976",
    "addr:postcode":"3976",
    "addr:street":"Cnr Stuart Ave & Fordholm Rd",
    "iso:country":"AU",
    "sg:address":"Cnr Stuart Ave & Fordholm Rd",
    "sg:city":"Hampton Park",
    "sg:classifiers":[
        {
            "category":"Health Services",
            "subcategory":"Doctor",
            "type":"Services"
        }
    ],
    "sg:phone":"+61 3 9799 2233",
    "sg:postcode":"3976",
    "sg:province":"VIC",
    "sg:tags":[
        "medical",
        "practitioner"
    ],
    "wof:name":"Troedson Gayle",
    "wof:placetype":"venue"
},
  "geometry": {"coordinates":[145.26371765100001,-38.0344810486],"type":"Point"}
}