{
  "type": "Feature",
  "properties": {
    "iso:country":"AU",
    "sg:address":"114 Hertford St",
    "sg:city":"Sebastopol",
    "sg:classifiers":[
        {
            "category":"Autos & Motor Vehicles",
            "subcategory":"Automobile Sales",
            "type":"Retail Goods"
        }
    ],
    "sg:phone":"+61 3 5336 2158",
    "sg:postcode":"3356",
    "sg:province":"VIC",
    "sg:tags":[
        "car",
        "used"
    ],
    "wof:name":"Ballarat's Cheapest Cars",
    "wof:placetype":"venue"
},
  "geometry": {"coordinates":[143.826874,-37.587086],"type":"Point"}
}