{
  "type": "Feature",
  "properties": {
    "iso:country":"AU",
    "sg:address":"2B Canterbury St",
    "sg:city":"Deer Park",
    "sg:classifiers":[
        {
            "category":"Fast Food",
            "type":"Food & Drink"
        }
    ],
    "sg:phone":"+61 3 9363 6181",
    "sg:postcode":"3023",
    "sg:province":"VIC",
    "sg:tags":[
        "away",
        "take"
    ],
    "wof:name":"Dial A Menu Home Delivery Service",
    "wof:placetype":"venue"
},
  "geometry": {"coordinates":[144.77432300000001,-37.771275],"type":"Point"}
}