{
  "type": "Feature",
  "properties": {
    "addr:full":"64 Simmons Rd North Ipswich QLD 4305",
    "addr:housenumber":"64",
    "addr:postcode":"4305",
    "addr:street":"Simmons Rd",
    "iso:country":"AU",
    "sg:address":"64 Simmons Rd",
    "sg:city":"North Ipswich",
    "sg:classifiers":[
        {
            "category":"Home & Garden",
            "subcategory":"Building Materials",
            "type":"Retail Goods"
        }
    ],
    "sg:phone":"+61 7 3389 9078",
    "sg:postcode":"4305",
    "sg:province":"QLD",
    "sg:tags":[
        "merchant",
        "glass",
        "glazier"
    ],
    "wof:name":"Pro Glass & Glazing",
    "wof:placetype":"venue"
},
  "geometry": {"coordinates":[152.76136779800001,-27.5864772797],"type":"Point"}
}