{
  "type": "Feature",
  "properties": {
    "iso:country":"AU",
    "sg:address":"162 The Entrance Rd",
    "sg:city":"Erina",
    "sg:classifiers":[
        {
            "category":"Banks & Credit Unions",
            "subcategory":"Investment Brokerage",
            "type":"Services"
        }
    ],
    "sg:phone":"+61 2 4367 2555",
    "sg:postcode":"2250",
    "sg:province":"NSW",
    "sg:tags":[
        "broker"
    ],
    "wof:name":"BXI NSW",
    "wof:placetype":"venue"
},
  "geometry": {"coordinates":[151.384643555,-33.4362258911],"type":"Point"}
}