{
  "type": "Feature",
  "properties": {
    "iso:country":"AU",
    "sg:address":"38 Gymea Bay Rd",
    "sg:city":"Gymea",
    "sg:classifiers":[
        {
            "category":"Food & Beverages",
            "subcategory":"Supermarket",
            "type":"Retail Goods"
        }
    ],
    "sg:phone":"+61 2 9524 2228",
    "sg:postcode":"2227",
    "sg:province":"NSW",
    "sg:tags":[
        "grocery",
        "store"
    ],
    "wof:name":"Gymea Supermarket",
    "wof:placetype":"venue"
},
  "geometry": {"coordinates":[151.08535766599999,-34.0341644287],"type":"Point"}
}