{
  "type": "Feature",
  "properties": {
    "addr:full":"Swinstone St Rockingham WA 6168",
    "addr:postcode":"6168",
    "addr:street":"St",
    "iso:country":"AU",
    "sg:address":"Swinstone St",
    "sg:city":"Rockingham",
    "sg:classifiers":[
        {
            "category":"Education",
            "subcategory":"Kindergarten",
            "type":"Public Place"
        }
    ],
    "sg:phone":"+61 8 9527 1588",
    "sg:postcode":"6168",
    "sg:province":"WA",
    "sg:tags":[
        "pre-schools"
    ],
    "wof:name":"Catholic Church",
    "wof:placetype":"venue"
},
  "geometry": {"coordinates":[115.73906700000001,-32.286041],"type":"Point"}
}