{
  "type": "Feature",
  "properties": {
    "addr:full":"205 Sringwood Rd Springwood QLD 4127",
    "addr:housenumber":"205",
    "addr:postcode":"4127",
    "addr:street":"Sringwood Rd",
    "iso:country":"AU",
    "sg:address":"205 Sringwood Rd",
    "sg:city":"Springwood",
    "sg:classifiers":[
        {
            "category":"Structure",
            "subcategory":"Building",
            "type":"Public Place"
        }
    ],
    "sg:phone":"+61 402 851 777",
    "sg:postcode":"4127",
    "sg:province":"QLD",
    "sg:tags":[
        "sail",
        "shade"
    ],
    "wof:name":"Fasta Shade",
    "wof:placetype":"venue"
},
  "geometry": {"coordinates":[153.13560485799999,-27.613615036],"type":"Point"}
}