{
  "type": "Feature",
  "properties": {
    "addr:full":"77a Carrington St Revesby NSW 2212",
    "addr:housenumber":"77a",
    "addr:postcode":"2212",
    "addr:street":"Carrington St",
    "iso:country":"AU",
    "sg:address":"77a Carrington St",
    "sg:city":"Revesby",
    "sg:classifiers":[
        {
            "category":"Utilities",
            "subcategory":"Refuse",
            "type":"Services"
        }
    ],
    "sg:phone":"+61 2 9780 8000",
    "sg:postcode":"2212",
    "sg:province":"NSW",
    "sg:tags":[
        "boiler"
    ],
    "wof:name":"L & A Pressure Welding Pty Ltd",
    "wof:placetype":"venue"
},
  "geometry": {"coordinates":[151.00756799999999,-33.940205],"type":"Point"}
}