{
  "type": "Feature",
  "properties": {
    "iso:country":"AU",
    "sg:address":"4 Bertha St",
    "sg:city":"Mt Gambier",
    "sg:classifiers":[
        {
            "category":"Wholesale",
            "subcategory":"Electrical",
            "type":"Manufacturing & Wholesale Goods"
        }
    ],
    "sg:phone":"+61 8 8723 2333",
    "sg:postcode":"5290",
    "sg:province":"SA",
    "sg:tags":[
        "wholesaler"
    ],
    "wof:name":"Rexel Electrical Supplies",
    "wof:placetype":"venue"
},
  "geometry": {"coordinates":[140.771805,-37.825821],"type":"Point"}
}