{
  "type": "Feature",
  "properties": {
    "addr:full":"Littlecroft & Narre-Warr Rd Narre Warren South VIC 3804",
    "addr:postcode":"3804",
    "addr:street":"Rd",
    "iso:country":"AU",
    "sg:address":"Littlecroft & Narre-Warr Rd",
    "sg:city":"Narre Warren South",
    "sg:classifiers":[
        {
            "category":"Fast Food",
            "type":"Food & Drink"
        }
    ],
    "sg:phone":"+61 3 9704 8891",
    "sg:postcode":"3804",
    "sg:province":"VIC",
    "sg:tags":[
        "away",
        "take"
    ],
    "wof:name":"Flakey Jake's Fish & Chips Casey Central",
    "wof:placetype":"venue"
},
  "geometry": {"coordinates":[145.313430786,-37.9869728088],"type":"Point"}
}