{
  "type": "Feature",
  "properties": {
    "addr:full":"Lot21/ Fawcett Rd Waroona WA 6215",
    "addr:postcode":"6215",
    "addr:street":"Fawcett Rd",
    "iso:country":"AU",
    "sg:address":"Lot21/ Fawcett Rd",
    "sg:city":"Waroona",
    "sg:classifiers":[
        {
            "category":"Manufacturing",
            "subcategory":"Tools & Machinery",
            "type":"Manufacturing & Wholesale Goods"
        }
    ],
    "sg:phone":"+61 8 9733 1280",
    "sg:postcode":"6215",
    "sg:province":"WA",
    "sg:tags":[
        "earth",
        "excavating",
        "moving",
        "equipment"
    ],
    "wof:name":"Carna Earth Moving",
    "wof:placetype":"venue"
},
  "geometry": {"coordinates":[115.901337,-32.840942],"type":"Point"}
}