{
  "type": "Feature",
  "properties": {
    "iso:country":"AU",
    "sg:address":"1083 High St",
    "sg:city":"Armadale",
    "sg:classifiers":[
        {
            "category":"Shopping",
            "subcategory":"Clothing, Apparel, & Fashions",
            "type":"Retail Goods"
        }
    ],
    "sg:phone":"+61 3 9822 3984",
    "sg:postcode":"3143",
    "sg:province":"VIC",
    "sg:tags":[
        "lady",
        "wear"
    ],
    "wof:name":"Perri Cutten",
    "wof:placetype":"venue"
},
  "geometry": {"coordinates":[145.022872925,-37.8556365967],"type":"Point"}
}