{
  "type": "Feature",
  "properties": {
    "addr:full":"U9/ 18 Redland Drv Mitcham VIC 3132",
    "addr:housenumber":"18",
    "addr:postcode":"3132",
    "addr:street":"U9 /;Redland Drv",
    "iso:country":"AU",
    "sg:address":"U9/ 18 Redland Drv",
    "sg:city":"Mitcham",
    "sg:classifiers":[
        {
            "category":"Shopping",
            "subcategory":"Computers & Home Electronics",
            "type":"Retail Goods"
        }
    ],
    "sg:phone":"+61 3 9873 7452",
    "sg:postcode":"3132",
    "sg:province":"VIC",
    "sg:tags":[
        "plate",
        "name"
    ],
    "wof:name":"Creative Engraving Solutions",
    "wof:placetype":"venue"
},
  "geometry": {"coordinates":[145.19065856899999,-37.8301353455],"type":"Point"}
}