{
  "type": "Feature",
  "properties": {
    "iso:country":"AU",
    "sg:address":"1129 Albany Hwy",
    "sg:city":"Bentley",
    "sg:classifiers":[
        {
            "category":"Home & Garden",
            "subcategory":"Household Appliances",
            "type":"Retail Goods"
        }
    ],
    "sg:phone":"+61 8 9451 8855",
    "sg:postcode":"6102",
    "sg:province":"WA",
    "sg:tags":[
        "equipment",
        "gas"
    ],
    "wof:name":"A Hot And Air",
    "wof:placetype":"venue"
},
  "geometry": {"coordinates":[115.91834258999999,-32.0013618469],"type":"Point"}
}