{
  "type": "Feature",
  "properties": {
    "iso:country":"AU",
    "sg:address":"210 Graham Rd",
    "sg:city":"Bridgeman Downs",
    "sg:classifiers":[
        {
            "category":"Health Services",
            "subcategory":"Health Practitioner",
            "type":"Services"
        }
    ],
    "sg:phone":"+61 7 3263 9452",
    "sg:postcode":"4035",
    "sg:province":"QLD",
    "sg:tags":[
        "physiotherapist"
    ],
    "wof:name":"Dixon Kaye",
    "wof:placetype":"venue"
},
  "geometry": {"coordinates":[152.99955700000001,-27.353497],"type":"Point"}
}