{
  "type": "Feature",
  "properties": {
    "iso:country":"AU",
    "sg:address":"Cnr Hill & Maesbury Sts",
    "sg:city":"Kensington",
    "sg:classifiers":[
        {
            "category":"Manufacturing",
            "subcategory":"Textiles",
            "type":"Manufacturing & Wholesale Goods"
        }
    ],
    "sg:phone":"+61 8 8331 0325",
    "sg:postcode":"5068",
    "sg:province":"SA",
    "sg:tags":[
        "wholesaler",
        "knitwear",
        "mfrs"
    ],
    "wof:name":"Spinelli Knitting",
    "wof:placetype":"venue"
},
  "geometry": {"coordinates":[138.64505004899999,-34.9263648987],"type":"Point"}
}