{
  "type": "Feature",
  "properties": {
    "iso:country":"AU",
    "sg:address":"64 High St",
    "sg:city":"Mansfield",
    "sg:classifiers":[
        {
            "category":"Professional",
            "subcategory":"Accounting & Tax Preparation",
            "type":"Services"
        }
    ],
    "sg:phone":"+61 3 5775 2466",
    "sg:postcode":"3722",
    "sg:province":"VIC",
    "sg:tags":[
        "accountant",
        "auditor"
    ],
    "wof:name":"Black R N & Co",
    "wof:placetype":"venue"
},
  "geometry": {"coordinates":[146.089645386,-37.0526351929],"type":"Point"}
}