{
  "type": "Feature",
  "properties": {
    "iso:country":"AU",
    "sg:address":"23 Blue Waters Drv",
    "sg:city":"Ocean Grove",
    "sg:classifiers":[
        {
            "category":"Professional",
            "subcategory":"Printing & Photocopies",
            "type":"Services"
        }
    ],
    "sg:phone":"+61 3 5256 3833",
    "sg:postcode":"3226",
    "sg:province":"VIC",
    "sg:tags":[
        "embroidery"
    ],
    "wof:name":"West Coast Embroidery",
    "wof:placetype":"venue"
},
  "geometry": {"coordinates":[144.512131,-38.256615],"type":"Point"}
}