{
  "type": "Feature",
  "properties": {
    "iso:country":"AU",
    "sg:address":"Ste 205, 2nd Floor, 304",
    "sg:city":"-318 The Kings Way Caringbah",
    "sg:classifiers":[
        {
            "category":"Banks & Credit Unions",
            "subcategory":"Bank",
            "type":"Services"
        }
    ],
    "sg:phone":"+61 2 9525 0400",
    "sg:postcode":"2229",
    "sg:province":"NSW",
    "sg:tags":[
        "broker",
        "mortgage"
    ],
    "wof:name":"Anton Home Loans",
    "wof:placetype":"venue"
},
  "geometry": {"coordinates":[151.12420654300001,-34.0129547119],"type":"Point"}
}