{
  "type": "Feature",
  "properties": {
    "iso:country":"AU",
    "sg:address":"Mail Box 22/53 Darling St",
    "sg:city":"Balmain",
    "sg:classifiers":[
        {
            "category":"Sports & Exercise",
            "subcategory":"Gym",
            "type":"Entertainment"
        }
    ],
    "sg:phone":"+61 421 911 319",
    "sg:postcode":"2041",
    "sg:province":"NSW",
    "sg:tags":[
        "personal",
        "trainer",
        "fitness"
    ],
    "wof:name":"Paul Cremen Registered Professional Fitness Trainer",
    "wof:placetype":"venue"
},
  "geometry": {"coordinates":[151.192215,-33.855484],"type":"Point"}
}