{
  "type": "Feature",
  "properties": {
    "iso:country":"AU",
    "sg:address":"1513 Pittwater Rd",
    "sg:city":"North Narrabeen",
    "sg:classifiers":[
        {
            "category":"Health Services",
            "subcategory":"Chiropractor",
            "type":"Services"
        }
    ],
    "sg:phone":"+61 2 9913 9009",
    "sg:postcode":"2101",
    "sg:province":"NSW",
    "wof:name":"Bird Michael",
    "wof:placetype":"venue"
},
  "geometry": {"coordinates":[151.29722599999999,-33.704426],"type":"Point"}
}