{
  "type": "Feature",
  "properties": {
    "iso:country":"AU",
    "sg:address":"15 Treeview Pl",
    "sg:city":"North Rocks",
    "sg:classifiers":[
        {
            "category":"Building & Trades",
            "subcategory":"Construction",
            "type":"Services"
        }
    ],
    "sg:phone":"+61 2 9871 0301",
    "sg:postcode":"2151",
    "sg:province":"NSW",
    "sg:tags":[
        "contractor"
    ],
    "wof:name":"May King Builders Pty Ltd",
    "wof:placetype":"venue"
},
  "geometry": {"coordinates":[151.02189636200001,-33.7695503235],"type":"Point"}
}