{
  "type": "Feature",
  "properties": {
    "addr:full":"34a Jellicoe St Manly West QLD 4179",
    "addr:housenumber":"34a",
    "addr:postcode":"4179",
    "addr:street":"Jellicoe St",
    "iso:country":"AU",
    "sg:address":"34a Jellicoe St",
    "sg:city":"Manly West",
    "sg:classifiers":[
        {
            "category":"Education",
            "subcategory":"Music School",
            "type":"Public Place"
        }
    ],
    "sg:phone":"+61 7 3396 0669",
    "sg:postcode":"4179",
    "sg:province":"QLD",
    "sg:tags":[
        "teacher"
    ],
    "wof:name":"Graham Philip",
    "wof:placetype":"venue"
},
  "geometry": {"coordinates":[153.17066955600001,-27.4566917419],"type":"Point"}
}