{
  "type": "Feature",
  "properties": {
    "addr:full":"Glen Osmond Rd Parkside SA 5063",
    "addr:postcode":"5063",
    "addr:street":"Glen Osmond Rd",
    "iso:country":"AU",
    "sg:address":"Glen Osmond Rd",
    "sg:city":"Parkside",
    "sg:classifiers":[
        {
            "category":"Banks & Credit Unions",
            "subcategory":"Investment Brokerage",
            "type":"Services"
        }
    ],
    "sg:phone":"+61 413 186 717",
    "sg:postcode":"5063",
    "sg:province":"SA",
    "sg:tags":[
        "finance",
        "broker"
    ],
    "wof:name":"A.C.L. Financiers",
    "wof:placetype":"venue"
},
  "geometry": {"coordinates":[138.62042236299999,-34.9434318542],"type":"Point"}
}