{
  "type": "Feature",
  "properties": {
    "iso:country":"AU",
    "sg:address":"1281 Dayboro Rd",
    "sg:city":"Rush Creek",
    "sg:classifiers":[
        {
            "category":"Social Services",
            "subcategory":"Adult Care",
            "type":"Services"
        }
    ],
    "sg:phone":"+61 418 750 481",
    "sg:postcode":"4521",
    "sg:province":"QLD",
    "sg:tags":[
        "towing"
    ],
    "wof:name":"Dayboro Towing Services",
    "wof:placetype":"venue"
},
  "geometry": {"coordinates":[152.891235,-27.217628],"type":"Point"}
}