{
  "type": "Feature",
  "properties": {
    "addr:full":"Shop 4 Pelican Waters Shopng Village 44 Pelican Waters Blvd Caloundra QLD 4551",
    "addr:housenumber":"shop 4;44",
    "addr:postcode":"4551",
    "addr:street":"Village;Waters Blvd",
    "iso:country":"AU",
    "sg:address":"Shop 4 Pelican Waters Shopng Village 44 Pelican Waters Blvd",
    "sg:city":"Caloundra",
    "sg:classifiers":[
        {
            "category":"Food & Beverages",
            "subcategory":"Liquor & Beverages",
            "type":"Retail Goods"
        }
    ],
    "sg:phone":"+61 7 5437 3722",
    "sg:postcode":"4551",
    "sg:province":"QLD",
    "sg:tags":[
        "store"
    ],
    "wof:name":"BWS Liquor Stores",
    "wof:placetype":"venue"
},
  "geometry": {"coordinates":[153.11210632300001,-26.8327465057],"type":"Point"}
}