{
  "type": "Feature",
  "properties": {
    "iso:country":"AU",
    "sg:address":"5 Stuart Pl",
    "sg:city":"Sunshine Bay",
    "sg:classifiers":[
        {
            "category":"Building & Trades",
            "subcategory":"Construction",
            "type":"Services"
        }
    ],
    "sg:phone":"+61 2 4472 8463",
    "sg:postcode":"2536",
    "sg:province":"NSW",
    "sg:tags":[
        "contractor"
    ],
    "wof:name":"Masterton Homes Pty Ltd",
    "wof:placetype":"venue"
},
  "geometry": {"coordinates":[150.204345703,-35.7439346313],"type":"Point"}
}