{
  "type": "Feature",
  "properties": {
    "addr:full":"Private Bag 67 Kingston SE SA 5275",
    "addr:postcode":"5275",
    "iso:country":"AU",
    "sg:address":"Private Bag 67",
    "sg:city":"Kingston SE",
    "sg:classifiers":[
        {
            "category":"Farming",
            "subcategory":"Vineyard",
            "type":"Manufacturing & Wholesale Goods"
        }
    ],
    "sg:phone":"+61 8 8768 7264",
    "sg:postcode":"5275",
    "sg:province":"SA",
    "sg:tags":[
        "winery"
    ],
    "wof:name":"Cape Thomas Vineyard Pty Ltd",
    "wof:placetype":"venue"
},
  "geometry": {"coordinates":[139.86163300000001,-36.825432],"type":"Point"}
}