{
  "type": "Feature",
  "properties": {
    "addr:full":"PO Box 265 Humpty Doo NT 0836",
    "addr:postcode":"nt 0836",
    "iso:country":"AU",
    "sg:address":"PO Box 265",
    "sg:city":"Humpty Doo",
    "sg:classifiers":[
        {
            "category":"Food & Beverages",
            "subcategory":"Fruits & Vegetables",
            "type":"Retail Goods"
        }
    ],
    "sg:phone":"+61 8 8988 4940",
    "sg:postcode":"0836",
    "sg:province":"NT",
    "sg:tags":[
        "wholesale"
    ],
    "wof:name":"Connolly's Produce",
    "wof:placetype":"venue"
},
  "geometry": {"coordinates":[131.10987900000001,-12.57374],"type":"Point"}
}