{
  "type": "Feature",
  "properties": {
    "iso:country":"AU",
    "sg:address":"1019 Victoria Rd",
    "sg:city":"West Ryde",
    "sg:classifiers":[
        {
            "category":"Communications",
            "subcategory":"Film & Video Production",
            "type":"Services"
        }
    ],
    "sg:phone":"+61 2 9808 2299",
    "sg:postcode":"2114",
    "sg:province":"NSW",
    "sg:tags":[
        "dvd",
        "library"
    ],
    "wof:name":"Civic Video Pty Ltd",
    "wof:placetype":"venue"
},
  "geometry": {"coordinates":[151.08705139200001,-33.8072891235],"type":"Point"}
}