{
  "type": "Feature",
  "properties": {
    "addr:full":"PO Box 349 Kadina SA 5554",
    "addr:postcode":"5554",
    "iso:country":"AU",
    "sg:address":"PO Box 349",
    "sg:city":"Kadina",
    "sg:classifiers":[
        {
            "category":"Building & Trades",
            "subcategory":"Landscaping Services",
            "type":"Services"
        }
    ],
    "sg:phone":"+61 429 678 055",
    "sg:postcode":"5554",
    "sg:province":"SA",
    "sg:tags":[
        "designer",
        "landscape",
        "contractor"
    ],
    "wof:name":"Copper Coast Landscaping & Irrigation",
    "wof:placetype":"venue"
},
  "geometry": {"coordinates":[137.71598815900001,-33.9657783508],"type":"Point"}
}