{
  "type": "Feature",
  "properties": {
    "addr:full":"484 Mt Alexander Rd Ascot Vale VIC 3032",
    "addr:housenumber":"484",
    "addr:postcode":"3032",
    "addr:street":"Mt Alexander Rd",
    "iso:country":"AU",
    "sg:address":"484 Mt Alexander Rd",
    "sg:city":"Ascot Vale",
    "sg:classifiers":[
        {
            "category":"Retail",
            "subcategory":"Auto Rental",
            "type":"Services"
        }
    ],
    "sg:phone":"+61 3 9326 0631",
    "sg:postcode":"3032",
    "sg:province":"VIC",
    "sg:tags":[
        "bus",
        "truck"
    ],
    "wof:name":"Network Car & Truck Rentals",
    "wof:placetype":"venue"
},
  "geometry": {"coordinates":[144.92875699999999,-37.775715],"type":"Point"}
}