{
  "type": "Feature",
  "properties": {
    "addr:full":"1163 Glenhuntly Rd Glen Huntly VIC 3163",
    "addr:housenumber":"1163",
    "addr:postcode":"3163",
    "addr:street":"Glenhuntly Rd",
    "iso:country":"AU",
    "sg:address":"1163 Glenhuntly Rd",
    "sg:city":"Glen Huntly",
    "sg:classifiers":[
        {
            "category":"Shopping",
            "subcategory":"Discount & Variety Stores",
            "type":"Retail Goods"
        }
    ],
    "sg:phone":"+61 3 9571 1110",
    "sg:postcode":"3163",
    "sg:province":"VIC",
    "sg:tags":[
        "shop",
        "adult"
    ],
    "wof:name":"Club X",
    "wof:placetype":"venue"
},
  "geometry": {"coordinates":[145.04275512699999,-37.8893508911],"type":"Point"}
}