{
  "type": "Feature",
  "properties": {
    "addr:full":"Unit 8 140 Wecker Rd Mansfield QLD 4122",
    "addr:housenumber":"140",
    "addr:postcode":"4122",
    "addr:street":"Wecker Rd",
    "iso:country":"AU",
    "sg:address":"Unit 8 140 Wecker Rd",
    "sg:city":"Mansfield",
    "sg:classifiers":[
        {
            "category":"Building & Trades",
            "subcategory":"Plumbing",
            "type":"Services"
        }
    ],
    "sg:phone":"+61 7 3006 1555",
    "sg:postcode":"4122",
    "sg:province":"QLD",
    "sg:tags":[
        "repair",
        "appliance",
        "system",
        "heating"
    ],
    "wof:name":"Carrier Air Conditioning Pty Ltd",
    "wof:placetype":"venue"
},
  "geometry": {"coordinates":[153.100799561,-27.5333843231],"type":"Point"}
}