{
  "type": "Feature",
  "properties": {
    "addr:full":"81 Basalt St Geebung QLD 4034",
    "addr:housenumber":"81",
    "addr:postcode":"4034",
    "addr:street":"Basalt St",
    "iso:country":"AU",
    "sg:address":"81 Basalt St",
    "sg:city":"Geebung",
    "sg:classifiers":[
        {
            "category":"Autos & Motor Vehicles",
            "subcategory":"Auto Supplies",
            "type":"Retail Goods"
        }
    ],
    "sg:phone":"+61 7 3865 2014",
    "sg:postcode":"4034",
    "sg:province":"QLD",
    "sg:tags":[
        "accessory"
    ],
    "wof:name":"Custom Carbon Pty Ltd",
    "wof:placetype":"venue"
},
  "geometry": {"coordinates":[153.05221599999999,-27.365395],"type":"Point"}
}