{
  "type": "Feature",
  "properties": {
    "iso:country":"AU",
    "sg:address":"Fcty8/ 387-393 Old Geelong Rd",
    "sg:city":"Hoppers Crossing",
    "sg:classifiers":[
        {
            "category":"Autos & Motor Vehicles",
            "subcategory":"Automobile Sales",
            "type":"Retail Goods"
        }
    ],
    "sg:phone":"+61 3 8360 8140",
    "sg:postcode":"3029",
    "sg:province":"VIC",
    "sg:tags":[
        "car",
        "used"
    ],
    "wof:name":"MJ's Crazy Cars",
    "wof:placetype":"venue"
},
  "geometry": {"coordinates":[144.728165,-37.870144],"type":"Point"}
}