{
  "type": "Feature",
  "properties": {
    "addr:full":"Buckleys Rd Winston Hills NSW 2153",
    "addr:postcode":"2153",
    "addr:street":"Buckleys Rd",
    "iso:country":"AU",
    "sg:address":"Buckleys Rd",
    "sg:city":"Winston Hills",
    "sg:classifiers":[
        {
            "category":"Education",
            "subcategory":"School",
            "type":"Public Place"
        }
    ],
    "sg:phone":"+61 2 9624 7485",
    "sg:postcode":"2153",
    "sg:province":"NSW",
    "sg:tags":[
        "state",
        "-",
        "nsw"
    ],
    "wof:name":"Winston Heights Public School",
    "wof:placetype":"venue"
},
  "geometry": {"coordinates":[150.97300720199999,-33.7765922546],"type":"Point"}
}