{
  "type": "Feature",
  "properties": {
    "addr:full":"46 Shaftsbury St Coburg VIC 3058",
    "addr:housenumber":"46",
    "addr:postcode":"3058",
    "addr:street":"Shaftsbury St",
    "iso:country":"AU",
    "sg:address":"46 Shaftsbury St",
    "sg:city":"Coburg",
    "sg:classifiers":[
        {
            "category":"Utilities",
            "subcategory":"Electric",
            "type":"Services"
        }
    ],
    "sg:phone":"+61 414 343 967",
    "sg:postcode":"3058",
    "sg:province":"VIC",
    "sg:tags":[
        "electrical",
        "contractor"
    ],
    "wof:name":"Coulsell Craig Electrics",
    "wof:placetype":"venue"
},
  "geometry": {"coordinates":[144.95410156200001,-37.7509231567],"type":"Point"}
}