{
  "type": "Feature",
  "properties": {
    "addr:full":"66 Auburn Pde Hawthorn East VIC 3123",
    "addr:housenumber":"66",
    "addr:postcode":"3123",
    "addr:street":"Auburn Pde",
    "iso:country":"AU",
    "sg:address":"66 Auburn Pde",
    "sg:city":"Hawthorn East",
    "sg:classifiers":[
        {
            "category":"Professional",
            "subcategory":"Business Services",
            "type":"Services"
        }
    ],
    "sg:phone":"+61 3 9882 7001",
    "sg:postcode":"3123",
    "sg:province":"VIC",
    "sg:tags":[
        "drafting"
    ],
    "wof:name":"Balwyn Design & Drafting P/L",
    "wof:placetype":"venue"
},
  "geometry": {"coordinates":[145.053268433,-37.8256988525],"type":"Point"}
}