{
  "type": "Feature",
  "properties": {
    "addr:full":"119 Moorindil St Tewantin QLD 4565",
    "addr:housenumber":"119",
    "addr:postcode":"4565",
    "addr:street":"Moorindil St",
    "iso:country":"AU",
    "sg:address":"119 Moorindil St",
    "sg:city":"Tewantin",
    "sg:classifiers":[
        {
            "category":"Travel",
            "subcategory":"Hostel",
            "type":"Entertainment"
        }
    ],
    "sg:phone":"+61 7 5449 9878",
    "sg:postcode":"4565",
    "sg:province":"QLD",
    "sg:tags":[
        "home"
    ],
    "wof:name":"Sovereign Lodge",
    "wof:placetype":"venue"
},
  "geometry": {"coordinates":[153.03651428200001,-26.38256073],"type":"Point"}
}