{
  "type": "Feature",
  "properties": {
    "iso:country":"AU",
    "sg:address":"Unit 6, 8 George St",
    "sg:city":"Bunbury",
    "sg:classifiers":[
        {
            "category":"Utilities",
            "subcategory":"Water",
            "type":"Services"
        }
    ],
    "sg:phone":"+61 8 9721 7366",
    "sg:postcode":"6230",
    "sg:province":"WA",
    "sg:tags":[
        "hot",
        "system"
    ],
    "wof:name":"Quantum Refrigeration",
    "wof:placetype":"venue"
},
  "geometry": {"coordinates":[115.64167,-33.333527],"type":"Point"}
}