{
  "type": "Feature",
  "properties": {
    "addr:full":"182 Glenroy Rd Glenroy VIC 3046",
    "addr:housenumber":"182",
    "addr:postcode":"3046",
    "addr:street":"Glenroy Rd",
    "iso:country":"AU",
    "sg:address":"182 Glenroy Rd",
    "sg:city":"Glenroy",
    "sg:classifiers":[
        {
            "category":"Health Services",
            "subcategory":"Doctor",
            "type":"Services"
        }
    ],
    "sg:phone":"+61 3 9306 1444",
    "sg:postcode":"3046",
    "sg:province":"VIC",
    "sg:tags":[
        "medical",
        "practitioner"
    ],
    "wof:name":"Hill A",
    "wof:placetype":"venue"
},
  "geometry": {"coordinates":[144.92005920400001,-37.7053985596],"type":"Point"}
}