{
  "type": "Feature",
  "properties": {
    "addr:full":"105 Windsor Rd Kellyville NSW 2155",
    "addr:housenumber":"105",
    "addr:postcode":"2155",
    "addr:street":"Windsor Rd",
    "iso:country":"AU",
    "sg:address":"105 Windsor Rd",
    "sg:city":"Kellyville",
    "sg:classifiers":[
        {
            "category":"Home & Garden",
            "subcategory":"Carpets & Floor Coverings",
            "type":"Retail Goods"
        }
    ],
    "sg:phone":"+61 2 9629 5511",
    "sg:postcode":"2155",
    "sg:province":"NSW",
    "sg:tags":[
        "tile",
        "wall",
        "layer"
    ],
    "wof:name":"Fischer T",
    "wof:placetype":"venue"
},
  "geometry": {"coordinates":[150.94900512699999,-33.7098884583],"type":"Point"}
}