{
  "type": "Feature",
  "properties": {
    "iso:country":"AU",
    "sg:address":"PO Box 137",
    "sg:city":"Magnetic Island",
    "sg:classifiers":[
        {
            "category":"Social Services",
            "subcategory":"Retirement Home",
            "type":"Services"
        }
    ],
    "sg:phone":"+61 419 712 579",
    "sg:postcode":"4819",
    "sg:province":"QLD",
    "sg:tags":[
        "environmental",
        "consultant",
        "pollution"
    ],
    "wof:name":"Reef EcoTours",
    "wof:placetype":"venue"
},
  "geometry": {"coordinates":[146.848495,-19.153242],"type":"Point"}
}