{
  "type": "Feature",
  "properties": {
    "iso:country":"AU",
    "sg:address":"24 Springs Rd",
    "sg:city":"Spring Farm",
    "sg:classifiers":[
        {
            "category":"Retail",
            "subcategory":"Repair Shop",
            "type":"Services"
        }
    ],
    "sg:phone":"+61 2 4658 1301",
    "sg:postcode":"2570",
    "sg:province":"NSW",
    "sg:tags":[
        "upholsterer"
    ],
    "wof:name":"Spring Farm Upholstery",
    "wof:placetype":"venue"
},
  "geometry": {"coordinates":[150.714569092,-34.0686035156],"type":"Point"}
}