{
  "type": "Feature",
  "properties": {
    "iso:country":"AU",
    "sg:address":"34 Zambesi St",
    "sg:city":"Riverhills",
    "sg:classifiers":[
        {
            "category":"Professional",
            "subcategory":"Art Services",
            "type":"Services"
        }
    ],
    "sg:phone":"+61 7 3279 6714",
    "sg:postcode":"4074",
    "sg:province":"QLD",
    "sg:tags":[
        "product",
        "industrial",
        "designer"
    ],
    "wof:name":"Upside Solutions",
    "wof:placetype":"venue"
},
  "geometry": {"coordinates":[152.908737183,-27.5572032928],"type":"Point"}
}