{
  "type": "Feature",
  "properties": {
    "addr:full":"46 Playne St Frankston VIC 3199",
    "addr:housenumber":"46",
    "addr:postcode":"3199",
    "addr:street":"Playne St",
    "iso:country":"AU",
    "sg:address":"46 Playne St",
    "sg:city":"Frankston",
    "sg:classifiers":[
        {
            "category":"Banks & Credit Unions",
            "subcategory":"Financial Services",
            "type":"Services"
        }
    ],
    "sg:phone":"+61 3 9770 1888",
    "sg:postcode":"3199",
    "sg:province":"VIC",
    "sg:tags":[
        "planning"
    ],
    "wof:name":"Frankston Financial Services Pty Ltd",
    "wof:placetype":"venue"
},
  "geometry": {"coordinates":[145.12336730999999,-38.1454963684],"type":"Point"}
}