{
  "type": "Feature",
  "properties": {
    "iso:country":"AU",
    "sg:address":"Kingsgrove Rd",
    "sg:city":"Kingsgrove",
    "sg:classifiers":[
        {
            "category":"Government",
            "subcategory":"Court House",
            "type":"Public Place"
        }
    ],
    "sg:phone":"+61 408 213 942",
    "sg:postcode":"2208",
    "sg:province":"NSW",
    "sg:tags":[
        "personal",
        "marriage",
        "family",
        "counselling"
    ],
    "wof:name":"Butterfly Counselling",
    "wof:placetype":"venue"
},
  "geometry": {"coordinates":[151.100784,-33.939339],"type":"Point"}
}