{
  "type": "Feature",
  "properties": {
    "addr:full":"Lvl 1/ 535 Hunter St Newcastle West NSW 2302",
    "addr:housenumber":"/ 535",
    "addr:postcode":"2302",
    "addr:street":"Hunter St",
    "iso:country":"AU",
    "sg:address":"Lvl 1/ 535 Hunter St",
    "sg:city":"Newcastle West",
    "sg:classifiers":[
        {
            "category":"Professional",
            "subcategory":"Business Services",
            "type":"Services"
        }
    ],
    "sg:phone":"+61 2 4929 4000",
    "sg:postcode":"2302",
    "sg:province":"NSW",
    "sg:tags":[
        "consultant",
        "promoter",
        "entertainment"
    ],
    "wof:name":"Newcastle Live Sites",
    "wof:placetype":"venue"
},
  "geometry": {"coordinates":[151.760513,-32.925835],"type":"Point"}
}