{
  "type": "Feature",
  "properties": {
    "addr:full":"Telephone La Baldivis WA 6171",
    "addr:postcode":"6171",
    "addr:street":"Telephone",
    "iso:country":"AU",
    "sg:address":"Telephone La",
    "sg:city":"Baldivis",
    "sg:classifiers":[
        {
            "category":"Professional",
            "subcategory":"Business Services",
            "type":"Services"
        }
    ],
    "sg:phone":"+61 8 9524 1018",
    "sg:postcode":"6171",
    "sg:province":"WA",
    "sg:tags":[
        "livestock",
        "transport"
    ],
    "wof:name":"Wellard Rural Transport",
    "wof:placetype":"venue"
},
  "geometry": {"coordinates":[115.879013,-32.313828],"type":"Point"}
}