{
  "type": "Feature",
  "properties": {
    "iso:country":"AU",
    "sg:address":"41 Carnarvon St",
    "sg:city":"Broome",
    "sg:classifiers":[
        {
            "category":"Insurance",
            "subcategory":"Insurance Agent",
            "type":"Services"
        }
    ],
    "sg:phone":"+61 8 9192 1081",
    "sg:postcode":"6725",
    "sg:province":"WA",
    "sg:tags":[
        "broker"
    ],
    "wof:name":"Broome Insurance Services",
    "wof:placetype":"venue"
},
  "geometry": {"coordinates":[122.24295044,-17.9560451508],"type":"Point"}
}