{
  "type": "Feature",
  "properties": {
    "iso:country":"AU",
    "sg:address":"102 Watt Rd",
    "sg:city":"Mornington",
    "sg:classifiers":[
        {
            "category":"Building & Trades",
            "subcategory":"Construction",
            "type":"Services"
        }
    ],
    "sg:phone":"+61 3 5975 6670",
    "sg:postcode":"3931",
    "sg:province":"VIC",
    "sg:tags":[
        "contractor"
    ],
    "wof:name":"Merrigal Homes Pty Ltd",
    "wof:placetype":"venue"
},
  "geometry": {"coordinates":[145.06208801299999,-38.2336463928],"type":"Point"}
}