{
  "type": "Feature",
  "properties": {
    "iso:country":"AU",
    "sg:address":"8 Broughton St",
    "sg:city":"Canterbury",
    "sg:classifiers":[
        {
            "category":"Professional",
            "subcategory":"Art Services",
            "type":"Services"
        }
    ],
    "sg:phone":"+61 2 9787 2268",
    "sg:postcode":"2193",
    "sg:province":"NSW",
    "sg:tags":[
        "interior",
        "decorator"
    ],
    "wof:name":"Angus Artistic Design & Construction Pty Ltd",
    "wof:placetype":"venue"
},
  "geometry": {"coordinates":[151.117157,-33.910027],"type":"Point"}
}