{
  "type": "Feature",
  "properties": {
    "addr:full":"64 Clyde St Thornbury VIC 3071",
    "addr:housenumber":"64",
    "addr:postcode":"3071",
    "addr:street":"Clyde St",
    "iso:country":"AU",
    "sg:address":"64 Clyde St",
    "sg:city":"Thornbury",
    "sg:classifiers":[
        {
            "category":"Social Services",
            "subcategory":"Child Care",
            "type":"Services"
        }
    ],
    "sg:phone":"+61 3 9480 6531",
    "sg:postcode":"3071",
    "sg:province":"VIC",
    "sg:tags":[
        "support",
        "health"
    ],
    "wof:name":"Maternal & Child Health Centres",
    "wof:placetype":"venue"
},
  "geometry": {"coordinates":[145.01303100600001,-37.7617683411],"type":"Point"}
}