{
  "type": "Feature",
  "properties": {
    "iso:country":"AU",
    "sg:address":"Shop 21, Pelican Plaza, Golden Grove Rd",
    "sg:city":"Modbury",
    "sg:classifiers":[
        {
            "category":"Wholesale",
            "subcategory":"Medical Equipment & Supplies",
            "type":"Manufacturing & Wholesale Goods"
        }
    ],
    "sg:phone":"+61 8 8395 6955",
    "sg:postcode":"5092",
    "sg:province":"SA",
    "sg:tags":[
        "aids",
        "hearing"
    ],
    "wof:name":"National Hearing Care",
    "wof:placetype":"venue"
},
  "geometry": {"coordinates":[138.693817139,-34.8275375366],"type":"Point"}
}