{
  "type": "Feature",
  "properties": {
    "addr:full":"6 Euroa Ave Banksia Park SA 5091",
    "addr:housenumber":"6",
    "addr:postcode":"5091",
    "addr:street":"Euroa Ave",
    "iso:country":"AU",
    "sg:address":"6 Euroa Ave",
    "sg:city":"Banksia Park",
    "sg:classifiers":[
        {
            "category":"Mining & Drilling",
            "type":"Manufacturing & Wholesale Goods"
        }
    ],
    "sg:phone":"+61 8 8251 2225",
    "sg:postcode":"5091",
    "sg:province":"SA",
    "sg:tags":[
        "geologist"
    ],
    "wof:name":"Johnson Geological Services Pty Ltd",
    "wof:placetype":"venue"
},
  "geometry": {"coordinates":[138.73406982399999,-34.8089561462],"type":"Point"}
}