{
  "type": "Feature",
  "properties": {
    "addr:full":"Sunninghill Rd Cudlee Creek SA 5232",
    "addr:postcode":"5232",
    "addr:street":"Sunninghill Rd",
    "iso:country":"AU",
    "sg:address":"Sunninghill Rd",
    "sg:city":"Cudlee Creek",
    "sg:classifiers":[
        {
            "category":"Education",
            "subcategory":"School",
            "type":"Public Place"
        }
    ],
    "sg:phone":"+61 8 8389 2284",
    "sg:postcode":"5232",
    "sg:province":"SA",
    "sg:tags":[
        "state",
        "except",
        "nsw"
    ],
    "wof:name":"Millbrook Primary",
    "wof:placetype":"venue"
},
  "geometry": {"coordinates":[138.81993102999999,-34.8343963623],"type":"Point"}
}