{
  "type": "Feature",
  "properties": {
    "addr:full":"172 Old Hume Hwy Yerrinbool NSW 2575",
    "addr:housenumber":"172",
    "addr:postcode":"2575",
    "addr:street":"Old Hume Hwy",
    "iso:country":"AU",
    "sg:address":"172 Old Hume Hwy",
    "sg:city":"Yerrinbool",
    "sg:classifiers":[
        {
            "category":"Building & Trades",
            "subcategory":"Construction",
            "type":"Services"
        }
    ],
    "sg:phone":"+61 2 4883 9344",
    "sg:postcode":"2575",
    "sg:province":"NSW",
    "sg:tags":[
        "plasterboard",
        "plasterer",
        "fixer"
    ],
    "wof:name":"Frendo Jim",
    "wof:placetype":"venue"
},
  "geometry": {"coordinates":[150.44294738799999,-34.4492645264],"type":"Point"}
}