{
  "type": "Feature",
  "properties": {
    "addr:full":"Unit 5/ 18 York Rd Ingleburn NSW 2565",
    "addr:postcode":"2565",
    "addr:street":"York Rd",
    "iso:country":"AU",
    "sg:address":"Unit 5/ 18 York Rd",
    "sg:city":"Ingleburn",
    "sg:classifiers":[
        {
            "category":"Professional",
            "type":"Services"
        }
    ],
    "sg:phone":"+61 2 9829 6777",
    "sg:postcode":"2565",
    "sg:province":"NSW",
    "sg:tags":[
        "spray",
        "painting"
    ],
    "wof:name":"PolyTech Speciality Glass & Coatings",
    "wof:placetype":"venue"
},
  "geometry": {"coordinates":[150.86137390100001,-33.9919967651],"type":"Point"}
}