{
  "type": "Feature",
  "properties": {
    "iso:country":"AU",
    "sg:address":"Suite 2, 177 Main North Rd",
    "sg:city":"Clare",
    "sg:classifiers":[
        {
            "category":"Health Services",
            "subcategory":"Dentist",
            "type":"Services"
        }
    ],
    "sg:phone":"+61 8 8842 2999",
    "sg:postcode":"5453",
    "sg:province":"SA",
    "wof:name":"Clare Dental",
    "wof:placetype":"venue"
},
  "geometry": {"coordinates":[138.61144999999999,-33.832825],"type":"Point"}
}