{
  "type": "Feature",
  "properties": {
    "addr:full":"Level 2/ 695 Burke Rd Camberwell VIC 3124",
    "addr:housenumber":"/ 695",
    "addr:postcode":"3124",
    "addr:street":"Burke Rd",
    "iso:country":"AU",
    "sg:address":"Level 2/ 695 Burke Rd",
    "sg:city":"Camberwell",
    "sg:classifiers":[
        {
            "category":"Insurance",
            "subcategory":"Insurance Agent",
            "type":"Services"
        }
    ],
    "sg:phone":"+61 3 9813 1244",
    "sg:postcode":"3124",
    "sg:province":"VIC",
    "sg:tags":[
        "broker"
    ],
    "wof:name":"Honan Insurance Brokers",
    "wof:placetype":"venue"
},
  "geometry": {"coordinates":[145.056350708,-37.8323173523],"type":"Point"}
}