{
  "type": "Feature",
  "properties": {
    "addr:full":"394 Fitzgerald St North Perth WA 6006",
    "addr:housenumber":"394",
    "addr:postcode":"6006",
    "addr:street":"Fitzgerald St",
    "iso:country":"AU",
    "sg:address":"394 Fitzgerald St",
    "sg:city":"North Perth",
    "sg:classifiers":[
        {
            "category":"Fast Food",
            "type":"Food & Drink"
        }
    ],
    "sg:phone":"+61 8 9227 0121",
    "sg:postcode":"6006",
    "sg:province":"WA",
    "sg:tags":[
        "away",
        "take"
    ],
    "wof:name":"Istanbul Kitchen",
    "wof:placetype":"venue"
},
  "geometry": {"coordinates":[115.85925293,-31.9332008362],"type":"Point"}
}