{
  "type": "Feature",
  "properties": {
    "addr:full":"PO Box 651 Strathpine QLD 4500",
    "addr:postcode":"4500",
    "iso:country":"AU",
    "sg:address":"PO Box 651",
    "sg:city":"Strathpine",
    "sg:classifiers":[
        {
            "category":"Real Estate",
            "subcategory":"Architect",
            "type":"Services"
        }
    ],
    "sg:phone":"+61 7 3889 9119",
    "sg:postcode":"4500",
    "sg:province":"QLD",
    "sg:tags":[
        "building",
        "designer"
    ],
    "wof:name":"Building Designers&#039; Association Of Queensland Inc",
    "wof:placetype":"venue"
},
  "geometry": {"coordinates":[152.987823486,-27.3017196655],"type":"Point"}
}