{
  "type": "Feature",
  "properties": {
    "iso:country":"AU",
    "sg:address":"14 Resthaven Rd",
    "sg:city":"Parafield Gardens",
    "sg:classifiers":[
        {
            "category":"Professional",
            "subcategory":"Computer Services",
            "type":"Services"
        }
    ],
    "sg:phone":"+61 8 8250 8165",
    "sg:postcode":"5107",
    "sg:province":"SA",
    "sg:tags":[
        "repairs",
        "upgrade",
        "equipment"
    ],
    "wof:name":"Schneider Computers",
    "wof:placetype":"venue"
},
  "geometry": {"coordinates":[138.622802734,-34.7870826721],"type":"Point"}
}