{
  "type": "Feature",
  "properties": {
    "addr:full":"92 Wilsons Rd Mornington VIC 3931",
    "addr:housenumber":"92",
    "addr:postcode":"3931",
    "addr:street":"Wilsons Rd",
    "iso:country":"AU",
    "sg:address":"92 Wilsons Rd",
    "sg:city":"Mornington",
    "sg:classifiers":[
        {
            "category":"Fast Food",
            "type":"Food & Drink"
        }
    ],
    "sg:phone":"+61 3 5977 2228",
    "sg:postcode":"3931",
    "sg:province":"VIC",
    "sg:tags":[
        "away",
        "take"
    ],
    "wof:name":"Wilsons Rd Pizza & Pasta",
    "wof:placetype":"venue"
},
  "geometry": {"coordinates":[145.03790283199999,-38.2303314209],"type":"Point"}
}