{
  "type": "Feature",
  "properties": {
    "iso:country":"AU",
    "sg:address":"45 Barton Drv",
    "sg:city":"Australind",
    "sg:classifiers":[
        {
            "category":"Utilities",
            "subcategory":"Electric",
            "type":"Services"
        }
    ],
    "sg:phone":"+61 418 932 428",
    "sg:postcode":"6233",
    "sg:province":"WA",
    "sg:tags":[
        "electrical",
        "contractor"
    ],
    "wof:name":"Archer Electrics",
    "wof:placetype":"venue"
},
  "geometry": {"coordinates":[115.741859,-33.260971],"type":"Point"}
}