{
  "type": "Feature",
  "properties": {
    "addr:full":"3 High St Stirling SA 5152",
    "addr:housenumber":"3",
    "addr:postcode":"5152",
    "addr:street":"High St",
    "iso:country":"AU",
    "sg:address":"3 High St",
    "sg:city":"Stirling",
    "sg:classifiers":[
        {
            "category":"Building & Trades",
            "subcategory":"Plumbing",
            "type":"Services"
        }
    ],
    "sg:phone":"+61 8 8370 1333",
    "sg:postcode":"5152",
    "sg:province":"SA",
    "sg:tags":[
        "plumber",
        "gasfitters"
    ],
    "wof:name":"Dung Beetle Plumbing",
    "wof:placetype":"venue"
},
  "geometry": {"coordinates":[138.70445251500001,-35.012336731],"type":"Point"}
}