{
  "type": "Feature",
  "properties": {
    "addr:full":"210 Railway Tce Guildford NSW 2161",
    "addr:housenumber":"210",
    "addr:postcode":"2161",
    "addr:street":"Railway Tce",
    "iso:country":"AU",
    "sg:address":"210 Railway Tce",
    "sg:city":"Guildford",
    "sg:classifiers":[
        {
            "category":"Shopping",
            "subcategory":"Stationery & Office Supplies",
            "type":"Retail Goods"
        }
    ],
    "sg:phone":"+61 2 9637 0888",
    "sg:postcode":"2161",
    "sg:province":"NSW",
    "sg:tags":[
        "packaging",
        "equipment",
        "sealing",
        "filling"
    ],
    "sg:website":"http://www.secura.com.au",
    "wof:name":"Cyklop Secura Pty Ltd",
    "wof:placetype":"venue"
},
  "geometry": {"coordinates":[150.96890258799999,-33.8661193848],"type":"Point"}
}