{
  "type": "Feature",
  "properties": {
    "iso:country":"AU",
    "sg:address":"WL Building, 310-312 Anzac Ave",
    "sg:city":"Toowoomba",
    "sg:classifiers":[
        {
            "category":"Insurance",
            "subcategory":"Hazard Insurance",
            "type":"Services"
        }
    ],
    "sg:phone":"+61 7 4632 5809",
    "sg:postcode":"4350",
    "sg:province":"QLD",
    "sg:tags":[
        "fire",
        "accident",
        "marine"
    ],
    "wof:name":"Wesfarmers Federation Insurance",
    "wof:placetype":"venue"
},
  "geometry": {"coordinates":[151.91864,-27.583683],"type":"Point"}
}