{
  "type": "Feature",
  "properties": {
    "iso:country":"AU",
    "sg:address":"144 Gilba Rd",
    "sg:city":"Girraween",
    "sg:classifiers":[
        {
            "category":"Manufacturing",
            "subcategory":"Chemicals & Compounds",
            "type":"Manufacturing & Wholesale Goods"
        }
    ],
    "sg:phone":"+61 2 9636 0800",
    "sg:postcode":"2145",
    "sg:province":"NSW",
    "sg:tags":[
        "agricultural"
    ],
    "wof:name":"Deltrex Chemicals",
    "wof:placetype":"venue"
},
  "geometry": {"coordinates":[150.94119262699999,-33.7970161438],"type":"Point"}
}