{
  "type": "Feature",
  "properties": {
    "addr:full":"24 Banksia Crt Heathmont VIC 3135",
    "addr:housenumber":"24",
    "addr:postcode":"3135",
    "addr:street":"Banksia Crt",
    "iso:country":"AU",
    "sg:address":"24 Banksia Crt",
    "sg:city":"Heathmont",
    "sg:classifiers":[
        {
            "category":"Building & Trades",
            "subcategory":"Construction",
            "type":"Services"
        }
    ],
    "sg:phone":"+61 3 9720 1390",
    "sg:postcode":"3135",
    "sg:province":"VIC",
    "sg:tags":[
        "contractor"
    ],
    "wof:name":"Sturtz A.K.W Builders",
    "wof:placetype":"venue"
},
  "geometry": {"coordinates":[145.25148010300001,-37.8281478882],"type":"Point"}
}