{
  "type": "Feature",
  "properties": {
    "addr:full":"38 Bridge St Uralla NSW 2358",
    "addr:housenumber":"38",
    "addr:postcode":"2358",
    "addr:street":"Bridge St",
    "iso:country":"AU",
    "sg:address":"38 Bridge St",
    "sg:city":"Uralla",
    "sg:classifiers":[
        {
            "category":"Shopping",
            "subcategory":"Crafts & Fabrics",
            "type":"Retail Goods"
        }
    ],
    "sg:phone":"+61 2 6778 4226",
    "sg:postcode":"2358",
    "sg:province":"NSW",
    "sg:tags":[
        "wool",
        "knitting",
        "accessory"
    ],
    "wof:name":"Uralla Wool Room",
    "wof:placetype":"venue"
},
  "geometry": {"coordinates":[151.498214722,-30.642950058],"type":"Point"}
}