{
  "type": "Feature",
  "properties": {
    "addr:full":"PO Box 43 Virginia NT 0835",
    "addr:postcode":"nt 0835",
    "iso:country":"AU",
    "sg:address":"PO Box 43",
    "sg:city":"Virginia",
    "sg:classifiers":[
        {
            "category":"Building & Trades",
            "subcategory":"Landscaping Services",
            "type":"Services"
        }
    ],
    "sg:phone":"+61 417 801 318",
    "sg:postcode":"0835",
    "sg:province":"NT",
    "sg:tags":[
        "designer",
        "landscape",
        "contractor"
    ],
    "wof:name":"Fence Masters (N.T.) Pty Ltd",
    "wof:placetype":"venue"
},
  "geometry": {"coordinates":[131.02928199999999,-12.52754],"type":"Point"}
}