{
  "type": "Feature",
  "properties": {
    "iso:country":"AU",
    "sg:address":"11 Hamilton St",
    "sg:city":"Subiaco",
    "sg:classifiers":[
        {
            "category":"Health Services",
            "subcategory":"Health Practitioner",
            "type":"Services"
        }
    ],
    "sg:phone":"+61 407 084 880",
    "sg:postcode":"6008",
    "sg:province":"WA",
    "sg:tags":[
        "psychologist"
    ],
    "wof:name":"Connor Carmela Dr",
    "wof:placetype":"venue"
},
  "geometry": {"coordinates":[115.835601807,-31.9456310272],"type":"Point"}
}