{
  "type": "Feature",
  "properties": {
    "iso:country":"AU",
    "sg:address":"4/ 41 Trouton St",
    "sg:city":"Balmain",
    "sg:classifiers":[
        {
            "category":"Banks & Credit Unions",
            "subcategory":"Investment Brokerage",
            "type":"Services"
        }
    ],
    "sg:phone":"+61 2 9555 2314",
    "sg:postcode":"2041",
    "sg:province":"NSW",
    "sg:tags":[
        "broker"
    ],
    "wof:name":"Allied Business Brokers",
    "wof:placetype":"venue"
},
  "geometry": {"coordinates":[151.185699,-33.85569],"type":"Point"}
}