{
  "type": "Feature",
  "properties": {
    "addr:full":"82 Hopkins Hwy Warrnambool VIC 3280",
    "addr:housenumber":"82",
    "addr:postcode":"3280",
    "addr:street":"Hopkins Hwy",
    "iso:country":"AU",
    "sg:address":"82 Hopkins Hwy",
    "sg:city":"Warrnambool",
    "sg:classifiers":[
        {
            "category":"Professional",
            "subcategory":"Business Services",
            "type":"Services"
        }
    ],
    "sg:phone":"+61 3 5561 2976",
    "sg:postcode":"3280",
    "sg:province":"VIC",
    "sg:tags":[
        "drafting"
    ],
    "wof:name":"Kimberley Homes",
    "wof:placetype":"venue"
},
  "geometry": {"coordinates":[142.52339172399999,-38.3978767395],"type":"Point"}
}