{
  "type": "Feature",
  "properties": {
    "addr:full":"30 Mulga Rd Hazelwood North VIC 3840",
    "addr:housenumber":"30",
    "addr:postcode":"3840",
    "addr:street":"Mulga Rd",
    "iso:country":"AU",
    "sg:address":"30 Mulga Rd",
    "sg:city":"Hazelwood North",
    "sg:classifiers":[
        {
            "category":"Building & Trades",
            "subcategory":"Construction",
            "type":"Services"
        }
    ],
    "sg:phone":"+61 3 5166 1600",
    "sg:postcode":"3840",
    "sg:province":"VIC",
    "sg:tags":[
        "contractor"
    ],
    "wof:name":"Grimshaw Building Solutions",
    "wof:placetype":"venue"
},
  "geometry": {"coordinates":[146.45367431599999,-38.2636528015],"type":"Point"}
}