{
  "type": "Feature",
  "properties": {
    "addr:full":"16 Stephen St Albion Park NSW 2527",
    "addr:housenumber":"16",
    "addr:postcode":"2527",
    "addr:street":"Stephen St",
    "iso:country":"AU",
    "sg:address":"16 Stephen St",
    "sg:city":"Albion Park",
    "sg:classifiers":[
        {
            "category":"Building & Trades",
            "subcategory":"Construction",
            "type":"Services"
        }
    ],
    "sg:phone":"+61 417 265 272",
    "sg:postcode":"2527",
    "sg:province":"NSW",
    "sg:tags":[
        "polishing",
        "sanding",
        "floor"
    ],
    "wof:name":"Mannys Floors",
    "wof:placetype":"venue"
},
  "geometry": {"coordinates":[150.78121948200001,-34.5867118835],"type":"Point"}
}