{
  "type": "Feature",
  "properties": {
    "iso:country":"AU",
    "sg:address":"801 Mount Alexander Rd",
    "sg:city":"Moonee Ponds",
    "sg:classifiers":[
        {
            "category":"Personal",
            "subcategory":"Beauty Salon",
            "type":"Services"
        }
    ],
    "sg:phone":"+61 3 9370 0250",
    "sg:postcode":"3039",
    "sg:province":"VIC",
    "sg:tags":[
        "hairdresser"
    ],
    "wof:name":"Circa Hairdressing",
    "wof:placetype":"venue"
},
  "geometry": {"coordinates":[144.92025799999999,-37.759972],"type":"Point"}
}