{
  "type": "Feature",
  "properties": {
    "addr:full":"6 Briar St St Ives NSW 2075",
    "addr:housenumber":"6",
    "addr:postcode":"2075",
    "addr:street":"Briar St",
    "iso:country":"AU",
    "sg:address":"6 Briar St",
    "sg:city":"St Ives",
    "sg:classifiers":[
        {
            "category":"Manufacturing",
            "subcategory":"Glass & Minerals",
            "type":"Manufacturing & Wholesale Goods"
        }
    ],
    "sg:phone":"+61 2 9144 4399",
    "sg:postcode":"2075",
    "sg:province":"NSW",
    "sg:tags":[
        "merchant",
        "granite",
        "marble"
    ],
    "wof:name":"El Cid Pty Ltd",
    "wof:placetype":"venue"
},
  "geometry": {"coordinates":[151.171432495,-33.7271575928],"type":"Point"}
}