{
  "type": "Feature",
  "properties": {
    "addr:full":"Unit 3-4 18 Thomas St Ferntree Gully VIC 3156",
    "addr:housenumber":"18",
    "addr:postcode":"3156",
    "addr:street":"Thomas St",
    "iso:country":"AU",
    "sg:address":"Unit 3-4 18 Thomas St",
    "sg:city":"Ferntree Gully",
    "sg:classifiers":[
        {
            "category":"Social Services",
            "subcategory":"Retirement Home",
            "type":"Services"
        }
    ],
    "sg:phone":"+61 3 9758 7299",
    "sg:postcode":"3156",
    "sg:province":"VIC",
    "sg:tags":[
        "environmental",
        "consultant",
        "pollution"
    ],
    "wof:name":"A.W.N. (Air Water Noise) Consultants",
    "wof:placetype":"venue"
},
  "geometry": {"coordinates":[145.28182983400001,-37.8862915039],"type":"Point"}
}