{
  "type": "Feature",
  "properties": {
    "addr:full":"RMB 200 ab Manilla Rd Tamworth NSW 2340",
    "addr:postcode":"2340",
    "addr:street":"Manilla Rd",
    "iso:country":"AU",
    "sg:address":"RMB 200 ab Manilla Rd",
    "sg:city":"Tamworth",
    "sg:classifiers":[
        {
            "category":"Manufacturing",
            "subcategory":"Tools & Machinery",
            "type":"Manufacturing & Wholesale Goods"
        }
    ],
    "sg:phone":"+61 2 6761 7788",
    "sg:postcode":"2340",
    "sg:province":"NSW",
    "sg:tags":[
        "earth",
        "excavating",
        "moving",
        "equipment"
    ],
    "wof:name":"Smith M S & D",
    "wof:placetype":"venue"
},
  "geometry": {"coordinates":[150.919647217,-31.0795688629],"type":"Point"}
}