{
  "type": "Feature",
  "properties": {
    "iso:country":"AU",
    "sg:address":"2833 Point Nepean Rd",
    "sg:city":"Blairgowrie",
    "sg:classifiers":[
        {
            "category":"Food & Beverages",
            "subcategory":"Supermarket",
            "type":"Retail Goods"
        }
    ],
    "sg:phone":"+61 3 5988 8550",
    "sg:postcode":"3942",
    "sg:province":"VIC",
    "sg:tags":[
        "grocery",
        "store"
    ],
    "wof:name":"Blairgowrie Food & Liquor",
    "wof:placetype":"venue"
},
  "geometry": {"coordinates":[144.779663086,-38.3614234924],"type":"Point"}
}