{
  "type": "Feature",
  "properties": {
    "addr:full":"1st Floor 2 Baroona Rd Milton QLD 4064",
    "addr:housenumber":"2",
    "addr:postcode":"4064",
    "addr:street":"Baroona Rd",
    "iso:country":"AU",
    "sg:address":"1st Floor 2 Baroona Rd",
    "sg:city":"Milton",
    "sg:classifiers":[
        {
            "category":"Shopping",
            "subcategory":"Computers & Home Electronics",
            "type":"Retail Goods"
        }
    ],
    "sg:phone":"+61 7 3368 2866",
    "sg:postcode":"4064",
    "sg:province":"QLD",
    "sg:tags":[
        "hardware",
        "equipment"
    ],
    "wof:name":"Hall Computer Services",
    "wof:placetype":"venue"
},
  "geometry": {"coordinates":[153.003143311,-27.4688930511],"type":"Point"}
}