{
  "type": "Feature",
  "properties": {
    "addr:full":"7 Col Drew Drv Lithgow NSW 2790",
    "addr:housenumber":"7",
    "addr:postcode":"2790",
    "addr:street":"Col Drew Drv",
    "iso:country":"AU",
    "sg:address":"7 Col Drew Drv",
    "sg:city":"Lithgow",
    "sg:classifiers":[
        {
            "category":"Health Services",
            "subcategory":"Doctor",
            "type":"Services"
        }
    ],
    "sg:phone":"+61 2 6352 2533",
    "sg:postcode":"2790",
    "sg:province":"NSW",
    "sg:tags":[
        "medical",
        "practitioner"
    ],
    "wof:name":"Denovan Dr",
    "wof:placetype":"venue"
},
  "geometry": {"coordinates":[150.12763977,-33.4996948242],"type":"Point"}
}