{
  "type": "Feature",
  "properties": {
    "addr:full":"14a Henry-Wilson Drv Rosebud VIC 3939",
    "addr:housenumber":"14a",
    "addr:postcode":"3939",
    "addr:street":"Henry-Wilson Drv",
    "iso:country":"AU",
    "sg:address":"14a Henry-Wilson Drv",
    "sg:city":"Rosebud",
    "sg:classifiers":[
        {
            "category":"Utilities",
            "subcategory":"Refuse",
            "type":"Services"
        }
    ],
    "sg:phone":"+61 3 5982 2880",
    "sg:postcode":"3939",
    "sg:province":"VIC",
    "sg:tags":[
        "remover",
        "rubbish"
    ],
    "wof:name":"Harris B",
    "wof:placetype":"venue"
},
  "geometry": {"coordinates":[144.88536071799999,-38.3828582764],"type":"Point"}
}