{
  "type": "Feature",
  "properties": {
    "addr:full":"8 Victoria Ave Victoria Park Industrial Estate Castle Hill NSW 2154",
    "addr:housenumber":"8",
    "addr:postcode":"2154",
    "addr:street":"Victoria Ave Victoria",
    "iso:country":"AU",
    "sg:address":"8 Victoria Ave",
    "sg:city":"Victoria Park Industrial Estate Castle Hill",
    "sg:classifiers":[
        {
            "category":"Banks & Credit Unions",
            "subcategory":"Bank",
            "type":"Services"
        }
    ],
    "sg:phone":"+61 2 9899 7833",
    "sg:postcode":"2154",
    "sg:province":"NSW",
    "wof:name":"Colonial",
    "wof:placetype":"venue"
},
  "geometry": {"coordinates":[150.97972106899999,-33.7313995361],"type":"Point"}
}