{
  "type": "Feature",
  "properties": {
    "iso:country":"AU",
    "sg:address":"9 Angophora Pl",
    "sg:city":"Alfords Point",
    "sg:classifiers":[
        {
            "category":"Government",
            "subcategory":"Court House",
            "type":"Public Place"
        }
    ],
    "sg:phone":"+61 408 876 282",
    "sg:postcode":"2234",
    "sg:province":"NSW",
    "sg:tags":[
        "personal",
        "marriage",
        "family",
        "counselling"
    ],
    "wof:name":"Silverleaf",
    "wof:placetype":"venue"
},
  "geometry": {"coordinates":[151.023605347,-33.9945030212],"type":"Point"}
}