{
  "type": "Feature",
  "properties": {
    "addr:full":"277 Wyndham St Shepparton VIC 3630",
    "addr:housenumber":"277",
    "addr:postcode":"3630",
    "addr:street":"Wyndham St",
    "iso:country":"AU",
    "sg:address":"277 Wyndham St",
    "sg:city":"Shepparton",
    "sg:classifiers":[
        {
            "category":"Professional",
            "subcategory":"Employment Agencies",
            "type":"Services"
        }
    ],
    "sg:phone":"+61 3 5821 8555",
    "sg:postcode":"3630",
    "sg:province":"VIC",
    "wof:name":"CVGT Employment & Training Specialists",
    "wof:placetype":"venue"
},
  "geometry": {"coordinates":[145.39984130900001,-36.3792686462],"type":"Point"}
}