{
  "type": "Feature",
  "properties": {
    "addr:full":"52 Christine Ave Miami QLD 4220",
    "addr:housenumber":"52",
    "addr:postcode":"4220",
    "addr:street":"Christine Ave",
    "iso:country":"AU",
    "sg:address":"52 Christine Ave",
    "sg:city":"Miami",
    "sg:classifiers":[
        {
            "category":"Building & Trades",
            "subcategory":"Plumbing",
            "type":"Services"
        }
    ],
    "sg:phone":"+61 7 5535 2298",
    "sg:postcode":"4220",
    "sg:province":"QLD",
    "sg:tags":[
        "plumber",
        "gasfitters"
    ],
    "wof:name":"Evans Peter",
    "wof:placetype":"venue"
},
  "geometry": {"coordinates":[153.440582275,-28.078042984],"type":"Point"}
}