{
  "type": "Feature",
  "properties": {
    "addr:full":"7 Leonard Crs Strathpine QLD 4500",
    "addr:housenumber":"7",
    "addr:postcode":"4500",
    "addr:street":"Leonard Crs",
    "iso:country":"AU",
    "sg:address":"7 Leonard Crs",
    "sg:city":"Strathpine",
    "sg:classifiers":[
        {
            "category":"Government",
            "subcategory":"Fire Station",
            "type":"Public Place"
        }
    ],
    "sg:phone":"+61 7 3205 7755",
    "sg:postcode":"4500",
    "sg:province":"QLD",
    "sg:tags":[
        "spring",
        "shock",
        "absorbers",
        "suspension"
    ],
    "wof:name":"Better Suspension & Automotive",
    "wof:placetype":"venue"
},
  "geometry": {"coordinates":[152.987823486,-27.3017196655],"type":"Point"}
}