{
  "type": "Feature",
  "properties": {
    "addr:full":"76 Greenwell Point Rd Greenwell Point NSW 2540",
    "addr:housenumber":"76",
    "addr:postcode":"2540",
    "addr:street":"Greenwell Point Rd",
    "iso:country":"AU",
    "sg:address":"76 Greenwell Point Rd",
    "sg:city":"Greenwell Point",
    "sg:classifiers":[
        {
            "category":"Real Estate",
            "subcategory":"Real Estate Agent",
            "type":"Services"
        }
    ],
    "sg:phone":"+61 2 4447 0470",
    "sg:postcode":"2540",
    "sg:province":"NSW",
    "wof:name":"East West Real Estate",
    "wof:placetype":"venue"
},
  "geometry": {"coordinates":[150.731933594,-34.9080276489],"type":"Point"}
}