{
  "type": "Feature",
  "properties": {
    "addr:full":"1 Hester St Harvey WA 6220",
    "addr:housenumber":"1",
    "addr:postcode":"6220",
    "addr:street":"Hester St",
    "iso:country":"AU",
    "sg:address":"1 Hester St",
    "sg:city":"Harvey",
    "sg:classifiers":[
        {
            "category":"Social Services",
            "subcategory":"Child Care",
            "type":"Services"
        }
    ],
    "sg:phone":"+61 8 9729 3344",
    "sg:postcode":"6220",
    "sg:province":"WA",
    "wof:name":"Little Thinkers Early Learning Center",
    "wof:placetype":"venue"
},
  "geometry": {"coordinates":[115.890327,-33.081978],"type":"Point"}
}