{
  "type": "Feature",
  "properties": {
    "addr:full":"127 Victoria Rd Rozelle NSW 2039",
    "addr:housenumber":"127",
    "addr:postcode":"2039",
    "addr:street":"Victoria Rd",
    "iso:country":"AU",
    "sg:address":"127 Victoria Rd",
    "sg:city":"Rozelle",
    "sg:classifiers":[
        {
            "category":"Retail",
            "subcategory":"Auto Rental",
            "type":"Services"
        }
    ],
    "sg:phone":"+61 2 9555 2797",
    "sg:postcode":"2039",
    "sg:province":"NSW",
    "sg:tags":[
        "car",
        "hire",
        "minibus"
    ],
    "wof:name":"A AAAscot Car Rentals",
    "wof:placetype":"venue"
},
  "geometry": {"coordinates":[151.16784668,-33.8622398376],"type":"Point"}
}