{
  "type": "Feature",
  "properties": {
    "iso:country":"AU",
    "sg:address":"6 Criterion St",
    "sg:city":"Hobart",
    "sg:classifiers":[
        {
            "category":"Manufacturing",
            "subcategory":"Jewelry",
            "type":"Manufacturing & Wholesale Goods"
        }
    ],
    "sg:phone":"+61 3 6234 2180",
    "sg:postcode":"7000",
    "sg:province":"TAS",
    "sg:tags":[
        "designer",
        "jewellery"
    ],
    "wof:name":"Darts Jewellers",
    "wof:placetype":"venue"
},
  "geometry": {"coordinates":[147.326446533,-42.8817520142],"type":"Point"}
}