{
  "type": "Feature",
  "properties": {
    "addr:full":"U1&2/ 4 Railway Wlk Brighton VIC 3186",
    "addr:housenumber":"4",
    "addr:postcode":"3186",
    "addr:street":"Railway Wlk",
    "iso:country":"AU",
    "sg:address":"U1&2/ 4",
    "sg:city":"Railway Wlk Brighton",
    "sg:classifiers":[
        {
            "category":"Professional",
            "subcategory":"Art Services",
            "type":"Services"
        }
    ],
    "sg:phone":"+61 3 9553 8789",
    "sg:postcode":"3186",
    "sg:province":"VIC",
    "sg:tags":[
        "interior",
        "decorator"
    ],
    "wof:name":"A Consulting",
    "wof:placetype":"venue"
},
  "geometry": {"coordinates":[144.99696350100001,-37.9148674011],"type":"Point"}
}