{
  "type": "Feature",
  "properties": {
    "iso:country":"AU",
    "sg:address":"Suite 1 , 25 Arnold St",
    "sg:city":"Box Hill",
    "sg:classifiers":[
        {
            "category":"Health Services",
            "subcategory":"Doctor",
            "type":"Services"
        }
    ],
    "sg:phone":"+61 3 8892 2222",
    "sg:postcode":"3128",
    "sg:province":"VIC",
    "sg:tags":[
        "medical",
        "practitioner"
    ],
    "wof:name":"Proimos G",
    "wof:placetype":"venue"
},
  "geometry": {"coordinates":[145.115997314,-37.8141021729],"type":"Point"}
}