{
  "type": "Feature",
  "properties": {
    "iso:country":"AU",
    "sg:address":"PO Box 111",
    "sg:city":"Brunswick Heads",
    "sg:classifiers":[
        {
            "category":"Banks & Credit Unions",
            "subcategory":"Bank",
            "type":"Services"
        }
    ],
    "sg:phone":"+61 2 6684 6877",
    "sg:postcode":"2483",
    "sg:province":"NSW",
    "sg:tags":[
        "equipment",
        "sale",
        "point"
    ],
    "wof:name":"Aster ADS",
    "wof:placetype":"venue"
},
  "geometry": {"coordinates":[153.54104614299999,-28.5602302551],"type":"Point"}
}