{
  "type": "Feature",
  "properties": {
    "iso:country":"AU",
    "sg:address":"50 Teasdale Crs",
    "sg:city":"Kialla",
    "sg:classifiers":[
        {
            "category":"Professional",
            "subcategory":"Business Services",
            "type":"Services"
        }
    ],
    "sg:phone":"+61 3 5823 1372",
    "sg:postcode":"3631",
    "sg:province":"VIC",
    "sg:tags":[
        "drafting"
    ],
    "wof:name":"Con-struct Drafting",
    "wof:placetype":"venue"
},
  "geometry": {"coordinates":[145.38958740199999,-36.4276008606],"type":"Point"}
}