{
  "type": "Feature",
  "properties": {
    "iso:country":"AU",
    "sg:address":"169 Burnley St",
    "sg:city":"Richmond",
    "sg:classifiers":[
        {
            "category":"Shopping",
            "subcategory":"Clothing, Apparel, & Fashions",
            "type":"Retail Goods"
        }
    ],
    "sg:phone":"+61 3 9429 8266",
    "sg:postcode":"3121",
    "sg:province":"VIC",
    "sg:tags":[
        "menswear"
    ],
    "wof:name":"Associated Retailers Limited",
    "wof:placetype":"venue"
},
  "geometry": {"coordinates":[145.008712769,-37.8180389404],"type":"Point"}
}