{
  "type": "Feature",
  "properties": {
    "addr:full":"123 Whitehorse Rd Balwyn VIC 3103",
    "addr:housenumber":"123",
    "addr:postcode":"3103",
    "addr:street":"Whitehorse Rd",
    "iso:country":"AU",
    "sg:address":"123 Whitehorse Rd",
    "sg:city":"Balwyn",
    "sg:classifiers":[
        {
            "category":"Health Services",
            "subcategory":"Doctor",
            "type":"Services"
        }
    ],
    "sg:phone":"+61 3 9816 9096",
    "sg:postcode":"3103",
    "sg:province":"VIC",
    "sg:tags":[
        "medical",
        "practitioner"
    ],
    "wof:name":"Inner Eastern Melbourne Division Of General Practice",
    "wof:placetype":"venue"
},
  "geometry": {"coordinates":[145.06727600100001,-37.8110084534],"type":"Point"}
}