{
  "type": "Feature",
  "properties": {
    "addr:full":"140 Railways St Gatton QLD 4343",
    "addr:housenumber":"140",
    "addr:postcode":"4343",
    "addr:street":"Railways St",
    "iso:country":"AU",
    "sg:address":"140 Railways St",
    "sg:city":"Gatton",
    "sg:classifiers":[
        {
            "category":"Building & Trades",
            "subcategory":"Landscaping Services",
            "type":"Services"
        }
    ],
    "sg:phone":"+61 403 000 964",
    "sg:postcode":"4343",
    "sg:province":"QLD",
    "sg:tags":[
        "designer",
        "landscape",
        "contractor"
    ],
    "wof:name":"Sharmal Landscaping",
    "wof:placetype":"venue"
},
  "geometry": {"coordinates":[152.27296447800001,-27.5663204193],"type":"Point"}
}