{
  "type": "Feature",
  "properties": {
    "addr:full":"1681 Burwood Hwy Belgrave VIC 3160",
    "addr:housenumber":"1681",
    "addr:postcode":"3160",
    "addr:street":"Burwood Hwy",
    "iso:country":"AU",
    "sg:address":"1681 Burwood Hwy",
    "sg:city":"Belgrave",
    "sg:classifiers":[
        {
            "category":"Arena",
            "subcategory":"Sports Club",
            "type":"Entertainment"
        }
    ],
    "sg:phone":"+61 3 9754 7892",
    "sg:postcode":"3160",
    "sg:province":"VIC",
    "sg:tags":[
        "defence",
        "supply",
        "self",
        "instruction",
        "martial art"
    ],
    "wof:name":"Golden Cobra School Of Martial Arts",
    "wof:placetype":"venue"
},
  "geometry": {"coordinates":[145.35450744600001,-37.9088478088],"type":"Point"}
}