{
  "type": "Feature",
  "properties": {
    "addr:full":"Riverside Shopng Cntr, Shp 18, 233 Geroge Windsor NSW 2756",
    "addr:housenumber":"18 233",
    "addr:postcode":"2756",
    "addr:street":"Geroge Windsor",
    "iso:country":"AU",
    "sg:address":"Riverside Shopng Cntr, Shp 18, 233",
    "sg:city":"Geroge Windsor",
    "sg:classifiers":[
        {
            "category":"Shopping",
            "subcategory":"Computers & Home Electronics",
            "type":"Retail Goods"
        }
    ],
    "sg:phone":"+61 2 4577 5244",
    "sg:postcode":"2756",
    "sg:province":"NSW",
    "sg:tags":[
        "equipment",
        "part",
        "electronic"
    ],
    "wof:name":"Dick Smith Electronics",
    "wof:placetype":"venue"
},
  "geometry": {"coordinates":[150.81382751500001,-33.6134490967],"type":"Point"}
}