{
  "type": "Feature",
  "properties": {
    "iso:country":"AU",
    "sg:address":"U1/ 9 Isaacs St",
    "sg:city":"Busselton",
    "sg:classifiers":[
        {
            "category":"Retail",
            "subcategory":"Auto Repair",
            "type":"Services"
        }
    ],
    "sg:phone":"+61 8 9751 5470",
    "sg:postcode":"6280",
    "sg:province":"WA",
    "sg:tags":[
        "beater",
        "painter",
        "panel"
    ],
    "wof:name":"Busselton Panel & Paint",
    "wof:placetype":"venue"
},
  "geometry": {"coordinates":[115.350769043,-33.6612930298],"type":"Point"}
}