{
  "type": "Feature",
  "properties": {
    "iso:country":"AU",
    "sg:address":"6 Coraki Pl",
    "sg:city":"Westleigh",
    "sg:classifiers":[
        {
            "category":"Professional",
            "subcategory":"Computer Services",
            "type":"Services"
        }
    ],
    "sg:phone":"+61 2 9875 5300",
    "sg:postcode":"2120",
    "sg:province":"NSW",
    "sg:tags":[
        "consultant",
        "system"
    ],
    "wof:name":"Intergrated Management Sciences Pty Ltd",
    "wof:placetype":"venue"
},
  "geometry": {"coordinates":[151.06361389200001,-33.718711853],"type":"Point"}
}