{
  "type": "Feature",
  "properties": {
    "iso:country":"AU",
    "sg:address":"9 Robb St",
    "sg:city":"Russellton Industrial Est Alstonville",
    "sg:phone":"+61 1800 655 938",
    "sg:postcode":"2477",
    "sg:province":"NSW",
    "wof:name":"Duraplas",
    "wof:placetype":"venue"
},
  "geometry": {"coordinates":[153.42291259800001,-28.8372058868],"type":"Point"}
}