{
  "type": "Feature",
  "properties": {
    "addr:full":"Upstair-Entry via Diva Hair 9 Johnston St Collingwood VIC 3066",
    "addr:housenumber":"9",
    "addr:postcode":"3066",
    "addr:street":"Via;Johnston St",
    "iso:country":"AU",
    "sg:address":"Upstair-Entry via Diva Hair 9 Johnston St",
    "sg:city":"Collingwood",
    "sg:classifiers":[
        {
            "category":"Personal",
            "subcategory":"Massage",
            "type":"Services"
        }
    ],
    "sg:phone":"+61 3 9419 7668",
    "sg:postcode":"3066",
    "sg:province":"VIC",
    "sg:tags":[
        "therapy"
    ],
    "wof:name":"Aalive Massage Therapies",
    "wof:placetype":"venue"
},
  "geometry": {"coordinates":[144.98472595199999,-37.7991142273],"type":"Point"}
}