{
  "type": "Feature",
  "properties": {
    "addr:full":"347 Stuart Hwy Winnellie NT 0820",
    "addr:housenumber":"347",
    "addr:postcode":"nt 0820",
    "addr:street":"Stuart Hwy",
    "iso:country":"AU",
    "sg:address":"347 Stuart Hwy",
    "sg:city":"Winnellie",
    "sg:classifiers":[
        {
            "category":"Banks & Credit Unions",
            "subcategory":"Bank",
            "type":"Services"
        }
    ],
    "sg:phone":"+61 13 20 32",
    "sg:postcode":"0820",
    "sg:province":"NT",
    "wof:name":"Westpac",
    "wof:placetype":"venue"
},
  "geometry": {"coordinates":[130.86343383799999,-12.426399231],"type":"Point"}
}