{
  "type": "Feature",
  "properties": {
    "addr:full":"Unit 15/31- 37 Salisbury Rd Hornsby NSW 2077",
    "addr:housenumber":"/;37",
    "addr:postcode":"2077",
    "addr:street":"Salisbury Rd",
    "iso:country":"AU",
    "sg:address":"Unit 15/31- 37 Salisbury Rd",
    "sg:city":"Hornsby",
    "sg:classifiers":[
        {
            "category":"Retail",
            "subcategory":"Auto Repair",
            "type":"Services"
        }
    ],
    "sg:phone":"+61 2 9477 7009",
    "sg:postcode":"2077",
    "sg:province":"NSW",
    "sg:tags":[
        "repairer",
        "motor",
        "engineer"
    ],
    "wof:name":"Rev Doctor The",
    "wof:placetype":"venue"
},
  "geometry": {"coordinates":[151.11077880900001,-33.6945343018],"type":"Point"}
}