{
  "type": "Feature",
  "properties": {
    "addr:full":"241 Wardell Rd Dulwich Hill NSW 2203",
    "addr:housenumber":"241",
    "addr:postcode":"2203",
    "addr:street":"Wardell Rd",
    "iso:country":"AU",
    "sg:address":"241 Wardell Rd",
    "sg:city":"Dulwich Hill",
    "sg:classifiers":[
        {
            "category":"Health Services",
            "subcategory":"Dentist",
            "type":"Services"
        }
    ],
    "sg:phone":"+61 2 9559 4005",
    "sg:postcode":"2203",
    "sg:province":"NSW",
    "sg:tags":[
        "dental",
        "emergency"
    ],
    "wof:name":"Emergency Service Dulwich Hill",
    "wof:placetype":"venue"
},
  "geometry": {"coordinates":[151.141525,-33.9105],"type":"Point"}
}