{
  "type": "Feature",
  "properties": {
    "addr:full":"Ste 2/ 19-21 Robinson St Dandenong VIC 3175",
    "addr:housenumber":"/ 19-21",
    "addr:postcode":"3175",
    "addr:street":"Robinson St",
    "iso:country":"AU",
    "sg:address":"Ste 2/ 19-21 Robinson St",
    "sg:city":"Dandenong",
    "sg:classifiers":[
        {
            "category":"Professional",
            "subcategory":"Employment Agencies",
            "type":"Services"
        }
    ],
    "sg:phone":"+61 3 9701 3722",
    "sg:postcode":"3175",
    "sg:province":"VIC",
    "wof:name":"Impact Personnel",
    "wof:placetype":"venue"
},
  "geometry": {"coordinates":[145.21072387699999,-37.9876594543],"type":"Point"}
}