{
  "type": "Feature",
  "properties": {
    "addr:full":"103 Grand Central Shopng Cntr, Cnr Margaret & Dent Toowoomba QLD 4350",
    "addr:housenumber":"103",
    "addr:postcode":"4350",
    "addr:street":"Grand Central Shopng Cntr Cnr Margaret",
    "iso:country":"AU",
    "sg:address":"103 Grand Central Shopng Cntr, Cnr Margaret & Dent",
    "sg:city":"Toowoomba",
    "sg:classifiers":[
        {
            "category":"Shopping",
            "subcategory":"Mobile Phones",
            "type":"Retail Goods"
        }
    ],
    "sg:phone":"+61 7 4637 8455",
    "sg:postcode":"4350",
    "sg:province":"QLD",
    "sg:tags":[
        "telephone",
        "accessory"
    ],
    "wof:name":"Optus World",
    "wof:placetype":"venue"
},
  "geometry": {"coordinates":[151.875641,-27.55761],"type":"Point"}
}