{
  "type": "Feature",
  "properties": {
    "addr:full":"140 Eastern Service Rd Burpengary QLD 4505",
    "addr:housenumber":"140",
    "addr:postcode":"4505",
    "addr:street":"Eastern Service Rd",
    "iso:country":"AU",
    "sg:address":"140 Eastern Service Rd",
    "sg:city":"Burpengary",
    "sg:classifiers":[
        {
            "category":"Social Services",
            "subcategory":"Retirement Home",
            "type":"Services"
        }
    ],
    "sg:phone":"+61 7 3888 9799",
    "sg:postcode":"4505",
    "sg:province":"QLD",
    "sg:tags":[
        "village"
    ],
    "wof:name":"Nasa Investments Pty Ltd",
    "wof:placetype":"venue"
},
  "geometry": {"coordinates":[152.9921875,-27.1472892761],"type":"Point"}
}