{
  "type": "Feature",
  "properties": {
    "iso:country":"AU",
    "sg:address":"19 Stuart Rd",
    "sg:city":"Lilydale",
    "sg:classifiers":[
        {
            "category":"Utilities",
            "subcategory":"Mobile Phone",
            "type":"Services"
        }
    ],
    "sg:phone":"+61 3 9735 4271",
    "sg:postcode":"3140",
    "sg:province":"VIC",
    "sg:tags":[
        "aviation",
        "consultant"
    ],
    "wof:name":"Airways Engineering Services",
    "wof:placetype":"venue"
},
  "geometry": {"coordinates":[145.335403442,-37.7570800781],"type":"Point"}
}