{
  "type": "Feature",
  "properties": {
    "iso:country":"AU",
    "sg:address":"25 Jijaws St",
    "sg:city":"Sumner Park",
    "sg:classifiers":[
        {
            "category":"Wholesale",
            "subcategory":"Metals & Minerals",
            "type":"Manufacturing & Wholesale Goods"
        }
    ],
    "sg:phone":"+61 419 789 221",
    "sg:postcode":"4074",
    "sg:province":"QLD",
    "sg:tags":[
        "steel",
        "merchant"
    ],
    "wof:name":"All Metal Service Centre",
    "wof:placetype":"venue"
},
  "geometry": {"coordinates":[152.9400177,-27.5640468597],"type":"Point"}
}