{
  "type": "Feature",
  "properties": {
    "iso:country":"AU",
    "sg:address":"Level 1, 574 A North Rd",
    "sg:city":"Ormond",
    "sg:classifiers":[
        {
            "category":"Recreation",
            "type":"Entertainment"
        }
    ],
    "sg:phone":"+61 3 9578 2332",
    "sg:postcode":"3204",
    "sg:province":"VIC",
    "sg:tags":[
        "children's",
        "play",
        "programme"
    ],
    "wof:name":"Wiz Kids Kindergym",
    "wof:placetype":"venue"
},
  "geometry": {"coordinates":[145.04032900000001,-37.903961],"type":"Point"}
}