{
  "type": "Feature",
  "properties": {
    "addr:full":"5 Tennyson St Granville NSW 2142",
    "addr:housenumber":"5",
    "addr:postcode":"2142",
    "addr:street":"Tennyson St",
    "iso:country":"AU",
    "sg:address":"5 Tennyson St",
    "sg:city":"Granville",
    "sg:classifiers":[
        {
            "category":"Building & Trades",
            "subcategory":"Construction",
            "type":"Services"
        }
    ],
    "sg:phone":"+61 2 9637 3243",
    "sg:postcode":"2142",
    "sg:province":"NSW",
    "sg:tags":[
        "welding"
    ],
    "wof:name":"Davcron Engineering Pty Ltd",
    "wof:placetype":"venue"
},
  "geometry": {"coordinates":[151.02693176299999,-33.833026886],"type":"Point"}
}