{
  "type": "Feature",
  "properties": {
    "addr:full":"83 Coluche Rd Armidale NSW 2350",
    "addr:housenumber":"83",
    "addr:postcode":"2350",
    "addr:street":"Coluche Rd",
    "iso:country":"AU",
    "sg:address":"83 Coluche Rd",
    "sg:city":"Armidale",
    "sg:classifiers":[
        {
            "category":"Industrial Area",
            "type":"Public Place"
        }
    ],
    "sg:phone":"+61 2 6772 9559",
    "sg:postcode":"2350",
    "sg:province":"NSW",
    "sg:tags":[
        "rural",
        "shed"
    ],
    "wof:name":"Armidale Titan Sheds & Garages",
    "wof:placetype":"venue"
},
  "geometry": {"coordinates":[151.66644287099999,-30.4700088501],"type":"Point"}
}