{
  "type": "Feature",
  "properties": {
    "addr:full":"51 Balaclava St Woolloongabba QLD 4102",
    "addr:housenumber":"51",
    "addr:postcode":"4102",
    "addr:street":"Balaclava St",
    "iso:country":"AU",
    "sg:address":"51 Balaclava St",
    "sg:city":"Woolloongabba",
    "sg:classifiers":[
        {
            "category":"Retail",
            "subcategory":"Auto Repair",
            "type":"Services"
        }
    ],
    "sg:phone":"+61 7 3391 6722",
    "sg:postcode":"4102",
    "sg:province":"QLD",
    "sg:tags":[
        "electrical"
    ],
    "wof:name":"Brisbane Auto Electrics",
    "wof:placetype":"venue"
},
  "geometry": {"coordinates":[153.03874206500001,-27.4905395508],"type":"Point"}
}