{
  "type": "Feature",
  "properties": {
    "iso:country":"AU",
    "sg:address":"103- 111 Stanley St",
    "sg:city":"West Melbourne",
    "sg:classifiers":[
        {
            "category":"Health Services",
            "subcategory":"Medical Lab",
            "type":"Services"
        }
    ],
    "sg:phone":"+61 3 9326 4744",
    "sg:postcode":"3003",
    "sg:province":"VIC",
    "sg:tags":[
        "laboratory",
        "pathology"
    ],
    "wof:name":"Hitech Pathology",
    "wof:placetype":"venue"
},
  "geometry": {"coordinates":[144.94795227,-37.8090705872],"type":"Point"}
}