{
  "type": "Feature",
  "properties": {
    "addr:full":"5 Monkland St Gympie QLD 4570",
    "addr:housenumber":"5",
    "addr:postcode":"4570",
    "addr:street":"Monkland St",
    "iso:country":"AU",
    "sg:address":"5 Monkland St",
    "sg:city":"Gympie",
    "sg:classifiers":[
        {
            "category":"Autos & Motor Vehicles",
            "subcategory":"Auto Supplies",
            "type":"Retail Goods"
        }
    ],
    "sg:phone":"+61 7 5482 3566",
    "sg:postcode":"4570",
    "sg:province":"QLD",
    "sg:tags":[
        "accessory"
    ],
    "wof:name":"Gympie Auto Parts Distributors",
    "wof:placetype":"venue"
},
  "geometry": {"coordinates":[152.657958984,-26.1928577423],"type":"Point"}
}