{
  "type": "Feature",
  "properties": {
    "addr:full":"94 Grove Rd Glenorchy TAS 7010",
    "addr:housenumber":"94",
    "addr:postcode":"7010",
    "addr:street":"Grove Rd",
    "iso:country":"AU",
    "sg:address":"94 Grove Rd",
    "sg:city":"Glenorchy",
    "sg:classifiers":[
        {
            "category":"Bars & Pubs",
            "subcategory":"Gay Bar",
            "type":"Food & Drink"
        }
    ],
    "sg:phone":"+61 3 6272 0068",
    "sg:postcode":"7010",
    "sg:province":"TAS",
    "sg:tags":[
        "plywood",
        "veneer"
    ],
    "wof:name":"Romcke",
    "wof:placetype":"venue"
},
  "geometry": {"coordinates":[147.271774292,-42.8270874023],"type":"Point"}
}