{
  "type": "Feature",
  "properties": {
    "addr:full":"160 Bath Rd Kirrawee NSW 2232",
    "addr:housenumber":"160",
    "addr:postcode":"2232",
    "addr:street":"Bath Rd",
    "iso:country":"AU",
    "sg:address":"160 Bath Rd",
    "sg:city":"Kirrawee",
    "sg:classifiers":[
        {
            "category":"Government",
            "subcategory":"Court House",
            "type":"Public Place"
        }
    ],
    "sg:phone":"+61 2 9545 3566",
    "sg:postcode":"2232",
    "sg:province":"NSW",
    "sg:tags":[
        "personal",
        "marriage",
        "family",
        "counselling"
    ],
    "wof:name":"Family Life Movement Of Aust (Interrelate)",
    "wof:placetype":"venue"
},
  "geometry": {"coordinates":[151.07603454599999,-34.0338668823],"type":"Point"}
}