{
  "type": "Feature",
  "properties": {
    "addr:full":"12 Shiraz Crt Buderim QLD 4556",
    "addr:housenumber":"12",
    "addr:postcode":"4556",
    "addr:street":"Shiraz Crt",
    "iso:country":"AU",
    "sg:address":"12 Shiraz Crt",
    "sg:city":"Buderim",
    "sg:classifiers":[
        {
            "category":"Building & Trades",
            "subcategory":"Construction",
            "type":"Services"
        }
    ],
    "sg:phone":"+61 7 5476 8712",
    "sg:postcode":"4556",
    "sg:province":"QLD",
    "sg:tags":[
        "contractor"
    ],
    "wof:name":"Scoble Developments Pty Ltd",
    "wof:placetype":"venue"
},
  "geometry": {"coordinates":[153.0753479,-26.6994304657],"type":"Point"}
}