{
  "type": "Feature",
  "properties": {
    "addr:full":"123d Kendal St Cowra NSW 2794",
    "addr:housenumber":"123d",
    "addr:postcode":"2794",
    "addr:street":"Kendal St",
    "iso:country":"AU",
    "sg:address":"123d Kendal St",
    "sg:city":"Cowra",
    "sg:classifiers":[
        {
            "category":"Organizations",
            "subcategory":"Non-profit Organization",
            "type":"Services"
        }
    ],
    "sg:phone":"+61 2 6342 4900",
    "sg:postcode":"2794",
    "sg:province":"NSW",
    "sg:tags":[
        "support",
        "disability",
        "organisation"
    ],
    "wof:name":"Home & Community Care Program",
    "wof:placetype":"venue"
},
  "geometry": {"coordinates":[148.69776916500001,-33.8355636597],"type":"Point"}
}