{
  "type": "Feature",
  "properties": {
    "addr:full":"3/49- 51 Regentville Rd Penrith NSW 2750",
    "addr:housenumber":"/;51",
    "addr:postcode":"2750",
    "addr:street":"49;Regentville Rd",
    "iso:country":"AU",
    "sg:address":"3/49- 51 Regentville Rd",
    "sg:city":"Penrith",
    "sg:classifiers":[
        {
            "category":"Bars & Pubs",
            "subcategory":"Gay Bar",
            "type":"Food & Drink"
        }
    ],
    "sg:phone":"+61 2 4732 3788",
    "sg:postcode":"2750",
    "sg:province":"NSW",
    "sg:tags":[
        "plywood",
        "veneer"
    ],
    "wof:name":"Mister Ply & Wood",
    "wof:placetype":"venue"
},
  "geometry": {"coordinates":[150.68312072800001,-33.7653541565],"type":"Point"}
}