{
  "type": "Feature",
  "properties": {
    "iso:country":"AU",
    "sg:address":"77 Archer St",
    "sg:city":"Woodford",
    "sg:classifiers":[
        {
            "category":"Travel",
            "subcategory":"Hotels & Motels",
            "type":"Entertainment"
        }
    ],
    "sg:phone":"+61 7 5496 1122",
    "sg:postcode":"4514",
    "sg:province":"QLD",
    "wof:name":"Woodford Country Motel",
    "wof:placetype":"venue"
},
  "geometry": {"coordinates":[152.77742,-26.95208],"type":"Point"}
}