{
  "type": "Feature",
  "properties": {
    "addr:full":"20 Langbeckers Rd Bundaberg QLD 4670",
    "addr:housenumber":"20",
    "addr:postcode":"4670",
    "addr:street":"Langbeckers Rd",
    "iso:country":"AU",
    "sg:address":"20 Langbeckers Rd",
    "sg:city":"Bundaberg",
    "sg:classifiers":[
        {
            "category":"Building & Trades",
            "subcategory":"Plumbing",
            "type":"Services"
        }
    ],
    "sg:phone":"+61 428 383 145",
    "sg:postcode":"4670",
    "sg:province":"QLD",
    "sg:tags":[
        "pump",
        "repairer"
    ],
    "wof:name":"PumpMate",
    "wof:placetype":"venue"
},
  "geometry": {"coordinates":[152.371536255,-24.9176464081],"type":"Point"}
}