{
  "type": "Feature",
  "properties": {
    "addr:full":"57 Andrew Smith Drv Parafield Gardens SA 5107",
    "addr:housenumber":"57",
    "addr:postcode":"5107",
    "addr:street":"Andrew Smith Drv",
    "iso:country":"AU",
    "sg:address":"57 Andrew Smith Drv",
    "sg:city":"Parafield Gardens",
    "sg:classifiers":[
        {
            "category":"Fast Food",
            "type":"Food & Drink"
        }
    ],
    "sg:phone":"+61 8 8281 2993",
    "sg:postcode":"5107",
    "sg:province":"SA",
    "sg:tags":[
        "away",
        "take"
    ],
    "wof:name":"Pines Take Away",
    "wof:placetype":"venue"
},
  "geometry": {"coordinates":[138.60565185600001,-34.7723770142],"type":"Point"}
}