{
  "type": "Feature",
  "properties": {
    "addr:full":"13 Grey St St Kilda VIC 3182",
    "addr:housenumber":"13",
    "addr:postcode":"3182",
    "addr:street":"Grey St",
    "iso:country":"AU",
    "sg:address":"13 Grey St St",
    "sg:city":"Kilda",
    "sg:classifiers":[
        {
            "category":"Real Estate",
            "subcategory":"Real Estate Agent",
            "type":"Services"
        }
    ],
    "sg:phone":"+61 3 9534 8014",
    "sg:postcode":"3182",
    "sg:province":"VIC",
    "wof:name":"Whiting & Co Pty Ltd",
    "wof:placetype":"venue"
},
  "geometry": {"coordinates":[144.97782898,-37.8603439331],"type":"Point"}
}