{
  "type": "Feature",
  "properties": {
    "addr:full":"Ste B/ 111 Main St Blacktown NSW 2148",
    "addr:housenumber":"/ 111",
    "addr:postcode":"2148",
    "addr:street":"Main St",
    "iso:country":"AU",
    "sg:address":"Ste B/ 111 Main St",
    "sg:city":"Blacktown",
    "sg:classifiers":[
        {
            "category":"Shopping",
            "subcategory":"Clothing, Apparel, & Fashions",
            "type":"Retail Goods"
        }
    ],
    "sg:phone":"+61 2 9622 1270",
    "sg:postcode":"2148",
    "sg:province":"NSW",
    "sg:tags":[
        "lady",
        "wear"
    ],
    "wof:name":"Amal Trading",
    "wof:placetype":"venue"
},
  "geometry": {"coordinates":[150.910766602,-33.7711029053],"type":"Point"}
}