{
  "type": "Feature",
  "properties": {
    "addr:full":"U6/ 3 Britton St Smithfield NSW 2164",
    "addr:housenumber":"3",
    "addr:postcode":"2164",
    "addr:street":"U6 /;Britton St",
    "iso:country":"AU",
    "sg:address":"U6/ 3 Britton St",
    "sg:city":"Smithfield",
    "sg:classifiers":[
        {
            "category":"Home & Garden",
            "subcategory":"Furniture",
            "type":"Retail Goods"
        }
    ],
    "sg:phone":"+61 2 9729 2160",
    "sg:postcode":"2164",
    "sg:province":"NSW",
    "sg:tags":[
        "business"
    ],
    "wof:name":"Workstations R Us Pty Ltd",
    "wof:placetype":"venue"
},
  "geometry": {"coordinates":[150.94505310100001,-33.8457145691],"type":"Point"}
}