{
  "type": "Feature",
  "properties": {
    "addr:full":"36 Old Perth Rd Bassendean WA 6054",
    "addr:housenumber":"36",
    "addr:postcode":"6054",
    "addr:street":"Old Perth Rd",
    "iso:country":"AU",
    "sg:address":"36 Old Perth Rd",
    "sg:city":"Bassendean",
    "sg:classifiers":[
        {
            "category":"Real Estate",
            "subcategory":"Real Estate Agent",
            "type":"Services"
        }
    ],
    "sg:phone":"+61 8 9279 0000",
    "sg:postcode":"6054",
    "sg:province":"WA",
    "wof:name":"RE/MAX Alliance",
    "wof:placetype":"venue"
},
  "geometry": {"coordinates":[115.94873809800001,-31.9040584564],"type":"Point"}
}