{
  "type": "Feature",
  "properties": {
    "addr:full":"362 Sydney Rd Coburg VIC 3058",
    "addr:housenumber":"362",
    "addr:postcode":"3058",
    "addr:street":"Sydney Rd",
    "iso:country":"AU",
    "sg:address":"362 Sydney Rd",
    "sg:city":"Coburg",
    "sg:classifiers":[
        {
            "category":"Health Services",
            "subcategory":"Doctor",
            "type":"Services"
        }
    ],
    "sg:phone":"+61 3 9386 5666",
    "sg:postcode":"3058",
    "sg:province":"VIC",
    "sg:tags":[
        "medical",
        "practitioner"
    ],
    "wof:name":"Coburg Medical Centre",
    "wof:placetype":"venue"
},
  "geometry": {"coordinates":[144.966064453,-37.7450790405],"type":"Point"}
}