{
  "type": "Feature",
  "properties": {
    "addr:full":"160 Herring Rd North Ryde NSW 2113",
    "addr:housenumber":"160",
    "addr:postcode":"2113",
    "addr:street":"Herring Rd",
    "iso:country":"AU",
    "sg:address":"160 Herring Rd",
    "sg:city":"North Ryde",
    "sg:classifiers":[
        {
            "category":"Shopping",
            "subcategory":"Bicycles & Sporting Goods",
            "type":"Retail Goods"
        }
    ],
    "sg:phone":"+61 13 72 22",
    "sg:postcode":"2113",
    "sg:province":"NSW",
    "sg:tags":[
        "chemical",
        "equipment",
        "pool",
        "swimming"
    ],
    "wof:name":"Strantrol - Siemens",
    "wof:placetype":"venue"
},
  "geometry": {"coordinates":[151.11605835,-33.7795944214],"type":"Point"}
}