{
  "type": "Feature",
  "properties": {
    "iso:country":"AU",
    "sg:address":"189 Daws Rd",
    "sg:city":"Pasadena",
    "sg:classifiers":[
        {
            "category":"Health Services",
            "subcategory":"Doctor",
            "type":"Services"
        }
    ],
    "sg:phone":"+61 8 8277 4458",
    "sg:postcode":"5042",
    "sg:province":"SA",
    "sg:tags":[
        "medical",
        "practitioner"
    ],
    "wof:name":"Dare Gregory L",
    "wof:placetype":"venue"
},
  "geometry": {"coordinates":[138.58225999999999,-34.992672],"type":"Point"}
}