{
  "type": "Feature",
  "properties": {
    "addr:full":"Suite 1 & 2/ 36 Fitzroy St Surry Hills NSW 2010",
    "addr:housenumber":"& 2 / 36",
    "addr:postcode":"2010",
    "addr:street":"Fitzroy St",
    "iso:country":"AU",
    "sg:address":"Suite 1 & 2/ 36 Fitzroy St",
    "sg:city":"Surry Hills",
    "sg:classifiers":[
        {
            "category":"Wholesale",
            "subcategory":"Farm Supplies",
            "type":"Manufacturing & Wholesale Goods"
        }
    ],
    "sg:phone":"+61 2 9428 7555",
    "sg:postcode":"2010",
    "sg:province":"NSW",
    "sg:tags":[
        "material",
        "filtering"
    ],
    "wof:name":"Pall Australia",
    "wof:placetype":"venue"
},
  "geometry": {"coordinates":[151.21466064399999,-33.8847694397],"type":"Point"}
}