{
  "type": "Feature",
  "properties": {
    "addr:full":"215 Dairy Creek Rd Waterford QLD 4133",
    "addr:housenumber":"215",
    "addr:postcode":"4133",
    "addr:street":"Dairy Creek Rd",
    "iso:country":"AU",
    "sg:address":"215 Dairy Creek Rd",
    "sg:city":"Waterford",
    "sg:classifiers":[
        {
            "category":"Recreation",
            "subcategory":"Fishing",
            "type":"Entertainment"
        }
    ],
    "sg:phone":"+61 7 3299 6641",
    "sg:postcode":"4133",
    "sg:province":"QLD",
    "sg:tags":[
        "bait"
    ],
    "wof:name":"Australian Worm Farms Pty Ltd",
    "wof:placetype":"venue"
},
  "geometry": {"coordinates":[153.14137268100001,-27.7179279327],"type":"Point"}
}