{
  "type": "Feature",
  "properties": {
    "iso:country":"AU",
    "sg:address":"Unit 5 63 Norman St",
    "sg:city":"Peakhurst",
    "sg:classifiers":[
        {
            "category":"Retail",
            "subcategory":"Auto Repair",
            "type":"Services"
        }
    ],
    "sg:phone":"+61 2 9533 3323",
    "sg:postcode":"2210",
    "sg:province":"NSW",
    "sg:tags":[
        "beater",
        "painter",
        "panel"
    ],
    "wof:name":"Three Way Auto",
    "wof:placetype":"venue"
},
  "geometry": {"coordinates":[151.06199599999999,-33.965248],"type":"Point"}
}