{
  "type": "Feature",
  "properties": {
    "addr:full":"23 Redfern St Cowra NSW 2794",
    "addr:housenumber":"23",
    "addr:postcode":"2794",
    "addr:street":"Redfern St",
    "iso:country":"AU",
    "sg:address":"23 Redfern St",
    "sg:city":"Cowra",
    "sg:classifiers":[
        {
            "category":"Shopping",
            "subcategory":"Shoes",
            "type":"Retail Goods"
        }
    ],
    "sg:phone":"+61 2 6342 3618",
    "sg:postcode":"2794",
    "sg:province":"NSW",
    "sg:tags":[
        "footwear"
    ],
    "wof:name":"French's Store Cowra",
    "wof:placetype":"venue"
},
  "geometry": {"coordinates":[148.68324279800001,-33.8302726746],"type":"Point"}
}