{
  "type": "Feature",
  "properties": {
    "addr:full":"Shp3/ 3 Friend Way Mt Pritchard NSW 2170",
    "addr:housenumber":"3",
    "addr:postcode":"2170",
    "addr:street":"Friend Way;Pritchard",
    "iso:country":"AU",
    "sg:address":"Shp3/ 3 Friend Way",
    "sg:city":"Mt Pritchard",
    "sg:classifiers":[
        {
            "category":"Transit Center",
            "subcategory":"Passenger",
            "type":"Transportation"
        }
    ],
    "sg:phone":"+61 2 9610 9355",
    "sg:postcode":"2170",
    "sg:province":"NSW",
    "sg:tags":[
        "frozen",
        "food",
        "retail"
    ],
    "wof:name":"Song Long Food",
    "wof:placetype":"venue"
},
  "geometry": {"coordinates":[150.90899658199999,-33.9024467468],"type":"Point"}
}