{
  "type": "Feature",
  "properties": {
    "iso:country":"AU",
    "sg:address":"Unit 4/ 14 Bode Ave",
    "sg:city":"North Wollongong",
    "sg:classifiers":[
        {
            "category":"Building & Trades",
            "subcategory":"Construction",
            "type":"Services"
        }
    ],
    "sg:phone":"+61 2 4225 0199",
    "sg:postcode":"2500",
    "sg:province":"NSW",
    "sg:tags":[
        "contractor"
    ],
    "wof:name":"Doughty G J & R",
    "wof:placetype":"venue"
},
  "geometry": {"coordinates":[150.89692700000001,-34.412781],"type":"Point"}
}