{
  "type": "Feature",
  "properties": {
    "iso:country":"AU",
    "sg:address":"Unit 1, 17 May Holman Drv",
    "sg:city":"Bassendean",
    "sg:classifiers":[
        {
            "category":"Donuts",
            "subcategory":"None",
            "type":"Food & Drink"
        }
    ],
    "sg:phone":"+61 8 9377 0242",
    "sg:postcode":"6054",
    "sg:province":"WA",
    "sg:tags":[
        "die",
        "engraver",
        "sinker"
    ],
    "wof:name":"Advanced Engraving & Lettering",
    "wof:placetype":"venue"
},
  "geometry": {"coordinates":[115.938926697,-31.906370163],"type":"Point"}
}