{
  "type": "Feature",
  "properties": {
    "iso:country":"AU",
    "sg:address":"70- 74 May St",
    "sg:city":"St Peters",
    "sg:classifiers":[
        {
            "category":"Home & Garden",
            "subcategory":"Building Materials",
            "type":"Retail Goods"
        }
    ],
    "sg:phone":"+61 2 9550 4288",
    "sg:postcode":"2044",
    "sg:province":"NSW",
    "sg:tags":[
        "supply"
    ],
    "wof:name":"Wholesale Roofing Supplies",
    "wof:placetype":"venue"
},
  "geometry": {"coordinates":[151.177933,-33.909668],"type":"Point"}
}