{
  "type": "Feature",
  "properties": {
    "iso:country":"AU",
    "sg:address":"19 Taylor St",
    "sg:city":"Hervey Bay",
    "sg:classifiers":[
        {
            "category":"Professional",
            "subcategory":"Computer Services",
            "type":"Services"
        }
    ],
    "sg:phone":"+61 7 4197 1888",
    "sg:postcode":"4655",
    "sg:province":"QLD",
    "sg:tags":[
        "package",
        "software"
    ],
    "sg:website":"http://www.awinya.com.au",
    "wof:name":"Awinya Consulting",
    "wof:placetype":"venue"
},
  "geometry": {"coordinates":[152.843735,-25.282637],"type":"Point"}
}