{
  "type": "Feature",
  "properties": {
    "addr:full":"768 The Entrance Rd Wamberal NSW 2260",
    "addr:housenumber":"768",
    "addr:postcode":"2260",
    "addr:street":"The Entrance Rd",
    "iso:country":"AU",
    "sg:address":"768 The Entrance Rd",
    "sg:city":"Wamberal",
    "sg:classifiers":[
        {
            "category":"Fast Food",
            "type":"Food & Drink"
        }
    ],
    "sg:phone":"+61 2 4384 5212",
    "sg:postcode":"2260",
    "sg:province":"NSW",
    "sg:tags":[
        "away",
        "take"
    ],
    "wof:name":"Wambie Whopper",
    "wof:placetype":"venue"
},
  "geometry": {"coordinates":[151.446045,-33.418468],"type":"Point"}
}