{
  "type": "Feature",
  "properties": {
    "addr:full":"2 a Bruce St Crows Nest NSW 2065",
    "addr:housenumber":"2 a",
    "addr:postcode":"2065",
    "addr:street":"Bruce St",
    "iso:country":"AU",
    "sg:address":"2 a Bruce St",
    "sg:city":"Crows Nest",
    "sg:classifiers":[
        {
            "category":"Professional",
            "subcategory":"Computer Services",
            "type":"Services"
        }
    ],
    "sg:phone":"+61 2 9437 5944",
    "sg:postcode":"2065",
    "sg:province":"NSW",
    "sg:tags":[
        "repairs",
        "upgrade",
        "equipment"
    ],
    "wof:name":"Comrecen",
    "wof:placetype":"venue"
},
  "geometry": {"coordinates":[151.20120239299999,-33.8293876648],"type":"Point"}
}