{
  "type": "Feature",
  "properties": {
    "iso:country":"AU",
    "sg:address":"PO Box 1",
    "sg:city":"Goombungee",
    "sg:classifiers":[
        {
            "category":"Building & Trades",
            "subcategory":"Construction",
            "type":"Services"
        }
    ],
    "sg:phone":"+61 408 719 883",
    "sg:postcode":"4354",
    "sg:province":"QLD",
    "sg:tags":[
        "concrete",
        "contractor"
    ],
    "wof:name":"Goombungee Concreting Services",
    "wof:placetype":"venue"
},
  "geometry": {"coordinates":[151.85313400000001,-27.301399],"type":"Point"}
}