{
  "type": "Feature",
  "properties": {
    "iso:country":"AU",
    "sg:address":"38 Queen St",
    "sg:city":"Revesby",
    "sg:classifiers":[
        {
            "category":"Building & Trades",
            "subcategory":"Construction",
            "type":"Services"
        }
    ],
    "sg:phone":"+61 2 9792 3222",
    "sg:postcode":"2212",
    "sg:province":"NSW",
    "sg:tags":[
        "fencing",
        "contractor"
    ],
    "wof:name":"Tri-Line",
    "wof:placetype":"venue"
},
  "geometry": {"coordinates":[151.009735,-33.944923],"type":"Point"}
}