{
  "type": "Feature",
  "properties": {
    "addr:full":"9 Gulligal St Kingsthorpe QLD 4400",
    "addr:housenumber":"9",
    "addr:postcode":"4400",
    "addr:street":"Gulligal St",
    "iso:country":"AU",
    "sg:address":"9 Gulligal St",
    "sg:city":"Kingsthorpe",
    "sg:classifiers":[
        {
            "category":"Professional",
            "subcategory":"Art Services",
            "type":"Services"
        }
    ],
    "sg:phone":"+61 7 4630 0170",
    "sg:postcode":"4400",
    "sg:province":"QLD",
    "sg:tags":[
        "decorator",
        "painter"
    ],
    "wof:name":"Beutel R C & R K",
    "wof:placetype":"venue"
},
  "geometry": {"coordinates":[151.83306884800001,-27.4742641449],"type":"Point"}
}