{
  "type": "Feature",
  "properties": {
    "iso:country":"AU",
    "sg:address":"Atchison St",
    "sg:city":"Wollongong",
    "sg:classifiers":[
        {
            "category":"Insurance",
            "subcategory":"Insurance Agent",
            "type":"Services"
        }
    ],
    "sg:phone":"+61 2 4226 8700",
    "sg:postcode":"2500",
    "sg:province":"NSW",
    "sg:tags":[
        "broker"
    ],
    "wof:name":"OAMPS Insurance Brokers",
    "wof:placetype":"venue"
},
  "geometry": {"coordinates":[150.89570599999999,-34.423481],"type":"Point"}
}