{
  "type": "Feature",
  "properties": {
    "iso:country":"AU",
    "sg:address":"PO Box 2001 MDC",
    "sg:city":"Sunbury",
    "sg:classifiers":[
        {
            "category":"Health Services",
            "subcategory":"Doctor",
            "type":"Services"
        }
    ],
    "sg:phone":"+61 3 9740 4047",
    "sg:postcode":"3429",
    "sg:province":"VIC",
    "sg:tags":[
        "nurse",
        "nursing"
    ],
    "wof:name":"Lee Consulting Australia Pty Ltd-Focus",
    "wof:placetype":"venue"
},
  "geometry": {"coordinates":[144.7290802,-37.5800704956],"type":"Point"}
}