{
  "type": "Feature",
  "properties": {
    "iso:country":"AU",
    "sg:address":"55 Dooley St",
    "sg:city":"Wy Yung",
    "sg:classifiers":[
        {
            "category":"Retail",
            "subcategory":"Auto Repair",
            "type":"Services"
        }
    ],
    "sg:phone":"+61 411 522 835",
    "sg:postcode":"3875",
    "sg:province":"VIC",
    "sg:tags":[
        "repairer",
        "motor",
        "engineer"
    ],
    "wof:name":"Concept Automotive Services",
    "wof:placetype":"venue"
},
  "geometry": {"coordinates":[147.60885620100001,-37.8030204773],"type":"Point"}
}