{
  "type": "Feature",
  "properties": {
    "addr:full":"77 Millbank Rd Terara NSW 2540",
    "addr:housenumber":"77",
    "addr:postcode":"2540",
    "addr:street":"Millbank Rd",
    "iso:country":"AU",
    "sg:address":"77 Millbank Rd",
    "sg:city":"Terara",
    "sg:classifiers":[
        {
            "category":"Retail",
            "subcategory":"Event Space",
            "type":"Services"
        }
    ],
    "sg:phone":"+61 2 4421 5511",
    "sg:postcode":"2540",
    "sg:province":"NSW",
    "sg:tags":[
        "venue",
        "reception",
        "wedding"
    ],
    "wof:name":"Terrara House Estate Pty Ltd",
    "wof:placetype":"venue"
},
  "geometry": {"coordinates":[150.62974548299999,-34.8735084534],"type":"Point"}
}