{
  "type": "Feature",
  "properties": {
    "addr:full":"76 Alison Rd Carrara QLD 4211",
    "addr:housenumber":"76",
    "addr:postcode":"4211",
    "addr:street":"Alison Rd",
    "iso:country":"AU",
    "sg:address":"76 Alison Rd",
    "sg:city":"Carrara",
    "sg:classifiers":[
        {
            "category":"Social Services",
            "subcategory":"Child Care",
            "type":"Services"
        }
    ],
    "sg:phone":"+61 7 5594 5046",
    "sg:postcode":"4211",
    "sg:province":"QLD",
    "wof:name":"Method Montessori",
    "wof:placetype":"venue"
},
  "geometry": {"coordinates":[153.35772705100001,-28.0206546783],"type":"Point"}
}