{
  "type": "Feature",
  "properties": {
    "addr:full":"31 Boormanii Drv Mornington VIC 3931",
    "addr:housenumber":"31",
    "addr:postcode":"3931",
    "addr:street":"Boormanii Drv",
    "iso:country":"AU",
    "sg:address":"31 Boormanii Drv",
    "sg:city":"Mornington",
    "sg:classifiers":[
        {
            "category":"Retail",
            "subcategory":"Storage",
            "type":"Services"
        }
    ],
    "sg:phone":"+61 3 5975 6070",
    "sg:postcode":"3931",
    "sg:province":"VIC",
    "sg:tags":[
        "removal",
        "furniture"
    ],
    "wof:name":"Southern Peninsula Removals & Storage",
    "wof:placetype":"venue"
},
  "geometry": {"coordinates":[145.05157470699999,-38.244720459],"type":"Point"}
}