{
  "type": "Feature",
  "properties": {
    "addr:full":"Percy St Portland VIC 3305",
    "addr:postcode":"3305",
    "addr:street":"Percy St",
    "iso:country":"AU",
    "sg:address":"Percy St",
    "sg:city":"Portland",
    "sg:classifiers":[
        {
            "category":"Autos & Motor Vehicles",
            "subcategory":"Fuel & Gas Station",
            "type":"Retail Goods"
        }
    ],
    "sg:phone":"+61 3 5523 3300",
    "sg:postcode":"3305",
    "sg:province":"VIC",
    "wof:name":"BP Australia Limited",
    "wof:placetype":"venue"
},
  "geometry": {"coordinates":[141.60345459000001,-38.3519134521],"type":"Point"}
}