{
  "type": "Feature",
  "properties": {
    "addr:full":"Factory 5/ 6 Leo St Fawkner VIC 3060",
    "addr:housenumber":"/ 6",
    "addr:postcode":"3060",
    "addr:street":"Leo St",
    "iso:country":"AU",
    "sg:address":"Factory 5/ 6 Leo St",
    "sg:city":"Fawkner",
    "sg:classifiers":[
        {
            "category":"Shopping",
            "subcategory":"Clothing, Apparel, & Fashions",
            "type":"Retail Goods"
        }
    ],
    "sg:phone":"+61 3 9359 2155",
    "sg:postcode":"3060",
    "sg:province":"VIC",
    "sg:tags":[
        "sportswear"
    ],
    "wof:name":"Giramondo Sportswear Pty Ltd",
    "wof:placetype":"venue"
},
  "geometry": {"coordinates":[144.96324157699999,-37.7081832886],"type":"Point"}
}