{
  "type": "Feature",
  "properties": {
    "iso:country":"AU",
    "sg:address":"123 Franklin St",
    "sg:city":"Traralgon",
    "sg:classifiers":[
        {
            "category":"Shopping",
            "subcategory":"Mobile Phones",
            "type":"Retail Goods"
        }
    ],
    "sg:phone":"+61 3 5176 5666",
    "sg:postcode":"3844",
    "sg:province":"VIC",
    "sg:tags":[
        "telephone",
        "accessory"
    ],
    "wof:name":"Telstra Licensed Country Shop",
    "wof:placetype":"venue"
},
  "geometry": {"coordinates":[146.53788757300001,-38.1957244873],"type":"Point"}
}