{
  "type": "Feature",
  "properties": {
    "addr:full":"PO Box 283 Applecross Private Boxes WA 6953",
    "addr:postcode":"6953",
    "iso:country":"AU",
    "sg:address":"PO Box 283",
    "sg:city":"Applecross Private Boxes",
    "sg:classifiers":[
        {
            "category":"Mining & Drilling",
            "type":"Manufacturing & Wholesale Goods"
        }
    ],
    "sg:phone":"+61 8 9316 4577",
    "sg:postcode":"6953",
    "sg:province":"WA",
    "sg:tags":[
        "geologist"
    ],
    "wof:name":"Peter Russell Living Geology",
    "wof:placetype":"venue"
},
  "geometry": {"coordinates":[115.833221435,-32.0194015503],"type":"Point"}
}