{
  "type": "Feature",
  "properties": {
    "addr:full":"291 Canterbury Rd Bankstown NSW 2200",
    "addr:housenumber":"291",
    "addr:postcode":"2200",
    "addr:street":"Canterbury Rd",
    "iso:country":"AU",
    "sg:address":"291 Canterbury Rd",
    "sg:city":"Bankstown",
    "sg:classifiers":[
        {
            "category":"Wholesale",
            "subcategory":"Machinery & Supplies",
            "type":"Manufacturing & Wholesale Goods"
        }
    ],
    "sg:phone":"+61 2 9774 2888",
    "sg:postcode":"2200",
    "sg:province":"NSW",
    "wof:name":"Capital Machinery Aust Pty Ltd",
    "wof:placetype":"venue"
},
  "geometry": {"coordinates":[151.055542,-33.931713],"type":"Point"}
}