{
  "type": "Feature",
  "properties": {
    "iso:country":"AU",
    "sg:address":"369 Macauley Rd",
    "sg:city":"Kensington",
    "sg:classifiers":[
        {
            "category":"Shopping",
            "subcategory":"Musical Instruments",
            "type":"Retail Goods"
        }
    ],
    "sg:phone":"+61 3 9376 9642",
    "sg:postcode":"3031",
    "sg:province":"VIC",
    "sg:tags":[
        "musician",
        "agent"
    ],
    "wof:name":"Inglis Peter R",
    "wof:placetype":"venue"
},
  "geometry": {"coordinates":[144.934677,-37.795048],"type":"Point"}
}