{
  "type": "Feature",
  "properties": {
    "addr:full":"104 Miles St Mt Isa QLD 4825",
    "addr:housenumber":"104",
    "addr:postcode":"4825",
    "addr:street":"Miles St",
    "iso:country":"AU",
    "sg:address":"104 Miles St",
    "sg:city":"Mt Isa",
    "sg:classifiers":[
        {
            "category":"Building & Trades",
            "subcategory":"Landscaping Services",
            "type":"Services"
        }
    ],
    "sg:phone":"+61 7 4748 4808",
    "sg:postcode":"4825",
    "sg:province":"QLD",
    "sg:tags":[
        "grazier"
    ],
    "wof:name":"Campbell D C & M M",
    "wof:placetype":"venue"
},
  "geometry": {"coordinates":[139.494293,-20.717163],"type":"Point"}
}