{
  "type": "Feature",
  "properties": {
    "addr:full":"1390 Toorak Rd Burwood VIC 3125",
    "addr:housenumber":"1390",
    "addr:postcode":"3125",
    "addr:street":"Toorak Rd",
    "iso:country":"AU",
    "sg:address":"1390 Toorak Rd",
    "sg:city":"Burwood",
    "sg:classifiers":[
        {
            "category":"Shopping",
            "subcategory":"Clothing, Apparel, & Fashions",
            "type":"Retail Goods"
        }
    ],
    "sg:phone":"+61 3 9889 6211",
    "sg:postcode":"3125",
    "sg:province":"VIC",
    "sg:tags":[
        "lady",
        "wear"
    ],
    "wof:name":"Millhouse",
    "wof:placetype":"venue"
},
  "geometry": {"coordinates":[145.09385681099999,-37.8503189087],"type":"Point"}
}