{
  "type": "Feature",
  "properties": {
    "addr:full":"39 Gloucester Rd Epping NSW 2121",
    "addr:housenumber":"39",
    "addr:postcode":"2121",
    "addr:street":"Gloucester Rd",
    "iso:country":"AU",
    "sg:address":"39 Gloucester Rd",
    "sg:city":"Epping",
    "sg:classifiers":[
        {
            "category":"Professional",
            "subcategory":"Computer Services",
            "type":"Services"
        }
    ],
    "sg:phone":"+61 2 9868 7000",
    "sg:postcode":"2121",
    "sg:province":"NSW",
    "sg:tags":[
        "consultant",
        "system"
    ],
    "wof:name":"Proactive Edge Pty Ltd",
    "wof:placetype":"venue"
},
  "geometry": {"coordinates":[151.093383789,-33.7661895752],"type":"Point"}
}