{
  "type": "Feature",
  "properties": {
    "addr:full":"129 Olinda-Monbulk Rd Olinda VIC 3788",
    "addr:housenumber":"129",
    "addr:postcode":"3788",
    "addr:street":"Olinda-Monbulk Rd",
    "iso:country":"AU",
    "sg:address":"129 Olinda-Monbulk Rd",
    "sg:city":"Olinda",
    "sg:classifiers":[
        {
            "category":"Restaurant",
            "type":"Food & Drink"
        }
    ],
    "sg:phone":"+61 3 9751 1043",
    "sg:postcode":"3788",
    "sg:province":"VIC",
    "wof:name":"Coonara Springs Restaurant",
    "wof:placetype":"venue"
},
  "geometry": {"coordinates":[145.378387,-37.869518],"type":"Point"}
}