{
  "type": "Feature",
  "properties": {
    "addr:full":"2A Gregory Pl Parramatta NSW 2150",
    "addr:housenumber":"2a",
    "addr:postcode":"2150",
    "addr:street":"Gregory Pl",
    "iso:country":"AU",
    "sg:address":"2A Gregory Pl",
    "sg:city":"Parramatta",
    "sg:classifiers":[
        {
            "category":"Professional",
            "subcategory":"Detective & Security Services",
            "type":"Services"
        }
    ],
    "sg:phone":"+61 2 9893 8866",
    "sg:postcode":"2150",
    "sg:province":"NSW",
    "sg:tags":[
        "guard",
        "patrol"
    ],
    "wof:name":"Corporate Business Protection Pty Ltd",
    "wof:placetype":"venue"
},
  "geometry": {"coordinates":[151.01576232900001,-33.8200263977],"type":"Point"}
}