{
  "type": "Feature",
  "properties": {
    "addr:full":"1 Duke St Stuart Park NT 0820",
    "addr:housenumber":"1",
    "addr:postcode":"0820",
    "addr:street":"Duke St",
    "iso:country":"AU",
    "sg:address":"1 Duke St",
    "sg:city":"Stuart Park",
    "sg:classifiers":[
        {
            "category":"Autos & Motor Vehicles",
            "subcategory":"Automobile Sales",
            "type":"Retail Goods"
        }
    ],
    "sg:phone":"+61 8 8941 6511",
    "sg:postcode":"0820",
    "sg:province":"NT",
    "sg:tags":[
        "car",
        "used"
    ],
    "wof:name":"Sapphire Motors",
    "wof:placetype":"venue"
},
  "geometry": {"coordinates":[130.84136962900001,-12.4515657425],"type":"Point"}
}