{
  "type": "Feature",
  "properties": {
    "addr:full":"Court St Bundarra NSW 2359",
    "addr:postcode":"2359",
    "addr:street":"Court St",
    "iso:country":"AU",
    "sg:address":"Court St",
    "sg:city":"Bundarra",
    "sg:classifiers":[
        {
            "category":"Farming",
            "subcategory":"Farm & Veterinary Services",
            "type":"Manufacturing & Wholesale Goods"
        }
    ],
    "sg:phone":"+61 2 6723 7219",
    "sg:postcode":"2359",
    "sg:province":"NSW",
    "sg:tags":[
        "shearing",
        "contractor"
    ],
    "wof:name":"Layton R F",
    "wof:placetype":"venue"
},
  "geometry": {"coordinates":[151.072143555,-30.1710548401],"type":"Point"}
}