{
  "type": "Feature",
  "properties": {
    "addr:full":"330 Sailors Bay Rd Northbridge NSW 2063",
    "addr:housenumber":"330",
    "addr:postcode":"2063",
    "addr:street":"Sailors Bay Rd",
    "iso:country":"AU",
    "sg:address":"330 Sailors Bay Rd",
    "sg:city":"Northbridge",
    "sg:classifiers":[
        {
            "category":"Building & Trades",
            "subcategory":"Construction",
            "type":"Services"
        }
    ],
    "sg:phone":"+61 2 9674 2444",
    "sg:postcode":"2063",
    "sg:province":"NSW",
    "sg:tags":[
        "repairing",
        "window"
    ],
    "wof:name":"Able Aluminium - Window and Door Repairs",
    "wof:placetype":"venue"
},
  "geometry": {"coordinates":[151.21807861299999,-33.8120574951],"type":"Point"}
}