{
  "type": "Feature",
  "properties": {
    "addr:full":"33 Evans Ave North Mackay QLD 4740",
    "addr:housenumber":"33",
    "addr:postcode":"4740",
    "addr:street":"Evans Ave",
    "iso:country":"AU",
    "sg:address":"33 Evans Ave",
    "sg:city":"North Mackay",
    "sg:classifiers":[
        {
            "category":"Health Services",
            "subcategory":"Doctor",
            "type":"Services"
        }
    ],
    "sg:phone":"+61 7 4957 5177",
    "sg:postcode":"4740",
    "sg:province":"QLD",
    "sg:tags":[
        "medical",
        "practitioner"
    ],
    "wof:name":"Lawal Rasheed Dr",
    "wof:placetype":"venue"
},
  "geometry": {"coordinates":[149.183243,-21.120333],"type":"Point"}
}