{
  "type": "Feature",
  "properties": {
    "addr:full":"327 MacDonnell Rd Clontarf QLD 4019",
    "addr:housenumber":"327",
    "addr:postcode":"4019",
    "addr:street":"Macdonnell Rd",
    "iso:country":"AU",
    "sg:address":"327 MacDonnell Rd",
    "sg:city":"Clontarf",
    "sg:classifiers":[
        {
            "category":"Building & Trades",
            "subcategory":"Locksmith",
            "type":"Services"
        }
    ],
    "sg:phone":"+61 7 3284 7539",
    "sg:postcode":"4019",
    "sg:province":"QLD",
    "sg:tags":[
        "equipment",
        "operating",
        "door",
        "gate"
    ],
    "wof:name":"A. Abbey Auto's",
    "wof:placetype":"venue"
},
  "geometry": {"coordinates":[153.08201599099999,-27.2338237762],"type":"Point"}
}