{
  "type": "Feature",
  "properties": {
    "iso:country":"AU",
    "sg:address":"85 Monaro St",
    "sg:city":"Queanbeyan",
    "sg:classifiers":[
        {
            "category":"Travel",
            "subcategory":"Hotels & Motels",
            "type":"Entertainment"
        }
    ],
    "sg:phone":"+61 2 6297 1444",
    "sg:postcode":"2620",
    "sg:province":"ACT",
    "sg:tags":[
        "accommodation"
    ],
    "wof:name":"Royal Hotel",
    "wof:placetype":"venue"
},
  "geometry": {"coordinates":[149.16082763700001,-35.4727630615],"type":"Point"}
}