{
  "type": "Feature",
  "properties": {
    "iso:country":"AU",
    "sg:address":"506 Oxley Hwy",
    "sg:city":"Port Macquarie",
    "sg:classifiers":[
        {
            "category":"Social Services",
            "subcategory":"Retirement Home",
            "type":"Services"
        }
    ],
    "sg:phone":"+61 1800 998 805",
    "sg:postcode":"2444",
    "sg:province":"NSW",
    "sg:tags":[
        "village"
    ],
    "wof:name":"Oxley Gardens Retirement",
    "wof:placetype":"venue"
},
  "geometry": {"coordinates":[152.874084,-31.455809],"type":"Point"}
}