{
  "type": "Feature",
  "properties": {
    "addr:full":"PO Box 2195 Mandurah WA 6210",
    "addr:postcode":"6210",
    "iso:country":"AU",
    "sg:address":"PO Box 2195",
    "sg:city":"Mandurah",
    "sg:classifiers":[
        {
            "category":"Building & Trades",
            "subcategory":"Construction",
            "type":"Services"
        }
    ],
    "sg:phone":"+61 408 905 279",
    "sg:postcode":"6210",
    "sg:province":"WA",
    "sg:tags":[
        "earth",
        "excavating",
        "moving",
        "contractor"
    ],
    "wof:name":"Anytime Truck & Bobcat Hire",
    "wof:placetype":"venue"
},
  "geometry": {"coordinates":[115.74401899999999,-32.557606],"type":"Point"}
}