{
  "type": "Feature",
  "properties": {
    "addr:full":"22 Meadows Mews Kings Meadows TAS 7249",
    "addr:housenumber":"22",
    "addr:postcode":"7249",
    "addr:street":"Meadows Mews",
    "iso:country":"AU",
    "sg:address":"22 Meadows Mews",
    "sg:city":"Kings Meadows",
    "sg:classifiers":[
        {
            "category":"Personal",
            "subcategory":"Shoe Repair & Shine",
            "type":"Services"
        }
    ],
    "sg:phone":"+61 3 6343 1830",
    "sg:postcode":"7249",
    "sg:province":"TAS",
    "sg:tags":[
        "footwear"
    ],
    "wof:name":"Quickfix",
    "wof:placetype":"venue"
},
  "geometry": {"coordinates":[147.16050720199999,-41.4677696228],"type":"Point"}
}