{
  "type": "Feature",
  "properties": {
    "iso:country":"AU",
    "sg:address":"3 Faversham St",
    "sg:city":"Marrickville",
    "sg:classifiers":[
        {
            "category":"Utilities",
            "subcategory":"Mobile Phone",
            "type":"Services"
        }
    ],
    "sg:phone":"+61 2 9519 3815",
    "sg:postcode":"2204",
    "sg:province":"NSW",
    "sg:tags":[
        "assembly",
        "part",
        "electronic"
    ],
    "wof:name":"Alpha Assembly Services",
    "wof:placetype":"venue"
},
  "geometry": {"coordinates":[151.164276,-33.90992],"type":"Point"}
}