{
  "type": "Feature",
  "properties": {
    "iso:country":"AU",
    "sg:address":"45 Smart St",
    "sg:city":"Fairfield",
    "sg:classifiers":[
        {
            "category":"Food & Beverages",
            "subcategory":"Groceries & Convenience Stores",
            "type":"Retail Goods"
        }
    ],
    "sg:phone":"+61 2 9725 6665",
    "sg:postcode":"2165",
    "sg:province":"NSW",
    "wof:name":"Abey's Eastern Grocery & Nuts",
    "wof:placetype":"venue"
},
  "geometry": {"coordinates":[150.95318603499999,-33.8656196594],"type":"Point"}
}