{
  "type": "Feature",
  "properties": {
    "addr:full":"76 Collie Rd Gembrook VIC 3783",
    "addr:housenumber":"76",
    "addr:postcode":"3783",
    "addr:street":"Collie Rd",
    "iso:country":"AU",
    "sg:address":"76 Collie Rd",
    "sg:city":"Gembrook",
    "sg:classifiers":[
        {
            "category":"Park",
            "subcategory":"County",
            "type":"Public Place"
        }
    ],
    "sg:phone":"+61 3 5968 1616",
    "sg:postcode":"3783",
    "sg:province":"VIC",
    "sg:tags":[
        "sanctuary",
        "zoos",
        "animal"
    ],
    "sg:website":"http://www.animalsonthemove.com.au",
    "wof:name":"Animals On The Move",
    "wof:placetype":"venue"
},
  "geometry": {"coordinates":[145.555939,-37.943127],"type":"Point"}
}