{
  "type": "Feature",
  "properties": {
    "addr:full":"9 Keppel Drv Hallam VIC 3803",
    "addr:housenumber":"9",
    "addr:postcode":"3803",
    "addr:street":"Keppel Drv",
    "iso:country":"AU",
    "sg:address":"9 Keppel Drv",
    "sg:city":"Hallam",
    "sg:classifiers":[
        {
            "category":"Retail",
            "subcategory":"Auto Repair",
            "type":"Services"
        }
    ],
    "sg:phone":"+61 3 8786 3844",
    "sg:postcode":"3803",
    "sg:province":"VIC",
    "sg:tags":[
        "clutch",
        "brake"
    ],
    "wof:name":"Neville Pearce Brakes",
    "wof:placetype":"venue"
},
  "geometry": {"coordinates":[145.271652222,-38.0156173706],"type":"Point"}
}