{
  "type": "Feature",
  "properties": {
    "addr:full":"680 Diggers Rd Werribee South VIC 3030",
    "addr:postcode":"680;3030",
    "addr:street":"Diggers Rd",
    "iso:country":"AU",
    "sg:address":"680 Diggers Rd",
    "sg:city":"Werribee South",
    "sg:classifiers":[
        {
            "category":"Professional",
            "subcategory":"Art Services",
            "type":"Services"
        }
    ],
    "sg:phone":"+61 407 536 396",
    "sg:postcode":"3030",
    "sg:province":"VIC",
    "sg:tags":[
        "artist"
    ],
    "wof:name":"Clare Bannatyne Design In Glass",
    "wof:placetype":"venue"
},
  "geometry": {"coordinates":[144.68528699999999,-37.970566],"type":"Point"}
}