{
  "type": "Feature",
  "properties": {
    "addr:full":"33 Stratford Pde Stratford QLD 4870",
    "addr:housenumber":"33",
    "addr:postcode":"4870",
    "addr:street":"Stratford Pde",
    "iso:country":"AU",
    "sg:address":"33 Stratford Pde",
    "sg:city":"Stratford",
    "sg:classifiers":[
        {
            "category":"Wholesale",
            "subcategory":"Painting Supplies",
            "type":"Manufacturing & Wholesale Goods"
        }
    ],
    "sg:phone":"+61 7 4058 2608",
    "sg:postcode":"4870",
    "sg:province":"QLD",
    "sg:tags":[
        "product",
        "cleaning"
    ],
    "wof:name":"Dp Cleaning Supplies Pty Ltd",
    "wof:placetype":"venue"
},
  "geometry": {"coordinates":[145.73518371599999,-16.875295639],"type":"Point"}
}