{
  "type": "Feature",
  "properties": {
    "addr:full":"23 Western View Drv Albury NSW 2640",
    "addr:housenumber":"23",
    "addr:postcode":"2640",
    "addr:street":"Western View Drv",
    "iso:country":"AU",
    "sg:address":"23 Western View Drv",
    "sg:city":"Albury",
    "sg:classifiers":[
        {
            "category":"Building & Trades",
            "subcategory":"Pest Control",
            "type":"Services"
        }
    ],
    "sg:phone":"+61 2 6023 2657",
    "sg:postcode":"2640",
    "sg:province":"NSW",
    "wof:name":"Hume Pest Control Pty Ltd",
    "wof:placetype":"venue"
},
  "geometry": {"coordinates":[146.88778686500001,-36.0745124817],"type":"Point"}
}