{
  "type": "Feature",
  "properties": {
    "iso:country":"AU",
    "sg:address":"810 Springvale Rd",
    "sg:city":"Braeside",
    "sg:classifiers":[
        {
            "category":"Home & Garden",
            "subcategory":"Garden Supply",
            "type":"Retail Goods"
        }
    ],
    "sg:phone":"+61 3 9798 4599",
    "sg:postcode":"3195",
    "sg:province":"VIC",
    "sg:tags":[
        "statuary",
        "fountains",
        "sundial"
    ],
    "wof:name":"Lotus Water Gardens",
    "wof:placetype":"venue"
},
  "geometry": {"coordinates":[145.14276123100001,-37.9992637634],"type":"Point"}
}