{
  "type": "Feature",
  "properties": {
    "addr:full":"43 Beach Rd Balcolyn NSW 2264",
    "addr:housenumber":"43",
    "addr:postcode":"2264",
    "addr:street":"Beach Rd",
    "iso:country":"AU",
    "sg:address":"43 Beach Rd",
    "sg:city":"Balcolyn",
    "sg:classifiers":[
        {
            "category":"Building & Trades",
            "subcategory":"Plumbing",
            "type":"Services"
        }
    ],
    "sg:phone":"+61 2 4973 6956",
    "sg:postcode":"2264",
    "sg:province":"NSW",
    "sg:tags":[
        "plumber",
        "gasfitters"
    ],
    "wof:name":"D J McLean Plumbing",
    "wof:placetype":"venue"
},
  "geometry": {"coordinates":[151.55882299999999,-33.099422],"type":"Point"}
}