{
  "type": "Feature",
  "properties": {
    "iso:country":"AU",
    "sg:address":"12 Almay St",
    "sg:city":"Kenmore",
    "sg:classifiers":[
        {
            "category":"Building & Trades",
            "subcategory":"Construction",
            "type":"Services"
        }
    ],
    "sg:phone":"+61 7 3378 1155",
    "sg:postcode":"4069",
    "sg:province":"QLD",
    "sg:tags":[
        "contractor"
    ],
    "wof:name":"Knowlman McDonald McMillan",
    "wof:placetype":"venue"
},
  "geometry": {"coordinates":[152.93893432600001,-27.5103969574],"type":"Point"}
}