{
  "type": "Feature",
  "properties": {
    "iso:country":"AU",
    "sg:address":"14 Gibsonville St",
    "sg:city":"Tallebudgera Valley",
    "sg:classifiers":[
        {
            "category":"Farming",
            "subcategory":"Nursery",
            "type":"Manufacturing & Wholesale Goods"
        }
    ],
    "sg:phone":"+61 7 5533 8005",
    "sg:postcode":"4228",
    "sg:province":"QLD",
    "wof:name":"Wild Valley Propagation",
    "wof:placetype":"venue"
},
  "geometry": {"coordinates":[153.37767028799999,-28.1692218781],"type":"Point"}
}