{
  "type": "Feature",
  "properties": {
    "addr:full":"Homebase Shopng Cntr Rowood Rd Prospect NSW 2148",
    "addr:postcode":"2148",
    "addr:street":"Shopng;Rowood Rd",
    "iso:country":"AU",
    "sg:address":"Homebase Shopng Cntr Rowood Rd",
    "sg:city":"Prospect",
    "sg:classifiers":[
        {
            "category":"Fast Food",
            "type":"Food & Drink"
        }
    ],
    "sg:phone":"+61 2 9896 0553",
    "sg:postcode":"2148",
    "sg:province":"NSW",
    "sg:tags":[
        "away",
        "take"
    ],
    "wof:name":"McDonald's Family Restaurants",
    "wof:placetype":"venue"
},
  "geometry": {"coordinates":[150.91903686500001,-33.8011932373],"type":"Point"}
}