{
  "type": "Feature",
  "properties": {
    "addr:full":"224 Main Rd McLaren Vale SA 5171",
    "addr:housenumber":"224",
    "addr:postcode":"5171",
    "addr:street":"Main Rd",
    "iso:country":"AU",
    "sg:address":"224 Main Rd",
    "sg:city":"McLaren Vale",
    "sg:classifiers":[
        {
            "category":"Social Services",
            "subcategory":"Child Care",
            "type":"Services"
        }
    ],
    "sg:phone":"+61 8 8323 9554",
    "sg:postcode":"5171",
    "sg:province":"SA",
    "wof:name":"Early Learning Centre McLaren Vale",
    "wof:placetype":"venue"
},
  "geometry": {"coordinates":[138.533294678,-35.2120933533],"type":"Point"}
}