{
  "type": "Feature",
  "properties": {
    "addr:full":"Arrival Rd Adelaide Airport Adelaide SA 5000",
    "addr:postcode":"5000",
    "addr:street":"Arrival Rd;Airport",
    "iso:country":"AU",
    "sg:address":"Arrival Rd",
    "sg:city":"Adelaide Airport Adelaide",
    "sg:classifiers":[
        {
            "category":"Professional",
            "type":"Services"
        }
    ],
    "sg:phone":"+61 8 8400 3512",
    "sg:postcode":"5000",
    "sg:province":"SA",
    "sg:tags":[
        "courier"
    ],
    "wof:name":"Australian Air Express Regional",
    "wof:placetype":"venue"
},
  "geometry": {"coordinates":[138.60076904300001,-34.9256401062],"type":"Point"}
}