{
  "type": "Feature",
  "properties": {
    "iso:country":"AU",
    "sg:address":"Unit C31, 63- 85 Turner St",
    "sg:city":"Port Melbourne",
    "sg:classifiers":[
        {
            "category":"Shopping",
            "subcategory":"Party Supplies",
            "type":"Retail Goods"
        }
    ],
    "sg:phone":"+61 1300 139 930",
    "sg:postcode":"3207",
    "sg:province":"VIC",
    "sg:tags":[
        "equipment",
        "laminating"
    ],
    "wof:name":"Celkote Pty Ltd.",
    "wof:placetype":"venue"
},
  "geometry": {"coordinates":[144.923874,-37.823681],"type":"Point"}
}