{
  "type": "Feature",
  "properties": {
    "addr:full":"18 Lightcliff Ave Lindfield NSW 2070",
    "addr:housenumber":"18",
    "addr:postcode":"2070",
    "addr:street":"Lightcliff Ave",
    "iso:country":"AU",
    "sg:address":"18 Lightcliff Ave",
    "sg:city":"Lindfield",
    "sg:classifiers":[
        {
            "category":"Professional",
            "subcategory":"Management & Consulting",
            "type":"Services"
        }
    ],
    "sg:phone":"+61 2 9415 8057",
    "sg:postcode":"2070",
    "sg:province":"NSW",
    "sg:tags":[
        "consultant"
    ],
    "wof:name":"Jon Isaacs Consulting Pty Ltd",
    "wof:placetype":"venue"
},
  "geometry": {"coordinates":[151.173919678,-33.7720184326],"type":"Point"}
}