{
  "type": "Feature",
  "properties": {
    "addr:full":"239- 249 Ferntree Gully Rd Mt Waverley VIC 3149",
    "addr:housenumber":"249",
    "addr:postcode":"3149",
    "addr:street":"Ferntree Gully Rd",
    "iso:country":"AU",
    "sg:address":"239- 249 Ferntree Gully Rd",
    "sg:city":"Mt Waverley",
    "sg:classifiers":[
        {
            "category":"Building & Trades",
            "subcategory":"Construction",
            "type":"Services"
        }
    ],
    "sg:phone":"+61 1300 651 669",
    "sg:postcode":"3149",
    "sg:province":"VIC",
    "sg:tags":[
        "rigging",
        "erection",
        "contractor"
    ],
    "wof:name":"Rigweld Pty Ltd",
    "wof:placetype":"venue"
},
  "geometry": {"coordinates":[145.12559509299999,-37.8991203308],"type":"Point"}
}