{
  "type": "Feature",
  "properties": {
    "iso:country":"AU",
    "sg:address":"579 Pinjarra Rd",
    "sg:city":"Barragup",
    "sg:classifiers":[
        {
            "category":"Shopping",
            "type":"Retail Goods"
        }
    ],
    "sg:phone":"+61 8 9581 3533",
    "sg:postcode":"6210",
    "sg:province":"WA",
    "sg:tags":[
        "produce",
        "grain"
    ],
    "wof:name":"Barragup Stockfeeds",
    "wof:placetype":"venue"
},
  "geometry": {"coordinates":[115.771248,-32.546276],"type":"Point"}
}