{
  "type": "Feature",
  "properties": {
    "addr:full":"Warren Rd Mordialloc VIC 3195",
    "addr:postcode":"3195",
    "addr:street":"Warren Rd",
    "iso:country":"AU",
    "sg:address":"Warren Rd",
    "sg:city":"Mordialloc",
    "sg:classifiers":[
        {
            "category":"Education",
            "subcategory":"School",
            "type":"Public Place"
        }
    ],
    "sg:phone":"+61 3 9580 6311",
    "sg:postcode":"3195",
    "sg:province":"VIC",
    "sg:tags":[
        "state",
        "except",
        "nsw"
    ],
    "wof:name":"Parkdale Secondary College",
    "wof:placetype":"venue"
},
  "geometry": {"coordinates":[145.091308594,-38.000289917],"type":"Point"}
}