{
  "type": "Feature",
  "properties": {
    "iso:country":"AU",
    "sg:address":"95 King St",
    "sg:city":"Buderim",
    "sg:classifiers":[
        {
            "category":"Building & Trades",
            "subcategory":"Construction",
            "type":"Services"
        }
    ],
    "sg:phone":"+61 1300 654 010",
    "sg:postcode":"4556",
    "sg:province":"QLD",
    "sg:tags":[
        "contractor"
    ],
    "sg:website":"http://www.kithomes.com.au",
    "wof:name":"Classic Queenslanders",
    "wof:placetype":"venue"
},
  "geometry": {"coordinates":[153.06520080600001,-26.682472229],"type":"Point"}
}