{
  "type": "Feature",
  "properties": {
    "addr:full":"789 Hunter St Newcastle West NSW 2302",
    "addr:housenumber":"789",
    "addr:postcode":"2302",
    "addr:street":"Hunter St",
    "iso:country":"AU",
    "sg:address":"789 Hunter St",
    "sg:city":"Newcastle West",
    "sg:classifiers":[
        {
            "category":"Travel",
            "subcategory":"Hotels & Motels",
            "type":"Entertainment"
        }
    ],
    "sg:phone":"+61 2 4962 2459",
    "sg:postcode":"2302",
    "sg:province":"NSW",
    "sg:tags":[
        "accommodation"
    ],
    "wof:name":"Cambridge Hotel",
    "wof:placetype":"venue"
},
  "geometry": {"coordinates":[151.75794999999999,-32.924824],"type":"Point"}
}