{
  "type": "Feature",
  "properties": {
    "iso:country":"AU",
    "sg:address":"9 Moir St",
    "sg:city":"Borden",
    "sg:classifiers":[
        {
            "category":"Food & Beverages",
            "subcategory":"Groceries & Convenience Stores",
            "type":"Retail Goods"
        }
    ],
    "sg:phone":"+61 8 9828 1045",
    "sg:postcode":"6338",
    "sg:province":"WA",
    "wof:name":"Borden General Store",
    "wof:placetype":"venue"
},
  "geometry": {"coordinates":[118.263763428,-34.071269989],"type":"Point"}
}