{
  "type": "Feature",
  "properties": {
    "addr:full":"736- 742 Hampton St Brighton VIC 3186",
    "addr:housenumber":"736 742",
    "addr:postcode":"3186",
    "addr:street":"Hampton St",
    "iso:country":"AU",
    "sg:address":"736- 742 Hampton St",
    "sg:city":"Brighton",
    "sg:classifiers":[
        {
            "category":"Professional",
            "subcategory":"Accounting & Tax Preparation",
            "type":"Services"
        }
    ],
    "sg:phone":"+61 3 9592 4333",
    "sg:postcode":"3186",
    "sg:province":"VIC",
    "sg:tags":[
        "distributor",
        "lock",
        "mfrs"
    ],
    "wof:name":"Protector Series",
    "wof:placetype":"venue"
},
  "geometry": {"coordinates":[145.006134033,-37.9193267822],"type":"Point"}
}