{
  "type": "Feature",
  "properties": {
    "iso:country":"AU",
    "sg:address":"90 Talbragar St",
    "sg:city":"Dubbo",
    "sg:classifiers":[
        {
            "category":"Shopping",
            "subcategory":"Pawn Shop",
            "type":"Retail Goods"
        }
    ],
    "sg:phone":"+61 2 6884 2608",
    "sg:postcode":"2830",
    "sg:province":"NSW",
    "sg:tags":[
        "pawnbroker"
    ],
    "wof:name":"Ezy Cash Pawnbrokers",
    "wof:placetype":"venue"
},
  "geometry": {"coordinates":[148.60458374000001,-32.2450370789],"type":"Point"}
}