{
  "type": "Feature",
  "properties": {
    "addr:full":"Lvl 6/ 313 La Trobe St Melbourne VIC 3000",
    "addr:housenumber":"/ 313",
    "addr:postcode":"3000",
    "addr:street":"La Trobe St",
    "iso:country":"AU",
    "sg:address":"Lvl 6/ 313 La Trobe St",
    "sg:city":"Melbourne",
    "sg:classifiers":[
        {
            "category":"Real Estate",
            "subcategory":"Real Estate Operator",
            "type":"Services"
        }
    ],
    "sg:phone":"+61 3 8641 6666",
    "sg:postcode":"3000",
    "sg:province":"VIC",
    "sg:tags":[
        "building",
        "consultant",
        "management"
    ],
    "wof:name":"Facility Management Association of Australia (FMA Australia)",
    "wof:placetype":"venue"
},
  "geometry": {"coordinates":[144.96002197300001,-37.8108406067],"type":"Point"}
}