{
  "type": "Feature",
  "properties": {
    "addr:full":"Shop G33 Stockland Mall McFarlane St Merrylands NSW 2160",
    "addr:housenumber":"g33",
    "addr:postcode":"2160",
    "addr:street":"Mcfarlane St",
    "iso:country":"AU",
    "sg:address":"Shop G33 Stockland Mall McFarlane St",
    "sg:city":"Merrylands",
    "sg:classifiers":[
        {
            "category":"Fast Food",
            "type":"Food & Drink"
        }
    ],
    "sg:phone":"+61 2 9637 3023",
    "sg:postcode":"2160",
    "sg:province":"NSW",
    "sg:tags":[
        "away",
        "take"
    ],
    "wof:name":"McDonald's Family Restaurants",
    "wof:placetype":"venue"
},
  "geometry": {"coordinates":[150.98890685999999,-33.8352241516],"type":"Point"}
}