{
  "type": "Feature",
  "properties": {
    "iso:country":"AU",
    "sg:address":"Shop 54/ Central Market Arc",
    "sg:city":"Adelaide",
    "sg:classifiers":[
        {
            "category":"Shopping",
            "subcategory":"Jewelry",
            "type":"Retail Goods"
        }
    ],
    "sg:phone":"+61 8 8231 1736",
    "sg:postcode":"5000",
    "sg:province":"SA",
    "sg:tags":[
        "fashion",
        "jewellery"
    ],
    "wof:name":"Recollections Jewellery",
    "wof:placetype":"venue"
},
  "geometry": {"coordinates":[138.600875855,-34.9273452759],"type":"Point"}
}