{
  "type": "Feature",
  "properties": {
    "addr:full":"Cobden Rd Timboon VIC 3268",
    "addr:postcode":"3268",
    "addr:street":"Cobden Rd",
    "iso:country":"AU",
    "sg:address":"Cobden Rd",
    "sg:city":"Timboon",
    "sg:classifiers":[
        {
            "category":"Retail",
            "subcategory":"Auto Rental",
            "type":"Services"
        }
    ],
    "sg:phone":"+61 3 5598 3031",
    "sg:postcode":"3268",
    "sg:province":"VIC",
    "sg:tags":[
        "car",
        "hire",
        "minibus"
    ],
    "wof:name":"Popes Consolidated Bus Lines Pty Ltd",
    "wof:placetype":"venue"
},
  "geometry": {"coordinates":[142.968353272,-38.4829101562],"type":"Point"}
}