{
  "type": "Feature",
  "properties": {
    "addr:full":"130 Taren Point Rd Taren Point NSW 2229",
    "addr:housenumber":"130",
    "addr:postcode":"2229",
    "addr:street":"Taren Point Rd",
    "iso:country":"AU",
    "sg:address":"130 Taren Point Rd",
    "sg:city":"Taren Point",
    "sg:classifiers":[
        {
            "category":"Social Services",
            "subcategory":"Adult Care",
            "type":"Services"
        }
    ],
    "sg:phone":"+61 2 9525 2480",
    "sg:postcode":"2229",
    "sg:province":"NSW",
    "sg:tags":[
        "towing"
    ],
    "wof:name":"Crashcare Collision Centre",
    "wof:placetype":"venue"
},
  "geometry": {"coordinates":[151.12187194800001,-34.0201072693],"type":"Point"}
}