{
  "type": "Feature",
  "properties": {
    "addr:full":"3 Carolyn Crt Frankston VIC 3199",
    "addr:housenumber":"3",
    "addr:postcode":"3199",
    "addr:street":"Carolyn Crt",
    "iso:country":"AU",
    "sg:address":"3 Carolyn Crt",
    "sg:city":"Frankston",
    "sg:classifiers":[
        {
            "category":"Donuts",
            "subcategory":"None",
            "type":"Food & Drink"
        }
    ],
    "sg:phone":"+61 3 8790 8188",
    "sg:postcode":"3199",
    "sg:province":"VIC",
    "sg:tags":[
        "die",
        "engraver",
        "sinker"
    ],
    "wof:name":"Bayside Engraving",
    "wof:placetype":"venue"
},
  "geometry": {"coordinates":[145.165481567,-38.1427192688],"type":"Point"}
}