{
  "type": "Feature",
  "properties": {
    "addr:full":"23 Wells Rd Oakleigh VIC 3166",
    "addr:housenumber":"23",
    "addr:postcode":"3166",
    "addr:street":"Wells Rd",
    "iso:country":"AU",
    "sg:address":"23 Wells Rd",
    "sg:city":"Oakleigh",
    "sg:classifiers":[
        {
            "category":"Professional",
            "subcategory":"Engineering",
            "type":"Services"
        }
    ],
    "sg:phone":"+61 3 9568 8615",
    "sg:postcode":"3166",
    "sg:province":"VIC",
    "sg:tags":[
        "consulting",
        "engineer"
    ],
    "wof:name":"M Consult",
    "wof:placetype":"venue"
},
  "geometry": {"coordinates":[145.096893311,-37.9042053223],"type":"Point"}
}