{
  "type": "Feature",
  "properties": {
    "addr:full":"2 Third St Blackheath NSW 2785",
    "addr:housenumber":"2",
    "addr:postcode":"2785",
    "addr:street":"Third St",
    "iso:country":"AU",
    "sg:address":"2 Third St",
    "sg:city":"Blackheath",
    "sg:classifiers":[
        {
            "category":"Social Services",
            "type":"Services"
        }
    ],
    "sg:phone":"+61 2 4787 7577",
    "sg:postcode":"2785",
    "sg:province":"NSW",
    "sg:tags":[
        "disabled",
        "person",
        "equipment"
    ],
    "wof:name":"Wheelchairs To Go",
    "wof:placetype":"venue"
},
  "geometry": {"coordinates":[150.29606628400001,-33.6352615356],"type":"Point"}
}