{
  "type": "Feature",
  "properties": {
    "addr:full":"5 Princess St Bulimba QLD 4171",
    "addr:housenumber":"5",
    "addr:postcode":"4171",
    "addr:street":"Princess St",
    "iso:country":"AU",
    "sg:address":"5 Princess St",
    "sg:city":"Bulimba",
    "sg:classifiers":[
        {
            "category":"Communications",
            "subcategory":"Film & Video Production",
            "type":"Services"
        }
    ],
    "sg:phone":"+61 7 3399 1227",
    "sg:postcode":"4171",
    "sg:province":"QLD",
    "sg:tags":[
        "dvd",
        "library"
    ],
    "wof:name":"Blockbuster",
    "wof:placetype":"venue"
},
  "geometry": {"coordinates":[153.05824279800001,-27.4508457184],"type":"Point"}
}