{
  "type": "Feature",
  "properties": {
    "iso:country":"AU",
    "sg:address":"88 South Head Rd",
    "sg:city":"Moruya",
    "sg:classifiers":[
        {
            "category":"Shopping",
            "subcategory":"Crafts & Fabrics",
            "type":"Retail Goods"
        }
    ],
    "sg:phone":"+61 2 4474 3639",
    "sg:postcode":"2537",
    "sg:province":"NSW",
    "sg:tags":[
        "synthetic",
        "canvas",
        "product"
    ],
    "wof:name":"MPH Custom Canvas",
    "wof:placetype":"venue"
},
  "geometry": {"coordinates":[150.097122192,-35.9163398743],"type":"Point"}
}