{
  "type": "Feature",
  "properties": {
    "addr:full":"1/ 383 Brighton Rd Hove SA 5048",
    "addr:housenumber":"/ 383",
    "addr:postcode":"5048",
    "addr:street":"Brighton Rd",
    "iso:country":"AU",
    "sg:address":"1/ 383 Brighton Rd",
    "sg:city":"Hove",
    "sg:classifiers":[
        {
            "category":"Shopping",
            "subcategory":"Bicycles & Sporting Goods",
            "type":"Retail Goods"
        }
    ],
    "sg:phone":"+61 8 8296 0668",
    "sg:postcode":"5048",
    "sg:province":"SA",
    "sg:tags":[
        "trampoline"
    ],
    "wof:name":"Adelaide Trampoline Mats & Restitching Service",
    "wof:placetype":"venue"
},
  "geometry": {"coordinates":[138.522369,-35.011234],"type":"Point"}
}