{
  "type": "Feature",
  "properties": {
    "addr:full":"9 Jackson St Bassendean WA 6054",
    "addr:housenumber":"9",
    "addr:postcode":"6054",
    "addr:street":"Jackson St",
    "iso:country":"AU",
    "sg:address":"9 Jackson St",
    "sg:city":"Bassendean",
    "sg:classifiers":[
        {
            "category":"Professional",
            "type":"Services"
        }
    ],
    "sg:phone":"+61 8 9446 8999",
    "sg:postcode":"6054",
    "sg:province":"WA",
    "sg:tags":[
        "mail",
        "contractor"
    ],
    "wof:name":"Salmat",
    "wof:placetype":"venue"
},
  "geometry": {"coordinates":[115.933631897,-31.9126243591],"type":"Point"}
}