{
  "type": "Feature",
  "properties": {
    "addr:full":"29 William St Ulverstone TAS 7315",
    "addr:housenumber":"29",
    "addr:postcode":"7315",
    "addr:street":"William St",
    "iso:country":"AU",
    "sg:address":"29 William St",
    "sg:city":"Ulverstone",
    "sg:classifiers":[
        {
            "category":"Home & Garden",
            "subcategory":"Building Materials",
            "type":"Retail Goods"
        }
    ],
    "sg:phone":"+61 407 807 846",
    "sg:postcode":"7315",
    "sg:province":"TAS",
    "sg:tags":[
        "lawn",
        "cutting",
        "maintenance"
    ],
    "wof:name":"Butlers Complete Garden Maintenance",
    "wof:placetype":"venue"
},
  "geometry": {"coordinates":[146.17918395999999,-41.1633071899],"type":"Point"}
}