{
  "type": "Feature",
  "properties": {
    "addr:full":"47 Leda St Burleigh Heads QLD 4220",
    "addr:housenumber":"47",
    "addr:postcode":"4220",
    "addr:street":"Leda St",
    "iso:country":"AU",
    "sg:address":"47 Leda St",
    "sg:city":"Burleigh Heads",
    "sg:classifiers":[
        {
            "category":"Farming",
            "subcategory":"Dairy Farm",
            "type":"Manufacturing & Wholesale Goods"
        }
    ],
    "sg:phone":"+61 7 5576 5311",
    "sg:postcode":"4220",
    "sg:province":"QLD",
    "sg:tags":[
        "wholesaler",
        "product",
        "mfrs"
    ],
    "wof:name":"Downs Dairy Products Pty Ltd The",
    "wof:placetype":"venue"
},
  "geometry": {"coordinates":[153.43275451700001,-28.1038665771],"type":"Point"}
}