{
  "type": "Feature",
  "properties": {
    "addr:full":"781 Waverley Rd Glen Waverley VIC 3150",
    "addr:housenumber":"781",
    "addr:postcode":"3150",
    "addr:street":"Waverley Rd",
    "iso:country":"AU",
    "sg:address":"781 Waverley Rd",
    "sg:city":"Glen Waverley",
    "sg:classifiers":[
        {
            "category":"Building & Trades",
            "subcategory":"Equipment Rental",
            "type":"Services"
        }
    ],
    "sg:phone":"+61 409 197 700",
    "sg:postcode":"3150",
    "sg:province":"VIC",
    "sg:tags":[
        "platform",
        "hire",
        "work",
        "elevating"
    ],
    "wof:name":"Telegat Pty Ltd",
    "wof:placetype":"venue"
},
  "geometry": {"coordinates":[145.17655944800001,-37.8901329041],"type":"Point"}
}