{
  "type": "Feature",
  "properties": {
    "iso:country":"AU",
    "sg:address":"107 Northgate Drv",
    "sg:city":"Thomastown",
    "sg:classifiers":[
        {
            "category":"Autos & Motor Vehicles",
            "subcategory":"Auto Supplies",
            "type":"Retail Goods"
        }
    ],
    "sg:phone":"+61 3 9464 2227",
    "sg:postcode":"3074",
    "sg:province":"VIC",
    "sg:tags":[
        "accessory"
    ],
    "wof:name":"A. Jorge Roofracks",
    "wof:placetype":"venue"
},
  "geometry": {"coordinates":[145.03050231899999,-37.6885757446],"type":"Point"}
}