{
  "type": "Feature",
  "properties": {
    "addr:full":"22 Johnstone Rd Brendale QLD 4500",
    "addr:housenumber":"22",
    "addr:postcode":"4500",
    "addr:street":"Johnstone Rd",
    "iso:country":"AU",
    "sg:address":"22 Johnstone Rd",
    "sg:city":"Brendale",
    "sg:classifiers":[
        {
            "category":"Shopping",
            "type":"Retail Goods"
        }
    ],
    "sg:phone":"+61 7 3881 3855",
    "sg:postcode":"4500",
    "sg:province":"QLD",
    "sg:tags":[
        "equipment",
        "safety",
        "accessory"
    ],
    "wof:name":"Linster Agencies",
    "wof:placetype":"venue"
},
  "geometry": {"coordinates":[152.99305725100001,-27.3220615387],"type":"Point"}
}