{
  "type": "Feature",
  "properties": {
    "addr:full":"59 Ellen St Woody Point QLD 4019",
    "addr:housenumber":"59",
    "addr:postcode":"4019",
    "addr:street":"Ellen St",
    "iso:country":"AU",
    "sg:address":"59 Ellen St",
    "sg:city":"Woody Point",
    "sg:classifiers":[
        {
            "category":"Professional",
            "subcategory":"Management & Consulting",
            "type":"Services"
        }
    ],
    "sg:phone":"+61 7 3283 5884",
    "sg:postcode":"4019",
    "sg:province":"QLD",
    "sg:tags":[
        "consultant",
        "industrial",
        "relation"
    ],
    "wof:name":"Brodie C A & S E Pty Ltd",
    "wof:placetype":"venue"
},
  "geometry": {"coordinates":[153.104003906,-27.2549953461],"type":"Point"}
}