{
  "type": "Feature",
  "properties": {
    "iso:country":"AU",
    "sg:address":"Shop 97",
    "sg:city":"A Australia Fair Shopng Cntr Southport",
    "sg:classifiers":[
        {
            "category":"Shopping",
            "subcategory":"Pets & Pet Supplies",
            "type":"Retail Goods"
        }
    ],
    "sg:phone":"+61 7 5591 4894",
    "sg:postcode":"4215",
    "sg:province":"QLD",
    "sg:tags":[
        "shop",
        "supplier"
    ],
    "wof:name":"Pets Paradise",
    "wof:placetype":"venue"
},
  "geometry": {"coordinates":[153.415557861,-27.9655303955],"type":"Point"}
}