{
  "type": "Feature",
  "properties": {
    "addr:full":"3 Irvine St Upwey VIC 3158",
    "addr:housenumber":"3",
    "addr:postcode":"3158",
    "addr:street":"Irvine St",
    "iso:country":"AU",
    "sg:address":"3 Irvine St",
    "sg:city":"Upwey",
    "sg:classifiers":[
        {
            "category":"Professional",
            "subcategory":"Art Services",
            "type":"Services"
        }
    ],
    "sg:phone":"+61 3 9754 4786",
    "sg:postcode":"3158",
    "sg:province":"VIC",
    "sg:tags":[
        "graphic",
        "designer"
    ],
    "wof:name":"Small Back Room Productions",
    "wof:placetype":"venue"
},
  "geometry": {"coordinates":[145.334075928,-37.9062042236],"type":"Point"}
}