{
  "type": "Feature",
  "properties": {
    "addr:full":"PO Box 2210 Marmion WA 6020",
    "addr:postcode":"6020",
    "iso:country":"AU",
    "sg:address":"PO Box 2210",
    "sg:city":"Marmion",
    "sg:classifiers":[
        {
            "category":"Professional",
            "subcategory":"Accounting & Tax Preparation",
            "type":"Services"
        }
    ],
    "sg:phone":"+61 8 9246 9055",
    "sg:postcode":"6020",
    "sg:province":"WA",
    "sg:tags":[
        "consultant",
        "taxation"
    ],
    "wof:name":"Tax Team",
    "wof:placetype":"venue"
},
  "geometry": {"coordinates":[115.76235199,-31.8460617065],"type":"Point"}
}