{
  "type": "Feature",
  "properties": {
    "addr:full":"8 Apollo Crt Victoria Point QLD 4165",
    "addr:housenumber":"8",
    "addr:postcode":"4165",
    "addr:street":"Apollo Crt",
    "iso:country":"AU",
    "sg:address":"8 Apollo Crt",
    "sg:city":"Victoria Point",
    "sg:classifiers":[
        {
            "category":"Building & Trades",
            "subcategory":"Equipment Rental",
            "type":"Services"
        }
    ],
    "sg:phone":"+61 418 156 300",
    "sg:postcode":"4165",
    "sg:province":"QLD",
    "sg:tags":[
        "crane",
        "hire"
    ],
    "wof:name":"Paul Loudoun",
    "wof:placetype":"venue"
},
  "geometry": {"coordinates":[153.273147583,-27.587896347],"type":"Point"}
}