{
  "type": "Feature",
  "properties": {
    "addr:full":"Head Rd Wandin VIC 3139",
    "addr:postcode":"3139",
    "addr:street":"Head Rd",
    "iso:country":"AU",
    "sg:address":"Head Rd",
    "sg:city":"Wandin",
    "sg:classifiers":[
        {
            "category":"Food & Beverages",
            "subcategory":"Fruits & Vegetables",
            "type":"Retail Goods"
        }
    ],
    "sg:phone":"+61 3 5964 4295",
    "sg:postcode":"3139",
    "sg:province":"VIC",
    "sg:tags":[
        "grower"
    ],
    "wof:name":"Hasan N & C",
    "wof:placetype":"venue"
},
  "geometry": {"coordinates":[145.442260742,-37.8119697571],"type":"Point"}
}