{
  "type": "Feature",
  "properties": {
    "addr:full":"Fairhill Rd North Arm QLD 4561",
    "addr:postcode":"4561",
    "addr:street":"Fairhill Rd",
    "iso:country":"AU",
    "sg:address":"Fairhill Rd",
    "sg:city":"North Arm",
    "sg:classifiers":[
        {
            "category":"Education",
            "subcategory":"School",
            "type":"Public Place"
        }
    ],
    "sg:phone":"+61 7 5472 9888",
    "sg:postcode":"4561",
    "sg:province":"QLD",
    "sg:tags":[
        "state",
        "except",
        "nsw"
    ],
    "wof:name":"North Arm Primary School",
    "wof:placetype":"venue"
},
  "geometry": {"coordinates":[152.96841430699999,-26.5259399414],"type":"Point"}
}