{
  "type": "Feature",
  "properties": {
    "addr:full":"83 Darling St Glebe NSW 2037",
    "addr:housenumber":"83",
    "addr:postcode":"2037",
    "addr:street":"Darling St",
    "iso:country":"AU",
    "sg:address":"83 Darling St",
    "sg:city":"Glebe",
    "sg:classifiers":[
        {
            "category":"Professional",
            "subcategory":"Art Services",
            "type":"Services"
        }
    ],
    "sg:phone":"+61 2 9552 2662",
    "sg:postcode":"2037",
    "sg:province":"NSW",
    "sg:tags":[
        "graphic",
        "designer"
    ],
    "wof:name":"Shadowline Graphics",
    "wof:placetype":"venue"
},
  "geometry": {"coordinates":[151.189086914,-33.8772888184],"type":"Point"}
}