{
  "type": "Feature",
  "properties": {
    "addr:full":"10 Moor St Sandringham VIC 3191",
    "addr:housenumber":"10",
    "addr:postcode":"3191",
    "addr:street":"Moor St",
    "iso:country":"AU",
    "sg:address":"10 Moor St",
    "sg:city":"Sandringham",
    "sg:classifiers":[
        {
            "category":"Professional",
            "subcategory":"Accounting & Tax Preparation",
            "type":"Services"
        }
    ],
    "sg:phone":"+61 3 9521 0617",
    "sg:postcode":"3191",
    "sg:province":"VIC",
    "sg:tags":[
        "jukebox"
    ],
    "wof:name":"Jukebox Music Co",
    "wof:placetype":"venue"
},
  "geometry": {"coordinates":[145.004562378,-37.9462966919],"type":"Point"}
}