{
  "type": "Feature",
  "properties": {
    "addr:full":"PO Box 3307 Wetherill Park NSW 2164",
    "addr:postcode":"2164",
    "iso:country":"AU",
    "sg:address":"PO Box 3307",
    "sg:city":"Wetherill Park",
    "sg:classifiers":[
        {
            "category":"Banks & Credit Unions",
            "subcategory":"Financial Services",
            "type":"Services"
        }
    ],
    "sg:phone":"+61 431 228 801",
    "sg:postcode":"2164",
    "sg:province":"NSW",
    "sg:tags":[
        "loan",
        "finance",
        "mortgage"
    ],
    "wof:name":"RAMS Home Loans",
    "wof:placetype":"venue"
},
  "geometry": {"coordinates":[150.90489196799999,-33.8546104431],"type":"Point"}
}