{
  "type": "Feature",
  "properties": {
    "addr:full":"3 Whitmore St Taringa QLD 4068",
    "addr:housenumber":"3",
    "addr:postcode":"4068",
    "addr:street":"Whitmore St",
    "iso:country":"AU",
    "sg:address":"3 Whitmore St",
    "sg:city":"Taringa",
    "sg:classifiers":[
        {
            "category":"Travel",
            "subcategory":"Hotels & Motels",
            "type":"Entertainment"
        }
    ],
    "sg:phone":"+61 7 3870 4931",
    "sg:postcode":"4068",
    "sg:province":"QLD",
    "wof:name":"Whitmore Park Apartments",
    "wof:placetype":"venue"
},
  "geometry": {"coordinates":[152.9868927,-27.4902820587],"type":"Point"}
}