{
  "type": "Feature",
  "properties": {
    "addr:full":"102a Longueville Rd Lane Cove NSW 2066",
    "addr:housenumber":"102a",
    "addr:postcode":"2066",
    "addr:street":"Longueville Rd",
    "iso:country":"AU",
    "sg:address":"102a Longueville Rd",
    "sg:city":"Lane Cove",
    "sg:classifiers":[
        {
            "category":"Health Services",
            "subcategory":"Health Practitioner",
            "type":"Services"
        }
    ],
    "sg:phone":"+61 411 225 418",
    "sg:postcode":"2066",
    "sg:province":"NSW",
    "sg:tags":[
        "psychologist"
    ],
    "wof:name":"Barnes Christine",
    "wof:placetype":"venue"
},
  "geometry": {"coordinates":[151.17005920400001,-33.8141937256],"type":"Point"}
}