{
  "type": "Feature",
  "properties": {
    "iso:country":"AU",
    "sg:address":"32 - 34 Railway Ave",
    "sg:city":"Ringwood East",
    "sg:classifiers":[
        {
            "category":"Wholesale",
            "subcategory":"Medical Equipment & Supplies",
            "type":"Manufacturing & Wholesale Goods"
        }
    ],
    "sg:phone":"+61 3 9879 8885",
    "sg:postcode":"3135",
    "sg:province":"VIC",
    "sg:tags":[
        "scooter",
        "mobility"
    ],
    "wof:name":"Maroondah Home Healthcare",
    "wof:placetype":"venue"
},
  "geometry": {"coordinates":[145.25213623100001,-37.8116378784],"type":"Point"}
}