{
  "type": "Feature",
  "properties": {
    "addr:full":"2 Rutledge St Queanbeyan NSW 2620",
    "addr:housenumber":"2",
    "addr:postcode":"2620",
    "addr:street":"Rutledge St",
    "iso:country":"AU",
    "sg:address":"2 Rutledge St",
    "sg:city":"Queanbeyan",
    "sg:classifiers":[
        {
            "category":"Health Services",
            "subcategory":"Dentist",
            "type":"Services"
        }
    ],
    "sg:phone":"+61 2 6297 8838",
    "sg:postcode":"2620",
    "sg:province":"NSW",
    "wof:name":"Da Cruz J M Dr",
    "wof:placetype":"venue"
},
  "geometry": {"coordinates":[149.23370361299999,-35.3559265137],"type":"Point"}
}