{
  "type": "Feature",
  "properties": {
    "addr:full":"2167- 2181 Princes Hwy Clayton VIC 3168",
    "addr:housenumber":"2167 2181",
    "addr:postcode":"3168",
    "addr:street":"Princes Hwy",
    "iso:country":"AU",
    "sg:address":"2167- 2181 Princes Hwy",
    "sg:city":"Clayton",
    "sg:classifiers":[
        {
            "category":"Shopping",
            "subcategory":"Baby Store",
            "type":"Retail Goods"
        }
    ],
    "sg:phone":"+61 3 9574 0700",
    "sg:postcode":"3168",
    "sg:province":"VIC",
    "sg:tags":[
        "wear"
    ],
    "wof:name":"Baby Gallery The",
    "wof:placetype":"venue"
},
  "geometry": {"coordinates":[145.145462036,-37.925403595],"type":"Point"}
}