{
  "type": "Feature",
  "properties": {
    "iso:country":"AU",
    "sg:address":"377 Sydney Rd",
    "sg:city":"Balgowlah",
    "sg:classifiers":[
        {
            "category":"Personal",
            "subcategory":"Beauty Salon",
            "type":"Services"
        }
    ],
    "sg:phone":"+61 2 9949 5572",
    "sg:postcode":"2093",
    "sg:province":"NSW",
    "sg:tags":[
        "hairdresser"
    ],
    "wof:name":"Snip Into",
    "wof:placetype":"venue"
},
  "geometry": {"coordinates":[151.26425170900001,-33.794380188],"type":"Point"}
}