{
  "type": "Feature",
  "properties": {
    "addr:full":"440 Camberwell Rd Camberwell VIC 3124",
    "addr:housenumber":"440",
    "addr:postcode":"3124",
    "addr:street":"Camberwell Rd",
    "iso:country":"AU",
    "sg:address":"440 Camberwell Rd",
    "sg:city":"Camberwell",
    "sg:classifiers":[
        {
            "category":"Social Services",
            "subcategory":"Retirement Home",
            "type":"Services"
        }
    ],
    "sg:phone":"+61 3 9889 0611",
    "sg:postcode":"3124",
    "sg:province":"VIC",
    "sg:tags":[
        "village"
    ],
    "wof:name":"Retirement Care Australia",
    "wof:placetype":"venue"
},
  "geometry": {"coordinates":[145.064376831,-37.8381309509],"type":"Point"}
}