{
  "type": "Feature",
  "properties": {
    "addr:full":"Suite 1, 5 -9 Hunter St Parramatta NSW 2150",
    "addr:housenumber":"5 -9",
    "addr:postcode":"2150",
    "addr:street":"Hunter St",
    "iso:country":"AU",
    "sg:address":"Suite 1, 5 -9 Hunter St",
    "sg:city":"Parramatta",
    "sg:classifiers":[
        {
            "category":"Professional",
            "subcategory":"Art Services",
            "type":"Services"
        }
    ],
    "sg:phone":"+61 2 9633 2150",
    "sg:postcode":"2150",
    "sg:province":"NSW",
    "sg:tags":[
        "graphic",
        "designer"
    ],
    "wof:name":"Creative Fusion",
    "wof:placetype":"venue"
},
  "geometry": {"coordinates":[151.03511047399999,-33.8429794312],"type":"Point"}
}