{
  "type": "Feature",
  "properties": {
    "addr:full":"5 Glen Munro Rd Muswellbrook NSW 2333",
    "addr:housenumber":"5",
    "addr:postcode":"2333",
    "addr:street":"Glen Munro Rd",
    "iso:country":"AU",
    "sg:address":"5 Glen Munro Rd",
    "sg:city":"Muswellbrook",
    "sg:classifiers":[
        {
            "category":"Building & Trades",
            "subcategory":"Plumbing",
            "type":"Services"
        }
    ],
    "sg:phone":"+61 2 6542 5244",
    "sg:postcode":"2333",
    "sg:province":"NSW",
    "sg:tags":[
        "fitting",
        "hose",
        "supply"
    ],
    "wof:name":"Parker Enzed",
    "wof:placetype":"venue"
},
  "geometry": {"coordinates":[150.880661011,-32.3138313293],"type":"Point"}
}