{
  "type": "Feature",
  "properties": {
    "addr:full":"12/68- 70 Wollongong St Fyshwick ACT 2609",
    "addr:housenumber":"12 / 68 70",
    "addr:postcode":"2609",
    "addr:street":"Wollongong St",
    "iso:country":"AU",
    "sg:address":"12/68- 70 Wollongong St",
    "sg:city":"Fyshwick",
    "sg:classifiers":[
        {
            "category":"Shopping",
            "subcategory":"Crafts & Fabrics",
            "type":"Retail Goods"
        }
    ],
    "sg:phone":"+61 2 6280 0083",
    "sg:postcode":"2609",
    "sg:province":"ACT",
    "sg:tags":[
        "synthetic",
        "canvas",
        "product"
    ],
    "wof:name":"Specialty Canvas",
    "wof:placetype":"venue"
},
  "geometry": {"coordinates":[149.17918395999999,-35.323638916],"type":"Point"}
}