{
  "type": "Feature",
  "properties": {
    "addr:full":"346 Moreland Rd Brunswick VIC 3056",
    "addr:housenumber":"346",
    "addr:postcode":"3056",
    "addr:street":"Moreland Rd",
    "iso:country":"AU",
    "sg:address":"346 Moreland Rd",
    "sg:city":"Brunswick",
    "sg:classifiers":[
        {
            "category":"Health Services",
            "subcategory":"Health Practitioner",
            "type":"Services"
        }
    ],
    "sg:phone":"+61 3 9386 8451",
    "sg:postcode":"3056",
    "sg:province":"VIC",
    "sg:tags":[
        "myotherapy"
    ],
    "wof:name":"Moreland Myotherapy & Acupuncture",
    "wof:placetype":"venue"
},
  "geometry": {"coordinates":[144.95019531200001,-37.7539176941],"type":"Point"}
}