{
  "type": "Feature",
  "properties": {
    "addr:full":"Mayreefe Rd Elmore VIC 3558",
    "addr:postcode":"3558",
    "addr:street":"Mayreefe Rd",
    "iso:country":"AU",
    "sg:address":"Mayreefe Rd",
    "sg:city":"Elmore",
    "sg:classifiers":[
        {
            "category":"Farming",
            "subcategory":"Farm & Veterinary Services",
            "type":"Manufacturing & Wholesale Goods"
        }
    ],
    "sg:phone":"+61 3 5432 6120",
    "sg:postcode":"3558",
    "sg:province":"VIC",
    "sg:tags":[
        "contracting"
    ],
    "wof:name":"D & M Emberson- Elmore",
    "wof:placetype":"venue"
},
  "geometry": {"coordinates":[144.60948181099999,-36.4930915833],"type":"Point"}
}