{
  "type": "Feature",
  "properties": {
    "addr:full":"PO Box 38 Torquay VIC 3228",
    "addr:postcode":"3228",
    "iso:country":"AU",
    "sg:address":"PO Box 38",
    "sg:city":"Torquay",
    "sg:classifiers":[
        {
            "category":"Professional",
            "subcategory":"Detective & Security Services",
            "type":"Services"
        }
    ],
    "sg:phone":"+61 3 5261 3523",
    "sg:postcode":"3228",
    "sg:province":"VIC",
    "sg:tags":[
        "investigator"
    ],
    "wof:name":"BD Investigations",
    "wof:placetype":"venue"
},
  "geometry": {"coordinates":[144.31811500000001,-38.329899],"type":"Point"}
}