{
  "type": "Feature",
  "properties": {
    "iso:country":"AU",
    "sg:address":"PO Box 1695",
    "sg:city":"Canning Vale PLB",
    "sg:classifiers":[
        {
            "category":"Building & Trades",
            "subcategory":"Cleaning & Sanitation",
            "type":"Services"
        }
    ],
    "sg:phone":"+61 412 929 730",
    "sg:postcode":"6970",
    "sg:province":"WA",
    "sg:tags":[
        "window"
    ],
    "wof:name":"Pummells Sparkling Glass",
    "wof:placetype":"venue"
},
  "geometry": {"coordinates":[115.920921326,-32.0658683777],"type":"Point"}
}