{
  "type": "Feature",
  "properties": {
    "addr:full":"90 Hart St Semaphore South SA 5019",
    "addr:housenumber":"90",
    "addr:postcode":"5019",
    "addr:street":"Hart St",
    "iso:country":"AU",
    "sg:address":"90 Hart St",
    "sg:city":"Semaphore South",
    "sg:classifiers":[
        {
            "category":"Education",
            "subcategory":"School",
            "type":"Public Place"
        }
    ],
    "sg:phone":"+61 8 8449 7004",
    "sg:postcode":"5019",
    "sg:province":"SA",
    "sg:tags":[
        "state",
        "except",
        "nsw"
    ],
    "wof:name":"Le Fevre High",
    "wof:placetype":"venue"
},
  "geometry": {"coordinates":[138.484939575,-34.844745636],"type":"Point"}
}