{
  "type": "Feature",
  "properties": {
    "addr:full":"25- 33 Elliott Crt Hillcrest QLD 4118",
    "addr:housenumber":"33",
    "addr:postcode":"4118",
    "addr:street":"Elliott Crt",
    "iso:country":"AU",
    "sg:address":"25- 33 Elliott Crt",
    "sg:city":"Hillcrest",
    "sg:classifiers":[
        {
            "category":"Building & Trades",
            "subcategory":"Construction",
            "type":"Services"
        }
    ],
    "sg:phone":"+61 7 3809 3936",
    "sg:postcode":"4118",
    "sg:province":"QLD",
    "sg:tags":[
        "concrete",
        "contractor"
    ],
    "wof:name":"Specified Kerb & Channel",
    "wof:placetype":"venue"
},
  "geometry": {"coordinates":[153.032836914,-27.6608371735],"type":"Point"}
}