{
  "type": "Feature",
  "properties": {
    "addr:full":"45 Bangholme Rd Dandenong South VIC 3175",
    "addr:housenumber":"45",
    "addr:postcode":"3175",
    "addr:street":"Bangholme Rd",
    "iso:country":"AU",
    "sg:address":"45 Bangholme Rd",
    "sg:city":"Dandenong South",
    "sg:classifiers":[
        {
            "category":"Manufacturing",
            "subcategory":"Building Materials",
            "type":"Manufacturing & Wholesale Goods"
        }
    ],
    "sg:phone":"+61 3 9706 5111",
    "sg:postcode":"3175",
    "sg:province":"VIC",
    "sg:tags":[
        "concrete",
        "product"
    ],
    "wof:name":"C.T.C. Concrete Technologies Corporation Pty Ltd",
    "wof:placetype":"venue"
},
  "geometry": {"coordinates":[145.200683594,-38.0380401611],"type":"Point"}
}