{
  "type": "Feature",
  "properties": {
    "iso:country":"AU",
    "sg:address":"42 Park Rd",
    "sg:city":"Kensington Park",
    "sg:classifiers":[
        {
            "category":"Banks & Credit Unions",
            "subcategory":"Financial Services",
            "type":"Services"
        }
    ],
    "sg:phone":"+61 8 8364 2885",
    "sg:postcode":"5068",
    "sg:province":"SA",
    "sg:tags":[
        "planning"
    ],
    "wof:name":"APT Strategy Pty Ltd",
    "wof:placetype":"venue"
},
  "geometry": {"coordinates":[138.65594482399999,-34.9233665466],"type":"Point"}
}