{
  "type": "Feature",
  "properties": {
    "addr:full":"38 Barrie Rd Tullamarine VIC 3043",
    "addr:housenumber":"38",
    "addr:postcode":"3043",
    "addr:street":"Barrie Rd",
    "iso:country":"AU",
    "sg:address":"38 Barrie Rd",
    "sg:city":"Tullamarine",
    "sg:classifiers":[
        {
            "category":"Professional",
            "type":"Services"
        }
    ],
    "sg:phone":"+61 3 9335 6000",
    "sg:postcode":"3043",
    "sg:province":"VIC",
    "sg:tags":[
        "mail",
        "contractor"
    ],
    "sg:website":"http://www.advancedmailing.com.au",
    "wof:name":"Advanced Mailing Solutions",
    "wof:placetype":"venue"
},
  "geometry": {"coordinates":[144.87725830100001,-37.7122077942],"type":"Point"}
}