{
  "type": "Feature",
  "properties": {
    "addr:full":"18 Loombah St Bilgola Plateau NSW 2107",
    "addr:housenumber":"18",
    "addr:postcode":"2107",
    "addr:street":"Loombah St",
    "iso:country":"AU",
    "sg:address":"18 Loombah St",
    "sg:city":"Bilgola Plateau",
    "sg:classifiers":[
        {
            "category":"Government",
            "subcategory":"Court House",
            "type":"Public Place"
        }
    ],
    "sg:phone":"+61 2 9918 8733",
    "sg:postcode":"2107",
    "sg:province":"NSW",
    "sg:tags":[
        "personal",
        "marriage",
        "family",
        "counselling"
    ],
    "wof:name":"Bennett Kelly R",
    "wof:placetype":"venue"
},
  "geometry": {"coordinates":[151.31126403799999,-33.6457023621],"type":"Point"}
}