{
  "type": "Feature",
  "properties": {
    "iso:country":"AU",
    "sg:address":"St Georges Rd",
    "sg:city":"Beaconsfield Upper",
    "sg:classifiers":[
        {
            "category":"Food & Beverages",
            "subcategory":"Supermarket",
            "type":"Retail Goods"
        }
    ],
    "sg:phone":"+61 3 5944 3255",
    "sg:postcode":"3808",
    "sg:province":"VIC",
    "sg:tags":[
        "grocery",
        "store"
    ],
    "wof:name":"Upper Beaconsfield Supermarket Pty Ltd",
    "wof:placetype":"venue"
},
  "geometry": {"coordinates":[145.39184599999999,-37.991344],"type":"Point"}
}