{
  "type": "Feature",
  "properties": {
    "addr:full":"9 Gabriel Crt Oakhurst QLD 4650",
    "addr:housenumber":"9",
    "addr:postcode":"4650",
    "addr:street":"Gabriel Crt",
    "iso:country":"AU",
    "sg:address":"9 Gabriel Crt",
    "sg:city":"Oakhurst",
    "sg:classifiers":[
        {
            "category":"Building & Trades",
            "subcategory":"Plumbing",
            "type":"Services"
        }
    ],
    "sg:phone":"+61 428 216 657",
    "sg:postcode":"4650",
    "sg:province":"QLD",
    "sg:tags":[
        "plumber",
        "gasfitters"
    ],
    "wof:name":"Wayne Smith Plumbing Co Pty Ltd",
    "wof:placetype":"venue"
},
  "geometry": {"coordinates":[152.611603,-25.51214],"type":"Point"}
}