{
  "type": "Feature",
  "properties": {
    "addr:full":"Albany Hwy, Cnr Cecil Ave Cannington WA 6107",
    "addr:postcode":"6107",
    "addr:street":"Albany Hwy Cnr Cecil Ave",
    "iso:country":"AU",
    "sg:address":"Albany Hwy, Cnr Cecil Ave",
    "sg:city":"Cannington",
    "sg:classifiers":[
        {
            "category":"Fast Food",
            "type":"Food & Drink"
        }
    ],
    "sg:phone":"+61 8 9358 6000",
    "sg:postcode":"6107",
    "sg:province":"WA",
    "sg:tags":[
        "away",
        "take"
    ],
    "wof:name":"McDonald's Family Restaurants",
    "wof:placetype":"venue"
},
  "geometry": {"coordinates":[115.935668945,-32.0175590515],"type":"Point"}
}