{
  "type": "Feature",
  "properties": {
    "iso:country":"AU",
    "sg:address":"3 Wonga St",
    "sg:city":"North Balgowlah",
    "sg:classifiers":[
        {
            "category":"Building & Trades",
            "subcategory":"Plumbing",
            "type":"Services"
        }
    ],
    "sg:phone":"+61 2 9948 6125",
    "sg:postcode":"2093",
    "sg:province":"NSW",
    "sg:tags":[
        "plumber",
        "gasfitters"
    ],
    "wof:name":"M & S Innes",
    "wof:placetype":"venue"
},
  "geometry": {"coordinates":[151.25030517600001,-33.7845878601],"type":"Point"}
}