{
  "type": "Feature",
  "properties": {
    "addr:full":"Oaklands Rd Pambula NSW 2549",
    "addr:postcode":"2549",
    "addr:street":"Oaklands Rd",
    "iso:country":"AU",
    "sg:address":"Oaklands Rd",
    "sg:city":"Pambula",
    "sg:classifiers":[
        {
            "category":"Farming",
            "subcategory":"Dairy Farm",
            "type":"Manufacturing & Wholesale Goods"
        }
    ],
    "sg:phone":"+61 2 6495 7906",
    "sg:postcode":"2549",
    "sg:province":"NSW",
    "sg:tags":[
        "wholesaler",
        "product",
        "mfrs"
    ],
    "wof:name":"Sapphire Coast Milk and Dairy Supplies",
    "wof:placetype":"venue"
},
  "geometry": {"coordinates":[149.86407470699999,-36.9300346375],"type":"Point"}
}