{
  "type": "Feature",
  "properties": {
    "iso:country":"AU",
    "sg:address":"46 Wyndham St",
    "sg:city":"Shepparton",
    "sg:classifiers":[
        {
            "category":"Banks & Credit Unions",
            "subcategory":"Financial Services",
            "type":"Services"
        }
    ],
    "sg:phone":"+61 3 5831 2055",
    "sg:postcode":"3630",
    "sg:province":"VIC",
    "sg:tags":[
        "planning"
    ],
    "wof:name":"Life Financial Services",
    "wof:placetype":"venue"
},
  "geometry": {"coordinates":[145.401153564,-36.3707962036],"type":"Point"}
}