{
  "type": "Feature",
  "properties": {
    "iso:country":"AU",
    "sg:address":"12 Alkina St",
    "sg:city":"Kenmore",
    "sg:classifiers":[
        {
            "category":"Utilities",
            "subcategory":"Natural Gas",
            "type":"Services"
        }
    ],
    "sg:phone":"+61 7 3378 9066",
    "sg:postcode":"4069",
    "sg:province":"QLD",
    "sg:tags":[
        "consultant",
        "resource"
    ],
    "wof:name":"Integrated Open Space Services(IOSS)",
    "wof:placetype":"venue"
},
  "geometry": {"coordinates":[152.948394775,-27.5103149414],"type":"Point"}
}