{
  "type": "Feature",
  "properties": {
    "addr:full":"Shop G12, Citymark Building, 683-689 George St Haymarket NSW 2000",
    "addr:housenumber":"g12;683-689",
    "addr:postcode":"2000",
    "addr:street":"George St",
    "iso:country":"AU",
    "sg:address":"Shop G12, Citymark Building, 683-689 George St",
    "sg:city":"Haymarket",
    "sg:classifiers":[
        {
            "category":"Health Services",
            "subcategory":"Optometrist",
            "type":"Services"
        }
    ],
    "sg:phone":"+61 2 9211 2668",
    "sg:postcode":"2000",
    "sg:province":"NSW",
    "wof:name":"Icontact",
    "wof:placetype":"venue"
},
  "geometry": {"coordinates":[151.20509338400001,-33.8799552917],"type":"Point"}
}