{
  "type": "Feature",
  "properties": {
    "addr:full":"37 Wyena St Camp Hill QLD 4152",
    "addr:housenumber":"37",
    "addr:postcode":"4152",
    "addr:street":"Wyena St",
    "iso:country":"AU",
    "sg:address":"37 Wyena St",
    "sg:city":"Camp Hill",
    "sg:classifiers":[
        {
            "category":"Wholesale",
            "subcategory":"Medical Equipment & Supplies",
            "type":"Manufacturing & Wholesale Goods"
        }
    ],
    "sg:phone":"+61 1300 792 060",
    "sg:postcode":"4152",
    "sg:province":"QLD",
    "sg:tags":[
        "dental"
    ],
    "wof:name":"Vince Cicchini",
    "wof:placetype":"venue"
},
  "geometry": {"coordinates":[153.080612183,-27.4881324768],"type":"Point"}
}