{
  "type": "Feature",
  "properties": {
    "addr:full":"4, 3- 7 Bryant Ave Tuggerah NSW 2259",
    "addr:housenumber":"7",
    "addr:postcode":"2259",
    "addr:street":"Bryant Ave",
    "iso:country":"AU",
    "sg:address":"4, 3- 7 Bryant Ave",
    "sg:city":"Tuggerah",
    "sg:classifiers":[
        {
            "category":"Banks & Credit Unions",
            "subcategory":"Financial Services",
            "type":"Services"
        }
    ],
    "sg:phone":"+61 2 4353 3800",
    "sg:postcode":"2259",
    "sg:province":"NSW",
    "sg:tags":[
        "planning"
    ],
    "wof:name":"Joe Timp",
    "wof:placetype":"venue"
},
  "geometry": {"coordinates":[151.42254638700001,-33.3113670349],"type":"Point"}
}