{
  "type": "Feature",
  "properties": {
    "addr:full":"72 Wigram St Harris Park NSW 2150",
    "addr:housenumber":"72",
    "addr:postcode":"2150",
    "addr:street":"Wigram St",
    "iso:country":"AU",
    "sg:address":"72 Wigram St",
    "sg:city":"Harris Park",
    "sg:classifiers":[
        {
            "category":"Health Services",
            "subcategory":"Doctor",
            "type":"Services"
        }
    ],
    "sg:phone":"+61 2 9633 3744",
    "sg:postcode":"2150",
    "sg:province":"NSW",
    "sg:tags":[
        "medical",
        "practitioner"
    ],
    "wof:name":"Wigram St Family Medical Practice",
    "wof:placetype":"venue"
},
  "geometry": {"coordinates":[151.00895690900001,-33.8213691711],"type":"Point"}
}