{
  "type": "Feature",
  "properties": {
    "addr:full":"Shop 7, 47 Ashmore Rd Bundall QLD 4217",
    "addr:housenumber":"shop;47",
    "addr:postcode":"4217",
    "addr:street":"Ashmore Rd",
    "iso:country":"AU",
    "sg:address":"Shop 7, 47 Ashmore Rd",
    "sg:city":"Bundall",
    "sg:classifiers":[
        {
            "category":"Restaurant",
            "type":"Food & Drink"
        }
    ],
    "sg:phone":"+61 7 5592 4011",
    "sg:postcode":"4217",
    "sg:province":"QLD",
    "wof:name":"Royal Phuket Thai",
    "wof:placetype":"venue"
},
  "geometry": {"coordinates":[153.40742492699999,-28.0104084015],"type":"Point"}
}