{
  "type": "Feature",
  "properties": {
    "iso:country":"AU",
    "sg:address":"U1/ 547 Bourke St",
    "sg:city":"Surry Hills",
    "sg:classifiers":[
        {
            "category":"Cafe",
            "type":"Food & Drink"
        }
    ],
    "sg:phone":"+61 2 9331 5900",
    "sg:postcode":"2010",
    "sg:province":"NSW",
    "wof:name":"Chado- The Way of Tea",
    "wof:placetype":"venue"
},
  "geometry": {"coordinates":[151.21516418499999,-33.887260437],"type":"Point"}
}