{
  "type": "Feature",
  "properties": {
    "addr:full":"315 Charman Rd Cheltenham VIC 3192",
    "addr:housenumber":"315",
    "addr:postcode":"3192",
    "addr:street":"Charman Rd",
    "iso:country":"AU",
    "sg:address":"315 Charman Rd",
    "sg:city":"Cheltenham",
    "sg:classifiers":[
        {
            "category":"Utilities",
            "subcategory":"Telephone",
            "type":"Services"
        }
    ],
    "sg:phone":"+61 3 9584 6922",
    "sg:postcode":"3192",
    "sg:province":"VIC",
    "sg:tags":[
        "equipment",
        "system"
    ],
    "wof:name":"TBS Bayside",
    "wof:placetype":"venue"
},
  "geometry": {"coordinates":[145.05572509800001,-37.9643363953],"type":"Point"}
}