{
  "type": "Feature",
  "properties": {
    "iso:country":"AU",
    "sg:address":"121 Torquay Rd",
    "sg:city":"Scarness",
    "sg:classifiers":[
        {
            "category":"Retail",
            "subcategory":"Repair Shop",
            "type":"Services"
        }
    ],
    "sg:phone":"+61 7 4124 7101",
    "sg:postcode":"4655",
    "sg:province":"QLD",
    "sg:tags":[
        "machine",
        "sewing"
    ],
    "wof:name":"Hervey Bay Sewing Machines",
    "wof:placetype":"venue"
},
  "geometry": {"coordinates":[152.852295,-25.28631],"type":"Point"}
}