{
  "type": "Feature",
  "properties": {
    "addr:full":"8/ 39 Secam St Mansfield QLD 4122",
    "addr:housenumber":"/ 39",
    "addr:postcode":"4122",
    "addr:street":"Secam St",
    "iso:country":"AU",
    "sg:address":"8/ 39 Secam St",
    "sg:city":"Mansfield",
    "sg:classifiers":[
        {
            "category":"Retail",
            "subcategory":"Auto Repair",
            "type":"Services"
        }
    ],
    "sg:phone":"+61 7 3349 6642",
    "sg:postcode":"4122",
    "sg:province":"QLD",
    "sg:tags":[
        "repairer",
        "motor",
        "engineer"
    ],
    "wof:name":"Megalube Express Pty Ltd",
    "wof:placetype":"venue"
},
  "geometry": {"coordinates":[153.098480225,-27.5306606293],"type":"Point"}
}