{
  "type": "Feature",
  "properties": {
    "addr:full":"17 Para St Renmark SA 5341",
    "addr:housenumber":"17",
    "addr:postcode":"5341",
    "addr:street":"Para St",
    "iso:country":"AU",
    "sg:address":"17 Para St",
    "sg:city":"Renmark",
    "sg:classifiers":[
        {
            "category":"Autos & Motor Vehicles",
            "subcategory":"Auto Supplies",
            "type":"Retail Goods"
        }
    ],
    "sg:phone":"+61 8 8586 6751",
    "sg:postcode":"5341",
    "sg:province":"SA",
    "sg:tags":[
        "battery",
        "automotive"
    ],
    "wof:name":"Beaurepaires",
    "wof:placetype":"venue"
},
  "geometry": {"coordinates":[140.74681091299999,-34.1772079468],"type":"Point"}
}