{
  "type": "Feature",
  "properties": {
    "addr:full":"6b Garland Pl Karratha WA 6714",
    "addr:housenumber":"6b",
    "addr:postcode":"6714",
    "addr:street":"Garland Pl Karratha",
    "iso:country":"AU",
    "sg:address":"6b Garland Pl",
    "sg:city":"Karratha",
    "sg:classifiers":[
        {
            "category":"Train Station",
            "subcategory":"Rail",
            "type":"Transportation"
        }
    ],
    "sg:phone":"+61 8 9185 5762",
    "sg:postcode":"6714",
    "sg:province":"WA",
    "sg:tags":[
        "rolling",
        "railway",
        "tramway",
        "stock"
    ],
    "wof:name":"Bradken",
    "wof:placetype":"venue"
},
  "geometry": {"coordinates":[116.816230774,-20.7452087402],"type":"Point"}
}