{
  "type": "Feature",
  "properties": {
    "iso:country":"AU",
    "sg:address":"Suite 1a 45 Minchinton St",
    "sg:city":"Caloundra",
    "sg:classifiers":[
        {
            "category":"Health Services",
            "subcategory":"Health Practitioner",
            "type":"Services"
        }
    ],
    "sg:phone":"+61 7 5491 6393",
    "sg:postcode":"4551",
    "sg:province":"QLD",
    "sg:tags":[
        "physiotherapist"
    ],
    "wof:name":"Tresna Stokes Physiotherapy",
    "wof:placetype":"venue"
},
  "geometry": {"coordinates":[153.13229370100001,-26.8040008545],"type":"Point"}
}