{
  "type": "Feature",
  "properties": {
    "addr:full":"7 Hassall St Parramatta NSW 2150",
    "addr:housenumber":"7",
    "addr:postcode":"2150",
    "addr:street":"Hassall St",
    "iso:country":"AU",
    "sg:address":"7 Hassall St",
    "sg:city":"Parramatta",
    "sg:classifiers":[
        {
            "category":"Education",
            "subcategory":"Dance Studio",
            "type":"Public Place"
        }
    ],
    "sg:phone":"+61 2 9689 3659",
    "sg:postcode":"2150",
    "sg:province":"NSW",
    "sg:tags":[
        "instruction",
        "language"
    ],
    "wof:name":"Australian Centre For Languages The",
    "wof:placetype":"venue"
},
  "geometry": {"coordinates":[150.98860168499999,-33.8093948364],"type":"Point"}
}