{
  "type": "Feature",
  "properties": {
    "addr:full":"4 / 30 Balleter St Essendon VIC 3040",
    "addr:housenumber":"/ 30",
    "addr:postcode":"3040",
    "addr:street":"Balleter St",
    "iso:country":"AU",
    "sg:address":"4 / 30 Balleter St",
    "sg:city":"Essendon",
    "sg:classifiers":[
        {
            "category":"Utilities",
            "subcategory":"Electric",
            "type":"Services"
        }
    ],
    "sg:phone":"+61 3 9337 0222",
    "sg:postcode":"3040",
    "sg:province":"VIC",
    "sg:tags":[
        "electrical",
        "contractor"
    ],
    "wof:name":"Rize Electronics Pty Ltd",
    "wof:placetype":"venue"
},
  "geometry": {"coordinates":[144.90545654300001,-37.7482070923],"type":"Point"}
}