{
  "type": "Feature",
  "properties": {
    "addr:full":"Shp 2/ 227 Windang Rd Windang NSW 2528",
    "addr:housenumber":"/ 227",
    "addr:postcode":"2528",
    "addr:street":"Windang Rd",
    "iso:country":"AU",
    "sg:address":"Shp 2/ 227 Windang Rd",
    "sg:city":"Windang",
    "sg:classifiers":[
        {
            "category":"Personal",
            "subcategory":"Beauty Salon",
            "type":"Services"
        }
    ],
    "sg:phone":"+61 2 4296 2444",
    "sg:postcode":"2528",
    "sg:province":"NSW",
    "sg:tags":[
        "hairdresser"
    ],
    "wof:name":"Beautiful Hair Studio",
    "wof:placetype":"venue"
},
  "geometry": {"coordinates":[150.86892700199999,-34.5317840576],"type":"Point"}
}