{
  "type": "Feature",
  "properties": {
    "addr:full":"Unit 15/ 16 narabang Way Belrose NSW 2085",
    "addr:housenumber":"/ 16",
    "addr:postcode":"2085",
    "addr:street":"Narabang Way",
    "iso:country":"AU",
    "sg:address":"Unit 15/ 16 narabang Way",
    "sg:city":"Belrose",
    "sg:classifiers":[
        {
            "category":"Building & Trades",
            "subcategory":"Construction",
            "type":"Services"
        }
    ],
    "sg:phone":"+61 2 9986 1585",
    "sg:postcode":"2085",
    "sg:province":"NSW",
    "sg:tags":[
        "pool",
        "swimming"
    ],
    "wof:name":"Aspect Pools",
    "wof:placetype":"venue"
},
  "geometry": {"coordinates":[151.212432861,-33.7053604126],"type":"Point"}
}