{
  "type": "Feature",
  "properties": {
    "addr:full":"7/ 1118 Oxley Rd Oxley QLD 4075",
    "addr:housenumber":"/ 1118",
    "addr:postcode":"4075",
    "addr:street":"Oxley Rd",
    "iso:country":"AU",
    "sg:address":"7/ 1118 Oxley Rd",
    "sg:city":"Oxley",
    "sg:classifiers":[
        {
            "category":"Building & Trades",
            "subcategory":"Locksmith",
            "type":"Services"
        }
    ],
    "sg:phone":"+61 1800 777 027",
    "sg:postcode":"4075",
    "sg:province":"QLD",
    "sg:tags":[
        "strongroom",
        "safe",
        "door"
    ],
    "wof:name":"Locksmiths Today",
    "wof:placetype":"venue"
},
  "geometry": {"coordinates":[152.97845459000001,-27.5604305267],"type":"Point"}
}