{
  "type": "Feature",
  "properties": {
    "addr:full":"Level 1, 17 Pacific Pde Dee Why NSW 2099",
    "addr:housenumber":"17",
    "addr:postcode":"2099",
    "addr:street":"Pacific Pde",
    "iso:country":"AU",
    "sg:address":"Level 1, 17 Pacific Pde",
    "sg:city":"Dee Why",
    "sg:classifiers":[
        {
            "category":"Personal",
            "subcategory":"Skin Care",
            "type":"Services"
        }
    ],
    "sg:phone":"+61 2 9411 6199",
    "sg:postcode":"2099",
    "sg:province":"NSW",
    "sg:tags":[
        "treatment"
    ],
    "wof:name":"Ainley Fiona Dr",
    "wof:placetype":"venue"
},
  "geometry": {"coordinates":[151.28546142600001,-33.7546730042],"type":"Point"}
}