{
  "type": "Feature",
  "properties": {
    "addr:full":"110 Bald Hills Rd Tarwin Lower VIC 3956",
    "addr:housenumber":"110",
    "addr:postcode":"3956",
    "addr:street":"Bald Hills Rd",
    "iso:country":"AU",
    "sg:address":"110 Bald Hills Rd",
    "sg:city":"Tarwin Lower",
    "sg:classifiers":[
        {
            "category":"Building & Trades",
            "subcategory":"Construction",
            "type":"Services"
        }
    ],
    "sg:phone":"+61 3 5663 5274",
    "sg:postcode":"3956",
    "sg:province":"VIC",
    "sg:tags":[
        "contractor"
    ],
    "wof:name":"Fauna Park Homes",
    "wof:placetype":"venue"
},
  "geometry": {"coordinates":[145.905563355,-38.7307815552],"type":"Point"}
}