{
  "type": "Feature",
  "properties": {
    "addr:full":"478 Peel St Tamworth NSW 2340",
    "addr:housenumber":"478",
    "addr:postcode":"2340",
    "addr:street":"Peel St",
    "iso:country":"AU",
    "sg:address":"478 Peel St",
    "sg:city":"Tamworth",
    "sg:classifiers":[
        {
            "category":"Retail",
            "subcategory":"Car Wash",
            "type":"Services"
        }
    ],
    "sg:phone":"+61 2 6766 9874",
    "sg:postcode":"2340",
    "sg:province":"NSW",
    "sg:tags":[
        "truck",
        "cleaning"
    ],
    "wof:name":"CarLovers Carwash Tamworth",
    "wof:placetype":"venue"
},
  "geometry": {"coordinates":[150.93409729000001,-31.0950450897],"type":"Point"}
}