{
  "type": "Feature",
  "properties": {
    "iso:country":"AU",
    "sg:address":"&#034;Halcyon&#034; 571 Dawson Rd",
    "sg:city":"Berajondo",
    "sg:classifiers":[
        {
            "category":"Building & Trades",
            "subcategory":"Landscaping Services",
            "type":"Services"
        }
    ],
    "sg:phone":"+61 7 4156 5165",
    "sg:postcode":"4674",
    "sg:province":"QLD",
    "sg:tags":[
        "grazier"
    ],
    "wof:name":"Dawson N L",
    "wof:placetype":"venue"
},
  "geometry": {"coordinates":[151.845383,-24.617479],"type":"Point"}
}