{
  "type": "Feature",
  "properties": {
    "iso:country":"AU",
    "sg:address":"Shp 16/ 255 Gregory St",
    "sg:city":"South West Rocks",
    "sg:classifiers":[
        {
            "category":"Personal",
            "subcategory":"Beauty Salon",
            "type":"Services"
        }
    ],
    "sg:phone":"+61 2 6566 6199",
    "sg:postcode":"2431",
    "sg:province":"NSW",
    "wof:name":"Rock Beauty Therapy Bilo Complex",
    "wof:placetype":"venue"
},
  "geometry": {"coordinates":[153.03907799999999,-30.885706],"type":"Point"}
}