{
  "type": "Feature",
  "properties": {
    "addr:full":"98 Sapphire St Greystanes NSW 2145",
    "addr:housenumber":"98",
    "addr:postcode":"2145",
    "addr:street":"Sapphire St",
    "iso:country":"AU",
    "sg:address":"98 Sapphire St",
    "sg:city":"Greystanes",
    "sg:classifiers":[
        {
            "category":"Professional",
            "subcategory":"Management & Consulting",
            "type":"Services"
        }
    ],
    "sg:phone":"+61 2 9896 0359",
    "sg:postcode":"2145",
    "sg:province":"NSW",
    "sg:tags":[
        "consultant"
    ],
    "wof:name":"ValueFirst Pty Ltd",
    "wof:placetype":"venue"
},
  "geometry": {"coordinates":[150.94891357399999,-33.8115692139],"type":"Point"}
}