{
  "type": "Feature",
  "properties": {
    "addr:full":"196 Baylis St Wagga Wagga NSW 2650",
    "addr:housenumber":"196",
    "addr:postcode":"2650",
    "addr:street":"Baylis St",
    "iso:country":"AU",
    "sg:address":"196 Baylis St",
    "sg:city":"Wagga Wagga",
    "sg:classifiers":[
        {
            "category":"Manufacturing",
            "subcategory":"Jewelry",
            "type":"Manufacturing & Wholesale Goods"
        }
    ],
    "sg:phone":"+61 2 6921 3000",
    "sg:postcode":"2650",
    "sg:province":"NSW",
    "sg:tags":[
        "mfrg",
        "jeweller"
    ],
    "wof:name":"Diors",
    "wof:placetype":"venue"
},
  "geometry": {"coordinates":[147.37005615199999,-35.1114959717],"type":"Point"}
}