{
  "type": "Feature",
  "properties": {
    "addr:full":"27 Massey Ave Reservoir VIC 3073",
    "addr:housenumber":"27",
    "addr:postcode":"3073",
    "addr:street":"Massey Ave",
    "iso:country":"AU",
    "sg:address":"27 Massey Ave",
    "sg:city":"Reservoir",
    "sg:classifiers":[
        {
            "category":"Farming",
            "subcategory":"Farm & Veterinary Services",
            "type":"Manufacturing & Wholesale Goods"
        }
    ],
    "sg:phone":"+61 3 9462 6789",
    "sg:postcode":"3073",
    "sg:province":"VIC",
    "sg:tags":[
        "poultry",
        "processing",
        "supply"
    ],
    "wof:name":"Poultryline Pty Ltd",
    "wof:placetype":"venue"
},
  "geometry": {"coordinates":[144.98979187,-37.7053184509],"type":"Point"}
}