{
  "type": "Feature",
  "properties": {
    "iso:country":"AU",
    "sg:address":"10/ 449 St Kilda Rd",
    "sg:city":"Melbourne",
    "sg:classifiers":[
        {
            "category":"Health Services",
            "subcategory":"Doctor",
            "type":"Services"
        }
    ],
    "sg:phone":"+61 3 9867 6640",
    "sg:postcode":"3000",
    "sg:province":"VIC",
    "sg:tags":[
        "medical",
        "practitioner"
    ],
    "wof:name":"Quin D Dr",
    "wof:placetype":"venue"
},
  "geometry": {"coordinates":[144.96751403799999,-37.8176269531],"type":"Point"}
}