{
  "type": "Feature",
  "properties": {
    "addr:full":"U 10/ 49 Jijaws St Sumner QLD 4074",
    "addr:housenumber":"10 / 49",
    "addr:postcode":"4074",
    "addr:street":"Jijaws St",
    "iso:country":"AU",
    "sg:address":"U 10/ 49 Jijaws St",
    "sg:city":"Sumner",
    "sg:classifiers":[
        {
            "category":"Shopping",
            "subcategory":"Party Supplies",
            "type":"Retail Goods"
        }
    ],
    "sg:phone":"+61 7 3279 7138",
    "sg:postcode":"4074",
    "sg:province":"QLD",
    "sg:tags":[
        "selling",
        "plan"
    ],
    "wof:name":"Dreams And Traditions",
    "wof:placetype":"venue"
},
  "geometry": {"coordinates":[152.93930053700001,-27.562538147],"type":"Point"}
}