{
  "type": "Feature",
  "properties": {
    "addr:full":"56 Boronia Rd Bullaburra NSW 2784",
    "addr:housenumber":"56",
    "addr:postcode":"2784",
    "addr:street":"Boronia Rd",
    "iso:country":"AU",
    "sg:address":"56 Boronia Rd",
    "sg:city":"Bullaburra",
    "sg:classifiers":[
        {
            "category":"Building & Trades",
            "subcategory":"Construction",
            "type":"Services"
        }
    ],
    "sg:phone":"+61 414 593 324",
    "sg:postcode":"2784",
    "sg:province":"NSW",
    "sg:tags":[
        "joiner",
        "carpenter"
    ],
    "wof:name":"Bullaburra Carpentry",
    "wof:placetype":"venue"
},
  "geometry": {"coordinates":[150.417114258,-33.7300033569],"type":"Point"}
}