{
  "type": "Feature",
  "properties": {
    "addr:full":"Cnr Princes Hwy & Government Rd Eden NSW 2551",
    "addr:postcode":"2551",
    "addr:street":"Cnr Princes Hwy & Government Rd",
    "iso:country":"AU",
    "sg:address":"Cnr Princes Hwy & Government Rd",
    "sg:city":"Eden",
    "sg:classifiers":[
        {
            "category":"Utilities",
            "type":"Services"
        }
    ],
    "sg:phone":"+61 2 6496 4411",
    "sg:postcode":"2551",
    "sg:province":"NSW",
    "sg:tags":[
        "equipment",
        "towing"
    ],
    "wof:name":"Aussie Recreational Vehicles",
    "wof:placetype":"venue"
},
  "geometry": {"coordinates":[149.90425109899999,-37.0629806519],"type":"Point"}
}