{
  "type": "Feature",
  "properties": {
    "addr:full":"1406 Princes Hwy Killarney VIC 3283",
    "addr:housenumber":"1406",
    "addr:postcode":"3283",
    "addr:street":"Princes Hwy",
    "iso:country":"AU",
    "sg:address":"1406 Princes Hwy",
    "sg:city":"Killarney",
    "sg:classifiers":[
        {
            "category":"Building & Trades",
            "subcategory":"Construction",
            "type":"Services"
        }
    ],
    "sg:phone":"+61 3 5568 7246",
    "sg:postcode":"3283",
    "sg:province":"VIC",
    "sg:tags":[
        "stonework",
        "stone",
        "mason"
    ],
    "wof:name":"C & J Moloney Stone Masonry",
    "wof:placetype":"venue"
},
  "geometry": {"coordinates":[142.29498290999999,-38.3470611572],"type":"Point"}
}