{
  "type": "Feature",
  "properties": {
    "addr:full":"Captain Cook Hwy Ellis Beach QLD 4879",
    "addr:postcode":"4879",
    "addr:street":"Captain Cook Hwy Ellis",
    "iso:country":"AU",
    "sg:address":"Captain Cook Hwy",
    "sg:city":"Ellis Beach",
    "sg:classifiers":[
        {
            "category":"Arena",
            "subcategory":"Sports Club",
            "type":"Entertainment"
        }
    ],
    "sg:phone":"+61 7 4055 3695",
    "sg:postcode":"4879",
    "sg:province":"QLD",
    "sg:tags":[
        "life",
        "surfing",
        "saving"
    ],
    "wof:name":"Ellis Beach Surf Lifesaving Club",
    "wof:placetype":"venue"
},
  "geometry": {"coordinates":[145.643066406,-16.722869873],"type":"Point"}
}