{
  "type": "Feature",
  "properties": {
    "addr:full":"22 Deloraine Drv Warrenup WA 6330",
    "addr:housenumber":"22",
    "addr:postcode":"6330",
    "addr:street":"Deloraine Drv",
    "iso:country":"AU",
    "sg:address":"22 Deloraine Drv",
    "sg:city":"Warrenup",
    "sg:classifiers":[
        {
            "category":"Building & Trades",
            "subcategory":"Plumbing",
            "type":"Services"
        }
    ],
    "sg:phone":"+61 418 954 212",
    "sg:postcode":"6330",
    "sg:province":"WA",
    "sg:tags":[
        "plumber",
        "gasfitters"
    ],
    "wof:name":"Whyte R A & C M",
    "wof:placetype":"venue"
},
  "geometry": {"coordinates":[117.877891541,-35.0000419617],"type":"Point"}
}