{
  "type": "Feature",
  "properties": {
    "iso:country":"AU",
    "sg:address":"7 Derwyn Cl",
    "sg:city":"Gosford North",
    "sg:classifiers":[
        {
            "category":"Building & Trades",
            "subcategory":"Construction",
            "type":"Services"
        }
    ],
    "sg:phone":"+61 2 4325 7092",
    "sg:postcode":"2250",
    "sg:province":"NSW",
    "sg:tags":[
        "contractor"
    ],
    "wof:name":"K Graf Building",
    "wof:placetype":"venue"
},
  "geometry": {"coordinates":[151.32798767099999,-33.4495162964],"type":"Point"}
}