{
  "type": "Feature",
  "properties": {
    "addr:full":"316 Mandalay Rd Airlie Beach QLD 4802",
    "addr:housenumber":"316",
    "addr:postcode":"4802",
    "addr:street":"Mandalay Rd",
    "iso:country":"AU",
    "sg:address":"316 Mandalay Rd",
    "sg:city":"Airlie Beach",
    "sg:classifiers":[
        {
            "category":"Real Estate",
            "subcategory":"Surveying",
            "type":"Services"
        }
    ],
    "sg:phone":"+61 7 4946 5760",
    "sg:postcode":"4802",
    "sg:province":"QLD",
    "sg:tags":[
        "surveyor",
        "marine",
        "cargo"
    ],
    "wof:name":"All Coast Marine Consultants",
    "wof:placetype":"venue"
},
  "geometry": {"coordinates":[148.73710632300001,-20.2565994263],"type":"Point"}
}