{
  "type": "Feature",
  "properties": {
    "addr:full":"274a Henley Beach Rd Underdale SA 5032",
    "addr:housenumber":"274a",
    "addr:postcode":"5032",
    "addr:street":"Henley Beach Rd",
    "iso:country":"AU",
    "sg:address":"274a Henley Beach Rd",
    "sg:city":"Underdale",
    "sg:classifiers":[
        {
            "category":"Health Services",
            "subcategory":"Dentist",
            "type":"Services"
        }
    ],
    "sg:phone":"+61 8 8352 8541",
    "sg:postcode":"5032",
    "sg:province":"SA",
    "sg:tags":[
        "technician",
        "dental"
    ],
    "wof:name":"Joe & Frank's Denture Clinics",
    "wof:placetype":"venue"
},
  "geometry": {"coordinates":[138.54747009299999,-34.9246902466],"type":"Point"}
}