{
  "type": "Feature",
  "properties": {
    "iso:country":"AU",
    "sg:address":"2 Watergum Pl",
    "sg:city":"Bogangar",
    "sg:classifiers":[
        {
            "category":"Professional",
            "subcategory":"Business Services",
            "type":"Services"
        }
    ],
    "sg:phone":"+61 407 624 610",
    "sg:postcode":"2488",
    "sg:province":"NSW",
    "sg:tags":[
        "drafting"
    ],
    "wof:name":"Tweed Coast Design Drafting",
    "wof:placetype":"venue"
},
  "geometry": {"coordinates":[153.564957,-28.341694],"type":"Point"}
}