{
  "type": "Feature",
  "properties": {
    "addr:full":"Shop 1, 13- 19 Hurtle Pde Mawson Lakes SA 5095",
    "addr:housenumber":"shop;13 19",
    "addr:postcode":"5095",
    "addr:street":"Hurtle Pde",
    "iso:country":"AU",
    "sg:address":"Shop 1, 13- 19 Hurtle Pde",
    "sg:city":"Mawson Lakes",
    "sg:classifiers":[
        {
            "category":"Professional",
            "subcategory":"Computer Services",
            "type":"Services"
        }
    ],
    "sg:phone":"+61 8 8359 0159",
    "sg:postcode":"5095",
    "sg:province":"SA",
    "sg:tags":[
        "repairs",
        "upgrade",
        "equipment"
    ],
    "wof:name":"Chase Computer Repairs",
    "wof:placetype":"venue"
},
  "geometry": {"coordinates":[138.616790772,-34.8082618713],"type":"Point"}
}