{
  "type": "Feature",
  "properties": {
    "addr:full":"Grand Secret La Charters Towers QLD 4820",
    "addr:postcode":"4820",
    "iso:country":"AU",
    "sg:address":"Grand Secret La",
    "sg:city":"Charters Towers",
    "sg:classifiers":[
        {
            "category":"Retail",
            "subcategory":"Auto Repair",
            "type":"Services"
        }
    ],
    "sg:phone":"+61 7 4787 3303",
    "sg:postcode":"4820",
    "sg:province":"QLD",
    "sg:tags":[
        "repairer",
        "motor",
        "engineer"
    ],
    "wof:name":"Ken Watson Mechanical Services",
    "wof:placetype":"venue"
},
  "geometry": {"coordinates":[146.26315299999999,-20.0774],"type":"Point"}
}