{
  "type": "Feature",
  "properties": {
    "addr:full":"19 Fullers Rd Glenhaven NSW 2156",
    "addr:housenumber":"19",
    "addr:postcode":"2156",
    "addr:street":"Fullers Rd",
    "iso:country":"AU",
    "sg:address":"19 Fullers Rd",
    "sg:city":"Glenhaven",
    "sg:classifiers":[
        {
            "category":"Professional",
            "subcategory":"Printing & Photocopies",
            "type":"Services"
        }
    ],
    "sg:phone":"+61 2 9634 5708",
    "sg:postcode":"2156",
    "sg:province":"NSW",
    "sg:tags":[
        "textile",
        "clothing"
    ],
    "wof:name":"A Sozuti Signs, Designs & Prints Pty Ltd - Hills District",
    "wof:placetype":"venue"
},
  "geometry": {"coordinates":[151.00848388700001,-33.7066726685],"type":"Point"}
}