{
  "type": "Feature",
  "properties": {
    "addr:full":"437 Gaffney St Pascoe Vale VIC 3044",
    "addr:housenumber":"437",
    "addr:postcode":"3044",
    "addr:street":"Gaffney St",
    "iso:country":"AU",
    "sg:address":"437 Gaffney St",
    "sg:city":"Pascoe Vale",
    "sg:classifiers":[
        {
            "category":"Real Estate",
            "subcategory":"Real Estate Agent",
            "type":"Services"
        }
    ],
    "sg:phone":"+61 3 9379 9700",
    "sg:postcode":"3044",
    "sg:province":"VIC",
    "wof:name":"City Link Real Estate Agency Pty Ltd",
    "wof:placetype":"venue"
},
  "geometry": {"coordinates":[144.927810669,-37.7304801941],"type":"Point"}
}