{
  "type": "Feature",
  "properties": {
    "addr:full":"4 Kythera Rd Emerald QLD 4720",
    "addr:housenumber":"4",
    "addr:postcode":"4720",
    "addr:street":"Kythera Rd",
    "iso:country":"AU",
    "sg:address":"4 Kythera Rd",
    "sg:city":"Emerald",
    "sg:classifiers":[
        {
            "category":"Building & Trades",
            "subcategory":"Construction",
            "type":"Services"
        }
    ],
    "sg:phone":"+61 7 4982 3454",
    "sg:postcode":"4720",
    "sg:province":"QLD",
    "sg:tags":[
        "concrete",
        "contractor"
    ],
    "wof:name":"Peterson F J & L M",
    "wof:placetype":"venue"
},
  "geometry": {"coordinates":[148.16606100000001,-23.54685],"type":"Point"}
}