{
  "type": "Feature",
  "properties": {
    "addr:full":"58 Sawpit St Mt Sheridan QLD 4868",
    "addr:housenumber":"58",
    "addr:postcode":"4868",
    "addr:street":"Sawpit St Mt",
    "iso:country":"AU",
    "sg:address":"58 Sawpit St",
    "sg:city":"Mt Sheridan",
    "sg:classifiers":[
        {
            "category":"Mining & Drilling",
            "type":"Manufacturing & Wholesale Goods"
        }
    ],
    "sg:phone":"+61 7 4036 0060",
    "sg:postcode":"4868",
    "sg:province":"QLD",
    "sg:tags":[
        "geologist"
    ],
    "wof:name":"Bremar Minerals Pty Ltd",
    "wof:placetype":"venue"
},
  "geometry": {"coordinates":[145.73687744099999,-16.9749011993],"type":"Point"}
}