{
  "type": "Feature",
  "properties": {
    "addr:full":"Lake Entrance Rd Blackbutt NSW 2529",
    "addr:postcode":"2529",
    "addr:street":"Entrance Rd",
    "iso:country":"AU",
    "sg:address":"Lake Entrance Rd",
    "sg:city":"Blackbutt",
    "sg:classifiers":[
        {
            "category":"Shopping",
            "subcategory":"Clothing, Apparel, & Fashions",
            "type":"Retail Goods"
        }
    ],
    "sg:phone":"+61 2 9482 1090",
    "sg:postcode":"2529",
    "sg:province":"NSW",
    "sg:tags":[
        "lingerie",
        "hosiery",
        "sleepwear"
    ],
    "wof:name":"Bras N Things",
    "wof:placetype":"venue"
},
  "geometry": {"coordinates":[150.861816406,-34.5697441101],"type":"Point"}
}