{
  "type": "Feature",
  "properties": {
    "addr:full":"4 Vaughan Crt Berri SA 5343",
    "addr:housenumber":"4",
    "addr:postcode":"5343",
    "addr:street":"Vaughan Crt",
    "iso:country":"AU",
    "sg:address":"4 Vaughan Crt",
    "sg:city":"Berri",
    "sg:classifiers":[
        {
            "category":"Professional",
            "subcategory":"Employment Agencies",
            "type":"Services"
        }
    ],
    "sg:phone":"+61 8 8582 4444",
    "sg:postcode":"5343",
    "sg:province":"SA",
    "sg:tags":[
        "hire",
        "labour",
        "contractor"
    ],
    "wof:name":"Select Industrial",
    "wof:placetype":"venue"
},
  "geometry": {"coordinates":[140.602615356,-34.2856864929],"type":"Point"}
}