{
  "type": "Feature",
  "properties": {
    "addr:full":"Shop 8a 20-30 Mt Warren Blv Mt Warren Park QLD 4207",
    "addr:housenumber":"shop 8a 20-30",
    "addr:postcode":"4207",
    "addr:street":"Mt Warren Blv Mt Warren",
    "iso:country":"AU",
    "sg:address":"Shop 8a 20-30 Mt Warren Blv",
    "sg:city":"Mt Warren Park",
    "sg:classifiers":[
        {
            "category":"Health Services",
            "subcategory":"Doctor",
            "type":"Services"
        }
    ],
    "sg:phone":"+61 7 3807 8588",
    "sg:postcode":"4207",
    "sg:province":"QLD",
    "sg:tags":[
        "medical",
        "practitioner"
    ],
    "wof:name":"Ting Nicholas",
    "wof:placetype":"venue"
},
  "geometry": {"coordinates":[153.19778442399999,-27.7239227295],"type":"Point"}
}