{
  "type": "Feature",
  "properties": {
    "addr:full":"967 Henry Lawson Drv Padstow NSW 2211",
    "addr:housenumber":"967",
    "addr:postcode":"2211",
    "addr:street":"Henry Lawson Drv",
    "iso:country":"AU",
    "sg:address":"967 Henry Lawson Drv",
    "sg:city":"Padstow",
    "sg:classifiers":[
        {
            "category":"Social Services",
            "subcategory":"Retirement Home",
            "type":"Services"
        }
    ],
    "sg:phone":"+61 2 9773 9646",
    "sg:postcode":"2211",
    "sg:province":"NSW",
    "sg:tags":[
        "village"
    ],
    "wof:name":"Eventide Homes Retirement Village",
    "wof:placetype":"venue"
},
  "geometry": {"coordinates":[151.03804,-33.965179],"type":"Point"}
}