{
  "type": "Feature",
  "properties": {
    "addr:full":"PO Box 25 Highbury SA 5089",
    "addr:postcode":"5089",
    "iso:country":"AU",
    "sg:address":"PO Box 25",
    "sg:city":"Highbury",
    "sg:classifiers":[
        {
            "category":"Building & Trades",
            "subcategory":"Landscaping Services",
            "type":"Services"
        }
    ],
    "sg:phone":"+61 417 887 845",
    "sg:postcode":"5089",
    "sg:province":"SA",
    "sg:tags":[
        "stump",
        "tree",
        "felling",
        "removal"
    ],
    "wof:name":"Pro-Lop Tree Service",
    "wof:placetype":"venue"
},
  "geometry": {"coordinates":[138.703582764,-34.8526000977],"type":"Point"}
}