{
  "type": "Feature",
  "properties": {
    "addr:full":"224 Brunker Rd Adamstown NSW 2289",
    "addr:housenumber":"224",
    "addr:postcode":"2289",
    "addr:street":"Brunker Rd",
    "iso:country":"AU",
    "sg:address":"224 Brunker Rd",
    "sg:city":"Adamstown",
    "sg:classifiers":[
        {
            "category":"Retail",
            "subcategory":"Repair Shop",
            "type":"Services"
        }
    ],
    "sg:phone":"+61 2 4952 3388",
    "sg:postcode":"2289",
    "sg:province":"NSW",
    "sg:tags":[
        "maintenance",
        "pool",
        "swimming"
    ],
    "wof:name":"Adamstown Pool Services",
    "wof:placetype":"venue"
},
  "geometry": {"coordinates":[151.72584533700001,-32.9337844849],"type":"Point"}
}