{
  "type": "Feature",
  "properties": {
    "iso:country":"AU",
    "sg:address":"The Centre 45 Victoria St",
    "sg:city":"Hobart",
    "sg:classifiers":[
        {
            "category":"Organizations",
            "subcategory":"Membership Organization",
            "type":"Services"
        }
    ],
    "sg:phone":"+61 3 6224 2060",
    "sg:postcode":"7000",
    "sg:province":"TAS",
    "sg:tags":[
        "support",
        "health",
        "organisation"
    ],
    "wof:name":"Cancer Self Help Support",
    "wof:placetype":"venue"
},
  "geometry": {"coordinates":[147.32530212399999,-42.8841323853],"type":"Point"}
}