{
  "type": "Feature",
  "properties": {
    "addr:full":"61 Hampshire Rd Glen Waverley VIC 3150",
    "addr:housenumber":"61",
    "addr:postcode":"3150",
    "addr:street":"Hampshire Rd",
    "iso:country":"AU",
    "sg:address":"61 Hampshire Rd",
    "sg:city":"Glen Waverley",
    "sg:classifiers":[
        {
            "category":"Professional",
            "subcategory":"Art Services",
            "type":"Services"
        }
    ],
    "sg:phone":"+61 3 9561 6431",
    "sg:postcode":"3150",
    "sg:province":"VIC",
    "sg:tags":[
        "decorator",
        "painter"
    ],
    "wof:name":"Hampshire Painting Tiling & Restoring",
    "wof:placetype":"venue"
},
  "geometry": {"coordinates":[145.14918518100001,-37.9012451172],"type":"Point"}
}