{
  "type": "Feature",
  "properties": {
    "addr:full":"11 Webb St Narre Warren VIC 3805",
    "addr:housenumber":"11",
    "addr:postcode":"3805",
    "addr:street":"Webb St",
    "iso:country":"AU",
    "sg:address":"11 Webb St",
    "sg:city":"Narre Warren",
    "sg:classifiers":[
        {
            "category":"Fast Food",
            "type":"Food & Drink"
        }
    ],
    "sg:phone":"+61 3 9704 8469",
    "sg:postcode":"3805",
    "sg:province":"VIC",
    "sg:tags":[
        "away",
        "take"
    ],
    "wof:name":"Narre Warren Pizza",
    "wof:placetype":"venue"
},
  "geometry": {"coordinates":[145.30354299999999,-38.025974],"type":"Point"}
}