{
  "type": "Feature",
  "properties": {
    "addr:full":"11/ 29 Barry St Bayswater VIC 3153",
    "addr:housenumber":"11 / 29",
    "addr:postcode":"3153",
    "addr:street":"Barry St",
    "iso:country":"AU",
    "sg:address":"11/ 29 Barry St",
    "sg:city":"Bayswater",
    "sg:classifiers":[
        {
            "category":"Wholesale",
            "subcategory":"Electrical",
            "type":"Manufacturing & Wholesale Goods"
        }
    ],
    "sg:phone":"+61 3 9720 4628",
    "sg:postcode":"3153",
    "sg:province":"VIC",
    "sg:tags":[
        "control",
        "equipment",
        "switch"
    ],
    "wof:name":"MDC Electronics Australia Pty Ltd",
    "wof:placetype":"venue"
},
  "geometry": {"coordinates":[145.27610778799999,-37.8469543457],"type":"Point"}
}