{
  "type": "Feature",
  "properties": {
    "addr:full":"1 Diana St Clarendon Vale TAS 7019",
    "addr:housenumber":"1",
    "addr:postcode":"7019",
    "addr:street":"Diana St",
    "iso:country":"AU",
    "sg:address":"1 Diana St",
    "sg:city":"Clarendon Vale",
    "sg:classifiers":[
        {
            "category":"Building & Trades",
            "subcategory":"Construction",
            "type":"Services"
        }
    ],
    "sg:phone":"+61 437 989 270",
    "sg:postcode":"7019",
    "sg:province":"TAS",
    "sg:tags":[
        "welding"
    ],
    "wof:name":"Brendan Goss Welding",
    "wof:placetype":"venue"
},
  "geometry": {"coordinates":[147.446212769,-42.8865318298],"type":"Point"}
}