{
  "type": "Feature",
  "properties": {
    "iso:country":"AU",
    "sg:address":"36 Beryl St",
    "sg:city":"Tweed Heads",
    "sg:classifiers":[
        {
            "category":"Health Services",
            "subcategory":"Health Practitioner",
            "type":"Services"
        }
    ],
    "sg:phone":"+61 7 5599 2220",
    "sg:postcode":"2485",
    "sg:province":"NSW",
    "sg:tags":[
        "psychologist"
    ],
    "wof:name":"Solstice Mind Matters",
    "wof:placetype":"venue"
},
  "geometry": {"coordinates":[153.54107665999999,-28.1749343872],"type":"Point"}
}