{
  "type": "Feature",
  "properties": {
    "addr:full":"368 King William St Adelaide SA 5000",
    "addr:housenumber":"368",
    "addr:postcode":"5000",
    "addr:street":"King William St",
    "iso:country":"AU",
    "sg:address":"368 King William St",
    "sg:city":"Adelaide",
    "sg:classifiers":[
        {
            "category":"Education",
            "subcategory":"School",
            "type":"Public Place"
        }
    ],
    "sg:phone":"+61 8 8212 4342",
    "sg:postcode":"5000",
    "sg:province":"SA",
    "sg:tags":[
        "co-educational"
    ],
    "sg:website":"http://www.muirden.sa.edu.au",
    "wof:name":"Muirden College Ltd",
    "wof:placetype":"venue"
},
  "geometry": {"coordinates":[138.600463867,-34.931602478],"type":"Point"}
}