{
  "type": "Feature",
  "properties": {
    "addr:full":"24 Tooloon St Coonamble NSW 2829",
    "addr:housenumber":"24",
    "addr:postcode":"2829",
    "addr:street":"Tooloon St",
    "iso:country":"AU",
    "sg:address":"24 Tooloon St",
    "sg:city":"Coonamble",
    "sg:classifiers":[
        {
            "category":"Travel",
            "subcategory":"Hotels & Motels",
            "type":"Entertainment"
        }
    ],
    "sg:phone":"+61 2 6822 1663",
    "sg:postcode":"2829",
    "sg:province":"NSW",
    "sg:tags":[
        "accommodation"
    ],
    "wof:name":"Clubhouse Hotel",
    "wof:placetype":"venue"
},
  "geometry": {"coordinates":[148.389892578,-30.9523868561],"type":"Point"}
}