{
  "type": "Feature",
  "properties": {
    "addr:full":"163a Parramatta Rd Annandale NSW 2038",
    "addr:housenumber":"163a",
    "addr:postcode":"2038",
    "addr:street":"Parramatta Rd",
    "iso:country":"AU",
    "sg:address":"163a Parramatta Rd",
    "sg:city":"Annandale",
    "sg:classifiers":[
        {
            "category":"Education",
            "subcategory":"Dance Studio",
            "type":"Public Place"
        }
    ],
    "sg:phone":"+61 2 9560 8540",
    "sg:postcode":"2038",
    "sg:province":"NSW",
    "sg:tags":[
        "venue",
        "tuition"
    ],
    "wof:name":"El Paso Latin American Dance Studio",
    "wof:placetype":"venue"
},
  "geometry": {"coordinates":[151.16554260300001,-33.8879623413],"type":"Point"}
}