{
  "type": "Feature",
  "properties": {
    "addr:full":"98 Fleming St Islington NSW 2296",
    "addr:housenumber":"98",
    "addr:postcode":"2296",
    "addr:street":"Fleming St",
    "iso:country":"AU",
    "sg:address":"98 Fleming St",
    "sg:city":"Islington",
    "sg:classifiers":[
        {
            "category":"Shopping",
            "subcategory":"Gifts & Souvenirs",
            "type":"Retail Goods"
        }
    ],
    "sg:phone":"+61 2 4961 6176",
    "sg:postcode":"2296",
    "sg:province":"NSW",
    "sg:tags":[
        "shop",
        "supply"
    ],
    "wof:name":"Crafty Thoughts",
    "wof:placetype":"venue"
},
  "geometry": {"coordinates":[151.75152587900001,-32.9172325134],"type":"Point"}
}