{
  "type": "Feature",
  "properties": {
    "iso:country":"AU",
    "sg:address":"17 Roylston St",
    "sg:city":"Paddington",
    "sg:classifiers":[
        {
            "category":"Professional",
            "subcategory":"Art Services",
            "type":"Services"
        }
    ],
    "sg:phone":"+61 2 9331 8959",
    "sg:postcode":"2021",
    "sg:province":"NSW",
    "sg:tags":[
        "graphic",
        "designer"
    ],
    "wof:name":"Caper Creative",
    "wof:placetype":"venue"
},
  "geometry": {"coordinates":[151.23289489699999,-33.8816490173],"type":"Point"}
}