{
  "type": "Feature",
  "properties": {
    "iso:country":"AU",
    "sg:address":"34 Sungold Ave",
    "sg:city":"Southport",
    "sg:classifiers":[
        {
            "category":"Building & Trades",
            "subcategory":"Plumbing",
            "type":"Services"
        }
    ],
    "sg:phone":"+61 7 5532 4281",
    "sg:postcode":"4215",
    "sg:province":"QLD",
    "sg:tags":[
        "plumber",
        "gasfitters"
    ],
    "wof:name":"Koch A P",
    "wof:placetype":"venue"
},
  "geometry": {"coordinates":[153.39231872600001,-27.9655075073],"type":"Point"}
}