{
  "type": "Feature",
  "properties": {
    "iso:country":"AU",
    "sg:address":"5 O'Connor Crt",
    "sg:city":"Gepps Cross",
    "sg:classifiers":[
        {
            "category":"Home & Garden",
            "subcategory":"Household Appliances",
            "type":"Retail Goods"
        }
    ],
    "sg:phone":"+61 8 8349 5959",
    "sg:postcode":"5094",
    "sg:province":"SA",
    "sg:tags":[
        "heating",
        "system"
    ],
    "wof:name":"Polyaire Pty Ltd",
    "wof:placetype":"venue"
},
  "geometry": {"coordinates":[138.592285156,-34.8433914185],"type":"Point"}
}