{
  "type": "Feature",
  "properties": {
    "addr:full":"54 Andrew Ave Tarragindi QLD 4121",
    "addr:housenumber":"54",
    "addr:postcode":"4121",
    "addr:street":"Andrew Ave",
    "iso:country":"AU",
    "sg:address":"54 Andrew Ave",
    "sg:city":"Tarragindi",
    "sg:classifiers":[
        {
            "category":"Industrial Area",
            "type":"Public Place"
        }
    ],
    "sg:phone":"+61 7 3392 9088",
    "sg:postcode":"4121",
    "sg:province":"QLD",
    "sg:tags":[
        "protective",
        "clothing"
    ],
    "wof:name":"Defiant Pty Ltd",
    "wof:placetype":"venue"
},
  "geometry": {"coordinates":[153.039520264,-27.5257015228],"type":"Point"}
}