{
  "type": "Feature",
  "properties": {
    "addr:full":"U1/ 143 Marrickville Rd Marrickville NSW 2204",
    "addr:housenumber":"143",
    "addr:postcode":"2204",
    "addr:street":"U1 /;Marrickville Rd",
    "iso:country":"AU",
    "sg:address":"U1/ 143 Marrickville Rd",
    "sg:city":"Marrickville",
    "sg:classifiers":[
        {
            "category":"Personal",
            "subcategory":"Massage",
            "type":"Services"
        }
    ],
    "sg:phone":"+61 2 9569 9213",
    "sg:postcode":"2204",
    "sg:province":"NSW",
    "sg:tags":[
        "therapy"
    ],
    "wof:name":"Yukada Service",
    "wof:placetype":"venue"
},
  "geometry": {"coordinates":[151.159592,-33.911892],"type":"Point"}
}