{
  "type": "Feature",
  "properties": {
    "addr:full":"246 Crete Rd Robinvale VIC 3549",
    "addr:housenumber":"246",
    "addr:postcode":"3549",
    "addr:street":"Crete Rd",
    "iso:country":"AU",
    "sg:address":"246 Crete Rd",
    "sg:city":"Robinvale",
    "sg:classifiers":[
        {
            "category":"Freight",
            "type":"Transportation"
        }
    ],
    "sg:phone":"+61 3 5026 4800",
    "sg:postcode":"3549",
    "sg:province":"VIC",
    "sg:tags":[
        "transport",
        "refrigerated"
    ],
    "wof:name":"Leslie Refrigerated Transport",
    "wof:placetype":"venue"
},
  "geometry": {"coordinates":[142.767669678,-34.6226081848],"type":"Point"}
}