{
  "type": "Feature",
  "properties": {
    "addr:full":"Thorpe St Moranbah QLD 4744",
    "addr:postcode":"4744",
    "addr:street":"St",
    "iso:country":"AU",
    "sg:address":"Thorpe St",
    "sg:city":"Moranbah",
    "sg:classifiers":[
        {
            "category":"Retail",
            "subcategory":"Storage",
            "type":"Services"
        }
    ],
    "sg:phone":"+61 7 4941 9897",
    "sg:postcode":"4744",
    "sg:province":"QLD",
    "wof:name":"Extra Storage",
    "wof:placetype":"venue"
},
  "geometry": {"coordinates":[148.09439086899999,-22.1004600525],"type":"Point"}
}