{
  "type": "Feature",
  "properties": {
    "addr:full":"PO Box 124 Calliope QLD 4680",
    "addr:postcode":"4680",
    "iso:country":"AU",
    "sg:address":"PO Box 124",
    "sg:city":"Calliope",
    "sg:classifiers":[
        {
            "category":"Real Estate",
            "subcategory":"Real Estate Agent",
            "type":"Services"
        }
    ],
    "sg:phone":"+61 7 4975 6329",
    "sg:postcode":"4680",
    "sg:province":"QLD",
    "sg:tags":[
        "handyman's",
        "equipment",
        "hire",
        "builders",
        "contractor"
    ],
    "wof:name":"JTM Industries",
    "wof:placetype":"venue"
},
  "geometry": {"coordinates":[151.21209716800001,-23.9871997833],"type":"Point"}
}