{
  "type": "Feature",
  "properties": {
    "iso:country":"AU",
    "sg:address":"18 Cantrill Ave",
    "sg:city":"Maroubra",
    "sg:classifiers":[
        {
            "category":"Retail",
            "subcategory":"Auto Rental",
            "type":"Services"
        }
    ],
    "sg:phone":"+61 1300 852 252",
    "sg:postcode":"2035",
    "sg:province":"NSW",
    "sg:tags":[
        "chauffeur",
        "car",
        "hire",
        "driven",
        "limousine"
    ],
    "wof:name":"A All Limousine World",
    "wof:placetype":"venue"
},
  "geometry": {"coordinates":[151.25032043499999,-33.9382133484],"type":"Point"}
}