{
  "type": "Feature",
  "properties": {
    "addr:full":"26 Orchard St Toowong QLD 4066",
    "addr:housenumber":"26",
    "addr:postcode":"4066",
    "addr:street":"Orchard St",
    "iso:country":"AU",
    "sg:address":"26 Orchard St",
    "sg:city":"Toowong",
    "sg:classifiers":[
        {
            "category":"Shopping",
            "subcategory":"Party Supplies",
            "type":"Retail Goods"
        }
    ],
    "sg:phone":"+61 7 3876 0200",
    "sg:postcode":"4066",
    "sg:province":"QLD",
    "wof:name":"Balloons Galore",
    "wof:placetype":"venue"
},
  "geometry": {"coordinates":[152.97877502399999,-27.4848880768],"type":"Point"}
}