{
  "type": "Feature",
  "properties": {
    "addr:full":"229 Woodward Rd Golden Square VIC 3555",
    "addr:housenumber":"229",
    "addr:postcode":"3555",
    "addr:street":"Woodward Rd",
    "iso:country":"AU",
    "sg:address":"229 Woodward Rd",
    "sg:city":"Golden Square",
    "sg:classifiers":[
        {
            "category":"Social Services",
            "subcategory":"Retirement Home",
            "type":"Services"
        }
    ],
    "sg:phone":"+61 3 5444 4810",
    "sg:postcode":"3555",
    "sg:province":"VIC",
    "sg:tags":[
        "environmental",
        "consultant",
        "pollution"
    ],
    "wof:name":"Bowler Geotechnical Pty Ltd",
    "wof:placetype":"venue"
},
  "geometry": {"coordinates":[144.265548706,-36.7803993225],"type":"Point"}
}