{
  "type": "Feature",
  "properties": {
    "iso:country":"AU",
    "sg:address":"Sturt Ave",
    "sg:city":"Kapooka",
    "sg:classifiers":[
        {
            "category":"Education",
            "subcategory":"Kindergarten",
            "type":"Public Place"
        }
    ],
    "sg:phone":"+61 2 6931 2722",
    "sg:postcode":"2661",
    "sg:province":"NSW",
    "sg:tags":[
        "pre-schools"
    ],
    "wof:name":"Kapooka Early Childhood Centre Inc",
    "wof:placetype":"venue"
},
  "geometry": {"coordinates":[147.370437622,-35.1057472229],"type":"Point"}
}