{
  "type": "Feature",
  "properties": {
    "addr:full":"58 Baxter St Fortitude Valley QLD 4006",
    "addr:housenumber":"58",
    "addr:postcode":"4006",
    "addr:street":"Baxter St",
    "iso:country":"AU",
    "sg:address":"58 Baxter St",
    "sg:city":"Fortitude Valley",
    "sg:classifiers":[
        {
            "category":"Organizations",
            "subcategory":"Professional Association",
            "type":"Services"
        }
    ],
    "sg:phone":"+61 7 3634 8200",
    "sg:postcode":"4006",
    "sg:province":"QLD",
    "sg:tags":[
        "web",
        "internet"
    ],
    "wof:name":"JSA Digital",
    "wof:placetype":"venue"
},
  "geometry": {"coordinates":[153.031494141,-27.4539299011],"type":"Point"}
}