{
  "type": "Feature",
  "properties": {
    "iso:country":"AU",
    "sg:address":"19 Castlewood Drv",
    "sg:city":"Castle Hill",
    "sg:classifiers":[
        {
            "category":"Personal",
            "subcategory":"Beauty Salon",
            "type":"Services"
        }
    ],
    "sg:phone":"+61 418 473 086",
    "sg:postcode":"2154",
    "sg:province":"NSW",
    "wof:name":"Heavenly Bliss Beauty Therapy",
    "wof:placetype":"venue"
},
  "geometry": {"coordinates":[151.01849365199999,-33.7378845215],"type":"Point"}
}