{
  "type": "Feature",
  "properties": {
    "iso:country":"AU",
    "sg:address":"11th Floor 155 Queen St",
    "sg:city":"Melbourne",
    "sg:classifiers":[
        {
            "category":"Professional",
            "subcategory":"Computer Services",
            "type":"Services"
        }
    ],
    "sg:phone":"+61 3 9604 3333",
    "sg:postcode":"3000",
    "sg:province":"VIC",
    "sg:tags":[
        "package",
        "software"
    ],
    "wof:name":"Sterling Software (Australia) Pty Ltd",
    "wof:placetype":"venue"
},
  "geometry": {"coordinates":[144.960494995,-37.8149337769],"type":"Point"}
}