{
  "type": "Feature",
  "properties": {
    "iso:country":"AU",
    "sg:address":"173 Byrne St",
    "sg:city":"Mareeba",
    "sg:classifiers":[
        {
            "category":"Food & Beverages",
            "subcategory":"Bakery",
            "type":"Retail Goods"
        }
    ],
    "sg:phone":"+61 7 4092 7900",
    "sg:postcode":"4880",
    "sg:province":"QLD",
    "sg:tags":[
        "baker"
    ],
    "wof:name":"Brumbys Bakeries",
    "wof:placetype":"venue"
},
  "geometry": {"coordinates":[145.420166016,-16.9858970642],"type":"Point"}
}