{
  "type": "Feature",
  "properties": {
    "addr:full":"Unit 2 115 Howe St Osborne Park WA 6017",
    "addr:housenumber":"115",
    "addr:postcode":"6017",
    "addr:street":"Howe St",
    "iso:country":"AU",
    "sg:address":"Unit 2 115 Howe St",
    "sg:city":"Osborne Park",
    "sg:classifiers":[
        {
            "category":"Professional",
            "subcategory":"Engineering",
            "type":"Services"
        }
    ],
    "sg:phone":"+61 8 9242 3616",
    "sg:postcode":"6017",
    "sg:province":"WA",
    "sg:tags":[
        "electronic",
        "engineer"
    ],
    "wof:name":"Techtronic Services",
    "wof:placetype":"venue"
},
  "geometry": {"coordinates":[115.815948486,-31.9092617035],"type":"Point"}
}