{
  "type": "Feature",
  "properties": {
    "iso:country":"AU",
    "sg:address":"91 - 93 Belmont Ave",
    "sg:city":"Belmont",
    "sg:classifiers":[
        {
            "category":"Home & Garden",
            "subcategory":"Garden Supply",
            "type":"Retail Goods"
        }
    ],
    "sg:phone":"+61 8 9477 4181",
    "sg:postcode":"6104",
    "sg:province":"WA",
    "sg:tags":[
        "equipment"
    ],
    "wof:name":"City Farmers",
    "wof:placetype":"venue"
},
  "geometry": {"coordinates":[115.924919128,-31.9582576752],"type":"Point"}
}