{
  "type": "Feature",
  "properties": {
    "iso:country":"AU",
    "sg:address":"L1, 70 Molesworth St",
    "sg:city":"Lismore",
    "sg:classifiers":[
        {
            "category":"Health Services",
            "subcategory":"Chiropractor",
            "type":"Services"
        }
    ],
    "sg:phone":"+61 2 6622 5415",
    "sg:postcode":"2480",
    "sg:province":"NSW",
    "wof:name":"Essence Network Care",
    "wof:placetype":"venue"
},
  "geometry": {"coordinates":[153.27691650400001,-28.8074474335],"type":"Point"}
}