{
  "type": "Feature",
  "properties": {
    "iso:country":"AU",
    "sg:address":"Shp 8/ 47 Maple St",
    "sg:city":"Maleny",
    "sg:classifiers":[
        {
            "category":"Personal",
            "subcategory":"Beauty Salon",
            "type":"Services"
        }
    ],
    "sg:phone":"+61 7 5494 3310",
    "sg:postcode":"4552",
    "sg:province":"QLD",
    "sg:tags":[
        "hairdresser"
    ],
    "wof:name":"Maleny Hair Art & Beauty",
    "wof:placetype":"venue"
},
  "geometry": {"coordinates":[152.84974670400001,-26.7583217621],"type":"Point"}
}