{
  "type": "Feature",
  "properties": {
    "addr:full":"11 Bentley St Stoneville WA 6081",
    "addr:housenumber":"11",
    "addr:postcode":"6081",
    "addr:street":"Bentley St",
    "iso:country":"AU",
    "sg:address":"11 Bentley St",
    "sg:city":"Stoneville",
    "sg:classifiers":[
        {
            "category":"Retail",
            "subcategory":"Storage",
            "type":"Services"
        }
    ],
    "sg:phone":"+61 8 9295 6037",
    "sg:postcode":"6081",
    "sg:province":"WA",
    "sg:tags":[
        "removal",
        "furniture"
    ],
    "sg:website":"http://www.themovingman.com.au",
    "wof:name":"The Moving Man",
    "wof:placetype":"venue"
},
  "geometry": {"coordinates":[116.109413147,-31.896270752],"type":"Point"}
}