{
  "type": "Feature",
  "properties": {
    "addr:full":"39 Carronvale Rd Mooroolbark VIC 3138",
    "addr:housenumber":"39",
    "addr:postcode":"3138",
    "addr:street":"Carronvale Rd",
    "iso:country":"AU",
    "sg:address":"39 Carronvale Rd",
    "sg:city":"Mooroolbark",
    "sg:classifiers":[
        {
            "category":"Government",
            "subcategory":"Fire Station",
            "type":"Public Place"
        }
    ],
    "sg:phone":"+61 3 9727 5855",
    "sg:postcode":"3138",
    "sg:province":"VIC",
    "sg:tags":[
        "equipment",
        "protection",
        "consultant"
    ],
    "wof:name":"Pro-Tec Fire Alarms",
    "wof:placetype":"venue"
},
  "geometry": {"coordinates":[145.32818603499999,-37.7825546265],"type":"Point"}
}