{
  "type": "Feature",
  "properties": {
    "addr:full":"25 Pacific Hwy Grafton NSW 2460",
    "addr:housenumber":"25",
    "addr:postcode":"2460",
    "addr:street":"Pacific Hwy",
    "iso:country":"AU",
    "sg:address":"25 Pacific Hwy",
    "sg:city":"Grafton",
    "sg:classifiers":[
        {
            "category":"Travel",
            "subcategory":"Hotels & Motels",
            "type":"Entertainment"
        }
    ],
    "sg:phone":"+61 2 6642 1588",
    "sg:postcode":"2460",
    "sg:province":"NSW",
    "wof:name":"Hi Way Motel",
    "wof:placetype":"venue"
},
  "geometry": {"coordinates":[152.95904540999999,-29.6988945007],"type":"Point"}
}