{
  "type": "Feature",
  "properties": {
    "addr:full":"265 Pennant Hills Rd Thornleigh NSW 2120",
    "addr:housenumber":"265",
    "addr:postcode":"2120",
    "addr:street":"Pennant Hills Rd",
    "iso:country":"AU",
    "sg:address":"265 Pennant Hills Rd",
    "sg:city":"Thornleigh",
    "sg:classifiers":[
        {
            "category":"Professional",
            "subcategory":"Accounting & Tax Preparation",
            "type":"Services"
        }
    ],
    "sg:phone":"+61 13 23 25",
    "sg:postcode":"2120",
    "sg:province":"NSW",
    "sg:tags":[
        "consultant",
        "taxation"
    ],
    "wof:name":"H & R Block",
    "wof:placetype":"venue"
},
  "geometry": {"coordinates":[151.0806427,-33.7314300537],"type":"Point"}
}