{
  "type": "Feature",
  "properties": {
    "iso:country":"AU",
    "sg:address":"5a Cann St",
    "sg:city":"Guildford",
    "sg:classifiers":[
        {
            "category":"Shopping",
            "subcategory":"Mobile Phones",
            "type":"Retail Goods"
        }
    ],
    "sg:phone":"+61 2 9632 2837",
    "sg:postcode":"2161",
    "sg:province":"NSW",
    "sg:tags":[
        "wholesaler",
        "mfrs",
        "electrical",
        "switchboard"
    ],
    "wof:name":"Inca Control & Engineering Pty Ltd",
    "wof:placetype":"venue"
},
  "geometry": {"coordinates":[150.97947692899999,-33.859413147],"type":"Point"}
}