{
  "type": "Feature",
  "properties": {
    "addr:full":"16 Elwers St Watsonia VIC 3087",
    "addr:housenumber":"16",
    "addr:postcode":"3087",
    "addr:street":"Elwers St",
    "iso:country":"AU",
    "sg:address":"16 Elwers St",
    "sg:city":"Watsonia",
    "sg:classifiers":[
        {
            "category":"Professional",
            "subcategory":"Computer Services",
            "type":"Services"
        }
    ],
    "sg:phone":"+61 418 563 354",
    "sg:postcode":"3087",
    "sg:province":"VIC",
    "sg:tags":[
        "package",
        "software"
    ],
    "wof:name":"Cowell & Associates Pty Ltd",
    "wof:placetype":"venue"
},
  "geometry": {"coordinates":[145.08570861800001,-37.6995925903],"type":"Point"}
}