{
  "type": "Feature",
  "properties": {
    "addr:full":"373 Manns Rd Gosford West NSW 2250",
    "addr:housenumber":"373",
    "addr:postcode":"2250",
    "addr:street":"Manns Rd",
    "iso:country":"AU",
    "sg:address":"373 Manns Rd",
    "sg:city":"Gosford West",
    "sg:classifiers":[
        {
            "category":"Coffee & Tea",
            "type":"Food & Drink"
        }
    ],
    "sg:phone":"+61 2 4324 2867",
    "sg:postcode":"2250",
    "sg:province":"NSW",
    "sg:tags":[
        "kayak",
        "canoe"
    ],
    "wof:name":"Southern Adventures",
    "wof:placetype":"venue"
},
  "geometry": {"coordinates":[151.31932067899999,-33.4247665405],"type":"Point"}
}