{
  "type": "Feature",
  "properties": {
    "iso:country":"AU",
    "sg:address":"47 Second Ave",
    "sg:city":"Toukley",
    "sg:classifiers":[
        {
            "category":"Building & Trades",
            "subcategory":"Construction",
            "type":"Services"
        }
    ],
    "sg:phone":"+61 417 254 334",
    "sg:postcode":"2263",
    "sg:province":"NSW",
    "sg:tags":[
        "plasterboard",
        "plasterer",
        "fixer"
    ],
    "wof:name":"Layhaze Pty Ltd",
    "wof:placetype":"venue"
},
  "geometry": {"coordinates":[151.549026,-33.259995],"type":"Point"}
}