{
  "type": "Feature",
  "properties": {
    "addr:full":"PO Box 125 Nuriootpa SA 5355",
    "addr:postcode":"5355",
    "iso:country":"AU",
    "sg:address":"PO Box 125",
    "sg:city":"Nuriootpa",
    "sg:classifiers":[
        {
            "category":"Utilities",
            "subcategory":"Water",
            "type":"Services"
        }
    ],
    "sg:phone":"+61 8 8562 3655",
    "sg:postcode":"5355",
    "sg:province":"SA",
    "sg:tags":[
        "hot",
        "system"
    ],
    "wof:name":"Perry Trade Services",
    "wof:placetype":"venue"
},
  "geometry": {"coordinates":[138.98793029800001,-34.4606895447],"type":"Point"}
}