{
  "type": "Feature",
  "properties": {
    "addr:full":"52 Lightfoot St Cessnock NSW 2325",
    "addr:housenumber":"52",
    "addr:postcode":"2325",
    "addr:street":"Lightfoot St",
    "iso:country":"AU",
    "sg:address":"52 Lightfoot St",
    "sg:city":"Cessnock",
    "sg:classifiers":[
        {
            "category":"Professional",
            "subcategory":"Printing & Photocopies",
            "type":"Services"
        }
    ],
    "sg:phone":"+61 2 4990 2198",
    "sg:postcode":"2325",
    "sg:province":"NSW",
    "sg:tags":[
        "embroidery"
    ],
    "wof:name":"Hel's Bells Clothing & Embroidery",
    "wof:placetype":"venue"
},
  "geometry": {"coordinates":[151.35760498100001,-32.8248023987],"type":"Point"}
}