{
  "type": "Feature",
  "properties": {
    "addr:full":"22 Harman Rd Sorrento WA 6020",
    "addr:housenumber":"22",
    "addr:postcode":"6020",
    "addr:street":"Harman Rd",
    "iso:country":"AU",
    "sg:address":"22 Harman Rd",
    "sg:city":"Sorrento",
    "sg:classifiers":[
        {
            "category":"Health Services",
            "subcategory":"Dentist",
            "type":"Services"
        }
    ],
    "sg:phone":"+61 8 9341 7577",
    "sg:postcode":"6020",
    "sg:province":"WA",
    "wof:name":"Moran John H",
    "wof:placetype":"venue"
},
  "geometry": {"coordinates":[115.7579422,-31.8222045898],"type":"Point"}
}