{
  "type": "Feature",
  "properties": {
    "addr:full":"29b Giblett Rd Manjimup WA 6258",
    "addr:housenumber":"29b",
    "addr:postcode":"6258",
    "addr:street":"Giblett Rd",
    "iso:country":"AU",
    "sg:address":"29b Giblett Rd",
    "sg:city":"Manjimup",
    "sg:classifiers":[
        {
            "category":"Banks & Credit Unions",
            "subcategory":"Investment Brokerage",
            "type":"Services"
        }
    ],
    "sg:phone":"+61 8 9771 1400",
    "sg:postcode":"6258",
    "sg:province":"WA",
    "sg:tags":[
        "management",
        "property"
    ],
    "wof:name":"Professionals Real Estate Group The",
    "wof:placetype":"venue"
},
  "geometry": {"coordinates":[116.145759583,-34.2423248291],"type":"Point"}
}