{
  "type": "Feature",
  "properties": {
    "addr:full":"65 Canada St Lake Cargelligo NSW 2672",
    "addr:housenumber":"65",
    "addr:postcode":"2672",
    "addr:street":"Canada St",
    "iso:country":"AU",
    "sg:address":"65 Canada St",
    "sg:city":"Lake Cargelligo",
    "sg:classifiers":[
        {
            "category":"Education",
            "subcategory":"School",
            "type":"Public Place"
        }
    ],
    "sg:phone":"+61 2 6898 1008",
    "sg:postcode":"2672",
    "sg:province":"NSW",
    "sg:tags":[
        "state",
        "-",
        "nsw"
    ],
    "wof:name":"Lake Cargelligo Central School",
    "wof:placetype":"venue"
},
  "geometry": {"coordinates":[146.37405395499999,-33.2989044189],"type":"Point"}
}