{
  "type": "Feature",
  "properties": {
    "addr:full":"101 McIntyre Rd Para Hills West SA 5096",
    "addr:housenumber":"101",
    "addr:postcode":"5096",
    "addr:street":"Mcintyre Rd Para Hills West",
    "iso:country":"AU",
    "sg:address":"101 McIntyre Rd",
    "sg:city":"Para Hills West",
    "sg:classifiers":[
        {
            "category":"Professional",
            "subcategory":"Engineering",
            "type":"Services"
        }
    ],
    "sg:phone":"+61 8 8445 8050",
    "sg:postcode":"5096",
    "sg:province":"SA",
    "sg:tags":[
        "engineer"
    ],
    "wof:name":"Hy-Tip Industries Pty Ltd",
    "wof:placetype":"venue"
},
  "geometry": {"coordinates":[138.655395508,-34.7971115112],"type":"Point"}
}