{
  "type": "Feature",
  "properties": {
    "addr:full":"Station St Oakleigh VIC 3166",
    "addr:postcode":"3166",
    "addr:street":"Station St",
    "iso:country":"AU",
    "sg:address":"Station St",
    "sg:city":"Oakleigh",
    "sg:classifiers":[
        {
            "category":"Food & Beverages",
            "subcategory":"Bakery",
            "type":"Retail Goods"
        }
    ],
    "sg:phone":"+61 3 9563 1280",
    "sg:postcode":"3166",
    "sg:province":"VIC",
    "sg:tags":[
        "cake",
        "shop",
        "pastry"
    ],
    "wof:name":"Sun Bakery",
    "wof:placetype":"venue"
},
  "geometry": {"coordinates":[145.088546753,-37.8996620178],"type":"Point"}
}