{
  "type": "Feature",
  "properties": {
    "iso:country":"AU",
    "sg:address":"9 Albert Ave",
    "sg:city":"Strathfieldsaye",
    "sg:classifiers":[
        {
            "category":"Professional",
            "subcategory":"Computer Services",
            "type":"Services"
        }
    ],
    "sg:phone":"+61 417 591 380",
    "sg:postcode":"3539",
    "sg:province":"VIC",
    "sg:tags":[
        "package",
        "software"
    ],
    "wof:name":"Just Turn Key Solutions",
    "wof:placetype":"venue"
},
  "geometry": {"coordinates":[144.318314,-36.766399],"type":"Point"}
}