{
  "type": "Feature",
  "properties": {
    "addr:full":"78 North West Coastal Hwy Geraldton WA 6530",
    "addr:housenumber":"78",
    "addr:postcode":"6530",
    "addr:street":"North West Coastal Hwy",
    "iso:country":"AU",
    "sg:address":"78 North West Coastal Hwy",
    "sg:city":"Geraldton",
    "sg:classifiers":[
        {
            "category":"Manufacturing",
            "subcategory":"Motor Vehicles & Parts",
            "type":"Manufacturing & Wholesale Goods"
        }
    ],
    "sg:phone":"+61 8 9965 7000",
    "sg:postcode":"6530",
    "sg:province":"WA",
    "sg:tags":[
        "replacement"
    ],
    "wof:name":"Auto One Parts And Accessories",
    "wof:placetype":"venue"
},
  "geometry": {"coordinates":[114.625343323,-28.7729263306],"type":"Point"}
}