{
  "type": "Feature",
  "properties": {
    "addr:full":"130 Perkins St West South Townsville QLD 4810",
    "addr:housenumber":"130",
    "addr:postcode":"4810",
    "addr:street":"Perkins St West",
    "iso:country":"AU",
    "sg:address":"130 Perkins St West",
    "sg:city":"South Townsville",
    "sg:classifiers":[
        {
            "category":"Building & Trades",
            "subcategory":"Construction",
            "type":"Services"
        }
    ],
    "sg:phone":"+61 7 4721 2629",
    "sg:postcode":"4810",
    "sg:province":"QLD",
    "sg:tags":[
        "ceiling"
    ],
    "wof:name":"CD Projects",
    "wof:placetype":"venue"
},
  "geometry": {"coordinates":[146.82115200000001,-19.269169],"type":"Point"}
}