{
  "type": "Feature",
  "properties": {
    "addr:full":"Ramsgate Rd Ramsgate NSW 2217",
    "addr:postcode":"2217",
    "addr:street":"Ramsgate Rd",
    "iso:country":"AU",
    "sg:address":"Ramsgate Rd",
    "sg:city":"Ramsgate",
    "sg:classifiers":[
        {
            "category":"Food & Beverages",
            "subcategory":"Supermarket",
            "type":"Retail Goods"
        }
    ],
    "sg:phone":"+61 2 9529 9030",
    "sg:postcode":"2217",
    "sg:province":"NSW",
    "sg:tags":[
        "grocery",
        "store"
    ],
    "wof:name":"Franklins Limited",
    "wof:placetype":"venue"
},
  "geometry": {"coordinates":[151.13807700000001,-33.984398],"type":"Point"}
}