{
  "type": "Feature",
  "properties": {
    "iso:country":"AU",
    "sg:address":"10 Royal Mantle Drv",
    "sg:city":"Ulladulla",
    "sg:classifiers":[
        {
            "category":"Professional",
            "subcategory":"Art Services",
            "type":"Services"
        }
    ],
    "sg:phone":"+61 2 4455 1515",
    "sg:postcode":"2539",
    "sg:province":"NSW",
    "sg:tags":[
        "decorator",
        "painter"
    ],
    "wof:name":"Halls C L",
    "wof:placetype":"venue"
},
  "geometry": {"coordinates":[150.460327148,-35.3433151245],"type":"Point"}
}