{
  "type": "Feature",
  "properties": {
    "addr:full":"55 John St Lilydale VIC 3140",
    "addr:housenumber":"55",
    "addr:postcode":"3140",
    "addr:street":"John St",
    "iso:country":"AU",
    "sg:address":"55 John St",
    "sg:city":"Lilydale",
    "sg:classifiers":[
        {
            "category":"Retail",
            "subcategory":"Auto Repair",
            "type":"Services"
        }
    ],
    "sg:phone":"+61 3 9735 0788",
    "sg:postcode":"3140",
    "sg:province":"VIC",
    "sg:tags":[
        "repairer",
        "motor",
        "engineer"
    ],
    "wof:name":"Holt's Brakes",
    "wof:placetype":"venue"
},
  "geometry": {"coordinates":[145.35023498499999,-37.7588577271],"type":"Point"}
}