{
  "type": "Feature",
  "properties": {
    "iso:country":"AU",
    "sg:address":"Unit 2/ 5 Stockwell Pl",
    "sg:city":"Archerfield",
    "sg:classifiers":[
        {
            "category":"Autos & Motor Vehicles",
            "subcategory":"Auto Supplies",
            "type":"Retail Goods"
        }
    ],
    "sg:phone":"+61 7 3850 9566",
    "sg:postcode":"4108",
    "sg:province":"QLD",
    "sg:tags":[
        "transmission",
        "equipment",
        "power"
    ],
    "wof:name":"Sumitomo Cyclo",
    "wof:placetype":"venue"
},
  "geometry": {"coordinates":[153.01658630399999,-27.5674705505],"type":"Point"}
}