{
  "type": "Feature",
  "properties": {
    "addr:full":"Darwin Central 21 Knuckey St Darwin NT 0801",
    "addr:housenumber":"21",
    "addr:postcode":"nt 0801",
    "addr:street":"Darwin Central;St",
    "iso:country":"AU",
    "sg:address":"Darwin Central 21 Knuckey St",
    "sg:city":"Darwin",
    "sg:classifiers":[
        {
            "category":"Shopping",
            "subcategory":"Jewelry",
            "type":"Retail Goods"
        }
    ],
    "sg:phone":"+61 8 8981 6329",
    "sg:postcode":"0801",
    "sg:province":"NT",
    "sg:tags":[
        "jeweller"
    ],
    "wof:name":"Darwin Allure",
    "wof:placetype":"venue"
},
  "geometry": {"coordinates":[130.84127807600001,-12.4631080627],"type":"Point"}
}