{
  "type": "Feature",
  "properties": {
    "addr:full":"581 Springvale Rd Springvale South VIC 3172",
    "addr:housenumber":"581",
    "addr:postcode":"3172",
    "addr:street":"Springvale Rd",
    "iso:country":"AU",
    "sg:address":"581 Springvale Rd",
    "sg:city":"Springvale South",
    "sg:classifiers":[
        {
            "category":"Food & Beverages",
            "subcategory":"Groceries & Convenience Stores",
            "type":"Retail Goods"
        }
    ],
    "sg:phone":"+61 3 9548 0531",
    "sg:postcode":"3172",
    "sg:province":"VIC",
    "wof:name":"7-Eleven Stores Pty Ltd",
    "wof:placetype":"venue"
},
  "geometry": {"coordinates":[145.14849853499999,-37.9723510742],"type":"Point"}
}