{
  "type": "Feature",
  "properties": {
    "iso:country":"AU",
    "sg:address":"U14/ 15-23 Kumulla Rd",
    "sg:city":"Miranda",
    "sg:classifiers":[
        {
            "category":"Retail",
            "subcategory":"Repair Shop",
            "type":"Services"
        }
    ],
    "sg:phone":"+61 2 9524 4187",
    "sg:postcode":"2228",
    "sg:province":"NSW",
    "sg:tags":[
        "upholsterer"
    ],
    "wof:name":"Pennie J & Sons",
    "wof:placetype":"venue"
},
  "geometry": {"coordinates":[151.11671447800001,-34.0285072327],"type":"Point"}
}