{
  "type": "Feature",
  "properties": {
    "iso:country":"AU",
    "sg:address":"39 Lear Jet Drv",
    "sg:city":"Caboolture",
    "sg:classifiers":[
        {
            "category":"Autos & Motor Vehicles",
            "subcategory":"Auto Supplies",
            "type":"Retail Goods"
        }
    ],
    "sg:phone":"+61 7 5495 8277",
    "sg:postcode":"4510",
    "sg:province":"QLD",
    "sg:tags":[
        "camper-trailers",
        "caravan",
        "equipment"
    ],
    "wof:name":"Phoenix Caravans",
    "wof:placetype":"venue"
},
  "geometry": {"coordinates":[152.94695999999999,-27.070293],"type":"Point"}
}