{
  "type": "Feature",
  "properties": {
    "addr:full":"Shed 2 Barts St Woombye QLD 4559",
    "addr:housenumber":"2",
    "addr:postcode":"4559",
    "addr:street":"Barts St",
    "iso:country":"AU",
    "sg:address":"Shed 2 Barts St",
    "sg:city":"Woombye",
    "sg:classifiers":[
        {
            "category":"Building & Trades",
            "subcategory":"Construction",
            "type":"Services"
        }
    ],
    "sg:phone":"+61 7 5442 2344",
    "sg:postcode":"4559",
    "sg:province":"QLD",
    "sg:tags":[
        "renovation",
        "alterations",
        "extension",
        "contractor"
    ],
    "wof:name":"Woombye Cabinetmaking",
    "wof:placetype":"venue"
},
  "geometry": {"coordinates":[152.96330261200001,-26.6598014832],"type":"Point"}
}