{
  "type": "Feature",
  "properties": {
    "iso:country":"AU",
    "sg:address":"Homestead Drv (cnr Poinciana Drv)",
    "sg:city":"Jimboomba",
    "sg:classifiers":[
        {
            "category":"Education",
            "subcategory":"School",
            "type":"Public Place"
        }
    ],
    "sg:phone":"+61 7 5547 9333",
    "sg:postcode":"4280",
    "sg:province":"QLD",
    "sg:tags":[
        "state",
        "except",
        "nsw"
    ],
    "wof:name":"Flagstone State Community College (Yrs 8 to 11)",
    "wof:placetype":"venue"
},
  "geometry": {"coordinates":[152.969147,-27.817064],"type":"Point"}
}