{
  "type": "Feature",
  "properties": {
    "addr:full":"9 Acton St Sutherland NSW 2232",
    "addr:housenumber":"9",
    "addr:postcode":"2232",
    "addr:street":"Acton St",
    "iso:country":"AU",
    "sg:address":"9 Acton St",
    "sg:city":"Sutherland",
    "sg:classifiers":[
        {
            "category":"Building & Trades",
            "subcategory":"Pest Control",
            "type":"Services"
        }
    ],
    "sg:phone":"+61 2 9543 3200",
    "sg:postcode":"2232",
    "sg:province":"NSW",
    "wof:name":"Bird-Master Systems",
    "wof:placetype":"venue"
},
  "geometry": {"coordinates":[151.06124877900001,-34.0291557312],"type":"Point"}
}