{
  "type": "Feature",
  "properties": {
    "iso:country":"AU",
    "sg:address":"Bruce Hwy",
    "sg:city":"Delta",
    "sg:classifiers":[
        {
            "category":"Autos & Motor Vehicles",
            "subcategory":"Fuel & Gas Station",
            "type":"Retail Goods"
        }
    ],
    "sg:phone":"+61 7 4785 2300",
    "sg:postcode":"4805",
    "sg:province":"QLD",
    "wof:name":"Rio Don Roadhouse",
    "wof:placetype":"venue"
},
  "geometry": {"coordinates":[148.1927948,-20.0164279938],"type":"Point"}
}