{
  "type": "Feature",
  "properties": {
    "addr:full":"4 Brinkworth St Plympton South SA 5038",
    "addr:housenumber":"4",
    "addr:postcode":"5038",
    "addr:street":"Brinkworth St",
    "iso:country":"AU",
    "sg:address":"4 Brinkworth St",
    "sg:city":"Plympton South",
    "sg:classifiers":[
        {
            "category":"Personal",
            "subcategory":"Beauty Salon",
            "type":"Services"
        }
    ],
    "sg:phone":"+61 8 8371 1627",
    "sg:postcode":"5038",
    "sg:province":"SA",
    "sg:tags":[
        "hairdresser"
    ],
    "wof:name":"Snazzy Hair Designs",
    "wof:placetype":"venue"
},
  "geometry": {"coordinates":[138.56080627399999,-34.9673576355],"type":"Point"}
}