{
  "type": "Feature",
  "properties": {
    "iso:country":"AU",
    "sg:address":"Suite 5/ 1 Alvan St",
    "sg:city":"Mt Lawley",
    "sg:classifiers":[
        {
            "category":"Real Estate",
            "subcategory":"Real Estate Agent",
            "type":"Services"
        }
    ],
    "sg:phone":"+61 1800 818 616",
    "sg:postcode":"6050",
    "sg:province":"WA",
    "wof:name":"Professionals Real Estate Group",
    "wof:placetype":"venue"
},
  "geometry": {"coordinates":[115.873497009,-31.9346065521],"type":"Point"}
}