{
  "type": "Feature",
  "properties": {
    "iso:country":"AU",
    "sg:address":"33 East St",
    "sg:city":"Yoogali",
    "sg:classifiers":[
        {
            "category":"Transit Center",
            "subcategory":"Passenger",
            "type":"Transportation"
        }
    ],
    "sg:phone":"+61 412 179 444",
    "sg:postcode":"2680",
    "sg:province":"NSW",
    "sg:tags":[
        "frozen",
        "food",
        "retail"
    ],
    "wof:name":"Pizza Italiana",
    "wof:placetype":"venue"
},
  "geometry": {"coordinates":[146.087616,-34.298222],"type":"Point"}
}