{
  "type": "Feature",
  "properties": {
    "addr:full":"90 Vulture St West End (Brisbane) QLD 4101",
    "addr:housenumber":"90",
    "addr:postcode":"4101",
    "addr:street":"Vulture St",
    "iso:country":"AU",
    "sg:address":"90 Vulture St",
    "sg:city":"West End (Brisbane)",
    "sg:classifiers":[
        {
            "category":"Travel",
            "subcategory":"Travel Agent",
            "type":"Entertainment"
        }
    ],
    "sg:phone":"+61 7 3844 2088",
    "sg:postcode":"4101",
    "sg:province":"QLD",
    "sg:tags":[
        "consultant"
    ],
    "wof:name":"Target Travel & Tours",
    "wof:placetype":"venue"
},
  "geometry": {"coordinates":[153.012573242,-27.4808979034],"type":"Point"}
}