{
  "type": "Feature",
  "properties": {
    "addr:full":"19 Northgate St Karrinyup WA 6018",
    "addr:housenumber":"19",
    "addr:postcode":"6018",
    "addr:street":"Northgate St",
    "iso:country":"AU",
    "sg:address":"19 Northgate St",
    "sg:city":"Karrinyup",
    "sg:classifiers":[
        {
            "category":"Health Services",
            "subcategory":"Dentist",
            "type":"Services"
        }
    ],
    "sg:phone":"+61 8 9204 2000",
    "sg:postcode":"6018",
    "sg:province":"WA",
    "wof:name":"De Jesus Lucy",
    "wof:placetype":"venue"
},
  "geometry": {"coordinates":[115.780563355,-31.8796157837],"type":"Point"}
}