{
  "type": "Feature",
  "properties": {
    "addr:full":"2 Haveaux St Werribee VIC 3030",
    "addr:housenumber":"2",
    "addr:postcode":"3030",
    "addr:street":"Haveaux St",
    "iso:country":"AU",
    "sg:address":"2 Haveaux St",
    "sg:city":"Werribee",
    "sg:classifiers":[
        {
            "category":"Building & Trades",
            "subcategory":"Construction",
            "type":"Services"
        }
    ],
    "sg:phone":"+61 412 358 909",
    "sg:postcode":"3030",
    "sg:province":"VIC",
    "sg:tags":[
        "joiner",
        "carpenter"
    ],
    "wof:name":"Dugald McLachlan",
    "wof:placetype":"venue"
},
  "geometry": {"coordinates":[144.634613,-37.904045],"type":"Point"}
}