{
  "type": "Feature",
  "properties": {
    "addr:full":"1219 High St Armadale VIC 3143",
    "addr:housenumber":"1219",
    "addr:postcode":"3143",
    "addr:street":"High St",
    "iso:country":"AU",
    "sg:address":"1219 High St",
    "sg:city":"Armadale",
    "sg:classifiers":[
        {
            "category":"Food & Beverages",
            "subcategory":"Liquor & Beverages",
            "type":"Retail Goods"
        }
    ],
    "sg:phone":"+61 3 9822 9100",
    "sg:postcode":"3143",
    "sg:province":"VIC",
    "sg:tags":[
        "merchant",
        "spirit",
        "wine"
    ],
    "wof:name":"Nicks Wine Merchants Pty Ltd",
    "wof:placetype":"venue"
},
  "geometry": {"coordinates":[145.02821350100001,-37.8563232422],"type":"Point"}
}