{
  "type": "Feature",
  "properties": {
    "iso:country":"AU",
    "sg:address":"6 Sunrise Hill Rd",
    "sg:city":"Montrose",
    "sg:classifiers":[
        {
            "category":"Building & Trades",
            "subcategory":"Construction",
            "type":"Services"
        }
    ],
    "sg:phone":"+61 412 365 613",
    "sg:postcode":"3765",
    "sg:province":"VIC",
    "sg:tags":[
        "bitumen",
        "paving",
        "asphalt"
    ],
    "wof:name":"Asphalt & Civil Construction Pty Ltd",
    "wof:placetype":"venue"
},
  "geometry": {"coordinates":[145.344970703,-37.8187980652],"type":"Point"}
}