{
  "type": "Feature",
  "properties": {
    "iso:country":"AU",
    "sg:address":"262A Glenferrie Rd",
    "sg:city":"Malvern",
    "sg:classifiers":[
        {
            "category":"Shopping",
            "subcategory":"Jewelry",
            "type":"Retail Goods"
        }
    ],
    "sg:phone":"+61 1300 130 613",
    "sg:postcode":"3144",
    "sg:province":"VIC",
    "sg:tags":[
        "jeweller"
    ],
    "wof:name":"Byzantine",
    "wof:placetype":"venue"
},
  "geometry": {"coordinates":[145.029296875,-37.8575439453],"type":"Point"}
}