{
  "type": "Feature",
  "properties": {
    "addr:full":"819 Port Rd Woodville SA 5011",
    "addr:housenumber":"819",
    "addr:postcode":"5011",
    "addr:street":"Port Rd",
    "iso:country":"AU",
    "sg:address":"819 Port Rd",
    "sg:city":"Woodville",
    "sg:classifiers":[
        {
            "category":"Professional",
            "subcategory":"Business Services",
            "type":"Services"
        }
    ],
    "sg:phone":"+61 8 8445 7400",
    "sg:postcode":"5011",
    "sg:province":"SA",
    "sg:tags":[
        "management",
        "event"
    ],
    "wof:name":"AMF Bowling Centre",
    "wof:placetype":"venue"
},
  "geometry": {"coordinates":[138.53242492699999,-34.87840271],"type":"Point"}
}