{
  "type": "Feature",
  "properties": {
    "addr:full":"168/ 170 Cavendish Rd Coorparoo QLD 4151",
    "addr:housenumber":"168 / 170",
    "addr:postcode":"4151",
    "addr:street":"Cavendish Rd",
    "iso:country":"AU",
    "sg:address":"168/ 170 Cavendish Rd",
    "sg:city":"Coorparoo",
    "sg:classifiers":[
        {
            "category":"Health Services",
            "subcategory":"Health Practitioner",
            "type":"Services"
        }
    ],
    "sg:phone":"+61 7 3397 9276",
    "sg:postcode":"4151",
    "sg:province":"QLD",
    "sg:tags":[
        "naturopath"
    ],
    "wof:name":"Karen Byrne",
    "wof:placetype":"venue"
},
  "geometry": {"coordinates":[153.05897522000001,-27.4938373566],"type":"Point"}
}