{
  "type": "Feature",
  "properties": {
    "addr:full":"869 Springvale Rd Mulgrave VIC 3170",
    "addr:housenumber":"869",
    "addr:postcode":"3170",
    "addr:street":"Springvale Rd",
    "iso:country":"AU",
    "sg:address":"869 Springvale Rd",
    "sg:city":"Mulgrave",
    "sg:classifiers":[
        {
            "category":"Health Services",
            "subcategory":"Chiropractor",
            "type":"Services"
        }
    ],
    "sg:phone":"+61 3 9548 5050",
    "sg:postcode":"3170",
    "sg:province":"VIC",
    "wof:name":"Advanced Chiropractic",
    "wof:placetype":"venue"
},
  "geometry": {"coordinates":[145.15635681099999,-37.9291877747],"type":"Point"}
}