{
  "type": "Feature",
  "properties": {
    "addr:full":"10/ 6 Dellamarta Rd Wangara WA 6065",
    "addr:housenumber":"10 / 6",
    "addr:postcode":"6065",
    "addr:street":"Dellamarta Rd",
    "iso:country":"AU",
    "sg:address":"10/ 6 Dellamarta Rd",
    "sg:city":"Wangara",
    "sg:classifiers":[
        {
            "category":"Building & Trades",
            "subcategory":"Construction",
            "type":"Services"
        }
    ],
    "sg:phone":"+61 8 9309 4403",
    "sg:postcode":"6065",
    "sg:province":"WA",
    "sg:tags":[
        "welding"
    ],
    "wof:name":"Van Gemmert Engineering",
    "wof:placetype":"venue"
},
  "geometry": {"coordinates":[115.81477356000001,-31.7891311646],"type":"Point"}
}