{
  "type": "Feature",
  "properties": {
    "addr:full":"Stephens Uniting Church Hall, Cnr Kadumba St & Kinsley Pde Yeronga QLD 4104",
    "addr:postcode":"4104",
    "addr:street":"Cnr Kadumba St & Kinsley Pde",
    "iso:country":"AU",
    "sg:address":"Stephens Uniting Church Hall, Cnr Kadumba St & Kinsley Pde",
    "sg:city":"Yeronga",
    "sg:classifiers":[
        {
            "category":"Arts & Performance",
            "subcategory":"Dance",
            "type":"Entertainment"
        }
    ],
    "sg:phone":"+61 410 260 847",
    "sg:postcode":"4104",
    "sg:province":"QLD",
    "sg:tags":[
        "theatrical",
        "ballet",
        "tuition"
    ],
    "wof:name":"Dance@Yeronga",
    "wof:placetype":"venue"
},
  "geometry": {"coordinates":[153.00689697300001,-27.5133609772],"type":"Point"}
}