{
  "type": "Feature",
  "properties": {
    "addr:full":"96 Gawler Pl Adelaide SA 5000",
    "addr:housenumber":"96",
    "addr:postcode":"5000",
    "addr:street":"Gawler Pl",
    "iso:country":"AU",
    "sg:address":"96 Gawler Pl",
    "sg:city":"Adelaide",
    "sg:classifiers":[
        {
            "category":"Arena",
            "subcategory":"Sports Club",
            "type":"Entertainment"
        }
    ],
    "sg:phone":"+61 1300 300 117",
    "sg:postcode":"5000",
    "sg:province":"SA",
    "sg:tags":[
        "defence",
        "supply",
        "self",
        "instruction",
        "martial art"
    ],
    "wof:name":"Karate For Kids",
    "wof:placetype":"venue"
},
  "geometry": {"coordinates":[138.602172852,-34.9246902466],"type":"Point"}
}