{
  "type": "Feature",
  "properties": {
    "iso:country":"AU",
    "sg:address":"40 Hawthorne St",
    "sg:city":"Sadliers Crossing",
    "sg:classifiers":[
        {
            "category":"Wholesale",
            "subcategory":"Home Furnishings",
            "type":"Manufacturing & Wholesale Goods"
        }
    ],
    "sg:phone":"+61 7 3282 8296",
    "sg:postcode":"4305",
    "sg:province":"QLD",
    "sg:tags":[
        "wholesaler",
        "curtain",
        "mfrs"
    ],
    "wof:name":"Myden Manufacturing",
    "wof:placetype":"venue"
},
  "geometry": {"coordinates":[152.74612426799999,-27.6094226837],"type":"Point"}
}