{
  "type": "Feature",
  "properties": {
    "addr:full":"4 Thomas St Johns River NSW 2443",
    "addr:housenumber":"4",
    "addr:postcode":"2443",
    "addr:street":"Thomas St Johns River",
    "iso:country":"AU",
    "sg:address":"4 Thomas St",
    "sg:city":"Johns River",
    "sg:classifiers":[
        {
            "category":"Professional",
            "subcategory":"Detective & Security Services",
            "type":"Services"
        }
    ],
    "sg:phone":"+61 2 6556 5052",
    "sg:postcode":"2443",
    "sg:province":"NSW",
    "sg:tags":[
        "equipment",
        "window",
        "doors"
    ],
    "wof:name":"Phantom Screens",
    "wof:placetype":"venue"
},
  "geometry": {"coordinates":[152.69654800000001,-31.730276],"type":"Point"}
}