{
  "type": "Feature",
  "properties": {
    "addr:full":"Unit 8, 27 York St Subiaco WA 6008",
    "addr:housenumber":"27",
    "addr:postcode":"6008",
    "addr:street":"York St",
    "iso:country":"AU",
    "sg:address":"Unit 8, 27 York St",
    "sg:city":"Subiaco",
    "sg:classifiers":[
        {
            "category":"Insurance",
            "subcategory":"Hazard Insurance",
            "type":"Services"
        }
    ],
    "sg:phone":"+61 8 9388 8733",
    "sg:postcode":"6008",
    "sg:province":"WA",
    "sg:tags":[
        "motor",
        "vehicle"
    ],
    "wof:name":"Famous Classic Car Insurance",
    "wof:placetype":"venue"
},
  "geometry": {"coordinates":[115.834968567,-31.9463863373],"type":"Point"}
}