{
  "type": "Feature",
  "properties": {
    "iso:country":"AU",
    "sg:address":"8 A Station St",
    "sg:city":"Thornleigh",
    "sg:classifiers":[
        {
            "category":"Personal",
            "subcategory":"Beauty Salon",
            "type":"Services"
        }
    ],
    "sg:phone":"+61 2 9980 5883",
    "sg:postcode":"2120",
    "sg:province":"NSW",
    "sg:tags":[
        "hairdresser"
    ],
    "wof:name":"Tanya's Unique Hair Studio",
    "wof:placetype":"venue"
},
  "geometry": {"coordinates":[151.08058166500001,-33.7324447632],"type":"Point"}
}