{
  "type": "Feature",
  "properties": {
    "iso:country":"AU",
    "sg:address":"45 McIntyre Rd",
    "sg:city":"Sunshine",
    "sg:classifiers":[
        {
            "category":"Autos & Motor Vehicles",
            "subcategory":"Fuel & Gas Station",
            "type":"Retail Goods"
        }
    ],
    "sg:phone":"+61 3 9310 2009",
    "sg:postcode":"3020",
    "sg:province":"VIC",
    "wof:name":"Better Choice",
    "wof:placetype":"venue"
},
  "geometry": {"coordinates":[144.82929999999999,-37.772953],"type":"Point"}
}