{
  "type": "Feature",
  "properties": {
    "addr:full":"21- 29 West Tce Adelaide SA 5000",
    "addr:housenumber":"29",
    "addr:postcode":"5000",
    "addr:street":"West Tce",
    "iso:country":"AU",
    "sg:address":"21- 29",
    "sg:city":"West Tce Adelaide",
    "sg:classifiers":[
        {
            "category":"Autos & Motor Vehicles",
            "subcategory":"Automobile Sales",
            "type":"Retail Goods"
        }
    ],
    "sg:phone":"+61 8 8212 1000",
    "sg:postcode":"5000",
    "sg:province":"SA",
    "sg:tags":[
        "car",
        "new"
    ],
    "wof:name":"United Motors Ltd",
    "wof:placetype":"venue"
},
  "geometry": {"coordinates":[138.60076904300001,-34.9256401062],"type":"Point"}
}