{
  "type": "Feature",
  "properties": {
    "iso:country":"AU",
    "sg:address":"184 High St",
    "sg:city":"Belmont",
    "sg:classifiers":[
        {
            "category":"Professional",
            "subcategory":"Accounting & Tax Preparation",
            "type":"Services"
        }
    ],
    "sg:phone":"+61 3 5244 3244",
    "sg:postcode":"3216",
    "sg:province":"VIC",
    "sg:tags":[
        "consultant",
        "taxation"
    ],
    "wof:name":"H & R Block",
    "wof:placetype":"venue"
},
  "geometry": {"coordinates":[144.34251403799999,-38.1750602722],"type":"Point"}
}