{
  "type": "Feature",
  "properties": {
    "addr:full":"6/ 84 Newmarket Rd Newmarket QLD 4051",
    "addr:housenumber":"/ 84",
    "addr:postcode":"4051",
    "addr:street":"Newmarket Rd",
    "iso:country":"AU",
    "sg:address":"6/ 84 Newmarket Rd",
    "sg:city":"Newmarket",
    "sg:classifiers":[
        {
            "category":"Manufacturing",
            "subcategory":"Furniture",
            "type":"Manufacturing & Wholesale Goods"
        }
    ],
    "sg:phone":"+61 7 3857 5397",
    "sg:postcode":"4051",
    "sg:province":"QLD",
    "sg:tags":[
        "builder",
        "designer",
        "custom"
    ],
    "wof:name":"Urban Key",
    "wof:placetype":"venue"
},
  "geometry": {"coordinates":[153.007156372,-27.436870575],"type":"Point"}
}