{
  "type": "Feature",
  "properties": {
    "addr:full":"200 Main Rd Moonah TAS 7009",
    "addr:housenumber":"200",
    "addr:postcode":"7009",
    "addr:street":"Main Rd",
    "iso:country":"AU",
    "sg:address":"200 Main Rd",
    "sg:city":"Moonah",
    "sg:classifiers":[
        {
            "category":"Autos & Motor Vehicles",
            "subcategory":"Fuel & Gas Station",
            "type":"Retail Goods"
        }
    ],
    "sg:phone":"+61 3 6272 0046",
    "sg:postcode":"7009",
    "sg:province":"TAS",
    "wof:name":"Caltex Moonah",
    "wof:placetype":"venue"
},
  "geometry": {"coordinates":[147.29043579099999,-42.8406944275],"type":"Point"}
}