{
  "type": "Feature",
  "properties": {
    "addr:full":"30 Pradella St Darra QLD 4076",
    "addr:housenumber":"30",
    "addr:postcode":"4076",
    "addr:street":"Pradella St",
    "iso:country":"AU",
    "sg:address":"30 Pradella St",
    "sg:city":"Darra",
    "sg:classifiers":[
        {
            "category":"Retail",
            "subcategory":"Auto Repair",
            "type":"Services"
        }
    ],
    "sg:phone":"+61 7 3375 3022",
    "sg:postcode":"4076",
    "sg:province":"QLD",
    "sg:tags":[
        "muffler",
        "exhaust",
        "system"
    ],
    "wof:name":"Mercury Mufflers (Qld) Pty Ltd",
    "wof:placetype":"venue"
},
  "geometry": {"coordinates":[152.95164489699999,-27.5770187378],"type":"Point"}
}