{
  "type": "Feature",
  "properties": {
    "iso:country":"AU",
    "sg:address":"2 Amelia St",
    "sg:city":"Knoxfield",
    "sg:classifiers":[
        {
            "category":"Retail",
            "subcategory":"Driving School",
            "type":"Services"
        }
    ],
    "sg:phone":"+61 421 060 597",
    "sg:postcode":"3180",
    "sg:province":"VIC",
    "wof:name":"Petars Driving School",
    "wof:placetype":"venue"
},
  "geometry": {"coordinates":[145.25674438499999,-37.8782272339],"type":"Point"}
}