{
  "type": "Feature",
  "properties": {
    "addr:full":"43 King St Norwood SA 5067",
    "addr:housenumber":"43",
    "addr:postcode":"5067",
    "addr:street":"King St",
    "iso:country":"AU",
    "sg:address":"43 King St",
    "sg:city":"Norwood",
    "sg:classifiers":[
        {
            "category":"Sports & Exercise",
            "subcategory":"Ski Slope",
            "type":"Entertainment"
        }
    ],
    "sg:phone":"+61 411 112 211",
    "sg:postcode":"5067",
    "sg:province":"SA",
    "sg:tags":[
        "equipment",
        "hire",
        "retail",
        "snow"
    ],
    "wof:name":"Snowboard Hire",
    "wof:placetype":"venue"
},
  "geometry": {"coordinates":[138.626785278,-34.9173545837],"type":"Point"}
}