{
  "type": "Feature",
  "properties": {
    "iso:country":"AU",
    "sg:address":"5 Katjusha Crt",
    "sg:city":"Pakenham",
    "sg:classifiers":[
        {
            "category":"Banks & Credit Unions",
            "subcategory":"Bank",
            "type":"Services"
        }
    ],
    "sg:phone":"+61 3 5941 2221",
    "sg:postcode":"3810",
    "sg:province":"VIC",
    "sg:tags":[
        "broker",
        "mortgage"
    ],
    "wof:name":"Better Logic Pty Ltd",
    "wof:placetype":"venue"
},
  "geometry": {"coordinates":[145.481506,-38.071499],"type":"Point"}
}