{
  "type": "Feature",
  "properties": {
    "iso:country":"AU",
    "sg:address":"Fac 2/ 100 Lower Paper Mills Rd",
    "sg:city":"Fyansford",
    "sg:classifiers":[
        {
            "category":"Home & Garden",
            "subcategory":"Building Materials",
            "type":"Retail Goods"
        }
    ],
    "sg:phone":"+61 417 384 062",
    "sg:postcode":"3221",
    "sg:province":"VIC",
    "sg:tags":[
        "fencing"
    ],
    "wof:name":"Big Red Trading Pty Ltd",
    "wof:placetype":"venue"
},
  "geometry": {"coordinates":[144.307114,-38.144211],"type":"Point"}
}