{
  "type": "Feature",
  "properties": {
    "iso:country":"AU",
    "sg:address":"Lot 330 Forest Rd",
    "sg:city":"Lara",
    "sg:classifiers":[
        {
            "category":"Manufacturing",
            "subcategory":"Metals",
            "type":"Manufacturing & Wholesale Goods"
        }
    ],
    "sg:phone":"+61 3 5275 6400",
    "sg:postcode":"3212",
    "sg:province":"VIC",
    "sg:tags":[
        "sheet",
        "worker"
    ],
    "wof:name":"Western Sheetmetal Insulation & Asbestos Removal Pty. Ltd.",
    "wof:placetype":"venue"
},
  "geometry": {"coordinates":[144.401245117,-37.9940376282],"type":"Point"}
}