{
  "type": "Feature",
  "properties": {
    "iso:country":"AU",
    "sg:address":"11 Duckett St",
    "sg:city":"Beaudesert",
    "sg:classifiers":[
        {
            "category":"Health Services",
            "subcategory":"Doctor",
            "type":"Services"
        }
    ],
    "sg:phone":"+61 7 5541 2141",
    "sg:postcode":"4285",
    "sg:province":"QLD",
    "sg:tags":[
        "medical",
        "practitioner"
    ],
    "wof:name":"Kuiper A M",
    "wof:placetype":"venue"
},
  "geometry": {"coordinates":[153.000229,-27.989708],"type":"Point"}
}