{
  "type": "Feature",
  "properties": {
    "addr:full":"11 Duckett St Beaudesert QLD 4285",
    "addr:housenumber":"11",
    "addr:postcode":"4285",
    "addr:street":"Duckett St",
    "iso:country":"AU",
    "sg:address":"11 Duckett St",
    "sg:city":"Beaudesert",
    "sg:classifiers":[
        {
            "category":"Health Services",
            "subcategory":"Doctor",
            "type":"Services"
        }
    ],
    "sg:phone":"+61 7 5541 2141",
    "sg:postcode":"4285",
    "sg:province":"QLD",
    "sg:tags":[
        "medical",
        "practitioner"
    ],
    "wof:name":"Kuiper A M",
    "wof:placetype":"venue"
},
  "geometry": {"coordinates":[153.00022899999999,-27.989708],"type":"Point"}
}