{
  "type": "Feature",
  "properties": {
    "iso:country":"AU",
    "sg:address":"4 Tanner Pl",
    "sg:city":"Kiama",
    "sg:classifiers":[
        {
            "category":"Professional",
            "subcategory":"Printing & Photocopies",
            "type":"Services"
        }
    ],
    "sg:phone":"+61 2 4233 2868",
    "sg:postcode":"2533",
    "sg:province":"NSW",
    "sg:tags":[
        "trophy"
    ],
    "wof:name":"Kiama Engraving",
    "wof:placetype":"venue"
},
  "geometry": {"coordinates":[150.84585571299999,-34.6793174744],"type":"Point"}
}