{
  "type": "Feature",
  "properties": {
    "addr:full":"Shop 3/5 Mt. Milman Drv Smithfield QLD 4878",
    "addr:housenumber":"shop 3 / 5",
    "addr:postcode":"4878",
    "addr:street":"Mt. Milman Drv",
    "iso:country":"AU",
    "sg:address":"Shop 3/5 Mt. Milman Drv",
    "sg:city":"Smithfield",
    "sg:classifiers":[
        {
            "category":"Personal",
            "subcategory":"Nail Salon",
            "type":"Services"
        }
    ],
    "sg:phone":"+61 7 4038 1788",
    "sg:postcode":"4878",
    "sg:province":"QLD",
    "sg:tags":[
        "artificial"
    ],
    "wof:name":"Beauty Uncovered",
    "wof:placetype":"venue"
},
  "geometry": {"coordinates":[145.69581604000001,-16.8365840912],"type":"Point"}
}