{
  "type": "Feature",
  "properties": {
    "iso:country":"AU",
    "sg:address":"62 Paterson St",
    "sg:city":"Launceston",
    "sg:classifiers":[
        {
            "category":"Professional",
            "subcategory":"Accounting & Tax Preparation",
            "type":"Services"
        }
    ],
    "sg:phone":"+61 3 6323 1222",
    "sg:postcode":"7250",
    "sg:province":"TAS",
    "sg:tags":[
        "accountant",
        "auditor"
    ],
    "wof:name":"Loone Anthony J",
    "wof:placetype":"venue"
},
  "geometry": {"coordinates":[147.13572692899999,-41.4374885559],"type":"Point"}
}