{
  "type": "Feature",
  "properties": {
    "addr:full":"Unit 3, 6 Trade St Ormiston QLD 4160",
    "addr:housenumber":"6",
    "addr:postcode":"4160",
    "addr:street":"Trade St",
    "iso:country":"AU",
    "sg:address":"Unit 3, 6 Trade St",
    "sg:city":"Ormiston",
    "sg:classifiers":[
        {
            "category":"Shopping",
            "subcategory":"Stationery & Office Supplies",
            "type":"Retail Goods"
        }
    ],
    "sg:phone":"+61 7 3821 7730",
    "sg:postcode":"4160",
    "sg:province":"QLD",
    "sg:tags":[
        "equipment",
        "display",
        "exhibition"
    ],
    "wof:name":"Xanita (Oceana) Pty Ltd",
    "wof:placetype":"venue"
},
  "geometry": {"coordinates":[153.25656127900001,-27.5212783813],"type":"Point"}
}