{
  "type": "Feature",
  "properties": {
    "iso:country":"AU",
    "sg:address":"PO Box 252",
    "sg:city":"Chirnside Park",
    "sg:classifiers":[
        {
            "category":"Building & Trades",
            "subcategory":"Construction",
            "type":"Services"
        }
    ],
    "sg:phone":"+61 417 144 783",
    "sg:postcode":"3116",
    "sg:province":"VIC",
    "sg:tags":[
        "contractor"
    ],
    "wof:name":"John Budinski",
    "wof:placetype":"venue"
},
  "geometry": {"coordinates":[145.31483459500001,-37.7397918701],"type":"Point"}
}