{
  "type": "Feature",
  "properties": {
    "addr:full":"89-103 Boundary Rd Laverton North VIC 3026",
    "addr:housenumber":"89-103",
    "addr:postcode":"3026",
    "addr:street":"Boundary Rd",
    "iso:country":"AU",
    "sg:address":"89-103 Boundary Rd",
    "sg:city":"Laverton North",
    "sg:classifiers":[
        {
            "category":"Commercial Area",
            "type":"Public Place"
        }
    ],
    "sg:phone":"+61 3 8368 7200",
    "sg:postcode":"3026",
    "sg:province":"VIC",
    "sg:tags":[
        "heavy",
        "carrier"
    ],
    "wof:name":"Border Express Pty Ltd",
    "wof:placetype":"venue"
},
  "geometry": {"coordinates":[144.79847699999999,-37.814545],"type":"Point"}
}