{
  "type": "Feature",
  "properties": {
    "addr:full":"19 Biarritz Ave Beaumaris VIC 3193",
    "addr:housenumber":"19",
    "addr:postcode":"3193",
    "addr:street":"Biarritz Ave",
    "iso:country":"AU",
    "sg:address":"19 Biarritz Ave",
    "sg:city":"Beaumaris",
    "sg:classifiers":[
        {
            "category":"Professional",
            "subcategory":"Computer Services",
            "type":"Services"
        }
    ],
    "sg:phone":"+61 3 9589 6467",
    "sg:postcode":"3193",
    "sg:province":"VIC",
    "sg:tags":[
        "package",
        "software"
    ],
    "wof:name":"Accountsoft Business Computing Pty Ltd",
    "wof:placetype":"venue"
},
  "geometry": {"coordinates":[145.04675293,-37.9745635986],"type":"Point"}
}