{
  "type": "Feature",
  "properties": {
    "addr:full":"Cnr Airds Rd & Sussex St Minto NSW 2566",
    "addr:postcode":"2566",
    "addr:street":"Cnr Airds Rd & Sussex St",
    "iso:country":"AU",
    "sg:address":"Cnr Airds Rd & Sussex St",
    "sg:city":"Minto",
    "sg:classifiers":[
        {
            "category":"Wholesale",
            "subcategory":"Machinery & Supplies",
            "type":"Manufacturing & Wholesale Goods"
        }
    ],
    "sg:phone":"+61 2 9603 8600",
    "sg:postcode":"2566",
    "sg:province":"NSW",
    "sg:tags":[
        "agricultural"
    ],
    "wof:name":"Town & Country Tractors & Machinery P/L",
    "wof:placetype":"venue"
},
  "geometry": {"coordinates":[150.838134766,-34.0298194885],"type":"Point"}
}