{
  "type": "Feature",
  "properties": {
    "addr:full":"27a Chester St Fortitude Valley QLD 4006",
    "addr:housenumber":"27a",
    "addr:postcode":"4006",
    "addr:street":"Chester St",
    "iso:country":"AU",
    "sg:address":"27a Chester St",
    "sg:city":"Fortitude Valley",
    "sg:classifiers":[
        {
            "category":"Fast Food",
            "type":"Food & Drink"
        }
    ],
    "sg:phone":"+61 7 3252 2422",
    "sg:postcode":"4006",
    "sg:province":"QLD",
    "sg:tags":[
        "away",
        "take"
    ],
    "wof:name":"Chester Street Snack Bar",
    "wof:placetype":"venue"
},
  "geometry": {"coordinates":[153.04156494099999,-27.4550113678],"type":"Point"}
}