{
  "type": "Feature",
  "properties": {
    "addr:full":"5 Howitt Rd Padbury WA 6025",
    "addr:housenumber":"5",
    "addr:postcode":"6025",
    "addr:street":"Howitt Rd",
    "iso:country":"AU",
    "sg:address":"5 Howitt Rd",
    "sg:city":"Padbury",
    "sg:classifiers":[
        {
            "category":"Wholesale",
            "subcategory":"Machinery & Supplies",
            "type":"Manufacturing & Wholesale Goods"
        }
    ],
    "sg:phone":"+61 8 9402 2775",
    "sg:postcode":"6025",
    "sg:province":"WA",
    "sg:tags":[
        "equipment",
        "laboratory"
    ],
    "wof:name":"Bamrico",
    "wof:placetype":"venue"
},
  "geometry": {"coordinates":[115.76640319800001,-31.8087005615],"type":"Point"}
}