{
  "type": "Feature",
  "properties": {
    "addr:full":"4/ 40 Kalaroo Rd Redhead NSW 2290",
    "addr:housenumber":"/ 40",
    "addr:postcode":"2290",
    "addr:street":"Kalaroo Rd",
    "iso:country":"AU",
    "sg:address":"4/ 40 Kalaroo Rd",
    "sg:city":"Redhead",
    "sg:classifiers":[
        {
            "category":"Professional",
            "type":"Services"
        }
    ],
    "sg:phone":"+61 2 4942 6970",
    "sg:postcode":"2290",
    "sg:province":"NSW",
    "sg:tags":[
        "spray",
        "painting"
    ],
    "wof:name":"Keighran J & S",
    "wof:placetype":"venue"
},
  "geometry": {"coordinates":[151.70054626500001,-33.0157165527],"type":"Point"}
}