{
  "type": "Feature",
  "properties": {
    "addr:full":"10 E 32-60 Alice St Newtown NSW 2042",
    "addr:housenumber":"10",
    "addr:postcode":"2042",
    "addr:street":"E 32-60 Alice St",
    "iso:country":"AU",
    "sg:address":"10 E 32-60 Alice St",
    "sg:city":"Newtown",
    "sg:classifiers":[
        {
            "category":"Manufacturing",
            "subcategory":"Furniture",
            "type":"Manufacturing & Wholesale Goods"
        }
    ],
    "sg:phone":"+61 2 9519 6175",
    "sg:postcode":"2042",
    "sg:province":"NSW",
    "sg:tags":[
        "builder",
        "designer",
        "custom"
    ],
    "wof:name":"James Lee Warner Furniture",
    "wof:placetype":"venue"
},
  "geometry": {"coordinates":[151.177628,-33.903648],"type":"Point"}
}