{
  "type": "Feature",
  "properties": {
    "iso:country":"AU",
    "sg:address":"27 Vicary St",
    "sg:city":"Triabunna",
    "sg:classifiers":[
        {
            "category":"Professional",
            "subcategory":"Art Services",
            "type":"Services"
        }
    ],
    "sg:phone":"+61 3 6257 3470",
    "sg:postcode":"7190",
    "sg:province":"TAS",
    "sg:tags":[
        "decorator",
        "painter"
    ],
    "wof:name":"Castle D S B",
    "wof:placetype":"venue"
},
  "geometry": {"coordinates":[147.915527,-42.507561],"type":"Point"}
}