{
  "type": "Feature",
  "properties": {
    "addr:full":"58 Commercial Rd Prahran VIC 3181",
    "addr:housenumber":"58",
    "addr:postcode":"3181",
    "addr:street":"Commercial Rd",
    "iso:country":"AU",
    "sg:address":"58 Commercial Rd",
    "sg:city":"Prahran",
    "sg:classifiers":[
        {
            "category":"Food & Beverages",
            "subcategory":"Liquor & Beverages",
            "type":"Retail Goods"
        }
    ],
    "sg:phone":"+61 3 9510 5424",
    "sg:postcode":"3181",
    "sg:province":"VIC",
    "sg:tags":[
        "store"
    ],
    "wof:name":"Winebins",
    "wof:placetype":"venue"
},
  "geometry": {"coordinates":[144.987884522,-37.8461647034],"type":"Point"}
}