{
  "type": "Feature",
  "properties": {
    "addr:full":"81 Scenic Drv Budgewoi NSW 2262",
    "addr:housenumber":"81",
    "addr:postcode":"2262",
    "addr:street":"Scenic Drv",
    "iso:country":"AU",
    "sg:address":"81 Scenic Drv",
    "sg:city":"Budgewoi",
    "sg:classifiers":[
        {
            "category":"Banks & Credit Unions",
            "subcategory":"Bank",
            "type":"Services"
        }
    ],
    "sg:phone":"+61 1300 654 477",
    "sg:postcode":"2262",
    "sg:province":"NSW",
    "sg:tags":[
        "society"
    ],
    "wof:name":"Power Credit Union",
    "wof:placetype":"venue"
},
  "geometry": {"coordinates":[151.55345199999999,-33.233513],"type":"Point"}
}