{
  "type": "Feature",
  "properties": {
    "addr:full":"27 Alanbar St Waratah NSW 2298",
    "addr:housenumber":"27",
    "addr:postcode":"2298",
    "addr:street":"Alanbar St",
    "iso:country":"AU",
    "sg:address":"27 Alanbar St",
    "sg:city":"Waratah",
    "sg:classifiers":[
        {
            "category":"Education",
            "subcategory":"Kindergarten",
            "type":"Public Place"
        }
    ],
    "sg:phone":"+61 2 6297 3850",
    "sg:postcode":"2298",
    "sg:province":"NSW",
    "sg:tags":[
        "pre-schools"
    ],
    "wof:name":"Qbyn And District Pre-School Assoc",
    "wof:placetype":"venue"
},
  "geometry": {"coordinates":[151.722854614,-32.904209137],"type":"Point"}
}