{
  "type": "Feature",
  "properties": {
    "addr:full":"15 Higgerson Ave Engadine NSW 2233",
    "addr:housenumber":"15",
    "addr:postcode":"2233",
    "addr:street":"Higgerson Ave",
    "iso:country":"AU",
    "sg:address":"15 Higgerson Ave",
    "sg:city":"Engadine",
    "sg:classifiers":[
        {
            "category":"Professional",
            "type":"Services"
        }
    ],
    "sg:phone":"+61 2 9520 6075",
    "sg:postcode":"2233",
    "sg:province":"NSW",
    "sg:tags":[
        "transport"
    ],
    "wof:name":"BGR Transport Services",
    "wof:placetype":"venue"
},
  "geometry": {"coordinates":[151.00457763700001,-34.0711669922],"type":"Point"}
}