{
  "type": "Feature",
  "properties": {
    "iso:country":"AU",
    "sg:address":"8 Louisa Crt",
    "sg:city":"Emerald",
    "sg:classifiers":[
        {
            "category":"Banks & Credit Unions",
            "subcategory":"Investment Brokerage",
            "type":"Services"
        }
    ],
    "sg:phone":"+61 7 4982 0377",
    "sg:postcode":"4720",
    "sg:province":"QLD",
    "wof:name":"C Q Financial Planning & Investment Services Pty Ltd",
    "wof:placetype":"venue"
},
  "geometry": {"coordinates":[148.150955,-23.528847],"type":"Point"}
}