{
  "type": "Feature",
  "properties": {
    "addr:full":"8 Louisa Crt Emerald QLD 4720",
    "addr:housenumber":"8",
    "addr:postcode":"4720",
    "addr:street":"Louisa Crt",
    "iso:country":"AU",
    "sg:address":"8 Louisa Crt",
    "sg:city":"Emerald",
    "sg:classifiers":[
        {
            "category":"Banks & Credit Unions",
            "subcategory":"Investment Brokerage",
            "type":"Services"
        }
    ],
    "sg:phone":"+61 7 4982 0377",
    "sg:postcode":"4720",
    "sg:province":"QLD",
    "wof:name":"C Q Financial Planning & Investment Services Pty Ltd",
    "wof:placetype":"venue"
},
  "geometry": {"coordinates":[148.15095500000001,-23.528847],"type":"Point"}
}