{
  "type": "Feature",
  "properties": {
    "addr:full":"Shop 3/ 296 Kingsway Rd Caringbah NSW 2229",
    "addr:housenumber":"shop 3 / 296",
    "addr:postcode":"2229",
    "addr:street":"Kingsway Rd",
    "iso:country":"AU",
    "sg:address":"Shop 3/ 296 Kingsway Rd",
    "sg:city":"Caringbah",
    "sg:classifiers":[
        {
            "category":"Banks & Credit Unions",
            "subcategory":"Bureau De Change",
            "type":"Services"
        }
    ],
    "sg:phone":"+61 1300 472 668",
    "sg:postcode":"2229",
    "sg:province":"NSW",
    "sg:tags":[
        "motorised",
        "scooter"
    ],
    "wof:name":"Scooter Store Pty Ltd The",
    "wof:placetype":"venue"
},
  "geometry": {"coordinates":[151.124343872,-34.043510437],"type":"Point"}
}