{
  "type": "Feature",
  "properties": {
    "iso:country":"AU",
    "sg:address":"127 Pyrmont St",
    "sg:city":"Pyrmont",
    "sg:classifiers":[
        {
            "category":"Professional",
            "subcategory":"Art Services",
            "type":"Services"
        }
    ],
    "sg:phone":"+61 2 9566 2600",
    "sg:postcode":"2009",
    "sg:province":"NSW",
    "sg:tags":[
        "arranger",
        "music",
        "composer"
    ],
    "wof:name":"Noise International Pty Ltd",
    "wof:placetype":"venue"
},
  "geometry": {"coordinates":[151.195404053,-33.8704223633],"type":"Point"}
}