{
  "type": "Feature",
  "properties": {
    "iso:country":"AU",
    "sg:address":"26 Wilfred Barrett Drv",
    "sg:city":"The Entrance North",
    "sg:classifiers":[
        {
            "category":"Building & Trades",
            "subcategory":"Cleaning & Sanitation",
            "type":"Services"
        }
    ],
    "sg:phone":"+61 2 4333 3556",
    "sg:postcode":"2261",
    "sg:province":"NSW",
    "sg:tags":[
        "cleaner",
        "repairer",
        "roof"
    ],
    "wof:name":"Roofing Central Pty Ltd",
    "wof:placetype":"venue"
},
  "geometry": {"coordinates":[151.503387,-33.331844],"type":"Point"}
}