{
  "type": "Feature",
  "properties": {
    "iso:country":"AU",
    "sg:address":"6 Yawl St",
    "sg:city":"Burleigh Centre",
    "sg:classifiers":[
        {
            "category":"Building & Trades",
            "subcategory":"Landscaping Services",
            "type":"Services"
        }
    ],
    "sg:phone":"+61 405 694 485",
    "sg:postcode":"4220",
    "sg:province":"QLD",
    "sg:tags":[
        "designer",
        "landscape",
        "contractor"
    ],
    "wof:name":"Rainforest Landscaping",
    "wof:placetype":"venue"
},
  "geometry": {"coordinates":[153.432662964,-28.0981998444],"type":"Point"}
}