{
  "type": "Feature",
  "properties": {
    "addr:full":"7 Industrial Ave Caboolture QLD 4510",
    "addr:housenumber":"7",
    "addr:postcode":"4510",
    "addr:street":"Industrial Ave",
    "iso:country":"AU",
    "sg:address":"7 Industrial Ave",
    "sg:city":"Caboolture",
    "sg:classifiers":[
        {
            "category":"Home & Garden",
            "subcategory":"Hardware",
            "type":"Retail Goods"
        }
    ],
    "sg:phone":"+61 7 5495 5343",
    "sg:postcode":"4510",
    "sg:province":"QLD",
    "sg:tags":[
        "repair",
        "tool",
        "power"
    ],
    "wof:name":"Caboolture Power Tool Service",
    "wof:placetype":"venue"
},
  "geometry": {"coordinates":[152.95147700000001,-27.093416],"type":"Point"}
}