{
  "type": "Feature",
  "properties": {
    "addr:full":"Tenterfield St Deepwater NSW 2371",
    "addr:postcode":"2371",
    "addr:street":"Tenterfield St",
    "iso:country":"AU",
    "sg:address":"Tenterfield St",
    "sg:city":"Deepwater",
    "sg:classifiers":[
        {
            "category":"Cafe",
            "type":"Food & Drink"
        }
    ],
    "sg:phone":"+61 2 6734 5283",
    "sg:postcode":"2371",
    "sg:province":"NSW",
    "wof:name":"Theodore H",
    "wof:placetype":"venue"
},
  "geometry": {"coordinates":[151.84576415999999,-29.443813324],"type":"Point"}
}