{
  "type": "Feature",
  "properties": {
    "iso:country":"AU",
    "sg:address":"477 Southport-Nerang Rd",
    "sg:city":"Ashmore",
    "sg:classifiers":[
        {
            "category":"Retail",
            "subcategory":"Auto Repair",
            "type":"Services"
        }
    ],
    "sg:phone":"+61 7 5597 1311",
    "sg:postcode":"4214",
    "sg:province":"QLD",
    "sg:tags":[
        "body",
        "builder",
        "motor"
    ],
    "wof:name":"Swiftco Truck Bodies",
    "wof:placetype":"venue"
},
  "geometry": {"coordinates":[153.347198486,-27.9816970825],"type":"Point"}
}