{
  "type": "Feature",
  "properties": {
    "addr:full":"U6/ 11 Alloa St Maddington WA 6109",
    "addr:postcode":"6109",
    "addr:street":"U6 / 11 Alloa St",
    "iso:country":"AU",
    "sg:address":"U6/ 11 Alloa St",
    "sg:city":"Maddington",
    "sg:classifiers":[
        {
            "category":"Shopping",
            "subcategory":"Stationery & Office Supplies",
            "type":"Retail Goods"
        }
    ],
    "sg:phone":"+61 8 9452 7188",
    "sg:postcode":"6109",
    "sg:province":"WA",
    "sg:tags":[
        "partition"
    ],
    "wof:name":"Rynat Australia Pty Ltd",
    "wof:placetype":"venue"
},
  "geometry": {"coordinates":[115.98445892300001,-32.044883728],"type":"Point"}
}