{
  "type": "Feature",
  "properties": {
    "iso:country":"AU",
    "sg:address":"Borrow St",
    "sg:city":"Freeling",
    "sg:classifiers":[
        {
            "category":"Wholesale",
            "subcategory":"Machinery & Supplies",
            "type":"Manufacturing & Wholesale Goods"
        }
    ],
    "sg:phone":"+61 8 8525 3500",
    "sg:postcode":"5372",
    "sg:province":"SA",
    "sg:tags":[
        "agricultural"
    ],
    "wof:name":"Agpoint Australia",
    "wof:placetype":"venue"
},
  "geometry": {"coordinates":[138.815505981,-34.4514160156],"type":"Point"}
}