{
  "type": "Feature",
  "properties": {
    "addr:full":"PO Box 3098 Newstead QLD 4006",
    "addr:postcode":"4006",
    "iso:country":"AU",
    "sg:address":"PO Box 3098",
    "sg:city":"Newstead",
    "sg:classifiers":[
        {
            "category":"Professional",
            "subcategory":"Art Services",
            "type":"Services"
        }
    ],
    "sg:phone":"+61 404 067 085",
    "sg:postcode":"4006",
    "sg:province":"QLD",
    "sg:tags":[
        "decorator",
        "painter"
    ],
    "wof:name":"J Decco Painter and Decorator",
    "wof:placetype":"venue"
},
  "geometry": {"coordinates":[153.04527282699999,-27.4538993835],"type":"Point"}
}