{
  "type": "Feature",
  "properties": {
    "addr:full":"43- 45 Great Ocean Rd Apollo Bay VIC 3233",
    "addr:housenumber":"45",
    "addr:postcode":"3233",
    "addr:street":"Great Ocean Rd",
    "iso:country":"AU",
    "sg:address":"43- 45 Great Ocean Rd",
    "sg:city":"Apollo Bay",
    "sg:classifiers":[
        {
            "category":"Banks & Credit Unions",
            "subcategory":"Bank",
            "type":"Services"
        }
    ],
    "sg:phone":"+61 13 20 32",
    "sg:postcode":"3233",
    "sg:province":"VIC",
    "wof:name":"Westpac",
    "wof:placetype":"venue"
},
  "geometry": {"coordinates":[143.66632080100001,-38.7666511536],"type":"Point"}
}