{
  "type": "Feature",
  "properties": {
    "addr:full":"PO Box 1043 Kensington Gardens SA 5068",
    "addr:postcode":"5068",
    "addr:street":"Kensington",
    "iso:country":"AU",
    "sg:address":"PO Box 1043",
    "sg:city":"Kensington Gardens",
    "sg:classifiers":[
        {
            "category":"Wholesale",
            "subcategory":"Machinery & Supplies",
            "type":"Manufacturing & Wholesale Goods"
        }
    ],
    "sg:phone":"+61 8 8431 0707",
    "sg:postcode":"5068",
    "sg:province":"SA",
    "sg:tags":[
        "equipment",
        "laboratory"
    ],
    "wof:name":"R & D Equipment Brokers",
    "wof:placetype":"venue"
},
  "geometry": {"coordinates":[138.664916992,-34.9197502136],"type":"Point"}
}