{
  "type": "Feature",
  "properties": {
    "addr:full":"56 Bowker St Somerton Park SA 5044",
    "addr:housenumber":"56",
    "addr:postcode":"5044",
    "addr:street":"Bowker St",
    "iso:country":"AU",
    "sg:address":"56 Bowker St",
    "sg:city":"Somerton Park",
    "sg:classifiers":[
        {
            "category":"Government",
            "subcategory":"Post Office",
            "type":"Public Place"
        }
    ],
    "sg:phone":"+61 8 8296 9515",
    "sg:postcode":"5044",
    "sg:province":"SA",
    "sg:tags":[
        "yoga"
    ],
    "wof:name":"Patricia Grainger",
    "wof:placetype":"venue"
},
  "geometry": {"coordinates":[138.52858000000001,-35.00164],"type":"Point"}
}