{
  "type": "Feature",
  "properties": {
    "addr:full":"6 Cohen St Fairlight NSW 2094",
    "addr:housenumber":"6",
    "addr:postcode":"2094",
    "addr:street":"Cohen St",
    "iso:country":"AU",
    "sg:address":"6 Cohen St",
    "sg:city":"Fairlight",
    "sg:classifiers":[
        {
            "category":"Real Estate",
            "subcategory":"Real Estate Agent",
            "type":"Services"
        }
    ],
    "sg:phone":"+61 2 9948 0005",
    "sg:postcode":"2094",
    "sg:province":"NSW",
    "wof:name":"Peter Giles Real Estate",
    "wof:placetype":"venue"
},
  "geometry": {"coordinates":[151.27525329599999,-33.7954826355],"type":"Point"}
}