{
  "type": "Feature",
  "properties": {
    "iso:country":"AU",
    "sg:address":"Shop 4/ 41- 53 Miller St",
    "sg:city":"Epping",
    "sg:classifiers":[
        {
            "category":"Health Services",
            "subcategory":"Health Practitioner",
            "type":"Services"
        }
    ],
    "sg:phone":"+61 3 9401 1855",
    "sg:postcode":"3076",
    "sg:province":"VIC",
    "sg:tags":[
        "physiotherapist"
    ],
    "wof:name":"Bedem Claire",
    "wof:placetype":"venue"
},
  "geometry": {"coordinates":[144.99229431099999,-37.7515411377],"type":"Point"}
}