{
  "type": "Feature",
  "properties": {
    "addr:full":"29 Mayne St Chifley ACT 2606",
    "addr:housenumber":"29",
    "addr:postcode":"2606",
    "addr:street":"Mayne St",
    "iso:country":"AU",
    "sg:address":"29 Mayne St",
    "sg:city":"Chifley",
    "sg:classifiers":[
        {
            "category":"Building & Trades",
            "subcategory":"Construction",
            "type":"Services"
        }
    ],
    "sg:phone":"+61 417 591 144",
    "sg:postcode":"2606",
    "sg:province":"ACT",
    "sg:tags":[
        "contractor"
    ],
    "wof:name":"Sabane Property Group",
    "wof:placetype":"venue"
},
  "geometry": {"coordinates":[149.07513427699999,-35.3589515686],"type":"Point"}
}