{
  "type": "Feature",
  "properties": {
    "addr:full":"Lvl 29/ 239 George St Brisbane QLD 4000",
    "addr:housenumber":"/ 239",
    "addr:postcode":"4000",
    "addr:street":"George St",
    "iso:country":"AU",
    "sg:address":"Lvl 29/ 239 George St",
    "sg:city":"Brisbane",
    "sg:classifiers":[
        {
            "category":"Professional",
            "subcategory":"Business Services",
            "type":"Services"
        }
    ],
    "sg:phone":"+61 1800 018 810",
    "sg:postcode":"4000",
    "sg:province":"QLD",
    "sg:tags":[
        "management",
        "event"
    ],
    "wof:name":"Ozevents.Com",
    "wof:placetype":"venue"
},
  "geometry": {"coordinates":[153.02322387699999,-27.4703712463],"type":"Point"}
}