{
  "type": "Feature",
  "properties": {
    "addr:full":"724 Woodville Rd Fairfield East NSW 2165",
    "addr:housenumber":"724",
    "addr:postcode":"2165",
    "addr:street":"Woodville Rd",
    "iso:country":"AU",
    "sg:address":"724 Woodville Rd",
    "sg:city":"Fairfield East",
    "sg:classifiers":[
        {
            "category":"Home & Garden",
            "subcategory":"Building Materials",
            "type":"Retail Goods"
        }
    ],
    "sg:phone":"+61 411 398 355",
    "sg:postcode":"2165",
    "sg:province":"NSW",
    "sg:tags":[
        "supply"
    ],
    "wof:name":"Sabant",
    "wof:placetype":"venue"
},
  "geometry": {"coordinates":[150.98472595199999,-33.8711357117],"type":"Point"}
}