{
  "type": "Feature",
  "properties": {
    "iso:country":"AU",
    "sg:address":"188 Victoria Rd",
    "sg:city":"Drummoyne",
    "sg:classifiers":[
        {
            "category":"Retail",
            "subcategory":"Repair Shop",
            "type":"Services"
        }
    ],
    "sg:phone":"+61 2 9181 4096",
    "sg:postcode":"2047",
    "sg:province":"NSW",
    "sg:tags":[
        "mending",
        "clothing",
        "alteration"
    ],
    "wof:name":"Drummoyne Mens & Ladies Alteration Tailor",
    "wof:placetype":"venue"
},
  "geometry": {"coordinates":[151.155045,-33.851364],"type":"Point"}
}