{
  "type": "Feature",
  "properties": {
    "addr:full":"387 Lake Rd Glendale NSW 2285",
    "addr:housenumber":"387",
    "addr:postcode":"2285",
    "addr:street":"Lake Rd",
    "iso:country":"AU",
    "sg:address":"387 Lake Rd",
    "sg:city":"Glendale",
    "sg:classifiers":[
        {
            "category":"Retail",
            "subcategory":"Car Wash",
            "type":"Services"
        }
    ],
    "sg:phone":"+61 2 4954 0654",
    "sg:postcode":"2285",
    "sg:province":"NSW",
    "sg:tags":[
        "truck",
        "cleaning"
    ],
    "wof:name":"Sqirts Carwash",
    "wof:placetype":"venue"
},
  "geometry": {"coordinates":[151.63470459000001,-32.933429718],"type":"Point"}
}