{
  "type": "Feature",
  "properties": {
    "addr:full":"291 Honour Ave Graceville QLD 4075",
    "addr:housenumber":"291",
    "addr:postcode":"4075",
    "addr:street":"Honour Ave",
    "iso:country":"AU",
    "sg:address":"291 Honour Ave",
    "sg:city":"Graceville",
    "sg:classifiers":[
        {
            "category":"Banks & Credit Unions",
            "subcategory":"Investment Brokerage",
            "type":"Services"
        }
    ],
    "sg:phone":"+61 7 3379 9322",
    "sg:postcode":"4075",
    "sg:province":"QLD",
    "sg:tags":[
        "management",
        "property"
    ],
    "wof:name":"Nanette Lilley Property Centre",
    "wof:placetype":"venue"
},
  "geometry": {"coordinates":[152.975143433,-27.5199050903],"type":"Point"}
}