{
  "type": "Feature",
  "properties": {
    "iso:country":"AU",
    "sg:address":"1 Forest Rd",
    "sg:city":"Lara",
    "sg:classifiers":[
        {
            "category":"Retail",
            "subcategory":"Auto Repair",
            "type":"Services"
        }
    ],
    "sg:phone":"+61 3 5282 3144",
    "sg:postcode":"3212",
    "sg:province":"VIC",
    "sg:tags":[
        "repairer",
        "motor",
        "engineer"
    ],
    "wof:name":"Pete's Car & 4WD Centre",
    "wof:placetype":"venue"
},
  "geometry": {"coordinates":[144.39625549300001,-38.0225601196],"type":"Point"}
}