{
  "type": "Feature",
  "properties": {
    "iso:country":"AU",
    "sg:address":"Neusa Vale Rd",
    "sg:city":"Kin Kin",
    "sg:classifiers":[
        {
            "category":"Building & Trades",
            "subcategory":"Landscaping Services",
            "type":"Services"
        }
    ],
    "sg:phone":"+61 7 5486 7164",
    "sg:postcode":"4571",
    "sg:province":"QLD",
    "sg:tags":[
        "horticultural",
        "consultant"
    ],
    "wof:name":"Leaf & Limb Horticultural Consultancy",
    "wof:placetype":"venue"
},
  "geometry": {"coordinates":[152.857986,-26.225134],"type":"Point"}
}