{
  "type": "Feature",
  "properties": {
    "iso:country":"AU",
    "sg:address":"Shop 1",
    "sg:city":"K Shopping Fair Stockland Rockhampton North R",
    "sg:classifiers":[
        {
            "category":"Travel",
            "subcategory":"Travel Agent",
            "type":"Entertainment"
        }
    ],
    "sg:phone":"+61 13 18 66",
    "sg:postcode":"4701",
    "sg:province":"QLD",
    "sg:tags":[
        "consultant"
    ],
    "wof:name":"Flight Centre",
    "wof:placetype":"venue"
},
  "geometry": {"coordinates":[150.54896545400001,-23.3510398865],"type":"Point"}
}