{
  "type": "Feature",
  "properties": {
    "iso:country":"AU",
    "sg:address":"Shp7/ 3 Minerva Rd",
    "sg:city":"Herne Hill",
    "sg:classifiers":[
        {
            "category":"Fast Food",
            "type":"Food & Drink"
        }
    ],
    "sg:phone":"+61 3 5272 3225",
    "sg:postcode":"3218",
    "sg:province":"VIC",
    "sg:tags":[
        "away",
        "take"
    ],
    "wof:name":"Minerva Pizza & Pasta",
    "wof:placetype":"venue"
},
  "geometry": {"coordinates":[144.33169555699999,-38.1299972534],"type":"Point"}
}