{
  "type": "Feature",
  "properties": {
    "iso:country":"AU",
    "sg:address":"Lot 1450 Suite 6A Winnellie Rd Opp C.U.B",
    "sg:city":"Winnellie",
    "sg:classifiers":[
        {
            "category":"Building & Trades",
            "subcategory":"Construction",
            "type":"Services"
        }
    ],
    "sg:phone":"+61 8 8947 0211",
    "sg:postcode":"0820",
    "sg:province":"NT",
    "sg:tags":[
        "contractor"
    ],
    "wof:name":"Contractor Accreditation Ltd",
    "wof:placetype":"venue"
},
  "geometry": {"coordinates":[130.870727539,-12.4263362885],"type":"Point"}
}