{
  "type": "Feature",
  "properties": {
    "addr:full":"3 Byrne Crt Mildura VIC 3500",
    "addr:housenumber":"3",
    "addr:postcode":"3500",
    "addr:street":"Byrne Crt",
    "iso:country":"AU",
    "sg:address":"3 Byrne Crt",
    "sg:city":"Mildura",
    "sg:classifiers":[
        {
            "category":"Freight",
            "type":"Transportation"
        }
    ],
    "sg:phone":"+61 3 5022 0955",
    "sg:postcode":"3500",
    "sg:province":"VIC",
    "sg:tags":[
        "transport",
        "refrigerated"
    ],
    "wof:name":"Mangan Transport Pty Ltd",
    "wof:placetype":"venue"
},
  "geometry": {"coordinates":[142.173583984,-34.1975746155],"type":"Point"}
}