{
  "type": "Feature",
  "properties": {
    "addr:full":"132 Sydney Rd Coburg VIC 3058",
    "addr:housenumber":"132",
    "addr:postcode":"3058",
    "addr:street":"Sydney Rd",
    "iso:country":"AU",
    "sg:address":"132 Sydney Rd",
    "sg:city":"Coburg",
    "sg:classifiers":[
        {
            "category":"Health Services",
            "subcategory":"Doctor",
            "type":"Services"
        }
    ],
    "sg:phone":"+61 3 9383 3355",
    "sg:postcode":"3058",
    "sg:province":"VIC",
    "sg:tags":[
        "medical",
        "practitioner"
    ],
    "wof:name":"Munir H H & B",
    "wof:placetype":"venue"
},
  "geometry": {"coordinates":[144.96496582,-37.7515983582],"type":"Point"}
}