{
  "type": "Feature",
  "properties": {
    "addr:full":"Bay 3, Lot 40 Apprentice Drv Berkeley Vale NSW 2261",
    "addr:housenumber":"3 lot 40",
    "addr:postcode":"2261",
    "addr:street":"Apprentice Drv",
    "iso:country":"AU",
    "sg:address":"Bay 3, Lot 40 Apprentice Drv",
    "sg:city":"Berkeley Vale",
    "sg:classifiers":[
        {
            "category":"Retail",
            "subcategory":"Auto Repair",
            "type":"Services"
        }
    ],
    "sg:phone":"+61 2 4388 4711",
    "sg:postcode":"2261",
    "sg:province":"NSW",
    "sg:tags":[
        "recapping",
        "repairing",
        "retreading",
        "tyre"
    ],
    "wof:name":"Berkeley Vale Tyre Service",
    "wof:placetype":"venue"
},
  "geometry": {"coordinates":[151.42497299999999,-33.328617],"type":"Point"}
}