{
  "type": "Feature",
  "properties": {
    "iso:country":"AU",
    "sg:address":"86 Higginbotham Rd",
    "sg:city":"Ryde",
    "sg:classifiers":[
        {
            "category":"Building & Trades",
            "subcategory":"Construction",
            "type":"Services"
        }
    ],
    "sg:phone":"+61 2 9808 3793",
    "sg:postcode":"2112",
    "sg:province":"NSW",
    "sg:tags":[
        "contractor"
    ],
    "wof:name":"G & N Bloomfield Pty Ltd",
    "wof:placetype":"venue"
},
  "geometry": {"coordinates":[151.12245178200001,-33.8151817322],"type":"Point"}
}