{
  "type": "Feature",
  "properties": {
    "iso:country":"AU",
    "sg:address":"12 Kenneth Pl",
    "sg:city":"Mannering Park",
    "sg:classifiers":[
        {
            "category":"Professional",
            "subcategory":"Management & Consulting",
            "type":"Services"
        }
    ],
    "sg:phone":"+61 418 455 164",
    "sg:postcode":"2259",
    "sg:province":"NSW",
    "sg:tags":[
        "consultant",
        "educational"
    ],
    "wof:name":"Science On Show Pty Ltd",
    "wof:placetype":"venue"
},
  "geometry": {"coordinates":[151.53263855,-33.1581459045],"type":"Point"}
}