{
  "type": "Feature",
  "properties": {
    "addr:full":"33 Mystery Bay Rd Mystery Bay NSW 2546",
    "addr:housenumber":"33",
    "addr:postcode":"2546",
    "addr:street":"Mystery Bay Rd Mystery",
    "iso:country":"AU",
    "sg:address":"33 Mystery Bay Rd",
    "sg:city":"Mystery Bay",
    "sg:classifiers":[
        {
            "category":"Building & Trades",
            "subcategory":"Construction",
            "type":"Services"
        }
    ],
    "sg:phone":"+61 2 4473 7600",
    "sg:postcode":"2546",
    "sg:province":"NSW",
    "sg:tags":[
        "road",
        "contractor"
    ],
    "wof:name":"Mystery Bay Excavations",
    "wof:placetype":"venue"
},
  "geometry": {"coordinates":[150.13206481899999,-36.3014717102],"type":"Point"}
}