{
  "type": "Feature",
  "properties": {
    "addr:full":"35/ 5 Ponderosa Pde Warriewood NSW 2102",
    "addr:housenumber":"35 / 5",
    "addr:postcode":"2102",
    "addr:street":"Ponderosa Pde",
    "iso:country":"AU",
    "sg:address":"35/ 5 Ponderosa Pde",
    "sg:city":"Warriewood",
    "sg:classifiers":[
        {
            "category":"Education",
            "subcategory":"School",
            "type":"Public Place"
        }
    ],
    "sg:phone":"+61 2 9979 5262",
    "sg:postcode":"2102",
    "sg:province":"NSW",
    "sg:tags":[
        "supply"
    ],
    "wof:name":"Kembo-Cuisenaire",
    "wof:placetype":"venue"
},
  "geometry": {"coordinates":[151.28829999999999,-33.680737],"type":"Point"}
}