{
  "type": "Feature",
  "properties": {
    "addr:full":"34 Marsden St Boorowa NSW 2586",
    "addr:housenumber":"34",
    "addr:postcode":"2586",
    "addr:street":"Marsden St",
    "iso:country":"AU",
    "sg:address":"34 Marsden St",
    "sg:city":"Boorowa",
    "sg:classifiers":[
        {
            "category":"Manufacturing",
            "subcategory":"Chemicals & Compounds",
            "type":"Manufacturing & Wholesale Goods"
        }
    ],
    "sg:phone":"+61 2 6385 3624",
    "sg:postcode":"2586",
    "sg:province":"NSW",
    "sg:tags":[
        "agricultural"
    ],
    "wof:name":"Thompson's Rural Supplies",
    "wof:placetype":"venue"
},
  "geometry": {"coordinates":[148.71627807600001,-34.4379234314],"type":"Point"}
}