{
  "type": "Feature",
  "properties": {
    "addr:full":"Shop 15, Bayswater Village Shopping Centre Bayswater VIC 3153",
    "addr:housenumber":"shop 15",
    "addr:postcode":"3153",
    "iso:country":"AU",
    "sg:address":"Shop 15, Bayswater Village Shopping Centre",
    "sg:city":"Bayswater",
    "sg:classifiers":[
        {
            "category":"Shopping",
            "subcategory":"Clothing, Apparel, & Fashions",
            "type":"Retail Goods"
        }
    ],
    "sg:phone":"+61 3 9738 0951",
    "sg:postcode":"3153",
    "sg:province":"VIC",
    "sg:tags":[
        "recycled",
        "clothing"
    ],
    "wof:name":"Bayswater New Beginnings",
    "wof:placetype":"venue"
},
  "geometry": {"coordinates":[145.27105712900001,-37.8386421204],"type":"Point"}
}