{
  "type": "Feature",
  "properties": {
    "addr:full":"2 Colorado Crt Morphett Vale SA 5162",
    "addr:housenumber":"2",
    "addr:postcode":"5162",
    "addr:street":"Colorado Crt",
    "iso:country":"AU",
    "sg:address":"2 Colorado Crt",
    "sg:city":"Morphett Vale",
    "sg:classifiers":[
        {
            "category":"Building & Trades",
            "subcategory":"Construction",
            "type":"Services"
        }
    ],
    "sg:phone":"+61 8 8387 3755",
    "sg:postcode":"5162",
    "sg:province":"SA",
    "sg:tags":[
        "window",
        "aluminium"
    ],
    "wof:name":"Sunbrite Aluminium",
    "wof:placetype":"venue"
},
  "geometry": {"coordinates":[138.546676636,-35.1096076965],"type":"Point"}
}