{
  "type": "Feature",
  "properties": {
    "addr:full":"PO Box 1878 Traralgon VIC 3844",
    "addr:postcode":"3844",
    "iso:country":"AU",
    "sg:address":"PO Box 1878",
    "sg:city":"Traralgon",
    "sg:classifiers":[
        {
            "category":"Social Services",
            "subcategory":"Retirement Home",
            "type":"Services"
        }
    ],
    "sg:phone":"+61 427 760 637",
    "sg:postcode":"3844",
    "sg:province":"VIC",
    "sg:tags":[
        "life",
        "coaching"
    ],
    "wof:name":"Imago Life By Design",
    "wof:placetype":"venue"
},
  "geometry": {"coordinates":[146.53814697300001,-38.1949501038],"type":"Point"}
}