{
  "type": "Feature",
  "properties": {
    "addr:full":"Ground Floor, 518 Hunter St Newcastle NSW 2300",
    "addr:housenumber":"518",
    "addr:postcode":"2300",
    "addr:street":"Hunter St",
    "iso:country":"AU",
    "sg:address":"Ground Floor, 518 Hunter St",
    "sg:city":"Newcastle",
    "sg:classifiers":[
        {
            "category":"Organizations",
            "subcategory":"Non-profit Organization",
            "type":"Services"
        }
    ],
    "sg:phone":"+61 2 4926 2103",
    "sg:postcode":"2300",
    "sg:province":"NSW",
    "sg:tags":[
        "environmental",
        "organisation",
        "conservation"
    ],
    "wof:name":"Conservation Volunteers Australia",
    "wof:placetype":"venue"
},
  "geometry": {"coordinates":[151.76916499999999,-32.927139],"type":"Point"}
}