{
  "type": "Feature",
  "properties": {
    "iso:country":"AU",
    "sg:address":"210 Beachworth Rd",
    "sg:city":"Wodonga",
    "sg:classifiers":[
        {
            "category":"Personal",
            "subcategory":"Massage",
            "type":"Services"
        }
    ],
    "sg:phone":"+61 409 698 756",
    "sg:postcode":"3690",
    "sg:province":"VIC",
    "sg:tags":[
        "therapy"
    ],
    "wof:name":"Thompson Pamela",
    "wof:placetype":"venue"
},
  "geometry": {"coordinates":[146.88795471200001,-36.1268959045],"type":"Point"}
}