{
  "type": "Feature",
  "properties": {
    "addr:full":"38 High St Hastings VIC 3915",
    "addr:housenumber":"38",
    "addr:postcode":"3915",
    "addr:street":"High St",
    "iso:country":"AU",
    "sg:address":"38 High St",
    "sg:city":"Hastings",
    "sg:classifiers":[
        {
            "category":"Personal",
            "subcategory":"Beauty Salon",
            "type":"Services"
        }
    ],
    "sg:phone":"+61 3 5979 3611",
    "sg:postcode":"3915",
    "sg:province":"VIC",
    "sg:tags":[
        "hairdresser"
    ],
    "wof:name":"Salon D&#039;Cazbar Unisex Hair Design",
    "wof:placetype":"venue"
},
  "geometry": {"coordinates":[145.19190979000001,-38.3075714111],"type":"Point"}
}