{
  "type": "Feature",
  "properties": {
    "addr:full":"Cnr Cartwright Ave & Woodward Crs Miller NSW 2168",
    "addr:housenumber":"cnr",
    "addr:postcode":"2168",
    "addr:street":"Cartwright Ave & Woodward Crs",
    "iso:country":"AU",
    "sg:address":"Cnr Cartwright Ave & Woodward Crs",
    "sg:city":"Miller",
    "sg:classifiers":[
        {
            "category":"Autos & Motor Vehicles",
            "subcategory":"Fuel & Gas Station",
            "type":"Retail Goods"
        }
    ],
    "sg:phone":"+61 2 9607 7205",
    "sg:postcode":"2168",
    "sg:province":"NSW",
    "wof:name":"Ampol",
    "wof:placetype":"venue"
},
  "geometry": {"coordinates":[150.88676452600001,-33.9200935364],"type":"Point"}
}