{
  "type": "Feature",
  "properties": {
    "iso:country":"AU",
    "sg:address":"Level 4 10 Rudd St",
    "sg:city":"Canberra",
    "sg:classifiers":[
        {
            "category":"Banks & Credit Unions",
            "subcategory":"Investment Brokerage",
            "type":"Services"
        }
    ],
    "sg:phone":"+61 2 6247 0677",
    "sg:postcode":"2601",
    "sg:province":"ACT",
    "wof:name":"Macquarie Investment Management Ltd",
    "wof:placetype":"venue"
},
  "geometry": {"coordinates":[149.12718200699999,-35.2767333984],"type":"Point"}
}