{
  "type": "Feature",
  "properties": {
    "addr:full":"23 Danielle Crs Heathmont VIC 3135",
    "addr:housenumber":"23",
    "addr:postcode":"3135",
    "addr:street":"Danielle Crs",
    "iso:country":"AU",
    "sg:address":"23 Danielle Crs",
    "sg:city":"Heathmont",
    "sg:classifiers":[
        {
            "category":"Building & Trades",
            "subcategory":"Cleaning & Sanitation",
            "type":"Services"
        }
    ],
    "sg:phone":"+61 3 9729 7396",
    "sg:postcode":"3135",
    "sg:province":"VIC",
    "sg:tags":[
        "window"
    ],
    "wof:name":"Gee's Window Cleaning Pty Ltd",
    "wof:placetype":"venue"
},
  "geometry": {"coordinates":[145.19889831500001,-37.8485450745],"type":"Point"}
}