{
  "type": "Feature",
  "properties": {
    "iso:country":"AU",
    "sg:address":"30 Howard Ave",
    "sg:city":"Dee Why",
    "sg:classifiers":[
        {
            "category":"Organizations",
            "subcategory":"Community Association",
            "type":"Services"
        }
    ],
    "sg:phone":"+61 2 9982 3044",
    "sg:postcode":"2099",
    "sg:province":"NSW",
    "sg:tags":[
        "organisation",
        "family",
        "welfare"
    ],
    "wof:name":"Volunteer Recruitment & Training Services",
    "wof:placetype":"venue"
},
  "geometry": {"coordinates":[151.28921508799999,-33.7526397705],"type":"Point"}
}