{
  "type": "Feature",
  "properties": {
    "iso:country":"AU",
    "sg:address":"22 Hill St",
    "sg:city":"Toowoomba",
    "sg:classifiers":[
        {
            "category":"Professional",
            "subcategory":"Detective & Security Services",
            "type":"Services"
        }
    ],
    "sg:phone":"+61 7 4639 1911",
    "sg:postcode":"4350",
    "sg:province":"QLD",
    "sg:tags":[
        "domestic",
        "alarm",
        "commercial",
        "burglar"
    ],
    "wof:name":"Ambush Security",
    "wof:placetype":"venue"
},
  "geometry": {"coordinates":[151.947723,-27.561989],"type":"Point"}
}