{
  "type": "Feature",
  "properties": {
    "addr:full":"Big Muster Drv Dinner Plain VIC 3898",
    "addr:postcode":"3898",
    "addr:street":"Muster Drv",
    "iso:country":"AU",
    "sg:address":"Big Muster Drv",
    "sg:city":"Dinner Plain",
    "sg:classifiers":[
        {
            "category":"Personal",
            "subcategory":"Day Spa",
            "type":"Services"
        }
    ],
    "sg:phone":"+61 3 5150 8880",
    "sg:postcode":"3898",
    "sg:province":"VIC",
    "wof:name":"Onsen Retreat & Spa",
    "wof:placetype":"venue"
},
  "geometry": {"coordinates":[147.238845825,-37.0218963623],"type":"Point"}
}