{
  "type": "Feature",
  "properties": {
    "addr:full":"Cnr Reynolds & Glendarragh Rds Templestowe VIC 3106",
    "addr:postcode":"3106",
    "addr:street":"Cnr",
    "iso:country":"AU",
    "sg:address":"Cnr Reynolds & Glendarragh Rds",
    "sg:city":"Templestowe",
    "sg:classifiers":[
        {
            "category":"Health Services",
            "subcategory":"Dentist",
            "type":"Services"
        }
    ],
    "sg:phone":"+61 3 9846 4522",
    "sg:postcode":"3106",
    "sg:province":"VIC",
    "wof:name":"A. Advance Medical Centre",
    "wof:placetype":"venue"
},
  "geometry": {"coordinates":[145.161743164,-37.7609214783],"type":"Point"}
}