{
  "type": "Feature",
  "properties": {
    "iso:country":"AU",
    "sg:address":"PO Box 541",
    "sg:city":"Mittagong",
    "sg:classifiers":[
        {
            "category":"Education",
            "subcategory":"Kindergarten",
            "type":"Public Place"
        }
    ],
    "sg:phone":"+61 407 391 397",
    "sg:postcode":"2575",
    "sg:province":"NSW",
    "sg:tags":[
        "pre-schools"
    ],
    "wof:name":"Northern Villages Mobile Pre-School",
    "wof:placetype":"venue"
},
  "geometry": {"coordinates":[150.44688415499999,-34.4510002136],"type":"Point"}
}