{
  "type": "Feature",
  "properties": {
    "addr:full":"Mulberry La Lockwood South VIC 3551",
    "addr:postcode":"3551",
    "addr:street":"Mulberry La",
    "iso:country":"AU",
    "sg:address":"Mulberry La",
    "sg:city":"Lockwood South",
    "sg:classifiers":[
        {
            "category":"Building & Trades",
            "subcategory":"Landscaping Services",
            "type":"Services"
        }
    ],
    "sg:phone":"+61 3 5435 4140",
    "sg:postcode":"3551",
    "sg:province":"VIC",
    "sg:tags":[
        "slashing",
        "contractor"
    ],
    "wof:name":"D. Pascoe",
    "wof:placetype":"venue"
},
  "geometry": {"coordinates":[144.13841247600001,-36.8949546814],"type":"Point"}
}