{
  "type": "Feature",
  "properties": {
    "addr:full":"22 Uligandi St Ettalong Beach NSW 2257",
    "addr:housenumber":"22",
    "addr:postcode":"2257",
    "addr:street":"Uligandi St",
    "iso:country":"AU",
    "sg:address":"22 Uligandi St",
    "sg:city":"Ettalong Beach",
    "sg:classifiers":[
        {
            "category":"Home & Garden",
            "subcategory":"Building Materials",
            "type":"Retail Goods"
        }
    ],
    "sg:phone":"+61 2 4342 8255",
    "sg:postcode":"2257",
    "sg:province":"NSW",
    "sg:tags":[
        "lawn",
        "cutting",
        "maintenance"
    ],
    "wof:name":"Aussie Home & lawn Services",
    "wof:placetype":"venue"
},
  "geometry": {"coordinates":[151.33203125,-33.5140533447],"type":"Point"}
}