{
  "type": "Feature",
  "properties": {
    "iso:country":"AU",
    "sg:address":"Old Hamilton Rd",
    "sg:city":"Horsham",
    "sg:classifiers":[
        {
            "category":"Professional",
            "subcategory":"Engineering",
            "type":"Services"
        }
    ],
    "sg:phone":"+61 3 5382 1560",
    "sg:postcode":"3400",
    "sg:province":"VIC",
    "sg:tags":[
        "engineer"
    ],
    "wof:name":"Pohlner T J & F L Pty Ltd",
    "wof:placetype":"venue"
},
  "geometry": {"coordinates":[142.20550537099999,-36.7398223877],"type":"Point"}
}