{
  "type": "Feature",
  "properties": {
    "addr:full":"4 Whitfield Ave Ashfield NSW 2131",
    "addr:housenumber":"4",
    "addr:postcode":"2131",
    "addr:street":"Whitfield Ave",
    "iso:country":"AU",
    "sg:address":"4 Whitfield Ave",
    "sg:city":"Ashfield",
    "sg:classifiers":[
        {
            "category":"Building & Trades",
            "subcategory":"Locksmith",
            "type":"Services"
        }
    ],
    "sg:phone":"+61 2 9799 2766",
    "sg:postcode":"2131",
    "sg:province":"NSW",
    "sg:tags":[
        "lock"
    ],
    "wof:name":"Polley R W",
    "wof:placetype":"venue"
},
  "geometry": {"coordinates":[151.117385864,-33.8959274292],"type":"Point"}
}