{
  "type": "Feature",
  "properties": {
    "addr:full":"Cnr Cavendish Rd & Stanley St (East) Coorparoo QLD 4151",
    "addr:postcode":"4151",
    "addr:street":"Cnr Cavendish Rd & Stanley St East",
    "iso:country":"AU",
    "sg:address":"Cnr Cavendish Rd & Stanley St (East)",
    "sg:city":"Coorparoo",
    "sg:classifiers":[
        {
            "category":"Education",
            "subcategory":"School",
            "type":"Public Place"
        }
    ],
    "sg:phone":"+61 7 3394 8888",
    "sg:postcode":"4151",
    "sg:province":"QLD",
    "sg:tags":[
        "state",
        "except",
        "nsw"
    ],
    "wof:name":"Coorparoo Secondary College",
    "wof:placetype":"venue"
},
  "geometry": {"coordinates":[153.06152343799999,-27.49817276],"type":"Point"}
}