{
  "type": "Feature",
  "properties": {
    "addr:full":"380a Oxford St Paddington NSW 2021",
    "addr:housenumber":"380a",
    "addr:postcode":"2021",
    "addr:street":"Oxford St",
    "iso:country":"AU",
    "sg:address":"380a Oxford St",
    "sg:city":"Paddington",
    "sg:classifiers":[
        {
            "category":"Shopping",
            "subcategory":"Shoes",
            "type":"Retail Goods"
        }
    ],
    "sg:phone":"+61 2 9380 9885",
    "sg:postcode":"2021",
    "sg:province":"NSW",
    "sg:tags":[
        "footwear"
    ],
    "wof:name":"Kagui",
    "wof:placetype":"venue"
},
  "geometry": {"coordinates":[151.23016357399999,-33.8867912292],"type":"Point"}
}