{
  "type": "Feature",
  "properties": {
    "iso:country":"AU",
    "sg:address":"3 Sayonara Rd",
    "sg:city":"Broome",
    "sg:classifiers":[
        {
            "category":"Building & Trades",
            "subcategory":"Construction",
            "type":"Services"
        }
    ],
    "sg:phone":"+61 8 9192 2855",
    "sg:postcode":"6725",
    "sg:province":"WA",
    "sg:tags":[
        "contractor"
    ],
    "wof:name":"Gregg K",
    "wof:placetype":"venue"
},
  "geometry": {"coordinates":[122.220542908,-17.9348526001],"type":"Point"}
}