{
  "type": "Feature",
  "properties": {
    "iso:country":"AU",
    "sg:address":"Cnr Piesse & Brookman Sts",
    "sg:city":"Boulder",
    "sg:classifiers":[
        {
            "category":"Education",
            "subcategory":"School",
            "type":"Public Place"
        }
    ],
    "sg:phone":"+61 8 9093 2728",
    "sg:postcode":"6432",
    "sg:province":"WA",
    "sg:tags":[
        "state",
        "except",
        "nsw"
    ],
    "wof:name":"Kalgoorlie School Of The Air",
    "wof:placetype":"venue"
},
  "geometry": {"coordinates":[121.489959717,-30.7830295563],"type":"Point"}
}