{
  "type": "Feature",
  "properties": {
    "addr:full":"4 Formby Rd Devonport TAS 7310",
    "addr:housenumber":"4",
    "addr:postcode":"7310",
    "addr:street":"Formby Rd",
    "iso:country":"AU",
    "sg:address":"4 Formby Rd",
    "sg:city":"Devonport",
    "sg:classifiers":[
        {
            "category":"Personal",
            "subcategory":"Skin Care",
            "type":"Services"
        }
    ],
    "sg:phone":"+61 3 6424 3972",
    "sg:postcode":"7310",
    "sg:province":"TAS",
    "sg:tags":[
        "leather",
        "merchant"
    ],
    "wof:name":"Simon Martin Whips & Leathercraft",
    "wof:placetype":"venue"
},
  "geometry": {"coordinates":[146.36340332,-41.193775177],"type":"Point"}
}