{
  "type": "Feature",
  "properties": {
    "iso:country":"AU",
    "sg:address":"2 Telina Drv",
    "sg:city":"Beaconsfield",
    "sg:classifiers":[
        {
            "category":"Health Services",
            "subcategory":"Health Practitioner",
            "type":"Services"
        }
    ],
    "sg:phone":"+61 7 4942 3033",
    "sg:postcode":"4740",
    "sg:province":"QLD",
    "sg:tags":[
        "osteopath"
    ],
    "wof:name":"Preventative Health Centre",
    "wof:placetype":"venue"
},
  "geometry": {"coordinates":[149.171707,-21.101116],"type":"Point"}
}