{
  "type": "Feature",
  "properties": {
    "iso:country":"AU",
    "sg:address":"106 Liverpool St",
    "sg:city":"Port Lincoln",
    "sg:classifiers":[
        {
            "category":"Autos & Motor Vehicles",
            "subcategory":"Auto Supplies",
            "type":"Retail Goods"
        }
    ],
    "sg:phone":"+61 8 8682 2044",
    "sg:postcode":"5606",
    "sg:province":"SA",
    "sg:tags":[
        "battery",
        "automotive"
    ],
    "wof:name":"Beaurepaires",
    "wof:placetype":"venue"
},
  "geometry": {"coordinates":[135.864563,-34.724464],"type":"Point"}
}