{
  "type": "Feature",
  "properties": {
    "iso:country":"AU",
    "sg:address":"Unit 9, 83- 85 Morayfield Rd",
    "sg:city":"Morayfield",
    "sg:classifiers":[
        {
            "category":"Banks & Credit Unions",
            "subcategory":"Bank",
            "type":"Services"
        }
    ],
    "sg:phone":"+61 7 5432 4433",
    "sg:postcode":"4506",
    "sg:province":"QLD",
    "sg:tags":[
        "broker",
        "mortgage"
    ],
    "wof:name":"Wizard",
    "wof:placetype":"venue"
},
  "geometry": {"coordinates":[152.94993591299999,-27.1102333069],"type":"Point"}
}