{
  "type": "Feature",
  "properties": {
    "addr:full":"61 Glenlyon Rd Brunswick VIC 3056",
    "addr:housenumber":"61",
    "addr:postcode":"3056",
    "addr:street":"Glenlyon Rd",
    "iso:country":"AU",
    "sg:address":"61 Glenlyon Rd",
    "sg:city":"Brunswick",
    "sg:classifiers":[
        {
            "category":"Education",
            "subcategory":"Kindergarten",
            "type":"Public Place"
        }
    ],
    "sg:phone":"+61 3 9380 8948",
    "sg:postcode":"3056",
    "sg:province":"VIC",
    "sg:tags":[
        "pre-schools"
    ],
    "wof:name":"Brunswick Kindergarten Inc",
    "wof:placetype":"venue"
},
  "geometry": {"coordinates":[144.96546935999999,-37.7718238831],"type":"Point"}
}