{
  "type": "Feature",
  "properties": {
    "addr:full":"250 Silvesters Rd Somersby NSW 2250",
    "addr:housenumber":"250",
    "addr:postcode":"2250",
    "addr:street":"Silvesters Rd",
    "iso:country":"AU",
    "sg:address":"250 Silvesters Rd",
    "sg:city":"Somersby",
    "sg:classifiers":[
        {
            "category":"Real Estate",
            "subcategory":"Architect",
            "type":"Services"
        }
    ],
    "sg:phone":"+61 2 4372 1513",
    "sg:postcode":"2250",
    "sg:province":"NSW",
    "wof:name":"Burl Ian Pty Ltd",
    "wof:placetype":"venue"
},
  "geometry": {"coordinates":[151.272872925,-33.3528404236],"type":"Point"}
}