{
  "type": "Feature",
  "properties": {
    "addr:full":"5 Myola Crt Carindale QLD 4152",
    "addr:housenumber":"5",
    "addr:postcode":"4152",
    "addr:street":"Myola Crt",
    "iso:country":"AU",
    "sg:address":"5 Myola Crt",
    "sg:city":"Carindale",
    "sg:classifiers":[
        {
            "category":"Bars & Pubs",
            "subcategory":"Dive Bar",
            "type":"Food & Drink"
        }
    ],
    "sg:phone":"+61 7 3843 2746",
    "sg:postcode":"4152",
    "sg:province":"QLD",
    "sg:tags":[
        "knitwear",
        "retail"
    ],
    "wof:name":"Bayliss R & M Pty Ltd",
    "wof:placetype":"venue"
},
  "geometry": {"coordinates":[153.106933594,-27.5136528015],"type":"Point"}
}