{
  "type": "Feature",
  "properties": {
    "addr:full":"16 Jetty Rd Largs Bay SA 5016",
    "addr:housenumber":"16",
    "addr:postcode":"5016",
    "addr:street":"Jetty Rd",
    "iso:country":"AU",
    "sg:address":"16 Jetty Rd",
    "sg:city":"Largs Bay",
    "sg:classifiers":[
        {
            "category":"Personal",
            "subcategory":"Beauty Salon",
            "type":"Services"
        }
    ],
    "sg:phone":"+61 8 8341 7266",
    "sg:postcode":"5016",
    "sg:province":"SA",
    "sg:tags":[
        "hairdresser"
    ],
    "wof:name":"Interlocks Hair Studio",
    "wof:placetype":"venue"
},
  "geometry": {"coordinates":[138.50062560999999,-34.8252830505],"type":"Point"}
}