{
  "type": "Feature",
  "properties": {
    "iso:country":"AU",
    "sg:address":"24 Eastern Rd",
    "sg:city":"South Melbourne",
    "sg:classifiers":[
        {
            "category":"Education",
            "subcategory":"University",
            "type":"Public Place"
        }
    ],
    "sg:phone":"+61 3 9699 8299",
    "sg:postcode":"3205",
    "sg:province":"VIC",
    "sg:tags":[
        "educational",
        "organisation",
        "cultural"
    ],
    "wof:name":"Arts Access Society",
    "wof:placetype":"venue"
},
  "geometry": {"coordinates":[144.964813,-37.831905],"type":"Point"}
}