{
  "type": "Feature",
  "properties": {
    "addr:full":"31 Cornhill St Ferntree Gully VIC 3156",
    "addr:housenumber":"31",
    "addr:postcode":"3156",
    "addr:street":"Cornhill St",
    "iso:country":"AU",
    "sg:address":"31 Cornhill St",
    "sg:city":"Ferntree Gully",
    "sg:classifiers":[
        {
            "category":"Retail",
            "subcategory":"Auto Repair",
            "type":"Services"
        }
    ],
    "sg:phone":"+61 3 9753 6972",
    "sg:postcode":"3156",
    "sg:province":"VIC",
    "sg:tags":[
        "bus",
        "truck"
    ],
    "wof:name":"Tyre Seal",
    "wof:placetype":"venue"
},
  "geometry": {"coordinates":[145.29580688499999,-37.894367218],"type":"Point"}
}