{
  "type": "Feature",
  "properties": {
    "iso:country":"AU",
    "sg:address":"19 Dawson St",
    "sg:city":"Coburg",
    "sg:classifiers":[
        {
            "category":"Shopping",
            "subcategory":"Stationery & Office Supplies",
            "type":"Retail Goods"
        }
    ],
    "sg:phone":"+61 3 9355 7666",
    "sg:postcode":"3058",
    "sg:province":"VIC",
    "sg:tags":[
        "packaging",
        "material"
    ],
    "wof:name":"Pack Synergy",
    "wof:placetype":"venue"
},
  "geometry": {"coordinates":[144.95826721200001,-37.7332000732],"type":"Point"}
}