{
  "type": "Feature",
  "properties": {
    "addr:full":"101 Warawarrup Rd Cookernup WA 6220",
    "addr:housenumber":"101",
    "addr:postcode":"6220",
    "addr:street":"Warawarrup Rd",
    "iso:country":"AU",
    "sg:address":"101 Warawarrup Rd",
    "sg:city":"Cookernup",
    "sg:classifiers":[
        {
            "category":"Building & Trades",
            "subcategory":"Landscaping Services",
            "type":"Services"
        }
    ],
    "sg:phone":"+61 8 9733 5157",
    "sg:postcode":"6220",
    "sg:province":"WA",
    "sg:tags":[
        "control",
        "weed"
    ],
    "wof:name":"Rural Weed Control",
    "wof:placetype":"venue"
},
  "geometry": {"coordinates":[115.89138,-33.014885],"type":"Point"}
}