{
  "type": "Feature",
  "properties": {
    "addr:full":"43 Lakeside Drv Reservoir VIC 3073",
    "addr:housenumber":"43",
    "addr:postcode":"3073",
    "addr:street":"Lakeside Drv",
    "iso:country":"AU",
    "sg:address":"43 Lakeside Drv",
    "sg:city":"Reservoir",
    "sg:classifiers":[
        {
            "category":"Manufacturing",
            "subcategory":"Tools & Machinery",
            "type":"Manufacturing & Wholesale Goods"
        }
    ],
    "sg:phone":"+61 3 9460 3622",
    "sg:postcode":"3073",
    "sg:province":"VIC",
    "sg:tags":[
        "wholesaler",
        "mfrs",
        "hosiery"
    ],
    "wof:name":"Merlo Hosiery Mills Pty Ltd",
    "wof:placetype":"venue"
},
  "geometry": {"coordinates":[144.98829650900001,-37.7076683044],"type":"Point"}
}