{
  "type": "Feature",
  "properties": {
    "addr:full":"Shop 3, 45 Burrendah Blv Willetton WA 6155",
    "addr:housenumber":"shop;45",
    "addr:postcode":"6155",
    "addr:street":"Burrendah Blv",
    "iso:country":"AU",
    "sg:address":"Shop 3, 45 Burrendah Blv",
    "sg:city":"Willetton",
    "sg:classifiers":[
        {
            "category":"Restaurant",
            "type":"Food & Drink"
        }
    ],
    "sg:phone":"+61 8 9310 9764",
    "sg:postcode":"6155",
    "sg:province":"WA",
    "sg:tags":[
        "pizza"
    ],
    "wof:name":"Eagle Boys Pizza",
    "wof:placetype":"venue"
},
  "geometry": {"coordinates":[115.881416,-32.057213],"type":"Point"}
}