{
  "type": "Feature",
  "properties": {
    "addr:full":"1 Eveline St Margate QLD 4019",
    "addr:housenumber":"1",
    "addr:postcode":"4019",
    "addr:street":"Eveline St",
    "iso:country":"AU",
    "sg:address":"1 Eveline St",
    "sg:city":"Margate",
    "sg:classifiers":[
        {
            "category":"Utilities",
            "subcategory":"Electric",
            "type":"Services"
        }
    ],
    "sg:phone":"+61 7 3283 3463",
    "sg:postcode":"4019",
    "sg:province":"QLD",
    "sg:tags":[
        "electrical",
        "contractor"
    ],
    "wof:name":"Rob Saurini Electrical",
    "wof:placetype":"venue"
},
  "geometry": {"coordinates":[153.110275269,-27.2486362457],"type":"Point"}
}