{
  "type": "Feature",
  "properties": {
    "iso:country":"AU",
    "sg:address":"15 Barrier St",
    "sg:city":"Fyshwick",
    "sg:classifiers":[
        {
            "category":"Manufacturing",
            "subcategory":"Petroleum Products",
            "type":"Manufacturing & Wholesale Goods"
        }
    ],
    "sg:phone":"+61 2 6239 3750",
    "sg:postcode":"2609",
    "sg:province":"ACT",
    "sg:tags":[
        "lubricant"
    ],
    "wof:name":"Hill & Co.",
    "wof:placetype":"venue"
},
  "geometry": {"coordinates":[149.17344665499999,-35.3294334412],"type":"Point"}
}