{
  "type": "Feature",
  "properties": {
    "addr:full":"56 Keon Pde Reservoir VIC 3073",
    "addr:housenumber":"56",
    "addr:postcode":"3073",
    "addr:street":"Keon Pde",
    "iso:country":"AU",
    "sg:address":"56 Keon Pde",
    "sg:city":"Reservoir",
    "sg:classifiers":[
        {
            "category":"Building & Trades",
            "subcategory":"Equipment Rental",
            "type":"Services"
        }
    ],
    "sg:phone":"+61 3 9462 4322",
    "sg:postcode":"3073",
    "sg:province":"VIC",
    "sg:tags":[
        "party",
        "hire"
    ],
    "sg:website":"http://www.ozparty.com.au",
    "wof:name":"Oz Party Hire",
    "wof:placetype":"venue"
},
  "geometry": {"coordinates":[145.01954650900001,-37.6954956055],"type":"Point"}
}