{
  "type": "Feature",
  "properties": {
    "addr:full":"Shop 2 Cnr Fletcher & Lawson St Byron Bay NSW 2481",
    "addr:housenumber":"shop 2",
    "addr:postcode":"2481",
    "addr:street":"Cnr Fletcher & Lawson St",
    "iso:country":"AU",
    "sg:address":"Shop 2 Cnr Fletcher & Lawson St",
    "sg:city":"Byron Bay",
    "sg:classifiers":[
        {
            "category":"Cafe",
            "type":"Food & Drink"
        }
    ],
    "sg:phone":"+61 2 6685 5909",
    "sg:postcode":"2481",
    "sg:province":"NSW",
    "wof:name":"Cafe Wunderbar",
    "wof:placetype":"venue"
},
  "geometry": {"coordinates":[153.61468505900001,-28.6427612305],"type":"Point"}
}