{
  "type": "Feature",
  "properties": {
    "addr:full":"Lamington National Park Rd Canungra QLD 4275",
    "addr:postcode":"4275",
    "addr:street":"Park Rd",
    "iso:country":"AU",
    "sg:address":"Lamington National Park Rd",
    "sg:city":"Canungra",
    "sg:classifiers":[
        {
            "category":"Utilities",
            "subcategory":"Water",
            "type":"Services"
        }
    ],
    "sg:phone":"+61 7 5543 5346",
    "sg:postcode":"4275",
    "sg:province":"QLD",
    "sg:tags":[
        "cartage"
    ],
    "wof:name":"Canungra Backhoe, Tipper Hire & Water Cartage",
    "wof:placetype":"venue"
},
  "geometry": {"coordinates":[153.163406372,-28.0196266174],"type":"Point"}
}