{
  "type": "Feature",
  "properties": {
    "iso:country":"AU",
    "sg:address":"Level 2 124 Bridport St",
    "sg:city":"Albert Park",
    "sg:classifiers":[
        {
            "category":"Personal",
            "subcategory":"Massage",
            "type":"Services"
        }
    ],
    "sg:phone":"+61 3 9686 7454",
    "sg:postcode":"3206",
    "sg:province":"VIC",
    "sg:tags":[
        "therapy"
    ],
    "wof:name":"The Pagoda Tree",
    "wof:placetype":"venue"
},
  "geometry": {"coordinates":[144.95611600000001,-37.840443],"type":"Point"}
}