{
  "type": "Feature",
  "properties": {
    "iso:country":"AU",
    "sg:address":"23 Della Torre Rd",
    "sg:city":"Moe",
    "sg:classifiers":[
        {
            "category":"Industrial Area",
            "type":"Public Place"
        }
    ],
    "sg:phone":"+61 3 5127 5000",
    "sg:postcode":"3825",
    "sg:province":"VIC",
    "sg:tags":[
        "rural",
        "shed"
    ],
    "wof:name":"Proline Sheds & Garages",
    "wof:placetype":"venue"
},
  "geometry": {"coordinates":[146.257904,-38.167614],"type":"Point"}
}