{
  "type": "Feature",
  "properties": {
    "addr:full":"Level 1, 293 Queen St Brisbane QLD 4000",
    "addr:housenumber":"293",
    "addr:postcode":"4000",
    "addr:street":"Queen St",
    "iso:country":"AU",
    "sg:address":"Level 1, 293 Queen St",
    "sg:city":"Brisbane",
    "sg:classifiers":[
        {
            "category":"Professional",
            "subcategory":"Accounting & Tax Preparation",
            "type":"Services"
        }
    ],
    "sg:phone":"+61 7 3211 8560",
    "sg:postcode":"4000",
    "sg:province":"QLD",
    "sg:tags":[
        "accountant",
        "auditor"
    ],
    "wof:name":"Alands Accountants",
    "wof:placetype":"venue"
},
  "geometry": {"coordinates":[153.02833557100001,-27.4674053192],"type":"Point"}
}