{
  "type": "Feature",
  "properties": {
    "addr:full":"132 Turpin Rd Labrador QLD 4215",
    "addr:housenumber":"132",
    "addr:postcode":"4215",
    "addr:street":"Turpin Rd",
    "iso:country":"AU",
    "sg:address":"132 Turpin Rd",
    "sg:city":"Labrador",
    "sg:classifiers":[
        {
            "category":"Professional",
            "subcategory":"Art Services",
            "type":"Services"
        }
    ],
    "sg:phone":"+61 7 5531 4199",
    "sg:postcode":"4215",
    "sg:province":"QLD",
    "sg:tags":[
        "graphic",
        "designer"
    ],
    "wof:name":"Complete Signs & Graphics",
    "wof:placetype":"venue"
},
  "geometry": {"coordinates":[153.402435303,-27.9464321136],"type":"Point"}
}