{
  "type": "Feature",
  "properties": {
    "addr:full":"10 Windarra Crt Sunbury VIC 3429",
    "addr:housenumber":"10",
    "addr:postcode":"3429",
    "addr:street":"Windarra Crt",
    "iso:country":"AU",
    "sg:address":"10 Windarra Crt",
    "sg:city":"Sunbury",
    "sg:classifiers":[
        {
            "category":"Professional",
            "subcategory":"Computer Services",
            "type":"Services"
        }
    ],
    "sg:phone":"+61 3 8746 8217",
    "sg:postcode":"3429",
    "sg:province":"VIC",
    "sg:tags":[
        "training"
    ],
    "wof:name":"The PC Tutor",
    "wof:placetype":"venue"
},
  "geometry": {"coordinates":[144.69720459000001,-37.5752105713],"type":"Point"}
}