{
  "type": "Feature",
  "properties": {
    "iso:country":"AU",
    "sg:address":"PO Box 6275",
    "sg:city":"Mackay Mail Centre",
    "sg:classifiers":[
        {
            "category":"Professional",
            "subcategory":"Business Services",
            "type":"Services"
        }
    ],
    "sg:phone":"+61 7 4944 0546",
    "sg:postcode":"4741",
    "sg:province":"QLD",
    "sg:tags":[
        "drafting"
    ],
    "wof:name":"Ten Drafting",
    "wof:placetype":"venue"
},
  "geometry": {"coordinates":[148.339584,-21.01993],"type":"Point"}
}