{
  "type": "Feature",
  "properties": {
    "addr:full":"26 Connemara Rd Gaven QLD 4211",
    "addr:housenumber":"26",
    "addr:postcode":"4211",
    "addr:street":"Connemara Rd",
    "iso:country":"AU",
    "sg:address":"26 Connemara Rd",
    "sg:city":"Gaven",
    "sg:classifiers":[
        {
            "category":"Utilities",
            "subcategory":"Water",
            "type":"Services"
        }
    ],
    "sg:phone":"+61 7 5561 7358",
    "sg:postcode":"4211",
    "sg:province":"QLD",
    "sg:tags":[
        "cartage"
    ],
    "wof:name":"Need Water Now Pty Ltd",
    "wof:placetype":"venue"
},
  "geometry": {"coordinates":[153.33302307100001,-27.938835144],"type":"Point"}
}