{
  "type": "Feature",
  "properties": {
    "iso:country":"AU",
    "sg:address":"1 St Johns Park Cntr",
    "sg:city":"St Johns Park",
    "sg:classifiers":[
        {
            "category":"Food & Beverages",
            "subcategory":"Supermarket",
            "type":"Retail Goods"
        }
    ],
    "sg:phone":"+61 2 9610 3231",
    "sg:postcode":"2176",
    "sg:province":"NSW",
    "sg:tags":[
        "grocery",
        "store"
    ],
    "wof:name":"Franklins Stores",
    "wof:placetype":"venue"
},
  "geometry": {"coordinates":[150.91551208499999,-33.8873634338],"type":"Point"}
}