{
  "type": "Feature",
  "properties": {
    "addr:full":"Studio 3A 37-39 O&#039;Connor St Broadway NSW 2007",
    "addr:housenumber":"3a 37-39 o",
    "addr:postcode":"2007",
    "addr:street":"Connor St",
    "iso:country":"AU",
    "sg:address":"Studio 3A 37-39 O&#039;Connor St",
    "sg:city":"Broadway",
    "sg:classifiers":[
        {
            "category":"Education",
            "subcategory":"Dance Studio",
            "type":"Public Place"
        }
    ],
    "sg:phone":"+61 2 9698 5782",
    "sg:postcode":"2007",
    "sg:province":"NSW",
    "sg:tags":[
        "venue",
        "tuition"
    ],
    "wof:name":"Broadway Ballroom",
    "wof:placetype":"venue"
},
  "geometry": {"coordinates":[151.199905395,-33.8842887878],"type":"Point"}
}