{
  "type": "Feature",
  "properties": {
    "addr:full":"222 Arthur St St George QLD 4487",
    "addr:housenumber":"222",
    "addr:postcode":"4487",
    "addr:street":"Arthur St",
    "iso:country":"AU",
    "sg:address":"222 Arthur St",
    "sg:city":"St George",
    "sg:classifiers":[
        {
            "category":"Building & Trades",
            "subcategory":"Landscaping Services",
            "type":"Services"
        }
    ],
    "sg:phone":"+61 7 4625 5320",
    "sg:postcode":"4487",
    "sg:province":"QLD",
    "sg:tags":[
        "control",
        "weed"
    ],
    "wof:name":"Andrew Dohle",
    "wof:placetype":"venue"
},
  "geometry": {"coordinates":[148.57771301299999,-28.0481643677],"type":"Point"}
}