{
  "type": "Feature",
  "properties": {
    "addr:full":"116 Lee St Wellington NSW 2820",
    "addr:housenumber":"116",
    "addr:postcode":"2820",
    "addr:street":"Lee St",
    "iso:country":"AU",
    "sg:address":"116 Lee St",
    "sg:city":"Wellington",
    "sg:classifiers":[
        {
            "category":"Health Services",
            "subcategory":"Dentist",
            "type":"Services"
        }
    ],
    "sg:phone":"+61 2 6845 1076",
    "sg:postcode":"2820",
    "sg:province":"NSW",
    "wof:name":"Wood D G",
    "wof:placetype":"venue"
},
  "geometry": {"coordinates":[148.94145202600001,-32.5521812439],"type":"Point"}
}