{
  "type": "Feature",
  "properties": {
    "iso:country":"AU",
    "sg:address":"23 Maryland St",
    "sg:city":"Stanthorpe",
    "sg:classifiers":[
        {
            "category":"Food & Beverages",
            "subcategory":"Bakery",
            "type":"Retail Goods"
        }
    ],
    "sg:phone":"+61 7 4681 1457",
    "sg:postcode":"4380",
    "sg:province":"QLD",
    "sg:tags":[
        "cake",
        "shop",
        "pastry"
    ],
    "wof:name":"Owens&#039; Bakery",
    "wof:placetype":"venue"
},
  "geometry": {"coordinates":[151.933929,-28.656414],"type":"Point"}
}