{
  "type": "Feature",
  "properties": {
    "addr:full":"21/ 5 Hudson Ave Castle Hill NSW 2154",
    "addr:housenumber":"21 / 5",
    "addr:postcode":"2154",
    "addr:street":"Hudson Ave",
    "iso:country":"AU",
    "sg:address":"21/ 5 Hudson Ave",
    "sg:city":"Castle Hill",
    "sg:classifiers":[
        {
            "category":"Wholesale",
            "subcategory":"Painting Supplies",
            "type":"Manufacturing & Wholesale Goods"
        }
    ],
    "sg:phone":"+61 2 9894 6566",
    "sg:postcode":"2154",
    "sg:province":"NSW",
    "sg:tags":[
        "wholesaler",
        "paint",
        "mfrs"
    ],
    "wof:name":"Newport Marine Technology Pty Ltd",
    "wof:placetype":"venue"
},
  "geometry": {"coordinates":[150.97465515100001,-33.731300354],"type":"Point"}
}