{
  "type": "Feature",
  "properties": {
    "addr:full":"Fcty3/ 43 Slater Pde Keilor East VIC 3033",
    "addr:postcode":"3033",
    "addr:street":"Slater Pde",
    "iso:country":"AU",
    "sg:address":"Fcty3/ 43 Slater Pde",
    "sg:city":"Keilor East",
    "sg:classifiers":[
        {
            "category":"Banks & Credit Unions",
            "subcategory":"Investment Brokerage",
            "type":"Services"
        }
    ],
    "sg:phone":"+61 3 9336 0122",
    "sg:postcode":"3033",
    "sg:province":"VIC",
    "sg:tags":[
        "mechanical",
        "oil",
        "seal"
    ],
    "wof:name":"Hydraulic Seals Pty Ltd",
    "wof:placetype":"venue"
},
  "geometry": {"coordinates":[144.85958862300001,-37.7320289612],"type":"Point"}
}