{
  "type": "Feature",
  "properties": {
    "iso:country":"AU",
    "sg:address":"31 Matipo St",
    "sg:city":"Doveton",
    "sg:classifiers":[
        {
            "category":"Retail",
            "subcategory":"Storage",
            "type":"Services"
        }
    ],
    "sg:phone":"+61 3 9791 4569",
    "sg:postcode":"3177",
    "sg:province":"VIC",
    "sg:tags":[
        "removal",
        "furniture"
    ],
    "wof:name":"M & J Furniture Removals and Storage",
    "wof:placetype":"venue"
},
  "geometry": {"coordinates":[145.235473633,-37.992515564],"type":"Point"}
}