{
  "type": "Feature",
  "properties": {
    "iso:country":"AU",
    "sg:address":"PO Box 241",
    "sg:city":"Thornlie PLB",
    "sg:classifiers":[
        {
            "category":"Building & Trades",
            "subcategory":"Cleaning & Sanitation",
            "type":"Services"
        }
    ],
    "sg:phone":"+61 401 644 286",
    "sg:postcode":"6988",
    "sg:province":"WA",
    "sg:tags":[
        "cleaner",
        "repairer",
        "roof"
    ],
    "wof:name":"A1 Access Roofing",
    "wof:placetype":"venue"
},
  "geometry": {"coordinates":[115.962212,-32.055225],"type":"Point"}
}