{
  "type": "Feature",
  "properties": {
    "addr:full":"522 The Entrance Rd Erina Heights NSW 2260",
    "addr:housenumber":"522",
    "addr:postcode":"2260",
    "addr:street":"The Entrance Rd",
    "iso:country":"AU",
    "sg:address":"522 The Entrance Rd",
    "sg:city":"Erina Heights",
    "sg:classifiers":[
        {
            "category":"Manufacturing",
            "subcategory":"Glass & Minerals",
            "type":"Manufacturing & Wholesale Goods"
        }
    ],
    "sg:phone":"+61 2 4365 0977",
    "sg:postcode":"2260",
    "sg:province":"NSW",
    "sg:tags":[
        "stained"
    ],
    "wof:name":"Echidna Studios",
    "wof:placetype":"venue"
},
  "geometry": {"coordinates":[151.417755,-33.426849],"type":"Point"}
}