{
  "type": "Feature",
  "properties": {
    "addr:full":"Shop 24/ Centro Mall Goulburn NSW 2580",
    "addr:housenumber":"shop 24 / centro mall",
    "addr:postcode":"2580",
    "iso:country":"AU",
    "sg:address":"Shop 24/ Centro Mall",
    "sg:city":"Goulburn",
    "sg:classifiers":[
        {
            "category":"Health Services",
            "subcategory":"Optometrist",
            "type":"Services"
        }
    ],
    "sg:phone":"+61 2 4821 5120",
    "sg:postcode":"2580",
    "sg:province":"NSW",
    "wof:name":"Bernadette Moran",
    "wof:placetype":"venue"
},
  "geometry": {"coordinates":[149.73440551799999,-34.7438926697],"type":"Point"}
}