{
  "type": "Feature",
  "properties": {
    "iso:country":"AU",
    "sg:address":"590 Main Rd",
    "sg:city":"Cororooke",
    "sg:classifiers":[
        {
            "category":"Utilities",
            "subcategory":"Electric",
            "type":"Services"
        }
    ],
    "sg:phone":"+61 428 521 127",
    "sg:postcode":"3254",
    "sg:province":"VIC",
    "sg:tags":[
        "electrical",
        "contractor"
    ],
    "wof:name":"Pownceby Brett",
    "wof:placetype":"venue"
},
  "geometry": {"coordinates":[143.530045,-38.29644],"type":"Point"}
}