{
  "type": "Feature",
  "properties": {
    "addr:full":"183 Hare St Echuca VIC 3564",
    "addr:housenumber":"183",
    "addr:postcode":"3564",
    "addr:street":"Hare St",
    "iso:country":"AU",
    "sg:address":"183 Hare St",
    "sg:city":"Echuca",
    "sg:classifiers":[
        {
            "category":"Travel",
            "subcategory":"Hotels & Motels",
            "type":"Entertainment"
        }
    ],
    "sg:phone":"+61 3 5482 1266",
    "sg:postcode":"3564",
    "sg:province":"VIC",
    "sg:tags":[
        "accommodation"
    ],
    "wof:name":"Harvest Hotel",
    "wof:placetype":"venue"
},
  "geometry": {"coordinates":[144.748977661,-36.1262054443],"type":"Point"}
}