{
  "type": "Feature",
  "properties": {
    "addr:full":"550 Portrush Rd Glen Osmond SA 5064",
    "addr:housenumber":"550",
    "addr:postcode":"5064",
    "addr:street":"Portrush Rd",
    "iso:country":"AU",
    "sg:address":"550 Portrush Rd",
    "sg:city":"Glen Osmond",
    "sg:classifiers":[
        {
            "category":"Health Services",
            "subcategory":"Nursing And Care Facility",
            "type":"Services"
        }
    ],
    "sg:phone":"+61 8 8379 1449",
    "sg:postcode":"5064",
    "sg:province":"SA",
    "sg:tags":[
        "home"
    ],
    "wof:name":"Life Care",
    "wof:placetype":"venue"
},
  "geometry": {"coordinates":[138.643966675,-34.9571800232],"type":"Point"}
}