{
  "type": "Feature",
  "properties": {
    "iso:country":"AU",
    "sg:address":"Government Rd",
    "sg:city":"Eden",
    "sg:classifiers":[
        {
            "category":"Farming",
            "subcategory":"Vineyard",
            "type":"Manufacturing & Wholesale Goods"
        }
    ],
    "sg:phone":"+61 2 6496 4145",
    "sg:postcode":"2551",
    "sg:province":"NSW",
    "sg:tags":[
        "winery"
    ],
    "wof:name":"Disaster Bay Chillies",
    "wof:placetype":"venue"
},
  "geometry": {"coordinates":[149.90994262699999,-37.0422210693],"type":"Point"}
}