{
  "type": "Feature",
  "properties": {
    "iso:country":"AU",
    "sg:address":"24 East St",
    "sg:city":"Clifton",
    "sg:classifiers":[
        {
            "category":"Autos & Motor Vehicles",
            "subcategory":"Fuel & Gas Station",
            "type":"Retail Goods"
        }
    ],
    "sg:phone":"+61 7 4697 3388",
    "sg:postcode":"4361",
    "sg:province":"QLD",
    "wof:name":"R & A Motors",
    "wof:placetype":"venue"
},
  "geometry": {"coordinates":[151.90834045400001,-27.9328632355],"type":"Point"}
}