{
  "type": "Feature",
  "properties": {
    "addr:full":"Shop 3 3 Bent St Lindfield NSW 2070",
    "addr:housenumber":"shop;3",
    "addr:postcode":"2070",
    "addr:street":"Bent St",
    "iso:country":"AU",
    "sg:address":"Shop 3 3 Bent St",
    "sg:city":"Lindfield",
    "sg:classifiers":[
        {
            "category":"Personal",
            "subcategory":"Beauty Salon",
            "type":"Services"
        }
    ],
    "sg:phone":"+61 2 9415 6410",
    "sg:postcode":"2070",
    "sg:province":"NSW",
    "sg:tags":[
        "hairdresser"
    ],
    "wof:name":"Shorewaves Hair Studio",
    "wof:placetype":"venue"
},
  "geometry": {"coordinates":[151.167282105,-33.775062561],"type":"Point"}
}