{
  "type": "Feature",
  "properties": {
    "addr:full":"Unit 5, 6 Wynyard Gr Wattle Park SA 5066",
    "addr:housenumber":"6",
    "addr:postcode":"5066",
    "addr:street":"Wynyard Gr",
    "iso:country":"AU",
    "sg:address":"Unit 5, 6 Wynyard Gr",
    "sg:city":"Wattle Park",
    "sg:classifiers":[
        {
            "category":"Sports & Exercise",
            "subcategory":"Sports Center",
            "type":"Entertainment"
        }
    ],
    "sg:phone":"+61 412 182 646",
    "sg:postcode":"5066",
    "sg:province":"SA",
    "sg:tags":[
        "coach",
        "tennis"
    ],
    "wof:name":"Dane Bennett Tennis Coaching",
    "wof:placetype":"venue"
},
  "geometry": {"coordinates":[138.671676636,-34.9254722595],"type":"Point"}
}