{
  "type": "Feature",
  "properties": {
    "addr:full":"1879 Albany Hwy Maddington WA 6109",
    "addr:housenumber":"1879",
    "addr:postcode":"6109",
    "addr:street":"Albany Hwy",
    "iso:country":"AU",
    "sg:address":"1879 Albany Hwy",
    "sg:city":"Maddington",
    "sg:classifiers":[
        {
            "category":"Autos & Motor Vehicles",
            "subcategory":"Automobile Sales",
            "type":"Retail Goods"
        }
    ],
    "sg:phone":"+61 8 9459 9917",
    "sg:postcode":"6109",
    "sg:province":"WA",
    "sg:tags":[
        "car",
        "used"
    ],
    "wof:name":"John Murray Autos",
    "wof:placetype":"venue"
},
  "geometry": {"coordinates":[115.98123169,-32.0500793457],"type":"Point"}
}