{
  "type": "Feature",
  "properties": {
    "addr:full":"6 Forrest Ave Phillip Island VIC 3922",
    "addr:housenumber":"6",
    "addr:postcode":"3922",
    "addr:street":"Forrest Ave Phillip Island",
    "iso:country":"AU",
    "sg:address":"6 Forrest Ave",
    "sg:city":"Phillip Island",
    "sg:classifiers":[
        {
            "category":"Personal",
            "subcategory":"Massage",
            "type":"Services"
        }
    ],
    "sg:phone":"+61 3 5956 7886",
    "sg:postcode":"3922",
    "sg:province":"VIC",
    "sg:tags":[
        "therapy"
    ],
    "sg:website":"http://www.islandhealing.com.au",
    "wof:name":"Island Healing - Health Spa & Fitness Centre",
    "wof:placetype":"venue"
},
  "geometry": {"coordinates":[145.21527099599999,-38.4884300232],"type":"Point"}
}