{
  "type": "Feature",
  "properties": {
    "addr:full":"1/ 181 Hutton St Osborne Park WA 6017",
    "addr:housenumber":"/ 181",
    "addr:postcode":"6017",
    "addr:street":"Hutton St",
    "iso:country":"AU",
    "sg:address":"1/ 181 Hutton St",
    "sg:city":"Osborne Park",
    "sg:classifiers":[
        {
            "category":"Health Services",
            "subcategory":"Doctor",
            "type":"Services"
        }
    ],
    "sg:phone":"+61 8 9349 1300",
    "sg:postcode":"6017",
    "sg:province":"WA",
    "sg:tags":[
        "medical",
        "practitioner"
    ],
    "wof:name":"Partridge Noel Dr",
    "wof:placetype":"venue"
},
  "geometry": {"coordinates":[115.827140808,-31.8966121674],"type":"Point"}
}