{
  "type": "Feature",
  "properties": {
    "iso:country":"AU",
    "sg:address":"Lvl 1/ 456 Spencer St",
    "sg:city":"West Melbourne",
    "sg:classifiers":[
        {
            "category":"Professional",
            "subcategory":"Accounting & Tax Preparation",
            "type":"Services"
        }
    ],
    "sg:phone":"+61 3 9348 9855",
    "sg:postcode":"3003",
    "sg:province":"VIC",
    "sg:tags":[
        "accountant",
        "auditor"
    ],
    "wof:name":"Unal & Associates",
    "wof:placetype":"venue"
},
  "geometry": {"coordinates":[144.94979858400001,-37.8095588684],"type":"Point"}
}