{
  "type": "Feature",
  "properties": {
    "addr:full":"962 Old Princes Hwy Engadine NSW 2233",
    "addr:housenumber":"962",
    "addr:postcode":"2233",
    "addr:street":"Old Princes Hwy",
    "iso:country":"AU",
    "sg:address":"962 Old Princes Hwy",
    "sg:city":"Engadine",
    "sg:classifiers":[
        {
            "category":"Shopping",
            "subcategory":"Bicycles & Sporting Goods",
            "type":"Retail Goods"
        }
    ],
    "sg:phone":"+61 2 9520 2322",
    "sg:postcode":"2233",
    "sg:province":"NSW",
    "sg:tags":[
        "chemical",
        "equipment",
        "pool",
        "swimming"
    ],
    "wof:name":"Sparkle Pools & Spas Pty Ltd",
    "wof:placetype":"venue"
},
  "geometry": {"coordinates":[151.01690673799999,-34.064704895],"type":"Point"}
}