{
  "type": "Feature",
  "properties": {
    "addr:full":"Lot 3245 Muramats Rd, Berrimah NT 0828",
    "addr:housenumber":"3245",
    "addr:postcode":"nt 0828",
    "addr:street":"Muramats Rd",
    "iso:country":"AU",
    "sg:address":"Lot 3245 Muramats Rd,",
    "sg:city":"Berrimah",
    "sg:classifiers":[
        {
            "category":"Transit Center",
            "subcategory":"Freight",
            "type":"Transportation"
        }
    ],
    "sg:phone":"+61 8 8947 1118",
    "sg:postcode":"0828",
    "sg:province":"NT",
    "sg:tags":[
        "agent",
        "shipping"
    ],
    "wof:name":"Tiwi Barge Services Pty Ltd",
    "wof:placetype":"venue"
},
  "geometry": {"coordinates":[130.92489624000001,-12.4796762466],"type":"Point"}
}