{
  "type": "Feature",
  "properties": {
    "addr:full":"3 Vicki Pl Victoria Point QLD 4165",
    "addr:housenumber":"3",
    "addr:postcode":"4165",
    "addr:street":"Vicki Pl",
    "iso:country":"AU",
    "sg:address":"3 Vicki Pl",
    "sg:city":"Victoria Point",
    "sg:classifiers":[
        {
            "category":"Building & Trades",
            "subcategory":"Landscaping Services",
            "type":"Services"
        }
    ],
    "sg:phone":"+61 1300 551 734",
    "sg:postcode":"4165",
    "sg:province":"QLD",
    "sg:tags":[
        "stump",
        "tree",
        "felling",
        "removal"
    ],
    "wof:name":"Perfect Finish Lawns & Gardens",
    "wof:placetype":"venue"
},
  "geometry": {"coordinates":[153.307937622,-27.5842552185],"type":"Point"}
}