{
  "type": "Feature",
  "properties": {
    "addr:full":"469 Regency Rd Prospect SA 5082",
    "addr:housenumber":"469",
    "addr:postcode":"5082",
    "addr:street":"Regency Rd",
    "iso:country":"AU",
    "sg:address":"469 Regency Rd",
    "sg:city":"Prospect",
    "sg:classifiers":[
        {
            "category":"Real Estate",
            "subcategory":"Real Estate Services",
            "type":"Services"
        }
    ],
    "sg:phone":"+61 8 8269 3399",
    "sg:postcode":"5082",
    "sg:province":"SA",
    "sg:tags":[
        "valuer"
    ],
    "wof:name":"Elders Real Estate Valuations - North Adelaide",
    "wof:placetype":"venue"
},
  "geometry": {"coordinates":[138.60029602,-34.873588562],"type":"Point"}
}