{
  "type": "Feature",
  "properties": {
    "iso:country":"AU",
    "sg:address":"Shop 4, 8 Main North Rd",
    "sg:city":"Elizabeth",
    "sg:classifiers":[
        {
            "category":"Real Estate",
            "subcategory":"Real Estate Agent",
            "type":"Services"
        }
    ],
    "sg:phone":"+61 8 8284 0055",
    "sg:postcode":"5112",
    "sg:province":"SA",
    "wof:name":"Ray White Craigmore/Elizabeth",
    "wof:placetype":"venue"
},
  "geometry": {"coordinates":[138.672607422,-34.7171020508],"type":"Point"}
}