{
  "type": "Feature",
  "properties": {
    "iso:country":"AU",
    "sg:address":"267 Rockingham Rd",
    "sg:city":"Spearwood",
    "sg:classifiers":[
        {
            "category":"Social Services",
            "subcategory":"Child Care",
            "type":"Services"
        }
    ],
    "sg:phone":"+61 8 9434 3167",
    "sg:postcode":"6163",
    "sg:province":"WA",
    "wof:name":"Little Woodpeckers Childcare Centre",
    "wof:placetype":"venue"
},
  "geometry": {"coordinates":[115.782608,-32.095844],"type":"Point"}
}