{
  "type": "Feature",
  "properties": {
    "addr:full":"417 Rokeby Rd Subiaco WA 6008",
    "addr:housenumber":"417",
    "addr:postcode":"6008",
    "addr:street":"Rokeby Rd",
    "iso:country":"AU",
    "sg:address":"417 Rokeby Rd",
    "sg:city":"Subiaco",
    "sg:classifiers":[
        {
            "category":"Government",
            "subcategory":"Court House",
            "type":"Public Place"
        }
    ],
    "sg:phone":"+61 417 997 016",
    "sg:postcode":"6008",
    "sg:province":"WA",
    "sg:tags":[
        "personal",
        "marriage",
        "family",
        "counselling"
    ],
    "wof:name":"Trauma Recovery Support Network",
    "wof:placetype":"venue"
},
  "geometry": {"coordinates":[115.82373809800001,-31.9563083649],"type":"Point"}
}