{
  "type": "Feature",
  "properties": {
    "addr:full":"PO Box 3054 Frankston East VIC 3199",
    "addr:postcode":"3199",
    "iso:country":"AU",
    "sg:address":"PO Box 3054",
    "sg:city":"Frankston East",
    "sg:classifiers":[
        {
            "category":"Building & Trades",
            "subcategory":"Landscaping Services",
            "type":"Services"
        }
    ],
    "sg:phone":"+61 417 394 954",
    "sg:postcode":"3199",
    "sg:province":"VIC",
    "sg:tags":[
        "designer",
        "landscape",
        "contractor"
    ],
    "wof:name":"Hi-Tech Paving",
    "wof:placetype":"venue"
},
  "geometry": {"coordinates":[144.968505859,-37.7856292725],"type":"Point"}
}