{
  "type": "Feature",
  "properties": {
    "iso:country":"AU",
    "sg:address":"177 Kissing Point Rd",
    "sg:city":"Turramurra",
    "sg:classifiers":[
        {
            "category":"Real Estate",
            "subcategory":"Real Estate Services",
            "type":"Services"
        }
    ],
    "sg:phone":"+61 2 9488 8973",
    "sg:postcode":"2074",
    "sg:province":"NSW",
    "sg:tags":[
        "consultant",
        "property"
    ],
    "wof:name":"Eagleview Services Pty Ltd",
    "wof:placetype":"venue"
},
  "geometry": {"coordinates":[151.11247253400001,-33.7450218201],"type":"Point"}
}