{
  "type": "Feature",
  "properties": {
    "addr:full":"4 Romsey St Waitara NSW 2077",
    "addr:housenumber":"4",
    "addr:postcode":"2077",
    "addr:street":"Romsey St",
    "iso:country":"AU",
    "sg:address":"4 Romsey St",
    "sg:city":"Waitara",
    "sg:classifiers":[
        {
            "category":"Retail",
            "subcategory":"Auto Repair",
            "type":"Services"
        }
    ],
    "sg:phone":"+61 2 9489 2261",
    "sg:postcode":"2077",
    "sg:province":"NSW",
    "sg:tags":[
        "transmission",
        "automotive",
        "car"
    ],
    "wof:name":"Allstates Automotive Transmissions Pty Ltd",
    "wof:placetype":"venue"
},
  "geometry": {"coordinates":[151.10304260300001,-33.7099990845],"type":"Point"}
}