{
  "type": "Feature",
  "properties": {
    "iso:country":"AU",
    "sg:address":"93 Miller Rd",
    "sg:city":"Villawood",
    "sg:classifiers":[
        {
            "category":"Food & Beverages",
            "subcategory":"Supermarket",
            "type":"Retail Goods"
        }
    ],
    "sg:phone":"+61 2 9644 5698",
    "sg:postcode":"2163",
    "sg:province":"NSW",
    "sg:tags":[
        "grocery",
        "store"
    ],
    "wof:name":"Cut Price Food Markets",
    "wof:placetype":"venue"
},
  "geometry": {"coordinates":[150.992950439,-33.8839149475],"type":"Point"}
}