{
  "type": "Feature",
  "properties": {
    "iso:country":"AU",
    "sg:address":"PO Box 110",
    "sg:city":"Enmore",
    "sg:classifiers":[
        {
            "category":"Professional",
            "subcategory":"Art Services",
            "type":"Services"
        }
    ],
    "sg:phone":"+61 2 9569 0462",
    "sg:postcode":"2042",
    "sg:province":"NSW",
    "sg:tags":[
        "graphic",
        "designer"
    ],
    "wof:name":"Black Moggie Graphics",
    "wof:placetype":"venue"
},
  "geometry": {"coordinates":[151.17117300000001,-33.899288],"type":"Point"}
}