{
  "type": "Feature",
  "properties": {
    "iso:country":"AU",
    "sg:address":"95 Hume St",
    "sg:city":"Wodonga",
    "sg:classifiers":[
        {
            "category":"Education",
            "subcategory":"Special Training",
            "type":"Public Place"
        }
    ],
    "sg:phone":"+61 2 6056 0185",
    "sg:postcode":"3689",
    "sg:province":"VIC",
    "sg:tags":[
        "development"
    ],
    "wof:name":"Vecci Apprenticeships Services",
    "wof:placetype":"venue"
},
  "geometry": {"coordinates":[146.88597100000001,-36.122051],"type":"Point"}
}