{
  "type": "Feature",
  "properties": {
    "addr:full":"43 Docker St Wangaratta VIC 3676",
    "addr:housenumber":"43",
    "addr:postcode":"3676",
    "addr:street":"Docker St",
    "iso:country":"AU",
    "sg:address":"43 Docker St",
    "sg:city":"Wangaratta",
    "sg:classifiers":[
        {
            "category":"Wholesale",
            "subcategory":"Medical Equipment & Supplies",
            "type":"Manufacturing & Wholesale Goods"
        }
    ],
    "sg:phone":"+61 1800 800 515",
    "sg:postcode":"3676",
    "sg:province":"VIC",
    "sg:tags":[
        "aids",
        "hearing"
    ],
    "wof:name":"Terence Ryan Hearing Aids",
    "wof:placetype":"venue"
},
  "geometry": {"coordinates":[146.31596400000001,-36.353691],"type":"Point"}
}