{
  "type": "Feature",
  "properties": {
    "iso:country":"AU",
    "sg:address":"301 Goodwood Rd",
    "sg:city":"Kings Park",
    "sg:classifiers":[
        {
            "category":"Shopping",
            "subcategory":"Bicycles & Sporting Goods",
            "type":"Retail Goods"
        }
    ],
    "sg:phone":"+61 8 8272 3332",
    "sg:postcode":"5034",
    "sg:province":"SA",
    "sg:tags":[
        "chemical",
        "equipment",
        "pool",
        "swimming"
    ],
    "wof:name":"Pool Owners Club Of S.A. Incorporated",
    "wof:placetype":"venue"
},
  "geometry": {"coordinates":[138.59071350100001,-34.9632530212],"type":"Point"}
}