{
  "type": "Feature",
  "properties": {
    "iso:country":"AU",
    "sg:address":"1 Jardine St",
    "sg:city":"Fairy Meadow",
    "sg:classifiers":[
        {
            "category":"Professional",
            "subcategory":"Engineering",
            "type":"Services"
        }
    ],
    "sg:phone":"+61 2 4285 4199",
    "sg:postcode":"2519",
    "sg:province":"NSW",
    "sg:tags":[
        "diesel",
        "engineer"
    ],
    "wof:name":"Illawarra Diesel Servicing",
    "wof:placetype":"venue"
},
  "geometry": {"coordinates":[150.898254,-34.388561],"type":"Point"}
}