{
  "type": "Feature",
  "properties": {
    "iso:country":"AU",
    "sg:address":"25 Dover Drv",
    "sg:city":"Burleigh Heads",
    "sg:classifiers":[
        {
            "category":"Building & Trades",
            "subcategory":"Construction",
            "type":"Services"
        }
    ],
    "sg:phone":"+61 7 5520 1200",
    "sg:postcode":"4220",
    "sg:province":"QLD",
    "sg:tags":[
        "window",
        "aluminium"
    ],
    "wof:name":"C-View Windows",
    "wof:placetype":"venue"
},
  "geometry": {"coordinates":[153.42684936500001,-28.1036758423],"type":"Point"}
}