{
  "type": "Feature",
  "properties": {
    "iso:country":"AU",
    "sg:address":"PO Box 2443",
    "sg:city":"North Parramatta",
    "sg:classifiers":[
        {
            "category":"Transit Center",
            "subcategory":"Freight",
            "type":"Transportation"
        }
    ],
    "sg:phone":"+61 1300 768 662",
    "sg:postcode":"1750",
    "sg:province":"NSW",
    "sg:tags":[
        "equipment",
        "transport",
        "road",
        "vehicle"
    ],
    "wof:name":"Sydney Traffic Operations Pty Ltd",
    "wof:placetype":"venue"
},
  "geometry": {"coordinates":[151.010712,-33.798038],"type":"Point"}
}