{
  "type": "Feature",
  "properties": {
    "addr:full":"Cedar St Dorrigo NSW 2453",
    "addr:postcode":"2453",
    "addr:street":"Cedar St",
    "iso:country":"AU",
    "sg:address":"Cedar St",
    "sg:city":"Dorrigo",
    "sg:classifiers":[
        {
            "category":"Social Services",
            "subcategory":"Child Care",
            "type":"Services"
        }
    ],
    "sg:phone":"+61 2 6657 2078",
    "sg:postcode":"2453",
    "sg:province":"NSW",
    "wof:name":"Dorrigo Pre School Association Incorporated Inc.",
    "wof:placetype":"venue"
},
  "geometry": {"coordinates":[152.711197,-30.341763],"type":"Point"}
}