{
  "type": "Feature",
  "properties": {
    "iso:country":"AU",
    "sg:address":"42 Hurrell Way",
    "sg:city":"Rockingham",
    "sg:classifiers":[
        {
            "category":"Retail",
            "subcategory":"Car Wash",
            "type":"Services"
        }
    ],
    "sg:phone":"+61 8 9592 2522",
    "sg:postcode":"6168",
    "sg:province":"WA",
    "sg:tags":[
        "truck",
        "cleaning"
    ],
    "wof:name":"Rhino Car Wash Rockingham",
    "wof:placetype":"venue"
},
  "geometry": {"coordinates":[115.758438,-32.283283],"type":"Point"}
}