{
  "type": "Feature",
  "properties": {
    "iso:country":"AU",
    "sg:address":"10 Best Rd",
    "sg:city":"Seven Hills",
    "sg:classifiers":[
        {
            "category":"Building & Trades",
            "subcategory":"Construction",
            "type":"Services"
        }
    ],
    "sg:phone":"+61 2 9688 3031",
    "sg:postcode":"2147",
    "sg:province":"NSW",
    "sg:tags":[
        "concrete",
        "contractor"
    ],
    "wof:name":"Kennelly's Concrete Contractors",
    "wof:placetype":"venue"
},
  "geometry": {"coordinates":[150.94134521500001,-33.7835159302],"type":"Point"}
}