{
  "type": "Feature",
  "properties": {
    "addr:full":"188 Kerry Rd Archerfield QLD 4108",
    "addr:housenumber":"188",
    "addr:postcode":"4108",
    "addr:street":"Kerry Rd",
    "iso:country":"AU",
    "sg:address":"188 Kerry Rd",
    "sg:city":"Archerfield",
    "sg:phone":"+61 7 3216 6333",
    "sg:postcode":"4108",
    "sg:province":"QLD",
    "wof:name":"Sakura Filters",
    "wof:placetype":"venue"
},
  "geometry": {"coordinates":[153.014938355,-27.5715732574],"type":"Point"}
}