{
  "type": "Feature",
  "properties": {
    "iso:country":"AU",
    "sg:address":"14 Sanford Rd",
    "sg:city":"Albany",
    "sg:classifiers":[
        {
            "category":"Autos & Motor Vehicles",
            "subcategory":"Automobile Sales",
            "type":"Retail Goods"
        }
    ],
    "sg:phone":"+61 8 9841 4152",
    "sg:postcode":"6330",
    "sg:province":"WA",
    "sg:tags":[
        "car",
        "new"
    ],
    "wof:name":"Albany Kia",
    "wof:placetype":"venue"
},
  "geometry": {"coordinates":[117.880249023,-35.0164031982],"type":"Point"}
}