{
  "type": "Feature",
  "properties": {
    "iso:country":"AU",
    "sg:address":"177 Phillip St",
    "sg:city":"Redfern",
    "sg:classifiers":[
        {
            "category":"Autos & Motor Vehicles",
            "subcategory":"Boat Sales",
            "type":"Retail Goods"
        }
    ],
    "sg:phone":"+61 2 9318 2128",
    "sg:postcode":"2016",
    "sg:province":"NSW",
    "sg:tags":[
        "equipment",
        "yacht"
    ],
    "wof:name":"Barlow Distributors (Australia) Pty Ltd",
    "wof:placetype":"venue"
},
  "geometry": {"coordinates":[151.21081543,-33.8967590332],"type":"Point"}
}