{
  "type": "Feature",
  "properties": {
    "addr:full":"14 Union St Stepney SA 5069",
    "addr:housenumber":"14",
    "addr:postcode":"5069",
    "addr:street":"Union St",
    "iso:country":"AU",
    "sg:address":"14 Union St",
    "sg:city":"Stepney",
    "sg:classifiers":[
        {
            "category":"Retail",
            "subcategory":"Auto Repair",
            "type":"Services"
        }
    ],
    "sg:phone":"+61 8 8362 0932",
    "sg:postcode":"5069",
    "sg:province":"SA",
    "sg:tags":[
        "repairer",
        "motor",
        "engineer"
    ],
    "wof:name":"Eurocar Service",
    "wof:placetype":"venue"
},
  "geometry": {"coordinates":[138.62921142600001,-34.9136314392],"type":"Point"}
}