{
  "type": "Feature",
  "properties": {
    "addr:full":"63 Wingewarra St Dubbo NSW 2830",
    "addr:housenumber":"63",
    "addr:postcode":"2830",
    "addr:street":"Wingewarra St",
    "iso:country":"AU",
    "sg:address":"63 Wingewarra St",
    "sg:city":"Dubbo",
    "sg:classifiers":[
        {
            "category":"Retail",
            "subcategory":"Repair Shop",
            "type":"Services"
        }
    ],
    "sg:phone":"+61 2 6884 9522",
    "sg:postcode":"2830",
    "sg:province":"NSW",
    "sg:tags":[
        "cleaner",
        "part",
        "vacuum"
    ],
    "wof:name":"Dubbo Vacuum Cleaner Specialists",
    "wof:placetype":"venue"
},
  "geometry": {"coordinates":[148.602615356,-32.2493095398],"type":"Point"}
}