{
  "type": "Feature",
  "properties": {
    "iso:country":"AU",
    "sg:address":"144 Pittwater Rd",
    "sg:city":"Boronia Park",
    "sg:classifiers":[
        {
            "category":"Personal",
            "subcategory":"Beauty Salon",
            "type":"Services"
        }
    ],
    "sg:phone":"+61 2 9817 4220",
    "sg:postcode":"2111",
    "sg:province":"NSW",
    "wof:name":"Advanced Skin Care",
    "wof:placetype":"venue"
},
  "geometry": {"coordinates":[151.13450622600001,-33.8214492798],"type":"Point"}
}