{
  "type": "Feature",
  "properties": {
    "addr:full":"692 Sydney Rd Brunswick VIC 3056",
    "addr:housenumber":"692",
    "addr:postcode":"3056",
    "addr:street":"Sydney Rd",
    "iso:country":"AU",
    "sg:address":"692 Sydney Rd",
    "sg:city":"Brunswick",
    "sg:classifiers":[
        {
            "category":"Food & Beverages",
            "subcategory":"Bakery",
            "type":"Retail Goods"
        }
    ],
    "sg:phone":"+61 3 9386 4144",
    "sg:postcode":"3056",
    "sg:province":"VIC",
    "sg:tags":[
        "baker"
    ],
    "wof:name":"Pamukkale Bakery",
    "wof:placetype":"venue"
},
  "geometry": {"coordinates":[144.96322631800001,-37.7612113953],"type":"Point"}
}