{
  "type": "Feature",
  "properties": {
    "addr:full":"219a Hanson Rd Athol Park SA 5012",
    "addr:housenumber":"219a",
    "addr:postcode":"5012",
    "addr:street":"Hanson Rd",
    "iso:country":"AU",
    "sg:address":"219a Hanson Rd",
    "sg:city":"Athol Park",
    "sg:classifiers":[
        {
            "category":"Food & Beverages",
            "subcategory":"Groceries & Convenience Stores",
            "type":"Retail Goods"
        }
    ],
    "sg:phone":"+61 8 8268 5033",
    "sg:postcode":"5012",
    "sg:province":"SA",
    "wof:name":"L.P. Minimart",
    "wof:placetype":"venue"
},
  "geometry": {"coordinates":[138.54681396500001,-34.8536720276],"type":"Point"}
}