{
  "type": "Feature",
  "properties": {
    "addr:full":"Suite 1, Lvl 4 58 Pitt St Sydney NSW 2000",
    "addr:housenumber":"58",
    "addr:postcode":"2000",
    "addr:street":"Pitt St",
    "iso:country":"AU",
    "sg:address":"Suite 1, Lvl 4 58 Pitt St",
    "sg:city":"Sydney",
    "sg:classifiers":[
        {
            "category":"Banks & Credit Unions",
            "subcategory":"Financial Services",
            "type":"Services"
        }
    ],
    "sg:phone":"+61 2 9251 6399",
    "sg:postcode":"2000",
    "sg:province":"NSW",
    "sg:tags":[
        "merchant",
        "banker"
    ],
    "wof:name":"Sirius Capital",
    "wof:placetype":"venue"
},
  "geometry": {"coordinates":[151.20903015100001,-33.864025116],"type":"Point"}
}