{
  "type": "Feature",
  "properties": {
    "addr:full":"106 McKillop St Geelong VIC 3220",
    "addr:housenumber":"106",
    "addr:postcode":"3220",
    "addr:street":"Mckillop St",
    "iso:country":"AU",
    "sg:address":"106 McKillop St",
    "sg:city":"Geelong",
    "sg:classifiers":[
        {
            "category":"Health Services",
            "subcategory":"Doctor",
            "type":"Services"
        }
    ],
    "sg:phone":"+61 3 5229 6866",
    "sg:postcode":"3220",
    "sg:province":"VIC",
    "sg:tags":[
        "medical",
        "practitioner"
    ],
    "wof:name":"Geelong Leg Vein Centre",
    "wof:placetype":"venue"
},
  "geometry": {"coordinates":[144.363235,-38.155132],"type":"Point"}
}