{
  "type": "Feature",
  "properties": {
    "iso:country":"AU",
    "sg:address":"45 High St",
    "sg:city":"Wallan",
    "sg:classifiers":[
        {
            "category":"Health Services",
            "subcategory":"Chiropractor",
            "type":"Services"
        }
    ],
    "sg:phone":"+61 3 5783 1709",
    "sg:postcode":"3756",
    "sg:province":"VIC",
    "wof:name":"Wallan Chiropractic & Natural Health",
    "wof:placetype":"venue"
},
  "geometry": {"coordinates":[144.978989,-37.415924],"type":"Point"}
}