{
  "type": "Feature",
  "properties": {
    "addr:full":"7 Ladera Drv Copacabana NSW 2251",
    "addr:housenumber":"7",
    "addr:postcode":"2251",
    "addr:street":"Ladera Drv",
    "iso:country":"AU",
    "sg:address":"7 Ladera Drv",
    "sg:city":"Copacabana",
    "sg:classifiers":[
        {
            "category":"Building & Trades",
            "subcategory":"Plumbing",
            "type":"Services"
        }
    ],
    "sg:phone":"+61 2 4382 3076",
    "sg:postcode":"2251",
    "sg:province":"NSW",
    "sg:tags":[
        "plumber",
        "gasfitters"
    ],
    "wof:name":"Copacabana Plumbing Services",
    "wof:placetype":"venue"
},
  "geometry": {"coordinates":[151.42869567899999,-33.4884643555],"type":"Point"}
}