{
  "type": "Feature",
  "properties": {
    "addr:full":"Cnr Gilba & Toongabbie Rds Girraween NSW 2145",
    "addr:postcode":"2145",
    "addr:street":"Cnr Gilba &;Rds",
    "iso:country":"AU",
    "sg:address":"Cnr Gilba & Toongabbie Rds",
    "sg:city":"Girraween",
    "sg:classifiers":[
        {
            "category":"Autos & Motor Vehicles",
            "subcategory":"Fuel & Gas Station",
            "type":"Retail Goods"
        }
    ],
    "sg:phone":"+61 2 9631 0624",
    "sg:postcode":"2145",
    "sg:province":"NSW",
    "wof:name":"BP Fox Hills Service Station",
    "wof:placetype":"venue"
},
  "geometry": {"coordinates":[150.946533203,-33.7993583679],"type":"Point"}
}