{
  "type": "Feature",
  "properties": {
    "addr:full":"35 Lipscombe Rd Deception Bay QLD 4508",
    "addr:housenumber":"35",
    "addr:postcode":"4508",
    "addr:street":"Lipscombe Rd",
    "iso:country":"AU",
    "sg:address":"35 Lipscombe Rd",
    "sg:city":"Deception Bay",
    "sg:classifiers":[
        {
            "category":"Personal",
            "type":"Services"
        }
    ],
    "sg:phone":"+61 7 3293 1322",
    "sg:postcode":"4508",
    "sg:province":"QLD",
    "sg:tags":[
        "reducing",
        "treatment",
        "weight"
    ],
    "wof:name":"Herbalife Deception Bay",
    "wof:placetype":"venue"
},
  "geometry": {"coordinates":[153.01675415,-27.193239212],"type":"Point"}
}