{
  "type": "Feature",
  "properties": {
    "iso:country":"AU",
    "sg:address":"146- 160 Colin St",
    "sg:city":"West Perth",
    "sg:classifiers":[
        {
            "category":"Organizations",
            "subcategory":"Non-profit Organization",
            "type":"Services"
        }
    ],
    "sg:phone":"+61 8 9426 9737",
    "sg:postcode":"6005",
    "sg:province":"WA",
    "sg:tags":[
        "support",
        "disability",
        "organisation"
    ],
    "wof:name":"Council of DSC Funded Agencies (COFA)",
    "wof:placetype":"venue"
},
  "geometry": {"coordinates":[115.84349822999999,-31.9449043274],"type":"Point"}
}