{
  "type": "Feature",
  "properties": {
    "addr:full":"369 Hawthorn Rd Caulfield South VIC 3162",
    "addr:housenumber":"369",
    "addr:postcode":"3162",
    "addr:street":"Hawthorn Rd",
    "iso:country":"AU",
    "sg:address":"369 Hawthorn Rd",
    "sg:city":"Caulfield South",
    "sg:classifiers":[
        {
            "category":"Autos & Motor Vehicles",
            "subcategory":"Auto Supplies",
            "type":"Retail Goods"
        }
    ],
    "sg:phone":"+61 3 9528 6766",
    "sg:postcode":"3162",
    "sg:province":"VIC",
    "sg:tags":[
        "tyre"
    ],
    "wof:name":"Caulfield Tyre & Mechanical Repairs",
    "wof:placetype":"venue"
},
  "geometry": {"coordinates":[145.02200317399999,-37.887550354],"type":"Point"}
}