{
  "type": "Feature",
  "properties": {
    "addr:full":"34 Baker St Cockatoo VIC 3781",
    "addr:housenumber":"34",
    "addr:postcode":"3781",
    "addr:street":"Baker St",
    "iso:country":"AU",
    "sg:address":"34 Baker St",
    "sg:city":"Cockatoo",
    "sg:classifiers":[
        {
            "category":"Shopping",
            "subcategory":"Crafts & Fabrics",
            "type":"Retail Goods"
        }
    ],
    "sg:phone":"+61 3 5968 0291",
    "sg:postcode":"3781",
    "sg:province":"VIC",
    "sg:tags":[
        "supply"
    ],
    "wof:name":"Lasting Impressions",
    "wof:placetype":"venue"
},
  "geometry": {"coordinates":[145.488327,-37.931629],"type":"Point"}
}