{
  "type": "Feature",
  "properties": {
    "iso:country":"AU",
    "sg:address":"15 The Gateway Great Eastern Hwy",
    "sg:city":"Kalgoorlie",
    "sg:classifiers":[
        {
            "category":"Building & Trades",
            "subcategory":"Construction",
            "type":"Services"
        }
    ],
    "sg:phone":"+61 8 9091 5327",
    "sg:postcode":"6430",
    "sg:province":"WA",
    "sg:tags":[
        "joiner",
        "carpenter"
    ],
    "wof:name":"E.R. & S.S. Richards Pty Ltd",
    "wof:placetype":"venue"
},
  "geometry": {"coordinates":[121.451637268,-30.7649421692],"type":"Point"}
}