{
  "type": "Feature",
  "properties": {
    "addr:full":"Suite 810/ 63 Crown St Woolloomooloo NSW 2011",
    "addr:housenumber":"810 / 63",
    "addr:postcode":"2011",
    "addr:street":"Crown St",
    "iso:country":"AU",
    "sg:address":"Suite 810/ 63 Crown St",
    "sg:city":"Woolloomooloo",
    "sg:classifiers":[
        {
            "category":"Autos & Motor Vehicles",
            "subcategory":"Auto Supplies",
            "type":"Retail Goods"
        }
    ],
    "sg:phone":"+61 2 9331 6134",
    "sg:postcode":"2011",
    "sg:province":"NSW",
    "sg:tags":[
        "transmission",
        "equipment",
        "power"
    ],
    "wof:name":"Antac Aust Pty Limited",
    "wof:placetype":"venue"
},
  "geometry": {"coordinates":[151.21635437,-33.8734550476],"type":"Point"}
}