{
  "type": "Feature",
  "properties": {
    "addr:full":"187c Pacific Hwy Hornsby NSW 2077",
    "addr:housenumber":"187c",
    "addr:postcode":"2077",
    "addr:street":"Pacific Hwy",
    "iso:country":"AU",
    "sg:address":"187c Pacific Hwy",
    "sg:city":"Hornsby",
    "sg:classifiers":[
        {
            "category":"Banks & Credit Unions",
            "subcategory":"Bureau De Change",
            "type":"Services"
        }
    ],
    "sg:phone":"+61 2 9482 1123",
    "sg:postcode":"2077",
    "sg:province":"NSW",
    "sg:tags":[
        "repairs",
        "part",
        "appliance",
        "electrical"
    ],
    "wof:name":"Anytime TV & Video Service",
    "wof:placetype":"venue"
},
  "geometry": {"coordinates":[151.09687805199999,-33.7022819519],"type":"Point"}
}