{
  "type": "Feature",
  "properties": {
    "addr:full":"27 Lowes Rd Placid Hills QLD 4343",
    "addr:housenumber":"27",
    "addr:postcode":"4343",
    "addr:street":"Lowes Rd",
    "iso:country":"AU",
    "sg:address":"27 Lowes Rd",
    "sg:city":"Placid Hills",
    "sg:classifiers":[
        {
            "category":"Home & Garden",
            "subcategory":"Garden Supply",
            "type":"Retail Goods"
        }
    ],
    "sg:phone":"+61 412 453 388",
    "sg:postcode":"4343",
    "sg:province":"QLD",
    "sg:tags":[
        "turf",
        "lawn"
    ],
    "wof:name":"Placid Hills Turf Supplies",
    "wof:placetype":"venue"
},
  "geometry": {"coordinates":[152.238647461,-27.5715503693],"type":"Point"}
}