{
  "type": "Feature",
  "properties": {
    "addr:full":"6/ 176 Canterbury Rd Bayswater VIC 3153",
    "addr:housenumber":"/ 176",
    "addr:postcode":"3153",
    "addr:street":"Canterbury Rd",
    "iso:country":"AU",
    "sg:address":"6/ 176 Canterbury Rd",
    "sg:city":"Bayswater",
    "sg:classifiers":[
        {
            "category":"Food & Beverages",
            "subcategory":"Specialty",
            "type":"Retail Goods"
        }
    ],
    "sg:phone":"+61 3 9720 6722",
    "sg:postcode":"3153",
    "sg:province":"VIC",
    "sg:tags":[
        "solvent"
    ],
    "wof:name":"Transpacific Solvents Services",
    "wof:placetype":"venue"
},
  "geometry": {"coordinates":[145.284591675,-37.8267707825],"type":"Point"}
}