{
  "type": "Feature",
  "properties": {
    "addr:full":"Shop 2, 171 Elizabeth Bay Drv Lake Munmorah NSW 2259",
    "addr:housenumber":"shop 2 171",
    "addr:postcode":"2259",
    "addr:street":"Elizabeth Bay Drv",
    "iso:country":"AU",
    "sg:address":"Shop 2, 171 Elizabeth Bay Drv",
    "sg:city":"Lake Munmorah",
    "sg:classifiers":[
        {
            "category":"Food & Beverages",
            "subcategory":"Groceries & Convenience Stores",
            "type":"Retail Goods"
        }
    ],
    "sg:phone":"+61 2 4358 8412",
    "sg:postcode":"2259",
    "sg:province":"NSW",
    "wof:name":"Pacific Lakes General Store",
    "wof:placetype":"venue"
},
  "geometry": {"coordinates":[151.57943725600001,-33.193031311],"type":"Point"}
}