{
  "type": "Feature",
  "properties": {
    "iso:country":"AU",
    "sg:address":"Level 1, 48 Chapel St",
    "sg:city":"Windsor",
    "sg:classifiers":[
        {
            "category":"Personal",
            "subcategory":"Beauty Salon",
            "type":"Services"
        }
    ],
    "sg:phone":"+61 3 9510 1024",
    "sg:postcode":"3181",
    "sg:province":"VIC",
    "wof:name":"Lizmarys Beauty Clinic",
    "wof:placetype":"venue"
},
  "geometry": {"coordinates":[144.99273681599999,-37.8560714722],"type":"Point"}
}