{
  "type": "Feature",
  "properties": {
    "addr:full":"34 Halimah St Chapel Hill QLD 4069",
    "addr:housenumber":"34",
    "addr:postcode":"4069",
    "addr:street":"Halimah St",
    "iso:country":"AU",
    "sg:address":"34 Halimah St",
    "sg:city":"Chapel Hill",
    "sg:classifiers":[
        {
            "category":"Building & Trades",
            "subcategory":"Construction",
            "type":"Services"
        }
    ],
    "sg:phone":"+61 7 3378 1684",
    "sg:postcode":"4069",
    "sg:province":"QLD",
    "sg:tags":[
        "concrete",
        "treatment",
        "repair"
    ],
    "wof:name":"Nosh Protective Coatings",
    "wof:placetype":"venue"
},
  "geometry": {"coordinates":[152.95286560100001,-27.5008850098],"type":"Point"}
}