{
  "type": "Feature",
  "properties": {
    "addr:full":"21 Arthur St Manilla NSW 2346",
    "addr:housenumber":"21",
    "addr:postcode":"2346",
    "addr:street":"Arthur St",
    "iso:country":"AU",
    "sg:address":"21 Arthur St",
    "sg:city":"Manilla",
    "sg:classifiers":[
        {
            "category":"Commercial Area",
            "type":"Public Place"
        }
    ],
    "sg:phone":"+61 428 851 828",
    "sg:postcode":"2346",
    "sg:province":"NSW",
    "sg:tags":[
        "heavy",
        "carrier"
    ],
    "wof:name":"Blanchs - Manilla",
    "wof:placetype":"venue"
},
  "geometry": {"coordinates":[150.72492980999999,-30.7479896545],"type":"Point"}
}