{
  "type": "Feature",
  "properties": {
    "iso:country":"AU",
    "sg:address":"140- 150 Rocky Point Rd",
    "sg:city":"Kogarah",
    "sg:classifiers":[
        {
            "category":"Communications",
            "subcategory":"Film & Video Production",
            "type":"Services"
        }
    ],
    "sg:phone":"+61 2 9587 3629",
    "sg:postcode":"2217",
    "sg:province":"NSW",
    "sg:tags":[
        "linen",
        "good"
    ],
    "wof:name":"Manchester Warehouse",
    "wof:placetype":"venue"
},
  "geometry": {"coordinates":[151.136826,-33.977905],"type":"Point"}
}