{
  "type": "Feature",
  "properties": {
    "addr:full":"140- 150 Rocky Point Rd Kogarah NSW 2217",
    "addr:housenumber":"150",
    "addr:postcode":"2217",
    "addr:street":"Rocky Point Rd",
    "iso:country":"AU",
    "sg:address":"140- 150 Rocky Point Rd",
    "sg:city":"Kogarah",
    "sg:classifiers":[
        {
            "category":"Communications",
            "subcategory":"Film & Video Production",
            "type":"Services"
        }
    ],
    "sg:phone":"+61 2 9587 3629",
    "sg:postcode":"2217",
    "sg:province":"NSW",
    "sg:tags":[
        "linen",
        "good"
    ],
    "wof:name":"Manchester Warehouse",
    "wof:placetype":"venue"
},
  "geometry": {"coordinates":[151.13682600000001,-33.977905],"type":"Point"}
}