{
  "type": "Feature",
  "properties": {
    "addr:full":"24 Barramundi Crs Ocean Grove VIC 3226",
    "addr:housenumber":"24",
    "addr:postcode":"3226",
    "addr:street":"Barramundi Crs",
    "iso:country":"AU",
    "sg:address":"24 Barramundi Crs",
    "sg:city":"Ocean Grove",
    "sg:classifiers":[
        {
            "category":"Retail",
            "subcategory":"Repair Shop",
            "type":"Services"
        }
    ],
    "sg:phone":"+61 3 5256 2088",
    "sg:postcode":"3226",
    "sg:province":"VIC",
    "sg:tags":[
        "maintenance",
        "pool",
        "swimming"
    ],
    "wof:name":"Sunrise Pools & Spas Pty Ltd",
    "wof:placetype":"venue"
},
  "geometry": {"coordinates":[144.53810100000001,-38.265339],"type":"Point"}
}