{
  "type": "Feature",
  "properties": {
    "addr:full":"50 River Rd Emu Plains NSW 2750",
    "addr:housenumber":"50",
    "addr:postcode":"2750",
    "addr:street":"River Rd",
    "iso:country":"AU",
    "sg:address":"50 River Rd",
    "sg:city":"Emu Plains",
    "sg:classifiers":[
        {
            "category":"Health Services",
            "subcategory":"Dentist",
            "type":"Services"
        }
    ],
    "sg:phone":"+61 2 4735 2811",
    "sg:postcode":"2750",
    "sg:province":"NSW",
    "wof:name":"Dr Kroon E W",
    "wof:placetype":"venue"
},
  "geometry": {"coordinates":[150.670974731,-33.7537765503],"type":"Point"}
}