{
  "type": "Feature",
  "properties": {
    "addr:full":"236 Wells Rd Chelsea Heights VIC 3196",
    "addr:housenumber":"236",
    "addr:postcode":"3196",
    "addr:street":"Wells Rd",
    "iso:country":"AU",
    "sg:address":"236 Wells Rd",
    "sg:city":"Chelsea Heights",
    "sg:classifiers":[
        {
            "category":"Fast Food",
            "type":"Food & Drink"
        }
    ],
    "sg:phone":"+61 3 9772 5964",
    "sg:postcode":"3196",
    "sg:province":"VIC",
    "sg:tags":[
        "away",
        "take"
    ],
    "wof:name":"Chelsea Heights Fish & Chippery",
    "wof:placetype":"venue"
},
  "geometry": {"coordinates":[145.14186096200001,-38.0478057861],"type":"Point"}
}