{
  "type": "Feature",
  "properties": {
    "addr:full":"106 Nepean Hwy Mentone VIC 3194",
    "addr:housenumber":"106",
    "addr:postcode":"3194",
    "addr:street":"Nepean Hwy",
    "iso:country":"AU",
    "sg:address":"106 Nepean Hwy",
    "sg:city":"Mentone",
    "sg:classifiers":[
        {
            "category":"Government",
            "subcategory":"Customs House",
            "type":"Public Place"
        }
    ],
    "sg:phone":"+61 3 9585 0344",
    "sg:postcode":"3194",
    "sg:province":"VIC",
    "sg:tags":[
        "title",
        "management",
        "stratum"
    ],
    "wof:name":"Ace Body Corporate Management - Carrum Downs/Kingston Commercial",
    "wof:placetype":"venue"
},
  "geometry": {"coordinates":[145.069778442,-37.9811248779],"type":"Point"}
}