{
  "type": "Feature",
  "properties": {
    "addr:full":"3 Brightview Rd Glenore Grove QLD 4342",
    "addr:housenumber":"3",
    "addr:postcode":"4342",
    "addr:street":"Brightview Rd",
    "iso:country":"AU",
    "sg:address":"3 Brightview Rd",
    "sg:city":"Glenore Grove",
    "sg:classifiers":[
        {
            "category":"Education",
            "subcategory":"School",
            "type":"Public Place"
        }
    ],
    "sg:phone":"+61 7 5466 5313",
    "sg:postcode":"4342",
    "sg:province":"QLD",
    "sg:tags":[
        "state",
        "except",
        "nsw"
    ],
    "wof:name":"Glenore Grove Preschool",
    "wof:placetype":"venue"
},
  "geometry": {"coordinates":[152.40855407699999,-27.530040741],"type":"Point"}
}