{
  "type": "Feature",
  "properties": {
    "addr:full":"St Andrews Pl 33 North St Spring Hill QLD 4000",
    "addr:housenumber":"33",
    "addr:postcode":"4000",
    "addr:street":"Pl;North St",
    "iso:country":"AU",
    "sg:address":"St Andrews Pl 33 North St",
    "sg:city":"Spring Hill",
    "sg:classifiers":[
        {
            "category":"Health Services",
            "subcategory":"Doctor",
            "type":"Services"
        }
    ],
    "sg:phone":"+61 7 3839 4494",
    "sg:postcode":"4000",
    "sg:province":"QLD",
    "sg:tags":[
        "medical",
        "practitioner"
    ],
    "wof:name":"Galea E G",
    "wof:placetype":"venue"
},
  "geometry": {"coordinates":[153.021606445,-27.4612216949],"type":"Point"}
}