{
  "type": "Feature",
  "properties": {
    "iso:country":"AU",
    "sg:address":"48 Smith St",
    "sg:city":"Melton",
    "sg:classifiers":[
        {
            "category":"Personal",
            "subcategory":"Beauty Salon",
            "type":"Services"
        }
    ],
    "sg:phone":"+61 3 9743 4523",
    "sg:postcode":"3337",
    "sg:province":"VIC",
    "sg:tags":[
        "hairdresser"
    ],
    "wof:name":"Jill's Hair Design",
    "wof:placetype":"venue"
},
  "geometry": {"coordinates":[144.58551,-37.681698],"type":"Point"}
}