{
  "type": "Feature",
  "properties": {
    "addr:full":"Cnr Warburton Hwy & Sebire Ave Wandin North VIC 3139",
    "addr:postcode":"3139",
    "addr:street":"Cnr Warburton Hwy & Sebire Ave",
    "iso:country":"AU",
    "sg:address":"Cnr Warburton Hwy & Sebire Ave",
    "sg:city":"Wandin North",
    "sg:classifiers":[
        {
            "category":"Retail",
            "subcategory":"Auto Repair",
            "type":"Services"
        }
    ],
    "sg:phone":"+61 3 5964 2177",
    "sg:postcode":"3139",
    "sg:province":"VIC",
    "sg:tags":[
        "repairer",
        "motor",
        "engineer"
    ],
    "wof:name":"Wandin Motors",
    "wof:placetype":"venue"
},
  "geometry": {"coordinates":[145.42729187,-37.7789382935],"type":"Point"}
}