{
  "type": "Feature",
  "properties": {
    "addr:full":"Unit 199 South Creek Rd Dee Why NSW 2099",
    "addr:postcode":"2099",
    "addr:street":"South Creek Rd",
    "iso:country":"AU",
    "sg:address":"Unit 199 South Creek Rd",
    "sg:city":"Dee Why",
    "sg:classifiers":[
        {
            "category":"Home & Garden",
            "subcategory":"Building Materials",
            "type":"Retail Goods"
        }
    ],
    "sg:phone":"+61 1800 674 532",
    "sg:postcode":"2099",
    "sg:province":"NSW",
    "sg:tags":[
        "ventilating",
        "equipment",
        "system"
    ],
    "wof:name":"Edmonds Pty Limited",
    "wof:placetype":"venue"
},
  "geometry": {"coordinates":[151.27833557100001,-33.7334098816],"type":"Point"}
}