{
  "type": "Feature",
  "properties": {
    "addr:full":"Newell Hwy Parkes NSW 2870",
    "addr:postcode":"2870",
    "addr:street":"Newell Hwy",
    "iso:country":"AU",
    "sg:address":"Newell Hwy",
    "sg:city":"Parkes",
    "sg:classifiers":[
        {
            "category":"Utilities",
            "subcategory":"Fuel Oil & Lpg",
            "type":"Services"
        }
    ],
    "sg:phone":"+61 2 6862 5692",
    "sg:postcode":"2870",
    "sg:province":"NSW",
    "sg:tags":[
        "merchant"
    ],
    "wof:name":"Lachlan Valley Oil",
    "wof:placetype":"venue"
},
  "geometry": {"coordinates":[148.17463699999999,-33.136883],"type":"Point"}
}