{
  "type": "Feature",
  "properties": {
    "iso:country":"AU",
    "sg:address":"2a Victoria St",
    "sg:city":"Wollongong",
    "sg:classifiers":[
        {
            "category":"Food & Beverages",
            "subcategory":"Supermarket",
            "type":"Retail Goods"
        }
    ],
    "sg:phone":"+61 2 4226 3779",
    "sg:postcode":"2500",
    "sg:province":"NSW",
    "sg:tags":[
        "grocery",
        "store"
    ],
    "wof:name":"Vina Asian Foodstore",
    "wof:placetype":"venue"
},
  "geometry": {"coordinates":[150.892853,-34.422123],"type":"Point"}
}