{
  "type": "Feature",
  "properties": {
    "iso:country":"AU",
    "sg:address":"52 Finlay St",
    "sg:city":"Albert Park",
    "sg:classifiers":[
        {
            "category":"Real Estate",
            "subcategory":"Architect",
            "type":"Services"
        }
    ],
    "sg:phone":"+61 3 9690 5997",
    "sg:postcode":"3206",
    "sg:province":"VIC",
    "sg:tags":[
        "building",
        "designer"
    ],
    "wof:name":"Clegg Consulting Pty Ltd",
    "wof:placetype":"venue"
},
  "geometry": {"coordinates":[144.953796,-37.843887],"type":"Point"}
}