{
  "type": "Feature",
  "properties": {
    "addr:full":"19 Beverage Drv Tullamarine VIC 3043",
    "addr:postcode":"3043",
    "addr:street":"Beverage Drv",
    "iso:country":"AU",
    "sg:address":"19 Beverage Drv",
    "sg:city":"Tullamarine",
    "sg:classifiers":[
        {
            "category":"Retail",
            "subcategory":"Storage",
            "type":"Services"
        }
    ],
    "sg:phone":"+61 3 9338 0344",
    "sg:postcode":"3043",
    "sg:province":"VIC",
    "sg:tags":[
        "removal",
        "furniture"
    ],
    "wof:name":"Red X Transport Pty Ltd",
    "wof:placetype":"venue"
},
  "geometry": {"coordinates":[144.86192321799999,-37.7176132202],"type":"Point"}
}