{
  "type": "Feature",
  "properties": {
    "addr:full":"PO Box 2049 Runcorn QLD 4113",
    "addr:postcode":"4113",
    "iso:country":"AU",
    "sg:address":"PO Box 2049",
    "sg:city":"Runcorn",
    "sg:classifiers":[
        {
            "category":"Professional",
            "subcategory":"Art Services",
            "type":"Services"
        }
    ],
    "sg:phone":"+61 7 3341 3015",
    "sg:postcode":"4113",
    "sg:province":"QLD",
    "sg:tags":[
        "graphic",
        "designer"
    ],
    "wof:name":"Antzpantz Design",
    "wof:placetype":"venue"
},
  "geometry": {"coordinates":[153.07298278799999,-27.5956707001],"type":"Point"}
}