{
  "type": "Feature",
  "properties": {
    "iso:country":"AU",
    "sg:address":"Cnr The Northern Rd & Porrende St",
    "sg:city":"Narellan",
    "sg:classifiers":[
        {
            "category":"Retail",
            "subcategory":"Repair Shop",
            "type":"Services"
        }
    ],
    "sg:phone":"+61 2 4647 9722",
    "sg:postcode":"2567",
    "sg:province":"NSW",
    "sg:tags":[
        "maintenance",
        "pool",
        "swimming"
    ],
    "wof:name":"PoolWerx",
    "wof:placetype":"venue"
},
  "geometry": {"coordinates":[150.735275269,-34.0400428772],"type":"Point"}
}