{
  "type": "Feature",
  "properties": {
    "addr:full":"8 Railway Pde Camberwell VIC 3124",
    "addr:housenumber":"8",
    "addr:postcode":"3124",
    "addr:street":"Railway Pde",
    "iso:country":"AU",
    "sg:address":"8 Railway Pde",
    "sg:city":"Camberwell",
    "sg:classifiers":[
        {
            "category":"Food & Beverages",
            "subcategory":"Liquor & Beverages",
            "type":"Retail Goods"
        }
    ],
    "sg:phone":"+61 1300 553 716",
    "sg:postcode":"3124",
    "sg:province":"VIC",
    "sg:tags":[
        "merchant",
        "spirit",
        "wine"
    ],
    "wof:name":"Wine Box Warehouse",
    "wof:placetype":"venue"
},
  "geometry": {"coordinates":[145.058319092,-37.8277702332],"type":"Point"}
}