{
  "type": "Feature",
  "properties": {
    "addr:full":"83 Halsey St Fulham SA 5024",
    "addr:housenumber":"83",
    "addr:postcode":"5024",
    "addr:street":"Halsey St",
    "iso:country":"AU",
    "sg:address":"83 Halsey St",
    "sg:city":"Fulham",
    "sg:classifiers":[
        {
            "category":"Arts & Performance",
            "subcategory":"Music",
            "type":"Entertainment"
        }
    ],
    "sg:phone":"+61 412 111 227",
    "sg:postcode":"5024",
    "sg:province":"SA",
    "sg:tags":[
        "mobile",
        "jockey",
        "disc"
    ],
    "wof:name":"All Time Entertainment",
    "wof:placetype":"venue"
},
  "geometry": {"coordinates":[138.509963989,-34.9319725037],"type":"Point"}
}