{
  "type": "Feature",
  "properties": {
    "addr:full":"510 Lower North East Rd Campbelltown SA 5074",
    "addr:housenumber":"510",
    "addr:postcode":"5074",
    "addr:street":"Lower North East Rd",
    "iso:country":"AU",
    "sg:address":"510 Lower North East Rd",
    "sg:city":"Campbelltown",
    "sg:classifiers":[
        {
            "category":"Real Estate",
            "subcategory":"Real Estate Agent",
            "type":"Services"
        }
    ],
    "sg:phone":"+61 8 8365 7000",
    "sg:postcode":"5074",
    "sg:province":"SA",
    "wof:name":"Raine & Horne Glynde",
    "wof:placetype":"venue"
},
  "geometry": {"coordinates":[138.661712647,-34.8808746338],"type":"Point"}
}