{
  "type": "Feature",
  "properties": {
    "addr:full":"162-170 Pulteney St ( Cnr Pirie St Adelaide SA 5000",
    "addr:housenumber":"162-170",
    "addr:postcode":"5000",
    "addr:street":"Pulteney St Cnr Pirie St",
    "iso:country":"AU",
    "sg:address":"162-170 Pulteney St ( Cnr Pirie St",
    "sg:city":"Adelaide",
    "sg:classifiers":[
        {
            "category":"Restaurant",
            "type":"Food & Drink"
        }
    ],
    "sg:phone":"+61 8 8227 0099",
    "sg:postcode":"5000",
    "sg:province":"SA",
    "wof:name":"Amore Caffe Restaurant",
    "wof:placetype":"venue"
},
  "geometry": {"coordinates":[138.60606384299999,-34.9265060425],"type":"Point"}
}