{
  "type": "Feature",
  "properties": {
    "addr:full":"Unit 2/ 18 Vale St Malaga WA 6090",
    "addr:housenumber":"18",
    "addr:postcode":"6090",
    "addr:street":"Vale St",
    "iso:country":"AU",
    "sg:address":"Unit 2/ 18 Vale St",
    "sg:city":"Malaga",
    "sg:classifiers":[
        {
            "category":"Retail",
            "subcategory":"Auto Repair",
            "type":"Services"
        }
    ],
    "sg:phone":"+61 8 9248 8786",
    "sg:postcode":"6090",
    "sg:province":"WA",
    "sg:tags":[
        "car",
        "restoration",
        "supply"
    ],
    "wof:name":"D & S Quality Refinishes",
    "wof:placetype":"venue"
},
  "geometry": {"coordinates":[115.891342163,-31.848405838],"type":"Point"}
}