{
  "type": "Feature",
  "properties": {
    "addr:full":"15 Andrew Mew St Moriac VIC 3240",
    "addr:housenumber":"15",
    "addr:postcode":"3240",
    "addr:street":"Andrew Mew St",
    "iso:country":"AU",
    "sg:address":"15 Andrew Mew St",
    "sg:city":"Moriac",
    "sg:classifiers":[
        {
            "category":"Farming",
            "subcategory":"Farm & Veterinary Services",
            "type":"Manufacturing & Wholesale Goods"
        }
    ],
    "sg:phone":"+61 419 526 973",
    "sg:postcode":"3240",
    "sg:province":"VIC",
    "sg:tags":[
        "contracting"
    ],
    "wof:name":"Finch Contractors",
    "wof:placetype":"venue"
},
  "geometry": {"coordinates":[144.167312622,-38.2456817627],"type":"Point"}
}