{
  "type": "Feature",
  "properties": {
    "addr:full":"14 George St Rockhampton QLD 4700",
    "addr:housenumber":"14",
    "addr:postcode":"4700",
    "addr:street":"George St",
    "iso:country":"AU",
    "sg:address":"14 George St",
    "sg:city":"Rockhampton",
    "sg:classifiers":[
        {
            "category":"Building & Trades",
            "subcategory":"Locksmith",
            "type":"Services"
        }
    ],
    "sg:phone":"+61 7 4927 3400",
    "sg:postcode":"4700",
    "sg:province":"QLD",
    "sg:tags":[
        "strongroom",
        "safe",
        "door"
    ],
    "wof:name":"Keycut Services Pty Ltd",
    "wof:placetype":"venue"
},
  "geometry": {"coordinates":[150.510375977,-23.3874645233],"type":"Point"}
}