{
  "type": "Feature",
  "properties": {
    "iso:country":"AU",
    "sg:address":"57 Bridge St",
    "sg:city":"North Lismore",
    "sg:classifiers":[
        {
            "category":"Food & Beverages",
            "subcategory":"Bakery",
            "type":"Retail Goods"
        }
    ],
    "sg:phone":"+61 2 6621 3036",
    "sg:postcode":"2480",
    "sg:province":"NSW",
    "sg:tags":[
        "baker"
    ],
    "wof:name":"Wakely Bros Pty Ltd",
    "wof:placetype":"venue"
},
  "geometry": {"coordinates":[153.27577209500001,-28.8032493591],"type":"Point"}
}