{
  "type": "Feature",
  "properties": {
    "iso:country":"AU",
    "sg:address":"84 Percival Rd",
    "sg:city":"Smithfield",
    "sg:classifiers":[
        {
            "category":"Military Area",
            "subcategory":"Air Force Base",
            "type":"Public Place"
        }
    ],
    "sg:phone":"+61 2 9604 3255",
    "sg:postcode":"2164",
    "sg:province":"NSW",
    "sg:tags":[
        "box",
        "case",
        "wood"
    ],
    "wof:name":"Cooperage Pallets & Boxes",
    "wof:placetype":"venue"
},
  "geometry": {"coordinates":[150.950439453,-33.8404541016],"type":"Point"}
}