{
  "type": "Feature",
  "properties": {
    "addr:full":"16 Thompson Ave Cowes VIC 3922",
    "addr:housenumber":"16",
    "addr:postcode":"3922",
    "addr:street":"Thompson Ave",
    "iso:country":"AU",
    "sg:address":"16 Thompson Ave",
    "sg:city":"Cowes",
    "sg:classifiers":[
        {
            "category":"Fast Food",
            "type":"Food & Drink"
        }
    ],
    "sg:phone":"+61 3 5952 3614",
    "sg:postcode":"3922",
    "sg:province":"VIC",
    "sg:tags":[
        "away",
        "take"
    ],
    "wof:name":"Q Take Away",
    "wof:placetype":"venue"
},
  "geometry": {"coordinates":[145.238815308,-38.448638916],"type":"Point"}
}