{
  "type": "Feature",
  "properties": {
    "iso:country":"AU",
    "sg:address":"150 Drayton Road MacDonald Shopping Centre",
    "sg:city":"Toowoomba",
    "sg:classifiers":[
        {
            "category":"Personal",
            "subcategory":"Beauty Salon",
            "type":"Services"
        }
    ],
    "sg:phone":"+61 7 4635 0956",
    "sg:postcode":"4350",
    "sg:province":"QLD",
    "sg:tags":[
        "hair",
        "wedding"
    ],
    "wof:name":"Turning Heads Hair Design",
    "wof:placetype":"venue"
},
  "geometry": {"coordinates":[151.92988600000001,-27.58884],"type":"Point"}
}