{
  "type": "Feature",
  "properties": {
    "iso:country":"AU",
    "sg:address":"14 Wimmera St",
    "sg:city":"Moorabbin",
    "sg:classifiers":[
        {
            "category":"Utilities",
            "subcategory":"Electric",
            "type":"Services"
        }
    ],
    "sg:phone":"+61 3 9553 0434",
    "sg:postcode":"3189",
    "sg:province":"VIC",
    "sg:tags":[
        "electrical",
        "contractor"
    ],
    "wof:name":"Warrah Electrics",
    "wof:placetype":"venue"
},
  "geometry": {"coordinates":[145.05084228499999,-37.9446258545],"type":"Point"}
}