{
  "type": "Feature",
  "properties": {
    "iso:country":"AU",
    "sg:address":"649C Beaufort St",
    "sg:city":"Mt Lawley",
    "sg:classifiers":[
        {
            "category":"Food & Beverages",
            "subcategory":"Bakery",
            "type":"Retail Goods"
        }
    ],
    "sg:phone":"+61 8 9227 0606",
    "sg:postcode":"6050",
    "sg:province":"WA",
    "sg:tags":[
        "baker"
    ],
    "wof:name":"Brumbys WA & NT",
    "wof:placetype":"venue"
},
  "geometry": {"coordinates":[115.868530273,-31.9404754639],"type":"Point"}
}