{
  "type": "Feature",
  "properties": {
    "iso:country":"AU",
    "sg:address":"40- 42 Mills Rd",
    "sg:city":"Braeside",
    "sg:classifiers":[
        {
            "category":"Retail",
            "subcategory":"Auto Repair",
            "type":"Services"
        }
    ],
    "sg:phone":"+61 3 8586 2555",
    "sg:postcode":"3195",
    "sg:province":"VIC",
    "sg:tags":[
        "clutch",
        "brake"
    ],
    "wof:name":"Cebco Brakes",
    "wof:placetype":"venue"
},
  "geometry": {"coordinates":[145.114776611,-37.9944000244],"type":"Point"}
}