{
  "type": "Feature",
  "properties": {
    "iso:country":"AU",
    "sg:address":"14 Alloa St",
    "sg:city":"Maddington",
    "sg:classifiers":[
        {
            "category":"Retail",
            "subcategory":"Auto Repair",
            "type":"Services"
        }
    ],
    "sg:phone":"+61 8 9459 3931",
    "sg:postcode":"6109",
    "sg:province":"WA",
    "sg:tags":[
        "beater",
        "painter",
        "panel"
    ],
    "wof:name":"Bryden D J Panel & Paint",
    "wof:placetype":"venue"
},
  "geometry": {"coordinates":[115.983512878,-32.046081543],"type":"Point"}
}