{
  "type": "Feature",
  "properties": {
    "iso:country":"AU",
    "sg:address":"88 Monaro Ave",
    "sg:city":"Kingsgrove",
    "sg:classifiers":[
        {
            "category":"Utilities",
            "subcategory":"Electric",
            "type":"Services"
        }
    ],
    "sg:phone":"+61 2 9554 9212",
    "sg:postcode":"2208",
    "sg:province":"NSW",
    "sg:tags":[
        "electrical",
        "contractor"
    ],
    "wof:name":"Ignite Electrical Services Pty Ltd",
    "wof:placetype":"venue"
},
  "geometry": {"coordinates":[151.095474,-33.944847],"type":"Point"}
}