{
  "type": "Feature",
  "properties": {
    "iso:country":"AU",
    "sg:address":"136 Bridge St",
    "sg:city":"Toowoomba",
    "sg:classifiers":[
        {
            "category":"Personal",
            "subcategory":"Beauty Salon",
            "type":"Services"
        }
    ],
    "sg:phone":"+61 7 4632 4353",
    "sg:postcode":"4350",
    "sg:province":"QLD",
    "sg:tags":[
        "hairdresser"
    ],
    "wof:name":"Bridge St Barber Shop",
    "wof:placetype":"venue"
},
  "geometry": {"coordinates":[151.90057400000001,-27.533758],"type":"Point"}
}