{
  "type": "Feature",
  "properties": {
    "addr:full":"Level 41 108 St Georges Terrace Perth WA 6000",
    "addr:housenumber":"108",
    "addr:postcode":"6000",
    "addr:street":"St Georges Terrace",
    "iso:country":"AU",
    "sg:address":"Level 41 108 St",
    "sg:city":"Georges Terrace Perth",
    "sg:classifiers":[
        {
            "category":"Professional",
            "subcategory":"Accounting & Tax Preparation",
            "type":"Services"
        }
    ],
    "sg:phone":"+61 8 9463 2463",
    "sg:postcode":"6000",
    "sg:province":"WA",
    "sg:tags":[
        "accountant",
        "auditor"
    ],
    "wof:name":"MGI Bridge Partners",
    "wof:placetype":"venue"
},
  "geometry": {"coordinates":[115.856697083,-31.9545955658],"type":"Point"}
}