{
  "type": "Feature",
  "properties": {
    "iso:country":"AU",
    "sg:address":"19 Fairfield Ave",
    "sg:city":"New Lambton",
    "sg:classifiers":[
        {
            "category":"Home & Garden",
            "subcategory":"Building Materials",
            "type":"Retail Goods"
        }
    ],
    "sg:phone":"+61 2 4952 5942",
    "sg:postcode":"2305",
    "sg:province":"NSW",
    "sg:tags":[
        "lawn",
        "cutting",
        "maintenance"
    ],
    "wof:name":"Charles In Charge Lawns Gardens & House Maintenance",
    "wof:placetype":"venue"
},
  "geometry": {"coordinates":[151.717377,-32.93269],"type":"Point"}
}