{
  "type": "Feature",
  "properties": {
    "addr:full":"17 Iluka Rd Mosman NSW 2088",
    "addr:housenumber":"17",
    "addr:postcode":"2088",
    "addr:street":"Iluka Rd",
    "iso:country":"AU",
    "sg:address":"17 Iluka Rd",
    "sg:city":"Mosman",
    "sg:classifiers":[
        {
            "category":"Health Services",
            "subcategory":"Health Practitioner",
            "type":"Services"
        }
    ],
    "sg:phone":"+61 2 9960 3891",
    "sg:postcode":"2088",
    "sg:province":"NSW",
    "sg:tags":[
        "physiotherapist"
    ],
    "wof:name":"Holcombe Lynn",
    "wof:placetype":"venue"
},
  "geometry": {"coordinates":[151.249435425,-33.8419265747],"type":"Point"}
}