{
  "type": "Feature",
  "properties": {
    "iso:country":"AU",
    "sg:address":"377 George St",
    "sg:city":"Deniliquin",
    "sg:classifiers":[
        {
            "category":"Professional",
            "subcategory":"Accounting & Tax Preparation",
            "type":"Services"
        }
    ],
    "sg:phone":"+61 3 5881 8380",
    "sg:postcode":"2710",
    "sg:province":"NSW",
    "sg:tags":[
        "accountant",
        "auditor"
    ],
    "wof:name":"Darren Young Accounting Pty Ltd",
    "wof:placetype":"venue"
},
  "geometry": {"coordinates":[144.96267700199999,-35.5264015198],"type":"Point"}
}