{
  "type": "Feature",
  "properties": {
    "addr:full":"U5/ 278 Camboon Rd Malaga WA 6090",
    "addr:housenumber":"278",
    "addr:postcode":"6090",
    "addr:street":"U5 /;Camboon Rd",
    "iso:country":"AU",
    "sg:address":"U5/ 278 Camboon Rd",
    "sg:city":"Malaga",
    "sg:classifiers":[
        {
            "category":"Shopping",
            "subcategory":"Mobile Phones",
            "type":"Retail Goods"
        }
    ],
    "sg:phone":"+61 8 9249 9238",
    "sg:postcode":"6090",
    "sg:province":"WA",
    "sg:tags":[
        "telephone",
        "accessory"
    ],
    "wof:name":"Mobile Reality Pty Ltd",
    "wof:placetype":"venue"
},
  "geometry": {"coordinates":[115.88723754900001,-31.8556880951],"type":"Point"}
}