{
  "type": "Feature",
  "properties": {
    "iso:country":"AU",
    "sg:address":"176 George St",
    "sg:city":"Sydney",
    "sg:classifiers":[
        {
            "category":"Bars & Pubs",
            "subcategory":"Nightclub",
            "type":"Food & Drink"
        }
    ],
    "sg:phone":"+61 2 9247 2727",
    "sg:postcode":"2000",
    "sg:province":"NSW",
    "sg:tags":[
        "discotheque"
    ],
    "wof:name":"Luna Lounge At Jacksons",
    "wof:placetype":"venue"
},
  "geometry": {"coordinates":[151.20814514200001,-33.8618392944],"type":"Point"}
}