{
  "type": "Feature",
  "properties": {
    "addr:full":"17a Francis St Fairlight NSW 2094",
    "addr:housenumber":"17a",
    "addr:postcode":"2094",
    "addr:street":"Francis St",
    "iso:country":"AU",
    "sg:address":"17a Francis St",
    "sg:city":"Fairlight",
    "sg:classifiers":[
        {
            "category":"Professional",
            "subcategory":"Management & Consulting",
            "type":"Services"
        }
    ],
    "sg:phone":"+61 2 8966 9548",
    "sg:postcode":"2094",
    "sg:province":"NSW",
    "sg:tags":[
        "consultant"
    ],
    "wof:name":"Bruce Alcorn & Associates",
    "wof:placetype":"venue"
},
  "geometry": {"coordinates":[151.278167725,-33.7931365967],"type":"Point"}
}