{
  "type": "Feature",
  "properties": {
    "addr:full":"PO Box 1429 Canning Vale DC WA 6970",
    "addr:postcode":"6970",
    "iso:country":"AU",
    "sg:address":"PO Box 1429",
    "sg:city":"Canning Vale DC",
    "sg:classifiers":[
        {
            "category":"Building & Trades",
            "subcategory":"Plumbing",
            "type":"Services"
        }
    ],
    "sg:phone":"+61 408 909 455",
    "sg:postcode":"6970",
    "sg:province":"WA",
    "sg:tags":[
        "drainers"
    ],
    "wof:name":"R & RM Drainage",
    "wof:placetype":"venue"
},
  "geometry": {"coordinates":[115.920921326,-32.0658683777],"type":"Point"}
}