{
  "type": "Feature",
  "properties": {
    "iso:country":"AU",
    "sg:address":"2- 4 Anesbury St",
    "sg:city":"Whyalla Norrie",
    "sg:classifiers":[
        {
            "category":"Social Services",
            "subcategory":"Retirement Home",
            "type":"Services"
        }
    ],
    "sg:phone":"+61 8 8645 2469",
    "sg:postcode":"5600",
    "sg:province":"SA",
    "sg:tags":[
        "village"
    ],
    "wof:name":"Village Life",
    "wof:placetype":"venue"
},
  "geometry": {"coordinates":[137.540176,-33.022892],"type":"Point"}
}