{
  "type": "Feature",
  "properties": {
    "addr:full":"13 Devenish St East Victoria Park WA 6101",
    "addr:housenumber":"13",
    "addr:postcode":"6101",
    "addr:street":"Devenish St",
    "iso:country":"AU",
    "sg:address":"13 Devenish St",
    "sg:city":"East Victoria Park",
    "sg:classifiers":[
        {
            "category":"Communications",
            "subcategory":"Newspaper",
            "type":"Services"
        }
    ],
    "sg:phone":"+61 8 9361 1259",
    "sg:postcode":"6101",
    "sg:province":"WA",
    "sg:tags":[
        "whiteboards",
        "chalkboard"
    ],
    "wof:name":"Graphics By Design",
    "wof:placetype":"venue"
},
  "geometry": {"coordinates":[115.894256592,-31.9886837006],"type":"Point"}
}