{
  "type": "Feature",
  "properties": {
    "addr:full":"9 Tarzali St Algester QLD 4115",
    "addr:housenumber":"9",
    "addr:postcode":"4115",
    "addr:street":"Tarzali St",
    "iso:country":"AU",
    "sg:address":"9 Tarzali St",
    "sg:city":"Algester",
    "sg:classifiers":[
        {
            "category":"Retail",
            "subcategory":"Driving School",
            "type":"Services"
        }
    ],
    "sg:phone":"+61 409 576 082",
    "sg:postcode":"4115",
    "sg:province":"QLD",
    "wof:name":"Sunnybank Driving School",
    "wof:placetype":"venue"
},
  "geometry": {"coordinates":[153.026657105,-27.6121768951],"type":"Point"}
}