{
  "type": "Feature",
  "properties": {
    "iso:country":"AU",
    "sg:address":"257 Dundas St",
    "sg:city":"Preston",
    "sg:classifiers":[
        {
            "category":"Professional",
            "type":"Services"
        }
    ],
    "sg:phone":"+61 3 9480 5024",
    "sg:postcode":"3072",
    "sg:province":"VIC",
    "sg:tags":[
        "shop",
        "fitting"
    ],
    "wof:name":"Phelan Robert Pty Ltd",
    "wof:placetype":"venue"
},
  "geometry": {"coordinates":[145.02711486800001,-37.7549743652],"type":"Point"}
}