{
  "type": "Feature",
  "properties": {
    "iso:country":"AU",
    "sg:address":"Unit 2, 113 Boundary Rd",
    "sg:city":"Peakhurst",
    "sg:classifiers":[
        {
            "category":"Professional",
            "subcategory":"Printing & Photocopies",
            "type":"Services"
        }
    ],
    "sg:phone":"+61 2 9153 9165",
    "sg:postcode":"2210",
    "sg:province":"NSW",
    "sg:tags":[
        "trophy"
    ],
    "wof:name":"Boundary Trophies & Giftware",
    "wof:placetype":"venue"
},
  "geometry": {"coordinates":[151.066193,-33.961788],"type":"Point"}
}