{
  "type": "Feature",
  "properties": {
    "iso:country":"AU",
    "sg:address":"32 Burke Rd",
    "sg:city":"Malvern East",
    "sg:classifiers":[
        {
            "category":"Personal",
            "subcategory":"Massage",
            "type":"Services"
        }
    ],
    "sg:phone":"+61 3 9822 8590",
    "sg:postcode":"3145",
    "sg:province":"VIC",
    "sg:tags":[
        "therapy"
    ],
    "wof:name":"Rochester K & L",
    "wof:placetype":"venue"
},
  "geometry": {"coordinates":[145.04841613799999,-37.8755645752],"type":"Point"}
}