{
  "type": "Feature",
  "properties": {
    "addr:full":"6 Acacia St Yarrawonga VIC 3730",
    "addr:housenumber":"6",
    "addr:postcode":"3730",
    "addr:street":"Acacia St",
    "iso:country":"AU",
    "sg:address":"6 Acacia St",
    "sg:city":"Yarrawonga",
    "sg:classifiers":[
        {
            "category":"Professional",
            "type":"Services"
        }
    ],
    "sg:phone":"+61 3 5743 1811",
    "sg:postcode":"3730",
    "sg:province":"VIC",
    "sg:tags":[
        "transport"
    ],
    "wof:name":"Adkins Transport Pty Ltd",
    "wof:placetype":"venue"
},
  "geometry": {"coordinates":[145.998779297,-36.0273742676],"type":"Point"}
}