{
  "type": "Feature",
  "properties": {
    "iso:country":"AU",
    "sg:address":"35 Wallaby Drv",
    "sg:city":"Gum Scrub",
    "sg:classifiers":[
        {
            "category":"Manufacturing",
            "subcategory":"Tools & Machinery",
            "type":"Manufacturing & Wholesale Goods"
        }
    ],
    "sg:phone":"+61 2 6585 8014",
    "sg:postcode":"2441",
    "sg:province":"NSW",
    "sg:tags":[
        "earth",
        "excavating",
        "moving",
        "equipment"
    ],
    "wof:name":"Galloway Excavations & Earthmoving Pty Ltd.",
    "wof:placetype":"venue"
},
  "geometry": {"coordinates":[152.740982,-31.295752],"type":"Point"}
}