{
  "type": "Feature",
  "properties": {
    "addr:full":"Shp2/ 13 Addison St Shellharbour NSW 2529",
    "addr:housenumber":"13",
    "addr:postcode":"2529",
    "addr:street":"Addison St",
    "iso:country":"AU",
    "sg:address":"Shp2/ 13 Addison St",
    "sg:city":"Shellharbour",
    "sg:classifiers":[
        {
            "category":"Personal",
            "subcategory":"Beauty Salon",
            "type":"Services"
        }
    ],
    "sg:phone":"+61 2 4296 9333",
    "sg:postcode":"2529",
    "sg:province":"NSW",
    "sg:tags":[
        "hairdresser"
    ],
    "wof:name":"Chelsea Hair Body Face",
    "wof:placetype":"venue"
},
  "geometry": {"coordinates":[150.86761474599999,-34.5792884827],"type":"Point"}
}