{
  "type": "Feature",
  "properties": {
    "iso:country":"AU",
    "sg:address":"20 Moresby St",
    "sg:city":"Trinity Beach",
    "sg:classifiers":[
        {
            "category":"Shopping",
            "subcategory":"Pets & Pet Supplies",
            "type":"Retail Goods"
        }
    ],
    "sg:phone":"+61 7 4057 8452",
    "sg:postcode":"4879",
    "sg:province":"QLD",
    "sg:tags":[
        "food"
    ],
    "wof:name":"The Real McCoy",
    "wof:placetype":"venue"
},
  "geometry": {"coordinates":[145.69642639200001,-16.7911911011],"type":"Point"}
}