{
  "type": "Feature",
  "properties": {
    "addr:full":"40 Marshall St Goondiwindi QLD 4390",
    "addr:housenumber":"40",
    "addr:postcode":"4390",
    "addr:street":"Marshall St",
    "iso:country":"AU",
    "sg:address":"40 Marshall St",
    "sg:city":"Goondiwindi",
    "sg:classifiers":[
        {
            "category":"Professional",
            "subcategory":"Accounting & Tax Preparation",
            "type":"Services"
        }
    ],
    "sg:phone":"+61 7 4671 2100",
    "sg:postcode":"4390",
    "sg:province":"QLD",
    "sg:tags":[
        "consultant",
        "taxation"
    ],
    "wof:name":"Fox & Elder",
    "wof:placetype":"venue"
},
  "geometry": {"coordinates":[150.31797790499999,-28.5484237671],"type":"Point"}
}