{
  "type": "Feature",
  "properties": {
    "addr:full":"268 Warrigal Rd Cheltenham VIC 3192",
    "addr:housenumber":"268",
    "addr:postcode":"3192",
    "addr:street":"Warrigal Rd",
    "iso:country":"AU",
    "sg:address":"268 Warrigal Rd",
    "sg:city":"Cheltenham",
    "sg:classifiers":[
        {
            "category":"Fast Food",
            "type":"Food & Drink"
        }
    ],
    "sg:phone":"+61 3 9585 0876",
    "sg:postcode":"3192",
    "sg:province":"VIC",
    "sg:tags":[
        "away",
        "take"
    ],
    "wof:name":"A.B.C. Chinese Take Away",
    "wof:placetype":"venue"
},
  "geometry": {"coordinates":[145.073974609,-37.9692230225],"type":"Point"}
}