{
  "type": "Feature",
  "properties": {
    "iso:country":"AU",
    "sg:address":"Shop 113, Level 3, Macquarie Centre",
    "sg:city":"North Ryde",
    "sg:classifiers":[
        {
            "category":"Personal",
            "subcategory":"Hair Removal",
            "type":"Services"
        }
    ],
    "sg:phone":"+61 2 9889 4777",
    "sg:postcode":"2113",
    "sg:province":"NSW",
    "sg:website":"http://www.waxitbetty.com",
    "wof:name":"Wax It Betty",
    "wof:placetype":"venue"
},
  "geometry": {"coordinates":[151.12094116200001,-33.7941093445],"type":"Point"}
}