{
  "type": "Feature",
  "properties": {
    "addr:full":"1 Watson La Jerilderie NSW 2716",
    "addr:housenumber":"1",
    "addr:postcode":"2716",
    "addr:street":"Watson La",
    "iso:country":"AU",
    "sg:address":"1 Watson La",
    "sg:city":"Jerilderie",
    "sg:classifiers":[
        {
            "category":"Commercial Area",
            "type":"Public Place"
        }
    ],
    "sg:phone":"+61 418 942 711",
    "sg:postcode":"2716",
    "sg:province":"NSW",
    "sg:tags":[
        "heavy",
        "carrier"
    ],
    "wof:name":"Riverluck Transport Pty Ltd",
    "wof:placetype":"venue"
},
  "geometry": {"coordinates":[145.70838928200001,-35.3622436523],"type":"Point"}
}