{
  "type": "Feature",
  "properties": {
    "iso:country":"AU",
    "sg:address":"1080 Sydney Rd",
    "sg:city":"Fawkner",
    "sg:classifiers":[
        {
            "category":"Autos & Motor Vehicles",
            "subcategory":"Automobile Sales",
            "type":"Retail Goods"
        }
    ],
    "sg:phone":"+61 3 9357 3700",
    "sg:postcode":"3060",
    "sg:province":"VIC",
    "sg:tags":[
        "car",
        "used"
    ],
    "wof:name":"Sydney Road Car Centre",
    "wof:placetype":"venue"
},
  "geometry": {"coordinates":[144.96295165999999,-37.7174911499],"type":"Point"}
}