{
  "type": "Feature",
  "properties": {
    "addr:full":"21 Government Rd Cessnock NSW 2325",
    "addr:housenumber":"21",
    "addr:postcode":"2325",
    "addr:street":"Government Rd",
    "iso:country":"AU",
    "sg:address":"21 Government Rd",
    "sg:city":"Cessnock",
    "sg:classifiers":[
        {
            "category":"Utilities",
            "subcategory":"Fuel Oil & Lpg",
            "type":"Services"
        }
    ],
    "sg:phone":"+61 2 4991 4600",
    "sg:postcode":"2325",
    "sg:province":"NSW",
    "sg:tags":[
        "merchant"
    ],
    "wof:name":"O'Neill P & L Pty Ltd",
    "wof:placetype":"venue"
},
  "geometry": {"coordinates":[151.36700439399999,-32.8213768005],"type":"Point"}
}