{
  "type": "Feature",
  "properties": {
    "addr:full":"42 Oakland Ave Ballina NSW 2478",
    "addr:housenumber":"42",
    "addr:postcode":"2478",
    "addr:street":"Oakland Ave",
    "iso:country":"AU",
    "sg:address":"42 Oakland Ave",
    "sg:city":"Ballina",
    "sg:classifiers":[
        {
            "category":"Personal",
            "subcategory":"Massage",
            "type":"Services"
        }
    ],
    "sg:phone":"+61 2 6686 5443",
    "sg:postcode":"2478",
    "sg:province":"NSW",
    "sg:tags":[
        "therapy"
    ],
    "wof:name":"Liz Hanns Bodywork Clinic",
    "wof:placetype":"venue"
},
  "geometry": {"coordinates":[153.53631591800001,-28.8650131226],"type":"Point"}
}