{
  "type": "Feature",
  "properties": {
    "iso:country":"AU",
    "sg:address":"109 Berry St",
    "sg:city":"Nowra",
    "sg:classifiers":[
        {
            "category":"Retail",
            "subcategory":"Veterinary Services",
            "type":"Services"
        }
    ],
    "sg:phone":"+61 2 4421 3150",
    "sg:postcode":"2541",
    "sg:province":"NSW",
    "sg:tags":[
        "surgeon"
    ],
    "wof:name":"Clarke Justin",
    "wof:placetype":"venue"
},
  "geometry": {"coordinates":[150.598953247,-34.8817062378],"type":"Point"}
}