{
  "type": "Feature",
  "properties": {
    "addr:full":"Shp 10/ 2 Collins La Kiama NSW 2533",
    "addr:housenumber":"10 / 2",
    "addr:postcode":"2533",
    "addr:street":"Collins La",
    "iso:country":"AU",
    "sg:address":"Shp 10/ 2 Collins La",
    "sg:city":"Kiama",
    "sg:classifiers":[
        {
            "category":"Personal",
            "subcategory":"Beauty Salon",
            "type":"Services"
        }
    ],
    "sg:phone":"+61 2 4232 1929",
    "sg:postcode":"2533",
    "sg:province":"NSW",
    "sg:tags":[
        "hairdresser"
    ],
    "wof:name":"Blondies",
    "wof:placetype":"venue"
},
  "geometry": {"coordinates":[150.851806641,-34.6771583557],"type":"Point"}
}