{
  "type": "Feature",
  "properties": {
    "addr:full":"Uniting Church Hall Clarendon St Armadale VIC 3143",
    "addr:postcode":"3143",
    "addr:street":"Clarendon St",
    "iso:country":"AU",
    "sg:address":"Uniting Church Hall Clarendon St",
    "sg:city":"Armadale",
    "sg:classifiers":[
        {
            "category":"Education",
            "subcategory":"Dance Studio",
            "type":"Public Place"
        }
    ],
    "sg:phone":"+61 3 9527 6963",
    "sg:postcode":"3143",
    "sg:province":"VIC",
    "sg:tags":[
        "venue",
        "tuition"
    ],
    "wof:name":"Dance Start Bridal Waltz In Social Ballroom Style Of Dancing",
    "wof:placetype":"venue"
},
  "geometry": {"coordinates":[145.02125549300001,-37.856300354],"type":"Point"}
}