{
  "type": "Feature",
  "properties": {
    "iso:country":"AU",
    "sg:address":"44 Leonard Ave",
    "sg:city":"Toukley",
    "sg:classifiers":[
        {
            "category":"Home & Garden",
            "subcategory":"Hardware",
            "type":"Retail Goods"
        }
    ],
    "sg:phone":"+61 2 4396 4420",
    "sg:postcode":"2263",
    "sg:province":"NSW",
    "sg:tags":[
        "plumber",
        "supply"
    ],
    "wof:name":"R & K Rennie Enterprises Pty Ltd",
    "wof:placetype":"venue"
},
  "geometry": {"coordinates":[151.544937,-33.25713],"type":"Point"}
}