{
  "type": "Feature",
  "properties": {
    "addr:full":"35 Rutleys Rd Wyee Point NSW 2259",
    "addr:housenumber":"35",
    "addr:postcode":"2259",
    "addr:street":"Rutleys Rd",
    "iso:country":"AU",
    "sg:address":"35 Rutleys Rd",
    "sg:city":"Wyee Point",
    "sg:classifiers":[
        {
            "category":"Donuts",
            "subcategory":"None",
            "type":"Food & Drink"
        }
    ],
    "sg:phone":"+61 2 4359 1622",
    "sg:postcode":"2259",
    "sg:province":"NSW",
    "sg:tags":[
        "die",
        "engraver",
        "sinker"
    ],
    "wof:name":"Neil's Timber Signs",
    "wof:placetype":"venue"
},
  "geometry": {"coordinates":[151.521850586,-33.1522674561],"type":"Point"}
}