{
  "type": "Feature",
  "properties": {
    "addr:full":"Suite 4/ 33 Chesterville Rd Moorabbin VIC 3189",
    "addr:housenumber":"33",
    "addr:postcode":"3189",
    "addr:street":"Chesterville Rd",
    "iso:country":"AU",
    "sg:address":"Suite 4/ 33 Chesterville Rd",
    "sg:city":"Moorabbin",
    "sg:classifiers":[
        {
            "category":"Building & Trades",
            "subcategory":"Construction",
            "type":"Services"
        }
    ],
    "sg:phone":"+61 3 9873 4106",
    "sg:postcode":"3189",
    "sg:province":"VIC",
    "sg:tags":[
        "fencing",
        "contractor"
    ],
    "wof:name":"A-AAA-Brick & Steel Fences",
    "wof:placetype":"venue"
},
  "geometry": {"coordinates":[145.05973815900001,-37.9439315796],"type":"Point"}
}