{
  "type": "Feature",
  "properties": {
    "addr:full":"12 Hutcheson St Albion QLD 4010",
    "addr:housenumber":"12",
    "addr:postcode":"4010",
    "addr:street":"Hutcheson St",
    "iso:country":"AU",
    "sg:address":"12 Hutcheson St",
    "sg:city":"Albion",
    "sg:classifiers":[
        {
            "category":"Professional",
            "type":"Services"
        }
    ],
    "sg:phone":"+61 7 3267 1300",
    "sg:postcode":"4010",
    "sg:province":"QLD",
    "sg:tags":[
        "forwarding",
        "agent",
        "transport"
    ],
    "wof:name":"Freightnet International (Qld) Pty Ltd",
    "wof:placetype":"venue"
},
  "geometry": {"coordinates":[153.04450988799999,-27.4396324158],"type":"Point"}
}