{
  "type": "Feature",
  "properties": {
    "iso:country":"AU",
    "sg:address":"Isdell Pl",
    "sg:city":"Gosnells",
    "sg:classifiers":[
        {
            "category":"Education",
            "subcategory":"School",
            "type":"Public Place"
        }
    ],
    "sg:phone":"+61 8 9398 1233",
    "sg:postcode":"6110",
    "sg:province":"WA",
    "sg:tags":[
        "co-educational"
    ],
    "wof:name":"St Munchin's",
    "wof:placetype":"venue"
},
  "geometry": {"coordinates":[115.986831665,-32.0813865662],"type":"Point"}
}