{
  "type": "Feature",
  "properties": {
    "addr:full":"Shop 1 Myall St Shopng Cntr Dubbo NSW 2830",
    "addr:housenumber":"shop 1",
    "addr:postcode":"2830",
    "addr:street":"Myall St Shopng Cntr",
    "iso:country":"AU",
    "sg:address":"Shop 1 Myall St Shopng Cntr",
    "sg:city":"Dubbo",
    "sg:classifiers":[
        {
            "category":"Personal",
            "subcategory":"Beauty Salon",
            "type":"Services"
        }
    ],
    "sg:phone":"+61 2 6884 3555",
    "sg:postcode":"2830",
    "sg:province":"NSW",
    "wof:name":"Annes Beauty Dubbo",
    "wof:placetype":"venue"
},
  "geometry": {"coordinates":[148.615692139,-32.240486145],"type":"Point"}
}