{
  "type": "Feature",
  "properties": {
    "iso:country":"AU",
    "sg:address":"100 Rupert St",
    "sg:city":"Collingwood",
    "sg:classifiers":[
        {
            "category":"Communications",
            "subcategory":"Film & Video Production",
            "type":"Services"
        }
    ],
    "sg:phone":"+61 3 9419 3511",
    "sg:postcode":"3066",
    "sg:province":"VIC",
    "sg:tags":[
        "lighting",
        "emergency",
        "power"
    ],
    "wof:name":"Famco Lighting Pty Ltd",
    "wof:placetype":"venue"
},
  "geometry": {"coordinates":[144.98927307100001,-37.8061256409],"type":"Point"}
}