{
  "type": "Feature",
  "properties": {
    "addr:full":"Shed 3/ 105 Archibald St Mackay QLD 4740",
    "addr:housenumber":"3 / 105",
    "addr:postcode":"4740",
    "addr:street":"Archibald St",
    "iso:country":"AU",
    "sg:address":"Shed 3/ 105 Archibald St",
    "sg:city":"Mackay",
    "sg:classifiers":[
        {
            "category":"Professional",
            "type":"Services"
        }
    ],
    "sg:phone":"+61 7 4952 4434",
    "sg:postcode":"4740",
    "sg:province":"QLD",
    "sg:tags":[
        "spray",
        "painting"
    ],
    "wof:name":"Pittys Paint Shop",
    "wof:placetype":"venue"
},
  "geometry": {"coordinates":[149.16351299999999,-21.168154],"type":"Point"}
}