{
  "type": "Feature",
  "properties": {
    "addr:full":"CAE Centre 256 Flinders St Melbourne VIC 3000",
    "addr:housenumber":"256",
    "addr:postcode":"3000",
    "addr:street":"Flinders St",
    "iso:country":"AU",
    "sg:address":"CAE Centre 256 Flinders St",
    "sg:city":"Melbourne",
    "sg:classifiers":[
        {
            "category":"Education",
            "subcategory":"University",
            "type":"Public Place"
        }
    ],
    "sg:phone":"+61 3 9652 0649",
    "sg:postcode":"3000",
    "sg:province":"VIC",
    "sg:tags":[
        "educational",
        "organisation",
        "cultural"
    ],
    "wof:name":"Universities Of The Third Age (U3A) - Victorian Network",
    "wof:placetype":"venue"
},
  "geometry": {"coordinates":[144.96572875999999,-37.8178253174],"type":"Point"}
}