{
  "type": "Feature",
  "properties": {
    "iso:country":"AU",
    "sg:address":"18 Grice Ave",
    "sg:city":"Paradise Point",
    "sg:classifiers":[
        {
            "category":"Shopping",
            "subcategory":"Clothing, Apparel, & Fashions",
            "type":"Retail Goods"
        }
    ],
    "sg:phone":"+61 7 5577 4688",
    "sg:postcode":"4216",
    "sg:province":"QLD",
    "sg:tags":[
        "recycled",
        "clothing"
    ],
    "wof:name":"2nd Wardrobe",
    "wof:placetype":"venue"
},
  "geometry": {"coordinates":[153.39442443900001,-27.8852443695],"type":"Point"}
}