{
  "type": "Feature",
  "properties": {
    "iso:country":"AU",
    "sg:address":"1965 Logan Rd",
    "sg:city":"Upper Mt Gravatt",
    "sg:classifiers":[
        {
            "category":"Food & Beverages",
            "subcategory":"Specialty",
            "type":"Retail Goods"
        }
    ],
    "sg:phone":"+61 7 3219 3822",
    "sg:postcode":"4122",
    "sg:province":"QLD",
    "sg:tags":[
        "product",
        "health"
    ],
    "wof:name":"AAA Universal Fitness Shop",
    "wof:placetype":"venue"
},
  "geometry": {"coordinates":[153.08038330100001,-27.5586986542],"type":"Point"}
}