{
  "type": "Feature",
  "properties": {
    "iso:country":"AU",
    "sg:address":"1315 Ferntree Gully Rd",
    "sg:city":"Scoresby",
    "sg:classifiers":[
        {
            "category":"Social Services",
            "subcategory":"Child Care",
            "type":"Services"
        }
    ],
    "sg:phone":"+61 3 9763 8306",
    "sg:postcode":"3179",
    "sg:province":"VIC",
    "wof:name":"Scoresby Village Child Care Centre",
    "wof:placetype":"venue"
},
  "geometry": {"coordinates":[145.228515625,-37.8989562988],"type":"Point"}
}