{
  "type": "Feature",
  "properties": {
    "addr:full":"Suite 1/ 43 Commerce Drv Robina QLD 4226",
    "addr:housenumber":"43",
    "addr:postcode":"4226",
    "addr:street":"Commerce Drv",
    "iso:country":"AU",
    "sg:address":"Suite 1/ 43 Commerce Drv",
    "sg:city":"Robina",
    "sg:classifiers":[
        {
            "category":"Health Services",
            "subcategory":"Health Practitioner",
            "type":"Services"
        }
    ],
    "sg:phone":"+61 7 5578 7233",
    "sg:postcode":"4226",
    "sg:province":"QLD",
    "sg:tags":[
        "physiotherapist"
    ],
    "wof:name":"Leigh McCutcheon & Associates",
    "wof:placetype":"venue"
},
  "geometry": {"coordinates":[153.403686523,-28.0650520325],"type":"Point"}
}