{
  "type": "Feature",
  "properties": {
    "addr:full":"19 Geddes St Mulgrave VIC 3170",
    "addr:housenumber":"19",
    "addr:postcode":"3170",
    "addr:street":"Geddes St",
    "iso:country":"AU",
    "sg:address":"19 Geddes St",
    "sg:city":"Mulgrave",
    "sg:classifiers":[
        {
            "category":"Utilities",
            "subcategory":"Water",
            "type":"Services"
        }
    ],
    "sg:phone":"+61 3 9560 1155",
    "sg:postcode":"3170",
    "sg:province":"VIC",
    "sg:tags":[
        "equipment",
        "treatment"
    ],
    "wof:name":"Australian Separation Technologies Group Pty Ltd",
    "wof:placetype":"venue"
},
  "geometry": {"coordinates":[145.15447998100001,-37.9059028625],"type":"Point"}
}