{
  "type": "Feature",
  "properties": {
    "iso:country":"AU",
    "sg:address":"Deep Creek Rd",
    "sg:city":"Wynyard",
    "sg:classifiers":[
        {
            "category":"Farming",
            "subcategory":"Farm",
            "type":"Manufacturing & Wholesale Goods"
        }
    ],
    "sg:phone":"+61 3 6442 3358",
    "sg:postcode":"7325",
    "sg:province":"TAS",
    "sg:tags":[
        "farmer"
    ],
    "wof:name":"Flint S R & L F",
    "wof:placetype":"venue"
},
  "geometry": {"coordinates":[145.71142599999999,-40.99633],"type":"Point"}
}