{
  "type": "Feature",
  "properties": {
    "addr:full":"182 Redfern Rd Redfern NSW 2016",
    "addr:housenumber":"182",
    "addr:postcode":"2016",
    "addr:street":"Redfern Rd",
    "iso:country":"AU",
    "sg:address":"182 Redfern Rd",
    "sg:city":"Redfern",
    "sg:classifiers":[
        {
            "category":"Professional",
            "subcategory":"Detective & Security Services",
            "type":"Services"
        }
    ],
    "sg:phone":"+61 2 9212 6663",
    "sg:postcode":"2016",
    "sg:province":"NSW",
    "sg:tags":[
        "consultant",
        "laser"
    ],
    "wof:name":"AAA Visual Signs",
    "wof:placetype":"venue"
},
  "geometry": {"coordinates":[151.20074462900001,-33.8921928406],"type":"Point"}
}