{
  "type": "Feature",
  "properties": {
    "addr:full":"Suite 2d/Second Floor 23-29 South St Rydalmere NSW 2116",
    "addr:housenumber":"2d /;23-29",
    "addr:postcode":"2116",
    "addr:street":"South St",
    "iso:country":"AU",
    "sg:address":"Suite 2d/Second Floor 23-29 South St",
    "sg:city":"Rydalmere",
    "sg:classifiers":[
        {
            "category":"Professional",
            "subcategory":"Engineering",
            "type":"Services"
        }
    ],
    "sg:phone":"+61 2 9898 3888",
    "sg:postcode":"2116",
    "sg:province":"NSW",
    "sg:tags":[
        "chemical",
        "engineer"
    ],
    "wof:name":"Process Design & Fabrication Pty Ltd",
    "wof:placetype":"venue"
},
  "geometry": {"coordinates":[151.01124572800001,-33.8335876465],"type":"Point"}
}