{
  "type": "Feature",
  "properties": {
    "iso:country":"AU",
    "sg:address":"60 buninyong St",
    "sg:city":"Yarraville",
    "sg:classifiers":[
        {
            "category":"Professional",
            "subcategory":"Computer Services",
            "type":"Services"
        }
    ],
    "sg:phone":"+61 411 731 356",
    "sg:postcode":"3013",
    "sg:province":"VIC",
    "sg:tags":[
        "equipment",
        "networking",
        "installation"
    ],
    "wof:name":"Ramming Network Maintenance",
    "wof:placetype":"venue"
},
  "geometry": {"coordinates":[144.88783264200001,-37.820148468],"type":"Point"}
}