{
  "type": "Feature",
  "properties": {
    "addr:full":"Shop 21 Bayswater Village 9 High Bayswater VIC 3153",
    "addr:housenumber":"shop 21;9",
    "addr:postcode":"3153",
    "addr:street":"Village;High",
    "iso:country":"AU",
    "sg:address":"Shop 21 Bayswater Village 9 High",
    "sg:city":"Bayswater",
    "sg:classifiers":[
        {
            "category":"Casinos & Gambling",
            "type":"Entertainment"
        }
    ],
    "sg:phone":"+61 3 9729 0119",
    "sg:postcode":"3153",
    "sg:province":"VIC",
    "sg:tags":[
        "lottery",
        "agent"
    ],
    "wof:name":"Bayswater Tattslotto Shop,",
    "wof:placetype":"venue"
},
  "geometry": {"coordinates":[145.26669311500001,-37.8427352905],"type":"Point"}
}