{
  "type": "Feature",
  "properties": {
    "addr:full":"Shop 24 Eaton St Mall Oakleigh VIC 3166",
    "addr:housenumber":"shop 24",
    "addr:postcode":"3166",
    "addr:street":"Eaton St Mall",
    "iso:country":"AU",
    "sg:address":"Shop 24 Eaton St",
    "sg:city":"Mall Oakleigh",
    "sg:classifiers":[
        {
            "category":"Food & Beverages",
            "subcategory":"Bakery",
            "type":"Retail Goods"
        }
    ],
    "sg:phone":"+61 3 9568 4422",
    "sg:postcode":"3166",
    "sg:province":"VIC",
    "sg:tags":[
        "cake",
        "shop",
        "pastry"
    ],
    "wof:name":"The Cake House",
    "wof:placetype":"venue"
},
  "geometry": {"coordinates":[145.090133667,-37.8997154236],"type":"Point"}
}