{
  "type": "Feature",
  "properties": {
    "iso:country":"AU",
    "sg:address":"124b Bulwer St",
    "sg:city":"Perth",
    "sg:classifiers":[
        {
            "category":"Building & Trades",
            "subcategory":"Cleaning & Sanitation",
            "type":"Services"
        }
    ],
    "sg:phone":"+61 419 867 684",
    "sg:postcode":"6000",
    "sg:province":"WA",
    "sg:tags":[
        "window"
    ],
    "wof:name":"Orbit Group",
    "wof:placetype":"venue"
},
  "geometry": {"coordinates":[115.85989379900001,-31.9394207001],"type":"Point"}
}