{
  "type": "Feature",
  "properties": {
    "iso:country":"AU",
    "sg:address":"2 Vision Drv",
    "sg:city":"Burwood East",
    "sg:classifiers":[
        {
            "category":"Government",
            "subcategory":"Court House",
            "type":"Public Place"
        }
    ],
    "sg:phone":"+61 3 9886 3899",
    "sg:postcode":"3151",
    "sg:province":"VIC",
    "sg:tags":[
        "personal",
        "marriage",
        "family",
        "counselling"
    ],
    "wof:name":"Crossway Pastoral Counselling Centre",
    "wof:placetype":"venue"
},
  "geometry": {"coordinates":[145.168457031,-37.8589248657],"type":"Point"}
}