{
  "type": "Feature",
  "properties": {
    "addr:full":"35 Armadale Rd Forrestdale WA 6112",
    "addr:housenumber":"35",
    "addr:postcode":"6112",
    "addr:street":"Armadale Rd",
    "iso:country":"AU",
    "sg:address":"35 Armadale Rd",
    "sg:city":"Forrestdale",
    "sg:classifiers":[
        {
            "category":"Manufacturing",
            "subcategory":"Metals",
            "type":"Manufacturing & Wholesale Goods"
        }
    ],
    "sg:phone":"+61 8 9397 1110",
    "sg:postcode":"6112",
    "sg:province":"WA",
    "sg:tags":[
        "spinner"
    ],
    "wof:name":"Brinkworth Engineering",
    "wof:placetype":"venue"
},
  "geometry": {"coordinates":[115.957206726,-32.1477928162],"type":"Point"}
}