{
  "type": "Feature",
  "properties": {
    "iso:country":"AU",
    "sg:address":"134 Walker St",
    "sg:city":"Sebastopol",
    "sg:classifiers":[
        {
            "category":"Home & Garden",
            "subcategory":"Garden Supply",
            "type":"Retail Goods"
        }
    ],
    "sg:phone":"+61 3 5336 1265",
    "sg:postcode":"3356",
    "sg:province":"VIC",
    "sg:tags":[
        "equipment"
    ],
    "wof:name":"Neish's Garden Bags",
    "wof:placetype":"venue"
},
  "geometry": {"coordinates":[143.83627300000001,-37.595177],"type":"Point"}
}