{
  "type": "Feature",
  "properties": {
    "addr:full":"Strathvole Crt Caboolture QLD 4510",
    "addr:postcode":"4510",
    "addr:street":"Strathvole Crt",
    "iso:country":"AU",
    "sg:address":"Strathvole Crt",
    "sg:city":"Caboolture",
    "sg:classifiers":[
        {
            "category":"Home & Garden",
            "subcategory":"Building Materials",
            "type":"Retail Goods"
        }
    ],
    "sg:phone":"+61 7 3205 7075",
    "sg:postcode":"4510",
    "sg:province":"QLD",
    "sg:tags":[
        "pre-mixed",
        "concrete"
    ],
    "wof:name":"Excel Concrete Pty. Ltd.",
    "wof:placetype":"venue"
},
  "geometry": {"coordinates":[152.94586200000001,-27.070316],"type":"Point"}
}