{
  "type": "Feature",
  "properties": {
    "iso:country":"AU",
    "sg:address":"2a Scarborough Drv",
    "sg:city":"Beacon Hill",
    "sg:classifiers":[
        {
            "category":"Home & Garden",
            "subcategory":"Furniture",
            "type":"Retail Goods"
        }
    ],
    "sg:phone":"+61 410 351 622",
    "sg:postcode":"2100",
    "sg:province":"NSW",
    "sg:tags":[
        "repair",
        "restoration"
    ],
    "sg:website":"http://steve.furnituremedic.googlepages.com/home",
    "wof:name":"Furniture Medic",
    "wof:placetype":"venue"
},
  "geometry": {"coordinates":[151.258422852,-33.7455558777],"type":"Point"}
}