{
  "type": "Feature",
  "properties": {
    "addr:full":"124 Moray St South Melbourne VIC 3205",
    "addr:housenumber":"124",
    "addr:postcode":"3205",
    "addr:street":"Moray St",
    "iso:country":"AU",
    "sg:address":"124 Moray St",
    "sg:city":"South Melbourne",
    "sg:classifiers":[
        {
            "category":"Retail",
            "subcategory":"Auto Rental",
            "type":"Services"
        }
    ],
    "sg:phone":"+61 3 9690 9944",
    "sg:postcode":"3205",
    "sg:province":"VIC",
    "sg:tags":[
        "car",
        "hire",
        "minibus"
    ],
    "wof:name":"Avis",
    "wof:placetype":"venue"
},
  "geometry": {"coordinates":[144.96174600000001,-37.829784],"type":"Point"}
}