{
  "type": "Feature",
  "properties": {
    "addr:full":"190 Shipper Drv Coomera QLD 4209",
    "addr:housenumber":"190",
    "addr:postcode":"4209",
    "addr:street":"Shipper Drv",
    "iso:country":"AU",
    "sg:address":"190 Shipper Drv",
    "sg:city":"Coomera",
    "sg:classifiers":[
        {
            "category":"Education",
            "subcategory":"Vocational School",
            "type":"Public Place"
        }
    ],
    "sg:phone":"+61 7 5573 0360",
    "sg:postcode":"4209",
    "sg:province":"QLD",
    "sg:tags":[
        "cake",
        "decorating",
        "decorator"
    ],
    "wof:name":"Mandy Owen-Jones Cake Decorator",
    "wof:placetype":"venue"
},
  "geometry": {"coordinates":[153.33653259299999,-27.8613739014],"type":"Point"}
}