{
  "type": "Feature",
  "properties": {
    "addr:full":"1a Salisbury Hwy Salisbury SA 5108",
    "addr:housenumber":"1a",
    "addr:postcode":"5108",
    "addr:street":"Salisbury Hwy",
    "iso:country":"AU",
    "sg:address":"1a Salisbury Hwy",
    "sg:city":"Salisbury",
    "sg:classifiers":[
        {
            "category":"Recreation",
            "subcategory":"Fishing",
            "type":"Entertainment"
        }
    ],
    "sg:phone":"+61 8 8258 1166",
    "sg:postcode":"5108",
    "sg:province":"SA",
    "sg:tags":[
        "tackle"
    ],
    "wof:name":"Salisbury Dive & TackleWorld",
    "wof:placetype":"venue"
},
  "geometry": {"coordinates":[138.64729309099999,-34.7559089661],"type":"Point"}
}