{
  "type": "Feature",
  "properties": {
    "iso:country":"AU",
    "sg:address":"140 Matthew Flinders Drv",
    "sg:city":"Port Macquarie",
    "sg:classifiers":[
        {
            "category":"Cafe",
            "type":"Food & Drink"
        }
    ],
    "sg:phone":"+61 2 6582 5888",
    "sg:postcode":"2444",
    "sg:province":"NSW",
    "wof:name":"Village Cafe Restaurant",
    "wof:placetype":"venue"
},
  "geometry": {"coordinates":[152.934204,-31.471434],"type":"Point"}
}