{
  "type": "Feature",
  "properties": {
    "addr:full":"140 Matthew Flinders Drv Port Macquarie NSW 2444",
    "addr:housenumber":"140",
    "addr:postcode":"2444",
    "addr:street":"Matthew Flinders Drv",
    "iso:country":"AU",
    "sg:address":"140 Matthew Flinders Drv",
    "sg:city":"Port Macquarie",
    "sg:classifiers":[
        {
            "category":"Cafe",
            "type":"Food & Drink"
        }
    ],
    "sg:phone":"+61 2 6582 5888",
    "sg:postcode":"2444",
    "sg:province":"NSW",
    "wof:name":"Village Cafe Restaurant",
    "wof:placetype":"venue"
},
  "geometry": {"coordinates":[152.93420399999999,-31.471434],"type":"Point"}
}