{
  "type": "Feature",
  "properties": {
    "iso:country":"AU",
    "sg:address":"1321 Hay St",
    "sg:city":"West Perth",
    "sg:classifiers":[
        {
            "category":"Professional",
            "subcategory":"Accounting & Tax Preparation",
            "type":"Services"
        }
    ],
    "sg:phone":"+61 8 9322 1454",
    "sg:postcode":"6005",
    "sg:province":"WA",
    "sg:tags":[
        "accountant",
        "auditor"
    ],
    "wof:name":"Pierluigi G P",
    "wof:placetype":"venue"
},
  "geometry": {"coordinates":[115.837532044,-31.9473552704],"type":"Point"}
}