{
  "type": "Feature",
  "properties": {
    "addr:full":"45 Bromfield St Colac VIC 3250",
    "addr:housenumber":"45",
    "addr:postcode":"3250",
    "addr:street":"Bromfield St",
    "iso:country":"AU",
    "sg:address":"45 Bromfield St",
    "sg:city":"Colac",
    "sg:classifiers":[
        {
            "category":"Personal",
            "subcategory":"Beauty Salon",
            "type":"Services"
        }
    ],
    "sg:phone":"+61 3 5232 2766",
    "sg:postcode":"3250",
    "sg:province":"VIC",
    "sg:tags":[
        "hairdresser"
    ],
    "wof:name":"Unisexcuts",
    "wof:placetype":"venue"
},
  "geometry": {"coordinates":[143.586792,-38.340775],"type":"Point"}
}