{
  "type": "Feature",
  "properties": {
    "addr:full":"Ste2/ 7 Strathaird Rd Bundall QLD 4217",
    "addr:housenumber":"7",
    "addr:postcode":"4217",
    "addr:street":"Strathaird Rd",
    "iso:country":"AU",
    "sg:address":"Ste2/ 7 Strathaird Rd",
    "sg:city":"Bundall",
    "sg:classifiers":[
        {
            "category":"Wholesale",
            "subcategory":"Apparel",
            "type":"Manufacturing & Wholesale Goods"
        }
    ],
    "sg:phone":"+61 7 5592 6899",
    "sg:postcode":"4217",
    "sg:province":"QLD",
    "sg:tags":[
        "wholesaler",
        "mfrs",
        "cap",
        "hat"
    ],
    "wof:name":"Australiana Products",
    "wof:placetype":"venue"
},
  "geometry": {"coordinates":[153.40432739299999,-28.0090942383],"type":"Point"}
}