{
  "type": "Feature",
  "properties": {
    "addr:full":"58 Channon St Gympie QLD 4570",
    "addr:housenumber":"58",
    "addr:postcode":"4570",
    "addr:street":"Channon St",
    "iso:country":"AU",
    "sg:address":"58 Channon St",
    "sg:city":"Gympie",
    "sg:classifiers":[
        {
            "category":"Building & Trades",
            "subcategory":"Construction",
            "type":"Services"
        }
    ],
    "sg:phone":"+61 7 5482 6368",
    "sg:postcode":"4570",
    "sg:province":"QLD",
    "sg:tags":[
        "road",
        "contractor"
    ],
    "wof:name":"Cooloola Civil Constructions",
    "wof:placetype":"venue"
},
  "geometry": {"coordinates":[152.66152954099999,-26.1848583221],"type":"Point"}
}