{
  "type": "Feature",
  "properties": {
    "addr:full":"19 Frost St Clontarf QLD 4019",
    "addr:housenumber":"19",
    "addr:postcode":"4019",
    "addr:street":"Frost St",
    "iso:country":"AU",
    "sg:address":"19 Frost St",
    "sg:city":"Clontarf",
    "sg:classifiers":[
        {
            "category":"Home & Garden",
            "subcategory":"Household Appliances",
            "type":"Retail Goods"
        }
    ],
    "sg:phone":"+61 418 745 763",
    "sg:postcode":"4019",
    "sg:province":"QLD",
    "sg:tags":[
        "equipment",
        "gas"
    ],
    "wof:name":"Gas Supplies & Fitters (Northside)",
    "wof:placetype":"venue"
},
  "geometry": {"coordinates":[153.077514648,-27.2538070679],"type":"Point"}
}