{
  "type": "Feature",
  "properties": {
    "addr:full":"109 Coulstock St Warrnambool VIC 3280",
    "addr:housenumber":"109",
    "addr:postcode":"3280",
    "addr:street":"Coulstock St",
    "iso:country":"AU",
    "sg:address":"109 Coulstock St",
    "sg:city":"Warrnambool",
    "sg:classifiers":[
        {
            "category":"Building & Trades",
            "subcategory":"Construction",
            "type":"Services"
        }
    ],
    "sg:phone":"+61 3 5562 7944",
    "sg:postcode":"3280",
    "sg:province":"VIC",
    "sg:tags":[
        "contractor"
    ],
    "wof:name":"Armitstead S C & L J",
    "wof:placetype":"venue"
},
  "geometry": {"coordinates":[142.495437622,-38.3818702698],"type":"Point"}
}