{
  "type": "Feature",
  "properties": {
    "iso:country":"AU",
    "sg:address":"79 Swallow St",
    "sg:city":"Port Melbourne",
    "sg:classifiers":[
        {
            "category":"Travel",
            "subcategory":"Hostel",
            "type":"Entertainment"
        }
    ],
    "sg:phone":"+61 3 9646 0588",
    "sg:postcode":"3207",
    "sg:province":"VIC",
    "sg:tags":[
        "home"
    ],
    "wof:name":"Wintringham Hostels",
    "wof:placetype":"venue"
},
  "geometry": {"coordinates":[144.933197,-37.83786],"type":"Point"}
}