{
  "type": "Feature",
  "properties": {
    "iso:country":"AU",
    "sg:address":"Cnr Hallam & Ormond Rds",
    "sg:city":"Hampton Park",
    "sg:classifiers":[
        {
            "category":"Autos & Motor Vehicles",
            "subcategory":"Fuel & Gas Station",
            "type":"Retail Goods"
        }
    ],
    "sg:phone":"+61 3 9799 0900",
    "sg:postcode":"3976",
    "sg:province":"VIC",
    "wof:name":"Better Choice",
    "wof:placetype":"venue"
},
  "geometry": {"coordinates":[145.26614379899999,-38.0417861938],"type":"Point"}
}