{
  "type": "Feature",
  "properties": {
    "addr:full":"27/ 427 Montague Rd Modbury North SA 5092",
    "addr:housenumber":"27 / 427",
    "addr:postcode":"5092",
    "addr:street":"Montague Rd",
    "iso:country":"AU",
    "sg:address":"27/ 427 Montague Rd",
    "sg:city":"Modbury North",
    "sg:classifiers":[
        {
            "category":"Professional",
            "subcategory":"Accounting & Tax Preparation",
            "type":"Services"
        }
    ],
    "sg:phone":"+61 8 8263 4009",
    "sg:postcode":"5092",
    "sg:province":"SA",
    "sg:tags":[
        "consultant",
        "taxation"
    ],
    "wof:name":"NieuVision Finance",
    "wof:placetype":"venue"
},
  "geometry": {"coordinates":[138.671432495,-34.829120636],"type":"Point"}
}