{
  "type": "Feature",
  "properties": {
    "addr:full":"83 Clarence St Sydney NSW 2000",
    "addr:housenumber":"83",
    "addr:postcode":"2000",
    "addr:street":"Clarence St",
    "iso:country":"AU",
    "sg:address":"83 Clarence St",
    "sg:city":"Sydney",
    "sg:classifiers":[
        {
            "category":"Cafe",
            "type":"Food & Drink"
        }
    ],
    "sg:phone":"+61 2 9299 5050",
    "sg:postcode":"2000",
    "sg:province":"NSW",
    "wof:name":"Cafe Revive",
    "wof:placetype":"venue"
},
  "geometry": {"coordinates":[151.20472717300001,-33.8655471802],"type":"Point"}
}