{
  "type": "Feature",
  "properties": {
    "addr:full":"10 Nestor Drv Meadowbrook QLD 4131",
    "addr:housenumber":"10",
    "addr:postcode":"4131",
    "addr:street":"Nestor Drv",
    "iso:country":"AU",
    "sg:address":"10 Nestor Drv",
    "sg:city":"Meadowbrook",
    "sg:classifiers":[
        {
            "category":"Building & Trades",
            "subcategory":"Construction",
            "type":"Services"
        }
    ],
    "sg:phone":"+61 7 3200 9299",
    "sg:postcode":"4131",
    "sg:province":"QLD",
    "sg:tags":[
        "road",
        "contractor"
    ],
    "wof:name":"Frostdale Pty Ltd",
    "wof:placetype":"venue"
},
  "geometry": {"coordinates":[153.13702392600001,-27.6684627533],"type":"Point"}
}