{
  "type": "Feature",
  "properties": {
    "iso:country":"AU",
    "sg:address":"ShpS8/ 59 Darlington Drv",
    "sg:city":"Banora Point",
    "sg:classifiers":[
        {
            "category":"Food & Beverages",
            "subcategory":"Bakery",
            "type":"Retail Goods"
        }
    ],
    "sg:phone":"+61 7 5524 8188",
    "sg:postcode":"2486",
    "sg:province":"NSW",
    "sg:tags":[
        "baker"
    ],
    "wof:name":"Banora Bakery",
    "wof:placetype":"venue"
},
  "geometry": {"coordinates":[153.54124450699999,-28.2140808105],"type":"Point"}
}