{
  "type": "Feature",
  "properties": {
    "addr:full":"861a Waverley Rd Glen Waverley VIC 3150",
    "addr:housenumber":"861a",
    "addr:postcode":"3150",
    "addr:street":"Waverley Rd",
    "iso:country":"AU",
    "sg:address":"861a Waverley Rd",
    "sg:city":"Glen Waverley",
    "sg:classifiers":[
        {
            "category":"Health Services",
            "subcategory":"Dentist",
            "type":"Services"
        }
    ],
    "sg:phone":"+61 3 9560 2702",
    "sg:postcode":"3150",
    "sg:province":"VIC",
    "wof:name":"Kave Barry Dr",
    "wof:placetype":"venue"
},
  "geometry": {"coordinates":[145.19151306099999,-37.8919868469],"type":"Point"}
}