{
  "type": "Feature",
  "properties": {
    "addr:full":"2 Saffron St Elanora QLD 4221",
    "addr:housenumber":"2",
    "addr:postcode":"4221",
    "addr:street":"Saffron St",
    "iso:country":"AU",
    "sg:address":"2 Saffron St",
    "sg:city":"Elanora",
    "sg:classifiers":[
        {
            "category":"Real Estate",
            "subcategory":"Real Estate Agent",
            "type":"Services"
        }
    ],
    "sg:phone":"+61 7 5522 4588",
    "sg:postcode":"4221",
    "sg:province":"QLD",
    "wof:name":"Ray White Elanora",
    "wof:placetype":"venue"
},
  "geometry": {"coordinates":[153.446243286,-28.1300086975],"type":"Point"}
}