{
  "type": "Feature",
  "properties": {
    "iso:country":"AU",
    "sg:address":"89A Gilbert St",
    "sg:city":"Latrobe",
    "sg:classifiers":[
        {
            "category":"Utilities",
            "subcategory":"Recycling",
            "type":"Services"
        }
    ],
    "sg:phone":"+61 3 6426 2111",
    "sg:postcode":"7307",
    "sg:province":"TAS",
    "wof:name":"Gleecraft Recycling Centre",
    "wof:placetype":"venue"
},
  "geometry": {"coordinates":[146.40978999999999,-41.235428],"type":"Point"}
}