{
  "type": "Feature",
  "properties": {
    "addr:full":"1 Blossom St Mitcham VIC 3132",
    "addr:housenumber":"1",
    "addr:postcode":"3132",
    "addr:street":"Blossom St",
    "iso:country":"AU",
    "sg:address":"1 Blossom St",
    "sg:city":"Mitcham",
    "sg:classifiers":[
        {
            "category":"Health Services",
            "subcategory":"Health Practitioner",
            "type":"Services"
        }
    ],
    "sg:phone":"+61 3 8802 4420",
    "sg:postcode":"3132",
    "sg:province":"VIC",
    "sg:tags":[
        "hypnotherapy"
    ],
    "wof:name":"Alpha Hypnotics",
    "wof:placetype":"venue"
},
  "geometry": {"coordinates":[145.21009826700001,-37.8235244751],"type":"Point"}
}