{
  "type": "Feature",
  "properties": {
    "addr:full":"24 Gwynne St Richmond VIC 3121",
    "addr:housenumber":"24",
    "addr:postcode":"3121",
    "addr:street":"Gwynne St",
    "iso:country":"AU",
    "sg:address":"24 Gwynne St",
    "sg:city":"Richmond",
    "sg:classifiers":[
        {
            "category":"Arena",
            "subcategory":"Sports Club",
            "type":"Entertainment"
        }
    ],
    "sg:phone":"+61 3 9850 3972",
    "sg:postcode":"3121",
    "sg:province":"VIC",
    "sg:tags":[
        "defence",
        "supply",
        "self",
        "instruction",
        "martial art"
    ],
    "wof:name":"Riai Aikido",
    "wof:placetype":"venue"
},
  "geometry": {"coordinates":[144.99313354500001,-37.8275604248],"type":"Point"}
}