{
  "type": "Feature",
  "properties": {
    "iso:country":"AU",
    "sg:address":"80 Main Rd",
    "sg:city":"McLaren Vale",
    "sg:classifiers":[
        {
            "category":"Retail",
            "subcategory":"Driving School",
            "type":"Services"
        }
    ],
    "sg:phone":"+61 8 8323 7709",
    "sg:postcode":"5171",
    "sg:province":"SA",
    "wof:name":"Avril Dargie Driver Training & Testing",
    "wof:placetype":"venue"
},
  "geometry": {"coordinates":[138.536911011,-35.214805603],"type":"Point"}
}