{
  "type": "Feature",
  "properties": {
    "iso:country":"AU",
    "sg:address":"Lvl 1, 63b Market St",
    "sg:city":"Wollongong",
    "sg:classifiers":[
        {
            "category":"Organizations",
            "subcategory":"Community Association",
            "type":"Services"
        }
    ],
    "sg:phone":"+61 2 4221 2000",
    "sg:postcode":"2500",
    "sg:province":"NSW",
    "sg:tags":[
        "organisation",
        "family",
        "welfare"
    ],
    "wof:name":"Relationships Australia Family Law Mediation",
    "wof:placetype":"venue"
},
  "geometry": {"coordinates":[150.894226,-34.423626],"type":"Point"}
}