{
  "type": "Feature",
  "properties": {
    "addr:full":"PO Box 7179 Alexandria NSW 2015",
    "addr:postcode":"2015",
    "iso:country":"AU",
    "sg:address":"PO Box 7179",
    "sg:city":"Alexandria",
    "sg:classifiers":[
        {
            "category":"Professional",
            "subcategory":"Detective & Security Services",
            "type":"Services"
        }
    ],
    "sg:phone":"+61 414 402 060",
    "sg:postcode":"2015",
    "sg:province":"NSW",
    "sg:tags":[
        "consultant",
        "system"
    ],
    "wof:name":"ICU Digital CCTV & Security",
    "wof:placetype":"venue"
},
  "geometry": {"coordinates":[151.19627380399999,-33.9135818481],"type":"Point"}
}