{
  "type": "Feature",
  "properties": {
    "iso:country":"AU",
    "sg:address":"3/ 10 Tandem Ave",
    "sg:city":"Warana",
    "sg:classifiers":[
        {
            "category":"Building & Trades",
            "subcategory":"Plumbing",
            "type":"Services"
        }
    ],
    "sg:phone":"+61 7 5493 9068",
    "sg:postcode":"4575",
    "sg:province":"QLD",
    "sg:tags":[
        "pump",
        "repairer"
    ],
    "wof:name":"Kawana Rewinds",
    "wof:placetype":"venue"
},
  "geometry": {"coordinates":[153.125488,-26.728136],"type":"Point"}
}