{
  "type": "Feature",
  "properties": {
    "iso:country":"AU",
    "sg:address":"14 Panton Rd",
    "sg:city":"Mandurah",
    "sg:classifiers":[
        {
            "category":"Autos & Motor Vehicles",
            "subcategory":"Automobile Sales",
            "type":"Retail Goods"
        }
    ],
    "sg:phone":"+61 8 9582 6200",
    "sg:postcode":"6210",
    "sg:province":"WA",
    "sg:tags":[
        "car",
        "new"
    ],
    "wof:name":"Peel Honda Mandurah",
    "wof:placetype":"venue"
},
  "geometry": {"coordinates":[115.744911,-32.513054],"type":"Point"}
}