{
  "type": "Feature",
  "properties": {
    "addr:full":"4 Wingate Rd McGraths Hill NSW 2756",
    "addr:housenumber":"4",
    "addr:postcode":"2756",
    "addr:street":"Wingate Rd",
    "iso:country":"AU",
    "sg:address":"4 Wingate Rd",
    "sg:city":"McGraths Hill",
    "sg:classifiers":[
        {
            "category":"Retail",
            "subcategory":"Car Wash",
            "type":"Services"
        }
    ],
    "sg:phone":"+61 2 4577 7455",
    "sg:postcode":"2756",
    "sg:province":"NSW",
    "sg:tags":[
        "truck",
        "cleaning"
    ],
    "wof:name":"Maxi Shine",
    "wof:placetype":"venue"
},
  "geometry": {"coordinates":[150.835845947,-33.6222877502],"type":"Point"}
}