{
  "type": "Feature",
  "properties": {
    "addr:full":"3-17 Snook St Clontarf QLD 4019",
    "addr:housenumber":"3-17",
    "addr:postcode":"4019",
    "addr:street":"Snook St",
    "iso:country":"AU",
    "sg:address":"3-17 Snook St",
    "sg:city":"Clontarf",
    "sg:phone":"+61 500 877 866",
    "sg:postcode":"4019",
    "sg:province":"QLD",
    "wof:name":"AA Professional Filter Cleaning",
    "wof:placetype":"venue"
},
  "geometry": {"coordinates":[153.082595825,-27.2463092804],"type":"Point"}
}