{
  "type": "Feature",
  "properties": {
    "addr:full":"73 Murphy St Blaxland NSW 2774",
    "addr:housenumber":"73",
    "addr:postcode":"2774",
    "addr:street":"Murphy St",
    "iso:country":"AU",
    "sg:address":"73 Murphy St",
    "sg:city":"Blaxland",
    "sg:classifiers":[
        {
            "category":"Retail",
            "subcategory":"Auto Repair",
            "type":"Services"
        }
    ],
    "sg:phone":"+61 2 4739 4508",
    "sg:postcode":"2774",
    "sg:province":"NSW",
    "sg:tags":[
        "repairer",
        "motor",
        "engineer"
    ],
    "wof:name":"I.G. Auto Repairs",
    "wof:placetype":"venue"
},
  "geometry": {"coordinates":[150.612884522,-33.7575645447],"type":"Point"}
}