{
  "type": "Feature",
  "properties": {
    "iso:country":"AU",
    "sg:address":"Cnr Mill & Hutchinson Sts",
    "sg:city":"Tinonee",
    "sg:classifiers":[
        {
            "category":"Cinema",
            "subcategory":"Movie Theater",
            "type":"Entertainment"
        }
    ],
    "sg:phone":"+61 2 6553 1428",
    "sg:postcode":"2430",
    "sg:province":"NSW",
    "wof:name":"The Terrace Cinema",
    "wof:placetype":"venue"
},
  "geometry": {"coordinates":[152.4142,-31.932096],"type":"Point"}
}