{
  "type": "Feature",
  "properties": {
    "addr:full":"21 Cameron Pl St Helens Park NSW 2560",
    "addr:housenumber":"21",
    "addr:postcode":"2560",
    "addr:street":"Cameron Pl",
    "iso:country":"AU",
    "sg:address":"21 Cameron Pl St",
    "sg:city":"Helens Park",
    "sg:classifiers":[
        {
            "category":"Personal",
            "subcategory":"Nail Salon",
            "type":"Services"
        }
    ],
    "sg:phone":"+61 2 4621 1177",
    "sg:postcode":"2560",
    "sg:province":"NSW",
    "sg:tags":[
        "artificial"
    ],
    "wof:name":"Gabis Classique Nails",
    "wof:placetype":"venue"
},
  "geometry": {"coordinates":[150.80450439399999,-34.1113967896],"type":"Point"}
}