{
  "type": "Feature",
  "properties": {
    "addr:full":"22 Boronia Rd Lake Munmorah NSW 2259",
    "addr:housenumber":"22",
    "addr:postcode":"2259",
    "addr:street":"Boronia Rd",
    "iso:country":"AU",
    "sg:address":"22 Boronia Rd",
    "sg:city":"Lake Munmorah",
    "sg:classifiers":[
        {
            "category":"Utilities",
            "subcategory":"Electric",
            "type":"Services"
        }
    ],
    "sg:phone":"+61 405 195 311",
    "sg:postcode":"2259",
    "sg:province":"NSW",
    "sg:tags":[
        "electrical",
        "contractor"
    ],
    "wof:name":"Coastal Reception",
    "wof:placetype":"venue"
},
  "geometry": {"coordinates":[151.56817626899999,-33.192855835],"type":"Point"}
}