{
  "type": "Feature",
  "properties": {
    "iso:country":"AU",
    "sg:address":"78 Dudley St",
    "sg:city":"Gorokan",
    "sg:classifiers":[
        {
            "category":"Food & Beverages",
            "subcategory":"Groceries & Convenience Stores",
            "type":"Retail Goods"
        }
    ],
    "sg:phone":"+61 2 4392 5668",
    "sg:postcode":"2263",
    "sg:province":"NSW",
    "wof:name":"Hilltop General Store",
    "wof:placetype":"venue"
},
  "geometry": {"coordinates":[151.50697299999999,-33.255978],"type":"Point"}
}