{
  "type": "Feature",
  "properties": {
    "iso:country":"AU",
    "sg:address":"465 Maroondah Hwy",
    "sg:city":"Lilydale",
    "sg:classifiers":[
        {
            "category":"Wholesale",
            "subcategory":"Machinery & Supplies",
            "type":"Manufacturing & Wholesale Goods"
        }
    ],
    "sg:phone":"+61 3 9739 5006",
    "sg:postcode":"3140",
    "sg:province":"VIC",
    "sg:tags":[
        "agricultural"
    ],
    "wof:name":"Agpower",
    "wof:placetype":"venue"
},
  "geometry": {"coordinates":[145.36425781200001,-37.7535858154],"type":"Point"}
}