{
  "type": "Feature",
  "properties": {
    "addr:full":"Ground Flr, East Point Plaza, 233 Adelaide Tce Perth WA 6000",
    "addr:housenumber":"233",
    "addr:postcode":"6000",
    "addr:street":"Adelaide Tce",
    "iso:country":"AU",
    "sg:address":"Ground Flr, East Point Plaza, 233",
    "sg:city":"Adelaide Tce Perth",
    "sg:classifiers":[
        {
            "category":"Real Estate",
            "subcategory":"Real Estate Agent",
            "type":"Services"
        }
    ],
    "sg:phone":"+61 8 9223 7400",
    "sg:postcode":"6000",
    "sg:province":"WA",
    "wof:name":"Pro Property",
    "wof:placetype":"venue"
},
  "geometry": {"coordinates":[115.867431641,-31.9584407806],"type":"Point"}
}