{
  "type": "Feature",
  "properties": {
    "addr:full":"High St Macarthur VIC 3286",
    "addr:postcode":"3286",
    "addr:street":"High St",
    "iso:country":"AU",
    "sg:address":"High St",
    "sg:city":"Macarthur",
    "sg:classifiers":[
        {
            "category":"Organizations",
            "subcategory":"Community Association",
            "type":"Services"
        }
    ],
    "sg:phone":"+61 3 5576 1128",
    "sg:postcode":"3286",
    "sg:province":"VIC",
    "sg:tags":[
        "club",
        "senior",
        "citizen"
    ],
    "wof:name":"Macarthur Senior Citizens Centre",
    "wof:placetype":"venue"
},
  "geometry": {"coordinates":[142.000442505,-38.0333786011],"type":"Point"}
}