{
  "type": "Feature",
  "properties": {
    "addr:full":"3a Walker St Bundaberg QLD 4670",
    "addr:housenumber":"3a",
    "addr:postcode":"4670",
    "addr:street":"Walker St",
    "iso:country":"AU",
    "sg:address":"3a Walker St",
    "sg:city":"Bundaberg",
    "sg:classifiers":[
        {
            "category":"Autos & Motor Vehicles",
            "subcategory":"Auto Supplies",
            "type":"Retail Goods"
        }
    ],
    "sg:phone":"+61 7 4154 1577",
    "sg:postcode":"4670",
    "sg:province":"QLD",
    "sg:tags":[
        "paint",
        "automotive"
    ],
    "wof:name":"Bennett's Paint Centre Pty Ltd",
    "wof:placetype":"venue"
},
  "geometry": {"coordinates":[152.36250305199999,-24.8763027191],"type":"Point"}
}