{
  "type": "Feature",
  "properties": {
    "addr:full":"PO Box 410 Bribie Island QLD 4507",
    "addr:postcode":"4507",
    "iso:country":"AU",
    "sg:address":"PO Box 410",
    "sg:city":"Bribie Island",
    "sg:classifiers":[
        {
            "category":"Mining & Drilling",
            "type":"Manufacturing & Wholesale Goods"
        }
    ],
    "sg:phone":"+61 415 650 466",
    "sg:postcode":"4507",
    "sg:province":"QLD",
    "sg:tags":[
        "concrete",
        "breaking",
        "grinding",
        "sawing"
    ],
    "wof:name":"Powercut Concrete Cutting & Core Driling",
    "wof:placetype":"venue"
},
  "geometry": {"coordinates":[153.14137268100001,-26.9570903778],"type":"Point"}
}