{
  "type": "Feature",
  "properties": {
    "iso:country":"AU",
    "sg:address":"454 Centre Rd",
    "sg:city":"Bentleigh",
    "sg:classifiers":[
        {
            "category":"Manufacturing",
            "subcategory":"Jewelry",
            "type":"Manufacturing & Wholesale Goods"
        }
    ],
    "sg:phone":"+61 3 9557 9555",
    "sg:postcode":"3204",
    "sg:province":"VIC",
    "sg:tags":[
        "mfrg",
        "jeweller"
    ],
    "sg:website":"http://www.myjeweller.com.au",
    "wof:name":"Bentleigh Jewellers",
    "wof:placetype":"venue"
},
  "geometry": {"coordinates":[145.039093,-37.918591],"type":"Point"}
}