{
  "type": "Feature",
  "properties": {
    "addr:full":"6 Techno Park Drv Williamstown VIC 3016",
    "addr:housenumber":"6",
    "addr:postcode":"3016",
    "addr:street":"Techno Park Drv",
    "iso:country":"AU",
    "sg:address":"6 Techno Park Drv",
    "sg:city":"Williamstown",
    "sg:classifiers":[
        {
            "category":"Banks & Credit Unions",
            "subcategory":"Investment Brokerage",
            "type":"Services"
        }
    ],
    "sg:phone":"+61 419 872 569",
    "sg:postcode":"3016",
    "sg:province":"VIC",
    "sg:tags":[
        "heat",
        "metal",
        "treatment"
    ],
    "wof:name":"Cooperheat Of Australia Pty Ltd",
    "wof:placetype":"venue"
},
  "geometry": {"coordinates":[144.85952758799999,-37.855556488],"type":"Point"}
}