{
  "type": "Feature",
  "properties": {
    "addr:full":"110 Aberdeen St Northbridge WA 6003",
    "addr:housenumber":"110",
    "addr:postcode":"6003",
    "addr:street":"Aberdeen St",
    "iso:country":"AU",
    "sg:address":"110 Aberdeen St",
    "sg:city":"Northbridge",
    "sg:classifiers":[
        {
            "category":"Travel",
            "subcategory":"Hotels & Motels",
            "type":"Entertainment"
        }
    ],
    "sg:phone":"+61 8 9227 5244",
    "sg:postcode":"6003",
    "sg:province":"WA",
    "sg:tags":[
        "pub"
    ],
    "wof:name":"Eurobar",
    "wof:placetype":"venue"
},
  "geometry": {"coordinates":[115.85777282700001,-31.9457778931],"type":"Point"}
}