{
  "type": "Feature",
  "properties": {
    "iso:country":"AU",
    "sg:address":"Albert St",
    "sg:city":"Brisbane City",
    "sg:classifiers":[
        {
            "category":"Health Services",
            "subcategory":"Optometrist",
            "type":"Services"
        }
    ],
    "sg:phone":"+61 7 3211 2200",
    "sg:postcode":"4000",
    "sg:province":"QLD",
    "sg:website":"http://www.opticalwarehouse.com.au",
    "wof:name":"Optical Warehouse",
    "wof:placetype":"venue"
},
  "geometry": {"coordinates":[153.021209717,-27.4654808044],"type":"Point"}
}