{
  "type": "Feature",
  "properties": {
    "addr:full":"1 Buffalo Crs Goulburn NSW 2580",
    "addr:housenumber":"1",
    "addr:postcode":"2580",
    "addr:street":"Buffalo Crs",
    "iso:country":"AU",
    "sg:address":"1 Buffalo Crs",
    "sg:city":"Goulburn",
    "sg:classifiers":[
        {
            "category":"Utilities",
            "subcategory":"Refuse",
            "type":"Services"
        }
    ],
    "sg:phone":"+61 2 4821 9734",
    "sg:postcode":"2580",
    "sg:province":"NSW",
    "sg:tags":[
        "remover",
        "rubbish"
    ],
    "wof:name":"Town & Country Waste Services",
    "wof:placetype":"venue"
},
  "geometry": {"coordinates":[149.716262817,-34.7571792603],"type":"Point"}
}