{
  "type": "Feature",
  "properties": {
    "addr:full":"1 Strathcona St West Perth WA 6005",
    "addr:housenumber":"1",
    "addr:postcode":"6005",
    "addr:street":"Strathcona St",
    "iso:country":"AU",
    "sg:address":"1 Strathcona St",
    "sg:city":"West Perth",
    "sg:classifiers":[
        {
            "category":"Education",
            "subcategory":"Kindergarten",
            "type":"Public Place"
        }
    ],
    "sg:phone":"+61 8 9328 6029",
    "sg:postcode":"6005",
    "sg:province":"WA",
    "sg:tags":[
        "pre-schools"
    ],
    "wof:name":"Farnham House Early Education Centre",
    "wof:placetype":"venue"
},
  "geometry": {"coordinates":[115.849441528,-31.9402503967],"type":"Point"}
}