{
  "type": "Feature",
  "properties": {
    "addr:full":"521 Wilson St Albury NSW 2640",
    "addr:housenumber":"521",
    "addr:postcode":"2640",
    "addr:street":"Wilson St",
    "iso:country":"AU",
    "sg:address":"521 Wilson St",
    "sg:city":"Albury",
    "sg:classifiers":[
        {
            "category":"Professional",
            "subcategory":"Accounting & Tax Preparation",
            "type":"Services"
        }
    ],
    "sg:phone":"+61 2 6021 0277",
    "sg:postcode":"2640",
    "sg:province":"NSW",
    "sg:tags":[
        "accountant",
        "auditor"
    ],
    "wof:name":"Judd Carol & Co",
    "wof:placetype":"venue"
},
  "geometry": {"coordinates":[146.91815185600001,-36.0768661499],"type":"Point"}
}