{
  "type": "Feature",
  "properties": {
    "addr:full":"29 Canara St Cranbrook QLD 4814",
    "addr:housenumber":"29",
    "addr:postcode":"4814",
    "addr:street":"Canara St",
    "iso:country":"AU",
    "sg:address":"29 Canara St",
    "sg:city":"Cranbrook",
    "sg:classifiers":[
        {
            "category":"Shopping",
            "subcategory":"Crafts & Fabrics",
            "type":"Retail Goods"
        }
    ],
    "sg:phone":"+61 7 4775 4328",
    "sg:postcode":"4814",
    "sg:province":"QLD",
    "sg:tags":[
        "supply"
    ],
    "wof:name":"Genesis Creations",
    "wof:placetype":"venue"
},
  "geometry": {"coordinates":[146.75105300000001,-19.301907],"type":"Point"}
}