{
  "type": "Feature",
  "properties": {
    "addr:full":"23- 25 George St Jamestown SA 5491",
    "addr:housenumber":"25",
    "addr:postcode":"5491",
    "addr:street":"George St",
    "iso:country":"AU",
    "sg:address":"23- 25 George St",
    "sg:city":"Jamestown",
    "sg:classifiers":[
        {
            "category":"Retail",
            "subcategory":"Auto Repair",
            "type":"Services"
        }
    ],
    "sg:phone":"+61 8 8664 1675",
    "sg:postcode":"5491",
    "sg:province":"SA",
    "sg:tags":[
        "beater",
        "painter",
        "panel"
    ],
    "wof:name":"Jamestown Crash Repairs",
    "wof:placetype":"venue"
},
  "geometry": {"coordinates":[138.60357665999999,-33.1965370178],"type":"Point"}
}