{
  "type": "Feature",
  "properties": {
    "addr:full":"Suite 6, Level 11, 22 Arthur St North Sydney NSW 2060",
    "addr:housenumber":"22",
    "addr:postcode":"2060",
    "addr:street":"Arthur St",
    "iso:country":"AU",
    "sg:address":"Suite 6, Level 11, 22 Arthur St",
    "sg:city":"North Sydney",
    "sg:classifiers":[
        {
            "category":"Health Services",
            "subcategory":"Doctor",
            "type":"Services"
        }
    ],
    "sg:phone":"+61 1300 653 706",
    "sg:postcode":"2060",
    "sg:province":"NSW",
    "sg:tags":[
        "nurse",
        "nursing"
    ],
    "sg:website":"http://www.northshorenurses.com.au",
    "wof:name":"Australian Nursing Network",
    "wof:placetype":"venue"
},
  "geometry": {"coordinates":[151.20956420900001,-33.8406486511],"type":"Point"}
}