{
  "type": "Feature",
  "properties": {
    "addr:full":"Lot 3 , Wilwendan Cl Wamberal NSW 2260",
    "addr:postcode":"2260",
    "addr:street":"Cl Wamberal",
    "iso:country":"AU",
    "sg:address":"Lot 3",
    "sg:city":", Wilwendan Cl Wamberal",
    "sg:classifiers":[
        {
            "category":"Building & Trades",
            "subcategory":"Construction",
            "type":"Services"
        }
    ],
    "sg:phone":"+61 414 406 004",
    "sg:postcode":"2260",
    "sg:province":"NSW",
    "sg:tags":[
        "earth",
        "excavating",
        "moving",
        "contractor"
    ],
    "wof:name":"D & K Goodman Pty Ltd",
    "wof:placetype":"venue"
},
  "geometry": {"coordinates":[151.44314600000001,-33.418209],"type":"Point"}
}