{
  "type": "Feature",
  "properties": {
    "addr:full":"13- 19 Western Ave Tullamarine VIC 3043",
    "addr:housenumber":"19",
    "addr:postcode":"3043",
    "addr:street":"Western Ave",
    "iso:country":"AU",
    "sg:address":"13- 19 Western Ave",
    "sg:city":"Tullamarine",
    "sg:classifiers":[
        {
            "category":"Professional",
            "subcategory":"Employment Agencies",
            "type":"Services"
        }
    ],
    "sg:phone":"+61 3 9339 3900",
    "sg:postcode":"3043",
    "sg:province":"VIC",
    "sg:tags":[
        "broker",
        "custom"
    ],
    "wof:name":"Kuehne & Nagel (Australia) Pty Ltd",
    "wof:placetype":"venue"
},
  "geometry": {"coordinates":[144.88081359899999,-37.6842308044],"type":"Point"}
}