{
  "type": "Feature",
  "properties": {
    "iso:country":"AU",
    "sg:address":"19/29- 31 Scrivener St",
    "sg:city":"Warwick Farm",
    "sg:classifiers":[
        {
            "category":"Home & Garden",
            "subcategory":"Building Materials",
            "type":"Retail Goods"
        }
    ],
    "sg:phone":"+61 2 9824 0131",
    "sg:postcode":"2170",
    "sg:province":"NSW",
    "sg:tags":[
        "lawn",
        "cutting",
        "maintenance"
    ],
    "wof:name":"Enterpraise",
    "wof:placetype":"venue"
},
  "geometry": {"coordinates":[150.93760681099999,-33.9189414978],"type":"Point"}
}