{
  "type": "Feature",
  "properties": {
    "addr:full":"53 Lucas Ave Moorebank NSW 2170",
    "addr:housenumber":"53",
    "addr:postcode":"2170",
    "addr:street":"Lucas Ave",
    "iso:country":"AU",
    "sg:address":"53 Lucas Ave",
    "sg:city":"Moorebank",
    "sg:classifiers":[
        {
            "category":"Farming",
            "subcategory":"Fish & Marine Products",
            "type":"Manufacturing & Wholesale Goods"
        }
    ],
    "sg:phone":"+61 2 9602 0996",
    "sg:postcode":"2170",
    "sg:province":"NSW",
    "sg:tags":[
        "lead",
        "supply"
    ],
    "wof:name":"Moorebank Plumbing Service",
    "wof:placetype":"venue"
},
  "geometry": {"coordinates":[150.953491211,-33.9309463501],"type":"Point"}
}