{
  "type": "Feature",
  "properties": {
    "addr:full":"330 Burwood Rd Belmore NSW 2192",
    "addr:housenumber":"330",
    "addr:postcode":"2192",
    "addr:street":"Burwood Rd",
    "iso:country":"AU",
    "sg:address":"330 Burwood Rd",
    "sg:city":"Belmore",
    "sg:classifiers":[
        {
            "category":"Personal",
            "subcategory":"Beauty Salon",
            "type":"Services"
        }
    ],
    "sg:phone":"+61 2 9758 2260",
    "sg:postcode":"2192",
    "sg:province":"NSW",
    "wof:name":"California Nails Beauty Massage Centre",
    "wof:placetype":"venue"
},
  "geometry": {"coordinates":[151.08763099999999,-33.916519],"type":"Point"}
}