{
  "type": "Feature",
  "properties": {
    "addr:full":"9 Fink St Preston VIC 3072",
    "addr:housenumber":"9",
    "addr:postcode":"3072",
    "addr:street":"Fink St",
    "iso:country":"AU",
    "sg:address":"9 Fink St",
    "sg:city":"Preston",
    "sg:classifiers":[
        {
            "category":"Manufacturing",
            "subcategory":"Wood Products",
            "type":"Manufacturing & Wholesale Goods"
        }
    ],
    "sg:phone":"+61 3 9416 8499",
    "sg:postcode":"3072",
    "sg:province":"VIC",
    "sg:tags":[
        "pallet",
        "platform"
    ],
    "wof:name":"B J Turner & Co.",
    "wof:placetype":"venue"
},
  "geometry": {"coordinates":[145.02656555199999,-37.7529373169],"type":"Point"}
}