{
  "type": "Feature",
  "properties": {
    "addr:full":"6 Dean St Prospect SA 5082",
    "addr:housenumber":"6",
    "addr:postcode":"5082",
    "addr:street":"Dean St",
    "iso:country":"AU",
    "sg:address":"6 Dean St",
    "sg:city":"Prospect",
    "sg:classifiers":[
        {
            "category":"Social Services",
            "subcategory":"Retirement Home",
            "type":"Services"
        }
    ],
    "sg:phone":"+61 8 8269 4114",
    "sg:postcode":"5082",
    "sg:province":"SA",
    "sg:tags":[
        "accommodation",
        "special"
    ],
    "wof:name":"Prospect Residential Care Service",
    "wof:placetype":"venue"
},
  "geometry": {"coordinates":[138.601074219,-34.8815383911],"type":"Point"}
}