{
  "type": "Feature",
  "properties": {
    "addr:full":"Kiosk 33/ 111 West Lake Blv West Lakes SA 5021",
    "addr:housenumber":"111",
    "addr:postcode":"5021",
    "addr:street":"West Lake Blv",
    "iso:country":"AU",
    "sg:address":"Kiosk 33/ 111",
    "sg:city":"West Lake Blv West Lakes",
    "sg:classifiers":[
        {
            "category":"Fast Food",
            "type":"Food & Drink"
        }
    ],
    "sg:phone":"+61 8 8355 1565",
    "sg:postcode":"5021",
    "sg:province":"SA",
    "sg:tags":[
        "away",
        "take"
    ],
    "wof:name":"Sushi Suki",
    "wof:placetype":"venue"
},
  "geometry": {"coordinates":[138.488006592,-34.8724136353],"type":"Point"}
}