{
  "type": "Feature",
  "properties": {
    "addr:full":"Lvl 2/ 11 Help St Chatswood NSW 2067",
    "addr:housenumber":"/ 11",
    "addr:postcode":"2067",
    "addr:street":"Help St",
    "iso:country":"AU",
    "sg:address":"Lvl 2/ 11 Help St",
    "sg:city":"Chatswood",
    "sg:classifiers":[
        {
            "category":"Shopping",
            "subcategory":"Computers & Home Electronics",
            "type":"Retail Goods"
        }
    ],
    "sg:phone":"+61 2 9419 3200",
    "sg:postcode":"2067",
    "sg:province":"NSW",
    "sg:tags":[
        "equipment",
        "supply"
    ],
    "wof:name":"Tier-3 Pty Ltd",
    "wof:placetype":"venue"
},
  "geometry": {"coordinates":[151.17906189000001,-33.7957992554],"type":"Point"}
}