{
  "type": "Feature",
  "properties": {
    "addr:full":"79b High St Willoughby NSW 2068",
    "addr:housenumber":"79b",
    "addr:postcode":"2068",
    "addr:street":"High St",
    "iso:country":"AU",
    "sg:address":"79b High St",
    "sg:city":"Willoughby",
    "sg:classifiers":[
        {
            "category":"Professional",
            "subcategory":"Computer Services",
            "type":"Services"
        }
    ],
    "sg:phone":"+61 2 9967 0006",
    "sg:postcode":"2068",
    "sg:province":"NSW",
    "sg:tags":[
        "training"
    ],
    "wof:name":"Wall To Wall Computer Services",
    "wof:placetype":"venue"
},
  "geometry": {"coordinates":[151.203948975,-33.8032150269],"type":"Point"}
}