{
  "type": "Feature",
  "properties": {
    "iso:country":"AU",
    "sg:address":"2 Falie St",
    "sg:city":"Port Broughton",
    "sg:classifiers":[
        {
            "category":"Home & Garden",
            "subcategory":"Building Materials",
            "type":"Retail Goods"
        }
    ],
    "sg:phone":"+61 8 8635 2088",
    "sg:postcode":"5522",
    "sg:province":"SA",
    "sg:tags":[
        "lawn",
        "cutting",
        "maintenance"
    ],
    "wof:name":"Port Broughton Lawn Mowing Service",
    "wof:placetype":"venue"
},
  "geometry": {"coordinates":[137.92523193400001,-33.4048156738],"type":"Point"}
}