{
  "type": "Feature",
  "properties": {
    "iso:country":"AU",
    "sg:address":"Factory 2 226 Headland Rd",
    "sg:city":"Dee Why",
    "sg:classifiers":[
        {
            "category":"Home & Garden",
            "subcategory":"Building Materials",
            "type":"Retail Goods"
        }
    ],
    "sg:phone":"+61 2 9905 4264",
    "sg:postcode":"2099",
    "sg:province":"NSW",
    "sg:tags":[
        "plaster",
        "plasterboard",
        "supply"
    ],
    "wof:name":"Warringah Fibrous Plaster",
    "wof:placetype":"venue"
},
  "geometry": {"coordinates":[151.281814575,-33.7600288391],"type":"Point"}
}