{
  "type": "Feature",
  "properties": {
    "addr:full":"40 Allen St Charters Towers QLD 4820",
    "addr:housenumber":"40",
    "addr:postcode":"4820",
    "addr:street":"Allen St",
    "iso:country":"AU",
    "sg:address":"40 Allen St",
    "sg:city":"Charters Towers",
    "sg:classifiers":[
        {
            "category":"Banks & Credit Unions",
            "subcategory":"Bureau De Change",
            "type":"Services"
        }
    ],
    "sg:phone":"+61 427 828 848",
    "sg:postcode":"4820",
    "sg:province":"QLD",
    "sg:tags":[
        "escort",
        "transport",
        "pilot"
    ],
    "wof:name":"A.B.H.N.Q.",
    "wof:placetype":"venue"
},
  "geometry": {"coordinates":[146.25938400000001,-20.06381],"type":"Point"}
}