{
  "type": "Feature",
  "properties": {
    "iso:country":"AU",
    "sg:address":"95 Hackney Rd",
    "sg:city":"Hackney",
    "sg:classifiers":[
        {
            "category":"Retail",
            "subcategory":"Event Space",
            "type":"Services"
        }
    ],
    "sg:phone":"+61 8 8362 9282",
    "sg:postcode":"5069",
    "sg:province":"SA",
    "sg:tags":[
        "venue",
        "reception",
        "wedding"
    ],
    "wof:name":"Hackney Hotel",
    "wof:placetype":"venue"
},
  "geometry": {"coordinates":[138.61323547399999,-34.9102287292],"type":"Point"}
}