{
  "type": "Feature",
  "properties": {
    "iso:country":"AU",
    "sg:address":"PO Box 9251",
    "sg:city":"South Yarra",
    "sg:classifiers":[
        {
            "category":"Organizations",
            "subcategory":"Professional Association",
            "type":"Services"
        }
    ],
    "sg:phone":"+61 1300 662 658",
    "sg:postcode":"3141",
    "sg:province":"VIC",
    "sg:tags":[
        "web",
        "internet"
    ],
    "wof:name":"Uppershot Web Design",
    "wof:placetype":"venue"
},
  "geometry": {"coordinates":[144.99111938499999,-37.8378791809],"type":"Point"}
}