{
  "type": "Feature",
  "properties": {
    "addr:full":"126 Borilla St Emerald QLD 4720",
    "addr:housenumber":"126",
    "addr:postcode":"4720",
    "addr:street":"Borilla St",
    "iso:country":"AU",
    "sg:address":"126 Borilla St",
    "sg:city":"Emerald",
    "sg:classifiers":[
        {
            "category":"Health Services",
            "subcategory":"Nursing And Care Facility",
            "type":"Services"
        }
    ],
    "sg:phone":"+61 7 4982 1144",
    "sg:postcode":"4720",
    "sg:province":"QLD",
    "sg:tags":[
        "home"
    ],
    "wof:name":"Central Highlands Aged Persons Home",
    "wof:placetype":"venue"
},
  "geometry": {"coordinates":[148.165344,-23.51729],"type":"Point"}
}