{
  "type": "Feature",
  "properties": {
    "addr:full":"1 Barry Crt Wonga Park VIC 3115",
    "addr:housenumber":"1",
    "addr:postcode":"3115",
    "addr:street":"Barry Crt",
    "iso:country":"AU",
    "sg:address":"1 Barry Crt",
    "sg:city":"Wonga Park",
    "sg:classifiers":[
        {
            "category":"Building & Trades",
            "subcategory":"Landscaping Services",
            "type":"Services"
        }
    ],
    "sg:phone":"+61 419 550 135",
    "sg:postcode":"3115",
    "sg:province":"VIC",
    "sg:tags":[
        "designer",
        "landscape",
        "contractor"
    ],
    "wof:name":"Aqua Earth Stone Landscapes",
    "wof:placetype":"venue"
},
  "geometry": {"coordinates":[145.27212524399999,-37.7402763367],"type":"Point"}
}