{
  "type": "Feature",
  "properties": {
    "addr:full":"15 Main St Palmwoods QLD 4555",
    "addr:housenumber":"15",
    "addr:postcode":"4555",
    "addr:street":"Main St",
    "iso:country":"AU",
    "sg:address":"15 Main St",
    "sg:city":"Palmwoods",
    "sg:classifiers":[
        {
            "category":"Structure",
            "subcategory":"Bridge",
            "type":"Public Place"
        }
    ],
    "sg:phone":"+61 7 5445 9811",
    "sg:postcode":"4555",
    "sg:province":"QLD",
    "sg:tags":[
        "chainsaw",
        "brushcutters"
    ],
    "wof:name":"Palmwoods Mower Service",
    "wof:placetype":"venue"
},
  "geometry": {"coordinates":[152.95945739699999,-26.6881484985],"type":"Point"}
}