{
  "type": "Feature",
  "properties": {
    "addr:full":"21- 23 Webb Rd Airport West VIC 3042",
    "addr:housenumber":"23",
    "addr:postcode":"3042",
    "addr:street":"Webb Rd",
    "iso:country":"AU",
    "sg:address":"21- 23 Webb Rd",
    "sg:city":"Airport West",
    "sg:classifiers":[
        {
            "category":"Shopping",
            "subcategory":"Antiques",
            "type":"Retail Goods"
        }
    ],
    "sg:phone":"+61 3 9379 9009",
    "sg:postcode":"3042",
    "sg:province":"VIC",
    "sg:tags":[
        "collectable",
        "memorabilia"
    ],
    "wof:name":"Major Creations",
    "wof:placetype":"venue"
},
  "geometry": {"coordinates":[144.88987731899999,-37.7160987854],"type":"Point"}
}