{
  "type": "Feature",
  "properties": {
    "iso:country":"AU",
    "sg:address":"902 Old Northern Rd",
    "sg:city":"Glenorie",
    "sg:classifiers":[
        {
            "category":"Building & Trades",
            "subcategory":"Construction",
            "type":"Services"
        }
    ],
    "sg:phone":"+61 2 9652 1412",
    "sg:postcode":"2157",
    "sg:province":"NSW",
    "sg:tags":[
        "contractor"
    ],
    "wof:name":"Schwebel L E",
    "wof:placetype":"venue"
},
  "geometry": {"coordinates":[151.01776123100001,-33.6087417603],"type":"Point"}
}