{
  "type": "Feature",
  "properties": {
    "iso:country":"AU",
    "sg:address":"Shp 2, 43- 45 North Steyne",
    "sg:city":"Manly",
    "sg:classifiers":[
        {
            "category":"Fast Food",
            "type":"Food & Drink"
        }
    ],
    "sg:phone":"+61 2 9977 3488",
    "sg:postcode":"2095",
    "sg:province":"NSW",
    "sg:tags":[
        "away",
        "take"
    ],
    "wof:name":"Oporto Manly",
    "wof:placetype":"venue"
},
  "geometry": {"coordinates":[151.287506103,-33.7960777283],"type":"Point"}
}