{
  "type": "Feature",
  "properties": {
    "addr:full":"47 Hill St Clifton Springs VIC 3222",
    "addr:housenumber":"47",
    "addr:postcode":"3222",
    "addr:street":"Hill St",
    "iso:country":"AU",
    "sg:address":"47 Hill St",
    "sg:city":"Clifton Springs",
    "sg:classifiers":[
        {
            "category":"Freight",
            "type":"Transportation"
        }
    ],
    "sg:phone":"+61 408 392 549",
    "sg:postcode":"3222",
    "sg:province":"VIC",
    "sg:tags":[
        "transport",
        "refrigerated"
    ],
    "wof:name":"McDonald's Refrigerated Freighters Geelong",
    "wof:placetype":"venue"
},
  "geometry": {"coordinates":[144.56016500000001,-38.163116],"type":"Point"}
}