{
  "type": "Feature",
  "properties": {
    "addr:full":"Cnr Norton & Macauley Sts Leichhardt NSW 2040",
    "addr:postcode":"2040",
    "addr:street":"Cnr",
    "iso:country":"AU",
    "sg:address":"Cnr Norton & Macauley Sts",
    "sg:city":"Leichhardt",
    "sg:classifiers":[
        {
            "category":"Health Services",
            "subcategory":"Optometrist",
            "type":"Services"
        }
    ],
    "sg:phone":"+61 2 9560 2014",
    "sg:postcode":"2040",
    "sg:province":"NSW",
    "wof:name":"Allens Vision & Hearing Specialists",
    "wof:placetype":"venue"
},
  "geometry": {"coordinates":[151.158905,-33.883659],"type":"Point"}
}