{
  "type": "Feature",
  "properties": {
    "addr:full":"Shop 2 34 Hallett Rd Stonyfell SA 5066",
    "addr:housenumber":"shop;34",
    "addr:postcode":"5066",
    "addr:street":"Hallett Rd",
    "iso:country":"AU",
    "sg:address":"Shop 2 34 Hallett Rd",
    "sg:city":"Stonyfell",
    "sg:classifiers":[
        {
            "category":"Personal",
            "subcategory":"Beauty Salon",
            "type":"Services"
        }
    ],
    "sg:phone":"+61 8 8431 0221",
    "sg:postcode":"5066",
    "sg:province":"SA",
    "wof:name":"Femme Beauty Therapy",
    "wof:placetype":"venue"
},
  "geometry": {"coordinates":[138.66867065400001,-34.9317893982],"type":"Point"}
}