{
  "type": "Feature",
  "properties": {
    "addr:full":"16 Holloway Rd Sandringham VIC 3191",
    "addr:housenumber":"16",
    "addr:postcode":"3191",
    "addr:street":"Holloway Rd",
    "iso:country":"AU",
    "sg:address":"16 Holloway Rd",
    "sg:city":"Sandringham",
    "sg:classifiers":[
        {
            "category":"Health Services",
            "subcategory":"Health Practitioner",
            "type":"Services"
        }
    ],
    "sg:phone":"+61 3 9521 0396",
    "sg:postcode":"3191",
    "sg:province":"VIC",
    "sg:tags":[
        "technique",
        "alexander"
    ],
    "wof:name":"Alexander Technique Australian Society Of Teachers Of The (Austat)",
    "wof:placetype":"venue"
},
  "geometry": {"coordinates":[145.02226257300001,-37.9569740295],"type":"Point"}
}