{
  "type": "Feature",
  "properties": {
    "addr:full":"3030 Bass Hwy Bass VIC 3991",
    "addr:housenumber":"3030",
    "addr:postcode":"3991",
    "addr:street":"Bass Hwy Bass",
    "iso:country":"AU",
    "sg:address":"3030 Bass Hwy",
    "sg:city":"Bass",
    "sg:classifiers":[
        {
            "category":"Real Estate",
            "subcategory":"Real Estate Agent",
            "type":"Services"
        }
    ],
    "sg:phone":"+61 418 591 641",
    "sg:postcode":"3991",
    "sg:province":"VIC",
    "sg:tags":[
        "handyman's",
        "equipment",
        "hire",
        "builders",
        "contractor"
    ],
    "wof:name":"Andy Stuart",
    "wof:placetype":"venue"
},
  "geometry": {"coordinates":[145.46739199999999,-38.480789],"type":"Point"}
}