{
  "type": "Feature",
  "properties": {
    "addr:full":"25 Harrow St Sylvania NSW 2224",
    "addr:housenumber":"25",
    "addr:postcode":"2224",
    "addr:street":"Harrow St",
    "iso:country":"AU",
    "sg:address":"25 Harrow St",
    "sg:city":"Sylvania",
    "sg:classifiers":[
        {
            "category":"Autos & Motor Vehicles",
            "subcategory":"Boat Sales",
            "type":"Retail Goods"
        }
    ],
    "sg:phone":"+61 2 9522 4594",
    "sg:postcode":"2224",
    "sg:province":"NSW",
    "sg:tags":[
        "builder",
        "yacht",
        "repairer"
    ],
    "wof:name":"Caribbean Cruises Sales & Service Pty Ltd",
    "wof:placetype":"venue"
},
  "geometry": {"coordinates":[151.108642578,-34.0066184998],"type":"Point"}
}