{
  "type": "Feature",
  "properties": {
    "addr:full":"21 Hargreaves St Castlemaine VIC 3450",
    "addr:housenumber":"21",
    "addr:postcode":"3450",
    "addr:street":"Hargreaves St",
    "iso:country":"AU",
    "sg:address":"21 Hargreaves St",
    "sg:city":"Castlemaine",
    "sg:classifiers":[
        {
            "category":"Real Estate",
            "subcategory":"Real Estate Agent",
            "type":"Services"
        }
    ],
    "sg:phone":"+61 3 5472 1248",
    "sg:postcode":"3450",
    "sg:province":"VIC",
    "wof:name":"Keogh Real Estate Pty Ltd",
    "wof:placetype":"venue"
},
  "geometry": {"coordinates":[144.21929931599999,-37.0653152466],"type":"Point"}
}