{
  "type": "Feature",
  "properties": {
    "iso:country":"AU",
    "sg:address":"141 - 143 Bay Rd",
    "sg:city":"Toowoon Bay",
    "sg:classifiers":[
        {
            "category":"Restaurant",
            "type":"Food & Drink"
        }
    ],
    "sg:phone":"+61 2 4332 7135",
    "sg:postcode":"2261",
    "sg:province":"NSW",
    "sg:website":"http://www.thebaycafe.com.au",
    "wof:name":"The Bay Cafe Restaurant",
    "wof:placetype":"venue"
},
  "geometry": {"coordinates":[151.496857,-33.357738],"type":"Point"}
}