{
  "type": "Feature",
  "properties": {
    "addr:full":"95 Byrnes Rd Mareeba QLD 4880",
    "addr:housenumber":"95",
    "addr:postcode":"4880",
    "addr:street":"Byrnes Rd",
    "iso:country":"AU",
    "sg:address":"95 Byrnes Rd",
    "sg:city":"Mareeba",
    "sg:classifiers":[
        {
            "category":"Fast Food",
            "type":"Food & Drink"
        }
    ],
    "sg:phone":"+61 7 4092 5444",
    "sg:postcode":"4880",
    "sg:province":"QLD",
    "sg:tags":[
        "away",
        "take"
    ],
    "wof:name":"Eagle Boys Pizza - Mareeba",
    "wof:placetype":"venue"
},
  "geometry": {"coordinates":[145.42013549800001,-16.9853229523],"type":"Point"}
}