{
  "type": "Feature",
  "properties": {
    "addr:full":"13 Birwood St Frankston VIC 3199",
    "addr:housenumber":"13",
    "addr:postcode":"3199",
    "addr:street":"Birwood St",
    "iso:country":"AU",
    "sg:address":"13 Birwood St",
    "sg:city":"Frankston",
    "sg:classifiers":[
        {
            "category":"Professional",
            "subcategory":"Detective & Security Services",
            "type":"Services"
        }
    ],
    "sg:phone":"+61 1300 305 954",
    "sg:postcode":"3199",
    "sg:province":"VIC",
    "sg:tags":[
        "identification",
        "system"
    ],
    "wof:name":"Ausbadge Identification Solutions",
    "wof:placetype":"venue"
},
  "geometry": {"coordinates":[145.105072022,-38.029006958],"type":"Point"}
}