{
  "type": "Feature",
  "properties": {
    "addr:full":"Leonora Pde Waratah West NSW 2298",
    "addr:postcode":"2298",
    "addr:street":"Leonora Pde",
    "iso:country":"AU",
    "sg:address":"Leonora Pde",
    "sg:city":"Waratah West",
    "sg:classifiers":[
        {
            "category":"Education",
            "subcategory":"School",
            "type":"Public Place"
        }
    ],
    "sg:phone":"+61 2 4968 1765",
    "sg:postcode":"2298",
    "sg:province":"NSW",
    "sg:tags":[
        "state",
        "-",
        "nsw"
    ],
    "wof:name":"Waratah West Public School",
    "wof:placetype":"venue"
},
  "geometry": {"coordinates":[151.712356567,-32.8988494873],"type":"Point"}
}