{
  "type": "Feature",
  "properties": {
    "addr:full":"66B Chapel St Windsor VIC 3181",
    "addr:housenumber":"66b",
    "addr:postcode":"3181",
    "addr:street":"Chapel St",
    "iso:country":"AU",
    "sg:address":"66B Chapel St",
    "sg:city":"Windsor",
    "sg:classifiers":[
        {
            "category":"Home & Garden",
            "subcategory":"Garden Supply",
            "type":"Retail Goods"
        }
    ],
    "sg:phone":"+61 3 9510 6832",
    "sg:postcode":"3181",
    "sg:province":"VIC",
    "sg:tags":[
        "equipment",
        "hydroponics"
    ],
    "wof:name":"F.L.O.W.",
    "wof:placetype":"venue"
},
  "geometry": {"coordinates":[144.99285888700001,-37.8554153442],"type":"Point"}
}