{
  "type": "Feature",
  "properties": {
    "addr:full":"PO Box 3365 Tuggerah NSW 2259",
    "addr:postcode":"2259",
    "iso:country":"AU",
    "sg:address":"PO Box 3365",
    "sg:city":"Tuggerah",
    "sg:classifiers":[
        {
            "category":"Fast Food",
            "type":"Food & Drink"
        }
    ],
    "sg:phone":"+61 414 265 821",
    "sg:postcode":"2259",
    "sg:province":"NSW",
    "sg:tags":[
        "away",
        "take"
    ],
    "wof:name":"Shop &#039;N&#039; Home",
    "wof:placetype":"venue"
},
  "geometry": {"coordinates":[151.420410156,-33.3050003052],"type":"Point"}
}