{
  "type": "Feature",
  "properties": {
    "addr:full":"(Rear) 43 Reibey St Ulverstone TAS 7315",
    "addr:housenumber":"43",
    "addr:postcode":"7315",
    "addr:street":"Reibey St",
    "iso:country":"AU",
    "sg:address":"(Rear) 43 Reibey St",
    "sg:city":"Ulverstone",
    "sg:classifiers":[
        {
            "category":"Personal",
            "subcategory":"Beauty Salon",
            "type":"Services"
        }
    ],
    "sg:phone":"+61 3 6425 2148",
    "sg:postcode":"7315",
    "sg:province":"TAS",
    "sg:tags":[
        "hairdresser"
    ],
    "wof:name":"Scissor Trix",
    "wof:placetype":"venue"
},
  "geometry": {"coordinates":[146.17193603499999,-41.1571846008],"type":"Point"}
}