{
  "type": "Feature",
  "properties": {
    "iso:country":"AU",
    "sg:address":"Cnr William & Kent Sts",
    "sg:city":"Rockhampton",
    "sg:classifiers":[
        {
            "category":"Coffee & Tea",
            "type":"Food & Drink"
        }
    ],
    "sg:phone":"+61 1800 652 102",
    "sg:postcode":"4700",
    "sg:province":"QLD",
    "sg:tags":[
        "kayak",
        "canoe"
    ],
    "wof:name":"Campco",
    "wof:placetype":"venue"
},
  "geometry": {"coordinates":[150.52232360799999,-23.3991985321],"type":"Point"}
}