{
  "type": "Feature",
  "properties": {
    "addr:full":"17 Princess St Bundaberg QLD 4670",
    "addr:housenumber":"17",
    "addr:postcode":"4670",
    "addr:street":"Princess St",
    "iso:country":"AU",
    "sg:address":"17 Princess St",
    "sg:city":"Bundaberg",
    "sg:classifiers":[
        {
            "category":"Autos & Motor Vehicles",
            "subcategory":"Fuel & Gas Station",
            "type":"Retail Goods"
        }
    ],
    "sg:phone":"+61 7 4152 3818",
    "sg:postcode":"4670",
    "sg:province":"QLD",
    "wof:name":"Budget Fuels",
    "wof:placetype":"venue"
},
  "geometry": {"coordinates":[152.367095947,-24.8611030579],"type":"Point"}
}