{
  "type": "Feature",
  "properties": {
    "addr:full":"618 Light St Dianella WA 6059",
    "addr:housenumber":"618",
    "addr:postcode":"6059",
    "addr:street":"Light St",
    "iso:country":"AU",
    "sg:address":"618 Light St",
    "sg:city":"Dianella",
    "sg:classifiers":[
        {
            "category":"Utilities",
            "subcategory":"Electric",
            "type":"Services"
        }
    ],
    "sg:phone":"+61 8 9275 2135",
    "sg:postcode":"6059",
    "sg:province":"WA",
    "sg:tags":[
        "electrical",
        "contractor"
    ],
    "wof:name":"Power Logic Electrical Pty Ltd",
    "wof:placetype":"venue"
},
  "geometry": {"coordinates":[115.871459961,-31.881111145],"type":"Point"}
}