{
  "type": "Feature",
  "properties": {
    "iso:country":"AU",
    "sg:address":"2/ 16 Nicholson St",
    "sg:city":"Balmain East",
    "sg:classifiers":[
        {
            "category":"Professional",
            "subcategory":"Management & Consulting",
            "type":"Services"
        }
    ],
    "sg:phone":"+61 2 9810 4119",
    "sg:postcode":"2041",
    "sg:province":"NSW",
    "sg:tags":[
        "consultant"
    ],
    "wof:name":"Mark Tredinnick Consulting Pty Ltd",
    "wof:placetype":"venue"
},
  "geometry": {"coordinates":[151.192886,-33.85656],"type":"Point"}
}