{
  "type": "Feature",
  "properties": {
    "iso:country":"AU",
    "sg:address":"420 Hay St",
    "sg:city":"Subiaco",
    "sg:classifiers":[
        {
            "category":"Personal",
            "subcategory":"Beauty Salon",
            "type":"Services"
        }
    ],
    "sg:phone":"+61 8 9388 8449",
    "sg:postcode":"6008",
    "sg:province":"WA",
    "sg:tags":[
        "hairdresser"
    ],
    "wof:name":"Hair On Central",
    "wof:placetype":"venue"
},
  "geometry": {"coordinates":[115.825538635,-31.9468803406],"type":"Point"}
}