{
  "type": "Feature",
  "properties": {
    "addr:full":"684 Elgar Rd Box Hill North VIC 3129",
    "addr:housenumber":"684",
    "addr:postcode":"3129",
    "addr:street":"Elgar Rd",
    "iso:country":"AU",
    "sg:address":"684 Elgar Rd",
    "sg:city":"Box Hill North",
    "sg:classifiers":[
        {
            "category":"Farming",
            "subcategory":"Livestock Farm",
            "type":"Manufacturing & Wholesale Goods"
        }
    ],
    "sg:phone":"+61 3 9898 9384",
    "sg:postcode":"3129",
    "sg:province":"VIC",
    "sg:tags":[
        "school",
        "theological"
    ],
    "wof:name":"Presbyterian Theological College",
    "wof:placetype":"venue"
},
  "geometry": {"coordinates":[145.11875915499999,-37.7972602844],"type":"Point"}
}