{
  "type": "Feature",
  "properties": {
    "addr:full":"12 Carrington St Millner NT 0810",
    "addr:housenumber":"12",
    "addr:postcode":"nt 0810",
    "addr:street":"Carrington St",
    "iso:country":"AU",
    "sg:address":"12 Carrington St",
    "sg:city":"Millner",
    "sg:classifiers":[
        {
            "category":"Travel",
            "subcategory":"Travel Agent",
            "type":"Entertainment"
        }
    ],
    "sg:phone":"+61 8 8985 2134",
    "sg:postcode":"0810",
    "sg:province":"NT",
    "sg:tags":[
        "tour",
        "holiday",
        "adventure"
    ],
    "wof:name":"Willis's Walkabouts",
    "wof:placetype":"venue"
},
  "geometry": {"coordinates":[130.86553955100001,-12.3920249939],"type":"Point"}
}