{
  "type": "Feature",
  "properties": {
    "addr:full":"86 Nicholson St Abbotsford VIC 3067",
    "addr:housenumber":"86",
    "addr:postcode":"3067",
    "addr:street":"Nicholson St",
    "iso:country":"AU",
    "sg:address":"86 Nicholson St",
    "sg:city":"Abbotsford",
    "sg:classifiers":[
        {
            "category":"Farming",
            "subcategory":"Fish & Marine Products",
            "type":"Manufacturing & Wholesale Goods"
        }
    ],
    "sg:phone":"+61 3 9419 4927",
    "sg:postcode":"3067",
    "sg:province":"VIC",
    "sg:tags":[
        "wholesaler",
        "mfrs",
        "swimwear"
    ],
    "wof:name":"Bra Cup Fabric Moulders (Bragstar Pty Ltd)",
    "wof:placetype":"venue"
},
  "geometry": {"coordinates":[144.996704102,-37.8064041138],"type":"Point"}
}