{
  "type": "Feature",
  "properties": {
    "addr:full":"Level 1 323 Elizabeth St Melbourne VIC 3000",
    "addr:housenumber":"323",
    "addr:postcode":"3000",
    "addr:street":"Elizabeth St",
    "iso:country":"AU",
    "sg:address":"Level 1 323 Elizabeth St",
    "sg:city":"Melbourne",
    "sg:classifiers":[
        {
            "category":"Manufacturing",
            "subcategory":"Motor Vehicles & Parts",
            "type":"Manufacturing & Wholesale Goods"
        }
    ],
    "sg:phone":"+61 3 9602 4400",
    "sg:postcode":"3000",
    "sg:province":"VIC",
    "sg:tags":[
        "wholesaler",
        "cycle",
        "mfrs",
        "accessory"
    ],
    "wof:name":"Australian-Italian Imports",
    "wof:placetype":"venue"
},
  "geometry": {"coordinates":[144.96156310999999,-37.8111038208],"type":"Point"}
}