{
  "type": "Feature",
  "properties": {
    "addr:full":"3/ 200-208 North St Albury NSW 2640",
    "addr:housenumber":"/ 200-208",
    "addr:postcode":"2640",
    "addr:street":"North St",
    "iso:country":"AU",
    "sg:address":"3/ 200-208 North St",
    "sg:city":"Albury",
    "sg:classifiers":[
        {
            "category":"Professional",
            "subcategory":"Engineering",
            "type":"Services"
        }
    ],
    "sg:phone":"+61 2 6040 7066",
    "sg:postcode":"2640",
    "sg:province":"NSW",
    "sg:tags":[
        "engineer"
    ],
    "wof:name":"Albury Steel Fabricators",
    "wof:placetype":"venue"
},
  "geometry": {"coordinates":[146.94093322800001,-36.0698509216],"type":"Point"}
}