{
  "type": "Feature",
  "properties": {
    "addr:full":"662 Goodwood Rd Daw Park SA 5041",
    "addr:housenumber":"662",
    "addr:postcode":"5041",
    "addr:street":"Goodwood Rd",
    "iso:country":"AU",
    "sg:address":"662 Goodwood Rd",
    "sg:city":"Daw Park",
    "sg:phone":"+61 8 8357 6243",
    "sg:postcode":"5041",
    "sg:province":"SA",
    "wof:name":"Green Streets - Sustainable Urban Environments",
    "wof:placetype":"venue"
},
  "geometry": {"coordinates":[138.59231600000001,-34.987385],"type":"Point"}
}