{
  "type": "Feature",
  "properties": {
    "addr:full":"6 Centre Rd Morwell VIC 3840",
    "addr:housenumber":"6",
    "addr:postcode":"3840",
    "addr:street":"Centre Rd",
    "iso:country":"AU",
    "sg:address":"6 Centre Rd",
    "sg:city":"Morwell",
    "sg:classifiers":[
        {
            "category":"Building & Trades",
            "subcategory":"Construction",
            "type":"Services"
        }
    ],
    "sg:phone":"+61 3 5134 2111",
    "sg:postcode":"3840",
    "sg:province":"VIC",
    "sg:tags":[
        "window",
        "tinting"
    ],
    "wof:name":"MEP Films",
    "wof:placetype":"venue"
},
  "geometry": {"coordinates":[146.44056701700001,-38.2282447815],"type":"Point"}
}