{
  "type": "Feature",
  "properties": {
    "addr:full":"33 Hill St Orange NSW 2800",
    "addr:housenumber":"33",
    "addr:postcode":"2800",
    "addr:street":"Hill St",
    "iso:country":"AU",
    "sg:address":"33 Hill St",
    "sg:city":"Orange",
    "sg:classifiers":[
        {
            "category":"Home & Garden",
            "subcategory":"Building Materials",
            "type":"Retail Goods"
        }
    ],
    "sg:phone":"+61 2 6362 1606",
    "sg:postcode":"2800",
    "sg:province":"NSW",
    "sg:tags":[
        "retaining",
        "wall"
    ],
    "wof:name":"McNabb's Professional Landscaping",
    "wof:placetype":"venue"
},
  "geometry": {"coordinates":[149.093383789,-33.28383255],"type":"Point"}
}