{
  "type": "Feature",
  "properties": {
    "addr:full":"37 Caroville Drv Warrnambool VIC 3280",
    "addr:housenumber":"37",
    "addr:postcode":"3280",
    "addr:street":"Caroville Drv",
    "iso:country":"AU",
    "sg:address":"37 Caroville Drv",
    "sg:city":"Warrnambool",
    "sg:classifiers":[
        {
            "category":"Social Services",
            "subcategory":"Retirement Home",
            "type":"Services"
        }
    ],
    "sg:phone":"+61 3 5561 0188",
    "sg:postcode":"3280",
    "sg:province":"VIC",
    "sg:tags":[
        "village"
    ],
    "wof:name":"Village Life",
    "wof:placetype":"venue"
},
  "geometry": {"coordinates":[142.51820373499999,-38.3805580139],"type":"Point"}
}