{
  "type": "Feature",
  "properties": {
    "iso:country":"AU",
    "sg:address":"50 Pitman Ave",
    "sg:city":"Buronga",
    "sg:classifiers":[
        {
            "category":"Farming",
            "subcategory":"Nursery",
            "type":"Manufacturing & Wholesale Goods"
        }
    ],
    "sg:phone":"+61 428 211 819",
    "sg:postcode":"2739",
    "sg:province":"NSW",
    "wof:name":"Keighley Hill Bonsai",
    "wof:placetype":"venue"
},
  "geometry": {"coordinates":[142.19876099999999,-34.170132],"type":"Point"}
}