{
  "type": "Feature",
  "properties": {
    "iso:country":"AU",
    "sg:address":"10 Barnett St",
    "sg:city":"Fremantle",
    "sg:classifiers":[
        {
            "category":"Real Estate",
            "subcategory":"Architect",
            "type":"Services"
        }
    ],
    "sg:phone":"+61 8 9335 8570",
    "sg:postcode":"6160",
    "sg:province":"WA",
    "sg:tags":[
        "building",
        "designer"
    ],
    "wof:name":"Slavin Architects Pty Ltd",
    "wof:placetype":"venue"
},
  "geometry": {"coordinates":[115.751823,-32.048939],"type":"Point"}
}