{
  "type": "Feature",
  "properties": {
    "addr:full":"49 Stephenson St Richmond VIC 3121",
    "addr:housenumber":"49",
    "addr:postcode":"3121",
    "addr:street":"Stephenson St",
    "iso:country":"AU",
    "sg:address":"49 Stephenson St",
    "sg:city":"Richmond",
    "sg:classifiers":[
        {
            "category":"Banks & Credit Unions",
            "subcategory":"Investment Brokerage",
            "type":"Services"
        }
    ],
    "sg:phone":"+61 3 9429 9866",
    "sg:postcode":"3121",
    "sg:province":"VIC",
    "sg:tags":[
        "baby",
        "wholesaler",
        "mfrs",
        "wear"
    ],
    "wof:name":"Anuello Pty Ltd",
    "wof:placetype":"venue"
},
  "geometry": {"coordinates":[144.99371337900001,-37.8286437988],"type":"Point"}
}