{
  "type": "Feature",
  "properties": {
    "iso:country":"AU",
    "sg:address":"14 Hallmarc Business Pk, Burnside Rd",
    "sg:city":"Yatala",
    "sg:classifiers":[
        {
            "category":"Retail",
            "subcategory":"Laundry & Dry Cleaning",
            "type":"Services"
        }
    ],
    "sg:phone":"+61 406 764 757",
    "sg:postcode":"4207",
    "sg:province":"QLD",
    "sg:tags":[
        "cloth",
        "supply"
    ],
    "wof:name":"Roo Rags",
    "wof:placetype":"venue"
},
  "geometry": {"coordinates":[153.241897583,-27.7537536621],"type":"Point"}
}