{
  "type": "Feature",
  "properties": {
    "addr:full":"73 Albany St Coffs Harbour NSW 2450",
    "addr:housenumber":"73",
    "addr:postcode":"2450",
    "addr:street":"Albany St",
    "iso:country":"AU",
    "sg:address":"73 Albany St",
    "sg:city":"Coffs Harbour",
    "sg:classifiers":[
        {
            "category":"Health Services",
            "subcategory":"Doctor",
            "type":"Services"
        }
    ],
    "sg:phone":"+61 2 6652 8992",
    "sg:postcode":"2450",
    "sg:province":"NSW",
    "sg:tags":[
        "medical",
        "practitioner"
    ],
    "wof:name":"Young Ivan M. Dr.",
    "wof:placetype":"venue"
},
  "geometry": {"coordinates":[153.11631800000001,-30.300798],"type":"Point"}
}