{
  "type": "Feature",
  "properties": {
    "iso:country":"AU",
    "sg:address":"14 Horwood St",
    "sg:city":"Whyalla",
    "sg:classifiers":[
        {
            "category":"Retail",
            "subcategory":"Photofinishing",
            "type":"Services"
        }
    ],
    "sg:phone":"+61 8 8645 0963",
    "sg:postcode":"5600",
    "sg:province":"SA",
    "sg:tags":[
        "refractory"
    ],
    "wof:name":"Cookson Plibrico Pty Ltd",
    "wof:placetype":"venue"
},
  "geometry": {"coordinates":[137.58691400000001,-33.034332],"type":"Point"}
}