{
  "type": "Feature",
  "properties": {
    "iso:country":"AU",
    "sg:address":"461 Hume Hwy",
    "sg:city":"Yagoona",
    "sg:classifiers":[
        {
            "category":"Real Estate",
            "subcategory":"Real Estate Agent",
            "type":"Services"
        }
    ],
    "sg:phone":"+61 2 9708 1988",
    "sg:postcode":"2199",
    "sg:province":"NSW",
    "wof:name":"Todd & Co Real Estate Pty Ltd",
    "wof:placetype":"venue"
},
  "geometry": {"coordinates":[151.02351400000001,-33.907413],"type":"Point"}
}