{
  "type": "Feature",
  "properties": {
    "addr:full":"Level 4, 1 Queens Rd Melbourne VIC 3004",
    "addr:housenumber":"1",
    "addr:postcode":"3004",
    "addr:street":"Queens Rd",
    "iso:country":"AU",
    "sg:address":"Level 4, 1 Queens Rd",
    "sg:city":"Melbourne",
    "sg:classifiers":[
        {
            "category":"Education",
            "subcategory":"Special Training",
            "type":"Public Place"
        }
    ],
    "sg:phone":"+61 3 9537 2844",
    "sg:postcode":"3004",
    "sg:province":"VIC",
    "sg:tags":[
        "development",
        "sale"
    ],
    "sg:website":"http://www.vividmessage.com",
    "wof:name":"Vivid Presentation Skills",
    "wof:placetype":"venue"
},
  "geometry": {"coordinates":[144.97369384800001,-37.8357315063],"type":"Point"}
}