{
  "type": "Feature",
  "properties": {
    "iso:country":"AU",
    "sg:address":"Port Wakefield Service Rd",
    "sg:city":"Burton",
    "sg:classifiers":[
        {
            "category":"Retail",
            "subcategory":"Auto Repair",
            "type":"Services"
        }
    ],
    "sg:phone":"+61 8 8280 8133",
    "sg:postcode":"5110",
    "sg:province":"SA",
    "sg:tags":[
        "bus",
        "truck"
    ],
    "wof:name":"Wakefield Trucks Pty Ltd",
    "wof:placetype":"venue"
},
  "geometry": {"coordinates":[138.58607482900001,-34.7412948608],"type":"Point"}
}