{
  "type": "Feature",
  "properties": {
    "addr:full":"326 David Low Way Bli Bli QLD 4560",
    "addr:housenumber":"326",
    "addr:postcode":"4560",
    "addr:street":"David Low Way",
    "iso:country":"AU",
    "sg:address":"326 David Low Way",
    "sg:city":"Bli Bli",
    "sg:classifiers":[
        {
            "category":"Personal",
            "subcategory":"Beauty Salon",
            "type":"Services"
        }
    ],
    "sg:phone":"+61 7 5450 0109",
    "sg:postcode":"4560",
    "sg:province":"QLD",
    "sg:tags":[
        "hairdresser"
    ],
    "wof:name":"The Hair Shop",
    "wof:placetype":"venue"
},
  "geometry": {"coordinates":[153.04312133799999,-26.6218852997],"type":"Point"}
}