{
  "type": "Feature",
  "properties": {
    "iso:country":"AU",
    "sg:address":"PO Box 304",
    "sg:city":"Tin Can Bay",
    "sg:classifiers":[
        {
            "category":"Professional",
            "type":"Services"
        }
    ],
    "sg:phone":"+61 7 5488 0044",
    "sg:postcode":"4580",
    "sg:province":"QLD",
    "sg:tags":[
        "quality",
        "assurance"
    ],
    "wof:name":"Ferriby Group of Companies Pty Ltd",
    "wof:placetype":"venue"
},
  "geometry": {"coordinates":[152.999832153,-25.9213199615],"type":"Point"}
}