{
  "type": "Feature",
  "properties": {
    "addr:full":"Shop 6 & 7 Portwood Pl Redcliffe QLD 4020",
    "addr:housenumber":"shop 6 & 7",
    "addr:postcode":"4020",
    "addr:street":"Portwood Pl",
    "iso:country":"AU",
    "sg:address":"Shop 6 & 7 Portwood Pl",
    "sg:city":"Redcliffe",
    "sg:classifiers":[
        {
            "category":"Shopping",
            "subcategory":"Bicycles & Sporting Goods",
            "type":"Retail Goods"
        }
    ],
    "sg:phone":"+61 7 3203 0838",
    "sg:postcode":"4020",
    "sg:province":"QLD",
    "sg:tags":[
        "chemical",
        "equipment",
        "pool",
        "swimming"
    ],
    "wof:name":"Crown Pools & Spas (Qld) Pty Ltd",
    "wof:placetype":"venue"
},
  "geometry": {"coordinates":[153.10609400000001,-27.225863],"type":"Point"}
}