{
  "type": "Feature",
  "properties": {
    "addr:full":"Fact 7/ 26 Longstaff Rd Bayswater VIC 3153",
    "addr:housenumber":"7 / 26",
    "addr:postcode":"3153",
    "addr:street":"Fact;Longstaff Rd",
    "iso:country":"AU",
    "sg:address":"Fact 7/ 26 Longstaff Rd",
    "sg:city":"Bayswater",
    "sg:classifiers":[
        {
            "category":"Professional",
            "type":"Services"
        }
    ],
    "sg:phone":"+61 3 9720 9455",
    "sg:postcode":"3153",
    "sg:province":"VIC",
    "sg:tags":[
        "coating",
        "powder"
    ],
    "wof:name":"Active Powder Coating Pty Ltd",
    "wof:placetype":"venue"
},
  "geometry": {"coordinates":[145.283447266,-37.8355674744],"type":"Point"}
}