{
  "type": "Feature",
  "properties": {
    "iso:country":"AU",
    "sg:address":"72 Anders St",
    "sg:city":"Jimboomba",
    "sg:classifiers":[
        {
            "category":"Home & Garden",
            "subcategory":"Building Materials",
            "type":"Retail Goods"
        }
    ],
    "sg:phone":"+61 7 5546 0321",
    "sg:postcode":"4280",
    "sg:province":"QLD",
    "sg:tags":[
        "fencing"
    ],
    "sg:website":"http://www.topnotch.com.au",
    "wof:name":"Jimboomba Fencing & Steel Supplies",
    "wof:placetype":"venue"
},
  "geometry": {"coordinates":[153.031296,-27.825373],"type":"Point"}
}