{
  "type": "Feature",
  "properties": {
    "addr:full":"47 Dorking Rd Cabarita NSW 2137",
    "addr:housenumber":"47",
    "addr:postcode":"2137",
    "addr:street":"Dorking Rd",
    "iso:country":"AU",
    "sg:address":"47 Dorking Rd",
    "sg:city":"Cabarita",
    "sg:classifiers":[
        {
            "category":"Professional",
            "subcategory":"Management & Consulting",
            "type":"Services"
        }
    ],
    "sg:phone":"+61 2 9712 0011",
    "sg:postcode":"2137",
    "sg:province":"NSW",
    "sg:tags":[
        "consultant"
    ],
    "wof:name":"Ryleblend Pty Ltd",
    "wof:placetype":"venue"
},
  "geometry": {"coordinates":[151.116821289,-33.8471069336],"type":"Point"}
}