{
  "type": "Feature",
  "properties": {
    "addr:full":"5 Currajong St Parkes NSW 2870",
    "addr:housenumber":"5",
    "addr:postcode":"2870",
    "addr:street":"Currajong St",
    "iso:country":"AU",
    "sg:address":"5 Currajong St",
    "sg:city":"Parkes",
    "sg:classifiers":[
        {
            "category":"Home & Garden",
            "subcategory":"Hardware",
            "type":"Retail Goods"
        }
    ],
    "sg:phone":"+61 2 6863 5200",
    "sg:postcode":"2870",
    "sg:province":"NSW",
    "sg:tags":[
        "repair",
        "tool",
        "power"
    ],
    "wof:name":"Power Tools Plus",
    "wof:placetype":"venue"
},
  "geometry": {"coordinates":[148.17585800000001,-33.133091],"type":"Point"}
}