{
  "type": "Feature",
  "properties": {
    "addr:full":"381 High Street Rd Mt Waverley VIC 3149",
    "addr:housenumber":"381",
    "addr:postcode":"3149",
    "addr:street":"High Street Rd",
    "iso:country":"AU",
    "sg:address":"381 High Street Rd",
    "sg:city":"Mt Waverley",
    "sg:classifiers":[
        {
            "category":"Professional",
            "subcategory":"Engineering",
            "type":"Services"
        }
    ],
    "sg:phone":"+61 3 9888 1577",
    "sg:postcode":"3149",
    "sg:province":"VIC",
    "sg:tags":[
        "consulting",
        "engineer"
    ],
    "wof:name":"Clarke Anthony W & Associates Pty Ltd",
    "wof:placetype":"venue"
},
  "geometry": {"coordinates":[145.134002686,-37.8703193665],"type":"Point"}
}