{
  "type": "Feature",
  "properties": {
    "addr:full":"Royal George La Rosewood QLD 4340",
    "addr:postcode":"4340",
    "iso:country":"AU",
    "sg:address":"Royal George La",
    "sg:city":"Rosewood",
    "sg:classifiers":[
        {
            "category":"Fast Food",
            "type":"Food & Drink"
        }
    ],
    "sg:phone":"+61 7 5464 1368",
    "sg:postcode":"4340",
    "sg:province":"QLD",
    "sg:tags":[
        "away",
        "take"
    ],
    "wof:name":"Plaza Corner Take-Away",
    "wof:placetype":"venue"
},
  "geometry": {"coordinates":[152.59120178200001,-27.6418437958],"type":"Point"}
}