{
  "type": "Feature",
  "properties": {
    "iso:country":"AU",
    "sg:address":"2 Kinka Rd",
    "sg:city":"Terrey Hills",
    "sg:classifiers":[
        {
            "category":"Farming",
            "subcategory":"Livestock Farm",
            "type":"Manufacturing & Wholesale Goods"
        }
    ],
    "sg:phone":"+61 2 9450 0025",
    "sg:postcode":"2084",
    "sg:province":"NSW",
    "sg:tags":[
        "agistment"
    ],
    "wof:name":"Pindari Park Stables",
    "wof:placetype":"venue"
},
  "geometry": {"coordinates":[151.199295044,-33.677646637],"type":"Point"}
}