{
  "type": "Feature",
  "properties": {
    "addr:full":"261 Haly St Kingaroy QLD 4610",
    "addr:housenumber":"261",
    "addr:postcode":"4610",
    "addr:street":"Haly St",
    "iso:country":"AU",
    "sg:address":"261 Haly St",
    "sg:city":"Kingaroy",
    "sg:classifiers":[
        {
            "category":"Education",
            "subcategory":"Kindergarten",
            "type":"Public Place"
        }
    ],
    "sg:phone":"+61 7 4162 7233",
    "sg:postcode":"4610",
    "sg:province":"QLD",
    "sg:tags":[
        "pre-schools"
    ],
    "wof:name":"Kingaroy Early Education Centre",
    "wof:placetype":"venue"
},
  "geometry": {"coordinates":[151.83888244600001,-26.5392513275],"type":"Point"}
}