{
  "type": "Feature",
  "properties": {
    "addr:full":"185 Mount St Burnie TAS 7320",
    "addr:housenumber":"185",
    "addr:postcode":"7320",
    "addr:street":"Mount St",
    "iso:country":"AU",
    "sg:address":"185 Mount St",
    "sg:city":"Burnie",
    "sg:classifiers":[
        {
            "category":"Utilities",
            "type":"Services"
        }
    ],
    "sg:phone":"+61 3 6431 1361",
    "sg:postcode":"7320",
    "sg:province":"TAS",
    "sg:tags":[
        "refrigeration",
        "industrial",
        "commercial",
        "retail"
    ],
    "wof:name":"C.R. Morton Pty Ltd",
    "wof:placetype":"venue"
},
  "geometry": {"coordinates":[145.901398,-41.06905],"type":"Point"}
}