{
  "type": "Feature",
  "properties": {
    "addr:full":"5 Blackstone St Wetherill Park NSW 2164",
    "addr:housenumber":"5",
    "addr:postcode":"2164",
    "addr:street":"Blackstone St",
    "iso:country":"AU",
    "sg:address":"5 Blackstone St",
    "sg:city":"Wetherill Park",
    "sg:classifiers":[
        {
            "category":"Wholesale",
            "subcategory":"Stationery",
            "type":"Manufacturing & Wholesale Goods"
        }
    ],
    "sg:phone":"+61 2 9604 7727",
    "sg:postcode":"2164",
    "sg:province":"NSW",
    "sg:tags":[
        "mfrg"
    ],
    "wof:name":"National Envelopes",
    "wof:placetype":"venue"
},
  "geometry": {"coordinates":[150.921798706,-33.8418006897],"type":"Point"}
}