{
  "type": "Feature",
  "properties": {
    "iso:country":"AU",
    "sg:address":"Building 3B, Archerfield Industrial Park, Cnr Kerry & Beaudesert Roads",
    "sg:city":"Archerfield",
    "sg:classifiers":[
        {
            "category":"Wholesale",
            "subcategory":"Medical Equipment & Supplies",
            "type":"Manufacturing & Wholesale Goods"
        }
    ],
    "sg:phone":"+61 7 3275 2050",
    "sg:postcode":"4108",
    "sg:province":"QLD",
    "sg:tags":[
        "dental"
    ],
    "wof:name":"Mediquip Pty Ltd",
    "wof:placetype":"venue"
},
  "geometry": {"coordinates":[153.02378845199999,-27.5669746399],"type":"Point"}
}