{
  "type": "Feature",
  "properties": {
    "addr:full":"T08 Central West Plaza Cnr Ashley & South Rd West Footscray VIC 3012",
    "addr:postcode":"3012",
    "addr:street":"Cnr;South Rd",
    "iso:country":"AU",
    "sg:address":"T08 Central West Plaza Cnr Ashley & South Rd",
    "sg:city":"West Footscray",
    "sg:classifiers":[
        {
            "category":"Food & Beverages",
            "subcategory":"Bakery",
            "type":"Retail Goods"
        }
    ],
    "sg:phone":"+61 3 9396 1318",
    "sg:postcode":"3012",
    "sg:province":"VIC",
    "sg:tags":[
        "cake",
        "shop",
        "pastry"
    ],
    "wof:name":"Michels Patisserie",
    "wof:placetype":"venue"
},
  "geometry": {"coordinates":[144.86210632300001,-37.7993469238],"type":"Point"}
}