{
  "type": "Feature",
  "properties": {
    "addr:full":"Suite 1, 24 Eastern Rd South Melbourne VIC 3205",
    "addr:housenumber":"24",
    "addr:postcode":"3205",
    "addr:street":"Eastern Rd",
    "iso:country":"AU",
    "sg:address":"Suite 1, 24 Eastern Rd",
    "sg:city":"South Melbourne",
    "sg:classifiers":[
        {
            "category":"Professional",
            "subcategory":"Business Services",
            "type":"Services"
        }
    ],
    "sg:phone":"+61 3 9682 1792",
    "sg:postcode":"3205",
    "sg:province":"VIC",
    "sg:tags":[
        "management",
        "event"
    ],
    "sg:website":"http://www.immediacy.com.au",
    "wof:name":"Immediacy Pty Ltd",
    "wof:placetype":"venue"
},
  "geometry": {"coordinates":[144.96481299999999,-37.831905],"type":"Point"}
}