{
  "type": "Feature",
  "properties": {
    "addr:full":"4/ 617 Toohey Rd Salisbury QLD 4107",
    "addr:housenumber":"/ 617",
    "addr:postcode":"4107",
    "addr:street":"Toohey Rd",
    "iso:country":"AU",
    "sg:address":"4/ 617 Toohey Rd",
    "sg:city":"Salisbury",
    "sg:classifiers":[
        {
            "category":"Home & Garden",
            "subcategory":"Building Materials",
            "type":"Retail Goods"
        }
    ],
    "sg:phone":"+61 7 3274 4852",
    "sg:postcode":"4107",
    "sg:province":"QLD",
    "sg:tags":[
        "merchant",
        "glass",
        "glazier"
    ],
    "wof:name":"Andersons Glass & Screen Service",
    "wof:placetype":"venue"
},
  "geometry": {"coordinates":[153.039352417,-27.5433330536],"type":"Point"}
}