{
  "type": "Feature",
  "properties": {
    "addr:full":"PO Box 1042 Barwon Heads VIC 3227",
    "addr:postcode":"3227",
    "iso:country":"AU",
    "sg:address":"PO Box 1042",
    "sg:city":"Barwon Heads",
    "sg:classifiers":[
        {
            "category":"Manufacturing",
            "subcategory":"Food",
            "type":"Manufacturing & Wholesale Goods"
        }
    ],
    "sg:phone":"+61 3 5256 2657",
    "sg:postcode":"3227",
    "sg:province":"VIC",
    "sg:tags":[
        "function",
        "catering"
    ],
    "wof:name":"Bellarine B.B.Q. Catering",
    "wof:placetype":"venue"
},
  "geometry": {"coordinates":[144.49195900000001,-38.282379],"type":"Point"}
}