{
  "type": "Feature",
  "properties": {
    "iso:country":"AU",
    "sg:address":"48 Boundary St",
    "sg:city":"Paddington",
    "sg:classifiers":[
        {
            "category":"Professional",
            "subcategory":"Computer Services",
            "type":"Services"
        }
    ],
    "sg:phone":"+61 2 9360 4493",
    "sg:postcode":"2021",
    "sg:province":"NSW",
    "sg:tags":[
        "equipment",
        "networking",
        "installation"
    ],
    "wof:name":"JSR Systems Solutions",
    "wof:placetype":"venue"
},
  "geometry": {"coordinates":[151.22233581500001,-33.8809509277],"type":"Point"}
}