{
  "type": "Feature",
  "properties": {
    "iso:country":"AU",
    "sg:address":"Cnr Davidson St & Hume Highway",
    "sg:city":"Chullora",
    "sg:classifiers":[
        {
            "category":"Home & Garden",
            "subcategory":"Building Materials",
            "type":"Retail Goods"
        }
    ],
    "sg:phone":"+61 2 9742 6822",
    "sg:postcode":"2190",
    "sg:province":"NSW",
    "sg:tags":[
        "supply"
    ],
    "wof:name":"Materials In The Raw",
    "wof:placetype":"venue"
},
  "geometry": {"coordinates":[151.065842,-33.88623],"type":"Point"}
}