{
  "type": "Feature",
  "properties": {
    "addr:full":"19 Burgess St Ipswich QLD 4305",
    "addr:housenumber":"19",
    "addr:postcode":"4305",
    "addr:street":"Burgess St",
    "iso:country":"AU",
    "sg:address":"19 Burgess St",
    "sg:city":"Ipswich",
    "sg:classifiers":[
        {
            "category":"Banks & Credit Unions",
            "subcategory":"Financial Services",
            "type":"Services"
        }
    ],
    "sg:phone":"+61 7 3288 6400",
    "sg:postcode":"4305",
    "sg:province":"QLD",
    "sg:tags":[
        "loan",
        "finance",
        "mortgage"
    ],
    "wof:name":"Les Scott & Associates",
    "wof:placetype":"venue"
},
  "geometry": {"coordinates":[152.783599853,-27.6427211761],"type":"Point"}
}