{
  "type": "Feature",
  "properties": {
    "iso:country":"AU",
    "sg:address":"Cnr Golden Grove Rd & Laburnum Drv",
    "sg:city":"Greenwith",
    "sg:classifiers":[
        {
            "category":"Education",
            "subcategory":"Kindergarten",
            "type":"Public Place"
        }
    ],
    "sg:phone":"+61 8 8289 7696",
    "sg:postcode":"5125",
    "sg:province":"SA",
    "sg:tags":[
        "pre-schools"
    ],
    "wof:name":"Greenwith Kindergarten",
    "wof:placetype":"venue"
},
  "geometry": {"coordinates":[138.719696,-34.768936],"type":"Point"}
}