{
  "type": "Feature",
  "properties": {
    "addr:full":"30 Northview Drv Pambula South NSW 2549",
    "addr:housenumber":"30",
    "addr:postcode":"2549",
    "addr:street":"Northview Drv",
    "iso:country":"AU",
    "sg:address":"30 Northview Drv",
    "sg:city":"Pambula South",
    "sg:classifiers":[
        {
            "category":"Retail",
            "subcategory":"Repair Shop",
            "type":"Services"
        }
    ],
    "sg:phone":"+61 2 6495 7187",
    "sg:postcode":"2549",
    "sg:province":"NSW",
    "sg:tags":[
        "machine",
        "repairs",
        "part",
        "dryer",
        "washing"
    ],
    "wof:name":"Direct Appliance Service",
    "wof:placetype":"venue"
},
  "geometry": {"coordinates":[149.860839844,-36.9426994324],"type":"Point"}
}