{
  "type": "Feature",
  "properties": {
    "iso:country":"AU",
    "sg:address":"Suite 3/ 108 Haldon St",
    "sg:city":"Lakemba",
    "sg:classifiers":[
        {
            "category":"Professional",
            "subcategory":"Management & Consulting",
            "type":"Services"
        }
    ],
    "sg:phone":"+61 2 9740 8612",
    "sg:postcode":"2195",
    "sg:province":"NSW",
    "sg:tags":[
        "consultant",
        "educational"
    ],
    "wof:name":"H B D Services",
    "wof:placetype":"venue"
},
  "geometry": {"coordinates":[151.077911,-33.921524],"type":"Point"}
}