{
  "type": "Feature",
  "properties": {
    "addr:full":"1667 Centre Rd Springvale VIC 3171",
    "addr:housenumber":"1667",
    "addr:postcode":"3171",
    "addr:street":"Centre Rd",
    "iso:country":"AU",
    "sg:address":"1667 Centre Rd",
    "sg:city":"Springvale",
    "sg:classifiers":[
        {
            "category":"Home & Garden",
            "subcategory":"Building Materials",
            "type":"Retail Goods"
        }
    ],
    "sg:phone":"+61 3 9546 0555",
    "sg:postcode":"3171",
    "sg:province":"VIC",
    "sg:tags":[
        "supply"
    ],
    "wof:name":"Dahlsens",
    "wof:placetype":"venue"
},
  "geometry": {"coordinates":[145.14828491200001,-37.9320144653],"type":"Point"}
}