{
  "type": "Feature",
  "properties": {
    "iso:country":"AU",
    "sg:address":"391 Princes Hwy",
    "sg:city":"Woonona",
    "sg:classifiers":[
        {
            "category":"Health Services",
            "subcategory":"Dentist",
            "type":"Services"
        }
    ],
    "sg:phone":"+61 2 4284 4486",
    "sg:postcode":"2517",
    "sg:province":"NSW",
    "wof:name":"Renaud Richard",
    "wof:placetype":"venue"
},
  "geometry": {"coordinates":[150.906342,-34.34161],"type":"Point"}
}