{
  "type": "Feature",
  "properties": {
    "addr:full":"953 Glen Huntly Rd Caulfield South VIC 3162",
    "addr:housenumber":"953",
    "addr:postcode":"3162",
    "addr:street":"Glen Huntly Rd",
    "iso:country":"AU",
    "sg:address":"953 Glen Huntly Rd",
    "sg:city":"Caulfield South",
    "sg:classifiers":[
        {
            "category":"Retail",
            "subcategory":"Auto Repair",
            "type":"Services"
        }
    ],
    "sg:phone":"+61 3 9563 6755",
    "sg:postcode":"3162",
    "sg:province":"VIC",
    "sg:tags":[
        "electrical"
    ],
    "wof:name":"Glen Huntly Auto Electrical",
    "wof:placetype":"venue"
},
  "geometry": {"coordinates":[145.03016662600001,-37.8877639771],"type":"Point"}
}