{
  "type": "Feature",
  "properties": {
    "iso:country":"AU",
    "sg:address":"23 Glastonbury Drv",
    "sg:city":"Bethania",
    "sg:classifiers":[
        {
            "category":"Retail",
            "subcategory":"Auto Repair",
            "type":"Services"
        }
    ],
    "sg:phone":"+61 7 3805 6766",
    "sg:postcode":"4205",
    "sg:province":"QLD",
    "sg:tags":[
        "automotive",
        "air conditioning"
    ],
    "wof:name":"Transport Air Conditioning",
    "wof:placetype":"venue"
},
  "geometry": {"coordinates":[153.16001892099999,-27.6933631897],"type":"Point"}
}