{
  "type": "Feature",
  "properties": {
    "addr:full":"11 Beaumont St Hamilton NSW 2303",
    "addr:housenumber":"11",
    "addr:postcode":"2303",
    "addr:street":"Beaumont St",
    "iso:country":"AU",
    "sg:address":"11 Beaumont St",
    "sg:city":"Hamilton",
    "sg:classifiers":[
        {
            "category":"Personal",
            "subcategory":"Barber",
            "type":"Services"
        }
    ],
    "sg:phone":"+61 2 4969 7747",
    "sg:postcode":"2303",
    "sg:province":"NSW",
    "wof:name":"Sportsmans Barber",
    "wof:placetype":"venue"
},
  "geometry": {"coordinates":[151.74766500000001,-32.921051],"type":"Point"}
}