{
  "type": "Feature",
  "properties": {
    "addr:full":"Piemonte Rd Mutchilba QLD 4872",
    "addr:postcode":"4872",
    "addr:street":"Piemonte Rd",
    "iso:country":"AU",
    "sg:address":"Piemonte Rd",
    "sg:city":"Mutchilba",
    "sg:classifiers":[
        {
            "category":"Farming",
            "subcategory":"Farm",
            "type":"Manufacturing & Wholesale Goods"
        }
    ],
    "sg:phone":"+61 7 4093 1171",
    "sg:postcode":"4872",
    "sg:province":"QLD",
    "sg:tags":[
        "farmer"
    ],
    "wof:name":"Genovese L",
    "wof:placetype":"venue"
},
  "geometry": {"coordinates":[145.16636657699999,-17.1458816528],"type":"Point"}
}