{
  "type": "Feature",
  "properties": {
    "addr:full":"52 Tannery Rd Cambewarra NSW 2540",
    "addr:housenumber":"52",
    "addr:postcode":"2540",
    "addr:street":"Tannery Rd",
    "iso:country":"AU",
    "sg:address":"52 Tannery Rd",
    "sg:city":"Cambewarra",
    "sg:classifiers":[
        {
            "category":"Building & Trades",
            "subcategory":"Construction",
            "type":"Services"
        }
    ],
    "sg:phone":"+61 427 359 539",
    "sg:postcode":"2540",
    "sg:province":"NSW",
    "sg:tags":[
        "earth",
        "excavating",
        "moving",
        "contractor"
    ],
    "wof:name":"DK Earthworks",
    "wof:placetype":"venue"
},
  "geometry": {"coordinates":[150.56089782699999,-34.8185577393],"type":"Point"}
}