{
  "type": "Feature",
  "properties": {
    "iso:country":"AU",
    "sg:address":"Segenhoe Rd",
    "sg:city":"Scone",
    "sg:classifiers":[
        {
            "category":"Farming",
            "subcategory":"Livestock Farm",
            "type":"Manufacturing & Wholesale Goods"
        }
    ],
    "sg:phone":"+61 2 6543 8333",
    "sg:postcode":"2337",
    "sg:province":"NSW",
    "sg:tags":[
        "breeder",
        "horse",
        "stud"
    ],
    "wof:name":"Vinery Stud Pty Limited",
    "wof:placetype":"venue"
},
  "geometry": {"coordinates":[150.93453979500001,-32.0640792847],"type":"Point"}
}