{
  "type": "Feature",
  "properties": {
    "addr:full":"13- 21 Mandible St Alexandria NSW 2015",
    "addr:housenumber":"21",
    "addr:postcode":"2015",
    "addr:street":"Mandible St",
    "iso:country":"AU",
    "sg:address":"13- 21 Mandible St",
    "sg:city":"Alexandria",
    "sg:classifiers":[
        {
            "category":"Professional",
            "type":"Services"
        }
    ],
    "sg:phone":"+61 2 9319 2755",
    "sg:postcode":"2015",
    "sg:province":"NSW",
    "sg:tags":[
        "forwarding",
        "agent",
        "transport"
    ],
    "wof:name":"Star Ship Cargo Services",
    "wof:placetype":"venue"
},
  "geometry": {"coordinates":[151.19924926799999,-33.9048309326],"type":"Point"}
}