{
  "type": "Feature",
  "properties": {
    "addr:full":"Esk Forest Rd Esk QLD 4312",
    "addr:postcode":"4312",
    "addr:street":"Forest Rd",
    "iso:country":"AU",
    "sg:address":"Esk Forest Rd",
    "sg:city":"Esk",
    "sg:classifiers":[
        {
            "category":"Food & Beverages",
            "subcategory":"Farmers Market",
            "type":"Retail Goods"
        }
    ],
    "sg:phone":"+61 7 5424 1432",
    "sg:postcode":"4312",
    "sg:province":"QLD",
    "sg:tags":[
        "beekeeper"
    ],
    "wof:name":"Twilight Grove Farm Stay",
    "wof:placetype":"venue"
},
  "geometry": {"coordinates":[152.424591064,-27.2427997589],"type":"Point"}
}