{
  "type": "Feature",
  "properties": {
    "addr:full":"32 Beckman St Zillmere QLD 4034",
    "addr:housenumber":"32",
    "addr:postcode":"4034",
    "addr:street":"Beckman St",
    "iso:country":"AU",
    "sg:address":"32 Beckman St",
    "sg:city":"Zillmere",
    "sg:classifiers":[
        {
            "category":"Health Services",
            "subcategory":"Health Practitioner",
            "type":"Services"
        }
    ],
    "sg:phone":"+61 7 3265 5373",
    "sg:postcode":"4034",
    "sg:province":"QLD",
    "sg:tags":[
        "naturopath"
    ],
    "wof:name":"Joanne Davidson",
    "wof:placetype":"venue"
},
  "geometry": {"coordinates":[153.049576,-27.359056],"type":"Point"}
}