{
  "type": "Feature",
  "properties": {
    "addr:full":"301 Hanson Rd Wingfield SA 5013",
    "addr:housenumber":"301",
    "addr:postcode":"5013",
    "addr:street":"Hanson Rd",
    "iso:country":"AU",
    "sg:address":"301 Hanson Rd",
    "sg:city":"Wingfield",
    "sg:classifiers":[
        {
            "category":"Wholesale",
            "subcategory":"Metals & Minerals",
            "type":"Manufacturing & Wholesale Goods"
        }
    ],
    "sg:phone":"+61 8 8244 7666",
    "sg:postcode":"5013",
    "sg:province":"SA",
    "sg:tags":[
        "steel",
        "merchant"
    ],
    "wof:name":"Coil Steels",
    "wof:placetype":"venue"
},
  "geometry": {"coordinates":[138.54583740199999,-34.8416671753],"type":"Point"}
}