{
  "type": "Feature",
  "properties": {
    "addr:full":"Davidson Rd Yungaburra QLD 4872",
    "addr:postcode":"4872",
    "addr:street":"Davidson Rd",
    "iso:country":"AU",
    "sg:address":"Davidson Rd",
    "sg:city":"Yungaburra",
    "sg:classifiers":[
        {
            "category":"Communications",
            "subcategory":"News Services",
            "type":"Services"
        }
    ],
    "sg:phone":"+61 7 4095 3118",
    "sg:postcode":"4872",
    "sg:province":"QLD",
    "sg:tags":[
        "information",
        "tourist",
        "attractions"
    ],
    "wof:name":"Withersleigh Farmstay",
    "wof:placetype":"venue"
},
  "geometry": {"coordinates":[145.65928649899999,-17.1755447388],"type":"Point"}
}