{
  "type": "Feature",
  "properties": {
    "addr:full":"GPO Box 6535 Halifax St Adelaide SA 5000",
    "addr:postcode":"5000",
    "addr:street":"St",
    "iso:country":"AU",
    "sg:address":"GPO Box 6535 Halifax St",
    "sg:city":"Adelaide",
    "sg:classifiers":[
        {
            "category":"Government",
            "subcategory":"Fire Station",
            "type":"Public Place"
        }
    ],
    "sg:phone":"+61 8 8221 6083",
    "sg:postcode":"5000",
    "sg:province":"SA",
    "sg:tags":[
        "equipment",
        "protection",
        "consultant"
    ],
    "wof:name":"B Fire Safe Pty Ltd",
    "wof:placetype":"venue"
},
  "geometry": {"coordinates":[138.60061645499999,-34.9327926636],"type":"Point"}
}