{
  "type": "Feature",
  "properties": {
    "iso:country":"AU",
    "sg:address":"100 Murdoch Ave",
    "sg:city":"Murdoch",
    "sg:classifiers":[
        {
            "category":"Health Services",
            "subcategory":"Health Practitioner",
            "type":"Services"
        }
    ],
    "sg:phone":"+61 8 9366 1730",
    "sg:postcode":"6150",
    "sg:province":"WA",
    "sg:tags":[
        "physiotherapist"
    ],
    "wof:name":"Leo Ng",
    "wof:placetype":"venue"
},
  "geometry": {"coordinates":[115.842239,-32.068344],"type":"Point"}
}