{
  "type": "Feature",
  "properties": {
    "iso:country":"AU",
    "sg:address":"1/ 1 Bellamy St",
    "sg:city":"O'Connor",
    "sg:classifiers":[
        {
            "category":"Wholesale",
            "subcategory":"Machinery & Supplies",
            "type":"Manufacturing & Wholesale Goods"
        }
    ],
    "sg:phone":"+61 8 9331 3348",
    "sg:postcode":"6163",
    "sg:province":"WA",
    "sg:tags":[
        "bearing",
        "bushing"
    ],
    "wof:name":"Precise Motion Products",
    "wof:placetype":"venue"
},
  "geometry": {"coordinates":[115.799767,-32.062298],"type":"Point"}
}