{
  "type": "Feature",
  "properties": {
    "addr:full":"Unit 1b/ 14 Whyalla St Willetton WA 6155",
    "addr:housenumber":"unit 1b / 14",
    "addr:postcode":"6155",
    "addr:street":"Whyalla St",
    "iso:country":"AU",
    "sg:address":"Unit 1b/ 14 Whyalla St",
    "sg:city":"Willetton",
    "sg:classifiers":[
        {
            "category":"Banks & Credit Unions",
            "subcategory":"Bank",
            "type":"Services"
        }
    ],
    "sg:phone":"+61 8 9354 9911",
    "sg:postcode":"6155",
    "sg:province":"WA",
    "sg:tags":[
        "equipment",
        "sale",
        "point"
    ],
    "sg:website":"http://www.samfordsoftware.com.au",
    "wof:name":"On-Q Point Of Sale",
    "wof:placetype":"venue"
},
  "geometry": {"coordinates":[115.88282,-32.042076],"type":"Point"}
}