{
  "type": "Feature",
  "properties": {
    "addr:full":"110 Macfarlane Drv Minchinbury NSW 2770",
    "addr:housenumber":"110",
    "addr:postcode":"2770",
    "addr:street":"Macfarlane Drv",
    "iso:country":"AU",
    "sg:address":"110 Macfarlane Drv",
    "sg:city":"Minchinbury",
    "sg:classifiers":[
        {
            "category":"Education",
            "subcategory":"Kindergarten",
            "type":"Public Place"
        }
    ],
    "sg:phone":"+61 2 9675 2129",
    "sg:postcode":"2770",
    "sg:province":"NSW",
    "sg:tags":[
        "pre-schools"
    ],
    "wof:name":"Jiminey Cricket Long Day Care",
    "wof:placetype":"venue"
},
  "geometry": {"coordinates":[150.824417114,-33.7870254517],"type":"Point"}
}