{
  "type": "Feature",
  "properties": {
    "addr:full":"17 Adelaide St East Maitland NSW 2323",
    "addr:housenumber":"17",
    "addr:postcode":"2323",
    "addr:street":"Adelaide St",
    "iso:country":"AU",
    "sg:address":"17 Adelaide St",
    "sg:city":"East Maitland",
    "sg:classifiers":[
        {
            "category":"Home & Garden",
            "subcategory":"Building Materials",
            "type":"Retail Goods"
        }
    ],
    "sg:phone":"+61 2 4936 6123",
    "sg:postcode":"2323",
    "sg:province":"NSW",
    "sg:tags":[
        "lawn",
        "cutting",
        "maintenance"
    ],
    "wof:name":"SJ & LG Goodridge Mowing",
    "wof:placetype":"venue"
},
  "geometry": {"coordinates":[151.58914184599999,-32.7585220337],"type":"Point"}
}