{
  "type": "Feature",
  "properties": {
    "iso:country":"AU",
    "sg:address":"Unit 3/ 68 Ives St",
    "sg:city":"Murarrie",
    "sg:classifiers":[
        {
            "category":"Utilities",
            "subcategory":"Electric",
            "type":"Services"
        }
    ],
    "sg:phone":"+61 7 3907 8089",
    "sg:postcode":"4172",
    "sg:province":"QLD",
    "sg:tags":[
        "electrical",
        "contractor"
    ],
    "wof:name":"FR Innsol Electrical Pty Ltd",
    "wof:placetype":"venue"
},
  "geometry": {"coordinates":[153.09901428200001,-27.4608402252],"type":"Point"}
}