{
  "type": "Feature",
  "properties": {
    "iso:country":"AU",
    "sg:address":"47 Auburn St",
    "sg:city":"Wollongong",
    "sg:classifiers":[
        {
            "category":"Communications",
            "type":"Services"
        }
    ],
    "sg:phone":"+61 2 4226 5595",
    "sg:postcode":"2500",
    "sg:province":"NSW",
    "sg:tags":[
        "public",
        "system",
        "address"
    ],
    "wof:name":"Illawarra Production Services",
    "wof:placetype":"venue"
},
  "geometry": {"coordinates":[150.88884,-34.430969],"type":"Point"}
}