{
  "type": "Feature",
  "properties": {
    "addr:full":"24 Duyfken St Cairns QLD 4870",
    "addr:housenumber":"24",
    "addr:postcode":"4870",
    "addr:street":"Duyfken St",
    "iso:country":"AU",
    "sg:address":"24 Duyfken St",
    "sg:city":"Cairns",
    "sg:classifiers":[
        {
            "category":"Building & Trades",
            "subcategory":"Construction",
            "type":"Services"
        }
    ],
    "sg:phone":"+61 7 4051 0732",
    "sg:postcode":"4870",
    "sg:province":"QLD",
    "sg:tags":[
        "tennis court",
        "repair"
    ],
    "wof:name":"Grand Slam Court Constructions",
    "wof:placetype":"venue"
},
  "geometry": {"coordinates":[145.73666381800001,-17.0073623657],"type":"Point"}
}