{
  "type": "Feature",
  "properties": {
    "addr:full":"&#034;Oakfields&#034; Road Mail Cowell SA 5602",
    "addr:postcode":"5602",
    "addr:street":"034 Road",
    "iso:country":"AU",
    "sg:address":"&#034;Oakfields&#034; Road",
    "sg:city":"Mail Cowell",
    "sg:classifiers":[
        {
            "category":"Shopping",
            "subcategory":"Bicycles & Sporting Goods",
            "type":"Retail Goods"
        }
    ],
    "sg:phone":"+61 8 8628 5092",
    "sg:postcode":"5602",
    "sg:province":"SA",
    "sg:tags":[
        "trampoline"
    ],
    "wof:name":"Arrow Trampoline Products",
    "wof:placetype":"venue"
},
  "geometry": {"coordinates":[136.92486600000001,-33.683262],"type":"Point"}
}