{
  "type": "Feature",
  "properties": {
    "addr:full":"21 King St Grafton NSW 2460",
    "addr:housenumber":"21",
    "addr:postcode":"2460",
    "addr:street":"King St",
    "iso:country":"AU",
    "sg:address":"21 King St",
    "sg:city":"Grafton",
    "sg:classifiers":[
        {
            "category":"Professional",
            "subcategory":"Art Services",
            "type":"Services"
        }
    ],
    "sg:phone":"+61 2 6642 1105",
    "sg:postcode":"2460",
    "sg:province":"NSW",
    "sg:tags":[
        "picture",
        "frame",
        "framing"
    ],
    "wof:name":"Pretty & Nice",
    "wof:placetype":"venue"
},
  "geometry": {"coordinates":[152.93301391599999,-29.6891765594],"type":"Point"}
}