{
  "type": "Feature",
  "properties": {
    "addr:full":"Shp2/ 622 Wynnum Rd Morningside QLD 4170",
    "addr:housenumber":"622",
    "addr:postcode":"4170",
    "addr:street":"Wynnum Rd",
    "iso:country":"AU",
    "sg:address":"Shp2/ 622 Wynnum Rd",
    "sg:city":"Morningside",
    "sg:classifiers":[
        {
            "category":"Real Estate",
            "subcategory":"Real Estate Agent",
            "type":"Services"
        }
    ],
    "sg:phone":"+61 7 3899 8588",
    "sg:postcode":"4170",
    "sg:province":"QLD",
    "wof:name":"Brinckman Team",
    "wof:placetype":"venue"
},
  "geometry": {"coordinates":[153.071777344,-27.4680747986],"type":"Point"}
}