{
  "type": "Feature",
  "properties": {
    "addr:full":"U3/ 8 Dobra Rd Yangebup WA 6164",
    "addr:housenumber":"8",
    "addr:postcode":"6164",
    "addr:street":"U3 /;Dobra Rd",
    "iso:country":"AU",
    "sg:address":"U3/ 8 Dobra Rd",
    "sg:city":"Yangebup",
    "sg:classifiers":[
        {
            "category":"Food & Beverages",
            "subcategory":"Specialty",
            "type":"Retail Goods"
        }
    ],
    "sg:phone":"+61 8 9418 1568",
    "sg:postcode":"6164",
    "sg:province":"WA",
    "sg:tags":[
        "delicacy"
    ],
    "wof:name":"Chillin' Out In Wa",
    "wof:placetype":"venue"
},
  "geometry": {"coordinates":[115.796288,-32.116886],"type":"Point"}
}