{
  "type": "Feature",
  "properties": {
    "iso:country":"AU",
    "sg:address":"8 Campbell St",
    "sg:city":"Wallsend",
    "sg:classifiers":[
        {
            "category":"Personal",
            "type":"Services"
        }
    ],
    "sg:phone":"+61 2 9990 3175",
    "sg:postcode":"2287",
    "sg:province":"NSW",
    "sg:tags":[
        "reducing",
        "treatment",
        "weight"
    ],
    "wof:name":"Ms Louise Ridley",
    "wof:placetype":"venue"
},
  "geometry": {"coordinates":[151.67056274399999,-32.9038085938],"type":"Point"}
}