{
  "type": "Feature",
  "properties": {
    "addr:full":"Shop 4, 12 Leda Blv Morayfield QLD 4506",
    "addr:housenumber":"shop;12",
    "addr:postcode":"4506",
    "addr:street":"Leda Blv",
    "iso:country":"AU",
    "sg:address":"Shop 4, 12 Leda Blv",
    "sg:city":"Morayfield",
    "sg:classifiers":[
        {
            "category":"Education",
            "subcategory":"Vocational School",
            "type":"Public Place"
        }
    ],
    "sg:phone":"+61 1300 131 899",
    "sg:postcode":"4506",
    "sg:province":"QLD",
    "sg:tags":[
        "beauty"
    ],
    "wof:name":"Katrina's School Of Hair & Beauty",
    "wof:placetype":"venue"
},
  "geometry": {"coordinates":[152.94900512699999,-27.10414505],"type":"Point"}
}