{
  "type": "Feature",
  "properties": {
    "addr:full":"252 Kensington Rd Leabrook SA 5068",
    "addr:housenumber":"252",
    "addr:postcode":"5068",
    "addr:street":"Kensington Rd",
    "iso:country":"AU",
    "sg:address":"252 Kensington Rd",
    "sg:city":"Leabrook",
    "sg:classifiers":[
        {
            "category":"Health Services",
            "subcategory":"Chiropractor",
            "type":"Services"
        }
    ],
    "sg:phone":"+61 8 8364 5044",
    "sg:postcode":"5068",
    "sg:province":"SA",
    "wof:name":"Quigley Kate Dr",
    "wof:placetype":"venue"
},
  "geometry": {"coordinates":[138.65544128400001,-34.9260864258],"type":"Point"}
}