{
  "type": "Feature",
  "properties": {
    "addr:full":"Unit 3/9- 11 South St Rydalmere NSW 2116",
    "addr:housenumber":"11",
    "addr:postcode":"2116",
    "addr:street":"South St",
    "iso:country":"AU",
    "sg:address":"Unit 3/9- 11 South St",
    "sg:city":"Rydalmere",
    "sg:classifiers":[
        {
            "category":"Wholesale",
            "subcategory":"Vending Machines",
            "type":"Manufacturing & Wholesale Goods"
        }
    ],
    "sg:phone":"+61 2 9684 2400",
    "sg:postcode":"2116",
    "sg:province":"NSW",
    "sg:tags":[
        "engraving",
        "accessory"
    ],
    "wof:name":"New Hermes International Ltd",
    "wof:placetype":"venue"
},
  "geometry": {"coordinates":[151.01136779800001,-33.8329658508],"type":"Point"}
}