{
  "type": "Feature",
  "properties": {
    "addr:full":"295 Woodville Rd Guildford NSW 2161",
    "addr:housenumber":"295",
    "addr:postcode":"2161",
    "addr:street":"Woodville Rd",
    "iso:country":"AU",
    "sg:address":"295 Woodville Rd",
    "sg:city":"Guildford",
    "sg:classifiers":[
        {
            "category":"Autos & Motor Vehicles",
            "subcategory":"Fuel & Gas Station",
            "type":"Retail Goods"
        }
    ],
    "sg:phone":"+61 2 9892 1848",
    "sg:postcode":"2161",
    "sg:province":"NSW",
    "wof:name":"Caltex Ampol Service Station",
    "wof:placetype":"venue"
},
  "geometry": {"coordinates":[150.996749878,-33.8506851196],"type":"Point"}
}