{
  "type": "Feature",
  "properties": {
    "iso:country":"AU",
    "sg:address":"65 Coppards Rd",
    "sg:city":"Newcomb",
    "sg:classifiers":[
        {
            "category":"Retail",
            "subcategory":"Veterinary Services",
            "type":"Services"
        }
    ],
    "sg:phone":"+61 3 5248 2009",
    "sg:postcode":"3219",
    "sg:province":"VIC",
    "sg:tags":[
        "surgeon"
    ],
    "wof:name":"Polly Schofield-Smith",
    "wof:placetype":"venue"
},
  "geometry": {"coordinates":[144.40269470199999,-38.1732826233],"type":"Point"}
}