{
  "type": "Feature",
  "properties": {
    "iso:country":"AU",
    "sg:address":"129 Queensbridge St",
    "sg:city":"Southbank",
    "sg:classifiers":[
        {
            "category":"Professional",
            "subcategory":"Art Services",
            "type":"Services"
        }
    ],
    "sg:phone":"+61 3 9690 0905",
    "sg:postcode":"3006",
    "sg:province":"VIC",
    "sg:tags":[
        "graphic",
        "designer"
    ],
    "wof:name":"Disegno Group Pty Ltd",
    "wof:placetype":"venue"
},
  "geometry": {"coordinates":[144.96043395999999,-37.825302124],"type":"Point"}
}