{
  "type": "Feature",
  "properties": {
    "addr:full":"105 Ford St Ganmain NSW 2702",
    "addr:housenumber":"105",
    "addr:postcode":"2702",
    "addr:street":"Ford St",
    "iso:country":"AU",
    "sg:address":"105 Ford St",
    "sg:city":"Ganmain",
    "sg:classifiers":[
        {
            "category":"Food & Beverages",
            "subcategory":"Bakery",
            "type":"Retail Goods"
        }
    ],
    "sg:phone":"+61 2 6927 6401",
    "sg:postcode":"2702",
    "sg:province":"NSW",
    "sg:tags":[
        "baker"
    ],
    "wof:name":"Ganmain Bakery",
    "wof:placetype":"venue"
},
  "geometry": {"coordinates":[147.03939819300001,-34.7924537659],"type":"Point"}
}