{
  "type": "Feature",
  "properties": {
    "addr:full":"52 Lyndhurst Rd Seaford SA 5169",
    "addr:housenumber":"52",
    "addr:postcode":"5169",
    "addr:street":"Lyndhurst Rd",
    "iso:country":"AU",
    "sg:address":"52 Lyndhurst Rd",
    "sg:city":"Seaford",
    "sg:classifiers":[
        {
            "category":"Education",
            "subcategory":"Dance Studio",
            "type":"Public Place"
        }
    ],
    "sg:phone":"+61 8 8386 2593",
    "sg:postcode":"5169",
    "sg:province":"SA",
    "sg:tags":[
        "venue",
        "tuition"
    ],
    "wof:name":"Adelaide Bluegrass Cloggers",
    "wof:placetype":"venue"
},
  "geometry": {"coordinates":[138.47264099099999,-35.1805076599],"type":"Point"}
}