{
  "type": "Feature",
  "properties": {
    "addr:full":"U7/ 100 Long St Smithfield NSW 2164",
    "addr:housenumber":"100",
    "addr:postcode":"2164",
    "addr:street":"U7 /;Long St",
    "iso:country":"AU",
    "sg:address":"U7/ 100 Long St",
    "sg:city":"Smithfield",
    "sg:classifiers":[
        {
            "category":"Manufacturing",
            "subcategory":"Metals",
            "type":"Manufacturing & Wholesale Goods"
        }
    ],
    "sg:phone":"+61 2 9609 3159",
    "sg:postcode":"2164",
    "sg:province":"NSW",
    "sg:tags":[
        "fabricator",
        "aluminium"
    ],
    "wof:name":"K & S Metal Fabrication",
    "wof:placetype":"venue"
},
  "geometry": {"coordinates":[150.93356323200001,-33.8416862488],"type":"Point"}
}