{
  "type": "Feature",
  "properties": {
    "addr:full":"501 Great Eastern Highway Redcliffe WA 6104",
    "addr:housenumber":"501",
    "addr:postcode":"6104",
    "addr:street":"Great Eastern Highway",
    "iso:country":"AU",
    "sg:address":"501 Great Eastern Highway",
    "sg:city":"Redcliffe",
    "sg:classifiers":[
        {
            "category":"Mining & Drilling",
            "type":"Manufacturing & Wholesale Goods"
        }
    ],
    "sg:phone":"+61 8 9475 3800",
    "sg:postcode":"6104",
    "sg:province":"WA",
    "sg:tags":[
        "equipment",
        "quarrying",
        "supply"
    ],
    "wof:name":"ET Underground Mining Hire & Sales",
    "wof:placetype":"venue"
},
  "geometry": {"coordinates":[115.951141357,-31.9264507294],"type":"Point"}
}