{
  "type": "Feature",
  "properties": {
    "iso:country":"AU",
    "sg:address":"Level 2, 17-21 Hunter St",
    "sg:city":"Parramatta",
    "sg:classifiers":[
        {
            "category":"Health Services",
            "subcategory":"Doctor",
            "type":"Services"
        }
    ],
    "sg:phone":"+61 2 9635 0663",
    "sg:postcode":"2150",
    "sg:province":"NSW",
    "sg:tags":[
        "medical",
        "practitioner"
    ],
    "sg:website":"http://www.huntereye.com.au",
    "wof:name":"Hunter Street Eye Specialists Thomson, Sumich & Associates",
    "wof:placetype":"venue"
},
  "geometry": {"coordinates":[151.03553772000001,-33.8424835205],"type":"Point"}
}