{
  "type": "Feature",
  "properties": {
    "addr:full":"483 Kingsford Smith Drv Hamilton QLD 4007",
    "addr:housenumber":"483",
    "addr:postcode":"4007",
    "addr:street":"Kingsford Smith Drv",
    "iso:country":"AU",
    "sg:address":"483 Kingsford Smith Drv",
    "sg:city":"Hamilton",
    "sg:classifiers":[
        {
            "category":"Building & Trades",
            "subcategory":"Cleaning & Sanitation",
            "type":"Services"
        }
    ],
    "sg:phone":"+61 7 3268 6632",
    "sg:postcode":"4007",
    "sg:province":"QLD",
    "sg:tags":[
        "industrial",
        "commercial",
        "contractor"
    ],
    "wof:name":"Kitchen & Oven Cleaners",
    "wof:placetype":"venue"
},
  "geometry": {"coordinates":[153.06561300000001,-27.439051],"type":"Point"}
}