{
  "type": "Feature",
  "properties": {
    "addr:full":"50 - 56 Mellor St Gympie QLD 4570",
    "addr:housenumber":"56",
    "addr:postcode":"4570",
    "addr:street":"Mellor St",
    "iso:country":"AU",
    "sg:address":"50 - 56 Mellor St",
    "sg:city":"Gympie",
    "sg:classifiers":[
        {
            "category":"Autos & Motor Vehicles",
            "subcategory":"Auto Supplies",
            "type":"Retail Goods"
        }
    ],
    "sg:phone":"+61 7 5482 6633",
    "sg:postcode":"4570",
    "sg:province":"QLD",
    "sg:tags":[
        "battery",
        "automotive"
    ],
    "wof:name":"Beaurepaires",
    "wof:placetype":"venue"
},
  "geometry": {"coordinates":[152.66732788100001,-26.1880340576],"type":"Point"}
}