{
  "type": "Feature",
  "properties": {
    "addr:full":"4 Ballinderry St Everton Park QLD 4053",
    "addr:housenumber":"4",
    "addr:postcode":"4053",
    "addr:street":"Ballinderry St",
    "iso:country":"AU",
    "sg:address":"4 Ballinderry St",
    "sg:city":"Everton Park",
    "sg:classifiers":[
        {
            "category":"Building & Trades",
            "subcategory":"Construction",
            "type":"Services"
        }
    ],
    "sg:phone":"+61 7 3354 2448",
    "sg:postcode":"4053",
    "sg:province":"QLD",
    "sg:tags":[
        "industrial",
        "commercial",
        "air conditioning"
    ],
    "wof:name":"Aurora Air Conditioning",
    "wof:placetype":"venue"
},
  "geometry": {"coordinates":[152.981964111,-27.3977508545],"type":"Point"}
}