{
  "type": "Feature",
  "properties": {
    "addr:full":"20 Lennox St Parramatta NSW 2150",
    "addr:housenumber":"20",
    "addr:postcode":"2150",
    "addr:street":"Lennox St",
    "iso:country":"AU",
    "sg:address":"20 Lennox St",
    "sg:city":"Parramatta",
    "sg:classifiers":[
        {
            "category":"Utilities",
            "subcategory":"Electric",
            "type":"Services"
        }
    ],
    "sg:phone":"+61 412 910 980",
    "sg:postcode":"2150",
    "sg:province":"NSW",
    "sg:tags":[
        "electrical",
        "contractor"
    ],
    "wof:name":"Safari Electrical Services",
    "wof:placetype":"venue"
},
  "geometry": {"coordinates":[150.99783325199999,-33.7829322815],"type":"Point"}
}