{
  "type": "Feature",
  "properties": {
    "addr:full":"11 Beerwah Pde Beerwah QLD 4519",
    "addr:housenumber":"11",
    "addr:postcode":"4519",
    "addr:street":"Beerwah Pde",
    "iso:country":"AU",
    "sg:address":"11 Beerwah Pde",
    "sg:city":"Beerwah",
    "sg:classifiers":[
        {
            "category":"Retail",
            "subcategory":"Repair Shop",
            "type":"Services"
        }
    ],
    "sg:phone":"+61 7 5494 6040",
    "sg:postcode":"4519",
    "sg:province":"QLD",
    "sg:tags":[
        "windscreen"
    ],
    "wof:name":"Beerwah Windscreens",
    "wof:placetype":"venue"
},
  "geometry": {"coordinates":[152.95872499999999,-26.853794],"type":"Point"}
}