{
  "type": "Feature",
  "properties": {
    "addr:full":"40 Anderson Rd Sunshine VIC 3020",
    "addr:housenumber":"40",
    "addr:postcode":"3020",
    "addr:street":"Anderson Rd",
    "iso:country":"AU",
    "sg:address":"40 Anderson Rd",
    "sg:city":"Sunshine",
    "sg:classifiers":[
        {
            "category":"Travel",
            "subcategory":"Hostel",
            "type":"Entertainment"
        }
    ],
    "sg:phone":"+61 3 8311 8888",
    "sg:postcode":"3020",
    "sg:province":"VIC",
    "sg:tags":[
        "home"
    ],
    "wof:name":"Western Gardens Nursing Home & Hostel",
    "wof:placetype":"venue"
},
  "geometry": {"coordinates":[144.82720900000001,-37.791824],"type":"Point"}
}