{
  "type": "Feature",
  "properties": {
    "iso:country":"AU",
    "sg:address":"40 Anderson Rd",
    "sg:city":"Sunshine",
    "sg:classifiers":[
        {
            "category":"Travel",
            "subcategory":"Hostel",
            "type":"Entertainment"
        }
    ],
    "sg:phone":"+61 3 8311 8888",
    "sg:postcode":"3020",
    "sg:province":"VIC",
    "sg:tags":[
        "home"
    ],
    "wof:name":"Western Gardens Nursing Home & Hostel",
    "wof:placetype":"venue"
},
  "geometry": {"coordinates":[144.827209,-37.791824],"type":"Point"}
}