{
  "type": "Feature",
  "properties": {
    "iso:country":"AU",
    "sg:address":"Ste 708/ 45 Market St",
    "sg:city":"Sydney",
    "sg:classifiers":[
        {
            "category":"Shopping",
            "type":"Retail Goods"
        }
    ],
    "sg:phone":"+61 2 9264 1619",
    "sg:postcode":"2000",
    "sg:province":"NSW",
    "sg:tags":[
        "clearance",
        "factory",
        "outlet"
    ],
    "wof:name":"Julias Perfumery",
    "wof:placetype":"venue"
},
  "geometry": {"coordinates":[151.207275391,-33.8709106445],"type":"Point"}
}