{
  "type": "Feature",
  "properties": {
    "addr:full":"42 marchamley St Carlisle WA 6101",
    "addr:housenumber":"42",
    "addr:postcode":"6101",
    "addr:street":"Marchamley St",
    "iso:country":"AU",
    "sg:address":"42 marchamley St",
    "sg:city":"Carlisle",
    "sg:classifiers":[
        {
            "category":"Retail",
            "subcategory":"Repair Shop",
            "type":"Services"
        }
    ],
    "sg:phone":"+61 8 9209 2692",
    "sg:postcode":"6101",
    "sg:province":"WA",
    "sg:tags":[
        "upholsterer"
    ],
    "wof:name":"Tru-Style Furniture",
    "wof:placetype":"venue"
},
  "geometry": {"coordinates":[115.918426514,-31.9733028412],"type":"Point"}
}