{
  "type": "Feature",
  "properties": {
    "iso:country":"AU",
    "sg:address":"33 Fitzgibbon La",
    "sg:city":"Rosemeadow",
    "sg:classifiers":[
        {
            "category":"Health Services",
            "subcategory":"Doctor",
            "type":"Services"
        }
    ],
    "sg:phone":"+61 2 4621 4397",
    "sg:postcode":"2560",
    "sg:province":"NSW",
    "sg:tags":[
        "medical",
        "practitioner"
    ],
    "wof:name":"Sydney Pathology Services Pty Ltd",
    "wof:placetype":"venue"
},
  "geometry": {"coordinates":[150.79788207999999,-34.1015815735],"type":"Point"}
}