{
  "type": "Feature",
  "properties": {
    "iso:country":"AU",
    "sg:address":"28 Rushton St",
    "sg:city":"Burswood",
    "sg:classifiers":[
        {
            "category":"Mining & Drilling",
            "type":"Manufacturing & Wholesale Goods"
        }
    ],
    "sg:phone":"+61 8 9472 0597",
    "sg:postcode":"6100",
    "sg:province":"WA",
    "sg:tags":[
        "geologist"
    ],
    "wof:name":"Geotask",
    "wof:placetype":"venue"
},
  "geometry": {"coordinates":[115.89527130099999,-31.9696750641],"type":"Point"}
}