{
  "type": "Feature",
  "properties": {
    "addr:full":"Shop 1, 102 Herbert St Ingham QLD 4850",
    "addr:housenumber":"shop 1 102",
    "addr:postcode":"4850",
    "addr:street":"Herbert St",
    "iso:country":"AU",
    "sg:address":"Shop 1, 102 Herbert St",
    "sg:city":"Ingham",
    "sg:classifiers":[
        {
            "category":"Fast Food",
            "type":"Food & Drink"
        }
    ],
    "sg:phone":"+61 7 4776 3550",
    "sg:postcode":"4850",
    "sg:province":"QLD",
    "sg:tags":[
        "away",
        "take"
    ],
    "wof:name":"Eagle Boys Pizza",
    "wof:placetype":"venue"
},
  "geometry": {"coordinates":[146.161575317,-18.6469249725],"type":"Point"}
}