{
  "type": "Feature",
  "properties": {
    "addr:full":"Monkey Mia Rd Shark Bay WA 6537",
    "addr:postcode":"6537",
    "addr:street":"Monkey Mia Rd",
    "iso:country":"AU",
    "sg:address":"Monkey Mia Rd",
    "sg:city":"Shark Bay",
    "sg:classifiers":[
        {
            "category":"Communications",
            "subcategory":"News Services",
            "type":"Services"
        }
    ],
    "sg:phone":"+61 8 9948 1320",
    "sg:postcode":"6537",
    "sg:province":"WA",
    "sg:tags":[
        "information",
        "tourist",
        "attractions"
    ],
    "wof:name":"Monkey Mia Dolphin Resort",
    "wof:placetype":"venue"
},
  "geometry": {"coordinates":[113.54242706300001,-25.926279068],"type":"Point"}
}