{
  "type": "Feature",
  "properties": {
    "addr:full":"1 Scenic Drv Nowra NSW 2541",
    "addr:housenumber":"1",
    "addr:postcode":"2541",
    "addr:street":"Scenic Drv",
    "iso:country":"AU",
    "sg:address":"1 Scenic Drv",
    "sg:city":"Nowra",
    "sg:classifiers":[
        {
            "category":"Cafe",
            "type":"Food & Drink"
        }
    ],
    "sg:phone":"+61 2 4421 2044",
    "sg:postcode":"2541",
    "sg:province":"NSW",
    "wof:name":"The Waters Edge",
    "wof:placetype":"venue"
},
  "geometry": {"coordinates":[150.60040283199999,-34.8660964966],"type":"Point"}
}