{
  "type": "Feature",
  "properties": {
    "addr:full":"1/ 219 Victoria Rd Gladesville NSW 2111",
    "addr:housenumber":"/ 219",
    "addr:postcode":"2111",
    "addr:street":"Victoria Rd",
    "iso:country":"AU",
    "sg:address":"1/ 219 Victoria Rd",
    "sg:city":"Gladesville",
    "sg:classifiers":[
        {
            "category":"Professional",
            "subcategory":"Lawyer & Legal Services",
            "type":"Services"
        }
    ],
    "sg:phone":"+61 2 9887 2888",
    "sg:postcode":"2111",
    "sg:province":"NSW",
    "sg:tags":[
        "wills",
        "probate",
        "estate"
    ],
    "wof:name":"Winston Readford",
    "wof:placetype":"venue"
},
  "geometry": {"coordinates":[151.12709045400001,-33.8321342468],"type":"Point"}
}