{
  "type": "Feature",
  "properties": {
    "addr:full":"5 F/ 401 Sussex St Haymarket NSW 2000",
    "addr:housenumber":"5 f / 401",
    "addr:postcode":"2000",
    "addr:street":"Sussex St",
    "iso:country":"AU",
    "sg:address":"5 F/ 401 Sussex St",
    "sg:city":"Haymarket",
    "sg:classifiers":[
        {
            "category":"Health Services",
            "subcategory":"Doctor",
            "type":"Services"
        }
    ],
    "sg:phone":"+61 2 9281 9133",
    "sg:postcode":"2000",
    "sg:province":"NSW",
    "sg:tags":[
        "medical",
        "practitioner"
    ],
    "wof:name":"Tang Georgiana Dr",
    "wof:placetype":"venue"
},
  "geometry": {"coordinates":[151.20463562,-33.8782501221],"type":"Point"}
}