{
  "type": "Feature",
  "properties": {
    "iso:country":"AU",
    "sg:address":"1st Floor Main St Arcade 85 Lake St",
    "sg:city":"Cairns",
    "sg:classifiers":[
        {
            "category":"Health Services",
            "subcategory":"Dentist",
            "type":"Services"
        }
    ],
    "sg:phone":"+61 7 4051 2142",
    "sg:postcode":"4870",
    "sg:province":"QLD",
    "wof:name":"Emery Angela Dr",
    "wof:placetype":"venue"
},
  "geometry": {"coordinates":[145.776412964,-16.9230213165],"type":"Point"}
}