{
  "type": "Feature",
  "properties": {
    "addr:full":"5 Provincial St Auburn NSW 2144",
    "addr:housenumber":"5",
    "addr:postcode":"2144",
    "addr:street":"Provincial St",
    "iso:country":"AU",
    "sg:address":"5 Provincial St",
    "sg:city":"Auburn",
    "sg:classifiers":[
        {
            "category":"Home & Garden",
            "subcategory":"Building Materials",
            "type":"Retail Goods"
        }
    ],
    "sg:phone":"+61 418 459 573",
    "sg:postcode":"2144",
    "sg:province":"NSW",
    "sg:tags":[
        "restoration",
        "supply"
    ],
    "wof:name":"Heritage Stonemasonry",
    "wof:placetype":"venue"
},
  "geometry": {"coordinates":[151.028808594,-33.8561515808],"type":"Point"}
}