{
  "type": "Feature",
  "properties": {
    "addr:full":"39 Beaumont Drv Lismore NSW 2480",
    "addr:housenumber":"39",
    "addr:postcode":"2480",
    "addr:street":"Beaumont Drv",
    "iso:country":"AU",
    "sg:address":"39 Beaumont Drv",
    "sg:city":"Lismore",
    "sg:classifiers":[
        {
            "category":"Building & Trades",
            "subcategory":"Construction",
            "type":"Services"
        }
    ],
    "sg:phone":"+61 407 728 224",
    "sg:postcode":"2480",
    "sg:province":"NSW",
    "sg:tags":[
        "earth",
        "excavating",
        "moving",
        "contractor"
    ],
    "wof:name":"Limited Access Earthworx",
    "wof:placetype":"venue"
},
  "geometry": {"coordinates":[153.279495239,-28.8287162781],"type":"Point"}
}