{
  "type": "Feature",
  "properties": {
    "addr:full":"238 Gilmore Rd Berrinba QLD 4117",
    "addr:housenumber":"238",
    "addr:postcode":"4117",
    "addr:street":"Gilmore Rd",
    "iso:country":"AU",
    "sg:address":"238 Gilmore Rd",
    "sg:city":"Berrinba",
    "sg:classifiers":[
        {
            "category":"Building & Trades",
            "subcategory":"Equipment Rental",
            "type":"Services"
        }
    ],
    "sg:phone":"+61 7 3808 6716",
    "sg:postcode":"4117",
    "sg:province":"QLD",
    "sg:tags":[
        "crane",
        "hire"
    ],
    "wof:name":"Skylift Services Pty Ltd",
    "wof:placetype":"venue"
},
  "geometry": {"coordinates":[153.082275391,-27.6545562744],"type":"Point"}
}