{
  "type": "Feature",
  "properties": {
    "addr:full":"14 Paula Ave Windsor Gardens SA 5087",
    "addr:housenumber":"14",
    "addr:postcode":"5087",
    "addr:street":"Paula Ave",
    "iso:country":"AU",
    "sg:address":"14 Paula Ave",
    "sg:city":"Windsor Gardens",
    "sg:classifiers":[
        {
            "category":"Retail",
            "subcategory":"Car Wash",
            "type":"Services"
        }
    ],
    "sg:phone":"+61 8 8369 0777",
    "sg:postcode":"5087",
    "sg:province":"SA",
    "sg:tags":[
        "truck",
        "cleaning"
    ],
    "wof:name":"Big Boyz Toyz",
    "wof:placetype":"venue"
},
  "geometry": {"coordinates":[138.65017700199999,-34.8631401062],"type":"Point"}
}