{
  "type": "Feature",
  "properties": {
    "addr:full":"2 Parker St Quairading WA 6383",
    "addr:housenumber":"2",
    "addr:postcode":"6383",
    "addr:street":"Parker St",
    "iso:country":"AU",
    "sg:address":"2 Parker St",
    "sg:city":"Quairading",
    "sg:classifiers":[
        {
            "category":"Retail",
            "subcategory":"Auto Repair",
            "type":"Services"
        }
    ],
    "sg:phone":"+61 8 9645 1179",
    "sg:postcode":"6383",
    "sg:province":"WA",
    "sg:tags":[
        "beater",
        "painter",
        "panel"
    ],
    "wof:name":"Quairading Smash Repairs",
    "wof:placetype":"venue"
},
  "geometry": {"coordinates":[117.396362,-32.012085],"type":"Point"}
}