{
  "type": "Feature",
  "properties": {
    "addr:full":"42 Prospect St Fortitude Valley QLD 4006",
    "addr:housenumber":"42",
    "addr:postcode":"4006",
    "addr:street":"Prospect St",
    "iso:country":"AU",
    "sg:address":"42 Prospect St",
    "sg:city":"Fortitude Valley",
    "sg:classifiers":[
        {
            "category":"Building & Trades",
            "subcategory":"Landscaping Services",
            "type":"Services"
        }
    ],
    "sg:phone":"+61 439 451 683",
    "sg:postcode":"4006",
    "sg:province":"QLD",
    "sg:tags":[
        "designer",
        "landscape",
        "contractor"
    ],
    "wof:name":"Landscape Network",
    "wof:placetype":"venue"
},
  "geometry": {"coordinates":[153.038864136,-27.4503974915],"type":"Point"}
}