{
  "type": "Feature",
  "properties": {
    "addr:full":"29 Buderim St Currimundi QLD 4551",
    "addr:housenumber":"29",
    "addr:postcode":"4551",
    "addr:street":"Buderim St",
    "iso:country":"AU",
    "sg:address":"29 Buderim St",
    "sg:city":"Currimundi",
    "sg:classifiers":[
        {
            "category":"Education",
            "subcategory":"Kindergarten",
            "type":"Public Place"
        }
    ],
    "sg:phone":"+61 7 5492 6688",
    "sg:postcode":"4551",
    "sg:province":"QLD",
    "sg:tags":[
        "pre-schools"
    ],
    "wof:name":"Currimundi Childcare Centre",
    "wof:placetype":"venue"
},
  "geometry": {"coordinates":[153.13418579099999,-26.7767543793],"type":"Point"}
}