{
  "type": "Feature",
  "properties": {
    "iso:country":"AU",
    "sg:address":"12a Carlow St",
    "sg:city":"North Sydney",
    "sg:classifiers":[
        {
            "category":"Real Estate",
            "subcategory":"Architect",
            "type":"Services"
        }
    ],
    "sg:phone":"+61 2 9925 0104",
    "sg:postcode":"2060",
    "sg:province":"NSW",
    "wof:name":"Hugh Slatyer & Associates Architects",
    "wof:placetype":"venue"
},
  "geometry": {"coordinates":[151.206863403,-33.8304862976],"type":"Point"}
}