{
  "type": "Feature",
  "properties": {
    "iso:country":"AU",
    "sg:address":"PO Box 1302",
    "sg:city":"Upwey",
    "sg:classifiers":[
        {
            "category":"Professional",
            "subcategory":"Art Services",
            "type":"Services"
        }
    ],
    "sg:phone":"+61 425 711 243",
    "sg:postcode":"3158",
    "sg:province":"VIC",
    "sg:tags":[
        "decorator",
        "painter"
    ],
    "wof:name":"Michael Dede Painting & Decorating",
    "wof:placetype":"venue"
},
  "geometry": {"coordinates":[145.329956055,-37.9020690918],"type":"Point"}
}