{
  "type": "Feature",
  "properties": {
    "iso:country":"AU",
    "sg:address":"358 Bay Rd",
    "sg:city":"Cheltenham",
    "sg:classifiers":[
        {
            "category":"Personal",
            "subcategory":"Beauty Salon",
            "type":"Services"
        }
    ],
    "sg:phone":"+61 3 9584 6032",
    "sg:postcode":"3192",
    "sg:province":"VIC",
    "sg:tags":[
        "hairdresser"
    ],
    "wof:name":"Anndez Reflections Hairdressing",
    "wof:placetype":"venue"
},
  "geometry": {"coordinates":[145.04417419399999,-37.9566078186],"type":"Point"}
}