{
  "type": "Feature",
  "properties": {
    "iso:country":"AU",
    "sg:address":"8 William St",
    "sg:city":"Morphett Vale",
    "sg:classifiers":[
        {
            "category":"Professional",
            "subcategory":"Art Services",
            "type":"Services"
        }
    ],
    "sg:phone":"+61 8 8186 2257",
    "sg:postcode":"5162",
    "sg:province":"SA",
    "sg:tags":[
        "picture",
        "frame",
        "framing"
    ],
    "wof:name":"The Old School Custom Picture Framing",
    "wof:placetype":"venue"
},
  "geometry": {"coordinates":[138.52423095699999,-35.1225852966],"type":"Point"}
}