{
  "type": "Feature",
  "properties": {
    "addr:full":"Dayrell Rd Nowergup WA 6032",
    "addr:postcode":"6032",
    "addr:street":"Dayrell Rd",
    "iso:country":"AU",
    "sg:address":"Dayrell Rd",
    "sg:city":"Nowergup",
    "sg:classifiers":[
        {
            "category":"Recreation",
            "subcategory":"Fishing",
            "type":"Entertainment"
        }
    ],
    "sg:phone":"+61 8 9407 4433",
    "sg:postcode":"6032",
    "sg:province":"WA",
    "sg:tags":[
        "trip"
    ],
    "wof:name":"Crystal Springs",
    "wof:placetype":"venue"
},
  "geometry": {"coordinates":[115.76011657700001,-31.6600112915],"type":"Point"}
}