{
  "type": "Feature",
  "properties": {
    "iso:country":"AU",
    "sg:address":"418 Payneham Rd",
    "sg:city":"Glynde",
    "sg:classifiers":[
        {
            "category":"Food & Beverages",
            "subcategory":"Supermarket",
            "type":"Retail Goods"
        }
    ],
    "sg:phone":"+61 8 8336 5108",
    "sg:postcode":"5070",
    "sg:province":"SA",
    "sg:tags":[
        "grocery",
        "store"
    ],
    "wof:name":"Welcome Mart Supermarkets",
    "wof:placetype":"venue"
},
  "geometry": {"coordinates":[138.648895264,-34.8926124573],"type":"Point"}
}