{
  "type": "Feature",
  "properties": {
    "iso:country":"AU",
    "sg:address":"207 Hamilton Rd",
    "sg:city":"Wavell Heights",
    "sg:classifiers":[
        {
            "category":"Professional",
            "subcategory":"Secretarial Services",
            "type":"Services"
        }
    ],
    "sg:phone":"+61 7 3256 9550",
    "sg:postcode":"4012",
    "sg:province":"QLD",
    "sg:tags":[
        "typing"
    ],
    "wof:name":"Secretarial Assistance",
    "wof:placetype":"venue"
},
  "geometry": {"coordinates":[153.04684448200001,-27.3880805969],"type":"Point"}
}