{
  "type": "Feature",
  "properties": {
    "addr:full":"48/ 62-70 Davies Rd Claremont WA 6010",
    "addr:housenumber":"48 / 62-70",
    "addr:postcode":"6010",
    "addr:street":"Davies Rd",
    "iso:country":"AU",
    "sg:address":"48/ 62-70 Davies Rd",
    "sg:city":"Claremont",
    "sg:classifiers":[
        {
            "category":"Autos & Motor Vehicles",
            "subcategory":"Boat Sales",
            "type":"Retail Goods"
        }
    ],
    "sg:phone":"+61 8 9384 2777",
    "sg:postcode":"6010",
    "sg:province":"WA",
    "sg:tags":[
        "equipment",
        "yacht"
    ],
    "wof:name":"SeaRoom",
    "wof:placetype":"venue"
},
  "geometry": {"coordinates":[115.781478882,-31.9764175415],"type":"Point"}
}