{
  "type": "Feature",
  "properties": {
    "addr:full":"Lot 100 Sandy Creek Rd Riddells Creek VIC 3431",
    "addr:postcode":"3431",
    "addr:street":"Sandy Creek Rd",
    "iso:country":"AU",
    "sg:address":"Lot 100 Sandy Creek Rd",
    "sg:city":"Riddells Creek",
    "sg:classifiers":[
        {
            "category":"Retail",
            "subcategory":"Driving School",
            "type":"Services"
        }
    ],
    "sg:phone":"+61 408 357 241",
    "sg:postcode":"3431",
    "sg:province":"VIC",
    "wof:name":"A-One Driving School",
    "wof:placetype":"venue"
},
  "geometry": {"coordinates":[144.68081665,-37.447353363],"type":"Point"}
}