{
  "type": "Feature",
  "properties": {
    "iso:country":"AU",
    "sg:address":"23 Clayton St",
    "sg:city":"Bellevue",
    "sg:phone":"+61 1800 999 599",
    "sg:postcode":"6056",
    "sg:province":"WA",
    "sg:website":"http://www.pioneertanks.com.au",
    "wof:name":"Pioneer Water Tanks (Australia 94) Pty Ltd",
    "wof:placetype":"venue"
},
  "geometry": {"coordinates":[116.01953125,-31.8986339569],"type":"Point"}
}