{
  "type": "Feature",
  "properties": {
    "iso:country":"AU",
    "sg:address":"Warbrook Rd",
    "sg:city":"Bullsbrook East",
    "sg:classifiers":[
        {
            "category":"Building & Trades",
            "subcategory":"Plumbing",
            "type":"Services"
        }
    ],
    "sg:phone":"+61 438 711 133",
    "sg:postcode":"6084",
    "sg:province":"WA",
    "sg:tags":[
        "plumber",
        "gasfitters"
    ],
    "wof:name":"Swan Valley Plumbing & Gas",
    "wof:placetype":"venue"
},
  "geometry": {"coordinates":[116.03301239,-31.7126083374],"type":"Point"}
}