{
  "type": "Feature",
  "properties": {
    "iso:country":"AU",
    "sg:address":"38 Frances St",
    "sg:city":"South Wentworthville",
    "sg:classifiers":[
        {
            "category":"Professional",
            "subcategory":"Art Services",
            "type":"Services"
        }
    ],
    "sg:phone":"+61 438 204 346",
    "sg:postcode":"2145",
    "sg:province":"NSW",
    "sg:tags":[
        "decorator",
        "painter"
    ],
    "wof:name":"Adecor Painting Services",
    "wof:placetype":"venue"
},
  "geometry": {"coordinates":[150.976196289,-33.8236427307],"type":"Point"}
}