{
  "type": "Feature",
  "properties": {
    "iso:country":"AU",
    "sg:address":"21 Sangster Pl",
    "sg:city":"Wanniassa",
    "sg:classifiers":[
        {
            "category":"Food & Beverages",
            "subcategory":"Bakery",
            "type":"Retail Goods"
        }
    ],
    "sg:phone":"+61 2 6231 2913",
    "sg:postcode":"2903",
    "sg:province":"ACT",
    "sg:tags":[
        "baker"
    ],
    "wof:name":"Vina Bake House",
    "wof:placetype":"venue"
},
  "geometry": {"coordinates":[149.086303711,-35.3915672302],"type":"Point"}
}