{
  "type": "Feature",
  "properties": {
    "addr:full":"PO Box 152 Pomona QLD 4568",
    "addr:postcode":"4568",
    "iso:country":"AU",
    "sg:address":"PO Box 152",
    "sg:city":"Pomona",
    "sg:classifiers":[
        {
            "category":"Communications",
            "type":"Services"
        }
    ],
    "sg:phone":"+61 417 339 422",
    "sg:postcode":"4568",
    "sg:province":"QLD",
    "sg:tags":[
        "equipment",
        "satellite"
    ],
    "wof:name":"Pat's Antennas",
    "wof:placetype":"venue"
},
  "geometry": {"coordinates":[152.855392456,-26.3908901215],"type":"Point"}
}