{
  "type": "Feature",
  "properties": {
    "addr:full":"31 Cleek Ave Oakleigh South VIC 3167",
    "addr:housenumber":"31",
    "addr:postcode":"3167",
    "addr:street":"Cleek Ave",
    "iso:country":"AU",
    "sg:address":"31 Cleek Ave",
    "sg:city":"Oakleigh South",
    "sg:classifiers":[
        {
            "category":"Building & Trades",
            "subcategory":"Plumbing",
            "type":"Services"
        }
    ],
    "sg:phone":"+61 412 589 766",
    "sg:postcode":"3167",
    "sg:province":"VIC",
    "sg:tags":[
        "plumber",
        "gasfitters"
    ],
    "wof:name":"Les Bishop Plumbing",
    "wof:placetype":"venue"
},
  "geometry": {"coordinates":[145.08758544899999,-37.9126281738],"type":"Point"}
}