{
  "type": "Feature",
  "properties": {
    "iso:country":"AU",
    "sg:address":"937 Doncaster Rd",
    "sg:city":"Doncaster East",
    "sg:classifiers":[
        {
            "category":"Health Services",
            "subcategory":"Health Practitioner",
            "type":"Services"
        }
    ],
    "sg:phone":"+61 3 9841 5199",
    "sg:postcode":"3109",
    "sg:province":"VIC",
    "sg:tags":[
        "psychotherapist"
    ],
    "wof:name":"Stokes Mark",
    "wof:placetype":"venue"
},
  "geometry": {"coordinates":[145.153076172,-37.7878913879],"type":"Point"}
}