{
  "type": "Feature",
  "properties": {
    "addr:full":"1083 South Gippsland Hwy Cranbourne North VIC 3977",
    "addr:housenumber":"1083",
    "addr:postcode":"3977",
    "addr:street":"South Gippsland Hwy",
    "iso:country":"AU",
    "sg:address":"1083 South Gippsland Hwy",
    "sg:city":"Cranbourne North",
    "sg:classifiers":[
        {
            "category":"Shopping",
            "subcategory":"Pets & Pet Supplies",
            "type":"Retail Goods"
        }
    ],
    "sg:phone":"+61 3 5995 8844",
    "sg:postcode":"3977",
    "sg:province":"VIC",
    "sg:tags":[
        "shop",
        "supplier"
    ],
    "wof:name":"Parkway Family Pet Centre",
    "wof:placetype":"venue"
},
  "geometry": {"coordinates":[145.276245117,-38.0814437866],"type":"Point"}
}