{
  "type": "Feature",
  "properties": {
    "iso:country":"AU",
    "sg:address":"Suite 6, Level 1 (MP24) 280 Bannister Rd",
    "sg:city":"Canning Vale",
    "sg:classifiers":[
        {
            "category":"Professional",
            "subcategory":"Accounting & Tax Preparation",
            "type":"Services"
        }
    ],
    "sg:phone":"+61 8 9256 2777",
    "sg:postcode":"6155",
    "sg:province":"WA",
    "sg:tags":[
        "consultant",
        "taxation"
    ],
    "wof:name":"Brealey Quill Kenny CPA's",
    "wof:placetype":"venue"
},
  "geometry": {"coordinates":[115.895592,-32.070065],"type":"Point"}
}