{
  "type": "Feature",
  "properties": {
    "addr:full":"78b Abel St Boyup Brook WA 6244",
    "addr:housenumber":"78b",
    "addr:postcode":"6244",
    "addr:street":"Abel St",
    "iso:country":"AU",
    "sg:address":"78b Abel St",
    "sg:city":"Boyup Brook",
    "sg:classifiers":[
        {
            "category":"Health Services",
            "subcategory":"Doctor",
            "type":"Services"
        }
    ],
    "sg:phone":"+61 8 9765 1026",
    "sg:postcode":"6244",
    "sg:province":"WA",
    "sg:tags":[
        "medical",
        "practitioner"
    ],
    "wof:name":"Boyup Brook Medical Centre",
    "wof:placetype":"venue"
},
  "geometry": {"coordinates":[116.388778687,-33.8328742981],"type":"Point"}
}