{
  "type": "Feature",
  "properties": {
    "iso:country":"AU",
    "sg:address":"12 Memorial Airport Drv",
    "sg:city":"Evans Head",
    "sg:classifiers":[
        {
            "category":"Real Estate",
            "subcategory":"Real Estate Agent",
            "type":"Services"
        }
    ],
    "sg:phone":"+61 2 6682 4623",
    "sg:postcode":"2473",
    "sg:province":"NSW",
    "sg:tags":[
        "handyman's",
        "equipment",
        "hire",
        "builders",
        "contractor"
    ],
    "wof:name":"Evans Head Hire Service",
    "wof:placetype":"venue"
},
  "geometry": {"coordinates":[153.423095703,-29.1048030853],"type":"Point"}
}