{
  "type": "Feature",
  "properties": {
    "addr:full":"Unit 5/ 100 Yangoora Rd Lakemba NSW 2195",
    "addr:housenumber":"/ 100",
    "addr:postcode":"2195",
    "addr:street":"Yangoora Rd",
    "iso:country":"AU",
    "sg:address":"Unit 5/ 100 Yangoora Rd",
    "sg:city":"Lakemba",
    "sg:classifiers":[
        {
            "category":"Building & Trades",
            "subcategory":"Cleaning & Sanitation",
            "type":"Services"
        }
    ],
    "sg:phone":"+61 2 9758 4652",
    "sg:postcode":"2195",
    "sg:province":"NSW",
    "sg:tags":[
        "industrial",
        "commercial",
        "contractor"
    ],
    "wof:name":"All Seasons Cleaning Services",
    "wof:placetype":"venue"
},
  "geometry": {"coordinates":[151.07655299999999,-33.913567],"type":"Point"}
}