{
  "type": "Feature",
  "properties": {
    "iso:country":"AU",
    "sg:address":"Shp 1/ 2 Sunset Blv",
    "sg:city":"Soldiers Point",
    "sg:classifiers":[
        {
            "category":"Restaurant",
            "type":"Food & Drink"
        }
    ],
    "sg:phone":"+61 2 4919 1502",
    "sg:postcode":"2317",
    "sg:province":"NSW",
    "wof:name":"Deck The",
    "wof:placetype":"venue"
},
  "geometry": {"coordinates":[152.06333900000001,-32.701538],"type":"Point"}
}