{
  "type": "Feature",
  "properties": {
    "iso:country":"AU",
    "sg:address":"Cnr Ridgeway & Bellchambers Rds",
    "sg:city":"Elizabeth West",
    "sg:classifiers":[
        {
            "category":"Professional",
            "subcategory":"Art Services",
            "type":"Services"
        }
    ],
    "sg:phone":"+61 13 78 72",
    "sg:postcode":"5113",
    "sg:province":"SA",
    "sg:tags":[
        "medical",
        "industrial",
        "gas"
    ],
    "wof:name":"Supagas",
    "wof:placetype":"venue"
},
  "geometry": {"coordinates":[138.65725707999999,-34.7041969299],"type":"Point"}
}