{
  "type": "Feature",
  "properties": {
    "addr:full":"5 Fitzgerald St Perth WA 6000",
    "addr:housenumber":"5",
    "addr:postcode":"6000",
    "addr:street":"Fitzgerald St",
    "iso:country":"AU",
    "sg:address":"5 Fitzgerald St",
    "sg:city":"Perth",
    "sg:classifiers":[
        {
            "category":"Shopping",
            "subcategory":"Clothing, Apparel, & Fashions",
            "type":"Retail Goods"
        }
    ],
    "sg:phone":"+61 8 9227 7281",
    "sg:postcode":"6000",
    "sg:province":"WA",
    "sg:tags":[
        "sportswear"
    ],
    "wof:name":"Runner's World",
    "wof:placetype":"venue"
},
  "geometry": {"coordinates":[115.85558319099999,-31.9412212372],"type":"Point"}
}