{
  "type": "Feature",
  "properties": {
    "addr:full":"30 Burnside St Bayswater WA 6053",
    "addr:housenumber":"30",
    "addr:postcode":"6053",
    "addr:street":"Burnside St",
    "iso:country":"AU",
    "sg:address":"30 Burnside St",
    "sg:city":"Bayswater",
    "sg:classifiers":[
        {
            "category":"Mining & Drilling",
            "type":"Manufacturing & Wholesale Goods"
        }
    ],
    "sg:phone":"+61 403 040 686",
    "sg:postcode":"6053",
    "sg:province":"WA",
    "sg:tags":[
        "concrete",
        "breaking",
        "grinding",
        "sawing"
    ],
    "wof:name":"Clear Cut Chasing",
    "wof:placetype":"venue"
},
  "geometry": {"coordinates":[115.902160645,-31.9264526367],"type":"Point"}
}