{
  "type": "Feature",
  "properties": {
    "iso:country":"AU",
    "sg:address":"PO Box 380",
    "sg:city":"Buddina",
    "sg:classifiers":[
        {
            "category":"Building & Trades",
            "subcategory":"Construction",
            "type":"Services"
        }
    ],
    "sg:phone":"+61 7 5493 4066",
    "sg:postcode":"4575",
    "sg:province":"QLD",
    "sg:tags":[
        "industrial",
        "commercial",
        "air conditioning"
    ],
    "wof:name":"Airwave Airconditioning",
    "wof:placetype":"venue"
},
  "geometry": {"coordinates":[153.129639,-26.700609],"type":"Point"}
}