{
  "type": "Feature",
  "properties": {
    "addr:full":"81 Edith St Innisfail QLD 4860",
    "addr:housenumber":"81",
    "addr:postcode":"4860",
    "addr:street":"Edith St",
    "iso:country":"AU",
    "sg:address":"81 Edith St",
    "sg:city":"Innisfail",
    "sg:classifiers":[
        {
            "category":"Food & Beverages",
            "subcategory":"Groceries & Convenience Stores",
            "type":"Retail Goods"
        }
    ],
    "sg:phone":"+61 7 4061 1269",
    "sg:postcode":"4860",
    "sg:province":"QLD",
    "wof:name":"Magnanini D",
    "wof:placetype":"venue"
},
  "geometry": {"coordinates":[146.02845764200001,-17.5244293213],"type":"Point"}
}