{
  "type": "Feature",
  "properties": {
    "addr:full":"79 Dohertys Rd Laverton North VIC 3026",
    "addr:housenumber":"79",
    "addr:postcode":"3026",
    "addr:street":"Dohertys Rd",
    "iso:country":"AU",
    "sg:address":"79 Dohertys Rd",
    "sg:city":"Laverton North",
    "sg:classifiers":[
        {
            "category":"Utilities",
            "subcategory":"Refuse",
            "type":"Services"
        }
    ],
    "sg:phone":"+61 1800 629 476",
    "sg:postcode":"3026",
    "sg:province":"VIC",
    "sg:tags":[
        "disposal",
        "reduction",
        "waste"
    ],
    "wof:name":"Auscol Pty Limited",
    "wof:placetype":"venue"
},
  "geometry": {"coordinates":[144.79605100000001,-37.828964],"type":"Point"}
}