{
  "type": "Feature",
  "properties": {
    "addr:full":"71 Wattlepark Ave Moolap VIC 3221",
    "addr:housenumber":"71",
    "addr:postcode":"3221",
    "addr:street":"Wattlepark Ave",
    "iso:country":"AU",
    "sg:address":"71 Wattlepark Ave",
    "sg:city":"Moolap",
    "sg:classifiers":[
        {
            "category":"Utilities",
            "subcategory":"Electric",
            "type":"Services"
        }
    ],
    "sg:phone":"+61 3 5248 4700",
    "sg:postcode":"3221",
    "sg:province":"VIC",
    "sg:tags":[
        "electrical",
        "contractor"
    ],
    "wof:name":"Geelong Rewires Pty Ltd",
    "wof:placetype":"venue"
},
  "geometry": {"coordinates":[144.40875199999999,-38.168434],"type":"Point"}
}