{
  "type": "Feature",
  "properties": {
    "iso:country":"AU",
    "sg:address":"Jubilee Hwy West",
    "sg:city":"Mt Gambier",
    "sg:classifiers":[
        {
            "category":"Autos & Motor Vehicles",
            "subcategory":"Automobile Sales",
            "type":"Retail Goods"
        }
    ],
    "sg:phone":"+61 8 8724 1111",
    "sg:postcode":"5290",
    "sg:province":"SA",
    "sg:tags":[
        "car",
        "new"
    ],
    "wof:name":"General Motors Holden's Ltd",
    "wof:placetype":"venue"
},
  "geometry": {"coordinates":[140.782684,-37.823311],"type":"Point"}
}