{
  "type": "Feature",
  "properties": {
    "iso:country":"AU",
    "sg:address":"13 Cambridge Ave",
    "sg:city":"Bankstown",
    "sg:classifiers":[
        {
            "category":"Health Services",
            "subcategory":"Dentist",
            "type":"Services"
        }
    ],
    "sg:phone":"+61 2 9790 2792",
    "sg:postcode":"2200",
    "sg:province":"NSW",
    "wof:name":"Eikens L I",
    "wof:placetype":"venue"
},
  "geometry": {"coordinates":[151.02969400000001,-33.92141],"type":"Point"}
}