{
  "type": "Feature",
  "properties": {
    "iso:country":"AU",
    "sg:address":"Centro Springwood, Fitzgerald Avenue",
    "sg:city":"Springwood",
    "sg:classifiers":[
        {
            "category":"Utilities",
            "subcategory":"Mobile Phone",
            "type":"Services"
        }
    ],
    "sg:phone":"+61 7 3299 4433",
    "sg:postcode":"4127",
    "sg:province":"QLD",
    "sg:tags":[
        "repair",
        "telephone"
    ],
    "wof:name":"Network Communications",
    "wof:placetype":"venue"
},
  "geometry": {"coordinates":[153.12535095199999,-27.613035202],"type":"Point"}
}