{
  "type": "Feature",
  "properties": {
    "addr:full":"35 Nerang St Waterford QLD 4133",
    "addr:housenumber":"35",
    "addr:postcode":"4133",
    "addr:street":"Nerang St",
    "iso:country":"AU",
    "sg:address":"35 Nerang St",
    "sg:city":"Waterford",
    "sg:classifiers":[
        {
            "category":"Professional",
            "subcategory":"Detective & Security Services",
            "type":"Services"
        }
    ],
    "sg:phone":"+61 1800 359 389",
    "sg:postcode":"4133",
    "sg:province":"QLD",
    "sg:tags":[
        "consultant",
        "system"
    ],
    "wof:name":"PIR Security Systems",
    "wof:placetype":"venue"
},
  "geometry": {"coordinates":[153.143508911,-27.6957569122],"type":"Point"}
}