{
  "type": "Feature",
  "properties": {
    "addr:full":"13 Bulls Rd Cronulla NSW 2230",
    "addr:housenumber":"13",
    "addr:postcode":"2230",
    "addr:street":"Bulls Rd",
    "iso:country":"AU",
    "sg:address":"13 Bulls Rd",
    "sg:city":"Cronulla",
    "sg:classifiers":[
        {
            "category":"Home & Garden",
            "subcategory":"Kitchen Supply",
            "type":"Retail Goods"
        }
    ],
    "sg:phone":"+61 2 9544 0516",
    "sg:postcode":"2230",
    "sg:province":"NSW",
    "sg:tags":[
        "equipment",
        "diving"
    ],
    "wof:name":"Manns N W",
    "wof:placetype":"venue"
},
  "geometry": {"coordinates":[151.138839722,-34.0658454895],"type":"Point"}
}