{
  "type": "Feature",
  "properties": {
    "addr:full":"Cnr Main Rd & White St Silvan VIC 3795",
    "addr:postcode":"3795",
    "addr:street":"Cnr Main Rd & White St",
    "iso:country":"AU",
    "sg:address":"Cnr Main Rd & White St",
    "sg:city":"Silvan",
    "sg:classifiers":[
        {
            "category":"Education",
            "subcategory":"School",
            "type":"Public Place"
        }
    ],
    "sg:phone":"+61 3 9737 9258",
    "sg:postcode":"3795",
    "sg:province":"VIC",
    "sg:tags":[
        "state",
        "except",
        "nsw"
    ],
    "wof:name":"Silvan Primary",
    "wof:placetype":"venue"
},
  "geometry": {"coordinates":[145.42201232900001,-37.8232002258],"type":"Point"}
}