{
  "type": "Feature",
  "properties": {
    "iso:country":"AU",
    "sg:address":"954 Glenhuntly Rd",
    "sg:city":"Caulfield",
    "sg:classifiers":[
        {
            "category":"Home & Garden",
            "subcategory":"Building Materials",
            "type":"Retail Goods"
        }
    ],
    "sg:phone":"+61 3 9571 5666",
    "sg:postcode":"3162",
    "sg:province":"VIC",
    "sg:tags":[
        "fitting",
        "door"
    ],
    "wof:name":"Justor Spring Hinge",
    "wof:placetype":"venue"
},
  "geometry": {"coordinates":[145.030319214,-37.8880386353],"type":"Point"}
}