{
  "type": "Feature",
  "properties": {
    "iso:country":"AU",
    "sg:address":"26 Harvester Ave",
    "sg:city":"Sunshine North",
    "sg:classifiers":[
        {
            "category":"Retail",
            "subcategory":"Auto Repair",
            "type":"Services"
        }
    ],
    "sg:phone":"+61 3 9310 1466",
    "sg:postcode":"3020",
    "sg:province":"VIC",
    "sg:tags":[
        "repairer",
        "motor",
        "engineer"
    ],
    "wof:name":"Spimar Car Repairs",
    "wof:placetype":"venue"
},
  "geometry": {"coordinates":[144.835846,-37.760612],"type":"Point"}
}