{
  "type": "Feature",
  "properties": {
    "addr:full":"Level 3/ 33 Queen St Brisbane QLD 4000",
    "addr:housenumber":"/ 33",
    "addr:postcode":"4000",
    "addr:street":"Queen St",
    "iso:country":"AU",
    "sg:address":"Level 3/ 33 Queen St",
    "sg:city":"Brisbane",
    "sg:classifiers":[
        {
            "category":"Banks & Credit Unions",
            "subcategory":"Investment Brokerage",
            "type":"Services"
        }
    ],
    "sg:phone":"+61 7 3210 7110",
    "sg:postcode":"4000",
    "sg:province":"QLD",
    "sg:tags":[
        "finance",
        "broker"
    ],
    "wof:name":"ForceOne Group",
    "wof:placetype":"venue"
},
  "geometry": {"coordinates":[153.02375793499999,-27.4709091187],"type":"Point"}
}