{
  "type": "Feature",
  "properties": {
    "addr:full":"Lot 8 Cessna Crt Echuca VIC 3564",
    "addr:postcode":"3564",
    "addr:street":"Cessna Crt",
    "iso:country":"AU",
    "sg:address":"Lot 8 Cessna Crt",
    "sg:city":"Echuca",
    "sg:classifiers":[
        {
            "category":"Airline",
            "type":"Transportation"
        }
    ],
    "sg:phone":"+61 3 5480 3100",
    "sg:postcode":"3564",
    "sg:province":"VIC",
    "sg:tags":[
        "aircraft",
        "rental",
        "charter"
    ],
    "wof:name":"Aus - Air Australia Pty Ltd",
    "wof:placetype":"venue"
},
  "geometry": {"coordinates":[144.764282227,-36.1638755798],"type":"Point"}
}