{
  "type": "Feature",
  "properties": {
    "iso:country":"AU",
    "sg:address":"22 Dareen St",
    "sg:city":"Beacon Hill",
    "sg:classifiers":[
        {
            "category":"Professional",
            "subcategory":"Computer Services",
            "type":"Services"
        }
    ],
    "sg:phone":"+61 438 243 121",
    "sg:postcode":"2100",
    "sg:province":"NSW",
    "sg:tags":[
        "technical",
        "support"
    ],
    "wof:name":"Fix N Macs",
    "wof:placetype":"venue"
},
  "geometry": {"coordinates":[151.250457764,-33.7507667542],"type":"Point"}
}