{
  "type": "Feature",
  "properties": {
    "iso:country":"AU",
    "sg:address":"Shp2/ 10 Market St",
    "sg:city":"Breakfast Point",
    "sg:classifiers":[
        {
            "category":"Personal",
            "subcategory":"Day Spa",
            "type":"Services"
        }
    ],
    "sg:phone":"+61 2 9743 0334",
    "sg:postcode":"2137",
    "sg:province":"NSW",
    "wof:name":"The Urban Spa Breakfast Point",
    "wof:placetype":"venue"
},
  "geometry": {"coordinates":[151.108886719,-33.8422164917],"type":"Point"}
}