{
  "type": "Feature",
  "properties": {
    "addr:full":"Calam Rd & Crompton Rd Sunnybank Hills QLD 4109",
    "addr:postcode":"4109",
    "addr:street":"Calam Rd & Crompton Rd",
    "iso:country":"AU",
    "sg:address":"Calam Rd & Crompton Rd",
    "sg:city":"Sunnybank Hills",
    "sg:classifiers":[
        {
            "category":"Food & Beverages",
            "subcategory":"Supermarket",
            "type":"Retail Goods"
        }
    ],
    "sg:phone":"+61 7 3272 6566",
    "sg:postcode":"4109",
    "sg:province":"QLD",
    "sg:tags":[
        "grocery",
        "store"
    ],
    "wof:name":"Woolworths Limited",
    "wof:placetype":"venue"
},
  "geometry": {"coordinates":[153.055587769,-27.6049785614],"type":"Point"}
}