{
  "type": "Feature",
  "properties": {
    "iso:country":"AU",
    "sg:address":"LPO Box 6062",
    "sg:city":", Cromer",
    "sg:classifiers":[
        {
            "category":"Professional",
            "subcategory":"Business Services",
            "type":"Services"
        }
    ],
    "sg:phone":"+61 3 9585 5780",
    "sg:postcode":"3193",
    "sg:province":"VIC",
    "sg:tags":[
        "processing",
        "word"
    ],
    "wof:name":"&#034;A Claytons Secretary&#034;",
    "wof:placetype":"venue"
},
  "geometry": {"coordinates":[145.04496765100001,-37.9804611206],"type":"Point"}
}