{
  "type": "Feature",
  "properties": {
    "iso:country":"AU",
    "sg:address":"357 Rossmoyne St",
    "sg:city":"Thornbury",
    "sg:classifiers":[
        {
            "category":"Commercial Area",
            "type":"Public Place"
        }
    ],
    "sg:phone":"+61 3 9484 1265",
    "sg:postcode":"3071",
    "sg:province":"VIC",
    "sg:tags":[
        "heavy",
        "carrier"
    ],
    "wof:name":"Agosta Transport Pty Ltd",
    "wof:placetype":"venue"
},
  "geometry": {"coordinates":[145.02407836899999,-37.7594261169],"type":"Point"}
}