{
  "type": "Feature",
  "properties": {
    "addr:full":"Ste4/ 75a Angas St Adelaide SA 5000",
    "addr:housenumber":"75a",
    "addr:postcode":"5000",
    "addr:street":"Angas St",
    "iso:country":"AU",
    "sg:address":"Ste4/ 75a Angas St",
    "sg:city":"Adelaide",
    "sg:classifiers":[
        {
            "category":"Banks & Credit Unions",
            "subcategory":"Financial Services",
            "type":"Services"
        }
    ],
    "sg:phone":"+61 8 8232 4555",
    "sg:postcode":"5000",
    "sg:province":"SA",
    "sg:tags":[
        "planning"
    ],
    "wof:name":"Optimum Lifefocus Financial Planning",
    "wof:placetype":"venue"
},
  "geometry": {"coordinates":[138.60325622600001,-34.9300956726],"type":"Point"}
}