{
  "type": "Feature",
  "properties": {
    "addr:full":"42 Challis Rd Armadale WA 6112",
    "addr:housenumber":"42",
    "addr:postcode":"6112",
    "addr:street":"Challis Rd",
    "iso:country":"AU",
    "sg:address":"42 Challis Rd",
    "sg:city":"Armadale",
    "sg:classifiers":[
        {
            "category":"Deli",
            "type":"Food & Drink"
        }
    ],
    "sg:phone":"+61 8 9399 2466",
    "sg:postcode":"6112",
    "sg:province":"WA",
    "sg:tags":[
        "delicatessen"
    ],
    "wof:name":"Challis Super Deli",
    "wof:placetype":"venue"
},
  "geometry": {"coordinates":[116.006492615,-32.1404457092],"type":"Point"}
}