{
  "type": "Feature",
  "properties": {
    "iso:country":"AU",
    "sg:address":"PO Box 22",
    "sg:city":"Northcote",
    "sg:classifiers":[
        {
            "category":"Organizations",
            "subcategory":"Professional Association",
            "type":"Services"
        }
    ],
    "sg:phone":"+61 3 9489 9445",
    "sg:postcode":"3070",
    "sg:province":"VIC",
    "sg:tags":[
        "web",
        "internet"
    ],
    "wof:name":"Cornerstone Design",
    "wof:placetype":"venue"
},
  "geometry": {"coordinates":[144.99939,-37.772289],"type":"Point"}
}