{
  "type": "Feature",
  "properties": {
    "addr:full":"6 Navarre St Frankston VIC 3199",
    "addr:housenumber":"6",
    "addr:postcode":"3199",
    "addr:street":"Navarre St",
    "iso:country":"AU",
    "sg:address":"6 Navarre St",
    "sg:city":"Frankston",
    "sg:classifiers":[
        {
            "category":"Manufacturing",
            "subcategory":"Tools & Machinery",
            "type":"Manufacturing & Wholesale Goods"
        }
    ],
    "sg:phone":"+61 3 9789 9350",
    "sg:postcode":"3199",
    "sg:province":"VIC",
    "sg:tags":[
        "earth",
        "excavating",
        "moving",
        "equipment"
    ],
    "wof:name":"R&S Shalders",
    "wof:placetype":"venue"
},
  "geometry": {"coordinates":[145.15269470199999,-38.1747550964],"type":"Point"}
}