{
  "type": "Feature",
  "properties": {
    "iso:country":"AU",
    "sg:address":"PO Box 66",
    "sg:city":"Kurmond",
    "sg:classifiers":[
        {
            "category":"Building & Trades",
            "subcategory":"Construction",
            "type":"Services"
        }
    ],
    "sg:phone":"+61 2 4571 3278",
    "sg:postcode":"2757",
    "sg:province":"NSW",
    "sg:tags":[
        "earth",
        "excavating",
        "moving",
        "contractor"
    ],
    "wof:name":"Hawkesbury Valley Bobcat & Tipper Hire",
    "wof:placetype":"venue"
},
  "geometry": {"coordinates":[150.70112609899999,-33.5494499207],"type":"Point"}
}