{
  "type": "Feature",
  "properties": {
    "addr:full":"2 Schiller St Wagga Wagga NSW 2650",
    "addr:postcode":"2650",
    "addr:street":"Schiller St",
    "iso:country":"AU",
    "sg:address":"2 Schiller St",
    "sg:city":"Wagga Wagga",
    "sg:classifiers":[
        {
            "category":"Professional",
            "type":"Services"
        }
    ],
    "sg:phone":"+61 2 6921 4466",
    "sg:postcode":"2650",
    "sg:province":"NSW",
    "sg:tags":[
        "transport"
    ],
    "wof:name":"Patrick Logistics",
    "wof:placetype":"venue"
},
  "geometry": {"coordinates":[147.41746520999999,-35.1273918152],"type":"Point"}
}