{
  "type": "Feature",
  "properties": {
    "iso:country":"AU",
    "sg:address":"73 Holmview Rd",
    "sg:city":"Beenleigh",
    "sg:classifiers":[
        {
            "category":"Retail",
            "subcategory":"Repair Shop",
            "type":"Services"
        }
    ],
    "sg:phone":"+61 408 880 321",
    "sg:postcode":"4207",
    "sg:province":"QLD",
    "sg:tags":[
        "windscreen"
    ],
    "wof:name":"Keens Windscreens",
    "wof:placetype":"venue"
},
  "geometry": {"coordinates":[153.181564331,-27.7094612122],"type":"Point"}
}