{
  "type": "Feature",
  "properties": {
    "iso:country":"AU",
    "sg:address":"230 King St",
    "sg:city":"Newtown",
    "sg:classifiers":[
        {
            "category":"Shopping",
            "subcategory":"Clothing, Apparel, & Fashions",
            "type":"Retail Goods"
        }
    ],
    "sg:phone":"+61 2 9550 2455",
    "sg:postcode":"2042",
    "sg:province":"NSW",
    "sg:tags":[
        "recycled",
        "clothing"
    ],
    "wof:name":"Look The",
    "wof:placetype":"venue"
},
  "geometry": {"coordinates":[151.181656,-33.89547],"type":"Point"}
}