{
  "type": "Feature",
  "properties": {
    "addr:full":"Shp810/ 86 Lake St Cairns City QLD 4870",
    "addr:housenumber":"86",
    "addr:postcode":"4870",
    "addr:street":"Lake St",
    "iso:country":"AU",
    "sg:address":"Shp810/ 86 Lake St",
    "sg:city":"Cairns City",
    "sg:classifiers":[
        {
            "category":"Personal",
            "subcategory":"Massage",
            "type":"Services"
        }
    ],
    "sg:phone":"+61 7 4041 3901",
    "sg:postcode":"4870",
    "sg:province":"QLD",
    "sg:tags":[
        "therapy"
    ],
    "wof:name":"Cool Body Asian Healing",
    "wof:placetype":"venue"
},
  "geometry": {"coordinates":[145.776657105,-16.9228858948],"type":"Point"}
}