{
  "type": "Feature",
  "properties": {
    "addr:full":"249 Waterworks Rd (Cnr Stewart Rd) Ashgrove QLD 4060",
    "addr:housenumber":"249",
    "addr:postcode":"4060",
    "addr:street":"Waterworks Rd Cnr Stewart Rd",
    "iso:country":"AU",
    "sg:address":"249 Waterworks Rd",
    "sg:city":"(Cnr Stewart Rd) Ashgrove",
    "sg:classifiers":[
        {
            "category":"Shopping",
            "subcategory":"Gifts & Souvenirs",
            "type":"Retail Goods"
        }
    ],
    "sg:phone":"+61 7 3366 9555",
    "sg:postcode":"4060",
    "sg:province":"QLD",
    "sg:tags":[
        "print",
        "poster",
        "pictures"
    ],
    "wof:name":"Rockaway Records",
    "wof:placetype":"venue"
},
  "geometry": {"coordinates":[152.992385864,-27.4457054138],"type":"Point"}
}