{
  "type": "Feature",
  "properties": {
    "addr:full":"48 Commercial St Kaniva VIC 3419",
    "addr:housenumber":"48",
    "addr:postcode":"3419",
    "addr:street":"Commercial St",
    "iso:country":"AU",
    "sg:address":"48 Commercial St",
    "sg:city":"Kaniva",
    "sg:classifiers":[
        {
            "category":"Health Services",
            "subcategory":"Dentist",
            "type":"Services"
        }
    ],
    "sg:phone":"+61 3 5392 2845",
    "sg:postcode":"3419",
    "sg:province":"VIC",
    "sg:tags":[
        "technician",
        "dental"
    ],
    "wof:name":"Hall Michael",
    "wof:placetype":"venue"
},
  "geometry": {"coordinates":[141.236526489,-36.3779258728],"type":"Point"}
}