{
  "type": "Feature",
  "properties": {
    "iso:country":"AU",
    "sg:address":"179 Bank St",
    "sg:city":"East Victoria Park",
    "sg:classifiers":[
        {
            "category":"Building & Trades",
            "subcategory":"Equipment Rental",
            "type":"Services"
        }
    ],
    "sg:phone":"+61 8 9361 1179",
    "sg:postcode":"6101",
    "sg:province":"WA",
    "sg:tags":[
        "renting",
        "trailer"
    ],
    "wof:name":"Crommelins Handyman Hire & Sales",
    "wof:placetype":"venue"
},
  "geometry": {"coordinates":[115.91665649399999,-31.9891490936],"type":"Point"}
}