{
  "type": "Feature",
  "properties": {
    "addr:full":"Cnr Moggill & Samford Rds Indooroopilly QLD 4068",
    "addr:postcode":"4068",
    "addr:street":"Cnr",
    "iso:country":"AU",
    "sg:address":"Cnr Moggill & Samford Rds",
    "sg:city":"Indooroopilly",
    "sg:classifiers":[
        {
            "category":"Autos & Motor Vehicles",
            "subcategory":"Fuel & Gas Station",
            "type":"Retail Goods"
        }
    ],
    "sg:phone":"+61 7 3378 2574",
    "sg:postcode":"4068",
    "sg:province":"QLD",
    "wof:name":"BP",
    "wof:placetype":"venue"
},
  "geometry": {"coordinates":[152.974487305,-27.4973583221],"type":"Point"}
}