{
  "type": "Feature",
  "properties": {
    "addr:full":"22 Frederick Henry Pde Cremorne TAS 7024",
    "addr:housenumber":"22",
    "addr:postcode":"7024",
    "addr:street":"Frederick Henry Pde",
    "iso:country":"AU",
    "sg:address":"22 Frederick Henry Pde",
    "sg:city":"Cremorne",
    "sg:classifiers":[
        {
            "category":"Home & Garden",
            "subcategory":"Carpets & Floor Coverings",
            "type":"Retail Goods"
        }
    ],
    "sg:phone":"+61 438 577 576",
    "sg:postcode":"7024",
    "sg:province":"TAS",
    "sg:tags":[
        "tile",
        "wall",
        "layer"
    ],
    "wof:name":"Joe Stirling",
    "wof:placetype":"venue"
},
  "geometry": {"coordinates":[147.533401489,-42.9569129944],"type":"Point"}
}