{
  "type": "Feature",
  "properties": {
    "iso:country":"AU",
    "sg:address":"154 Chapman Rd",
    "sg:city":"Geraldton",
    "sg:classifiers":[
        {
            "category":"Home & Garden",
            "subcategory":"Carpets & Floor Coverings",
            "type":"Retail Goods"
        }
    ],
    "sg:phone":"+61 8 9964 4554",
    "sg:postcode":"6530",
    "sg:province":"WA",
    "wof:name":"Da Vinci's Tile Gallery",
    "wof:placetype":"venue"
},
  "geometry": {"coordinates":[114.615791321,-28.763217926],"type":"Point"}
}