{
  "type": "Feature",
  "properties": {
    "addr:full":"U6/ 2 Stout Rd Mt Druitt NSW 2770",
    "addr:housenumber":"2",
    "addr:postcode":"2770",
    "addr:street":"U6 /;Stout Rd",
    "iso:country":"AU",
    "sg:address":"U6/ 2 Stout Rd",
    "sg:city":"Mt Druitt",
    "sg:classifiers":[
        {
            "category":"Manufacturing",
            "subcategory":"Metals",
            "type":"Manufacturing & Wholesale Goods"
        }
    ],
    "sg:phone":"+61 2 9832 1801",
    "sg:postcode":"2770",
    "sg:province":"NSW",
    "sg:tags":[
        "steel",
        "fabricator",
        "mfrs"
    ],
    "wof:name":"Iron Web Services Pty Ltd",
    "wof:placetype":"venue"
},
  "geometry": {"coordinates":[150.81101989699999,-33.766960144],"type":"Point"}
}