{
  "type": "Feature",
  "properties": {
    "addr:full":"Gwelup Plza North Beach Rd Gwelup WA 6018",
    "addr:postcode":"6018",
    "addr:street":"Plza North Beach Rd",
    "iso:country":"AU",
    "sg:address":"Gwelup Plza North Beach Rd",
    "sg:city":"Gwelup",
    "sg:classifiers":[
        {
            "category":"Food & Beverages",
            "subcategory":"Supermarket",
            "type":"Retail Goods"
        }
    ],
    "sg:phone":"+61 8 9244 2392",
    "sg:postcode":"6018",
    "sg:province":"WA",
    "sg:tags":[
        "grocery",
        "store"
    ],
    "wof:name":"Supa IGA",
    "wof:placetype":"venue"
},
  "geometry": {"coordinates":[115.79073333700001,-31.8599567413],"type":"Point"}
}