{
  "type": "Feature",
  "properties": {
    "iso:country":"AU",
    "sg:address":"11 Morphett Rd",
    "sg:city":"Camden Park",
    "sg:classifiers":[
        {
            "category":"Professional",
            "subcategory":"Computer Services",
            "type":"Services"
        }
    ],
    "sg:phone":"+61 403 029 997",
    "sg:postcode":"5038",
    "sg:province":"SA",
    "sg:tags":[
        "consultant",
        "system"
    ],
    "wof:name":"Dannex Pty Ltd",
    "wof:placetype":"venue"
},
  "geometry": {"coordinates":[138.53767395,-34.9724769592],"type":"Point"}
}