{
  "type": "Feature",
  "properties": {
    "addr:full":"U 2 / 25 Mosey St Landsdale WA 6065",
    "addr:postcode":"6065",
    "addr:street":"25 Mosey St",
    "iso:country":"AU",
    "sg:address":"U 2 / 25 Mosey St",
    "sg:city":"Landsdale",
    "sg:classifiers":[
        {
            "category":"Wholesale",
            "subcategory":"Machinery & Supplies",
            "type":"Manufacturing & Wholesale Goods"
        }
    ],
    "sg:phone":"+61 8 9302 5607",
    "sg:postcode":"6065",
    "sg:province":"WA",
    "sg:tags":[
        "bearing",
        "bushing"
    ],
    "wof:name":"PTP Powertrans (Aus)",
    "wof:placetype":"venue"
},
  "geometry": {"coordinates":[115.841369629,-31.8034591675],"type":"Point"}
}