{
  "type": "Feature",
  "properties": {
    "addr:full":"Memorial Rd Curlwaa NSW 2648",
    "addr:postcode":"2648",
    "addr:street":"Memorial Rd",
    "iso:country":"AU",
    "sg:address":"Memorial Rd",
    "sg:city":"Curlwaa",
    "sg:classifiers":[
        {
            "category":"Parking",
            "subcategory":"Lot",
            "type":"Transportation"
        }
    ],
    "sg:phone":"+61 3 5027 6201",
    "sg:postcode":"2648",
    "sg:province":"NSW",
    "sg:tags":[
        "vegetable",
        "packing",
        "fruit",
        "pack"
    ],
    "wof:name":"E J T Packers",
    "wof:placetype":"venue"
},
  "geometry": {"coordinates":[141.97479200000001,-34.095951],"type":"Point"}
}