{
  "type": "Feature",
  "properties": {
    "iso:country":"AU",
    "sg:address":"Shop 184 Footscray Market Cnr Hopkins & Leeds Sts",
    "sg:city":"Footscray",
    "sg:classifiers":[
        {
            "category":"Casinos & Gambling",
            "type":"Entertainment"
        }
    ],
    "sg:phone":"+61 3 9689 7839",
    "sg:postcode":"3011",
    "sg:province":"VIC",
    "sg:tags":[
        "lottery",
        "agent"
    ],
    "wof:name":"Footscray Lottery Centre",
    "wof:placetype":"venue"
},
  "geometry": {"coordinates":[144.90139770499999,-37.7975654602],"type":"Point"}
}