{
  "type": "Feature",
  "properties": {
    "addr:full":"11/ 236-- 238 Manns Rd Gosford West NSW 2250",
    "addr:housenumber":"11 / 236 238",
    "addr:postcode":"2250",
    "addr:street":"Manns Rd",
    "iso:country":"AU",
    "sg:address":"11/ 236-- 238 Manns Rd",
    "sg:city":"Gosford West",
    "sg:classifiers":[
        {
            "category":"Manufacturing",
            "subcategory":"Metals",
            "type":"Manufacturing & Wholesale Goods"
        }
    ],
    "sg:phone":"+61 2 4324 5949",
    "sg:postcode":"2250",
    "sg:province":"NSW",
    "sg:tags":[
        "sheet",
        "worker"
    ],
    "wof:name":"Josinet Pty Ltd",
    "wof:placetype":"venue"
},
  "geometry": {"coordinates":[151.31944274899999,-33.4243774414],"type":"Point"}
}