{
  "type": "Feature",
  "properties": {
    "iso:country":"AU",
    "sg:address":"17 Cookson St",
    "sg:city":"Camberwell",
    "sg:classifiers":[
        {
            "category":"Personal",
            "subcategory":"Beauty Salon",
            "type":"Services"
        }
    ],
    "sg:phone":"+61 3 9882 6688",
    "sg:postcode":"3124",
    "sg:province":"VIC",
    "sg:website":"http://www.skinformation.com.au",
    "wof:name":"Skinformation Clinic",
    "wof:placetype":"venue"
},
  "geometry": {"coordinates":[145.058303833,-37.8261451721],"type":"Point"}
}