{
  "type": "Feature",
  "properties": {
    "addr:full":"349 Maroondah Hwy Healesville VIC 3777",
    "addr:housenumber":"349",
    "addr:postcode":"3777",
    "addr:street":"Maroondah Hwy",
    "iso:country":"AU",
    "sg:address":"349 Maroondah Hwy",
    "sg:city":"Healesville",
    "sg:classifiers":[
        {
            "category":"Cafe",
            "type":"Food & Drink"
        }
    ],
    "sg:phone":"+61 3 5962 6045",
    "sg:postcode":"3777",
    "sg:province":"VIC",
    "wof:name":"Black Spur Nursery Cafe",
    "wof:placetype":"venue"
},
  "geometry": {"coordinates":[145.52534499999999,-37.649044],"type":"Point"}
}