{
  "type": "Feature",
  "properties": {
    "addr:full":"338 Findon Rd Kidman Park SA 5025",
    "addr:housenumber":"338",
    "addr:postcode":"5025",
    "addr:street":"Findon Rd",
    "iso:country":"AU",
    "sg:address":"338 Findon Rd",
    "sg:city":"Kidman Park",
    "sg:classifiers":[
        {
            "category":"Structure",
            "subcategory":"Office Building",
            "type":"Public Place"
        }
    ],
    "sg:phone":"+61 8 8355 3122",
    "sg:postcode":"5025",
    "sg:province":"SA",
    "sg:tags":[
        "wholesaler",
        "tool",
        "mfrs",
        "power"
    ],
    "wof:name":"Porsche Machine & Tool Pty Ltd",
    "wof:placetype":"venue"
},
  "geometry": {"coordinates":[138.533081055,-34.90883255],"type":"Point"}
}