{
  "type": "Feature",
  "properties": {
    "addr:full":"215 Main St Lilydale VIC 3140",
    "addr:housenumber":"215",
    "addr:postcode":"3140",
    "addr:street":"Main St",
    "iso:country":"AU",
    "sg:address":"215 Main St",
    "sg:city":"Lilydale",
    "sg:classifiers":[
        {
            "category":"Real Estate",
            "subcategory":"Real Estate Agent",
            "type":"Services"
        }
    ],
    "sg:phone":"+61 3 9735 1688",
    "sg:postcode":"3140",
    "sg:province":"VIC",
    "wof:name":"Allan Dobbin Real Estate",
    "wof:placetype":"venue"
},
  "geometry": {"coordinates":[145.350631714,-37.7574462891],"type":"Point"}
}