{
  "type": "Feature",
  "properties": {
    "addr:full":"13A Livingstone Rd Rockingham WA 6168",
    "addr:housenumber":"13a",
    "addr:postcode":"6168",
    "addr:street":"Livingstone Rd",
    "iso:country":"AU",
    "sg:address":"13A Livingstone Rd",
    "sg:city":"Rockingham",
    "sg:classifiers":[
        {
            "category":"Real Estate",
            "subcategory":"Real Estate Agent",
            "type":"Services"
        }
    ],
    "sg:phone":"+61 8 9528 5111",
    "sg:postcode":"6168",
    "sg:province":"WA",
    "wof:name":"GoPrivate Pty Ltd",
    "wof:placetype":"venue"
},
  "geometry": {"coordinates":[115.742538,-32.287373],"type":"Point"}
}