{
  "type": "Feature",
  "properties": {
    "iso:country":"AU",
    "sg:address":"159 Yarra St",
    "sg:city":"Geelong",
    "sg:classifiers":[
        {
            "category":"Health Services",
            "subcategory":"Doctor",
            "type":"Services"
        }
    ],
    "sg:phone":"+61 3 5223 2213",
    "sg:postcode":"3220",
    "sg:province":"VIC",
    "sg:tags":[
        "medical",
        "practitioner"
    ],
    "wof:name":"van der Linden Martin Dr",
    "wof:placetype":"venue"
},
  "geometry": {"coordinates":[144.36093099999999,-38.153538],"type":"Point"}
}