{
  "type": "Feature",
  "properties": {
    "addr:full":"8- 10 Leeds St Rhodes NSW 2138",
    "addr:housenumber":"10",
    "addr:postcode":"2138",
    "addr:street":"8;Leeds St",
    "iso:country":"AU",
    "sg:address":"8- 10 Leeds St",
    "sg:city":"Rhodes",
    "sg:classifiers":[
        {
            "category":"Retail",
            "subcategory":"Auto Repair",
            "type":"Services"
        }
    ],
    "sg:phone":"+61 500 802 030",
    "sg:postcode":"2138",
    "sg:province":"NSW",
    "sg:tags":[
        "body",
        "builder",
        "motor"
    ],
    "wof:name":"Torco Oil Australia Pty Ltd",
    "wof:placetype":"venue"
},
  "geometry": {"coordinates":[151.09085082999999,-33.8245544434],"type":"Point"}
}