{
  "type": "Feature",
  "properties": {
    "addr:full":"129 Commercial St East Mt Gambier SA 5290",
    "addr:housenumber":"129",
    "addr:postcode":"5290",
    "addr:street":"Commercial St East Mt",
    "iso:country":"AU",
    "sg:address":"129 Commercial St",
    "sg:city":"East Mt Gambier",
    "sg:classifiers":[
        {
            "category":"Food & Beverages",
            "subcategory":"Meat & Fish",
            "type":"Retail Goods"
        }
    ],
    "sg:phone":"+61 8 8725 6182",
    "sg:postcode":"5290",
    "sg:province":"SA",
    "sg:tags":[
        "seafood"
    ],
    "wof:name":"East Gambier Fish Shop",
    "wof:placetype":"venue"
},
  "geometry": {"coordinates":[140.78825399999999,-37.830685],"type":"Point"}
}