{
  "type": "Feature",
  "properties": {
    "addr:full":"PO Box 905 Pymble NSW 2073",
    "addr:postcode":"2073",
    "iso:country":"AU",
    "sg:address":"PO Box 905",
    "sg:city":"Pymble",
    "sg:classifiers":[
        {
            "category":"Autos & Motor Vehicles",
            "subcategory":"Auto Supplies",
            "type":"Retail Goods"
        }
    ],
    "sg:phone":"+61 439 044 741",
    "sg:postcode":"2073",
    "sg:province":"NSW",
    "sg:tags":[
        "oil",
        "spirit"
    ],
    "wof:name":"MINI-TANKERS CENTRAL COAST",
    "wof:placetype":"venue"
},
  "geometry": {"coordinates":[151.13749694800001,-33.7405281067],"type":"Point"}
}