{
  "type": "Feature",
  "properties": {
    "addr:full":"89 Castle Hill Drv Nerang QLD 4211",
    "addr:housenumber":"89",
    "addr:postcode":"4211",
    "addr:street":"Castle Hill Drv",
    "iso:country":"AU",
    "sg:address":"89 Castle Hill Drv",
    "sg:city":"Nerang",
    "sg:classifiers":[
        {
            "category":"Professional",
            "type":"Services"
        }
    ],
    "sg:phone":"+61 7 5502 2111",
    "sg:postcode":"4211",
    "sg:province":"QLD",
    "sg:tags":[
        "transport"
    ],
    "wof:name":"S E Q Transport",
    "wof:placetype":"venue"
},
  "geometry": {"coordinates":[153.33058166500001,-27.9597511292],"type":"Point"}
}