{
  "type": "Feature",
  "properties": {
    "addr:full":"PO Box 964 Cooktown QLD 4895",
    "addr:postcode":"4895",
    "iso:country":"AU",
    "sg:address":"PO Box 964",
    "sg:city":"Cooktown",
    "sg:classifiers":[
        {
            "category":"Building & Trades",
            "subcategory":"Construction",
            "type":"Services"
        }
    ],
    "sg:phone":"+61 417 002 143",
    "sg:postcode":"4895",
    "sg:province":"QLD",
    "sg:tags":[
        "earth",
        "excavating",
        "moving",
        "contractor"
    ],
    "wof:name":"Cooktown Civil Group",
    "wof:placetype":"venue"
},
  "geometry": {"coordinates":[145.25123596200001,-15.4621591568],"type":"Point"}
}