{
  "type": "Feature",
  "properties": {
    "addr:full":"34 Pacific Hwy Wyong NSW 2259",
    "addr:housenumber":"34",
    "addr:postcode":"2259",
    "addr:street":"Pacific Hwy",
    "iso:country":"AU",
    "sg:address":"34 Pacific Hwy",
    "sg:city":"Wyong",
    "sg:classifiers":[
        {
            "category":"Real Estate",
            "subcategory":"Developer",
            "type":"Services"
        }
    ],
    "sg:phone":"+61 2 4351 5731",
    "sg:postcode":"2259",
    "sg:province":"NSW",
    "sg:tags":[
        "development"
    ],
    "wof:name":"Sentros Pty Ltd",
    "wof:placetype":"venue"
},
  "geometry": {"coordinates":[151.424194336,-33.287071228],"type":"Point"}
}