{
  "type": "Feature",
  "properties": {
    "addr:full":"45 Scanlons Rd Wandong VIC 3758",
    "addr:housenumber":"45",
    "addr:postcode":"3758",
    "addr:street":"Scanlons Rd",
    "iso:country":"AU",
    "sg:address":"45 Scanlons Rd",
    "sg:city":"Wandong",
    "sg:classifiers":[
        {
            "category":"Building & Trades",
            "subcategory":"Construction",
            "type":"Services"
        }
    ],
    "sg:phone":"+61 3 5787 1521",
    "sg:postcode":"3758",
    "sg:province":"VIC",
    "sg:tags":[
        "earth",
        "excavating",
        "moving",
        "contractor"
    ],
    "wof:name":"Garnet Do It Excavations",
    "wof:placetype":"venue"
},
  "geometry": {"coordinates":[145.058243,-37.353809],"type":"Point"}
}