{
  "type": "Feature",
  "properties": {
    "addr:full":"PO Box 451 Salisbury QLD 4107",
    "addr:postcode":"4107",
    "iso:country":"AU",
    "sg:address":"PO Box 451",
    "sg:city":"Salisbury",
    "sg:classifiers":[
        {
            "category":"Wholesale",
            "subcategory":"Painting Supplies",
            "type":"Manufacturing & Wholesale Goods"
        }
    ],
    "sg:phone":"+61 7 3277 9785",
    "sg:postcode":"4107",
    "sg:province":"QLD",
    "sg:tags":[
        "product",
        "polyurethane"
    ],
    "wof:name":"Total Insulation (QLD) Pty Ltd",
    "wof:placetype":"venue"
},
  "geometry": {"coordinates":[153.03176879899999,-27.5451107025],"type":"Point"}
}