{
  "type": "Feature",
  "properties": {
    "addr:full":"169a Avenue Rd Mosman NSW 2088",
    "addr:postcode":"2088",
    "addr:street":"169A Avenue Rd",
    "iso:country":"AU",
    "sg:address":"169a Avenue Rd",
    "sg:city":"Mosman",
    "sg:classifiers":[
        {
            "category":"Professional",
            "subcategory":"Art Services",
            "type":"Services"
        }
    ],
    "sg:phone":"+61 2 9960 2117",
    "sg:postcode":"2088",
    "sg:province":"NSW",
    "sg:tags":[
        "interior",
        "decorator"
    ],
    "wof:name":"Eurotex Interiors",
    "wof:placetype":"venue"
},
  "geometry": {"coordinates":[151.24359130900001,-33.8303565979],"type":"Point"}
}