{
  "type": "Feature",
  "properties": {
    "iso:country":"AU",
    "sg:address":"Suite 2 202 Jersey Rd",
    "sg:city":"Woollahra",
    "sg:classifiers":[
        {
            "category":"Professional",
            "subcategory":"Art Services",
            "type":"Services"
        }
    ],
    "sg:phone":"+61 2 9328 5288",
    "sg:postcode":"2025",
    "sg:province":"NSW",
    "wof:name":"Berkeley Editions",
    "wof:placetype":"venue"
},
  "geometry": {"coordinates":[151.23695373499999,-33.885471344],"type":"Point"}
}