{
  "type": "Feature",
  "properties": {
    "addr:full":"Shop 7, 473 Beach Rd Duncraig WA 6023",
    "addr:housenumber":"shop 7 473",
    "addr:postcode":"6023",
    "addr:street":"Beach Rd",
    "iso:country":"AU",
    "sg:address":"Shop 7, 473 Beach Rd",
    "sg:city":"Duncraig",
    "sg:classifiers":[
        {
            "category":"Food & Beverages",
            "subcategory":"Specialty",
            "type":"Retail Goods"
        }
    ],
    "sg:phone":"+61 8 9448 9993",
    "sg:postcode":"6023",
    "sg:province":"WA",
    "sg:tags":[
        "delicacy"
    ],
    "wof:name":"Liquorice Gourmet Foods",
    "wof:placetype":"venue"
},
  "geometry": {"coordinates":[115.784988403,-31.8456058502],"type":"Point"}
}