{
  "type": "Feature",
  "properties": {
    "addr:full":"Copeland Rd Lethbridge Park NSW 2770",
    "addr:postcode":"2770",
    "addr:street":"Copeland Rd",
    "iso:country":"AU",
    "sg:address":"Copeland Rd",
    "sg:city":"Lethbridge Park",
    "sg:classifiers":[
        {
            "category":"Social Services",
            "subcategory":"Child Care",
            "type":"Services"
        }
    ],
    "sg:phone":"+61 2 9628 0818",
    "sg:postcode":"2770",
    "sg:province":"NSW",
    "sg:tags":[
        "support",
        "health"
    ],
    "wof:name":"Early Childhood Health Centres",
    "wof:placetype":"venue"
},
  "geometry": {"coordinates":[150.800613403,-33.7367630005],"type":"Point"}
}