{
  "type": "Feature",
  "properties": {
    "iso:country":"AU",
    "sg:address":"Level 1, 144 Cabramatta Rd",
    "sg:city":"Cremorne",
    "sg:classifiers":[
        {
            "category":"Personal",
            "type":"Services"
        }
    ],
    "sg:phone":"+61 2 9959 2380",
    "sg:postcode":"2090",
    "sg:province":"NSW",
    "sg:tags":[
        "reducing",
        "treatment",
        "weight"
    ],
    "wof:name":"Lifestyle Health & Weight Management Centre",
    "wof:placetype":"venue"
},
  "geometry": {"coordinates":[151.229614258,-33.8289375305],"type":"Point"}
}