{
  "type": "Feature",
  "properties": {
    "addr:full":"10 Jon Sanders Drv Glendalough WA 6016",
    "addr:housenumber":"10",
    "addr:postcode":"6016",
    "addr:street":"Jon Sanders Drv",
    "iso:country":"AU",
    "sg:address":"10 Jon Sanders Drv",
    "sg:city":"Glendalough",
    "sg:classifiers":[
        {
            "category":"Health Services",
            "subcategory":"Doctor",
            "type":"Services"
        }
    ],
    "sg:phone":"+61 8 9444 0533",
    "sg:postcode":"6016",
    "sg:province":"WA",
    "sg:tags":[
        "medical",
        "practitioner"
    ],
    "wof:name":"Tan C H (Bob)",
    "wof:placetype":"venue"
},
  "geometry": {"coordinates":[115.818862915,-31.9225845337],"type":"Point"}
}