{
  "type": "Feature",
  "properties": {
    "addr:full":"PO Box 61 Scone NSW 2337",
    "addr:postcode":"2337",
    "iso:country":"AU",
    "sg:address":"PO Box 61",
    "sg:city":"Scone",
    "sg:classifiers":[
        {
            "category":"Utilities",
            "type":"Services"
        }
    ],
    "sg:phone":"+61 408 471 585",
    "sg:postcode":"2337",
    "sg:province":"NSW",
    "sg:tags":[
        "refrigeration",
        "industrial",
        "commercial",
        "retail"
    ],
    "wof:name":"M.J.G. Air",
    "wof:placetype":"venue"
},
  "geometry": {"coordinates":[150.86781310999999,-32.0457496643],"type":"Point"}
}