{
  "type": "Feature",
  "properties": {
    "iso:country":"AU",
    "sg:address":"387 Lake Rd",
    "sg:city":"Glendale",
    "sg:classifiers":[
        {
            "category":"Cinema",
            "subcategory":"Movie Theater",
            "type":"Entertainment"
        }
    ],
    "sg:phone":"+61 2 4956 9331",
    "sg:postcode":"2285",
    "sg:province":"NSW",
    "wof:name":"Greater Union Organisation Pty Ltd",
    "wof:placetype":"venue"
},
  "geometry": {"coordinates":[151.63470459000001,-32.933429718],"type":"Point"}
}