{
  "type": "Feature",
  "properties": {
    "iso:country":"AU",
    "sg:address":"18/ 31 Wentworth St",
    "sg:city":"Chullora",
    "sg:classifiers":[
        {
            "category":"Education",
            "subcategory":"Music School",
            "type":"Public Place"
        }
    ],
    "sg:phone":"+61 2 9742 1322",
    "sg:postcode":"2190",
    "sg:province":"NSW",
    "sg:tags":[
        "hi-fi",
        "equipment",
        "wholesaler",
        "mfrs"
    ],
    "wof:name":"Access To Sound Pty Ltd",
    "wof:placetype":"venue"
},
  "geometry": {"coordinates":[151.06964099999999,-33.900391],"type":"Point"}
}