{
  "type": "Feature",
  "properties": {
    "addr:full":"3 Applebee St St Peters NSW 2044",
    "addr:housenumber":"3",
    "addr:postcode":"2044",
    "addr:street":"Applebee St",
    "iso:country":"AU",
    "sg:address":"3 Applebee St",
    "sg:city":"St Peters",
    "sg:classifiers":[
        {
            "category":"Banks & Credit Unions",
            "subcategory":"Atm",
            "type":"Services"
        }
    ],
    "sg:phone":"+61 2 9565 5565",
    "sg:postcode":"2044",
    "sg:province":"NSW",
    "sg:tags":[
        "wholesaler",
        "mfrs",
        "shirt",
        "pyjama"
    ],
    "wof:name":"Touma Shirts",
    "wof:placetype":"venue"
},
  "geometry": {"coordinates":[151.18005400000001,-33.908997],"type":"Point"}
}