{
  "type": "Feature",
  "properties": {
    "addr:full":"67 Hosken St Balwyn VIC 3103",
    "addr:housenumber":"67",
    "addr:postcode":"3103",
    "addr:street":"Hosken St",
    "iso:country":"AU",
    "sg:address":"67 Hosken St",
    "sg:city":"Balwyn",
    "sg:classifiers":[
        {
            "category":"Health Services",
            "subcategory":"Health Practitioner",
            "type":"Services"
        }
    ],
    "sg:phone":"+61 3 9857 7354",
    "sg:postcode":"3103",
    "sg:province":"VIC",
    "sg:tags":[
        "psychologist"
    ],
    "wof:name":"Louise Buchanan",
    "wof:placetype":"venue"
},
  "geometry": {"coordinates":[145.087280273,-37.7979850769],"type":"Point"}
}