{
  "type": "Feature",
  "properties": {
    "addr:full":"4 Side St Gladstone QLD 4680",
    "addr:housenumber":"4",
    "addr:postcode":"4680",
    "addr:street":"Side St",
    "iso:country":"AU",
    "sg:address":"4 Side St",
    "sg:city":"Gladstone",
    "sg:classifiers":[
        {
            "category":"Home & Garden",
            "subcategory":"Building Materials",
            "type":"Retail Goods"
        }
    ],
    "sg:phone":"+61 7 4972 2080",
    "sg:postcode":"4680",
    "sg:province":"QLD",
    "sg:tags":[
        "fitting",
        "door"
    ],
    "wof:name":"Busteed Building Supplies",
    "wof:placetype":"venue"
},
  "geometry": {"coordinates":[151.24794006400001,-23.8443698883],"type":"Point"}
}