{
  "type": "Feature",
  "properties": {
    "addr:full":"Wanganella St Balgowlah NSW 2093",
    "addr:postcode":"2093",
    "addr:street":"Wanganella St",
    "iso:country":"AU",
    "sg:address":"Wanganella St",
    "sg:city":"Balgowlah",
    "sg:classifiers":[
        {
            "category":"Education",
            "subcategory":"School",
            "type":"Public Place"
        }
    ],
    "sg:phone":"+61 2 9948 3069",
    "sg:postcode":"2093",
    "sg:province":"NSW",
    "wof:name":"Saint Cecilia School",
    "wof:placetype":"venue"
},
  "geometry": {"coordinates":[151.25816345199999,-33.7936286926],"type":"Point"}
}