{
  "type": "Feature",
  "properties": {
    "iso:country":"AU",
    "sg:address":"3-5 El Centro",
    "sg:city":"Chirnside Park",
    "sg:classifiers":[
        {
            "category":"Social Services",
            "subcategory":"Child Care",
            "type":"Services"
        }
    ],
    "sg:phone":"+61 3 9727 3727",
    "sg:postcode":"3116",
    "sg:province":"VIC",
    "wof:name":"Paddingtons Kinder & Child Care",
    "wof:placetype":"venue"
},
  "geometry": {"coordinates":[145.313400269,-37.7554283142],"type":"Point"}
}