{
  "type": "Feature",
  "properties": {
    "iso:country":"AU",
    "sg:address":"Lvl 7/ 16 St Georges Tce",
    "sg:city":"Perth",
    "sg:classifiers":[
        {
            "category":"Communications",
            "type":"Services"
        }
    ],
    "sg:phone":"+61 8 9225 7800",
    "sg:postcode":"6000",
    "sg:province":"WA",
    "sg:tags":[
        "equipment",
        "satellite"
    ],
    "wof:name":"Orion Satellite Systems",
    "wof:placetype":"venue"
},
  "geometry": {"coordinates":[115.86406707800001,-31.9570007324],"type":"Point"}
}