{
  "type": "Feature",
  "properties": {
    "iso:country":"AU",
    "sg:address":"317 Victoria Rd",
    "sg:city":"Gladesville",
    "sg:classifiers":[
        {
            "category":"Fast Food",
            "type":"Food & Drink"
        }
    ],
    "sg:phone":"+61 2 9817 1135",
    "sg:postcode":"2111",
    "sg:province":"NSW",
    "sg:tags":[
        "away",
        "take"
    ],
    "wof:name":"Red Rooster",
    "wof:placetype":"venue"
},
  "geometry": {"coordinates":[151.12652587900001,-33.8271141052],"type":"Point"}
}