{
  "type": "Feature",
  "properties": {
    "addr:full":"20A Desaumarez St Kensington Park SA 5068",
    "addr:housenumber":"20a",
    "addr:postcode":"5068",
    "addr:street":"Desaumarez St",
    "iso:country":"AU",
    "sg:address":"20A Desaumarez St",
    "sg:city":"Kensington Park",
    "sg:classifiers":[
        {
            "category":"Professional",
            "subcategory":"Management & Consulting",
            "type":"Services"
        }
    ],
    "sg:phone":"+61 8 8364 3312",
    "sg:postcode":"5068",
    "sg:province":"SA",
    "sg:tags":[
        "consultant",
        "relocation"
    ],
    "wof:name":"Relocations Australia Pty Ltd",
    "wof:placetype":"venue"
},
  "geometry": {"coordinates":[138.657806397,-34.922416687],"type":"Point"}
}