{
  "type": "Feature",
  "properties": {
    "iso:country":"AU",
    "sg:address":"2 Moncur St",
    "sg:city":"Woollahra",
    "sg:classifiers":[
        {
            "category":"Health Services",
            "subcategory":"Health Practitioner",
            "type":"Services"
        }
    ],
    "sg:phone":"+61 417 213 344",
    "sg:postcode":"2025",
    "sg:province":"NSW",
    "sg:tags":[
        "naturopath"
    ],
    "wof:name":"Bondi Balance Natural Health Care",
    "wof:placetype":"venue"
},
  "geometry": {"coordinates":[151.237457275,-33.8901596069],"type":"Point"}
}