{
  "type": "Feature",
  "properties": {
    "addr:full":"PO BOX 42 Warners Bay NSW 2282 Hillsborough NSW 2290",
    "addr:postcode":"2282;2290",
    "iso:country":"AU",
    "sg:address":"PO BOX 42 Warners Bay NSW 2282",
    "sg:city":"Hillsborough",
    "sg:classifiers":[
        {
            "category":"Wholesale",
            "subcategory":"Machinery & Supplies",
            "type":"Manufacturing & Wholesale Goods"
        }
    ],
    "sg:phone":"+61 409 206 208",
    "sg:postcode":"2290",
    "sg:province":"NSW",
    "sg:tags":[
        "equipment",
        "welding"
    ],
    "wof:name":"Industrial Technology",
    "wof:placetype":"venue"
},
  "geometry": {"coordinates":[151.67381286599999,-32.9756698608],"type":"Point"}
}