{
  "type": "Feature",
  "properties": {
    "addr:full":"75 Pacific Hwy Waitara NSW 2077",
    "addr:housenumber":"75",
    "addr:postcode":"2077",
    "addr:street":"Pacific Hwy",
    "iso:country":"AU",
    "sg:address":"75 Pacific Hwy",
    "sg:city":"Waitara",
    "sg:classifiers":[
        {
            "category":"Professional",
            "subcategory":"Accounting & Tax Preparation",
            "type":"Services"
        }
    ],
    "sg:phone":"+61 2 9487 6899",
    "sg:postcode":"2077",
    "sg:province":"NSW",
    "sg:tags":[
        "accountant",
        "auditor"
    ],
    "wof:name":"Ferose Rattani & Associates",
    "wof:placetype":"venue"
},
  "geometry": {"coordinates":[151.10154724099999,-33.7098693848],"type":"Point"}
}