{
  "type": "Feature",
  "properties": {
    "addr:full":"27 Dent St Glen Iris VIC 3146",
    "addr:housenumber":"27",
    "addr:postcode":"3146",
    "addr:street":"Dent St",
    "iso:country":"AU",
    "sg:address":"27 Dent St",
    "sg:city":"Glen Iris",
    "sg:classifiers":[
        {
            "category":"Professional",
            "subcategory":"Art Services",
            "type":"Services"
        }
    ],
    "sg:phone":"+61 3 9885 1430",
    "sg:postcode":"3146",
    "sg:province":"VIC",
    "sg:tags":[
        "decorator",
        "painter"
    ],
    "wof:name":"Korosec Hans",
    "wof:placetype":"venue"
},
  "geometry": {"coordinates":[145.072265625,-37.866317749],"type":"Point"}
}