{
  "type": "Feature",
  "properties": {
    "addr:full":"Belar Ave Frankston VIC 3199",
    "addr:postcode":"3199",
    "addr:street":"Belar Ave",
    "iso:country":"AU",
    "sg:address":"Belar Ave",
    "sg:city":"Frankston",
    "sg:classifiers":[
        {
            "category":"Education",
            "subcategory":"School",
            "type":"Public Place"
        }
    ],
    "sg:phone":"+61 3 9789 4544",
    "sg:postcode":"3199",
    "sg:province":"VIC",
    "sg:tags":[
        "state",
        "except",
        "nsw"
    ],
    "wof:name":"Karingal Park Secondary College",
    "wof:placetype":"venue"
},
  "geometry": {"coordinates":[145.15769958499999,-38.1448135376],"type":"Point"}
}