{
  "type": "Feature",
  "properties": {
    "addr:full":"33 Hartley St Alice Springs NT 0870",
    "addr:housenumber":"33",
    "addr:postcode":"nt 0870",
    "addr:street":"Hartley St",
    "iso:country":"AU",
    "sg:address":"33 Hartley St",
    "sg:city":"Alice Springs",
    "sg:classifiers":[
        {
            "category":"Government",
            "subcategory":"Post Office",
            "type":"Public Place"
        }
    ],
    "sg:phone":"+61 13 13 18",
    "sg:postcode":"0870",
    "sg:province":"NT",
    "sg:tags":[
        "postal"
    ],
    "wof:name":"Australia Post",
    "wof:placetype":"venue"
},
  "geometry": {"coordinates":[133.88166809099999,-23.6984786987],"type":"Point"}
}