{
  "type": "Feature",
  "properties": {
    "addr:full":"1 Miller St Victoria Park WA 6100",
    "addr:housenumber":"1",
    "addr:postcode":"6100",
    "addr:street":"Miller St",
    "iso:country":"AU",
    "sg:address":"1 Miller St",
    "sg:city":"Victoria Park",
    "sg:classifiers":[
        {
            "category":"Autos & Motor Vehicles",
            "subcategory":"Automobile Sales",
            "type":"Retail Goods"
        }
    ],
    "sg:phone":"+61 8 9470 3501",
    "sg:postcode":"6100",
    "sg:province":"WA",
    "sg:tags":[
        "car",
        "used"
    ],
    "wof:name":"Roadshow Autos",
    "wof:placetype":"venue"
},
  "geometry": {"coordinates":[115.90699005099999,-31.9762992859],"type":"Point"}
}