{
  "type": "Feature",
  "properties": {
    "addr:full":"Grove Plaza Offices, Suite 2, 156 Torquay Rd Grovedale VIC 3216",
    "addr:housenumber":"156",
    "addr:postcode":"3216",
    "addr:street":"Torquay Rd",
    "iso:country":"AU",
    "sg:address":"Grove Plaza Offices, Suite 2, 156 Torquay Rd",
    "sg:city":"Grovedale",
    "sg:classifiers":[
        {
            "category":"Building & Trades",
            "subcategory":"Landscaping Services",
            "type":"Services"
        }
    ],
    "sg:phone":"+61 3 5241 2559",
    "sg:postcode":"3216",
    "sg:province":"VIC",
    "sg:tags":[
        "consultant"
    ],
    "wof:name":"Brian Sherwell & Associates",
    "wof:placetype":"venue"
},
  "geometry": {"coordinates":[144.340499878,-38.2066993713],"type":"Point"}
}