{
  "type": "Feature",
  "properties": {
    "iso:country":"AU",
    "sg:address":"1/ 3 Windsor Rd",
    "sg:city":"Nambour",
    "sg:classifiers":[
        {
            "category":"Retail",
            "subcategory":"Auto Repair",
            "type":"Services"
        }
    ],
    "sg:phone":"+61 7 5441 4588",
    "sg:postcode":"4560",
    "sg:province":"QLD",
    "sg:tags":[
        "beater",
        "painter",
        "panel"
    ],
    "wof:name":"Creative Bodyworks",
    "wof:placetype":"venue"
},
  "geometry": {"coordinates":[152.95260620100001,-26.6317672729],"type":"Point"}
}