{
  "type": "Feature",
  "properties": {
    "addr:full":"1 Hamilton Drv Boambee NSW 2450",
    "addr:housenumber":"1",
    "addr:postcode":"2450",
    "addr:street":"Hamilton Drv",
    "iso:country":"AU",
    "sg:address":"1 Hamilton Drv",
    "sg:city":"Boambee",
    "sg:classifiers":[
        {
            "category":"Home & Garden",
            "subcategory":"Garden Supply",
            "type":"Retail Goods"
        }
    ],
    "sg:phone":"+61 2 6653 2033",
    "sg:postcode":"2450",
    "sg:province":"NSW",
    "sg:tags":[
        "nursery"
    ],
    "wof:name":"MI Fertilizers",
    "wof:placetype":"venue"
},
  "geometry": {"coordinates":[153.08360300000001,-30.337641],"type":"Point"}
}