{
  "type": "Feature",
  "properties": {
    "iso:country":"AU",
    "sg:address":"76a Carrington St",
    "sg:city":"West Wallsend",
    "sg:classifiers":[
        {
            "category":"Home & Garden",
            "subcategory":"Garden Supply",
            "type":"Retail Goods"
        }
    ],
    "sg:phone":"+61 2 4953 1558",
    "sg:postcode":"2286",
    "sg:province":"NSW",
    "sg:tags":[
        "fertilizer"
    ],
    "wof:name":"West Wallsend Produce",
    "wof:placetype":"venue"
},
  "geometry": {"coordinates":[151.57951355,-32.9033813477],"type":"Point"}
}