{
  "type": "Feature",
  "properties": {
    "iso:country":"AU",
    "sg:address":"PO Box 210",
    "sg:city":"Haberfield",
    "sg:classifiers":[
        {
            "category":"Wholesale",
            "subcategory":"Construction Materials",
            "type":"Manufacturing & Wholesale Goods"
        }
    ],
    "sg:phone":"+61 2 9745 4271",
    "sg:postcode":"2045",
    "sg:province":"NSW",
    "sg:tags":[
        "wholesaler",
        "lighting",
        "mfrs",
        "accessory"
    ],
    "wof:name":"Candela Australia",
    "wof:placetype":"venue"
},
  "geometry": {"coordinates":[151.139267,-33.881031],"type":"Point"}
}