{
  "type": "Feature",
  "properties": {
    "addr:full":"318 Bronte Rd Waverley NSW 2024",
    "addr:housenumber":"318",
    "addr:postcode":"2024",
    "addr:street":"Bronte Rd",
    "iso:country":"AU",
    "sg:address":"318 Bronte Rd",
    "sg:city":"Waverley",
    "sg:classifiers":[
        {
            "category":"Recreation",
            "subcategory":"Fishing",
            "type":"Entertainment"
        }
    ],
    "sg:phone":"+61 2 9369 4133",
    "sg:postcode":"2024",
    "sg:province":"NSW",
    "sg:tags":[
        "tackle"
    ],
    "wof:name":"The Tackle Shop",
    "wof:placetype":"venue"
},
  "geometry": {"coordinates":[151.25462341299999,-33.9018135071],"type":"Point"}
}