{
  "type": "Feature",
  "properties": {
    "iso:country":"AU",
    "sg:address":"1 Ballantyne Rd",
    "sg:city":"Kewdale",
    "sg:classifiers":[
        {
            "category":"Manufacturing",
            "subcategory":"Tools & Machinery",
            "type":"Manufacturing & Wholesale Goods"
        }
    ],
    "sg:phone":"+61 8 9353 5262",
    "sg:postcode":"6105",
    "sg:province":"WA",
    "sg:tags":[
        "earth",
        "excavating",
        "moving",
        "equipment"
    ],
    "wof:name":"National Tyres",
    "wof:placetype":"venue"
},
  "geometry": {"coordinates":[115.936889648,-31.9866714478],"type":"Point"}
}