{
  "type": "Feature",
  "properties": {
    "addr:full":"PO Box 3043 Wanniassa ACT 2903",
    "addr:postcode":"2903",
    "iso:country":"AU",
    "sg:address":"PO Box 3043",
    "sg:city":"Wanniassa",
    "sg:classifiers":[
        {
            "category":"Utilities",
            "subcategory":"Refuse",
            "type":"Services"
        }
    ],
    "sg:phone":"+61 2 6296 4358",
    "sg:postcode":"2903",
    "sg:province":"ACT",
    "sg:tags":[
        "disposal",
        "reduction",
        "waste"
    ],
    "wof:name":"C & T Trashpacks",
    "wof:placetype":"venue"
},
  "geometry": {"coordinates":[149.09135437,-35.4031486511],"type":"Point"}
}