{
  "type": "Feature",
  "properties": {
    "addr:full":"PO Box 744 Port Pirie SA 5540",
    "addr:postcode":"5540",
    "iso:country":"AU",
    "sg:address":"PO Box 744",
    "sg:city":"Port Pirie",
    "sg:classifiers":[
        {
            "category":"Building & Trades",
            "subcategory":"Construction",
            "type":"Services"
        }
    ],
    "sg:phone":"+61 8 8632 4491",
    "sg:postcode":"5540",
    "sg:province":"SA",
    "sg:tags":[
        "contractor"
    ],
    "wof:name":"Camporeale Housing & Construction",
    "wof:placetype":"venue"
},
  "geometry": {"coordinates":[138.011550903,-33.2095603943],"type":"Point"}
}