{
  "type": "Feature",
  "properties": {
    "iso:country":"AU",
    "sg:address":"130- 140 Parraweena. Rd",
    "sg:city":"Taren Point",
    "sg:classifiers":[
        {
            "category":"Shopping",
            "subcategory":"Computers & Home Electronics",
            "type":"Retail Goods"
        }
    ],
    "sg:phone":"+61 2 9525 2766",
    "sg:postcode":"2229",
    "sg:province":"NSW",
    "sg:tags":[
        "wholesaler",
        "equipment",
        "electronic",
        "mfrs"
    ],
    "wof:name":"Rittal Pty Ltd",
    "wof:placetype":"venue"
},
  "geometry": {"coordinates":[151.11561584500001,-34.0271186829],"type":"Point"}
}