{
  "type": "Feature",
  "properties": {
    "iso:country":"AU",
    "sg:address":"71 Bridge St",
    "sg:city":"Benalla",
    "sg:classifiers":[
        {
            "category":"Food & Beverages",
            "subcategory":"Bakery",
            "type":"Retail Goods"
        }
    ],
    "sg:phone":"+61 3 5762 1096",
    "sg:postcode":"3672",
    "sg:province":"VIC",
    "sg:tags":[
        "baker"
    ],
    "wof:name":"Bouwmeesters",
    "wof:placetype":"venue"
},
  "geometry": {"coordinates":[145.985016,-36.55125],"type":"Point"}
}