{
  "type": "Feature",
  "properties": {
    "iso:country":"AU",
    "sg:address":"22 Elbow St",
    "sg:city":"Kempsey",
    "sg:classifiers":[
        {
            "category":"Fast Food",
            "type":"Food & Drink"
        }
    ],
    "sg:phone":"+61 2 6562 2444",
    "sg:postcode":"2440",
    "sg:province":"NSW",
    "sg:tags":[
        "away",
        "take"
    ],
    "wof:name":"My Kitchen",
    "wof:placetype":"venue"
},
  "geometry": {"coordinates":[152.831039,-31.079674],"type":"Point"}
}