{
  "type": "Feature",
  "properties": {
    "iso:country":"AU",
    "sg:address":"Suite 5/ 481 Parramatta Rd",
    "sg:city":"Leichhardt",
    "sg:classifiers":[
        {
            "category":"Professional",
            "subcategory":"Computer Services",
            "type":"Services"
        }
    ],
    "sg:phone":"+61 2 9518 1544",
    "sg:postcode":"2040",
    "sg:province":"NSW",
    "sg:tags":[
        "training"
    ],
    "wof:name":"Multimedia Training Services",
    "wof:placetype":"venue"
},
  "geometry": {"coordinates":[151.154526,-33.888599],"type":"Point"}
}