{
  "type": "Feature",
  "properties": {
    "iso:country":"AU",
    "sg:address":"10 Millard St",
    "sg:city":"Mt Gambier",
    "sg:classifiers":[
        {
            "category":"Manufacturing",
            "subcategory":"Glass & Minerals",
            "type":"Manufacturing & Wholesale Goods"
        }
    ],
    "sg:phone":"+61 408 085 175",
    "sg:postcode":"5290",
    "sg:province":"SA",
    "sg:tags":[
        "repair",
        "fibreglass",
        "product"
    ],
    "wof:name":"SE Truck & Panels",
    "wof:placetype":"venue"
},
  "geometry": {"coordinates":[140.757614,-37.826576],"type":"Point"}
}