{
  "type": "Feature",
  "properties": {
    "addr:full":"Shop 5 Allamanda Drv Daisy Hill QLD 4127",
    "addr:housenumber":"shop 5",
    "addr:postcode":"4127",
    "addr:street":"Allamanda Drv",
    "iso:country":"AU",
    "sg:address":"Shop 5 Allamanda Drv",
    "sg:city":"Daisy Hill",
    "sg:classifiers":[
        {
            "category":"Retail",
            "subcategory":"Repair Shop",
            "type":"Services"
        }
    ],
    "sg:phone":"+61 7 3299 6122",
    "sg:postcode":"4127",
    "sg:province":"QLD",
    "sg:tags":[
        "maintenance",
        "pool",
        "swimming"
    ],
    "wof:name":"Total Pool Care",
    "wof:placetype":"venue"
},
  "geometry": {"coordinates":[153.15357971200001,-27.6444072723],"type":"Point"}
}