{
  "type": "Feature",
  "properties": {
    "addr:full":"267 Glenferrie Rd Malvern VIC 3144",
    "addr:housenumber":"267",
    "addr:postcode":"3144",
    "addr:street":"Glenferrie Rd",
    "iso:country":"AU",
    "sg:address":"267 Glenferrie Rd",
    "sg:city":"Malvern",
    "sg:classifiers":[
        {
            "category":"Cafe",
            "type":"Food & Drink"
        }
    ],
    "sg:phone":"+61 3 9576 3222",
    "sg:postcode":"3144",
    "sg:province":"VIC",
    "wof:name":"Wild Oats Cafe",
    "wof:placetype":"venue"
},
  "geometry": {"coordinates":[145.02897644000001,-37.8574523926],"type":"Point"}
}