{
  "type": "Feature",
  "properties": {
    "addr:full":"20 Chowilla St Eden Hills SA 5050",
    "addr:housenumber":"20",
    "addr:postcode":"5050",
    "addr:street":"Chowilla St",
    "iso:country":"AU",
    "sg:address":"20 Chowilla St",
    "sg:city":"Eden Hills",
    "sg:classifiers":[
        {
            "category":"Health Services",
            "subcategory":"Medical Lab",
            "type":"Services"
        }
    ],
    "sg:phone":"+61 8 8278 1037",
    "sg:postcode":"5050",
    "sg:province":"SA",
    "sg:tags":[
        "laboratory",
        "dental"
    ],
    "wof:name":"Dental Precision",
    "wof:placetype":"venue"
},
  "geometry": {"coordinates":[138.59515400000001,-35.026207],"type":"Point"}
}