{
  "type": "Feature",
  "properties": {
    "addr:full":"73 Windsor St Glenorchy TAS 7010",
    "addr:housenumber":"73",
    "addr:postcode":"7010",
    "addr:street":"Windsor St",
    "iso:country":"AU",
    "sg:address":"73 Windsor St",
    "sg:city":"Glenorchy",
    "sg:classifiers":[
        {
            "category":"Utilities",
            "subcategory":"Electric",
            "type":"Services"
        }
    ],
    "sg:phone":"+61 418 127 756",
    "sg:postcode":"7010",
    "sg:province":"TAS",
    "sg:tags":[
        "electrical",
        "contractor"
    ],
    "wof:name":"Energised Electrical",
    "wof:placetype":"venue"
},
  "geometry": {"coordinates":[147.278076172,-42.8399887085],"type":"Point"}
}