{
  "type": "Feature",
  "properties": {
    "addr:full":"252- 256 Ballarat Rd Footscray VIC 3011",
    "addr:housenumber":"256",
    "addr:postcode":"3011",
    "addr:street":"Ballarat Rd",
    "iso:country":"AU",
    "sg:address":"252- 256 Ballarat Rd",
    "sg:city":"Footscray",
    "sg:classifiers":[
        {
            "category":"Wholesale",
            "subcategory":"Auto Parts",
            "type":"Manufacturing & Wholesale Goods"
        }
    ],
    "sg:phone":"+61 3 9318 5444",
    "sg:postcode":"3011",
    "sg:province":"VIC",
    "sg:tags":[
        "recyclers"
    ],
    "wof:name":"Ballarat Road Motors & Wreckers",
    "wof:placetype":"venue"
},
  "geometry": {"coordinates":[144.88574218799999,-37.7894897461],"type":"Point"}
}