{
  "type": "Feature",
  "properties": {
    "addr:full":"19/ 1 Baden St Osborne Park WA 6017",
    "addr:housenumber":"19 / 1",
    "addr:postcode":"6017",
    "addr:street":"Baden St",
    "iso:country":"AU",
    "sg:address":"19/ 1 Baden St",
    "sg:city":"Osborne Park",
    "sg:classifiers":[
        {
            "category":"Professional",
            "subcategory":"Detective & Security Services",
            "type":"Services"
        }
    ],
    "sg:phone":"+61 1300 555 965",
    "sg:postcode":"6017",
    "sg:province":"WA",
    "sg:tags":[
        "equipment",
        "window",
        "doors"
    ],
    "wof:name":"Prestige Security Films & Glass",
    "wof:placetype":"venue"
},
  "geometry": {"coordinates":[115.82469940199999,-31.9123210907],"type":"Point"}
}