{
  "type": "Feature",
  "properties": {
    "addr:full":"Shop 4/ 216 Dorset Rd Boronia VIC 3155",
    "addr:housenumber":"shop 4 / 216",
    "addr:postcode":"3155",
    "addr:street":"Dorset Rd",
    "iso:country":"AU",
    "sg:address":"Shop 4/ 216 Dorset Rd",
    "sg:city":"Boronia",
    "sg:classifiers":[
        {
            "category":"Autos & Motor Vehicles",
            "subcategory":"Auto Supplies",
            "type":"Retail Goods"
        }
    ],
    "sg:phone":"+61 3 9762 7095",
    "sg:postcode":"3155",
    "sg:province":"VIC",
    "sg:tags":[
        "accessory"
    ],
    "wof:name":"Summit Auto Accessories",
    "wof:placetype":"venue"
},
  "geometry": {"coordinates":[145.28579711899999,-37.8619003296],"type":"Point"}
}