{
  "type": "Feature",
  "properties": {
    "addr:full":"Suite 4, Lvl 1/ 150 Albert Rd South Melbourne VIC 3205",
    "addr:housenumber":"/ 150",
    "addr:postcode":"3205",
    "addr:street":"Albert Rd",
    "iso:country":"AU",
    "sg:address":"Suite 4, Lvl 1/ 150 Albert Rd",
    "sg:city":"South Melbourne",
    "sg:classifiers":[
        {
            "category":"Shopping",
            "subcategory":"News",
            "type":"Retail Goods"
        }
    ],
    "sg:phone":"+61 3 9694 6444",
    "sg:postcode":"3205",
    "sg:province":"VIC",
    "sg:tags":[
        "magazine",
        "periodical"
    ],
    "wof:name":"Universal Magazines Pty Ltd",
    "wof:placetype":"venue"
},
  "geometry": {"coordinates":[144.96923799999999,-37.836338],"type":"Point"}
}