{
  "type": "Feature",
  "properties": {
    "addr:full":"Specialist Medical Centre 211/155 Hawkesbury Rd Westmead NSW 2145",
    "addr:housenumber":"211 / 155",
    "addr:postcode":"2145",
    "addr:street":"Hawkesbury Rd",
    "iso:country":"AU",
    "sg:address":"Specialist Medical Centre 211/155 Hawkesbury Rd",
    "sg:city":"Westmead",
    "sg:classifiers":[
        {
            "category":"Health Services",
            "subcategory":"Doctor",
            "type":"Services"
        }
    ],
    "sg:phone":"+61 2 9635 1510",
    "sg:postcode":"2145",
    "sg:province":"NSW",
    "sg:tags":[
        "medical",
        "practitioner"
    ],
    "wof:name":"Lin Rita Dr",
    "wof:placetype":"venue"
},
  "geometry": {"coordinates":[150.987838745,-33.8072357178],"type":"Point"}
}