{
  "type": "Feature",
  "properties": {
    "addr:full":"Blackhill Rd Black Hill NSW 2322",
    "addr:postcode":"2322",
    "addr:street":"Blackhill Rd",
    "iso:country":"AU",
    "sg:address":"Blackhill Rd",
    "sg:city":"Black Hill",
    "sg:classifiers":[
        {
            "category":"Building & Trades",
            "subcategory":"Construction",
            "type":"Services"
        }
    ],
    "sg:phone":"+61 2 4930 3266",
    "sg:postcode":"2322",
    "sg:province":"NSW",
    "sg:tags":[
        "contractor"
    ],
    "wof:name":"A & K MacKay Building Company Pty Ltd",
    "wof:placetype":"venue"
},
  "geometry": {"coordinates":[151.58943176299999,-32.833770752],"type":"Point"}
}