{
  "type": "Feature",
  "properties": {
    "addr:full":"15 Industrial Ave Wacol QLD 4076",
    "addr:housenumber":"15",
    "addr:postcode":"4076",
    "addr:street":"Industrial Ave",
    "iso:country":"AU",
    "sg:address":"15 Industrial Ave",
    "sg:city":"Wacol",
    "sg:classifiers":[
        {
            "category":"Wholesale",
            "subcategory":"Construction Materials",
            "type":"Manufacturing & Wholesale Goods"
        }
    ],
    "sg:phone":"+61 7 3335 3500",
    "sg:postcode":"4076",
    "sg:province":"QLD",
    "sg:tags":[
        "wholesaler",
        "lighting",
        "mfrs",
        "accessory"
    ],
    "wof:name":"Spectra Lighting",
    "wof:placetype":"venue"
},
  "geometry": {"coordinates":[152.92930602999999,-27.5929946899],"type":"Point"}
}