{
  "type": "Feature",
  "properties": {
    "addr:full":"1 Bournemouth Ave Springvale VIC 3171",
    "addr:housenumber":"1",
    "addr:postcode":"3171",
    "addr:street":"Bournemouth Ave",
    "iso:country":"AU",
    "sg:address":"1 Bournemouth Ave",
    "sg:city":"Springvale",
    "sg:classifiers":[
        {
            "category":"Shopping",
            "subcategory":"Discount & Variety Stores",
            "type":"Retail Goods"
        }
    ],
    "sg:phone":"+61 3 9540 3644",
    "sg:postcode":"3171",
    "sg:province":"VIC",
    "sg:tags":[
        "register",
        "cash"
    ],
    "wof:name":"Cash Register Network The",
    "wof:placetype":"venue"
},
  "geometry": {"coordinates":[145.13752746599999,-37.9573669434],"type":"Point"}
}