{
  "type": "Feature",
  "properties": {
    "addr:full":"90 Compton Rd Woodridge QLD 4114",
    "addr:housenumber":"90",
    "addr:postcode":"4114",
    "addr:street":"Compton Rd",
    "iso:country":"AU",
    "sg:address":"90 Compton Rd",
    "sg:city":"Woodridge",
    "sg:classifiers":[
        {
            "category":"Shopping",
            "subcategory":"Gifts & Souvenirs",
            "type":"Retail Goods"
        }
    ],
    "sg:phone":"+61 7 3299 5188",
    "sg:postcode":"4114",
    "sg:province":"QLD",
    "sg:tags":[
        "shop",
        "supply"
    ],
    "wof:name":"ABC DIRECT",
    "wof:placetype":"venue"
},
  "geometry": {"coordinates":[153.107223511,-27.6191959381],"type":"Point"}
}