{
  "type": "Feature",
  "properties": {
    "addr:full":"PO Box 413 Mansfield VIC 3724",
    "addr:postcode":"3724",
    "iso:country":"AU",
    "sg:address":"PO Box 413",
    "sg:city":"Mansfield",
    "sg:classifiers":[
        {
            "category":"Building & Trades",
            "subcategory":"Construction",
            "type":"Services"
        }
    ],
    "sg:phone":"+61 418 475 549",
    "sg:postcode":"3724",
    "sg:province":"VIC",
    "sg:tags":[
        "concrete",
        "paving"
    ],
    "wof:name":"Anton Kelleher",
    "wof:placetype":"venue"
},
  "geometry": {"coordinates":[146.087890625,-37.052318573],"type":"Point"}
}