{
  "type": "Feature",
  "properties": {
    "addr:full":"111 Bateau Bay Rd Bateau Bay NSW 2261",
    "addr:housenumber":"111",
    "addr:postcode":"2261",
    "addr:street":"Bateau Bay Rd",
    "iso:country":"AU",
    "sg:address":"111 Bateau Bay Rd",
    "sg:city":"Bateau Bay",
    "sg:classifiers":[
        {
            "category":"Utilities",
            "subcategory":"Electric",
            "type":"Services"
        }
    ],
    "sg:phone":"+61 429 320 408",
    "sg:postcode":"2261",
    "sg:province":"NSW",
    "sg:tags":[
        "electrical",
        "contractor"
    ],
    "wof:name":"Stuart Cox Electrical",
    "wof:placetype":"venue"
},
  "geometry": {"coordinates":[151.47996499999999,-33.381863],"type":"Point"}
}