{
  "type": "Feature",
  "properties": {
    "iso:country":"AU",
    "sg:address":"71 Sydney Rd",
    "sg:city":"Brunswick",
    "sg:classifiers":[
        {
            "category":"Sports & Exercise",
            "subcategory":"Playing Field",
            "type":"Entertainment"
        }
    ],
    "sg:phone":"+61 3 9387 2387",
    "sg:postcode":"3056",
    "sg:province":"VIC",
    "sg:tags":[
        "gaming",
        "venue"
    ],
    "wof:name":"Northern Jackpot Pokies",
    "wof:placetype":"venue"
},
  "geometry": {"coordinates":[144.960479736,-37.7758636475],"type":"Point"}
}