{
  "type": "Feature",
  "properties": {
    "addr:full":"20 Surflen St Adelaide SA 5000",
    "addr:housenumber":"20",
    "addr:postcode":"5000",
    "addr:street":"Surflen St",
    "iso:country":"AU",
    "sg:address":"20 Surflen St",
    "sg:city":"Adelaide",
    "sg:classifiers":[
        {
            "category":"Home & Garden",
            "subcategory":"Carpets & Floor Coverings",
            "type":"Retail Goods"
        }
    ],
    "sg:phone":"+61 8 8212 8244",
    "sg:postcode":"5000",
    "sg:province":"SA",
    "sg:tags":[
        "mattress"
    ],
    "wof:name":"BEDeBUYS",
    "wof:placetype":"venue"
},
  "geometry": {"coordinates":[138.60235595699999,-34.9320259094],"type":"Point"}
}