{
  "type": "Feature",
  "properties": {
    "addr:full":"Level 10, 109 St Georges Terrace Perth Perth WA 6000",
    "addr:housenumber":"109",
    "addr:postcode":"6000",
    "addr:street":"St Georges Terrace",
    "iso:country":"AU",
    "sg:address":"Level 10, 109 St",
    "sg:city":"Georges Terrace Perth Perth",
    "sg:classifiers":[
        {
            "category":"Professional",
            "subcategory":"Employment Agencies",
            "type":"Services"
        }
    ],
    "sg:phone":"+61 8 9266 0900",
    "sg:postcode":"6000",
    "sg:province":"WA",
    "wof:name":"Robert Walters",
    "wof:placetype":"venue"
},
  "geometry": {"coordinates":[115.856590271,-31.9548244476],"type":"Point"}
}