{
  "type": "Feature",
  "properties": {
    "addr:full":"Suite 4, 26 Joseph St Blackburn North VIC 3130",
    "addr:housenumber":"26",
    "addr:postcode":"3130",
    "addr:street":"Joseph St",
    "iso:country":"AU",
    "sg:address":"Suite 4, 26 Joseph St",
    "sg:city":"Blackburn North",
    "sg:classifiers":[
        {
            "category":"Banks & Credit Unions",
            "subcategory":"Bank",
            "type":"Services"
        }
    ],
    "sg:phone":"+61 3 9897 4177",
    "sg:postcode":"3130",
    "sg:province":"VIC",
    "sg:tags":[
        "broker",
        "mortgage"
    ],
    "wof:name":"Money Depot",
    "wof:placetype":"venue"
},
  "geometry": {"coordinates":[145.14437866200001,-37.8001708984],"type":"Point"}
}