{
  "type": "Feature",
  "properties": {
    "addr:full":"2nd Flr, 102 Beaufort St Perth WA 6000",
    "addr:housenumber":"102",
    "addr:postcode":"6000",
    "addr:street":"Beaufort St",
    "iso:country":"AU",
    "sg:address":"2nd Flr, 102 Beaufort St",
    "sg:city":"Perth",
    "sg:classifiers":[
        {
            "category":"Banks & Credit Unions",
            "subcategory":"Financial Services",
            "type":"Services"
        }
    ],
    "sg:phone":"+61 8 9228 0700",
    "sg:postcode":"6000",
    "sg:province":"WA",
    "sg:tags":[
        "planning"
    ],
    "wof:name":"Count Wealth Accountants",
    "wof:placetype":"venue"
},
  "geometry": {"coordinates":[115.865112305,-31.9453620911],"type":"Point"}
}