{
  "type": "Feature",
  "properties": {
    "iso:country":"AU",
    "sg:address":"Unit 8 Rowallan St St",
    "sg:city":"Osborne Park",
    "sg:classifiers":[
        {
            "category":"Building & Trades",
            "subcategory":"Equipment Rental",
            "type":"Services"
        }
    ],
    "sg:phone":"+61 1300 339 000",
    "sg:postcode":"6017",
    "sg:province":"WA",
    "sg:tags":[
        "party",
        "hire"
    ],
    "wof:name":"Phenomenon Prop Shop",
    "wof:placetype":"venue"
},
  "geometry": {"coordinates":[115.82476043699999,-31.9120998383],"type":"Point"}
}