{
  "type": "Feature",
  "properties": {
    "addr:full":"14 Rosewood Ave Torquay QLD 4655",
    "addr:housenumber":"14",
    "addr:postcode":"4655",
    "addr:street":"Rosewood Ave",
    "iso:country":"AU",
    "sg:address":"14 Rosewood Ave",
    "sg:city":"Torquay",
    "sg:classifiers":[
        {
            "category":"Travel",
            "subcategory":"Travel Agent",
            "type":"Entertainment"
        }
    ],
    "sg:phone":"+61 7 4125 4922",
    "sg:postcode":"4655",
    "sg:province":"QLD",
    "sg:tags":[
        "consultant"
    ],
    "wof:name":"Total Luxury Australia",
    "wof:placetype":"venue"
},
  "geometry": {"coordinates":[152.870575,-25.309681],"type":"Point"}
}