{
  "type": "Feature",
  "properties": {
    "addr:full":"31b Rose St Manjimup WA 6258",
    "addr:housenumber":"31b",
    "addr:postcode":"6258",
    "addr:street":"Rose St",
    "iso:country":"AU",
    "sg:address":"31b Rose St",
    "sg:city":"Manjimup",
    "sg:classifiers":[
        {
            "category":"Fast Food",
            "type":"Food & Drink"
        }
    ],
    "sg:phone":"+61 8 9777 1331",
    "sg:postcode":"6258",
    "sg:province":"WA",
    "sg:tags":[
        "away",
        "take"
    ],
    "wof:name":"Slice Of Heaven Cafe",
    "wof:placetype":"venue"
},
  "geometry": {"coordinates":[116.146522522,-34.2388839722],"type":"Point"}
}