{
  "type": "Feature",
  "properties": {
    "addr:full":"36- 40 Bendix Drv Clayton VIC 3168",
    "addr:housenumber":"40",
    "addr:postcode":"3168",
    "addr:street":"Bendix Drv",
    "iso:country":"AU",
    "sg:address":"36- 40 Bendix Drv",
    "sg:city":"Clayton",
    "sg:classifiers":[
        {
            "category":"Professional",
            "subcategory":"Printing & Photocopies",
            "type":"Services"
        }
    ],
    "sg:phone":"+61 3 9543 5533",
    "sg:postcode":"3168",
    "sg:province":"VIC",
    "sg:tags":[
        "embroidery"
    ],
    "wof:name":"Storm Embroidery",
    "wof:placetype":"venue"
},
  "geometry": {"coordinates":[145.127853394,-37.9287757874],"type":"Point"}
}