{
  "type": "Feature",
  "properties": {
    "addr:full":"Suite 5/36 Belmore St Burwood NSW 2134",
    "addr:housenumber":"36",
    "addr:postcode":"2134",
    "addr:street":"Belmore St",
    "iso:country":"AU",
    "sg:address":"Suite 5/36 Belmore St",
    "sg:city":"Burwood",
    "sg:classifiers":[
        {
            "category":"Professional",
            "subcategory":"Accounting & Tax Preparation",
            "type":"Services"
        }
    ],
    "sg:phone":"+61 2 9715 2122",
    "sg:postcode":"2134",
    "sg:province":"NSW",
    "sg:tags":[
        "accountant",
        "auditor"
    ],
    "wof:name":"St George & Associates Chartered Accountants",
    "wof:placetype":"venue"
},
  "geometry": {"coordinates":[151.10188293499999,-33.8788070679],"type":"Point"}
}