{
  "type": "Feature",
  "properties": {
    "iso:country":"AU",
    "sg:address":"1 Hooke St",
    "sg:city":"Dungog",
    "sg:classifiers":[
        {
            "category":"Home & Garden",
            "subcategory":"Building Materials",
            "type":"Retail Goods"
        }
    ],
    "sg:phone":"+61 2 4992 1031",
    "sg:postcode":"2420",
    "sg:province":"NSW",
    "sg:tags":[
        "laminate",
        "laminated",
        "panel"
    ],
    "wof:name":"Dale Glass Industries",
    "wof:placetype":"venue"
},
  "geometry": {"coordinates":[151.758636,-32.399822],"type":"Point"}
}