{
  "type": "Feature",
  "properties": {
    "addr:full":"77 Torquay Rd Pialba QLD 4655",
    "addr:housenumber":"77",
    "addr:postcode":"4655",
    "addr:street":"Torquay Rd",
    "iso:country":"AU",
    "sg:address":"77 Torquay Rd",
    "sg:city":"Pialba",
    "sg:classifiers":[
        {
            "category":"Building & Trades",
            "subcategory":"Construction",
            "type":"Services"
        }
    ],
    "sg:phone":"+61 7 4128 2880",
    "sg:postcode":"4655",
    "sg:province":"QLD",
    "sg:tags":[
        "pool",
        "swimming"
    ],
    "wof:name":"Hervey Bay Pool & Spa Supplies",
    "wof:placetype":"venue"
},
  "geometry": {"coordinates":[152.84715299999999,-25.2854],"type":"Point"}
}