{
  "type": "Feature",
  "properties": {
    "iso:country":"AU",
    "sg:address":"77 Torquay Rd",
    "sg:city":"Pialba",
    "sg:classifiers":[
        {
            "category":"Building & Trades",
            "subcategory":"Construction",
            "type":"Services"
        }
    ],
    "sg:phone":"+61 7 4128 2880",
    "sg:postcode":"4655",
    "sg:province":"QLD",
    "sg:tags":[
        "pool",
        "swimming"
    ],
    "wof:name":"Hervey Bay Pool & Spa Supplies",
    "wof:placetype":"venue"
},
  "geometry": {"coordinates":[152.847153,-25.2854],"type":"Point"}
}