{
  "type": "Feature",
  "properties": {
    "iso:country":"AU",
    "sg:address":"Lot 17 Northgate Shopng Cntr Chapman Rd",
    "sg:city":"Geraldton",
    "sg:classifiers":[
        {
            "category":"Shopping",
            "subcategory":"Music",
            "type":"Retail Goods"
        }
    ],
    "sg:phone":"+61 8 9921 6547",
    "sg:postcode":"6530",
    "sg:province":"WA",
    "sg:tags":[
        "store"
    ],
    "wof:name":"Sanity",
    "wof:placetype":"venue"
},
  "geometry": {"coordinates":[114.62223815900001,-28.7424926758],"type":"Point"}
}