{
  "type": "Feature",
  "properties": {
    "iso:country":"AU",
    "sg:address":"16 Pokolbin St",
    "sg:city":"Kearsley",
    "sg:classifiers":[
        {
            "category":"Retail",
            "subcategory":"Auto Repair",
            "type":"Services"
        }
    ],
    "sg:phone":"+61 2 4991 1791",
    "sg:postcode":"2325",
    "sg:province":"NSW",
    "sg:tags":[
        "sport",
        "motor"
    ],
    "wof:name":"Be Sign Yourself",
    "wof:placetype":"venue"
},
  "geometry": {"coordinates":[151.396286011,-32.8597679138],"type":"Point"}
}