{
  "type": "Feature",
  "properties": {
    "addr:full":"147 Talbragar St Dubbo NSW 2830",
    "addr:housenumber":"147",
    "addr:postcode":"2830",
    "addr:street":"Talbragar St",
    "iso:country":"AU",
    "sg:address":"147 Talbragar St",
    "sg:city":"Dubbo",
    "sg:classifiers":[
        {
            "category":"Personal",
            "subcategory":"Shoe Repair & Shine",
            "type":"Services"
        }
    ],
    "sg:phone":"+61 2 6882 2390",
    "sg:postcode":"2830",
    "sg:province":"NSW",
    "sg:tags":[
        "footwear"
    ],
    "wof:name":"Central Shoe Repairs",
    "wof:placetype":"venue"
},
  "geometry": {"coordinates":[148.60226440400001,-32.2450408936],"type":"Point"}
}