{
  "type": "Feature",
  "properties": {
    "addr:full":"11 Antares St Southern Cross WA 6426",
    "addr:housenumber":"11",
    "addr:postcode":"6426",
    "addr:street":"Antares St",
    "iso:country":"AU",
    "sg:address":"11 Antares St",
    "sg:city":"Southern Cross",
    "sg:classifiers":[
        {
            "category":"Fast Food",
            "type":"Food & Drink"
        }
    ],
    "sg:phone":"+61 8 9049 1514",
    "sg:postcode":"6426",
    "sg:province":"WA",
    "sg:tags":[
        "away",
        "take"
    ],
    "wof:name":"Cross Pasteries & Pizza Bar The",
    "wof:placetype":"venue"
},
  "geometry": {"coordinates":[119.329483,-31.232628],"type":"Point"}
}