{
  "type": "Feature",
  "properties": {
    "addr:full":"Shop 1 2, Level 1 Arcadia Walk Noosa Junction QLD 4567",
    "addr:housenumber":"shop;1",
    "addr:postcode":"4567",
    "addr:street":"Arcadia Walk Noosa",
    "iso:country":"AU",
    "sg:address":"Shop 1",
    "sg:city":"2, Level 1 Arcadia Walk Noosa Junction",
    "sg:classifiers":[
        {
            "category":"Education",
            "subcategory":"Music School",
            "type":"Public Place"
        }
    ],
    "sg:phone":"+61 7 5447 4955",
    "sg:postcode":"4567",
    "sg:province":"QLD",
    "sg:tags":[
        "therapy",
        "relaxation"
    ],
    "wof:name":"Elementals",
    "wof:placetype":"venue"
},
  "geometry": {"coordinates":[153.090240478,-26.3972702026],"type":"Point"}
}