{
  "type": "Feature",
  "properties": {
    "addr:full":"157- 161 Burnley St Richmond VIC 3121",
    "addr:housenumber":"161",
    "addr:postcode":"3121",
    "addr:street":"Burnley St",
    "iso:country":"AU",
    "sg:address":"157- 161 Burnley St",
    "sg:city":"Richmond",
    "sg:classifiers":[
        {
            "category":"Wholesale",
            "subcategory":"Apparel",
            "type":"Manufacturing & Wholesale Goods"
        }
    ],
    "sg:phone":"+61 3 9428 9211",
    "sg:postcode":"3121",
    "sg:province":"VIC",
    "sg:tags":[
        "wholesaler",
        "mfrs",
        "uniform"
    ],
    "wof:name":"Motto",
    "wof:placetype":"venue"
},
  "geometry": {"coordinates":[145.00875854500001,-37.8177528381],"type":"Point"}
}