{
  "type": "Feature",
  "properties": {
    "iso:country":"AU",
    "sg:address":"19 Pacific St",
    "sg:city":"Manly",
    "sg:classifiers":[
        {
            "category":"Travel",
            "subcategory":"Hotels & Motels",
            "type":"Entertainment"
        }
    ],
    "sg:phone":"+61 2 9977 1774",
    "sg:postcode":"2095",
    "sg:province":"NSW",
    "wof:name":"Manly Seaview Motel",
    "wof:placetype":"venue"
},
  "geometry": {"coordinates":[151.28573608400001,-33.7879905701],"type":"Point"}
}