{
  "type": "Feature",
  "properties": {
    "addr:full":"16 Rassmussen Rd Horsham VIC 3400",
    "addr:housenumber":"16",
    "addr:postcode":"3400",
    "addr:street":"Rassmussen Rd",
    "iso:country":"AU",
    "sg:address":"16 Rassmussen Rd",
    "sg:city":"Horsham",
    "sg:classifiers":[
        {
            "category":"Professional",
            "subcategory":"Art Services",
            "type":"Services"
        }
    ],
    "sg:phone":"+61 3 5382 4630",
    "sg:postcode":"3400",
    "sg:province":"VIC",
    "sg:tags":[
        "decorator",
        "painter"
    ],
    "wof:name":"Carrick L J & M B",
    "wof:placetype":"venue"
},
  "geometry": {"coordinates":[142.20623779300001,-36.6970672607],"type":"Point"}
}