{
  "type": "Feature",
  "properties": {
    "iso:country":"AU",
    "sg:address":"61 Glenlyon Drv",
    "sg:city":"Wulguru",
    "sg:classifiers":[
        {
            "category":"Transit Center",
            "subcategory":"Passenger",
            "type":"Transportation"
        }
    ],
    "sg:phone":"+61 7 4778 4266",
    "sg:postcode":"4811",
    "sg:province":"QLD",
    "sg:tags":[
        "reading",
        "improvement"
    ],
    "wof:name":"ICS Learning Group NQ",
    "wof:placetype":"venue"
},
  "geometry": {"coordinates":[146.818497,-19.330235],"type":"Point"}
}