{
  "type": "Feature",
  "properties": {
    "addr:full":"64 Pages Rd Wynyard TAS 7325",
    "addr:housenumber":"64",
    "addr:postcode":"7325",
    "addr:street":"Pages Rd",
    "iso:country":"AU",
    "sg:address":"64 Pages Rd",
    "sg:city":"Wynyard",
    "sg:classifiers":[
        {
            "category":"Education",
            "subcategory":"Vocational School",
            "type":"Public Place"
        }
    ],
    "sg:phone":"+61 400 106 357",
    "sg:postcode":"7325",
    "sg:province":"TAS",
    "sg:tags":[
        "cake",
        "decorating",
        "decorator"
    ],
    "wof:name":"Lindridge Cakes",
    "wof:placetype":"venue"
},
  "geometry": {"coordinates":[145.65287799999999,-41.000092],"type":"Point"}
}