{
  "type": "Feature",
  "properties": {
    "addr:full":"PO Box 667 Sarina QLD 4737",
    "addr:postcode":"4737",
    "iso:country":"AU",
    "sg:address":"PO Box 667",
    "sg:city":"Sarina",
    "sg:classifiers":[
        {
            "category":"Real Estate",
            "subcategory":"Real Estate Operator",
            "type":"Services"
        }
    ],
    "sg:phone":"+61 7 4943 0717",
    "sg:postcode":"4737",
    "sg:province":"QLD",
    "sg:tags":[
        "concrete",
        "pumping"
    ],
    "wof:name":"Sarina Concrete Pumping Pty Ltd",
    "wof:placetype":"venue"
},
  "geometry": {"coordinates":[149.21603400000001,-21.420919],"type":"Point"}
}