{
  "type": "Feature",
  "properties": {
    "addr:full":"PO Box 592 Yarrawonga VIC 3730",
    "addr:postcode":"3730",
    "iso:country":"AU",
    "sg:address":"PO Box 592",
    "sg:city":"Yarrawonga",
    "sg:classifiers":[
        {
            "category":"Education",
            "subcategory":"Special Training",
            "type":"Public Place"
        }
    ],
    "sg:phone":"+61 419 594 992",
    "sg:postcode":"3730",
    "sg:province":"VIC",
    "sg:tags":[
        "instruction",
        "display",
        "parachuting"
    ],
    "wof:name":"Skydive Geelong",
    "wof:placetype":"venue"
},
  "geometry": {"coordinates":[146.00526428200001,-36.017490387],"type":"Point"}
}