{
  "type": "Feature",
  "properties": {
    "addr:full":"346 Unley Rd Unley Park SA 5061",
    "addr:housenumber":"346",
    "addr:postcode":"5061",
    "addr:street":"Unley Rd",
    "iso:country":"AU",
    "sg:address":"346 Unley Rd",
    "sg:city":"Unley Park",
    "sg:classifiers":[
        {
            "category":"Health Services",
            "subcategory":"Dentist",
            "type":"Services"
        }
    ],
    "sg:phone":"+61 8 8373 4755",
    "sg:postcode":"5061",
    "sg:province":"SA",
    "wof:name":"Unley Park Dental Clinic",
    "wof:placetype":"venue"
},
  "geometry": {"coordinates":[138.60810852,-34.9599952698],"type":"Point"}
}