{
  "type": "Feature",
  "properties": {
    "addr:full":"New England Hwy Allora QLD 4362",
    "addr:postcode":"4362",
    "addr:street":"England Hwy",
    "iso:country":"AU",
    "sg:address":"New England Hwy",
    "sg:city":"Allora",
    "sg:classifiers":[
        {
            "category":"Home & Garden",
            "subcategory":"Garden Supply",
            "type":"Retail Goods"
        }
    ],
    "sg:phone":"+61 7 4666 3290",
    "sg:postcode":"4362",
    "sg:province":"QLD",
    "sg:tags":[
        "fertilizer"
    ],
    "wof:name":"DFC Agri Services",
    "wof:placetype":"venue"
},
  "geometry": {"coordinates":[151.99156189000001,-28.004535675],"type":"Point"}
}