{
  "type": "Feature",
  "properties": {
    "iso:country":"AU",
    "sg:address":"105 Todd St",
    "sg:city":"Alice Springs",
    "sg:classifiers":[
        {
            "category":"Food & Beverages",
            "subcategory":"Groceries & Convenience Stores",
            "type":"Retail Goods"
        }
    ],
    "sg:phone":"+61 8 8952 4124",
    "sg:postcode":"0870",
    "sg:province":"NT",
    "wof:name":"Alice 24 Store",
    "wof:placetype":"venue"
},
  "geometry": {"coordinates":[133.88124084500001,-23.7030525208],"type":"Point"}
}