{
  "type": "Feature",
  "properties": {
    "addr:full":"445 Pulteney St Adelaide SA 5000",
    "addr:housenumber":"445",
    "addr:postcode":"5000",
    "addr:street":"Pulteney St",
    "iso:country":"AU",
    "sg:address":"445 Pulteney St",
    "sg:city":"Adelaide",
    "sg:classifiers":[
        {
            "category":"Fast Food",
            "type":"Food & Drink"
        }
    ],
    "sg:phone":"+61 8 8232 5118",
    "sg:postcode":"5000",
    "sg:province":"SA",
    "sg:tags":[
        "away",
        "take"
    ],
    "wof:name":"Red Fortune Chinese Restaurant",
    "wof:placetype":"venue"
},
  "geometry": {"coordinates":[138.60626220699999,-34.934223175],"type":"Point"}
}