{
  "type": "Feature",
  "properties": {
    "iso:country":"AU",
    "sg:address":"14 Rohs Rd",
    "sg:city":"Bendigo",
    "sg:classifiers":[
        {
            "category":"Building & Trades",
            "subcategory":"Construction",
            "type":"Services"
        }
    ],
    "sg:phone":"+61 3 5444 0909",
    "sg:postcode":"3539",
    "sg:province":"VIC",
    "sg:tags":[
        "pool",
        "swimming"
    ],
    "wof:name":"KCH Tiles",
    "wof:placetype":"venue"
},
  "geometry": {"coordinates":[144.3134,-36.744781],"type":"Point"}
}