{
  "type": "Feature",
  "properties": {
    "iso:country":"AU",
    "sg:address":"1 Bell St",
    "sg:city":"Coburg",
    "sg:classifiers":[
        {
            "category":"Autos & Motor Vehicles",
            "subcategory":"Auto Supplies",
            "type":"Retail Goods"
        }
    ],
    "sg:phone":"+61 3 9350 4311",
    "sg:postcode":"3058",
    "sg:province":"VIC",
    "sg:tags":[
        "accessory"
    ],
    "wof:name":"Mr Sunroofs",
    "wof:placetype":"venue"
},
  "geometry": {"coordinates":[144.970993042,-37.7416191101],"type":"Point"}
}