{
  "type": "Feature",
  "properties": {
    "iso:country":"AU",
    "sg:address":"Suite 12 1 Redman Rd",
    "sg:city":"Dee Why",
    "sg:classifiers":[
        {
            "category":"Real Estate",
            "subcategory":"Real Estate Operator",
            "type":"Services"
        }
    ],
    "sg:phone":"+61 2 9972 1966",
    "sg:postcode":"2099",
    "sg:province":"NSW",
    "sg:tags":[
        "building",
        "consultant",
        "management"
    ],
    "wof:name":"Cooper Jim & Associates Carpet Consultancy",
    "wof:placetype":"venue"
},
  "geometry": {"coordinates":[151.28414917000001,-33.753578186],"type":"Point"}
}