{
  "type": "Feature",
  "properties": {
    "iso:country":"AU",
    "sg:address":"Shp 1/ 124 Main St",
    "sg:city":"Proserpine",
    "sg:classifiers":[
        {
            "category":"Personal",
            "subcategory":"Beauty Salon",
            "type":"Services"
        }
    ],
    "sg:phone":"+61 7 4945 3600",
    "sg:postcode":"4800",
    "sg:province":"QLD",
    "sg:tags":[
        "hairdresser"
    ],
    "wof:name":"Handz On Headz",
    "wof:placetype":"venue"
},
  "geometry": {"coordinates":[148.58546447800001,-20.4021224976],"type":"Point"}
}