{
  "type": "Feature",
  "properties": {
    "addr:full":"75 Postans Rd Hope Valley WA 6165",
    "addr:housenumber":"75",
    "addr:postcode":"6165",
    "addr:street":"Postans Rd",
    "iso:country":"AU",
    "sg:address":"75 Postans Rd",
    "sg:city":"Hope Valley",
    "sg:classifiers":[
        {
            "category":"Professional",
            "subcategory":"Business Services",
            "type":"Services"
        }
    ],
    "sg:phone":"+61 8 9437 1344",
    "sg:postcode":"6165",
    "sg:province":"WA",
    "sg:tags":[
        "exporter"
    ],
    "wof:name":"C T P Exports",
    "wof:placetype":"venue"
},
  "geometry": {"coordinates":[115.81205,-32.198814],"type":"Point"}
}