{
  "type": "Feature",
  "properties": {
    "iso:country":"AU",
    "sg:address":"Shop 31",
    "sg:city":"Karingal Hub Frankston",
    "sg:classifiers":[
        {
            "category":"Shopping",
            "subcategory":"Clothing, Apparel, & Fashions",
            "type":"Retail Goods"
        }
    ],
    "sg:phone":"+61 3 9775 5961",
    "sg:postcode":"3199",
    "sg:province":"VIC",
    "sg:tags":[
        "lady",
        "wear"
    ],
    "wof:name":"1626",
    "wof:placetype":"venue"
},
  "geometry": {"coordinates":[145.294265747,-37.7672348022],"type":"Point"}
}