{
  "type": "Feature",
  "properties": {
    "iso:country":"AU",
    "sg:address":"622 Centre Rd",
    "sg:city":"Bentleigh",
    "sg:classifiers":[
        {
            "category":"Health Services",
            "subcategory":"Doctor",
            "type":"Services"
        }
    ],
    "sg:phone":"+61 3 9557 2486",
    "sg:postcode":"3204",
    "sg:province":"VIC",
    "sg:tags":[
        "medical",
        "practitioner"
    ],
    "wof:name":"Southern Cross Anaesthetic Group",
    "wof:placetype":"venue"
},
  "geometry": {"coordinates":[145.05072000000001,-37.920177],"type":"Point"}
}