{
  "type": "Feature",
  "properties": {
    "iso:country":"AU",
    "sg:address":"60 Heather St",
    "sg:city":"Heatherbrae",
    "sg:classifiers":[
        {
            "category":"Retail",
            "subcategory":"Auto Repair",
            "type":"Services"
        }
    ],
    "sg:phone":"+61 2 4987 6922",
    "sg:postcode":"2324",
    "sg:province":"NSW",
    "sg:tags":[
        "camper-trailers",
        "caravan",
        "servicing"
    ],
    "wof:name":"Classic Caravan & Trailer Repairs",
    "wof:placetype":"venue"
},
  "geometry": {"coordinates":[151.733886719,-32.7857513428],"type":"Point"}
}