{
  "type": "Feature",
  "properties": {
    "addr:full":"50 Wattlepark Ave Moolap VIC 3221",
    "addr:housenumber":"50",
    "addr:postcode":"3221",
    "addr:street":"Wattlepark Ave",
    "iso:country":"AU",
    "sg:address":"50 Wattlepark Ave",
    "sg:city":"Moolap",
    "sg:classifiers":[
        {
            "category":"Manufacturing",
            "subcategory":"Chemicals & Compounds",
            "type":"Manufacturing & Wholesale Goods"
        }
    ],
    "sg:phone":"+61 3 5248 6867",
    "sg:postcode":"3221",
    "sg:province":"VIC",
    "sg:tags":[
        "industrial"
    ],
    "wof:name":"Milestone Chemicals Pty Ltd",
    "wof:placetype":"venue"
},
  "geometry": {"coordinates":[144.408661,-38.167061],"type":"Point"}
}