{
  "type": "Feature",
  "properties": {
    "addr:full":"180 Smith St Collingwood VIC 3066",
    "addr:housenumber":"180",
    "addr:postcode":"3066",
    "addr:street":"Smith St",
    "iso:country":"AU",
    "sg:address":"180 Smith St",
    "sg:city":"Collingwood",
    "sg:classifiers":[
        {
            "category":"Shopping",
            "subcategory":"Pawn Shop",
            "type":"Retail Goods"
        }
    ],
    "sg:phone":"+61 3 9417 4620",
    "sg:postcode":"3066",
    "sg:province":"VIC",
    "sg:tags":[
        "pawnbroker"
    ],
    "wof:name":"Cash Converters",
    "wof:placetype":"venue"
},
  "geometry": {"coordinates":[144.98367309599999,-37.8032798767],"type":"Point"}
}