{
  "type": "Feature",
  "properties": {
    "iso:country":"AU",
    "sg:address":"11 Kooemba Rd",
    "sg:city":"Beverly Hills",
    "sg:classifiers":[
        {
            "category":"Manufacturing",
            "subcategory":"Paper Products",
            "type":"Manufacturing & Wholesale Goods"
        }
    ],
    "sg:phone":"+61 400 777 735",
    "sg:postcode":"2209",
    "sg:province":"NSW",
    "sg:tags":[
        "box",
        "fibre",
        "carton",
        "cardboard"
    ],
    "wof:name":"Just Boxes",
    "wof:placetype":"venue"
},
  "geometry": {"coordinates":[151.086166,-33.943901],"type":"Point"}
}