{
  "type": "Feature",
  "properties": {
    "iso:country":"AU",
    "sg:address":"Factory 4 400 Princes Hwy",
    "sg:city":"Noble Park",
    "sg:classifiers":[
        {
            "category":"Home & Garden",
            "subcategory":"Building Materials",
            "type":"Retail Goods"
        }
    ],
    "sg:phone":"+61 3 9790 6599",
    "sg:postcode":"3174",
    "sg:province":"VIC",
    "sg:tags":[
        "wall",
        "frame",
        "truss",
        "roof"
    ],
    "wof:name":"Engtruss",
    "wof:placetype":"venue"
},
  "geometry": {"coordinates":[145.188064575,-37.960849762],"type":"Point"}
}