{
  "type": "Feature",
  "properties": {
    "iso:country":"AU",
    "sg:address":"110 Angle St",
    "sg:city":"Walcha",
    "sg:classifiers":[
        {
            "category":"Education",
            "subcategory":"School",
            "type":"Public Place"
        }
    ],
    "sg:phone":"+61 2 6777 2777",
    "sg:postcode":"2354",
    "sg:province":"NSW",
    "sg:tags":[
        "state",
        "-",
        "nsw"
    ],
    "wof:name":"Walcha Central School",
    "wof:placetype":"venue"
},
  "geometry": {"coordinates":[151.603973389,-30.9778118134],"type":"Point"}
}