{
  "type": "Feature",
  "properties": {
    "addr:full":"166 High St Wodonga VIC 3690",
    "addr:housenumber":"166",
    "addr:postcode":"3690",
    "addr:street":"High St",
    "iso:country":"AU",
    "sg:address":"166 High St",
    "sg:city":"Wodonga",
    "sg:classifiers":[
        {
            "category":"Fast Food",
            "type":"Food & Drink"
        }
    ],
    "sg:phone":"+61 2 6024 2948",
    "sg:postcode":"3690",
    "sg:province":"VIC",
    "sg:tags":[
        "away",
        "take"
    ],
    "wof:name":"Wodonga Characoal Chicken",
    "wof:placetype":"venue"
},
  "geometry": {"coordinates":[146.888275147,-36.1217308044],"type":"Point"}
}