{
  "type": "Feature",
  "properties": {
    "addr:full":"54 Moons Ave Lugarno NSW 2210",
    "addr:housenumber":"54",
    "addr:postcode":"2210",
    "addr:street":"Moons Ave",
    "iso:country":"AU",
    "sg:address":"54 Moons Ave",
    "sg:city":"Lugarno",
    "sg:classifiers":[
        {
            "category":"Banks & Credit Unions",
            "subcategory":"Bank",
            "type":"Services"
        }
    ],
    "sg:phone":"+61 2 9533 7575",
    "sg:postcode":"2210",
    "sg:province":"NSW",
    "sg:tags":[
        "broker",
        "mortgage"
    ],
    "wof:name":"Prestige Mortgages",
    "wof:placetype":"venue"
},
  "geometry": {"coordinates":[151.03819300000001,-33.985344],"type":"Point"}
}