{
  "type": "Feature",
  "properties": {
    "iso:country":"AU",
    "sg:address":"10 Drayton St",
    "sg:city":"Dalby",
    "sg:classifiers":[
        {
            "category":"Communications",
            "subcategory":"Film & Video Production",
            "type":"Services"
        }
    ],
    "sg:phone":"+61 7 4662 4801",
    "sg:postcode":"4405",
    "sg:province":"QLD",
    "sg:tags":[
        "dvd",
        "library"
    ],
    "wof:name":"Video Ezy",
    "wof:placetype":"venue"
},
  "geometry": {"coordinates":[151.25907898,-27.1793613434],"type":"Point"}
}