{
  "type": "Feature",
  "properties": {
    "iso:country":"AU",
    "sg:address":"15 Mends St",
    "sg:city":"South Perth",
    "sg:classifiers":[
        {
            "category":"Health Services",
            "subcategory":"Health Practitioner",
            "type":"Services"
        }
    ],
    "sg:phone":"+61 8 9367 1185",
    "sg:postcode":"6151",
    "sg:province":"WA",
    "sg:tags":[
        "homoeopath"
    ],
    "wof:name":"The Old Mill Pharmacy",
    "wof:placetype":"venue"
},
  "geometry": {"coordinates":[115.852379,-31.97245],"type":"Point"}
}