{
  "type": "Feature",
  "properties": {
    "addr:full":"22 Orion St Yass NSW 2582",
    "addr:housenumber":"22",
    "addr:postcode":"2582",
    "addr:street":"Orion St",
    "iso:country":"AU",
    "sg:address":"22 Orion St",
    "sg:city":"Yass",
    "sg:classifiers":[
        {
            "category":"Utilities",
            "subcategory":"Electric",
            "type":"Services"
        }
    ],
    "sg:phone":"+61 2 6226 3160",
    "sg:postcode":"2582",
    "sg:province":"NSW",
    "sg:tags":[
        "electrical",
        "contractor"
    ],
    "wof:name":"T.J.G. Electrical",
    "wof:placetype":"venue"
},
  "geometry": {"coordinates":[148.91195678700001,-34.8259162903],"type":"Point"}
}