{
  "type": "Feature",
  "properties": {
    "addr:full":"24 Hunter St Heywood VIC 3304",
    "addr:housenumber":"24",
    "addr:postcode":"3304",
    "addr:street":"Hunter St",
    "iso:country":"AU",
    "sg:address":"24 Hunter St",
    "sg:city":"Heywood",
    "sg:classifiers":[
        {
            "category":"Education",
            "subcategory":"Kindergarten",
            "type":"Public Place"
        }
    ],
    "sg:phone":"+61 3 5527 1382",
    "sg:postcode":"3304",
    "sg:province":"VIC",
    "sg:tags":[
        "pre-schools"
    ],
    "wof:name":"Heywood Kindergarten",
    "wof:placetype":"venue"
},
  "geometry": {"coordinates":[141.62876892099999,-38.130657196],"type":"Point"}
}