{
  "type": "Feature",
  "properties": {
    "addr:full":"336 Main St Emerald VIC 3782",
    "addr:housenumber":"336",
    "addr:postcode":"3782",
    "addr:street":"Main St",
    "iso:country":"AU",
    "sg:address":"336 Main St",
    "sg:city":"Emerald",
    "sg:classifiers":[
        {
            "category":"Autos & Motor Vehicles",
            "subcategory":"Fuel & Gas Station",
            "type":"Retail Goods"
        }
    ],
    "sg:phone":"+61 3 5968 4350",
    "sg:postcode":"3782",
    "sg:province":"VIC",
    "wof:name":"Shell Emerald Village",
    "wof:placetype":"venue"
},
  "geometry": {"coordinates":[145.441193,-37.932167],"type":"Point"}
}