{
  "type": "Feature",
  "properties": {
    "iso:country":"AU",
    "sg:address":"12 Susan St",
    "sg:city":"Hindmarsh",
    "sg:classifiers":[
        {
            "category":"Building & Trades",
            "subcategory":"Plumbing",
            "type":"Services"
        }
    ],
    "sg:phone":"+61 8 8258 1755",
    "sg:postcode":"5007",
    "sg:province":"SA",
    "sg:tags":[
        "equipment",
        "valves"
    ],
    "wof:name":"Tradelink Plumbing Supplies",
    "wof:placetype":"venue"
},
  "geometry": {"coordinates":[138.56590270999999,-34.9079971313],"type":"Point"}
}