{
  "type": "Feature",
  "properties": {
    "addr:full":"28 Mint St Wantirna VIC 3152",
    "addr:housenumber":"28",
    "addr:postcode":"3152",
    "addr:street":"Mint St",
    "iso:country":"AU",
    "sg:address":"28 Mint St",
    "sg:city":"Wantirna",
    "sg:classifiers":[
        {
            "category":"Building & Trades",
            "subcategory":"Cleaning & Sanitation",
            "type":"Services"
        }
    ],
    "sg:phone":"+61 3 9887 4029",
    "sg:postcode":"3152",
    "sg:province":"VIC",
    "sg:tags":[
        "commercial",
        "maintenance"
    ],
    "wof:name":"Hollins Building Maintenance Pty Ltd",
    "wof:placetype":"venue"
},
  "geometry": {"coordinates":[145.22467040999999,-37.8392295837],"type":"Point"}
}