{
  "type": "Feature",
  "properties": {
    "iso:country":"AU",
    "sg:address":"Anglesea Barracks, Davey St",
    "sg:city":"Hobart",
    "sg:classifiers":[
        {
            "category":"Professional",
            "subcategory":"Employment Agencies",
            "type":"Services"
        }
    ],
    "sg:phone":"+61 3 6237 7250",
    "sg:postcode":"7000",
    "sg:province":"TAS",
    "wof:name":"Manpower Defence Recruitment",
    "wof:placetype":"venue"
},
  "geometry": {"coordinates":[147.329177856,-42.8848304749],"type":"Point"}
}