{
  "type": "Feature",
  "properties": {
    "iso:country":"AU",
    "sg:address":"38A Carrier St",
    "sg:city":"Benalla",
    "sg:classifiers":[
        {
            "category":"Organizations",
            "subcategory":"Membership Organization",
            "type":"Services"
        }
    ],
    "sg:phone":"+61 3 5762 6299",
    "sg:postcode":"3671",
    "sg:province":"VIC",
    "sg:tags":[
        "support",
        "health",
        "organisation"
    ],
    "wof:name":"Alzheimer's Australia Vic",
    "wof:placetype":"venue"
},
  "geometry": {"coordinates":[145.984894,-36.548779],"type":"Point"}
}