{
  "type": "Feature",
  "properties": {
    "addr:full":"15 Jackson Cct St Albans VIC 3021",
    "addr:housenumber":"15",
    "addr:postcode":"3021",
    "addr:street":"Jackson Cct",
    "iso:country":"AU",
    "sg:address":"15 Jackson Cct St",
    "sg:city":"Albans",
    "sg:classifiers":[
        {
            "category":"Building & Trades",
            "subcategory":"Construction",
            "type":"Services"
        }
    ],
    "sg:phone":"+61 3 9366 1344",
    "sg:postcode":"3021",
    "sg:province":"VIC",
    "sg:tags":[
        "fencing",
        "contractor"
    ],
    "wof:name":"Western Fencing Company",
    "wof:placetype":"venue"
},
  "geometry": {"coordinates":[144.76788300000001,-37.742065],"type":"Point"}
}