{
  "type": "Feature",
  "properties": {
    "addr:full":"29 McMahon St Traralgon VIC 3844",
    "addr:housenumber":"29",
    "addr:postcode":"3844",
    "addr:street":"Mcmahon St",
    "iso:country":"AU",
    "sg:address":"29 McMahon St",
    "sg:city":"Traralgon",
    "sg:classifiers":[
        {
            "category":"Building & Trades",
            "subcategory":"Plumbing",
            "type":"Services"
        }
    ],
    "sg:phone":"+61 438 539 330",
    "sg:postcode":"3844",
    "sg:province":"VIC",
    "sg:tags":[
        "plumber",
        "gasfitters"
    ],
    "wof:name":"Ellis Plumbers Pty Ltd",
    "wof:placetype":"venue"
},
  "geometry": {"coordinates":[146.55734252900001,-38.1902961731],"type":"Point"}
}