{
  "type": "Feature",
  "properties": {
    "addr:full":"183 Princes Hwy Dandenong VIC 3175",
    "addr:housenumber":"183",
    "addr:postcode":"3175",
    "addr:street":"Princes Hwy",
    "iso:country":"AU",
    "sg:address":"183 Princes Hwy",
    "sg:city":"Dandenong",
    "sg:classifiers":[
        {
            "category":"Autos & Motor Vehicles",
            "subcategory":"Automobile Sales",
            "type":"Retail Goods"
        }
    ],
    "sg:phone":"+61 3 9791 4677",
    "sg:postcode":"3175",
    "sg:province":"VIC",
    "sg:tags":[
        "car",
        "used"
    ],
    "wof:name":"R.G.S. Motors",
    "wof:placetype":"venue"
},
  "geometry": {"coordinates":[145.20138549800001,-37.9737625122],"type":"Point"}
}