{
  "type": "Feature",
  "properties": {
    "addr:full":"87 Hall St Semaphore SA 5019",
    "addr:housenumber":"87",
    "addr:postcode":"5019",
    "addr:street":"Hall St",
    "iso:country":"AU",
    "sg:address":"87 Hall St",
    "sg:city":"Semaphore",
    "sg:classifiers":[
        {
            "category":"Social Services",
            "subcategory":"Retirement Home",
            "type":"Services"
        }
    ],
    "sg:phone":"+61 8 8449 5990",
    "sg:postcode":"5019",
    "sg:province":"SA",
    "sg:tags":[
        "accommodation",
        "special"
    ],
    "wof:name":"Seabreeze Villa",
    "wof:placetype":"venue"
},
  "geometry": {"coordinates":[138.487182617,-34.8370323181],"type":"Point"}
}