{
  "type": "Feature",
  "properties": {
    "addr:full":"73 Park Rd Homebush NSW 2140",
    "addr:housenumber":"73",
    "addr:postcode":"2140",
    "addr:street":"Park Rd",
    "iso:country":"AU",
    "sg:address":"73 Park Rd",
    "sg:city":"Homebush",
    "sg:classifiers":[
        {
            "category":"Retail",
            "subcategory":"Auto Repair",
            "type":"Services"
        }
    ],
    "sg:phone":"+61 2 9746 6141",
    "sg:postcode":"2140",
    "sg:province":"NSW",
    "sg:tags":[
        "beater",
        "painter",
        "panel"
    ],
    "wof:name":"Bransby Smash Repairs",
    "wof:placetype":"venue"
},
  "geometry": {"coordinates":[151.08206176799999,-33.8634757996],"type":"Point"}
}