{
  "type": "Feature",
  "properties": {
    "addr:full":"303 Bexley Rd Bexley North NSW 2207",
    "addr:housenumber":"303",
    "addr:postcode":"2207",
    "addr:street":"Bexley Rd",
    "iso:country":"AU",
    "sg:address":"303 Bexley Rd",
    "sg:city":"Bexley North",
    "sg:classifiers":[
        {
            "category":"Health Services",
            "subcategory":"Dentist",
            "type":"Services"
        }
    ],
    "sg:phone":"+61 2 9554 3254",
    "sg:postcode":"2207",
    "sg:province":"NSW",
    "wof:name":"Tsepetzis George",
    "wof:placetype":"venue"
},
  "geometry": {"coordinates":[151.115555,-33.94054],"type":"Point"}
}