{
  "type": "Feature",
  "properties": {
    "addr:full":"277 Hancock St Doubleview WA 6018",
    "addr:housenumber":"277",
    "addr:postcode":"6018",
    "addr:street":"Hancock St",
    "iso:country":"AU",
    "sg:address":"277 Hancock St",
    "sg:city":"Doubleview",
    "sg:classifiers":[
        {
            "category":"Home & Garden",
            "subcategory":"Building Materials",
            "type":"Retail Goods"
        }
    ],
    "sg:phone":"+61 403 860 402",
    "sg:postcode":"6018",
    "sg:province":"WA",
    "sg:tags":[
        "lawn",
        "cutting",
        "maintenance"
    ],
    "wof:name":"B & H Watts Home and Garden Services",
    "wof:placetype":"venue"
},
  "geometry": {"coordinates":[115.779899597,-31.8972702026],"type":"Point"}
}