{
  "type": "Feature",
  "properties": {
    "iso:country":"AU",
    "sg:address":"166 Pacific Hwy",
    "sg:city":"Wyong",
    "sg:classifiers":[
        {
            "category":"Home & Garden",
            "subcategory":"Building Materials",
            "type":"Retail Goods"
        }
    ],
    "sg:phone":"+61 13 16 16",
    "sg:postcode":"2259",
    "sg:province":"NSW",
    "sg:tags":[
        "merchant",
        "glass",
        "glazier"
    ],
    "wof:name":"O&#039;Brien",
    "wof:placetype":"venue"
},
  "geometry": {"coordinates":[151.42953491200001,-33.2738265991],"type":"Point"}
}