{
  "type": "Feature",
  "properties": {
    "addr:full":"971 Beaufort St Inglewood WA 6052",
    "addr:housenumber":"971",
    "addr:postcode":"6052",
    "addr:street":"Beaufort St",
    "iso:country":"AU",
    "sg:address":"971 Beaufort St",
    "sg:city":"Inglewood",
    "sg:classifiers":[
        {
            "category":"Fast Food",
            "type":"Food & Drink"
        }
    ],
    "sg:phone":"+61 8 9371 3700",
    "sg:postcode":"6052",
    "sg:province":"WA",
    "sg:tags":[
        "away",
        "take"
    ],
    "wof:name":"Charcoal Chicken",
    "wof:placetype":"venue"
},
  "geometry": {"coordinates":[115.886642456,-31.9209842682],"type":"Point"}
}