{
  "type": "Feature",
  "properties": {
    "iso:country":"AU",
    "sg:address":"65 Great North Rd",
    "sg:city":"Five Dock",
    "sg:classifiers":[
        {
            "category":"Health Services",
            "subcategory":"Dentist",
            "type":"Services"
        }
    ],
    "sg:phone":"+61 2 9713 7337",
    "sg:postcode":"2046",
    "sg:province":"NSW",
    "wof:name":"Cistulli J",
    "wof:placetype":"venue"
},
  "geometry": {"coordinates":[151.129089,-33.870308],"type":"Point"}
}