{
  "type": "Feature",
  "properties": {
    "iso:country":"AU",
    "sg:address":"7 Ada St",
    "sg:city":"Vincentia",
    "sg:classifiers":[
        {
            "category":"Building & Trades",
            "subcategory":"Construction",
            "type":"Services"
        }
    ],
    "sg:phone":"+61 2 4441 5366",
    "sg:postcode":"2540",
    "sg:province":"NSW",
    "sg:tags":[
        "earth",
        "excavating",
        "moving",
        "contractor"
    ],
    "wof:name":"David Sheehy Bobcat Hire",
    "wof:placetype":"venue"
},
  "geometry": {"coordinates":[150.67779540999999,-35.0716743469],"type":"Point"}
}