{
  "type": "Feature",
  "properties": {
    "addr:full":"Colivas Rd Fannie Bay NT 0820",
    "addr:postcode":"nt 0820",
    "addr:street":"Colivas Rd",
    "iso:country":"AU",
    "sg:address":"Colivas Rd",
    "sg:city":"Fannie Bay",
    "sg:classifiers":[
        {
            "category":"Autos & Motor Vehicles",
            "subcategory":"Motorcycle Sales",
            "type":"Retail Goods"
        }
    ],
    "sg:phone":"+61 8 8981 7481",
    "sg:postcode":"0820",
    "sg:province":"NT",
    "sg:tags":[
        "outboard"
    ],
    "wof:name":"Spot On Marine",
    "wof:placetype":"venue"
},
  "geometry": {"coordinates":[130.83314514200001,-12.4137239456],"type":"Point"}
}