{
  "type": "Feature",
  "properties": {
    "addr:full":"339 Ruthven St Toowoomba QLD 4350",
    "addr:housenumber":"339",
    "addr:postcode":"4350",
    "addr:street":"Ruthven St",
    "iso:country":"AU",
    "sg:address":"339 Ruthven St",
    "sg:city":"Toowoomba",
    "sg:classifiers":[
        {
            "category":"Banks & Credit Unions",
            "subcategory":"Financial Services",
            "type":"Services"
        }
    ],
    "sg:phone":"+61 7 4632 0546",
    "sg:postcode":"4350",
    "sg:province":"QLD",
    "sg:tags":[
        "coin"
    ],
    "wof:name":"Collectable Creations",
    "wof:placetype":"venue"
},
  "geometry": {"coordinates":[151.93682899999999,-27.562117],"type":"Point"}
}