{
  "type": "Feature",
  "properties": {
    "iso:country":"AU",
    "sg:address":"3/ 51 Ferry Rd",
    "sg:city":"Southport",
    "sg:classifiers":[
        {
            "category":"Retail",
            "subcategory":"Auto Repair",
            "type":"Services"
        }
    ],
    "sg:phone":"+61 7 5532 7871",
    "sg:postcode":"4215",
    "sg:province":"QLD",
    "sg:tags":[
        "repairer",
        "motor",
        "engineer"
    ],
    "wof:name":"Surfside Auto Repairs",
    "wof:placetype":"venue"
},
  "geometry": {"coordinates":[153.41070556599999,-27.9759254456],"type":"Point"}
}