{
  "type": "Feature",
  "properties": {
    "addr:full":"415 William St Perth WA 6000",
    "addr:housenumber":"415",
    "addr:postcode":"6000",
    "addr:street":"William St",
    "iso:country":"AU",
    "sg:address":"415 William St",
    "sg:city":"Perth",
    "sg:classifiers":[
        {
            "category":"Transit Center",
            "subcategory":"Passenger",
            "type":"Transportation"
        }
    ],
    "sg:phone":"+61 8 9328 2813",
    "sg:postcode":"6000",
    "sg:province":"WA",
    "sg:tags":[
        "frozen",
        "food",
        "retail"
    ],
    "wof:name":"Centurion Seafood WA Pty Ltd",
    "wof:placetype":"venue"
},
  "geometry": {"coordinates":[115.856658935,-31.9540195465],"type":"Point"}
}