{
  "type": "Feature",
  "properties": {
    "addr:full":"Unit 2, 24 Barralong Rd Erina NSW 2250",
    "addr:housenumber":"24",
    "addr:postcode":"2250",
    "addr:street":"Barralong Rd",
    "iso:country":"AU",
    "sg:address":"Unit 2, 24 Barralong Rd",
    "sg:city":"Erina",
    "sg:classifiers":[
        {
            "category":"Building & Trades",
            "subcategory":"Construction",
            "type":"Services"
        }
    ],
    "sg:phone":"+61 2 4365 0559",
    "sg:postcode":"2250",
    "sg:province":"NSW",
    "sg:tags":[
        "contractor"
    ],
    "wof:name":"Additions Up & Out",
    "wof:placetype":"venue"
},
  "geometry": {"coordinates":[151.385528564,-33.4333114624],"type":"Point"}
}