{
  "type": "Feature",
  "properties": {
    "addr:full":"7 Brooklyn Ave Dandenong VIC 3175",
    "addr:housenumber":"7",
    "addr:postcode":"3175",
    "addr:street":"Brooklyn Ave",
    "iso:country":"AU",
    "sg:address":"7 Brooklyn Ave",
    "sg:city":"Dandenong",
    "sg:classifiers":[
        {
            "category":"Professional",
            "subcategory":"Engineering",
            "type":"Services"
        }
    ],
    "sg:phone":"+61 3 9794 5766",
    "sg:postcode":"3175",
    "sg:province":"VIC",
    "sg:tags":[
        "engineer"
    ],
    "wof:name":"Ausmech Engineering Pty Ltd",
    "wof:placetype":"venue"
},
  "geometry": {"coordinates":[145.19767761200001,-37.9933242798],"type":"Point"}
}