{
  "type": "Feature",
  "properties": {
    "addr:full":"8 Irymple Ave St Kilda VIC 3182",
    "addr:housenumber":"8",
    "addr:postcode":"3182",
    "addr:street":"Irymple Ave",
    "iso:country":"AU",
    "sg:address":"8 Irymple Ave",
    "sg:city":"St Kilda",
    "sg:classifiers":[
        {
            "category":"Real Estate",
            "subcategory":"Architect",
            "type":"Services"
        }
    ],
    "sg:phone":"+61 3 9534 1462",
    "sg:postcode":"3182",
    "sg:province":"VIC",
    "wof:name":"Schenkel Peter C",
    "wof:placetype":"venue"
},
  "geometry": {"coordinates":[144.986083984,-37.8688964844],"type":"Point"}
}