{
  "type": "Feature",
  "properties": {
    "iso:country":"AU",
    "sg:address":"20 Murrumba Drv",
    "sg:city":"Ashmore",
    "sg:classifiers":[
        {
            "category":"Building & Trades",
            "subcategory":"Landscaping Services",
            "type":"Services"
        }
    ],
    "sg:phone":"+61 7 5539 4143",
    "sg:postcode":"4214",
    "sg:province":"QLD",
    "sg:tags":[
        "gardener"
    ],
    "wof:name":"Neat As A Pin",
    "wof:placetype":"venue"
},
  "geometry": {"coordinates":[153.37266540499999,-27.9874458313],"type":"Point"}
}