{
  "type": "Feature",
  "properties": {
    "addr:full":"17 Acrylon Rd Salisbury South SA 5106",
    "addr:housenumber":"17",
    "addr:postcode":"5106",
    "addr:street":"Acrylon Rd",
    "iso:country":"AU",
    "sg:address":"17 Acrylon Rd",
    "sg:city":"Salisbury South",
    "sg:classifiers":[
        {
            "category":"Autos & Motor Vehicles",
            "subcategory":"Boat Sales",
            "type":"Retail Goods"
        }
    ],
    "sg:phone":"+61 8 8283 0933",
    "sg:postcode":"5106",
    "sg:province":"SA",
    "sg:tags":[
        "builder",
        "yacht",
        "repairer"
    ],
    "wof:name":"Complete Boat Care",
    "wof:placetype":"venue"
},
  "geometry": {"coordinates":[138.64308199999999,-34.78223],"type":"Point"}
}