{
  "type": "Feature",
  "properties": {
    "addr:full":"699 Albany Creek Rd Albany Creek QLD 4035",
    "addr:housenumber":"699",
    "addr:postcode":"4035",
    "addr:street":"Albany Creek Rd",
    "iso:country":"AU",
    "sg:address":"699 Albany Creek Rd",
    "sg:city":"Albany Creek",
    "sg:classifiers":[
        {
            "category":"Health Services",
            "subcategory":"Dentist",
            "type":"Services"
        }
    ],
    "sg:phone":"+61 7 3878 2519",
    "sg:postcode":"4035",
    "sg:province":"QLD",
    "sg:tags":[
        "periodontist"
    ],
    "wof:name":"Foundation Dental Services",
    "wof:placetype":"venue"
},
  "geometry": {"coordinates":[152.965836,-27.345341],"type":"Point"}
}