{
  "type": "Feature",
  "properties": {
    "addr:full":"PO Box 6767 Charnwood ACT 2615",
    "addr:postcode":"2615",
    "iso:country":"AU",
    "sg:address":"PO Box 6767",
    "sg:city":"Charnwood",
    "sg:classifiers":[
        {
            "category":"Utilities",
            "subcategory":"Refuse",
            "type":"Services"
        }
    ],
    "sg:phone":"+61 2 6278 3168",
    "sg:postcode":"2615",
    "sg:province":"ACT",
    "sg:tags":[
        "disposal",
        "reduction",
        "waste"
    ],
    "wof:name":"A1 Bins",
    "wof:placetype":"venue"
},
  "geometry": {"coordinates":[149.032348633,-35.1979789734],"type":"Point"}
}