{
  "type": "Feature",
  "properties": {
    "addr:full":"22 Liverpool St Port Lincoln SA 5606",
    "addr:housenumber":"22",
    "addr:postcode":"5606",
    "addr:street":"Liverpool St",
    "iso:country":"AU",
    "sg:address":"22 Liverpool St",
    "sg:city":"Port Lincoln",
    "sg:classifiers":[
        {
            "category":"Health Services",
            "subcategory":"Optometrist",
            "type":"Services"
        }
    ],
    "sg:phone":"+61 8 8682 4566",
    "sg:postcode":"5606",
    "sg:province":"SA",
    "wof:name":"Clem Philip",
    "wof:placetype":"venue"
},
  "geometry": {"coordinates":[135.85841400000001,-34.722256],"type":"Point"}
}