{
  "type": "Feature",
  "properties": {
    "iso:country":"AU",
    "sg:address":"76 Kularoo Drv",
    "sg:city":"Forster",
    "sg:classifiers":[
        {
            "category":"Professional",
            "subcategory":"Detective & Security Services",
            "type":"Services"
        }
    ],
    "sg:phone":"+61 2 6554 7018",
    "sg:postcode":"2428",
    "sg:province":"NSW",
    "sg:tags":[
        "equipment",
        "window",
        "doors"
    ],
    "wof:name":"MILLIGAN'S SHOWER SCREENS",
    "wof:placetype":"venue"
},
  "geometry": {"coordinates":[152.524246,-32.197327],"type":"Point"}
}