{
  "type": "Feature",
  "properties": {
    "addr:full":"2/ 37 Rowell St Zillmere QLD 4034",
    "addr:housenumber":"/ 37",
    "addr:postcode":"4034",
    "addr:street":"Rowell St",
    "iso:country":"AU",
    "sg:address":"2/ 37 Rowell St",
    "sg:city":"Zillmere",
    "sg:classifiers":[
        {
            "category":"Food & Beverages",
            "subcategory":"Specialty",
            "type":"Retail Goods"
        }
    ],
    "sg:phone":"+61 7 3265 6154",
    "sg:postcode":"4034",
    "sg:province":"QLD",
    "sg:tags":[
        "product",
        "health"
    ],
    "wof:name":"Herbalife Zillmere",
    "wof:placetype":"venue"
},
  "geometry": {"coordinates":[153.041595,-27.358088],"type":"Point"}
}