{
  "type": "Feature",
  "properties": {
    "iso:country":"AU",
    "sg:address":"9 Robinlee Ave",
    "sg:city":"Burwood East",
    "sg:classifiers":[
        {
            "category":"Professional",
            "subcategory":"Accounting & Tax Preparation",
            "type":"Services"
        }
    ],
    "sg:phone":"+61 3 9803 4198",
    "sg:postcode":"3151",
    "sg:province":"VIC",
    "sg:tags":[
        "accountant",
        "auditor"
    ],
    "wof:name":"Luke Dullens",
    "wof:placetype":"venue"
},
  "geometry": {"coordinates":[145.15919494600001,-37.8465576172],"type":"Point"}
}