{
  "type": "Feature",
  "properties": {
    "addr:full":"263 Macquarie St Hobart TAS 7000",
    "addr:housenumber":"263",
    "addr:postcode":"7000",
    "addr:street":"Macquarie St",
    "iso:country":"AU",
    "sg:address":"263 Macquarie St",
    "sg:city":"Hobart",
    "sg:classifiers":[
        {
            "category":"Professional",
            "subcategory":"Business Services",
            "type":"Services"
        }
    ],
    "sg:phone":"+61 3 6224 9393",
    "sg:postcode":"7000",
    "sg:province":"TAS",
    "sg:tags":[
        "drafting"
    ],
    "wof:name":"Shorter & Lloyd Architectural Design & Drafting",
    "wof:placetype":"venue"
},
  "geometry": {"coordinates":[147.32139587399999,-42.8893508911],"type":"Point"}
}