{
  "type": "Feature",
  "properties": {
    "iso:country":"AU",
    "sg:address":"Cnr Garland & Leahy Sts",
    "sg:city":"Dalwallinu",
    "sg:classifiers":[
        {
            "category":"Home & Garden",
            "subcategory":"Garden Supply",
            "type":"Retail Goods"
        }
    ],
    "sg:phone":"+61 8 9661 1264",
    "sg:postcode":"6609",
    "sg:province":"WA",
    "sg:tags":[
        "fertilizer"
    ],
    "wof:name":"Sprigg L J & M A & Sons",
    "wof:placetype":"venue"
},
  "geometry": {"coordinates":[116.665489197,-30.2796993256],"type":"Point"}
}