{
  "type": "Feature",
  "properties": {
    "addr:full":"356 Keilor Rd Niddrie VIC 3042",
    "addr:housenumber":"356",
    "addr:postcode":"3042",
    "addr:street":"Keilor Rd",
    "iso:country":"AU",
    "sg:address":"356 Keilor Rd",
    "sg:city":"Niddrie",
    "sg:classifiers":[
        {
            "category":"Health Services",
            "subcategory":"Optometrist",
            "type":"Services"
        }
    ],
    "sg:phone":"+61 3 9374 4211",
    "sg:postcode":"3042",
    "sg:province":"VIC",
    "wof:name":"Di Falco Sam Mr",
    "wof:placetype":"venue"
},
  "geometry": {"coordinates":[144.89047241200001,-37.7364196777],"type":"Point"}
}