{
  "type": "Feature",
  "properties": {
    "addr:full":"PO Box 373 Balmain NSW 2041",
    "addr:postcode":"2041",
    "iso:country":"AU",
    "sg:address":"PO Box 373",
    "sg:city":"Balmain",
    "sg:classifiers":[
        {
            "category":"Building & Trades",
            "subcategory":"Landscaping Services",
            "type":"Services"
        }
    ],
    "sg:phone":"+61 2 9518 1662",
    "sg:postcode":"2041",
    "sg:province":"NSW",
    "sg:tags":[
        "designer",
        "landscape",
        "contractor"
    ],
    "wof:name":"Alberts Garden & Maintenance",
    "wof:placetype":"venue"
},
  "geometry": {"coordinates":[151.17602500000001,-33.85603],"type":"Point"}
}