{
  "type": "Feature",
  "properties": {
    "addr:full":"2 Mcpherson Rd Wyong NSW 2259",
    "addr:housenumber":"2",
    "addr:postcode":"2259",
    "addr:street":"Mcpherson Rd",
    "iso:country":"AU",
    "sg:address":"2 Mcpherson Rd",
    "sg:city":"Wyong",
    "sg:classifiers":[
        {
            "category":"Home & Garden",
            "subcategory":"Building Materials",
            "type":"Retail Goods"
        }
    ],
    "sg:phone":"+61 2 4351 9911",
    "sg:postcode":"2259",
    "sg:province":"NSW",
    "sg:tags":[
        "plaster",
        "plasterboard",
        "supply"
    ],
    "wof:name":"Beveridges Plasterboard Co the Pty Ltd",
    "wof:placetype":"venue"
},
  "geometry": {"coordinates":[151.421676636,-33.2911376953],"type":"Point"}
}