{
  "type": "Feature",
  "properties": {
    "addr:full":"The Centreway Waverly Rd Lara VIC 3212",
    "addr:postcode":"3212",
    "addr:street":"Waverly Rd",
    "iso:country":"AU",
    "sg:address":"The Centreway Waverly Rd",
    "sg:city":"Lara",
    "sg:classifiers":[
        {
            "category":"Food & Beverages",
            "subcategory":"Supermarket",
            "type":"Retail Goods"
        }
    ],
    "sg:phone":"+61 3 5282 1243",
    "sg:postcode":"3212",
    "sg:province":"VIC",
    "sg:tags":[
        "grocery",
        "store"
    ],
    "wof:name":"Safeway",
    "wof:placetype":"venue"
},
  "geometry": {"coordinates":[144.40692138700001,-38.0224838257],"type":"Point"}
}