{
  "type": "Feature",
  "properties": {
    "addr:full":"Shop 3a, 40 Waddell Rd Bicton WA 6157",
    "addr:housenumber":"shop 3a 40",
    "addr:postcode":"6157",
    "addr:street":"Waddell Rd",
    "iso:country":"AU",
    "sg:address":"Shop 3a, 40 Waddell Rd",
    "sg:city":"Bicton",
    "sg:classifiers":[
        {
            "category":"Personal",
            "subcategory":"Beauty Salon",
            "type":"Services"
        }
    ],
    "sg:phone":"+61 8 9319 8828",
    "sg:postcode":"6157",
    "sg:province":"WA",
    "sg:tags":[
        "hairdresser"
    ],
    "wof:name":"Raven Hair Design",
    "wof:placetype":"venue"
},
  "geometry": {"coordinates":[115.79257200000001,-32.034264],"type":"Point"}
}