{
  "type": "Feature",
  "properties": {
    "addr:full":"Shp3/ 44 Bulcock St Caloundra QLD 4551",
    "addr:postcode":"4551",
    "addr:street":"Bulcock St",
    "iso:country":"AU",
    "sg:address":"Shp3/ 44 Bulcock St",
    "sg:city":"Caloundra",
    "sg:classifiers":[
        {
            "category":"Shopping",
            "subcategory":"Clothing, Apparel, & Fashions",
            "type":"Retail Goods"
        }
    ],
    "sg:phone":"+61 7 5499 6010",
    "sg:postcode":"4551",
    "sg:province":"QLD",
    "sg:tags":[
        "accessory"
    ],
    "wof:name":"Emporium Faszination",
    "wof:placetype":"venue"
},
  "geometry": {"coordinates":[153.129440308,-26.8046550751],"type":"Point"}
}