{
  "type": "Feature",
  "properties": {
    "iso:country":"AU",
    "sg:address":"Lvl2/ 66 Archer St",
    "sg:city":"Chatswood",
    "sg:classifiers":[
        {
            "category":"Professional",
            "subcategory":"Business Services",
            "type":"Services"
        }
    ],
    "sg:phone":"+61 2 9411 4297",
    "sg:postcode":"2057",
    "sg:province":"NSW",
    "sg:tags":[
        "broker"
    ],
    "wof:name":"Power Growth Australia",
    "wof:placetype":"venue"
},
  "geometry": {"coordinates":[151.185623,-33.796547],"type":"Point"}
}