{
  "type": "Feature",
  "properties": {
    "addr:full":"4 St Ives Loop Kallaroo WA 6025",
    "addr:housenumber":"4",
    "addr:postcode":"6025",
    "addr:street":"St Ives Loop",
    "iso:country":"AU",
    "sg:address":"4 St",
    "sg:city":"Ives Loop Kallaroo",
    "sg:classifiers":[
        {
            "category":"Social Services",
            "subcategory":"Retirement Home",
            "type":"Services"
        }
    ],
    "sg:phone":"+61 8 9307 1469",
    "sg:postcode":"6025",
    "sg:province":"WA",
    "sg:tags":[
        "environmental",
        "consultant",
        "pollution"
    ],
    "wof:name":"Murex Consultants Pty Ltd",
    "wof:placetype":"venue"
},
  "geometry": {"coordinates":[115.736152649,-31.7932662964],"type":"Point"}
}