{
  "type": "Feature",
  "properties": {
    "addr:full":"62 Centre St Casino NSW 2470",
    "addr:housenumber":"62",
    "addr:postcode":"2470",
    "addr:street":"Centre St",
    "iso:country":"AU",
    "sg:address":"62 Centre St",
    "sg:city":"Casino",
    "sg:classifiers":[
        {
            "category":"Health Services",
            "subcategory":"Nursing And Care Facility",
            "type":"Services"
        }
    ],
    "sg:phone":"+61 2 6662 1433",
    "sg:postcode":"2470",
    "sg:province":"NSW",
    "sg:tags":[
        "home"
    ],
    "wof:name":"St Michaels Home For The Aged",
    "wof:placetype":"venue"
},
  "geometry": {"coordinates":[153.04745483400001,-28.8560276031],"type":"Point"}
}