{
  "type": "Feature",
  "properties": {
    "addr:full":"Clayton St Bellevue WA 6056",
    "addr:postcode":"6056",
    "addr:street":"Clayton St",
    "iso:country":"AU",
    "sg:address":"Clayton St",
    "sg:city":"Bellevue",
    "sg:classifiers":[
        {
            "category":"Retail",
            "subcategory":"Auto Repair",
            "type":"Services"
        }
    ],
    "sg:phone":"+61 419 615 544",
    "sg:postcode":"6056",
    "sg:province":"WA",
    "sg:tags":[
        "bus",
        "truck"
    ],
    "wof:name":"B.I.T.S. Engineering",
    "wof:placetype":"venue"
},
  "geometry": {"coordinates":[116.020759583,-31.8990821838],"type":"Point"}
}