{
  "type": "Feature",
  "properties": {
    "addr:full":"358A Main Rd Toukley NSW 2263",
    "addr:housenumber":"358a",
    "addr:postcode":"2263",
    "addr:street":"Main Rd",
    "iso:country":"AU",
    "sg:address":"358A Main Rd",
    "sg:city":"Toukley",
    "sg:classifiers":[
        {
            "category":"Professional",
            "type":"Services"
        }
    ],
    "sg:phone":"+61 2 4396 5971",
    "sg:postcode":"2263",
    "sg:province":"NSW",
    "sg:tags":[
        "shop",
        "fitting"
    ],
    "wof:name":"Central Coast Rack & Shelving",
    "wof:placetype":"venue"
},
  "geometry": {"coordinates":[151.548416,-33.266136],"type":"Point"}
}