{
  "type": "Feature",
  "properties": {
    "addr:full":"62 Hartnett Drv Seaford VIC 3198",
    "addr:housenumber":"62",
    "addr:postcode":"3198",
    "addr:street":"Hartnett Drv",
    "iso:country":"AU",
    "sg:address":"62 Hartnett Drv",
    "sg:city":"Seaford",
    "sg:classifiers":[
        {
            "category":"Manufacturing",
            "subcategory":"Textiles",
            "type":"Manufacturing & Wholesale Goods"
        }
    ],
    "sg:phone":"+61 3 9786 1113",
    "sg:postcode":"3198",
    "sg:province":"VIC",
    "sg:tags":[
        "wholesaler",
        "knitwear",
        "mfrs"
    ],
    "wof:name":"Hysport International",
    "wof:placetype":"venue"
},
  "geometry": {"coordinates":[145.14051818900001,-38.117389679],"type":"Point"}
}