{
  "type": "Feature",
  "properties": {
    "iso:country":"AU",
    "sg:address":"PO Box 74",
    "sg:city":"Cottesloe",
    "sg:classifiers":[
        {
            "category":"Building & Trades",
            "subcategory":"Landscaping Services",
            "type":"Services"
        }
    ],
    "sg:phone":"+61 419 899 492",
    "sg:postcode":"6011",
    "sg:province":"WA",
    "sg:tags":[
        "designer",
        "landscape",
        "contractor"
    ],
    "wof:name":"Kate Kenny Garden Design",
    "wof:placetype":"venue"
},
  "geometry": {"coordinates":[115.757278442,-31.996049881],"type":"Point"}
}