{
  "type": "Feature",
  "properties": {
    "iso:country":"AU",
    "sg:address":"Manor Lakes Shopping Cntr Cnr Ballan Rd & Manor Lakes Blv",
    "sg:city":"Wyndham Vale",
    "sg:classifiers":[
        {
            "category":"Fast Food",
            "type":"Food & Drink"
        }
    ],
    "sg:phone":"+61 3 9741 7322",
    "sg:postcode":"3024",
    "sg:province":"VIC",
    "sg:tags":[
        "away",
        "take"
    ],
    "wof:name":"Red Rooster",
    "wof:placetype":"venue"
},
  "geometry": {"coordinates":[144.62574799999999,-37.886162],"type":"Point"}
}