{
  "type": "Feature",
  "properties": {
    "addr:full":"85 Vines Rd Hamlyn Heights VIC 3215",
    "addr:housenumber":"85",
    "addr:postcode":"3215",
    "addr:street":"Vines Rd",
    "iso:country":"AU",
    "sg:address":"85 Vines Rd",
    "sg:city":"Hamlyn Heights",
    "sg:classifiers":[
        {
            "category":"Building & Trades",
            "subcategory":"Construction",
            "type":"Services"
        }
    ],
    "sg:phone":"+61 3 5240 4111",
    "sg:postcode":"3215",
    "sg:province":"VIC",
    "sg:tags":[
        "renovation",
        "alterations",
        "extension",
        "contractor"
    ],
    "wof:name":"Trendcraft Property Services Pty Ltd",
    "wof:placetype":"venue"
},
  "geometry": {"coordinates":[144.328369141,-38.1212120056],"type":"Point"}
}