{
  "type": "Feature",
  "properties": {
    "iso:country":"AU",
    "sg:address":"Shp 1/ Pethybridge Cl",
    "sg:city":"Dingley Village",
    "sg:classifiers":[
        {
            "category":"Personal",
            "subcategory":"Beauty Salon",
            "type":"Services"
        }
    ],
    "sg:phone":"+61 3 9558 1228",
    "sg:postcode":"3172",
    "sg:province":"VIC",
    "wof:name":"About Beauty",
    "wof:placetype":"venue"
},
  "geometry": {"coordinates":[145.13380432100001,-37.9817695618],"type":"Point"}
}