{
  "type": "Feature",
  "properties": {
    "addr:full":"138 Coppin St Richmond VIC 3121",
    "addr:housenumber":"138",
    "addr:postcode":"3121",
    "addr:street":"Coppin St",
    "iso:country":"AU",
    "sg:address":"138 Coppin St",
    "sg:city":"Richmond",
    "sg:classifiers":[
        {
            "category":"Health Services",
            "subcategory":"Health Practitioner",
            "type":"Services"
        }
    ],
    "sg:phone":"+61 3 9429 0290",
    "sg:postcode":"3121",
    "sg:province":"VIC",
    "sg:tags":[
        "acupuncture"
    ],
    "wof:name":"My Urban Oasis",
    "wof:placetype":"venue"
},
  "geometry": {"coordinates":[145.00291442899999,-37.8228721619],"type":"Point"}
}