{
  "type": "Feature",
  "properties": {
    "iso:country":"AU",
    "sg:address":"21 Tuaggra St",
    "sg:city":"Maryborough",
    "sg:classifiers":[
        {
            "category":"Food & Beverages",
            "subcategory":"Bakery",
            "type":"Retail Goods"
        }
    ],
    "sg:phone":"+61 3 5461 4655",
    "sg:postcode":"3465",
    "sg:province":"VIC",
    "sg:tags":[
        "baker"
    ],
    "wof:name":"Parkview Bakery",
    "wof:placetype":"venue"
},
  "geometry": {"coordinates":[143.74134826700001,-37.0476455688],"type":"Point"}
}