{
  "type": "Feature",
  "properties": {
    "addr:full":"Shop 13 Sunnybank Plaza Cnr Mains Rd & McCullough Sunnybank QLD 4109",
    "addr:housenumber":"shop 13",
    "addr:postcode":"4109",
    "addr:street":"Sunnybank Plaza Cnr Mains Rd &",
    "iso:country":"AU",
    "sg:address":"Shop 13 Sunnybank Plaza Cnr Mains Rd & McCullough",
    "sg:city":"Sunnybank",
    "sg:classifiers":[
        {
            "category":"Personal",
            "subcategory":"Beauty Salon",
            "type":"Services"
        }
    ],
    "sg:phone":"+61 7 3344 2611",
    "sg:postcode":"4109",
    "sg:province":"QLD",
    "sg:tags":[
        "hairdresser"
    ],
    "wof:name":"Price Attack",
    "wof:placetype":"venue"
},
  "geometry": {"coordinates":[153.06275939899999,-27.5783214569],"type":"Point"}
}