{
  "type": "Feature",
  "properties": {
    "addr:full":"22 Cabarita Rd Concord NSW 2137",
    "addr:housenumber":"22",
    "addr:postcode":"2137",
    "addr:street":"Cabarita Rd",
    "iso:country":"AU",
    "sg:address":"22 Cabarita Rd",
    "sg:city":"Concord",
    "sg:classifiers":[
        {
            "category":"Fast Food",
            "type":"Food & Drink"
        }
    ],
    "sg:phone":"+61 2 9743 1807",
    "sg:postcode":"2137",
    "sg:province":"NSW",
    "sg:tags":[
        "away",
        "take"
    ],
    "wof:name":"Theos Seafood Take Away",
    "wof:placetype":"venue"
},
  "geometry": {"coordinates":[151.10658264200001,-33.8519973755],"type":"Point"}
}