{
  "type": "Feature",
  "properties": {
    "addr:full":"Centenary Ave Maitland SA 5573",
    "addr:postcode":"5573",
    "addr:street":"Centenary Ave",
    "iso:country":"AU",
    "sg:address":"Centenary Ave",
    "sg:city":"Maitland",
    "sg:classifiers":[
        {
            "category":"Travel",
            "subcategory":"Hostel",
            "type":"Entertainment"
        }
    ],
    "sg:phone":"+61 8 8832 2007",
    "sg:postcode":"5573",
    "sg:province":"SA",
    "sg:tags":[
        "home"
    ],
    "wof:name":"Village Maitland The",
    "wof:placetype":"venue"
},
  "geometry": {"coordinates":[137.67556762699999,-34.3693618774],"type":"Point"}
}