{
  "type": "Feature",
  "properties": {
    "addr:full":"50 Beach St Kippa-Ring QLD 4021",
    "addr:housenumber":"50",
    "addr:postcode":"4021",
    "addr:street":"Beach St",
    "iso:country":"AU",
    "sg:address":"50 Beach St",
    "sg:city":"Kippa-Ring",
    "sg:classifiers":[
        {
            "category":"Manufacturing",
            "subcategory":"Signs",
            "type":"Manufacturing & Wholesale Goods"
        }
    ],
    "sg:phone":"+61 7 3284 9326",
    "sg:postcode":"4021",
    "sg:province":"QLD",
    "sg:tags":[
        "traffic",
        "safety"
    ],
    "wof:name":"Signs Of Safety (QLD)",
    "wof:placetype":"venue"
},
  "geometry": {"coordinates":[153.09059099999999,-27.224888],"type":"Point"}
}