{
  "type": "Feature",
  "properties": {
    "addr:full":"40 Cedar Drv Glenside SA 5065",
    "addr:housenumber":"40",
    "addr:postcode":"5065",
    "addr:street":"Cedar Drv",
    "iso:country":"AU",
    "sg:address":"40 Cedar Drv",
    "sg:city":"Glenside",
    "sg:classifiers":[
        {
            "category":"Travel",
            "subcategory":"Hotels & Motels",
            "type":"Entertainment"
        }
    ],
    "sg:phone":"+61 8 8338 2309",
    "sg:postcode":"5065",
    "sg:province":"SA",
    "wof:name":"McMahon Holdings",
    "wof:placetype":"venue"
},
  "geometry": {"coordinates":[138.63055419899999,-34.94348526],"type":"Point"}
}