{
  "type": "Feature",
  "properties": {
    "addr:full":"355 Homer St Earlwood NSW 2206",
    "addr:housenumber":"355",
    "addr:postcode":"2206",
    "addr:street":"Homer St",
    "iso:country":"AU",
    "sg:address":"355 Homer St",
    "sg:city":"Earlwood",
    "sg:classifiers":[
        {
            "category":"Real Estate",
            "subcategory":"Real Estate Agent",
            "type":"Services"
        }
    ],
    "sg:phone":"+61 2 9559 3333",
    "sg:postcode":"2206",
    "sg:province":"NSW",
    "wof:name":"Australiawide Real Estate Pty Ltd",
    "wof:placetype":"venue"
},
  "geometry": {"coordinates":[151.125092,-33.926643],"type":"Point"}
}