{
  "type": "Feature",
  "properties": {
    "addr:full":"PO Box 294 Milton NSW 2538",
    "addr:postcode":"2538",
    "iso:country":"AU",
    "sg:address":"PO Box 294",
    "sg:city":"Milton",
    "sg:classifiers":[
        {
            "category":"Professional",
            "subcategory":"Business Services",
            "type":"Services"
        }
    ],
    "sg:phone":"+61 2 4455 4207",
    "sg:postcode":"2538",
    "sg:province":"NSW",
    "sg:tags":[
        "drafting"
    ],
    "wof:name":"Milton Drafting & Design",
    "wof:placetype":"venue"
},
  "geometry": {"coordinates":[150.43661499000001,-35.316860199],"type":"Point"}
}