{
  "type": "Feature",
  "properties": {
    "addr:full":"Shp1/ 379 Burwood Rd Hawthorn VIC 3122",
    "addr:housenumber":"379",
    "addr:postcode":"3122",
    "addr:street":"Burwood Rd",
    "iso:country":"AU",
    "sg:address":"Shp1/ 379 Burwood Rd",
    "sg:city":"Hawthorn",
    "sg:classifiers":[
        {
            "category":"Personal",
            "subcategory":"Beauty Salon",
            "type":"Services"
        }
    ],
    "sg:phone":"+61 3 9818 5185",
    "sg:postcode":"3122",
    "sg:province":"VIC",
    "sg:tags":[
        "hairdresser"
    ],
    "wof:name":"80-Vol Hair Studio",
    "wof:placetype":"venue"
},
  "geometry": {"coordinates":[145.03640747099999,-37.8225517273],"type":"Point"}
}