{
  "type": "Feature",
  "properties": {
    "iso:country":"AU",
    "sg:address":"61 Township Drv",
    "sg:city":"West Burleigh",
    "sg:classifiers":[
        {
            "category":"Retail",
            "subcategory":"Storage",
            "type":"Services"
        }
    ],
    "sg:phone":"+61 7 5520 0788",
    "sg:postcode":"4219",
    "sg:province":"QLD",
    "sg:tags":[
        "removal",
        "furniture"
    ],
    "wof:name":"Johnno's Removals",
    "wof:placetype":"venue"
},
  "geometry": {"coordinates":[153.433670044,-28.1124839783],"type":"Point"}
}