{
  "type": "Feature",
  "properties": {
    "addr:full":"1617 Point Nepean Rd Rosebud West VIC 3940",
    "addr:housenumber":"1617",
    "addr:postcode":"3940",
    "addr:street":"Point Nepean Rd",
    "iso:country":"AU",
    "sg:address":"1617 Point Nepean Rd",
    "sg:city":"Rosebud West",
    "sg:classifiers":[
        {
            "category":"Fast Food",
            "type":"Food & Drink"
        }
    ],
    "sg:phone":"+61 3 5981 2654",
    "sg:postcode":"3940",
    "sg:province":"VIC",
    "sg:tags":[
        "away",
        "take"
    ],
    "wof:name":"Rosebud West Fish & Chips",
    "wof:placetype":"venue"
},
  "geometry": {"coordinates":[144.87673950199999,-38.3635787964],"type":"Point"}
}