{
  "type": "Feature",
  "properties": {
    "iso:country":"AU",
    "sg:address":"14 Norman Ave",
    "sg:city":"Auburn",
    "sg:classifiers":[
        {
            "category":"Wholesale",
            "subcategory":"Vending Machines",
            "type":"Manufacturing & Wholesale Goods"
        }
    ],
    "sg:phone":"+61 433 350 225",
    "sg:postcode":"2144",
    "sg:province":"NSW",
    "sg:tags":[
        "equipment",
        "mailing"
    ],
    "wof:name":"Mail-On Technical Services",
    "wof:placetype":"venue"
},
  "geometry": {"coordinates":[151.02423095699999,-33.8711547852],"type":"Point"}
}