{
  "type": "Feature",
  "properties": {
    "addr:full":"5 The Pde Norwood SA 5067",
    "addr:housenumber":"5",
    "addr:postcode":"5067",
    "addr:street":"The Pde",
    "iso:country":"AU",
    "sg:address":"5 The Pde",
    "sg:city":"Norwood",
    "sg:classifiers":[
        {
            "category":"Health Services",
            "subcategory":"Doctor",
            "type":"Services"
        }
    ],
    "sg:phone":"+61 8 8363 7770",
    "sg:postcode":"5067",
    "sg:province":"SA",
    "sg:tags":[
        "medical",
        "practitioner"
    ],
    "wof:name":"Mutton Catherine Dr",
    "wof:placetype":"venue"
},
  "geometry": {"coordinates":[138.62367248499999,-34.9219436646],"type":"Point"}
}