{
  "type": "Feature",
  "properties": {
    "addr:full":"9 Minmi Rd Maryland NSW 2287",
    "addr:housenumber":"9",
    "addr:postcode":"2287",
    "addr:street":"Minmi Rd",
    "iso:country":"AU",
    "sg:address":"9 Minmi Rd",
    "sg:city":"Maryland",
    "sg:classifiers":[
        {
            "category":"Retail",
            "subcategory":"Veterinary Services",
            "type":"Services"
        }
    ],
    "sg:phone":"+61 2 4965 6644",
    "sg:postcode":"2287",
    "sg:province":"NSW",
    "sg:tags":[
        "surgeon"
    ],
    "wof:name":"Minmi Road Maryland Veterinary Clinic",
    "wof:placetype":"venue"
},
  "geometry": {"coordinates":[151.66690063499999,-32.8911170959],"type":"Point"}
}