{
  "type": "Feature",
  "properties": {
    "iso:country":"AU",
    "sg:address":"Level 1, 337a Lennox St",
    "sg:city":"Richmond",
    "sg:classifiers":[
        {
            "category":"Insurance",
            "subcategory":"Life Insurance",
            "type":"Services"
        }
    ],
    "sg:phone":"+61 3 9429 7777",
    "sg:postcode":"3121",
    "sg:province":"VIC",
    "wof:name":"Andrew Young & Associates",
    "wof:placetype":"venue"
},
  "geometry": {"coordinates":[144.99357605,-37.8250732422],"type":"Point"}
}