{
  "type": "Feature",
  "properties": {
    "addr:full":"88 Duri Rd Tamworth South NSW 2340",
    "addr:postcode":"2340",
    "addr:street":"Duri Rd",
    "iso:country":"AU",
    "sg:address":"88 Duri Rd",
    "sg:city":"Tamworth South",
    "sg:classifiers":[
        {
            "category":"Retail",
            "subcategory":"Veterinary Services",
            "type":"Services"
        }
    ],
    "sg:phone":"+61 2 6765 4244",
    "sg:postcode":"2340",
    "sg:province":"NSW",
    "sg:tags":[
        "surgeon"
    ],
    "wof:name":"Best Peter",
    "wof:placetype":"venue"
},
  "geometry": {"coordinates":[150.89746093799999,-31.1108875275],"type":"Point"}
}