{
  "type": "Feature",
  "properties": {
    "iso:country":"AU",
    "sg:address":"392 Torrens Rd",
    "sg:city":"Kilkenny",
    "sg:classifiers":[
        {
            "category":"Shopping",
            "subcategory":"Pets & Pet Supplies",
            "type":"Retail Goods"
        }
    ],
    "sg:phone":"+61 8 8347 0355",
    "sg:postcode":"5009",
    "sg:province":"SA",
    "sg:tags":[
        "sheep",
        "equipment",
        "shearing"
    ],
    "wof:name":"Stockowners Shearing Australia",
    "wof:placetype":"venue"
},
  "geometry": {"coordinates":[138.55464172399999,-34.8787612915],"type":"Point"}
}