{
  "type": "Feature",
  "properties": {
    "addr:full":"PO Box 181 Port Vincent SA 5581",
    "addr:postcode":"5581",
    "iso:country":"AU",
    "sg:address":"PO Box 181",
    "sg:city":"Port Vincent",
    "sg:classifiers":[
        {
            "category":"Deli",
            "type":"Food & Drink"
        }
    ],
    "sg:phone":"+61 8 8853 7060",
    "sg:postcode":"5581",
    "sg:province":"SA",
    "sg:tags":[
        "delicatessen"
    ],
    "wof:name":"Fast &#039;n&#039; Fresh Foodstores",
    "wof:placetype":"venue"
},
  "geometry": {"coordinates":[137.83456420900001,-34.7845497131],"type":"Point"}
}