{
  "type": "Feature",
  "properties": {
    "addr:full":"36 Meylin St Port MacDonnell SA 5291",
    "addr:housenumber":"36",
    "addr:postcode":"5291",
    "addr:street":"Meylin St",
    "iso:country":"AU",
    "sg:address":"36 Meylin St",
    "sg:city":"Port MacDonnell",
    "sg:classifiers":[
        {
            "category":"Professional",
            "subcategory":"Art Services",
            "type":"Services"
        }
    ],
    "sg:phone":"+61 438 382 188",
    "sg:postcode":"5291",
    "sg:province":"SA",
    "sg:tags":[
        "decorator",
        "painter"
    ],
    "wof:name":"Murdoch R & J",
    "wof:placetype":"venue"
},
  "geometry": {"coordinates":[140.70060699999999,-38.052425],"type":"Point"}
}