{
  "type": "Feature",
  "properties": {
    "addr:full":"6 Shadlin Pl Penrith South NSW 2750",
    "addr:housenumber":"6",
    "addr:postcode":"2750",
    "addr:street":"Shadlin Pl",
    "iso:country":"AU",
    "sg:address":"6 Shadlin Pl",
    "sg:city":"Penrith South",
    "sg:classifiers":[
        {
            "category":"Building & Trades",
            "subcategory":"Plumbing",
            "type":"Services"
        }
    ],
    "sg:phone":"+61 418 645 160",
    "sg:postcode":"2750",
    "sg:province":"NSW",
    "sg:tags":[
        "plumber",
        "gasfitters"
    ],
    "wof:name":"Sipple Terry",
    "wof:placetype":"venue"
},
  "geometry": {"coordinates":[150.70195007300001,-33.7818069458],"type":"Point"}
}