{
  "type": "Feature",
  "properties": {
    "addr:full":"264 Glenmore Rd Paddington NSW 2021",
    "addr:housenumber":"264",
    "addr:postcode":"2021",
    "addr:street":"Glenmore Rd",
    "iso:country":"AU",
    "sg:address":"264 Glenmore Rd",
    "sg:city":"Paddington",
    "sg:classifiers":[
        {
            "category":"Arts & Performance",
            "subcategory":"Art Gallery",
            "type":"Entertainment"
        }
    ],
    "sg:phone":"+61 2 9361 0295",
    "sg:postcode":"2021",
    "sg:province":"NSW",
    "wof:name":"Inyaka African Art Gallery",
    "wof:placetype":"venue"
},
  "geometry": {"coordinates":[151.229415894,-33.8814315796],"type":"Point"}
}