{
  "type": "Feature",
  "properties": {
    "iso:country":"AU",
    "sg:address":"13 Jarrah Pl",
    "sg:city":"Durack",
    "sg:classifiers":[
        {
            "category":"Organizations",
            "subcategory":"Community Association",
            "type":"Services"
        }
    ],
    "sg:phone":"+61 1300 720 009",
    "sg:postcode":"4077",
    "sg:province":"QLD",
    "sg:tags":[
        "electricity",
        "control",
        "static"
    ],
    "wof:name":"ZapNo Pty Ltd",
    "wof:placetype":"venue"
},
  "geometry": {"coordinates":[152.982421875,-27.5941390991],"type":"Point"}
}