{
  "type": "Feature",
  "properties": {
    "addr:full":"97 Byrnes St Mareeba QLD 4880",
    "addr:housenumber":"97",
    "addr:postcode":"4880",
    "addr:street":"Byrnes St",
    "iso:country":"AU",
    "sg:address":"97 Byrnes St",
    "sg:city":"Mareeba",
    "sg:classifiers":[
        {
            "category":"Cafe",
            "type":"Food & Drink"
        }
    ],
    "sg:phone":"+61 7 4092 4150",
    "sg:postcode":"4880",
    "sg:province":"QLD",
    "wof:name":"Hi Ho Cafe",
    "wof:placetype":"venue"
},
  "geometry": {"coordinates":[145.422363281,-16.99376297],"type":"Point"}
}