{
  "type": "Feature",
  "properties": {
    "addr:full":"609 Hovell St Albury NSW 2640",
    "addr:housenumber":"609",
    "addr:postcode":"2640",
    "addr:street":"Hovell St",
    "iso:country":"AU",
    "sg:address":"609 Hovell St",
    "sg:city":"Albury",
    "sg:classifiers":[
        {
            "category":"Food & Beverages",
            "subcategory":"Fruits & Vegetables",
            "type":"Retail Goods"
        }
    ],
    "sg:phone":"+61 2 6021 7613",
    "sg:postcode":"2640",
    "sg:province":"NSW",
    "sg:tags":[
        "greengrocer",
        "fruiterer"
    ],
    "wof:name":"Border Fresh Fruit & Vegetables",
    "wof:placetype":"venue"
},
  "geometry": {"coordinates":[146.90951538100001,-36.0864181519],"type":"Point"}
}