{
  "type": "Feature",
  "properties": {
    "addr:full":"392- 394 Elizabeth St North Hobart TAS 7000",
    "addr:housenumber":"394",
    "addr:postcode":"7000",
    "addr:street":"Elizabeth St",
    "iso:country":"AU",
    "sg:address":"392- 394 Elizabeth St",
    "sg:city":"North Hobart",
    "sg:classifiers":[
        {
            "category":"Cafe",
            "type":"Food & Drink"
        }
    ],
    "sg:phone":"+61 3 6234 5975",
    "sg:postcode":"7000",
    "sg:province":"TAS",
    "wof:name":"Raincheck Lounge",
    "wof:placetype":"venue"
},
  "geometry": {"coordinates":[147.315216064,-42.8730964661],"type":"Point"}
}