{
  "type": "Feature",
  "properties": {
    "addr:full":"99 Shepperton Rd Victoria Park WA 6100",
    "addr:housenumber":"99",
    "addr:postcode":"6100",
    "addr:street":"Shepperton Rd",
    "iso:country":"AU",
    "sg:address":"99 Shepperton Rd",
    "sg:city":"Victoria Park",
    "sg:classifiers":[
        {
            "category":"Government",
            "subcategory":"Department Of Motor Vehicles",
            "type":"Public Place"
        }
    ],
    "sg:phone":"+61 8 9311 8111",
    "sg:postcode":"6100",
    "sg:province":"WA",
    "sg:tags":[
        "organisation",
        "local"
    ],
    "wof:name":"Victoria Park Town of",
    "wof:placetype":"venue"
},
  "geometry": {"coordinates":[115.896751404,-31.971818924],"type":"Point"}
}