{
  "type": "Feature",
  "properties": {
    "addr:full":"2/ 86 Vellgrove Ave Parkwood WA 6147",
    "addr:housenumber":"/ 86",
    "addr:postcode":"6147",
    "addr:street":"Vellgrove Ave",
    "iso:country":"AU",
    "sg:address":"2/ 86 Vellgrove Ave",
    "sg:city":"Parkwood",
    "sg:classifiers":[
        {
            "category":"Health Services",
            "subcategory":"Dentist",
            "type":"Services"
        }
    ],
    "sg:phone":"+61 8 9457 8377",
    "sg:postcode":"6147",
    "sg:province":"WA",
    "wof:name":"Welten Frank",
    "wof:placetype":"venue"
},
  "geometry": {"coordinates":[115.91973900000001,-32.049412],"type":"Point"}
}