{
  "type": "Feature",
  "properties": {
    "addr:full":"205 Victoria Pde Collingwood VIC 3066",
    "addr:housenumber":"205",
    "addr:postcode":"3066",
    "addr:street":"Victoria Pde",
    "iso:country":"AU",
    "sg:address":"205 Victoria Pde",
    "sg:city":"Collingwood",
    "sg:classifiers":[
        {
            "category":"Wholesale",
            "subcategory":"Medical Equipment & Supplies",
            "type":"Manufacturing & Wholesale Goods"
        }
    ],
    "sg:phone":"+61 1300 136 292",
    "sg:postcode":"3066",
    "sg:province":"VIC",
    "sg:tags":[
        "dental"
    ],
    "wof:name":"Forestadent",
    "wof:placetype":"venue"
},
  "geometry": {"coordinates":[144.99058532699999,-37.8094558716],"type":"Point"}
}