{
  "type": "Feature",
  "properties": {
    "addr:full":"PO Box 1014 Oxenford QLD 4210",
    "addr:postcode":"4210",
    "iso:country":"AU",
    "sg:address":"PO Box 1014",
    "sg:city":"Oxenford",
    "sg:classifiers":[
        {
            "category":"Organizations",
            "subcategory":"Professional Association",
            "type":"Services"
        }
    ],
    "sg:phone":"+61 404 673 105",
    "sg:postcode":"4210",
    "sg:province":"QLD",
    "sg:tags":[
        "web",
        "internet"
    ],
    "wof:name":"Back 9 Media",
    "wof:placetype":"venue"
},
  "geometry": {"coordinates":[153.31413269000001,-27.9020309448],"type":"Point"}
}