{
  "type": "Feature",
  "properties": {
    "addr:full":"Sydney Entertainment Centre 60 Hay St Haymarket NSW 2000",
    "addr:housenumber":"60",
    "addr:postcode":"2000",
    "addr:street":"Hay St",
    "iso:country":"AU",
    "sg:address":"Sydney Entertainment Centre 60 Hay St",
    "sg:city":"Haymarket",
    "sg:classifiers":[
        {
            "category":"Fast Food",
            "type":"Food & Drink"
        }
    ],
    "sg:phone":"+61 2 9212 2591",
    "sg:postcode":"2000",
    "sg:province":"NSW",
    "sg:tags":[
        "away",
        "take"
    ],
    "wof:name":"McDonald's Family Restaurants",
    "wof:placetype":"venue"
},
  "geometry": {"coordinates":[151.20367431599999,-33.8792648315],"type":"Point"}
}