{
  "type": "Feature",
  "properties": {
    "iso:country":"AU",
    "sg:address":"451 Churchill Ave",
    "sg:city":"Sandy Bay",
    "sg:classifiers":[
        {
            "category":"Building & Trades",
            "subcategory":"Equipment Rental",
            "type":"Services"
        }
    ],
    "sg:phone":"+61 3 6225 0228",
    "sg:postcode":"7005",
    "sg:province":"TAS",
    "sg:tags":[
        "platform",
        "hire",
        "work",
        "elevating"
    ],
    "wof:name":"Hookway Aerospace Pty Ltd",
    "wof:placetype":"venue"
},
  "geometry": {"coordinates":[147.34916687,-42.9179115295],"type":"Point"}
}