{
  "type": "Feature",
  "properties": {
    "addr:full":"77 Upper Heidelberg Rd Ivanhoe VIC 3079",
    "addr:housenumber":"77",
    "addr:postcode":"3079",
    "addr:street":"Upper Heidelberg Rd",
    "iso:country":"AU",
    "sg:address":"77 Upper Heidelberg Rd",
    "sg:city":"Ivanhoe",
    "sg:classifiers":[
        {
            "category":"Government",
            "subcategory":"Fire Station",
            "type":"Public Place"
        }
    ],
    "sg:phone":"+61 3 9499 6504",
    "sg:postcode":"3079",
    "sg:province":"VIC",
    "sg:tags":[
        "equipment",
        "protection",
        "consultant"
    ],
    "wof:name":"Australian Essential Services Group",
    "wof:placetype":"venue"
},
  "geometry": {"coordinates":[145.04103088400001,-37.7700004578],"type":"Point"}
}