{
  "type": "Feature",
  "properties": {
    "iso:country":"AU",
    "sg:address":"27 Sandalwood Ave",
    "sg:city":"Hillside",
    "sg:classifiers":[
        {
            "category":"Building & Trades",
            "subcategory":"Cleaning & Sanitation",
            "type":"Services"
        }
    ],
    "sg:phone":"+61 411 234 522",
    "sg:postcode":"3037",
    "sg:province":"VIC",
    "sg:tags":[
        "industrial",
        "commercial",
        "contractor"
    ],
    "wof:name":"MGS Grounds Maintenance",
    "wof:placetype":"venue"
},
  "geometry": {"coordinates":[144.748062,-37.684296],"type":"Point"}
}