{
  "type": "Feature",
  "properties": {
    "iso:country":"AU",
    "sg:address":"84 Benerembah St",
    "sg:city":"Griffith",
    "sg:classifiers":[
        {
            "category":"Taxi",
            "type":"Transportation"
        }
    ],
    "sg:phone":"+61 2 6962 3980",
    "sg:postcode":"2680",
    "sg:province":"NSW",
    "sg:tags":[
        "truck"
    ],
    "wof:name":"A & V Taxi Trucks",
    "wof:placetype":"venue"
},
  "geometry": {"coordinates":[146.03544600000001,-34.284897],"type":"Point"}
}