{
  "type": "Feature",
  "properties": {
    "addr:full":"2/ 14 Barnett Pl Ernest QLD 4214",
    "addr:housenumber":"/ 14",
    "addr:postcode":"4214",
    "addr:street":"Barnett Pl Ernest",
    "iso:country":"AU",
    "sg:address":"2/ 14 Barnett Pl",
    "sg:city":"Ernest",
    "sg:classifiers":[
        {
            "category":"Home & Garden",
            "subcategory":"Home Furnishings",
            "type":"Retail Goods"
        }
    ],
    "sg:phone":"+61 7 5574 4347",
    "sg:postcode":"4214",
    "sg:province":"QLD",
    "sg:tags":[
        "shower",
        "screen"
    ],
    "wof:name":"Styleline Shower & Wardrobes Pty Ltd",
    "wof:placetype":"venue"
},
  "geometry": {"coordinates":[153.35934448200001,-27.9653892517],"type":"Point"}
}