{
  "type": "Feature",
  "properties": {
    "addr:full":"21 Wattle St Andergrove QLD 4740",
    "addr:housenumber":"21",
    "addr:postcode":"4740",
    "addr:street":"Wattle St",
    "iso:country":"AU",
    "sg:address":"21 Wattle St",
    "sg:city":"Andergrove",
    "sg:classifiers":[
        {
            "category":"Professional",
            "subcategory":"Art Services",
            "type":"Services"
        }
    ],
    "sg:phone":"+61 7 4955 6984",
    "sg:postcode":"4740",
    "sg:province":"QLD",
    "sg:tags":[
        "decorator",
        "painter"
    ],
    "wof:name":"Wayne Anderson Painting",
    "wof:placetype":"venue"
},
  "geometry": {"coordinates":[149.191193,-21.082071],"type":"Point"}
}