{
  "type": "Feature",
  "properties": {
    "addr:full":"90 Parramatta Rd Croydon NSW 2132",
    "addr:housenumber":"90",
    "addr:postcode":"2132",
    "addr:street":"Parramatta Rd",
    "iso:country":"AU",
    "sg:address":"90 Parramatta Rd",
    "sg:city":"Croydon",
    "sg:classifiers":[
        {
            "category":"Retail",
            "subcategory":"Car Wash",
            "type":"Services"
        }
    ],
    "sg:phone":"+61 2 9747 6616",
    "sg:postcode":"2132",
    "sg:province":"NSW",
    "sg:tags":[
        "truck",
        "cleaning"
    ],
    "wof:name":"Pro Detailing",
    "wof:placetype":"venue"
},
  "geometry": {"coordinates":[151.115356445,-33.8705291748],"type":"Point"}
}