{
  "type": "Feature",
  "properties": {
    "addr:full":"7 Wahroonga Ave Wahroonga NSW 2076",
    "addr:housenumber":"7",
    "addr:postcode":"2076",
    "addr:street":"Wahroonga Ave",
    "iso:country":"AU",
    "sg:address":"7 Wahroonga Ave",
    "sg:city":"Wahroonga",
    "sg:classifiers":[
        {
            "category":"Building & Trades",
            "subcategory":"Construction",
            "type":"Services"
        }
    ],
    "sg:phone":"+61 411 888 831",
    "sg:postcode":"2076",
    "sg:province":"NSW",
    "sg:tags":[
        "renovation",
        "alterations",
        "extension",
        "contractor"
    ],
    "wof:name":"Northside Building",
    "wof:placetype":"venue"
},
  "geometry": {"coordinates":[151.12643432600001,-33.7119407654],"type":"Point"}
}