{
  "type": "Feature",
  "properties": {
    "iso:country":"AU",
    "sg:address":"2 Ward Crs",
    "sg:city":"Oyster Bay",
    "sg:classifiers":[
        {
            "category":"Professional",
            "subcategory":"Secretarial Services",
            "type":"Services"
        }
    ],
    "sg:phone":"+61 2 9528 4038",
    "sg:postcode":"2225",
    "sg:province":"NSW",
    "sg:tags":[
        "typing"
    ],
    "wof:name":"Jemash Properties",
    "wof:placetype":"venue"
},
  "geometry": {"coordinates":[151.08096313499999,-34.0068588257],"type":"Point"}
}