{
  "type": "Feature",
  "properties": {
    "addr:full":"13 Grant St Brighton East VIC 3187",
    "addr:housenumber":"13",
    "addr:postcode":"3187",
    "addr:street":"Grant St",
    "iso:country":"AU",
    "sg:address":"13 Grant St",
    "sg:city":"Brighton East",
    "sg:classifiers":[
        {
            "category":"Professional",
            "subcategory":"Employment Agencies",
            "type":"Services"
        }
    ],
    "sg:phone":"+61 3 9592 1828",
    "sg:postcode":"3187",
    "sg:province":"VIC",
    "sg:tags":[
        "theatrical",
        "managers",
        "agent",
        "producer"
    ],
    "wof:name":"Charleston Productions",
    "wof:placetype":"venue"
},
  "geometry": {"coordinates":[145.00868225100001,-37.9132385254],"type":"Point"}
}