{
  "type": "Feature",
  "properties": {
    "addr:full":"32 Craig St Bendigo VIC 3550",
    "addr:housenumber":"32",
    "addr:postcode":"3550",
    "addr:street":"Craig St",
    "iso:country":"AU",
    "sg:address":"32 Craig St",
    "sg:city":"Bendigo",
    "sg:classifiers":[
        {
            "category":"Professional",
            "type":"Services"
        }
    ],
    "sg:phone":"+61 3 5443 6766",
    "sg:postcode":"3550",
    "sg:province":"VIC",
    "sg:tags":[
        "transport"
    ],
    "wof:name":"Lampow Logistics",
    "wof:placetype":"venue"
},
  "geometry": {"coordinates":[144.26130676299999,-36.7421875],"type":"Point"}
}