{
  "type": "Feature",
  "properties": {
    "iso:country":"AU",
    "sg:address":"140- 140 Parramattta Rd",
    "sg:city":"Camperdown",
    "sg:classifiers":[
        {
            "category":"Manufacturing",
            "subcategory":"Food",
            "type":"Manufacturing & Wholesale Goods"
        }
    ],
    "sg:phone":"+61 2 9516 4466",
    "sg:postcode":"2050",
    "sg:province":"NSW",
    "sg:tags":[
        "function",
        "catering"
    ],
    "wof:name":"Wineplanet",
    "wof:placetype":"venue"
},
  "geometry": {"coordinates":[151.17718500000001,-33.88866],"type":"Point"}
}