{
  "type": "Feature",
  "properties": {
    "addr:full":"13 Best St Lane Cove NSW 2066",
    "addr:housenumber":"13",
    "addr:postcode":"2066",
    "addr:street":"Best St",
    "iso:country":"AU",
    "sg:address":"13 Best St",
    "sg:city":"Lane Cove",
    "sg:classifiers":[
        {
            "category":"Autos & Motor Vehicles",
            "subcategory":"Auto Supplies",
            "type":"Retail Goods"
        }
    ],
    "sg:phone":"+61 2 9420 8011",
    "sg:postcode":"2066",
    "sg:province":"NSW",
    "sg:tags":[
        "wheel",
        "automotive",
        "rim"
    ],
    "wof:name":"Beton Pty Ltd",
    "wof:placetype":"venue"
},
  "geometry": {"coordinates":[151.154296875,-33.8159637451],"type":"Point"}
}