{
  "type": "Feature",
  "properties": {
    "iso:country":"AU",
    "sg:address":"8 Tingle Way",
    "sg:city":"Halls Head",
    "sg:classifiers":[
        {
            "category":"Bars & Pubs",
            "subcategory":"Nightclub",
            "type":"Food & Drink"
        }
    ],
    "sg:phone":"+61 8 9535 9676",
    "sg:postcode":"6210",
    "sg:province":"WA",
    "sg:tags":[
        "karaoke"
    ],
    "wof:name":"Moonlight Karaoke & Entertainment",
    "wof:placetype":"venue"
},
  "geometry": {"coordinates":[115.684547,-32.551369],"type":"Point"}
}