{
  "type": "Feature",
  "properties": {
    "addr:full":"10 Normanby Ave Sunshine West VIC 3020",
    "addr:housenumber":"10",
    "addr:postcode":"3020",
    "addr:street":"Normanby Ave",
    "iso:country":"AU",
    "sg:address":"10 Normanby Ave",
    "sg:city":"Sunshine West",
    "sg:classifiers":[
        {
            "category":"Military Area",
            "subcategory":"Air Force Base",
            "type":"Public Place"
        }
    ],
    "sg:phone":"+61 3 9310 2888",
    "sg:postcode":"3020",
    "sg:province":"VIC",
    "sg:tags":[
        "box",
        "case",
        "wood"
    ],
    "wof:name":"A.A. Aussie Pallets",
    "wof:placetype":"venue"
},
  "geometry": {"coordinates":[144.81312600000001,-37.811497],"type":"Point"}
}