{
  "type": "Feature",
  "properties": {
    "addr:full":"Shop 82, Garden City Shopping Centre, Riseley St Booragoon WA 6154",
    "addr:housenumber":"shop 82",
    "addr:postcode":"6154",
    "addr:street":"Riseley St",
    "iso:country":"AU",
    "sg:address":"Shop 82, Garden City Shopping Centre, Riseley St",
    "sg:city":"Booragoon",
    "sg:classifiers":[
        {
            "category":"Personal",
            "subcategory":"Beauty Salon",
            "type":"Services"
        }
    ],
    "sg:phone":"+61 8 9315 5547",
    "sg:postcode":"6154",
    "sg:province":"WA",
    "wof:name":"Placecol",
    "wof:placetype":"venue"
},
  "geometry": {"coordinates":[115.837959,-32.0364],"type":"Point"}
}