{
  "type": "Feature",
  "properties": {
    "addr:full":"31 Post Office Pl Traralgon VIC 3844",
    "addr:housenumber":"31",
    "addr:postcode":"3844",
    "addr:street":"Post Office Pl",
    "iso:country":"AU",
    "sg:address":"31 Post Office Pl",
    "sg:city":"Traralgon",
    "sg:classifiers":[
        {
            "category":"Shopping",
            "subcategory":"Mobile Phones",
            "type":"Retail Goods"
        }
    ],
    "sg:phone":"+61 3 5174 7727",
    "sg:postcode":"3844",
    "sg:province":"VIC",
    "sg:tags":[
        "telephone",
        "accessory"
    ],
    "wof:name":"Optus World",
    "wof:placetype":"venue"
},
  "geometry": {"coordinates":[146.539825439,-38.1952934265],"type":"Point"}
}