{
  "type": "Feature",
  "properties": {
    "addr:full":"Room 418 37 Swanston St Melbourne VIC 3000",
    "addr:housenumber":"37",
    "addr:postcode":"3000",
    "addr:street":"Swanston St",
    "iso:country":"AU",
    "sg:address":"Room 418 37 Swanston St",
    "sg:city":"Melbourne",
    "sg:classifiers":[
        {
            "category":"Shopping",
            "subcategory":"Computers & Home Electronics",
            "type":"Retail Goods"
        }
    ],
    "sg:phone":"+61 3 9654 3933",
    "sg:postcode":"3000",
    "sg:province":"VIC",
    "sg:tags":[
        "equipment",
        "multimedia"
    ],
    "wof:name":"Anima Multimedia",
    "wof:placetype":"venue"
},
  "geometry": {"coordinates":[144.96693420400001,-37.8166503906],"type":"Point"}
}