{
  "type": "Feature",
  "properties": {
    "addr:full":"49 Bellevue Ave Gaythorne QLD 4051",
    "addr:housenumber":"49",
    "addr:postcode":"4051",
    "addr:street":"Bellevue Ave",
    "iso:country":"AU",
    "sg:address":"49 Bellevue Ave",
    "sg:city":"Gaythorne",
    "sg:classifiers":[
        {
            "category":"Personal",
            "type":"Services"
        }
    ],
    "sg:phone":"+61 7 3855 4155",
    "sg:postcode":"4051",
    "sg:province":"QLD",
    "sg:tags":[
        "reducing",
        "treatment",
        "weight"
    ],
    "wof:name":"Intuitive Eating Centre",
    "wof:placetype":"venue"
},
  "geometry": {"coordinates":[152.98333740199999,-27.415140152],"type":"Point"}
}