{
  "type": "Feature",
  "properties": {
    "addr:full":"17 kimberly Ave Gympie QLD 4570",
    "addr:housenumber":"17",
    "addr:postcode":"4570",
    "addr:street":"Kimberly Ave",
    "iso:country":"AU",
    "sg:address":"17 kimberly Ave",
    "sg:city":"Gympie",
    "sg:classifiers":[
        {
            "category":"Building & Trades",
            "subcategory":"Construction",
            "type":"Services"
        }
    ],
    "sg:phone":"+61 7 5482 5291",
    "sg:postcode":"4570",
    "sg:province":"QLD",
    "sg:tags":[
        "plasterboard",
        "plasterer",
        "fixer"
    ],
    "wof:name":"Hodge Steve",
    "wof:placetype":"venue"
},
  "geometry": {"coordinates":[152.65103149399999,-26.221736908],"type":"Point"}
}