{
  "type": "Feature",
  "properties": {
    "addr:full":"PO Box 990 Warners Bay NSW 2282",
    "addr:postcode":"2282",
    "iso:country":"AU",
    "sg:address":"PO Box 990",
    "sg:city":"Warners Bay",
    "sg:classifiers":[
        {
            "category":"Commercial Area",
            "type":"Public Place"
        }
    ],
    "sg:phone":"+61 2 4930 5666",
    "sg:postcode":"2282",
    "sg:province":"NSW",
    "sg:tags":[
        "heavy",
        "carrier"
    ],
    "wof:name":"Trueway Logistics P/L",
    "wof:placetype":"venue"
},
  "geometry": {"coordinates":[151.64869689899999,-32.973110199],"type":"Point"}
}