{
  "type": "Feature",
  "properties": {
    "addr:full":"58- 60 Lakewood Drv Burpengary QLD 4505",
    "addr:housenumber":"60",
    "addr:postcode":"4505",
    "addr:street":"Lakewood Drv",
    "iso:country":"AU",
    "sg:address":"58- 60 Lakewood Drv",
    "sg:city":"Burpengary",
    "sg:classifiers":[
        {
            "category":"Home & Garden",
            "subcategory":"Carpets & Floor Coverings",
            "type":"Retail Goods"
        }
    ],
    "sg:phone":"+61 412 455 682",
    "sg:postcode":"4505",
    "sg:province":"QLD",
    "sg:tags":[
        "tile",
        "wall",
        "layer"
    ],
    "wof:name":"Savic Tiling",
    "wof:placetype":"venue"
},
  "geometry": {"coordinates":[153.00062560999999,-27.1643123627],"type":"Point"}
}