{
  "type": "Feature",
  "properties": {
    "addr:full":"6 Derby St St Ives NSW 2075",
    "addr:housenumber":"6",
    "addr:postcode":"2075",
    "addr:street":"Derby St",
    "iso:country":"AU",
    "sg:address":"6 Derby St St",
    "sg:city":"Ives",
    "sg:classifiers":[
        {
            "category":"Professional",
            "subcategory":"Management & Consulting",
            "type":"Services"
        }
    ],
    "sg:phone":"+61 2 9440 2778",
    "sg:postcode":"2075",
    "sg:province":"NSW",
    "sg:tags":[
        "consultant"
    ],
    "wof:name":"S M G Australasia Pty Ltd",
    "wof:placetype":"venue"
},
  "geometry": {"coordinates":[151.1668396,-33.736995697],"type":"Point"}
}