{
  "type": "Feature",
  "properties": {
    "addr:full":"65 Buckingham Drv Wangara WA 6065",
    "addr:housenumber":"65",
    "addr:postcode":"6065",
    "addr:street":"Buckingham Drv",
    "iso:country":"AU",
    "sg:address":"65 Buckingham Drv",
    "sg:city":"Wangara",
    "sg:classifiers":[
        {
            "category":"Professional",
            "subcategory":"Detective & Security Services",
            "type":"Services"
        }
    ],
    "sg:phone":"+61 8 9309 3747",
    "sg:postcode":"6065",
    "sg:province":"WA",
    "sg:tags":[
        "equipment",
        "window",
        "doors"
    ],
    "wof:name":"Mirage Industries Pty Ltd",
    "wof:placetype":"venue"
},
  "geometry": {"coordinates":[115.824882507,-31.7873916626],"type":"Point"}
}