{
  "type": "Feature",
  "properties": {
    "addr:full":"22 James St Richmond VIC 3121",
    "addr:housenumber":"22",
    "addr:postcode":"3121",
    "addr:street":"James St",
    "iso:country":"AU",
    "sg:address":"22 James St",
    "sg:city":"Richmond",
    "sg:classifiers":[
        {
            "category":"Building & Trades",
            "subcategory":"Construction",
            "type":"Services"
        }
    ],
    "sg:phone":"+61 425 747 189",
    "sg:postcode":"3121",
    "sg:province":"VIC",
    "sg:tags":[
        "polishing",
        "sanding",
        "floor"
    ],
    "wof:name":"Richard Barclay",
    "wof:placetype":"venue"
},
  "geometry": {"coordinates":[145.00059509299999,-37.8277244568],"type":"Point"}
}