{
  "type": "Feature",
  "properties": {
    "addr:full":"Shop 13 Karratha Village Shopping Centre Karratha WA 6714",
    "addr:housenumber":"shop 13",
    "addr:postcode":"6714",
    "addr:street":"Karratha Village",
    "iso:country":"AU",
    "sg:address":"Shop 13",
    "sg:city":"Karratha Village Shopping Centre Karratha",
    "sg:classifiers":[
        {
            "category":"Personal",
            "subcategory":"Beauty Salon",
            "type":"Services"
        }
    ],
    "sg:phone":"+61 8 9185 5599",
    "sg:postcode":"6714",
    "sg:province":"WA",
    "sg:tags":[
        "hairdresser"
    ],
    "wof:name":"B Enlightened Hair Beauty Spa",
    "wof:placetype":"venue"
},
  "geometry": {"coordinates":[116.84902954099999,-20.7548427582],"type":"Point"}
}