{
  "type": "Feature",
  "properties": {
    "iso:country":"AU",
    "sg:address":"17b Perry St",
    "sg:city":"Mudgee",
    "sg:classifiers":[
        {
            "category":"Insurance",
            "subcategory":"Insurance Agent",
            "type":"Services"
        }
    ],
    "sg:phone":"+61 2 6372 0195",
    "sg:postcode":"2850",
    "sg:province":"NSW",
    "sg:tags":[
        "broker"
    ],
    "wof:name":"Insurance Australia Broking Pty Ltd",
    "wof:placetype":"venue"
},
  "geometry": {"coordinates":[149.585373,-32.593933],"type":"Point"}
}