{
  "type": "Feature",
  "properties": {
    "addr:full":"59 Holmes Rd Moonee Ponds VIC 3039",
    "addr:housenumber":"59",
    "addr:postcode":"3039",
    "addr:street":"Holmes Rd",
    "iso:country":"AU",
    "sg:address":"59 Holmes Rd",
    "sg:city":"Moonee Ponds",
    "sg:classifiers":[
        {
            "category":"Government",
            "subcategory":"Court House",
            "type":"Public Place"
        }
    ],
    "sg:phone":"+61 438 266 956",
    "sg:postcode":"3039",
    "sg:province":"VIC",
    "sg:tags":[
        "personal",
        "marriage",
        "family",
        "counselling"
    ],
    "wof:name":"Patricia Barbaro",
    "wof:placetype":"venue"
},
  "geometry": {"coordinates":[144.91598500000001,-37.766312],"type":"Point"}
}