{
  "type": "Feature",
  "properties": {
    "iso:country":"AU",
    "sg:address":"10/ 43 Burns Bay Rd",
    "sg:city":"Lane Cove",
    "sg:classifiers":[
        {
            "category":"Personal",
            "subcategory":"Shoe Repair & Shine",
            "type":"Services"
        }
    ],
    "sg:phone":"+61 2 9427 3376",
    "sg:postcode":"2066",
    "sg:province":"NSW",
    "sg:tags":[
        "footwear"
    ],
    "wof:name":"Lane Cove Village Shoe Repairs",
    "wof:placetype":"venue"
},
  "geometry": {"coordinates":[151.168212891,-33.8144035339],"type":"Point"}
}