{
  "type": "Feature",
  "properties": {
    "addr:full":"174 Leighlands Rd Evandale TAS 7212",
    "addr:housenumber":"174",
    "addr:postcode":"7212",
    "addr:street":"Leighlands Rd",
    "iso:country":"AU",
    "sg:address":"174 Leighlands Rd",
    "sg:city":"Evandale",
    "sg:classifiers":[
        {
            "category":"Building & Trades",
            "subcategory":"Landscaping Services",
            "type":"Services"
        }
    ],
    "sg:phone":"+61 3 6391 8437",
    "sg:postcode":"7212",
    "sg:province":"TAS",
    "sg:tags":[
        "designer",
        "landscape",
        "contractor"
    ],
    "wof:name":"Barbour Tim",
    "wof:placetype":"venue"
},
  "geometry": {"coordinates":[147.228714,-41.586735],"type":"Point"}
}