{
  "type": "Feature",
  "properties": {
    "iso:country":"AU",
    "sg:address":"Ste 84/ 330 Wattle St",
    "sg:city":"Ultimo",
    "sg:classifiers":[
        {
            "category":"Professional",
            "subcategory":"Computer Services",
            "type":"Services"
        }
    ],
    "sg:phone":"+61 2 9281 2311",
    "sg:postcode":"2007",
    "sg:province":"NSW",
    "sg:tags":[
        "package",
        "software"
    ],
    "wof:name":"Datex Technology Pty Ltd",
    "wof:placetype":"venue"
},
  "geometry": {"coordinates":[151.19630432100001,-33.8796920776],"type":"Point"}
}