{
  "type": "Feature",
  "properties": {
    "iso:country":"AU",
    "sg:address":"37 Kelsey Rd",
    "sg:city":"Noraville",
    "sg:classifiers":[
        {
            "category":"Retail",
            "subcategory":"Storage",
            "type":"Services"
        }
    ],
    "sg:phone":"+61 438 343 217",
    "sg:postcode":"2263",
    "sg:province":"NSW",
    "sg:tags":[
        "removal",
        "furniture"
    ],
    "wof:name":"Entrance Removals",
    "wof:placetype":"venue"
},
  "geometry": {"coordinates":[151.55349699999999,-33.269348],"type":"Point"}
}