{
  "type": "Feature",
  "properties": {
    "addr:full":"Shp4/ 25 Moreton Tce Dongara WA 6525",
    "addr:postcode":"6525",
    "addr:street":"Moreton Tce",
    "iso:country":"AU",
    "sg:address":"Shp4/ 25 Moreton Tce",
    "sg:city":"Dongara",
    "sg:classifiers":[
        {
            "category":"Recreation",
            "subcategory":"Fishing",
            "type":"Entertainment"
        }
    ],
    "sg:phone":"+61 8 9927 1196",
    "sg:postcode":"6525",
    "sg:province":"WA",
    "sg:tags":[
        "tackle"
    ],
    "wof:name":"Dongara Sport & Tackle",
    "wof:placetype":"venue"
},
  "geometry": {"coordinates":[114.93360900899999,-29.2512073517],"type":"Point"}
}