{
  "type": "Feature",
  "properties": {
    "iso:country":"AU",
    "sg:address":"PO Box 635",
    "sg:city":"Morisset",
    "sg:classifiers":[
        {
            "category":"Banks & Credit Unions",
            "subcategory":"Bureau De Change",
            "type":"Services"
        }
    ],
    "sg:phone":"+61 2 4970 4188",
    "sg:postcode":"2264",
    "sg:province":"NSW",
    "sg:tags":[
        "archaeology"
    ],
    "wof:name":"Nexus Archaeology & Heritage",
    "wof:placetype":"venue"
},
  "geometry": {"coordinates":[151.488388,-33.108139],"type":"Point"}
}