{
  "type": "Feature",
  "properties": {
    "addr:full":"159a Anzac Pde Kensington NSW 2033",
    "addr:housenumber":"159a",
    "addr:postcode":"2033",
    "addr:street":"Anzac Pde",
    "iso:country":"AU",
    "sg:address":"159a Anzac Pde",
    "sg:city":"Kensington",
    "sg:classifiers":[
        {
            "category":"Professional",
            "subcategory":"Accounting & Tax Preparation",
            "type":"Services"
        }
    ],
    "sg:phone":"+61 2 9313 6066",
    "sg:postcode":"2033",
    "sg:province":"NSW",
    "sg:tags":[
        "consultant",
        "taxation"
    ],
    "wof:name":"Alexandrou Taxation Services",
    "wof:placetype":"venue"
},
  "geometry": {"coordinates":[151.22306800000001,-33.911785],"type":"Point"}
}