{
  "type": "Feature",
  "properties": {
    "addr:full":"1573 Teatree Rd Campania TAS 7026",
    "addr:housenumber":"1573",
    "addr:postcode":"7026",
    "addr:street":"Teatree Rd",
    "iso:country":"AU",
    "sg:address":"1573 Teatree Rd",
    "sg:city":"Campania",
    "sg:classifiers":[
        {
            "category":"Wholesale",
            "subcategory":"Machinery & Supplies",
            "type":"Manufacturing & Wholesale Goods"
        }
    ],
    "sg:phone":"+61 408 604 135",
    "sg:postcode":"7026",
    "sg:province":"TAS",
    "sg:tags":[
        "agricultural"
    ],
    "wof:name":"Enfield Machinery",
    "wof:placetype":"venue"
},
  "geometry": {"coordinates":[147.41197204599999,-42.677520752],"type":"Point"}
}