{
  "type": "Feature",
  "properties": {
    "iso:country":"AU",
    "sg:address":"63 Hogans Rd",
    "sg:city":"Hoppers Crossing",
    "sg:classifiers":[
        {
            "category":"Health Services",
            "subcategory":"Dentist",
            "type":"Services"
        }
    ],
    "sg:phone":"+61 3 9749 6777",
    "sg:postcode":"3029",
    "sg:province":"VIC",
    "wof:name":"Patten Bill Dr",
    "wof:placetype":"venue"
},
  "geometry": {"coordinates":[144.69473300000001,-37.864059],"type":"Point"}
}