{
  "type": "Feature",
  "properties": {
    "addr:full":"6 Short St Southport QLD 4215",
    "addr:housenumber":"6",
    "addr:postcode":"4215",
    "addr:street":"Short St",
    "iso:country":"AU",
    "sg:address":"6 Short St",
    "sg:city":"Southport",
    "sg:classifiers":[
        {
            "category":"Banks & Credit Unions",
            "subcategory":"Investment Brokerage",
            "type":"Services"
        }
    ],
    "sg:phone":"+61 1300 369 505",
    "sg:postcode":"4215",
    "sg:province":"QLD",
    "sg:tags":[
        "share",
        "broker",
        "stock"
    ],
    "wof:name":"Burrell Stockbroking",
    "wof:placetype":"venue"
},
  "geometry": {"coordinates":[153.41656494099999,-27.9703502655],"type":"Point"}
}