{
  "type": "Feature",
  "properties": {
    "iso:country":"AU",
    "sg:address":"12e Dean St",
    "sg:city":"South Townsville",
    "sg:classifiers":[
        {
            "category":"Fast Food",
            "type":"Food & Drink"
        }
    ],
    "sg:phone":"+61 7 4772 5406",
    "sg:postcode":"4810",
    "sg:province":"QLD",
    "sg:tags":[
        "away",
        "take"
    ],
    "wof:name":"Daisys Cafe & Takeaway",
    "wof:placetype":"venue"
},
  "geometry": {"coordinates":[146.81987,-19.262007],"type":"Point"}
}