{
  "type": "Feature",
  "properties": {
    "addr:full":"1a Ailsa St Box Hill South VIC 3128",
    "addr:housenumber":"1a",
    "addr:postcode":"3128",
    "addr:street":"Ailsa St",
    "iso:country":"AU",
    "sg:address":"1a Ailsa St",
    "sg:city":"Box Hill South",
    "sg:classifiers":[
        {
            "category":"Professional",
            "subcategory":"Computer Services",
            "type":"Services"
        }
    ],
    "sg:phone":"+61 3 9898 2888",
    "sg:postcode":"3128",
    "sg:province":"VIC",
    "sg:tags":[
        "equipment",
        "networking",
        "installation"
    ],
    "wof:name":"Infotec Electronics Pty Ltd",
    "wof:placetype":"venue"
},
  "geometry": {"coordinates":[145.13360595699999,-37.8400650024],"type":"Point"}
}