{
  "type": "Feature",
  "properties": {
    "addr:full":"1029 Mate St Albury North NSW 2640",
    "addr:postcode":"1029;2640",
    "addr:street":"Mate St",
    "iso:country":"AU",
    "sg:address":"1029 Mate St",
    "sg:city":"Albury North",
    "sg:classifiers":[
        {
            "category":"Personal",
            "subcategory":"Massage",
            "type":"Services"
        }
    ],
    "sg:phone":"+61 2 6040 2700",
    "sg:postcode":"2640",
    "sg:province":"NSW",
    "sg:tags":[
        "therapy"
    ],
    "wof:name":"Hargrave Scott",
    "wof:placetype":"venue"
},
  "geometry": {"coordinates":[146.93267822300001,-36.0563926697],"type":"Point"}
}