{
  "type": "Feature",
  "properties": {
    "iso:country":"AU",
    "sg:address":"66 Donelan Drv",
    "sg:city":"Hernes Oak",
    "sg:classifiers":[
        {
            "category":"Professional",
            "subcategory":"Printing & Photocopies",
            "type":"Services"
        }
    ],
    "sg:phone":"+61 409 173 040",
    "sg:postcode":"3825",
    "sg:province":"VIC",
    "sg:tags":[
        "screen",
        "printer"
    ],
    "wof:name":"Sprint Screen Printing",
    "wof:placetype":"venue"
},
  "geometry": {"coordinates":[146.29208399999999,-38.206379],"type":"Point"}
}