{
  "type": "Feature",
  "properties": {
    "addr:full":"Lvl1, 135- 137 Harris St Pyrmont NSW 2009",
    "addr:housenumber":"137",
    "addr:postcode":"2009",
    "addr:street":"Harris St",
    "iso:country":"AU",
    "sg:address":"Lvl1, 135- 137 Harris St",
    "sg:city":"Pyrmont",
    "sg:classifiers":[
        {
            "category":"Professional",
            "subcategory":"Art Services",
            "type":"Services"
        }
    ],
    "sg:phone":"+61 2 9566 1977",
    "sg:postcode":"2009",
    "sg:province":"NSW",
    "sg:tags":[
        "graphic",
        "designer"
    ],
    "wof:name":"Hugonnet Design Associates",
    "wof:placetype":"venue"
},
  "geometry": {"coordinates":[151.19386291500001,-33.869846344],"type":"Point"}
}