{
  "type": "Feature",
  "properties": {
    "addr:full":"16 George St Hornsby NSW 2077",
    "addr:housenumber":"16",
    "addr:postcode":"2077",
    "addr:street":"George St",
    "iso:country":"AU",
    "sg:address":"16 George St",
    "sg:city":"Hornsby",
    "sg:classifiers":[
        {
            "category":"Health Services",
            "subcategory":"Dentist",
            "type":"Services"
        }
    ],
    "sg:phone":"+61 2 9477 1010",
    "sg:postcode":"2077",
    "sg:province":"NSW",
    "wof:name":"Lockwood J",
    "wof:placetype":"venue"
},
  "geometry": {"coordinates":[151.09916687,-33.7035064697],"type":"Point"}
}