{
  "type": "Feature",
  "properties": {
    "addr:full":"Studio 1240, Glenhuntly Road Glen Huntly VIC 3163",
    "addr:postcode":"3163",
    "addr:street":"Glenhuntly Road",
    "iso:country":"AU",
    "sg:address":"Studio 1240, Glenhuntly Road",
    "sg:city":"Glen Huntly",
    "sg:classifiers":[
        {
            "category":"Sports & Exercise",
            "subcategory":"Gym",
            "type":"Entertainment"
        }
    ],
    "sg:phone":"+61 404 472 863",
    "sg:postcode":"3163",
    "sg:province":"VIC",
    "sg:tags":[
        "personal",
        "trainer",
        "fitness"
    ],
    "wof:name":"Exhale &#039;Optimal Health & Fitness&#039;",
    "wof:placetype":"venue"
},
  "geometry": {"coordinates":[145.045944214,-37.8899688721],"type":"Point"}
}