{
  "type": "Feature",
  "properties": {
    "addr:full":"8 Mulwala Garden St Albans VIC 3021",
    "addr:housenumber":"8",
    "addr:postcode":"3021",
    "addr:street":"Garden",
    "iso:country":"AU",
    "sg:address":"8 Mulwala Garden",
    "sg:city":"St Albans",
    "sg:classifiers":[
        {
            "category":"Utilities",
            "subcategory":"Refuse",
            "type":"Services"
        }
    ],
    "sg:phone":"+61 400 364 115",
    "sg:postcode":"3021",
    "sg:province":"VIC",
    "sg:tags":[
        "remover",
        "rubbish"
    ],
    "wof:name":"Mc Naughton's Rubbish Removal",
    "wof:placetype":"venue"
},
  "geometry": {"coordinates":[144.82978800000001,-37.74826],"type":"Point"}
}