{
  "type": "Feature",
  "properties": {
    "addr:full":"43 Anderson St Yarraville VIC 3013",
    "addr:housenumber":"43",
    "addr:postcode":"3013",
    "addr:street":"Anderson St",
    "iso:country":"AU",
    "sg:address":"43 Anderson St",
    "sg:city":"Yarraville",
    "sg:classifiers":[
        {
            "category":"Cafe",
            "type":"Food & Drink"
        }
    ],
    "sg:phone":"+61 3 9687 1198",
    "sg:postcode":"3013",
    "sg:province":"VIC",
    "wof:name":"Caffe Urbano",
    "wof:placetype":"venue"
},
  "geometry": {"coordinates":[144.890457153,-37.8167381287],"type":"Point"}
}