{
  "type": "Feature",
  "properties": {
    "addr:full":"30 King St Hastings VIC 3915",
    "addr:housenumber":"30",
    "addr:postcode":"3915",
    "addr:street":"King St",
    "iso:country":"AU",
    "sg:address":"30 King St",
    "sg:city":"Hastings",
    "sg:classifiers":[
        {
            "category":"Professional",
            "subcategory":"Computer Services",
            "type":"Services"
        }
    ],
    "sg:phone":"+61 3 5979 2762",
    "sg:postcode":"3915",
    "sg:province":"VIC",
    "sg:tags":[
        "information"
    ],
    "wof:name":"Hastings Community Information & Support Centre",
    "wof:placetype":"venue"
},
  "geometry": {"coordinates":[145.19195556599999,-38.3082809448],"type":"Point"}
}