{
  "type": "Feature",
  "properties": {
    "addr:full":"Main St Buffalo VIC 3958",
    "addr:postcode":"3958",
    "addr:street":"Main St",
    "iso:country":"AU",
    "sg:address":"Main St",
    "sg:city":"Buffalo",
    "sg:classifiers":[
        {
            "category":"Shopping",
            "type":"Retail Goods"
        }
    ],
    "sg:phone":"+61 3 5663 6203",
    "sg:postcode":"3958",
    "sg:province":"VIC",
    "sg:tags":[
        "produce",
        "grain"
    ],
    "wof:name":"Browns Holt & Hannon",
    "wof:placetype":"venue"
},
  "geometry": {"coordinates":[146.02078247099999,-38.6765098572],"type":"Point"}
}