{
  "type": "Feature",
  "properties": {
    "addr:full":"Shp2/ 48 Kidman Ave Belmont VIC 3216",
    "addr:postcode":"3216",
    "addr:street":"Kidman Ave",
    "iso:country":"AU",
    "sg:address":"Shp2/ 48 Kidman Ave",
    "sg:city":"Belmont",
    "sg:classifiers":[
        {
            "category":"Sports & Exercise",
            "subcategory":"Ski Slope",
            "type":"Entertainment"
        }
    ],
    "sg:phone":"+61 3 5244 0111",
    "sg:postcode":"3216",
    "sg:province":"VIC",
    "sg:tags":[
        "equipment",
        "hire",
        "retail",
        "snow"
    ],
    "wof:name":"Oz Extreme Australia",
    "wof:placetype":"venue"
},
  "geometry": {"coordinates":[144.341308594,-38.1852836609],"type":"Point"}
}