{
  "type": "Feature",
  "properties": {
    "addr:full":"Marrabel Rd Saddleworth SA 5413",
    "addr:postcode":"5413",
    "addr:street":"Marrabel Rd",
    "iso:country":"AU",
    "sg:address":"Marrabel Rd",
    "sg:city":"Saddleworth",
    "sg:classifiers":[
        {
            "category":"Farming",
            "subcategory":"Farm",
            "type":"Manufacturing & Wholesale Goods"
        }
    ],
    "sg:phone":"+61 8 8847 4109",
    "sg:postcode":"5413",
    "sg:province":"SA",
    "sg:tags":[
        "farmer"
    ],
    "wof:name":"Vater A W & Co",
    "wof:placetype":"venue"
},
  "geometry": {"coordinates":[138.784332275,-34.0859642029],"type":"Point"}
}