{
  "type": "Feature",
  "properties": {
    "iso:country":"AU",
    "sg:address":"5- 6 Floribunda Ave",
    "sg:city":"Glenmore Park",
    "sg:classifiers":[
        {
            "category":"Education",
            "subcategory":"Kindergarten",
            "type":"Public Place"
        }
    ],
    "sg:phone":"+61 2 4733 4239",
    "sg:postcode":"2745",
    "sg:province":"NSW",
    "sg:tags":[
        "pre-schools"
    ],
    "wof:name":"Glenmore Park Early Childhood Centre",
    "wof:placetype":"venue"
},
  "geometry": {"coordinates":[150.66616821299999,-33.7821311951],"type":"Point"}
}