{
  "type": "Feature",
  "properties": {
    "addr:full":"Herbert St Doubleview WA 6018",
    "addr:postcode":"6018",
    "addr:street":"Herbert St",
    "iso:country":"AU",
    "sg:address":"Herbert St",
    "sg:city":"Doubleview",
    "sg:classifiers":[
        {
            "category":"Building & Trades",
            "subcategory":"Construction",
            "type":"Services"
        }
    ],
    "sg:phone":"+61 418 910 976",
    "sg:postcode":"6018",
    "sg:province":"WA",
    "sg:tags":[
        "waterproofing",
        "contractor"
    ],
    "wof:name":"Aquatite",
    "wof:placetype":"venue"
},
  "geometry": {"coordinates":[115.777687073,-31.895526886],"type":"Point"}
}