{
  "type": "Feature",
  "properties": {
    "addr:full":"21 Rochester St Homebush NSW 2140",
    "addr:housenumber":"21",
    "addr:postcode":"2140",
    "addr:street":"Rochester St",
    "iso:country":"AU",
    "sg:address":"21 Rochester St",
    "sg:city":"Homebush",
    "sg:classifiers":[
        {
            "category":"Food & Beverages",
            "subcategory":"Supermarket",
            "type":"Retail Goods"
        }
    ],
    "sg:phone":"+61 2 9746 8122",
    "sg:postcode":"2140",
    "sg:province":"NSW",
    "sg:tags":[
        "grocery",
        "store"
    ],
    "wof:name":"IGA Riteway",
    "wof:placetype":"venue"
},
  "geometry": {"coordinates":[151.08465576200001,-33.8670196533],"type":"Point"}
}