{
  "type": "Feature",
  "properties": {
    "iso:country":"AU",
    "sg:address":"Shop 2, 37 Commerce Drv",
    "sg:city":"Robina",
    "sg:classifiers":[
        {
            "category":"Personal",
            "subcategory":"Beauty Salon",
            "type":"Services"
        }
    ],
    "sg:phone":"+61 7 5593 2300",
    "sg:postcode":"4226",
    "sg:province":"QLD",
    "sg:tags":[
        "hairdresser"
    ],
    "wof:name":"OJ's Hairdressing",
    "wof:placetype":"venue"
},
  "geometry": {"coordinates":[153.39210510300001,-28.0869750977],"type":"Point"}
}