{
  "type": "Feature",
  "properties": {
    "iso:country":"AU",
    "sg:address":"2 Ring St",
    "sg:city":"Inverell",
    "sg:classifiers":[
        {
            "category":"Shopping",
            "type":"Retail Goods"
        }
    ],
    "sg:phone":"+61 2 6722 1955",
    "sg:postcode":"2360",
    "sg:province":"NSW",
    "sg:tags":[
        "produce",
        "grain"
    ],
    "wof:name":"Campbell Bros",
    "wof:placetype":"venue"
},
  "geometry": {"coordinates":[151.10963439899999,-29.7627639771],"type":"Point"}
}