{
  "type": "Feature",
  "properties": {
    "iso:country":"AU",
    "sg:address":"Mouramba St",
    "sg:city":"Hermidale",
    "sg:classifiers":[
        {
            "category":"Education",
            "subcategory":"School",
            "type":"Public Place"
        }
    ],
    "sg:phone":"+61 2 6833 0707",
    "sg:postcode":"2831",
    "sg:province":"NSW",
    "sg:tags":[
        "state",
        "-",
        "nsw"
    ],
    "wof:name":"Hermidale Public School",
    "wof:placetype":"venue"
},
  "geometry": {"coordinates":[146.725997925,-31.5508403778],"type":"Point"}
}