{
  "type": "Feature",
  "properties": {
    "addr:full":"12 Vivaldi Pl Beaumont Hills NSW 2155",
    "addr:housenumber":"12",
    "addr:postcode":"2155",
    "addr:street":"Vivaldi Pl",
    "iso:country":"AU",
    "sg:address":"12 Vivaldi Pl",
    "sg:city":"Beaumont Hills",
    "sg:classifiers":[
        {
            "category":"Personal",
            "subcategory":"Beauty Salon",
            "type":"Services"
        }
    ],
    "sg:phone":"+61 2 9629 1058",
    "sg:postcode":"2155",
    "sg:province":"NSW",
    "sg:tags":[
        "hairdresser"
    ],
    "wof:name":"Nothing But Style Hair Studio",
    "wof:placetype":"venue"
},
  "geometry": {"coordinates":[150.95291137699999,-33.700630188],"type":"Point"}
}