{
  "type": "Feature",
  "properties": {
    "iso:country":"AU",
    "sg:address":"19 Mcrae Ave",
    "sg:city":"St Albans",
    "sg:classifiers":[
        {
            "category":"Professional",
            "subcategory":"Computer Services",
            "type":"Services"
        }
    ],
    "sg:phone":"+61 3 9366 5884",
    "sg:postcode":"3021",
    "sg:province":"VIC",
    "sg:tags":[
        "consultant",
        "system"
    ],
    "wof:name":"Gate 5 Software",
    "wof:placetype":"venue"
},
  "geometry": {"coordinates":[144.784439,-37.736813],"type":"Point"}
}