{
  "type": "Feature",
  "properties": {
    "addr:full":"317 Neerim Rd Carnegie VIC 3163",
    "addr:housenumber":"317",
    "addr:postcode":"3163",
    "addr:street":"Neerim Rd",
    "iso:country":"AU",
    "sg:address":"317 Neerim Rd",
    "sg:city":"Carnegie",
    "sg:classifiers":[
        {
            "category":"Building & Trades",
            "subcategory":"Locksmith",
            "type":"Services"
        }
    ],
    "sg:phone":"+61 402 397 299",
    "sg:postcode":"3163",
    "sg:province":"VIC",
    "sg:tags":[
        "lock"
    ],
    "wof:name":"Carnegie Locksmith",
    "wof:placetype":"venue"
},
  "geometry": {"coordinates":[145.05744934099999,-37.8893508911],"type":"Point"}
}