{
  "type": "Feature",
  "properties": {
    "addr:full":"5/ 36 Premier Cct Warana QLD 4575",
    "addr:housenumber":"/ 36",
    "addr:postcode":"4575",
    "iso:country":"AU",
    "sg:address":"5/ 36",
    "sg:city":"Premier Cct Warana",
    "sg:classifiers":[
        {
            "category":"Real Estate",
            "subcategory":"Architect",
            "type":"Services"
        }
    ],
    "sg:phone":"+61 7 5493 1227",
    "sg:postcode":"4575",
    "sg:province":"QLD",
    "sg:tags":[
        "magnet",
        "magnetic",
        "material"
    ],
    "wof:name":"Limitless Promotions",
    "wof:placetype":"venue"
},
  "geometry": {"coordinates":[153.13076799999999,-26.719839],"type":"Point"}
}