{
  "type": "Feature",
  "properties": {
    "addr:full":"Warwick Rd Ipswich QLD 4305",
    "addr:postcode":"4305",
    "addr:street":"Warwick Rd",
    "iso:country":"AU",
    "sg:address":"Warwick Rd",
    "sg:city":"Ipswich",
    "sg:classifiers":[
        {
            "category":"Food & Beverages",
            "subcategory":"Liquor & Beverages",
            "type":"Retail Goods"
        }
    ],
    "sg:phone":"+61 7 3282 8711",
    "sg:postcode":"4305",
    "sg:province":"QLD",
    "sg:tags":[
        "store"
    ],
    "wof:name":"Warwick Rd Liquor Mart",
    "wof:placetype":"venue"
},
  "geometry": {"coordinates":[152.76097106899999,-27.6198425293],"type":"Point"}
}