{
  "type": "Feature",
  "properties": {
    "addr:full":"27 Sundowner Crt Mermaid Waters QLD 4218",
    "addr:housenumber":"27",
    "addr:postcode":"4218",
    "addr:street":"Sundowner Crt",
    "iso:country":"AU",
    "sg:address":"27 Sundowner Crt",
    "sg:city":"Mermaid Waters",
    "sg:classifiers":[
        {
            "category":"Food & Beverages",
            "subcategory":"Fruits & Vegetables",
            "type":"Retail Goods"
        }
    ],
    "sg:phone":"+61 403 578 292",
    "sg:postcode":"4218",
    "sg:province":"QLD",
    "sg:tags":[
        "consultant",
        "catering"
    ],
    "wof:name":"Eljay Catering",
    "wof:placetype":"venue"
},
  "geometry": {"coordinates":[153.429855347,-28.0471305847],"type":"Point"}
}