{
  "type": "Feature",
  "properties": {
    "iso:country":"AU",
    "sg:address":"Unit 7, 3 Dursley Rd",
    "sg:city":"Yennora",
    "sg:classifiers":[
        {
            "category":"Autos & Motor Vehicles",
            "subcategory":"Auto Supplies",
            "type":"Retail Goods"
        }
    ],
    "sg:phone":"+61 2 9632 1312",
    "sg:postcode":"2161",
    "sg:province":"NSW",
    "sg:tags":[
        "camper-trailers",
        "caravan",
        "equipment"
    ],
    "wof:name":"Colonial Caravans",
    "wof:placetype":"venue"
},
  "geometry": {"coordinates":[150.99656677199999,-33.8502159119],"type":"Point"}
}