{
  "type": "Feature",
  "properties": {
    "addr:full":"PO Box 2129 Mt Gambier SA 5290",
    "addr:postcode":"5290",
    "iso:country":"AU",
    "sg:address":"PO Box 2129",
    "sg:city":"Mt Gambier",
    "sg:classifiers":[
        {
            "category":"Building & Trades",
            "subcategory":"Cleaning & Sanitation",
            "type":"Services"
        }
    ],
    "sg:phone":"+61 438 249 132",
    "sg:postcode":"5290",
    "sg:province":"SA",
    "sg:tags":[
        "industrial",
        "commercial",
        "contractor"
    ],
    "wof:name":"Mop & Bucket Home & Office Cleaning",
    "wof:placetype":"venue"
},
  "geometry": {"coordinates":[140.78329500000001,-37.826321],"type":"Point"}
}