{
  "type": "Feature",
  "properties": {
    "iso:country":"AU",
    "sg:address":"9 SHIELDS St",
    "sg:city":"Cairns",
    "sg:classifiers":[
        {
            "category":"Restaurant",
            "type":"Food & Drink"
        }
    ],
    "sg:phone":"+61 7 4041 5446",
    "sg:postcode":"4870",
    "sg:province":"QLD",
    "wof:name":"Buckin&#039; Mex",
    "wof:placetype":"venue"
},
  "geometry": {"coordinates":[145.77653503400001,-16.9216556549],"type":"Point"}
}