{
  "type": "Feature",
  "properties": {
    "addr:full":"218B Main Rd (East) St Albans VIC 3021",
    "addr:housenumber":"218b",
    "addr:postcode":"3021",
    "addr:street":"Main Rd East",
    "iso:country":"AU",
    "sg:address":"218B Main Rd (East) St",
    "sg:city":"Albans",
    "sg:classifiers":[
        {
            "category":"Autos & Motor Vehicles",
            "subcategory":"Auto Supplies",
            "type":"Retail Goods"
        }
    ],
    "sg:phone":"+61 3 9364 5877",
    "sg:postcode":"3021",
    "sg:province":"VIC",
    "sg:tags":[
        "battery",
        "automotive"
    ],
    "wof:name":"Comet Battery Service",
    "wof:placetype":"venue"
},
  "geometry": {"coordinates":[144.80999800000001,-37.745289],"type":"Point"}
}