{
  "type": "Feature",
  "properties": {
    "iso:country":"AU",
    "sg:address":"23 Viewtech Pl",
    "sg:city":"Rowville",
    "sg:classifiers":[
        {
            "category":"Commercial Area",
            "type":"Public Place"
        }
    ],
    "sg:phone":"+61 3 9764 4744",
    "sg:postcode":"3178",
    "sg:province":"VIC",
    "sg:tags":[
        "heavy",
        "carrier"
    ],
    "wof:name":"George Hilder & Co",
    "wof:placetype":"venue"
},
  "geometry": {"coordinates":[145.22190856899999,-37.9272918701],"type":"Point"}
}