{
  "type": "Feature",
  "properties": {
    "addr:full":"61 Miller St Epping VIC 3076",
    "addr:housenumber":"61",
    "addr:postcode":"3076",
    "addr:street":"Miller St",
    "iso:country":"AU",
    "sg:address":"61 Miller St",
    "sg:city":"Epping",
    "sg:classifiers":[
        {
            "category":"Retail",
            "subcategory":"Auto Repair",
            "type":"Services"
        }
    ],
    "sg:phone":"+61 3 9401 2062",
    "sg:postcode":"3076",
    "sg:province":"VIC",
    "sg:tags":[
        "electrical"
    ],
    "wof:name":"H.M.S. Auto Electrical Services",
    "wof:placetype":"venue"
},
  "geometry": {"coordinates":[144.99185180699999,-37.7514953613],"type":"Point"}
}