{
  "type": "Feature",
  "properties": {
    "addr:full":"Rear Building 276- 278 New Line Rd Dural NSW 2158",
    "addr:housenumber":"278",
    "addr:postcode":"2158",
    "addr:street":"New Line Rd",
    "iso:country":"AU",
    "sg:address":"Rear Building 276- 278 New Line Rd",
    "sg:city":"Dural",
    "sg:classifiers":[
        {
            "category":"Social Services",
            "subcategory":"Child Care",
            "type":"Services"
        }
    ],
    "sg:phone":"+61 2 9651 1855",
    "sg:postcode":"2158",
    "sg:province":"NSW",
    "wof:name":"Wakefield Children's Early Learning Centre",
    "wof:placetype":"venue"
},
  "geometry": {"coordinates":[151.03053283700001,-33.6961631775],"type":"Point"}
}