{
  "type": "Feature",
  "properties": {
    "iso:country":"AU",
    "sg:address":"17 Dartford Rd",
    "sg:city":"Thornleigh",
    "sg:classifiers":[
        {
            "category":"Food & Beverages",
            "subcategory":"Specialty",
            "type":"Retail Goods"
        }
    ],
    "sg:phone":"+61 2 9481 7838",
    "sg:postcode":"2120",
    "sg:province":"NSW",
    "sg:tags":[
        "product",
        "health"
    ],
    "wof:name":"Herbalife Thornleigh",
    "wof:placetype":"venue"
},
  "geometry": {"coordinates":[151.08734130900001,-33.7207641602],"type":"Point"}
}