{
  "type": "Feature",
  "properties": {
    "iso:country":"AU",
    "sg:address":"29 Steiner Ave",
    "sg:city":"Success",
    "sg:classifiers":[
        {
            "category":"Building & Trades",
            "subcategory":"Construction",
            "type":"Services"
        }
    ],
    "sg:phone":"+61 427 998 863",
    "sg:postcode":"6164",
    "sg:province":"WA",
    "sg:tags":[
        "brick",
        "paving"
    ],
    "wof:name":"Tony Wood Landcapes",
    "wof:placetype":"venue"
},
  "geometry": {"coordinates":[115.849998,-32.139881],"type":"Point"}
}