{
  "type": "Feature",
  "properties": {
    "iso:country":"AU",
    "sg:address":"2/ 34 Watt Rd",
    "sg:city":"Mornington",
    "sg:classifiers":[
        {
            "category":"Retail",
            "subcategory":"Auto Repair",
            "type":"Services"
        }
    ],
    "sg:phone":"+61 411 762 196",
    "sg:postcode":"3931",
    "sg:province":"VIC",
    "sg:tags":[
        "repairer",
        "motor",
        "engineer"
    ],
    "wof:name":"P T Js",
    "wof:placetype":"venue"
},
  "geometry": {"coordinates":[145.051879883,-38.2308654785],"type":"Point"}
}