{
  "type": "Feature",
  "properties": {
    "addr:full":"29 Dava Drv Mornington VIC 3931",
    "addr:housenumber":"29",
    "addr:postcode":"3931",
    "addr:street":"Dava Drv",
    "iso:country":"AU",
    "sg:address":"29 Dava Drv",
    "sg:city":"Mornington",
    "sg:classifiers":[
        {
            "category":"Health Services",
            "subcategory":"Health Practitioner",
            "type":"Services"
        }
    ],
    "sg:phone":"+61 3 5975 1500",
    "sg:postcode":"3931",
    "sg:province":"VIC",
    "sg:tags":[
        "pathologist",
        "speech"
    ],
    "wof:name":"O&#039;Callagan Margo",
    "wof:placetype":"venue"
},
  "geometry": {"coordinates":[145.03208923299999,-38.2406349182],"type":"Point"}
}