{
  "type": "Feature",
  "properties": {
    "iso:country":"AU",
    "sg:address":"139 Grants Rd",
    "sg:city":"Baxter",
    "sg:classifiers":[
        {
            "category":"Food & Beverages",
            "subcategory":"Groceries & Convenience Stores",
            "type":"Retail Goods"
        }
    ],
    "sg:phone":"+61 3 5971 4367",
    "sg:postcode":"3911",
    "sg:province":"VIC",
    "wof:name":"Baxter General Store",
    "wof:placetype":"venue"
},
  "geometry": {"coordinates":[145.181732178,-38.200378418],"type":"Point"}
}