{
  "type": "Feature",
  "properties": {
    "addr:full":"8 Maranoa St Parramatta Park QLD 4870",
    "addr:housenumber":"8",
    "addr:postcode":"4870",
    "addr:street":"Maranoa St",
    "iso:country":"AU",
    "sg:address":"8 Maranoa St",
    "sg:city":"Parramatta Park",
    "sg:classifiers":[
        {
            "category":"Building & Trades",
            "subcategory":"Construction",
            "type":"Services"
        }
    ],
    "sg:phone":"+61 7 4031 5457",
    "sg:postcode":"4870",
    "sg:province":"QLD",
    "sg:tags":[
        "window",
        "tinting"
    ],
    "wof:name":"Roland Graf's Auto Centre Pty Ltd",
    "wof:placetype":"venue"
},
  "geometry": {"coordinates":[145.767044067,-16.9217224121],"type":"Point"}
}