{
  "type": "Feature",
  "properties": {
    "addr:full":"342 Preservation Drv Sulphur Creek TAS 7316",
    "addr:housenumber":"342",
    "addr:postcode":"7316",
    "addr:street":"Preservation Drv Sulphur",
    "iso:country":"AU",
    "sg:address":"342 Preservation Drv",
    "sg:city":"Sulphur Creek",
    "sg:classifiers":[
        {
            "category":"Fast Food",
            "type":"Food & Drink"
        }
    ],
    "sg:phone":"+61 3 6435 4287",
    "sg:postcode":"7316",
    "sg:province":"TAS",
    "sg:tags":[
        "away",
        "take"
    ],
    "wof:name":"Dunkies News N Food",
    "wof:placetype":"venue"
},
  "geometry": {"coordinates":[146.019439697,-41.0918807983],"type":"Point"}
}