{
  "type": "Feature",
  "properties": {
    "addr:full":"110 Westminster Ave Golden Beach QLD 4551",
    "addr:housenumber":"110",
    "addr:postcode":"4551",
    "addr:street":"Westminster Ave",
    "iso:country":"AU",
    "sg:address":"110 Westminster Ave",
    "sg:city":"Golden Beach",
    "sg:classifiers":[
        {
            "category":"Structure",
            "subcategory":"Office Building",
            "type":"Public Place"
        }
    ],
    "sg:phone":"+61 412 714 100",
    "sg:postcode":"4551",
    "sg:province":"QLD",
    "sg:tags":[
        "slater",
        "tiler",
        "roof"
    ],
    "wof:name":"Tile Seal",
    "wof:placetype":"venue"
},
  "geometry": {"coordinates":[153.11677551299999,-26.8167629242],"type":"Point"}
}