{
  "type": "Feature",
  "properties": {
    "addr:full":"45 Bathurst St Forbes NSW 2871",
    "addr:housenumber":"45",
    "addr:postcode":"2871",
    "addr:street":"Bathurst St",
    "iso:country":"AU",
    "sg:address":"45 Bathurst St",
    "sg:city":"Forbes",
    "sg:classifiers":[
        {
            "category":"Farming",
            "subcategory":"Farm",
            "type":"Manufacturing & Wholesale Goods"
        }
    ],
    "sg:phone":"+61 2 6852 4446",
    "sg:postcode":"2871",
    "sg:province":"NSW",
    "sg:tags":[
        "farmer"
    ],
    "wof:name":"Stewart A W & L L",
    "wof:placetype":"venue"
},
  "geometry": {"coordinates":[148.0112,-33.399166],"type":"Point"}
}