{
  "type": "Feature",
  "properties": {
    "addr:full":"Unit 4/ 2 Cameron Rd Mt Barker SA 5251",
    "addr:housenumber":"2",
    "addr:postcode":"5251",
    "addr:street":"Cameron Rd",
    "iso:country":"AU",
    "sg:address":"Unit 4/ 2 Cameron Rd",
    "sg:city":"Mt Barker",
    "sg:classifiers":[
        {
            "category":"Health Services",
            "subcategory":"Dentist",
            "type":"Services"
        }
    ],
    "sg:phone":"+61 8 8391 6877",
    "sg:postcode":"5251",
    "sg:province":"SA",
    "sg:tags":[
        "dental",
        "prosthetist"
    ],
    "wof:name":"Joseph Spencer",
    "wof:placetype":"venue"
},
  "geometry": {"coordinates":[138.861328125,-35.0652008057],"type":"Point"}
}