{
  "type": "Feature",
  "properties": {
    "iso:country":"AU",
    "sg:address":"40 Paterson Rd",
    "sg:city":"Mt Nasura",
    "sg:classifiers":[
        {
            "category":"Utilities",
            "subcategory":"Water",
            "type":"Services"
        }
    ],
    "sg:phone":"+61 8 9390 0455",
    "sg:postcode":"6112",
    "sg:province":"WA",
    "sg:tags":[
        "equipment",
        "treatment"
    ],
    "wof:name":"Remote Water Services Pty Ltd",
    "wof:placetype":"venue"
},
  "geometry": {"coordinates":[116.032432556,-32.1332244873],"type":"Point"}
}