{
  "type": "Feature",
  "properties": {
    "addr:full":"758 Wood St Albury NSW 2640",
    "addr:housenumber":"758",
    "addr:postcode":"2640",
    "addr:street":"Wood St",
    "iso:country":"AU",
    "sg:address":"758 Wood St",
    "sg:city":"Albury",
    "sg:classifiers":[
        {
            "category":"Education",
            "subcategory":"Special Training",
            "type":"Public Place"
        }
    ],
    "sg:phone":"+61 2 6021 3500",
    "sg:postcode":"2640",
    "sg:province":"NSW",
    "sg:tags":[
        "tuition-educational"
    ],
    "wof:name":"Master Coaching",
    "wof:placetype":"venue"
},
  "geometry": {"coordinates":[146.928634644,-36.0687141418],"type":"Point"}
}