{
  "type": "Feature",
  "properties": {
    "iso:country":"AU",
    "sg:address":"13 Halstead St",
    "sg:city":"Hamilton Hill",
    "sg:classifiers":[
        {
            "category":"Health Services",
            "subcategory":"Health Practitioner",
            "type":"Services"
        }
    ],
    "sg:phone":"+61 8 9337 4596",
    "sg:postcode":"6163",
    "sg:province":"WA",
    "sg:tags":[
        "naturopath"
    ],
    "wof:name":"Kathie Giblett",
    "wof:placetype":"venue"
},
  "geometry": {"coordinates":[115.794823,-32.080666],"type":"Point"}
}