{
  "type": "Feature",
  "properties": {
    "iso:country":"AU",
    "sg:address":"Shp6/ 8 Bay Shore Drv",
    "sg:city":"Byron Bay",
    "sg:classifiers":[
        {
            "category":"Food & Beverages",
            "subcategory":"Bakery",
            "type":"Retail Goods"
        }
    ],
    "sg:phone":"+61 2 6685 6975",
    "sg:postcode":"2481",
    "sg:province":"NSW",
    "sg:tags":[
        "baker"
    ],
    "wof:name":"Village Bakehouse",
    "wof:placetype":"venue"
},
  "geometry": {"coordinates":[153.58595275900001,-28.6236476898],"type":"Point"}
}