{
  "type": "Feature",
  "properties": {
    "addr:full":"38 Berry St Nowra NSW 2541",
    "addr:housenumber":"38",
    "addr:postcode":"2541",
    "addr:street":"Berry St",
    "iso:country":"AU",
    "sg:address":"38 Berry St",
    "sg:city":"Nowra",
    "sg:classifiers":[
        {
            "category":"Organizations",
            "subcategory":"Community Association",
            "type":"Services"
        }
    ],
    "sg:phone":"+61 2 4423 0444",
    "sg:postcode":"2541",
    "sg:province":"NSW",
    "sg:tags":[
        "organisation",
        "family",
        "welfare"
    ],
    "wof:name":"Smith Family The",
    "wof:placetype":"venue"
},
  "geometry": {"coordinates":[150.59928894000001,-34.8815689087],"type":"Point"}
}