{
  "type": "Feature",
  "properties": {
    "addr:full":"388 Green Rd Heritage Park QLD 4118",
    "addr:housenumber":"388",
    "addr:postcode":"4118",
    "addr:street":"Green Rd",
    "iso:country":"AU",
    "sg:address":"388 Green Rd",
    "sg:city":"Heritage Park",
    "sg:classifiers":[
        {
            "category":"Building & Trades",
            "subcategory":"Construction",
            "type":"Services"
        }
    ],
    "sg:phone":"+61 7 3803 6333",
    "sg:postcode":"4118",
    "sg:province":"QLD",
    "sg:tags":[
        "contractor"
    ],
    "wof:name":"Kensington Homes",
    "wof:placetype":"venue"
},
  "geometry": {"coordinates":[153.06729125999999,-27.6921901703],"type":"Point"}
}