{
  "type": "Feature",
  "properties": {
    "addr:full":"3/ 40 Proprietary St Tingalpa QLD 4173",
    "addr:housenumber":"/ 40",
    "addr:postcode":"4173",
    "addr:street":"Proprietary St",
    "iso:country":"AU",
    "sg:address":"3/ 40 Proprietary St",
    "sg:city":"Tingalpa",
    "sg:classifiers":[
        {
            "category":"Donuts",
            "subcategory":"None",
            "type":"Food & Drink"
        }
    ],
    "sg:phone":"+61 7 3890 0679",
    "sg:postcode":"4173",
    "sg:province":"QLD",
    "sg:tags":[
        "die",
        "engraver",
        "sinker"
    ],
    "wof:name":"Bayside Engraving",
    "wof:placetype":"venue"
},
  "geometry": {"coordinates":[153.10736084000001,-27.4740467072],"type":"Point"}
}