{
  "type": "Feature",
  "properties": {
    "iso:country":"AU",
    "sg:address":"31 Mastgully Rd",
    "sg:city":"Upwey",
    "sg:classifiers":[
        {
            "category":"Professional",
            "subcategory":"Accounting & Tax Preparation",
            "type":"Services"
        }
    ],
    "sg:phone":"+61 3 9497 4699",
    "sg:postcode":"3158",
    "sg:province":"VIC",
    "sg:tags":[
        "jukebox"
    ],
    "wof:name":"Automatic Music Systems (Vic) Pty Ltd",
    "wof:placetype":"venue"
},
  "geometry": {"coordinates":[145.33351135300001,-37.8981781006],"type":"Point"}
}