{
  "type": "Feature",
  "properties": {
    "iso:country":"AU",
    "sg:address":"31 Crouch St South",
    "sg:city":"Mt Gambier",
    "sg:classifiers":[
        {
            "category":"Shopping",
            "subcategory":"Antiques",
            "type":"Retail Goods"
        }
    ],
    "sg:phone":"+61 8 8725 9765",
    "sg:postcode":"5290",
    "sg:province":"SA",
    "wof:name":"Goods & Chattels",
    "wof:placetype":"venue"
},
  "geometry": {"coordinates":[140.78808599999999,-37.827003],"type":"Point"}
}