{
  "type": "Feature",
  "properties": {
    "addr:full":"40 Munro St Babinda QLD 4861",
    "addr:housenumber":"40",
    "addr:postcode":"4861",
    "addr:street":"Munro St",
    "iso:country":"AU",
    "sg:address":"40 Munro St",
    "sg:city":"Babinda",
    "sg:classifiers":[
        {
            "category":"Shopping",
            "subcategory":"Clothing, Apparel, & Fashions",
            "type":"Retail Goods"
        }
    ],
    "sg:phone":"+61 7 4067 1466",
    "sg:postcode":"4861",
    "sg:province":"QLD",
    "sg:tags":[
        "menswear"
    ],
    "wof:name":"A.C. Mellick & Sons Pty Ltd",
    "wof:placetype":"venue"
},
  "geometry": {"coordinates":[145.92219543499999,-17.3438949585],"type":"Point"}
}