{
  "type": "Feature",
  "properties": {
    "addr:full":"83 Marion St Harris Park NSW 2150",
    "addr:housenumber":"83",
    "addr:postcode":"2150",
    "addr:street":"Marion St",
    "iso:country":"AU",
    "sg:address":"83 Marion St",
    "sg:city":"Harris Park",
    "sg:classifiers":[
        {
            "category":"Organizations",
            "subcategory":"Non-profit Organization",
            "type":"Services"
        }
    ],
    "sg:phone":"+61 2 9633 3380",
    "sg:postcode":"2150",
    "sg:province":"NSW",
    "sg:tags":[
        "environmental",
        "organisation",
        "conservation"
    ],
    "wof:name":"Keep Australia Beautiful (NSW)",
    "wof:placetype":"venue"
},
  "geometry": {"coordinates":[151.0103302,-33.8226890564],"type":"Point"}
}