{
  "type": "Feature",
  "properties": {
    "addr:full":"60 Talbot Rd Mt Waverley VIC 3149",
    "addr:housenumber":"60",
    "addr:postcode":"3149",
    "addr:street":"Talbot Rd",
    "iso:country":"AU",
    "sg:address":"60 Talbot Rd",
    "sg:city":"Mt Waverley",
    "sg:classifiers":[
        {
            "category":"Health Services",
            "subcategory":"Doctor",
            "type":"Services"
        }
    ],
    "sg:phone":"+61 3 9807 5474",
    "sg:postcode":"3149",
    "sg:province":"VIC",
    "sg:tags":[
        "medical",
        "practitioner"
    ],
    "wof:name":"Patrick E",
    "wof:placetype":"venue"
},
  "geometry": {"coordinates":[145.124237061,-37.8896484375],"type":"Point"}
}