{
  "type": "Feature",
  "properties": {
    "addr:full":"PO Box 17 Berry NSW 2535",
    "addr:postcode":"2535",
    "iso:country":"AU",
    "sg:address":"PO Box 17",
    "sg:city":"Berry",
    "sg:classifiers":[
        {
            "category":"Professional",
            "subcategory":"Employment Agencies",
            "type":"Services"
        }
    ],
    "sg:phone":"+61 2 4464 1718",
    "sg:postcode":"2535",
    "sg:province":"NSW",
    "sg:tags":[
        "theatrical",
        "managers",
        "agent",
        "producer"
    ],
    "wof:name":"Christine Dunstan Productions Pty Ltd & National Performance Conference",
    "wof:placetype":"venue"
},
  "geometry": {"coordinates":[150.692993164,-34.7750205994],"type":"Point"}
}