{
  "type": "Feature",
  "properties": {
    "iso:country":"AU",
    "sg:address":"20B High St",
    "sg:city":"Lancefield",
    "sg:classifiers":[
        {
            "category":"Banks & Credit Unions",
            "subcategory":"Bank",
            "type":"Services"
        }
    ],
    "sg:phone":"+61 3 5429 1977",
    "sg:postcode":"3435",
    "sg:province":"VIC",
    "wof:name":"Bendigo Community Bank",
    "wof:placetype":"venue"
},
  "geometry": {"coordinates":[144.73472595199999,-37.2768096924],"type":"Point"}
}