{
  "type": "Feature",
  "properties": {
    "addr:full":"Level 1, 73 Walker St North Sydney NSW 2060",
    "addr:housenumber":"73",
    "addr:postcode":"2060",
    "addr:street":"Walker St",
    "iso:country":"AU",
    "sg:address":"Level 1, 73 Walker St",
    "sg:city":"North Sydney",
    "sg:classifiers":[
        {
            "category":"Professional",
            "subcategory":"Employment Agencies",
            "type":"Services"
        }
    ],
    "sg:phone":"+61 2 9957 1166",
    "sg:postcode":"2060",
    "sg:province":"NSW",
    "wof:name":"ID Group",
    "wof:placetype":"venue"
},
  "geometry": {"coordinates":[151.208618164,-33.840549469],"type":"Point"}
}