{
  "type": "Feature",
  "properties": {
    "addr:full":"PO Box 871 Bacchus Marsh VIC 3340",
    "addr:postcode":"3340",
    "iso:country":"AU",
    "sg:address":"PO Box 871",
    "sg:city":"Bacchus Marsh",
    "sg:classifiers":[
        {
            "category":"Professional",
            "subcategory":"Employment Agencies",
            "type":"Services"
        }
    ],
    "sg:phone":"+61 1300 306 997",
    "sg:postcode":"3340",
    "sg:province":"VIC",
    "wof:name":"Better Catering Services",
    "wof:placetype":"venue"
},
  "geometry": {"coordinates":[144.435562,-37.67474],"type":"Point"}
}