{
  "type": "Feature",
  "properties": {
    "iso:country":"AU",
    "sg:address":"98 Acacia Rd",
    "sg:city":"Kirrawee",
    "sg:classifiers":[
        {
            "category":"Building & Trades",
            "subcategory":"Construction",
            "type":"Services"
        }
    ],
    "sg:phone":"+61 408 900 205",
    "sg:postcode":"2232",
    "sg:province":"NSW",
    "sg:tags":[
        "contractor"
    ],
    "wof:name":"S G C Building",
    "wof:placetype":"venue"
},
  "geometry": {"coordinates":[151.06625366200001,-34.0337982178],"type":"Point"}
}