{
  "type": "Feature",
  "properties": {
    "iso:country":"AU",
    "sg:address":"18 Borrell St",
    "sg:city":"Keilor",
    "sg:classifiers":[
        {
            "category":"Building & Trades",
            "subcategory":"Construction",
            "type":"Services"
        }
    ],
    "sg:phone":"+61 3 9331 7178",
    "sg:postcode":"3036",
    "sg:province":"VIC",
    "sg:tags":[
        "scaffolding"
    ],
    "wof:name":"SMS Scaffolding",
    "wof:placetype":"venue"
},
  "geometry": {"coordinates":[144.830414,-37.715179],"type":"Point"}
}