{
  "type": "Feature",
  "properties": {
    "iso:country":"AU",
    "sg:address":"14 Smithfield Ave",
    "sg:city":"Coogee",
    "sg:classifiers":[
        {
            "category":"Building & Trades",
            "subcategory":"Landscaping Services",
            "type":"Services"
        }
    ],
    "sg:phone":"+61 2 9315 8888",
    "sg:postcode":"2034",
    "sg:province":"NSW",
    "sg:tags":[
        "designer",
        "landscape",
        "contractor"
    ],
    "wof:name":"Boughry Pty Ltd",
    "wof:placetype":"venue"
},
  "geometry": {"coordinates":[151.25482177699999,-33.9169044495],"type":"Point"}
}