{
  "type": "Feature",
  "properties": {
    "iso:country":"AU",
    "sg:address":"24 Orchard Rd",
    "sg:city":"Brookvale",
    "sg:classifiers":[
        {
            "category":"Banks & Credit Unions",
            "subcategory":"Investment Brokerage",
            "type":"Services"
        }
    ],
    "sg:phone":"+61 2 9905 8422",
    "sg:postcode":"2100",
    "sg:province":"NSW",
    "sg:tags":[
        "shutter",
        "louvre"
    ],
    "wof:name":"Sarmax Detailed Joinery",
    "wof:placetype":"venue"
},
  "geometry": {"coordinates":[151.27249145499999,-33.7654266357],"type":"Point"}
}