{
  "type": "Feature",
  "properties": {
    "addr:full":"26 Jervis Drv Illawong NSW 2234",
    "addr:housenumber":"26",
    "addr:postcode":"2234",
    "addr:street":"Jervis Drv",
    "iso:country":"AU",
    "sg:address":"26 Jervis Drv",
    "sg:city":"Illawong",
    "sg:classifiers":[
        {
            "category":"Home & Garden",
            "subcategory":"Building Materials",
            "type":"Retail Goods"
        }
    ],
    "sg:phone":"+61 416 199 634",
    "sg:postcode":"2234",
    "sg:province":"NSW",
    "sg:tags":[
        "lawn",
        "cutting",
        "maintenance"
    ],
    "wof:name":"Matts Lawn & Garden Care",
    "wof:placetype":"venue"
},
  "geometry": {"coordinates":[151.01901245100001,-34.0047302246],"type":"Point"}
}