{
  "type": "Feature",
  "properties": {
    "addr:full":"60 Main Hurstbridge Rd Diamond Creek VIC 3089",
    "addr:housenumber":"60",
    "addr:postcode":"3089",
    "addr:street":"Main Hurstbridge Rd",
    "iso:country":"AU",
    "sg:address":"60 Main Hurstbridge Rd",
    "sg:city":"Diamond Creek",
    "sg:classifiers":[
        {
            "category":"Personal",
            "subcategory":"Hair Removal",
            "type":"Services"
        }
    ],
    "sg:phone":"+61 3 9438 5538",
    "sg:postcode":"3089",
    "sg:province":"VIC",
    "wof:name":"Silk Complexions",
    "wof:placetype":"venue"
},
  "geometry": {"coordinates":[145.151184,-37.672939],"type":"Point"}
}