{
  "type": "Feature",
  "properties": {
    "iso:country":"AU",
    "sg:address":"Princess Hwy",
    "sg:city":"Pambula",
    "sg:classifiers":[
        {
            "category":"Travel",
            "subcategory":"Hotels & Motels",
            "type":"Entertainment"
        }
    ],
    "sg:phone":"+61 2 6495 6700",
    "sg:postcode":"2549",
    "sg:province":"NSW",
    "wof:name":"Colonial Motor Inn",
    "wof:placetype":"venue"
},
  "geometry": {"coordinates":[149.87449645999999,-36.9297676086],"type":"Point"}
}