{
  "type": "Feature",
  "properties": {
    "addr:full":"57- 71 Fletcher St Adamstown NSW 2289",
    "addr:housenumber":"71",
    "addr:postcode":"2289",
    "addr:street":"Fletcher St",
    "iso:country":"AU",
    "sg:address":"57- 71 Fletcher St",
    "sg:city":"Adamstown",
    "sg:classifiers":[
        {
            "category":"Wholesale",
            "subcategory":"Farm Supplies",
            "type":"Manufacturing & Wholesale Goods"
        }
    ],
    "sg:phone":"+61 2 4956 3551",
    "sg:postcode":"2289",
    "sg:province":"NSW",
    "sg:tags":[
        "feed",
        "supplement",
        "stock"
    ],
    "wof:name":"Petstock Animal Supplies",
    "wof:placetype":"venue"
},
  "geometry": {"coordinates":[151.71929931599999,-32.9391288757],"type":"Point"}
}