{
  "type": "Feature",
  "properties": {
    "addr:full":"10 Sixteenth St Hepburn Springs VIC 3461",
    "addr:housenumber":"10",
    "addr:postcode":"3461",
    "addr:street":"Sixteenth St Hepburn Springs",
    "iso:country":"AU",
    "sg:address":"10 Sixteenth St",
    "sg:city":"Hepburn Springs",
    "sg:classifiers":[
        {
            "category":"Personal",
            "subcategory":"Massage",
            "type":"Services"
        }
    ],
    "sg:phone":"+61 3 5348 1506",
    "sg:postcode":"3461",
    "sg:province":"VIC",
    "sg:tags":[
        "therapy"
    ],
    "wof:name":"Julsindulgence",
    "wof:placetype":"venue"
},
  "geometry": {"coordinates":[144.128814697,-37.3066139221],"type":"Point"}
}