{
  "type": "Feature",
  "properties": {
    "addr:full":"103 Ingham Rd West End QLD 4810",
    "addr:housenumber":"103",
    "addr:postcode":"4810",
    "addr:street":"Ingham Rd",
    "iso:country":"AU",
    "sg:address":"103 Ingham Rd",
    "sg:city":"West End",
    "sg:classifiers":[
        {
            "category":"Retail",
            "subcategory":"Auto Repair",
            "type":"Services"
        }
    ],
    "sg:phone":"+61 7 4771 6344",
    "sg:postcode":"4810",
    "sg:province":"QLD",
    "sg:tags":[
        "recapping",
        "repairing",
        "retreading",
        "tyre"
    ],
    "wof:name":"Townsville Secondhand & New Tyres",
    "wof:placetype":"venue"
},
  "geometry": {"coordinates":[146.79684399999999,-19.267746],"type":"Point"}
}