{
  "type": "Feature",
  "properties": {
    "addr:full":"Level 7, CML Bldg, 17- 21 University Ave Canberra City ACT 2601",
    "addr:housenumber":"21",
    "addr:postcode":"2601",
    "addr:street":"University Ave",
    "iso:country":"AU",
    "sg:address":"Level 7, CML Bldg, 17- 21 University Ave",
    "sg:city":"Canberra City",
    "sg:classifiers":[
        {
            "category":"Banks & Credit Unions",
            "subcategory":"Financial Services",
            "type":"Services"
        }
    ],
    "sg:phone":"+61 2 6249 1555",
    "sg:postcode":"2601",
    "sg:province":"ACT",
    "sg:tags":[
        "planning"
    ],
    "wof:name":"Godfrey Pembroke Financial Consultants",
    "wof:placetype":"venue"
},
  "geometry": {"coordinates":[149.125274658,-35.2799682617],"type":"Point"}
}