{
  "type": "Feature",
  "properties": {
    "iso:country":"AU",
    "sg:address":"1097 Waugh Rd",
    "sg:city":"Albury North",
    "sg:classifiers":[
        {
            "category":"Manufacturing",
            "subcategory":"Furniture",
            "type":"Manufacturing & Wholesale Goods"
        }
    ],
    "sg:phone":"+61 2 6025 3061",
    "sg:postcode":"2640",
    "sg:province":"NSW",
    "sg:tags":[
        "equipment",
        "hire"
    ],
    "wof:name":"Peards Plant Hire",
    "wof:placetype":"venue"
},
  "geometry": {"coordinates":[146.931915283,-36.0530204773],"type":"Point"}
}