{
  "type": "Feature",
  "properties": {
    "addr:full":"125 Power St Hawthorn VIC 3122",
    "addr:housenumber":"125",
    "addr:postcode":"3122",
    "addr:street":"Power St",
    "iso:country":"AU",
    "sg:address":"125 Power St",
    "sg:city":"Hawthorn",
    "sg:classifiers":[
        {
            "category":"Health Services",
            "subcategory":"Doctor",
            "type":"Services"
        }
    ],
    "sg:phone":"+61 3 9818 7217",
    "sg:postcode":"3122",
    "sg:province":"VIC",
    "sg:tags":[
        "medical",
        "practitioner"
    ],
    "wof:name":"Piesse John Dr",
    "wof:placetype":"venue"
},
  "geometry": {"coordinates":[145.026412964,-37.8222236633],"type":"Point"}
}