{
  "type": "Feature",
  "properties": {
    "addr:full":"24 Executive Drv Burleigh Waters QLD 4220",
    "addr:housenumber":"24",
    "addr:postcode":"4220",
    "addr:street":"Executive Drv",
    "iso:country":"AU",
    "sg:address":"24 Executive Drv",
    "sg:city":"Burleigh Waters",
    "sg:classifiers":[
        {
            "category":"Retail",
            "subcategory":"Auto Rental",
            "type":"Services"
        }
    ],
    "sg:phone":"+61 7 5593 7772",
    "sg:postcode":"4220",
    "sg:province":"QLD",
    "sg:tags":[
        "bus",
        "truck"
    ],
    "wof:name":"U Drive Truck Rentals",
    "wof:placetype":"venue"
},
  "geometry": {"coordinates":[153.42604064899999,-28.0982913971],"type":"Point"}
}