{
  "type": "Feature",
  "properties": {
    "iso:country":"AU",
    "sg:address":"162 Wharparilla Drv",
    "sg:city":"Echuca",
    "sg:classifiers":[
        {
            "category":"Professional",
            "subcategory":"Engineering",
            "type":"Services"
        }
    ],
    "sg:phone":"+61 3 5480 1955",
    "sg:postcode":"3564",
    "sg:province":"VIC",
    "sg:tags":[
        "consulting",
        "engineer"
    ],
    "wof:name":"Alf Grigg & Associates",
    "wof:placetype":"venue"
},
  "geometry": {"coordinates":[144.716629028,-36.1074790955],"type":"Point"}
}