{
  "type": "Feature",
  "properties": {
    "iso:country":"AU",
    "sg:address":"3/ 51 Chard Rd",
    "sg:city":"Brookvale",
    "sg:classifiers":[
        {
            "category":"Professional",
            "subcategory":"Computer Services",
            "type":"Services"
        }
    ],
    "sg:phone":"+61 1300 883 466",
    "sg:postcode":"2100",
    "sg:province":"NSW",
    "sg:tags":[
        "repairs",
        "upgrade",
        "equipment"
    ],
    "wof:name":"Netkiosk Pty Ltd",
    "wof:placetype":"venue"
},
  "geometry": {"coordinates":[151.249542236,-33.7617835999],"type":"Point"}
}