{
  "type": "Feature",
  "properties": {
    "addr:full":"PO Box 44 Hivesville QLD 4612",
    "addr:postcode":"4612",
    "iso:country":"AU",
    "sg:address":"PO Box 44",
    "sg:city":"Hivesville",
    "sg:classifiers":[
        {
            "category":"Real Estate",
            "subcategory":"Real Estate Services",
            "type":"Services"
        }
    ],
    "sg:phone":"+61 1800 689 000",
    "sg:postcode":"4612",
    "sg:province":"QLD",
    "sg:tags":[
        "valuer"
    ],
    "wof:name":"Burnett Property Valuers",
    "wof:placetype":"venue"
},
  "geometry": {"coordinates":[151.686813355,-26.1734600067],"type":"Point"}
}