{
  "type": "Feature",
  "properties": {
    "addr:full":"Suite 2/ 2 Ennis Rd Milsons Point NSW 2061",
    "addr:postcode":"2061",
    "addr:street":"Ennis Rd",
    "iso:country":"AU",
    "sg:address":"Suite 2/ 2 Ennis Rd",
    "sg:city":"Milsons Point",
    "sg:classifiers":[
        {
            "category":"Personal",
            "subcategory":"Massage",
            "type":"Services"
        }
    ],
    "sg:phone":"+61 419 447 224",
    "sg:postcode":"2061",
    "sg:province":"NSW",
    "sg:tags":[
        "therapy"
    ],
    "wof:name":"balm or energy massage therapies",
    "wof:placetype":"venue"
},
  "geometry": {"coordinates":[151.21246337900001,-33.8459587097],"type":"Point"}
}