{
  "type": "Feature",
  "properties": {
    "addr:full":"16 Hampden Rd Mt Barker SA 5251",
    "addr:housenumber":"16",
    "addr:postcode":"5251",
    "addr:street":"Hampden Rd",
    "iso:country":"AU",
    "sg:address":"16 Hampden Rd",
    "sg:city":"Mt Barker",
    "sg:classifiers":[
        {
            "category":"Utilities",
            "subcategory":"Refuse",
            "type":"Services"
        }
    ],
    "sg:phone":"+61 8 8391 0716",
    "sg:postcode":"5251",
    "sg:province":"SA",
    "sg:tags":[
        "remover",
        "rubbish"
    ],
    "wof:name":"Kens Rubbish Bag Service",
    "wof:placetype":"venue"
},
  "geometry": {"coordinates":[138.86285400400001,-35.0709724426],"type":"Point"}
}