{
  "type": "Feature",
  "properties": {
    "addr:full":"217 Coolowie Rd Terrey Hills NSW 2084",
    "addr:housenumber":"217",
    "addr:postcode":"2084",
    "addr:street":"Coolowie Rd",
    "iso:country":"AU",
    "sg:address":"217 Coolowie Rd",
    "sg:city":"Terrey Hills",
    "sg:classifiers":[
        {
            "category":"Retail",
            "subcategory":"Repair Shop",
            "type":"Services"
        }
    ],
    "sg:phone":"+61 2 9949 5253",
    "sg:postcode":"2084",
    "sg:province":"NSW",
    "sg:tags":[
        "upholsterer"
    ],
    "wof:name":"Christensen Upholstery",
    "wof:placetype":"venue"
},
  "geometry": {"coordinates":[151.217285156,-33.6865653992],"type":"Point"}
}