{
  "type": "Feature",
  "properties": {
    "iso:country":"AU",
    "sg:address":"6 MacDermott Pde",
    "sg:city":"Darch",
    "sg:classifiers":[
        {
            "category":"Organizations",
            "subcategory":"Professional Association",
            "type":"Services"
        }
    ],
    "sg:phone":"+61 418 774 013",
    "sg:postcode":"6065",
    "sg:province":"WA",
    "sg:tags":[
        "web",
        "internet"
    ],
    "wof:name":"Hutton Web Development",
    "wof:placetype":"venue"
},
  "geometry": {"coordinates":[115.844741821,-31.8075046539],"type":"Point"}
}