{
  "type": "Feature",
  "properties": {
    "iso:country":"AU",
    "sg:address":"Newell Hwy",
    "sg:city":"Tooraweenah",
    "sg:classifiers":[
        {
            "category":"Travel",
            "subcategory":"Hotels & Motels",
            "type":"Entertainment"
        }
    ],
    "sg:phone":"+61 2 6848 1186",
    "sg:postcode":"2831",
    "sg:province":"NSW",
    "wof:name":"Tooraweenah Cross Roads Cabins",
    "wof:placetype":"venue"
},
  "geometry": {"coordinates":[148.92091369600001,-31.4693546295],"type":"Point"}
}