{
  "type": "Feature",
  "properties": {
    "iso:country":"AU",
    "sg:address":"9 Mathews St",
    "sg:city":"Lockhart",
    "sg:classifiers":[
        {
            "category":"Health Services",
            "subcategory":"Doctor",
            "type":"Services"
        }
    ],
    "sg:phone":"+61 2 6920 4280",
    "sg:postcode":"2656",
    "sg:province":"NSW",
    "sg:tags":[
        "medical",
        "practitioner"
    ],
    "wof:name":"Alsabti Maher",
    "wof:placetype":"venue"
},
  "geometry": {"coordinates":[146.71598815900001,-35.2220649719],"type":"Point"}
}