{
  "type": "Feature",
  "properties": {
    "addr:full":"124 Gowan Rd Runcorn QLD 4113",
    "addr:housenumber":"124",
    "addr:postcode":"4113",
    "addr:street":"Gowan Rd",
    "iso:country":"AU",
    "sg:address":"124 Gowan Rd",
    "sg:city":"Runcorn",
    "sg:classifiers":[
        {
            "category":"Retail",
            "subcategory":"Event Space",
            "type":"Services"
        }
    ],
    "sg:phone":"+61 7 3345 9622",
    "sg:postcode":"4113",
    "sg:province":"QLD",
    "sg:tags":[
        "venue",
        "reception",
        "wedding"
    ],
    "wof:name":"Runcorn Tavern Reception Centre",
    "wof:placetype":"venue"
},
  "geometry": {"coordinates":[153.06507873499999,-27.5956192017],"type":"Point"}
}