{
  "type": "Feature",
  "properties": {
    "addr:full":"(P.O. Building) Shop 1a / 85 Tamar St Ballina NSW 2478",
    "addr:housenumber":"1a / 85",
    "addr:postcode":"2478",
    "addr:street":"Tamar St",
    "iso:country":"AU",
    "sg:address":"(P.O. Building) Shop 1a / 85 Tamar St",
    "sg:city":"Ballina",
    "sg:classifiers":[
        {
            "category":"Personal",
            "subcategory":"Beauty Salon",
            "type":"Services"
        }
    ],
    "sg:phone":"+61 2 6686 4394",
    "sg:postcode":"2478",
    "sg:province":"NSW",
    "sg:tags":[
        "hairdresser"
    ],
    "wof:name":"Tamar Street Hair Studio",
    "wof:placetype":"venue"
},
  "geometry": {"coordinates":[153.55967712399999,-28.8685760498],"type":"Point"}
}