{
  "type": "Feature",
  "properties": {
    "iso:country":"AU",
    "sg:address":"95 Narrabeen Pde",
    "sg:city":"Warriewood",
    "sg:classifiers":[
        {
            "category":"Professional",
            "subcategory":"Printing & Photocopies",
            "type":"Services"
        }
    ],
    "sg:phone":"+61 2 9997 3469",
    "sg:postcode":"2102",
    "sg:province":"NSW",
    "sg:tags":[
        "publishing",
        "desktop"
    ],
    "wof:name":"KC Desktop Publishing",
    "wof:placetype":"venue"
},
  "geometry": {"coordinates":[151.307327,-33.699509],"type":"Point"}
}