{
  "type": "Feature",
  "properties": {
    "iso:country":"AU",
    "sg:address":"132 Wommara Ave",
    "sg:city":"Belmont North",
    "sg:classifiers":[
        {
            "category":"Professional",
            "subcategory":"Detective & Security Services",
            "type":"Services"
        }
    ],
    "sg:phone":"+61 2 4945 3740",
    "sg:postcode":"2280",
    "sg:province":"NSW",
    "sg:tags":[
        "protective",
        "rustproofing"
    ],
    "wof:name":"Jewells Rustproofing Pty Ltd",
    "wof:placetype":"venue"
},
  "geometry": {"coordinates":[151.67616272000001,-33.0215568542],"type":"Point"}
}