{
  "type": "Feature",
  "properties": {
    "addr:full":"Cnr Lester Rd & Cathedral Ave Geraldton WA 6530",
    "addr:postcode":"6530",
    "addr:street":"Cnr Lester Rd &;Ave",
    "iso:country":"AU",
    "sg:address":"Cnr Lester Rd & Cathedral Ave",
    "sg:city":"Geraldton",
    "sg:classifiers":[
        {
            "category":"Autos & Motor Vehicles",
            "subcategory":"Automobile Sales",
            "type":"Retail Goods"
        }
    ],
    "sg:phone":"+61 8 9965 6999",
    "sg:postcode":"6530",
    "sg:province":"WA",
    "sg:tags":[
        "car",
        "new"
    ],
    "wof:name":"Young's Mazda",
    "wof:placetype":"venue"
},
  "geometry": {"coordinates":[114.60975646999999,-28.7749729156],"type":"Point"}
}