{
  "type": "Feature",
  "properties": {
    "addr:full":"Unit 2 130 St Vigeons Rd Reservoir VIC 3073",
    "addr:housenumber":"130",
    "addr:postcode":"3073",
    "addr:street":"St Vigeons Rd",
    "iso:country":"AU",
    "sg:address":"Unit 2 130 St Vigeons Rd",
    "sg:city":"Reservoir",
    "sg:classifiers":[
        {
            "category":"Home & Garden",
            "subcategory":"Carpets & Floor Coverings",
            "type":"Retail Goods"
        }
    ],
    "sg:phone":"+61 407 797 900",
    "sg:postcode":"3073",
    "sg:province":"VIC",
    "sg:tags":[
        "layer",
        "planner"
    ],
    "wof:name":"Carpet Technique",
    "wof:placetype":"venue"
},
  "geometry": {"coordinates":[145.01914977999999,-37.7057037354],"type":"Point"}
}