{
  "type": "Feature",
  "properties": {
    "iso:country":"AU",
    "sg:address":"18 Bowerman Pl",
    "sg:city":"Cherrybrook",
    "sg:classifiers":[
        {
            "category":"Wholesale",
            "subcategory":"Machinery & Supplies",
            "type":"Manufacturing & Wholesale Goods"
        }
    ],
    "sg:phone":"+61 2 9980 7856",
    "sg:postcode":"2126",
    "sg:province":"NSW",
    "sg:tags":[
        "instrument",
        "scientific"
    ],
    "wof:name":"Andrew Young & Co Pty Ltd",
    "wof:placetype":"venue"
},
  "geometry": {"coordinates":[151.04354858400001,-33.7341156006],"type":"Point"}
}