{
  "type": "Feature",
  "properties": {
    "addr:full":"42 - 44 Dampier St Tamworth NSW 2340",
    "addr:housenumber":"44",
    "addr:postcode":"2340",
    "addr:street":"Dampier St",
    "iso:country":"AU",
    "sg:address":"42 - 44 Dampier St",
    "sg:city":"Tamworth",
    "sg:classifiers":[
        {
            "category":"Home & Garden",
            "subcategory":"Building Materials",
            "type":"Retail Goods"
        }
    ],
    "sg:phone":"+61 2 6755 3200",
    "sg:postcode":"2340",
    "sg:province":"NSW",
    "sg:tags":[
        "fencing"
    ],
    "wof:name":"Metalcorp Steel",
    "wof:placetype":"venue"
},
  "geometry": {"coordinates":[150.89796447800001,-31.0949268341],"type":"Point"}
}