{
  "type": "Feature",
  "properties": {
    "addr:full":"263 Fraser Rd (North) Canning Vale WA 6155",
    "addr:housenumber":"263",
    "addr:postcode":"6155",
    "addr:street":"Fraser Rd North",
    "iso:country":"AU",
    "sg:address":"263 Fraser Rd (North)",
    "sg:city":"Canning Vale",
    "sg:classifiers":[
        {
            "category":"Health Services",
            "subcategory":"Dentist",
            "type":"Services"
        }
    ],
    "sg:phone":"+61 1300 307 176",
    "sg:postcode":"6155",
    "sg:province":"WA",
    "wof:name":"Class I Orthodontics",
    "wof:placetype":"venue"
},
  "geometry": {"coordinates":[115.941406,-32.088154],"type":"Point"}
}