{
  "type": "Feature",
  "properties": {
    "iso:country":"AU",
    "sg:address":"135 Bundall Rd",
    "sg:city":"Surfers Paradise",
    "sg:classifiers":[
        {
            "category":"Retail",
            "subcategory":"Event Space",
            "type":"Services"
        }
    ],
    "sg:phone":"+61 7 5581 6500",
    "sg:postcode":"4217",
    "sg:province":"QLD",
    "sg:tags":[
        "venue",
        "reception",
        "wedding"
    ],
    "sg:website":"http://www.gcac.com.au",
    "wof:name":"Gold Coast Arts Centre",
    "wof:placetype":"venue"
},
  "geometry": {"coordinates":[153.41403198200001,-28.0024394989],"type":"Point"}
}