{
  "type": "Feature",
  "properties": {
    "addr:full":"Shop 1, 127 Balgownie Rd Balgownie NSW 2519",
    "addr:housenumber":"shop 1",
    "addr:postcode":"127;2519",
    "addr:street":"Balgownie Rd",
    "iso:country":"AU",
    "sg:address":"Shop 1, 127 Balgownie Rd",
    "sg:city":"Balgownie",
    "sg:classifiers":[
        {
            "category":"Health Services",
            "subcategory":"Health Practitioner",
            "type":"Services"
        }
    ],
    "sg:phone":"+61 2 4284 4511",
    "sg:postcode":"2519",
    "sg:province":"NSW",
    "sg:tags":[
        "bowen",
        "therapy"
    ],
    "wof:name":"Gwen Vardareff Bowen Therapist",
    "wof:placetype":"venue"
},
  "geometry": {"coordinates":[150.878265,-34.388783],"type":"Point"}
}