{
  "type": "Feature",
  "properties": {
    "addr:full":"Southport Central Tower 2 Level 4/ 5 Lawson St Southport QLD 4215",
    "addr:housenumber":"/ 5",
    "addr:postcode":"4215",
    "addr:street":"Lawson St",
    "iso:country":"AU",
    "sg:address":"Southport Central Tower 2 Level 4/ 5 Lawson St",
    "sg:city":"Southport",
    "sg:classifiers":[
        {
            "category":"Health Services",
            "subcategory":"Doctor",
            "type":"Services"
        }
    ],
    "sg:phone":"+61 7 5528 2934",
    "sg:postcode":"4215",
    "sg:province":"QLD",
    "sg:tags":[
        "medical",
        "practitioner"
    ],
    "wof:name":"Queensland Ultrasound For Women",
    "wof:placetype":"venue"
},
  "geometry": {"coordinates":[153.40992736800001,-27.9702301025],"type":"Point"}
}