{
  "type": "Feature",
  "properties": {
    "addr:full":"73 Bathurst St Hobart TAS 7000",
    "addr:housenumber":"73",
    "addr:postcode":"7000",
    "addr:street":"Bathurst St",
    "iso:country":"AU",
    "sg:address":"73 Bathurst St",
    "sg:city":"Hobart",
    "sg:classifiers":[
        {
            "category":"Building & Trades",
            "subcategory":"Equipment Rental",
            "type":"Services"
        }
    ],
    "sg:phone":"+61 438 215 795",
    "sg:postcode":"7000",
    "sg:province":"TAS",
    "sg:tags":[
        "fitness"
    ],
    "wof:name":"Cazaly Consulting",
    "wof:placetype":"venue"
},
  "geometry": {"coordinates":[147.32632446299999,-42.880153656],"type":"Point"}
}