{
  "type": "Feature",
  "properties": {
    "iso:country":"AU",
    "sg:address":"482 Gillies St",
    "sg:city":"Ballarat",
    "sg:classifiers":[
        {
            "category":"Personal",
            "type":"Services"
        }
    ],
    "sg:phone":"+61 1800 253 141",
    "sg:postcode":"3350",
    "sg:province":"VIC",
    "sg:tags":[
        "counselling",
        "alcohol",
        "drug"
    ],
    "wof:name":".05 Licence Back",
    "wof:placetype":"venue"
},
  "geometry": {"coordinates":[143.825119,-37.524975],"type":"Point"}
}