{
  "type": "Feature",
  "properties": {
    "addr:full":"Suite 359 - 656 Military Rd Mosman NSW 2088",
    "addr:housenumber":"656",
    "addr:postcode":"2088",
    "addr:street":"Military Rd",
    "iso:country":"AU",
    "sg:address":"Suite 359 - 656 Military Rd",
    "sg:city":"Mosman",
    "sg:classifiers":[
        {
            "category":"Professional",
            "subcategory":"Accounting & Tax Preparation",
            "type":"Services"
        }
    ],
    "sg:phone":"+61 2 9404 7008",
    "sg:postcode":"2088",
    "sg:province":"NSW",
    "sg:tags":[
        "accountant",
        "auditor"
    ],
    "wof:name":"Tax Travellers",
    "wof:placetype":"venue"
},
  "geometry": {"coordinates":[151.240356445,-33.8243598938],"type":"Point"}
}