{
  "type": "Feature",
  "properties": {
    "addr:full":"407 Chandler Rd Keysborough VIC 3173",
    "addr:housenumber":"407",
    "addr:postcode":"3173",
    "addr:street":"Chandler Rd",
    "iso:country":"AU",
    "sg:address":"407 Chandler Rd",
    "sg:city":"Keysborough",
    "sg:classifiers":[
        {
            "category":"Shopping",
            "subcategory":"Clothing, Apparel, & Fashions",
            "type":"Retail Goods"
        }
    ],
    "sg:phone":"+61 412 367 277",
    "sg:postcode":"3173",
    "sg:province":"VIC",
    "sg:tags":[
        "hire",
        "men's",
        "wear",
        "formal"
    ],
    "wof:name":"Cadesy Suits",
    "wof:placetype":"venue"
},
  "geometry": {"coordinates":[145.18258667000001,-37.9916877747],"type":"Point"}
}