{
  "type": "Feature",
  "properties": {
    "addr:full":"Unit 1, 87 Montague St North Wollongong NSW 2500",
    "addr:housenumber":"87",
    "addr:postcode":"2500",
    "addr:street":"Montague St North",
    "iso:country":"AU",
    "sg:address":"Unit 1, 87 Montague St",
    "sg:city":"North Wollongong",
    "sg:classifiers":[
        {
            "category":"Shopping",
            "subcategory":"Beauty & Cosmetics",
            "type":"Retail Goods"
        }
    ],
    "sg:phone":"+61 2 4226 1887",
    "sg:postcode":"2500",
    "sg:province":"NSW",
    "sg:tags":[
        "equipment",
        "salon",
        "supply"
    ],
    "wof:name":"South Coast Hair & Beauty Supplies",
    "wof:placetype":"venue"
},
  "geometry": {"coordinates":[150.89503500000001,-34.405331],"type":"Point"}
}