{
  "type": "Feature",
  "properties": {
    "addr:full":"Fcty 1/ 16 Swift Way Dandenong South VIC 3175",
    "addr:housenumber":"/ 16",
    "addr:postcode":"3175",
    "addr:street":"Swift Way",
    "iso:country":"AU",
    "sg:address":"Fcty 1/ 16 Swift Way",
    "sg:city":"Dandenong South",
    "sg:classifiers":[
        {
            "category":"Building & Trades",
            "subcategory":"Construction",
            "type":"Services"
        }
    ],
    "sg:phone":"+61 3 9706 5252",
    "sg:postcode":"3175",
    "sg:province":"VIC",
    "sg:tags":[
        "plasterboard",
        "plasterer",
        "fixer"
    ],
    "wof:name":"Triple M Plasterin (VIC) Pty Ltd",
    "wof:placetype":"venue"
},
  "geometry": {"coordinates":[145.20680236800001,-38.0342903137],"type":"Point"}
}