{
  "type": "Feature",
  "properties": {
    "addr:full":"98 - 110 Alexandra Pde Alexandra Headland QLD 4572",
    "addr:housenumber":"110",
    "addr:postcode":"4572",
    "addr:street":"98;Alexandra Pde",
    "iso:country":"AU",
    "sg:address":"98 - 110 Alexandra Pde",
    "sg:city":"Alexandra Headland",
    "sg:classifiers":[
        {
            "category":"Food & Beverages",
            "subcategory":"Bakery",
            "type":"Retail Goods"
        }
    ],
    "sg:phone":"+61 7 5479 4090",
    "sg:postcode":"4572",
    "sg:province":"QLD",
    "sg:tags":[
        "cake",
        "shop",
        "pastry"
    ],
    "wof:name":"The Pastry Chef Bakery Cafe",
    "wof:placetype":"venue"
},
  "geometry": {"coordinates":[153.10524000000001,-26.663979],"type":"Point"}
}