{
  "type": "Feature",
  "properties": {
    "addr:full":"11 Clarendon St Youngtown TAS 7249",
    "addr:housenumber":"11",
    "addr:postcode":"7249",
    "addr:street":"Clarendon St",
    "iso:country":"AU",
    "sg:address":"11 Clarendon St",
    "sg:city":"Youngtown",
    "sg:classifiers":[
        {
            "category":"Professional",
            "subcategory":"Art Services",
            "type":"Services"
        }
    ],
    "sg:phone":"+61 3 6344 6680",
    "sg:postcode":"7249",
    "sg:province":"TAS",
    "sg:tags":[
        "decorator",
        "painter"
    ],
    "wof:name":"Terry Mace",
    "wof:placetype":"venue"
},
  "geometry": {"coordinates":[147.17022705100001,-41.4788131714],"type":"Point"}
}