{
  "type": "Feature",
  "properties": {
    "addr:full":"68 Allima Ave Yallambie VIC 3085",
    "addr:housenumber":"68",
    "addr:postcode":"3085",
    "addr:street":"Allima Ave",
    "iso:country":"AU",
    "sg:address":"68 Allima Ave",
    "sg:city":"Yallambie",
    "sg:classifiers":[
        {
            "category":"Retail",
            "subcategory":"Repair Shop",
            "type":"Services"
        }
    ],
    "sg:phone":"+61 412 518 192",
    "sg:postcode":"3085",
    "sg:province":"VIC",
    "sg:tags":[
        "leadlights"
    ],
    "wof:name":"River Leadlights",
    "wof:placetype":"venue"
},
  "geometry": {"coordinates":[145.10932922399999,-37.7205429077],"type":"Point"}
}