{
  "type": "Feature",
  "properties": {
    "iso:country":"AU",
    "sg:address":"38 Railway Pde",
    "sg:city":"Condell Park",
    "sg:classifiers":[
        {
            "category":"Building & Trades",
            "subcategory":"Construction",
            "type":"Services"
        }
    ],
    "sg:phone":"+61 2 9796 3157",
    "sg:postcode":"2200",
    "sg:province":"NSW",
    "sg:tags":[
        "rendering",
        "cement"
    ],
    "wof:name":"Lebbos H & R Construction Pty Ltd",
    "wof:placetype":"venue"
},
  "geometry": {"coordinates":[151.00744599999999,-33.924702],"type":"Point"}
}