{
  "type": "Feature",
  "properties": {
    "addr:full":"Shp5/ 507 George St South Windsor NSW 2756",
    "addr:housenumber":"507",
    "addr:postcode":"2756",
    "addr:street":"George St",
    "iso:country":"AU",
    "sg:address":"Shp5/ 507 George St",
    "sg:city":"South Windsor",
    "sg:classifiers":[
        {
            "category":"Government",
            "subcategory":"Post Office",
            "type":"Public Place"
        }
    ],
    "sg:phone":"+61 2 4577 7007",
    "sg:postcode":"2756",
    "sg:province":"NSW",
    "sg:tags":[
        "house",
        "doll"
    ],
    "wof:name":"Emmas Doll House",
    "wof:placetype":"venue"
},
  "geometry": {"coordinates":[150.80708313,-33.6176605225],"type":"Point"}
}