{
  "type": "Feature",
  "properties": {
    "addr:full":"69 Keats St Sunnybank QLD 4109",
    "addr:housenumber":"69",
    "addr:postcode":"4109",
    "addr:street":"Keats St",
    "iso:country":"AU",
    "sg:address":"69 Keats St",
    "sg:city":"Sunnybank",
    "sg:classifiers":[
        {
            "category":"Building & Trades",
            "subcategory":"Construction",
            "type":"Services"
        }
    ],
    "sg:phone":"+61 7 3344 4671",
    "sg:postcode":"4109",
    "sg:province":"QLD",
    "sg:tags":[
        "concrete",
        "treatment",
        "repair"
    ],
    "wof:name":"Know How Concrete Technologies",
    "wof:placetype":"venue"
},
  "geometry": {"coordinates":[153.04945373499999,-27.5803604126],"type":"Point"}
}