{
  "type": "Feature",
  "properties": {
    "iso:country":"AU",
    "sg:address":"19 Speedwell Pl",
    "sg:city":"Windsor South",
    "sg:classifiers":[
        {
            "category":"Home & Garden",
            "subcategory":"Building Materials",
            "type":"Retail Goods"
        }
    ],
    "sg:phone":"+61 1300 552 555",
    "sg:postcode":"2756",
    "sg:province":"NSW",
    "sg:tags":[
        "pre-mixed",
        "concrete"
    ],
    "wof:name":"Boral Concrete",
    "wof:placetype":"venue"
},
  "geometry": {"coordinates":[150.81503295900001,-33.627620697],"type":"Point"}
}