{
  "type": "Feature",
  "properties": {
    "iso:country":"AU",
    "sg:address":"46 Grigor St",
    "sg:city":"Caloundra",
    "sg:classifiers":[
        {
            "category":"Structure",
            "subcategory":"Office Building",
            "type":"Public Place"
        }
    ],
    "sg:phone":"+61 7 5491 4988",
    "sg:postcode":"4551",
    "sg:province":"QLD",
    "sg:tags":[
        "tie",
        "concrete",
        "formwork",
        "form",
        "accessory"
    ],
    "wof:name":"Jenkins Formwork",
    "wof:placetype":"venue"
},
  "geometry": {"coordinates":[153.13670349099999,-26.7917060852],"type":"Point"}
}