{
  "type": "Feature",
  "properties": {
    "iso:country":"AU",
    "sg:address":"88 Slater Pde",
    "sg:city":"Keilor East",
    "sg:classifiers":[
        {
            "category":"Professional",
            "subcategory":"Art Services",
            "type":"Services"
        }
    ],
    "sg:phone":"+61 3 9331 6353",
    "sg:postcode":"3033",
    "sg:province":"VIC",
    "sg:tags":[
        "work",
        "metal"
    ],
    "wof:name":"Shush Industries",
    "wof:placetype":"venue"
},
  "geometry": {"coordinates":[144.859467,-37.732166],"type":"Point"}
}