{
  "type": "Feature",
  "properties": {
    "addr:full":"235 South Pine Rd Enoggera QLD 4051",
    "addr:housenumber":"235",
    "addr:postcode":"4051",
    "addr:street":"South Pine Rd",
    "iso:country":"AU",
    "sg:address":"235 South Pine Rd",
    "sg:city":"Enoggera",
    "sg:classifiers":[
        {
            "category":"Social Services",
            "subcategory":"Child Care",
            "type":"Services"
        }
    ],
    "sg:phone":"+61 7 3355 3870",
    "sg:postcode":"4051",
    "sg:province":"QLD",
    "wof:name":"YMCA Outside School Hours Care",
    "wof:placetype":"venue"
},
  "geometry": {"coordinates":[152.99296569800001,-27.4162540436],"type":"Point"}
}