{
  "type": "Feature",
  "properties": {
    "iso:country":"AU",
    "sg:address":"87 Sewell St",
    "sg:city":"East Fremantle",
    "sg:classifiers":[
        {
            "category":"Personal",
            "subcategory":"Massage",
            "type":"Services"
        }
    ],
    "sg:phone":"+61 8 9339 7548",
    "sg:postcode":"6158",
    "sg:province":"WA",
    "sg:tags":[
        "therapy"
    ],
    "wof:name":"Massage Tonic",
    "wof:placetype":"venue"
},
  "geometry": {"coordinates":[115.761139,-32.046677],"type":"Point"}
}