{
  "type": "Feature",
  "properties": {
    "iso:country":"AU",
    "sg:address":"4/ 53 Boyland Ave",
    "sg:city":"Coopers Plains",
    "sg:classifiers":[
        {
            "category":"Utilities",
            "subcategory":"Electric",
            "type":"Services"
        }
    ],
    "sg:phone":"+61 7 3277 7190",
    "sg:postcode":"4108",
    "sg:province":"QLD",
    "sg:tags":[
        "electrical",
        "contractor"
    ],
    "wof:name":"Crown Electrical Pty Ltd",
    "wof:placetype":"venue"
},
  "geometry": {"coordinates":[153.025756836,-27.5641078949],"type":"Point"}
}