{
  "type": "Feature",
  "properties": {
    "iso:country":"AU",
    "sg:address":"96 Spencer Rd",
    "sg:city":"Nerang",
    "sg:classifiers":[
        {
            "category":"Retail",
            "subcategory":"Auto Repair",
            "type":"Services"
        }
    ],
    "sg:phone":"+61 7 5500 4999",
    "sg:postcode":"4211",
    "sg:province":"QLD",
    "sg:tags":[
        "gas",
        "conversion",
        "natural",
        "lp",
        "vehicle"
    ],
    "wof:name":"TrueblueGREEN# Australia Pty Ltd",
    "wof:placetype":"venue"
},
  "geometry": {"coordinates":[153.34437560999999,-28.0073051453],"type":"Point"}
}