{
  "type": "Feature",
  "properties": {
    "addr:full":"323 Corrigan Rd Keysborough VIC 3173",
    "addr:housenumber":"323",
    "addr:postcode":"3173",
    "addr:street":"Corrigan Rd",
    "iso:country":"AU",
    "sg:address":"323 Corrigan Rd",
    "sg:city":"Keysborough",
    "sg:classifiers":[
        {
            "category":"Professional",
            "subcategory":"Art Services",
            "type":"Services"
        }
    ],
    "sg:phone":"+61 3 9798 7553",
    "sg:postcode":"3173",
    "sg:province":"VIC",
    "sg:tags":[
        "decorator",
        "painter"
    ],
    "wof:name":"XLNT Coatings Pty Ltd",
    "wof:placetype":"venue"
},
  "geometry": {"coordinates":[145.16494750999999,-37.9834632874],"type":"Point"}
}