{
  "type": "Feature",
  "properties": {
    "iso:country":"AU",
    "sg:address":"25 Haddon Crs",
    "sg:city":"Marks Point",
    "sg:classifiers":[
        {
            "category":"Retail",
            "subcategory":"Driving School",
            "type":"Services"
        }
    ],
    "sg:phone":"+61 418 470 912",
    "sg:postcode":"2280",
    "sg:province":"NSW",
    "wof:name":"Surf-Side Driving School",
    "wof:placetype":"venue"
},
  "geometry": {"coordinates":[151.65264892600001,-33.056728363],"type":"Point"}
}