{
  "type": "Feature",
  "properties": {
    "addr:full":"8 Hanly St Redhead NSW 2290",
    "addr:housenumber":"8",
    "addr:postcode":"2290",
    "addr:street":"Hanly St",
    "iso:country":"AU",
    "sg:address":"8 Hanly St",
    "sg:city":"Redhead",
    "sg:classifiers":[
        {
            "category":"Professional",
            "subcategory":"Business Services",
            "type":"Services"
        }
    ],
    "sg:phone":"+61 2 4944 9021",
    "sg:postcode":"2290",
    "sg:province":"NSW",
    "sg:tags":[
        "drafting"
    ],
    "wof:name":"Michael Frew Drafting Services",
    "wof:placetype":"venue"
},
  "geometry": {"coordinates":[151.72108459500001,-33.0104904175],"type":"Point"}
}