{
  "type": "Feature",
  "properties": {
    "addr:full":"39 Mountain St Ultimo NSW 2007",
    "addr:housenumber":"39",
    "addr:postcode":"2007",
    "addr:street":"Mountain St",
    "iso:country":"AU",
    "sg:address":"39 Mountain St",
    "sg:city":"Ultimo",
    "sg:classifiers":[
        {
            "category":"Utilities",
            "subcategory":"Telephone",
            "type":"Services"
        }
    ],
    "sg:phone":"+61 2 9212 7257",
    "sg:postcode":"2007",
    "sg:province":"NSW",
    "sg:tags":[
        "accessory"
    ],
    "wof:name":"New Era Communications (Aust) Pty Ltd",
    "wof:placetype":"venue"
},
  "geometry": {"coordinates":[151.196075439,-33.8826828003],"type":"Point"}
}