{
  "type": "Feature",
  "properties": {
    "addr:full":"1050 Nepean Hwy Mornington VIC 3931",
    "addr:housenumber":"1050",
    "addr:postcode":"3931",
    "addr:street":"Nepean Hwy",
    "iso:country":"AU",
    "sg:address":"1050 Nepean Hwy",
    "sg:city":"Mornington",
    "sg:classifiers":[
        {
            "category":"Health Services",
            "subcategory":"Doctor",
            "type":"Services"
        }
    ],
    "sg:phone":"+61 3 5975 6095",
    "sg:postcode":"3931",
    "sg:province":"VIC",
    "sg:tags":[
        "medical",
        "practitioner"
    ],
    "wof:name":"Rope S",
    "wof:placetype":"venue"
},
  "geometry": {"coordinates":[145.055343628,-38.2216873169],"type":"Point"}
}