{
  "type": "Feature",
  "properties": {
    "iso:country":"AU",
    "sg:address":"PO Box 116",
    "sg:city":"Hurstville",
    "sg:classifiers":[
        {
            "category":"Retail",
            "subcategory":"Car Wash",
            "type":"Services"
        }
    ],
    "sg:phone":"+61 414 351 091",
    "sg:postcode":"1493",
    "sg:province":"NSW",
    "sg:tags":[
        "truck",
        "cleaning"
    ],
    "wof:name":"Dynamic Mobile Car Detailing",
    "wof:placetype":"venue"
},
  "geometry": {"coordinates":[151.101181,-33.965919],"type":"Point"}
}