{
  "type": "Feature",
  "properties": {
    "iso:country":"AU",
    "sg:address":"10 Downes St",
    "sg:city":"Belfield",
    "sg:classifiers":[
        {
            "category":"Social Services",
            "subcategory":"Child Care",
            "type":"Services"
        }
    ],
    "sg:phone":"+61 2 9642 8540",
    "sg:postcode":"2191",
    "sg:province":"NSW",
    "wof:name":"Belfield Kindergarten & Nursery",
    "wof:placetype":"venue"
},
  "geometry": {"coordinates":[151.084518,-33.903191],"type":"Point"}
}