{
  "type": "Feature",
  "properties": {
    "iso:country":"AU",
    "sg:address":"9/ 38 Kendor St",
    "sg:city":"Arundel",
    "sg:classifiers":[
        {
            "category":"Professional",
            "type":"Services"
        }
    ],
    "sg:phone":"+61 7 5537 3888",
    "sg:postcode":"4214",
    "sg:province":"QLD",
    "sg:tags":[
        "shop",
        "fitting"
    ],
    "wof:name":"Store Development",
    "wof:placetype":"venue"
},
  "geometry": {"coordinates":[153.378143311,-27.9358501434],"type":"Point"}
}