{
  "type": "Feature",
  "properties": {
    "addr:full":"16 Portia St Flagstaff Hill SA 5159",
    "addr:housenumber":"16",
    "addr:postcode":"5159",
    "addr:street":"Portia St",
    "iso:country":"AU",
    "sg:address":"16 Portia St",
    "sg:city":"Flagstaff Hill",
    "sg:classifiers":[
        {
            "category":"Personal",
            "subcategory":"Beauty Salon",
            "type":"Services"
        }
    ],
    "sg:phone":"+61 410 881 965",
    "sg:postcode":"5159",
    "sg:province":"SA",
    "wof:name":"Beauty By Sam",
    "wof:placetype":"venue"
},
  "geometry": {"coordinates":[138.59510803200001,-35.0593223572],"type":"Point"}
}