{
  "type": "Feature",
  "properties": {
    "addr:full":"36 Kildare Rd (Cnr Balmoral St) Blacktown NSW 2148",
    "addr:housenumber":"36",
    "addr:postcode":"2148",
    "addr:street":"Kildare Rd Cnr Balmoral St",
    "iso:country":"AU",
    "sg:address":"36 Kildare Rd (Cnr Balmoral St)",
    "sg:city":"Blacktown",
    "sg:classifiers":[
        {
            "category":"Health Services",
            "subcategory":"Health Practitioner",
            "type":"Services"
        }
    ],
    "sg:phone":"+61 2 9831 2433",
    "sg:postcode":"2148",
    "sg:province":"NSW",
    "sg:tags":[
        "acupuncture"
    ],
    "wof:name":"Rushton P",
    "wof:placetype":"venue"
},
  "geometry": {"coordinates":[150.90472412099999,-33.7689971924],"type":"Point"}
}