{
  "type": "Feature",
  "properties": {
    "iso:country":"AU",
    "sg:address":"1st Floor, Bass House, Edward St",
    "sg:city":"Devonport",
    "sg:classifiers":[
        {
            "category":"Banks & Credit Unions",
            "subcategory":"Financial Services",
            "type":"Services"
        }
    ],
    "sg:phone":"+61 3 6423 1255",
    "sg:postcode":"7310",
    "sg:province":"TAS",
    "sg:tags":[
        "loan",
        "finance",
        "mortgage"
    ],
    "wof:name":"Tassie Home Loans Pty Ltd",
    "wof:placetype":"venue"
},
  "geometry": {"coordinates":[146.35972595199999,-41.1789932251],"type":"Point"}
}