{
  "type": "Feature",
  "properties": {
    "addr:full":"260 Fulham Rd Heatley QLD 4814",
    "addr:housenumber":"260",
    "addr:postcode":"4814",
    "addr:street":"Fulham Rd",
    "iso:country":"AU",
    "sg:address":"260 Fulham Rd",
    "sg:city":"Heatley",
    "sg:classifiers":[
        {
            "category":"Health Services",
            "subcategory":"Doctor",
            "type":"Services"
        }
    ],
    "sg:phone":"+61 7 4723 0855",
    "sg:postcode":"4814",
    "sg:province":"QLD",
    "sg:tags":[
        "nurse",
        "nursing"
    ],
    "wof:name":"St Lukes Nursing Service",
    "wof:placetype":"venue"
},
  "geometry": {"coordinates":[146.758881,-19.288057],"type":"Point"}
}