{
  "type": "Feature",
  "properties": {
    "addr:full":"269 Parker St Cootamundra NSW 2590",
    "addr:housenumber":"269",
    "addr:postcode":"2590",
    "addr:street":"Parker St",
    "iso:country":"AU",
    "sg:address":"269 Parker St",
    "sg:city":"Cootamundra",
    "sg:classifiers":[
        {
            "category":"Personal",
            "subcategory":"Beauty Salon",
            "type":"Services"
        }
    ],
    "sg:phone":"+61 2 6942 7788",
    "sg:postcode":"2590",
    "sg:province":"NSW",
    "wof:name":"Body Aspect",
    "wof:placetype":"venue"
},
  "geometry": {"coordinates":[148.02264404300001,-34.6399345398],"type":"Point"}
}