{
  "type": "Feature",
  "properties": {
    "addr:full":"Unit 5/ 30 Gordon St Burwood NSW 2134",
    "addr:housenumber":"30",
    "addr:postcode":"2134",
    "addr:street":"Gordon St",
    "iso:country":"AU",
    "sg:address":"Unit 5/ 30 Gordon St",
    "sg:city":"Burwood",
    "sg:classifiers":[
        {
            "category":"Wholesale",
            "subcategory":"Painting Supplies",
            "type":"Manufacturing & Wholesale Goods"
        }
    ],
    "sg:phone":"+61 2 9747 3647",
    "sg:postcode":"2134",
    "sg:province":"NSW",
    "sg:tags":[
        "product",
        "cleaning"
    ],
    "wof:name":"Tcheein Holding Pty Ltd",
    "wof:placetype":"venue"
},
  "geometry": {"coordinates":[151.099487305,-33.874206543],"type":"Point"}
}