{
  "type": "Feature",
  "properties": {
    "addr:full":"Pacific Hwy Lindfield NSW 2070",
    "addr:postcode":"2070",
    "addr:street":"Pacific Hwy",
    "iso:country":"AU",
    "sg:address":"Pacific Hwy",
    "sg:city":"Lindfield",
    "sg:classifiers":[
        {
            "category":"Cafe",
            "type":"Food & Drink"
        }
    ],
    "sg:phone":"+61 2 9416 8392",
    "sg:postcode":"2070",
    "sg:province":"NSW",
    "wof:name":"Cafe Belaroma",
    "wof:placetype":"venue"
},
  "geometry": {"coordinates":[151.16868591299999,-33.7751808167],"type":"Point"}
}