{
  "type": "Feature",
  "properties": {
    "iso:country":"AU",
    "sg:address":"125 Sturt St",
    "sg:city":"Ballarat",
    "sg:classifiers":[
        {
            "category":"Manufacturing",
            "subcategory":"Jewelry",
            "type":"Manufacturing & Wholesale Goods"
        }
    ],
    "sg:phone":"+61 3 5331 1182",
    "sg:postcode":"3350",
    "sg:province":"VIC",
    "sg:tags":[
        "designer",
        "jewellery"
    ],
    "wof:name":"McConnells Jewellers",
    "wof:placetype":"venue"
},
  "geometry": {"coordinates":[143.858337,-37.56234],"type":"Point"}
}