{
  "type": "Feature",
  "properties": {
    "addr:full":"Harbourside Shpng Cntr 91 Middle Cleveland QLD 4163",
    "addr:housenumber":"91",
    "addr:postcode":"4163",
    "addr:street":"Middle",
    "iso:country":"AU",
    "sg:address":"Harbourside Shpng Cntr 91 Middle",
    "sg:city":"Cleveland",
    "sg:classifiers":[
        {
            "category":"Shopping",
            "subcategory":"Clothing, Apparel, & Fashions",
            "type":"Retail Goods"
        }
    ],
    "sg:phone":"+61 7 3286 3133",
    "sg:postcode":"4163",
    "sg:province":"QLD",
    "sg:tags":[
        "lady",
        "wear"
    ],
    "wof:name":"Cleveland Centre Boutique",
    "wof:placetype":"venue"
},
  "geometry": {"coordinates":[153.26783752399999,-27.5260181427],"type":"Point"}
}