{
  "type": "Feature",
  "properties": {
    "addr:full":"42 Skarratt St Silverwater NSW 2128",
    "addr:housenumber":"42",
    "addr:postcode":"2128",
    "addr:street":"Skarratt St",
    "iso:country":"AU",
    "sg:address":"42 Skarratt St",
    "sg:city":"Silverwater",
    "sg:classifiers":[
        {
            "category":"Retail",
            "subcategory":"Auto Repair",
            "type":"Services"
        }
    ],
    "sg:phone":"+61 2 9647 0000",
    "sg:postcode":"2128",
    "sg:province":"NSW",
    "sg:tags":[
        "testing",
        "inspection",
        "motor",
        "vehicle"
    ],
    "wof:name":"Serv Group (AUST)",
    "wof:placetype":"venue"
},
  "geometry": {"coordinates":[151.03749084500001,-33.8345565796],"type":"Point"}
}