{
  "type": "Feature",
  "properties": {
    "addr:full":"63 MacOrna St Watsonia VIC 3087",
    "addr:housenumber":"63",
    "addr:postcode":"3087",
    "addr:street":"Macorna St",
    "iso:country":"AU",
    "sg:address":"63 MacOrna St",
    "sg:city":"Watsonia",
    "sg:classifiers":[
        {
            "category":"Building & Trades",
            "subcategory":"Landscaping Services",
            "type":"Services"
        }
    ],
    "sg:phone":"+61 3 9435 4350",
    "sg:postcode":"3087",
    "sg:province":"VIC",
    "sg:tags":[
        "designer",
        "landscape",
        "contractor"
    ],
    "wof:name":"Jaydees Landscaping",
    "wof:placetype":"venue"
},
  "geometry": {"coordinates":[145.08473205600001,-37.6980895996],"type":"Point"}
}