{
  "type": "Feature",
  "properties": {
    "iso:country":"AU",
    "sg:address":"Shp 1/ 379 Scarborough Beach Rd",
    "sg:city":"Innaloo",
    "sg:classifiers":[
        {
            "category":"Restaurant",
            "type":"Food & Drink"
        }
    ],
    "sg:phone":"+61 8 9244 1741",
    "sg:postcode":"6018",
    "sg:province":"WA",
    "wof:name":"Anghiti Restaurant",
    "wof:placetype":"venue"
},
  "geometry": {"coordinates":[115.797042847,-31.9025268555],"type":"Point"}
}