{
  "type": "Feature",
  "properties": {
    "iso:country":"AU",
    "sg:address":"74 Village High Rd",
    "sg:city":"Vaucluse",
    "sg:classifiers":[
        {
            "category":"Utilities",
            "subcategory":"Natural Gas",
            "type":"Services"
        }
    ],
    "sg:phone":"+61 2 9337 1260",
    "sg:postcode":"2030",
    "sg:province":"NSW",
    "sg:tags":[
        "supplier"
    ],
    "wof:name":"Independent Gas",
    "wof:placetype":"venue"
},
  "geometry": {"coordinates":[151.27972412099999,-33.851020813],"type":"Point"}
}