{
  "type": "Feature",
  "properties": {
    "addr:full":"6 Sanctuary Pl Hyland Park NSW 2448",
    "addr:housenumber":"6",
    "addr:postcode":"2448",
    "addr:street":"Sanctuary Pl",
    "iso:country":"AU",
    "sg:address":"6 Sanctuary Pl",
    "sg:city":"Hyland Park",
    "sg:classifiers":[
        {
            "category":"Real Estate",
            "subcategory":"Architect",
            "type":"Services"
        }
    ],
    "sg:phone":"+61 2 6568 9759",
    "sg:postcode":"2448",
    "sg:province":"NSW",
    "wof:name":"Hamilton & Hamilton Pty Ltd",
    "wof:placetype":"venue"
},
  "geometry": {"coordinates":[153.004639,-30.613001],"type":"Point"}
}