{
  "type": "Feature",
  "properties": {
    "addr:full":"133 Strickland Pde Ballarat VIC 3350",
    "addr:housenumber":"133",
    "addr:postcode":"3350",
    "addr:street":"Strickland Pde",
    "iso:country":"AU",
    "sg:address":"133 Strickland Pde",
    "sg:city":"Ballarat",
    "sg:classifiers":[
        {
            "category":"Home & Garden",
            "subcategory":"Building Materials",
            "type":"Retail Goods"
        }
    ],
    "sg:phone":"+61 418 518 270",
    "sg:postcode":"3350",
    "sg:province":"VIC",
    "sg:tags":[
        "roofing"
    ],
    "wof:name":"Promet Roofing",
    "wof:placetype":"venue"
},
  "geometry": {"coordinates":[143.90748600000001,-37.562191],"type":"Point"}
}