{
  "type": "Feature",
  "properties": {
    "iso:country":"AU",
    "sg:address":"Level 3, 283 Clarence St",
    "sg:city":"Sydney",
    "sg:classifiers":[
        {
            "category":"Insurance",
            "subcategory":"Insurance Agent",
            "type":"Services"
        }
    ],
    "sg:phone":"+61 2 8916 6450",
    "sg:postcode":"2000",
    "sg:province":"NSW",
    "sg:tags":[
        "broker"
    ],
    "sg:website":"http://www.chegwyn.com.au",
    "wof:name":"Chegwyn Corporate Services Pty Ltd",
    "wof:placetype":"venue"
},
  "geometry": {"coordinates":[151.205535889,-33.8725128174],"type":"Point"}
}