{
  "type": "Feature",
  "properties": {
    "iso:country":"AU",
    "sg:address":"5 Belmore Rd",
    "sg:city":"Riverwood",
    "sg:classifiers":[
        {
            "category":"Social Services",
            "subcategory":"Child Care",
            "type":"Services"
        }
    ],
    "sg:phone":"+61 2 9534 3157",
    "sg:postcode":"2210",
    "sg:province":"NSW",
    "wof:name":"SDN Childrens Services",
    "wof:placetype":"venue"
},
  "geometry": {"coordinates":[151.052963,-33.946522],"type":"Point"}
}