{
  "type": "Feature",
  "properties": {
    "iso:country":"AU",
    "sg:address":"60 Kingdon St",
    "sg:city":"Scone",
    "sg:classifiers":[
        {
            "category":"Education",
            "subcategory":"School",
            "type":"Public Place"
        }
    ],
    "sg:phone":"+61 2 6545 3131",
    "sg:postcode":"2337",
    "sg:province":"NSW",
    "sg:tags":[
        "co-educational"
    ],
    "wof:name":"Scone Grammar School",
    "wof:placetype":"venue"
},
  "geometry": {"coordinates":[150.863525391,-32.0520973206],"type":"Point"}
}