{
  "type": "Feature",
  "properties": {
    "addr:full":"6 Picton Ave Picton NSW 2571",
    "addr:housenumber":"6",
    "addr:postcode":"2571",
    "addr:street":"Picton Ave",
    "iso:country":"AU",
    "sg:address":"6 Picton Ave",
    "sg:city":"Picton",
    "sg:classifiers":[
        {
            "category":"Professional",
            "subcategory":"Accounting & Tax Preparation",
            "type":"Services"
        }
    ],
    "sg:phone":"+61 2 4677 1638",
    "sg:postcode":"2571",
    "sg:province":"NSW",
    "sg:tags":[
        "accountant",
        "auditor"
    ],
    "wof:name":"Apps B A",
    "wof:placetype":"venue"
},
  "geometry": {"coordinates":[150.611495972,-34.1690788269],"type":"Point"}
}