{
  "type": "Feature",
  "properties": {
    "addr:full":"30 Maitland St Muswellbrook NSW 2333",
    "addr:housenumber":"30",
    "addr:postcode":"2333",
    "addr:street":"Maitland St",
    "iso:country":"AU",
    "sg:address":"30 Maitland St",
    "sg:city":"Muswellbrook",
    "sg:classifiers":[
        {
            "category":"Sports & Exercise",
            "subcategory":"Gym",
            "type":"Entertainment"
        }
    ],
    "sg:phone":"+61 2 6543 1111",
    "sg:postcode":"2333",
    "sg:province":"NSW",
    "sg:tags":[
        "health",
        "fitness"
    ],
    "wof:name":"Muswellbrook Physiotherapy & Sports Injury Centre",
    "wof:placetype":"venue"
},
  "geometry": {"coordinates":[150.88911438,-32.2704849243],"type":"Point"}
}