{
  "type": "Feature",
  "properties": {
    "addr:full":"23 Nielson La Sussex Inlet NSW 2540",
    "addr:housenumber":"23",
    "addr:postcode":"2540",
    "addr:street":"Nielson La Sussex",
    "iso:country":"AU",
    "sg:address":"23 Nielson La",
    "sg:city":"Sussex Inlet",
    "sg:classifiers":[
        {
            "category":"Professional",
            "subcategory":"Accounting & Tax Preparation",
            "type":"Services"
        }
    ],
    "sg:phone":"+61 2 4441 3533",
    "sg:postcode":"2540",
    "sg:province":"NSW",
    "sg:tags":[
        "accountant",
        "auditor"
    ],
    "wof:name":"Bettadvisers Pty Ltd",
    "wof:placetype":"venue"
},
  "geometry": {"coordinates":[150.599212647,-35.157245636],"type":"Point"}
}