{
  "type": "Feature",
  "properties": {
    "iso:country":"AU",
    "sg:address":"9 Sandalwood Ave",
    "sg:city":"Maryland",
    "sg:classifiers":[
        {
            "category":"Wholesale",
            "subcategory":"Painting Supplies",
            "type":"Manufacturing & Wholesale Goods"
        }
    ],
    "sg:phone":"+61 2 4951 6470",
    "sg:postcode":"2287",
    "sg:province":"NSW",
    "sg:tags":[
        "product",
        "cleaning"
    ],
    "wof:name":"Hubbard Paul & Lynne (Amway Distributor)",
    "wof:placetype":"venue"
},
  "geometry": {"coordinates":[151.65126037600001,-32.8829345703],"type":"Point"}
}