{
  "type": "Feature",
  "properties": {
    "iso:country":"AU",
    "sg:address":"17 Scoresby Rd",
    "sg:city":"Bayswater",
    "sg:classifiers":[
        {
            "category":"Retail",
            "subcategory":"Auto Repair",
            "type":"Services"
        }
    ],
    "sg:phone":"+61 3 9720 8100",
    "sg:postcode":"3153",
    "sg:province":"VIC",
    "sg:tags":[
        "repairer",
        "motor",
        "engineer"
    ],
    "sg:website":"http://www.servautogroup.com.au",
    "wof:name":"Saa Serv",
    "wof:placetype":"venue"
},
  "geometry": {"coordinates":[145.27090454099999,-37.841053009],"type":"Point"}
}