{
  "type": "Feature",
  "properties": {
    "addr:full":"Tropical Arcade 1st Floor Cnr Shields & Abbotts Sts Cairns QLD 4870",
    "addr:housenumber":"cnr;&",
    "addr:postcode":"4870",
    "iso:country":"AU",
    "sg:address":"Tropical Arcade 1st Floor Cnr Shields & Abbotts Sts",
    "sg:city":"Cairns",
    "sg:classifiers":[
        {
            "category":"Organizations",
            "subcategory":"Community Association",
            "type":"Services"
        }
    ],
    "sg:phone":"+61 7 4031 6733",
    "sg:postcode":"4870",
    "sg:province":"QLD",
    "sg:tags":[
        "organisation",
        "family",
        "welfare"
    ],
    "wof:name":"Housing Resource Services",
    "wof:placetype":"venue"
},
  "geometry": {"coordinates":[145.77317810100001,-16.9241485596],"type":"Point"}
}