{
  "type": "Feature",
  "properties": {
    "addr:full":"17-19 Tatura Ave Gosford NSW 2250",
    "addr:housenumber":"17-19",
    "addr:postcode":"2250",
    "addr:street":"Tatura Ave",
    "iso:country":"AU",
    "sg:address":"17-19 Tatura Ave",
    "sg:city":"Gosford",
    "sg:classifiers":[
        {
            "category":"Home & Garden",
            "subcategory":"Building Materials",
            "type":"Retail Goods"
        }
    ],
    "sg:phone":"+61 2 4352 2620",
    "sg:postcode":"2250",
    "sg:province":"NSW",
    "sg:tags":[
        "gate"
    ],
    "wof:name":"Fencing Manufacturers Pty Ltd",
    "wof:placetype":"venue"
},
  "geometry": {"coordinates":[151.3412323,-33.4107055664],"type":"Point"}
}