{
  "type": "Feature",
  "properties": {
    "iso:country":"AU",
    "sg:address":"185 Cherry La",
    "sg:city":"Laverton North",
    "sg:classifiers":[
        {
            "category":"Building & Trades",
            "subcategory":"Equipment Rental",
            "type":"Services"
        }
    ],
    "sg:phone":"+61 3 9369 9111",
    "sg:postcode":"3026",
    "sg:province":"VIC",
    "sg:tags":[
        "repairing",
        "changing",
        "retreading",
        "tyre"
    ],
    "wof:name":"Eagle S.M.F. Distributors",
    "wof:placetype":"venue"
},
  "geometry": {"coordinates":[144.783875,-37.841927],"type":"Point"}
}