{
  "type": "Feature",
  "properties": {
    "addr:full":"276 Edward St, 1 st Flr Bowman Hse Brisbane City QLD 4000",
    "addr:housenumber":"276;1",
    "addr:postcode":"4000",
    "addr:street":"Edward St;St",
    "iso:country":"AU",
    "sg:address":"276 Edward St, 1",
    "sg:city":"st Flr Bowman Hse Brisbane City",
    "sg:classifiers":[
        {
            "category":"Health Services",
            "subcategory":"Dentist",
            "type":"Services"
        }
    ],
    "sg:phone":"+61 7 3221 4632",
    "sg:postcode":"4000",
    "sg:province":"QLD",
    "wof:name":"David M Cowhig",
    "wof:placetype":"venue"
},
  "geometry": {"coordinates":[153.02586364699999,-27.467420578],"type":"Point"}
}