{
  "type": "Feature",
  "properties": {
    "addr:full":"325 Woolcock St Garbutt QLD 4814",
    "addr:housenumber":"325",
    "addr:postcode":"4814",
    "addr:street":"Woolcock St",
    "iso:country":"AU",
    "sg:address":"325 Woolcock St",
    "sg:city":"Garbutt",
    "sg:classifiers":[
        {
            "category":"Industrial Area",
            "type":"Public Place"
        }
    ],
    "sg:phone":"+61 7 4728 4822",
    "sg:postcode":"4814",
    "sg:province":"QLD",
    "sg:tags":[
        "rural",
        "shed"
    ],
    "wof:name":"McSheds",
    "wof:placetype":"venue"
},
  "geometry": {"coordinates":[146.77131700000001,-19.268503],"type":"Point"}
}