{
  "type": "Feature",
  "properties": {
    "addr:full":"1 Fifth St Ardrossan SA 5571",
    "addr:housenumber":"1",
    "addr:postcode":"5571",
    "addr:street":"Fifth St",
    "iso:country":"AU",
    "sg:address":"1 Fifth St",
    "sg:city":"Ardrossan",
    "sg:classifiers":[
        {
            "category":"Travel",
            "subcategory":"Hotels & Motels",
            "type":"Entertainment"
        }
    ],
    "sg:phone":"+61 8 8837 3007",
    "sg:postcode":"5571",
    "sg:province":"SA",
    "wof:name":"Motel Hotel Royal House Ardrossan",
    "wof:placetype":"venue"
},
  "geometry": {"coordinates":[137.91920471200001,-34.4225654602],"type":"Point"}
}