{
  "type": "Feature",
  "properties": {
    "addr:full":"Caves Rd Dunsborough WA 6281",
    "addr:postcode":"6281",
    "addr:street":"Caves Rd",
    "iso:country":"AU",
    "sg:address":"Caves Rd",
    "sg:city":"Dunsborough",
    "sg:classifiers":[
        {
            "category":"Recreation",
            "subcategory":"Fishing",
            "type":"Entertainment"
        }
    ],
    "sg:phone":"+61 8 9755 3056",
    "sg:postcode":"6281",
    "sg:province":"WA",
    "sg:tags":[
        "bait"
    ],
    "wof:name":"Selim Processors",
    "wof:placetype":"venue"
},
  "geometry": {"coordinates":[115.102020264,-33.617477417],"type":"Point"}
}