{
  "type": "Feature",
  "properties": {
    "iso:country":"AU",
    "sg:address":"Lvl 1/ 10 Marine Tce",
    "sg:city":"Burnie",
    "sg:classifiers":[
        {
            "category":"Health Services",
            "subcategory":"Doctor",
            "type":"Services"
        }
    ],
    "sg:phone":"+61 3 6431 6511",
    "sg:postcode":"7320",
    "sg:province":"TAS",
    "sg:tags":[
        "medical",
        "practitioner"
    ],
    "wof:name":"Bulle Themba",
    "wof:placetype":"venue"
},
  "geometry": {"coordinates":[145.898254,-41.075859],"type":"Point"}
}