{
  "type": "Feature",
  "properties": {
    "iso:country":"AU",
    "sg:address":"230 Nicholls Rivulet Rd",
    "sg:city":"Oyster Cove",
    "sg:classifiers":[
        {
            "category":"Farming",
            "subcategory":"Nursery",
            "type":"Manufacturing & Wholesale Goods"
        }
    ],
    "sg:phone":"+61 3 6278 9538",
    "sg:postcode":"7150",
    "sg:province":"TAS",
    "wof:name":"Plants For Fruit Farm And Foliage",
    "wof:placetype":"venue"
},
  "geometry": {"coordinates":[147.217926025,-43.1045303345],"type":"Point"}
}