{
  "type": "Feature",
  "properties": {
    "addr:full":"Newcombe St Portarlington VIC 3223",
    "addr:postcode":"3223",
    "addr:street":"Newcombe St",
    "iso:country":"AU",
    "sg:address":"Newcombe St",
    "sg:city":"Portarlington",
    "sg:classifiers":[
        {
            "category":"Education",
            "subcategory":"Kindergarten",
            "type":"Public Place"
        }
    ],
    "sg:phone":"+61 3 5259 2572",
    "sg:postcode":"3223",
    "sg:province":"VIC",
    "sg:tags":[
        "pre-schools"
    ],
    "wof:name":"Portarlington Primary School",
    "wof:placetype":"venue"
},
  "geometry": {"coordinates":[144.65531899999999,-38.115242],"type":"Point"}
}