{
  "type": "Feature",
  "properties": {
    "addr:full":"550 Mitcham Rd Mitcham VIC 3132",
    "addr:housenumber":"550",
    "addr:postcode":"3132",
    "addr:street":"Mitcham Rd",
    "iso:country":"AU",
    "sg:address":"550 Mitcham Rd",
    "sg:city":"Mitcham",
    "sg:classifiers":[
        {
            "category":"Health Services",
            "subcategory":"Doctor",
            "type":"Services"
        }
    ],
    "sg:phone":"+61 3 9873 5627",
    "sg:postcode":"3132",
    "sg:province":"VIC",
    "sg:tags":[
        "podiatrist"
    ],
    "wof:name":"Holloway Podiatry Prudence F Holloway",
    "wof:placetype":"venue"
},
  "geometry": {"coordinates":[145.19436645499999,-37.8269958496],"type":"Point"}
}