{
  "type": "Feature",
  "properties": {
    "iso:country":"AU",
    "sg:address":"17 Crispian St",
    "sg:city":"Fulham",
    "sg:classifiers":[
        {
            "category":"Professional",
            "subcategory":"Business Services",
            "type":"Services"
        }
    ],
    "sg:phone":"+61 403 028 354",
    "sg:postcode":"5024",
    "sg:province":"SA",
    "sg:tags":[
        "drafting"
    ],
    "wof:name":"Perry Design Pty Ltd",
    "wof:placetype":"venue"
},
  "geometry": {"coordinates":[138.509841919,-34.9229774475],"type":"Point"}
}