{
  "type": "Feature",
  "properties": {
    "addr:full":"5 Market St Cohuna VIC 3568",
    "addr:housenumber":"5",
    "addr:postcode":"3568",
    "addr:street":"Market St",
    "iso:country":"AU",
    "sg:address":"5 Market St",
    "sg:city":"Cohuna",
    "sg:classifiers":[
        {
            "category":"Professional",
            "subcategory":"Accounting & Tax Preparation",
            "type":"Services"
        }
    ],
    "sg:phone":"+61 3 5456 2704",
    "sg:postcode":"3568",
    "sg:province":"VIC",
    "sg:tags":[
        "consultant",
        "taxation"
    ],
    "wof:name":"May Partners Pty Ltd",
    "wof:placetype":"venue"
},
  "geometry": {"coordinates":[144.222564697,-35.8099937439],"type":"Point"}
}