{
  "type": "Feature",
  "properties": {
    "addr:full":"Shops 5-7, Centro Oakleigh Shopping Centre Oakleigh VIC 3166",
    "addr:housenumber":"5-7 centro",
    "addr:postcode":"3166",
    "iso:country":"AU",
    "sg:address":"Shops 5-7, Centro Oakleigh Shopping Centre",
    "sg:city":"Oakleigh",
    "sg:classifiers":[
        {
            "category":"Personal",
            "subcategory":"Piercing",
            "type":"Services"
        }
    ],
    "sg:phone":"+61 3 9563 2044",
    "sg:postcode":"3166",
    "sg:province":"VIC",
    "sg:tags":[
        "body",
        "ear"
    ],
    "wof:name":"Oakleigh Central Amcal Chemist",
    "wof:placetype":"venue"
},
  "geometry": {"coordinates":[145.107421875,-37.8991851807],"type":"Point"}
}