{
  "type": "Feature",
  "properties": {
    "addr:full":"In Russell St Corrimal NSW 2518",
    "addr:postcode":"2518",
    "addr:street":"Russell St",
    "iso:country":"AU",
    "sg:address":"In Russell St",
    "sg:city":"Corrimal",
    "sg:classifiers":[
        {
            "category":"Personal",
            "subcategory":"Shoe Repair & Shine",
            "type":"Services"
        }
    ],
    "sg:phone":"+61 2 4284 3748",
    "sg:postcode":"2518",
    "sg:province":"NSW",
    "sg:tags":[
        "footwear"
    ],
    "wof:name":"Colin Lewis Corrimal Shoe Repairs",
    "wof:placetype":"venue"
},
  "geometry": {"coordinates":[150.89686599999999,-34.371128],"type":"Point"}
}