{
  "type": "Feature",
  "properties": {
    "addr:full":"Unit 2/ 338 Boronia Rd Boronia VIC 3155",
    "addr:housenumber":"/ 338",
    "addr:postcode":"3155",
    "addr:street":"Boronia Rd",
    "iso:country":"AU",
    "sg:address":"Unit 2/ 338 Boronia Rd",
    "sg:city":"Boronia",
    "sg:classifiers":[
        {
            "category":"Home & Garden",
            "subcategory":"Building Materials",
            "type":"Retail Goods"
        }
    ],
    "sg:phone":"+61 3 9800 0348",
    "sg:postcode":"3155",
    "sg:province":"VIC",
    "sg:tags":[
        "lawn",
        "cutting",
        "maintenance"
    ],
    "wof:name":"Middle Earth Mowing",
    "wof:placetype":"venue"
},
  "geometry": {"coordinates":[145.26077270499999,-37.8587303162],"type":"Point"}
}