{
  "type": "Feature",
  "properties": {
    "addr:full":"152 Olsen Ave Arundel QLD 4214",
    "addr:housenumber":"152",
    "addr:postcode":"4214",
    "addr:street":"Olsen Ave",
    "iso:country":"AU",
    "sg:address":"152 Olsen Ave",
    "sg:city":"Arundel",
    "sg:classifiers":[
        {
            "category":"Personal",
            "subcategory":"Beauty Salon",
            "type":"Services"
        }
    ],
    "sg:phone":"+61 7 5594 0986",
    "sg:postcode":"4214",
    "sg:province":"QLD",
    "wof:name":"Afterglow Skin Care Salon",
    "wof:placetype":"venue"
},
  "geometry": {"coordinates":[153.38052368199999,-27.9571723938],"type":"Point"}
}