{
  "type": "Feature",
  "properties": {
    "addr:full":"154 Union St The Junction NSW 2291",
    "addr:housenumber":"154",
    "addr:postcode":"2291",
    "addr:street":"Union St",
    "iso:country":"AU",
    "sg:address":"154 Union St",
    "sg:city":"The Junction",
    "sg:classifiers":[
        {
            "category":"Personal",
            "subcategory":"Beauty Salon",
            "type":"Services"
        }
    ],
    "sg:phone":"+61 2 4940 0335",
    "sg:postcode":"2291",
    "sg:province":"NSW",
    "sg:tags":[
        "hairdresser"
    ],
    "wof:name":"Adam's At The Junction",
    "wof:placetype":"venue"
},
  "geometry": {"coordinates":[151.76008605999999,-32.9368362427],"type":"Point"}
}