{
  "type": "Feature",
  "properties": {
    "addr:full":"2 Park Rd Surrey Hills VIC 3127",
    "addr:housenumber":"2",
    "addr:postcode":"3127",
    "addr:street":"Park Rd",
    "iso:country":"AU",
    "sg:address":"2 Park Rd",
    "sg:city":"Surrey Hills",
    "sg:classifiers":[
        {
            "category":"Wholesale",
            "subcategory":"Hardware",
            "type":"Manufacturing & Wholesale Goods"
        }
    ],
    "sg:phone":"+61 3 9808 5357",
    "sg:postcode":"3127",
    "sg:province":"VIC",
    "wof:name":"Great Wall Tools",
    "wof:placetype":"venue"
},
  "geometry": {"coordinates":[145.111251831,-37.8372421265],"type":"Point"}
}