{
  "type": "Feature",
  "properties": {
    "addr:full":"Suite 7, 22-26 Princes Way Drouin VIC 3818",
    "addr:housenumber":"22-26",
    "addr:postcode":"3818",
    "addr:street":"Princes Way",
    "iso:country":"AU",
    "sg:address":"Suite 7, 22-26 Princes Way",
    "sg:city":"Drouin",
    "sg:classifiers":[
        {
            "category":"Professional",
            "subcategory":"Accounting & Tax Preparation",
            "type":"Services"
        }
    ],
    "sg:phone":"+61 411 154 256",
    "sg:postcode":"3818",
    "sg:province":"VIC",
    "sg:tags":[
        "accountant",
        "auditor"
    ],
    "wof:name":"Boyd & Boyd Pty Ltd",
    "wof:placetype":"venue"
},
  "geometry": {"coordinates":[145.865128,-38.139545],"type":"Point"}
}