{
  "type": "Feature",
  "properties": {
    "addr:full":"Airport Industrial Estate 1/7 Beech St Marcoola QLD 4564",
    "addr:housenumber":"1 / 7",
    "addr:postcode":"4564",
    "addr:street":"Estate;Beech St",
    "iso:country":"AU",
    "sg:address":"Airport Industrial Estate 1/7 Beech St",
    "sg:city":"Marcoola",
    "sg:classifiers":[
        {
            "category":"Wholesale",
            "subcategory":"Apparel",
            "type":"Manufacturing & Wholesale Goods"
        }
    ],
    "sg:phone":"+61 7 5448 7124",
    "sg:postcode":"4564",
    "sg:province":"QLD",
    "sg:tags":[
        "wholesaler",
        "mfrs",
        "uniform"
    ],
    "wof:name":"Seaborne Clothing",
    "wof:placetype":"venue"
},
  "geometry": {"coordinates":[153.08395385700001,-26.6082706451],"type":"Point"}
}