{
  "type": "Feature",
  "properties": {
    "addr:full":"Level 1/ 6 William St Turramurra NSW 2074",
    "addr:housenumber":"/ 6",
    "addr:postcode":"2074",
    "addr:street":"William St",
    "iso:country":"AU",
    "sg:address":"Level 1/ 6 William St",
    "sg:city":"Turramurra",
    "sg:classifiers":[
        {
            "category":"Professional",
            "subcategory":"Secretarial Services",
            "type":"Services"
        }
    ],
    "sg:phone":"+61 2 9449 9400",
    "sg:postcode":"2074",
    "sg:province":"NSW",
    "sg:tags":[
        "typing"
    ],
    "wof:name":"North Shore Secreterial Service",
    "wof:placetype":"venue"
},
  "geometry": {"coordinates":[151.128143311,-33.7329025269],"type":"Point"}
}