{
  "type": "Feature",
  "properties": {
    "addr:full":"Cnr Victoria & Macalister Sts Mackay QLD 4740",
    "addr:postcode":"4740",
    "addr:street":"Cnr",
    "iso:country":"AU",
    "sg:address":"Cnr Victoria & Macalister Sts",
    "sg:city":"Mackay",
    "sg:classifiers":[
        {
            "category":"Health Services",
            "subcategory":"Dentist",
            "type":"Services"
        }
    ],
    "sg:phone":"+61 7 4953 4545",
    "sg:postcode":"4740",
    "sg:province":"QLD",
    "sg:tags":[
        "dental",
        "prosthetist"
    ],
    "wof:name":"City & Country Denture Clinic",
    "wof:placetype":"venue"
},
  "geometry": {"coordinates":[149.17674299999999,-21.140074],"type":"Point"}
}