{
  "type": "Feature",
  "properties": {
    "iso:country":"AU",
    "sg:address":"509 Port Rd",
    "sg:city":"West Croydon",
    "sg:classifiers":[
        {
            "category":"Building & Trades",
            "subcategory":"Construction",
            "type":"Services"
        }
    ],
    "sg:phone":"+61 8 8346 6724",
    "sg:postcode":"5008",
    "sg:province":"SA",
    "sg:tags":[
        "fencing",
        "contractor"
    ],
    "wof:name":"Budget Fencing",
    "wof:placetype":"venue"
},
  "geometry": {"coordinates":[138.559158,-34.896225],"type":"Point"}
}