{
  "type": "Feature",
  "properties": {
    "addr:full":"PO Box 489 Browns Plains BC QLD 4118",
    "addr:postcode":"qld 4118",
    "iso:country":"AU",
    "sg:address":"PO Box 489",
    "sg:city":"Browns Plains BC",
    "sg:classifiers":[
        {
            "category":"Retail",
            "subcategory":"Driving School",
            "type":"Services"
        }
    ],
    "sg:phone":"+61 7 3803 3353",
    "sg:postcode":"4118",
    "sg:province":"QLD",
    "sg:tags":[
        "equipment",
        "pile",
        "contractor"
    ],
    "wof:name":"Screw-Pile International",
    "wof:placetype":"venue"
},
  "geometry": {"coordinates":[153.043136597,-27.6639003754],"type":"Point"}
}