{
  "type": "Feature",
  "properties": {
    "addr:full":"Shop 17 A, Big B Arcade Burleigh Heads QLD 4220",
    "addr:housenumber":"shop 17 a",
    "addr:postcode":"4220",
    "addr:street":"Big",
    "iso:country":"AU",
    "sg:address":"Shop 17",
    "sg:city":"A, Big B Arcade Burleigh Heads",
    "sg:classifiers":[
        {
            "category":"Health Services",
            "subcategory":"Health Practitioner",
            "type":"Services"
        }
    ],
    "sg:phone":"+61 422 640 632",
    "sg:postcode":"4220",
    "sg:province":"QLD",
    "sg:tags":[
        "reiki"
    ],
    "wof:name":"Good Karma Spirit",
    "wof:placetype":"venue"
},
  "geometry": {"coordinates":[153.449752808,-28.0879096985],"type":"Point"}
}