{
  "type": "Feature",
  "properties": {
    "iso:country":"AU",
    "sg:address":"11 Shetland Pl",
    "sg:city":"Eaton",
    "sg:classifiers":[
        {
            "category":"Banks & Credit Unions",
            "subcategory":"Bank",
            "type":"Services"
        }
    ],
    "sg:phone":"+61 8 9725 1934",
    "sg:postcode":"6232",
    "sg:province":"WA",
    "sg:tags":[
        "concrete",
        "reinforcement"
    ],
    "wof:name":"Golds Steel Fixing Services",
    "wof:placetype":"venue"
},
  "geometry": {"coordinates":[115.723251,-33.31097],"type":"Point"}
}