{
  "type": "Feature",
  "properties": {
    "addr:full":"691 High St Thornbury VIC 3071",
    "addr:housenumber":"691",
    "addr:postcode":"3071",
    "addr:street":"High St",
    "iso:country":"AU",
    "sg:address":"691 High St",
    "sg:city":"Thornbury",
    "sg:classifiers":[
        {
            "category":"Professional",
            "subcategory":"Accounting & Tax Preparation",
            "type":"Services"
        }
    ],
    "sg:phone":"+61 3 9416 9322",
    "sg:postcode":"3071",
    "sg:province":"VIC",
    "sg:tags":[
        "accountant",
        "auditor"
    ],
    "wof:name":"De Luca Partners",
    "wof:placetype":"venue"
},
  "geometry": {"coordinates":[145.00021362300001,-37.7599601746],"type":"Point"}
}