{
  "type": "Feature",
  "properties": {
    "addr:full":"830 Wellington Rd Rowville VIC 3178",
    "addr:housenumber":"830",
    "addr:postcode":"3178",
    "addr:street":"Wellington Rd",
    "iso:country":"AU",
    "sg:address":"830 Wellington Rd",
    "sg:city":"Rowville",
    "sg:classifiers":[
        {
            "category":"Organizations",
            "subcategory":"Community Association",
            "type":"Services"
        }
    ],
    "sg:phone":"+61 3 9764 6677",
    "sg:postcode":"3178",
    "sg:province":"VIC",
    "sg:tags":[
        "cheese",
        "product"
    ],
    "wof:name":"Bonland Dairies",
    "wof:placetype":"venue"
},
  "geometry": {"coordinates":[145.21881103499999,-37.926410675],"type":"Point"}
}