{
  "type": "Feature",
  "properties": {
    "iso:country":"AU",
    "sg:address":"Unit 5, 19- 25 Kembla St",
    "sg:city":"Fyshwick",
    "sg:classifiers":[
        {
            "category":"Utilities",
            "subcategory":"Electric",
            "type":"Services"
        }
    ],
    "sg:phone":"+61 2 6126 2999",
    "sg:postcode":"2609",
    "sg:province":"ACT",
    "sg:tags":[
        "electrical",
        "contractor"
    ],
    "wof:name":"Stowe Australia",
    "wof:placetype":"venue"
},
  "geometry": {"coordinates":[149.17706298799999,-35.3247833252],"type":"Point"}
}