{
  "type": "Feature",
  "properties": {
    "iso:country":"AU",
    "sg:address":"3/ 7 Timms Crt",
    "sg:city":"Underwood",
    "sg:classifiers":[
        {
            "category":"Retail",
            "subcategory":"Laundry & Dry Cleaning",
            "type":"Services"
        }
    ],
    "sg:phone":"+61 7 3209 1495",
    "sg:postcode":"4119",
    "sg:province":"QLD",
    "sg:tags":[
        "equipment",
        "supply"
    ],
    "wof:name":"Advance Commercial Laundry Equipment Pty Ltd",
    "wof:placetype":"venue"
},
  "geometry": {"coordinates":[153.106765747,-27.619972229],"type":"Point"}
}