{
  "type": "Feature",
  "properties": {
    "addr:full":"Bay St Greenwich NSW 2065",
    "addr:postcode":"2065",
    "addr:street":"Bay St",
    "iso:country":"AU",
    "sg:address":"Bay St",
    "sg:city":"Greenwich",
    "sg:classifiers":[
        {
            "category":"Recreation",
            "subcategory":"Sailing Club",
            "type":"Entertainment"
        }
    ],
    "sg:phone":"+61 2 9436 1901",
    "sg:postcode":"2065",
    "sg:province":"NSW",
    "sg:tags":[
        "yacht"
    ],
    "wof:name":"Greenwich Flying Squadron",
    "wof:placetype":"venue"
},
  "geometry": {"coordinates":[151.18371582,-33.83385849],"type":"Point"}
}