{
  "type": "Feature",
  "properties": {
    "addr:full":"20 Cook Drv Coffs Harbour NSW 2450",
    "addr:housenumber":"20",
    "addr:postcode":"2450",
    "addr:street":"Cook Drv",
    "iso:country":"AU",
    "sg:address":"20 Cook Drv",
    "sg:city":"Coffs Harbour",
    "sg:classifiers":[
        {
            "category":"Retail",
            "subcategory":"Storage",
            "type":"Services"
        }
    ],
    "sg:phone":"+61 2 6652 1958",
    "sg:postcode":"2450",
    "sg:province":"NSW",
    "sg:tags":[
        "removal",
        "furniture"
    ],
    "wof:name":"Coffs Harbour Removals & Storage P/L",
    "wof:placetype":"venue"
},
  "geometry": {"coordinates":[153.09913599999999,-30.315298],"type":"Point"}
}