{
  "type": "Feature",
  "properties": {
    "addr:full":"184 Scarborough Beach Rd Doubleview WA 6018",
    "addr:housenumber":"184",
    "addr:postcode":"6018",
    "addr:street":"Scarborough Beach Rd",
    "iso:country":"AU",
    "sg:address":"184 Scarborough Beach Rd",
    "sg:city":"Doubleview",
    "sg:classifiers":[
        {
            "category":"Health Services",
            "subcategory":"Dentist",
            "type":"Services"
        }
    ],
    "sg:phone":"+61 8 9446 1344",
    "sg:postcode":"6018",
    "sg:province":"WA",
    "wof:name":"Dr John Moran And Associates - Doubleview Dental Clinic",
    "wof:placetype":"venue"
},
  "geometry": {"coordinates":[115.77709197999999,-31.8938293457],"type":"Point"}
}