{
  "type": "Feature",
  "properties": {
    "addr:full":"97b Henry St Penrith NSW 2750",
    "addr:housenumber":"97b",
    "addr:postcode":"2750",
    "addr:street":"Henry St",
    "iso:country":"AU",
    "sg:address":"97b Henry St",
    "sg:city":"Penrith",
    "sg:classifiers":[
        {
            "category":"Shopping",
            "subcategory":"Mobile Phones",
            "type":"Retail Goods"
        }
    ],
    "sg:phone":"+61 2 4732 4455",
    "sg:postcode":"2750",
    "sg:province":"NSW",
    "sg:tags":[
        "telephone",
        "accessory"
    ],
    "wof:name":"Hi- Tech Communications",
    "wof:placetype":"venue"
},
  "geometry": {"coordinates":[150.982055664,-33.8592300415],"type":"Point"}
}