{
  "type": "Feature",
  "properties": {
    "addr:full":"Shop 16/ 41- 51 Bailey Rd Deception Bay QLD 4508",
    "addr:housenumber":"shop 16 / 41 51",
    "addr:postcode":"4508",
    "addr:street":"Bailey Rd",
    "iso:country":"AU",
    "sg:address":"Shop 16/ 41- 51 Bailey Rd",
    "sg:city":"Deception Bay",
    "sg:classifiers":[
        {
            "category":"Real Estate",
            "subcategory":"Real Estate Agent",
            "type":"Services"
        }
    ],
    "sg:phone":"+61 7 3204 0744",
    "sg:postcode":"4508",
    "sg:province":"QLD",
    "wof:name":"Hooker L.J Deception Bay",
    "wof:placetype":"venue"
},
  "geometry": {"coordinates":[153.024734497,-27.1889381409],"type":"Point"}
}