{
  "type": "Feature",
  "properties": {
    "addr:full":"276 Unley Rd Hyde Park SA 5061",
    "addr:housenumber":"276",
    "addr:postcode":"5061",
    "addr:street":"Unley Rd",
    "iso:country":"AU",
    "sg:address":"276 Unley Rd",
    "sg:city":"Hyde Park",
    "sg:classifiers":[
        {
            "category":"Professional",
            "subcategory":"Art Services",
            "type":"Services"
        }
    ],
    "sg:phone":"+61 8 8357 9350",
    "sg:postcode":"5061",
    "sg:province":"SA",
    "sg:tags":[
        "graphic",
        "designer"
    ],
    "wof:name":"Salmon Studio",
    "wof:placetype":"venue"
},
  "geometry": {"coordinates":[138.60772705100001,-34.955280304],"type":"Point"}
}