{
  "type": "Feature",
  "properties": {
    "addr:full":"11 Christensen Rd Yatala QLD 4207",
    "addr:housenumber":"11",
    "addr:postcode":"4207",
    "addr:street":"Christensen Rd",
    "iso:country":"AU",
    "sg:address":"11 Christensen Rd",
    "sg:city":"Yatala",
    "sg:classifiers":[
        {
            "category":"Autos & Motor Vehicles",
            "subcategory":"Motorcycle Sales",
            "type":"Retail Goods"
        }
    ],
    "sg:phone":"+61 7 3807 8299",
    "sg:postcode":"4207",
    "sg:province":"QLD",
    "sg:tags":[
        "outboard"
    ],
    "wof:name":"Yatala Yamaha",
    "wof:placetype":"venue"
},
  "geometry": {"coordinates":[153.230834961,-27.7358932495],"type":"Point"}
}