{
  "type": "Feature",
  "properties": {
    "iso:country":"AU",
    "sg:address":"3 Heathorn Ave",
    "sg:city":"Sandy Bay",
    "sg:classifiers":[
        {
            "category":"Professional",
            "subcategory":"Computer Services",
            "type":"Services"
        }
    ],
    "sg:phone":"+61 3 6225 0332",
    "sg:postcode":"7005",
    "sg:province":"TAS",
    "sg:tags":[
        "training"
    ],
    "wof:name":"Baby Boomer Internet Advice And Graphic Design",
    "wof:placetype":"venue"
},
  "geometry": {"coordinates":[147.35317993199999,-42.9107398987],"type":"Point"}
}