{
  "type": "Feature",
  "properties": {
    "addr:full":"2687 Warburton Hwy Wesburn VIC 3799",
    "addr:housenumber":"2687",
    "addr:postcode":"3799",
    "addr:street":"Warburton Hwy",
    "iso:country":"AU",
    "sg:address":"2687 Warburton Hwy",
    "sg:city":"Wesburn",
    "sg:classifiers":[
        {
            "category":"Home & Garden",
            "subcategory":"Garden Supply",
            "type":"Retail Goods"
        }
    ],
    "sg:phone":"+61 3 5967 1367",
    "sg:postcode":"3799",
    "sg:province":"VIC",
    "sg:tags":[
        "equipment"
    ],
    "wof:name":"Yarra Junction Garden Supplies",
    "wof:placetype":"venue"
},
  "geometry": {"coordinates":[145.64569091800001,-37.7635116577],"type":"Point"}
}