{
  "type": "Feature",
  "properties": {
    "iso:country":"AU",
    "sg:address":"10 Younger Ave",
    "sg:city":"Earlwood",
    "sg:classifiers":[
        {
            "category":"Retail",
            "subcategory":"Car Wash",
            "type":"Services"
        }
    ],
    "sg:phone":"+61 403 112 769",
    "sg:postcode":"2206",
    "sg:province":"NSW",
    "sg:tags":[
        "truck",
        "cleaning"
    ],
    "wof:name":"Jetboy Mobile Car Detailing Specialist",
    "wof:placetype":"venue"
},
  "geometry": {"coordinates":[151.128494,-33.916622],"type":"Point"}
}