{
  "type": "Feature",
  "properties": {
    "iso:country":"AU",
    "sg:address":"Reilly St",
    "sg:city":"Inverloch",
    "sg:classifiers":[
        {
            "category":"Sports & Exercise",
            "subcategory":"Gym",
            "type":"Entertainment"
        }
    ],
    "sg:phone":"+61 3 5674 3314",
    "sg:postcode":"3996",
    "sg:province":"VIC",
    "sg:tags":[
        "health",
        "fitness"
    ],
    "wof:name":"Fitness & Well Being Centre",
    "wof:placetype":"venue"
},
  "geometry": {"coordinates":[145.728363,-38.632195],"type":"Point"}
}