{
  "type": "Feature",
  "properties": {
    "addr:full":"PO Box 3584 West End (Brisbane) QLD 4101",
    "addr:postcode":"4101",
    "iso:country":"AU",
    "sg:address":"PO Box 3584",
    "sg:city":"West End (Brisbane)",
    "sg:classifiers":[
        {
            "category":"Shopping",
            "subcategory":"Gifts & Souvenirs",
            "type":"Retail Goods"
        }
    ],
    "sg:phone":"+61 7 3392 4011",
    "sg:postcode":"4101",
    "sg:province":"QLD",
    "sg:tags":[
        "shop",
        "supply"
    ],
    "wof:name":"Swann Agencies",
    "wof:placetype":"venue"
},
  "geometry": {"coordinates":[153.012161255,-27.4802494049],"type":"Point"}
}