{
  "type": "Feature",
  "properties": {
    "iso:country":"AU",
    "sg:address":"90 Lower Plenty Rd",
    "sg:city":"Rosanna",
    "sg:classifiers":[
        {
            "category":"Food & Beverages",
            "subcategory":"Supermarket",
            "type":"Retail Goods"
        }
    ],
    "sg:phone":"+61 3 9459 7718",
    "sg:postcode":"3084",
    "sg:province":"VIC",
    "sg:tags":[
        "grocery",
        "store"
    ],
    "wof:name":"IGA Everyday",
    "wof:placetype":"venue"
},
  "geometry": {"coordinates":[145.064544678,-37.7435379028],"type":"Point"}
}