{
  "type": "Feature",
  "properties": {
    "iso:country":"AU",
    "sg:address":"277 Mulgrave Rd",
    "sg:city":"Cairns",
    "sg:classifiers":[
        {
            "category":"Food & Beverages",
            "subcategory":"Supermarket",
            "type":"Retail Goods"
        }
    ],
    "sg:phone":"+61 7 4031 5220",
    "sg:postcode":"4870",
    "sg:province":"QLD",
    "sg:tags":[
        "grocery",
        "store"
    ],
    "wof:name":"Westcourt One-Stop",
    "wof:placetype":"venue"
},
  "geometry": {"coordinates":[145.74334716800001,-16.9400348663],"type":"Point"}
}