{
  "type": "Feature",
  "properties": {
    "iso:country":"AU",
    "sg:address":"4 Honeysuckle Crt",
    "sg:city":"Meadow Heights",
    "sg:classifiers":[
        {
            "category":"Professional",
            "type":"Services"
        }
    ],
    "sg:phone":"+61 3 9305 2968",
    "sg:postcode":"3048",
    "sg:province":"VIC",
    "sg:tags":[
        "transport"
    ],
    "wof:name":"KIR Transport Pty Ltd",
    "wof:placetype":"venue"
},
  "geometry": {"coordinates":[144.92572,-37.650669],"type":"Point"}
}