{
  "type": "Feature",
  "properties": {
    "addr:full":"7 Porter St Ryde NSW 2112",
    "addr:housenumber":"7",
    "addr:postcode":"2112",
    "addr:street":"Porter St",
    "iso:country":"AU",
    "sg:address":"7 Porter St",
    "sg:city":"Ryde",
    "sg:classifiers":[
        {
            "category":"Building & Trades",
            "subcategory":"Construction",
            "type":"Services"
        }
    ],
    "sg:phone":"+61 2 9809 3622",
    "sg:postcode":"2112",
    "sg:province":"NSW",
    "sg:tags":[
        "contractor"
    ],
    "wof:name":"New Age Construction (NSW) Pty Ltd",
    "wof:placetype":"venue"
},
  "geometry": {"coordinates":[151.09886169399999,-33.8190841675],"type":"Point"}
}