{
  "type": "Feature",
  "properties": {
    "iso:country":"AU",
    "sg:address":"1/ 225 High St",
    "sg:city":"Thomastown",
    "sg:classifiers":[
        {
            "category":"Personal",
            "subcategory":"Beauty Salon",
            "type":"Services"
        }
    ],
    "sg:phone":"+61 404 198 946",
    "sg:postcode":"3074",
    "sg:province":"VIC",
    "wof:name":"Sheer Silk Beauty Therapy",
    "wof:placetype":"venue"
},
  "geometry": {"coordinates":[145.013793945,-37.6795959473],"type":"Point"}
}