{
  "type": "Feature",
  "properties": {
    "iso:country":"AU",
    "sg:address":"Shop 15 Mt Druitt Shopping Town Westfield",
    "sg:city":"Mt Druitt",
    "sg:classifiers":[
        {
            "category":"Shopping",
            "subcategory":"Jewelry",
            "type":"Retail Goods"
        }
    ],
    "sg:phone":"+61 2 9832 4305",
    "sg:postcode":"2770",
    "sg:province":"NSW",
    "sg:tags":[
        "jeweller"
    ],
    "wof:name":"Diamond Hill Jewellers",
    "wof:placetype":"venue"
},
  "geometry": {"coordinates":[150.81263732900001,-33.7691421509],"type":"Point"}
}