{
  "type": "Feature",
  "properties": {
    "iso:country":"AU",
    "sg:address":"48 Lindsays Rd",
    "sg:city":"Boambee",
    "sg:classifiers":[
        {
            "category":"Utilities",
            "subcategory":"Refuse",
            "type":"Services"
        }
    ],
    "sg:phone":"+61 2 6658 8113",
    "sg:postcode":"2450",
    "sg:province":"NSW",
    "sg:tags":[
        "remover",
        "rubbish"
    ],
    "wof:name":"Rent-A-Sak",
    "wof:placetype":"venue"
},
  "geometry": {"coordinates":[153.078827,-30.335234],"type":"Point"}
}