{
  "type": "Feature",
  "properties": {
    "addr:full":"95 Rawlinson Drv Marangaroo WA 6064",
    "addr:housenumber":"95",
    "addr:postcode":"6064",
    "addr:street":"Rawlinson Drv Marangaroo",
    "iso:country":"AU",
    "sg:address":"95 Rawlinson Drv",
    "sg:city":"Marangaroo",
    "sg:classifiers":[
        {
            "category":"Travel",
            "subcategory":"Hostel",
            "type":"Entertainment"
        }
    ],
    "sg:phone":"+61 8 9343 5044",
    "sg:postcode":"6064",
    "sg:province":"WA",
    "sg:tags":[
        "home"
    ],
    "wof:name":"John Bryant Hostel",
    "wof:placetype":"venue"
},
  "geometry": {"coordinates":[115.84982299799999,-31.8286628723],"type":"Point"}
}