{
  "type": "Feature",
  "properties": {
    "addr:full":"73 Victoria Pde Fitzroy VIC 3065",
    "addr:housenumber":"73",
    "addr:postcode":"3065",
    "addr:street":"Victoria Pde",
    "iso:country":"AU",
    "sg:address":"73 Victoria Pde",
    "sg:city":"Fitzroy",
    "sg:classifiers":[
        {
            "category":"Health Services",
            "subcategory":"Optometrist",
            "type":"Services"
        }
    ],
    "sg:phone":"+61 3 9419 2333",
    "sg:postcode":"3065",
    "sg:province":"VIC",
    "wof:name":"Plus Optics",
    "wof:placetype":"venue"
},
  "geometry": {"coordinates":[144.97657775900001,-37.8079833984],"type":"Point"}
}