{
  "type": "Feature",
  "properties": {
    "addr:full":"PO Box 1083 North Adelaide SA 5006",
    "addr:postcode":"5006",
    "iso:country":"AU",
    "sg:address":"PO Box 1083",
    "sg:city":"North Adelaide",
    "sg:classifiers":[
        {
            "category":"Professional",
            "subcategory":"Accounting & Tax Preparation",
            "type":"Services"
        }
    ],
    "sg:phone":"+61 8 8354 4188",
    "sg:postcode":"5006",
    "sg:province":"SA",
    "sg:tags":[
        "bookkeeping"
    ],
    "wof:name":"Business 2 Basix",
    "wof:placetype":"venue"
},
  "geometry": {"coordinates":[138.59492492699999,-34.9090194702],"type":"Point"}
}