{
  "type": "Feature",
  "properties": {
    "addr:full":"Shop 42, Totem Shopping Centr Balgowlah NSW 2093",
    "addr:housenumber":"shop 42",
    "addr:postcode":"2093",
    "addr:street":"Totem",
    "iso:country":"AU",
    "sg:address":"Shop 42, Totem Shopping Centr",
    "sg:city":"Balgowlah",
    "sg:classifiers":[
        {
            "category":"Professional",
            "subcategory":"Detective & Security Services",
            "type":"Services"
        }
    ],
    "sg:phone":"+61 2 9949 7500",
    "sg:postcode":"2093",
    "sg:province":"NSW",
    "sg:tags":[
        "domestic",
        "alarm",
        "commercial",
        "burglar"
    ],
    "wof:name":"Capital Locksmiths",
    "wof:placetype":"venue"
},
  "geometry": {"coordinates":[151.26158142099999,-33.7939300537],"type":"Point"}
}