{
  "type": "Feature",
  "properties": {
    "addr:full":"Berth 8, Southbank Prm Melbourne VIC 3000",
    "addr:housenumber":"8",
    "addr:postcode":"3000",
    "addr:street":"Southbank Prm",
    "iso:country":"AU",
    "sg:address":"Berth 8, Southbank Prm",
    "sg:city":"Melbourne",
    "sg:classifiers":[
        {
            "category":"Recreation",
            "subcategory":"Boat Charter",
            "type":"Entertainment"
        }
    ],
    "sg:phone":"+61 3 8610 2600",
    "sg:postcode":"3000",
    "sg:province":"VIC",
    "wof:name":"melbourne river cruises",
    "wof:placetype":"venue"
},
  "geometry": {"coordinates":[144.97137451200001,-37.8162956238],"type":"Point"}
}