{
  "type": "Feature",
  "properties": {
    "addr:full":"388 Howick St Bathurst NSW 2795",
    "addr:housenumber":"388",
    "addr:postcode":"2795",
    "addr:street":"Howick St",
    "iso:country":"AU",
    "sg:address":"388 Howick St",
    "sg:city":"Bathurst",
    "sg:classifiers":[
        {
            "category":"Building & Trades",
            "subcategory":"Landscaping Services",
            "type":"Services"
        }
    ],
    "sg:phone":"+61 2 6331 5047",
    "sg:postcode":"2795",
    "sg:province":"NSW",
    "sg:tags":[
        "designer",
        "landscape",
        "contractor"
    ],
    "wof:name":"Michael Corby Design",
    "wof:placetype":"venue"
},
  "geometry": {"coordinates":[149.580734253,-33.4166717529],"type":"Point"}
}