{
  "type": "Feature",
  "properties": {
    "iso:country":"AU",
    "sg:address":"70 Rostrevor Rd",
    "sg:city":"Boondall",
    "sg:classifiers":[
        {
            "category":"Shopping",
            "subcategory":"Crafts & Fabrics",
            "type":"Retail Goods"
        }
    ],
    "sg:phone":"+61 7 3265 2082",
    "sg:postcode":"4034",
    "sg:province":"QLD",
    "sg:tags":[
        "supply"
    ],
    "wof:name":"Make-It Hobby N Craft",
    "wof:placetype":"venue"
},
  "geometry": {"coordinates":[153.062927,-27.342649],"type":"Point"}
}