{
  "type": "Feature",
  "properties": {
    "addr:full":"Plowman Pl Frankston VIC 3199",
    "addr:postcode":"3199",
    "addr:street":"Plowman Pl",
    "iso:country":"AU",
    "sg:address":"Plowman Pl",
    "sg:city":"Frankston",
    "sg:classifiers":[
        {
            "category":"Arena",
            "subcategory":"Sports Club",
            "type":"Entertainment"
        }
    ],
    "sg:phone":"+61 3 9783 7888",
    "sg:postcode":"3199",
    "sg:province":"VIC",
    "sg:tags":[
        "australian",
        "football",
        "rule"
    ],
    "wof:name":"Frankston Football Club Inc",
    "wof:placetype":"venue"
},
  "geometry": {"coordinates":[145.12059020999999,-38.1468162537],"type":"Point"}
}