{
  "type": "Feature",
  "properties": {
    "addr:full":"Factory 1-A Grace St Cranbourne VIC 3977",
    "addr:housenumber":"1-a",
    "addr:postcode":"3977",
    "addr:street":"Factory;Grace St",
    "iso:country":"AU",
    "sg:address":"Factory 1-A Grace St",
    "sg:city":"Cranbourne",
    "sg:classifiers":[
        {
            "category":"Building & Trades",
            "subcategory":"Construction",
            "type":"Services"
        }
    ],
    "sg:phone":"+61 3 5996 1577",
    "sg:postcode":"3977",
    "sg:province":"VIC",
    "sg:tags":[
        "window",
        "timber"
    ],
    "wof:name":"Dara Windows & Doors",
    "wof:placetype":"venue"
},
  "geometry": {"coordinates":[145.28236389200001,-38.1042671204],"type":"Point"}
}