{
  "type": "Feature",
  "properties": {
    "addr:full":"22 Brook St Sunbury VIC 3429",
    "addr:housenumber":"22",
    "addr:postcode":"3429",
    "addr:street":"Brook St",
    "iso:country":"AU",
    "sg:address":"22 Brook St",
    "sg:city":"Sunbury",
    "sg:classifiers":[
        {
            "category":"Food & Beverages",
            "subcategory":"Liquor & Beverages",
            "type":"Retail Goods"
        }
    ],
    "sg:phone":"+61 3 9744 1450",
    "sg:postcode":"3429",
    "sg:province":"VIC",
    "sg:tags":[
        "store"
    ],
    "wof:name":"Cheeers Liquor Group",
    "wof:placetype":"venue"
},
  "geometry": {"coordinates":[144.73033142099999,-37.5802955627],"type":"Point"}
}