{
  "type": "Feature",
  "properties": {
    "addr:full":"Shop 7, Bintamilling Arcade Egerton St Narrogin WA 6312",
    "addr:housenumber":"shop 7",
    "addr:postcode":"6312",
    "addr:street":"Bintamilling Arcade Egerton St",
    "iso:country":"AU",
    "sg:address":"Shop 7, Bintamilling Arcade Egerton St",
    "sg:city":"Narrogin",
    "sg:classifiers":[
        {
            "category":"Health Services",
            "subcategory":"Dentist",
            "type":"Services"
        }
    ],
    "sg:phone":"+61 8 9881 5573",
    "sg:postcode":"6312",
    "sg:province":"WA",
    "wof:name":"Fleming Bryan",
    "wof:placetype":"venue"
},
  "geometry": {"coordinates":[117.17842865,-32.9334487915],"type":"Point"}
}