{
  "type": "Feature",
  "properties": {
    "iso:country":"AU",
    "sg:address":"44 Johnson St",
    "sg:city":"Maffra",
    "sg:classifiers":[
        {
            "category":"Personal",
            "subcategory":"Massage",
            "type":"Services"
        }
    ],
    "sg:phone":"+61 3 5147 1313",
    "sg:postcode":"3860",
    "sg:province":"VIC",
    "sg:tags":[
        "therapy"
    ],
    "wof:name":"Maffra Health & Massage Clinic",
    "wof:placetype":"venue"
},
  "geometry": {"coordinates":[146.973587036,-37.9652404785],"type":"Point"}
}