{
  "type": "Feature",
  "properties": {
    "iso:country":"AU",
    "sg:address":"Q Super Centre Cnr Bermud & Market St",
    "sg:city":"Mermaid Waters",
    "sg:classifiers":[
        {
            "category":"Shopping",
            "subcategory":"Optical Goods",
            "type":"Retail Goods"
        }
    ],
    "sg:phone":"+61 7 5526 5284",
    "sg:postcode":"4218",
    "sg:province":"QLD",
    "sg:tags":[
        "dispenser",
        "prescription"
    ],
    "wof:name":"The Optical Superstore",
    "wof:placetype":"venue"
},
  "geometry": {"coordinates":[153.41465759299999,-28.0459346771],"type":"Point"}
}