{
  "type": "Feature",
  "properties": {
    "iso:country":"AU",
    "sg:address":"153 Victoria Rd",
    "sg:city":"Gladesville",
    "sg:classifiers":[
        {
            "category":"Professional",
            "subcategory":"Engineering",
            "type":"Services"
        }
    ],
    "sg:phone":"+61 2 9879 5577",
    "sg:postcode":"2111",
    "sg:province":"NSW",
    "sg:tags":[
        "consulting",
        "engineer"
    ],
    "wof:name":"D'Ambrosio Consulting Pty Ltd",
    "wof:placetype":"venue"
},
  "geometry": {"coordinates":[151.12783813499999,-33.8346786499],"type":"Point"}
}