{
  "type": "Feature",
  "properties": {
    "addr:full":"Unit 1 20 Smallwood St Underwood QLD 4119",
    "addr:housenumber":"20",
    "addr:postcode":"4119",
    "addr:street":"Smallwood St",
    "iso:country":"AU",
    "sg:address":"Unit 1 20 Smallwood St",
    "sg:city":"Underwood",
    "sg:classifiers":[
        {
            "category":"Building & Trades",
            "subcategory":"Construction",
            "type":"Services"
        }
    ],
    "sg:phone":"+61 7 3341 4544",
    "sg:postcode":"4119",
    "sg:province":"QLD",
    "sg:tags":[
        "roof"
    ],
    "wof:name":"Metal Line Roofing",
    "wof:placetype":"venue"
},
  "geometry": {"coordinates":[153.11366272000001,-27.6080741882],"type":"Point"}
}