{
  "type": "Feature",
  "properties": {
    "iso:country":"AU",
    "sg:address":"17 Feltham St",
    "sg:city":"Pearcedale",
    "sg:classifiers":[
        {
            "category":"Manufacturing",
            "subcategory":"Building Materials",
            "type":"Manufacturing & Wholesale Goods"
        }
    ],
    "sg:phone":"+61 3 5978 6890",
    "sg:postcode":"3912",
    "sg:province":"VIC",
    "sg:tags":[
        "equipment",
        "handling"
    ],
    "wof:name":"Cander Materials Handling",
    "wof:placetype":"venue"
},
  "geometry": {"coordinates":[145.237380981,-38.2051963806],"type":"Point"}
}