{
  "type": "Feature",
  "properties": {
    "addr:full":"Suite 37, 42 Swan Ave Strathfield NSW 2135",
    "addr:housenumber":"42",
    "addr:postcode":"2135",
    "addr:street":"Swan Ave",
    "iso:country":"AU",
    "sg:address":"Suite 37, 42 Swan Ave",
    "sg:city":"Strathfield",
    "sg:classifiers":[
        {
            "category":"Real Estate",
            "subcategory":"Architect",
            "type":"Services"
        }
    ],
    "sg:phone":"+61 2 9746 7062",
    "sg:postcode":"2135",
    "sg:province":"NSW",
    "sg:tags":[
        "building",
        "designer"
    ],
    "wof:name":"J. F. Building Consultants",
    "wof:placetype":"venue"
},
  "geometry": {"coordinates":[151.09483337399999,-33.8685798645],"type":"Point"}
}