{
  "type": "Feature",
  "properties": {
    "iso:country":"AU",
    "sg:address":"490 Old Cleveland Rd",
    "sg:city":"Camp Hill",
    "sg:classifiers":[
        {
            "category":"Real Estate",
            "subcategory":"Real Estate Agent",
            "type":"Services"
        }
    ],
    "sg:phone":"+61 7 3843 4511",
    "sg:postcode":"4152",
    "sg:province":"QLD",
    "wof:name":"Position One Brisbane Property Centre",
    "wof:placetype":"venue"
},
  "geometry": {"coordinates":[153.067504883,-27.4915161133],"type":"Point"}
}