{
  "type": "Feature",
  "properties": {
    "addr:full":"91 Kooyong Rd Caulfield VIC 3162",
    "addr:housenumber":"91",
    "addr:postcode":"3162",
    "addr:street":"Kooyong Rd",
    "iso:country":"AU",
    "sg:address":"91 Kooyong Rd",
    "sg:city":"Caulfield",
    "sg:classifiers":[
        {
            "category":"Retail",
            "subcategory":"Auto Repair",
            "type":"Services"
        }
    ],
    "sg:phone":"+61 3 9509 6103",
    "sg:postcode":"3162",
    "sg:province":"VIC",
    "sg:tags":[
        "repairer",
        "motor",
        "engineer"
    ],
    "wof:name":"Octane Motors",
    "wof:placetype":"venue"
},
  "geometry": {"coordinates":[145.012405395,-37.8986129761],"type":"Point"}
}