{
  "type": "Feature",
  "properties": {
    "addr:full":"53 First Ave Rodd Point NSW 2046",
    "addr:housenumber":"53",
    "addr:postcode":"2046",
    "addr:street":"First Ave",
    "iso:country":"AU",
    "sg:address":"53 First Ave",
    "sg:city":"Rodd Point",
    "sg:classifiers":[
        {
            "category":"Farming",
            "subcategory":"Fish & Marine Products",
            "type":"Manufacturing & Wholesale Goods"
        }
    ],
    "sg:phone":"+61 2 9712 5638",
    "sg:postcode":"2046",
    "sg:province":"NSW",
    "sg:tags":[
        "supplier",
        "oyster",
        "farmer"
    ],
    "wof:name":"Sydney Oyster Suppliers",
    "wof:placetype":"venue"
},
  "geometry": {"coordinates":[151.14144899999999,-33.866352],"type":"Point"}
}