{
  "type": "Feature",
  "properties": {
    "addr:full":"School Of Human Movement UWA+Parkway Entrance No 4 Nedlands WA 6009",
    "addr:postcode":"6009",
    "iso:country":"AU",
    "sg:address":"School Of Human Movement UWA+Parkway Entrance No 4",
    "sg:city":"Nedlands",
    "sg:classifiers":[
        {
            "category":"Health Services",
            "subcategory":"Health Practitioner",
            "type":"Services"
        }
    ],
    "sg:phone":"+61 8 6488 1039",
    "sg:postcode":"6009",
    "sg:province":"WA",
    "sg:tags":[
        "physiotherapist"
    ],
    "wof:name":"UWA Health & Rehabilitation Program",
    "wof:placetype":"venue"
},
  "geometry": {"coordinates":[115.81809199999999,-31.984907],"type":"Point"}
}