{
  "type": "Feature",
  "properties": {
    "iso:country":"AU",
    "sg:address":"69 Queens Rd",
    "sg:city":"Hermit Park",
    "sg:classifiers":[
        {
            "category":"Social Services",
            "subcategory":"Child Care",
            "type":"Services"
        }
    ],
    "sg:phone":"+61 7 4779 3715",
    "sg:postcode":"4812",
    "sg:province":"QLD",
    "wof:name":"Andy Pandy Child Care Centre Hermit Park",
    "wof:placetype":"venue"
},
  "geometry": {"coordinates":[146.803436,-19.284338],"type":"Point"}
}