{
  "type": "Feature",
  "properties": {
    "iso:country":"AU",
    "sg:address":"149 Boundary Rd",
    "sg:city":"Bardon",
    "sg:classifiers":[
        {
            "category":"Real Estate",
            "subcategory":"Architect",
            "type":"Services"
        }
    ],
    "sg:phone":"+61 7 3368 2136",
    "sg:postcode":"4065",
    "sg:province":"QLD",
    "wof:name":"6B Architecture Pty Ltd",
    "wof:placetype":"venue"
},
  "geometry": {"coordinates":[152.98442077600001,-27.4665584564],"type":"Point"}
}