{
  "type": "Feature",
  "properties": {
    "addr:full":"Suite 2, Level 4 1c Grand Ave Camellia NSW 2142",
    "addr:housenumber":"1c",
    "addr:postcode":"2142",
    "addr:street":"Grand Ave",
    "iso:country":"AU",
    "sg:address":"Suite 2, Level 4 1c Grand Ave",
    "sg:city":"Camellia",
    "sg:classifiers":[
        {
            "category":"Autos & Motor Vehicles",
            "subcategory":"Automobile Sales",
            "type":"Retail Goods"
        }
    ],
    "sg:phone":"+61 2 9638 7978",
    "sg:postcode":"2142",
    "sg:province":"NSW",
    "sg:tags":[
        "equipment",
        "trailer"
    ],
    "wof:name":"Omega Tankers & Trailers",
    "wof:placetype":"venue"
},
  "geometry": {"coordinates":[151.02606201200001,-33.8203201294],"type":"Point"}
}