{
  "type": "Feature",
  "properties": {
    "iso:country":"AU",
    "sg:address":"750 North East Rd",
    "sg:city":"Holden Hill",
    "sg:classifiers":[
        {
            "category":"Real Estate",
            "subcategory":"Real Estate Agent",
            "type":"Services"
        }
    ],
    "sg:phone":"+61 1800 253 321",
    "sg:postcode":"5088",
    "sg:province":"SA",
    "sg:website":"http://www.century21.com.au/holdenhill/",
    "wof:name":"Century 21 Go for Gold Realty",
    "wof:placetype":"venue"
},
  "geometry": {"coordinates":[138.67173767099999,-34.8443984985],"type":"Point"}
}