{
  "type": "Feature",
  "properties": {
    "addr:full":"270 Stafford Rd Stafford QLD 4053",
    "addr:housenumber":"270",
    "addr:postcode":"4053",
    "addr:street":"Stafford Rd",
    "iso:country":"AU",
    "sg:address":"270 Stafford Rd",
    "sg:city":"Stafford",
    "sg:classifiers":[
        {
            "category":"Real Estate",
            "subcategory":"Real Estate Agent",
            "type":"Services"
        }
    ],
    "sg:phone":"+61 7 3356 1111",
    "sg:postcode":"4053",
    "sg:province":"QLD",
    "wof:name":"Independent Team Pty Ltd",
    "wof:placetype":"venue"
},
  "geometry": {"coordinates":[153.019073486,-27.4108600616],"type":"Point"}
}