{
  "type": "Feature",
  "properties": {
    "addr:full":"1 Alfred Rd Chipping Norton NSW 2170",
    "addr:housenumber":"1",
    "addr:postcode":"2170",
    "addr:street":"Alfred Rd",
    "iso:country":"AU",
    "sg:address":"1 Alfred Rd",
    "sg:city":"Chipping Norton",
    "sg:classifiers":[
        {
            "category":"Manufacturing",
            "subcategory":"Building Materials",
            "type":"Manufacturing & Wholesale Goods"
        }
    ],
    "sg:phone":"+61 2 9755 4000",
    "sg:postcode":"2170",
    "sg:province":"NSW",
    "sg:tags":[
        "stone",
        "product",
        "supply"
    ],
    "wof:name":"Sandstone Australia",
    "wof:placetype":"venue"
},
  "geometry": {"coordinates":[150.96832275400001,-33.9228782654],"type":"Point"}
}