{
  "type": "Feature",
  "properties": {
    "addr:full":"140 Wood St (Opp TAFE) Mackay QLD 4740",
    "addr:housenumber":"140",
    "addr:postcode":"4740",
    "addr:street":"Wood St Opp Tafe",
    "iso:country":"AU",
    "sg:address":"140 Wood St (Opp TAFE)",
    "sg:city":"Mackay",
    "sg:classifiers":[
        {
            "category":"Shopping",
            "subcategory":"Party Supplies",
            "type":"Retail Goods"
        }
    ],
    "sg:phone":"+61 7 4953 4966",
    "sg:postcode":"4740",
    "sg:province":"QLD",
    "sg:tags":[
        "hire",
        "costume"
    ],
    "wof:name":"D.I.Y. Party Supplies",
    "wof:placetype":"venue"
},
  "geometry": {"coordinates":[149.18502799999999,-21.145988],"type":"Point"}
}