{
  "type": "Feature",
  "properties": {
    "addr:full":"4 Pine Ave Hahndorf SA 5245",
    "addr:housenumber":"4",
    "addr:postcode":"5245",
    "addr:street":"Pine Ave",
    "iso:country":"AU",
    "sg:address":"4 Pine Ave",
    "sg:city":"Hahndorf",
    "sg:classifiers":[
        {
            "category":"Autos & Motor Vehicles",
            "subcategory":"Auto Supplies",
            "type":"Retail Goods"
        }
    ],
    "sg:phone":"+61 8 8388 7311",
    "sg:postcode":"5245",
    "sg:province":"SA",
    "sg:tags":[
        "accessory"
    ],
    "wof:name":"Autopro",
    "wof:placetype":"venue"
},
  "geometry": {"coordinates":[138.8097229,-35.0302848816],"type":"Point"}
}