{
  "type": "Feature",
  "properties": {
    "iso:country":"AU",
    "sg:address":"Shp2/3 Pittards Rd",
    "sg:city":"Buderim",
    "sg:classifiers":[
        {
            "category":"Food & Beverages",
            "subcategory":"Bakery",
            "type":"Retail Goods"
        }
    ],
    "sg:phone":"+61 7 5445 5211",
    "sg:postcode":"4556",
    "sg:province":"QLD",
    "sg:tags":[
        "baker"
    ],
    "wof:name":"Swiss Bakery North Buderim",
    "wof:placetype":"venue"
},
  "geometry": {"coordinates":[153.051513672,-26.6636447906],"type":"Point"}
}