{
  "type": "Feature",
  "properties": {
    "addr:full":"Gemmels Rd Macclesfield SA 5153",
    "addr:postcode":"5153",
    "addr:street":"Gemmels Rd",
    "iso:country":"AU",
    "sg:address":"Gemmels Rd",
    "sg:city":"Macclesfield",
    "sg:classifiers":[
        {
            "category":"Farming",
            "subcategory":"Farm",
            "type":"Manufacturing & Wholesale Goods"
        }
    ],
    "sg:phone":"+61 8 8388 9247",
    "sg:postcode":"5153",
    "sg:province":"SA",
    "sg:tags":[
        "farmer"
    ],
    "wof:name":"Wright Brook",
    "wof:placetype":"venue"
},
  "geometry": {"coordinates":[138.85452270499999,-35.1768302917],"type":"Point"}
}