{
  "type": "Feature",
  "properties": {
    "addr:full":"66 Dauncey St Kingscote SA 5223",
    "addr:housenumber":"66",
    "addr:postcode":"5223",
    "addr:street":"Dauncey St",
    "iso:country":"AU",
    "sg:address":"66 Dauncey St",
    "sg:city":"Kingscote",
    "sg:classifiers":[
        {
            "category":"Real Estate",
            "subcategory":"Real Estate Agent",
            "type":"Services"
        }
    ],
    "sg:phone":"+61 8 8553 2688",
    "sg:postcode":"5223",
    "sg:province":"SA",
    "wof:name":"Century 21 Myles Pearce Kangaroo Island",
    "wof:placetype":"venue"
},
  "geometry": {"coordinates":[137.63926696799999,-35.6558914185],"type":"Point"}
}