{
  "type": "Feature",
  "properties": {
    "iso:country":"AU",
    "sg:address":"U13/ 21 Woods Point Rd",
    "sg:city":"Warburton",
    "sg:classifiers":[
        {
            "category":"Professional",
            "subcategory":"Accounting & Tax Preparation",
            "type":"Services"
        }
    ],
    "sg:phone":"+61 3 5966 9430",
    "sg:postcode":"3799",
    "sg:province":"VIC",
    "sg:tags":[
        "bookkeeping"
    ],
    "wof:name":"Tabbs Bookkeeping & Business Services",
    "wof:placetype":"venue"
},
  "geometry": {"coordinates":[145.74131774899999,-37.735332489],"type":"Point"}
}