{
  "type": "Feature",
  "properties": {
    "iso:country":"AU",
    "sg:address":"70 Graves St",
    "sg:city":"Kadina",
    "sg:classifiers":[
        {
            "category":"Health Services",
            "subcategory":"Dentist",
            "type":"Services"
        }
    ],
    "sg:phone":"+61 8 8821 2899",
    "sg:postcode":"5554",
    "sg:province":"SA",
    "wof:name":"Carles K",
    "wof:placetype":"venue"
},
  "geometry": {"coordinates":[137.71803283700001,-33.9626197815],"type":"Point"}
}