{
  "type": "Feature",
  "properties": {
    "addr:full":"842 Mulgoa Rd Mulgoa NSW 2745",
    "addr:housenumber":"842",
    "addr:postcode":"2745",
    "addr:street":"Mulgoa Rd",
    "iso:country":"AU",
    "sg:address":"842 Mulgoa Rd",
    "sg:city":"Mulgoa",
    "sg:classifiers":[
        {
            "category":"Utilities",
            "subcategory":"Refuse",
            "type":"Services"
        }
    ],
    "sg:phone":"+61 2 4773 8778",
    "sg:postcode":"2745",
    "sg:province":"NSW",
    "sg:tags":[
        "disposal",
        "reduction",
        "waste"
    ],
    "wof:name":"Penrith Waste Services Pty. Ltd.",
    "wof:placetype":"venue"
},
  "geometry": {"coordinates":[150.65103149399999,-33.8537406921],"type":"Point"}
}