{
  "type": "Feature",
  "properties": {
    "addr:full":"181 Bourke St Goulburn NSW 2580",
    "addr:housenumber":"181",
    "addr:postcode":"2580",
    "addr:street":"Bourke St",
    "iso:country":"AU",
    "sg:address":"181 Bourke St",
    "sg:city":"Goulburn",
    "sg:classifiers":[
        {
            "category":"Organizations",
            "subcategory":"Professional Association",
            "type":"Services"
        }
    ],
    "sg:phone":"+61 2 4821 2522",
    "sg:postcode":"2580",
    "sg:province":"NSW",
    "sg:tags":[
        "rural",
        "organisation",
        "production",
        "primary"
    ],
    "wof:name":"Rural Lands Protection Boards",
    "wof:placetype":"venue"
},
  "geometry": {"coordinates":[149.718841553,-34.7506408691],"type":"Point"}
}