{
  "type": "Feature",
  "properties": {
    "addr:full":"1 Bradly Ave Kirribilli NSW 2061",
    "addr:housenumber":"1",
    "addr:postcode":"2061",
    "addr:street":"Bradly Ave",
    "iso:country":"AU",
    "sg:address":"1 Bradly Ave",
    "sg:city":"Kirribilli",
    "sg:classifiers":[
        {
            "category":"Autos & Motor Vehicles",
            "subcategory":"Boat Sales",
            "type":"Retail Goods"
        }
    ],
    "sg:phone":"+61 2 9957 4252",
    "sg:postcode":"2061",
    "sg:province":"NSW",
    "sg:tags":[
        "builder",
        "yacht",
        "repairer"
    ],
    "wof:name":"Hudson Boat Building",
    "wof:placetype":"venue"
},
  "geometry": {"coordinates":[151.214752197,-33.8440208435],"type":"Point"}
}