{
  "type": "Feature",
  "properties": {
    "addr:full":"98 Josephine St Ulverstone TAS 7315",
    "addr:housenumber":"98",
    "addr:postcode":"7315",
    "addr:street":"Josephine St",
    "iso:country":"AU",
    "sg:address":"98 Josephine St",
    "sg:city":"Ulverstone",
    "sg:classifiers":[
        {
            "category":"Professional",
            "subcategory":"Art Services",
            "type":"Services"
        }
    ],
    "sg:phone":"+61 427 987 107",
    "sg:postcode":"7315",
    "sg:province":"TAS",
    "sg:tags":[
        "decorator",
        "painter"
    ],
    "wof:name":"S & J Painting Service",
    "wof:placetype":"venue"
},
  "geometry": {"coordinates":[146.157104492,-41.152179718],"type":"Point"}
}