{
  "type": "Feature",
  "properties": {
    "iso:country":"AU",
    "sg:address":"31 Garrett St",
    "sg:city":"Moss Vale",
    "sg:classifiers":[
        {
            "category":"Retail",
            "subcategory":"Auto Repair",
            "type":"Services"
        }
    ],
    "sg:phone":"+61 2 4868 1011",
    "sg:postcode":"2577",
    "sg:province":"NSW",
    "sg:tags":[
        "repairer",
        "motor",
        "engineer"
    ],
    "wof:name":"Allan Mackay Autos",
    "wof:placetype":"venue"
},
  "geometry": {"coordinates":[150.371185303,-34.5501174927],"type":"Point"}
}