{
  "type": "Feature",
  "properties": {
    "addr:full":"125 Dunlop St Mortlake VIC 3272",
    "addr:housenumber":"125",
    "addr:postcode":"3272",
    "addr:street":"Dunlop St",
    "iso:country":"AU",
    "sg:address":"125 Dunlop St",
    "sg:city":"Mortlake",
    "sg:classifiers":[
        {
            "category":"Fast Food",
            "type":"Food & Drink"
        }
    ],
    "sg:phone":"+61 3 5599 2353",
    "sg:postcode":"3272",
    "sg:province":"VIC",
    "sg:tags":[
        "away",
        "take"
    ],
    "wof:name":"Pauls Place",
    "wof:placetype":"venue"
},
  "geometry": {"coordinates":[142.807861328,-38.0810127258],"type":"Point"}
}