{
  "type": "Feature",
  "properties": {
    "iso:country":"AU",
    "sg:address":"Pacific Hwy",
    "sg:city":"Frederickton",
    "sg:classifiers":[
        {
            "category":"Farming",
            "subcategory":"Farm",
            "type":"Manufacturing & Wholesale Goods"
        }
    ],
    "sg:phone":"+61 2 6566 8214",
    "sg:postcode":"2440",
    "sg:province":"NSW",
    "sg:tags":[
        "farmer"
    ],
    "wof:name":"Mainey A N",
    "wof:placetype":"venue"
},
  "geometry": {"coordinates":[152.860565,-31.035406],"type":"Point"}
}