{
  "type": "Feature",
  "properties": {
    "iso:country":"AU",
    "sg:address":"8 Falmouth St",
    "sg:city":"Avoca",
    "sg:classifiers":[
        {
            "category":"Government",
            "subcategory":"Post Office",
            "type":"Public Place"
        }
    ],
    "sg:phone":"+61 3 6384 2129",
    "sg:postcode":"7213",
    "sg:province":"TAS",
    "sg:tags":[
        "postal"
    ],
    "wof:name":"Australia Post",
    "wof:placetype":"venue"
},
  "geometry": {"coordinates":[147.721115,-41.781826],"type":"Point"}
}