{
  "type": "Feature",
  "properties": {
    "iso:country":"AU",
    "sg:address":"12 Batar Creek Rd",
    "sg:city":"Kendall",
    "sg:classifiers":[
        {
            "category":"Professional",
            "subcategory":"Art Services",
            "type":"Services"
        }
    ],
    "sg:phone":"+61 2 6559 4004",
    "sg:postcode":"2439",
    "sg:province":"NSW",
    "sg:tags":[
        "decorator",
        "painter"
    ],
    "wof:name":"Gainey Lance & Annette",
    "wof:placetype":"venue"
},
  "geometry": {"coordinates":[152.70192,-31.633801],"type":"Point"}
}