{
  "type": "Feature",
  "properties": {
    "iso:country":"AU",
    "sg:address":"PO Box 119 Chadstone Centre",
    "sg:city":"Chadstone",
    "sg:classifiers":[
        {
            "category":"Building & Trades",
            "subcategory":"Electrical",
            "type":"Services"
        }
    ],
    "sg:phone":"+61 3 9888 3355",
    "sg:postcode":"3148",
    "sg:province":"VIC",
    "sg:tags":[
        "wholesaler",
        "mfrs",
        "appliance"
    ],
    "wof:name":"COS Corporation Pty Ltd",
    "wof:placetype":"venue"
},
  "geometry": {"coordinates":[145.079589844,-37.8796424866],"type":"Point"}
}