{
  "type": "Feature",
  "properties": {
    "addr:full":"480 Abernethy Rd Kewdale WA 6105",
    "addr:housenumber":"480",
    "addr:postcode":"6105",
    "addr:street":"Abernethy Rd",
    "iso:country":"AU",
    "sg:address":"480 Abernethy Rd",
    "sg:city":"Kewdale",
    "sg:classifiers":[
        {
            "category":"Mining & Drilling",
            "type":"Manufacturing & Wholesale Goods"
        }
    ],
    "sg:phone":"+61 8 9449 1118",
    "sg:postcode":"6105",
    "sg:province":"WA",
    "sg:tags":[
        "equipment",
        "quarrying",
        "supply"
    ],
    "wof:name":"Geographe Enterprises",
    "wof:placetype":"venue"
},
  "geometry": {"coordinates":[115.947631836,-31.9718418121],"type":"Point"}
}