{
  "type": "Feature",
  "properties": {
    "addr:full":"Shop B4 Stockland Mall Cnr North St & Princes Hwy Batemans Bay NSW 2536",
    "addr:housenumber":"b4",
    "addr:postcode":"2536",
    "addr:street":"Cnr North St & Princes Hwy",
    "iso:country":"AU",
    "sg:address":"Shop B4 Stockland Mall Cnr North St & Princes Hwy",
    "sg:city":"Batemans Bay",
    "sg:classifiers":[
        {
            "category":"Shopping",
            "subcategory":"Computers & Home Electronics",
            "type":"Retail Goods"
        }
    ],
    "sg:phone":"+61 2 4472 3844",
    "sg:postcode":"2536",
    "sg:province":"NSW",
    "sg:tags":[
        "equipment",
        "part",
        "electronic"
    ],
    "wof:name":"Dick Smith Electronics",
    "wof:placetype":"venue"
},
  "geometry": {"coordinates":[150.17735290499999,-35.7058448792],"type":"Point"}
}