{
  "type": "Feature",
  "properties": {
    "addr:full":"3/12 Ereton Drv Labrador QLD 4215",
    "addr:housenumber":"/ 12",
    "addr:postcode":"4215",
    "addr:street":"Ereton Drv",
    "iso:country":"AU",
    "sg:address":"3/12 Ereton Drv",
    "sg:city":"Labrador",
    "sg:classifiers":[
        {
            "category":"Train Station",
            "subcategory":"Rail",
            "type":"Transportation"
        }
    ],
    "sg:phone":"+61 7 5563 7444",
    "sg:postcode":"4215",
    "sg:province":"QLD",
    "sg:tags":[
        "ship",
        "chandler"
    ],
    "wof:name":"Bits For Boats (Gold Coast)",
    "wof:placetype":"venue"
},
  "geometry": {"coordinates":[153.386154175,-27.935043335],"type":"Point"}
}