{
  "type": "Feature",
  "properties": {
    "addr:full":"91 Gowrie St Greenvale VIC 3059",
    "addr:housenumber":"91",
    "addr:postcode":"3059",
    "addr:street":"Gowrie St",
    "iso:country":"AU",
    "sg:address":"91 Gowrie St",
    "sg:city":"Greenvale",
    "sg:classifiers":[
        {
            "category":"Home & Garden",
            "subcategory":"Hardware",
            "type":"Retail Goods"
        }
    ],
    "sg:phone":"+61 414 361 897",
    "sg:postcode":"3059",
    "sg:province":"VIC",
    "sg:tags":[
        "plumber",
        "supply"
    ],
    "wof:name":"S.E.C.A.",
    "wof:placetype":"venue"
},
  "geometry": {"coordinates":[144.941329956,-37.6973724365],"type":"Point"}
}