{
  "type": "Feature",
  "properties": {
    "iso:country":"AU",
    "sg:address":"1 Edward St",
    "sg:city":"Gladstone",
    "sg:classifiers":[
        {
            "category":"Professional",
            "subcategory":"Computer Services",
            "type":"Services"
        }
    ],
    "sg:phone":"+61 7 4972 0666",
    "sg:postcode":"4680",
    "sg:province":"QLD",
    "sg:tags":[
        "repairs",
        "upgrade",
        "equipment"
    ],
    "wof:name":"Arthur's Computer Essentials",
    "wof:placetype":"venue"
},
  "geometry": {"coordinates":[151.354568481,-23.9569358826],"type":"Point"}
}