{
  "type": "Feature",
  "properties": {
    "iso:country":"AU",
    "sg:address":"41 Volum St",
    "sg:city":"Manifold Heights",
    "sg:classifiers":[
        {
            "category":"Professional",
            "subcategory":"Engineering",
            "type":"Services"
        }
    ],
    "sg:phone":"+61 3 5229 3008",
    "sg:postcode":"3218",
    "sg:province":"VIC",
    "sg:tags":[
        "civil",
        "engineer"
    ],
    "wof:name":"Rodger Marsden M.E.S Pty Ltd",
    "wof:placetype":"venue"
},
  "geometry": {"coordinates":[144.331832886,-38.1387863159],"type":"Point"}
}