{
  "type": "Feature",
  "properties": {
    "iso:country":"AU",
    "sg:address":"Lampard Rd",
    "sg:city":"Waddi Forest",
    "sg:classifiers":[
        {
            "category":"Farming",
            "subcategory":"Farm",
            "type":"Manufacturing & Wholesale Goods"
        }
    ],
    "sg:phone":"+61 8 9952 3227",
    "sg:postcode":"6515",
    "sg:province":"WA",
    "sg:tags":[
        "farmer"
    ],
    "wof:name":"Enfield Park",
    "wof:placetype":"venue"
},
  "geometry": {"coordinates":[116.166122,-29.868],"type":"Point"}
}