{
  "type": "Feature",
  "properties": {
    "addr:full":"304 Pacific Hwy Hexham NSW 2322",
    "addr:housenumber":"304",
    "addr:postcode":"2322",
    "addr:street":"Pacific Hwy",
    "iso:country":"AU",
    "sg:address":"304 Pacific Hwy",
    "sg:city":"Hexham",
    "sg:classifiers":[
        {
            "category":"Professional",
            "subcategory":"Engineering",
            "type":"Services"
        }
    ],
    "sg:phone":"+61 2 4964 8245",
    "sg:postcode":"2322",
    "sg:province":"NSW",
    "sg:tags":[
        "engineer"
    ],
    "wof:name":"Forgacs Engineering Pty Ltd",
    "wof:placetype":"venue"
},
  "geometry": {"coordinates":[151.72366332999999,-32.7924385071],"type":"Point"}
}