{
  "type": "Feature",
  "properties": {
    "iso:country":"AU",
    "sg:address":"Cnr Richmond Rd & South St",
    "sg:city":"Marsden Park",
    "sg:classifiers":[
        {
            "category":"Home & Garden",
            "subcategory":"Garden Supply",
            "type":"Retail Goods"
        }
    ],
    "sg:phone":"+61 418 890 934",
    "sg:postcode":"2765",
    "sg:province":"NSW",
    "sg:tags":[
        "statuary",
        "fountains",
        "sundial"
    ],
    "wof:name":"Jack's House & Garden Centre",
    "wof:placetype":"venue"
},
  "geometry": {"coordinates":[150.83334350600001,-33.6991691589],"type":"Point"}
}