{
  "type": "Feature",
  "properties": {
    "addr:full":"11 Douglas Pde Williamstown VIC 3016",
    "addr:housenumber":"11",
    "addr:postcode":"3016",
    "addr:street":"Douglas Pde",
    "iso:country":"AU",
    "sg:address":"11 Douglas Pde",
    "sg:city":"Williamstown",
    "sg:classifiers":[
        {
            "category":"Cafe",
            "type":"Food & Drink"
        }
    ],
    "sg:phone":"+61 3 9397 3376",
    "sg:postcode":"3016",
    "sg:province":"VIC",
    "wof:name":"Nrg Food & Juice Bar Pty Ltd",
    "wof:placetype":"venue"
},
  "geometry": {"coordinates":[144.897781372,-37.8583183289],"type":"Point"}
}