{
  "type": "Feature",
  "properties": {
    "iso:country":"AU",
    "sg:address":"Shop 82A Mirrabooka Square Yirrigan Drv",
    "sg:city":"Mirrabooka",
    "sg:classifiers":[
        {
            "category":"Retail",
            "subcategory":"Repair Shop",
            "type":"Services"
        }
    ],
    "sg:phone":"+61 8 9344 5573",
    "sg:postcode":"6061",
    "sg:province":"WA",
    "sg:tags":[
        "handbag"
    ],
    "wof:name":"Kays Handbags & Luggage",
    "wof:placetype":"venue"
},
  "geometry": {"coordinates":[115.85492706300001,-31.8532066345],"type":"Point"}
}