{
  "type": "Feature",
  "properties": {
    "addr:full":"109A Cooramin St Wagga Wagga NSW 2650",
    "addr:housenumber":"109a",
    "addr:postcode":"2650",
    "addr:street":"Cooramin St",
    "iso:country":"AU",
    "sg:address":"109A Cooramin St",
    "sg:city":"Wagga Wagga",
    "sg:classifiers":[
        {
            "category":"Farming",
            "subcategory":"Farm",
            "type":"Manufacturing & Wholesale Goods"
        }
    ],
    "sg:phone":"+61 2 6933 1044",
    "sg:postcode":"2650",
    "sg:province":"NSW",
    "sg:tags":[
        "farmer"
    ],
    "wof:name":"Durnan Don & Shirley",
    "wof:placetype":"venue"
},
  "geometry": {"coordinates":[147.365325928,-35.0738677979],"type":"Point"}
}