{
  "type": "Feature",
  "properties": {
    "addr:full":"141 St Georges Rd Fitzroy North VIC 3068",
    "addr:housenumber":"141",
    "addr:postcode":"3068",
    "addr:street":"St Georges Rd",
    "iso:country":"AU",
    "sg:address":"141 St Georges Rd",
    "sg:city":"Fitzroy North",
    "sg:classifiers":[
        {
            "category":"Health Services",
            "subcategory":"Doctor",
            "type":"Services"
        }
    ],
    "sg:phone":"+61 3 9481 7222",
    "sg:postcode":"3068",
    "sg:province":"VIC",
    "sg:tags":[
        "nurse",
        "nursing"
    ],
    "wof:name":"SwingShift Nurses",
    "wof:placetype":"venue"
},
  "geometry": {"coordinates":[144.98141479500001,-37.785900116],"type":"Point"}
}