{
  "type": "Feature",
  "properties": {
    "addr:full":"2274 Albany Hwy Gosnells WA 6110",
    "addr:housenumber":"2274",
    "addr:postcode":"6110",
    "addr:street":"Albany Hwy",
    "iso:country":"AU",
    "sg:address":"2274 Albany Hwy",
    "sg:city":"Gosnells",
    "sg:classifiers":[
        {
            "category":"Banks & Credit Unions",
            "subcategory":"Bank",
            "type":"Services"
        }
    ],
    "sg:phone":"+61 13 20 32",
    "sg:postcode":"6110",
    "sg:province":"WA",
    "wof:name":"Westpac",
    "wof:placetype":"venue"
},
  "geometry": {"coordinates":[116.004730225,-32.0736579895],"type":"Point"}
}