{
  "type": "Feature",
  "properties": {
    "addr:full":"U3/ 367 Argent St Broken Hill NSW 2880",
    "addr:housenumber":"367",
    "addr:postcode":"2880",
    "addr:street":"U3 /;Argent St",
    "iso:country":"AU",
    "sg:address":"U3/ 367 Argent St",
    "sg:city":"Broken Hill",
    "sg:classifiers":[
        {
            "category":"Professional",
            "subcategory":"Detective & Security Services",
            "type":"Services"
        }
    ],
    "sg:phone":"+61 8 8087 8008",
    "sg:postcode":"2880",
    "sg:province":"NSW",
    "sg:tags":[
        "consultant",
        "system"
    ],
    "wof:name":"Silver City Security",
    "wof:placetype":"venue"
},
  "geometry": {"coordinates":[141.46702575699999,-31.9575691223],"type":"Point"}
}