{
  "type": "Feature",
  "properties": {
    "iso:country":"AU",
    "sg:address":"Cnr Mary & Knox Sts",
    "sg:city":"Goulburn",
    "sg:classifiers":[
        {
            "category":"Commercial Area",
            "type":"Public Place"
        }
    ],
    "sg:phone":"+61 2 4821 2040",
    "sg:postcode":"2580",
    "sg:province":"NSW",
    "sg:tags":[
        "heavy",
        "carrier"
    ],
    "wof:name":"Fife Ian Transport",
    "wof:placetype":"venue"
},
  "geometry": {"coordinates":[149.701934814,-34.7594184875],"type":"Point"}
}