{
  "type": "Feature",
  "properties": {
    "addr:full":"Shp2/ 302 Pitt St Sydney NSW 2000",
    "addr:housenumber":"302",
    "addr:postcode":"2000",
    "addr:street":"Pitt St",
    "iso:country":"AU",
    "sg:address":"Shp2/ 302 Pitt St",
    "sg:city":"Sydney",
    "sg:classifiers":[
        {
            "category":"Personal",
            "subcategory":"Beauty Salon",
            "type":"Services"
        }
    ],
    "sg:phone":"+61 2 9264 8595",
    "sg:postcode":"2000",
    "sg:province":"NSW",
    "sg:tags":[
        "hairdresser"
    ],
    "wof:name":"Sing Song Hair Salon",
    "wof:placetype":"venue"
},
  "geometry": {"coordinates":[151.20811462399999,-33.8749160767],"type":"Point"}
}