{
  "type": "Feature",
  "properties": {
    "iso:country":"AU",
    "sg:address":"1220 Grand Junction Rd",
    "sg:city":"Hope Valley",
    "sg:classifiers":[
        {
            "category":"Food & Beverages",
            "subcategory":"Supermarket",
            "type":"Retail Goods"
        }
    ],
    "sg:phone":"+61 8 8263 5122",
    "sg:postcode":"5090",
    "sg:province":"SA",
    "sg:tags":[
        "grocery",
        "store"
    ],
    "wof:name":"Foodland Supermarkets",
    "wof:placetype":"venue"
},
  "geometry": {"coordinates":[138.69989013700001,-34.8433532715],"type":"Point"}
}