{
  "type": "Feature",
  "properties": {
    "addr:full":"PO Box 3016 Narellan Delivery Cntr NSW 2567",
    "addr:postcode":"2567",
    "iso:country":"AU",
    "sg:address":"PO Box 3016",
    "sg:city":"Narellan Delivery Cntr",
    "sg:classifiers":[
        {
            "category":"Wholesale",
            "subcategory":"Machinery & Supplies",
            "type":"Manufacturing & Wholesale Goods"
        }
    ],
    "sg:phone":"+61 416 241 903",
    "sg:postcode":"2567",
    "sg:province":"NSW",
    "sg:tags":[
        "instrument"
    ],
    "wof:name":"Automotive Instrument Repair",
    "wof:placetype":"venue"
},
  "geometry": {"coordinates":[150.75428772000001,-34.0431098938],"type":"Point"}
}