{
  "type": "Feature",
  "properties": {
    "addr:full":"15 Darlington St Stan Hope Gardens NSW 2768",
    "addr:housenumber":"15",
    "addr:postcode":"2768",
    "addr:street":"Darlington St Stan;Gardens",
    "iso:country":"AU",
    "sg:address":"15 Darlington St",
    "sg:city":"Stan Hope Gardens",
    "sg:classifiers":[
        {
            "category":"Retail",
            "subcategory":"Driving School",
            "type":"Services"
        }
    ],
    "sg:phone":"+61 2 8824 7686",
    "sg:postcode":"2768",
    "sg:province":"NSW",
    "wof:name":"Liberty Driving School",
    "wof:placetype":"venue"
},
  "geometry": {"coordinates":[150.928436,-33.7131],"type":"Point"}
}