{
  "type": "Feature",
  "properties": {
    "addr:full":"90 Petrie Tce Brisbane QLD 4000",
    "addr:housenumber":"90",
    "addr:postcode":"4000",
    "addr:street":"Petrie Tce",
    "iso:country":"AU",
    "sg:address":"90 Petrie Tce",
    "sg:city":"Brisbane",
    "sg:classifiers":[
        {
            "category":"Organizations",
            "subcategory":"Professional Association",
            "type":"Services"
        }
    ],
    "sg:phone":"+61 7 3367 3555",
    "sg:postcode":"4000",
    "sg:province":"QLD",
    "sg:tags":[
        "web",
        "internet"
    ],
    "sg:website":"http://www.diggy.com.au",
    "wof:name":"Diggy Internet Services",
    "wof:placetype":"venue"
},
  "geometry": {"coordinates":[153.01385498100001,-27.4643192291],"type":"Point"}
}