{
  "type": "Feature",
  "properties": {
    "addr:full":"Shop 65 Willows Shoppingtown Kirwan QLD 4817",
    "addr:housenumber":"shop 65",
    "addr:postcode":"4817",
    "iso:country":"AU",
    "sg:address":"Shop 65 Willows Shoppingtown",
    "sg:city":"Kirwan",
    "sg:classifiers":[
        {
            "category":"Shopping",
            "subcategory":"Clothing, Apparel, & Fashions",
            "type":"Retail Goods"
        }
    ],
    "sg:phone":"+61 7 4723 1418",
    "sg:postcode":"4817",
    "sg:province":"QLD",
    "sg:tags":[
        "lingerie",
        "hosiery",
        "sleepwear"
    ],
    "wof:name":"Figgers",
    "wof:placetype":"venue"
},
  "geometry": {"coordinates":[146.73516799999999,-19.30369],"type":"Point"}
}