{
  "type": "Feature",
  "properties": {
    "iso:country":"AU",
    "sg:address":"10 Sammut St",
    "sg:city":"Smithfield",
    "sg:classifiers":[
        {
            "category":"Building & Trades",
            "subcategory":"Cleaning & Sanitation",
            "type":"Services"
        }
    ],
    "sg:phone":"+61 2 9757 3144",
    "sg:postcode":"2164",
    "sg:province":"NSW",
    "sg:tags":[
        "abrasive",
        "blasting"
    ],
    "wof:name":"Towner Bros. Pty. Ltd.",
    "wof:placetype":"venue"
},
  "geometry": {"coordinates":[150.93316650400001,-33.840839386],"type":"Point"}
}