{
  "type": "Feature",
  "properties": {
    "iso:country":"AU",
    "sg:address":"41 Goldsmith St",
    "sg:city":"Mackay",
    "sg:classifiers":[
        {
            "category":"Utilities",
            "subcategory":"Electric",
            "type":"Services"
        }
    ],
    "sg:phone":"+61 7 4953 4666",
    "sg:postcode":"4740",
    "sg:province":"QLD",
    "sg:tags":[
        "electrical",
        "contractor"
    ],
    "wof:name":"Climate Air Conditioning & Electrical",
    "wof:placetype":"venue"
},
  "geometry": {"coordinates":[149.191971,-21.161255],"type":"Point"}
}