{
  "type": "Feature",
  "properties": {
    "addr:full":"3 Belah St Leeton NSW 2705",
    "addr:housenumber":"3",
    "addr:postcode":"2705",
    "addr:street":"Belah St",
    "iso:country":"AU",
    "sg:address":"3 Belah St",
    "sg:city":"Leeton",
    "sg:classifiers":[
        {
            "category":"Retail",
            "subcategory":"Car Wash",
            "type":"Services"
        }
    ],
    "sg:phone":"+61 2 6953 2484",
    "sg:postcode":"2705",
    "sg:province":"NSW",
    "sg:tags":[
        "truck",
        "cleaning"
    ],
    "wof:name":"Car Spa On Belah",
    "wof:placetype":"venue"
},
  "geometry": {"coordinates":[146.400192261,-34.553981781],"type":"Point"}
}