{
  "type": "Feature",
  "properties": {
    "addr:full":"24 Wallis Ave Ivanhoe East VIC 3079",
    "addr:housenumber":"24",
    "addr:postcode":"3079",
    "addr:street":"Wallis Ave",
    "iso:country":"AU",
    "sg:address":"24 Wallis Ave",
    "sg:city":"Ivanhoe East",
    "sg:classifiers":[
        {
            "category":"Real Estate",
            "subcategory":"Surveying",
            "type":"Services"
        }
    ],
    "sg:phone":"+61 3 9499 2834",
    "sg:postcode":"3079",
    "sg:province":"VIC",
    "sg:tags":[
        "surveyor",
        "land"
    ],
    "wof:name":"Freeman T.G.& Associates Pty Ltd",
    "wof:placetype":"venue"
},
  "geometry": {"coordinates":[145.05697631800001,-37.7755775452],"type":"Point"}
}