{
  "type": "Feature",
  "properties": {
    "addr:full":"U 48/ 808 Anzac Pde Maroubra Junction NSW 2035",
    "addr:housenumber":"48 / 808",
    "addr:postcode":"2035",
    "addr:street":"Anzac Pde",
    "iso:country":"AU",
    "sg:address":"U 48/ 808 Anzac Pde",
    "sg:city":"Maroubra Junction",
    "sg:classifiers":[
        {
            "category":"Professional",
            "subcategory":"Accounting & Tax Preparation",
            "type":"Services"
        }
    ],
    "sg:phone":"+61 2 9349 3038",
    "sg:postcode":"2035",
    "sg:province":"NSW",
    "sg:tags":[
        "accountant",
        "auditor"
    ],
    "wof:name":"North A J",
    "wof:placetype":"venue"
},
  "geometry": {"coordinates":[151.239135742,-33.9389533997],"type":"Point"}
}