{
  "type": "Feature",
  "properties": {
    "iso:country":"AU",
    "sg:address":"58- 70 Hampstead Rd",
    "sg:city":"Maidstone",
    "sg:classifiers":[
        {
            "category":"Manufacturing",
            "subcategory":"Metals",
            "type":"Manufacturing & Wholesale Goods"
        }
    ],
    "sg:phone":"+61 3 9318 6077",
    "sg:postcode":"3012",
    "sg:province":"VIC",
    "sg:tags":[
        "fabricator",
        "aluminium"
    ],
    "wof:name":"Alucobond Architectural Pty Ltd",
    "wof:placetype":"venue"
},
  "geometry": {"coordinates":[144.87690734899999,-37.7778701782],"type":"Point"}
}