{
  "type": "Feature",
  "properties": {
    "iso:country":"AU",
    "sg:address":"U6/ 4 Wests Rd",
    "sg:city":"Maribyrnong",
    "sg:classifiers":[
        {
            "category":"Professional",
            "subcategory":"Management & Consulting",
            "type":"Services"
        }
    ],
    "sg:phone":"+61 3 9318 8152",
    "sg:postcode":"3032",
    "sg:province":"VIC",
    "sg:tags":[
        "consultant",
        "educational"
    ],
    "wof:name":"Mgm Australian Education",
    "wof:placetype":"venue"
},
  "geometry": {"coordinates":[144.881638,-37.773315],"type":"Point"}
}