{
  "type": "Feature",
  "properties": {
    "addr:full":"PO Box 347 Jannali NSW 2226",
    "addr:postcode":"2226",
    "iso:country":"AU",
    "sg:address":"PO Box 347",
    "sg:city":"Jannali",
    "sg:classifiers":[
        {
            "category":"Building & Trades",
            "subcategory":"Plumbing",
            "type":"Services"
        }
    ],
    "sg:phone":"+61 414 270 337",
    "sg:postcode":"2226",
    "sg:province":"NSW",
    "sg:tags":[
        "plumber",
        "gasfitters"
    ],
    "wof:name":"Pollard Craig Plumbing",
    "wof:placetype":"venue"
},
  "geometry": {"coordinates":[151.06605529800001,-34.0162887573],"type":"Point"}
}