{
  "type": "Feature",
  "properties": {
    "iso:country":"AU",
    "sg:address":"14 Main St",
    "sg:city":"Pialba",
    "sg:classifiers":[
        {
            "category":"Shopping",
            "subcategory":"Clothing, Apparel, & Fashions",
            "type":"Retail Goods"
        }
    ],
    "sg:phone":"+61 7 4124 4944",
    "sg:postcode":"4655",
    "sg:province":"QLD",
    "sg:tags":[
        "recycled",
        "clothing"
    ],
    "wof:name":"Lifeline Fraser District",
    "wof:placetype":"venue"
},
  "geometry": {"coordinates":[152.837631,-25.289988],"type":"Point"}
}