{
  "type": "Feature",
  "properties": {
    "iso:country":"AU",
    "sg:address":"93 Denison St",
    "sg:city":"Hamilton",
    "sg:classifiers":[
        {
            "category":"Shopping",
            "subcategory":"Event Tickets",
            "type":"Retail Goods"
        }
    ],
    "sg:phone":"+61 2 4969 4741",
    "sg:postcode":"2303",
    "sg:province":"NSW",
    "sg:tags":[
        "machine",
        "issuing"
    ],
    "wof:name":"ERG Transit System",
    "wof:placetype":"venue"
},
  "geometry": {"coordinates":[151.748795,-32.925617],"type":"Point"}
}