{
  "type": "Feature",
  "properties": {
    "addr:full":"101-103 McGregor Rd Smithfield (Cairns) QLD 4878",
    "addr:housenumber":"101-103",
    "addr:postcode":"4878",
    "addr:street":"Mcgregor Rd",
    "iso:country":"AU",
    "sg:address":"101-103 McGregor Rd",
    "sg:city":"Smithfield (Cairns)",
    "sg:classifiers":[
        {
            "category":"Home & Garden",
            "subcategory":"Garden Supply",
            "type":"Retail Goods"
        }
    ],
    "sg:phone":"+61 7 4055 6865",
    "sg:postcode":"4878",
    "sg:province":"QLD",
    "sg:tags":[
        "equipment"
    ],
    "wof:name":"Buffalo's Raw Material Supplies",
    "wof:placetype":"venue"
},
  "geometry": {"coordinates":[145.68858337399999,-16.8202629089],"type":"Point"}
}