{
  "type": "Feature",
  "properties": {
    "addr:full":"3/ 28 Moralla Ave Croydon VIC 3136",
    "addr:housenumber":"/ 28",
    "addr:postcode":"3136",
    "addr:street":"Moralla Ave",
    "iso:country":"AU",
    "sg:address":"3/ 28 Moralla Ave",
    "sg:city":"Croydon",
    "sg:classifiers":[
        {
            "category":"Education",
            "subcategory":"Music School",
            "type":"Public Place"
        }
    ],
    "sg:phone":"+61 3 9723 2160",
    "sg:postcode":"3136",
    "sg:province":"VIC",
    "sg:tags":[
        "teacher"
    ],
    "wof:name":"Drum Studios Ron & Dean Cooper",
    "wof:placetype":"venue"
},
  "geometry": {"coordinates":[145.271240234,-37.8032493591],"type":"Point"}
}