{
  "type": "Feature",
  "properties": {
    "iso:country":"AU",
    "sg:address":"195 Mouat St",
    "sg:city":"Lyneham",
    "sg:classifiers":[
        {
            "category":"Health Services",
            "subcategory":"Doctor",
            "type":"Services"
        }
    ],
    "sg:phone":"+61 2 6249 1758",
    "sg:postcode":"2602",
    "sg:province":"ACT",
    "sg:tags":[
        "podiatrist"
    ],
    "wof:name":"The Walking Clinic",
    "wof:placetype":"venue"
},
  "geometry": {"coordinates":[149.12657165499999,-35.2431030273],"type":"Point"}
}