{
  "type": "Feature",
  "properties": {
    "addr:full":"Unit 11 29 William St North Parramatta NSW 2151",
    "addr:housenumber":"29",
    "addr:postcode":"2151",
    "addr:street":"William St",
    "iso:country":"AU",
    "sg:address":"Unit 11 29 William St",
    "sg:city":"North Parramatta",
    "sg:classifiers":[
        {
            "category":"Building & Trades",
            "subcategory":"Landscaping Services",
            "type":"Services"
        }
    ],
    "sg:phone":"+61 2 9890 5636",
    "sg:postcode":"2151",
    "sg:province":"NSW",
    "sg:tags":[
        "consultant"
    ],
    "wof:name":"Precise Contract Estimations",
    "wof:placetype":"venue"
},
  "geometry": {"coordinates":[151.007904053,-33.7982749939],"type":"Point"}
}