{
  "type": "Feature",
  "properties": {
    "addr:full":"6 Thompson St Glen Waverley VIC 3150",
    "addr:housenumber":"6",
    "addr:postcode":"3150",
    "addr:street":"Thompson St",
    "iso:country":"AU",
    "sg:address":"6 Thompson St",
    "sg:city":"Glen Waverley",
    "sg:classifiers":[
        {
            "category":"Shopping",
            "subcategory":"Jewelry",
            "type":"Retail Goods"
        }
    ],
    "sg:phone":"+61 3 9803 9517",
    "sg:postcode":"3150",
    "sg:province":"VIC",
    "sg:tags":[
        "jeweller"
    ],
    "wof:name":"House Of Minerva",
    "wof:placetype":"venue"
},
  "geometry": {"coordinates":[145.169647217,-37.8676605225],"type":"Point"}
}