{
  "type": "Feature",
  "properties": {
    "addr:full":"56 Derby Drv Epping VIC 3076",
    "addr:housenumber":"56",
    "addr:postcode":"3076",
    "addr:street":"Derby Drv",
    "iso:country":"AU",
    "sg:address":"56 Derby Drv",
    "sg:city":"Epping",
    "sg:classifiers":[
        {
            "category":"Building & Trades",
            "subcategory":"Landscaping Services",
            "type":"Services"
        }
    ],
    "sg:phone":"+61 414 318 470",
    "sg:postcode":"3076",
    "sg:province":"VIC",
    "sg:tags":[
        "designer",
        "landscape",
        "contractor"
    ],
    "wof:name":"Greg's Indigenous Plants & Landscapes",
    "wof:placetype":"venue"
},
  "geometry": {"coordinates":[145.04466247600001,-37.6427497864],"type":"Point"}
}