{
  "type": "Feature",
  "properties": {
    "addr:full":"123 Swan St Morpeth NSW 2321",
    "addr:housenumber":"123",
    "addr:postcode":"2321",
    "addr:street":"Swan St",
    "iso:country":"AU",
    "sg:address":"123 Swan St",
    "sg:city":"Morpeth",
    "sg:classifiers":[
        {
            "category":"Museum",
            "type":"Entertainment"
        }
    ],
    "sg:phone":"+61 2 4934 4301",
    "sg:postcode":"2321",
    "sg:province":"NSW",
    "wof:name":"Morpeth Museum",
    "wof:placetype":"venue"
},
  "geometry": {"coordinates":[151.62701415999999,-32.7249908447],"type":"Point"}
}