{
  "type": "Feature",
  "properties": {
    "addr:full":"363 Forest Rd The Basin VIC 3154",
    "addr:housenumber":"363",
    "addr:postcode":"3154",
    "addr:street":"Forest Rd",
    "iso:country":"AU",
    "sg:address":"363 Forest Rd",
    "sg:city":"The Basin",
    "sg:classifiers":[
        {
            "category":"Professional",
            "subcategory":"Accounting & Tax Preparation",
            "type":"Services"
        }
    ],
    "sg:phone":"+61 3 9762 1330",
    "sg:postcode":"3154",
    "sg:province":"VIC",
    "sg:tags":[
        "bookkeeping"
    ],
    "wof:name":"Aliantha Office Solutions",
    "wof:placetype":"venue"
},
  "geometry": {"coordinates":[145.31387329099999,-37.8575172424],"type":"Point"}
}