{
  "type": "Feature",
  "properties": {
    "addr:full":"3 Old Sawmill Rd Gin Gin QLD 4671",
    "addr:housenumber":"3",
    "addr:postcode":"4671",
    "addr:street":"Old Sawmill Rd",
    "iso:country":"AU",
    "sg:address":"3 Old Sawmill Rd",
    "sg:city":"Gin Gin",
    "sg:classifiers":[
        {
            "category":"Building & Trades",
            "subcategory":"Construction",
            "type":"Services"
        }
    ],
    "sg:phone":"+61 428 135 364",
    "sg:postcode":"4671",
    "sg:province":"QLD",
    "sg:tags":[
        "earth",
        "excavating",
        "moving",
        "contractor"
    ],
    "wof:name":"Gin Gin Bulldozer Hire",
    "wof:placetype":"venue"
},
  "geometry": {"coordinates":[151.961975,-24.994024],"type":"Point"}
}