{
  "type": "Feature",
  "properties": {
    "iso:country":"AU",
    "sg:address":"532 Calderwood Rd",
    "sg:city":"Albion Park",
    "sg:classifiers":[
        {
            "category":"Sports & Exercise",
            "subcategory":"Golf",
            "type":"Entertainment"
        }
    ],
    "sg:phone":"+61 2 4256 3055",
    "sg:postcode":"2527",
    "sg:province":"NSW",
    "sg:tags":[
        "club"
    ],
    "wof:name":"Calderwood Valley Golf Course",
    "wof:placetype":"venue"
},
  "geometry": {"coordinates":[150.71112060600001,-34.5497627258],"type":"Point"}
}