{
  "type": "Feature",
  "properties": {
    "addr:full":"344 Mulgrave Rd Cairns QLD 4870",
    "addr:housenumber":"344",
    "addr:postcode":"4870",
    "addr:street":"Mulgrave Rd",
    "iso:country":"AU",
    "sg:address":"344 Mulgrave Rd",
    "sg:city":"Cairns",
    "sg:classifiers":[
        {
            "category":"Manufacturing",
            "subcategory":"Food",
            "type":"Manufacturing & Wholesale Goods"
        }
    ],
    "sg:phone":"+61 7 4054 4667",
    "sg:postcode":"4870",
    "sg:province":"QLD",
    "sg:tags":[
        "function",
        "catering"
    ],
    "wof:name":"Capra Catering Maxwell Services Pty Ltd",
    "wof:placetype":"venue"
},
  "geometry": {"coordinates":[145.747283936,-16.9377155304],"type":"Point"}
}