{
  "type": "Feature",
  "properties": {
    "addr:full":"Shop 7/ 1396 Creek Rd Carina QLD 4152",
    "addr:housenumber":"shop 7 / 1396",
    "addr:postcode":"4152",
    "addr:street":"Creek Rd",
    "iso:country":"AU",
    "sg:address":"Shop 7/ 1396 Creek Rd",
    "sg:city":"Carina",
    "sg:classifiers":[
        {
            "category":"Personal",
            "subcategory":"Nail Salon",
            "type":"Services"
        }
    ],
    "sg:phone":"+61 7 3343 9393",
    "sg:postcode":"4152",
    "sg:province":"QLD",
    "sg:tags":[
        "artificial"
    ],
    "wof:name":"Lauren Towner Nail Design",
    "wof:placetype":"venue"
},
  "geometry": {"coordinates":[153.10144043,-27.4932804108],"type":"Point"}
}