{
  "type": "Feature",
  "properties": {
    "iso:country":"AU",
    "sg:address":"P.O 595",
    "sg:city":"Roseville",
    "sg:classifiers":[
        {
            "category":"Shopping",
            "subcategory":"Crafts & Fabrics",
            "type":"Retail Goods"
        }
    ],
    "sg:phone":"+61 2 9440 2901",
    "sg:postcode":"2069",
    "sg:province":"NSW",
    "sg:tags":[
        "supply"
    ],
    "wof:name":"Craftmall.com.au",
    "wof:placetype":"venue"
},
  "geometry": {"coordinates":[151.18812560999999,-33.7779045105],"type":"Point"}
}