{
  "type": "Feature",
  "properties": {
    "addr:full":"Ground Floor Win Tower 2 Barolin St Bundaberg QLD 4670",
    "addr:postcode":"4670",
    "addr:street":"Barolin St",
    "iso:country":"AU",
    "sg:address":"Ground Floor Win Tower 2 Barolin St",
    "sg:city":"Bundaberg",
    "sg:classifiers":[
        {
            "category":"Real Estate",
            "subcategory":"Real Estate Agent",
            "type":"Services"
        }
    ],
    "sg:phone":"+61 7 4154 4178",
    "sg:postcode":"4670",
    "sg:province":"QLD",
    "wof:name":"C B D Realty",
    "wof:placetype":"venue"
},
  "geometry": {"coordinates":[152.34877014200001,-24.8653774261],"type":"Point"}
}