{
  "type": "Feature",
  "properties": {
    "addr:full":"Rear Unit 211 Balcatta Rd Balcatta WA 6021",
    "addr:postcode":"6021",
    "addr:street":"Balcatta Rd",
    "iso:country":"AU",
    "sg:address":"Rear Unit 211 Balcatta Rd",
    "sg:city":"Balcatta",
    "sg:classifiers":[
        {
            "category":"Home & Garden",
            "subcategory":"Carpets & Floor Coverings",
            "type":"Retail Goods"
        }
    ],
    "sg:phone":"+61 8 9345 3158",
    "sg:postcode":"6021",
    "sg:province":"WA",
    "sg:tags":[
        "tile",
        "wall"
    ],
    "wof:name":"Ceramic Wholesale Pty ltd",
    "wof:placetype":"venue"
},
  "geometry": {"coordinates":[115.816001892,-31.861700058],"type":"Point"}
}