{
  "type": "Feature",
  "properties": {
    "iso:country":"AU",
    "sg:address":"258 Kingsgrove Rd",
    "sg:city":"Kingsgrove",
    "sg:classifiers":[
        {
            "category":"Food & Beverages",
            "subcategory":"Bakery",
            "type":"Retail Goods"
        }
    ],
    "sg:phone":"+61 2 9150 9535",
    "sg:postcode":"2208",
    "sg:province":"NSW",
    "sg:tags":[
        "baker"
    ],
    "wof:name":"Kingsgrove Bakery",
    "wof:placetype":"venue"
},
  "geometry": {"coordinates":[151.10142500000001,-33.941566],"type":"Point"}
}