{
  "type": "Feature",
  "properties": {
    "addr:full":"110c Boundary St Paddington NSW 2021",
    "addr:housenumber":"110c",
    "addr:postcode":"2021",
    "addr:street":"Boundary St",
    "iso:country":"AU",
    "sg:address":"110c Boundary St",
    "sg:city":"Paddington",
    "sg:classifiers":[
        {
            "category":"Personal",
            "subcategory":"Beauty Salon",
            "type":"Services"
        }
    ],
    "sg:phone":"+61 2 9358 5188",
    "sg:postcode":"2021",
    "sg:province":"NSW",
    "sg:tags":[
        "hairdresser"
    ],
    "wof:name":"James Salon",
    "wof:placetype":"venue"
},
  "geometry": {"coordinates":[151.222091675,-33.8811073303],"type":"Point"}
}