{
  "type": "Feature",
  "properties": {
    "iso:country":"AU",
    "sg:address":"PO Box 80",
    "sg:city":"Berrimah",
    "sg:classifiers":[
        {
            "category":"Wholesale",
            "subcategory":"Auto Parts",
            "type":"Manufacturing & Wholesale Goods"
        }
    ],
    "sg:phone":"+61 8 8947 0093",
    "sg:postcode":"0828",
    "sg:province":"NT",
    "sg:tags":[
        "recyclers"
    ],
    "wof:name":"Aussie Car Centre",
    "wof:placetype":"venue"
},
  "geometry": {"coordinates":[130.91490173299999,-12.4386644363],"type":"Point"}
}