{
  "type": "Feature",
  "properties": {
    "addr:full":"Level 16, 15 Blue Street North Sydney NSW 2060",
    "addr:housenumber":"15",
    "addr:postcode":"2060",
    "addr:street":"Blue Street",
    "iso:country":"AU",
    "sg:address":"Level 16, 15 Blue Street",
    "sg:city":"North Sydney",
    "sg:classifiers":[
        {
            "category":"Professional",
            "subcategory":"Computer Services",
            "type":"Services"
        }
    ],
    "sg:postcode":"NSW 2060",
    "sg:website":"http://www.fujitsu.com",
    "wof:name":"Fujitsu",
    "wof:placetype":"venue"
},
  "geometry": {"coordinates":[151.20645999999999,-33.840821],"type":"Point"}
}