{
  "type": "Feature",
  "properties": {
    "iso:country":"AU",
    "sg:address":"4 Parramatta Rd",
    "sg:city":"Homebush",
    "sg:classifiers":[
        {
            "category":"Professional",
            "type":"Services"
        }
    ],
    "sg:phone":"+61 412 370 195",
    "sg:postcode":"2140",
    "sg:province":"NSW",
    "sg:tags":[
        "mail",
        "contractor"
    ],
    "wof:name":"Rushmore Mail",
    "wof:placetype":"venue"
},
  "geometry": {"coordinates":[151.08926391599999,-33.8653411865],"type":"Point"}
}