{
  "type": "Feature",
  "properties": {
    "iso:country":"AU",
    "sg:address":"2/ 55 Bulimba St",
    "sg:city":"Bulimba",
    "sg:classifiers":[
        {
            "category":"Wholesale",
            "subcategory":"Apparel",
            "type":"Manufacturing & Wholesale Goods"
        }
    ],
    "sg:phone":"+61 7 3399 8135",
    "sg:postcode":"4171",
    "sg:province":"QLD",
    "sg:tags":[
        "wholesaler",
        "mfrs",
        "cap",
        "hat"
    ],
    "wof:name":"Karen Bailey Millinery",
    "wof:placetype":"venue"
},
  "geometry": {"coordinates":[153.05621337900001,-27.4486598969],"type":"Point"}
}