{
  "type": "Feature",
  "properties": {
    "iso:country":"AU",
    "sg:address":"292 Allan St",
    "sg:city":"Kyabram",
    "sg:classifiers":[
        {
            "category":"Home & Garden",
            "subcategory":"Garden Supply",
            "type":"Retail Goods"
        }
    ],
    "sg:phone":"+61 3 5852 3202",
    "sg:postcode":"3620",
    "sg:province":"VIC",
    "sg:tags":[
        "equipment"
    ],
    "wof:name":"Ratcliffes Garden Machinery",
    "wof:placetype":"venue"
},
  "geometry": {"coordinates":[145.05130004899999,-36.3135795593],"type":"Point"}
}