{
  "type": "Feature",
  "properties": {
    "addr:full":"122 Percival Rd Stanmore NSW 2048",
    "addr:housenumber":"122",
    "addr:postcode":"2048",
    "addr:street":"Percival Rd",
    "iso:country":"AU",
    "sg:address":"122 Percival Rd",
    "sg:city":"Stanmore",
    "sg:classifiers":[
        {
            "category":"Home & Garden",
            "subcategory":"Carpets & Floor Coverings",
            "type":"Retail Goods"
        }
    ],
    "sg:phone":"+61 2 9569 4834",
    "sg:postcode":"2048",
    "sg:province":"NSW",
    "sg:tags":[
        "mattress"
    ],
    "sg:website":"http://www.naturalbedding.com.au",
    "wof:name":"The Natural Bedding Company Pty Ltd",
    "wof:placetype":"venue"
},
  "geometry": {"coordinates":[151.16412399999999,-33.893585],"type":"Point"}
}