{
  "type": "Feature",
  "properties": {
    "iso:country":"AU",
    "sg:address":"54 Porter St",
    "sg:city":"Templestowe",
    "sg:classifiers":[
        {
            "category":"Real Estate",
            "subcategory":"Architect",
            "type":"Services"
        }
    ],
    "sg:phone":"+61 3 9846 1819",
    "sg:postcode":"3106",
    "sg:province":"VIC",
    "wof:name":"Lewis A C K",
    "wof:placetype":"venue"
},
  "geometry": {"coordinates":[145.130584717,-37.7521057129],"type":"Point"}
}