{
  "type": "Feature",
  "properties": {
    "addr:full":"269-275 Abbotsford St North Melbourne VIC 3051",
    "addr:housenumber":"269-275",
    "addr:postcode":"abbotsford;3051",
    "addr:street":"St",
    "iso:country":"AU",
    "sg:address":"269-275 Abbotsford St",
    "sg:city":"North Melbourne",
    "sg:classifiers":[
        {
            "category":"Professional",
            "subcategory":"Art Services",
            "type":"Services"
        }
    ],
    "sg:phone":"+61 3 9329 0588",
    "sg:postcode":"3051",
    "sg:province":"VIC",
    "sg:tags":[
        "graphic",
        "designer"
    ],
    "wof:name":"Phat Media",
    "wof:placetype":"venue"
},
  "geometry": {"coordinates":[144.94566345199999,-37.8008575439],"type":"Point"}
}