{
  "type": "Feature",
  "properties": {
    "iso:country":"AU",
    "sg:address":"8/ 40 Thuringowa Drv",
    "sg:city":"Kirwan",
    "sg:classifiers":[
        {
            "category":"Professional",
            "subcategory":"Business Services",
            "type":"Services"
        }
    ],
    "sg:phone":"+61 7 4755 6145",
    "sg:postcode":"4817",
    "sg:province":"QLD",
    "sg:tags":[
        "broker"
    ],
    "wof:name":"Ray White Thuringowa",
    "wof:placetype":"venue"
},
  "geometry": {"coordinates":[146.729263,-19.313261],"type":"Point"}
}