{
  "type": "Feature",
  "properties": {
    "iso:country":"AU",
    "sg:address":"Unit 22, 6 Carr St",
    "sg:city":"Waverton",
    "sg:classifiers":[
        {
            "category":"Education",
            "subcategory":"Music School",
            "type":"Public Place"
        }
    ],
    "sg:phone":"+61 2 9956 5595",
    "sg:postcode":"2060",
    "sg:province":"NSW",
    "sg:tags":[
        "teacher"
    ],
    "wof:name":"Chan Shirley",
    "wof:placetype":"venue"
},
  "geometry": {"coordinates":[151.19955444300001,-33.8394241333],"type":"Point"}
}