{
  "type": "Feature",
  "properties": {
    "addr:full":"Unit 3/ 55 Gillam Drv Kelmscott WA 6111",
    "addr:housenumber":"55",
    "addr:postcode":"6111",
    "addr:street":"Gillam Drv",
    "iso:country":"AU",
    "sg:address":"Unit 3/ 55 Gillam Drv",
    "sg:city":"Kelmscott",
    "sg:classifiers":[
        {
            "category":"Retail",
            "subcategory":"Auto Repair",
            "type":"Services"
        }
    ],
    "sg:phone":"+61 8 9495 1049",
    "sg:postcode":"6111",
    "sg:province":"WA",
    "sg:tags":[
        "electrical"
    ],
    "wof:name":"Armkel Auto Electrics",
    "wof:placetype":"venue"
},
  "geometry": {"coordinates":[116.003112793,-32.1267356873],"type":"Point"}
}