{
  "type": "Feature",
  "properties": {
    "addr:full":"145 Glenayr Ave Bondi NSW 2026",
    "addr:housenumber":"145",
    "addr:postcode":"2026",
    "addr:street":"Glenayr Ave",
    "iso:country":"AU",
    "sg:address":"145 Glenayr Ave",
    "sg:city":"Bondi",
    "sg:classifiers":[
        {
            "category":"Personal",
            "subcategory":"Beauty Salon",
            "type":"Services"
        }
    ],
    "sg:phone":"+61 2 9130 2400",
    "sg:postcode":"2026",
    "sg:province":"NSW",
    "sg:tags":[
        "hairdresser"
    ],
    "wof:name":"Salon Judith Coiffure",
    "wof:placetype":"venue"
},
  "geometry": {"coordinates":[151.27125549300001,-33.8883171082],"type":"Point"}
}