{
  "type": "Feature",
  "properties": {
    "addr:full":"31 South St Manilla NSW 2346",
    "addr:housenumber":"31",
    "addr:postcode":"2346",
    "addr:street":"South St",
    "iso:country":"AU",
    "sg:address":"31 South St",
    "sg:city":"Manilla",
    "sg:classifiers":[
        {
            "category":"Taxi",
            "type":"Transportation"
        }
    ],
    "sg:phone":"+61 2 6785 1385",
    "sg:postcode":"2346",
    "sg:province":"NSW",
    "sg:tags":[
        "cab"
    ],
    "wof:name":"Manilla Taxi Service",
    "wof:placetype":"venue"
},
  "geometry": {"coordinates":[150.723556519,-30.7565975189],"type":"Point"}
}