{
  "type": "Feature",
  "properties": {
    "addr:full":"5 Norvel Rd Ferntree Gully VIC 3156",
    "addr:housenumber":"5",
    "addr:postcode":"3156",
    "addr:street":"Norvel Rd",
    "iso:country":"AU",
    "sg:address":"5 Norvel Rd",
    "sg:city":"Ferntree Gully",
    "sg:classifiers":[
        {
            "category":"Professional",
            "subcategory":"Art Services",
            "type":"Services"
        }
    ],
    "sg:phone":"+61 412 538 347",
    "sg:postcode":"3156",
    "sg:province":"VIC",
    "sg:tags":[
        "decorator",
        "painter"
    ],
    "wof:name":"Andrew Westbury Painters",
    "wof:placetype":"venue"
},
  "geometry": {"coordinates":[145.27090454099999,-37.871181488],"type":"Point"}
}