{
  "type": "Feature",
  "properties": {
    "iso:country":"AU",
    "sg:address":"PO Box 1046",
    "sg:city":"Slacks Creek",
    "sg:classifiers":[
        {
            "category":"Building & Trades",
            "subcategory":"Cleaning & Sanitation",
            "type":"Services"
        }
    ],
    "sg:phone":"+61 1300 668 342",
    "sg:postcode":"4127",
    "sg:province":"QLD",
    "sg:tags":[
        "asbestos",
        "treatment",
        "removal"
    ],
    "wof:name":"Demolition Services",
    "wof:placetype":"venue"
},
  "geometry": {"coordinates":[153.12637329099999,-27.6395797729],"type":"Point"}
}