{
  "type": "Feature",
  "properties": {
    "iso:country":"AU",
    "sg:address":"34 Nelson St",
    "sg:city":"Moorabbin",
    "sg:classifiers":[
        {
            "category":"Retail",
            "subcategory":"Laundry & Dry Cleaning",
            "type":"Services"
        }
    ],
    "sg:phone":"+61 3 9555 1877",
    "sg:postcode":"3189",
    "sg:province":"VIC",
    "sg:tags":[
        "cloth",
        "supply"
    ],
    "wof:name":"Kleen-Tex Trading Co",
    "wof:placetype":"venue"
},
  "geometry": {"coordinates":[145.072357178,-37.9450073242],"type":"Point"}
}