{
  "type": "Feature",
  "properties": {
    "iso:country":"AU",
    "sg:address":"Encouragement Centre Unit 15, Stirling Axis, 51 Cedric St",
    "sg:city":"Stirling",
    "sg:classifiers":[
        {
            "category":"Fast Food",
            "type":"Food & Drink"
        }
    ],
    "sg:phone":"+61 8 9440 5877",
    "sg:postcode":"6021",
    "sg:province":"WA",
    "sg:tags":[
        "away",
        "take"
    ],
    "sg:website":"http://www.chooks.com.au",
    "wof:name":"CHOOKS fresh & tasty Pty Ltd",
    "wof:placetype":"venue"
},
  "geometry": {"coordinates":[115.809677124,-31.886800766],"type":"Point"}
}