{
  "type": "Feature",
  "properties": {
    "addr:full":"144 Adelaide St Brisbane QLD 4000",
    "addr:housenumber":"144",
    "addr:postcode":"4000",
    "addr:street":"Adelaide St",
    "iso:country":"AU",
    "sg:address":"144 Adelaide St",
    "sg:city":"Brisbane",
    "sg:classifiers":[
        {
            "category":"Real Estate",
            "subcategory":"Real Estate Services",
            "type":"Services"
        }
    ],
    "sg:phone":"+61 7 3233 3999",
    "sg:postcode":"4000",
    "sg:province":"QLD",
    "sg:tags":[
        "valuer"
    ],
    "wof:name":"Blocksidge & Ferguson Ltd",
    "wof:placetype":"venue"
},
  "geometry": {"coordinates":[153.02542114299999,-27.4679546356],"type":"Point"}
}