{
  "type": "Feature",
  "properties": {
    "addr:full":"Lake Village Shopping Centre Gregory Crs Wagga Wagga NSW 2650",
    "addr:postcode":"2650",
    "addr:street":"Gregory Crs",
    "iso:country":"AU",
    "sg:address":"Lake Village Shopping Centre Gregory Crs",
    "sg:city":"Wagga Wagga",
    "sg:classifiers":[
        {
            "category":"Wholesale",
            "subcategory":"Home Furnishings",
            "type":"Manufacturing & Wholesale Goods"
        }
    ],
    "sg:phone":"+61 2 6922 5223",
    "sg:postcode":"2650",
    "sg:province":"NSW",
    "sg:tags":[
        "wholesaler",
        "curtain",
        "mfrs"
    ],
    "wof:name":"D B Finishing Touch",
    "wof:placetype":"venue"
},
  "geometry": {"coordinates":[147.384857178,-35.1721343994],"type":"Point"}
}