{
  "type": "Feature",
  "properties": {
    "iso:country":"AU",
    "sg:address":"Huon Hwy",
    "sg:city":"Lower Longley",
    "sg:classifiers":[
        {
            "category":"Utilities",
            "subcategory":"Water",
            "type":"Services"
        }
    ],
    "sg:phone":"+61 3 6266 4293",
    "sg:postcode":"7150",
    "sg:province":"TAS",
    "sg:tags":[
        "cartage"
    ],
    "wof:name":"Temple L.V.R.",
    "wof:placetype":"venue"
},
  "geometry": {"coordinates":[147.17825317399999,-42.9758987427],"type":"Point"}
}