{
  "type": "Feature",
  "properties": {
    "iso:country":"AU",
    "sg:address":"13- 17 Princes Hwy",
    "sg:city":"Albion Park Rail",
    "sg:classifiers":[
        {
            "category":"Manufacturing",
            "subcategory":"Motor Vehicles & Parts",
            "type":"Manufacturing & Wholesale Goods"
        }
    ],
    "sg:phone":"+61 2 4256 3022",
    "sg:postcode":"2527",
    "sg:province":"NSW",
    "sg:tags":[
        "replacement"
    ],
    "wof:name":"Tory Toyota",
    "wof:placetype":"venue"
},
  "geometry": {"coordinates":[150.806549072,-34.5684776306],"type":"Point"}
}