{
  "type": "Feature",
  "properties": {
    "iso:country":"AU",
    "sg:address":"West Lvl 2/360 Collins",
    "sg:city":"Melbourne",
    "sg:classifiers":[
        {
            "category":"Banks & Credit Unions",
            "subcategory":"Bank",
            "type":"Services"
        }
    ],
    "sg:phone":"+61 3 9608 3327",
    "sg:postcode":"3000",
    "sg:province":"VIC",
    "wof:name":"Westpac Banking Corporation",
    "wof:placetype":"venue"
},
  "geometry": {"coordinates":[144.96234130900001,-37.8158302307],"type":"Point"}
}