{
  "type": "Feature",
  "properties": {
    "addr:full":"284 Wood St Preston VIC 3072",
    "addr:housenumber":"284",
    "addr:postcode":"3072",
    "addr:street":"Wood St",
    "iso:country":"AU",
    "sg:address":"284 Wood St",
    "sg:city":"Preston",
    "sg:classifiers":[
        {
            "category":"Real Estate",
            "subcategory":"Real Estate Operator",
            "type":"Services"
        }
    ],
    "sg:phone":"+61 3 9478 3778",
    "sg:postcode":"3072",
    "sg:province":"VIC",
    "sg:tags":[
        "concrete",
        "pumping"
    ],
    "wof:name":"A Cheap Concrete Pumping",
    "wof:placetype":"venue"
},
  "geometry": {"coordinates":[145.007080078,-37.7334899902],"type":"Point"}
}