{
  "type": "Feature",
  "properties": {
    "addr:full":"187 Gertude St Fitzroy VIC 3065",
    "addr:housenumber":"187",
    "addr:postcode":"3065",
    "addr:street":"Gertude St",
    "iso:country":"AU",
    "sg:address":"187 Gertude St",
    "sg:city":"Fitzroy",
    "sg:classifiers":[
        {
            "category":"Professional",
            "subcategory":"Art Services",
            "type":"Services"
        }
    ],
    "sg:phone":"+61 3 9416 2201",
    "sg:postcode":"3065",
    "sg:province":"VIC",
    "sg:tags":[
        "picture",
        "frame",
        "framing"
    ],
    "wof:name":"Artsmith Gallery",
    "wof:placetype":"venue"
},
  "geometry": {"coordinates":[144.98078918499999,-37.8059844971],"type":"Point"}
}