{
  "type": "Feature",
  "properties": {
    "iso:country":"AU",
    "sg:address":"214 McCrae St",
    "sg:city":"Bendigo",
    "sg:classifiers":[
        {
            "category":"Health Services",
            "subcategory":"Health Practitioner",
            "type":"Services"
        }
    ],
    "sg:phone":"+61 437 989 645",
    "sg:postcode":"3539",
    "sg:province":"VIC",
    "sg:tags":[
        "alternative"
    ],
    "wof:name":"Amethyst Alyernative Therapies",
    "wof:placetype":"venue"
},
  "geometry": {"coordinates":[144.287811,-36.753098],"type":"Point"}
}