{
  "type": "Feature",
  "properties": {
    "addr:full":"Corrigin Rd South Kumminin WA 6368",
    "addr:postcode":"6368",
    "addr:street":"Corrigin Rd",
    "iso:country":"AU",
    "sg:address":"Corrigin Rd",
    "sg:city":"South Kumminin",
    "sg:classifiers":[
        {
            "category":"Farming",
            "subcategory":"Farm",
            "type":"Manufacturing & Wholesale Goods"
        }
    ],
    "sg:phone":"+61 8 9065 3012",
    "sg:postcode":"6368",
    "sg:province":"WA",
    "sg:tags":[
        "farmer"
    ],
    "wof:name":"Smith S B & S L",
    "wof:placetype":"venue"
},
  "geometry": {"coordinates":[118.512497,-32.20628],"type":"Point"}
}