{
  "type": "Feature",
  "properties": {
    "iso:country":"AU",
    "sg:address":"4 Gunya St",
    "sg:city":"Regents Park",
    "sg:classifiers":[
        {
            "category":"Retail",
            "subcategory":"Auto Repair",
            "type":"Services"
        }
    ],
    "sg:phone":"+61 2 9644 5908",
    "sg:postcode":"2143",
    "sg:province":"NSW",
    "sg:tags":[
        "repairer",
        "motor",
        "engineer"
    ],
    "wof:name":"Boltorque Automotive",
    "wof:placetype":"venue"
},
  "geometry": {"coordinates":[151.02311706500001,-33.8860969543],"type":"Point"}
}