{
  "type": "Feature",
  "properties": {
    "iso:country":"AU",
    "sg:address":"536 Frankston-Dandenong Rd",
    "sg:city":"Carrum Downs",
    "sg:classifiers":[
        {
            "category":"Retail",
            "subcategory":"Storage",
            "type":"Services"
        }
    ],
    "sg:phone":"+61 3 9775 1320",
    "sg:postcode":"3201",
    "sg:province":"VIC",
    "wof:name":"Frankston Mini Storage",
    "wof:placetype":"venue"
},
  "geometry": {"coordinates":[145.16850299999999,-38.103691],"type":"Point"}
}