{
  "type": "Feature",
  "properties": {
    "iso:country":"AU",
    "sg:address":"15 Robinson Rd",
    "sg:city":"Old Noarlunga",
    "sg:classifiers":[
        {
            "category":"Professional",
            "subcategory":"Art Services",
            "type":"Services"
        }
    ],
    "sg:phone":"+61 8 8386 0770",
    "sg:postcode":"5168",
    "sg:province":"SA",
    "sg:tags":[
        "artist"
    ],
    "wof:name":"Houston Patrica M",
    "wof:placetype":"venue"
},
  "geometry": {"coordinates":[138.491989136,-35.1904983521],"type":"Point"}
}