{
  "type": "Feature",
  "properties": {
    "iso:country":"AU",
    "sg:address":"44 Cadell St",
    "sg:city":"Wentworth",
    "sg:classifiers":[
        {
            "category":"Real Estate",
            "subcategory":"Real Estate Services",
            "type":"Services"
        }
    ],
    "sg:phone":"+61 3 5027 3066",
    "sg:postcode":"2648",
    "sg:province":"NSW",
    "sg:tags":[
        "house",
        "hire",
        "boat"
    ],
    "wof:name":"Adelora House Boats",
    "wof:placetype":"venue"
},
  "geometry": {"coordinates":[141.91445899999999,-34.110695],"type":"Point"}
}