{
  "type": "Feature",
  "properties": {
    "addr:full":"31 Merve Turners La Old Junee NSW 2652",
    "addr:housenumber":"31",
    "addr:postcode":"2652",
    "addr:street":"Merve Turners La Old",
    "iso:country":"AU",
    "sg:address":"31 Merve Turners La",
    "sg:city":"Old Junee",
    "sg:classifiers":[
        {
            "category":"Farming",
            "subcategory":"Poultry Farm",
            "type":"Manufacturing & Wholesale Goods"
        }
    ],
    "sg:phone":"+61 2 6924 1477",
    "sg:postcode":"2652",
    "sg:province":"NSW",
    "sg:tags":[
        "farmer"
    ],
    "wof:name":"Junee Hatchery Pty Ltd",
    "wof:placetype":"venue"
},
  "geometry": {"coordinates":[147.18467712399999,-34.396774292],"type":"Point"}
}