{
  "type": "Feature",
  "properties": {
    "addr:full":"9- 13 Simmons St South Yarra VIC 3141",
    "addr:housenumber":"13",
    "addr:postcode":"3141",
    "addr:street":"9;Simmons St",
    "iso:country":"AU",
    "sg:address":"9- 13 Simmons St",
    "sg:city":"South Yarra",
    "sg:classifiers":[
        {
            "category":"Shopping",
            "subcategory":"Computers & Home Electronics",
            "type":"Retail Goods"
        }
    ],
    "sg:phone":"+61 3 9826 9977",
    "sg:postcode":"3141",
    "sg:province":"VIC",
    "sg:tags":[
        "equipment",
        "multimedia"
    ],
    "wof:name":"McPherson Unimedia",
    "wof:placetype":"venue"
},
  "geometry": {"coordinates":[144.99571227999999,-37.8447418213],"type":"Point"}
}