{
  "type": "Feature",
  "properties": {
    "addr:full":"31 Calais Crt D&#039;Aguilar QLD 4514",
    "addr:housenumber":"31",
    "addr:postcode":"4514",
    "addr:street":"Calais Crt;Aguilar",
    "iso:country":"AU",
    "sg:address":"31 Calais Crt",
    "sg:city":"D&#039;Aguilar",
    "sg:classifiers":[
        {
            "category":"Building & Trades",
            "subcategory":"Plumbing",
            "type":"Services"
        }
    ],
    "sg:phone":"+61 417 927 200",
    "sg:postcode":"4514",
    "sg:province":"QLD",
    "sg:tags":[
        "plumber",
        "gasfitters"
    ],
    "wof:name":"Curtis Plumbing",
    "wof:placetype":"venue"
},
  "geometry": {"coordinates":[152.80664100000001,-26.980225],"type":"Point"}
}