{
  "type": "Feature",
  "properties": {
    "iso:country":"AU",
    "sg:address":"Level 1, 220 Collins St",
    "sg:city":"Melbourne",
    "sg:classifiers":[
        {
            "category":"Health Services",
            "subcategory":"Dentist",
            "type":"Services"
        }
    ],
    "sg:phone":"+61 3 9650 4920",
    "sg:postcode":"3000",
    "sg:province":"VIC",
    "wof:name":"Yusupov A",
    "wof:placetype":"venue"
},
  "geometry": {"coordinates":[144.96635437,-37.815410614],"type":"Point"}
}