{
  "type": "Feature",
  "properties": {
    "addr:full":"Cnr Bona Vista & Korumburra Rds Warragul VIC 3820",
    "addr:postcode":"3820",
    "iso:country":"AU",
    "sg:address":"Cnr Bona Vista & Korumburra Rds",
    "sg:city":"Warragul",
    "sg:classifiers":[
        {
            "category":"Retail",
            "subcategory":"Funeral Services",
            "type":"Services"
        }
    ],
    "sg:phone":"+61 3 5623 2338",
    "sg:postcode":"3820",
    "sg:province":"VIC",
    "sg:tags":[
        "director"
    ],
    "wof:name":"Green Robert",
    "wof:placetype":"venue"
},
  "geometry": {"coordinates":[145.932098,-38.173306],"type":"Point"}
}