{
  "type": "Feature",
  "properties": {
    "addr:full":"7 Wain Ave Logan Central QLD 4114",
    "addr:housenumber":"7",
    "addr:postcode":"4114",
    "addr:street":"Wain Ave",
    "iso:country":"AU",
    "sg:address":"7 Wain Ave",
    "sg:city":"Logan Central",
    "sg:classifiers":[
        {
            "category":"Professional",
            "subcategory":"Employment Agencies",
            "type":"Services"
        }
    ],
    "sg:phone":"+61 7 3208 6088",
    "sg:postcode":"4114",
    "sg:province":"QLD",
    "sg:tags":[
        "broker",
        "custom"
    ],
    "wof:name":"Baldwins Customs Services Pty Ltd",
    "wof:placetype":"venue"
},
  "geometry": {"coordinates":[153.10044860799999,-27.6462306976],"type":"Point"}
}