{
  "type": "Feature",
  "properties": {
    "addr:full":"71A Como Pde Parkdale VIC 3195",
    "addr:housenumber":"71a",
    "addr:postcode":"3195",
    "addr:street":"Como Pde",
    "iso:country":"AU",
    "sg:address":"71A Como Pde",
    "sg:city":"Parkdale",
    "sg:classifiers":[
        {
            "category":"Professional",
            "subcategory":"Management & Consulting",
            "type":"Services"
        }
    ],
    "sg:phone":"+61 411 988 337",
    "sg:postcode":"3195",
    "sg:province":"VIC",
    "sg:tags":[
        "consultant",
        "energy"
    ],
    "wof:name":"Electrize",
    "wof:placetype":"venue"
},
  "geometry": {"coordinates":[145.07286071799999,-37.9895973206],"type":"Point"}
}