{
  "type": "Feature",
  "properties": {
    "addr:full":"37 King St Bungendore ACT 2621",
    "addr:housenumber":"37",
    "addr:postcode":"2621",
    "addr:street":"King St",
    "iso:country":"AU",
    "sg:address":"37 King St",
    "sg:city":"Bungendore",
    "sg:classifiers":[
        {
            "category":"Autos & Motor Vehicles",
            "subcategory":"Auto Supplies",
            "type":"Retail Goods"
        }
    ],
    "sg:phone":"+61 2 6238 0522",
    "sg:postcode":"2621",
    "sg:province":"ACT",
    "sg:tags":[
        "part",
        "cycles",
        "accessory"
    ],
    "wof:name":"Americar Body Shop",
    "wof:placetype":"venue"
},
  "geometry": {"coordinates":[149.44097900400001,-35.2621154785],"type":"Point"}
}