{
  "type": "Feature",
  "properties": {
    "addr:full":"27 Denison St Gloucester NSW 2422",
    "addr:housenumber":"27",
    "addr:postcode":"2422",
    "addr:street":"Denison St",
    "iso:country":"AU",
    "sg:address":"27 Denison St",
    "sg:city":"Gloucester",
    "sg:classifiers":[
        {
            "category":"Professional",
            "subcategory":"Computer Services",
            "type":"Services"
        }
    ],
    "sg:phone":"+61 2 6558 1408",
    "sg:postcode":"2422",
    "sg:province":"NSW",
    "sg:tags":[
        "information"
    ],
    "wof:name":"Visitor Information Center",
    "wof:placetype":"venue"
},
  "geometry": {"coordinates":[151.959656,-32.007313],"type":"Point"}
}