{
  "type": "Feature",
  "properties": {
    "addr:full":"881 Hampton St Brighton VIC 3186",
    "addr:housenumber":"881",
    "addr:postcode":"3186",
    "addr:street":"Hampton St",
    "iso:country":"AU",
    "sg:address":"881 Hampton St",
    "sg:city":"Brighton",
    "sg:classifiers":[
        {
            "category":"Health Services",
            "subcategory":"Chiropractor",
            "type":"Services"
        }
    ],
    "sg:phone":"+61 3 9592 5372",
    "sg:postcode":"3186",
    "sg:province":"VIC",
    "wof:name":"Hawtin Cori",
    "wof:placetype":"venue"
},
  "geometry": {"coordinates":[145.00747680699999,-37.9100837708],"type":"Point"}
}