{
  "type": "Feature",
  "properties": {
    "iso:country":"AU",
    "sg:address":"Shop 3, 197 Great Western Hwy",
    "sg:city":"Hazelbrook",
    "sg:classifiers":[
        {
            "category":"Health Services",
            "subcategory":"Doctor",
            "type":"Services"
        }
    ],
    "sg:phone":"+61 2 4758 8892",
    "sg:postcode":"2779",
    "sg:province":"NSW",
    "sg:tags":[
        "medical",
        "practitioner"
    ],
    "wof:name":"Barratt & Smith Pathology",
    "wof:placetype":"venue"
},
  "geometry": {"coordinates":[150.45184326200001,-33.7209815979],"type":"Point"}
}