{
  "type": "Feature",
  "properties": {
    "addr:full":"1 Cumberland St Eaglemont VIC 3084",
    "addr:housenumber":"1",
    "addr:postcode":"3084",
    "addr:street":"Cumberland St",
    "iso:country":"AU",
    "sg:address":"1 Cumberland St",
    "sg:city":"Eaglemont",
    "sg:classifiers":[
        {
            "category":"Health Services",
            "subcategory":"Doctor",
            "type":"Services"
        }
    ],
    "sg:phone":"+61 3 9457 1039",
    "sg:postcode":"3084",
    "sg:province":"VIC",
    "sg:tags":[
        "medical",
        "practitioner"
    ],
    "wof:name":"Jansz Aubrey W",
    "wof:placetype":"venue"
},
  "geometry": {"coordinates":[145.06687927199999,-37.7620506287],"type":"Point"}
}