{
  "type": "Feature",
  "properties": {
    "addr:full":"408 Punt Rd South Yarra VIC 3141",
    "addr:housenumber":"408",
    "addr:postcode":"3141",
    "addr:street":"Punt Rd",
    "iso:country":"AU",
    "sg:address":"408 Punt Rd",
    "sg:city":"South Yarra",
    "sg:classifiers":[
        {
            "category":"Retail",
            "subcategory":"Auto Rental",
            "type":"Services"
        }
    ],
    "sg:phone":"+61 3 9821 5455",
    "sg:postcode":"3141",
    "sg:province":"VIC",
    "sg:tags":[
        "car",
        "hire",
        "minibus"
    ],
    "wof:name":"Hertz",
    "wof:placetype":"venue"
},
  "geometry": {"coordinates":[144.986602783,-37.8387145996],"type":"Point"}
}