{
  "type": "Feature",
  "properties": {
    "addr:full":"31 Coolgardie St Sunnybank Hills QLD 4109",
    "addr:housenumber":"31",
    "addr:postcode":"4109",
    "addr:street":"Coolgardie St",
    "iso:country":"AU",
    "sg:address":"31 Coolgardie St",
    "sg:city":"Sunnybank Hills",
    "sg:classifiers":[
        {
            "category":"Building & Trades",
            "subcategory":"Construction",
            "type":"Services"
        }
    ],
    "sg:phone":"+61 7 3345 2636",
    "sg:postcode":"4109",
    "sg:province":"QLD",
    "sg:tags":[
        "contractor"
    ],
    "wof:name":"Stehbens I R",
    "wof:placetype":"venue"
},
  "geometry": {"coordinates":[153.04344177199999,-27.5842380524],"type":"Point"}
}