{
  "type": "Feature",
  "properties": {
    "iso:country":"AU",
    "sg:address":"Shp 138",
    "sg:city":"The Glen Shopng Cntr Glen Waverley",
    "sg:classifiers":[
        {
            "category":"Banks & Credit Unions",
            "subcategory":"Bank",
            "type":"Services"
        }
    ],
    "sg:phone":"+61 3 9886 1572",
    "sg:postcode":"3150",
    "sg:province":"VIC",
    "wof:name":"Thomas Cook Ltd",
    "wof:placetype":"venue"
},
  "geometry": {"coordinates":[145.16778564399999,-37.8688812256],"type":"Point"}
}