{
  "type": "Feature",
  "properties": {
    "addr:full":"438 Ipswich Rd Annerley QLD 4103",
    "addr:housenumber":"438",
    "addr:postcode":"4103",
    "addr:street":"Ipswich Rd",
    "iso:country":"AU",
    "sg:address":"438 Ipswich Rd",
    "sg:city":"Annerley",
    "sg:classifiers":[
        {
            "category":"Organizations",
            "subcategory":"Professional Association",
            "type":"Services"
        }
    ],
    "sg:phone":"+61 7 3841 5530",
    "sg:postcode":"4103",
    "sg:province":"QLD",
    "sg:tags":[
        "web",
        "internet"
    ],
    "sg:website":"http://www.epiweb.net.au",
    "wof:name":"Web Development Australia",
    "wof:placetype":"venue"
},
  "geometry": {"coordinates":[153.03355407699999,-27.508928299],"type":"Point"}
}