{
  "type": "Feature",
  "properties": {
    "addr:full":"163 William St St Albans VIC 3021",
    "addr:housenumber":"163",
    "addr:postcode":"3021",
    "addr:street":"William St",
    "iso:country":"AU",
    "sg:address":"163 William St",
    "sg:city":"St Albans",
    "sg:classifiers":[
        {
            "category":"Sports & Exercise",
            "subcategory":"Gym",
            "type":"Entertainment"
        }
    ],
    "sg:phone":"+61 402 945 724",
    "sg:postcode":"3021",
    "sg:province":"VIC",
    "sg:tags":[
        "personal",
        "trainer",
        "fitness"
    ],
    "wof:name":"New Reflection Personal Training",
    "wof:placetype":"venue"
},
  "geometry": {"coordinates":[144.80394000000001,-37.73616],"type":"Point"}
}