{
  "type": "Feature",
  "properties": {
    "iso:country":"AU",
    "sg:address":"92 Bray St",
    "sg:city":"Coffs Harbour",
    "sg:classifiers":[
        {
            "category":"Social Services",
            "type":"Services"
        }
    ],
    "sg:phone":"+61 2 6651 2600",
    "sg:postcode":"2450",
    "sg:province":"NSW",
    "sg:tags":[
        "disabled",
        "person",
        "equipment"
    ],
    "wof:name":"Hales Orthotic Services",
    "wof:placetype":"venue"
},
  "geometry": {"coordinates":[153.11604299999999,-30.281874],"type":"Point"}
}