{
  "type": "Feature",
  "properties": {
    "addr:full":"28 Green St Thomastown VIC 3074",
    "addr:housenumber":"28",
    "addr:postcode":"3074",
    "addr:street":"Green St",
    "iso:country":"AU",
    "sg:address":"28 Green St",
    "sg:city":"Thomastown",
    "sg:classifiers":[
        {
            "category":"Wholesale",
            "subcategory":"Furniture",
            "type":"Manufacturing & Wholesale Goods"
        }
    ],
    "sg:phone":"+61 3 9465 8999",
    "sg:postcode":"3074",
    "sg:province":"VIC",
    "sg:tags":[
        "wholesaler",
        "mfrs"
    ],
    "wof:name":"Emmanuel International Pty Ltd",
    "wof:placetype":"venue"
},
  "geometry": {"coordinates":[145.03822326700001,-37.6913948059],"type":"Point"}
}