{
  "type": "Feature",
  "properties": {
    "iso:country":"AU",
    "sg:address":"18 Dayman St",
    "sg:city":"Urangan",
    "sg:classifiers":[
        {
            "category":"Fast Food",
            "type":"Food & Drink"
        }
    ],
    "sg:phone":"+61 7 4128 9270",
    "sg:postcode":"4655",
    "sg:province":"QLD",
    "sg:tags":[
        "away",
        "take"
    ],
    "wof:name":"Dayman General Store",
    "wof:placetype":"venue"
},
  "geometry": {"coordinates":[152.905914,-25.288963],"type":"Point"}
}