{
  "type": "Feature",
  "properties": {
    "addr:full":"45 Bryant St Padstow NSW 2211",
    "addr:housenumber":"45",
    "addr:postcode":"2211",
    "addr:street":"Bryant St",
    "iso:country":"AU",
    "sg:address":"45 Bryant St",
    "sg:city":"Padstow",
    "sg:classifiers":[
        {
            "category":"Retail",
            "subcategory":"Auto Repair",
            "type":"Services"
        }
    ],
    "sg:phone":"+61 2 9792 2055",
    "sg:postcode":"2211",
    "sg:province":"NSW",
    "sg:tags":[
        "repairer",
        "motor",
        "engineer"
    ],
    "wof:name":"Pedders Suspension",
    "wof:placetype":"venue"
},
  "geometry": {"coordinates":[151.033737,-33.941219],"type":"Point"}
}