{
  "type": "Feature",
  "properties": {
    "iso:country":"AU",
    "sg:address":"Lot 21, Bundaleer Crs",
    "sg:city":"Bensville",
    "sg:classifiers":[
        {
            "category":"Professional",
            "subcategory":"Art Services",
            "type":"Services"
        }
    ],
    "sg:phone":"+61 2 4368 2100",
    "sg:postcode":"2251",
    "sg:province":"NSW",
    "sg:tags":[
        "picture",
        "frame",
        "framing"
    ],
    "wof:name":"ANS Artframes",
    "wof:placetype":"venue"
},
  "geometry": {"coordinates":[151.39050293,-33.500541687],"type":"Point"}
}