{
  "type": "Feature",
  "properties": {
    "iso:country":"AU",
    "sg:address":"Unit21/ 53 Lorraine St",
    "sg:city":"Peakhurst",
    "sg:classifiers":[
        {
            "category":"Wholesale",
            "subcategory":"Machinery & Supplies",
            "type":"Manufacturing & Wholesale Goods"
        }
    ],
    "sg:phone":"+61 1300 131 516",
    "sg:postcode":"2210",
    "sg:province":"NSW",
    "sg:tags":[
        "equipment",
        "laboratory"
    ],
    "wof:name":"Palintest Australia",
    "wof:placetype":"venue"
},
  "geometry": {"coordinates":[151.06016500000001,-33.967651],"type":"Point"}
}