{
  "type": "Feature",
  "properties": {
    "iso:country":"AU",
    "sg:address":"PO Box 785",
    "sg:city":"Riverwood",
    "sg:classifiers":[
        {
            "category":"Professional",
            "subcategory":"Accounting & Tax Preparation",
            "type":"Services"
        }
    ],
    "sg:phone":"+61 1300 650 448",
    "sg:postcode":"2210",
    "sg:province":"NSW",
    "sg:tags":[
        "bookkeeping"
    ],
    "wof:name":"Busy Bookkeeping Morley",
    "wof:placetype":"venue"
},
  "geometry": {"coordinates":[151.051666,-33.953701],"type":"Point"}
}