{
  "type": "Feature",
  "properties": {
    "addr:full":"14 Cromer Rd Beaumaris VIC 3193",
    "addr:housenumber":"14",
    "addr:postcode":"3193",
    "addr:street":"Cromer Rd",
    "iso:country":"AU",
    "sg:address":"14 Cromer Rd",
    "sg:city":"Beaumaris",
    "sg:classifiers":[
        {
            "category":"Organizations",
            "subcategory":"Professional Association",
            "type":"Services"
        }
    ],
    "sg:phone":"+61 3 9583 4174",
    "sg:postcode":"3193",
    "sg:province":"VIC",
    "sg:tags":[
        "web",
        "internet"
    ],
    "wof:name":"Realtime Strategy",
    "wof:placetype":"venue"
},
  "geometry": {"coordinates":[145.044555664,-37.9879341125],"type":"Point"}
}