{
  "type": "Feature",
  "properties": {
    "addr:full":"5/ 144 Stirling Hwy Nedlands WA 6009",
    "addr:housenumber":"/ 144",
    "addr:postcode":"6009",
    "addr:street":"Stirling Hwy",
    "iso:country":"AU",
    "sg:address":"5/ 144 Stirling Hwy",
    "sg:city":"Nedlands",
    "sg:classifiers":[
        {
            "category":"Shopping",
            "subcategory":"Computers & Home Electronics",
            "type":"Retail Goods"
        }
    ],
    "sg:phone":"+61 8 9386 2777",
    "sg:postcode":"6009",
    "sg:province":"WA",
    "sg:tags":[
        "hardware",
        "equipment"
    ],
    "wof:name":"That Computer Shop",
    "wof:placetype":"venue"
},
  "geometry": {"coordinates":[115.79628,-31.98053],"type":"Point"}
}