{
  "type": "Feature",
  "properties": {
    "addr:full":"PO Box 2056 Forest Hill VIC 3131",
    "addr:postcode":"3131",
    "addr:street":"Hill",
    "iso:country":"AU",
    "sg:address":"PO Box 2056",
    "sg:city":"Forest Hill",
    "sg:classifiers":[
        {
            "category":"Health Services",
            "subcategory":"Health Practitioner",
            "type":"Services"
        }
    ],
    "sg:phone":"+61 3 9802 7248",
    "sg:postcode":"3131",
    "sg:province":"VIC",
    "sg:tags":[
        "hypnotherapy"
    ],
    "wof:name":"Essentially Organised",
    "wof:placetype":"venue"
},
  "geometry": {"coordinates":[145.17112731899999,-37.8427810669],"type":"Point"}
}