{
  "type": "Feature",
  "properties": {
    "addr:full":"60 Byng St Orange NSW 2800",
    "addr:housenumber":"60",
    "addr:postcode":"2800",
    "addr:street":"Byng St",
    "iso:country":"AU",
    "sg:address":"60 Byng St",
    "sg:city":"Orange",
    "sg:classifiers":[
        {
            "category":"Professional",
            "subcategory":"Management & Consulting",
            "type":"Services"
        }
    ],
    "sg:phone":"+61 2 6362 9078",
    "sg:postcode":"2800",
    "sg:province":"NSW",
    "sg:tags":[
        "consultant"
    ],
    "wof:name":"Galbally Pty Ltd",
    "wof:placetype":"venue"
},
  "geometry": {"coordinates":[149.09342956500001,-33.2806167603],"type":"Point"}
}