{
  "type": "Feature",
  "properties": {
    "iso:country":"AU",
    "sg:address":"103 Railway St",
    "sg:city":"Rockdale",
    "sg:classifiers":[
        {
            "category":"Shopping",
            "subcategory":"Clothing, Apparel, & Fashions",
            "type":"Retail Goods"
        }
    ],
    "sg:phone":"+61 2 9567 4877",
    "sg:postcode":"2216",
    "sg:province":"NSW",
    "sg:tags":[
        "lady",
        "wear"
    ],
    "wof:name":"Jazz For Men",
    "wof:placetype":"venue"
},
  "geometry": {"coordinates":[151.13580300000001,-33.952572],"type":"Point"}
}