{
  "type": "Feature",
  "properties": {
    "addr:full":"PO Box 149 Drouin VIC 3818",
    "addr:postcode":"3818",
    "iso:country":"AU",
    "sg:address":"PO Box 149",
    "sg:city":"Drouin",
    "sg:classifiers":[
        {
            "category":"Professional",
            "subcategory":"Computer Services",
            "type":"Services"
        }
    ],
    "sg:phone":"+61 3 5625 5200",
    "sg:postcode":"3818",
    "sg:province":"VIC",
    "sg:tags":[
        "package",
        "software"
    ],
    "wof:name":"CAD CAM - STS",
    "wof:placetype":"venue"
},
  "geometry": {"coordinates":[145.858124,-38.136688],"type":"Point"}
}