{
  "type": "Feature",
  "properties": {
    "iso:country":"AU",
    "sg:address":"PO Box 750",
    "sg:city":"Labrador",
    "sg:classifiers":[
        {
            "category":"Professional",
            "subcategory":"Employment Agencies",
            "type":"Services"
        }
    ],
    "sg:phone":"+61 1300 133 442",
    "sg:postcode":"4215",
    "sg:province":"QLD",
    "sg:tags":[
        "provider",
        "internet"
    ],
    "wof:name":"GCweb.com.au",
    "wof:placetype":"venue"
},
  "geometry": {"coordinates":[153.40838623100001,-27.945930481],"type":"Point"}
}