{
  "type": "Feature",
  "properties": {
    "addr:full":"34 First Settlement Drv Sorrento VIC 3943",
    "addr:housenumber":"34",
    "addr:postcode":"3943",
    "addr:street":"First Settlement Drv",
    "iso:country":"AU",
    "sg:address":"34 First Settlement Drv",
    "sg:city":"Sorrento",
    "sg:classifiers":[
        {
            "category":"Social Services",
            "subcategory":"Retirement Home",
            "type":"Services"
        }
    ],
    "sg:phone":"+61 3 5984 5600",
    "sg:postcode":"3943",
    "sg:province":"VIC",
    "sg:tags":[
        "environmental",
        "consultant",
        "pollution"
    ],
    "wof:name":"Integrated Environmental Systems",
    "wof:placetype":"venue"
},
  "geometry": {"coordinates":[144.75315856899999,-38.3528556824],"type":"Point"}
}