{
  "type": "Feature",
  "properties": {
    "addr:full":"Lot 2 Palmer St Romsey VIC 3434",
    "addr:postcode":"3434",
    "addr:street":"Palmer St",
    "iso:country":"AU",
    "sg:address":"Lot 2 Palmer St",
    "sg:city":"Romsey",
    "sg:classifiers":[
        {
            "category":"Professional",
            "subcategory":"Art Services",
            "type":"Services"
        }
    ],
    "sg:phone":"+61 3 5429 5309",
    "sg:postcode":"3434",
    "sg:province":"VIC",
    "sg:tags":[
        "picture",
        "frame",
        "framing"
    ],
    "wof:name":"Central Victoria Framing",
    "wof:placetype":"venue"
},
  "geometry": {"coordinates":[144.747650147,-37.3451271057],"type":"Point"}
}