{
  "type": "Feature",
  "properties": {
    "iso:country":"AU",
    "sg:address":"152 Ashmore Rd",
    "sg:city":"Benowa",
    "sg:classifiers":[
        {
            "category":"Health Services",
            "subcategory":"Health Practitioner",
            "type":"Services"
        }
    ],
    "sg:phone":"+61 7 5597 5711",
    "sg:postcode":"4217",
    "sg:province":"QLD",
    "sg:tags":[
        "osteopath"
    ],
    "wof:name":"Bispham Jonathan",
    "wof:placetype":"venue"
},
  "geometry": {"coordinates":[153.39651489299999,-28.0092983246],"type":"Point"}
}