{
  "type": "Feature",
  "properties": {
    "addr:full":"1 Whipple St Balcatta WA 6021",
    "addr:housenumber":"1",
    "addr:postcode":"6021",
    "addr:street":"Whipple St",
    "iso:country":"AU",
    "sg:address":"1 Whipple St",
    "sg:city":"Balcatta",
    "sg:classifiers":[
        {
            "category":"Professional",
            "subcategory":"Engineering",
            "type":"Services"
        }
    ],
    "sg:phone":"+61 8 9441 2311",
    "sg:postcode":"6021",
    "sg:province":"WA",
    "sg:tags":[
        "consulting",
        "engineer"
    ],
    "wof:name":"Orbital Consulting",
    "wof:placetype":"venue"
},
  "geometry": {"coordinates":[115.80573272700001,-31.8627643585],"type":"Point"}
}