{
  "type": "Feature",
  "properties": {
    "addr:full":"Shop 1, 133 Longeville Rd Lane Cove NSW 2066",
    "addr:housenumber":"shop 1",
    "addr:postcode":"133;2066",
    "addr:street":"Longeville Rd",
    "iso:country":"AU",
    "sg:address":"Shop 1, 133 Longeville Rd",
    "sg:city":"Lane Cove",
    "sg:classifiers":[
        {
            "category":"Ice Cream",
            "type":"Food & Drink"
        }
    ],
    "sg:phone":"+61 2 9420 2431",
    "sg:postcode":"2066",
    "sg:province":"NSW",
    "sg:tags":[
        "retail"
    ],
    "wof:name":"Baskin 31 Robbins Ice Cream & Yogurt",
    "wof:placetype":"venue"
},
  "geometry": {"coordinates":[151.16981506400001,-33.8150062561],"type":"Point"}
}