{
  "type": "Feature",
  "properties": {
    "addr:full":"250 Hannan St Kalgoorlie WA 6430",
    "addr:housenumber":"250",
    "addr:postcode":"6430",
    "addr:street":"Hannan St",
    "iso:country":"AU",
    "sg:address":"250 Hannan St",
    "sg:city":"Kalgoorlie",
    "sg:classifiers":[
        {
            "category":"Health Services",
            "subcategory":"Optometrist",
            "type":"Services"
        }
    ],
    "sg:phone":"+61 8 9022 7566",
    "sg:postcode":"6430",
    "sg:province":"WA",
    "wof:name":"GMF Optical Centre",
    "wof:placetype":"venue"
},
  "geometry": {"coordinates":[121.469413757,-30.7500915527],"type":"Point"}
}