{
  "type": "Feature",
  "properties": {
    "addr:full":"1/ 356 Bilsen Rd Geebung QLD 4034",
    "addr:housenumber":"/ 356",
    "addr:postcode":"4034",
    "addr:street":"Bilsen Rd",
    "iso:country":"AU",
    "sg:address":"1/ 356 Bilsen Rd",
    "sg:city":"Geebung",
    "sg:classifiers":[
        {
            "category":"Retail",
            "subcategory":"Auto Repair",
            "type":"Services"
        }
    ],
    "sg:phone":"+61 7 3865 3062",
    "sg:postcode":"4034",
    "sg:province":"QLD",
    "sg:tags":[
        "repairer",
        "motor",
        "engineer"
    ],
    "wof:name":"N B S Services Pty Ltd",
    "wof:placetype":"venue"
},
  "geometry": {"coordinates":[153.05520629899999,-27.3747177124],"type":"Point"}
}