{
  "type": "Feature",
  "properties": {
    "addr:full":"Pacific Hwy Lake Munmorah NSW 2259",
    "addr:postcode":"2259",
    "addr:street":"Pacific Hwy",
    "iso:country":"AU",
    "sg:address":"Pacific Hwy",
    "sg:city":"Lake Munmorah",
    "sg:classifiers":[
        {
            "category":"Arena",
            "subcategory":"Sports Club",
            "type":"Entertainment"
        }
    ],
    "sg:phone":"+61 2 4358 1563",
    "sg:postcode":"2259",
    "sg:province":"NSW",
    "sg:tags":[
        "league",
        "rugby"
    ],
    "wof:name":"Northern Lakes Rugby League Football Club",
    "wof:placetype":"venue"
},
  "geometry": {"coordinates":[151.579711914,-33.189037323],"type":"Point"}
}