{
  "type": "Feature",
  "properties": {
    "iso:country":"AU",
    "sg:address":"Farm Rd",
    "sg:city":"Werribee",
    "sg:classifiers":[
        {
            "category":"Museum",
            "type":"Entertainment"
        }
    ],
    "sg:phone":"+61 3 9731 1263",
    "sg:postcode":"3030",
    "sg:province":"VIC",
    "wof:name":"B 24 Liberator Memorial Restoration Fund",
    "wof:placetype":"venue"
},
  "geometry": {"coordinates":[144.648483,-37.909172],"type":"Point"}
}