{
  "type": "Feature",
  "properties": {
    "iso:country":"AU",
    "sg:address":"152- 154 Victoria St",
    "sg:city":"North Geelong",
    "sg:classifiers":[
        {
            "category":"Home & Garden",
            "subcategory":"Building Materials",
            "type":"Retail Goods"
        }
    ],
    "sg:phone":"+61 3 5278 7044",
    "sg:postcode":"3215",
    "sg:province":"VIC",
    "sg:tags":[
        "roofing"
    ],
    "wof:name":"JH Stephenson & Son P/L",
    "wof:placetype":"venue"
},
  "geometry": {"coordinates":[144.344116211,-38.1222038269],"type":"Point"}
}