{
  "type": "Feature",
  "properties": {
    "iso:country":"AU",
    "sg:address":"157 Ryrie St",
    "sg:city":"Geelong",
    "sg:classifiers":[
        {
            "category":"Shopping",
            "subcategory":"Clothing, Apparel, & Fashions",
            "type":"Retail Goods"
        }
    ],
    "sg:phone":"+61 3 5229 9601",
    "sg:postcode":"3220",
    "sg:province":"VIC",
    "sg:tags":[
        "uniform"
    ],
    "wof:name":"NNT Uniforms",
    "wof:placetype":"venue"
},
  "geometry": {"coordinates":[144.36021400000001,-38.149231],"type":"Point"}
}