{
  "type": "Feature",
  "properties": {
    "addr:full":"57 Polton Ave Rosebud VIC 3939",
    "addr:housenumber":"57",
    "addr:postcode":"3939",
    "addr:street":"Polton Ave",
    "iso:country":"AU",
    "sg:address":"57 Polton Ave",
    "sg:city":"Rosebud",
    "sg:classifiers":[
        {
            "category":"Utilities",
            "subcategory":"Refuse",
            "type":"Services"
        }
    ],
    "sg:phone":"+61 3 5988 6242",
    "sg:postcode":"3939",
    "sg:province":"VIC",
    "sg:tags":[
        "disposal",
        "reduction",
        "waste"
    ],
    "wof:name":"Shoreline Bin Hire",
    "wof:placetype":"venue"
},
  "geometry": {"coordinates":[144.91030883799999,-38.3658676147],"type":"Point"}
}