{
  "type": "Feature",
  "properties": {
    "iso:country":"AU",
    "sg:address":"216 William St",
    "sg:city":"Bathurst",
    "sg:classifiers":[
        {
            "category":"Food & Beverages",
            "subcategory":"Groceries & Convenience Stores",
            "type":"Retail Goods"
        }
    ],
    "sg:phone":"+61 2 6332 2363",
    "sg:postcode":"2795",
    "sg:province":"NSW",
    "wof:name":"Bathurst Corner Store",
    "wof:placetype":"venue"
},
  "geometry": {"coordinates":[149.57411193900001,-33.4227638245],"type":"Point"}
}