{
  "type": "Feature",
  "properties": {
    "addr:full":"5 Amy Crt Pittsworth QLD 4356",
    "addr:housenumber":"5",
    "addr:postcode":"4356",
    "addr:street":"Amy Crt",
    "iso:country":"AU",
    "sg:address":"5 Amy Crt",
    "sg:city":"Pittsworth",
    "sg:classifiers":[
        {
            "category":"Professional",
            "subcategory":"Business Services",
            "type":"Services"
        }
    ],
    "sg:phone":"+61 7 4637 2677",
    "sg:postcode":"4356",
    "sg:province":"QLD",
    "sg:tags":[
        "consultant",
        "promoter",
        "entertainment"
    ],
    "wof:name":"Steer Records Pty Ltd",
    "wof:placetype":"venue"
},
  "geometry": {"coordinates":[151.63258400000001,-27.70414],"type":"Point"}
}