{
  "type": "Feature",
  "properties": {
    "iso:country":"AU",
    "sg:address":"2 Hillside Pde",
    "sg:city":"Glen Iris",
    "sg:classifiers":[
        {
            "category":"Health Services",
            "subcategory":"Health Practitioner",
            "type":"Services"
        }
    ],
    "sg:phone":"+61 3 9889 6767",
    "sg:postcode":"3146",
    "sg:province":"VIC",
    "sg:tags":[
        "osteopath"
    ],
    "wof:name":"Mistus Penne Dr",
    "wof:placetype":"venue"
},
  "geometry": {"coordinates":[145.064254761,-37.8469963074],"type":"Point"}
}