{
  "type": "Feature",
  "properties": {
    "addr:full":"5- 11 Bradley St Kyabram VIC 3620",
    "addr:housenumber":"11",
    "addr:postcode":"3620",
    "addr:street":"5;Bradley St",
    "iso:country":"AU",
    "sg:address":"5- 11 Bradley St",
    "sg:city":"Kyabram",
    "sg:classifiers":[
        {
            "category":"Autos & Motor Vehicles",
            "subcategory":"Automobile Sales",
            "type":"Retail Goods"
        }
    ],
    "sg:phone":"+61 3 5852 2533",
    "sg:postcode":"3620",
    "sg:province":"VIC",
    "sg:tags":[
        "car",
        "used"
    ],
    "wof:name":"Jayell Ford",
    "wof:placetype":"venue"
},
  "geometry": {"coordinates":[145.04524230999999,-36.3123092651],"type":"Point"}
}