{
  "type": "Feature",
  "properties": {
    "addr:full":"132- 134 Fosters Rd Oakden SA 5086",
    "addr:housenumber":"134",
    "addr:postcode":"5086",
    "addr:street":"132;Fosters Rd",
    "iso:country":"AU",
    "sg:address":"132- 134 Fosters Rd",
    "sg:city":"Oakden",
    "sg:classifiers":[
        {
            "category":"Health Services",
            "subcategory":"Doctor",
            "type":"Services"
        }
    ],
    "sg:phone":"+61 8 8266 7788",
    "sg:postcode":"5086",
    "sg:province":"SA",
    "sg:tags":[
        "medical",
        "practitioner"
    ],
    "wof:name":"Oakden Medical Centre",
    "wof:placetype":"venue"
},
  "geometry": {"coordinates":[138.636474609,-34.859954834],"type":"Point"}
}