{
  "type": "Feature",
  "properties": {
    "addr:full":"6 Carl Pl Kings Langley NSW 2147",
    "addr:housenumber":"6",
    "addr:postcode":"2147",
    "addr:street":"Carl Pl",
    "iso:country":"AU",
    "sg:address":"6 Carl Pl",
    "sg:city":"Kings Langley",
    "sg:classifiers":[
        {
            "category":"Building & Trades",
            "subcategory":"Landscaping Services",
            "type":"Services"
        }
    ],
    "sg:phone":"+61 418 414 086",
    "sg:postcode":"2147",
    "sg:province":"NSW",
    "sg:tags":[
        "designer",
        "landscape",
        "contractor"
    ],
    "wof:name":"Cumberland Lawn Care",
    "wof:placetype":"venue"
},
  "geometry": {"coordinates":[150.948852539,-33.7596511841],"type":"Point"}
}