{
  "type": "Feature",
  "properties": {
    "addr:full":"1318 Pittwater Rd Narrabeen NSW 2101",
    "addr:housenumber":"1318",
    "addr:postcode":"2101",
    "addr:street":"Pittwater Rd",
    "iso:country":"AU",
    "sg:address":"1318 Pittwater Rd",
    "sg:city":"Narrabeen",
    "sg:classifiers":[
        {
            "category":"Personal",
            "subcategory":"Beauty Salon",
            "type":"Services"
        }
    ],
    "sg:phone":"+61 2 9913 8799",
    "sg:postcode":"2101",
    "sg:province":"NSW",
    "sg:tags":[
        "hairdresser"
    ],
    "wof:name":"Lock&#039;n&#039;Roll Hairdressing",
    "wof:placetype":"venue"
},
  "geometry": {"coordinates":[151.29718,-33.715328],"type":"Point"}
}