{
  "type": "Feature",
  "properties": {
    "addr:full":"10 Royton St Rosanna VIC 3084",
    "addr:housenumber":"10",
    "addr:postcode":"3084",
    "addr:street":"Royton St",
    "iso:country":"AU",
    "sg:address":"10 Royton St",
    "sg:city":"Rosanna",
    "sg:classifiers":[
        {
            "category":"Education",
            "subcategory":"Special Training",
            "type":"Public Place"
        }
    ],
    "sg:phone":"+61 418 174 469",
    "sg:postcode":"3084",
    "sg:province":"VIC",
    "sg:tags":[
        "wine"
    ],
    "wof:name":"Vernon Pigdon",
    "wof:placetype":"venue"
},
  "geometry": {"coordinates":[145.09182739299999,-37.7403945923],"type":"Point"}
}