{
  "type": "Feature",
  "properties": {
    "addr:full":"25 Jarrett St Gosford North NSW 2250",
    "addr:housenumber":"25",
    "addr:postcode":"2250",
    "addr:street":"Jarrett St",
    "iso:country":"AU",
    "sg:address":"25 Jarrett St",
    "sg:city":"Gosford North",
    "sg:classifiers":[
        {
            "category":"Health Services",
            "subcategory":"Doctor",
            "type":"Services"
        }
    ],
    "sg:phone":"+61 2 4323 3060",
    "sg:postcode":"2250",
    "sg:province":"NSW",
    "sg:tags":[
        "medical",
        "practitioner"
    ],
    "wof:name":"Woods J L",
    "wof:placetype":"venue"
},
  "geometry": {"coordinates":[151.35118102999999,-33.4180107117],"type":"Point"}
}