{
  "type": "Feature",
  "properties": {
    "addr:full":"35 Chilcomb Drv Hackham West SA 5163",
    "addr:housenumber":"35",
    "addr:postcode":"5163",
    "addr:street":"Chilcomb Drv",
    "iso:country":"AU",
    "sg:address":"35 Chilcomb Drv",
    "sg:city":"Hackham West",
    "sg:classifiers":[
        {
            "category":"Home & Garden",
            "subcategory":"Building Materials",
            "type":"Retail Goods"
        }
    ],
    "sg:phone":"+61 8 8382 9226",
    "sg:postcode":"5163",
    "sg:province":"SA",
    "sg:tags":[
        "lawn",
        "cutting",
        "maintenance"
    ],
    "wof:name":"Ryan's Home & Garden Service",
    "wof:placetype":"venue"
},
  "geometry": {"coordinates":[138.52296447800001,-35.1478881836],"type":"Point"}
}