{
  "type": "Feature",
  "properties": {
    "iso:country":"AU",
    "sg:address":"37 Currumbin Creek Rd",
    "sg:city":"Currumbin",
    "sg:classifiers":[
        {
            "category":"Building & Trades",
            "subcategory":"Equipment Rental",
            "type":"Services"
        }
    ],
    "sg:phone":"+61 7 5525 7700",
    "sg:postcode":"4223",
    "sg:province":"QLD",
    "sg:tags":[
        "fitness"
    ],
    "wof:name":"Butlers Gym Equipment",
    "wof:placetype":"venue"
},
  "geometry": {"coordinates":[153.472488403,-28.1428089142],"type":"Point"}
}