{
  "type": "Feature",
  "properties": {
    "addr:full":"19 Noarlunga Crs Bonython ACT 2905",
    "addr:housenumber":"19",
    "addr:postcode":"2905",
    "addr:street":"Noarlunga Crs",
    "iso:country":"AU",
    "sg:address":"19 Noarlunga Crs",
    "sg:city":"Bonython",
    "sg:classifiers":[
        {
            "category":"Manufacturing",
            "subcategory":"Glass & Minerals",
            "type":"Manufacturing & Wholesale Goods"
        }
    ],
    "sg:phone":"+61 2 6293 2332",
    "sg:postcode":"2905",
    "sg:province":"ACT",
    "sg:tags":[
        "stained"
    ],
    "wof:name":"A Drop Of Glass",
    "wof:placetype":"venue"
},
  "geometry": {"coordinates":[149.080200195,-35.4309082031],"type":"Point"}
}