{
  "type": "Feature",
  "properties": {
    "addr:full":"211 South Rd Ridleyton SA 5008",
    "addr:housenumber":"211",
    "addr:postcode":"5008",
    "addr:street":"South Rd",
    "iso:country":"AU",
    "sg:address":"211 South Rd",
    "sg:city":"Ridleyton",
    "sg:classifiers":[
        {
            "category":"Retail",
            "subcategory":"Auto Repair",
            "type":"Services"
        }
    ],
    "sg:phone":"+61 8 8346 2507",
    "sg:postcode":"5008",
    "sg:province":"SA",
    "sg:tags":[
        "repairer",
        "motor",
        "engineer"
    ],
    "wof:name":"Croydon Motors",
    "wof:placetype":"venue"
},
  "geometry": {"coordinates":[138.56950399999999,-34.890945],"type":"Point"}
}