{
  "type": "Feature",
  "properties": {
    "iso:country":"AU",
    "sg:address":"PO Box 290",
    "sg:city":"Ormond",
    "sg:classifiers":[
        {
            "category":"Building & Trades",
            "subcategory":"Landscaping Services",
            "type":"Services"
        }
    ],
    "sg:phone":"+61 408 553 515",
    "sg:postcode":"3204",
    "sg:province":"VIC",
    "sg:tags":[
        "designer",
        "landscape",
        "contractor"
    ],
    "wof:name":"Wild Seeds Tranquil Garden",
    "wof:placetype":"venue"
},
  "geometry": {"coordinates":[145.040344,-37.90398],"type":"Point"}
}