{
  "type": "Feature",
  "properties": {
    "addr:full":"PO Box 185 Narangba QLD 4504",
    "addr:postcode":"4504",
    "iso:country":"AU",
    "sg:address":"PO Box 185",
    "sg:city":"Narangba",
    "sg:classifiers":[
        {
            "category":"Retail",
            "subcategory":"Auto Repair",
            "type":"Services"
        }
    ],
    "sg:phone":"+61 412 573 341",
    "sg:postcode":"4504",
    "sg:province":"QLD",
    "sg:tags":[
        "automotive",
        "air conditioning"
    ],
    "wof:name":"Air 2 U",
    "wof:placetype":"venue"
},
  "geometry": {"coordinates":[152.92854309099999,-27.1869602203],"type":"Point"}
}