{
  "type": "Feature",
  "properties": {
    "addr:full":"10 Malcolm Crt Kealba VIC 3021",
    "addr:housenumber":"10",
    "addr:postcode":"3021",
    "addr:street":"Malcolm Crt",
    "iso:country":"AU",
    "sg:address":"10 Malcolm Crt",
    "sg:city":"Kealba",
    "sg:classifiers":[
        {
            "category":"Building & Trades",
            "subcategory":"Construction",
            "type":"Services"
        }
    ],
    "sg:phone":"+61 3 9310 7608",
    "sg:postcode":"3021",
    "sg:province":"VIC",
    "sg:tags":[
        "window",
        "aluminium"
    ],
    "wof:name":"Premium Windows",
    "wof:placetype":"venue"
},
  "geometry": {"coordinates":[144.826965,-37.740677],"type":"Point"}
}