{
  "type": "Feature",
  "properties": {
    "iso:country":"AU",
    "sg:address":"290 Galston Rd",
    "sg:city":"Galston",
    "sg:classifiers":[
        {
            "category":"Building & Trades",
            "subcategory":"Construction",
            "type":"Services"
        }
    ],
    "sg:phone":"+61 419 439 145",
    "sg:postcode":"2159",
    "sg:province":"NSW",
    "sg:tags":[
        "stonework",
        "stone",
        "mason"
    ],
    "wof:name":"Wilson Stonemasonry Pty Ltd",
    "wof:placetype":"venue"
},
  "geometry": {"coordinates":[151.05911254899999,-33.6529502869],"type":"Point"}
}