{
  "type": "Feature",
  "properties": {
    "addr:full":"3/ 30 Jarrad St Cottesloe WA 6011",
    "addr:housenumber":"/ 30",
    "addr:postcode":"6011",
    "addr:street":"Jarrad St",
    "iso:country":"AU",
    "sg:address":"3/ 30 Jarrad St",
    "sg:city":"Cottesloe",
    "sg:classifiers":[
        {
            "category":"Shopping",
            "subcategory":"Shoes",
            "type":"Retail Goods"
        }
    ],
    "sg:phone":"+61 8 9383 1888",
    "sg:postcode":"6011",
    "sg:province":"WA",
    "sg:tags":[
        "footwear"
    ],
    "wof:name":"Instyle Shoes & Accessories",
    "wof:placetype":"venue"
},
  "geometry": {"coordinates":[115.761062622,-31.9988803864],"type":"Point"}
}