{
  "type": "Feature",
  "properties": {
    "iso:country":"AU",
    "sg:address":"20 Cranes Rd",
    "sg:city":"Allens Rivulet",
    "sg:classifiers":[
        {
            "category":"Building & Trades",
            "subcategory":"Construction",
            "type":"Services"
        }
    ],
    "sg:phone":"+61 3 6239 6527",
    "sg:postcode":"7150",
    "sg:province":"TAS",
    "sg:tags":[
        "contractor"
    ],
    "wof:name":"Kerry Vince Builders",
    "wof:placetype":"venue"
},
  "geometry": {"coordinates":[147.19869995100001,-43.0040779114],"type":"Point"}
}