{
  "type": "Feature",
  "properties": {
    "iso:country":"AU",
    "sg:address":"257 Hanson Rd",
    "sg:city":"Wingfield",
    "sg:classifiers":[
        {
            "category":"Fast Food",
            "type":"Food & Drink"
        }
    ],
    "sg:phone":"+61 8 8345 5052",
    "sg:postcode":"5013",
    "sg:province":"SA",
    "sg:tags":[
        "away",
        "take"
    ],
    "wof:name":"Lunchcutters On Hanson",
    "wof:placetype":"venue"
},
  "geometry": {"coordinates":[138.546386719,-34.8480224609],"type":"Point"}
}