{
  "type": "Feature",
  "properties": {
    "iso:country":"AU",
    "sg:address":"76 O.G. Rd",
    "sg:city":"Klemzig",
    "sg:classifiers":[
        {
            "category":"Health Services",
            "subcategory":"Health Practitioner",
            "type":"Services"
        }
    ],
    "sg:phone":"+61 8 8261 6012",
    "sg:postcode":"5087",
    "sg:province":"SA",
    "sg:tags":[
        "physiotherapist"
    ],
    "wof:name":"Klemzig Physiotherapy",
    "wof:placetype":"venue"
},
  "geometry": {"coordinates":[138.63659668,-34.881439209],"type":"Point"}
}