{
  "type": "Feature",
  "properties": {
    "addr:full":"Lvl 3/ 1060 Hay St West Perth WA 6005",
    "addr:housenumber":"/ 1060",
    "addr:postcode":"6005",
    "addr:street":"Hay St",
    "iso:country":"AU",
    "sg:address":"Lvl 3/ 1060 Hay St",
    "sg:city":"West Perth",
    "sg:phone":"+61 1300 725 650",
    "sg:postcode":"6005",
    "sg:province":"WA",
    "wof:name":"Protective Glass Services",
    "wof:placetype":"venue"
},
  "geometry": {"coordinates":[115.847846985,-31.9504165649],"type":"Point"}
}