{
  "type": "Feature",
  "properties": {
    "addr:full":"521 George St Windsor NSW 2756",
    "addr:housenumber":"521",
    "addr:postcode":"2756",
    "addr:street":"George St",
    "iso:country":"AU",
    "sg:address":"521 George St",
    "sg:city":"Windsor",
    "sg:classifiers":[
        {
            "category":"Food & Beverages",
            "subcategory":"Liquor & Beverages",
            "type":"Retail Goods"
        }
    ],
    "sg:phone":"+61 2 4577 3374",
    "sg:postcode":"2756",
    "sg:province":"NSW",
    "sg:tags":[
        "store"
    ],
    "wof:name":"South Windsor Liquor Shoppe",
    "wof:placetype":"venue"
},
  "geometry": {"coordinates":[150.80650329599999,-33.6181907654],"type":"Point"}
}