{
  "type": "Feature",
  "properties": {
    "iso:country":"AU",
    "sg:address":"PO Box 856",
    "sg:city":"Mt Gravatt",
    "sg:classifiers":[
        {
            "category":"Shopping",
            "subcategory":"Party Supplies",
            "type":"Retail Goods"
        }
    ],
    "sg:phone":"+61 7 3849 7365",
    "sg:postcode":"4122",
    "sg:province":"QLD",
    "sg:tags":[
        "selling",
        "plan"
    ],
    "wof:name":"In Wear",
    "wof:placetype":"venue"
},
  "geometry": {"coordinates":[153.072723389,-27.5303192139],"type":"Point"}
}