{
  "type": "Feature",
  "properties": {
    "addr:full":"2/ 158 Browns Rd Noble Park VIC 3174",
    "addr:housenumber":"/ 158",
    "addr:postcode":"3174",
    "addr:street":"Browns Rd",
    "iso:country":"AU",
    "sg:address":"2/ 158 Browns Rd",
    "sg:city":"Noble Park",
    "sg:classifiers":[
        {
            "category":"Building & Trades",
            "subcategory":"Cleaning & Sanitation",
            "type":"Services"
        }
    ],
    "sg:phone":"+61 3 9790 4300",
    "sg:postcode":"3174",
    "sg:province":"VIC",
    "sg:tags":[
        "chemical",
        "pressure",
        "steam",
        "contractor"
    ],
    "wof:name":"Karcher Pty Ltd",
    "wof:placetype":"venue"
},
  "geometry": {"coordinates":[145.18467712399999,-37.950378418],"type":"Point"}
}