{
  "type": "Feature",
  "properties": {
    "iso:country":"AU",
    "sg:address":"61 Burns Bay Rd",
    "sg:city":"Lane Cove",
    "sg:classifiers":[
        {
            "category":"Health Services",
            "subcategory":"Dentist",
            "type":"Services"
        }
    ],
    "sg:phone":"+61 2 9427 1888",
    "sg:postcode":"2066",
    "sg:province":"NSW",
    "wof:name":"Ho Ken C K",
    "wof:placetype":"venue"
},
  "geometry": {"coordinates":[151.16659545900001,-33.8146362305],"type":"Point"}
}