{
  "type": "Feature",
  "properties": {
    "addr:full":"Foster St Maffra VIC 3860",
    "addr:postcode":"3860",
    "addr:street":"Foster St",
    "iso:country":"AU",
    "sg:address":"Foster St",
    "sg:city":"Maffra",
    "sg:classifiers":[
        {
            "category":"Wholesale",
            "subcategory":"Farm Supplies",
            "type":"Manufacturing & Wholesale Goods"
        }
    ],
    "sg:phone":"+61 3 5147 1994",
    "sg:postcode":"3860",
    "sg:province":"VIC",
    "sg:tags":[
        "equipment"
    ],
    "wof:name":"Murray Goulburn Trading Pty Ltd",
    "wof:placetype":"venue"
},
  "geometry": {"coordinates":[146.97764587399999,-37.9689445496],"type":"Point"}
}