{
  "type": "Feature",
  "properties": {
    "addr:full":"691 Ferntree Gully Rd Glen Waverley VIC 3150",
    "addr:housenumber":"691",
    "addr:postcode":"3150",
    "addr:street":"Ferntree Gully Rd",
    "iso:country":"AU",
    "sg:address":"691 Ferntree Gully Rd",
    "sg:city":"Glen Waverley",
    "sg:classifiers":[
        {
            "category":"Health Services",
            "subcategory":"Doctor",
            "type":"Services"
        }
    ],
    "sg:phone":"+61 3 9560 4468",
    "sg:postcode":"3150",
    "sg:province":"VIC",
    "sg:tags":[
        "medical",
        "practitioner"
    ],
    "wof:name":"Miglic W.D.",
    "wof:placetype":"venue"
},
  "geometry": {"coordinates":[145.16912841800001,-37.9042015076],"type":"Point"}
}