{
  "type": "Feature",
  "properties": {
    "addr:full":"82 Murray St Gawler SA 5118",
    "addr:housenumber":"82",
    "addr:postcode":"5118",
    "addr:street":"Murray St",
    "iso:country":"AU",
    "sg:address":"82 Murray St",
    "sg:city":"Gawler",
    "sg:classifiers":[
        {
            "category":"Shopping",
            "subcategory":"Stationery & Office Supplies",
            "type":"Retail Goods"
        }
    ],
    "sg:phone":"+61 8 8522 5683",
    "sg:postcode":"5118",
    "sg:province":"SA",
    "sg:tags":[
        "equipment",
        "facsimile"
    ],
    "wof:name":"Brother",
    "wof:placetype":"venue"
},
  "geometry": {"coordinates":[138.748886,-34.596359],"type":"Point"}
}