{
  "type": "Feature",
  "properties": {
    "addr:full":"64 Bullcreek Drv Bullcreek WA 6149",
    "addr:housenumber":"64",
    "addr:postcode":"6149",
    "addr:street":"Bullcreek Drv Bullcreek",
    "iso:country":"AU",
    "sg:address":"64 Bullcreek Drv",
    "sg:city":"Bullcreek",
    "sg:classifiers":[
        {
            "category":"Health Services",
            "subcategory":"Doctor",
            "type":"Services"
        }
    ],
    "sg:phone":"+61 8 9332 3277",
    "sg:postcode":"6149",
    "sg:province":"WA",
    "sg:tags":[
        "medical",
        "practitioner"
    ],
    "wof:name":"Tomasich J N",
    "wof:placetype":"venue"
},
  "geometry": {"coordinates":[115.87059000000001,-32.066471],"type":"Point"}
}