{
  "type": "Feature",
  "properties": {
    "iso:country":"AU",
    "sg:address":"24 Knightsbridge Ave",
    "sg:city":"Belrose",
    "sg:classifiers":[
        {
            "category":"Building & Trades",
            "subcategory":"Plumbing",
            "type":"Services"
        }
    ],
    "sg:phone":"+61 417 231 718",
    "sg:postcode":"2085",
    "sg:province":"NSW",
    "sg:tags":[
        "plumber",
        "gasfitters"
    ],
    "wof:name":"G B Reid Plumbing Services Pty Ltd",
    "wof:placetype":"venue"
},
  "geometry": {"coordinates":[151.21888732900001,-33.7299308777],"type":"Point"}
}