{
  "type": "Feature",
  "properties": {
    "addr:full":"152 Meakin Rd Slacks Creek QLD 4127",
    "addr:housenumber":"152",
    "addr:postcode":"4127",
    "addr:street":"Meakin Rd",
    "iso:country":"AU",
    "sg:address":"152 Meakin Rd",
    "sg:city":"Slacks Creek",
    "sg:classifiers":[
        {
            "category":"Professional",
            "subcategory":"Art Services",
            "type":"Services"
        }
    ],
    "sg:phone":"+61 7 3208 5945",
    "sg:postcode":"4127",
    "sg:province":"QLD",
    "sg:tags":[
        "decorator",
        "painter"
    ],
    "wof:name":"Austin Noel",
    "wof:placetype":"venue"
},
  "geometry": {"coordinates":[153.135162353,-27.651184082],"type":"Point"}
}