{
  "type": "Feature",
  "properties": {
    "addr:full":"Woodlands Calcol Rd Deniliquin VIC 2710",
    "addr:postcode":"2710",
    "addr:street":"Calcol Rd",
    "iso:country":"AU",
    "sg:address":"Woodlands Calcol Rd",
    "sg:city":"Deniliquin",
    "sg:classifiers":[
        {
            "category":"Farming",
            "subcategory":"Nursery",
            "type":"Manufacturing & Wholesale Goods"
        }
    ],
    "sg:phone":"+61 3 5882 3300",
    "sg:postcode":"2710",
    "sg:province":"VIC",
    "wof:name":"Roelink Wholesale Plants",
    "wof:placetype":"venue"
},
  "geometry": {"coordinates":[144.957397461,-35.529499054],"type":"Point"}
}