{
  "type": "Feature",
  "properties": {
    "addr:full":"312 Colburn Ave Victoria Point QLD 4165",
    "addr:housenumber":"312",
    "addr:postcode":"4165",
    "addr:street":"Colburn Ave",
    "iso:country":"AU",
    "sg:address":"312 Colburn Ave",
    "sg:city":"Victoria Point",
    "sg:classifiers":[
        {
            "category":"Banks & Credit Unions",
            "subcategory":"Investment Brokerage",
            "type":"Services"
        }
    ],
    "sg:phone":"+61 7 3820 9788",
    "sg:postcode":"4165",
    "sg:province":"QLD",
    "sg:tags":[
        "finance",
        "broker"
    ],
    "wof:name":"Gary Tolliday Finance",
    "wof:placetype":"venue"
},
  "geometry": {"coordinates":[153.29315185600001,-27.5836849213],"type":"Point"}
}