{
  "type": "Feature",
  "properties": {
    "addr:full":"29 Preston St Dennington VIC 3280",
    "addr:housenumber":"29",
    "addr:postcode":"3280",
    "addr:street":"Preston St",
    "iso:country":"AU",
    "sg:address":"29 Preston St",
    "sg:city":"Dennington",
    "sg:classifiers":[
        {
            "category":"Building & Trades",
            "subcategory":"Landscaping Services",
            "type":"Services"
        }
    ],
    "sg:phone":"+61 3 5562 1896",
    "sg:postcode":"3280",
    "sg:province":"VIC",
    "sg:tags":[
        "gardener"
    ],
    "wof:name":"Warrnambool Cutting Edge Gardening Services",
    "wof:placetype":"venue"
},
  "geometry": {"coordinates":[142.44467163100001,-38.3537559509],"type":"Point"}
}