{
  "type": "Feature",
  "properties": {
    "addr:full":"4 Boyne St Stuart QLD 4811",
    "addr:housenumber":"4",
    "addr:postcode":"4811",
    "addr:street":"Boyne St",
    "iso:country":"AU",
    "sg:address":"4 Boyne St",
    "sg:city":"Stuart",
    "sg:classifiers":[
        {
            "category":"Wholesale",
            "subcategory":"Construction Materials",
            "type":"Manufacturing & Wholesale Goods"
        }
    ],
    "sg:phone":"+61 7 4778 3111",
    "sg:postcode":"4811",
    "sg:province":"QLD",
    "sg:tags":[
        "protective",
        "coating"
    ],
    "wof:name":"Townsville Industrial Painting & Coatings",
    "wof:placetype":"venue"
},
  "geometry": {"coordinates":[146.847275,-19.345354],"type":"Point"}
}