{
  "type": "Feature",
  "properties": {
    "addr:full":"120 Ellen St Port Pirie SA 5540",
    "addr:housenumber":"120",
    "addr:postcode":"5540",
    "addr:street":"Ellen St",
    "iso:country":"AU",
    "sg:address":"120 Ellen St",
    "sg:city":"Port Pirie",
    "sg:classifiers":[
        {
            "category":"Shopping",
            "subcategory":"Baby Store",
            "type":"Retail Goods"
        }
    ],
    "sg:phone":"+61 8 8632 1869",
    "sg:postcode":"5540",
    "sg:province":"SA",
    "sg:tags":[
        "children's",
        "wear"
    ],
    "wof:name":"E Street Kidswear",
    "wof:placetype":"venue"
},
  "geometry": {"coordinates":[138.010131836,-33.1772918701],"type":"Point"}
}