{
  "type": "Feature",
  "properties": {
    "addr:full":"17 Pacific Drv Balnarring VIC 3926",
    "addr:housenumber":"17",
    "addr:postcode":"3926",
    "addr:street":"Pacific Drv",
    "iso:country":"AU",
    "sg:address":"17 Pacific Drv",
    "sg:city":"Balnarring",
    "sg:classifiers":[
        {
            "category":"Banks & Credit Unions",
            "subcategory":"Financial Services",
            "type":"Services"
        }
    ],
    "sg:phone":"+61 427 100 607",
    "sg:postcode":"3926",
    "sg:province":"VIC",
    "sg:tags":[
        "planning"
    ],
    "wof:name":"John Kercheval & Associates Pty Ltd",
    "wof:placetype":"venue"
},
  "geometry": {"coordinates":[145.11555480999999,-38.3701858521],"type":"Point"}
}