{
  "type": "Feature",
  "properties": {
    "addr:full":"Coward St West Mascot NSW 2020",
    "addr:postcode":"2020",
    "addr:street":"Coward St West",
    "iso:country":"AU",
    "sg:address":"Coward St West",
    "sg:city":"Mascot",
    "sg:classifiers":[
        {
            "category":"Manufacturing",
            "subcategory":"Building Materials",
            "type":"Manufacturing & Wholesale Goods"
        }
    ],
    "sg:phone":"+61 2 9317 8400",
    "sg:postcode":"2020",
    "sg:province":"NSW",
    "sg:tags":[
        "equipment",
        "handling"
    ],
    "wof:name":"Red Australia Equipment Pty Ltd",
    "wof:placetype":"venue"
},
  "geometry": {"coordinates":[151.19505310100001,-33.9254417419],"type":"Point"}
}