{
  "type": "Feature",
  "properties": {
    "iso:country":"AU",
    "sg:address":"1379 Ocean Drv",
    "sg:city":"Lake Cathie",
    "sg:classifiers":[
        {
            "category":"Travel",
            "subcategory":"Hotels & Motels",
            "type":"Entertainment"
        }
    ],
    "sg:phone":"+61 2 6585 5430",
    "sg:postcode":"2445",
    "sg:province":"NSW",
    "wof:name":"Surfside Resort Motel",
    "wof:placetype":"venue"
},
  "geometry": {"coordinates":[152.851944,-31.55607],"type":"Point"}
}