{
  "type": "Feature",
  "properties": {
    "iso:country":"AU",
    "sg:address":"1380 La Grange Rd",
    "sg:city":"Stoneville",
    "sg:classifiers":[
        {
            "category":"Manufacturing",
            "subcategory":"Glass & Minerals",
            "type":"Manufacturing & Wholesale Goods"
        }
    ],
    "sg:phone":"+61 8 9295 2835",
    "sg:postcode":"6081",
    "sg:province":"WA",
    "sg:tags":[
        "exploration"
    ],
    "wof:name":"Exploration & Management Consultants Pty Ltd",
    "wof:placetype":"venue"
},
  "geometry": {"coordinates":[116.158370972,-31.8515453339],"type":"Point"}
}