{
  "type": "Feature",
  "properties": {
    "addr:full":"Shp 3 113 Rosella Ave Werribee VIC 3030",
    "addr:housenumber":"113",
    "addr:postcode":"3030",
    "addr:street":"Rosella Ave",
    "iso:country":"AU",
    "sg:address":"Shp 3 113 Rosella Ave",
    "sg:city":"Werribee",
    "sg:classifiers":[
        {
            "category":"Fast Food",
            "type":"Food & Drink"
        }
    ],
    "sg:phone":"+61 3 9742 7141",
    "sg:postcode":"3030",
    "sg:province":"VIC",
    "sg:tags":[
        "away",
        "take"
    ],
    "wof:name":"Rosella Fish Shop",
    "wof:placetype":"venue"
},
  "geometry": {"coordinates":[144.66842700000001,-37.88142],"type":"Point"}
}