{
  "type": "Feature",
  "properties": {
    "iso:country":"AU",
    "sg:address":"Suite 5 179-181 Keira St",
    "sg:city":"Wollongong",
    "sg:classifiers":[
        {
            "category":"Health Services",
            "subcategory":"Health Practitioner",
            "type":"Services"
        }
    ],
    "sg:phone":"+61 2 4227 4084",
    "sg:postcode":"2500",
    "sg:province":"NSW",
    "sg:tags":[
        "psychologist"
    ],
    "wof:name":"Sanna Mary Psychologist",
    "wof:placetype":"venue"
},
  "geometry": {"coordinates":[150.893707,-34.42329],"type":"Point"}
}