{
  "type": "Feature",
  "properties": {
    "addr:full":"Level 6/ 55 Southbank Blv Southbank VIC 3006",
    "addr:housenumber":"/ 55",
    "addr:postcode":"3006",
    "addr:street":"Southbank Blv",
    "iso:country":"AU",
    "sg:address":"Level 6/ 55",
    "sg:city":"Southbank Blv Southbank",
    "sg:classifiers":[
        {
            "category":"Professional",
            "subcategory":"Employment Agencies",
            "type":"Services"
        }
    ],
    "sg:phone":"+61 3 9626 2660",
    "sg:postcode":"3006",
    "sg:province":"VIC",
    "wof:name":"Tad- Technical Careers & Contracts",
    "wof:placetype":"venue"
},
  "geometry": {"coordinates":[144.96450805699999,-37.8226203918],"type":"Point"}
}