{
  "type": "Feature",
  "properties": {
    "addr:full":"7-11 Burr Crt Laverton VIC 3028",
    "addr:housenumber":"7-11",
    "addr:postcode":"3028",
    "addr:street":"Burr Crt",
    "iso:country":"AU",
    "sg:address":"7-11 Burr Crt",
    "sg:city":"Laverton",
    "sg:classifiers":[
        {
            "category":"Wholesale",
            "subcategory":"Painting Supplies",
            "type":"Manufacturing & Wholesale Goods"
        }
    ],
    "sg:phone":"+61 3 9250 1050",
    "sg:postcode":"3028",
    "sg:province":"VIC",
    "sg:tags":[
        "product",
        "cleaning"
    ],
    "wof:name":"Campbell Brothers Limited",
    "wof:placetype":"venue"
},
  "geometry": {"coordinates":[144.805069,-37.817482],"type":"Point"}
}