{
  "type": "Feature",
  "properties": {
    "addr:full":"12 Weston Hill Rd Sorell TAS 7172",
    "addr:housenumber":"12",
    "addr:postcode":"7172",
    "addr:street":"Weston Hill Rd",
    "iso:country":"AU",
    "sg:address":"12 Weston Hill Rd",
    "sg:city":"Sorell",
    "sg:classifiers":[
        {
            "category":"Autos & Motor Vehicles",
            "subcategory":"Fuel & Gas Station",
            "type":"Retail Goods"
        }
    ],
    "sg:phone":"+61 3 6265 3648",
    "sg:postcode":"7172",
    "sg:province":"TAS",
    "wof:name":"Plus Petrol",
    "wof:placetype":"venue"
},
  "geometry": {"coordinates":[147.56904602,-42.7738990784],"type":"Point"}
}