{
  "type": "Feature",
  "properties": {
    "iso:country":"AU",
    "sg:address":"3 Maple Mews",
    "sg:city":"Duncraig",
    "sg:classifiers":[
        {
            "category":"Building & Trades",
            "subcategory":"Plumbing",
            "type":"Services"
        }
    ],
    "sg:phone":"+61 418 941 518",
    "sg:postcode":"6023",
    "sg:province":"WA",
    "sg:tags":[
        "plumber",
        "gasfitters"
    ],
    "wof:name":"A1 Tap Specialist",
    "wof:placetype":"venue"
},
  "geometry": {"coordinates":[115.791717529,-31.8443260193],"type":"Point"}
}