{
  "type": "Feature",
  "properties": {
    "addr:full":"Cnr Glenelg Hwy & Sutton St Delacombe VIC 3356",
    "addr:postcode":"3356",
    "addr:street":"Cnr Glenelg Hwy & Sutton St",
    "iso:country":"AU",
    "sg:address":"Cnr Glenelg Hwy & Sutton St",
    "sg:city":"Delacombe",
    "sg:classifiers":[
        {
            "category":"Social Services",
            "subcategory":"Child Care",
            "type":"Services"
        }
    ],
    "sg:phone":"+61 3 5336 1296",
    "sg:postcode":"3356",
    "sg:province":"VIC",
    "wof:name":"ABC Developmental Learning Centre",
    "wof:placetype":"venue"
},
  "geometry": {"coordinates":[143.82879600000001,-37.572372],"type":"Point"}
}