{
  "type": "Feature",
  "properties": {
    "addr:full":"194 Mulgrave Rd Cairns QLD 4870",
    "addr:housenumber":"194",
    "addr:postcode":"4870",
    "addr:street":"Mulgrave Rd",
    "iso:country":"AU",
    "sg:address":"194 Mulgrave Rd",
    "sg:city":"Cairns",
    "sg:classifiers":[
        {
            "category":"Shopping",
            "subcategory":"Computers & Home Electronics",
            "type":"Retail Goods"
        }
    ],
    "sg:phone":"+61 7 4052 5999",
    "sg:postcode":"4870",
    "sg:province":"QLD",
    "sg:tags":[
        "hardware",
        "equipment"
    ],
    "sg:website":"http://www.leshop.com.au",
    "wof:name":"Leading Edge Computers",
    "wof:placetype":"venue"
},
  "geometry": {"coordinates":[145.74693298299999,-16.9378223419],"type":"Point"}
}