{
  "type": "Feature",
  "properties": {
    "addr:full":"70 Haverfield St Echuca VIC 3564",
    "addr:housenumber":"70",
    "addr:postcode":"3564",
    "addr:street":"Haverfield St",
    "iso:country":"AU",
    "sg:address":"70 Haverfield St",
    "sg:city":"Echuca",
    "sg:classifiers":[
        {
            "category":"Travel",
            "subcategory":"Hostel",
            "type":"Entertainment"
        }
    ],
    "sg:phone":"+61 3 5482 3600",
    "sg:postcode":"3564",
    "sg:province":"VIC",
    "sg:tags":[
        "home"
    ],
    "wof:name":"Engelbert Lodge",
    "wof:placetype":"venue"
},
  "geometry": {"coordinates":[144.74635314899999,-36.138584137],"type":"Point"}
}