{
  "type": "Feature",
  "properties": {
    "addr:full":"17 Glen Osmond Rd Eastwood SA 5063",
    "addr:housenumber":"17",
    "addr:postcode":"5063",
    "addr:street":"Glen Osmond Rd",
    "iso:country":"AU",
    "sg:address":"17 Glen Osmond Rd",
    "sg:city":"Eastwood",
    "sg:classifiers":[
        {
            "category":"Professional",
            "subcategory":"Accounting & Tax Preparation",
            "type":"Services"
        }
    ],
    "sg:phone":"+61 8 8373 2119",
    "sg:postcode":"5063",
    "sg:province":"SA",
    "sg:tags":[
        "accountant",
        "auditor"
    ],
    "wof:name":"Olekalns Andrew",
    "wof:placetype":"venue"
},
  "geometry": {"coordinates":[138.617843628,-34.9416770935],"type":"Point"}
}