{
  "type": "Feature",
  "properties": {
    "iso:country":"AU",
    "sg:address":"8 Dingley Crt",
    "sg:city":"Dingley",
    "sg:classifiers":[
        {
            "category":"Home & Garden",
            "subcategory":"Hardware",
            "type":"Retail Goods"
        }
    ],
    "sg:phone":"+61 3 9551 9294",
    "sg:postcode":"3172",
    "sg:province":"VIC",
    "sg:tags":[
        "printed",
        "circuit"
    ],
    "wof:name":"PCB Solutions Pty Ltd",
    "wof:placetype":"venue"
},
  "geometry": {"coordinates":[145.13829040499999,-37.9863243103],"type":"Point"}
}