{
  "type": "Feature",
  "properties": {
    "iso:country":"AU",
    "sg:address":"4 Ford Rd",
    "sg:city":"Emerald",
    "sg:classifiers":[
        {
            "category":"Food & Beverages",
            "subcategory":"Specialty",
            "type":"Retail Goods"
        }
    ],
    "sg:phone":"+61 3 5968 5440",
    "sg:postcode":"3782",
    "sg:province":"VIC",
    "sg:tags":[
        "delicacy"
    ],
    "wof:name":"Viking Victoria",
    "wof:placetype":"venue"
},
  "geometry": {"coordinates":[145.46786499999999,-37.941727],"type":"Point"}
}