{
  "type": "Feature",
  "properties": {
    "addr:full":"415 Terrigal Drv Erina NSW 2250",
    "addr:housenumber":"415",
    "addr:postcode":"2250",
    "addr:street":"Terrigal Drv",
    "iso:country":"AU",
    "sg:address":"415 Terrigal Drv",
    "sg:city":"Erina",
    "sg:classifiers":[
        {
            "category":"Health Services",
            "subcategory":"Doctor",
            "type":"Services"
        }
    ],
    "sg:phone":"+61 2 4367 6600",
    "sg:postcode":"2250",
    "sg:province":"NSW",
    "sg:tags":[
        "medical",
        "practitioner"
    ],
    "wof:name":"Ashbrooke Cosmetic and Vein Centre",
    "wof:placetype":"venue"
},
  "geometry": {"coordinates":[151.392456055,-33.4340744019],"type":"Point"}
}