{
  "type": "Feature",
  "properties": {
    "iso:country":"AU",
    "sg:address":"3 Mason St",
    "sg:city":"Newport",
    "sg:classifiers":[
        {
            "category":"Organizations",
            "subcategory":"Community Association",
            "type":"Services"
        }
    ],
    "sg:phone":"+61 3 9391 7090",
    "sg:postcode":"3015",
    "sg:province":"VIC",
    "sg:tags":[
        "organisation",
        "family",
        "welfare"
    ],
    "wof:name":"Society of St Vincent De Paul Centres",
    "wof:placetype":"venue"
},
  "geometry": {"coordinates":[144.88255310100001,-37.8423042297],"type":"Point"}
}