{
  "type": "Feature",
  "properties": {
    "addr:full":"1 Curnow St Crows Nest QLD 4355",
    "addr:housenumber":"1",
    "addr:postcode":"4355",
    "addr:street":"Curnow St",
    "iso:country":"AU",
    "sg:address":"1 Curnow St",
    "sg:city":"Crows Nest",
    "sg:classifiers":[
        {
            "category":"Shopping",
            "type":"Retail Goods"
        }
    ],
    "sg:phone":"+61 7 4698 1187",
    "sg:postcode":"4355",
    "sg:province":"QLD",
    "sg:tags":[
        "produce",
        "grain"
    ],
    "wof:name":"C.N.Produce",
    "wof:placetype":"venue"
},
  "geometry": {"coordinates":[152.05632,-27.261839],"type":"Point"}
}