{
  "type": "Feature",
  "properties": {
    "iso:country":"AU",
    "sg:address":"471 High St",
    "sg:city":"Maitland",
    "sg:classifiers":[
        {
            "category":"Real Estate",
            "subcategory":"Real Estate Agent",
            "type":"Services"
        }
    ],
    "sg:phone":"+61 2 4933 2088",
    "sg:postcode":"2320",
    "sg:province":"NSW",
    "wof:name":"Professionals Maitland",
    "wof:placetype":"venue"
},
  "geometry": {"coordinates":[151.55325317399999,-32.7313232422],"type":"Point"}
}