{
  "type": "Feature",
  "properties": {
    "iso:country":"AU",
    "sg:address":"58 Spine St",
    "sg:city":"Sumner Park",
    "sg:classifiers":[
        {
            "category":"Home & Garden",
            "subcategory":"Carpets & Floor Coverings",
            "type":"Retail Goods"
        }
    ],
    "sg:phone":"+61 7 3279 0011",
    "sg:postcode":"4074",
    "sg:province":"QLD",
    "sg:tags":[
        "tile",
        "wall"
    ],
    "wof:name":"Metro Tiles",
    "wof:placetype":"venue"
},
  "geometry": {"coordinates":[152.93414306599999,-27.5609016418],"type":"Point"}
}