{
  "type": "Feature",
  "properties": {
    "iso:country":"AU",
    "sg:address":"182 Manns Rd",
    "sg:city":"Gosford West",
    "sg:classifiers":[
        {
            "category":"Wholesale",
            "subcategory":"Machinery & Supplies",
            "type":"Manufacturing & Wholesale Goods"
        }
    ],
    "sg:phone":"+61 418 802 973",
    "sg:postcode":"2250",
    "sg:province":"NSW",
    "sg:tags":[
        "equipment",
        "hydraulic"
    ],
    "wof:name":"T.J. Tools",
    "wof:placetype":"venue"
},
  "geometry": {"coordinates":[151.319488525,-33.4242134094],"type":"Point"}
}