{
  "type": "Feature",
  "properties": {
    "iso:country":"AU",
    "sg:address":"Main St",
    "sg:city":"Smeaton",
    "sg:classifiers":[
        {
            "category":"Manufacturing",
            "subcategory":"Lumber",
            "type":"Manufacturing & Wholesale Goods"
        }
    ],
    "sg:phone":"+61 3 5345 6204",
    "sg:postcode":"3364",
    "sg:province":"VIC",
    "sg:tags":[
        "sawmillers"
    ],
    "wof:name":"Doug Ford",
    "wof:placetype":"venue"
},
  "geometry": {"coordinates":[143.99253845199999,-37.1846237183],"type":"Point"}
}