{
  "type": "Feature",
  "properties": {
    "addr:full":"7 Aplin St Point Vernon QLD 4655",
    "addr:housenumber":"7",
    "addr:postcode":"4655",
    "addr:street":"Aplin St",
    "iso:country":"AU",
    "sg:address":"7 Aplin St",
    "sg:city":"Point Vernon",
    "sg:classifiers":[
        {
            "category":"Professional",
            "subcategory":"Business Services",
            "type":"Services"
        }
    ],
    "sg:phone":"+61 7 4128 1257",
    "sg:postcode":"4655",
    "sg:province":"QLD",
    "sg:tags":[
        "broker"
    ],
    "wof:name":"Equity Businesses",
    "wof:placetype":"venue"
},
  "geometry": {"coordinates":[152.825684,-25.249256],"type":"Point"}
}