{
  "type": "Feature",
  "properties": {
    "addr:full":"9 Livingstone St Ivanhoe VIC 3079",
    "addr:housenumber":"9",
    "addr:postcode":"3079",
    "addr:street":"Livingstone St",
    "iso:country":"AU",
    "sg:address":"9 Livingstone St",
    "sg:city":"Ivanhoe",
    "sg:classifiers":[
        {
            "category":"Health Services",
            "subcategory":"Doctor",
            "type":"Services"
        }
    ],
    "sg:phone":"+61 3 9497 1188",
    "sg:postcode":"3079",
    "sg:province":"VIC",
    "sg:tags":[
        "medical",
        "practitioner"
    ],
    "wof:name":"McHenry K J",
    "wof:placetype":"venue"
},
  "geometry": {"coordinates":[145.04176330600001,-37.7676010132],"type":"Point"}
}