{
  "type": "Feature",
  "properties": {
    "addr:full":"48 Tamar St Ballina NSW 2478",
    "addr:housenumber":"48",
    "addr:postcode":"2478",
    "addr:street":"Tamar St",
    "iso:country":"AU",
    "sg:address":"48 Tamar St",
    "sg:city":"Ballina",
    "sg:classifiers":[
        {
            "category":"Professional",
            "subcategory":"Accounting & Tax Preparation",
            "type":"Services"
        }
    ],
    "sg:phone":"+61 2 6628 3810",
    "sg:postcode":"2478",
    "sg:province":"NSW",
    "sg:tags":[
        "consultant",
        "taxation"
    ],
    "wof:name":"K & W Partners",
    "wof:placetype":"venue"
},
  "geometry": {"coordinates":[153.556838989,-28.8676586151],"type":"Point"}
}