{
  "type": "Feature",
  "properties": {
    "addr:full":"Unit 4/395 Warton Rd, Amherst Commercial Centre Canning Vale WA 6155",
    "addr:housenumber":"/ 395",
    "addr:postcode":"6155",
    "addr:street":"Warton Rd",
    "iso:country":"AU",
    "sg:address":"Unit 4/395 Warton Rd, Amherst Commercial Centre",
    "sg:city":"Canning Vale",
    "sg:classifiers":[
        {
            "category":"Real Estate",
            "subcategory":"Real Estate Agent",
            "type":"Services"
        }
    ],
    "sg:phone":"+61 8 9456 2777",
    "sg:postcode":"6155",
    "sg:province":"WA",
    "sg:website":"http://www.westaterealty.com.au",
    "wof:name":"Westate Realty",
    "wof:placetype":"venue"
},
  "geometry": {"coordinates":[115.935318,-32.0961],"type":"Point"}
}