{
  "type": "Feature",
  "properties": {
    "iso:country":"AU",
    "sg:address":"22 Grenville Crt",
    "sg:city":"Phillip",
    "sg:classifiers":[
        {
            "category":"Retail",
            "subcategory":"Repair Shop",
            "type":"Services"
        }
    ],
    "sg:phone":"+61 2 6282 0066",
    "sg:postcode":"2606",
    "sg:province":"ACT",
    "sg:tags":[
        "windscreen"
    ],
    "wof:name":"Aussie Windscreens",
    "wof:placetype":"venue"
},
  "geometry": {"coordinates":[149.087966919,-35.3511581421],"type":"Point"}
}