{
  "type": "Feature",
  "properties": {
    "addr:full":"1/ 7 Adams Rd Palmerston NT 0830",
    "addr:housenumber":"/ 7",
    "addr:postcode":"nt 0830",
    "addr:street":"Adams Rd",
    "iso:country":"AU",
    "sg:address":"1/ 7 Adams Rd",
    "sg:city":"Palmerston",
    "sg:classifiers":[
        {
            "category":"Personal",
            "subcategory":"Beauty Salon",
            "type":"Services"
        }
    ],
    "sg:phone":"+61 8 8931 1777",
    "sg:postcode":"0830",
    "sg:province":"NT",
    "sg:tags":[
        "hairdresser"
    ],
    "wof:name":"Annie's Barber Shop",
    "wof:placetype":"venue"
},
  "geometry": {"coordinates":[130.98898299999999,-12.47516],"type":"Point"}
}