{
  "type": "Feature",
  "properties": {
    "addr:full":"London Rd Stawell VIC 3380",
    "addr:postcode":"3380",
    "addr:street":"London Rd",
    "iso:country":"AU",
    "sg:address":"London Rd",
    "sg:city":"Stawell",
    "sg:classifiers":[
        {
            "category":"Communications",
            "subcategory":"News Services",
            "type":"Services"
        }
    ],
    "sg:phone":"+61 3 5358 1877",
    "sg:postcode":"3380",
    "sg:province":"VIC",
    "sg:tags":[
        "information",
        "tourist",
        "attractions"
    ],
    "wof:name":"Casper's World In Miniature",
    "wof:placetype":"venue"
},
  "geometry": {"coordinates":[142.765625,-37.0643806458],"type":"Point"}
}