{
  "type": "Feature",
  "properties": {
    "iso:country":"AU",
    "sg:address":"54 Bridge St",
    "sg:city":"Bendigo",
    "sg:classifiers":[
        {
            "category":"Wholesale",
            "subcategory":"Medical Equipment & Supplies",
            "type":"Manufacturing & Wholesale Goods"
        }
    ],
    "sg:phone":"+61 3 5442 1131",
    "sg:postcode":"3550",
    "sg:province":"VIC",
    "sg:tags":[
        "aid",
        "care",
        "health",
        "home"
    ],
    "wof:name":"Country Care Rehabilitation & Mobility Equipment",
    "wof:placetype":"venue"
},
  "geometry": {"coordinates":[144.28622436500001,-36.7638511658],"type":"Point"}
}