{
  "type": "Feature",
  "properties": {
    "addr:full":"516 Oaklands Rd Pambula NSW 2549",
    "addr:housenumber":"516",
    "addr:postcode":"2549",
    "addr:street":"Oaklands Rd",
    "iso:country":"AU",
    "sg:address":"516 Oaklands Rd",
    "sg:city":"Pambula",
    "sg:classifiers":[
        {
            "category":"Building & Trades",
            "subcategory":"Plumbing",
            "type":"Services"
        }
    ],
    "sg:phone":"+61 2 6495 6676",
    "sg:postcode":"2549",
    "sg:province":"NSW",
    "sg:tags":[
        "plumber",
        "gasfitters"
    ],
    "wof:name":"Glyn Miller",
    "wof:placetype":"venue"
},
  "geometry": {"coordinates":[149.85101318400001,-36.9297637939],"type":"Point"}
}