{
  "type": "Feature",
  "properties": {
    "iso:country":"AU",
    "sg:address":"Unit 6 18 Resolution Drv",
    "sg:city":"Caringbah",
    "sg:classifiers":[
        {
            "category":"Shopping",
            "subcategory":"Mobile Phones",
            "type":"Retail Goods"
        }
    ],
    "sg:phone":"+61 2 9525 6630",
    "sg:postcode":"2229",
    "sg:province":"NSW",
    "sg:tags":[
        "wholesaler",
        "mfrs",
        "electrical",
        "switchboard"
    ],
    "wof:name":"Power Switchboards Of Australia",
    "wof:placetype":"venue"
},
  "geometry": {"coordinates":[151.132415772,-34.0325012207],"type":"Point"}
}