{
  "type": "Feature",
  "properties": {
    "addr:full":"Shed 2/ 14 Fursden St Glenella QLD 4740",
    "addr:housenumber":"2 / 14",
    "addr:postcode":"4740",
    "addr:street":"Fursden St",
    "iso:country":"AU",
    "sg:address":"Shed 2/ 14 Fursden St",
    "sg:city":"Glenella",
    "sg:classifiers":[
        {
            "category":"Utilities",
            "subcategory":"Electric",
            "type":"Services"
        }
    ],
    "sg:phone":"+61 419 729 437",
    "sg:postcode":"4740",
    "sg:province":"QLD",
    "sg:tags":[
        "electrical",
        "contractor"
    ],
    "wof:name":"Daley Electrical",
    "wof:placetype":"venue"
},
  "geometry": {"coordinates":[149.15036000000001,-21.130594],"type":"Point"}
}