{
  "type": "Feature",
  "properties": {
    "addr:full":"51- 53 Kolora Rd Heidelberg West VIC 3081",
    "addr:housenumber":"53",
    "addr:postcode":"3081",
    "addr:street":"Kolora Rd",
    "iso:country":"AU",
    "sg:address":"51- 53 Kolora Rd",
    "sg:city":"Heidelberg West",
    "sg:classifiers":[
        {
            "category":"Shopping",
            "subcategory":"Stationery & Office Supplies",
            "type":"Retail Goods"
        }
    ],
    "sg:phone":"+61 3 9459 2644",
    "sg:postcode":"3081",
    "sg:province":"VIC",
    "sg:tags":[
        "equipment",
        "display",
        "exhibition"
    ],
    "wof:name":"Hanan Displays Pty Ltd",
    "wof:placetype":"venue"
},
  "geometry": {"coordinates":[145.04466247600001,-37.7337684631],"type":"Point"}
}