{
  "type": "Feature",
  "properties": {
    "addr:full":"25 Elder St Alice Springs NT 0870",
    "addr:housenumber":"25",
    "addr:postcode":"nt 0870",
    "addr:street":"Elder St",
    "iso:country":"AU",
    "sg:address":"25 Elder St",
    "sg:city":"Alice Springs",
    "sg:classifiers":[
        {
            "category":"Government",
            "subcategory":"Fire Station",
            "type":"Public Place"
        }
    ],
    "sg:phone":"+61 8 8953 4404",
    "sg:postcode":"0870",
    "sg:province":"NT",
    "sg:tags":[
        "equipment",
        "protection",
        "consultant"
    ],
    "wof:name":"N Tess",
    "wof:placetype":"venue"
},
  "geometry": {"coordinates":[133.86891174300001,-23.697385788],"type":"Point"}
}