{
  "type": "Feature",
  "properties": {
    "addr:full":"Thomas Crs Monarto SA 5254",
    "addr:postcode":"5254",
    "addr:street":"Thomas Crs",
    "iso:country":"AU",
    "sg:address":"Thomas Crs",
    "sg:city":"Monarto",
    "sg:classifiers":[
        {
            "category":"Professional",
            "subcategory":"Engineering",
            "type":"Services"
        }
    ],
    "sg:phone":"+61 8 8534 4188",
    "sg:postcode":"5254",
    "sg:province":"SA",
    "sg:tags":[
        "engineer"
    ],
    "wof:name":"Monarto Engineering & Design",
    "wof:placetype":"venue"
},
  "geometry": {"coordinates":[139.104415894,-35.1149215698],"type":"Point"}
}