{
  "type": "Feature",
  "properties": {
    "addr:full":"90 Backcreek Rd Lockwood VIC 3551",
    "addr:housenumber":"90",
    "addr:postcode":"3551",
    "addr:street":"Backcreek Rd",
    "iso:country":"AU",
    "sg:address":"90 Backcreek Rd",
    "sg:city":"Lockwood",
    "sg:classifiers":[
        {
            "category":"Building & Trades",
            "subcategory":"Plumbing",
            "type":"Services"
        }
    ],
    "sg:phone":"+61 417 055 963",
    "sg:postcode":"3551",
    "sg:province":"VIC",
    "sg:tags":[
        "plumber",
        "gasfitters"
    ],
    "wof:name":"Daniel Ashby Plumbing & Gasfitting",
    "wof:placetype":"venue"
},
  "geometry": {"coordinates":[144.10618591299999,-36.858543396],"type":"Point"}
}