{
  "type": "Feature",
  "properties": {
    "iso:country":"AU",
    "sg:address":"Wanneroo Central Shopping Centre, Cnr Conlan & Wan",
    "sg:city":"Wanneroo",
    "sg:classifiers":[
        {
            "category":"Insurance",
            "subcategory":"Health Insurance",
            "type":"Services"
        }
    ],
    "sg:phone":"+61 13 23 31",
    "sg:postcode":"6065",
    "sg:province":"WA",
    "wof:name":"Medibank Private (Fullife Pharmacy)",
    "wof:placetype":"venue"
},
  "geometry": {"coordinates":[115.803588867,-31.7522106171],"type":"Point"}
}