{
  "type": "Feature",
  "properties": {
    "iso:country":"AU",
    "sg:address":"6-8 Bonanza Pde",
    "sg:city":"Sans Souci",
    "sg:classifiers":[
        {
            "category":"Social Services",
            "subcategory":"Child Care",
            "type":"Services"
        }
    ],
    "sg:phone":"+61 2 9529 9444",
    "sg:postcode":"2219",
    "sg:province":"NSW",
    "wof:name":"Rainbow Cottage Child Care Centre",
    "wof:placetype":"venue"
},
  "geometry": {"coordinates":[151.133377,-33.991631],"type":"Point"}
}