{
  "type": "Feature",
  "properties": {
    "addr:full":"Cnr Mills Ave & Griffin St Moranbah QLD 4744",
    "addr:postcode":"4744",
    "addr:street":"Cnr Mills Ave & Griffin St",
    "iso:country":"AU",
    "sg:address":"Cnr Mills Ave & Griffin St",
    "sg:city":"Moranbah",
    "sg:classifiers":[
        {
            "category":"Autos & Motor Vehicles",
            "subcategory":"Fuel & Gas Station",
            "type":"Retail Goods"
        }
    ],
    "sg:phone":"+61 7 4941 7183",
    "sg:postcode":"4744",
    "sg:province":"QLD",
    "wof:name":"Ampol Moranbah Service Centre",
    "wof:placetype":"venue"
},
  "geometry": {"coordinates":[148.06712341299999,-21.9988174438],"type":"Point"}
}