{
  "type": "Feature",
  "properties": {
    "addr:full":"170 Main St Katoomba NSW 2780",
    "addr:housenumber":"170",
    "addr:postcode":"2780",
    "addr:street":"Main St",
    "iso:country":"AU",
    "sg:address":"170 Main St",
    "sg:city":"Katoomba",
    "sg:classifiers":[
        {
            "category":"Food & Beverages",
            "subcategory":"Fruits & Vegetables",
            "type":"Retail Goods"
        }
    ],
    "sg:phone":"+61 2 4782 4972",
    "sg:postcode":"2780",
    "sg:province":"NSW",
    "sg:tags":[
        "greengrocer",
        "fruiterer"
    ],
    "wof:name":"Todarello's Katoomba Village Fruit Market",
    "wof:placetype":"venue"
},
  "geometry": {"coordinates":[150.309646606,-33.7104072571],"type":"Point"}
}