{
  "type": "Feature",
  "properties": {
    "iso:country":"AU",
    "sg:address":"Level 3 697 Burke Rd",
    "sg:city":"Camberwell",
    "sg:classifiers":[
        {
            "category":"Professional",
            "subcategory":"Engineering",
            "type":"Services"
        }
    ],
    "sg:phone":"+61 3 9813 4000",
    "sg:postcode":"3124",
    "sg:province":"VIC",
    "sg:tags":[
        "consulting",
        "engineer"
    ],
    "wof:name":"Brown W P & Partners Pty Ltd",
    "wof:placetype":"venue"
},
  "geometry": {"coordinates":[145.056365967,-37.8321533203],"type":"Point"}
}