{
  "type": "Feature",
  "properties": {
    "addr:full":"Suite 1, Level 1, 25 Belmore Street Burwood NSW 2134",
    "addr:housenumber":"25",
    "addr:postcode":"2134",
    "addr:street":"Belmore Street",
    "iso:country":"AU",
    "sg:address":"Suite 1, Level 1, 25 Belmore Street",
    "sg:city":"Burwood",
    "sg:classifiers":[
        {
            "category":"Insurance",
            "subcategory":"Life Insurance",
            "type":"Services"
        }
    ],
    "sg:phone":"+61 2 9715 3333",
    "sg:postcode":"2134",
    "sg:province":"NSW",
    "wof:name":"Cedars Insurance Services (CES LICHAA)",
    "wof:placetype":"venue"
},
  "geometry": {"coordinates":[151.10287475600001,-33.8786697388],"type":"Point"}
}