{
  "type": "Feature",
  "properties": {
    "addr:full":"51 Yandilla St Pittsworth QLD 4356",
    "addr:housenumber":"51",
    "addr:postcode":"4356",
    "addr:street":"Yandilla St",
    "iso:country":"AU",
    "sg:address":"51 Yandilla St",
    "sg:city":"Pittsworth",
    "sg:classifiers":[
        {
            "category":"Utilities",
            "subcategory":"Electric",
            "type":"Services"
        }
    ],
    "sg:phone":"+61 7 4693 1467",
    "sg:postcode":"4356",
    "sg:province":"QLD",
    "sg:tags":[
        "electrical",
        "contractor"
    ],
    "wof:name":"Whittakers Electrical & Furniture",
    "wof:placetype":"venue"
},
  "geometry": {"coordinates":[151.63618500000001,-27.715303],"type":"Point"}
}