{
  "type": "Feature",
  "properties": {
    "addr:full":"4 King William St South Fremantle WA 6162",
    "addr:housenumber":"4",
    "addr:postcode":"6162",
    "addr:street":"King William St",
    "iso:country":"AU",
    "sg:address":"4 King William St",
    "sg:city":"South Fremantle",
    "sg:classifiers":[
        {
            "category":"Autos & Motor Vehicles",
            "subcategory":"Boat Sales",
            "type":"Retail Goods"
        }
    ],
    "sg:phone":"+61 8 9430 5181",
    "sg:postcode":"6162",
    "sg:province":"WA",
    "sg:tags":[
        "equipment",
        "yacht"
    ],
    "wof:name":"Mastervolt Australia",
    "wof:placetype":"venue"
},
  "geometry": {"coordinates":[115.75140399999999,-32.067123],"type":"Point"}
}