{
  "type": "Feature",
  "properties": {
    "addr:full":"18 / 40 Young St Redfern NSW 2016",
    "addr:housenumber":"18 / 40",
    "addr:postcode":"2016",
    "addr:street":"Young St",
    "iso:country":"AU",
    "sg:address":"18 / 40 Young St",
    "sg:city":"Redfern",
    "sg:classifiers":[
        {
            "category":"Building & Trades",
            "subcategory":"Pest Control",
            "type":"Services"
        }
    ],
    "sg:phone":"+61 2 9690 0619",
    "sg:postcode":"2016",
    "sg:province":"NSW",
    "wof:name":"Bug Buster Integrated Pest & Cleaning Management",
    "wof:placetype":"venue"
},
  "geometry": {"coordinates":[151.21043395999999,-33.8930778503],"type":"Point"}
}