{
  "type": "Feature",
  "properties": {
    "addr:full":"7 Hallam Belgrave Rd Hallam VIC 3803",
    "addr:housenumber":"7",
    "addr:postcode":"3803",
    "addr:street":"Hallam Belgrave Rd",
    "iso:country":"AU",
    "sg:address":"7 Hallam Belgrave Rd",
    "sg:city":"Hallam",
    "sg:classifiers":[
        {
            "category":"Fast Food",
            "type":"Food & Drink"
        }
    ],
    "sg:phone":"+61 3 9708 6005",
    "sg:postcode":"3803",
    "sg:province":"VIC",
    "sg:tags":[
        "away",
        "take"
    ],
    "wof:name":"Subway Sandwiches & Salads",
    "wof:placetype":"venue"
},
  "geometry": {"coordinates":[145.27302551299999,-38.0072021484],"type":"Point"}
}