{
  "type": "Feature",
  "properties": {
    "addr:full":"2 Knox Pl Normanhurst NSW 2076",
    "addr:housenumber":"2",
    "addr:postcode":"2076",
    "addr:street":"Knox Pl",
    "iso:country":"AU",
    "sg:address":"2 Knox Pl",
    "sg:city":"Normanhurst",
    "sg:classifiers":[
        {
            "category":"Sports & Exercise",
            "subcategory":"Sports Center",
            "type":"Entertainment"
        }
    ],
    "sg:phone":"+61 2 9489 6739",
    "sg:postcode":"2076",
    "sg:province":"NSW",
    "sg:tags":[
        "coach",
        "tennis"
    ],
    "wof:name":"Aim Tennis School",
    "wof:placetype":"venue"
},
  "geometry": {"coordinates":[151.09429931599999,-33.7214851379],"type":"Point"}
}