{
  "type": "Feature",
  "properties": {
    "addr:full":"2 Castle St Parkside SA 5063",
    "addr:housenumber":"2",
    "addr:postcode":"5063",
    "addr:street":"Castle St",
    "iso:country":"AU",
    "sg:address":"2 Castle St",
    "sg:city":"Parkside",
    "sg:classifiers":[
        {
            "category":"Manufacturing",
            "subcategory":"Metals",
            "type":"Manufacturing & Wholesale Goods"
        }
    ],
    "sg:phone":"+61 8 8373 4142",
    "sg:postcode":"5063",
    "sg:province":"SA",
    "sg:tags":[
        "polisher"
    ],
    "wof:name":"Benneche S C M & Co Pty Ltd",
    "wof:placetype":"venue"
},
  "geometry": {"coordinates":[138.61836242699999,-34.9441604614],"type":"Point"}
}