{
  "type": "Feature",
  "properties": {
    "addr:full":"13a Stanton Rd Seven Hills NSW 2147",
    "addr:housenumber":"13a",
    "addr:postcode":"2147",
    "addr:street":"Stanton Rd",
    "iso:country":"AU",
    "sg:address":"13a Stanton Rd",
    "sg:city":"Seven Hills",
    "sg:classifiers":[
        {
            "category":"Shopping",
            "subcategory":"Stationery & Office Supplies",
            "type":"Retail Goods"
        }
    ],
    "sg:phone":"+61 2 9624 4488",
    "sg:postcode":"2147",
    "sg:province":"NSW",
    "sg:tags":[
        "packaging",
        "material"
    ],
    "wof:name":"PlasPak JWS",
    "wof:placetype":"venue"
},
  "geometry": {"coordinates":[150.95123290999999,-33.7704772949],"type":"Point"}
}