{
  "type": "Feature",
  "properties": {
    "addr:full":"14- 18 Quinn St Preston VIC 3072",
    "addr:housenumber":"18",
    "addr:postcode":"3072",
    "addr:street":"Quinn St",
    "iso:country":"AU",
    "sg:address":"14- 18 Quinn St",
    "sg:city":"Preston",
    "sg:classifiers":[
        {
            "category":"Structure",
            "subcategory":"Office Building",
            "type":"Public Place"
        }
    ],
    "sg:phone":"+61 3 9480 2066",
    "sg:postcode":"3072",
    "sg:province":"VIC",
    "sg:tags":[
        "fire",
        "window",
        "door"
    ],
    "wof:name":"Skyrange Doors & Windows",
    "wof:placetype":"venue"
},
  "geometry": {"coordinates":[145.03240966800001,-37.7467346191],"type":"Point"}
}