{
  "type": "Feature",
  "properties": {
    "iso:country":"AU",
    "sg:address":"51 Amelia St",
    "sg:city":"Fortitude Valley",
    "sg:classifiers":[
        {
            "category":"Professional",
            "subcategory":"Art Services",
            "type":"Services"
        }
    ],
    "sg:phone":"+61 7 3252 4410",
    "sg:postcode":"4006",
    "sg:province":"QLD",
    "sg:tags":[
        "graphic",
        "designer"
    ],
    "wof:name":"Sunrose Graphics",
    "wof:placetype":"venue"
},
  "geometry": {"coordinates":[153.03140258799999,-27.4545440674],"type":"Point"}
}