{
  "type": "Feature",
  "properties": {
    "iso:country":"AU",
    "sg:address":"39 Caonran Ave",
    "sg:city":"Endeavour Hills",
    "sg:classifiers":[
        {
            "category":"Retail",
            "subcategory":"Funeral Services",
            "type":"Services"
        }
    ],
    "sg:phone":"+61 3 9706 1575",
    "sg:postcode":"3802",
    "sg:province":"VIC",
    "sg:tags":[
        "director"
    ],
    "wof:name":"J.B. Dias Funerals",
    "wof:placetype":"venue"
},
  "geometry": {"coordinates":[145.27349853499999,-37.9827194214],"type":"Point"}
}