{
  "type": "Feature",
  "properties": {
    "iso:country":"AU",
    "sg:address":"187 Cherry La",
    "sg:city":"Laverton North",
    "sg:classifiers":[
        {
            "category":"Wholesale",
            "subcategory":"Machinery & Supplies",
            "type":"Manufacturing & Wholesale Goods"
        }
    ],
    "sg:phone":"+61 3 9369 9550",
    "sg:postcode":"3026",
    "sg:province":"VIC",
    "sg:tags":[
        "equipment",
        "hydraulic"
    ],
    "sg:website":"http://www.hthydraulic.com.au",
    "wof:name":"HT Hydraulic Technology",
    "wof:placetype":"venue"
},
  "geometry": {"coordinates":[144.783432,-37.841862],"type":"Point"}
}