{
  "type": "Feature",
  "properties": {
    "addr:full":"Witches Chase St North Tamborine QLD 4272",
    "addr:postcode":"4272",
    "addr:street":"Witches Chase St North",
    "iso:country":"AU",
    "sg:address":"Witches Chase St",
    "sg:city":"North Tamborine",
    "sg:classifiers":[
        {
            "category":"Farming",
            "subcategory":"Farm",
            "type":"Manufacturing & Wholesale Goods"
        }
    ],
    "sg:phone":"+61 7 5545 1357",
    "sg:postcode":"4272",
    "sg:province":"QLD",
    "sg:tags":[
        "farmer"
    ],
    "wof:name":"McKay M H F",
    "wof:placetype":"venue"
},
  "geometry": {"coordinates":[153.18447875999999,-27.9284591675],"type":"Point"}
}