{
  "type": "Feature",
  "properties": {
    "iso:country":"AU",
    "sg:address":"10 The La",
    "sg:city":"Maryville",
    "sg:classifiers":[
        {
            "category":"Social Services",
            "subcategory":"Retirement Home",
            "type":"Services"
        }
    ],
    "sg:phone":"+61 2 4969 5599",
    "sg:postcode":"2293",
    "sg:province":"NSW",
    "sg:tags":[
        "environmental",
        "consultant",
        "pollution"
    ],
    "wof:name":"JP Environmental",
    "wof:placetype":"venue"
},
  "geometry": {"coordinates":[151.75979614299999,-32.9111251831],"type":"Point"}
}