{
  "type": "Feature",
  "properties": {
    "addr:full":"4 Biddick Crt Werribee VIC 3030",
    "addr:housenumber":"4",
    "addr:postcode":"3030",
    "addr:street":"Biddick Crt",
    "iso:country":"AU",
    "sg:address":"4 Biddick Crt",
    "sg:city":"Werribee",
    "sg:classifiers":[
        {
            "category":"Building & Trades",
            "subcategory":"Construction",
            "type":"Services"
        }
    ],
    "sg:phone":"+61 417 312 560",
    "sg:postcode":"3030",
    "sg:province":"VIC",
    "sg:tags":[
        "management"
    ],
    "wof:name":"Tiehuis F & P & Sons Construction",
    "wof:placetype":"venue"
},
  "geometry": {"coordinates":[144.67143200000001,-37.894245],"type":"Point"}
}