{
  "type": "Feature",
  "properties": {
    "addr:full":"Lvl 1/ 135 Browns Plains Rd Browns Plains QLD 4118",
    "addr:housenumber":"/ 135",
    "addr:postcode":"4118",
    "addr:street":"Browns Plains Rd",
    "iso:country":"AU",
    "sg:address":"Lvl 1/ 135 Browns Plains Rd",
    "sg:city":"Browns Plains",
    "sg:classifiers":[
        {
            "category":"Professional",
            "subcategory":"Accounting & Tax Preparation",
            "type":"Services"
        }
    ],
    "sg:phone":"+61 7 3809 2322",
    "sg:postcode":"4118",
    "sg:province":"QLD",
    "sg:tags":[
        "accountant",
        "auditor"
    ],
    "wof:name":"David Dwyer and Asoociates",
    "wof:placetype":"venue"
},
  "geometry": {"coordinates":[153.05250549300001,-27.6625957489],"type":"Point"}
}