{
  "type": "Feature",
  "properties": {
    "addr:full":"8- 10 Keenan Way Winthrop WA 6150",
    "addr:housenumber":"10",
    "addr:postcode":"6150",
    "addr:street":"8;Keenan Way",
    "iso:country":"AU",
    "sg:address":"8- 10",
    "sg:city":"Keenan Way Winthrop",
    "sg:classifiers":[
        {
            "category":"Building & Trades",
            "subcategory":"Construction",
            "type":"Services"
        }
    ],
    "sg:phone":"+61 413 179 777",
    "sg:postcode":"6150",
    "sg:province":"WA",
    "sg:tags":[
        "contractor"
    ],
    "wof:name":"A. Mondello & Co",
    "wof:placetype":"venue"
},
  "geometry": {"coordinates":[115.816299,-32.05109],"type":"Point"}
}