{
  "type": "Feature",
  "properties": {
    "iso:country":"AU",
    "sg:address":"93 Head St",
    "sg:city":"Alice Springs",
    "sg:classifiers":[
        {
            "category":"Home & Garden",
            "subcategory":"Carpets & Floor Coverings",
            "type":"Retail Goods"
        }
    ],
    "sg:phone":"+61 8 8952 4042",
    "sg:postcode":"0870",
    "sg:province":"NT",
    "sg:tags":[
        "tile",
        "wall"
    ],
    "wof:name":"Larry Hoey Tiler",
    "wof:placetype":"venue"
},
  "geometry": {"coordinates":[133.865692139,-23.6778678894],"type":"Point"}
}