{
  "type": "Feature",
  "properties": {
    "iso:country":"AU",
    "sg:address":"25 William St",
    "sg:city":"Balaclava",
    "sg:classifiers":[
        {
            "category":"Utilities",
            "subcategory":"Telephone",
            "type":"Services"
        }
    ],
    "sg:phone":"+61 3 9525 9711",
    "sg:postcode":"3183",
    "sg:province":"VIC",
    "sg:tags":[
        "installation",
        "system",
        "maintenance"
    ],
    "wof:name":"Digital Network",
    "wof:placetype":"venue"
},
  "geometry": {"coordinates":[144.99388122600001,-37.8705711365],"type":"Point"}
}