{
  "type": "Feature",
  "properties": {
    "addr:full":"10 Renshaw St North Rockhampton QLD 4701",
    "addr:housenumber":"10",
    "addr:postcode":"4701",
    "addr:street":"Renshaw St North",
    "iso:country":"AU",
    "sg:address":"10 Renshaw St",
    "sg:city":"North Rockhampton",
    "sg:classifiers":[
        {
            "category":"Farming",
            "subcategory":"Nursery",
            "type":"Manufacturing & Wholesale Goods"
        }
    ],
    "sg:phone":"+61 7 4922 1819",
    "sg:postcode":"4701",
    "sg:province":"QLD",
    "wof:name":"Yarrandoo Nursery",
    "wof:placetype":"venue"
},
  "geometry": {"coordinates":[150.50686645499999,-23.3582744598],"type":"Point"}
}