{
  "type": "Feature",
  "properties": {
    "addr:full":"47 Princes Hwy Arncliffe NSW 2205",
    "addr:housenumber":"47",
    "addr:postcode":"2205",
    "addr:street":"Princes Hwy",
    "iso:country":"AU",
    "sg:address":"47 Princes Hwy",
    "sg:city":"Arncliffe",
    "sg:classifiers":[
        {
            "category":"Retail",
            "subcategory":"Auto Repair",
            "type":"Services"
        }
    ],
    "sg:phone":"+61 2 9599 8965",
    "sg:postcode":"2205",
    "sg:province":"NSW",
    "sg:tags":[
        "repairer",
        "motor",
        "engineer"
    ],
    "wof:name":"Top One Automotive Repair",
    "wof:placetype":"venue"
},
  "geometry": {"coordinates":[151.14494300000001,-33.941536],"type":"Point"}
}