{
  "type": "Feature",
  "properties": {
    "iso:country":"AU",
    "sg:address":"Unit 6/ 8 Hanlon St",
    "sg:city":"Parkes",
    "sg:classifiers":[
        {
            "category":"Retail",
            "subcategory":"Storage",
            "type":"Services"
        }
    ],
    "sg:phone":"+61 2 6863 8888",
    "sg:postcode":"2870",
    "sg:province":"NSW",
    "wof:name":"Outer Space Self Storage Parkes",
    "wof:placetype":"venue"
},
  "geometry": {"coordinates":[148.159805,-33.153347],"type":"Point"}
}