{
  "type": "Feature",
  "properties": {
    "addr:full":"Suite A/ 135 Margaret St Toowoomba QLD 4350",
    "addr:housenumber":"suite;/ 135",
    "addr:postcode":"4350",
    "addr:street":"Margaret St",
    "iso:country":"AU",
    "sg:address":"Suite A/ 135 Margaret St",
    "sg:city":"Toowoomba",
    "sg:classifiers":[
        {
            "category":"Shopping",
            "subcategory":"Computers & Home Electronics",
            "type":"Retail Goods"
        }
    ],
    "sg:phone":"+61 7 4637 8328",
    "sg:postcode":"4350",
    "sg:province":"QLD",
    "sg:tags":[
        "equipment",
        "multimedia"
    ],
    "wof:name":"Firestorm Studios",
    "wof:placetype":"venue"
},
  "geometry": {"coordinates":[151.95463599999999,-27.561026],"type":"Point"}
}