{
  "type": "Feature",
  "properties": {
    "addr:full":"Shp 101 Dandenong Plz Dandenong VIC 3175",
    "addr:housenumber":"101",
    "addr:postcode":"3175",
    "addr:street":"Dandenong Plz",
    "iso:country":"AU",
    "sg:address":"Shp 101",
    "sg:city":"Dandenong Plz Dandenong",
    "sg:classifiers":[
        {
            "category":"Professional",
            "subcategory":"Accounting & Tax Preparation",
            "type":"Services"
        }
    ],
    "sg:phone":"+61 3 9792 0078",
    "sg:postcode":"3175",
    "sg:province":"VIC",
    "sg:tags":[
        "consultant",
        "taxation"
    ],
    "wof:name":"H & R Block",
    "wof:placetype":"venue"
},
  "geometry": {"coordinates":[145.200042725,-37.9915618896],"type":"Point"}
}