{
  "type": "Feature",
  "properties": {
    "iso:country":"AU",
    "sg:address":"68 Main St",
    "sg:city":"Pialba",
    "sg:classifiers":[
        {
            "category":"Travel",
            "subcategory":"Hotels & Motels",
            "type":"Entertainment"
        }
    ],
    "sg:phone":"+61 7 4128 3666",
    "sg:postcode":"4655",
    "sg:province":"QLD",
    "wof:name":"Comfort Inn Fraser Gateway",
    "wof:placetype":"venue"
},
  "geometry": {"coordinates":[152.838577,-25.286434],"type":"Point"}
}