{
  "type": "Feature",
  "properties": {
    "addr:full":"45 Vincent St Daylesford VIC 3460",
    "addr:housenumber":"45",
    "addr:postcode":"3460",
    "addr:street":"Vincent St",
    "iso:country":"AU",
    "sg:address":"45 Vincent St",
    "sg:city":"Daylesford",
    "sg:classifiers":[
        {
            "category":"Retail",
            "subcategory":"Auto Repair",
            "type":"Services"
        }
    ],
    "sg:phone":"+61 3 5348 2248",
    "sg:postcode":"3460",
    "sg:province":"VIC",
    "sg:tags":[
        "repairer",
        "motor",
        "engineer"
    ],
    "wof:name":"Holden",
    "wof:placetype":"venue"
},
  "geometry": {"coordinates":[144.14271545400001,-37.3422698975],"type":"Point"}
}