{
  "type": "Feature",
  "properties": {
    "addr:full":"6 Huon St Banksia Park SA 5091",
    "addr:housenumber":"6",
    "addr:postcode":"5091",
    "addr:street":"Huon St",
    "iso:country":"AU",
    "sg:address":"6 Huon St",
    "sg:city":"Banksia Park",
    "sg:classifiers":[
        {
            "category":"Retail",
            "subcategory":"Auto Repair",
            "type":"Services"
        }
    ],
    "sg:phone":"+61 8 8264 6629",
    "sg:postcode":"5091",
    "sg:province":"SA",
    "sg:tags":[
        "beater",
        "painter",
        "panel"
    ],
    "wof:name":"Duff Alan J",
    "wof:placetype":"venue"
},
  "geometry": {"coordinates":[138.723052978,-34.8078613281],"type":"Point"}
}