{
  "type": "Feature",
  "properties": {
    "addr:full":"1/ 13 Kingston Drv Maryborough QLD 4650",
    "addr:housenumber":"/ 13",
    "addr:postcode":"4650",
    "addr:street":"Kingston Drv",
    "iso:country":"AU",
    "sg:address":"1/ 13 Kingston Drv",
    "sg:city":"Maryborough",
    "sg:classifiers":[
        {
            "category":"Retail",
            "subcategory":"Auto Repair",
            "type":"Services"
        }
    ],
    "sg:phone":"+61 7 4123 4545",
    "sg:postcode":"4650",
    "sg:province":"QLD",
    "sg:tags":[
        "repairer",
        "motor",
        "engineer"
    ],
    "wof:name":"Cedrics Mechanical Repairs",
    "wof:placetype":"venue"
},
  "geometry": {"coordinates":[152.67747499999999,-25.516705],"type":"Point"}
}