{
  "type": "Feature",
  "properties": {
    "iso:country":"AU",
    "sg:address":"16 Bally St",
    "sg:city":"Kelvin Grove",
    "sg:classifiers":[
        {
            "category":"Manufacturing",
            "subcategory":"Jewelry",
            "type":"Manufacturing & Wholesale Goods"
        }
    ],
    "sg:phone":"+61 7 3356 7655",
    "sg:postcode":"4059",
    "sg:province":"QLD",
    "sg:tags":[
        "mfrg",
        "jeweller"
    ],
    "wof:name":"Amber Lady (Imports) The",
    "wof:placetype":"venue"
},
  "geometry": {"coordinates":[153.013946533,-27.4438934326],"type":"Point"}
}