{
  "type": "Feature",
  "properties": {
    "addr:full":"19 Ponton St Salisbury SA 5108",
    "addr:housenumber":"19",
    "addr:postcode":"5108",
    "addr:street":"Ponton St",
    "iso:country":"AU",
    "sg:address":"19 Ponton St",
    "sg:city":"Salisbury",
    "sg:classifiers":[
        {
            "category":"Utilities",
            "subcategory":"Electric",
            "type":"Services"
        }
    ],
    "sg:phone":"+61 8 8258 1833",
    "sg:postcode":"5108",
    "sg:province":"SA",
    "sg:tags":[
        "electrical",
        "contractor"
    ],
    "wof:name":"Caruso Angelo",
    "wof:placetype":"venue"
},
  "geometry": {"coordinates":[138.654174805,-34.7646179199],"type":"Point"}
}