{
  "type": "Feature",
  "properties": {
    "iso:country":"AU",
    "sg:address":"15 Forest Park Rd",
    "sg:city":"Blackheath",
    "sg:classifiers":[
        {
            "category":"Building & Trades",
            "subcategory":"Construction",
            "type":"Services"
        }
    ],
    "sg:phone":"+61 2 4787 8882",
    "sg:postcode":"2785",
    "sg:province":"NSW",
    "sg:tags":[
        "contractor"
    ],
    "wof:name":"Dwyer Owen H.",
    "wof:placetype":"venue"
},
  "geometry": {"coordinates":[150.30062866200001,-33.6499252319],"type":"Point"}
}