{
  "type": "Feature",
  "properties": {
    "addr:full":"43 Glen Osmond Rd Eastwood SA 5063",
    "addr:housenumber":"43",
    "addr:postcode":"5063",
    "addr:street":"Glen Osmond Rd",
    "iso:country":"AU",
    "sg:address":"43 Glen Osmond Rd",
    "sg:city":"Eastwood",
    "sg:classifiers":[
        {
            "category":"Real Estate",
            "subcategory":"Architect",
            "type":"Services"
        }
    ],
    "sg:phone":"+61 8 8373 1611",
    "sg:postcode":"5063",
    "sg:province":"SA",
    "sg:tags":[
        "building",
        "designer"
    ],
    "wof:name":"Shannon Architects",
    "wof:placetype":"venue"
},
  "geometry": {"coordinates":[138.61892700199999,-34.942363739],"type":"Point"}
}