{
  "type": "Feature",
  "properties": {
    "addr:full":"5A/ 330 Marine Tce Busselton WA 6280",
    "addr:housenumber":"5a / 330",
    "addr:postcode":"6280",
    "addr:street":"Marine Tce",
    "iso:country":"AU",
    "sg:address":"5A/ 330 Marine Tce",
    "sg:city":"Busselton",
    "sg:classifiers":[
        {
            "category":"Health Services",
            "subcategory":"Health Practitioner",
            "type":"Services"
        }
    ],
    "sg:phone":"+61 8 9754 8288",
    "sg:postcode":"6280",
    "sg:province":"WA",
    "sg:tags":[
        "physiotherapist"
    ],
    "wof:name":"Bayside Physiotherapy",
    "wof:placetype":"venue"
},
  "geometry": {"coordinates":[115.344818115,-33.652141571],"type":"Point"}
}