{
  "type": "Feature",
  "properties": {
    "addr:full":"3 Botanical Drv Kellyville NSW 2155",
    "addr:housenumber":"3",
    "addr:postcode":"2155",
    "addr:street":"Botanical Drv",
    "iso:country":"AU",
    "sg:address":"3 Botanical Drv",
    "sg:city":"Kellyville",
    "sg:classifiers":[
        {
            "category":"Building & Trades",
            "subcategory":"Cleaning & Sanitation",
            "type":"Services"
        }
    ],
    "sg:phone":"+61 2 8824 7022",
    "sg:postcode":"2155",
    "sg:province":"NSW",
    "sg:tags":[
        "industrial",
        "commercial",
        "contractor"
    ],
    "wof:name":"Kleenrite Pty Ltd",
    "wof:placetype":"venue"
},
  "geometry": {"coordinates":[150.94903564399999,-33.7086791992],"type":"Point"}
}