{
  "type": "Feature",
  "properties": {
    "iso:country":"AU",
    "sg:address":"17 Finlay Crt",
    "sg:city":"Kirwan",
    "sg:classifiers":[
        {
            "category":"Building & Trades",
            "subcategory":"Plumbing",
            "type":"Services"
        }
    ],
    "sg:phone":"+61 412 747 975",
    "sg:postcode":"4817",
    "sg:province":"QLD",
    "sg:tags":[
        "plumber",
        "gasfitters"
    ],
    "wof:name":"Mattson Plumbing & Drainage",
    "wof:placetype":"venue"
},
  "geometry": {"coordinates":[146.73445100000001,-19.290373],"type":"Point"}
}