{
  "type": "Feature",
  "properties": {
    "addr:full":"3 Elysium Crs Oakleigh East VIC 3166",
    "addr:housenumber":"3",
    "addr:postcode":"3166",
    "addr:street":"Elysium Crs",
    "iso:country":"AU",
    "sg:address":"3 Elysium Crs",
    "sg:city":"Oakleigh East",
    "sg:classifiers":[
        {
            "category":"Building & Trades",
            "subcategory":"Plumbing",
            "type":"Services"
        }
    ],
    "sg:phone":"+61 3 9543 3377",
    "sg:postcode":"3166",
    "sg:province":"VIC",
    "sg:tags":[
        "plumber",
        "gasfitters"
    ],
    "wof:name":"Eddington Allan Plumbing",
    "wof:placetype":"venue"
},
  "geometry": {"coordinates":[145.114135742,-37.9014396667],"type":"Point"}
}