{
  "type": "Feature",
  "properties": {
    "iso:country":"AU",
    "sg:address":"4 George St",
    "sg:city":"Dubbo",
    "sg:classifiers":[
        {
            "category":"Utilities",
            "subcategory":"Water",
            "type":"Services"
        }
    ],
    "sg:phone":"+61 2 6884 7979",
    "sg:postcode":"2830",
    "sg:province":"NSW",
    "sg:tags":[
        "cartage"
    ],
    "wof:name":"G & D McKechnie Pty Ltd",
    "wof:placetype":"venue"
},
  "geometry": {"coordinates":[148.61190795900001,-32.2515258789],"type":"Point"}
}