{
  "type": "Feature",
  "properties": {
    "addr:full":"11 Mittagong Crt Narre Warren VIC 3805",
    "addr:housenumber":"11",
    "addr:postcode":"3805",
    "addr:street":"Mittagong Crt",
    "iso:country":"AU",
    "sg:address":"11 Mittagong Crt",
    "sg:city":"Narre Warren",
    "sg:classifiers":[
        {
            "category":"Building & Trades",
            "subcategory":"Landscaping Services",
            "type":"Services"
        }
    ],
    "sg:phone":"+61 3 9704 9894",
    "sg:postcode":"3805",
    "sg:province":"VIC",
    "sg:tags":[
        "designer",
        "landscape",
        "contractor"
    ],
    "wof:name":"Oatlands Garden Care",
    "wof:placetype":"venue"
},
  "geometry": {"coordinates":[145.32685900000001,-38.014519],"type":"Point"}
}