{
  "type": "Feature",
  "properties": {
    "iso:country":"AU",
    "sg:address":"17 Croobyar Rd",
    "sg:city":"Milton",
    "sg:classifiers":[
        {
            "category":"Education",
            "subcategory":"School",
            "type":"Public Place"
        }
    ],
    "sg:phone":"+61 2 4454 0688",
    "sg:postcode":"2538",
    "sg:province":"NSW",
    "wof:name":"Shoalhaven Anglican School",
    "wof:placetype":"venue"
},
  "geometry": {"coordinates":[150.43333435100001,-35.3197669983],"type":"Point"}
}