{
  "type": "Feature",
  "properties": {
    "addr:full":"400 Victoria Ave Chatswood NSW 2067",
    "addr:housenumber":"400",
    "addr:postcode":"2067",
    "addr:street":"Victoria Ave",
    "iso:country":"AU",
    "sg:address":"400 Victoria Ave",
    "sg:city":"Chatswood",
    "sg:classifiers":[
        {
            "category":"Health Services",
            "subcategory":"Doctor",
            "type":"Services"
        }
    ],
    "sg:phone":"+61 2 9415 2288",
    "sg:postcode":"2067",
    "sg:province":"NSW",
    "sg:tags":[
        "medical",
        "practitioner"
    ],
    "wof:name":"Fung Denise",
    "wof:placetype":"venue"
},
  "geometry": {"coordinates":[151.18251037600001,-33.7965278625],"type":"Point"}
}