{
  "type": "Feature",
  "properties": {
    "addr:full":"10/ 2320 Silverdale Rd Silverdale NSW 2752",
    "addr:housenumber":"10 / 2320",
    "addr:postcode":"2752",
    "addr:street":"Silverdale Rd",
    "iso:country":"AU",
    "sg:address":"10/ 2320 Silverdale Rd",
    "sg:city":"Silverdale",
    "sg:classifiers":[
        {
            "category":"Manufacturing",
            "subcategory":"Metals",
            "type":"Manufacturing & Wholesale Goods"
        }
    ],
    "sg:phone":"+61 2 4774 0011",
    "sg:postcode":"2752",
    "sg:province":"NSW",
    "sg:tags":[
        "steel",
        "fabricator",
        "mfrs"
    ],
    "wof:name":"Ripa Steel Fabrications",
    "wof:placetype":"venue"
},
  "geometry": {"coordinates":[150.61315918,-33.8926353455],"type":"Point"}
}