{
  "type": "Feature",
  "properties": {
    "addr:full":"50 Rochford St St Clair NSW 2759",
    "addr:housenumber":"50",
    "addr:postcode":"2759",
    "addr:street":"Rochford St",
    "iso:country":"AU",
    "sg:address":"50 Rochford St",
    "sg:city":"St Clair",
    "sg:classifiers":[
        {
            "category":"Arts & Performance",
            "subcategory":"Music",
            "type":"Entertainment"
        }
    ],
    "sg:phone":"+61 2 9834 3830",
    "sg:postcode":"2759",
    "sg:province":"NSW",
    "sg:tags":[
        "mobile",
        "jockey",
        "disc"
    ],
    "wof:name":"Dee-Jay Music For All Occassions",
    "wof:placetype":"venue"
},
  "geometry": {"coordinates":[150.77517700199999,-33.7886009216],"type":"Point"}
}