{
  "type": "Feature",
  "properties": {
    "addr:full":"397 Argent St Broken Hill NSW 2880",
    "addr:housenumber":"397",
    "addr:postcode":"2880",
    "addr:street":"Argent St",
    "iso:country":"AU",
    "sg:address":"397 Argent St",
    "sg:city":"Broken Hill",
    "sg:classifiers":[
        {
            "category":"Cafe",
            "type":"Food & Drink"
        }
    ],
    "sg:phone":"+61 8 8087 5599",
    "sg:postcode":"2880",
    "sg:province":"NSW",
    "wof:name":"Alfrescos Cafe",
    "wof:placetype":"venue"
},
  "geometry": {"coordinates":[141.46795654300001,-31.9570102692],"type":"Point"}
}