{
  "type": "Feature",
  "properties": {
    "iso:country":"AU",
    "sg:address":"Mackenzie St",
    "sg:city":"Merriwa",
    "sg:classifiers":[
        {
            "category":"Health Services",
            "subcategory":"Hospital",
            "type":"Services"
        }
    ],
    "sg:phone":"+61 13 12 33",
    "sg:postcode":"2329",
    "sg:province":"NSW",
    "sg:tags":[
        "ambulance"
    ],
    "wof:name":"Ambulance Service Of NSW",
    "wof:placetype":"venue"
},
  "geometry": {"coordinates":[150.35658264200001,-32.1415481567],"type":"Point"}
}