{
  "type": "Feature",
  "properties": {
    "addr:full":"120 Messmate Rd Torquay VIC 3228",
    "addr:housenumber":"120",
    "addr:postcode":"3228",
    "addr:street":"Messmate Rd",
    "iso:country":"AU",
    "sg:address":"120 Messmate Rd",
    "sg:city":"Torquay",
    "sg:classifiers":[
        {
            "category":"Food & Beverages",
            "subcategory":"Fruits & Vegetables",
            "type":"Retail Goods"
        }
    ],
    "sg:phone":"+61 3 5261 3436",
    "sg:postcode":"3228",
    "sg:province":"VIC",
    "sg:tags":[
        "wholesale"
    ],
    "wof:name":"Cooinda Park Wholesalers",
    "wof:placetype":"venue"
},
  "geometry": {"coordinates":[144.31144699999999,-38.307278],"type":"Point"}
}