{
  "type": "Feature",
  "properties": {
    "addr:full":"Hartwood St Nymagee NSW 2831",
    "addr:postcode":"2831",
    "addr:street":"Hartwood St",
    "iso:country":"AU",
    "sg:address":"Hartwood St",
    "sg:city":"Nymagee",
    "sg:classifiers":[
        {
            "category":"Professional",
            "subcategory":"Employment Agencies",
            "type":"Services"
        }
    ],
    "sg:phone":"+61 2 6837 3667",
    "sg:postcode":"2831",
    "sg:province":"NSW",
    "sg:tags":[
        "entertainer",
        "agent"
    ],
    "wof:name":"Nymagee Promotions",
    "wof:placetype":"venue"
},
  "geometry": {"coordinates":[146.314331055,-32.069732666],"type":"Point"}
}