{
  "type": "Feature",
  "properties": {
    "addr:full":"9 Carlotta St Artarmon NSW 2064",
    "addr:housenumber":"9",
    "addr:postcode":"2064",
    "addr:street":"Carlotta St",
    "iso:country":"AU",
    "sg:address":"9 Carlotta St",
    "sg:city":"Artarmon",
    "sg:classifiers":[
        {
            "category":"Retail",
            "subcategory":"Auto Repair",
            "type":"Services"
        }
    ],
    "sg:phone":"+61 2 9439 2733",
    "sg:postcode":"2064",
    "sg:province":"NSW",
    "sg:tags":[
        "repairer",
        "motor",
        "engineer"
    ],
    "wof:name":"Eurocars (Northside) Pty Ltd",
    "wof:placetype":"venue"
},
  "geometry": {"coordinates":[151.18597412099999,-33.8159408569],"type":"Point"}
}