{
  "type": "Feature",
  "properties": {
    "iso:country":"AU",
    "sg:address":"Lvl 1 122 Fordham Rd",
    "sg:city":"Camberwell",
    "sg:classifiers":[
        {
            "category":"Shopping",
            "subcategory":"Computers & Home Electronics",
            "type":"Retail Goods"
        }
    ],
    "sg:phone":"+61 3 9889 7888",
    "sg:postcode":"3124",
    "sg:province":"VIC",
    "sg:tags":[
        "ergonomics"
    ],
    "wof:name":"Atkin Ergonomics",
    "wof:placetype":"venue"
},
  "geometry": {"coordinates":[145.076828003,-37.8445625305],"type":"Point"}
}