{
  "type": "Feature",
  "properties": {
    "addr:full":"13 Lawson Rd Happy Valley SA 5159",
    "addr:housenumber":"13",
    "addr:postcode":"5159",
    "addr:street":"Lawson Rd",
    "iso:country":"AU",
    "sg:address":"13 Lawson Rd",
    "sg:city":"Happy Valley",
    "sg:classifiers":[
        {
            "category":"Building & Trades",
            "subcategory":"Construction",
            "type":"Services"
        }
    ],
    "sg:phone":"+61 8 8381 1883",
    "sg:postcode":"5159",
    "sg:province":"SA",
    "sg:tags":[
        "joiner",
        "carpenter"
    ],
    "wof:name":"Barker G J",
    "wof:placetype":"venue"
},
  "geometry": {"coordinates":[138.569580078,-35.0867118835],"type":"Point"}
}