{
  "type": "Feature",
  "properties": {
    "addr:full":"PO Box 2134 Boronia Park NSW 2111",
    "addr:postcode":"2111",
    "iso:country":"AU",
    "sg:address":"PO Box 2134",
    "sg:city":"Boronia Park",
    "sg:classifiers":[
        {
            "category":"Professional",
            "subcategory":"Art Services",
            "type":"Services"
        }
    ],
    "sg:phone":"+61 2 9879 6705",
    "sg:postcode":"2111",
    "sg:province":"NSW",
    "sg:tags":[
        "arranger",
        "music",
        "composer"
    ],
    "wof:name":"Windchase Pty Ltd",
    "wof:placetype":"venue"
},
  "geometry": {"coordinates":[151.13375854500001,-33.8228187561],"type":"Point"}
}