{
  "type": "Feature",
  "properties": {
    "iso:country":"AU",
    "sg:address":"20 Moran Crt",
    "sg:city":"Vermont South",
    "sg:classifiers":[
        {
            "category":"Building & Trades",
            "subcategory":"Plumbing",
            "type":"Services"
        }
    ],
    "sg:phone":"+61 3 9802 8445",
    "sg:postcode":"3133",
    "sg:province":"VIC",
    "sg:tags":[
        "plumber",
        "gasfitters"
    ],
    "wof:name":"Moran Plumbing Pty Ltd",
    "wof:placetype":"venue"
},
  "geometry": {"coordinates":[145.17770385700001,-37.8603477478],"type":"Point"}
}