{
  "type": "Feature",
  "properties": {
    "iso:country":"AU",
    "sg:address":"267 Scarborough Beach Rd",
    "sg:city":"Mt Hawthorn",
    "sg:classifiers":[
        {
            "category":"Home & Garden",
            "subcategory":"Carpets & Floor Coverings",
            "type":"Retail Goods"
        }
    ],
    "sg:phone":"+61 8 9444 5809",
    "sg:postcode":"6016",
    "sg:province":"WA",
    "wof:name":"Artisan Rugs",
    "wof:placetype":"venue"
},
  "geometry": {"coordinates":[115.83518219,-31.9192829132],"type":"Point"}
}