{
  "type": "Feature",
  "properties": {
    "addr:full":"PO Box 6103 Lake Munmorah NSW 2259",
    "addr:postcode":"2259",
    "iso:country":"AU",
    "sg:address":"PO Box 6103",
    "sg:city":"Lake Munmorah",
    "sg:classifiers":[
        {
            "category":"Home & Garden",
            "subcategory":"Carpets & Floor Coverings",
            "type":"Retail Goods"
        }
    ],
    "sg:phone":"+61 2 4358 3865",
    "sg:postcode":"2259",
    "sg:province":"NSW",
    "sg:tags":[
        "tile",
        "wall",
        "layer"
    ],
    "wof:name":"DRJ Unique Floor & Wall Tiling",
    "wof:placetype":"venue"
},
  "geometry": {"coordinates":[151.48101806599999,-33.1748428345],"type":"Point"}
}