{
  "type": "Feature",
  "properties": {
    "addr:full":"Shop 4 The Link Arcade Central Ave Moorabbin VIC 3189",
    "addr:housenumber":"shop 4",
    "addr:postcode":"3189",
    "addr:street":"The Link;Central Ave",
    "iso:country":"AU",
    "sg:address":"Shop 4 The Link Arcade Central Ave",
    "sg:city":"Moorabbin",
    "sg:classifiers":[
        {
            "category":"Professional",
            "subcategory":"Employment Agencies",
            "type":"Services"
        }
    ],
    "sg:phone":"+61 3 9555 5859",
    "sg:postcode":"3189",
    "sg:province":"VIC",
    "sg:tags":[
        "entertainer",
        "agent"
    ],
    "wof:name":"Flanagan Enterprises Australia Pty Ltd",
    "wof:placetype":"venue"
},
  "geometry": {"coordinates":[145.039993286,-37.9352493286],"type":"Point"}
}