{
  "type": "Feature",
  "properties": {
    "addr:full":"Un 14/ 69 George St Beenleigh QLD 4207",
    "addr:housenumber":"/ 69",
    "addr:postcode":"4207",
    "addr:street":"George St",
    "iso:country":"AU",
    "sg:address":"Un 14/ 69 George St",
    "sg:city":"Beenleigh",
    "sg:classifiers":[
        {
            "category":"Banks & Credit Unions",
            "subcategory":"Financial Services",
            "type":"Services"
        }
    ],
    "sg:phone":"+61 7 3804 7899",
    "sg:postcode":"4207",
    "sg:province":"QLD",
    "sg:tags":[
        "planning"
    ],
    "wof:name":"State Invest Financial Services",
    "wof:placetype":"venue"
},
  "geometry": {"coordinates":[153.19923400900001,-27.7155780792],"type":"Point"}
}