{
  "type": "Feature",
  "properties": {
    "addr:full":"32 Rose St Brunswick VIC 3056",
    "addr:housenumber":"32",
    "addr:postcode":"3056",
    "addr:street":"Rose St",
    "iso:country":"AU",
    "sg:address":"32 Rose St",
    "sg:city":"Brunswick",
    "sg:classifiers":[
        {
            "category":"Wholesale",
            "subcategory":"Auto Parts",
            "type":"Manufacturing & Wholesale Goods"
        }
    ],
    "sg:phone":"+61 419 566 009",
    "sg:postcode":"3056",
    "sg:province":"VIC",
    "sg:tags":[
        "recyclers"
    ],
    "wof:name":"Smith J A",
    "wof:placetype":"venue"
},
  "geometry": {"coordinates":[144.952438355,-37.7576522827],"type":"Point"}
}