{
  "type": "Feature",
  "properties": {
    "iso:country":"AU",
    "sg:address":"Grnd Flr, World Trade Centre, Siddeley St",
    "sg:city":"Melbourne",
    "sg:classifiers":[
        {
            "category":"Sports & Exercise",
            "subcategory":"Gym",
            "type":"Entertainment"
        }
    ],
    "sg:phone":"+61 3 9621 2747",
    "sg:postcode":"3005",
    "sg:province":"VIC",
    "sg:tags":[
        "personal",
        "trainer",
        "fitness"
    ],
    "wof:name":"Docklands Gym",
    "wof:placetype":"venue"
},
  "geometry": {"coordinates":[144.95486450199999,-37.8222618103],"type":"Point"}
}