{
  "type": "Feature",
  "properties": {
    "addr:full":"Lot 92 Fairhaven Point Way Bermagui NSW 2546",
    "addr:postcode":"2546",
    "addr:street":"Point",
    "iso:country":"AU",
    "sg:address":"Lot 92 Fairhaven Point Way",
    "sg:city":"Bermagui",
    "sg:classifiers":[
        {
            "category":"Autos & Motor Vehicles",
            "subcategory":"Boat Sales",
            "type":"Retail Goods"
        }
    ],
    "sg:phone":"+61 2 6493 3152",
    "sg:postcode":"2546",
    "sg:province":"NSW",
    "sg:tags":[
        "yacht"
    ],
    "wof:name":"Repower Marine Bermagui Boat Brokers",
    "wof:placetype":"venue"
},
  "geometry": {"coordinates":[150.07612609899999,-36.4285583496],"type":"Point"}
}