{
  "type": "Feature",
  "properties": {
    "addr:full":"3/ 113a Walker St Waterloo NSW 2017",
    "addr:housenumber":"/ 113a",
    "addr:postcode":"2017",
    "addr:street":"Walker St",
    "iso:country":"AU",
    "sg:address":"3/ 113a Walker St",
    "sg:city":"Waterloo",
    "sg:classifiers":[
        {
            "category":"Professional",
            "subcategory":"Art Services",
            "type":"Services"
        }
    ],
    "sg:phone":"+61 2 9310 1878",
    "sg:postcode":"2017",
    "sg:province":"NSW",
    "sg:tags":[
        "product",
        "industrial",
        "designer"
    ],
    "wof:name":"Green Christopher M.A. Studio",
    "wof:placetype":"venue"
},
  "geometry": {"coordinates":[151.20767211899999,-33.8974494934],"type":"Point"}
}