{
  "type": "Feature",
  "properties": {
    "iso:country":"AU",
    "sg:address":"Cnr Narre Warren Nth Rd & Kurrajong Rd",
    "sg:city":"Narre Warren",
    "sg:classifiers":[
        {
            "category":"Health Services",
            "subcategory":"Doctor",
            "type":"Services"
        }
    ],
    "sg:phone":"+61 3 9704 8011",
    "sg:postcode":"3805",
    "sg:province":"VIC",
    "sg:tags":[
        "medical",
        "practitioner"
    ],
    "wof:name":"Fountain Gate Medical Centre",
    "wof:placetype":"venue"
},
  "geometry": {"coordinates":[145.312103,-38.015018],"type":"Point"}
}