{
  "type": "Feature",
  "properties": {
    "addr:full":"72 Main Rd Lancefield VIC 3435",
    "addr:housenumber":"72",
    "addr:postcode":"3435",
    "addr:street":"Main Rd",
    "iso:country":"AU",
    "sg:address":"72 Main Rd",
    "sg:city":"Lancefield",
    "sg:classifiers":[
        {
            "category":"Bars & Pubs",
            "subcategory":"Wine Bar",
            "type":"Food & Drink"
        }
    ],
    "sg:phone":"+61 3 5429 1666",
    "sg:postcode":"3435",
    "sg:province":"VIC",
    "wof:name":"Macedonia At Lancefield",
    "wof:placetype":"venue"
},
  "geometry": {"coordinates":[144.736694336,-37.2755966187],"type":"Point"}
}