{
  "type": "Feature",
  "properties": {
    "iso:country":"AU",
    "sg:address":"28 Cumberland St",
    "sg:city":"Cessnock",
    "sg:classifiers":[
        {
            "category":"Health Services",
            "subcategory":"Doctor",
            "type":"Services"
        }
    ],
    "sg:phone":"+61 2 4990 4766",
    "sg:postcode":"2325",
    "sg:province":"NSW",
    "sg:tags":[
        "medical",
        "practitioner"
    ],
    "wof:name":"Mayne Laverty Pathology Collection Centres",
    "wof:placetype":"venue"
},
  "geometry": {"coordinates":[151.357330322,-32.836025238],"type":"Point"}
}