{
  "type": "Feature",
  "properties": {
    "iso:country":"AU",
    "sg:address":"36 Lexington Dr",
    "sg:city":"Worongary",
    "sg:classifiers":[
        {
            "category":"Professional",
            "subcategory":"Art Services",
            "type":"Services"
        }
    ],
    "sg:phone":"+61 7 5630 2042",
    "sg:postcode":"4213",
    "sg:province":"QLD",
    "sg:tags":[
        "product",
        "industrial",
        "designer"
    ],
    "wof:name":"Twyford Engineering",
    "wof:placetype":"venue"
},
  "geometry": {"coordinates":[153.34710693400001,-28.0340633392],"type":"Point"}
}