{
  "type": "Feature",
  "properties": {
    "iso:country":"AU",
    "sg:address":"3 Crawford Rd",
    "sg:city":"Wynnum West",
    "sg:classifiers":[
        {
            "category":"Social Services",
            "subcategory":"Child Care",
            "type":"Services"
        }
    ],
    "sg:phone":"+61 7 3893 0511",
    "sg:postcode":"4178",
    "sg:province":"QLD",
    "wof:name":"Wynnum West Early Learning Centres",
    "wof:placetype":"venue"
},
  "geometry": {"coordinates":[153.14317321799999,-27.4481334686],"type":"Point"}
}