{
  "type": "Feature",
  "properties": {
    "iso:country":"AU",
    "sg:address":"10 Dryden Crt",
    "sg:city":"Woodend North",
    "sg:classifiers":[
        {
            "category":"Utilities",
            "subcategory":"Refuse",
            "type":"Services"
        }
    ],
    "sg:phone":"+61 1300 721 968",
    "sg:postcode":"3442",
    "sg:province":"VIC",
    "sg:tags":[
        "disposal",
        "reduction",
        "waste"
    ],
    "wof:name":"Midland Environmental Services",
    "wof:placetype":"venue"
},
  "geometry": {"coordinates":[144.53883361800001,-37.3258247375],"type":"Point"}
}