{
  "type": "Feature",
  "properties": {
    "addr:full":"46 Colin St West Perth WA 6005",
    "addr:housenumber":"46",
    "addr:postcode":"6005",
    "addr:street":"Colin St",
    "iso:country":"AU",
    "sg:address":"46 Colin St",
    "sg:city":"West Perth",
    "sg:classifiers":[
        {
            "category":"Insurance",
            "subcategory":"Hazard Insurance",
            "type":"Services"
        }
    ],
    "sg:phone":"+61 8 9254 3600",
    "sg:postcode":"6005",
    "sg:province":"WA",
    "sg:tags":[
        "fire",
        "accident",
        "marine"
    ],
    "wof:name":"CGU Professional Risks",
    "wof:placetype":"venue"
},
  "geometry": {"coordinates":[115.841499329,-31.9498138428],"type":"Point"}
}