{
  "type": "Feature",
  "properties": {
    "addr:full":"Unit 1, 278 Newmarket Rd Wilston QLD 4051",
    "addr:housenumber":"278",
    "addr:postcode":"4051",
    "addr:street":"Newmarket Rd",
    "iso:country":"AU",
    "sg:address":"Unit 1, 278 Newmarket Rd",
    "sg:city":"Wilston",
    "sg:classifiers":[
        {
            "category":"Shopping",
            "subcategory":"Clothing, Apparel, & Fashions",
            "type":"Retail Goods"
        }
    ],
    "sg:phone":"+61 7 3356 6546",
    "sg:postcode":"4051",
    "sg:province":"QLD",
    "sg:tags":[
        "recycled",
        "clothing"
    ],
    "wof:name":"Lifeline Clothing Shops",
    "wof:placetype":"venue"
},
  "geometry": {"coordinates":[153.01541137699999,-27.435918808],"type":"Point"}
}