{
  "type": "Feature",
  "properties": {
    "iso:country":"AU",
    "sg:address":"40 Sydney Rd",
    "sg:city":"Manly",
    "sg:classifiers":[
        {
            "category":"Recreation",
            "subcategory":"Boat Charter",
            "type":"Entertainment"
        }
    ],
    "sg:phone":"+61 2 9977 5077",
    "sg:postcode":"2095",
    "sg:province":"NSW",
    "sg:tags":[
        "hire",
        "drive"
    ],
    "wof:name":"Boatingclub.info",
    "wof:placetype":"venue"
},
  "geometry": {"coordinates":[151.28680419899999,-33.7914466858],"type":"Point"}
}