{
  "type": "Feature",
  "properties": {
    "addr:full":"Martyn St Manunda QLD 4870",
    "addr:postcode":"4870",
    "addr:street":"Martyn St",
    "iso:country":"AU",
    "sg:address":"Martyn St",
    "sg:city":"Manunda",
    "sg:classifiers":[
        {
            "category":"Sports & Exercise",
            "subcategory":"Sports Center",
            "type":"Entertainment"
        }
    ],
    "sg:phone":"+61 7 4051 7501",
    "sg:postcode":"4870",
    "sg:province":"QLD",
    "sg:tags":[
        "ground"
    ],
    "wof:name":"Cairns Netball Association",
    "wof:placetype":"venue"
},
  "geometry": {"coordinates":[145.756027222,-16.9134426117],"type":"Point"}
}