{
  "type": "Feature",
  "properties": {
    "iso:country":"AU",
    "sg:address":"90 Bondi Rd",
    "sg:city":"Bondi Junction",
    "sg:classifiers":[
        {
            "category":"Professional",
            "subcategory":"Art Services",
            "type":"Services"
        }
    ],
    "sg:phone":"+61 2 9389 6642",
    "sg:postcode":"2022",
    "sg:province":"NSW",
    "sg:tags":[
        "picture",
        "frame",
        "framing"
    ],
    "wof:name":"Right Angles Picture Framing",
    "wof:placetype":"venue"
},
  "geometry": {"coordinates":[151.25733947800001,-33.8928604126],"type":"Point"}
}