{
  "type": "Feature",
  "properties": {
    "addr:full":"75 Canagra Crs Greenwood WA 6024",
    "addr:housenumber":"75",
    "addr:postcode":"6024",
    "addr:street":"Canagra Crs",
    "iso:country":"AU",
    "sg:address":"75 Canagra Crs",
    "sg:city":"Greenwood",
    "sg:classifiers":[
        {
            "category":"Manufacturing",
            "subcategory":"Wood Products",
            "type":"Manufacturing & Wholesale Goods"
        }
    ],
    "sg:phone":"+61 8 9448 4792",
    "sg:postcode":"6024",
    "sg:province":"WA",
    "sg:tags":[
        "polisher",
        "french"
    ],
    "wof:name":"Trevor Skeels",
    "wof:placetype":"venue"
},
  "geometry": {"coordinates":[115.801742554,-31.8309402466],"type":"Point"}
}