{
  "type": "Feature",
  "properties": {
    "addr:full":"BKK Shopping Centre, Shop 10, Evans Ave Eastlakes NSW 2018",
    "addr:housenumber":"shop 10",
    "addr:postcode":"2018",
    "addr:street":"Evans Ave",
    "iso:country":"AU",
    "sg:address":"BKK Shopping Centre, Shop 10, Evans Ave",
    "sg:city":"Eastlakes",
    "sg:classifiers":[
        {
            "category":"Food & Beverages",
            "subcategory":"Supermarket",
            "type":"Retail Goods"
        }
    ],
    "sg:phone":"+61 2 9667 0697",
    "sg:postcode":"2018",
    "sg:province":"NSW",
    "sg:tags":[
        "grocery",
        "store"
    ],
    "wof:name":"Woolworths Limited",
    "wof:placetype":"venue"
},
  "geometry": {"coordinates":[151.20939636200001,-33.9245033264],"type":"Point"}
}