{
  "type": "Feature",
  "properties": {
    "iso:country":"AU",
    "sg:address":"475 Edward Rd",
    "sg:city":"Geraldton",
    "sg:classifiers":[
        {
            "category":"Manufacturing",
            "subcategory":"Tools & Machinery",
            "type":"Manufacturing & Wholesale Goods"
        }
    ],
    "sg:phone":"+61 8 9923 7000",
    "sg:postcode":"6530",
    "sg:province":"WA",
    "sg:tags":[
        "earth",
        "excavating",
        "moving",
        "equipment"
    ],
    "wof:name":"Northcoast Contractors Pty Ltd",
    "wof:placetype":"venue"
},
  "geometry": {"coordinates":[114.65701294,-28.7809333801],"type":"Point"}
}