{
  "type": "Feature",
  "properties": {
    "addr:full":"3 Milewa Ave Malvern East VIC 3145",
    "addr:housenumber":"3",
    "addr:postcode":"3145",
    "addr:street":"Milewa Ave",
    "iso:country":"AU",
    "sg:address":"3 Milewa Ave",
    "sg:city":"Malvern East",
    "sg:classifiers":[
        {
            "category":"Banks & Credit Unions",
            "subcategory":"Bank",
            "type":"Services"
        }
    ],
    "sg:phone":"+61 3 9568 3626",
    "sg:postcode":"3145",
    "sg:province":"VIC",
    "sg:tags":[
        "broker",
        "mortgage"
    ],
    "wof:name":"Smartline",
    "wof:placetype":"venue"
},
  "geometry": {"coordinates":[145.07469177199999,-37.8853416443],"type":"Point"}
}