{
  "type": "Feature",
  "properties": {
    "addr:full":"76 Shute Harbour Rd Cannonvale QLD 4802",
    "addr:housenumber":"76",
    "addr:postcode":"4802",
    "addr:street":"Shute Harbour Rd",
    "iso:country":"AU",
    "sg:address":"76 Shute Harbour Rd",
    "sg:city":"Cannonvale",
    "sg:classifiers":[
        {
            "category":"Professional",
            "subcategory":"Art Services",
            "type":"Services"
        }
    ],
    "sg:phone":"+61 438 184 441",
    "sg:postcode":"4802",
    "sg:province":"QLD",
    "sg:tags":[
        "picture",
        "frame",
        "framing"
    ],
    "wof:name":"Frames Away",
    "wof:placetype":"venue"
},
  "geometry": {"coordinates":[148.68797302199999,-20.2832527161],"type":"Point"}
}