{
  "type": "Feature",
  "properties": {
    "addr:full":"Old Federal Brewery Building 2/24 The Esplanade Wagga Wagga NSW 2650",
    "addr:housenumber":"/ 24",
    "addr:postcode":"2650",
    "addr:street":"The Esplanade",
    "iso:country":"AU",
    "sg:address":"Old Federal Brewery Building 2/24 The Esplanade",
    "sg:city":"Wagga Wagga",
    "sg:classifiers":[
        {
            "category":"Banks & Credit Unions",
            "subcategory":"Financial Services",
            "type":"Services"
        }
    ],
    "sg:phone":"+61 2 6921 1813",
    "sg:postcode":"2650",
    "sg:province":"NSW",
    "sg:tags":[
        "annuity",
        "rollover",
        "superannuation",
        "consultant"
    ],
    "wof:name":"ASB Financial Services",
    "wof:placetype":"venue"
},
  "geometry": {"coordinates":[147.366577148,-35.1102981567],"type":"Point"}
}