{
  "type": "Feature",
  "properties": {
    "iso:country":"AU",
    "sg:address":"10- 12 Industrial Ave",
    "sg:city":"Hoppers Crossing",
    "sg:classifiers":[
        {
            "category":"Professional",
            "type":"Services"
        }
    ],
    "sg:phone":"+61 3 9364 5888",
    "sg:postcode":"3029",
    "sg:province":"VIC",
    "sg:tags":[
        "forwarding",
        "agent",
        "transport"
    ],
    "wof:name":"Manila Freight Forwarder Australia Pty Ltd",
    "wof:placetype":"venue"
},
  "geometry": {"coordinates":[144.72631799999999,-37.869007],"type":"Point"}
}