{
  "type": "Feature",
  "properties": {
    "addr:full":"76 Railway Pde Welshpool WA 6106",
    "addr:housenumber":"76",
    "addr:postcode":"6106",
    "addr:street":"Railway Pde",
    "iso:country":"AU",
    "sg:address":"76 Railway Pde",
    "sg:city":"Welshpool",
    "sg:classifiers":[
        {
            "category":"Professional",
            "subcategory":"Engineering",
            "type":"Services"
        }
    ],
    "sg:phone":"+61 8 9451 8405",
    "sg:postcode":"6106",
    "sg:province":"WA",
    "sg:tags":[
        "manufacturing",
        "engineer"
    ],
    "wof:name":"Quality Sheet Metals",
    "wof:placetype":"venue"
},
  "geometry": {"coordinates":[115.93195342999999,-32.0011978149],"type":"Point"}
}