{
  "type": "Feature",
  "properties": {
    "addr:full":"Shp2/ 156 The Boulevarde Miranda NSW 2228",
    "addr:housenumber":"156",
    "addr:postcode":"2228",
    "addr:street":"The Boulevarde Miranda",
    "iso:country":"AU",
    "sg:address":"Shp2/ 156",
    "sg:city":"The Boulevarde Miranda",
    "sg:classifiers":[
        {
            "category":"Fast Food",
            "type":"Food & Drink"
        }
    ],
    "sg:phone":"+61 2 9524 0022",
    "sg:postcode":"2228",
    "sg:province":"NSW",
    "sg:tags":[
        "away",
        "take"
    ],
    "wof:name":"The Boulevarde Pizza & Grill",
    "wof:placetype":"venue"
},
  "geometry": {"coordinates":[151.102493286,-34.033908844],"type":"Point"}
}