{
  "type": "Feature",
  "properties": {
    "iso:country":"AU",
    "sg:address":"25 King St",
    "sg:city":"Scottsdale",
    "sg:classifiers":[
        {
            "category":"Communications",
            "subcategory":"Film & Video Production",
            "type":"Services"
        }
    ],
    "sg:phone":"+61 3 6352 4224",
    "sg:postcode":"7260",
    "sg:province":"TAS",
    "sg:tags":[
        "dvd",
        "library"
    ],
    "wof:name":"Top Video Scottsdale",
    "wof:placetype":"venue"
},
  "geometry": {"coordinates":[147.516602,-41.161133],"type":"Point"}
}