{
  "type": "Feature",
  "properties": {
    "iso:country":"AU",
    "sg:address":"Level 1/ 18 Thurso Rd",
    "sg:city":"Myaree",
    "sg:classifiers":[
        {
            "category":"Manufacturing",
            "subcategory":"Apparel",
            "type":"Manufacturing & Wholesale Goods"
        }
    ],
    "sg:phone":"+61 8 9330 9244",
    "sg:postcode":"6154",
    "sg:province":"WA",
    "sg:tags":[
        "wholesaler",
        "mfrs",
        "footwear"
    ],
    "wof:name":"Repete Agencies",
    "wof:placetype":"venue"
},
  "geometry": {"coordinates":[115.809097,-32.045803],"type":"Point"}
}