{
  "type": "Feature",
  "properties": {
    "addr:full":"Tweed City, 54 Minjungbal Drv Tweed Heads South NSW 2486",
    "addr:housenumber":"54",
    "addr:postcode":"2486",
    "addr:street":"Minjungbal Drv",
    "iso:country":"AU",
    "sg:address":"Tweed City, 54 Minjungbal Drv",
    "sg:city":"Tweed Heads South",
    "sg:classifiers":[
        {
            "category":"Shopping",
            "subcategory":"Mobile Phones",
            "type":"Retail Goods"
        }
    ],
    "sg:phone":"+61 7 5523 4901",
    "sg:postcode":"2486",
    "sg:province":"NSW",
    "sg:tags":[
        "telephone",
        "accessory"
    ],
    "wof:name":"Fone Zone",
    "wof:placetype":"venue"
},
  "geometry": {"coordinates":[153.544525147,-28.2034740448],"type":"Point"}
}