{
  "type": "Feature",
  "properties": {
    "addr:full":"17 Hotham Pde Artarmon NSW 2064",
    "addr:housenumber":"17",
    "addr:postcode":"2064",
    "addr:street":"Hotham Pde",
    "iso:country":"AU",
    "sg:address":"17 Hotham Pde",
    "sg:city":"Artarmon",
    "sg:classifiers":[
        {
            "category":"Retail",
            "subcategory":"Auto Repair",
            "type":"Services"
        }
    ],
    "sg:phone":"+61 2 9906 3344",
    "sg:postcode":"2064",
    "sg:province":"NSW",
    "sg:tags":[
        "beater",
        "painter",
        "panel"
    ],
    "wof:name":"Carcraft Smash Repairs",
    "wof:placetype":"venue"
},
  "geometry": {"coordinates":[151.183319092,-33.8138542175],"type":"Point"}
}