{
  "type": "Feature",
  "properties": {
    "addr:full":"15 Elizabeth Ave Taree NSW 2430",
    "addr:housenumber":"15",
    "addr:postcode":"2430",
    "addr:street":"Elizabeth Ave",
    "iso:country":"AU",
    "sg:address":"15 Elizabeth Ave",
    "sg:city":"Taree",
    "sg:classifiers":[
        {
            "category":"Wholesale",
            "subcategory":"Chemicals & Plastics",
            "type":"Manufacturing & Wholesale Goods"
        }
    ],
    "sg:phone":"+61 2 6551 0599",
    "sg:postcode":"2430",
    "sg:province":"NSW",
    "sg:tags":[
        "repair"
    ],
    "wof:name":"Taree Windscreen Services",
    "wof:placetype":"venue"
},
  "geometry": {"coordinates":[152.45517000000001,-31.90122],"type":"Point"}
}