{
  "type": "Feature",
  "properties": {
    "iso:country":"AU",
    "sg:address":"3 Ligar St",
    "sg:city":"Woodend",
    "sg:classifiers":[
        {
            "category":"Wholesale",
            "subcategory":"Farm Supplies",
            "type":"Manufacturing & Wholesale Goods"
        }
    ],
    "sg:phone":"+61 3 5427 1688",
    "sg:postcode":"3442",
    "sg:province":"VIC",
    "sg:tags":[
        "feed",
        "supplement",
        "stock"
    ],
    "wof:name":"Mountview Farm Supplies & Produce",
    "wof:placetype":"venue"
},
  "geometry": {"coordinates":[144.533004761,-37.3609008789],"type":"Point"}
}