{
  "type": "Feature",
  "properties": {
    "iso:country":"AU",
    "sg:address":"PO Box 911",
    "sg:city":"Panton Hill",
    "sg:classifiers":[
        {
            "category":"Utilities",
            "subcategory":"Electric",
            "type":"Services"
        }
    ],
    "sg:phone":"+61 438 197 976",
    "sg:postcode":"3759",
    "sg:province":"VIC",
    "sg:tags":[
        "electrical",
        "contractor"
    ],
    "wof:name":"C N C Electrics",
    "wof:placetype":"venue"
},
  "geometry": {"coordinates":[145.250473,-37.640678],"type":"Point"}
}