{
  "type": "Feature",
  "properties": {
    "iso:country":"AU",
    "sg:address":"PO Box 309",
    "sg:city":"Spit Junction",
    "sg:classifiers":[
        {
            "category":"Professional",
            "subcategory":"Management & Consulting",
            "type":"Services"
        }
    ],
    "sg:phone":"+61 2 9969 9450",
    "sg:postcode":"2088",
    "sg:province":"NSW",
    "sg:tags":[
        "consultant"
    ],
    "wof:name":"GBM & Associates",
    "wof:placetype":"venue"
},
  "geometry": {"coordinates":[151.24139404300001,-33.8247413635],"type":"Point"}
}