{
  "type": "Feature",
  "properties": {
    "iso:country":"AU",
    "sg:address":"14 Sunbeam Rd",
    "sg:city":"Glynde",
    "sg:classifiers":[
        {
            "category":"Home & Garden",
            "subcategory":"Building Materials",
            "type":"Retail Goods"
        }
    ],
    "sg:phone":"+61 8 8365 2688",
    "sg:postcode":"5070",
    "sg:province":"SA",
    "sg:tags":[
        "fitting",
        "door"
    ],
    "wof:name":"Universal Aluminium Pty Ltd",
    "wof:placetype":"venue"
},
  "geometry": {"coordinates":[138.653167725,-34.895324707],"type":"Point"}
}