{
  "type": "Feature",
  "properties": {
    "addr:full":"16- 18 National Blv Campbellfield VIC 3061",
    "addr:housenumber":"18",
    "addr:postcode":"3061",
    "addr:street":"National Blv",
    "iso:country":"AU",
    "sg:address":"16- 18",
    "sg:city":"National Blv Campbellfield",
    "sg:classifiers":[
        {
            "category":"Freight",
            "type":"Transportation"
        }
    ],
    "sg:phone":"+61 3 9793 6908",
    "sg:postcode":"3061",
    "sg:province":"VIC",
    "sg:tags":[
        "transport",
        "refrigerated"
    ],
    "wof:name":"Ice Man Fibreglass",
    "wof:placetype":"venue"
},
  "geometry": {"coordinates":[144.951248169,-37.6552963257],"type":"Point"}
}