{
  "type": "Feature",
  "properties": {
    "iso:country":"AU",
    "sg:address":"8 Kempsey St",
    "sg:city":"Blacktown",
    "sg:classifiers":[
        {
            "category":"Autos & Motor Vehicles",
            "subcategory":"Auto Supplies",
            "type":"Retail Goods"
        }
    ],
    "sg:phone":"+61 2 9831 8622",
    "sg:postcode":"2148",
    "sg:province":"NSW",
    "sg:tags":[
        "car",
        "alarm"
    ],
    "wof:name":"Maximum System",
    "wof:placetype":"venue"
},
  "geometry": {"coordinates":[150.912765503,-33.7746429443],"type":"Point"}
}