{
  "type": "Feature",
  "properties": {
    "iso:country":"AU",
    "sg:address":"Albany Market Pl",
    "sg:city":"Albany Creek",
    "sg:classifiers":[
        {
            "category":"Fast Food",
            "type":"Food & Drink"
        }
    ],
    "sg:phone":"+61 7 3264 2577",
    "sg:postcode":"4035",
    "sg:province":"QLD",
    "sg:tags":[
        "away",
        "take"
    ],
    "wof:name":"Tides Inn Home Delivery",
    "wof:placetype":"venue"
},
  "geometry": {"coordinates":[152.96537799999999,-27.34589],"type":"Point"}
}