{
  "type": "Feature",
  "properties": {
    "addr:full":"145 Langtree Ave Mildura VIC 3500",
    "addr:housenumber":"145",
    "addr:postcode":"3500",
    "addr:street":"Langtree Ave",
    "iso:country":"AU",
    "sg:address":"145 Langtree Ave",
    "sg:city":"Mildura",
    "sg:classifiers":[
        {
            "category":"Health Services",
            "subcategory":"Doctor",
            "type":"Services"
        }
    ],
    "sg:phone":"+61 3 5023 5156",
    "sg:postcode":"3500",
    "sg:province":"VIC",
    "sg:tags":[
        "medical",
        "practitioner"
    ],
    "wof:name":"Skorupanovic V",
    "wof:placetype":"venue"
},
  "geometry": {"coordinates":[142.15696716299999,-34.1877365112],"type":"Point"}
}