{
  "type": "Feature",
  "properties": {
    "addr:full":"38 Macleay St Potts Point NSW 2011",
    "addr:housenumber":"38",
    "addr:postcode":"2011",
    "addr:street":"Macleay St",
    "iso:country":"AU",
    "sg:address":"38 Macleay St",
    "sg:city":"Potts Point",
    "sg:classifiers":[
        {
            "category":"Travel",
            "subcategory":"Hotels & Motels",
            "type":"Entertainment"
        }
    ],
    "sg:phone":"+61 2 9358 2400",
    "sg:postcode":"2011",
    "sg:province":"NSW",
    "sg:tags":[
        "accommodation"
    ],
    "wof:name":"Dorchaster Inn",
    "wof:placetype":"venue"
},
  "geometry": {"coordinates":[151.22549438499999,-33.8705253601],"type":"Point"}
}