{
  "type": "Feature",
  "properties": {
    "addr:full":"43 John Ryan Drv South Morang VIC 3752",
    "addr:housenumber":"43",
    "addr:postcode":"3752",
    "addr:street":"John Ryan Drv",
    "iso:country":"AU",
    "sg:address":"43 John Ryan Drv",
    "sg:city":"South Morang",
    "sg:classifiers":[
        {
            "category":"Retail",
            "subcategory":"Auto Repair",
            "type":"Services"
        }
    ],
    "sg:phone":"+61 3 9436 6655",
    "sg:postcode":"3752",
    "sg:province":"VIC",
    "sg:tags":[
        "repairer",
        "motor",
        "engineer"
    ],
    "wof:name":"Exactatune",
    "wof:placetype":"venue"
},
  "geometry": {"coordinates":[145.09863281200001,-37.6562767029],"type":"Point"}
}