{
  "type": "Feature",
  "properties": {
    "addr:full":"89 Heatherdale Rd Ringwood VIC 3134",
    "addr:housenumber":"89",
    "addr:postcode":"3134",
    "addr:street":"Heatherdale Rd",
    "iso:country":"AU",
    "sg:address":"89 Heatherdale Rd",
    "sg:city":"Ringwood",
    "sg:classifiers":[
        {
            "category":"Building & Trades",
            "subcategory":"Equipment Rental",
            "type":"Services"
        }
    ],
    "sg:phone":"+61 3 8872 7888",
    "sg:postcode":"3134",
    "sg:province":"VIC",
    "sg:tags":[
        "demolition",
        "contractor"
    ],
    "sg:website":"http://www.able.com.au",
    "wof:name":"Able Demolitions & Excavations Pty Ltd",
    "wof:placetype":"venue"
},
  "geometry": {"coordinates":[145.213500977,-37.825668335],"type":"Point"}
}