{
  "type": "Feature",
  "properties": {
    "addr:full":"86 Main St Proserpine QLD 4800",
    "addr:housenumber":"86",
    "addr:postcode":"4800",
    "addr:street":"Main St",
    "iso:country":"AU",
    "sg:address":"86 Main St",
    "sg:city":"Proserpine",
    "sg:classifiers":[
        {
            "category":"Professional",
            "subcategory":"Accounting & Tax Preparation",
            "type":"Services"
        }
    ],
    "sg:phone":"+61 7 4945 1777",
    "sg:postcode":"4800",
    "sg:province":"QLD",
    "sg:tags":[
        "accountant",
        "auditor"
    ],
    "wof:name":"CE Smith & Co Proserpine",
    "wof:placetype":"venue"
},
  "geometry": {"coordinates":[148.583450317,-20.4019165039],"type":"Point"}
}