{
  "type": "Feature",
  "properties": {
    "addr:full":"25 Marshall Ave St Leonards NSW 2065",
    "addr:housenumber":"25",
    "addr:postcode":"2065",
    "addr:street":"Marshall Ave",
    "iso:country":"AU",
    "sg:address":"25 Marshall Ave",
    "sg:city":"St Leonards",
    "sg:classifiers":[
        {
            "category":"Health Services",
            "subcategory":"Health Practitioner",
            "type":"Services"
        }
    ],
    "sg:phone":"+61 407 063 300",
    "sg:postcode":"2065",
    "sg:province":"NSW",
    "sg:tags":[
        "psychotherapist"
    ],
    "wof:name":"Burns Lee",
    "wof:placetype":"venue"
},
  "geometry": {"coordinates":[151.19244384800001,-33.8247909546],"type":"Point"}
}