{
  "type": "Feature",
  "properties": {
    "addr:full":"58 Tamboon Drv St Helena VIC 3088",
    "addr:housenumber":"58",
    "addr:postcode":"3088",
    "addr:street":"Tamboon Drv",
    "iso:country":"AU",
    "sg:address":"58 Tamboon Drv",
    "sg:city":"St Helena",
    "sg:classifiers":[
        {
            "category":"Banks & Credit Unions",
            "subcategory":"Bureau De Change",
            "type":"Services"
        }
    ],
    "sg:phone":"+61 3 9432 1992",
    "sg:postcode":"3088",
    "sg:province":"VIC",
    "sg:tags":[
        "preparation",
        "processing",
        "data"
    ],
    "wof:name":"DataPrep",
    "wof:placetype":"venue"
},
  "geometry": {"coordinates":[145.13214111299999,-37.6938056946],"type":"Point"}
}