{
  "type": "Feature",
  "properties": {
    "iso:country":"AU",
    "sg:address":"Level 1, 294 King St",
    "sg:city":"Newtown",
    "sg:classifiers":[
        {
            "category":"Sports & Exercise",
            "subcategory":"Gym",
            "type":"Entertainment"
        }
    ],
    "sg:phone":"+61 2 9519 6969",
    "sg:postcode":"2042",
    "sg:province":"NSW",
    "sg:tags":[
        "health",
        "fitness"
    ],
    "wof:name":"Newtown Gym",
    "wof:placetype":"venue"
},
  "geometry": {"coordinates":[151.17991599999999,-33.896652],"type":"Point"}
}