{
  "type": "Feature",
  "properties": {
    "addr:full":"2 Panitz St Sorrento QLD 4217",
    "addr:housenumber":"2",
    "addr:postcode":"4217",
    "addr:street":"Panitz St",
    "iso:country":"AU",
    "sg:address":"2 Panitz St",
    "sg:city":"Sorrento",
    "sg:classifiers":[
        {
            "category":"Food & Beverages",
            "subcategory":"Fruits & Vegetables",
            "type":"Retail Goods"
        }
    ],
    "sg:phone":"+61 411 590 425",
    "sg:postcode":"4217",
    "sg:province":"QLD",
    "sg:tags":[
        "consultant",
        "catering"
    ],
    "wof:name":"J R's Spit Roasts",
    "wof:placetype":"venue"
},
  "geometry": {"coordinates":[153.40153503400001,-28.0225372314],"type":"Point"}
}