{
  "type": "Feature",
  "properties": {
    "iso:country":"AU",
    "sg:address":"500 Port Rd",
    "sg:city":"Hindmarsh",
    "sg:classifiers":[
        {
            "category":"Health Services",
            "subcategory":"Dentist",
            "type":"Services"
        }
    ],
    "sg:phone":"+61 8 8340 1142",
    "sg:postcode":"5007",
    "sg:province":"SA",
    "wof:name":"Le Ann Dr",
    "wof:placetype":"venue"
},
  "geometry": {"coordinates":[138.55894470199999,-34.8969688416],"type":"Point"}
}