{
  "type": "Feature",
  "properties": {
    "addr:full":"10 Hobson St Queenscliff VIC 3225",
    "addr:housenumber":"10",
    "addr:postcode":"3225",
    "addr:street":"Hobson St",
    "iso:country":"AU",
    "sg:address":"10 Hobson St",
    "sg:city":"Queenscliff",
    "sg:classifiers":[
        {
            "category":"Personal",
            "type":"Services"
        }
    ],
    "sg:phone":"+61 3 5258 1307",
    "sg:postcode":"3225",
    "sg:province":"VIC",
    "sg:tags":[
        "gift"
    ],
    "wof:name":"The New Queenscliff Florist",
    "wof:placetype":"venue"
},
  "geometry": {"coordinates":[144.661102,-38.266838],"type":"Point"}
}