{
  "type": "Feature",
  "properties": {
    "addr:full":"101 Tooronga Rd Glen Iris VIC 3146",
    "addr:housenumber":"101",
    "addr:postcode":"3146",
    "addr:street":"Tooronga Rd",
    "iso:country":"AU",
    "sg:address":"101 Tooronga Rd",
    "sg:city":"Glen Iris",
    "sg:classifiers":[
        {
            "category":"Social Services",
            "subcategory":"Child Care",
            "type":"Services"
        }
    ],
    "sg:phone":"+61 3 9509 1896",
    "sg:postcode":"3146",
    "sg:province":"VIC",
    "wof:name":"Malvern Day Nursery",
    "wof:placetype":"venue"
},
  "geometry": {"coordinates":[145.040084839,-37.8632698059],"type":"Point"}
}