{
  "type": "Feature",
  "properties": {
    "iso:country":"AU",
    "sg:address":"North St",
    "sg:city":"Thirlmere",
    "sg:classifiers":[
        {
            "category":"Shopping",
            "subcategory":"Baby Store",
            "type":"Retail Goods"
        }
    ],
    "sg:phone":"+61 2 4681 8583",
    "sg:postcode":"2572",
    "sg:province":"NSW",
    "sg:tags":[
        "children's",
        "wear"
    ],
    "wof:name":"Scribbly Graphics Pty Ltd",
    "wof:placetype":"venue"
},
  "geometry": {"coordinates":[150.568527222,-34.2003059387],"type":"Point"}
}