{
  "type": "Feature",
  "properties": {
    "addr:full":"Unit 17 82 Campbell Rd Hawthorn East VIC 3123",
    "addr:housenumber":"82",
    "addr:postcode":"3123",
    "addr:street":"Campbell Rd",
    "iso:country":"AU",
    "sg:address":"Unit 17 82 Campbell Rd",
    "sg:city":"Hawthorn East",
    "sg:classifiers":[
        {
            "category":"Professional",
            "subcategory":"Art Services",
            "type":"Services"
        }
    ],
    "sg:phone":"+61 3 9882 2662",
    "sg:postcode":"3123",
    "sg:province":"VIC",
    "sg:tags":[
        "graphic",
        "designer"
    ],
    "wof:name":"John Williams Design",
    "wof:placetype":"venue"
},
  "geometry": {"coordinates":[145.05456543,-37.833782196],"type":"Point"}
}