{
  "type": "Feature",
  "properties": {
    "addr:full":"288 Victoria Rd Gladesville NSW 2111",
    "addr:housenumber":"288",
    "addr:postcode":"2111",
    "addr:street":"Victoria Rd",
    "iso:country":"AU",
    "sg:address":"288 Victoria Rd",
    "sg:city":"Gladesville",
    "sg:classifiers":[
        {
            "category":"Banks & Credit Unions",
            "subcategory":"Investment Brokerage",
            "type":"Services"
        }
    ],
    "sg:phone":"+61 2 9817 3901",
    "sg:postcode":"2111",
    "sg:province":"NSW",
    "sg:tags":[
        "radiator",
        "motor"
    ],
    "wof:name":"Gladesville Radiators",
    "wof:placetype":"venue"
},
  "geometry": {"coordinates":[151.126342773,-33.8280143738],"type":"Point"}
}