{
  "type": "Feature",
  "properties": {
    "addr:full":"285 Marmion St Melville WA 6156",
    "addr:housenumber":"285",
    "addr:postcode":"6156",
    "addr:street":"Marmion St",
    "iso:country":"AU",
    "sg:address":"285 Marmion St",
    "sg:city":"Melville",
    "sg:classifiers":[
        {
            "category":"Building & Trades",
            "subcategory":"Cleaning & Sanitation",
            "type":"Services"
        }
    ],
    "sg:phone":"+61 8 9330 3638",
    "sg:postcode":"6156",
    "sg:province":"WA",
    "sg:tags":[
        "sweep",
        "chimney"
    ],
    "wof:name":"A AAABE Sure Cleaners",
    "wof:placetype":"venue"
},
  "geometry": {"coordinates":[115.795357,-32.046318],"type":"Point"}
}