{
  "type": "Feature",
  "properties": {
    "addr:full":"193 Dugan St Kalgoorlie WA 6430",
    "addr:housenumber":"193",
    "addr:postcode":"6430",
    "addr:street":"Dugan St",
    "iso:country":"AU",
    "sg:address":"193 Dugan St",
    "sg:city":"Kalgoorlie",
    "sg:classifiers":[
        {
            "category":"Home & Garden",
            "subcategory":"Carpets & Floor Coverings",
            "type":"Retail Goods"
        }
    ],
    "sg:phone":"+61 8 9022 9528",
    "sg:postcode":"6430",
    "sg:province":"WA",
    "sg:tags":[
        "mattress"
    ],
    "wof:name":"Kalgoorlie Kanvas",
    "wof:placetype":"venue"
},
  "geometry": {"coordinates":[121.461540222,-30.7538433075],"type":"Point"}
}