{
  "type": "Feature",
  "properties": {
    "addr:full":"John Schubert Drv Baranduda VIC 3691",
    "addr:postcode":"3691",
    "addr:street":"Schubert Drv",
    "iso:country":"AU",
    "sg:address":"John Schubert Drv",
    "sg:city":"Baranduda",
    "sg:classifiers":[
        {
            "category":"Education",
            "subcategory":"School",
            "type":"Public Place"
        }
    ],
    "sg:phone":"+61 2 6020 9105",
    "sg:postcode":"3691",
    "sg:province":"VIC",
    "wof:name":"Trinity Anglican College Wodonga",
    "wof:placetype":"venue"
},
  "geometry": {"coordinates":[146.95263700000001,-36.1782],"type":"Point"}
}