{
  "type": "Feature",
  "properties": {
    "addr:full":"46 Frances St South Wentworthville NSW 2145",
    "addr:housenumber":"46",
    "addr:postcode":"2145",
    "addr:street":"Frances St",
    "iso:country":"AU",
    "sg:address":"46 Frances St",
    "sg:city":"South Wentworthville",
    "sg:classifiers":[
        {
            "category":"Social Services",
            "subcategory":"Child Care",
            "type":"Services"
        }
    ],
    "sg:phone":"+61 2 9633 5440",
    "sg:postcode":"2145",
    "sg:province":"NSW",
    "wof:name":"Kindyway Learning Centre",
    "wof:placetype":"venue"
},
  "geometry": {"coordinates":[150.976287842,-33.8232498169],"type":"Point"}
}