{
  "type": "Feature",
  "properties": {
    "addr:full":"PO Box 30 Portland NSW 2847",
    "addr:postcode":"2847",
    "iso:country":"AU",
    "sg:address":"PO Box 30",
    "sg:city":"Portland",
    "sg:classifiers":[
        {
            "category":"Building & Trades",
            "subcategory":"Equipment Rental",
            "type":"Services"
        }
    ],
    "sg:phone":"+61 2 6355 5797",
    "sg:postcode":"2847",
    "sg:province":"NSW",
    "sg:tags":[
        "demolition",
        "contractor"
    ],
    "wof:name":"James Civil & Plant Hire Pty Ltd",
    "wof:placetype":"venue"
},
  "geometry": {"coordinates":[149.98175000000001,-33.35305],"type":"Point"}
}