{
  "type": "Feature",
  "properties": {
    "addr:full":"Unit 1, 55 Eastern Rd Browns Plains QLD 4118",
    "addr:housenumber":"55",
    "addr:postcode":"4118",
    "addr:street":"Eastern Rd",
    "iso:country":"AU",
    "sg:address":"Unit 1, 55 Eastern Rd",
    "sg:city":"Browns Plains",
    "sg:classifiers":[
        {
            "category":"Retail",
            "subcategory":"Auto Repair",
            "type":"Services"
        }
    ],
    "sg:phone":"+61 7 3800 9999",
    "sg:postcode":"4118",
    "sg:province":"QLD",
    "sg:tags":[
        "repairer",
        "motor",
        "engineer"
    ],
    "wof:name":"R.T.D. Automotive",
    "wof:placetype":"venue"
},
  "geometry": {"coordinates":[153.04835510300001,-27.6645050049],"type":"Point"}
}