{
  "type": "Feature",
  "properties": {
    "iso:country":"AU",
    "sg:address":"10 Prospect St",
    "sg:city":"Box Hill",
    "sg:classifiers":[
        {
            "category":"Professional",
            "subcategory":"Accounting & Tax Preparation",
            "type":"Services"
        }
    ],
    "sg:phone":"+61 3 9899 8276",
    "sg:postcode":"3128",
    "sg:province":"VIC",
    "sg:tags":[
        "accountant",
        "auditor"
    ],
    "wof:name":"Thom & Co",
    "wof:placetype":"venue"
},
  "geometry": {"coordinates":[145.11895751899999,-37.8180427551],"type":"Point"}
}