{
  "type": "Feature",
  "properties": {
    "addr:full":"PO Box 464 Bribie Island QLD 4507",
    "addr:postcode":"4507",
    "iso:country":"AU",
    "sg:address":"PO Box 464",
    "sg:city":"Bribie Island",
    "sg:classifiers":[
        {
            "category":"Building & Trades",
            "subcategory":"Landscaping Services",
            "type":"Services"
        }
    ],
    "sg:phone":"+61 7 3410 7934",
    "sg:postcode":"4507",
    "sg:province":"QLD",
    "sg:tags":[
        "designer",
        "landscape",
        "contractor"
    ],
    "wof:name":"Ocean Blue Landscaping",
    "wof:placetype":"venue"
},
  "geometry": {"coordinates":[153.14137268100001,-26.9570903778],"type":"Point"}
}