{
  "type": "Feature",
  "properties": {
    "addr:full":"282 Hare St Echuca VIC 3564",
    "addr:housenumber":"282",
    "addr:postcode":"3564",
    "addr:street":"Hare St",
    "iso:country":"AU",
    "sg:address":"282 Hare St",
    "sg:city":"Echuca",
    "sg:classifiers":[
        {
            "category":"Personal",
            "subcategory":"Beauty Salon",
            "type":"Services"
        }
    ],
    "sg:phone":"+61 3 5480 7044",
    "sg:postcode":"3564",
    "sg:province":"VIC",
    "sg:tags":[
        "hairdresser"
    ],
    "wof:name":"Articulate Hair Studio",
    "wof:placetype":"venue"
},
  "geometry": {"coordinates":[144.74888610799999,-36.1247177124],"type":"Point"}
}