{
  "type": "Feature",
  "properties": {
    "addr:full":"371 Chapel St South Yarra VIC 3141",
    "addr:housenumber":"371",
    "addr:postcode":"3141",
    "addr:street":"Chapel St",
    "iso:country":"AU",
    "sg:address":"371 Chapel St",
    "sg:city":"South Yarra",
    "sg:classifiers":[
        {
            "category":"Bars & Pubs",
            "subcategory":"Nightclub",
            "type":"Food & Drink"
        }
    ],
    "sg:phone":"+61 3 9827 1771",
    "sg:postcode":"3141",
    "sg:province":"VIC",
    "sg:tags":[
        "discotheque"
    ],
    "wof:name":"Viper Room The",
    "wof:placetype":"venue"
},
  "geometry": {"coordinates":[144.99412536599999,-37.8460922241],"type":"Point"}
}