{
  "type": "Feature",
  "properties": {
    "addr:full":"Kel Barclay Ave Adelaide Airport SA 5950",
    "addr:postcode":"5950",
    "addr:street":"Ave",
    "iso:country":"AU",
    "sg:address":"Kel Barclay Ave",
    "sg:city":"Adelaide Airport",
    "sg:classifiers":[
        {
            "category":"Airline",
            "type":"Transportation"
        }
    ],
    "sg:phone":"+61 8 8234 3244",
    "sg:postcode":"5950",
    "sg:province":"SA",
    "sg:tags":[
        "aircraft",
        "rental",
        "charter"
    ],
    "sg:website":"http://www.airsouth.com.au",
    "wof:name":"Air South Charter",
    "wof:placetype":"venue"
},
  "geometry": {"coordinates":[138.53663635300001,-34.9367675781],"type":"Point"}
}