{
  "type": "Feature",
  "properties": {
    "iso:country":"AU",
    "sg:address":"900 Old Gympie Rd",
    "sg:city":"Burpengary",
    "sg:classifiers":[
        {
            "category":"Retail",
            "subcategory":"Storage",
            "type":"Services"
        }
    ],
    "sg:phone":"+61 7 3888 8111",
    "sg:postcode":"4505",
    "sg:province":"QLD",
    "sg:tags":[
        "removal",
        "furniture"
    ],
    "wof:name":"Eureka Storage",
    "wof:placetype":"venue"
},
  "geometry": {"coordinates":[152.98046875,-27.1705341339],"type":"Point"}
}