{
  "type": "Feature",
  "properties": {
    "addr:full":"8 Pambula Crt Helensvale QLD 4212",
    "addr:housenumber":"8",
    "addr:postcode":"4212",
    "addr:street":"Pambula Crt",
    "iso:country":"AU",
    "sg:address":"8 Pambula Crt",
    "sg:city":"Helensvale",
    "sg:classifiers":[
        {
            "category":"Building & Trades",
            "subcategory":"Cleaning & Sanitation",
            "type":"Services"
        }
    ],
    "sg:phone":"+61 410 402 038",
    "sg:postcode":"4212",
    "sg:province":"QLD",
    "sg:tags":[
        "cleaner",
        "repairer",
        "roof"
    ],
    "wof:name":"Rod's Roof Restoration",
    "wof:placetype":"venue"
},
  "geometry": {"coordinates":[153.33860778799999,-27.9067344666],"type":"Point"}
}