{
  "type": "Feature",
  "properties": {
    "iso:country":"AU",
    "sg:address":"7- 9 Price St",
    "sg:city":"Kadina",
    "sg:classifiers":[
        {
            "category":"Wholesale",
            "subcategory":"Farm Supplies",
            "type":"Manufacturing & Wholesale Goods"
        }
    ],
    "sg:phone":"+61 8 8821 4433",
    "sg:postcode":"5554",
    "sg:province":"SA",
    "sg:tags":[
        "equipment"
    ],
    "wof:name":"Wisefarmers Y P",
    "wof:placetype":"venue"
},
  "geometry": {"coordinates":[137.707565308,-33.970287323],"type":"Point"}
}