{
  "type": "Feature",
  "properties": {
    "addr:full":"3 John St Corowa NSW 2646",
    "addr:housenumber":"3",
    "addr:postcode":"2646",
    "addr:street":"John St",
    "iso:country":"AU",
    "sg:address":"3 John St",
    "sg:city":"Corowa",
    "sg:classifiers":[
        {
            "category":"Professional",
            "subcategory":"Management & Consulting",
            "type":"Services"
        }
    ],
    "sg:phone":"+61 2 6033 3557",
    "sg:postcode":"2646",
    "sg:province":"NSW",
    "sg:tags":[
        "consultant",
        "business"
    ],
    "wof:name":"Business Plan Workshop",
    "wof:placetype":"venue"
},
  "geometry": {"coordinates":[146.38575744600001,-35.9991340637],"type":"Point"}
}