{
  "type": "Feature",
  "properties": {
    "addr:full":"Shop 1/ 2452 Warburton Hwy Yarra Junction VIC 3797",
    "addr:housenumber":"shop 1 / 2452",
    "addr:postcode":"3797",
    "addr:street":"Warburton Hwy",
    "iso:country":"AU",
    "sg:address":"Shop 1/ 2452 Warburton Hwy",
    "sg:city":"Yarra Junction",
    "sg:classifiers":[
        {
            "category":"Real Estate",
            "subcategory":"Real Estate Agent",
            "type":"Services"
        }
    ],
    "sg:phone":"+61 3 5967 2999",
    "sg:postcode":"3797",
    "sg:province":"VIC",
    "wof:name":"Ray White Yarra Valley",
    "wof:placetype":"venue"
},
  "geometry": {"coordinates":[145.60633850100001,-37.7797431946],"type":"Point"}
}