{
  "type": "Feature",
  "properties": {
    "addr:full":"47 John St Oakleigh VIC 3166",
    "addr:housenumber":"47",
    "addr:postcode":"3166",
    "addr:street":"John St",
    "iso:country":"AU",
    "sg:address":"47 John St",
    "sg:city":"Oakleigh",
    "sg:classifiers":[
        {
            "category":"Shopping",
            "type":"Retail Goods"
        }
    ],
    "sg:phone":"+61 3 9569 9564",
    "sg:postcode":"3166",
    "sg:province":"VIC",
    "sg:tags":[
        "product",
        "plastic"
    ],
    "wof:name":"Machine Talkers",
    "wof:placetype":"venue"
},
  "geometry": {"coordinates":[145.10049438499999,-37.9049911499],"type":"Point"}
}