{
  "type": "Feature",
  "properties": {
    "iso:country":"AU",
    "sg:address":"Unit 7/ 21 Myrtle St",
    "sg:city":"Botany",
    "sg:classifiers":[
        {
            "category":"Autos & Motor Vehicles",
            "subcategory":"Boat Sales",
            "type":"Retail Goods"
        }
    ],
    "sg:phone":"+61 2 9666 4444",
    "sg:postcode":"2019",
    "sg:province":"NSW",
    "sg:tags":[
        "equipment",
        "yacht"
    ],
    "wof:name":"Boating Security Systems",
    "wof:placetype":"venue"
},
  "geometry": {"coordinates":[151.20463562,-33.9403610229],"type":"Point"}
}