{
  "type": "Feature",
  "properties": {
    "addr:full":"Suite 4 13-15 Fenwick St Geelong VIC 3220",
    "addr:housenumber":"13-15",
    "addr:postcode":"3220",
    "addr:street":"Fenwick St",
    "iso:country":"AU",
    "sg:address":"Suite 4 13-15 Fenwick St",
    "sg:city":"Geelong",
    "sg:classifiers":[
        {
            "category":"Banks & Credit Unions",
            "subcategory":"Investment Brokerage",
            "type":"Services"
        }
    ],
    "sg:phone":"+61 416 290 501",
    "sg:postcode":"3220",
    "sg:province":"VIC",
    "sg:tags":[
        "finance",
        "broker"
    ],
    "wof:name":"United Financial Services",
    "wof:placetype":"venue"
},
  "geometry": {"coordinates":[144.354568,-38.148842],"type":"Point"}
}