{
  "type": "Feature",
  "properties": {
    "iso:country":"AU",
    "sg:address":"135 Victoria St",
    "sg:city":"Mackay",
    "sg:classifiers":[
        {
            "category":"Health Services",
            "subcategory":"Optometrist",
            "type":"Services"
        }
    ],
    "sg:phone":"+61 7 4957 4002",
    "sg:postcode":"4740",
    "sg:province":"QLD",
    "wof:name":"Hamilton's Optometrist",
    "wof:placetype":"venue"
},
  "geometry": {"coordinates":[149.18365499999999,-21.141115],"type":"Point"}
}