{
  "type": "Feature",
  "properties": {
    "iso:country":"AU",
    "sg:address":"7/ 70 Centennial Cct",
    "sg:city":"Byron Bay",
    "sg:classifiers":[
        {
            "category":"Food & Beverages",
            "subcategory":"Specialty",
            "type":"Retail Goods"
        }
    ],
    "sg:phone":"+61 2 6680 7883",
    "sg:postcode":"2481",
    "sg:province":"NSW",
    "sg:tags":[
        "delicacy"
    ],
    "wof:name":"Cheese Please & Delicacies",
    "wof:placetype":"venue"
},
  "geometry": {"coordinates":[153.57896423299999,-28.6370677948],"type":"Point"}
}