{
  "type": "Feature",
  "properties": {
    "addr:full":"Cnr Muir Rd & Worth St Chullora NSW 2190",
    "addr:housenumber":"cnr",
    "addr:postcode":"2190",
    "addr:street":"Muir Rd & Worth St",
    "iso:country":"AU",
    "sg:address":"Cnr Muir Rd & Worth St",
    "sg:city":"Chullora",
    "sg:classifiers":[
        {
            "category":"Education",
            "subcategory":"Vocational School",
            "type":"Public Place"
        }
    ],
    "sg:phone":"+61 2 9742 0400",
    "sg:postcode":"2190",
    "sg:province":"NSW",
    "sg:tags":[
        "tafe",
        "college",
        "training"
    ],
    "wof:name":"TAFE NSW - South Western Sydney Institute Chullora Campus",
    "wof:placetype":"venue"
},
  "geometry": {"coordinates":[151.04620399999999,-33.893375],"type":"Point"}
}