{
  "type": "Feature",
  "properties": {
    "addr:full":"11 Sturt St Kingsford NSW 2032",
    "addr:housenumber":"11",
    "addr:postcode":"2032",
    "addr:street":"Sturt St",
    "iso:country":"AU",
    "sg:address":"11 Sturt St",
    "sg:city":"Kingsford",
    "sg:classifiers":[
        {
            "category":"Health Services",
            "subcategory":"Dentist",
            "type":"Services"
        }
    ],
    "sg:phone":"+61 2 9349 5797",
    "sg:postcode":"2032",
    "sg:province":"NSW",
    "wof:name":"Bomba Irene Dr",
    "wof:placetype":"venue"
},
  "geometry": {"coordinates":[151.229415894,-33.9261665344],"type":"Point"}
}