{
  "type": "Feature",
  "properties": {
    "addr:full":"1 Esmond Rd Port Pirie SA 5540",
    "addr:housenumber":"1",
    "addr:postcode":"5540",
    "addr:street":"Esmond Rd",
    "iso:country":"AU",
    "sg:address":"1 Esmond Rd",
    "sg:city":"Port Pirie",
    "sg:classifiers":[
        {
            "category":"Building & Trades",
            "subcategory":"Construction",
            "type":"Services"
        }
    ],
    "sg:phone":"+61 407 689 377",
    "sg:postcode":"5540",
    "sg:province":"SA",
    "sg:tags":[
        "contractor"
    ],
    "wof:name":"Cameron Hoare",
    "wof:placetype":"venue"
},
  "geometry": {"coordinates":[138.01173400900001,-33.19323349],"type":"Point"}
}