{
  "type": "Feature",
  "properties": {
    "addr:full":"369 Keilor Rd Essendon North VIC 3041",
    "addr:housenumber":"369",
    "addr:postcode":"3041",
    "addr:street":"Keilor Rd",
    "iso:country":"AU",
    "sg:address":"369 Keilor Rd",
    "sg:city":"Essendon North",
    "sg:classifiers":[
        {
            "category":"Retail",
            "subcategory":"Auto Repair",
            "type":"Services"
        }
    ],
    "sg:phone":"+61 3 9374 1361",
    "sg:postcode":"3041",
    "sg:province":"VIC",
    "sg:tags":[
        "transmission",
        "automotive",
        "car"
    ],
    "wof:name":"Gordon Woods Pty Ltd",
    "wof:placetype":"venue"
},
  "geometry": {"coordinates":[144.89361572300001,-37.7379493713],"type":"Point"}
}