{
  "type": "Feature",
  "properties": {
    "iso:country":"AU",
    "sg:address":"East St",
    "sg:city":"Clermont",
    "sg:classifiers":[
        {
            "category":"Sports & Exercise",
            "subcategory":"Golf",
            "type":"Entertainment"
        }
    ],
    "sg:phone":"+61 7 4983 1163",
    "sg:postcode":"4721",
    "sg:province":"QLD",
    "sg:tags":[
        "club"
    ],
    "wof:name":"Clermont Golf Club Inc",
    "wof:placetype":"venue"
},
  "geometry": {"coordinates":[147.64584350600001,-22.8163871765],"type":"Point"}
}