{
  "type": "Feature",
  "properties": {
    "addr:full":"Federal Hwy Gearys Gap NSW 2621",
    "addr:postcode":"2621",
    "addr:street":"Federal Hwy Gearys",
    "iso:country":"AU",
    "sg:address":"Federal Hwy",
    "sg:city":"Gearys Gap",
    "sg:classifiers":[
        {
            "category":"Farming",
            "subcategory":"Livestock Farm",
            "type":"Manufacturing & Wholesale Goods"
        }
    ],
    "sg:phone":"+61 2 6236 9223",
    "sg:postcode":"2621",
    "sg:province":"NSW",
    "sg:tags":[
        "breeder",
        "horse",
        "stud"
    ],
    "wof:name":"Keir P W",
    "wof:placetype":"venue"
},
  "geometry": {"coordinates":[149.296142578,-35.1748123169],"type":"Point"}
}