{
  "type": "Feature",
  "properties": {
    "iso:country":"AU",
    "sg:address":"Suite 4, 1 Maitland Pl",
    "sg:city":"Baulkham Hills",
    "sg:classifiers":[
        {
            "category":"Banks & Credit Unions",
            "subcategory":"Financial Services",
            "type":"Services"
        }
    ],
    "sg:phone":"+61 2 9659 7686",
    "sg:postcode":"2153",
    "sg:province":"NSW",
    "sg:tags":[
        "loan",
        "finance",
        "mortgage"
    ],
    "wof:name":"Tailored Mortgage Solutions",
    "wof:placetype":"venue"
},
  "geometry": {"coordinates":[150.966064453,-33.7307014465],"type":"Point"}
}