{
  "type": "Feature",
  "properties": {
    "iso:country":"AU",
    "sg:address":"1619 Lytton Rd",
    "sg:city":"Lytton",
    "sg:classifiers":[
        {
            "category":"Building & Trades",
            "subcategory":"Construction",
            "type":"Services"
        }
    ],
    "sg:phone":"+61 7 3348 4100",
    "sg:postcode":"4178",
    "sg:province":"QLD",
    "sg:tags":[
        "earth",
        "excavating",
        "moving",
        "contractor"
    ],
    "wof:name":"Mallan Earth Moving Pty Ltd",
    "wof:placetype":"venue"
},
  "geometry": {"coordinates":[153.139724731,-27.4341831207],"type":"Point"}
}