{
  "type": "Feature",
  "properties": {
    "addr:full":"Flat 1 5 Branston Rd St Albans VIC 3021",
    "addr:housenumber":"5",
    "addr:postcode":"3021",
    "addr:street":"Branston Rd",
    "iso:country":"AU",
    "sg:address":"Flat 1 5 Branston Rd",
    "sg:city":"St Albans",
    "sg:classifiers":[
        {
            "category":"Professional",
            "subcategory":"Detective & Security Services",
            "type":"Services"
        }
    ],
    "sg:phone":"+61 3 9367 3347",
    "sg:postcode":"3021",
    "sg:province":"VIC",
    "sg:tags":[
        "guard",
        "patrol"
    ],
    "wof:name":"Victoria Night Patrol",
    "wof:placetype":"venue"
},
  "geometry": {"coordinates":[144.823532,-37.752068],"type":"Point"}
}