{
  "type": "Feature",
  "properties": {
    "iso:country":"AU",
    "sg:address":"40 Ainsdale St",
    "sg:city":"Chermside West",
    "sg:classifiers":[
        {
            "category":"Personal",
            "subcategory":"Massage",
            "type":"Services"
        }
    ],
    "sg:phone":"+61 7 3847 4000",
    "sg:postcode":"4032",
    "sg:province":"QLD",
    "sg:tags":[
        "therapy"
    ],
    "wof:name":"Contours International Weight Loss Centres",
    "wof:placetype":"venue"
},
  "geometry": {"coordinates":[153.009583,-27.388475],"type":"Point"}
}