{
  "type": "Feature",
  "properties": {
    "addr:full":"36 Wollumbin St Murwillumbah NSW 2484",
    "addr:housenumber":"36",
    "addr:postcode":"2484",
    "addr:street":"Wollumbin St",
    "iso:country":"AU",
    "sg:address":"36 Wollumbin St",
    "sg:city":"Murwillumbah",
    "sg:classifiers":[
        {
            "category":"Health Services",
            "subcategory":"Doctor",
            "type":"Services"
        }
    ],
    "sg:phone":"+61 2 6672 1488",
    "sg:postcode":"2484",
    "sg:province":"NSW",
    "sg:tags":[
        "medical",
        "practitioner"
    ],
    "wof:name":"Kettle I H",
    "wof:placetype":"venue"
},
  "geometry": {"coordinates":[153.39505004899999,-28.3273162842],"type":"Point"}
}