{
  "type": "Feature",
  "properties": {
    "addr:full":"242 Bong Bong St Bowral NSW 2576",
    "addr:housenumber":"242",
    "addr:postcode":"2576",
    "addr:street":"Bong Bong St",
    "iso:country":"AU",
    "sg:address":"242 Bong Bong St",
    "sg:city":"Bowral",
    "sg:classifiers":[
        {
            "category":"Personal",
            "subcategory":"Beauty Salon",
            "type":"Services"
        }
    ],
    "sg:phone":"+61 2 4862 2449",
    "sg:postcode":"2576",
    "sg:province":"NSW",
    "sg:tags":[
        "hairdresser"
    ],
    "wof:name":"Asish's Barber Shop",
    "wof:placetype":"venue"
},
  "geometry": {"coordinates":[150.41830444300001,-34.4775276184],"type":"Point"}
}