{
  "type": "Feature",
  "properties": {
    "addr:full":"220 Denison St Broadmeadow NSW 2292",
    "addr:housenumber":"220",
    "addr:postcode":"2292",
    "addr:street":"Denison St",
    "iso:country":"AU",
    "sg:address":"220 Denison St",
    "sg:city":"Broadmeadow",
    "sg:classifiers":[
        {
            "category":"Professional",
            "subcategory":"Business Services",
            "type":"Services"
        }
    ],
    "sg:phone":"+61 2 4961 3200",
    "sg:postcode":"2292",
    "sg:province":"NSW",
    "sg:tags":[
        "management",
        "event"
    ],
    "wof:name":"Helen Duncan Promotions",
    "wof:placetype":"venue"
},
  "geometry": {"coordinates":[151.73736572300001,-32.9247817993],"type":"Point"}
}