{
  "type": "Feature",
  "properties": {
    "addr:full":"46 Bridge St Morisset NSW 2264",
    "addr:housenumber":"46",
    "addr:postcode":"2264",
    "addr:street":"Bridge St",
    "iso:country":"AU",
    "sg:address":"46 Bridge St",
    "sg:city":"Morisset",
    "sg:classifiers":[
        {
            "category":"Health Services",
            "subcategory":"Health Practitioner",
            "type":"Services"
        }
    ],
    "sg:phone":"+61 2 4973 3741",
    "sg:postcode":"2264",
    "sg:province":"NSW",
    "sg:tags":[
        "physiotherapist"
    ],
    "wof:name":"Morisset Physiotherapy & Sports Injury Centre",
    "wof:placetype":"venue"
},
  "geometry": {"coordinates":[151.4897,-33.106888],"type":"Point"}
}