{
  "type": "Feature",
  "properties": {
    "addr:full":"14 Tuscan Crt Thomastown VIC 3074",
    "addr:housenumber":"14",
    "addr:postcode":"3074",
    "addr:street":"Tuscan Crt",
    "iso:country":"AU",
    "sg:address":"14 Tuscan Crt",
    "sg:city":"Thomastown",
    "sg:classifiers":[
        {
            "category":"Manufacturing",
            "subcategory":"Tools & Machinery",
            "type":"Manufacturing & Wholesale Goods"
        }
    ],
    "sg:phone":"+61 3 9469 4111",
    "sg:postcode":"3074",
    "sg:province":"VIC",
    "sg:tags":[
        "supplier",
        "diamond"
    ],
    "wof:name":"Ultra Hard Tools",
    "wof:placetype":"venue"
},
  "geometry": {"coordinates":[145.00553894000001,-37.6874504089],"type":"Point"}
}