{
  "type": "Feature",
  "properties": {
    "iso:country":"AU",
    "sg:address":"58 Oxford St",
    "sg:city":"Lidcombe",
    "sg:classifiers":[
        {
            "category":"Structure",
            "subcategory":"Office Building",
            "type":"Public Place"
        }
    ],
    "sg:phone":"+61 421 166 662",
    "sg:postcode":"2141",
    "sg:province":"NSW",
    "sg:tags":[
        "tie",
        "concrete",
        "formwork",
        "form",
        "accessory"
    ],
    "wof:name":"Champion Formwork",
    "wof:placetype":"venue"
},
  "geometry": {"coordinates":[151.03416442899999,-33.8654632568],"type":"Point"}
}