{
  "type": "Feature",
  "properties": {
    "iso:country":"AU",
    "sg:address":"87 Lake St",
    "sg:city":"Cairns",
    "sg:classifiers":[
        {
            "category":"Conference Center",
            "type":"Public Place"
        }
    ],
    "sg:phone":"+61 1800 079 266",
    "sg:postcode":"4870",
    "sg:province":"QLD",
    "sg:tags":[
        "venue",
        "convention"
    ],
    "wof:name":"Comfort Inn Hides - Cairns",
    "wof:placetype":"venue"
},
  "geometry": {"coordinates":[145.77618408199999,-16.9227600098],"type":"Point"}
}