{
  "type": "Feature",
  "properties": {
    "iso:country":"AU",
    "sg:address":"86 Cunninghams Rd",
    "sg:city":"Werribee South",
    "sg:classifiers":[
        {
            "category":"Food & Beverages",
            "subcategory":"Fruits & Vegetables",
            "type":"Retail Goods"
        }
    ],
    "sg:phone":"+61 3 9742 1246",
    "sg:postcode":"3030",
    "sg:province":"VIC",
    "sg:tags":[
        "grower"
    ],
    "wof:name":"Rappazzo Con",
    "wof:placetype":"venue"
},
  "geometry": {"coordinates":[144.728928,-37.931503],"type":"Point"}
}