{
  "type": "Feature",
  "properties": {
    "addr:full":"132 Weston St Brunswick East VIC 3057",
    "addr:housenumber":"132",
    "addr:postcode":"3057",
    "addr:street":"Weston St",
    "iso:country":"AU",
    "sg:address":"132 Weston St",
    "sg:city":"Brunswick East",
    "sg:classifiers":[
        {
            "category":"Manufacturing",
            "subcategory":"Tools & Machinery",
            "type":"Manufacturing & Wholesale Goods"
        }
    ],
    "sg:phone":"+61 3 9380 9945",
    "sg:postcode":"3057",
    "sg:province":"VIC",
    "sg:tags":[
        "wholesaler",
        "lingerie",
        "mfrs",
        "sleepwear"
    ],
    "wof:name":"Kaye Jones & Ginia Lingerie Pty Ltd",
    "wof:placetype":"venue"
},
  "geometry": {"coordinates":[144.971923828,-37.7760696411],"type":"Point"}
}