{
  "type": "Feature",
  "properties": {
    "addr:full":"11 Lower King St Caboolture QLD 4510",
    "addr:housenumber":"11",
    "addr:postcode":"4510",
    "addr:street":"Lower King St",
    "iso:country":"AU",
    "sg:address":"11 Lower King St",
    "sg:city":"Caboolture",
    "sg:classifiers":[
        {
            "category":"Travel",
            "subcategory":"Hotels & Motels",
            "type":"Entertainment"
        }
    ],
    "sg:phone":"+61 7 5428 3100",
    "sg:postcode":"4510",
    "sg:province":"QLD",
    "wof:name":"Caboolture Central Motor Inn",
    "wof:placetype":"venue"
},
  "geometry": {"coordinates":[152.955917,-27.084393],"type":"Point"}
}