{
  "type": "Feature",
  "properties": {
    "addr:full":"44 Queen St St Marys NSW 2760",
    "addr:housenumber":"44",
    "addr:postcode":"2760",
    "addr:street":"Queen St",
    "iso:country":"AU",
    "sg:address":"44 Queen St",
    "sg:city":"St Marys",
    "sg:classifiers":[
        {
            "category":"Professional",
            "subcategory":"Accounting & Tax Preparation",
            "type":"Services"
        }
    ],
    "sg:phone":"+61 2 9623 7780",
    "sg:postcode":"2760",
    "sg:province":"NSW",
    "sg:tags":[
        "consultant",
        "taxation"
    ],
    "wof:name":"I.T.P. The Income Tax Professionals",
    "wof:placetype":"venue"
},
  "geometry": {"coordinates":[150.77467346200001,-33.7638092041],"type":"Point"}
}