{
  "type": "Feature",
  "properties": {
    "addr:full":"Northern Hwy Kilmore VIC 3764",
    "addr:postcode":"3764",
    "addr:street":"Northern Hwy",
    "iso:country":"AU",
    "sg:address":"Northern Hwy",
    "sg:city":"Kilmore",
    "sg:classifiers":[
        {
            "category":"Cafe",
            "type":"Food & Drink"
        }
    ],
    "sg:phone":"+61 3 5782 1990",
    "sg:postcode":"3764",
    "sg:province":"VIC",
    "wof:name":"Silkie Gardens Rose Nursery & Cafe",
    "wof:placetype":"venue"
},
  "geometry": {"coordinates":[144.94926452600001,-37.2852172852],"type":"Point"}
}