{
  "type": "Feature",
  "properties": {
    "addr:full":"North West Rd Badgingarra WA 6521",
    "addr:postcode":"6521",
    "addr:street":"North West Rd",
    "iso:country":"AU",
    "sg:address":"North West Rd",
    "sg:city":"Badgingarra",
    "sg:classifiers":[
        {
            "category":"Building & Trades",
            "subcategory":"Construction",
            "type":"Services"
        }
    ],
    "sg:phone":"+61 8 9652 9081",
    "sg:postcode":"6521",
    "sg:province":"WA",
    "sg:tags":[
        "renovation",
        "alterations",
        "extension",
        "contractor"
    ],
    "wof:name":"Kamalla Contractors",
    "wof:placetype":"venue"
},
  "geometry": {"coordinates":[115.49848938,-30.3867378235],"type":"Point"}
}