{
  "type": "Feature",
  "properties": {
    "iso:country":"AU",
    "sg:address":"37 Were St",
    "sg:city":"Montmorency",
    "sg:classifiers":[
        {
            "category":"Banks & Credit Unions",
            "subcategory":"Financial Services",
            "type":"Services"
        }
    ],
    "sg:phone":"+61 3 9435 2766",
    "sg:postcode":"3094",
    "sg:province":"VIC",
    "sg:tags":[
        "annuity",
        "rollover",
        "superannuation",
        "consultant"
    ],
    "wof:name":"Professional Investment Services Pty Ltd",
    "wof:placetype":"venue"
},
  "geometry": {"coordinates":[145.12098693900001,-37.7166442871],"type":"Point"}
}