{
  "type": "Feature",
  "properties": {
    "addr:full":"599 Pacific Hwy Mt Colah NSW 2079",
    "addr:housenumber":"599",
    "addr:postcode":"2079",
    "addr:street":"Pacific Hwy Mt Colah",
    "iso:country":"AU",
    "sg:address":"599 Pacific Hwy",
    "sg:city":"Mt Colah",
    "sg:classifiers":[
        {
            "category":"Health Services",
            "subcategory":"Dentist",
            "type":"Services"
        }
    ],
    "sg:phone":"+61 2 9476 1418",
    "sg:postcode":"2079",
    "sg:province":"NSW",
    "wof:name":"Liem, Joseph Dr",
    "wof:placetype":"venue"
},
  "geometry": {"coordinates":[151.11471557600001,-33.6710319519],"type":"Point"}
}