{
  "type": "Feature",
  "properties": {
    "iso:country":"AU",
    "sg:address":"Marine Pde",
    "sg:city":"Hastings",
    "sg:classifiers":[
        {
            "category":"Social Services",
            "subcategory":"Child Care",
            "type":"Services"
        }
    ],
    "sg:phone":"+61 3 5979 1149",
    "sg:postcode":"3915",
    "sg:province":"VIC",
    "wof:name":"St Mary's Child Care Service",
    "wof:placetype":"venue"
},
  "geometry": {"coordinates":[145.19418335,-38.3070297241],"type":"Point"}
}