{
  "type": "Feature",
  "properties": {
    "iso:country":"AU",
    "sg:address":"5 Rosslare Crt",
    "sg:city":"Kuluin",
    "sg:classifiers":[
        {
            "category":"Education",
            "subcategory":"Music School",
            "type":"Public Place"
        }
    ],
    "sg:phone":"+61 7 5479 2494",
    "sg:postcode":"4558",
    "sg:province":"QLD",
    "sg:tags":[
        "teacher"
    ],
    "wof:name":"Bond Sue Singing Teacher",
    "wof:placetype":"venue"
},
  "geometry": {"coordinates":[153.05960082999999,-26.6576805115],"type":"Point"}
}