{
  "type": "Feature",
  "properties": {
    "iso:country":"AU",
    "sg:address":"131 Sailors Bay Rd",
    "sg:city":"Northbridge",
    "sg:classifiers":[
        {
            "category":"Real Estate",
            "subcategory":"Architect",
            "type":"Services"
        }
    ],
    "sg:phone":"+61 2 9958 1055",
    "sg:postcode":"2063",
    "sg:province":"NSW",
    "wof:name":"Curtin Kevin J & Partners (Architects) Pty Ltd",
    "wof:placetype":"venue"
},
  "geometry": {"coordinates":[151.21029663100001,-33.8106079102],"type":"Point"}
}