{
  "type": "Feature",
  "properties": {
    "iso:country":"AU",
    "sg:address":"c/-Alfred Deakin Centre Cnr 12th St & Deakin Ave",
    "sg:city":"Mildura",
    "sg:classifiers":[
        {
            "category":"Manufacturing",
            "subcategory":"Food",
            "type":"Manufacturing & Wholesale Goods"
        }
    ],
    "sg:phone":"+61 3 5018 8385",
    "sg:postcode":"3500",
    "sg:province":"VIC",
    "sg:tags":[
        "function",
        "catering"
    ],
    "wof:name":"Good Life Cafe",
    "wof:placetype":"venue"
},
  "geometry": {"coordinates":[142.143112183,-34.2014122009],"type":"Point"}
}