{
  "type": "Feature",
  "properties": {
    "addr:full":"45 White St Henley Beach SA 5022",
    "addr:housenumber":"45",
    "addr:postcode":"5022",
    "addr:street":"White St",
    "iso:country":"AU",
    "sg:address":"45 White St",
    "sg:city":"Henley Beach",
    "sg:classifiers":[
        {
            "category":"Professional",
            "subcategory":"Art Services",
            "type":"Services"
        }
    ],
    "sg:phone":"+61 402 890 342",
    "sg:postcode":"5022",
    "sg:province":"SA",
    "sg:tags":[
        "arranger",
        "music",
        "composer"
    ],
    "wof:name":"Mr Bojingles Creative Services",
    "wof:placetype":"venue"
},
  "geometry": {"coordinates":[138.49838256800001,-34.9211196899],"type":"Point"}
}