{
  "type": "Feature",
  "properties": {
    "iso:country":"AU",
    "sg:address":"46 Greenaway St",
    "sg:city":"Bulleen",
    "sg:classifiers":[
        {
            "category":"Home & Garden",
            "subcategory":"Building Materials",
            "type":"Retail Goods"
        }
    ],
    "sg:phone":"+61 3 9850 8874",
    "sg:postcode":"3105",
    "sg:province":"VIC",
    "sg:tags":[
        "supply"
    ],
    "wof:name":"Drive -in Building Supplies",
    "wof:placetype":"venue"
},
  "geometry": {"coordinates":[145.081756592,-37.764629364],"type":"Point"}
}