{
  "type": "Feature",
  "properties": {
    "addr:full":"24 Kalimnor St Loganholme QLD 4129",
    "addr:housenumber":"24",
    "addr:postcode":"4129",
    "addr:street":"Kalimnor St",
    "iso:country":"AU",
    "sg:address":"24 Kalimnor St",
    "sg:city":"Loganholme",
    "sg:classifiers":[
        {
            "category":"Utilities",
            "subcategory":"Electric",
            "type":"Services"
        }
    ],
    "sg:phone":"+61 7 3801 3134",
    "sg:postcode":"4129",
    "sg:province":"QLD",
    "sg:tags":[
        "electrical",
        "contractor"
    ],
    "wof:name":"Y & R Electrical",
    "wof:placetype":"venue"
},
  "geometry": {"coordinates":[153.189849853,-27.6916484833],"type":"Point"}
}