{
  "type": "Feature",
  "properties": {
    "iso:country":"AU",
    "sg:address":"69 Skye Point Rd",
    "sg:city":"Coal Point",
    "sg:classifiers":[
        {
            "category":"Professional",
            "subcategory":"Business Services",
            "type":"Services"
        }
    ],
    "sg:phone":"+61 2 4959 9211",
    "sg:postcode":"2283",
    "sg:province":"NSW",
    "sg:tags":[
        "drafting"
    ],
    "wof:name":"Architectural Design & Creation",
    "wof:placetype":"venue"
},
  "geometry": {"coordinates":[151.60792541500001,-32.9955177307],"type":"Point"}
}