{
  "type": "Feature",
  "properties": {
    "addr:full":"21 Oakes Ave Dee Why NSW 2099",
    "addr:housenumber":"21",
    "addr:postcode":"2099",
    "addr:street":"Oakes Ave",
    "iso:country":"AU",
    "sg:address":"21 Oakes Ave",
    "sg:city":"Dee Why",
    "sg:classifiers":[
        {
            "category":"Professional",
            "subcategory":"Business Services",
            "type":"Services"
        }
    ],
    "sg:phone":"+61 2 9417 0799",
    "sg:postcode":"2099",
    "sg:province":"NSW",
    "sg:tags":[
        "exporter"
    ],
    "wof:name":"Fujian Australia Pty Ltd",
    "wof:placetype":"venue"
},
  "geometry": {"coordinates":[151.28782653799999,-33.7538337708],"type":"Point"}
}