{
  "type": "Feature",
  "properties": {
    "addr:full":"Cnr Compton Rd & Allgas St Slacks Creek QLD 4127",
    "addr:postcode":"4127",
    "addr:street":"Cnr Compton Rd & Allgas St",
    "iso:country":"AU",
    "sg:address":"Cnr Compton Rd & Allgas St",
    "sg:city":"Slacks Creek",
    "sg:classifiers":[
        {
            "category":"Building & Trades",
            "subcategory":"Construction",
            "type":"Services"
        }
    ],
    "sg:phone":"+61 1300 360 346",
    "sg:postcode":"4127",
    "sg:province":"QLD",
    "sg:tags":[
        "insulation",
        "contractor"
    ],
    "wof:name":"Australian Insulation Super Store",
    "wof:placetype":"venue"
},
  "geometry": {"coordinates":[153.119750977,-27.6178703308],"type":"Point"}
}