{
  "type": "Feature",
  "properties": {
    "addr:full":"7 Mitchell St St Leonards NSW 2065",
    "addr:housenumber":"7",
    "addr:postcode":"2065",
    "addr:street":"Mitchell St",
    "iso:country":"AU",
    "sg:address":"7 Mitchell St",
    "sg:city":"St Leonards",
    "sg:classifiers":[
        {
            "category":"Fast Food",
            "type":"Food & Drink"
        }
    ],
    "sg:phone":"+61 2 9438 2468",
    "sg:postcode":"2065",
    "sg:province":"NSW",
    "sg:tags":[
        "away",
        "take"
    ],
    "wof:name":"Sandwich Shop The",
    "wof:placetype":"venue"
},
  "geometry": {"coordinates":[151.19725036599999,-33.8213729858],"type":"Point"}
}