{
  "type": "Feature",
  "properties": {
    "iso:country":"AU",
    "sg:address":"22 Centre Pl",
    "sg:city":"Melbourne",
    "sg:classifiers":[
        {
            "category":"Shopping",
            "subcategory":"Clothing, Apparel, & Fashions",
            "type":"Retail Goods"
        }
    ],
    "sg:phone":"+61 3 9650 0465",
    "sg:postcode":"3000",
    "sg:province":"VIC",
    "sg:tags":[
        "lady",
        "wear"
    ],
    "wof:name":"Kinki Gerlinki",
    "wof:placetype":"venue"
},
  "geometry": {"coordinates":[144.96534729000001,-37.8161201477],"type":"Point"}
}