{
  "type": "Feature",
  "properties": {
    "addr:full":"4/ 33 O'Callaghan Pde Horsham VIC 3400",
    "addr:housenumber":"/ 33",
    "addr:postcode":"3400",
    "addr:street":"O'Callaghan Pde",
    "iso:country":"AU",
    "sg:address":"4/ 33 O'Callaghan Pde",
    "sg:city":"Horsham",
    "sg:classifiers":[
        {
            "category":"Building & Trades",
            "subcategory":"Construction",
            "type":"Services"
        }
    ],
    "sg:phone":"+61 3 5382 0781",
    "sg:postcode":"3400",
    "sg:province":"VIC",
    "sg:tags":[
        "contractor"
    ],
    "wof:name":"Nu Steel Homes",
    "wof:placetype":"venue"
},
  "geometry": {"coordinates":[142.19619750999999,-36.7172393799],"type":"Point"}
}