{
  "type": "Feature",
  "properties": {
    "iso:country":"AU",
    "sg:address":"6 James St",
    "sg:city":"Waitara",
    "sg:classifiers":[
        {
            "category":"Retail",
            "subcategory":"Auto Repair",
            "type":"Services"
        }
    ],
    "sg:phone":"+61 2 9987 2699",
    "sg:postcode":"2077",
    "sg:province":"NSW",
    "sg:tags":[
        "electrical"
    ],
    "wof:name":"Australian Association of Automotive Electricians",
    "wof:placetype":"venue"
},
  "geometry": {"coordinates":[151.100875855,-33.7088088989],"type":"Point"}
}