{
  "type": "Feature",
  "properties": {
    "addr:full":"100 Drummond St Oakleigh VIC 3166",
    "addr:housenumber":"100",
    "addr:postcode":"3166",
    "addr:street":"Drummond St",
    "iso:country":"AU",
    "sg:address":"100 Drummond St",
    "sg:city":"Oakleigh",
    "sg:classifiers":[
        {
            "category":"Utilities",
            "subcategory":"Electric",
            "type":"Services"
        }
    ],
    "sg:phone":"+61 3 9563 0033",
    "sg:postcode":"3166",
    "sg:province":"VIC",
    "sg:tags":[
        "electrical",
        "contractor"
    ],
    "wof:name":"Allserv",
    "wof:placetype":"venue"
},
  "geometry": {"coordinates":[145.09120178200001,-37.8918151855],"type":"Point"}
}