{
  "type": "Feature",
  "properties": {
    "addr:full":"Lvl 11 / 23 Queen St Melbourne VIC 3000",
    "addr:housenumber":"/ 23",
    "addr:postcode":"3000",
    "addr:street":"Queen St",
    "iso:country":"AU",
    "sg:address":"Lvl 11 / 23 Queen St",
    "sg:city":"Melbourne",
    "sg:classifiers":[
        {
            "category":"Banks & Credit Unions",
            "subcategory":"Financial Services",
            "type":"Services"
        }
    ],
    "sg:phone":"+61 1800 630 705",
    "sg:postcode":"3000",
    "sg:province":"VIC",
    "sg:tags":[
        "planning"
    ],
    "wof:name":"St Andrew's Financial Services Ltd",
    "wof:placetype":"venue"
},
  "geometry": {"coordinates":[144.96206665,-37.8182258606],"type":"Point"}
}