{
  "type": "Feature",
  "properties": {
    "iso:country":"AU",
    "sg:address":"Barkly St",
    "sg:city":"Camooweal",
    "sg:classifiers":[
        {
            "category":"Autos & Motor Vehicles",
            "subcategory":"Fuel & Gas Station",
            "type":"Retail Goods"
        }
    ],
    "sg:phone":"+61 7 4748 2155",
    "sg:postcode":"4828",
    "sg:province":"QLD",
    "wof:name":"Shell Camooweal",
    "wof:placetype":"venue"
},
  "geometry": {"coordinates":[138.11976623499999,-19.9214363098],"type":"Point"}
}