{
  "type": "Feature",
  "properties": {
    "addr:full":"34 Cowper St Footscray VIC 3011",
    "addr:housenumber":"34",
    "addr:postcode":"3011",
    "addr:street":"Cowper St",
    "iso:country":"AU",
    "sg:address":"34 Cowper St",
    "sg:city":"Footscray",
    "sg:classifiers":[
        {
            "category":"Autos & Motor Vehicles",
            "subcategory":"Automobile Sales",
            "type":"Retail Goods"
        }
    ],
    "sg:phone":"+61 3 9687 5781",
    "sg:postcode":"3011",
    "sg:province":"VIC",
    "sg:tags":[
        "car",
        "new"
    ],
    "wof:name":"Ford Dealers",
    "wof:placetype":"venue"
},
  "geometry": {"coordinates":[144.90481567399999,-37.8009681702],"type":"Point"}
}