{
  "type": "Feature",
  "properties": {
    "iso:country":"AU",
    "sg:address":"PO Box 6106",
    "sg:city":"Doncaster",
    "sg:classifiers":[
        {
            "category":"Health Services",
            "subcategory":"Health Practitioner",
            "type":"Services"
        }
    ],
    "sg:phone":"+61 1800 204 868",
    "sg:postcode":"3108",
    "sg:province":"VIC",
    "sg:tags":[
        "alternative"
    ],
    "wof:name":"Light Streams",
    "wof:placetype":"venue"
},
  "geometry": {"coordinates":[145.122512817,-37.7830314636],"type":"Point"}
}