{
  "type": "Feature",
  "properties": {
    "addr:full":"Gymea Bay Rd Gymea NSW 2227",
    "addr:postcode":"2227",
    "addr:street":"Gymea Bay Rd",
    "iso:country":"AU",
    "sg:address":"Gymea Bay Rd",
    "sg:city":"Gymea",
    "sg:classifiers":[
        {
            "category":"Building & Trades",
            "subcategory":"Plumbing",
            "type":"Services"
        }
    ],
    "sg:phone":"+61 418 862 848",
    "sg:postcode":"2227",
    "sg:province":"NSW",
    "sg:tags":[
        "plumber",
        "gasfitters"
    ],
    "wof:name":"S J Wilson Plumbing Pty Ltd",
    "wof:placetype":"venue"
},
  "geometry": {"coordinates":[151.08497619600001,-34.0353393555],"type":"Point"}
}