{
  "type": "Feature",
  "properties": {
    "addr:full":"PO Box 2035 Dangar NSW 2309",
    "addr:postcode":"2309",
    "iso:country":"AU",
    "sg:address":"PO Box 2035",
    "sg:city":"Dangar",
    "sg:classifiers":[
        {
            "category":"Education",
            "subcategory":"Special Training",
            "type":"Public Place"
        }
    ],
    "sg:phone":"+61 2 4969 1344",
    "sg:postcode":"2309",
    "sg:province":"NSW",
    "sg:tags":[
        "development"
    ],
    "wof:name":"Industry Training Consultants",
    "wof:placetype":"venue"
},
  "geometry": {"coordinates":[151.23019400000001,-33.546558],"type":"Point"}
}