{
  "type": "Feature",
  "properties": {
    "addr:full":"Suite 1, 116 Dangar St Armidale NSW 2350",
    "addr:housenumber":"116",
    "addr:postcode":"2350",
    "addr:street":"Dangar St",
    "iso:country":"AU",
    "sg:address":"Suite 1, 116 Dangar St",
    "sg:city":"Armidale",
    "sg:classifiers":[
        {
            "category":"Personal",
            "subcategory":"Beauty Salon",
            "type":"Services"
        }
    ],
    "sg:phone":"+61 2 6772 9655",
    "sg:postcode":"2350",
    "sg:province":"NSW",
    "sg:tags":[
        "hairdresser"
    ],
    "wof:name":"We've Got The Look",
    "wof:placetype":"venue"
},
  "geometry": {"coordinates":[151.66490173299999,-30.51404953],"type":"Point"}
}