{
  "type": "Feature",
  "properties": {
    "addr:full":"Brianderry Rd Bega NSW 2550",
    "addr:postcode":"2550",
    "addr:street":"Brianderry Rd",
    "iso:country":"AU",
    "sg:address":"Brianderry Rd",
    "sg:city":"Bega",
    "sg:classifiers":[
        {
            "category":"Wholesale",
            "subcategory":"Meat",
            "type":"Manufacturing & Wholesale Goods"
        }
    ],
    "sg:phone":"+61 410 433 993",
    "sg:postcode":"2550",
    "sg:province":"NSW",
    "sg:tags":[
        "abattoir"
    ],
    "wof:name":"Bega Valley Gourmet Meats Co-operative",
    "wof:placetype":"venue"
},
  "geometry": {"coordinates":[149.808197022,-36.7064094543],"type":"Point"}
}