{
  "type": "Feature",
  "properties": {
    "addr:full":"10 Garsed St Bendigo VIC 3539",
    "addr:housenumber":"10",
    "addr:postcode":"3539",
    "addr:street":"Garsed St",
    "iso:country":"AU",
    "sg:address":"10 Garsed St",
    "sg:city":"Bendigo",
    "sg:classifiers":[
        {
            "category":"Banks & Credit Unions",
            "subcategory":"Financial Services",
            "type":"Services"
        }
    ],
    "sg:phone":"+61 3 5444 5200",
    "sg:postcode":"3539",
    "sg:province":"VIC",
    "sg:tags":[
        "finance",
        "motor",
        "vehicle"
    ],
    "wof:name":"Bendigo Lending Services",
    "wof:placetype":"venue"
},
  "geometry": {"coordinates":[144.28190599999999,-36.763077],"type":"Point"}
}