{
  "type": "Feature",
  "properties": {
    "iso:country":"AU",
    "sg:address":"14 Wentworth Ave",
    "sg:city":"Mascot",
    "sg:classifiers":[
        {
            "category":"Home & Garden",
            "subcategory":"Carpets & Floor Coverings",
            "type":"Retail Goods"
        }
    ],
    "sg:phone":"+61 2 8338 0880",
    "sg:postcode":"2020",
    "sg:province":"NSW",
    "wof:name":"Carpet Court",
    "wof:placetype":"venue"
},
  "geometry": {"coordinates":[151.19515991200001,-33.934627533],"type":"Point"}
}