{
  "type": "Feature",
  "properties": {
    "addr:full":"Bains Rd (cnr Panalatinga Rd) Woodcroft SA 5162",
    "addr:postcode":"5162",
    "addr:street":"Bains Rd Cnr Panalatinga Rd",
    "iso:country":"AU",
    "sg:address":"Bains Rd",
    "sg:city":"(cnr Panalatinga Rd) Woodcroft",
    "sg:classifiers":[
        {
            "category":"Food & Beverages",
            "subcategory":"Supermarket",
            "type":"Retail Goods"
        }
    ],
    "sg:phone":"+61 8 8325 1144",
    "sg:postcode":"5162",
    "sg:province":"SA",
    "sg:tags":[
        "grocery",
        "store"
    ],
    "wof:name":"Foodland Supermarkets",
    "wof:placetype":"venue"
},
  "geometry": {"coordinates":[138.55723571799999,-35.1140708923],"type":"Point"}
}