{
  "type": "Feature",
  "properties": {
    "addr:full":"401 Wellington St Perth WA 6000",
    "addr:housenumber":"401",
    "addr:postcode":"6000",
    "addr:street":"Wellington St",
    "iso:country":"AU",
    "sg:address":"401 Wellington St",
    "sg:city":"Perth",
    "sg:classifiers":[
        {
            "category":"Personal",
            "subcategory":"Beauty Salon",
            "type":"Services"
        }
    ],
    "sg:phone":"+61 8 9325 2664",
    "sg:postcode":"6000",
    "sg:province":"WA",
    "sg:tags":[
        "hairdresser"
    ],
    "wof:name":"Cut Out Hair Design",
    "wof:placetype":"venue"
},
  "geometry": {"coordinates":[115.851463318,-31.9491996765],"type":"Point"}
}