{
  "type": "Feature",
  "properties": {
    "addr:full":"Suite 208, 1 Burbank Place, Norwest Business Park Baulkham NSW 2153",
    "addr:housenumber":"1",
    "addr:postcode":"2153",
    "addr:street":"Burbank Place Norwest",
    "iso:country":"AU",
    "sg:address":"Suite 208, 1",
    "sg:city":"Burbank Place, Norwest Business Park Baulkham",
    "sg:classifiers":[
        {
            "category":"Banks & Credit Unions",
            "subcategory":"Financial Services",
            "type":"Services"
        }
    ],
    "sg:phone":"+61 2 8814 8404",
    "sg:postcode":"2153",
    "sg:province":"NSW",
    "sg:tags":[
        "loan",
        "finance",
        "mortgage"
    ],
    "wof:name":"Destiny Financial Solutions",
    "wof:placetype":"venue"
},
  "geometry": {"coordinates":[150.959228516,-33.7332649231],"type":"Point"}
}