{
  "type": "Feature",
  "properties": {
    "addr:full":"103 Hoddle St Collingwood VIC 3066",
    "addr:housenumber":"103",
    "addr:postcode":"3066",
    "addr:street":"Hoddle St",
    "iso:country":"AU",
    "sg:address":"103 Hoddle St",
    "sg:city":"Collingwood",
    "sg:classifiers":[
        {
            "category":"Professional",
            "subcategory":"Computer Services",
            "type":"Services"
        }
    ],
    "sg:phone":"+61 3 9419 5955",
    "sg:postcode":"3066",
    "sg:province":"VIC",
    "sg:tags":[
        "package",
        "software"
    ],
    "wof:name":"Sanderson Australia Pty Ltd",
    "wof:placetype":"venue"
},
  "geometry": {"coordinates":[144.99156189000001,-37.8068847656],"type":"Point"}
}