{
  "type": "Feature",
  "properties": {
    "addr:full":"106b Powlett St Kilmore VIC 3764",
    "addr:housenumber":"106b",
    "addr:postcode":"3764",
    "addr:street":"Powlett St",
    "iso:country":"AU",
    "sg:address":"106b Powlett St",
    "sg:city":"Kilmore",
    "sg:classifiers":[
        {
            "category":"Autos & Motor Vehicles",
            "subcategory":"Auto Supplies",
            "type":"Retail Goods"
        }
    ],
    "sg:phone":"+61 3 5782 1696",
    "sg:postcode":"3764",
    "sg:province":"VIC",
    "sg:tags":[
        "battery",
        "automotive"
    ],
    "wof:name":"Kilmore Auto Electrical",
    "wof:placetype":"venue"
},
  "geometry": {"coordinates":[144.95046997099999,-37.3060493469],"type":"Point"}
}