{
  "type": "Feature",
  "properties": {
    "iso:country":"AU",
    "sg:address":"Level 1, 7 Lydiard St",
    "sg:city":"South Ballarat",
    "sg:classifiers":[
        {
            "category":"Insurance",
            "subcategory":"Life Insurance",
            "type":"Services"
        }
    ],
    "sg:phone":"+61 418 536 603",
    "sg:postcode":"3350",
    "sg:province":"VIC",
    "wof:name":"McGuane Terry",
    "wof:placetype":"venue"
},
  "geometry": {"coordinates":[143.857834,-37.562401],"type":"Point"}
}