{
  "type": "Feature",
  "properties": {
    "addr:full":"25 Elkhorn Ave Surfers Paradise QLD 4217",
    "addr:housenumber":"25",
    "addr:postcode":"4217",
    "addr:street":"Elkhorn Ave",
    "iso:country":"AU",
    "sg:address":"25 Elkhorn Ave",
    "sg:city":"Surfers Paradise",
    "sg:classifiers":[
        {
            "category":"Retail",
            "subcategory":"Auto Rental",
            "type":"Services"
        }
    ],
    "sg:phone":"+61 1800 028 881",
    "sg:postcode":"4217",
    "sg:province":"QLD",
    "sg:tags":[
        "bus",
        "truck"
    ],
    "wof:name":"Choice Car Rentals",
    "wof:placetype":"venue"
},
  "geometry": {"coordinates":[153.42820739699999,-27.9987163544],"type":"Point"}
}