{
  "type": "Feature",
  "properties": {
    "addr:full":"400 Illawarra Rd Marrickville NSW 2204",
    "addr:housenumber":"400",
    "addr:postcode":"2204",
    "addr:street":"Illawarra Rd",
    "iso:country":"AU",
    "sg:address":"400 Illawarra Rd",
    "sg:city":"Marrickville",
    "sg:classifiers":[
        {
            "category":"Professional",
            "subcategory":"Accounting & Tax Preparation",
            "type":"Services"
        }
    ],
    "sg:phone":"+61 2 9559 7749",
    "sg:postcode":"2204",
    "sg:province":"NSW",
    "sg:tags":[
        "consultant",
        "taxation"
    ],
    "wof:name":"Trang K Nguyen & Binh V Nguyen",
    "wof:placetype":"venue"
},
  "geometry": {"coordinates":[151.149765,-33.91608],"type":"Point"}
}