{
  "type": "Feature",
  "properties": {
    "addr:full":"240 Peachey Rd Smithfield Plains SA 5114",
    "addr:housenumber":"240",
    "addr:postcode":"5114",
    "addr:street":"Peachey Rd",
    "iso:country":"AU",
    "sg:address":"240 Peachey Rd",
    "sg:city":"Smithfield Plains",
    "sg:classifiers":[
        {
            "category":"Health Services",
            "subcategory":"Doctor",
            "type":"Services"
        }
    ],
    "sg:phone":"+61 8 8254 6394",
    "sg:postcode":"5114",
    "sg:province":"SA",
    "sg:tags":[
        "medical",
        "practitioner"
    ],
    "wof:name":"Ling Francis H C",
    "wof:placetype":"venue"
},
  "geometry": {"coordinates":[138.676345825,-34.6764411926],"type":"Point"}
}