{
  "type": "Feature",
  "properties": {
    "iso:country":"AU",
    "sg:address":"211 Waverley Rd",
    "sg:city":"Malvern East",
    "sg:classifiers":[
        {
            "category":"Real Estate",
            "subcategory":"Developer",
            "type":"Services"
        }
    ],
    "sg:phone":"+61 3 9573 1189",
    "sg:postcode":"3145",
    "sg:province":"VIC",
    "sg:tags":[
        "development"
    ],
    "wof:name":"Dennis Family Corporation",
    "wof:placetype":"venue"
},
  "geometry": {"coordinates":[145.05250549300001,-37.8763313293],"type":"Point"}
}