{
  "type": "Feature",
  "properties": {
    "addr:full":"199 Toorak Rd South Yarra VIC 3141",
    "addr:housenumber":"199",
    "addr:postcode":"3141",
    "addr:street":"Toorak Rd",
    "iso:country":"AU",
    "sg:address":"199 Toorak Rd",
    "sg:city":"South Yarra",
    "sg:classifiers":[
        {
            "category":"Professional",
            "subcategory":"Employment Agencies",
            "type":"Services"
        }
    ],
    "sg:phone":"+61 3 9828 6565",
    "sg:postcode":"3141",
    "sg:province":"VIC",
    "wof:name":"McArthur Management Services Pty Ltd",
    "wof:placetype":"venue"
},
  "geometry": {"coordinates":[144.99395751899999,-37.839138031],"type":"Point"}
}