{
  "type": "Feature",
  "properties": {
    "iso:country":"AU",
    "sg:address":"26 Kinsellas Rd",
    "sg:city":"Mango Hill",
    "sg:classifiers":[
        {
            "category":"Professional",
            "subcategory":"Accounting & Tax Preparation",
            "type":"Services"
        }
    ],
    "sg:phone":"+61 411 017 478",
    "sg:postcode":"4509",
    "sg:province":"QLD",
    "sg:tags":[
        "bookkeeping"
    ],
    "wof:name":"DRG Bookkeeping Mango Hill",
    "wof:placetype":"venue"
},
  "geometry": {"coordinates":[153.02871704099999,-27.2292022705],"type":"Point"}
}