{
  "type": "Feature",
  "properties": {
    "iso:country":"AU",
    "sg:address":"Wells Rd",
    "sg:city":"Seaford South",
    "sg:classifiers":[
        {
            "category":"Education",
            "subcategory":"School",
            "type":"Public Place"
        }
    ],
    "sg:phone":"+61 3 9786 6066",
    "sg:postcode":"3198",
    "sg:province":"VIC",
    "sg:tags":[
        "state",
        "except",
        "nsw"
    ],
    "wof:name":"Kananook Primary",
    "wof:placetype":"venue"
},
  "geometry": {"coordinates":[145.13795471200001,-38.1102790833],"type":"Point"}
}