{
  "type": "Feature",
  "properties": {
    "addr:full":"PO Box 444 Doncaster VIC 3108",
    "addr:postcode":"3108",
    "iso:country":"AU",
    "sg:address":"PO Box 444",
    "sg:city":"Doncaster",
    "sg:classifiers":[
        {
            "category":"Professional",
            "subcategory":"Computer Services",
            "type":"Services"
        }
    ],
    "sg:phone":"+61 3 9848 9534",
    "sg:postcode":"3108",
    "sg:province":"VIC",
    "sg:tags":[
        "consultant",
        "system"
    ],
    "wof:name":"Neville J. Lang & Associates Pty Ltd",
    "wof:placetype":"venue"
},
  "geometry": {"coordinates":[145.122512817,-37.7830314636],"type":"Point"}
}