{
  "type": "Feature",
  "properties": {
    "addr:full":"17- 23 Carrington St Adelaide SA 5000",
    "addr:housenumber":"23",
    "addr:postcode":"5000",
    "addr:street":"Carrington St",
    "iso:country":"AU",
    "sg:address":"17- 23 Carrington St",
    "sg:city":"Adelaide",
    "sg:classifiers":[
        {
            "category":"Banks & Credit Unions",
            "subcategory":"Bank",
            "type":"Services"
        }
    ],
    "sg:phone":"+61 13 18 44",
    "sg:postcode":"5000",
    "sg:province":"SA",
    "sg:tags":[
        "society"
    ],
    "wof:name":"Police Credit Union",
    "wof:placetype":"venue"
},
  "geometry": {"coordinates":[138.60118102999999,-34.9315948486],"type":"Point"}
}