{
  "type": "Feature",
  "properties": {
    "addr:full":"Harper Rd Kangarilla SA 5157",
    "addr:postcode":"5157",
    "addr:street":"Harper Rd",
    "iso:country":"AU",
    "sg:address":"Harper Rd",
    "sg:city":"Kangarilla",
    "sg:classifiers":[
        {
            "category":"Building & Trades",
            "subcategory":"Landscaping Services",
            "type":"Services"
        }
    ],
    "sg:phone":"+61 8 8383 7002",
    "sg:postcode":"5157",
    "sg:province":"SA",
    "sg:tags":[
        "grazier"
    ],
    "wof:name":"Traeger Valley Pty Ltd",
    "wof:placetype":"venue"
},
  "geometry": {"coordinates":[138.708496094,-35.1522674561],"type":"Point"}
}