{
  "type": "Feature",
  "properties": {
    "iso:country":"AU",
    "sg:address":"2 / 130 Bonney Ave",
    "sg:city":"Clayfield",
    "sg:classifiers":[
        {
            "category":"Professional",
            "subcategory":"Art Services",
            "type":"Services"
        }
    ],
    "sg:phone":"+61 409 372 218",
    "sg:postcode":"4011",
    "sg:province":"QLD",
    "sg:tags":[
        "artist"
    ],
    "wof:name":"Judi Parkinson",
    "wof:placetype":"venue"
},
  "geometry": {"coordinates":[153.04718,-27.42066],"type":"Point"}
}