{
  "type": "Feature",
  "properties": {
    "iso:country":"AU",
    "sg:address":"7 Hamilton St",
    "sg:city":"Northgate",
    "sg:classifiers":[
        {
            "category":"Building & Trades",
            "subcategory":"Construction",
            "type":"Services"
        }
    ],
    "sg:phone":"+61 7 3260 6674",
    "sg:postcode":"4013",
    "sg:province":"QLD",
    "sg:tags":[
        "fencing",
        "contractor"
    ],
    "wof:name":"Sureline Fencing",
    "wof:placetype":"venue"
},
  "geometry": {"coordinates":[153.070037842,-27.3906536102],"type":"Point"}
}