{
  "type": "Feature",
  "properties": {
    "addr:full":"39 Pollack St Harrisville QLD 4307",
    "addr:housenumber":"39",
    "addr:postcode":"4307",
    "addr:street":"Pollack St",
    "iso:country":"AU",
    "sg:address":"39 Pollack St",
    "sg:city":"Harrisville",
    "sg:classifiers":[
        {
            "category":"Shopping",
            "type":"Retail Goods"
        }
    ],
    "sg:phone":"+61 7 5467 1109",
    "sg:postcode":"4307",
    "sg:province":"QLD",
    "sg:tags":[
        "agent",
        "stock"
    ],
    "wof:name":"Hayes Peter J",
    "wof:placetype":"venue"
},
  "geometry": {"coordinates":[152.66180419899999,-27.8114871979],"type":"Point"}
}