{
  "type": "Feature",
  "properties": {
    "addr:full":"Shop 8, Townhall Square, 464-480 Kent St Sydney NSW 1026",
    "addr:housenumber":"shop 8;464-480",
    "addr:postcode":"1026",
    "addr:street":"Townhall Square;Kent St",
    "iso:country":"AU",
    "sg:address":"Shop 8, Townhall Square, 464-480 Kent St",
    "sg:city":"Sydney",
    "sg:classifiers":[
        {
            "category":"Travel",
            "subcategory":"Travel Agent",
            "type":"Entertainment"
        }
    ],
    "sg:phone":"+61 2 9262 9692",
    "sg:postcode":"1026",
    "sg:province":"NSW",
    "sg:tags":[
        "consultant"
    ],
    "wof:name":"STA Travel",
    "wof:placetype":"venue"
},
  "geometry": {"coordinates":[151.20542907699999,-33.8741149902],"type":"Point"}
}