{
  "type": "Feature",
  "properties": {
    "addr:full":"28 Cross St Brookvale NSW 2100",
    "addr:housenumber":"28",
    "addr:postcode":"2100",
    "addr:street":"Cross St",
    "iso:country":"AU",
    "sg:address":"28 Cross St",
    "sg:city":"Brookvale",
    "sg:classifiers":[
        {
            "category":"Food & Beverages",
            "subcategory":"Bakery",
            "type":"Retail Goods"
        }
    ],
    "sg:phone":"+61 2 9905 6021",
    "sg:postcode":"2100",
    "sg:province":"NSW",
    "sg:tags":[
        "baker"
    ],
    "wof:name":"Fine Breads Of Australia Pty Ltd",
    "wof:placetype":"venue"
},
  "geometry": {"coordinates":[151.26547241200001,-33.764831543],"type":"Point"}
}