{
  "type": "Feature",
  "properties": {
    "iso:country":"AU",
    "sg:address":"104 Old Pittwater Rd",
    "sg:city":"Brookvale",
    "sg:classifiers":[
        {
            "category":"Manufacturing",
            "subcategory":"Metals",
            "type":"Manufacturing & Wholesale Goods"
        }
    ],
    "sg:phone":"+61 2 9939 7664",
    "sg:postcode":"2100",
    "sg:province":"NSW",
    "sg:tags":[
        "spinner"
    ],
    "wof:name":"A.D.N. Spunware",
    "wof:placetype":"venue"
},
  "geometry": {"coordinates":[151.26249694800001,-33.7639503479],"type":"Point"}
}