{
  "type": "Feature",
  "properties": {
    "iso:country":"AU",
    "sg:address":"Level 51, Melbourne Central Tower 360",
    "sg:city":"Elizabeth Melb Melbourne",
    "sg:classifiers":[
        {
            "category":"Real Estate",
            "subcategory":"Architect",
            "type":"Services"
        }
    ],
    "sg:phone":"+61 3 9654 9654",
    "sg:postcode":"3000",
    "sg:province":"VIC",
    "wof:name":"Williams J.C.",
    "wof:placetype":"venue"
},
  "geometry": {"coordinates":[144.968353272,-37.8130187988],"type":"Point"}
}