{
  "type": "Feature",
  "properties": {
    "iso:country":"AU",
    "sg:address":"64 O'Connell St",
    "sg:city":"Newtown",
    "sg:classifiers":[
        {
            "category":"Manufacturing",
            "subcategory":"Apparel",
            "type":"Manufacturing & Wholesale Goods"
        }
    ],
    "sg:phone":"+61 2 9516 3227",
    "sg:postcode":"2042",
    "sg:province":"NSW",
    "sg:tags":[
        "wholesaler",
        "mfrs",
        "footwear"
    ],
    "wof:name":"AXL Trading Co",
    "wof:placetype":"venue"
},
  "geometry": {"coordinates":[151.182205,-33.892746],"type":"Point"}
}