{
  "type": "Feature",
  "properties": {
    "iso:country":"AU",
    "sg:address":"18 City Rd",
    "sg:city":"Broadway",
    "sg:classifiers":[
        {
            "category":"Education",
            "subcategory":"Dance Studio",
            "type":"Public Place"
        }
    ],
    "sg:phone":"+61 2 8504 0265",
    "sg:postcode":"2007",
    "sg:province":"NSW",
    "sg:tags":[
        "venue",
        "tuition"
    ],
    "wof:name":"Latin Motion Dance Academy",
    "wof:placetype":"venue"
},
  "geometry": {"coordinates":[151.194580078,-33.8852767944],"type":"Point"}
}