{
  "type": "Feature",
  "properties": {
    "iso:country":"AU",
    "sg:address":"414 Kensington Rd",
    "sg:city":"Wattle Park",
    "sg:classifiers":[
        {
            "category":"Utilities",
            "subcategory":"Electric",
            "type":"Services"
        }
    ],
    "sg:phone":"+61 417 006 559",
    "sg:postcode":"5066",
    "sg:province":"SA",
    "sg:tags":[
        "electrical",
        "contractor"
    ],
    "wof:name":"Kettle G P Electrical",
    "wof:placetype":"venue"
},
  "geometry": {"coordinates":[138.68389892600001,-34.9298973083],"type":"Point"}
}