{
  "type": "Feature",
  "properties": {
    "addr:full":"41 Spencer St Bunbury WA 6230",
    "addr:housenumber":"41",
    "addr:postcode":"6230",
    "addr:street":"Spencer St",
    "iso:country":"AU",
    "sg:address":"41 Spencer St",
    "sg:city":"Bunbury",
    "sg:classifiers":[
        {
            "category":"Autos & Motor Vehicles",
            "subcategory":"Automobile Sales",
            "type":"Retail Goods"
        }
    ],
    "sg:phone":"+61 8 9721 4477",
    "sg:postcode":"6230",
    "sg:province":"WA",
    "sg:tags":[
        "car",
        "new"
    ],
    "wof:name":"Bunbury City Motors",
    "wof:placetype":"venue"
},
  "geometry": {"coordinates":[115.641548,-33.346901],"type":"Point"}
}