{
  "type": "Feature",
  "properties": {
    "addr:full":"114 Barker St Casino NSW 2470",
    "addr:housenumber":"114",
    "addr:postcode":"2470",
    "addr:street":"Barker St",
    "iso:country":"AU",
    "sg:address":"114 Barker St",
    "sg:city":"Casino",
    "sg:classifiers":[
        {
            "category":"Building & Trades",
            "subcategory":"Locksmith",
            "type":"Services"
        }
    ],
    "sg:phone":"+61 2 6662 5822",
    "sg:postcode":"2470",
    "sg:province":"NSW",
    "sg:tags":[
        "strongroom",
        "safe",
        "door"
    ],
    "wof:name":"Richmond Valley Locksmith",
    "wof:placetype":"venue"
},
  "geometry": {"coordinates":[153.047805786,-28.8647632599],"type":"Point"}
}