{
  "type": "Feature",
  "properties": {
    "addr:full":"66 Balo St Moree NSW 2400",
    "addr:housenumber":"66",
    "addr:postcode":"2400",
    "addr:street":"Balo St",
    "iso:country":"AU",
    "sg:address":"66 Balo St",
    "sg:city":"Moree",
    "sg:classifiers":[
        {
            "category":"Travel",
            "subcategory":"Travel Agent",
            "type":"Entertainment"
        }
    ],
    "sg:phone":"+61 2 6752 1575",
    "sg:postcode":"2400",
    "sg:province":"NSW",
    "sg:tags":[
        "consultant"
    ],
    "wof:name":"Moree Coach & Rail",
    "wof:placetype":"venue"
},
  "geometry": {"coordinates":[149.84175109899999,-29.4643573761],"type":"Point"}
}