{
  "type": "Feature",
  "properties": {
    "addr:full":"Stuart Hwy Glendambo SA 5710",
    "addr:postcode":"5710",
    "addr:street":"Stuart Hwy",
    "iso:country":"AU",
    "sg:address":"Stuart Hwy",
    "sg:city":"Glendambo",
    "sg:classifiers":[
        {
            "category":"Autos & Motor Vehicles",
            "subcategory":"Fuel & Gas Station",
            "type":"Retail Goods"
        }
    ],
    "sg:phone":"+61 8 8672 1035",
    "sg:postcode":"5710",
    "sg:province":"SA",
    "wof:name":"BP Glendambo Travelstop",
    "wof:placetype":"venue"
},
  "geometry": {"coordinates":[137.77220153799999,-32.4850463867],"type":"Point"}
}