{
  "type": "Feature",
  "properties": {
    "iso:country":"AU",
    "sg:address":"80 Mostyn St",
    "sg:city":"Castlemaine",
    "sg:classifiers":[
        {
            "category":"Professional",
            "subcategory":"Accounting & Tax Preparation",
            "type":"Services"
        }
    ],
    "sg:phone":"+61 3 5472 1138",
    "sg:postcode":"3450",
    "sg:province":"VIC",
    "sg:tags":[
        "consultant",
        "taxation"
    ],
    "wof:name":"Lawson Taxation Services Pty Ltd",
    "wof:placetype":"venue"
},
  "geometry": {"coordinates":[144.220794678,-37.066192627],"type":"Point"}
}