{
  "type": "Feature",
  "properties": {
    "addr:full":"Old Gracemere Rd Gracemere QLD 4702",
    "addr:postcode":"4702",
    "addr:street":"Gracemere Rd",
    "iso:country":"AU",
    "sg:address":"Old Gracemere Rd",
    "sg:city":"Gracemere",
    "sg:classifiers":[
        {
            "category":"Farming",
            "subcategory":"Farm & Veterinary Services",
            "type":"Manufacturing & Wholesale Goods"
        }
    ],
    "sg:phone":"+61 7 4933 1926",
    "sg:postcode":"4702",
    "sg:province":"QLD",
    "sg:tags":[
        "agricultural",
        "advisory"
    ],
    "wof:name":"Alan Spackman",
    "wof:placetype":"venue"
},
  "geometry": {"coordinates":[150.452194214,-23.4334201813],"type":"Point"}
}