{
  "type": "Feature",
  "properties": {
    "iso:country":"AU",
    "sg:address":"Cnr Richmond & Ellena Sts",
    "sg:city":"Maryborough",
    "sg:classifiers":[
        {
            "category":"Home & Garden",
            "subcategory":"Building Materials",
            "type":"Retail Goods"
        }
    ],
    "sg:phone":"+61 7 4122 2000",
    "sg:postcode":"4650",
    "sg:province":"QLD",
    "sg:tags":[
        "supply"
    ],
    "wof:name":"Dale & Meyers Timber Trade Centre Pty Ltd",
    "wof:placetype":"venue"
},
  "geometry": {"coordinates":[152.702896,-25.540688],"type":"Point"}
}