{
  "type": "Feature",
  "properties": {
    "addr:full":"33 Jermyn St Ulverstone TAS 7315",
    "addr:housenumber":"33",
    "addr:postcode":"7315",
    "addr:street":"Jermyn St",
    "iso:country":"AU",
    "sg:address":"33 Jermyn St",
    "sg:city":"Ulverstone",
    "sg:classifiers":[
        {
            "category":"Manufacturing",
            "subcategory":"Furniture",
            "type":"Manufacturing & Wholesale Goods"
        }
    ],
    "sg:phone":"+61 3 6425 4365",
    "sg:postcode":"7315",
    "sg:province":"TAS",
    "sg:tags":[
        "builder",
        "designer",
        "custom"
    ],
    "wof:name":"Beswick T & T",
    "wof:placetype":"venue"
},
  "geometry": {"coordinates":[146.16685485799999,-41.1634941101],"type":"Point"}
}