{
  "type": "Feature",
  "properties": {
    "iso:country":"AU",
    "sg:address":"310 Norton St",
    "sg:city":"Leichhardt",
    "sg:classifiers":[
        {
            "category":"Professional",
            "subcategory":"Accounting & Tax Preparation",
            "type":"Services"
        }
    ],
    "sg:phone":"+61 2 9560 7032",
    "sg:postcode":"2040",
    "sg:province":"NSW",
    "sg:tags":[
        "accountant",
        "auditor"
    ],
    "wof:name":"Mancuso S & Co Pty Ltd",
    "wof:placetype":"venue"
},
  "geometry": {"coordinates":[151.156067,-33.87682],"type":"Point"}
}