{
  "type": "Feature",
  "properties": {
    "addr:full":"11 Wheatley Drv Bullcreek WA 6149",
    "addr:housenumber":"11",
    "addr:postcode":"6149",
    "addr:street":"Wheatley Drv Bullcreek",
    "iso:country":"AU",
    "sg:address":"11 Wheatley Drv",
    "sg:city":"Bullcreek",
    "sg:classifiers":[
        {
            "category":"Retail",
            "subcategory":"Driving School",
            "type":"Services"
        }
    ],
    "sg:phone":"+61 8 9313 5883",
    "sg:postcode":"6149",
    "sg:province":"WA",
    "wof:name":"Ascot Driving School",
    "wof:placetype":"venue"
},
  "geometry": {"coordinates":[115.86467,-32.064346],"type":"Point"}
}