{
  "type": "Feature",
  "properties": {
    "addr:full":"233 Prospect Hwy Seven Hills NSW 2147",
    "addr:housenumber":"233",
    "addr:postcode":"2147",
    "addr:street":"Prospect Hwy",
    "iso:country":"AU",
    "sg:address":"233 Prospect Hwy",
    "sg:city":"Seven Hills",
    "sg:classifiers":[
        {
            "category":"Real Estate",
            "subcategory":"Real Estate Agent",
            "type":"Services"
        }
    ],
    "sg:phone":"+61 2 9831 2622",
    "sg:postcode":"2147",
    "sg:province":"NSW",
    "wof:name":"John Ross Century 21 Real Estate",
    "wof:placetype":"venue"
},
  "geometry": {"coordinates":[150.93406677199999,-33.7759819031],"type":"Point"}
}