{
  "type": "Feature",
  "properties": {
    "addr:full":"PO Box 45 Hamley Bridge SA 5401",
    "addr:postcode":"5401",
    "iso:country":"AU",
    "sg:address":"PO Box 45",
    "sg:city":"Hamley Bridge",
    "sg:classifiers":[
        {
            "category":"Home & Garden",
            "subcategory":"Household Appliances",
            "type":"Retail Goods"
        }
    ],
    "sg:phone":"+61 8 8528 2421",
    "sg:postcode":"5401",
    "sg:province":"SA",
    "sg:tags":[
        "equipment",
        "gas"
    ],
    "wof:name":"All Gas Consultancy Services",
    "wof:placetype":"venue"
},
  "geometry": {"coordinates":[138.65861511200001,-34.3192481995],"type":"Point"}
}