{
  "type": "Feature",
  "properties": {
    "iso:country":"AU",
    "sg:address":"108 South Rd",
    "sg:city":"Torrensville",
    "sg:classifiers":[
        {
            "category":"Professional",
            "subcategory":"Detective & Security Services",
            "type":"Services"
        }
    ],
    "sg:phone":"+61 8 8443 3333",
    "sg:postcode":"5031",
    "sg:province":"SA",
    "sg:tags":[
        "consultant",
        "system"
    ],
    "wof:name":"Australian Integrated Security",
    "wof:placetype":"venue"
},
  "geometry": {"coordinates":[138.568115234,-34.9191665649],"type":"Point"}
}