{
  "type": "Feature",
  "properties": {
    "addr:full":"Community Centre Wattle St Manangatang VIC 3546",
    "addr:postcode":"3546",
    "addr:street":"Wattle St",
    "iso:country":"AU",
    "sg:address":"Community Centre Wattle St",
    "sg:city":"Manangatang",
    "sg:classifiers":[
        {
            "category":"Social Services",
            "subcategory":"Child Care",
            "type":"Services"
        }
    ],
    "sg:phone":"+61 3 5035 1203",
    "sg:postcode":"3546",
    "sg:province":"VIC",
    "sg:tags":[
        "support",
        "health"
    ],
    "wof:name":"Maternal & Child Health Centres",
    "wof:placetype":"venue"
},
  "geometry": {"coordinates":[142.8828125,-35.0535545349],"type":"Point"}
}