{
  "type": "Feature",
  "properties": {
    "iso:country":"AU",
    "sg:address":"41 Perry St",
    "sg:city":"Mudgee",
    "sg:classifiers":[
        {
            "category":"Manufacturing",
            "subcategory":"Paper Products",
            "type":"Manufacturing & Wholesale Goods"
        }
    ],
    "sg:phone":"+61 2 6372 3028",
    "sg:postcode":"2850",
    "sg:province":"NSW",
    "sg:tags":[
        "bag"
    ],
    "wof:name":"Mudgee Wholesale Packaging",
    "wof:placetype":"venue"
},
  "geometry": {"coordinates":[149.585556,-32.594601],"type":"Point"}
}