{
  "type": "Feature",
  "properties": {
    "iso:country":"AU",
    "sg:address":"John Flynn Private Hospital, Inland Drv",
    "sg:city":"Tugun",
    "sg:classifiers":[
        {
            "category":"Health Services",
            "subcategory":"Doctor",
            "type":"Services"
        }
    ],
    "sg:phone":"+61 7 5598 0122",
    "sg:postcode":"4224",
    "sg:province":"QLD",
    "sg:tags":[
        "medical",
        "practitioner"
    ],
    "wof:name":"O&#039;Neill John",
    "wof:placetype":"venue"
},
  "geometry": {"coordinates":[153.49212646500001,-28.1418399811],"type":"Point"}
}