{
  "type": "Feature",
  "properties": {
    "iso:country":"AU",
    "sg:address":"PO Box 1427",
    "sg:city":"Baulkham Hills",
    "sg:classifiers":[
        {
            "category":"Education",
            "subcategory":"Special Training",
            "type":"Public Place"
        }
    ],
    "sg:phone":"+61 2 9894 0581",
    "sg:postcode":"2153",
    "sg:province":"NSW",
    "sg:tags":[
        "development"
    ],
    "wof:name":"Price Anthony",
    "wof:placetype":"venue"
},
  "geometry": {"coordinates":[150.97642517099999,-33.7541503906],"type":"Point"}
}