{
  "type": "Feature",
  "properties": {
    "iso:country":"AU",
    "sg:address":"5 Mabel St",
    "sg:city":"North Perth",
    "sg:classifiers":[
        {
            "category":"Food & Beverages",
            "subcategory":"Liquor & Beverages",
            "type":"Retail Goods"
        }
    ],
    "sg:phone":"+61 8 9444 6596",
    "sg:postcode":"6006",
    "sg:province":"WA",
    "sg:tags":[
        "merchant",
        "spirit",
        "wine"
    ],
    "wof:name":"Country Vintner Pty Ltd The",
    "wof:placetype":"venue"
},
  "geometry": {"coordinates":[115.858940124,-31.9243717194],"type":"Point"}
}