{
  "type": "Feature",
  "properties": {
    "addr:full":"18 Taralga Rd Goulburn NSW 2580",
    "addr:housenumber":"18",
    "addr:postcode":"2580",
    "addr:street":"Taralga Rd",
    "iso:country":"AU",
    "sg:address":"18 Taralga Rd",
    "sg:city":"Goulburn",
    "sg:phone":"+61 2 4821 4100",
    "sg:postcode":"2580",
    "sg:province":"NSW",
    "wof:name":"Economy Concrete Tanks (Goulburn)",
    "wof:placetype":"venue"
},
  "geometry": {"coordinates":[149.73562622099999,-34.7306175232],"type":"Point"}
}