{
  "type": "Feature",
  "properties": {
    "iso:country":"AU",
    "sg:address":"2 Glebe Rd",
    "sg:city":"New Norfolk",
    "sg:classifiers":[
        {
            "category":"Manufacturing",
            "subcategory":"Tools & Machinery",
            "type":"Manufacturing & Wholesale Goods"
        }
    ],
    "sg:phone":"+61 3 6261 3231",
    "sg:postcode":"7140",
    "sg:province":"TAS",
    "sg:tags":[
        "earth",
        "excavating",
        "moving",
        "equipment"
    ],
    "wof:name":"A M Williams",
    "wof:placetype":"venue"
},
  "geometry": {"coordinates":[147.06553600000001,-42.791924],"type":"Point"}
}