{
  "type": "Feature",
  "properties": {
    "addr:full":"13 Eschol Park Drv Eschol Park NSW 2558",
    "addr:housenumber":"13",
    "addr:postcode":"2558",
    "addr:street":"Eschol Park Drv",
    "iso:country":"AU",
    "sg:address":"13 Eschol Park Drv",
    "sg:city":"Eschol Park",
    "sg:classifiers":[
        {
            "category":"Utilities",
            "subcategory":"Electric",
            "type":"Services"
        }
    ],
    "sg:phone":"+61 418 113 823",
    "sg:postcode":"2558",
    "sg:province":"NSW",
    "sg:tags":[
        "electrical",
        "contractor"
    ],
    "wof:name":"Adelect Electrical Services",
    "wof:placetype":"venue"
},
  "geometry": {"coordinates":[150.81442260700001,-34.026966095],"type":"Point"}
}