{
  "type": "Feature",
  "properties": {
    "iso:country":"AU",
    "sg:address":"68 Martin Rd",
    "sg:city":"Glen Iris",
    "sg:classifiers":[
        {
            "category":"Health Services",
            "subcategory":"Health Practitioner",
            "type":"Services"
        }
    ],
    "sg:phone":"+61 3 9889 9992",
    "sg:postcode":"3146",
    "sg:province":"VIC",
    "sg:tags":[
        "psychologist"
    ],
    "wof:name":"Thomas Winsome",
    "wof:placetype":"venue"
},
  "geometry": {"coordinates":[145.05870056099999,-37.8516426086],"type":"Point"}
}