{
  "type": "Feature",
  "properties": {
    "iso:country":"AU",
    "sg:address":"16 Graham St",
    "sg:city":"Henty",
    "sg:classifiers":[
        {
            "category":"Utilities",
            "subcategory":"Electric",
            "type":"Services"
        }
    ],
    "sg:phone":"+61 500 545 434",
    "sg:postcode":"2658",
    "sg:province":"NSW",
    "sg:tags":[
        "electrical",
        "contractor"
    ],
    "wof:name":"Brenten Meyer",
    "wof:placetype":"venue"
},
  "geometry": {"coordinates":[147.03704834000001,-35.5170898438],"type":"Point"}
}