{
  "type": "Feature",
  "properties": {
    "addr:full":"7/ 401 Great Eastern Hwy Midland WA 6056",
    "addr:housenumber":"/ 401",
    "addr:postcode":"6056",
    "addr:street":"Great Eastern Hwy",
    "iso:country":"AU",
    "sg:address":"7/ 401 Great Eastern Hwy",
    "sg:city":"Midland",
    "sg:classifiers":[
        {
            "category":"Shopping",
            "subcategory":"Crafts & Fabrics",
            "type":"Retail Goods"
        }
    ],
    "sg:phone":"+61 8 9274 4955",
    "sg:postcode":"6056",
    "sg:province":"WA",
    "sg:tags":[
        "supply"
    ],
    "wof:name":"Handcrafters House",
    "wof:placetype":"venue"
},
  "geometry": {"coordinates":[116.006813049,-31.8887901306],"type":"Point"}
}