{
  "type": "Feature",
  "properties": {
    "iso:country":"AU",
    "sg:address":"Unit 1/ 126 Argyle St",
    "sg:city":"Albion",
    "sg:classifiers":[
        {
            "category":"Social Services",
            "type":"Services"
        }
    ],
    "sg:phone":"+61 1800 631 041",
    "sg:postcode":"4010",
    "sg:province":"QLD",
    "sg:tags":[
        "domestic",
        "help"
    ],
    "wof:name":"Dial-A-Sadie (Australia) Pty Ltd",
    "wof:placetype":"venue"
},
  "geometry": {"coordinates":[153.04263305699999,-27.4404525757],"type":"Point"}
}