{
  "type": "Feature",
  "properties": {
    "iso:country":"AU",
    "sg:address":"11 Carapook Crs",
    "sg:city":"Tallebudgera",
    "sg:classifiers":[
        {
            "category":"Building & Trades",
            "subcategory":"Construction",
            "type":"Services"
        }
    ],
    "sg:phone":"+61 7 5533 9181",
    "sg:postcode":"4228",
    "sg:province":"QLD",
    "sg:tags":[
        "contractor"
    ],
    "wof:name":"Steve Smith Building",
    "wof:placetype":"venue"
},
  "geometry": {"coordinates":[153.43301391599999,-28.1368694305],"type":"Point"}
}