{
  "type": "Feature",
  "properties": {
    "addr:full":"323 Hay St East Perth WA 6004",
    "addr:housenumber":"323",
    "addr:postcode":"6004",
    "addr:street":"Hay St East",
    "iso:country":"AU",
    "sg:address":"323 Hay St",
    "sg:city":"East Perth",
    "sg:classifiers":[
        {
            "category":"Arena",
            "subcategory":"Horse Racetrack",
            "type":"Entertainment"
        }
    ],
    "sg:phone":"+61 8 9221 9684",
    "sg:postcode":"6004",
    "sg:province":"WA",
    "sg:tags":[
        "retail",
        "swimwear"
    ],
    "wof:name":"Swim Shop The",
    "wof:placetype":"venue"
},
  "geometry": {"coordinates":[115.866363525,-31.9566917419],"type":"Point"}
}