{
  "type": "Feature",
  "properties": {
    "addr:full":"3 Clayton Rd Narrogin WA 6312",
    "addr:housenumber":"3",
    "addr:postcode":"6312",
    "addr:street":"Clayton Rd",
    "iso:country":"AU",
    "sg:address":"3 Clayton Rd",
    "sg:city":"Narrogin",
    "sg:classifiers":[
        {
            "category":"Home & Garden",
            "subcategory":"Carpets & Floor Coverings",
            "type":"Retail Goods"
        }
    ],
    "sg:phone":"+61 8 9881 4558",
    "sg:postcode":"6312",
    "sg:province":"WA",
    "sg:tags":[
        "tile",
        "wall"
    ],
    "wof:name":"Country Paint Supplies",
    "wof:placetype":"venue"
},
  "geometry": {"coordinates":[117.177963257,-32.9312171936],"type":"Point"}
}