{
  "type": "Feature",
  "properties": {
    "iso:country":"AU",
    "sg:address":"59 Dixon Rd",
    "sg:city":"Rockingham",
    "sg:classifiers":[
        {
            "category":"Autos & Motor Vehicles",
            "subcategory":"Auto Supplies",
            "type":"Retail Goods"
        }
    ],
    "sg:phone":"+61 8 9527 5093",
    "sg:postcode":"6168",
    "sg:province":"WA",
    "sg:tags":[
        "part",
        "cycles",
        "accessory"
    ],
    "wof:name":"Honda Country Motor Cycles",
    "wof:placetype":"venue"
},
  "geometry": {"coordinates":[115.75685900000001,-32.276806],"type":"Point"}
}