{
  "type": "Feature",
  "properties": {
    "addr:full":"148 McIntryre Rd Sunshine VIC 3020",
    "addr:housenumber":"148",
    "addr:postcode":"3020",
    "addr:street":"Mcintryre Rd",
    "iso:country":"AU",
    "sg:address":"148 McIntryre Rd",
    "sg:city":"Sunshine",
    "sg:classifiers":[
        {
            "category":"Wholesale",
            "subcategory":"Auto Parts",
            "type":"Manufacturing & Wholesale Goods"
        }
    ],
    "sg:phone":"+61 3 9311 0400",
    "sg:postcode":"3020",
    "sg:province":"VIC",
    "sg:tags":[
        "recyclers"
    ],
    "wof:name":"Auto Smart Car Recyclers",
    "wof:placetype":"venue"
},
  "geometry": {"coordinates":[144.83194,-37.760647],"type":"Point"}
}