{
  "type": "Feature",
  "properties": {
    "addr:full":"80 Grafton St Coffs Harbour NSW 2450",
    "addr:housenumber":"80",
    "addr:postcode":"2450",
    "addr:street":"Grafton St",
    "iso:country":"AU",
    "sg:address":"80 Grafton St",
    "sg:city":"Coffs Harbour",
    "sg:classifiers":[
        {
            "category":"Professional",
            "subcategory":"Business Services",
            "type":"Services"
        }
    ],
    "sg:phone":"+61 1300 650 058",
    "sg:postcode":"2450",
    "sg:province":"NSW",
    "sg:tags":[
        "small",
        "advisory"
    ],
    "wof:name":"Mid-North Coast Business Advisory Service",
    "wof:placetype":"venue"
},
  "geometry": {"coordinates":[153.11459400000001,-30.295349],"type":"Point"}
}