{
  "type": "Feature",
  "properties": {
    "addr:full":"75 Mitchell Rd Cardiff NSW 2285",
    "addr:housenumber":"75",
    "addr:postcode":"2285",
    "addr:street":"Mitchell Rd",
    "iso:country":"AU",
    "sg:address":"75 Mitchell Rd",
    "sg:city":"Cardiff",
    "sg:classifiers":[
        {
            "category":"Wholesale",
            "subcategory":"Machinery & Supplies",
            "type":"Manufacturing & Wholesale Goods"
        }
    ],
    "sg:phone":"+61 2 4954 7744",
    "sg:postcode":"2285",
    "sg:province":"NSW",
    "sg:tags":[
        "engineer"
    ],
    "wof:name":"Merino Engineering Supplies Pty Ltd",
    "wof:placetype":"venue"
},
  "geometry": {"coordinates":[151.642501831,-32.9446029663],"type":"Point"}
}