{
  "type": "Feature",
  "properties": {
    "addr:full":"Unit 1, 11 Shaw Rd Ingleburn NSW 1890",
    "addr:housenumber":"11",
    "addr:postcode":"1890",
    "addr:street":"Shaw Rd",
    "iso:country":"AU",
    "sg:address":"Unit 1, 11 Shaw Rd",
    "sg:city":"Ingleburn",
    "sg:classifiers":[
        {
            "category":"Professional",
            "type":"Services"
        }
    ],
    "sg:phone":"+61 2 9605 5777",
    "sg:postcode":"1890",
    "sg:province":"NSW",
    "sg:tags":[
        "transport"
    ],
    "wof:name":"M.J.O.Enterprises Pty Ltd",
    "wof:placetype":"venue"
},
  "geometry": {"coordinates":[150.855926514,-34.0007362366],"type":"Point"}
}