{
  "type": "Feature",
  "properties": {
    "iso:country":"AU",
    "sg:address":"Unit 1 / 4 Merlin St",
    "sg:city":"Neutral Bay",
    "sg:classifiers":[
        {
            "category":"Professional",
            "subcategory":"Computer Services",
            "type":"Services"
        }
    ],
    "sg:phone":"+61 413 127 444",
    "sg:postcode":"2089",
    "sg:province":"NSW",
    "sg:tags":[
        "consultant",
        "system"
    ],
    "wof:name":"Amulet Solutions",
    "wof:placetype":"venue"
},
  "geometry": {"coordinates":[151.217453003,-33.8389053345],"type":"Point"}
}