{
  "type": "Feature",
  "properties": {
    "iso:country":"AU",
    "sg:address":"687a The Horsley Drv",
    "sg:city":"Smithfield",
    "sg:classifiers":[
        {
            "category":"Professional",
            "subcategory":"Accounting & Tax Preparation",
            "type":"Services"
        }
    ],
    "sg:phone":"+61 2 9757 4667",
    "sg:postcode":"2164",
    "sg:province":"NSW",
    "sg:tags":[
        "consultant",
        "taxation"
    ],
    "wof:name":"Block H & R",
    "wof:placetype":"venue"
},
  "geometry": {"coordinates":[150.93951415999999,-33.8532104492],"type":"Point"}
}