{
  "type": "Feature",
  "properties": {
    "addr:full":"117 Brighton Rd Sandgate QLD 4017",
    "addr:housenumber":"117",
    "addr:postcode":"4017",
    "addr:street":"Brighton Rd",
    "iso:country":"AU",
    "sg:address":"117 Brighton Rd",
    "sg:city":"Sandgate",
    "sg:classifiers":[
        {
            "category":"Banks & Credit Unions",
            "subcategory":"Bank",
            "type":"Services"
        }
    ],
    "sg:phone":"+61 7 3869 3117",
    "sg:postcode":"4017",
    "sg:province":"QLD",
    "sg:tags":[
        "broker",
        "mortgage"
    ],
    "wof:name":"Wizard",
    "wof:placetype":"venue"
},
  "geometry": {"coordinates":[153.06788635300001,-27.317779541],"type":"Point"}
}