{
  "type": "Feature",
  "properties": {
    "addr:full":"36 Mount Leyshon Rd Charters Towers QLD 4820",
    "addr:housenumber":"36",
    "addr:postcode":"4820",
    "addr:street":"Mount Leyshon Rd",
    "iso:country":"AU",
    "sg:address":"36 Mount Leyshon Rd",
    "sg:city":"Charters Towers",
    "sg:classifiers":[
        {
            "category":"Banks & Credit Unions",
            "subcategory":"Investment Brokerage",
            "type":"Services"
        }
    ],
    "sg:phone":"+61 7 4787 4166",
    "sg:postcode":"4820",
    "sg:province":"QLD",
    "sg:tags":[
        "radiator",
        "motor"
    ],
    "wof:name":"R & C Radiators & Batteries",
    "wof:placetype":"venue"
},
  "geometry": {"coordinates":[146.262405,-20.089624],"type":"Point"}
}