{
  "type": "Feature",
  "properties": {
    "addr:full":"Unit 4 / Nowra South NSW 2541",
    "addr:postcode":"2541",
    "iso:country":"AU",
    "sg:address":"Unit 4",
    "sg:city":"/ Nowra South",
    "sg:classifiers":[
        {
            "category":"Recreation",
            "subcategory":"Amusement Park",
            "type":"Entertainment"
        }
    ],
    "sg:phone":"+61 2 4423 1665",
    "sg:postcode":"2541",
    "sg:province":"NSW",
    "wof:name":"Bounce N Slide On Central",
    "wof:placetype":"venue"
},
  "geometry": {"coordinates":[150.604370117,-34.875038147],"type":"Point"}
}