{
  "type": "Feature",
  "properties": {
    "addr:full":"Cnr South Rd & Sir Donald Bradman Drv Mile End SA 5031",
    "addr:postcode":"5031",
    "addr:street":"Cnr South Rd & Sir Donald Bradman Drv",
    "iso:country":"AU",
    "sg:address":"Cnr South Rd & Sir Donald Bradman Drv",
    "sg:city":"Mile End",
    "sg:classifiers":[
        {
            "category":"Health Services",
            "subcategory":"Medical Lab",
            "type":"Services"
        }
    ],
    "sg:phone":"+61 8 8159 7900",
    "sg:postcode":"5031",
    "sg:province":"SA",
    "sg:tags":[
        "laboratory",
        "pathology"
    ],
    "wof:name":"Abbott Pathology",
    "wof:placetype":"venue"
},
  "geometry": {"coordinates":[138.56988525400001,-34.9241867065],"type":"Point"}
}