{
  "type": "Feature",
  "properties": {
    "addr:full":"PO Box 6428 Melbourne VIC 3004",
    "addr:postcode":"3004",
    "iso:country":"AU",
    "sg:address":"PO Box 6428",
    "sg:city":"Melbourne",
    "sg:classifiers":[
        {
            "category":"Building & Trades",
            "subcategory":"Cleaning & Sanitation",
            "type":"Services"
        }
    ],
    "sg:phone":"+61 3 9563 3534",
    "sg:postcode":"3004",
    "sg:province":"VIC",
    "sg:tags":[
        "industrial",
        "commercial",
        "contractor"
    ],
    "wof:name":"Buzz Cleaning Services",
    "wof:placetype":"venue"
},
  "geometry": {"coordinates":[144.97633361800001,-37.8373184204],"type":"Point"}
}