{
  "type": "Feature",
  "properties": {
    "iso:country":"AU",
    "sg:address":"Cnr Maritana & Bourke Sts",
    "sg:city":"Kalgoorlie",
    "sg:classifiers":[
        {
            "category":"Autos & Motor Vehicles",
            "subcategory":"Fuel & Gas Station",
            "type":"Retail Goods"
        }
    ],
    "sg:phone":"+61 8 9021 8488",
    "sg:postcode":"6430",
    "sg:province":"WA",
    "wof:name":"Gull Petroleum (WA) Pty Ltd",
    "wof:placetype":"venue"
},
  "geometry": {"coordinates":[121.472511291,-30.74451828],"type":"Point"}
}