{
  "type": "Feature",
  "properties": {
    "addr:full":"284 Bondi Rd Bondi NSW 2026",
    "addr:housenumber":"284",
    "addr:postcode":"2026",
    "addr:street":"Bondi Rd",
    "iso:country":"AU",
    "sg:address":"284 Bondi Rd",
    "sg:city":"Bondi",
    "sg:classifiers":[
        {
            "category":"Professional",
            "subcategory":"Art Services",
            "type":"Services"
        }
    ],
    "sg:phone":"+61 2 9300 8844",
    "sg:postcode":"2026",
    "sg:province":"NSW",
    "sg:tags":[
        "picture",
        "frame",
        "framing"
    ],
    "wof:name":"Hall of Frame",
    "wof:placetype":"venue"
},
  "geometry": {"coordinates":[151.267822266,-33.8943977356],"type":"Point"}
}