{
  "type": "Feature",
  "properties": {
    "addr:full":"St Arnaud VIC 3478",
    "addr:postcode":"3478",
    "iso:country":"AU",
    "sg:address":"St",
    "sg:city":"Arnaud",
    "sg:classifiers":[
        {
            "category":"Building & Trades",
            "subcategory":"Cleaning & Sanitation",
            "type":"Services"
        }
    ],
    "sg:phone":"+61 3 5496 2247",
    "sg:postcode":"3478",
    "sg:province":"VIC",
    "sg:tags":[
        "abrasive",
        "blasting"
    ],
    "wof:name":"Peacocks Blast Cleaning",
    "wof:placetype":"venue"
},
  "geometry": {"coordinates":[143.25793457,-36.6163482666],"type":"Point"}
}