{
  "type": "Feature",
  "properties": {
    "iso:country":"AU",
    "sg:address":"PO Box 1369",
    "sg:city":"Tuggeranong",
    "sg:classifiers":[
        {
            "category":"Education",
            "subcategory":"Dance Studio",
            "type":"Public Place"
        }
    ],
    "sg:phone":"+61 2 6231 0363",
    "sg:postcode":"2901",
    "sg:province":"ACT",
    "sg:tags":[
        "venue",
        "tuition"
    ],
    "wof:name":"Shimmy Bellydance",
    "wof:placetype":"venue"
},
  "geometry": {"coordinates":[149.05650329599999,-35.4157295227],"type":"Point"}
}