{
  "type": "Feature",
  "properties": {
    "addr:full":"2 Theodore St Bundaberg QLD 4670",
    "addr:housenumber":"2",
    "addr:postcode":"4670",
    "addr:street":"Theodore St",
    "iso:country":"AU",
    "sg:address":"2 Theodore St",
    "sg:city":"Bundaberg",
    "sg:classifiers":[
        {
            "category":"Utilities",
            "subcategory":"Water",
            "type":"Services"
        }
    ],
    "sg:phone":"+61 7 4153 5966",
    "sg:postcode":"4670",
    "sg:province":"QLD",
    "sg:tags":[
        "hot",
        "system"
    ],
    "wof:name":"Mooney Trevor Electrical & Plumbing",
    "wof:placetype":"venue"
},
  "geometry": {"coordinates":[152.34231567399999,-24.8838329315],"type":"Point"}
}