{
  "type": "Feature",
  "properties": {
    "iso:country":"AU",
    "sg:address":"230 Comur St",
    "sg:city":"Yass",
    "sg:classifiers":[
        {
            "category":"Real Estate",
            "subcategory":"Real Estate Agent",
            "type":"Services"
        }
    ],
    "sg:phone":"+61 2 6226 1648",
    "sg:postcode":"2582",
    "sg:province":"NSW",
    "sg:tags":[
        "handyman's",
        "equipment",
        "hire",
        "builders",
        "contractor"
    ],
    "wof:name":"Yass Outdoor Power Centre",
    "wof:placetype":"venue"
},
  "geometry": {"coordinates":[148.91416931099999,-34.8452301025],"type":"Point"}
}