{
  "type": "Feature",
  "properties": {
    "addr:full":"52 Salkeld St Tarragindi QLD 4121",
    "addr:housenumber":"52",
    "addr:postcode":"4121",
    "addr:street":"Salkeld St",
    "iso:country":"AU",
    "sg:address":"52 Salkeld St",
    "sg:city":"Tarragindi",
    "sg:classifiers":[
        {
            "category":"Building & Trades",
            "subcategory":"Pest Control",
            "type":"Services"
        }
    ],
    "sg:phone":"+61 7 3411 7074",
    "sg:postcode":"4121",
    "sg:province":"QLD",
    "sg:website":"http://www.twinspectors.com.au",
    "wof:name":"Twinspectors",
    "wof:placetype":"venue"
},
  "geometry": {"coordinates":[153.04371643100001,-27.5257549286],"type":"Point"}
}