{
  "type": "Feature",
  "properties": {
    "iso:country":"AU",
    "sg:address":"16 Yarrabin St",
    "sg:city":"Belrose",
    "sg:classifiers":[
        {
            "category":"Shopping",
            "subcategory":"Computers & Home Electronics",
            "type":"Retail Goods"
        }
    ],
    "sg:phone":"+61 2 9452 1113",
    "sg:postcode":"2085",
    "sg:province":"NSW",
    "sg:tags":[
        "cleaning"
    ],
    "wof:name":"Computer Extras Pty Ltd",
    "wof:placetype":"venue"
},
  "geometry": {"coordinates":[151.21443176299999,-33.7381820679],"type":"Point"}
}