{
  "type": "Feature",
  "properties": {
    "iso:country":"AU",
    "sg:address":"34 Marian St",
    "sg:city":"Guildford",
    "sg:classifiers":[
        {
            "category":"Bus Charters",
            "type":"Transportation"
        }
    ],
    "sg:phone":"+61 2 9721 5100",
    "sg:postcode":"2161",
    "sg:province":"NSW",
    "sg:tags":[
        "builder"
    ],
    "wof:name":"Custom Coaches (Sales) Pty Ltd",
    "wof:placetype":"venue"
},
  "geometry": {"coordinates":[150.989990234,-33.8521881104],"type":"Point"}
}