{
  "type": "Feature",
  "properties": {
    "iso:country":"AU",
    "sg:address":"230 Cambridge Rd",
    "sg:city":"Kilsyth",
    "sg:classifiers":[
        {
            "category":"Building & Trades",
            "subcategory":"Construction",
            "type":"Services"
        }
    ],
    "sg:phone":"+61 3 9728 2537",
    "sg:postcode":"3137",
    "sg:province":"VIC",
    "sg:tags":[
        "plasterboard",
        "plasterer",
        "fixer"
    ],
    "wof:name":"Roberts Plasterers",
    "wof:placetype":"venue"
},
  "geometry": {"coordinates":[145.33128356899999,-37.8006210327],"type":"Point"}
}