{
  "type": "Feature",
  "properties": {
    "addr:full":"95-97 Merimbula Drv Merimbula NSW 2548",
    "addr:housenumber":"95-97",
    "addr:postcode":"2548",
    "addr:street":"Merimbula Drv",
    "iso:country":"AU",
    "sg:address":"95-97 Merimbula Drv",
    "sg:city":"Merimbula",
    "sg:classifiers":[
        {
            "category":"Travel",
            "subcategory":"Hotels & Motels",
            "type":"Entertainment"
        }
    ],
    "sg:phone":"+61 2 6495 1587",
    "sg:postcode":"2548",
    "sg:province":"NSW",
    "wof:name":"HC Resort-Hillcrest Motor Inn",
    "wof:placetype":"venue"
},
  "geometry": {"coordinates":[149.897903442,-36.8889007568],"type":"Point"}
}