{
  "type": "Feature",
  "properties": {
    "addr:full":"Cross St Hurstville NSW 2220",
    "addr:postcode":"2220",
    "addr:street":"Cross St",
    "iso:country":"AU",
    "sg:address":"Cross St",
    "sg:city":"Hurstville",
    "sg:classifiers":[
        {
            "category":"Home & Garden",
            "subcategory":"Building Materials",
            "type":"Retail Goods"
        }
    ],
    "sg:phone":"+61 2 9540 5103",
    "sg:postcode":"2220",
    "sg:province":"NSW",
    "sg:tags":[
        "merchant",
        "glass",
        "glazier"
    ],
    "wof:name":"Statewide Buying Group",
    "wof:placetype":"venue"
},
  "geometry": {"coordinates":[151.10418701200001,-33.965965271],"type":"Point"}
}