{
  "type": "Feature",
  "properties": {
    "addr:full":"Shop 1082 Westfield Shoppingtown Tuggerah NSW 2259",
    "addr:housenumber":"1082",
    "addr:postcode":"2259",
    "addr:street":"Westfield Shoppingtown",
    "iso:country":"AU",
    "sg:address":"Shop 1082",
    "sg:city":"Westfield Shoppingtown Tuggerah",
    "sg:classifiers":[
        {
            "category":"Shopping",
            "subcategory":"Computers & Home Electronics",
            "type":"Retail Goods"
        }
    ],
    "sg:phone":"+61 2 4353 5440",
    "sg:postcode":"2259",
    "sg:province":"NSW",
    "sg:tags":[
        "equipment",
        "part",
        "electronic"
    ],
    "wof:name":"Tandy Electronics",
    "wof:placetype":"venue"
},
  "geometry": {"coordinates":[151.415557861,-33.306930542],"type":"Point"}
}