{
  "type": "Feature",
  "properties": {
    "addr:full":"22 Wells St Bellevue WA 6056",
    "addr:housenumber":"22",
    "addr:postcode":"6056",
    "addr:street":"Wells St",
    "iso:country":"AU",
    "sg:address":"22 Wells St",
    "sg:city":"Bellevue",
    "sg:classifiers":[
        {
            "category":"Banks & Credit Unions",
            "subcategory":"Investment Brokerage",
            "type":"Services"
        }
    ],
    "sg:phone":"+61 8 9250 3232",
    "sg:postcode":"6056",
    "sg:province":"WA",
    "sg:tags":[
        "radiator",
        "motor"
    ],
    "wof:name":"Choice Radiators",
    "wof:placetype":"venue"
},
  "geometry": {"coordinates":[116.018440247,-31.9001674652],"type":"Point"}
}