{
  "type": "Feature",
  "properties": {
    "addr:full":"190 Birkdale Rd Birkdale QLD 4159",
    "addr:housenumber":"190",
    "addr:postcode":"4159",
    "addr:street":"Birkdale Rd",
    "iso:country":"AU",
    "sg:address":"190 Birkdale Rd",
    "sg:city":"Birkdale",
    "sg:classifiers":[
        {
            "category":"Health Services",
            "subcategory":"Health Practitioner",
            "type":"Services"
        }
    ],
    "sg:phone":"+61 7 3822 2122",
    "sg:postcode":"4159",
    "sg:province":"QLD",
    "sg:tags":[
        "physiotherapist"
    ],
    "wof:name":"Aylward Damian Sports & Family Physio",
    "wof:placetype":"venue"
},
  "geometry": {"coordinates":[153.210861206,-27.5004692078],"type":"Point"}
}