{
  "type": "Feature",
  "properties": {
    "addr:full":"19 / 663 Newcaslte St Leederville WA 6007",
    "addr:housenumber":"19 / 663",
    "addr:postcode":"6007",
    "addr:street":"Newcaslte St",
    "iso:country":"AU",
    "sg:address":"19 / 663 Newcaslte St",
    "sg:city":"Leederville",
    "sg:classifiers":[
        {
            "category":"Health Services",
            "subcategory":"Chiropractor",
            "type":"Services"
        }
    ],
    "sg:phone":"+61 8 9444 0100",
    "sg:postcode":"6007",
    "sg:province":"WA",
    "wof:name":"Leederville Chiropractic",
    "wof:placetype":"venue"
},
  "geometry": {"coordinates":[115.84204864500001,-31.9376754761],"type":"Point"}
}