{
  "type": "Feature",
  "properties": {
    "iso:country":"AU",
    "sg:address":"13 Keysor Rd",
    "sg:city":"Pagewood",
    "sg:classifiers":[
        {
            "category":"Professional",
            "subcategory":"Art Services",
            "type":"Services"
        }
    ],
    "sg:phone":"+61 407 131 714",
    "sg:postcode":"2035",
    "sg:province":"NSW",
    "sg:tags":[
        "decorator",
        "painter"
    ],
    "wof:name":"Pas Painters & Decorators",
    "wof:placetype":"venue"
},
  "geometry": {"coordinates":[151.22892761200001,-33.936164856],"type":"Point"}
}