{
  "type": "Feature",
  "properties": {
    "addr:full":"11 Newcastle St Rose Bay NSW 2029",
    "addr:housenumber":"11",
    "addr:postcode":"2029",
    "addr:street":"Newcastle St",
    "iso:country":"AU",
    "sg:address":"11 Newcastle St",
    "sg:city":"Rose Bay",
    "sg:classifiers":[
        {
            "category":"Health Services",
            "subcategory":"Doctor",
            "type":"Services"
        }
    ],
    "sg:phone":"+61 2 9371 1556",
    "sg:postcode":"2029",
    "sg:province":"NSW",
    "sg:tags":[
        "medical",
        "practitioner"
    ],
    "wof:name":"Yaniv I",
    "wof:placetype":"venue"
},
  "geometry": {"coordinates":[151.269088745,-33.870426178],"type":"Point"}
}