{
  "type": "Feature",
  "properties": {
    "addr:full":"1 Duffield St Gawler SA 5118",
    "addr:housenumber":"1",
    "addr:postcode":"5118",
    "addr:street":"Duffield St",
    "iso:country":"AU",
    "sg:address":"1 Duffield St",
    "sg:city":"Gawler",
    "sg:classifiers":[
        {
            "category":"Health Services",
            "subcategory":"Nursing And Care Facility",
            "type":"Services"
        }
    ],
    "sg:phone":"+61 8 8522 1355",
    "sg:postcode":"5118",
    "sg:province":"SA",
    "sg:tags":[
        "home"
    ],
    "wof:name":"Martindale Nursing Home",
    "wof:placetype":"venue"
},
  "geometry": {"coordinates":[138.751755,-34.600971],"type":"Point"}
}