{
  "type": "Feature",
  "properties": {
    "addr:full":"31 Newcastle St Fairfield QLD 4103",
    "addr:housenumber":"31",
    "addr:postcode":"4103",
    "addr:street":"Newcastle St",
    "iso:country":"AU",
    "sg:address":"31 Newcastle St",
    "sg:city":"Fairfield",
    "sg:classifiers":[
        {
            "category":"Banks & Credit Unions",
            "subcategory":"Atm",
            "type":"Services"
        }
    ],
    "sg:phone":"+61 409 274 211",
    "sg:postcode":"4103",
    "sg:province":"QLD",
    "sg:tags":[
        "reconditioners",
        "drum",
        "manufacturers"
    ],
    "wof:name":"Mad About Drums",
    "wof:placetype":"venue"
},
  "geometry": {"coordinates":[153.020019531,-27.5066680908],"type":"Point"}
}