{
  "type": "Feature",
  "properties": {
    "iso:country":"AU",
    "sg:address":"52 Hoskins St",
    "sg:city":"Mitchell",
    "sg:classifiers":[
        {
            "category":"Professional",
            "subcategory":"Printing & Photocopies",
            "type":"Services"
        }
    ],
    "sg:phone":"+61 2 6241 2313",
    "sg:postcode":"2911",
    "sg:province":"ACT",
    "sg:tags":[
        "screen",
        "printer"
    ],
    "wof:name":"Euro Sport",
    "wof:placetype":"venue"
},
  "geometry": {"coordinates":[149.137573242,-35.2160987854],"type":"Point"}
}