{
  "type": "Feature",
  "properties": {
    "iso:country":"AU",
    "sg:address":"Wonthaggi Road",
    "sg:city":"Loch",
    "sg:classifiers":[
        {
            "category":"Wholesale",
            "subcategory":"Meat",
            "type":"Manufacturing & Wholesale Goods"
        }
    ],
    "sg:phone":"+61 3 5657 2300",
    "sg:postcode":"3945",
    "sg:province":"VIC",
    "sg:tags":[
        "abattoir"
    ],
    "wof:name":"Arden Jenkins & Son Pty Ltd",
    "wof:placetype":"venue"
},
  "geometry": {"coordinates":[145.70698547399999,-38.3687782288],"type":"Point"}
}