{
  "type": "Feature",
  "properties": {
    "iso:country":"AU",
    "sg:address":"Unit 5 513 Grand Junction Rd",
    "sg:city":"Wingfield",
    "sg:classifiers":[
        {
            "category":"Autos & Motor Vehicles",
            "subcategory":"Auto Supplies",
            "type":"Retail Goods"
        }
    ],
    "sg:phone":"+61 8 8268 2633",
    "sg:postcode":"5013",
    "sg:province":"SA",
    "sg:tags":[
        "wheel",
        "four",
        "equipment",
        "drive",
        "accessory"
    ],
    "wof:name":"J & S Duce Industries",
    "wof:placetype":"venue"
},
  "geometry": {"coordinates":[138.56036376899999,-34.8497428894],"type":"Point"}
}