{
  "type": "Feature",
  "properties": {
    "addr:full":"73 Seventh St Mildura VIC 3500",
    "addr:housenumber":"73",
    "addr:postcode":"3500",
    "addr:street":"Seventh St",
    "iso:country":"AU",
    "sg:address":"73 Seventh St",
    "sg:city":"Mildura",
    "sg:classifiers":[
        {
            "category":"Fast Food",
            "type":"Food & Drink"
        }
    ],
    "sg:phone":"+61 3 5022 0252",
    "sg:postcode":"3500",
    "sg:province":"VIC",
    "sg:tags":[
        "away",
        "take"
    ],
    "wof:name":"Debs Takeaway",
    "wof:placetype":"venue"
},
  "geometry": {"coordinates":[142.153244019,-34.1758880615],"type":"Point"}
}