{
  "type": "Feature",
  "properties": {
    "iso:country":"AU",
    "sg:address":"Level 7, 288 Edward St",
    "sg:city":"Brisbane",
    "sg:classifiers":[
        {
            "category":"Health Services",
            "subcategory":"Doctor",
            "type":"Services"
        }
    ],
    "sg:phone":"+61 1800 211 555",
    "sg:postcode":"4000",
    "sg:province":"QLD",
    "sg:tags":[
        "nurse",
        "nursing"
    ],
    "wof:name":"Medistaff",
    "wof:placetype":"venue"
},
  "geometry": {"coordinates":[153.02569580100001,-27.4672489166],"type":"Point"}
}