{
  "type": "Feature",
  "properties": {
    "iso:country":"AU",
    "sg:address":"87 Albion St",
    "sg:city":"Annandale",
    "sg:classifiers":[
        {
            "category":"Health Services",
            "subcategory":"Health Practitioner",
            "type":"Services"
        }
    ],
    "sg:phone":"+61 2 9564 6102",
    "sg:postcode":"2038",
    "sg:province":"NSW",
    "sg:tags":[
        "psychologist"
    ],
    "wof:name":"Duncan Bob",
    "wof:placetype":"venue"
},
  "geometry": {"coordinates":[151.16380310100001,-33.8870620728],"type":"Point"}
}