{
  "type": "Feature",
  "properties": {
    "addr:full":"55 Cox Crs Dundas Valley NSW 2117",
    "addr:housenumber":"55",
    "addr:postcode":"2117",
    "addr:street":"Cox Crs",
    "iso:country":"AU",
    "sg:address":"55 Cox Crs",
    "sg:city":"Dundas Valley",
    "sg:classifiers":[
        {
            "category":"Arena",
            "subcategory":"Sports Club",
            "type":"Entertainment"
        }
    ],
    "sg:phone":"+61 406 949 914",
    "sg:postcode":"2117",
    "sg:province":"NSW",
    "sg:tags":[
        "defence",
        "supply",
        "self",
        "instruction",
        "martial art"
    ],
    "wof:name":"Kenseikan Karate Australia",
    "wof:placetype":"venue"
},
  "geometry": {"coordinates":[151.061447144,-33.7874183655],"type":"Point"}
}