{
  "type": "Feature",
  "properties": {
    "iso:country":"AU",
    "sg:address":"2/51 Edgar St",
    "sg:city":"Glen Iris",
    "sg:classifiers":[
        {
            "category":"Building & Trades",
            "subcategory":"Construction",
            "type":"Services"
        }
    ],
    "sg:phone":"+61 420 822 544",
    "sg:postcode":"3146",
    "sg:province":"VIC",
    "sg:tags":[
        "joiner",
        "carpenter"
    ],
    "wof:name":"Reid Master Carpentry",
    "wof:placetype":"venue"
},
  "geometry": {"coordinates":[145.045776367,-37.8525123596],"type":"Point"}
}