{
  "type": "Feature",
  "properties": {
    "addr:full":"101 Bentinck St Portland VIC 3305",
    "addr:housenumber":"101",
    "addr:postcode":"3305",
    "addr:street":"Bentinck St",
    "iso:country":"AU",
    "sg:address":"101 Bentinck St",
    "sg:city":"Portland",
    "sg:classifiers":[
        {
            "category":"Cafe",
            "type":"Food & Drink"
        }
    ],
    "sg:phone":"+61 3 5523 1032",
    "sg:postcode":"3305",
    "sg:province":"VIC",
    "wof:name":"Edward's Waterfront Cafe/Restaurant",
    "wof:placetype":"venue"
},
  "geometry": {"coordinates":[141.606124878,-38.347946167],"type":"Point"}
}