{
  "type": "Feature",
  "properties": {
    "addr:full":"1/ 232 Manns Rd Gosford West NSW 2250",
    "addr:housenumber":"/ 232",
    "addr:postcode":"2250",
    "addr:street":"Manns Rd",
    "iso:country":"AU",
    "sg:address":"1/ 232 Manns Rd",
    "sg:city":"Gosford West",
    "sg:classifiers":[
        {
            "category":"Manufacturing",
            "subcategory":"Retail Goods",
            "type":"Manufacturing & Wholesale Goods"
        }
    ],
    "sg:phone":"+61 2 4323 3999",
    "sg:postcode":"2250",
    "sg:province":"NSW",
    "sg:tags":[
        "merchant",
        "pump",
        "mfrs"
    ],
    "sg:website":"http://www.gosfordirrigation.com.au",
    "wof:name":"Gosford Irrigation & Pumping Supplies",
    "wof:placetype":"venue"
},
  "geometry": {"coordinates":[151.31944274899999,-33.4243583679],"type":"Point"}
}