{
  "type": "Feature",
  "properties": {
    "iso:country":"AU",
    "sg:address":"19 Stanley St",
    "sg:city":"Peakhurst",
    "sg:classifiers":[
        {
            "category":"Wholesale",
            "subcategory":"Auto Parts",
            "type":"Manufacturing & Wholesale Goods"
        }
    ],
    "sg:phone":"+61 2 9533 9122",
    "sg:postcode":"2210",
    "sg:province":"NSW",
    "sg:tags":[
        "wholesaler",
        "mfrs",
        "lacquer"
    ],
    "wof:name":"Becker Acroma Australia/Croma Coatings",
    "wof:placetype":"venue"
},
  "geometry": {"coordinates":[151.064346,-33.962055],"type":"Point"}
}