{
  "type": "Feature",
  "properties": {
    "addr:full":"PO Box 609 B/C Kent Town SA 5071 Kent Town SA 5071",
    "addr:housenumber":"b / c",
    "addr:postcode":"5071;5071",
    "iso:country":"AU",
    "sg:address":"PO Box 609 B/C Kent Town SA 5071",
    "sg:city":"Kent Town",
    "sg:classifiers":[
        {
            "category":"Farming",
            "subcategory":"Farm & Veterinary Services",
            "type":"Manufacturing & Wholesale Goods"
        }
    ],
    "sg:phone":"+61 8 8362 4824",
    "sg:postcode":"5071",
    "sg:province":"SA",
    "sg:tags":[
        "blacksmith",
        "farrier"
    ],
    "wof:name":"Alchemy Art & Iron Works",
    "wof:placetype":"venue"
},
  "geometry": {"coordinates":[138.616363525,-34.9215393066],"type":"Point"}
}