{
  "type": "Feature",
  "properties": {
    "addr:full":"Level 4, 423 Bourke St Melbourne VIC 3000",
    "addr:housenumber":"423",
    "addr:postcode":"3000",
    "addr:street":"Bourke St",
    "iso:country":"AU",
    "sg:address":"Level 4, 423 Bourke St",
    "sg:city":"Melbourne",
    "sg:classifiers":[
        {
            "category":"Banks & Credit Unions",
            "subcategory":"Financial Services",
            "type":"Services"
        }
    ],
    "sg:phone":"+61 3 9670 3434",
    "sg:postcode":"3000",
    "sg:province":"VIC",
    "sg:tags":[
        "planning"
    ],
    "wof:name":"Lifewealth Financial Strategies",
    "wof:placetype":"venue"
},
  "geometry": {"coordinates":[144.961395264,-37.8148880005],"type":"Point"}
}