{
  "type": "Feature",
  "properties": {
    "addr:full":"PO Box 300 Canley Heights NSW 2166",
    "addr:postcode":"2166",
    "iso:country":"AU",
    "sg:address":"PO Box 300",
    "sg:city":"Canley Heights",
    "sg:classifiers":[
        {
            "category":"Building & Trades",
            "subcategory":"Construction",
            "type":"Services"
        }
    ],
    "sg:phone":"+61 415 207 722",
    "sg:postcode":"2166",
    "sg:province":"NSW",
    "sg:tags":[
        "contractor"
    ],
    "wof:name":"AA Renobuild Constructions",
    "wof:placetype":"venue"
},
  "geometry": {"coordinates":[150.92576599099999,-33.8838882446],"type":"Point"}
}