{
  "type": "Feature",
  "properties": {
    "addr:full":"Suite 9/ 1 Gladstone Rd Castle Hill NSW 2154",
    "addr:postcode":"2154",
    "addr:street":"Gladstone Rd",
    "iso:country":"AU",
    "sg:address":"Suite 9/ 1 Gladstone Rd",
    "sg:city":"Castle Hill",
    "sg:classifiers":[
        {
            "category":"Professional",
            "subcategory":"Accounting & Tax Preparation",
            "type":"Services"
        }
    ],
    "sg:phone":"+61 416 056 870",
    "sg:postcode":"2154",
    "sg:province":"NSW",
    "sg:tags":[
        "accountant",
        "auditor"
    ],
    "wof:name":"Keep Track Accounting",
    "wof:placetype":"venue"
},
  "geometry": {"coordinates":[150.979370117,-33.7323722839],"type":"Point"}
}