{
  "type": "Feature",
  "properties": {
    "addr:full":"Landscape Drv Sydenham VIC 3037",
    "addr:postcode":"3037",
    "addr:street":"Landscape Drv",
    "iso:country":"AU",
    "sg:address":"Landscape Drv",
    "sg:city":"Sydenham",
    "sg:classifiers":[
        {
            "category":"Building & Trades",
            "subcategory":"Construction",
            "type":"Services"
        }
    ],
    "sg:phone":"+61 3 9449 2399",
    "sg:postcode":"3037",
    "sg:province":"VIC",
    "sg:tags":[
        "contractor"
    ],
    "wof:name":"P.M.P. Homes Pty Ltd",
    "wof:placetype":"venue"
},
  "geometry": {"coordinates":[144.73980700000001,-37.683952],"type":"Point"}
}