{
  "type": "Feature",
  "properties": {
    "iso:country":"AU",
    "sg:address":"Unit 2/ 32 Crompton Rd",
    "sg:city":"Rockingham",
    "sg:classifiers":[
        {
            "category":"Retail",
            "subcategory":"Auto Repair",
            "type":"Services"
        }
    ],
    "sg:phone":"+61 8 9592 1300",
    "sg:postcode":"6168",
    "sg:province":"WA",
    "sg:tags":[
        "repairer",
        "motor",
        "engineer"
    ],
    "wof:name":"Drivesafe Auto Repairs & Autogas",
    "wof:placetype":"venue"
},
  "geometry": {"coordinates":[115.76683,-32.274837],"type":"Point"}
}