{
  "type": "Feature",
  "properties": {
    "addr:full":"18 Union St Geelong VIC 3220",
    "addr:housenumber":"18",
    "addr:postcode":"3220",
    "addr:street":"Union St",
    "iso:country":"AU",
    "sg:address":"18 Union St",
    "sg:city":"Geelong",
    "sg:classifiers":[
        {
            "category":"Military Area",
            "subcategory":"Air Force Base",
            "type":"Public Place"
        }
    ],
    "sg:phone":"+61 3 5221 8256",
    "sg:postcode":"3220",
    "sg:province":"VIC",
    "sg:tags":[
        "men's",
        "tailor"
    ],
    "wof:name":"Uni Tailoring",
    "wof:placetype":"venue"
},
  "geometry": {"coordinates":[144.36082500000001,-38.149254],"type":"Point"}
}