{
  "type": "Feature",
  "properties": {
    "addr:full":"24 Meadow Rd Devon Meadows VIC 3977",
    "addr:housenumber":"24",
    "addr:postcode":"3977",
    "addr:street":"Meadow Rd",
    "iso:country":"AU",
    "sg:address":"24 Meadow Rd",
    "sg:city":"Devon Meadows",
    "sg:classifiers":[
        {
            "category":"Home & Garden",
            "subcategory":"Carpets & Floor Coverings",
            "type":"Retail Goods"
        }
    ],
    "sg:phone":"+61 3 5998 1012",
    "sg:postcode":"3977",
    "sg:province":"VIC",
    "sg:tags":[
        "tile",
        "wall",
        "layer"
    ],
    "wof:name":"Transcom Developments",
    "wof:placetype":"venue"
},
  "geometry": {"coordinates":[145.297561645,-38.1735572815],"type":"Point"}
}