{
  "type": "Feature",
  "properties": {
    "addr:full":"Shp 3, Nuggett Crossing Shopping Centre Jindabyne NSW 2627",
    "addr:housenumber":"3",
    "addr:postcode":"2627",
    "addr:street":"Nuggett Crossing",
    "iso:country":"AU",
    "sg:address":"Shp 3, Nuggett Crossing Shopping Centre",
    "sg:city":"Jindabyne",
    "sg:classifiers":[
        {
            "category":"Cafe",
            "type":"Food & Drink"
        }
    ],
    "sg:phone":"+61 2 6457 1388",
    "sg:postcode":"2627",
    "sg:province":"NSW",
    "wof:name":"Gloria Jeans Coffees",
    "wof:placetype":"venue"
},
  "geometry": {"coordinates":[148.60859680199999,-36.4327316284],"type":"Point"}
}