{
  "type": "Feature",
  "properties": {
    "iso:country":"AU",
    "sg:address":"36 Quay St",
    "sg:city":"Bundaberg",
    "sg:classifiers":[
        {
            "category":"Health Services",
            "subcategory":"Chiropractor",
            "type":"Services"
        }
    ],
    "sg:phone":"+61 7 4153 1821",
    "sg:postcode":"4670",
    "sg:province":"QLD",
    "wof:name":"Aaron Chiropractic Centre Pty Ltd",
    "wof:placetype":"venue"
},
  "geometry": {"coordinates":[152.34910583499999,-24.8649101257],"type":"Point"}
}