{
  "type": "Feature",
  "properties": {
    "addr:full":"Level 1, 19 Monaro St Queanbeyan NSW 2620",
    "addr:housenumber":"19",
    "addr:postcode":"2620",
    "addr:street":"Monaro St",
    "iso:country":"AU",
    "sg:address":"Level 1, 19 Monaro St",
    "sg:city":"Queanbeyan",
    "sg:classifiers":[
        {
            "category":"Real Estate",
            "subcategory":"Surveying",
            "type":"Services"
        }
    ],
    "sg:phone":"+61 2 6299 1836",
    "sg:postcode":"2620",
    "sg:province":"NSW",
    "sg:tags":[
        "surveyor",
        "land"
    ],
    "wof:name":"Clarke & Di Pauli",
    "wof:placetype":"venue"
},
  "geometry": {"coordinates":[149.232543945,-35.3540077209],"type":"Point"}
}