{
  "type": "Feature",
  "properties": {
    "addr:full":"Calabria Rd Griffith NSW 2680",
    "addr:postcode":"2680",
    "addr:street":"Calabria Rd",
    "iso:country":"AU",
    "sg:address":"Calabria Rd",
    "sg:city":"Griffith",
    "sg:classifiers":[
        {
            "category":"Building & Trades",
            "subcategory":"Construction",
            "type":"Services"
        }
    ],
    "sg:phone":"+61 2 6964 5665",
    "sg:postcode":"2680",
    "sg:province":"NSW",
    "sg:tags":[
        "contractor"
    ],
    "wof:name":"Davis Sanders Homes",
    "wof:placetype":"venue"
},
  "geometry": {"coordinates":[146.07946799999999,-34.263901],"type":"Point"}
}