{
  "type": "Feature",
  "properties": {
    "iso:country":"AU",
    "sg:address":"131 Victoria Ave",
    "sg:city":"Albert Park",
    "sg:classifiers":[
        {
            "category":"Personal",
            "subcategory":"Beauty Salon",
            "type":"Services"
        }
    ],
    "sg:phone":"+61 3 9690 6329",
    "sg:postcode":"3206",
    "sg:province":"VIC",
    "sg:tags":[
        "hairdresser"
    ],
    "wof:name":"Worth Hairdressing & Gifts",
    "wof:placetype":"venue"
},
  "geometry": {"coordinates":[144.95022599999999,-37.845577],"type":"Point"}
}