{
  "type": "Feature",
  "properties": {
    "iso:country":"AU",
    "sg:address":"E J Ward Centre 189 Underwood St",
    "sg:city":"Paddington",
    "sg:classifiers":[
        {
            "category":"Social Services",
            "subcategory":"Child Care",
            "type":"Services"
        }
    ],
    "sg:phone":"+61 2 9391 7000",
    "sg:postcode":"2021",
    "sg:province":"NSW",
    "sg:tags":[
        "palliative"
    ],
    "wof:name":"Home & Community Care Program (HACC)",
    "wof:placetype":"venue"
},
  "geometry": {"coordinates":[151.232955933,-33.887172699],"type":"Point"}
}