{
  "type": "Feature",
  "properties": {
    "addr:full":"63- 65 Boulder Rd Malaga WA 6090",
    "addr:housenumber":"65",
    "addr:postcode":"6090",
    "addr:street":"Boulder Rd",
    "iso:country":"AU",
    "sg:address":"63- 65 Boulder Rd",
    "sg:city":"Malaga",
    "sg:classifiers":[
        {
            "category":"Government",
            "subcategory":"Police Station",
            "type":"Public Place"
        }
    ],
    "sg:phone":"+61 8 9209 4999",
    "sg:postcode":"6090",
    "sg:province":"WA",
    "sg:tags":[
        "curtain",
        "air"
    ],
    "wof:name":"Systemaire Pty Ltd",
    "wof:placetype":"venue"
},
  "geometry": {"coordinates":[115.90699768099999,-31.8646411896],"type":"Point"}
}