{
  "type": "Feature",
  "properties": {
    "addr:full":"12 Fisher St Auburn NSW 2144",
    "addr:housenumber":"12",
    "addr:postcode":"2144",
    "addr:street":"Fisher St",
    "iso:country":"AU",
    "sg:address":"12 Fisher St",
    "sg:city":"Auburn",
    "sg:classifiers":[
        {
            "category":"Professional",
            "subcategory":"Printing & Photocopies",
            "type":"Services"
        }
    ],
    "sg:phone":"+61 2 9748 6588",
    "sg:postcode":"2144",
    "sg:province":"NSW",
    "sg:tags":[
        "screen",
        "printer"
    ],
    "wof:name":"Screen Prince Co",
    "wof:placetype":"venue"
},
  "geometry": {"coordinates":[151.03854370100001,-33.8348731995],"type":"Point"}
}