{
  "type": "Feature",
  "properties": {
    "addr:full":"63 Main St Greensborough VIC 3088",
    "addr:housenumber":"63",
    "addr:postcode":"3088",
    "addr:street":"Main St",
    "iso:country":"AU",
    "sg:address":"63 Main St",
    "sg:city":"Greensborough",
    "sg:classifiers":[
        {
            "category":"Shopping",
            "subcategory":"Shoes",
            "type":"Retail Goods"
        }
    ],
    "sg:phone":"+61 3 9432 6344",
    "sg:postcode":"3088",
    "sg:province":"VIC",
    "sg:tags":[
        "footwear"
    ],
    "wof:name":"Comfort & Fit",
    "wof:placetype":"venue"
},
  "geometry": {"coordinates":[145.10446167000001,-37.7031135559],"type":"Point"}
}