{
  "type": "Feature",
  "properties": {
    "iso:country":"AU",
    "sg:address":"Emmersons Rd",
    "sg:city":"Woolsthorpe",
    "sg:classifiers":[
        {
            "category":"Home & Garden",
            "subcategory":"Garden Supply",
            "type":"Retail Goods"
        }
    ],
    "sg:phone":"+61 3 5569 1556",
    "sg:postcode":"3276",
    "sg:province":"VIC",
    "sg:tags":[
        "fertilizer"
    ],
    "wof:name":"Rural Liquid Fertilisers",
    "wof:placetype":"venue"
},
  "geometry": {"coordinates":[142.52861023,-38.078830719],"type":"Point"}
}