{
  "type": "Feature",
  "properties": {
    "iso:country":"AU",
    "sg:address":"85 - 89 Asquith St",
    "sg:city":"Silverwater",
    "sg:classifiers":[
        {
            "category":"Home & Garden",
            "subcategory":"Carpets & Floor Coverings",
            "type":"Retail Goods"
        }
    ],
    "sg:phone":"+61 2 9748 8968",
    "sg:postcode":"2128",
    "sg:province":"NSW",
    "sg:tags":[
        "tile",
        "wall"
    ],
    "sg:website":"http://www.artofstoneandtiles.com.au",
    "wof:name":"Art Of Stone & Tiles",
    "wof:placetype":"venue"
},
  "geometry": {"coordinates":[151.03660583499999,-33.83618927],"type":"Point"}
}