{
  "type": "Feature",
  "properties": {
    "iso:country":"AU",
    "sg:address":"566 St Kilda Rd",
    "sg:city":"Melbourne",
    "sg:classifiers":[
        {
            "category":"Banks & Credit Unions",
            "subcategory":"Financial Services",
            "type":"Services"
        }
    ],
    "sg:phone":"+61 1800 801 999",
    "sg:postcode":"3004",
    "sg:province":"VIC",
    "sg:tags":[
        "loan",
        "finance",
        "mortgage"
    ],
    "wof:name":"Morgan Brooks Direct",
    "wof:placetype":"venue"
},
  "geometry": {"coordinates":[144.97903442399999,-37.8467979431],"type":"Point"}
}