{
  "type": "Feature",
  "properties": {
    "iso:country":"AU",
    "sg:address":"Factory 9/ 9 Brooklyn Ave",
    "sg:city":"Dandenong",
    "sg:classifiers":[
        {
            "category":"Retail",
            "subcategory":"Auto Repair",
            "type":"Services"
        }
    ],
    "sg:phone":"+61 412 505 499",
    "sg:postcode":"3175",
    "sg:province":"VIC",
    "sg:tags":[
        "electrical"
    ],
    "wof:name":"Pulse Auto Electrics Pty Ltd",
    "wof:placetype":"venue"
},
  "geometry": {"coordinates":[145.19760131800001,-37.993637085],"type":"Point"}
}