{
  "type": "Feature",
  "properties": {
    "iso:country":"AU",
    "sg:address":"25 Pennant Hills Rd",
    "sg:city":"North Parramatta",
    "sg:classifiers":[
        {
            "category":"Professional",
            "subcategory":"Secretarial Services",
            "type":"Services"
        }
    ],
    "sg:phone":"+61 2 9630 0694",
    "sg:postcode":"2151",
    "sg:province":"NSW",
    "sg:tags":[
        "typing"
    ],
    "wof:name":"ABFAB Resumes",
    "wof:placetype":"venue"
},
  "geometry": {"coordinates":[151.01077270499999,-33.7977523804],"type":"Point"}
}