{
  "type": "Feature",
  "properties": {
    "iso:country":"AU",
    "sg:address":"PO Box 1612",
    "sg:city":"Thuringowa Central BC",
    "sg:classifiers":[
        {
            "category":"Building & Trades",
            "subcategory":"Construction",
            "type":"Services"
        }
    ],
    "sg:phone":"+61 400 966 653",
    "sg:postcode":"4817",
    "sg:province":"QLD",
    "sg:tags":[
        "window",
        "tinting"
    ],
    "wof:name":"Extreme Glass Tinting Townsville",
    "wof:placetype":"venue"
},
  "geometry": {"coordinates":[146.72848500000001,-19.317053],"type":"Point"}
}