{
  "type": "Feature",
  "properties": {
    "iso:country":"AU",
    "sg:address":"38 Lyly Rd",
    "sg:city":"Allambie Heights",
    "sg:classifiers":[
        {
            "category":"Travel",
            "subcategory":"Hostel",
            "type":"Entertainment"
        }
    ],
    "sg:phone":"+61 2 9905 2200",
    "sg:postcode":"2100",
    "sg:province":"NSW",
    "sg:tags":[
        "home"
    ],
    "wof:name":"Aboriginal Hostels Ltd",
    "wof:placetype":"venue"
},
  "geometry": {"coordinates":[151.26091003400001,-33.7700920105],"type":"Point"}
}