{
  "type": "Feature",
  "properties": {
    "addr:full":"133 Ham Rd Mansfield QLD 4122",
    "addr:housenumber":"133",
    "addr:postcode":"4122",
    "addr:street":"Ham Rd",
    "iso:country":"AU",
    "sg:address":"133 Ham Rd",
    "sg:city":"Mansfield",
    "sg:classifiers":[
        {
            "category":"Manufacturing",
            "subcategory":"Tools & Machinery",
            "type":"Manufacturing & Wholesale Goods"
        }
    ],
    "sg:phone":"+61 7 3349 4753",
    "sg:postcode":"4122",
    "sg:province":"QLD",
    "sg:tags":[
        "earth",
        "excavating",
        "moving",
        "equipment"
    ],
    "wof:name":"Williamson J M",
    "wof:placetype":"venue"
},
  "geometry": {"coordinates":[153.105194092,-27.5417289734],"type":"Point"}
}