{
  "type": "Feature",
  "properties": {
    "addr:full":"5/ 51 - 53 Fitzpatrick St Revesby NSW 2212",
    "addr:housenumber":"/;53",
    "addr:postcode":"2212",
    "addr:street":"51;Fitzpatrick St",
    "iso:country":"AU",
    "sg:address":"5/ 51 - 53 Fitzpatrick St",
    "sg:city":"Revesby",
    "sg:classifiers":[
        {
            "category":"Building & Trades",
            "subcategory":"Construction",
            "type":"Services"
        }
    ],
    "sg:phone":"+61 2 9792 4383",
    "sg:postcode":"2212",
    "sg:province":"NSW",
    "sg:tags":[
        "joinery"
    ],
    "wof:name":"L & A Joinery",
    "wof:placetype":"venue"
},
  "geometry": {"coordinates":[151.00271599999999,-33.938942],"type":"Point"}
}