{
  "type": "Feature",
  "properties": {
    "addr:full":"4 Turner Crt Wodonga VIC 3690",
    "addr:housenumber":"4",
    "addr:postcode":"3690",
    "addr:street":"Turner Crt",
    "iso:country":"AU",
    "sg:address":"4 Turner Crt",
    "sg:city":"Wodonga",
    "sg:classifiers":[
        {
            "category":"Professional",
            "subcategory":"Detective & Security Services",
            "type":"Services"
        }
    ],
    "sg:phone":"+61 2 6024 2144",
    "sg:postcode":"3690",
    "sg:province":"VIC",
    "sg:tags":[
        "consultant",
        "laser"
    ],
    "wof:name":"Bertazzo Engineered",
    "wof:placetype":"venue"
},
  "geometry": {"coordinates":[146.87022399899999,-36.1027908325],"type":"Point"}
}