{
  "type": "Feature",
  "properties": {
    "addr:full":"Suite 8/ 116 Queen St Campbelltown NSW 2560",
    "addr:housenumber":"/ 116",
    "addr:postcode":"2560",
    "addr:street":"Queen St",
    "iso:country":"AU",
    "sg:address":"Suite 8/ 116 Queen St",
    "sg:city":"Campbelltown",
    "sg:classifiers":[
        {
            "category":"Real Estate",
            "subcategory":"Real Estate Agent",
            "type":"Services"
        }
    ],
    "sg:phone":"+61 1300 134 442",
    "sg:postcode":"2560",
    "sg:province":"NSW",
    "wof:name":"Property Online Pty Ltd",
    "wof:placetype":"venue"
},
  "geometry": {"coordinates":[150.81640625,-34.0645370483],"type":"Point"}
}