{
  "type": "Feature",
  "properties": {
    "iso:country":"AU",
    "sg:address":"18 Aldgate St",
    "sg:city":"Sutherland",
    "sg:classifiers":[
        {
            "category":"Utilities",
            "subcategory":"Electric",
            "type":"Services"
        }
    ],
    "sg:phone":"+61 2 9542 6896",
    "sg:postcode":"2232",
    "sg:province":"NSW",
    "sg:tags":[
        "electrical",
        "contractor"
    ],
    "wof:name":"Kevin Robinson Electrical",
    "wof:placetype":"venue"
},
  "geometry": {"coordinates":[151.06361389200001,-34.036693573],"type":"Point"}
}