{
  "type": "Feature",
  "properties": {
    "addr:full":"105 Barker St Casino NSW 2470",
    "addr:housenumber":"105",
    "addr:postcode":"2470",
    "addr:street":"Barker St",
    "iso:country":"AU",
    "sg:address":"105 Barker St",
    "sg:city":"Casino",
    "sg:classifiers":[
        {
            "category":"Shopping",
            "subcategory":"Stationery & Office Supplies",
            "type":"Retail Goods"
        }
    ],
    "sg:phone":"+61 2 6662 2215",
    "sg:postcode":"2470",
    "sg:province":"NSW",
    "sg:tags":[
        "equipment",
        "facsimile"
    ],
    "wof:name":"Star Office Choice",
    "wof:placetype":"venue"
},
  "geometry": {"coordinates":[153.047241211,-28.864938736],"type":"Point"}
}