{
  "type": "Feature",
  "properties": {
    "iso:country":"AU",
    "sg:address":"Shop 3 Kalbarri Arc",
    "sg:city":"Kalbarri",
    "sg:classifiers":[
        {
            "category":"Recreation",
            "subcategory":"Fishing",
            "type":"Entertainment"
        }
    ],
    "sg:phone":"+61 8 9937 1126",
    "sg:postcode":"6536",
    "sg:province":"WA",
    "sg:tags":[
        "tackle"
    ],
    "wof:name":"Kalbarri Sports & Dive",
    "wof:placetype":"venue"
},
  "geometry": {"coordinates":[114.16448211700001,-27.7109146118],"type":"Point"}
}