{
  "type": "Feature",
  "properties": {
    "addr:full":"5 Pendlebury Rd Cardiff NSW 2285",
    "addr:housenumber":"5",
    "addr:postcode":"2285",
    "addr:street":"Pendlebury Rd",
    "iso:country":"AU",
    "sg:address":"5 Pendlebury Rd",
    "sg:city":"Cardiff",
    "sg:classifiers":[
        {
            "category":"Professional",
            "subcategory":"Computer Services",
            "type":"Services"
        }
    ],
    "sg:phone":"+61 2 4956 7070",
    "sg:postcode":"2285",
    "sg:province":"NSW",
    "sg:tags":[
        "repairs",
        "upgrade",
        "equipment"
    ],
    "wof:name":"Premier Copier Service",
    "wof:placetype":"venue"
},
  "geometry": {"coordinates":[151.655960083,-32.9494361877],"type":"Point"}
}