{
  "type": "Feature",
  "properties": {
    "addr:full":"1730 Hume Hwy Campbellfield VIC 3061",
    "addr:housenumber":"1730",
    "addr:postcode":"3061",
    "addr:street":"Hume Hwy",
    "iso:country":"AU",
    "sg:address":"1730 Hume Hwy",
    "sg:city":"Campbellfield",
    "sg:classifiers":[
        {
            "category":"Transit Center",
            "subcategory":"Passenger",
            "type":"Transportation"
        }
    ],
    "sg:phone":"+61 1800 620 895",
    "sg:postcode":"3061",
    "sg:province":"VIC",
    "sg:tags":[
        "packing",
        "gasket"
    ],
    "sg:website":"http://www.aagaskets.com.au",
    "wof:name":"AA Gaskets Pty Ltd",
    "wof:placetype":"venue"
},
  "geometry": {"coordinates":[144.95596313499999,-37.6723709106],"type":"Point"}
}