{
  "type": "Feature",
  "properties": {
    "iso:country":"AU",
    "sg:address":"3 Birchwood Ave",
    "sg:city":"Templestowe Lower",
    "sg:classifiers":[
        {
            "category":"Education",
            "subcategory":"Kindergarten",
            "type":"Public Place"
        }
    ],
    "sg:phone":"+61 3 9850 8424",
    "sg:postcode":"3107",
    "sg:province":"VIC",
    "sg:tags":[
        "pre-schools"
    ],
    "wof:name":"Templestowe Valley Pre-School Association",
    "wof:placetype":"venue"
},
  "geometry": {"coordinates":[145.10856628400001,-37.7605438232],"type":"Point"}
}