{
  "type": "Feature",
  "properties": {
    "iso:country":"AU",
    "sg:address":"Unit 3/ 12 Ramly Drv",
    "sg:city":"Burleigh Heads",
    "sg:classifiers":[
        {
            "category":"Retail",
            "subcategory":"Auto Repair",
            "type":"Services"
        }
    ],
    "sg:phone":"+61 7 5576 5288",
    "sg:postcode":"4220",
    "sg:province":"QLD",
    "sg:tags":[
        "beater",
        "painter",
        "panel"
    ],
    "wof:name":"Gold Coast Auto Restorations",
    "wof:placetype":"venue"
},
  "geometry": {"coordinates":[153.434127808,-28.1036987305],"type":"Point"}
}