{
  "type": "Feature",
  "properties": {
    "addr:full":"2 Wentworth Crt Thomastown VIC 3074",
    "addr:housenumber":"2",
    "addr:postcode":"3074",
    "addr:street":"Wentworth Crt",
    "iso:country":"AU",
    "sg:address":"2 Wentworth Crt",
    "sg:city":"Thomastown",
    "sg:classifiers":[
        {
            "category":"Food & Beverages",
            "subcategory":"Groceries & Convenience Stores",
            "type":"Retail Goods"
        }
    ],
    "sg:phone":"+61 3 9460 7844",
    "sg:postcode":"3074",
    "sg:province":"VIC",
    "sg:tags":[
        "merchant",
        "egg"
    ],
    "wof:name":"Lago Game & Gourmet Pty Ltd",
    "wof:placetype":"venue"
},
  "geometry": {"coordinates":[144.990509033,-37.6903686523],"type":"Point"}
}