{
  "type": "Feature",
  "properties": {
    "iso:country":"AU",
    "sg:address":"728 Main St",
    "sg:city":"Kangaroo Point",
    "sg:classifiers":[
        {
            "category":"Autos & Motor Vehicles",
            "subcategory":"Automobile Sales",
            "type":"Retail Goods"
        }
    ],
    "sg:phone":"+61 7 3391 1114",
    "sg:postcode":"4169",
    "sg:province":"QLD",
    "sg:tags":[
        "car",
        "used"
    ],
    "wof:name":"AJM Motorsport",
    "wof:placetype":"venue"
},
  "geometry": {"coordinates":[153.03596496599999,-27.4817886353],"type":"Point"}
}