{
  "type": "Feature",
  "properties": {
    "addr:full":"10a Louisa La Gympie QLD 4570",
    "addr:housenumber":"10a",
    "addr:postcode":"4570",
    "addr:street":"Louisa La",
    "iso:country":"AU",
    "sg:address":"10a Louisa La",
    "sg:city":"Gympie",
    "sg:classifiers":[
        {
            "category":"Real Estate",
            "subcategory":"Real Estate Operator",
            "type":"Services"
        }
    ],
    "sg:phone":"+61 7 5483 9954",
    "sg:postcode":"4570",
    "sg:province":"QLD",
    "sg:tags":[
        "building",
        "consultant",
        "management"
    ],
    "wof:name":"A-Zone Carpentry & Construction",
    "wof:placetype":"venue"
},
  "geometry": {"coordinates":[152.66476440400001,-26.1824951172],"type":"Point"}
}