{
  "type": "Feature",
  "properties": {
    "iso:country":"AU",
    "sg:address":"355 Inkerman St",
    "sg:city":"Balaclava",
    "sg:classifiers":[
        {
            "category":"Real Estate",
            "subcategory":"Surveying",
            "type":"Services"
        }
    ],
    "sg:phone":"+61 3 9527 7800",
    "sg:postcode":"3183",
    "sg:province":"VIC",
    "sg:tags":[
        "surveyor",
        "land"
    ],
    "wof:name":"Southern Surveys Pty Ltd",
    "wof:placetype":"venue"
},
  "geometry": {"coordinates":[144.996017456,-37.8690795898],"type":"Point"}
}