{
  "type": "Feature",
  "properties": {
    "iso:country":"AU",
    "sg:address":"118a Avalon Pde",
    "sg:city":"Avalon",
    "sg:classifiers":[
        {
            "category":"Education",
            "subcategory":"Kindergarten",
            "type":"Public Place"
        }
    ],
    "sg:phone":"+61 2 9918 6583",
    "sg:postcode":"2107",
    "sg:province":"NSW",
    "sg:tags":[
        "pre-schools"
    ],
    "wof:name":"Avalon Playtime Kindergarten",
    "wof:placetype":"venue"
},
  "geometry": {"coordinates":[151.32139587399999,-33.633140564],"type":"Point"}
}