{
  "type": "Feature",
  "properties": {
    "addr:full":"14 Robert St Somerville VIC 3912",
    "addr:housenumber":"14",
    "addr:postcode":"3912",
    "addr:street":"Robert St",
    "iso:country":"AU",
    "sg:address":"14 Robert St",
    "sg:city":"Somerville",
    "sg:classifiers":[
        {
            "category":"Building & Trades",
            "subcategory":"Construction",
            "type":"Services"
        }
    ],
    "sg:phone":"+61 411 596 479",
    "sg:postcode":"3912",
    "sg:province":"VIC",
    "sg:tags":[
        "joiner",
        "carpenter"
    ],
    "wof:name":"KE & CA Howe",
    "wof:placetype":"venue"
},
  "geometry": {"coordinates":[145.17503356899999,-38.233745575],"type":"Point"}
}