{
  "type": "Feature",
  "properties": {
    "addr:full":"4 Sherstons Rd Spreyton TAS 7310",
    "addr:housenumber":"4",
    "addr:postcode":"7310",
    "addr:street":"Sherstons Rd",
    "iso:country":"AU",
    "sg:address":"4 Sherstons Rd",
    "sg:city":"Spreyton",
    "sg:classifiers":[
        {
            "category":"Home & Garden",
            "subcategory":"Carpets & Floor Coverings",
            "type":"Retail Goods"
        }
    ],
    "sg:phone":"+61 3 6427 3566",
    "sg:postcode":"7310",
    "sg:province":"TAS",
    "sg:tags":[
        "layer"
    ],
    "wof:name":"Rowlands J Floor Covering Contractor",
    "wof:placetype":"venue"
},
  "geometry": {"coordinates":[146.32273864699999,-41.2297096252],"type":"Point"}
}