{
  "type": "Feature",
  "properties": {
    "addr:full":"14 Memorial Drv Wodonga VIC 3690",
    "addr:housenumber":"14",
    "addr:postcode":"3690",
    "addr:street":"Memorial Drv",
    "iso:country":"AU",
    "sg:address":"14 Memorial Drv",
    "sg:city":"Wodonga",
    "sg:classifiers":[
        {
            "category":"Building & Trades",
            "subcategory":"Construction",
            "type":"Services"
        }
    ],
    "sg:phone":"+61 2 6024 2637",
    "sg:postcode":"3690",
    "sg:province":"VIC",
    "sg:tags":[
        "brick",
        "paving"
    ],
    "wof:name":"Hans & Steve Van Aken",
    "wof:placetype":"venue"
},
  "geometry": {"coordinates":[146.87577819800001,-36.1545982361],"type":"Point"}
}