{
  "type": "Feature",
  "properties": {
    "iso:country":"AU",
    "sg:address":"854 Hunter St",
    "sg:city":"Newcastle",
    "sg:classifiers":[
        {
            "category":"Shopping",
            "subcategory":"Pawn Shop",
            "type":"Retail Goods"
        }
    ],
    "sg:phone":"+61 2 4961 4622",
    "sg:postcode":"2300",
    "sg:province":"NSW",
    "sg:tags":[
        "pawnbroker"
    ],
    "wof:name":"Liquidation Sale",
    "wof:placetype":"venue"
},
  "geometry": {"coordinates":[151.757965,-32.924557],"type":"Point"}
}