{
  "type": "Feature",
  "properties": {
    "iso:country":"AU",
    "sg:address":"Werin St",
    "sg:city":"Tewantin",
    "sg:classifiers":[
        {
            "category":"Education",
            "subcategory":"School",
            "type":"Public Place"
        }
    ],
    "sg:phone":"+61 7 5447 1095",
    "sg:postcode":"4565",
    "sg:province":"QLD",
    "sg:tags":[
        "state",
        "except",
        "nsw"
    ],
    "wof:name":"Tewantin Preschool",
    "wof:placetype":"venue"
},
  "geometry": {"coordinates":[153.03251648,-26.3913402557],"type":"Point"}
}