{
  "type": "Feature",
  "properties": {
    "addr:full":"13 Stacey Crt Victoria Point QLD 4165",
    "addr:housenumber":"13",
    "addr:postcode":"4165",
    "addr:street":"Stacey Crt",
    "iso:country":"AU",
    "sg:address":"13 Stacey Crt",
    "sg:city":"Victoria Point",
    "sg:classifiers":[
        {
            "category":"Banks & Credit Unions",
            "subcategory":"Investment Brokerage",
            "type":"Services"
        }
    ],
    "sg:phone":"+61 7 3393 4444",
    "sg:postcode":"4165",
    "sg:province":"QLD",
    "sg:tags":[
        "care",
        "day",
        "family",
        "child"
    ],
    "wof:name":"Bayside Family Day Care",
    "wof:placetype":"venue"
},
  "geometry": {"coordinates":[153.29852294899999,-27.5817050934],"type":"Point"}
}