{
  "type": "Feature",
  "properties": {
    "iso:country":"AU",
    "sg:address":"Lot 34 Keliher Rd",
    "sg:city":"Delaneys Creek",
    "sg:classifiers":[
        {
            "category":"Shopping",
            "subcategory":"Antiques",
            "type":"Retail Goods"
        }
    ],
    "sg:phone":"+61 7 5496 4757",
    "sg:postcode":"4514",
    "sg:province":"QLD",
    "sg:tags":[
        "restoration",
        "reproduction"
    ],
    "wof:name":"Jones Stephen - French Polisher",
    "wof:placetype":"venue"
},
  "geometry": {"coordinates":[152.800507,-27.001541],"type":"Point"}
}