{
  "type": "Feature",
  "properties": {
    "addr:full":"10 Bow St Corowa NSW 2646",
    "addr:housenumber":"10",
    "addr:postcode":"2646",
    "addr:street":"Bow St",
    "iso:country":"AU",
    "sg:address":"10 Bow St",
    "sg:city":"Corowa",
    "sg:classifiers":[
        {
            "category":"Utilities",
            "type":"Services"
        }
    ],
    "sg:phone":"+61 2 6033 0642",
    "sg:postcode":"2646",
    "sg:province":"NSW",
    "sg:tags":[
        "refrigeration",
        "industrial",
        "commercial",
        "retail"
    ],
    "wof:name":"Corowa Refrigeration & Air Conditioning",
    "wof:placetype":"venue"
},
  "geometry": {"coordinates":[146.39031982399999,-35.9939079285],"type":"Point"}
}