{
  "type": "Feature",
  "properties": {
    "iso:country":"AU",
    "sg:address":"PO Box 32",
    "sg:city":"Glen Osmond",
    "sg:classifiers":[
        {
            "category":"Real Estate",
            "subcategory":"Real Estate Services",
            "type":"Services"
        }
    ],
    "sg:phone":"+61 8 8379 1111",
    "sg:postcode":"5064",
    "sg:province":"SA",
    "sg:tags":[
        "valuer"
    ],
    "wof:name":"ABA Property Group Valuation Services",
    "wof:placetype":"venue"
},
  "geometry": {"coordinates":[138.63575744600001,-34.9533500671],"type":"Point"}
}