{
  "type": "Feature",
  "properties": {
    "addr:full":"25A Ari Drv Campbellfield VIC 3061",
    "addr:housenumber":"25a",
    "addr:postcode":"3061",
    "addr:street":"Ari Drv",
    "iso:country":"AU",
    "sg:address":"25A Ari Drv",
    "sg:city":"Campbellfield",
    "sg:classifiers":[
        {
            "category":"Manufacturing",
            "subcategory":"Metals",
            "type":"Manufacturing & Wholesale Goods"
        }
    ],
    "sg:phone":"+61 3 9357 8249",
    "sg:postcode":"3061",
    "sg:province":"VIC",
    "sg:tags":[
        "steel",
        "fabricator",
        "mfrs"
    ],
    "wof:name":"Victorian Steel",
    "wof:placetype":"venue"
},
  "geometry": {"coordinates":[144.968475342,-37.6696815491],"type":"Point"}
}