{
  "type": "Feature",
  "properties": {
    "addr:full":"Unit 2/ 8 Bringelly Rd Kingswood NSW 2747",
    "addr:housenumber":"8",
    "addr:postcode":"2747",
    "addr:street":"Bringelly Rd",
    "iso:country":"AU",
    "sg:address":"Unit 2/ 8 Bringelly Rd",
    "sg:city":"Kingswood",
    "sg:classifiers":[
        {
            "category":"Shopping",
            "subcategory":"Computers & Home Electronics",
            "type":"Retail Goods"
        }
    ],
    "sg:phone":"+61 416 942 747",
    "sg:postcode":"2747",
    "sg:province":"NSW",
    "sg:tags":[
        "small",
        "equipment",
        "business"
    ],
    "wof:name":"Amazeu Computer Services",
    "wof:placetype":"venue"
},
  "geometry": {"coordinates":[150.720458984,-33.7607765198],"type":"Point"}
}