{
  "type": "Feature",
  "properties": {
    "iso:country":"AU",
    "sg:address":"22 Emperor Pl",
    "sg:city":"Kenthurst",
    "sg:classifiers":[
        {
            "category":"Professional",
            "subcategory":"Business Services",
            "type":"Services"
        }
    ],
    "sg:phone":"+61 2 9654 1481",
    "sg:postcode":"2156",
    "sg:province":"NSW",
    "sg:tags":[
        "drafting"
    ],
    "wof:name":"Good Design Pty Ltd",
    "wof:placetype":"venue"
},
  "geometry": {"coordinates":[150.984542847,-33.659412384],"type":"Point"}
}