{
  "type": "Feature",
  "properties": {
    "addr:full":"69 Avoca Drv Avoca Beach NSW 2251",
    "addr:housenumber":"69",
    "addr:postcode":"2251",
    "addr:street":"Avoca Drv",
    "iso:country":"AU",
    "sg:address":"69 Avoca Drv",
    "sg:city":"Avoca Beach",
    "sg:classifiers":[
        {
            "category":"Cinema",
            "subcategory":"Movie Theater",
            "type":"Entertainment"
        }
    ],
    "sg:phone":"+61 2 4382 1777",
    "sg:postcode":"2251",
    "sg:province":"NSW",
    "wof:name":"Avoca Beach Picture Theatre",
    "wof:placetype":"venue"
},
  "geometry": {"coordinates":[151.436309814,-33.4714813232],"type":"Point"}
}