{
  "type": "Feature",
  "properties": {
    "addr:full":"Unit 3/ 87 Herston Rd Kelvin Grove QLD 4059",
    "addr:housenumber":"87",
    "addr:postcode":"4059",
    "addr:street":"Herston Rd",
    "iso:country":"AU",
    "sg:address":"Unit 3/ 87 Herston Rd",
    "sg:city":"Kelvin Grove",
    "sg:classifiers":[
        {
            "category":"Manufacturing",
            "subcategory":"Tools & Machinery",
            "type":"Manufacturing & Wholesale Goods"
        }
    ],
    "sg:phone":"+61 418 785 583",
    "sg:postcode":"4059",
    "sg:province":"QLD",
    "sg:tags":[
        "machine",
        "industrial",
        "sewing"
    ],
    "wof:name":"Sewmac Services",
    "wof:placetype":"venue"
},
  "geometry": {"coordinates":[153.01445007300001,-27.4595909119],"type":"Point"}
}