{
  "type": "Feature",
  "properties": {
    "addr:full":"8 McGuilvray Pl Rouse Hill NSW 2155",
    "addr:housenumber":"8",
    "addr:postcode":"2155",
    "addr:street":"Mcguilvray Pl",
    "iso:country":"AU",
    "sg:address":"8 McGuilvray Pl",
    "sg:city":"Rouse Hill",
    "sg:classifiers":[
        {
            "category":"Home & Garden",
            "subcategory":"Carpets & Floor Coverings",
            "type":"Retail Goods"
        }
    ],
    "sg:phone":"+61 418 438 968",
    "sg:postcode":"2155",
    "sg:province":"NSW",
    "sg:tags":[
        "tile",
        "wall"
    ],
    "wof:name":"Rizzo Tiling",
    "wof:placetype":"venue"
},
  "geometry": {"coordinates":[150.91798400900001,-33.6762886047],"type":"Point"}
}