{
  "type": "Feature",
  "properties": {
    "iso:country":"AU",
    "sg:address":"261 Crown St",
    "sg:city":"Wollongong",
    "sg:classifiers":[
        {
            "category":"Professional",
            "subcategory":"Business Services",
            "type":"Services"
        }
    ],
    "sg:phone":"+61 2 4228 0633",
    "sg:postcode":"2500",
    "sg:province":"NSW",
    "sg:tags":[
        "broker"
    ],
    "wof:name":"Lewton Pennimpede Real Estate & Business Brokers",
    "wof:placetype":"venue"
},
  "geometry": {"coordinates":[150.89155600000001,-34.425365],"type":"Point"}
}