{
  "type": "Feature",
  "properties": {
    "iso:country":"AU",
    "sg:address":"4 Opportunity Crt",
    "sg:city":"Clifton",
    "sg:classifiers":[
        {
            "category":"Home & Garden",
            "subcategory":"Mobile Homes",
            "type":"Retail Goods"
        }
    ],
    "sg:phone":"+61 7 4612 3775",
    "sg:postcode":"4361",
    "sg:province":"QLD",
    "sg:tags":[
        "motor",
        "campervans"
    ],
    "wof:name":"Cruise RV's",
    "wof:placetype":"venue"
},
  "geometry": {"coordinates":[151.90321350100001,-27.9423980713],"type":"Point"}
}