{
  "type": "Feature",
  "properties": {
    "iso:country":"AU",
    "sg:address":"13c Sutton Square Shopping Cen Sutton St",
    "sg:city":"Mandurah",
    "sg:classifiers":[
        {
            "category":"Banks & Credit Unions",
            "subcategory":"Bank",
            "type":"Services"
        }
    ],
    "sg:phone":"+61 8 9531 6161",
    "sg:postcode":"6210",
    "sg:province":"WA",
    "sg:tags":[
        "society"
    ],
    "wof:name":"AWA Credit Union",
    "wof:placetype":"venue"
},
  "geometry": {"coordinates":[115.724083,-32.527809],"type":"Point"}
}