{
  "type": "Feature",
  "properties": {
    "iso:country":"AU",
    "sg:address":"336 Bridge Rd",
    "sg:city":"Richmond",
    "sg:classifiers":[
        {
            "category":"Health Services",
            "subcategory":"Health Practitioner",
            "type":"Services"
        }
    ],
    "sg:phone":"+61 3 9429 4922",
    "sg:postcode":"3121",
    "sg:province":"VIC",
    "sg:tags":[
        "acupuncture"
    ],
    "wof:name":"Vounoridis Adam",
    "wof:placetype":"venue"
},
  "geometry": {"coordinates":[145.00242614699999,-37.8190116882],"type":"Point"}
}