{
  "type": "Feature",
  "properties": {
    "addr:full":"'Bethesda Hospital 25 Queenslea Drv' Claremont WA 6010",
    "addr:housenumber":"25",
    "addr:postcode":"6010",
    "addr:street":"Queenslea Drv '",
    "iso:country":"AU",
    "sg:address":"'Bethesda Hospital 25 Queenslea Drv'",
    "sg:city":"Claremont",
    "sg:classifiers":[
        {
            "category":"Health Services",
            "subcategory":"Dentist",
            "type":"Services"
        }
    ],
    "sg:phone":"+61 8 9371 8585",
    "sg:postcode":"6010",
    "sg:province":"WA",
    "wof:name":"Greenberg HC Dr Oral Surgeon",
    "wof:placetype":"venue"
},
  "geometry": {"coordinates":[115.779632568,-31.9875202179],"type":"Point"}
}