{
  "type": "Feature",
  "properties": {
    "iso:country":"AU",
    "sg:address":"34 Gap Rd",
    "sg:city":"Sunbury",
    "sg:classifiers":[
        {
            "category":"Professional",
            "subcategory":"Employment Agencies",
            "type":"Services"
        }
    ],
    "sg:phone":"+61 3 9740 3011",
    "sg:postcode":"3429",
    "sg:province":"VIC",
    "wof:name":"Job Futures",
    "wof:placetype":"venue"
},
  "geometry": {"coordinates":[144.72418212900001,-37.5802383423],"type":"Point"}
}