{
  "type": "Feature",
  "properties": {
    "addr:full":"Box 6281, 600 St Kilda Rd Melbourne VIC 3004",
    "addr:housenumber":"600",
    "addr:postcode":"3004",
    "addr:street":"St Kilda Rd",
    "iso:country":"AU",
    "sg:address":"Box 6281, 600 St Kilda Rd",
    "sg:city":"Melbourne",
    "sg:classifiers":[
        {
            "category":"Professional",
            "subcategory":"Employment Agencies",
            "type":"Services"
        }
    ],
    "sg:phone":"+61 3 9525 9992",
    "sg:postcode":"3004",
    "sg:province":"VIC",
    "wof:name":"Crest Recruitment Group",
    "wof:placetype":"venue"
},
  "geometry": {"coordinates":[144.98034668,-37.8504943848],"type":"Point"}
}