{
  "type": "Feature",
  "properties": {
    "iso:country":"AU",
    "sg:address":"Cnr Grant & Warner Sts",
    "sg:city":"Port Douglas",
    "sg:classifiers":[
        {
            "category":"Arts & Performance",
            "subcategory":"Art Gallery",
            "type":"Entertainment"
        }
    ],
    "sg:phone":"+61 7 4099 4494",
    "sg:postcode":"4877",
    "sg:province":"QLD",
    "wof:name":"Australian & Oceanic Art Gallery",
    "wof:placetype":"venue"
},
  "geometry": {"coordinates":[145.4634552,-16.5268993378],"type":"Point"}
}