{
  "type": "Feature",
  "properties": {
    "addr:full":"PO Box 7061 East Brisbane QLD 4169",
    "addr:postcode":"4169",
    "iso:country":"AU",
    "sg:address":"PO Box 7061",
    "sg:city":"East Brisbane",
    "sg:classifiers":[
        {
            "category":"Personal",
            "subcategory":"Beauty Salon",
            "type":"Services"
        }
    ],
    "sg:phone":"+61 414 807 549",
    "sg:postcode":"4169",
    "sg:province":"QLD",
    "sg:tags":[
        "supply",
        "artist",
        "make-up"
    ],
    "wof:name":"Chintamani",
    "wof:placetype":"venue"
},
  "geometry": {"coordinates":[153.04368591299999,-27.483499527],"type":"Point"}
}