{
  "type": "Feature",
  "properties": {
    "addr:full":"70 Memorial Ave Woy Woy NSW 2256",
    "addr:housenumber":"70",
    "addr:postcode":"2256",
    "addr:street":"Memorial Ave",
    "iso:country":"AU",
    "sg:address":"70 Memorial Ave",
    "sg:city":"Woy Woy",
    "sg:classifiers":[
        {
            "category":"Retail",
            "subcategory":"Auto Repair",
            "type":"Services"
        }
    ],
    "sg:phone":"+61 2 4341 3458",
    "sg:postcode":"2256",
    "sg:province":"NSW",
    "sg:tags":[
        "electrical"
    ],
    "wof:name":"Smith George Auto Electrician",
    "wof:placetype":"venue"
},
  "geometry": {"coordinates":[151.331130981,-33.5087738037],"type":"Point"}
}