{
  "type": "Feature",
  "properties": {
    "addr:full":"11 George St North Beach WA 6020",
    "addr:housenumber":"11",
    "addr:postcode":"6020",
    "addr:street":"George St",
    "iso:country":"AU",
    "sg:address":"11 George St",
    "sg:city":"North Beach",
    "sg:classifiers":[
        {
            "category":"Health Services",
            "subcategory":"Health Practitioner",
            "type":"Services"
        }
    ],
    "sg:phone":"+61 418 456 404",
    "sg:postcode":"6020",
    "sg:province":"WA",
    "sg:tags":[
        "physiotherapist"
    ],
    "wof:name":"Hardey Linda",
    "wof:placetype":"venue"
},
  "geometry": {"coordinates":[115.75541687,-31.8586158752],"type":"Point"}
}