{
  "type": "Feature",
  "properties": {
    "addr:full":"8 Ramsay Ave Mt Gambier SA 5290",
    "addr:housenumber":"8",
    "addr:postcode":"5290",
    "addr:street":"Ramsay Ave",
    "iso:country":"AU",
    "sg:address":"8 Ramsay Ave",
    "sg:city":"Mt Gambier",
    "sg:classifiers":[
        {
            "category":"Professional",
            "subcategory":"Engineering",
            "type":"Services"
        }
    ],
    "sg:phone":"+61 8 8723 0377",
    "sg:postcode":"5290",
    "sg:province":"SA",
    "sg:tags":[
        "engineer"
    ],
    "wof:name":"C. & R. Machining",
    "wof:placetype":"venue"
},
  "geometry": {"coordinates":[140.803314,-37.83411],"type":"Point"}
}