{
  "type": "Feature",
  "properties": {
    "iso:country":"AU",
    "sg:address":"471 Nepean Hwy",
    "sg:city":"Frankston",
    "sg:classifiers":[
        {
            "category":"Real Estate",
            "subcategory":"Real Estate Agent",
            "type":"Services"
        }
    ],
    "sg:phone":"+61 3 9781 1822",
    "sg:postcode":"3199",
    "sg:province":"VIC",
    "wof:name":"Century 21",
    "wof:placetype":"venue"
},
  "geometry": {"coordinates":[145.01011657699999,-37.9074859619],"type":"Point"}
}