{
  "type": "Feature",
  "properties": {
    "iso:country":"AU",
    "sg:address":"604/ 15 Barton Rd",
    "sg:city":"Artarmon",
    "sg:classifiers":[
        {
            "category":"Education",
            "subcategory":"Special Training",
            "type":"Public Place"
        }
    ],
    "sg:phone":"+61 2 9410 1664",
    "sg:postcode":"2064",
    "sg:province":"NSW",
    "sg:tags":[
        "school",
        "art"
    ],
    "wof:name":"MB St James Art",
    "wof:placetype":"venue"
},
  "geometry": {"coordinates":[151.184204102,-33.8126983643],"type":"Point"}
}