{
  "type": "Feature",
  "properties": {
    "addr:full":"55 Christensen Rd Stapylton QLD 4207",
    "addr:housenumber":"55",
    "addr:postcode":"4207",
    "addr:street":"Christensen Rd",
    "iso:country":"AU",
    "sg:address":"55 Christensen Rd",
    "sg:city":"Stapylton",
    "sg:classifiers":[
        {
            "category":"Home & Garden",
            "subcategory":"Building Materials",
            "type":"Retail Goods"
        }
    ],
    "sg:phone":"+61 7 3807 4300",
    "sg:postcode":"4207",
    "sg:province":"QLD",
    "sg:tags":[
        "balustrading"
    ],
    "wof:name":"B & C Balustrades",
    "wof:placetype":"venue"
},
  "geometry": {"coordinates":[153.18800354000001,-27.7132759094],"type":"Point"}
}