{
  "type": "Feature",
  "properties": {
    "iso:country":"AU",
    "sg:address":"10 Station Rd",
    "sg:city":"Burpengary",
    "sg:classifiers":[
        {
            "category":"Social Services",
            "subcategory":"Child Care",
            "type":"Services"
        }
    ],
    "sg:phone":"+61 7 3888 5303",
    "sg:postcode":"4505",
    "sg:province":"QLD",
    "wof:name":"ABC Developmental Learning Centres",
    "wof:placetype":"venue"
},
  "geometry": {"coordinates":[152.97303772000001,-27.1544647217],"type":"Point"}
}