{
  "type": "Feature",
  "properties": {
    "addr:full":"1393 Burke Rd Kew East VIC 3102",
    "addr:housenumber":"1393",
    "addr:postcode":"3102",
    "addr:street":"Burke Rd",
    "iso:country":"AU",
    "sg:address":"1393 Burke Rd",
    "sg:city":"Kew East",
    "sg:classifiers":[
        {
            "category":"Education",
            "subcategory":"School",
            "type":"Public Place"
        }
    ],
    "sg:phone":"+61 3 9859 8652",
    "sg:postcode":"3102",
    "sg:province":"VIC",
    "sg:tags":[
        "state",
        "except",
        "nsw"
    ],
    "wof:name":"Kew High School",
    "wof:placetype":"venue"
},
  "geometry": {"coordinates":[145.063232422,-37.7962036133],"type":"Point"}
}