{
  "type": "Feature",
  "properties": {
    "iso:country":"AU",
    "sg:address":"84 Bull St",
    "sg:city":"Cooks Hill",
    "sg:classifiers":[
        {
            "category":"Manufacturing",
            "subcategory":"Food",
            "type":"Manufacturing & Wholesale Goods"
        }
    ],
    "sg:phone":"+61 2 4929 1939",
    "sg:postcode":"2300",
    "sg:province":"NSW",
    "sg:tags":[
        "function",
        "catering"
    ],
    "wof:name":"Feast Catering",
    "wof:placetype":"venue"
},
  "geometry": {"coordinates":[151.767975,-32.930408],"type":"Point"}
}