{
  "type": "Feature",
  "properties": {
    "addr:full":"PO Box 279 Walkerston QLD 4751",
    "addr:postcode":"4751",
    "iso:country":"AU",
    "sg:address":"PO Box 279",
    "sg:city":"Walkerston",
    "sg:classifiers":[
        {
            "category":"Building & Trades",
            "subcategory":"Construction",
            "type":"Services"
        }
    ],
    "sg:phone":"+61 417 625 714",
    "sg:postcode":"4751",
    "sg:province":"QLD",
    "sg:tags":[
        "home",
        "air conditioning"
    ],
    "wof:name":"Stratacool Refrigeration & Air Conditioning",
    "wof:placetype":"venue"
},
  "geometry": {"coordinates":[149.06546,-21.16041],"type":"Point"}
}