{
  "type": "Feature",
  "properties": {
    "addr:full":"370 High St Penrith NSW 2750",
    "addr:housenumber":"370",
    "addr:postcode":"2750",
    "addr:street":"High St",
    "iso:country":"AU",
    "sg:address":"370 High St",
    "sg:city":"Penrith",
    "sg:classifiers":[
        {
            "category":"Communications",
            "type":"Services"
        }
    ],
    "sg:phone":"+61 2 4732 1788",
    "sg:postcode":"2750",
    "sg:province":"NSW",
    "sg:tags":[
        "public",
        "system",
        "address"
    ],
    "wof:name":"Lightsounds",
    "wof:placetype":"venue"
},
  "geometry": {"coordinates":[150.91557312,-33.8948287964],"type":"Point"}
}