{
  "type": "Feature",
  "properties": {
    "addr:full":"54 Ternes Rd Upwey VIC 3158",
    "addr:housenumber":"54",
    "addr:postcode":"3158",
    "addr:street":"Ternes Rd",
    "iso:country":"AU",
    "sg:address":"54 Ternes Rd",
    "sg:city":"Upwey",
    "sg:classifiers":[
        {
            "category":"Building & Trades",
            "subcategory":"Landscaping Services",
            "type":"Services"
        }
    ],
    "sg:phone":"+61 3 9754 6376",
    "sg:postcode":"3158",
    "sg:province":"VIC",
    "sg:tags":[
        "designer",
        "landscape",
        "contractor"
    ],
    "wof:name":"Natural Garden Scapes",
    "wof:placetype":"venue"
},
  "geometry": {"coordinates":[145.32685852,-37.9076118469],"type":"Point"}
}