{
  "type": "Feature",
  "properties": {
    "addr:full":"8 Kellaway Pl Wetherill Park NSW 2164",
    "addr:housenumber":"8",
    "addr:postcode":"2164",
    "addr:street":"Kellaway Pl",
    "iso:country":"AU",
    "sg:address":"8 Kellaway Pl",
    "sg:city":"Wetherill Park",
    "sg:classifiers":[
        {
            "category":"Building & Trades",
            "subcategory":"Construction",
            "type":"Services"
        }
    ],
    "sg:phone":"+61 1800 626 996",
    "sg:postcode":"2164",
    "sg:province":"NSW",
    "sg:tags":[
        "home",
        "air conditioning"
    ],
    "wof:name":"A Aircon Rentals",
    "wof:placetype":"venue"
},
  "geometry": {"coordinates":[150.90507507300001,-33.8400268555],"type":"Point"}
}