{
  "type": "Feature",
  "properties": {
    "addr:full":"2 Campbell St Blacktown NSW 2148",
    "addr:housenumber":"2",
    "addr:postcode":"2148",
    "addr:street":"Campbell St",
    "iso:country":"AU",
    "sg:address":"2 Campbell St",
    "sg:city":"Blacktown",
    "sg:classifiers":[
        {
            "category":"Personal",
            "subcategory":"Beauty Salon",
            "type":"Services"
        }
    ],
    "sg:phone":"+61 2 9622 4467",
    "sg:postcode":"2148",
    "sg:province":"NSW",
    "sg:tags":[
        "hairdresser"
    ],
    "wof:name":"Barber Shop",
    "wof:placetype":"venue"
},
  "geometry": {"coordinates":[150.909713745,-33.7706184387],"type":"Point"}
}