{
  "type": "Feature",
  "properties": {
    "addr:full":"18 Sutton St Woodford NSW 2778",
    "addr:housenumber":"18",
    "addr:postcode":"2778",
    "addr:street":"Sutton St",
    "iso:country":"AU",
    "sg:address":"18 Sutton St",
    "sg:city":"Woodford",
    "sg:classifiers":[
        {
            "category":"Utilities",
            "type":"Services"
        }
    ],
    "sg:phone":"+61 2 4758 8440",
    "sg:postcode":"2778",
    "sg:province":"NSW",
    "sg:tags":[
        "refrigeration",
        "industrial",
        "commercial",
        "retail"
    ],
    "wof:name":"Acerwoods",
    "wof:placetype":"venue"
},
  "geometry": {"coordinates":[150.486206055,-33.7386665344],"type":"Point"}
}