{
  "type": "Feature",
  "properties": {
    "addr:full":"577 South Dowling St Surry Hills NSW 2010",
    "addr:housenumber":"577",
    "addr:postcode":"2010",
    "addr:street":"South Dowling St",
    "iso:country":"AU",
    "sg:address":"577 South Dowling St",
    "sg:city":"Surry Hills",
    "sg:classifiers":[
        {
            "category":"Personal",
            "subcategory":"Adult",
            "type":"Services"
        }
    ],
    "sg:phone":"+61 2 9361 5616",
    "sg:postcode":"2010",
    "sg:province":"NSW",
    "sg:tags":[
        "vic",
        "except",
        "state",
        "escort",
        "social",
        "qld"
    ],
    "wof:name":"A Kiss from Lips to Toes",
    "wof:placetype":"venue"
},
  "geometry": {"coordinates":[151.21723938,-33.8888969421],"type":"Point"}
}