{
  "type": "Feature",
  "properties": {
    "iso:country":"AU",
    "sg:address":"PO Box 6318",
    "sg:city":"Kincumber",
    "sg:classifiers":[
        {
            "category":"Building & Trades",
            "subcategory":"Construction",
            "type":"Services"
        }
    ],
    "sg:phone":"+61 2 4369 1325",
    "sg:postcode":"2251",
    "sg:province":"NSW",
    "sg:tags":[
        "joiner",
        "carpenter"
    ],
    "wof:name":"MJB Carpentry & Maintenance Services Pty Ltd",
    "wof:placetype":"venue"
},
  "geometry": {"coordinates":[151.38150024399999,-33.4676513672],"type":"Point"}
}