{
  "type": "Feature",
  "properties": {
    "iso:country":"AU",
    "sg:address":"33808 Tasman Hwy",
    "sg:city":"Tulendeena",
    "sg:classifiers":[
        {
            "category":"Home & Garden",
            "subcategory":"Garden Supply",
            "type":"Retail Goods"
        }
    ],
    "sg:phone":"+61 3 6354 6157",
    "sg:postcode":"7261",
    "sg:province":"TAS",
    "sg:tags":[
        "landscape"
    ],
    "wof:name":"Michael Rockliff",
    "wof:placetype":"venue"
},
  "geometry": {"coordinates":[147.655273,-41.17432],"type":"Point"}
}