{
  "type": "Feature",
  "properties": {
    "addr:full":"Shop 2, Albert Baker Arcade, Argyle St Camden NSW 2570",
    "addr:housenumber":"shop 2",
    "addr:postcode":"2570",
    "addr:street":"Albert Baker Arcade Argyle St",
    "iso:country":"AU",
    "sg:address":"Shop 2, Albert Baker Arcade, Argyle St",
    "sg:city":"Camden",
    "sg:classifiers":[
        {
            "category":"Personal",
            "subcategory":"Beauty Salon",
            "type":"Services"
        }
    ],
    "sg:phone":"+61 2 4655 6003",
    "sg:postcode":"2570",
    "sg:province":"NSW",
    "sg:tags":[
        "hairdresser"
    ],
    "wof:name":"Elite Enz Hair Design",
    "wof:placetype":"venue"
},
  "geometry": {"coordinates":[150.69418335,-34.0552787781],"type":"Point"}
}