{
  "type": "Feature",
  "properties": {
    "addr:full":"Hayes Rd Point Henry VIC 3221",
    "addr:postcode":"3221",
    "addr:street":"Hayes Rd",
    "iso:country":"AU",
    "sg:address":"Hayes Rd",
    "sg:city":"Point Henry",
    "sg:classifiers":[
        {
            "category":"Manufacturing",
            "subcategory":"Chemicals & Compounds",
            "type":"Manufacturing & Wholesale Goods"
        }
    ],
    "sg:phone":"+61 1800 641 386",
    "sg:postcode":"3221",
    "sg:province":"VIC",
    "sg:tags":[
        "industrial"
    ],
    "wof:name":"Rohm & Haas Australia Pty Ltd",
    "wof:placetype":"venue"
},
  "geometry": {"coordinates":[144.33479299999999,-38.087784],"type":"Point"}
}