{
  "type": "Feature",
  "properties": {
    "addr:full":"2/85 Paisley St Footscray VIC 3011",
    "addr:housenumber":"/ 85",
    "addr:postcode":"3011",
    "addr:street":"Paisley St",
    "iso:country":"AU",
    "sg:address":"2/85 Paisley St",
    "sg:city":"Footscray",
    "sg:classifiers":[
        {
            "category":"Health Services",
            "subcategory":"Dentist",
            "type":"Services"
        }
    ],
    "sg:phone":"+61 3 9687 6888",
    "sg:postcode":"3011",
    "sg:province":"VIC",
    "sg:tags":[
        "dental",
        "prosthetist"
    ],
    "wof:name":"Samet Veselovski",
    "wof:placetype":"venue"
},
  "geometry": {"coordinates":[144.89567565900001,-37.8005142212],"type":"Point"}
}