{
  "type": "Feature",
  "properties": {
    "iso:country":"AU",
    "sg:address":"Professional Court, Unit 3, 2 Montford Crs",
    "sg:city":"Lyneham",
    "sg:classifiers":[
        {
            "category":"Personal",
            "subcategory":"Tattoo Parlor",
            "type":"Services"
        }
    ],
    "sg:phone":"+61 2 6247 0490",
    "sg:postcode":"2602",
    "sg:province":"ACT",
    "sg:tags":[
        "tattooing"
    ],
    "wof:name":"Tattoo Power",
    "wof:placetype":"venue"
},
  "geometry": {"coordinates":[149.135162353,-35.249370575],"type":"Point"}
}