{
  "type": "Feature",
  "properties": {
    "addr:full":"7/116 Scarborough St (Entry Via Hicks St) Southport QLD 4215",
    "addr:housenumber":"/ 116",
    "addr:postcode":"4215",
    "addr:street":"Scarborough St Entry Via Hicks St",
    "iso:country":"AU",
    "sg:address":"7/116 Scarborough St",
    "sg:city":"(Entry Via Hicks St) Southport",
    "sg:classifiers":[
        {
            "category":"Health Services",
            "subcategory":"Health Practitioner",
            "type":"Services"
        }
    ],
    "sg:phone":"+61 7 5591 6955",
    "sg:postcode":"4215",
    "sg:province":"QLD",
    "sg:tags":[
        "herbalist"
    ],
    "wof:name":"Yan Ling Chinese Medicine Clinic",
    "wof:placetype":"venue"
},
  "geometry": {"coordinates":[153.412841797,-27.9657974243],"type":"Point"}
}