{
  "type": "Feature",
  "properties": {
    "addr:full":"314 Lenah Valley Rd Lenah Valley TAS 7008",
    "addr:housenumber":"314",
    "addr:postcode":"7008",
    "addr:street":"Lenah Valley Rd",
    "iso:country":"AU",
    "sg:address":"314 Lenah Valley Rd",
    "sg:city":"Lenah Valley",
    "sg:classifiers":[
        {
            "category":"Home & Garden",
            "subcategory":"Building Materials",
            "type":"Retail Goods"
        }
    ],
    "sg:phone":"+61 3 6228 5553",
    "sg:postcode":"7008",
    "sg:province":"TAS",
    "sg:tags":[
        "supply"
    ],
    "wof:name":"Jaanco Coatings Pty Ltd",
    "wof:placetype":"venue"
},
  "geometry": {"coordinates":[147.27482605,-42.8669929504],"type":"Point"}
}