{
  "type": "Feature",
  "properties": {
    "addr:full":"258- 262 Auburn St Goulburn NSW 2580",
    "addr:housenumber":"262",
    "addr:postcode":"2580",
    "addr:street":"Auburn St",
    "iso:country":"AU",
    "sg:address":"258- 262 Auburn St",
    "sg:city":"Goulburn",
    "sg:classifiers":[
        {
            "category":"Airline",
            "type":"Transportation"
        }
    ],
    "sg:phone":"+61 2 4821 8188",
    "sg:postcode":"2580",
    "sg:province":"NSW",
    "sg:tags":[
        "agent"
    ],
    "wof:name":"Harvey World Travel",
    "wof:placetype":"venue"
},
  "geometry": {"coordinates":[149.72007751500001,-34.7524414062],"type":"Point"}
}