{
  "type": "Feature",
  "properties": {
    "addr:full":"153 Melbourne Rd Williamstown VIC 3016",
    "addr:housenumber":"153",
    "addr:postcode":"3016",
    "addr:street":"Melbourne Rd",
    "iso:country":"AU",
    "sg:address":"153 Melbourne Rd",
    "sg:city":"Williamstown",
    "sg:classifiers":[
        {
            "category":"Professional",
            "subcategory":"Art Services",
            "type":"Services"
        }
    ],
    "sg:phone":"+61 3 9397 1570",
    "sg:postcode":"3016",
    "sg:province":"VIC",
    "sg:tags":[
        "decorator",
        "painter"
    ],
    "wof:name":"Pollock Painting Service Pty Ltd",
    "wof:placetype":"venue"
},
  "geometry": {"coordinates":[144.890701294,-37.8539009094],"type":"Point"}
}