{
  "type": "Feature",
  "properties": {
    "iso:country":"AU",
    "sg:address":"Suite 2, 288 Blackburn Rd",
    "sg:city":"Doncaster East",
    "sg:classifiers":[
        {
            "category":"Building & Trades",
            "subcategory":"Cleaning & Sanitation",
            "type":"Services"
        }
    ],
    "sg:phone":"+61 3 9841 5866",
    "sg:postcode":"3109",
    "sg:province":"VIC",
    "sg:tags":[
        "window"
    ],
    "sg:website":"http://www.meticulous.ocean.com.au",
    "wof:name":"Meticulous Cleaning Services",
    "wof:placetype":"venue"
},
  "geometry": {"coordinates":[145.163665772,-37.7814254761],"type":"Point"}
}