{
  "type": "Feature",
  "properties": {
    "addr:full":"Cherry Tree La Kangaroo Flat VIC 3555",
    "addr:postcode":"3555",
    "addr:street":"Cherry Tree La",
    "iso:country":"AU",
    "sg:address":"Cherry Tree La",
    "sg:city":"Kangaroo Flat",
    "sg:classifiers":[
        {
            "category":"Building & Trades",
            "subcategory":"Construction",
            "type":"Services"
        }
    ],
    "sg:phone":"+61 3 5447 8550",
    "sg:postcode":"3555",
    "sg:province":"VIC",
    "sg:tags":[
        "contractor"
    ],
    "wof:name":"Stevenson A K & J M",
    "wof:placetype":"venue"
},
  "geometry": {"coordinates":[144.23843383799999,-36.8330535889],"type":"Point"}
}