{
  "type": "Feature",
  "properties": {
    "addr:full":"108 De Courcey St Bordertown SA 5268",
    "addr:housenumber":"108",
    "addr:postcode":"5268",
    "addr:street":"De Courcey St",
    "iso:country":"AU",
    "sg:address":"108 De Courcey St",
    "sg:city":"Bordertown",
    "sg:classifiers":[
        {
            "category":"Personal",
            "subcategory":"Beauty Salon",
            "type":"Services"
        }
    ],
    "sg:phone":"+61 8 8752 1529",
    "sg:postcode":"5268",
    "sg:province":"SA",
    "sg:tags":[
        "hairdresser"
    ],
    "wof:name":"Optimum Cut The",
    "wof:placetype":"venue"
},
  "geometry": {"coordinates":[140.77273600000001,-36.311398],"type":"Point"}
}