{
  "type": "Feature",
  "properties": {
    "iso:country":"AU",
    "sg:address":"Suite 271, Level 1, Miramer Building 398-408 Pitt",
    "sg:city":"Sydney",
    "sg:classifiers":[
        {
            "category":"Professional",
            "subcategory":"Management & Consulting",
            "type":"Services"
        }
    ],
    "sg:phone":"+61 2 9266 0099",
    "sg:postcode":"2000",
    "sg:province":"NSW",
    "sg:tags":[
        "consultant",
        "migration"
    ],
    "wof:name":"Palany & Partners",
    "wof:placetype":"venue"
},
  "geometry": {"coordinates":[151.20744323700001,-33.8785820007],"type":"Point"}
}