{
  "type": "Feature",
  "properties": {
    "addr:full":"Unit 24-25/ 193 Hartley St Bungalow QLD 4870",
    "addr:housenumber":"24-25 / 193",
    "addr:postcode":"4870",
    "addr:street":"Hartley St",
    "iso:country":"AU",
    "sg:address":"Unit 24-25/ 193 Hartley St",
    "sg:city":"Bungalow",
    "sg:classifiers":[
        {
            "category":"Wholesale",
            "subcategory":"Seafood",
            "type":"Manufacturing & Wholesale Goods"
        }
    ],
    "sg:phone":"+61 7 4035 1429",
    "sg:postcode":"4870",
    "sg:province":"QLD",
    "sg:tags":[
        "fish"
    ],
    "wof:name":"North Qld Seafoods",
    "wof:placetype":"venue"
},
  "geometry": {"coordinates":[145.762252808,-16.93907547],"type":"Point"}
}