{
  "type": "Feature",
  "properties": {
    "iso:country":"AU",
    "sg:address":"606 Robinson Rd",
    "sg:city":"Aspley",
    "sg:classifiers":[
        {
            "category":"Health Services",
            "subcategory":"Health Practitioner",
            "type":"Services"
        }
    ],
    "sg:phone":"+61 7 3863 3389",
    "sg:postcode":"4034",
    "sg:province":"QLD",
    "sg:tags":[
        "naturopath"
    ],
    "wof:name":"Thomas Staudacher",
    "wof:placetype":"venue"
},
  "geometry": {"coordinates":[153.02792400000001,-27.365589],"type":"Point"}
}