{
  "type": "Feature",
  "properties": {
    "iso:country":"AU",
    "sg:address":"26 Carrs Rd",
    "sg:city":"Wilberforce",
    "sg:classifiers":[
        {
            "category":"Building & Trades",
            "subcategory":"Construction",
            "type":"Services"
        }
    ],
    "sg:phone":"+61 2 4576 3538",
    "sg:postcode":"2756",
    "sg:province":"NSW",
    "sg:tags":[
        "waterproofing",
        "contractor"
    ],
    "wof:name":"Epoxy Systems",
    "wof:placetype":"venue"
},
  "geometry": {"coordinates":[150.831344605,-33.5287132263],"type":"Point"}
}