{
  "type": "Feature",
  "properties": {
    "addr:full":"Cnr Concord Rd & Averill St Rhodes NSW 2138",
    "addr:postcode":"2138",
    "addr:street":"Cnr Concord Rd & Averill St",
    "iso:country":"AU",
    "sg:address":"Cnr Concord Rd & Averill St",
    "sg:city":"Rhodes",
    "sg:classifiers":[
        {
            "category":"Retail",
            "subcategory":"Auto Repair",
            "type":"Services"
        }
    ],
    "sg:phone":"+61 2 9767 4545",
    "sg:postcode":"2138",
    "sg:province":"NSW",
    "sg:tags":[
        "clutch",
        "brake"
    ],
    "wof:name":"MRT Performance",
    "wof:placetype":"venue"
},
  "geometry": {"coordinates":[151.09042358400001,-33.8270835876],"type":"Point"}
}