{
  "type": "Feature",
  "properties": {
    "addr:full":"Meriton St St Georges Basin NSW 2540",
    "addr:postcode":"2540",
    "addr:street":"Meriton St",
    "iso:country":"AU",
    "sg:address":"Meriton St",
    "sg:city":"St Georges Basin",
    "sg:classifiers":[
        {
            "category":"Organizations",
            "subcategory":"Community Association",
            "type":"Services"
        }
    ],
    "sg:phone":"+61 2 4443 9372",
    "sg:postcode":"2540",
    "sg:province":"NSW",
    "sg:tags":[
        "club",
        "senior",
        "citizen"
    ],
    "wof:name":"St Georges Basin Senior Citizens Club",
    "wof:placetype":"venue"
},
  "geometry": {"coordinates":[150.59812927199999,-35.0975456238],"type":"Point"}
}