{
  "type": "Feature",
  "properties": {
    "addr:full":"5 Textile Ave Kawana Waters QLD 4575",
    "addr:housenumber":"5",
    "addr:postcode":"4575",
    "addr:street":"Textile Ave",
    "iso:country":"AU",
    "sg:address":"5 Textile Ave",
    "sg:city":"Kawana Waters",
    "sg:classifiers":[
        {
            "category":"Sports & Exercise",
            "subcategory":"Gym",
            "type":"Entertainment"
        }
    ],
    "sg:phone":"+61 7 5493 5933",
    "sg:postcode":"4575",
    "sg:province":"QLD",
    "sg:tags":[
        "personal",
        "trainer",
        "fitness"
    ],
    "wof:name":"Suncoast Fitness Centre",
    "wof:placetype":"venue"
},
  "geometry": {"coordinates":[153.12441999999999,-26.728212],"type":"Point"}
}