{
  "type": "Feature",
  "properties": {
    "addr:full":"PO Box 293 Bonnyrigg NSW 2177",
    "addr:postcode":"2177",
    "iso:country":"AU",
    "sg:address":"PO Box 293",
    "sg:city":"Bonnyrigg",
    "sg:classifiers":[
        {
            "category":"Shopping",
            "subcategory":"Computers & Home Electronics",
            "type":"Retail Goods"
        }
    ],
    "sg:phone":"+61 2 9823 5096",
    "sg:postcode":"2177",
    "sg:province":"NSW",
    "sg:tags":[
        "small",
        "equipment",
        "business"
    ],
    "wof:name":"Cyber Solutions",
    "wof:placetype":"venue"
},
  "geometry": {"coordinates":[150.88322448700001,-33.8972702026],"type":"Point"}
}