{
  "type": "Feature",
  "properties": {
    "addr:full":"16 Hoskin St Shepparton VIC 3630",
    "addr:housenumber":"16",
    "addr:postcode":"3630",
    "addr:street":"Hoskin St",
    "iso:country":"AU",
    "sg:address":"16 Hoskin St",
    "sg:city":"Shepparton",
    "sg:classifiers":[
        {
            "category":"Shopping",
            "subcategory":"Crafts & Fabrics",
            "type":"Retail Goods"
        }
    ],
    "sg:phone":"+61 3 5831 7778",
    "sg:postcode":"3630",
    "sg:province":"VIC",
    "sg:tags":[
        "synthetic",
        "canvas",
        "product"
    ],
    "wof:name":"Falla's Motor Trimming",
    "wof:placetype":"venue"
},
  "geometry": {"coordinates":[145.40472412099999,-36.3835601807],"type":"Point"}
}