{
  "type": "Feature",
  "properties": {
    "addr:full":"51B Hogan St Tatura VIC 3616",
    "addr:housenumber":"51b",
    "addr:postcode":"3616",
    "addr:street":"Hogan St",
    "iso:country":"AU",
    "sg:address":"51B Hogan St",
    "sg:city":"Tatura",
    "sg:classifiers":[
        {
            "category":"Structure",
            "subcategory":"Bridge",
            "type":"Public Place"
        }
    ],
    "sg:phone":"+61 3 5824 1447",
    "sg:postcode":"3616",
    "sg:province":"VIC",
    "sg:tags":[
        "chainsaw",
        "brushcutters"
    ],
    "wof:name":"Tatura Automotive",
    "wof:placetype":"venue"
},
  "geometry": {"coordinates":[145.23031616200001,-36.4399757385],"type":"Point"}
}