{
  "type": "Feature",
  "properties": {
    "iso:country":"AU",
    "sg:address":"13 Dorlton St",
    "sg:city":"Kings Langley",
    "sg:classifiers":[
        {
            "category":"Manufacturing",
            "subcategory":"Tools & Machinery",
            "type":"Manufacturing & Wholesale Goods"
        }
    ],
    "sg:phone":"+61 2 9674 8588",
    "sg:postcode":"2147",
    "sg:province":"NSW",
    "sg:tags":[
        "equipment",
        "scale",
        "weighing"
    ],
    "wof:name":"City and Country Scales",
    "wof:placetype":"venue"
},
  "geometry": {"coordinates":[150.93132019000001,-33.7501411438],"type":"Point"}
}