{
  "type": "Feature",
  "properties": {
    "addr:full":"358 Wickham St Fortitude Valley QLD 4006",
    "addr:housenumber":"358",
    "addr:postcode":"4006",
    "addr:street":"Wickham St",
    "iso:country":"AU",
    "sg:address":"358 Wickham St",
    "sg:city":"Fortitude Valley",
    "sg:classifiers":[
        {
            "category":"Autos & Motor Vehicles",
            "subcategory":"Automobile Sales",
            "type":"Retail Goods"
        }
    ],
    "sg:phone":"+61 7 3251 6666",
    "sg:postcode":"4006",
    "sg:province":"QLD",
    "sg:tags":[
        "car",
        "used"
    ],
    "wof:name":"Mercedes-Benz of Brisbane",
    "wof:placetype":"venue"
},
  "geometry": {"coordinates":[153.03570556599999,-27.4551753998],"type":"Point"}
}