{
  "type": "Feature",
  "properties": {
    "addr:full":"1 Swansea St Swansea NSW 2281",
    "addr:housenumber":"1",
    "addr:postcode":"2281",
    "addr:street":"Swansea St",
    "iso:country":"AU",
    "sg:address":"1 Swansea St",
    "sg:city":"Swansea",
    "sg:classifiers":[
        {
            "category":"Retail",
            "subcategory":"Repair Shop",
            "type":"Services"
        }
    ],
    "sg:phone":"+61 409 714 035",
    "sg:postcode":"2281",
    "sg:province":"NSW",
    "sg:tags":[
        "windscreen"
    ],
    "wof:name":"All Class Windscreens",
    "wof:placetype":"venue"
},
  "geometry": {"coordinates":[151.635299683,-33.0854911804],"type":"Point"}
}