{
  "type": "Feature",
  "properties": {
    "addr:full":"8 Maude St Shepparton VIC 3630",
    "addr:housenumber":"8",
    "addr:postcode":"3630",
    "addr:street":"Maude St",
    "iso:country":"AU",
    "sg:address":"8 Maude St",
    "sg:city":"Shepparton",
    "sg:classifiers":[
        {
            "category":"Health Services",
            "subcategory":"Doctor",
            "type":"Services"
        }
    ],
    "sg:phone":"+61 3 5821 5626",
    "sg:postcode":"3630",
    "sg:province":"VIC",
    "sg:tags":[
        "medical",
        "practitioner"
    ],
    "wof:name":"Mackenzie Ruary",
    "wof:placetype":"venue"
},
  "geometry": {"coordinates":[145.40342712399999,-36.3675537109],"type":"Point"}
}