{
  "type": "Feature",
  "properties": {
    "iso:country":"AU",
    "sg:address":"Cnr Old Telegraph Rd & Bloomfield Rd",
    "sg:city":"Crossover",
    "sg:classifiers":[
        {
            "category":"Professional",
            "subcategory":"Art Services",
            "type":"Services"
        }
    ],
    "sg:phone":"+61 3 5626 8481",
    "sg:postcode":"3821",
    "sg:province":"VIC",
    "sg:tags":[
        "artist"
    ],
    "wof:name":"Warren Kerrie",
    "wof:placetype":"venue"
},
  "geometry": {"coordinates":[145.96722399999999,-38.062641],"type":"Point"}
}