{
  "type": "Feature",
  "properties": {
    "iso:country":"AU",
    "sg:address":"416 Burwood Rd",
    "sg:city":"Belmore",
    "sg:classifiers":[
        {
            "category":"Fast Food",
            "type":"Food & Drink"
        }
    ],
    "sg:phone":"+61 2 9758 2066",
    "sg:postcode":"2192",
    "sg:province":"NSW",
    "sg:tags":[
        "away",
        "take"
    ],
    "wof:name":"Belmore Awafy",
    "wof:placetype":"venue"
},
  "geometry": {"coordinates":[151.08921799999999,-33.919254],"type":"Point"}
}