{
  "type": "Feature",
  "properties": {
    "addr:full":"106a Annangrove Rd Kenthurst NSW 2156",
    "addr:housenumber":"106a",
    "addr:postcode":"2156",
    "addr:street":"Annangrove Rd",
    "iso:country":"AU",
    "sg:address":"106a Annangrove Rd",
    "sg:city":"Kenthurst",
    "sg:classifiers":[
        {
            "category":"Building & Trades",
            "subcategory":"Construction",
            "type":"Services"
        }
    ],
    "sg:phone":"+61 2 9654 2521",
    "sg:postcode":"2156",
    "sg:province":"NSW",
    "sg:tags":[
        "joiner",
        "carpenter"
    ],
    "wof:name":"Jeanneret J R",
    "wof:placetype":"venue"
},
  "geometry": {"coordinates":[150.978393555,-33.6808624268],"type":"Point"}
}