{
  "type": "Feature",
  "properties": {
    "iso:country":"AU",
    "sg:address":"67 Wallarah Rd",
    "sg:city":"Gorokan",
    "sg:classifiers":[
        {
            "category":"Autos & Motor Vehicles",
            "subcategory":"Fuel & Gas Station",
            "type":"Retail Goods"
        }
    ],
    "sg:phone":"+61 2 4392 2444",
    "sg:postcode":"2263",
    "sg:province":"NSW",
    "wof:name":"Shell Select",
    "wof:placetype":"venue"
},
  "geometry": {"coordinates":[151.507935,-33.256359],"type":"Point"}
}