{
  "type": "Feature",
  "properties": {
    "addr:full":"25 Botanical Drv Kellyville NSW 2155",
    "addr:housenumber":"25",
    "addr:postcode":"2155",
    "addr:street":"Botanical Drv",
    "iso:country":"AU",
    "sg:address":"25 Botanical Drv",
    "sg:city":"Kellyville",
    "sg:classifiers":[
        {
            "category":"Retail",
            "subcategory":"Auto Rental",
            "type":"Services"
        }
    ],
    "sg:phone":"+61 411 029 023",
    "sg:postcode":"2155",
    "sg:province":"NSW",
    "sg:tags":[
        "chauffeur",
        "car",
        "hire",
        "driven",
        "limousine"
    ],
    "wof:name":"Sydney Star Limousines",
    "wof:placetype":"venue"
},
  "geometry": {"coordinates":[150.94801330600001,-33.7084884644],"type":"Point"}
}