{
  "type": "Feature",
  "properties": {
    "iso:country":"AU",
    "sg:address":"61 McCoy St",
    "sg:city":"Myaree",
    "sg:classifiers":[
        {
            "category":"Utilities",
            "type":"Services"
        }
    ],
    "sg:phone":"+61 8 9317 2344",
    "sg:postcode":"6154",
    "sg:province":"WA",
    "sg:tags":[
        "equipment",
        "towing"
    ],
    "wof:name":"Off Road Equipment",
    "wof:placetype":"venue"
},
  "geometry": {"coordinates":[115.814194,-32.043655],"type":"Point"}
}