{
  "type": "Feature",
  "properties": {
    "addr:full":"/661 Ipswich Rd, Annerley 34 Centenary Pl Logan Village QLD 4207",
    "addr:housenumber":"/ 661;34",
    "addr:postcode":"4207",
    "addr:street":"Ipswich Rd;Centenary Pl Logan",
    "iso:country":"AU",
    "sg:address":"/661 Ipswich Rd, Annerley 34 Centenary Pl",
    "sg:city":"Logan Village",
    "sg:classifiers":[
        {
            "category":"Manufacturing",
            "subcategory":"Musical Instruments",
            "type":"Manufacturing & Wholesale Goods"
        }
    ],
    "sg:phone":"+61 7 5546 3711",
    "sg:postcode":"4207",
    "sg:province":"QLD",
    "sg:tags":[
        "repair",
        "maker"
    ],
    "wof:name":"Better Sounds Australia",
    "wof:placetype":"venue"
},
  "geometry": {"coordinates":[153.10963439899999,-27.7689743042],"type":"Point"}
}