{
  "type": "Feature",
  "properties": {
    "addr:full":"84 Plain St Tamworth NSW 2340",
    "addr:housenumber":"84",
    "addr:postcode":"2340",
    "addr:street":"Plain St",
    "iso:country":"AU",
    "sg:address":"84 Plain St",
    "sg:city":"Tamworth",
    "sg:classifiers":[
        {
            "category":"Home & Garden",
            "subcategory":"Hardware",
            "type":"Retail Goods"
        }
    ],
    "sg:phone":"+61 2 6762 5353",
    "sg:postcode":"2340",
    "sg:province":"NSW",
    "sg:tags":[
        "compressor",
        "air"
    ],
    "wof:name":"Ivan Flood",
    "wof:placetype":"venue"
},
  "geometry": {"coordinates":[150.91029357900001,-31.087890625],"type":"Point"}
}