{
  "type": "Feature",
  "properties": {
    "addr:full":"105 Nott St Port Melbourne VIC 3207",
    "addr:housenumber":"105",
    "addr:postcode":"3207",
    "addr:street":"Nott St",
    "iso:country":"AU",
    "sg:address":"105 Nott St",
    "sg:city":"Port Melbourne",
    "sg:classifiers":[
        {
            "category":"Professional",
            "subcategory":"Art Services",
            "type":"Services"
        }
    ],
    "sg:phone":"+61 3 9645 6999",
    "sg:postcode":"3207",
    "sg:province":"VIC",
    "sg:tags":[
        "interior",
        "designer"
    ],
    "wof:name":"Brown Jordan",
    "wof:placetype":"venue"
},
  "geometry": {"coordinates":[144.93884299999999,-37.840221],"type":"Point"}
}