{
  "type": "Feature",
  "properties": {
    "addr:full":"Level 1/ 51 Berry St North Sydney NSW 2060",
    "addr:housenumber":"/ 51",
    "addr:postcode":"2060",
    "addr:street":"Berry St",
    "iso:country":"AU",
    "sg:address":"Level 1/ 51 Berry St",
    "sg:city":"North Sydney",
    "sg:classifiers":[
        {
            "category":"Cafe",
            "type":"Food & Drink"
        }
    ],
    "sg:phone":"+61 2 9955 8891",
    "sg:postcode":"2060",
    "sg:province":"NSW",
    "wof:name":"Wild Berry Gourmet Cafe",
    "wof:placetype":"venue"
},
  "geometry": {"coordinates":[151.20661926299999,-33.8368530273],"type":"Point"}
}