{
  "type": "Feature",
  "properties": {
    "addr:full":"25 Wyeebo St Merimbula NSW 2548",
    "addr:housenumber":"25",
    "addr:postcode":"2548",
    "addr:street":"Wyeebo St",
    "iso:country":"AU",
    "sg:address":"25 Wyeebo St",
    "sg:city":"Merimbula",
    "sg:classifiers":[
        {
            "category":"Building & Trades",
            "subcategory":"Landscaping Services",
            "type":"Services"
        }
    ],
    "sg:phone":"+61 2 6495 2445",
    "sg:postcode":"2548",
    "sg:province":"NSW",
    "sg:tags":[
        "gardener"
    ],
    "wof:name":"Harbour Botanics",
    "wof:placetype":"venue"
},
  "geometry": {"coordinates":[149.92555236800001,-36.8909187317],"type":"Point"}
}