{
  "type": "Feature",
  "properties": {
    "addr:full":"47- 49 King St Norwood SA 5067",
    "addr:housenumber":"49",
    "addr:postcode":"5067",
    "addr:street":"King St",
    "iso:country":"AU",
    "sg:address":"47- 49 King St",
    "sg:city":"Norwood",
    "sg:classifiers":[
        {
            "category":"Shopping",
            "subcategory":"Computers & Home Electronics",
            "type":"Retail Goods"
        }
    ],
    "sg:phone":"+61 8 8362 8727",
    "sg:postcode":"5067",
    "sg:province":"SA",
    "sg:tags":[
        "equipment",
        "multimedia"
    ],
    "wof:name":"Grafxar Multimedia",
    "wof:placetype":"venue"
},
  "geometry": {"coordinates":[138.62709045400001,-34.917339325],"type":"Point"}
}