{
  "type": "Feature",
  "properties": {
    "iso:country":"AU",
    "sg:address":"24-26 Wedgewood Rd",
    "sg:city":"Hallam",
    "sg:classifiers":[
        {
            "category":"Professional",
            "subcategory":"Business Services",
            "type":"Services"
        }
    ],
    "sg:phone":"+61 3 9702 4764",
    "sg:postcode":"3803",
    "sg:province":"VIC",
    "sg:tags":[
        "broker"
    ],
    "wof:name":"Phillip James Business Sales",
    "wof:placetype":"venue"
},
  "geometry": {"coordinates":[145.25697326700001,-38.0057182312],"type":"Point"}
}