{
  "type": "Feature",
  "properties": {
    "iso:country":"AU",
    "sg:address":"240 Coleraine Rd",
    "sg:city":"Hamilton",
    "sg:classifiers":[
        {
            "category":"Wholesale",
            "subcategory":"Machinery & Supplies",
            "type":"Manufacturing & Wholesale Goods"
        }
    ],
    "sg:phone":"+61 3 5572 1822",
    "sg:postcode":"3300",
    "sg:province":"VIC",
    "sg:tags":[
        "agricultural"
    ],
    "wof:name":"Phillips Farm Machinery Sales & Service Pty Ltd",
    "wof:placetype":"venue"
},
  "geometry": {"coordinates":[142.00242614699999,-37.7280273438],"type":"Point"}
}