{
  "type": "Feature",
  "properties": {
    "addr:full":"Suite 3/ 75A Angas St Adelaide SA 5000",
    "addr:housenumber":"/ 75a",
    "addr:postcode":"5000",
    "addr:street":"Angas St",
    "iso:country":"AU",
    "sg:address":"Suite 3/ 75A Angas St",
    "sg:city":"Adelaide",
    "sg:classifiers":[
        {
            "category":"Professional",
            "subcategory":"Employment Agencies",
            "type":"Services"
        }
    ],
    "sg:phone":"+61 8 8232 8791",
    "sg:postcode":"5000",
    "sg:province":"SA",
    "sg:tags":[
        "model"
    ],
    "wof:name":"Mango Promotions",
    "wof:placetype":"venue"
},
  "geometry": {"coordinates":[138.60325622600001,-34.9300956726],"type":"Point"}
}