{
  "type": "Feature",
  "properties": {
    "iso:country":"AU",
    "sg:address":"Unit 2/ 18 Somer St",
    "sg:city":"Hyde Park",
    "sg:classifiers":[
        {
            "category":"Utilities",
            "subcategory":"Electric",
            "type":"Services"
        }
    ],
    "sg:phone":"+61 7 4724 2662",
    "sg:postcode":"4812",
    "sg:province":"QLD",
    "sg:tags":[
        "electrical",
        "contractor"
    ],
    "wof:name":"Northern Electrical Contractors",
    "wof:placetype":"venue"
},
  "geometry": {"coordinates":[146.800354,-19.273184],"type":"Point"}
}