{
  "type": "Feature",
  "properties": {
    "iso:country":"AU",
    "sg:address":"14 Arnhem Rd",
    "sg:city":"Allambie Heights",
    "sg:classifiers":[
        {
            "category":"Building & Trades",
            "subcategory":"Construction",
            "type":"Services"
        }
    ],
    "sg:phone":"+61 2 9451 8457",
    "sg:postcode":"2100",
    "sg:province":"NSW",
    "sg:tags":[
        "contractor"
    ],
    "wof:name":"Tait Building Services Pty Ltd",
    "wof:placetype":"venue"
},
  "geometry": {"coordinates":[151.24623107900001,-33.7596931458],"type":"Point"}
}