{
  "type": "Feature",
  "properties": {
    "iso:country":"AU",
    "sg:address":"96 Gisborne Rd",
    "sg:city":"Bacchus Marsh",
    "sg:classifiers":[
        {
            "category":"Health Services",
            "subcategory":"Nursing And Care Facility",
            "type":"Services"
        }
    ],
    "sg:phone":"+61 3 5367 8444",
    "sg:postcode":"3340",
    "sg:province":"VIC",
    "sg:tags":[
        "home"
    ],
    "wof:name":"Bacchus Marsh Retirement Living",
    "wof:placetype":"venue"
},
  "geometry": {"coordinates":[144.437653,-37.667469],"type":"Point"}
}