{
  "type": "Feature",
  "properties": {
    "iso:country":"AU",
    "sg:address":"16 Warby St",
    "sg:city":"Campbelltown",
    "sg:classifiers":[
        {
            "category":"Health Services",
            "subcategory":"Doctor",
            "type":"Services"
        }
    ],
    "sg:phone":"+61 2 4625 4400",
    "sg:postcode":"2560",
    "sg:province":"NSW",
    "sg:tags":[
        "occupational",
        "safety"
    ],
    "wof:name":"Active Working Solutions",
    "wof:placetype":"venue"
},
  "geometry": {"coordinates":[150.820404053,-34.0619544983],"type":"Point"}
}