{
  "type": "Feature",
  "properties": {
    "iso:country":"AU",
    "sg:address":"2 Regal Crt",
    "sg:city":"Bunbury",
    "sg:classifiers":[
        {
            "category":"Retail",
            "subcategory":"Driving School",
            "type":"Services"
        }
    ],
    "sg:phone":"+61 8 9721 1720",
    "sg:postcode":"6230",
    "sg:province":"WA",
    "wof:name":"Bunbury Driving School",
    "wof:placetype":"venue"
},
  "geometry": {"coordinates":[115.633873,-33.337421],"type":"Point"}
}