{
  "type": "Feature",
  "properties": {
    "addr:full":"PO Box 4366 Ringwood VIC 3134",
    "addr:postcode":"3134",
    "iso:country":"AU",
    "sg:address":"PO Box 4366",
    "sg:city":"Ringwood",
    "sg:classifiers":[
        {
            "category":"Professional",
            "subcategory":"Computer Services",
            "type":"Services"
        }
    ],
    "sg:phone":"+61 3 9876 6620",
    "sg:postcode":"3134",
    "sg:province":"VIC",
    "sg:tags":[
        "consultant",
        "system"
    ],
    "wof:name":"OSD Consulting",
    "wof:placetype":"venue"
},
  "geometry": {"coordinates":[145.22752380399999,-37.8157196045],"type":"Point"}
}