{
  "type": "Feature",
  "properties": {
    "addr:full":"PMB 12 via Katherine NT 0852",
    "addr:postcode":"nt 0852",
    "addr:street":"Via Katherine",
    "iso:country":"AU",
    "sg:address":"PMB 12 via",
    "sg:city":"Katherine",
    "sg:classifiers":[
        {
            "category":"Education",
            "subcategory":"School",
            "type":"Public Place"
        }
    ],
    "sg:phone":"+61 8 8975 4645",
    "sg:postcode":"0852",
    "sg:province":"NT",
    "sg:tags":[
        "state",
        "except",
        "nsw"
    ],
    "wof:name":"Urapunga School",
    "wof:placetype":"venue"
},
  "geometry": {"coordinates":[133.373886,-16.30308],"type":"Point"}
}