{
  "type": "Feature",
  "properties": {
    "addr:full":"152 Burgundy St Heidelberg VIC 3084",
    "addr:housenumber":"152",
    "addr:postcode":"3084",
    "addr:street":"Burgundy St",
    "iso:country":"AU",
    "sg:address":"152 Burgundy St",
    "sg:city":"Heidelberg",
    "sg:classifiers":[
        {
            "category":"Personal",
            "subcategory":"Beauty Salon",
            "type":"Services"
        }
    ],
    "sg:phone":"+61 3 9455 3557",
    "sg:postcode":"3084",
    "sg:province":"VIC",
    "wof:name":"Ella Bache Heidelberg",
    "wof:placetype":"venue"
},
  "geometry": {"coordinates":[145.065109253,-37.7559127808],"type":"Point"}
}