{
  "type": "Feature",
  "properties": {
    "addr:full":"15 Timbertop Drv Umina Beach NSW 2257",
    "addr:housenumber":"15",
    "addr:postcode":"2257",
    "addr:street":"Timbertop Drv",
    "iso:country":"AU",
    "sg:address":"15 Timbertop Drv",
    "sg:city":"Umina Beach",
    "sg:classifiers":[
        {
            "category":"Government",
            "subcategory":"Court House",
            "type":"Public Place"
        }
    ],
    "sg:phone":"+61 2 4341 9729",
    "sg:postcode":"2257",
    "sg:province":"NSW",
    "sg:tags":[
        "personal",
        "marriage",
        "family",
        "counselling"
    ],
    "wof:name":"Lynne Wilson",
    "wof:placetype":"venue"
},
  "geometry": {"coordinates":[151.300323486,-33.5062599182],"type":"Point"}
}