{
  "type": "Feature",
  "properties": {
    "addr:full":"29 Glenheath Ave Kellyville Ridge NSW 2155",
    "addr:housenumber":"29",
    "addr:postcode":"2155",
    "addr:street":"Glenheath Ave",
    "iso:country":"AU",
    "sg:address":"29 Glenheath Ave",
    "sg:city":"Kellyville Ridge",
    "sg:classifiers":[
        {
            "category":"Retail",
            "subcategory":"Storage",
            "type":"Services"
        }
    ],
    "sg:phone":"+61 1300 668 366",
    "sg:postcode":"2155",
    "sg:province":"NSW",
    "sg:tags":[
        "removal",
        "furniture"
    ],
    "wof:name":"All Freight Removals",
    "wof:placetype":"venue"
},
  "geometry": {"coordinates":[150.92257690400001,-33.6989479065],"type":"Point"}
}