{
  "type": "Feature",
  "properties": {
    "addr:full":"66 Main St Belgrave VIC 3160",
    "addr:housenumber":"66",
    "addr:postcode":"3160",
    "addr:street":"Main St",
    "iso:country":"AU",
    "sg:address":"66 Main St",
    "sg:city":"Belgrave",
    "sg:classifiers":[
        {
            "category":"Health Services",
            "subcategory":"Dentist",
            "type":"Services"
        }
    ],
    "sg:phone":"+61 3 9754 2081",
    "sg:postcode":"3160",
    "sg:province":"VIC",
    "sg:tags":[
        "dental",
        "prosthetist"
    ],
    "wof:name":"Carl Latham",
    "wof:placetype":"venue"
},
  "geometry": {"coordinates":[145.331466675,-37.90417099],"type":"Point"}
}