{
  "type": "Feature",
  "properties": {
    "iso:country":"AU",
    "sg:address":"Princes Hwy",
    "sg:city":"Milton",
    "sg:classifiers":[
        {
            "category":"Personal",
            "subcategory":"Massage",
            "type":"Services"
        }
    ],
    "sg:phone":"+61 2 4456 1394",
    "sg:postcode":"2538",
    "sg:province":"NSW",
    "sg:tags":[
        "therapy"
    ],
    "wof:name":"Bartlett Geoff",
    "wof:placetype":"venue"
},
  "geometry": {"coordinates":[150.436645508,-35.3168716431],"type":"Point"}
}