{
  "type": "Feature",
  "properties": {
    "addr:full":"Campbell St Camperdown VIC 3260",
    "addr:postcode":"3260",
    "addr:street":"St",
    "iso:country":"AU",
    "sg:address":"Campbell St",
    "sg:city":"Camperdown",
    "sg:classifiers":[
        {
            "category":"Education",
            "subcategory":"Kindergarten",
            "type":"Public Place"
        }
    ],
    "sg:phone":"+61 3 5593 1936",
    "sg:postcode":"3260",
    "sg:province":"VIC",
    "sg:tags":[
        "pre-schools"
    ],
    "wof:name":"Camperdown Pre-School Centre",
    "wof:placetype":"venue"
},
  "geometry": {"coordinates":[143.14419555699999,-38.2339096069],"type":"Point"}
}