{
  "type": "Feature",
  "properties": {
    "iso:country":"AU",
    "sg:address":"1a, 63- 65 Five Islands Rd",
    "sg:city":"Port Kembla",
    "sg:classifiers":[
        {
            "category":"Retail",
            "subcategory":"Auto Repair",
            "type":"Services"
        }
    ],
    "sg:phone":"+61 2 4276 3611",
    "sg:postcode":"2505",
    "sg:province":"NSW",
    "sg:tags":[
        "electrical"
    ],
    "wof:name":"Coastwide Auto Electrics & Air Conditioning",
    "wof:placetype":"venue"
},
  "geometry": {"coordinates":[150.89534,-34.478306],"type":"Point"}
}