{
  "type": "Feature",
  "properties": {
    "addr:full":"Shop 2/ 8 Bent St Toowong QLD 4066",
    "addr:housenumber":"shop 2 / 8",
    "addr:postcode":"4066",
    "addr:street":"Bent St",
    "iso:country":"AU",
    "sg:address":"Shop 2/ 8 Bent St",
    "sg:city":"Toowong",
    "sg:classifiers":[
        {
            "category":"Retail",
            "subcategory":"Self-service Laundry",
            "type":"Services"
        }
    ],
    "sg:phone":"+61 405 530 222",
    "sg:postcode":"4066",
    "sg:province":"QLD",
    "wof:name":"Toowong Laundromat",
    "wof:placetype":"venue"
},
  "geometry": {"coordinates":[152.980667114,-27.4840984344],"type":"Point"}
}