{
  "type": "Feature",
  "properties": {
    "addr:full":"54 Southern Rd Mentone VIC 3194",
    "addr:housenumber":"54",
    "addr:postcode":"3194",
    "addr:street":"Southern Rd",
    "iso:country":"AU",
    "sg:address":"54 Southern Rd",
    "sg:city":"Mentone",
    "sg:classifiers":[
        {
            "category":"Wholesale",
            "subcategory":"Construction Materials",
            "type":"Manufacturing & Wholesale Goods"
        }
    ],
    "sg:phone":"+61 3 9581 9333",
    "sg:postcode":"3194",
    "sg:province":"VIC",
    "sg:tags":[
        "wholesaler",
        "lighting",
        "mfrs",
        "accessory"
    ],
    "wof:name":"Hella Australia Pty Ltd",
    "wof:placetype":"venue"
},
  "geometry": {"coordinates":[145.08847045900001,-37.9785881042],"type":"Point"}
}