{
  "type": "Feature",
  "properties": {
    "iso:country":"AU",
    "sg:address":"89 Lord St",
    "sg:city":"Port Macquarie",
    "sg:classifiers":[
        {
            "category":"Government",
            "subcategory":"Court House",
            "type":"Public Place"
        }
    ],
    "sg:phone":"+61 2 6584 4790",
    "sg:postcode":"2444",
    "sg:province":"NSW",
    "sg:tags":[
        "personal",
        "marriage",
        "family",
        "counselling"
    ],
    "wof:name":"Natalie Green",
    "wof:placetype":"venue"
},
  "geometry": {"coordinates":[152.908173,-31.4296],"type":"Point"}
}