{
  "type": "Feature",
  "properties": {
    "iso:country":"AU",
    "sg:address":"PO Box 2114",
    "sg:city":"Deer Park",
    "sg:classifiers":[
        {
            "category":"Arts & Performance",
            "subcategory":"Music",
            "type":"Entertainment"
        }
    ],
    "sg:phone":"+61 424 666 203",
    "sg:postcode":"3023",
    "sg:province":"VIC",
    "sg:tags":[
        "mobile",
        "jockey",
        "disc"
    ],
    "wof:name":"Affordable DJ Professionals",
    "wof:placetype":"venue"
},
  "geometry": {"coordinates":[144.774857,-37.76955],"type":"Point"}
}