{
  "type": "Feature",
  "properties": {
    "iso:country":"AU",
    "sg:address":"22 Langton Rd",
    "sg:city":"Mt Barker",
    "sg:classifiers":[
        {
            "category":"Health Services",
            "subcategory":"Chiropractor",
            "type":"Services"
        }
    ],
    "sg:phone":"+61 8 9842 3303",
    "sg:postcode":"6324",
    "sg:province":"WA",
    "wof:name":"South West Chiropractic",
    "wof:placetype":"venue"
},
  "geometry": {"coordinates":[117.65984344500001,-34.6274757385],"type":"Point"}
}