{
  "type": "Feature",
  "properties": {
    "addr:full":"314 St Kilda Rd St Kilda VIC 3182",
    "addr:housenumber":"314",
    "addr:postcode":"3182",
    "addr:street":"St Kilda Rd",
    "iso:country":"AU",
    "sg:address":"314 St Kilda Rd",
    "sg:city":"St Kilda",
    "sg:classifiers":[
        {
            "category":"Manufacturing",
            "subcategory":"Furniture",
            "type":"Manufacturing & Wholesale Goods"
        }
    ],
    "sg:phone":"+61 3 9534 6262",
    "sg:postcode":"3182",
    "sg:province":"VIC",
    "sg:tags":[
        "builder",
        "designer",
        "custom"
    ],
    "wof:name":"Absymmetrix",
    "wof:placetype":"venue"
},
  "geometry": {"coordinates":[144.98617553700001,-37.8649215698],"type":"Point"}
}