{
  "type": "Feature",
  "properties": {
    "addr:full":"Exchange Courtyard, Grosvenor Pl Sydney NSW 2000",
    "addr:postcode":"2000",
    "addr:street":"Grosvenor Pl",
    "iso:country":"AU",
    "sg:address":"Exchange Courtyard, Grosvenor Pl",
    "sg:city":"Sydney",
    "sg:classifiers":[
        {
            "category":"Health Services",
            "subcategory":"Dentist",
            "type":"Services"
        }
    ],
    "sg:phone":"+61 2 9251 8889",
    "sg:postcode":"2000",
    "sg:province":"NSW",
    "wof:name":"Alam Juliana",
    "wof:placetype":"venue"
},
  "geometry": {"coordinates":[151.20736694300001,-33.8633956909],"type":"Point"}
}