{
  "type": "Feature",
  "properties": {
    "addr:full":"Balmore St Yarrawonga NSW 2850",
    "addr:postcode":"2850",
    "addr:street":"Balmore St",
    "iso:country":"AU",
    "sg:address":"Balmore St",
    "sg:city":"Yarrawonga",
    "sg:classifiers":[
        {
            "category":"Personal",
            "subcategory":"Massage",
            "type":"Services"
        }
    ],
    "sg:phone":"+61 3 5744 2148",
    "sg:postcode":"2850",
    "sg:province":"NSW",
    "sg:tags":[
        "therapy"
    ],
    "wof:name":"Mulwal Sports Injury Clinic",
    "wof:placetype":"venue"
},
  "geometry": {"coordinates":[149.579849,-32.590919],"type":"Point"}
}