{
  "type": "Feature",
  "properties": {
    "addr:full":"\"Giggiwa\" Captains Flat Rd Captains Flat NSW 2623",
    "addr:postcode":"2623",
    "addr:street":"Captains Flat Rd",
    "iso:country":"AU",
    "sg:address":"\"Giggiwa\" Captains Flat Rd",
    "sg:city":"Captains Flat",
    "sg:classifiers":[
        {
            "category":"Building & Trades",
            "subcategory":"Construction",
            "type":"Services"
        }
    ],
    "sg:phone":"+61 2 6236 6251",
    "sg:postcode":"2623",
    "sg:province":"NSW",
    "sg:tags":[
        "fencing",
        "contractor"
    ],
    "wof:name":"Cotterill Fencing",
    "wof:placetype":"venue"
},
  "geometry": {"coordinates":[149.44659423799999,-35.5912780762],"type":"Point"}
}