{
  "type": "Feature",
  "properties": {
    "addr:full":"9 Beaufort St Woodville SA 5011",
    "addr:housenumber":"9",
    "addr:postcode":"5011",
    "addr:street":"Beaufort St",
    "iso:country":"AU",
    "sg:address":"9 Beaufort St",
    "sg:city":"Woodville",
    "sg:classifiers":[
        {
            "category":"Shopping",
            "subcategory":"Antiques",
            "type":"Retail Goods"
        }
    ],
    "sg:phone":"+61 8 8268 2904",
    "sg:postcode":"5011",
    "sg:province":"SA",
    "sg:tags":[
        "restoration",
        "reproduction"
    ],
    "wof:name":"Robert Anton Furniture Restorations",
    "wof:placetype":"venue"
},
  "geometry": {"coordinates":[138.54284668,-34.8767127991],"type":"Point"}
}