{
  "type": "Feature",
  "properties": {
    "addr:full":"172 Albert St Sebastopol VIC 3356",
    "addr:housenumber":"172",
    "addr:postcode":"3356",
    "addr:street":"Albert St",
    "iso:country":"AU",
    "sg:address":"172 Albert St",
    "sg:city":"Sebastopol",
    "sg:classifiers":[
        {
            "category":"Health Services",
            "subcategory":"Doctor",
            "type":"Services"
        }
    ],
    "sg:phone":"+61 3 5335 7366",
    "sg:postcode":"3356",
    "sg:province":"VIC",
    "sg:tags":[
        "medical",
        "practitioner"
    ],
    "wof:name":"Rose J D",
    "wof:placetype":"venue"
},
  "geometry": {"coordinates":[143.840881,-37.596272],"type":"Point"}
}