{
  "type": "Feature",
  "properties": {
    "addr:full":"17 Lindsay St Grevillia NSW 2474",
    "addr:housenumber":"17",
    "addr:postcode":"2474",
    "addr:street":"Lindsay St",
    "iso:country":"AU",
    "sg:address":"17 Lindsay St",
    "sg:city":"Grevillia",
    "sg:classifiers":[
        {
            "category":"Building & Trades",
            "subcategory":"Construction",
            "type":"Services"
        }
    ],
    "sg:phone":"+61 2 6636 4132",
    "sg:postcode":"2474",
    "sg:province":"NSW",
    "sg:tags":[
        "earth",
        "excavating",
        "moving",
        "contractor"
    ],
    "wof:name":"O'Neill Earth Moving Peter",
    "wof:placetype":"venue"
},
  "geometry": {"coordinates":[153.08888244600001,-28.6464328766],"type":"Point"}
}