{
  "type": "Feature",
  "properties": {
    "addr:full":"1645 Burwood Hwy Belgrave VIC 3160",
    "addr:housenumber":"1645",
    "addr:postcode":"3160",
    "addr:street":"Burwood Hwy",
    "iso:country":"AU",
    "sg:address":"1645 Burwood Hwy",
    "sg:city":"Belgrave",
    "sg:classifiers":[
        {
            "category":"Travel",
            "subcategory":"Hotels & Motels",
            "type":"Entertainment"
        }
    ],
    "sg:phone":"+61 3 9754 2222",
    "sg:postcode":"3160",
    "sg:province":"VIC",
    "sg:tags":[
        "pub"
    ],
    "wof:name":"The Bell Tavern",
    "wof:placetype":"venue"
},
  "geometry": {"coordinates":[145.35336303700001,-37.9097557068],"type":"Point"}
}