{
  "type": "Feature",
  "properties": {
    "addr:full":"352 Station St Lalor VIC 3075",
    "addr:housenumber":"352",
    "addr:postcode":"3075",
    "addr:street":"Station St",
    "iso:country":"AU",
    "sg:address":"352 Station St",
    "sg:city":"Lalor",
    "sg:classifiers":[
        {
            "category":"Banks & Credit Unions",
            "subcategory":"Investment Brokerage",
            "type":"Services"
        }
    ],
    "sg:phone":"+61 1800 653 061",
    "sg:postcode":"3075",
    "sg:province":"VIC",
    "wof:name":"Commonwealth Financial Planning",
    "wof:placetype":"venue"
},
  "geometry": {"coordinates":[145.02059936500001,-37.7632484436],"type":"Point"}
}