{
  "type": "Feature",
  "properties": {
    "addr:full":"Cnr Norman & Dowling Sts Ballarat VIC 3350",
    "addr:postcode":"3350",
    "addr:street":"Cnr",
    "iso:country":"AU",
    "sg:address":"Cnr Norman & Dowling Sts",
    "sg:city":"Ballarat",
    "sg:classifiers":[
        {
            "category":"Retail",
            "subcategory":"Auto Rental",
            "type":"Services"
        }
    ],
    "sg:phone":"+61 13 61 39",
    "sg:postcode":"3350",
    "sg:province":"VIC",
    "sg:tags":[
        "bus",
        "truck"
    ],
    "wof:name":"Thrifty",
    "wof:placetype":"venue"
},
  "geometry": {"coordinates":[143.83952300000001,-37.543709],"type":"Point"}
}