{
  "type": "Feature",
  "properties": {
    "addr:full":"89 Booth St Annandale NSW 2038",
    "addr:housenumber":"89",
    "addr:postcode":"2038",
    "addr:street":"Booth St",
    "iso:country":"AU",
    "sg:address":"89 Booth St",
    "sg:city":"Annandale",
    "sg:classifiers":[
        {
            "category":"Communications",
            "subcategory":"Film & Video Production",
            "type":"Services"
        }
    ],
    "sg:phone":"+61 2 9692 8020",
    "sg:postcode":"2038",
    "sg:province":"NSW",
    "sg:tags":[
        "dvd",
        "library"
    ],
    "wof:name":"Videomanner Pty Ltd",
    "wof:placetype":"venue"
},
  "geometry": {"coordinates":[151.17198181099999,-33.8817214966],"type":"Point"}
}