{
  "type": "Feature",
  "properties": {
    "addr:full":"Shop 31, Castle Towers, Castle St Castle Hill NSW 2154",
    "addr:housenumber":"shop 31",
    "addr:postcode":"2154",
    "addr:street":"Castle Towers Castle St",
    "iso:country":"AU",
    "sg:address":"Shop 31, Castle Towers, Castle St",
    "sg:city":"Castle Hill",
    "sg:classifiers":[
        {
            "category":"Shopping",
            "subcategory":"Clothing, Apparel, & Fashions",
            "type":"Retail Goods"
        }
    ],
    "sg:phone":"+61 2 9634 5750",
    "sg:postcode":"2154",
    "sg:province":"NSW",
    "sg:tags":[
        "lady",
        "wear"
    ],
    "wof:name":"Noni- B-Fashions",
    "wof:placetype":"venue"
},
  "geometry": {"coordinates":[151.00462341299999,-33.7314338684],"type":"Point"}
}