{
  "type": "Feature",
  "properties": {
    "iso:country":"AU",
    "sg:address":"Shop 11, Gallery Level, Brisbane Arcade 160 Queen St",
    "sg:city":"Brisbane",
    "sg:classifiers":[
        {
            "category":"Manufacturing",
            "subcategory":"Jewelry",
            "type":"Manufacturing & Wholesale Goods"
        }
    ],
    "sg:phone":"+61 431 165 325",
    "sg:postcode":"4000",
    "sg:province":"QLD",
    "sg:tags":[
        "designer",
        "jewellery"
    ],
    "wof:name":"Sayangs Touch",
    "wof:placetype":"venue"
},
  "geometry": {"coordinates":[153.02586364699999,-27.4689807892],"type":"Point"}
}