{
  "type": "Feature",
  "properties": {
    "addr:full":"181 Morphett Rd North Plympton SA 5037",
    "addr:housenumber":"181",
    "addr:postcode":"5037",
    "addr:street":"Morphett Rd North",
    "iso:country":"AU",
    "sg:address":"181 Morphett Rd",
    "sg:city":"North Plympton",
    "sg:classifiers":[
        {
            "category":"Utilities",
            "subcategory":"Refuse",
            "type":"Services"
        }
    ],
    "sg:phone":"+61 8 8295 5077",
    "sg:postcode":"5037",
    "sg:province":"SA",
    "sg:tags":[
        "disposal",
        "reduction",
        "waste"
    ],
    "wof:name":"Solo Resource Recovery",
    "wof:placetype":"venue"
},
  "geometry": {"coordinates":[138.536575317,-34.9572639465],"type":"Point"}
}