{
  "type": "Feature",
  "properties": {
    "addr:full":"241b Greenhill Rd Dulwich SA 5065",
    "addr:housenumber":"241b",
    "addr:postcode":"5065",
    "addr:street":"Greenhill Rd",
    "iso:country":"AU",
    "sg:address":"241b Greenhill Rd",
    "sg:city":"Dulwich",
    "sg:classifiers":[
        {
            "category":"Wholesale",
            "subcategory":"Non-durable Goods",
            "type":"Manufacturing & Wholesale Goods"
        }
    ],
    "sg:phone":"+61 8 8364 4447",
    "sg:postcode":"5065",
    "sg:province":"SA",
    "sg:tags":[
        "wholesaler",
        "craft",
        "mfrs"
    ],
    "wof:name":"Designer Tools Aust",
    "wof:placetype":"venue"
},
  "geometry": {"coordinates":[138.62672424300001,-34.9398040771],"type":"Point"}
}