{
  "type": "Feature",
  "properties": {
    "addr:full":"57 Barehaven Ave (Cnr Spencer Rd) Thornlie WA 6108",
    "addr:housenumber":"57",
    "addr:postcode":"6108",
    "addr:street":"Barehaven Ave Cnr Spencer Rd",
    "iso:country":"AU",
    "sg:address":"57 Barehaven Ave (Cnr Spencer Rd)",
    "sg:city":"Thornlie",
    "sg:classifiers":[
        {
            "category":"Health Services",
            "subcategory":"Dentist",
            "type":"Services"
        }
    ],
    "sg:phone":"+61 8 9459 7675",
    "sg:postcode":"6108",
    "sg:province":"WA",
    "wof:name":"Spencer Rd Dental Care",
    "wof:placetype":"venue"
},
  "geometry": {"coordinates":[115.962120056,-32.0569267273],"type":"Point"}
}