{
  "type": "Feature",
  "properties": {
    "addr:full":"571 Grieve Pde Altona North VIC 3025",
    "addr:housenumber":"571",
    "addr:postcode":"3025",
    "addr:street":"Grieve Pde",
    "iso:country":"AU",
    "sg:address":"571 Grieve Pde",
    "sg:city":"Altona North",
    "sg:classifiers":[
        {
            "category":"Transit Center",
            "subcategory":"Freight",
            "type":"Transportation"
        }
    ],
    "sg:phone":"+61 3 9314 4755",
    "sg:postcode":"3025",
    "sg:province":"VIC",
    "sg:tags":[
        "equipment",
        "transport",
        "road",
        "vehicle"
    ],
    "wof:name":"Holmwood Highgate Tankers",
    "wof:placetype":"venue"
},
  "geometry": {"coordinates":[144.829193,-37.827606],"type":"Point"}
}