{
  "type": "Feature",
  "properties": {
    "addr:full":"64 Lime Ave Mildura VIC 3500",
    "addr:housenumber":"64",
    "addr:postcode":"3500",
    "addr:street":"Lime Ave",
    "iso:country":"AU",
    "sg:address":"64 Lime Ave",
    "sg:city":"Mildura",
    "sg:classifiers":[
        {
            "category":"Professional",
            "subcategory":"Accounting & Tax Preparation",
            "type":"Services"
        }
    ],
    "sg:phone":"+61 3 5023 6064",
    "sg:postcode":"3500",
    "sg:province":"VIC",
    "sg:tags":[
        "consultant",
        "taxation"
    ],
    "wof:name":"H&R Block",
    "wof:placetype":"venue"
},
  "geometry": {"coordinates":[142.15992736800001,-34.1840400696],"type":"Point"}
}