{
  "type": "Feature",
  "properties": {
    "addr:full":"350 Bishop Rd Beachmere QLD 4510",
    "addr:housenumber":"350",
    "addr:postcode":"4510",
    "addr:street":"Bishop Rd",
    "iso:country":"AU",
    "sg:address":"350 Bishop Rd",
    "sg:city":"Beachmere",
    "sg:classifiers":[
        {
            "category":"Home & Garden",
            "subcategory":"Garden Supply",
            "type":"Retail Goods"
        }
    ],
    "sg:phone":"+61 7 3211 3939",
    "sg:postcode":"4510",
    "sg:province":"QLD",
    "sg:tags":[
        "turf",
        "lawn"
    ],
    "wof:name":"Princess Turf",
    "wof:placetype":"venue"
},
  "geometry": {"coordinates":[153.06660500000001,-27.093452],"type":"Point"}
}