{
  "type": "Feature",
  "properties": {
    "addr:full":"1297 Pacific Hwy Turramurra NSW 2074",
    "addr:housenumber":"1297",
    "addr:postcode":"2074",
    "addr:street":"Pacific Hwy",
    "iso:country":"AU",
    "sg:address":"1297 Pacific Hwy",
    "sg:city":"Turramurra",
    "sg:classifiers":[
        {
            "category":"Health Services",
            "subcategory":"Dentist",
            "type":"Services"
        }
    ],
    "sg:phone":"+61 2 9488 9034",
    "sg:postcode":"2074",
    "sg:province":"NSW",
    "wof:name":"Abbott Michael",
    "wof:placetype":"venue"
},
  "geometry": {"coordinates":[151.12864685100001,-33.733291626],"type":"Point"}
}