{
  "type": "Feature",
  "properties": {
    "iso:country":"AU",
    "sg:address":"21 Dent St",
    "sg:city":"Toowoomba",
    "sg:classifiers":[
        {
            "category":"Banks & Credit Unions",
            "subcategory":"Bureau De Change",
            "type":"Services"
        }
    ],
    "sg:phone":"+61 7 4632 0055",
    "sg:postcode":"4350",
    "sg:province":"QLD",
    "sg:tags":[
        "equipment",
        "heat",
        "exchange"
    ],
    "wof:name":"Teralba Industries Fluid Process Equipment",
    "wof:placetype":"venue"
},
  "geometry": {"coordinates":[151.94923399999999,-27.562958],"type":"Point"}
}