{
  "type": "Feature",
  "properties": {
    "addr:full":"63- 65 Flinders St Darlinghurst NSW 2010",
    "addr:housenumber":"65",
    "addr:postcode":"2010",
    "addr:street":"Flinders St",
    "iso:country":"AU",
    "sg:address":"63- 65 Flinders St",
    "sg:city":"Darlinghurst",
    "sg:classifiers":[
        {
            "category":"Travel",
            "subcategory":"Hotels & Motels",
            "type":"Entertainment"
        }
    ],
    "sg:phone":"+61 2 9356 3622",
    "sg:postcode":"2010",
    "sg:province":"NSW",
    "sg:tags":[
        "pub"
    ],
    "wof:name":"Flinders Hotel Darlinghurst",
    "wof:placetype":"venue"
},
  "geometry": {"coordinates":[151.21722412099999,-33.88306427],"type":"Point"}
}