{
  "type": "Feature",
  "properties": {
    "iso:country":"AU",
    "sg:address":"Bolton St",
    "sg:city":"Eltham",
    "sg:classifiers":[
        {
            "category":"Food & Beverages",
            "subcategory":"Bakery",
            "type":"Retail Goods"
        }
    ],
    "sg:phone":"+61 3 9439 6837",
    "sg:postcode":"3095",
    "sg:province":"VIC",
    "sg:tags":[
        "baker"
    ],
    "wof:name":"Bolton St Hot Bread Kitchen",
    "wof:placetype":"venue"
},
  "geometry": {"coordinates":[145.13783264200001,-37.7172546387],"type":"Point"}
}