{
  "type": "Feature",
  "properties": {
    "iso:country":"AU",
    "sg:address":"8 Clay St",
    "sg:city":"West Ipswich",
    "sg:classifiers":[
        {
            "category":"Retail",
            "subcategory":"Auto Repair",
            "type":"Services"
        }
    ],
    "sg:phone":"+61 7 3282 7047",
    "sg:postcode":"4305",
    "sg:province":"QLD",
    "sg:tags":[
        "body",
        "builder",
        "motor"
    ],
    "wof:name":"Wizard Fabrications & Race Products",
    "wof:placetype":"venue"
},
  "geometry": {"coordinates":[152.75012207,-27.6170864105],"type":"Point"}
}