{
  "type": "Feature",
  "properties": {
    "addr:full":"107- 109 Kent Rd Pascoe Vale VIC 3044",
    "addr:housenumber":"109",
    "addr:postcode":"3044",
    "addr:street":"Kent Rd",
    "iso:country":"AU",
    "sg:address":"107- 109 Kent Rd",
    "sg:city":"Pascoe Vale",
    "sg:classifiers":[
        {
            "category":"Retail",
            "subcategory":"Auto Repair",
            "type":"Services"
        }
    ],
    "sg:phone":"+61 3 9350 2977",
    "sg:postcode":"3044",
    "sg:province":"VIC",
    "sg:tags":[
        "repairer",
        "motor",
        "engineer"
    ],
    "wof:name":"Prime Automotive",
    "wof:placetype":"venue"
},
  "geometry": {"coordinates":[144.940551758,-37.7202606201],"type":"Point"}
}