{
  "type": "Feature",
  "properties": {
    "addr:full":"168 Redland Bay Rd Capalaba QLD 4157",
    "addr:housenumber":"168",
    "addr:postcode":"4157",
    "addr:street":"Redland Bay Rd",
    "iso:country":"AU",
    "sg:address":"168 Redland Bay Rd",
    "sg:city":"Capalaba",
    "sg:classifiers":[
        {
            "category":"Manufacturing",
            "subcategory":"Textiles",
            "type":"Manufacturing & Wholesale Goods"
        }
    ],
    "sg:phone":"+61 7 3245 5775",
    "sg:postcode":"4157",
    "sg:province":"QLD",
    "sg:tags":[
        "knitted",
        "woven",
        "fabric"
    ],
    "wof:name":"Bargain Box Fabric Stores",
    "wof:placetype":"venue"
},
  "geometry": {"coordinates":[153.201080322,-27.5341873169],"type":"Point"}
}