{
  "type": "Feature",
  "properties": {
    "iso:country":"AU",
    "sg:address":"Shp1a/ 2 James St",
    "sg:city":"Salisbury",
    "sg:classifiers":[
        {
            "category":"Fast Food",
            "type":"Food & Drink"
        }
    ],
    "sg:phone":"+61 8 8250 9335",
    "sg:postcode":"5108",
    "sg:province":"SA",
    "sg:tags":[
        "away",
        "take"
    ],
    "wof:name":"Lb Vietnamese Food Dine In & Takeaway",
    "wof:placetype":"venue"
},
  "geometry": {"coordinates":[138.64422607399999,-34.7619094849],"type":"Point"}
}