{
  "type": "Feature",
  "properties": {
    "addr:full":"32 St Georges Rd Fitzroy VIC 3065",
    "addr:housenumber":"32",
    "addr:postcode":"3065",
    "addr:street":"St Georges Rd",
    "iso:country":"AU",
    "sg:address":"32 St Georges Rd",
    "sg:city":"Fitzroy",
    "sg:classifiers":[
        {
            "category":"Travel",
            "subcategory":"Hotels & Motels",
            "type":"Entertainment"
        }
    ],
    "sg:phone":"+61 3 9482 6484",
    "sg:postcode":"3065",
    "sg:province":"VIC",
    "sg:tags":[
        "pub"
    ],
    "wof:name":"North Fitzroy Star",
    "wof:placetype":"venue"
},
  "geometry": {"coordinates":[144.990234375,-37.7758560181],"type":"Point"}
}