{
  "type": "Feature",
  "properties": {
    "iso:country":"AU",
    "sg:address":"56 St Johns Ave",
    "sg:city":"Gordon",
    "sg:classifiers":[
        {
            "category":"Health Services",
            "subcategory":"Doctor",
            "type":"Services"
        }
    ],
    "sg:phone":"+61 2 9498 3553",
    "sg:postcode":"2072",
    "sg:province":"NSW",
    "sg:tags":[
        "medical",
        "practitioner"
    ],
    "wof:name":"Hooper Michael J",
    "wof:placetype":"venue"
},
  "geometry": {"coordinates":[151.14785766599999,-33.7586250305],"type":"Point"}
}