{
  "type": "Feature",
  "properties": {
    "addr:full":"16 Victoria St Brunswick East VIC 3057",
    "addr:housenumber":"16",
    "addr:postcode":"3057",
    "addr:street":"Victoria St",
    "iso:country":"AU",
    "sg:address":"16 Victoria St",
    "sg:city":"Brunswick East",
    "sg:classifiers":[
        {
            "category":"Retail",
            "subcategory":"Auto Repair",
            "type":"Services"
        }
    ],
    "sg:phone":"+61 3 9380 1212",
    "sg:postcode":"3057",
    "sg:province":"VIC",
    "sg:tags":[
        "electrical"
    ],
    "wof:name":"Expert Auto Electrical",
    "wof:placetype":"venue"
},
  "geometry": {"coordinates":[144.98272705100001,-37.7693367004],"type":"Point"}
}