{
  "type": "Feature",
  "properties": {
    "iso:country":"AU",
    "sg:address":"Shop 14, 564 The Esp",
    "sg:city":"Urangan",
    "sg:classifiers":[
        {
            "category":"Personal",
            "subcategory":"Beauty Salon",
            "type":"Services"
        }
    ],
    "sg:phone":"+61 7 4125 1377",
    "sg:postcode":"4655",
    "sg:province":"QLD",
    "sg:tags":[
        "hairdresser"
    ],
    "wof:name":"Kristie's Hairworx",
    "wof:placetype":"venue"
},
  "geometry": {"coordinates":[152.89790300000001,-25.285044],"type":"Point"}
}