{
  "type": "Feature",
  "properties": {
    "addr:full":"20 Stuart St Armadale VIC 3143",
    "addr:housenumber":"20",
    "addr:postcode":"3143",
    "addr:street":"Stuart St",
    "iso:country":"AU",
    "sg:address":"20 Stuart St",
    "sg:city":"Armadale",
    "sg:classifiers":[
        {
            "category":"Health Services",
            "subcategory":"Health Practitioner",
            "type":"Services"
        }
    ],
    "sg:phone":"+61 3 9509 1649",
    "sg:postcode":"3143",
    "sg:province":"VIC",
    "sg:tags":[
        "psychologist"
    ],
    "wof:name":"Moran Frances M Dr",
    "wof:placetype":"venue"
},
  "geometry": {"coordinates":[145.024536133,-37.8581466675],"type":"Point"}
}