{
  "type": "Feature",
  "properties": {
    "addr:full":"7 Florence St Hendon SA 5014",
    "addr:housenumber":"7",
    "addr:postcode":"5014",
    "addr:street":"Florence St",
    "iso:country":"AU",
    "sg:address":"7 Florence St",
    "sg:city":"Hendon",
    "sg:classifiers":[
        {
            "category":"Retail",
            "subcategory":"Storage",
            "type":"Services"
        }
    ],
    "sg:phone":"+61 8 8447 8673",
    "sg:postcode":"5014",
    "sg:province":"SA",
    "wof:name":"Hendon Self Storage",
    "wof:placetype":"venue"
},
  "geometry": {"coordinates":[138.51309204099999,-34.8704566956],"type":"Point"}
}