{
  "type": "Feature",
  "properties": {
    "addr:full":"310 Ipswich Rd Annerley QLD 4103",
    "addr:housenumber":"310",
    "addr:postcode":"4103",
    "addr:street":"Ipswich Rd",
    "iso:country":"AU",
    "sg:address":"310 Ipswich Rd",
    "sg:city":"Annerley",
    "sg:classifiers":[
        {
            "category":"Food & Beverages",
            "subcategory":"Supermarket",
            "type":"Retail Goods"
        }
    ],
    "sg:phone":"+61 7 3891 1791",
    "sg:postcode":"4103",
    "sg:province":"QLD",
    "sg:tags":[
        "grocery",
        "store"
    ],
    "wof:name":"Deli Oz",
    "wof:placetype":"venue"
},
  "geometry": {"coordinates":[153.034622192,-27.5025920868],"type":"Point"}
}