{
  "type": "Feature",
  "properties": {
    "addr:full":"20 Westmoreland St St Albans Park VIC 3219",
    "addr:housenumber":"20",
    "addr:postcode":"3219",
    "addr:street":"Westmoreland St",
    "iso:country":"AU",
    "sg:address":"20 Westmoreland St",
    "sg:city":"St Albans Park",
    "sg:classifiers":[
        {
            "category":"Home & Garden",
            "subcategory":"Hardware",
            "type":"Retail Goods"
        }
    ],
    "sg:phone":"+61 418 525 107",
    "sg:postcode":"3219",
    "sg:province":"VIC",
    "sg:tags":[
        "compressor",
        "air"
    ],
    "wof:name":"Geelong Air & Construction Machine Repair",
    "wof:placetype":"venue"
},
  "geometry": {"coordinates":[144.384368897,-38.1825523376],"type":"Point"}
}