{
  "type": "Feature",
  "properties": {
    "addr:full":"7 Pierre Rd Modbury SA 5092",
    "addr:housenumber":"7",
    "addr:postcode":"5092",
    "addr:street":"Pierre Rd",
    "iso:country":"AU",
    "sg:address":"7 Pierre Rd",
    "sg:city":"Modbury",
    "sg:classifiers":[
        {
            "category":"Personal",
            "subcategory":"Beauty Salon",
            "type":"Services"
        }
    ],
    "sg:phone":"+61 8 8263 1175",
    "sg:postcode":"5092",
    "sg:province":"SA",
    "wof:name":"Nail Creations By Raelene",
    "wof:placetype":"venue"
},
  "geometry": {"coordinates":[138.674758911,-34.8420410156],"type":"Point"}
}