{
  "type": "Feature",
  "properties": {
    "iso:country":"AU",
    "sg:address":"212 College Rd",
    "sg:city":"Karana Downs",
    "sg:classifiers":[
        {
            "category":"Personal",
            "subcategory":"Massage",
            "type":"Services"
        }
    ],
    "sg:phone":"+61 422 438 101",
    "sg:postcode":"4306",
    "sg:province":"QLD",
    "sg:tags":[
        "therapy"
    ],
    "wof:name":"Lindsay Hodgson",
    "wof:placetype":"venue"
},
  "geometry": {"coordinates":[152.831497192,-27.543888092],"type":"Point"}
}