{
  "type": "Feature",
  "properties": {
    "addr:full":"Bristol St Merrylands NSW 2160",
    "addr:postcode":"2160",
    "addr:street":"Bristol St",
    "iso:country":"AU",
    "sg:address":"Bristol St",
    "sg:city":"Merrylands",
    "sg:classifiers":[
        {
            "category":"Education",
            "subcategory":"School",
            "type":"Public Place"
        }
    ],
    "sg:phone":"+61 2 9632 9401",
    "sg:postcode":"2160",
    "sg:province":"NSW",
    "sg:tags":[
        "state",
        "-",
        "nsw"
    ],
    "wof:name":"Merrylands High School",
    "wof:placetype":"venue"
},
  "geometry": {"coordinates":[150.97381591800001,-33.8428649902],"type":"Point"}
}