{
  "type": "Feature",
  "properties": {
    "iso:country":"AU",
    "sg:address":"1 Elliott Ave",
    "sg:city":"Belair",
    "sg:classifiers":[
        {
            "category":"Education",
            "subcategory":"Special Training",
            "type":"Public Place"
        }
    ],
    "sg:phone":"+61 8 8278 3046",
    "sg:postcode":"5052",
    "sg:province":"SA",
    "sg:tags":[
        "school",
        "art"
    ],
    "wof:name":"Lesley Jorgensen Studio Of Arts",
    "wof:placetype":"venue"
},
  "geometry": {"coordinates":[138.622849,-34.99968],"type":"Point"}
}