{
  "type": "Feature",
  "properties": {
    "iso:country":"AU",
    "sg:address":"86 Bass Hwy",
    "sg:city":"Cooee",
    "sg:classifiers":[
        {
            "category":"Building & Trades",
            "subcategory":"Locksmith",
            "type":"Services"
        }
    ],
    "sg:phone":"+61 3 6431 4388",
    "sg:postcode":"7320",
    "sg:province":"TAS",
    "sg:tags":[
        "equipment",
        "operating",
        "door",
        "gate"
    ],
    "wof:name":"Doors & More",
    "wof:placetype":"venue"
},
  "geometry": {"coordinates":[145.873428,-41.040279],"type":"Point"}
}