{
  "type": "Feature",
  "properties": {
    "addr:full":"7 Adventure Pl Taren Point NSW 2229",
    "addr:housenumber":"7",
    "addr:postcode":"2229",
    "addr:street":"Adventure Pl",
    "iso:country":"AU",
    "sg:address":"7 Adventure Pl",
    "sg:city":"Taren Point",
    "sg:classifiers":[
        {
            "category":"Wholesale",
            "subcategory":"Painting Supplies",
            "type":"Manufacturing & Wholesale Goods"
        }
    ],
    "sg:phone":"+61 1800 818 904",
    "sg:postcode":"2229",
    "sg:province":"NSW",
    "sg:tags":[
        "painter"
    ],
    "wof:name":"C & A Brushware",
    "wof:placetype":"venue"
},
  "geometry": {"coordinates":[151.13043212900001,-34.0287399292],"type":"Point"}
}