{
  "type": "Feature",
  "properties": {
    "addr:full":"99 High St Avoca VIC 3467",
    "addr:housenumber":"99",
    "addr:postcode":"3467",
    "addr:street":"High St",
    "iso:country":"AU",
    "sg:address":"99 High St",
    "sg:city":"Avoca",
    "sg:classifiers":[
        {
            "category":"Autos & Motor Vehicles",
            "subcategory":"Fuel & Gas Station",
            "type":"Retail Goods"
        }
    ],
    "sg:phone":"+61 3 5465 3098",
    "sg:postcode":"3467",
    "sg:province":"VIC",
    "wof:name":"Gollops Garage Pty Ltd",
    "wof:placetype":"venue"
},
  "geometry": {"coordinates":[143.47413635300001,-37.0901947021],"type":"Point"}
}