{
  "type": "Feature",
  "properties": {
    "addr:full":"15 Lockwood Rd Shepparton VIC 3630",
    "addr:housenumber":"15",
    "addr:postcode":"3630",
    "addr:street":"Lockwood Rd",
    "iso:country":"AU",
    "sg:address":"15 Lockwood Rd",
    "sg:city":"Shepparton",
    "sg:classifiers":[
        {
            "category":"Transit Center",
            "subcategory":"Freight",
            "type":"Transportation"
        }
    ],
    "sg:phone":"+61 3 5822 2422",
    "sg:postcode":"3630",
    "sg:province":"VIC",
    "sg:tags":[
        "forklift",
        "truck"
    ],
    "wof:name":"Hsa Forklifts",
    "wof:placetype":"venue"
},
  "geometry": {"coordinates":[145.41644287099999,-36.379283905],"type":"Point"}
}