{
  "type": "Feature",
  "properties": {
    "iso:country":"AU",
    "sg:address":"Woodville House 57-59 Elizabeth St",
    "sg:city":"Moss Vale",
    "sg:classifiers":[
        {
            "category":"Health Services",
            "subcategory":"Dentist",
            "type":"Services"
        }
    ],
    "sg:phone":"+61 2 4869 3111",
    "sg:postcode":"2577",
    "sg:province":"NSW",
    "wof:name":"Dr Patrick J. Meaney & Associates",
    "wof:placetype":"venue"
},
  "geometry": {"coordinates":[150.37518310600001,-34.5479621887],"type":"Point"}
}