{
  "type": "Feature",
  "properties": {
    "addr:full":"Suite 211, 151 Hawkesbury Rd Westmead NSW 2145",
    "addr:housenumber":"151",
    "addr:postcode":"2145",
    "addr:street":"Hawkesbury Rd",
    "iso:country":"AU",
    "sg:address":"Suite 211, 151 Hawkesbury Rd",
    "sg:city":"Westmead",
    "sg:classifiers":[
        {
            "category":"Health Services",
            "subcategory":"Health Practitioner",
            "type":"Services"
        }
    ],
    "sg:phone":"+61 2 9891 1511",
    "sg:postcode":"2145",
    "sg:province":"NSW",
    "sg:tags":[
        "dietitian"
    ],
    "wof:name":"Liz Beavis",
    "wof:placetype":"venue"
},
  "geometry": {"coordinates":[150.98756408700001,-33.8075561523],"type":"Point"}
}