{
  "type": "Feature",
  "properties": {
    "addr:full":"596 Sydney Rd Coburg VIC 3058",
    "addr:housenumber":"596",
    "addr:postcode":"3058",
    "addr:street":"Sydney Rd",
    "iso:country":"AU",
    "sg:address":"596 Sydney Rd",
    "sg:city":"Coburg",
    "sg:classifiers":[
        {
            "category":"Retail",
            "subcategory":"Auto Repair",
            "type":"Services"
        }
    ],
    "sg:phone":"+61 3 9354 3993",
    "sg:postcode":"3058",
    "sg:province":"VIC",
    "sg:tags":[
        "repairer",
        "motor",
        "engineer"
    ],
    "wof:name":"Coburg Car Care",
    "wof:placetype":"venue"
},
  "geometry": {"coordinates":[144.96690368599999,-37.737247467],"type":"Point"}
}