{
  "type": "Feature",
  "properties": {
    "addr:full":"Level 4/Ste 13, 150 Albert Rd South Melbourne VIC 3205",
    "addr:housenumber":"150",
    "addr:postcode":"3205",
    "addr:street":"/;Albert Rd",
    "iso:country":"AU",
    "sg:address":"Level 4/Ste 13, 150 Albert Rd",
    "sg:city":"South Melbourne",
    "sg:classifiers":[
        {
            "category":"Education",
            "subcategory":"Special Training",
            "type":"Public Place"
        }
    ],
    "sg:phone":"+61 1300 733 466",
    "sg:postcode":"3205",
    "sg:province":"VIC",
    "sg:tags":[
        "development"
    ],
    "wof:name":"Matrix Training Group",
    "wof:placetype":"venue"
},
  "geometry": {"coordinates":[144.96923799999999,-37.836338],"type":"Point"}
}