{
  "type": "Feature",
  "properties": {
    "addr:full":"15 Jusfrute Drv Gosford West NSW 2250",
    "addr:housenumber":"15",
    "addr:postcode":"2250",
    "addr:street":"Jusfrute Drv",
    "iso:country":"AU",
    "sg:address":"15 Jusfrute Drv",
    "sg:city":"Gosford West",
    "sg:classifiers":[
        {
            "category":"Retail",
            "subcategory":"Auto Repair",
            "type":"Services"
        }
    ],
    "sg:phone":"+61 2 4323 9055",
    "sg:postcode":"2250",
    "sg:province":"NSW",
    "sg:tags":[
        "body",
        "builder",
        "motor"
    ],
    "wof:name":"Central Coast Motor Bodies",
    "wof:placetype":"venue"
},
  "geometry": {"coordinates":[151.3125,-33.4291343689],"type":"Point"}
}