{
  "type": "Feature",
  "properties": {
    "addr:full":"3 Lazarus St Bendigo VIC 3550",
    "addr:housenumber":"3",
    "addr:postcode":"3550",
    "addr:street":"Lazarus St",
    "iso:country":"AU",
    "sg:address":"3 Lazarus St",
    "sg:city":"Bendigo",
    "sg:classifiers":[
        {
            "category":"Retail",
            "subcategory":"Repair Shop",
            "type":"Services"
        }
    ],
    "sg:phone":"+61 3 5441 2469",
    "sg:postcode":"3550",
    "sg:province":"VIC",
    "sg:tags":[
        "upholsterer"
    ],
    "wof:name":"Bendigo Upholstery",
    "wof:placetype":"venue"
},
  "geometry": {"coordinates":[144.25273132300001,-36.7586364746],"type":"Point"}
}