{
  "type": "Feature",
  "properties": {
    "addr:full":"730 Old Cleveland Rd Wellington Point QLD 4160",
    "addr:housenumber":"730",
    "addr:postcode":"4160",
    "addr:street":"Old Cleveland Rd",
    "iso:country":"AU",
    "sg:address":"730 Old Cleveland Rd",
    "sg:city":"Wellington Point",
    "sg:classifiers":[
        {
            "category":"Banks & Credit Unions",
            "subcategory":"Investment Brokerage",
            "type":"Services"
        }
    ],
    "sg:phone":"+61 7 3393 4444",
    "sg:postcode":"4160",
    "sg:province":"QLD",
    "sg:tags":[
        "care",
        "day",
        "family",
        "child"
    ],
    "wof:name":"Bayside Family Day Care",
    "wof:placetype":"venue"
},
  "geometry": {"coordinates":[153.241622925,-27.5097923279],"type":"Point"}
}