{
  "type": "Feature",
  "properties": {
    "addr:full":"Shp2/ 100 Kinghorne St Nowra NSW 2541",
    "addr:postcode":"2541",
    "addr:street":"Kinghorne St",
    "iso:country":"AU",
    "sg:address":"Shp2/ 100 Kinghorne St",
    "sg:city":"Nowra",
    "sg:classifiers":[
        {
            "category":"Fast Food",
            "type":"Food & Drink"
        }
    ],
    "sg:phone":"+61 2 4422 9868",
    "sg:postcode":"2541",
    "sg:province":"NSW",
    "sg:tags":[
        "away",
        "take"
    ],
    "wof:name":"Country Noodles",
    "wof:placetype":"venue"
},
  "geometry": {"coordinates":[150.60284423799999,-34.876285553],"type":"Point"}
}