{
  "type": "Feature",
  "properties": {
    "addr:full":"111 Green St Lockhart NSW 2656",
    "addr:housenumber":"111",
    "addr:postcode":"2656",
    "addr:street":"Green St",
    "iso:country":"AU",
    "sg:address":"111 Green St",
    "sg:city":"Lockhart",
    "sg:classifiers":[
        {
            "category":"Travel",
            "subcategory":"Hotels & Motels",
            "type":"Entertainment"
        }
    ],
    "sg:phone":"+61 2 6920 5109",
    "sg:postcode":"2656",
    "sg:province":"NSW",
    "sg:tags":[
        "accommodation"
    ],
    "wof:name":"Commercial Hotel",
    "wof:placetype":"venue"
},
  "geometry": {"coordinates":[146.71810913100001,-35.2211608887],"type":"Point"}
}