{
  "type": "Feature",
  "properties": {
    "addr:full":"74 Stockwell Rd Angaston SA 5353",
    "addr:housenumber":"74",
    "addr:postcode":"5353",
    "addr:street":"Stockwell Rd",
    "iso:country":"AU",
    "sg:address":"74 Stockwell Rd",
    "sg:city":"Angaston",
    "sg:classifiers":[
        {
            "category":"Professional",
            "type":"Services"
        }
    ],
    "sg:phone":"+61 8 8564 3022",
    "sg:postcode":"5353",
    "sg:province":"SA",
    "sg:tags":[
        "courier"
    ],
    "wof:name":"Barossa Valley Coaches",
    "wof:placetype":"venue"
},
  "geometry": {"coordinates":[139.02835082999999,-34.4912986755],"type":"Point"}
}