{
  "type": "Feature",
  "properties": {
    "addr:full":"Cnr Richmond & Woodcroft Rds Woodcroft Plz Doonside NSW 2767",
    "addr:postcode":"2767",
    "addr:street":"Cnr;Woodcroft Plz",
    "iso:country":"AU",
    "sg:address":"Cnr Richmond & Woodcroft Rds",
    "sg:city":"Woodcroft Plz Doonside",
    "sg:classifiers":[
        {
            "category":"Fast Food",
            "type":"Food & Drink"
        }
    ],
    "sg:phone":"+61 2 9481 1111",
    "sg:postcode":"2767",
    "sg:province":"NSW",
    "sg:tags":[
        "away",
        "take"
    ],
    "wof:name":"Pizza Hut",
    "wof:placetype":"venue"
},
  "geometry": {"coordinates":[150.88249206500001,-33.7489852905],"type":"Point"}
}