{
  "type": "Feature",
  "properties": {
    "addr:full":"11 Grange Rd Cheltenham VIC 3192",
    "addr:housenumber":"11",
    "addr:postcode":"3192",
    "addr:street":"Grange Rd",
    "iso:country":"AU",
    "sg:address":"11 Grange Rd",
    "sg:city":"Cheltenham",
    "sg:classifiers":[
        {
            "category":"Wholesale",
            "subcategory":"Metals & Minerals",
            "type":"Manufacturing & Wholesale Goods"
        }
    ],
    "sg:phone":"+61 3 9585 5400",
    "sg:postcode":"3192",
    "sg:province":"VIC",
    "sg:tags":[
        "steel",
        "stainless",
        "product",
        "equipment"
    ],
    "wof:name":"Alfa Laval Australia",
    "wof:placetype":"venue"
},
  "geometry": {"coordinates":[145.086135864,-37.9754257202],"type":"Point"}
}