{
  "type": "Feature",
  "properties": {
    "addr:full":"Riverside Drv Kholo QLD 4306",
    "addr:postcode":"4306",
    "addr:street":"Riverside Drv",
    "iso:country":"AU",
    "sg:address":"Riverside Drv",
    "sg:city":"Kholo",
    "sg:classifiers":[
        {
            "category":"Building & Trades",
            "subcategory":"Construction",
            "type":"Services"
        }
    ],
    "sg:phone":"+61 7 3201 8527",
    "sg:postcode":"4306",
    "sg:province":"QLD",
    "sg:tags":[
        "contractor"
    ],
    "wof:name":"Williams I M & J M",
    "wof:placetype":"venue"
},
  "geometry": {"coordinates":[152.751754761,-27.5205211639],"type":"Point"}
}