{
  "type": "Feature",
  "properties": {
    "iso:country":"AU",
    "sg:address":"U2/ 258 Newcastle St",
    "sg:city":"Perth",
    "sg:classifiers":[
        {
            "category":"Personal",
            "subcategory":"Beauty Salon",
            "type":"Services"
        }
    ],
    "sg:phone":"+61 8 9328 4848",
    "sg:postcode":"6000",
    "sg:province":"WA",
    "wof:name":"MC Beauty",
    "wof:placetype":"venue"
},
  "geometry": {"coordinates":[115.858482361,-31.9449462891],"type":"Point"}
}