{
  "type": "Feature",
  "properties": {
    "addr:full":"2 Caldermeade Rd Corio VIC 3214",
    "addr:housenumber":"2",
    "addr:postcode":"3214",
    "addr:street":"Caldermeade Rd",
    "iso:country":"AU",
    "sg:address":"2 Caldermeade Rd",
    "sg:city":"Corio",
    "sg:classifiers":[
        {
            "category":"Professional",
            "subcategory":"Computer Services",
            "type":"Services"
        }
    ],
    "sg:phone":"+61 417 310 356",
    "sg:postcode":"3214",
    "sg:province":"VIC",
    "sg:tags":[
        "tele-communications",
        "consultant"
    ],
    "wof:name":"N B G Communications",
    "wof:placetype":"venue"
},
  "geometry": {"coordinates":[144.34396362300001,-38.0707015991],"type":"Point"}
}