{
  "type": "Feature",
  "properties": {
    "addr:full":"10 Rook St Lilydale VIC 3140",
    "addr:housenumber":"10",
    "addr:postcode":"3140",
    "addr:street":"Rook St",
    "iso:country":"AU",
    "sg:address":"10 Rook St",
    "sg:city":"Lilydale",
    "sg:classifiers":[
        {
            "category":"Building & Trades",
            "subcategory":"Construction",
            "type":"Services"
        }
    ],
    "sg:phone":"+61 403 370 587",
    "sg:postcode":"3140",
    "sg:province":"VIC",
    "sg:tags":[
        "concrete",
        "contractor"
    ],
    "wof:name":"JSM & B Concrete",
    "wof:placetype":"venue"
},
  "geometry": {"coordinates":[145.01968383799999,-37.8158111572],"type":"Point"}
}