{
  "type": "Feature",
  "properties": {
    "addr:full":"36 Lancelin Drv Mermaid Waters QLD 4218",
    "addr:housenumber":"36",
    "addr:postcode":"4218",
    "addr:street":"Lancelin Drv",
    "iso:country":"AU",
    "sg:address":"36 Lancelin Drv",
    "sg:city":"Mermaid Waters",
    "sg:classifiers":[
        {
            "category":"Building & Trades",
            "subcategory":"Construction",
            "type":"Services"
        }
    ],
    "sg:phone":"+61 413 749 136",
    "sg:postcode":"4218",
    "sg:province":"QLD",
    "sg:tags":[
        "concrete",
        "contractor"
    ],
    "wof:name":"B R & R J Gray",
    "wof:placetype":"venue"
},
  "geometry": {"coordinates":[153.420654297,-28.0654907227],"type":"Point"}
}