{
  "type": "Feature",
  "properties": {
    "addr:full":"Shop 2/ 25 Harbour Rd North Mackay QLD 4740",
    "addr:housenumber":"shop 2 / 25",
    "addr:postcode":"4740",
    "addr:street":"Harbour Rd",
    "iso:country":"AU",
    "sg:address":"Shop 2/ 25 Harbour Rd",
    "sg:city":"North Mackay",
    "sg:classifiers":[
        {
            "category":"Food & Beverages",
            "subcategory":"Fruits & Vegetables",
            "type":"Retail Goods"
        }
    ],
    "sg:phone":"+61 7 4951 2033",
    "sg:postcode":"4740",
    "sg:province":"QLD",
    "sg:tags":[
        "greengrocer",
        "fruiterer"
    ],
    "wof:name":"Thommo`s Big Banana Pty Ltd",
    "wof:placetype":"venue"
},
  "geometry": {"coordinates":[149.191833,-21.125122],"type":"Point"}
}