{
  "type": "Feature",
  "properties": {
    "iso:country":"AU",
    "sg:address":"Belyando Ave",
    "sg:city":"Moranbah",
    "sg:classifiers":[
        {
            "category":"Education",
            "subcategory":"School",
            "type":"Public Place"
        }
    ],
    "sg:phone":"+61 7 4949 2777",
    "sg:postcode":"4744",
    "sg:province":"QLD",
    "sg:tags":[
        "state",
        "except",
        "nsw"
    ],
    "wof:name":"Moranbah Primary School",
    "wof:placetype":"venue"
},
  "geometry": {"coordinates":[148.04861450199999,-21.9986724854],"type":"Point"}
}