{
  "type": "Feature",
  "properties": {
    "addr:full":"81 McLennans Rd Plenty VIC 3090",
    "addr:housenumber":"81",
    "addr:postcode":"3090",
    "addr:street":"Mclennans Rd",
    "iso:country":"AU",
    "sg:address":"81 McLennans Rd",
    "sg:city":"Plenty",
    "sg:classifiers":[
        {
            "category":"Health Services",
            "subcategory":"Doctor",
            "type":"Services"
        }
    ],
    "sg:phone":"+61 412 606 605",
    "sg:postcode":"3090",
    "sg:province":"VIC",
    "sg:tags":[
        "occupational",
        "safety"
    ],
    "wof:name":"Victorian Height Safety Services",
    "wof:placetype":"venue"
},
  "geometry": {"coordinates":[145.114746094,-37.6715393066],"type":"Point"}
}