{
  "type": "Feature",
  "properties": {
    "addr:full":"Wighton St Margate QLD 4019",
    "addr:postcode":"4019",
    "addr:street":"Wighton St",
    "iso:country":"AU",
    "sg:address":"Wighton St",
    "sg:city":"Margate",
    "sg:classifiers":[
        {
            "category":"Retail",
            "subcategory":"Laundry & Dry Cleaning",
            "type":"Services"
        }
    ],
    "sg:phone":"+61 7 3283 2357",
    "sg:postcode":"4019",
    "sg:province":"QLD",
    "wof:name":"Ellys Laundrette",
    "wof:placetype":"venue"
},
  "geometry": {"coordinates":[153.107818603,-27.2432003021],"type":"Point"}
}