{
  "type": "Feature",
  "properties": {
    "addr:full":"46 Turners Gully Rd Clarendon SA 5157",
    "addr:housenumber":"46",
    "addr:postcode":"5157",
    "addr:street":"Turners Gully Rd",
    "iso:country":"AU",
    "sg:address":"46 Turners Gully Rd",
    "sg:city":"Clarendon",
    "sg:classifiers":[
        {
            "category":"Personal",
            "subcategory":"Massage",
            "type":"Services"
        }
    ],
    "sg:phone":"+61 8 8383 6232",
    "sg:postcode":"5157",
    "sg:province":"SA",
    "sg:tags":[
        "therapy"
    ],
    "wof:name":"Whetton Pete",
    "wof:placetype":"venue"
},
  "geometry": {"coordinates":[138.62327575699999,-35.1027603149],"type":"Point"}
}