{
  "type": "Feature",
  "properties": {
    "addr:full":"1/ 364 Brighton Rd Hove SA 5048",
    "addr:housenumber":"/ 364",
    "addr:postcode":"5048",
    "addr:street":"Brighton Rd",
    "iso:country":"AU",
    "sg:address":"1/ 364 Brighton Rd",
    "sg:city":"Hove",
    "sg:classifiers":[
        {
            "category":"Wholesale",
            "subcategory":"Furniture",
            "type":"Manufacturing & Wholesale Goods"
        }
    ],
    "sg:phone":"+61 8 8358 1855",
    "sg:postcode":"5048",
    "sg:province":"SA",
    "sg:tags":[
        "wholesaler",
        "mfrs"
    ],
    "wof:name":"Agostino Hector Furniture",
    "wof:placetype":"venue"
},
  "geometry": {"coordinates":[138.52259799999999,-35.010067],"type":"Point"}
}