{
  "type": "Feature",
  "properties": {
    "addr:full":"70 Leichhardt St Ruse NSW 2560",
    "addr:housenumber":"70",
    "addr:postcode":"2560",
    "addr:street":"Leichhardt St",
    "iso:country":"AU",
    "sg:address":"70 Leichhardt St",
    "sg:city":"Ruse",
    "sg:classifiers":[
        {
            "category":"Personal",
            "subcategory":"Massage",
            "type":"Services"
        }
    ],
    "sg:phone":"+61 2 4625 0302",
    "sg:postcode":"2560",
    "sg:province":"NSW",
    "sg:tags":[
        "therapy"
    ],
    "wof:name":"Muscles Are Us",
    "wof:placetype":"venue"
},
  "geometry": {"coordinates":[150.83924865700001,-34.0683898926],"type":"Point"}
}