{
  "type": "Feature",
  "properties": {
    "iso:country":"AU",
    "sg:address":"Unit 6 71-83 Asquith St",
    "sg:city":"Silverwater",
    "sg:classifiers":[
        {
            "category":"Utilities",
            "subcategory":"Electric",
            "type":"Services"
        }
    ],
    "sg:phone":"+61 2 8666 7525",
    "sg:postcode":"2128",
    "sg:province":"NSW",
    "sg:tags":[
        "electrical",
        "contractor"
    ],
    "wof:name":"Deromes (A division of Ladd Electrical Pty. Ltd.)",
    "wof:placetype":"venue"
},
  "geometry": {"coordinates":[151.036712647,-33.8362503052],"type":"Point"}
}