{
  "type": "Feature",
  "properties": {
    "iso:country":"AU",
    "sg:address":"Main Rd",
    "sg:city":"Detention River",
    "sg:classifiers":[
        {
            "category":"Food & Beverages",
            "subcategory":"Supermarket",
            "type":"Retail Goods"
        }
    ],
    "sg:phone":"+61 3 6443 4159",
    "sg:postcode":"7321",
    "sg:province":"TAS",
    "sg:tags":[
        "grocery",
        "store"
    ],
    "wof:name":"Friendly Grocer IGA Stores",
    "wof:placetype":"venue"
},
  "geometry": {"coordinates":[145.92659,-41.06723],"type":"Point"}
}