{
  "type": "Feature",
  "properties": {
    "addr:full":"Lvl1/ 32 Old Town Centre Plz Bankstown NSW 2200",
    "addr:housenumber":"32",
    "addr:postcode":"2200",
    "addr:street":"Old;Centre Plz",
    "iso:country":"AU",
    "sg:address":"Lvl1/ 32",
    "sg:city":"Old Town Centre Plz Bankstown",
    "sg:classifiers":[
        {
            "category":"Personal",
            "subcategory":"Massage",
            "type":"Services"
        }
    ],
    "sg:phone":"+61 2 9709 6232",
    "sg:postcode":"2200",
    "sg:province":"NSW",
    "sg:tags":[
        "therapy"
    ],
    "sg:website":"http://www.pinkcrystalthaimassage.com",
    "wof:name":"Pink Crystal Thai Massage Center",
    "wof:placetype":"venue"
},
  "geometry": {"coordinates":[151.03474399999999,-33.918419],"type":"Point"}
}