{
  "type": "Feature",
  "properties": {
    "addr:full":"32 Gaine Rd Dandenong South VIC 3175",
    "addr:housenumber":"32",
    "addr:postcode":"3175",
    "addr:street":"Gaine Rd",
    "iso:country":"AU",
    "sg:address":"32 Gaine Rd",
    "sg:city":"Dandenong South",
    "sg:classifiers":[
        {
            "category":"Manufacturing",
            "subcategory":"Glass & Minerals",
            "type":"Manufacturing & Wholesale Goods"
        }
    ],
    "sg:phone":"+61 3 9329 0111",
    "sg:postcode":"3175",
    "sg:province":"VIC",
    "sg:tags":[
        "repair",
        "fibreglass",
        "product"
    ],
    "wof:name":"Owens Corning Australia Pty Limited",
    "wof:placetype":"venue"
},
  "geometry": {"coordinates":[145.24053955100001,-38.0324859619],"type":"Point"}
}