{
  "type": "Feature",
  "properties": {
    "iso:country":"AU",
    "sg:address":"PO Box 719",
    "sg:city":"Irymple",
    "sg:classifiers":[
        {
            "category":"Building & Trades",
            "subcategory":"Landscaping Services",
            "type":"Services"
        }
    ],
    "sg:phone":"+61 428 308 991",
    "sg:postcode":"3498",
    "sg:province":"VIC",
    "sg:tags":[
        "designer",
        "landscape",
        "contractor"
    ],
    "wof:name":"Northwest Bobcat & Tipper Hire",
    "wof:placetype":"venue"
},
  "geometry": {"coordinates":[142.17286682100001,-34.2372512817],"type":"Point"}
}