{
  "type": "Feature",
  "properties": {
    "addr:full":"14 Heidi Pl West Pennant Hills NSW 2125",
    "addr:housenumber":"14",
    "addr:postcode":"2125",
    "addr:street":"Heidi Pl",
    "iso:country":"AU",
    "sg:address":"14 Heidi Pl",
    "sg:city":"West Pennant Hills",
    "sg:classifiers":[
        {
            "category":"Home & Garden",
            "subcategory":"Building Materials",
            "type":"Retail Goods"
        }
    ],
    "sg:phone":"+61 2 9872 7929",
    "sg:postcode":"2125",
    "sg:province":"NSW",
    "sg:tags":[
        "lawn",
        "cutting",
        "maintenance"
    ],
    "wof:name":"James' Complete Property Service",
    "wof:placetype":"venue"
},
  "geometry": {"coordinates":[151.02998352,-33.7570457458],"type":"Point"}
}