{
  "type": "Feature",
  "properties": {
    "addr:full":"35 Sewell Rd Tanah Merah QLD 4128",
    "addr:housenumber":"35",
    "addr:postcode":"4128",
    "addr:street":"Sewell Rd",
    "iso:country":"AU",
    "sg:address":"35 Sewell Rd",
    "sg:city":"Tanah Merah",
    "sg:classifiers":[
        {
            "category":"Building & Trades",
            "subcategory":"Landscaping Services",
            "type":"Services"
        }
    ],
    "sg:phone":"+61 7 3209 7214",
    "sg:postcode":"4128",
    "sg:province":"QLD",
    "sg:tags":[
        "firebreak",
        "clearing",
        "land",
        "contractor"
    ],
    "wof:name":"Hilltop Slashing Service",
    "wof:placetype":"venue"
},
  "geometry": {"coordinates":[153.16427612300001,-27.6608181],"type":"Point"}
}