{
  "type": "Feature",
  "properties": {
    "iso:country":"AU",
    "sg:address":"PO Box 2190",
    "sg:city":"Ascot",
    "sg:classifiers":[
        {
            "category":"Professional",
            "type":"Services"
        }
    ],
    "sg:phone":"+61 7 3262 6200",
    "sg:postcode":"4007",
    "sg:province":"QLD",
    "sg:tags":[
        "shop",
        "fitting"
    ],
    "wof:name":"Onsite Constructions",
    "wof:placetype":"venue"
},
  "geometry": {"coordinates":[153.062012,-27.42802],"type":"Point"}
}