{
  "type": "Feature",
  "properties": {
    "addr:full":"Factory 17/ 10 Norton Drv Melton VIC 3337",
    "addr:housenumber":"17 / 10",
    "addr:postcode":"3337",
    "addr:street":"Norton Drv",
    "iso:country":"AU",
    "sg:address":"Factory 17/ 10 Norton Drv",
    "sg:city":"Melton",
    "sg:classifiers":[
        {
            "category":"Professional",
            "subcategory":"Printing & Photocopies",
            "type":"Services"
        }
    ],
    "sg:phone":"+61 3 9743 3885",
    "sg:postcode":"3337",
    "sg:province":"VIC",
    "sg:tags":[
        "trophy"
    ],
    "wof:name":"AKA Trophies",
    "wof:placetype":"venue"
},
  "geometry": {"coordinates":[144.60179099999999,-37.691059],"type":"Point"}
}