{
  "type": "Feature",
  "properties": {
    "addr:full":"14a Ritchie St Brown Hill VIC 3350",
    "addr:housenumber":"14a",
    "addr:postcode":"3350",
    "addr:street":"Ritchie St",
    "iso:country":"AU",
    "sg:address":"14a Ritchie St",
    "sg:city":"Brown Hill",
    "sg:classifiers":[
        {
            "category":"Professional",
            "subcategory":"Art Services",
            "type":"Services"
        }
    ],
    "sg:phone":"+61 3 5331 5983",
    "sg:postcode":"3350",
    "sg:province":"VIC",
    "sg:tags":[
        "picture",
        "frame",
        "framing"
    ],
    "wof:name":"Paul Bernard's Custom Picture Framing",
    "wof:placetype":"venue"
},
  "geometry": {"coordinates":[143.89866599999999,-37.555786],"type":"Point"}
}