{
  "type": "Feature",
  "properties": {
    "addr:full":"Shop T42, Direct Factory Outlet, 3-5 Underwood Rd, Homebush Homebush NSW 2140",
    "addr:housenumber":"3-5",
    "addr:postcode":"2140",
    "addr:street":"Underwood Rd",
    "iso:country":"AU",
    "sg:address":"Shop T42, Direct Factory Outlet, 3-5 Underwood Rd, Homebush",
    "sg:city":"Homebush",
    "sg:classifiers":[
        {
            "category":"Shopping",
            "subcategory":"Clothing, Apparel, & Fashions",
            "type":"Retail Goods"
        }
    ],
    "sg:phone":"+61 2 9764 6158",
    "sg:postcode":"2140",
    "sg:province":"NSW",
    "sg:tags":[
        "boutique"
    ],
    "wof:name":"Morrissey",
    "wof:placetype":"venue"
},
  "geometry": {"coordinates":[151.07850647000001,-33.8551635742],"type":"Point"}
}