{
  "type": "Feature",
  "properties": {
    "iso:country":"AU",
    "sg:address":"Shop 6, 183 Kruger Pde",
    "sg:city":"Redbank Plains",
    "sg:classifiers":[
        {
            "category":"Food & Beverages",
            "subcategory":"Groceries & Convenience Stores",
            "type":"Retail Goods"
        }
    ],
    "sg:phone":"+61 7 3814 2044",
    "sg:postcode":"4301",
    "sg:province":"QLD",
    "wof:name":"Lawsons Food Store",
    "wof:placetype":"venue"
},
  "geometry": {"coordinates":[152.87448120100001,-27.6292495728],"type":"Point"}
}