{
  "type": "Feature",
  "properties": {
    "iso:country":"AU",
    "sg:address":"20 Sherburn Pl",
    "sg:city":"Charlestown",
    "sg:classifiers":[
        {
            "category":"Education",
            "subcategory":"Special Training",
            "type":"Public Place"
        }
    ],
    "sg:phone":"+61 2 4942 4987",
    "sg:postcode":"2290",
    "sg:province":"NSW",
    "sg:tags":[
        "development"
    ],
    "wof:name":"Total Performance Concepts",
    "wof:placetype":"venue"
},
  "geometry": {"coordinates":[151.69769287099999,-32.9584083557],"type":"Point"}
}