{
  "type": "Feature",
  "properties": {
    "addr:full":"Unit 21 34- 36 Ralph St Alexandria NSW 2015",
    "addr:housenumber":"34 36",
    "addr:postcode":"2015",
    "addr:street":"Ralph St",
    "iso:country":"AU",
    "sg:address":"Unit 21 34- 36 Ralph St",
    "sg:city":"Alexandria",
    "sg:classifiers":[
        {
            "category":"Military Area",
            "subcategory":"Air Force Base",
            "type":"Public Place"
        }
    ],
    "sg:phone":"+61 2 8338 0222",
    "sg:postcode":"2015",
    "sg:province":"NSW",
    "sg:tags":[
        "wholesaler",
        "travel",
        "good",
        "mfrs"
    ],
    "wof:name":"STM (Standard Technical Merchandise)",
    "wof:placetype":"venue"
},
  "geometry": {"coordinates":[151.19773864699999,-33.9183998108],"type":"Point"}
}