{
  "type": "Feature",
  "properties": {
    "addr:full":"Unit 2/ 780 Boundary Rd Coopers Plains QLD 4108",
    "addr:housenumber":"/ 780",
    "addr:postcode":"4108",
    "addr:street":"Boundary Rd",
    "iso:country":"AU",
    "sg:address":"Unit 2/ 780 Boundary Rd",
    "sg:city":"Coopers Plains",
    "sg:classifiers":[
        {
            "category":"Autos & Motor Vehicles",
            "subcategory":"Automobile Sales",
            "type":"Retail Goods"
        }
    ],
    "sg:phone":"+61 7 3272 7415",
    "sg:postcode":"4108",
    "sg:province":"QLD",
    "sg:tags":[
        "equipment",
        "trailer"
    ],
    "wof:name":"ROC Hydraulics",
    "wof:placetype":"venue"
},
  "geometry": {"coordinates":[153.02760314899999,-27.5687637329],"type":"Point"}
}