{
  "type": "Feature",
  "properties": {
    "addr:full":"412 Musgrave Rd Coopers Plains QLD 4108",
    "addr:housenumber":"412",
    "addr:postcode":"4108",
    "addr:street":"Musgrave Rd",
    "iso:country":"AU",
    "sg:address":"412 Musgrave Rd",
    "sg:city":"Coopers Plains",
    "sg:classifiers":[
        {
            "category":"Organizations",
            "subcategory":"Community Association",
            "type":"Services"
        }
    ],
    "sg:phone":"+61 7 3345 8051",
    "sg:postcode":"4108",
    "sg:province":"QLD",
    "sg:tags":[
        "organisation",
        "family",
        "welfare"
    ],
    "wof:name":"Haemochromatosis Society Australia Inc",
    "wof:placetype":"venue"
},
  "geometry": {"coordinates":[153.043167114,-27.5636405945],"type":"Point"}
}