{
  "type": "Feature",
  "properties": {
    "addr:full":"PO Box 158 Bungalow QLD 4870",
    "addr:postcode":"4870",
    "iso:country":"AU",
    "sg:address":"PO Box 158",
    "sg:city":"Bungalow",
    "sg:classifiers":[
        {
            "category":"Building & Trades",
            "subcategory":"Landscaping Services",
            "type":"Services"
        }
    ],
    "sg:phone":"+61 413 808 013",
    "sg:postcode":"4870",
    "sg:province":"QLD",
    "sg:tags":[
        "stump",
        "tree",
        "felling",
        "removal"
    ],
    "wof:name":"Adam's Tree Services",
    "wof:placetype":"venue"
},
  "geometry": {"coordinates":[145.75726318400001,-16.9362392426],"type":"Point"}
}