{
  "type": "Feature",
  "properties": {
    "addr:full":"18 Curragundi Rd Jindalee QLD 4074",
    "addr:housenumber":"18",
    "addr:postcode":"4074",
    "addr:street":"Curragundi Rd",
    "iso:country":"AU",
    "sg:address":"18 Curragundi Rd",
    "sg:city":"Jindalee",
    "sg:classifiers":[
        {
            "category":"Social Services",
            "type":"Services"
        }
    ],
    "sg:phone":"+61 7 3376 1197",
    "sg:postcode":"4074",
    "sg:province":"QLD",
    "sg:tags":[
        "disabled",
        "person",
        "equipment"
    ],
    "wof:name":"Kohlbach Electronics",
    "wof:placetype":"venue"
},
  "geometry": {"coordinates":[152.94024658199999,-27.5361843109],"type":"Point"}
}