{
  "type": "Feature",
  "properties": {
    "iso:country":"AU",
    "sg:address":"105 Merthyr Rd",
    "sg:city":"New Farm",
    "sg:classifiers":[
        {
            "category":"Arts & Performance",
            "subcategory":"Art Gallery",
            "type":"Entertainment"
        }
    ],
    "sg:phone":"+61 7 3358 4295",
    "sg:postcode":"4005",
    "sg:province":"QLD",
    "wof:name":"Omniscient Gallery",
    "wof:placetype":"venue"
},
  "geometry": {"coordinates":[153.04728698700001,-27.466173172],"type":"Point"}
}