{
  "type": "Feature",
  "properties": {
    "addr:full":"Shop 1 204 Rowe St Eastwood NSW 2122",
    "addr:housenumber":"shop 1 204",
    "addr:postcode":"2122",
    "addr:street":"Rowe St",
    "iso:country":"AU",
    "sg:address":"Shop 1 204 Rowe St",
    "sg:city":"Eastwood",
    "sg:classifiers":[
        {
            "category":"Health Services",
            "subcategory":"Dentist",
            "type":"Services"
        }
    ],
    "sg:phone":"+61 2 9858 5709",
    "sg:postcode":"2122",
    "sg:province":"NSW",
    "wof:name":"Poon Daniel S K",
    "wof:placetype":"venue"
},
  "geometry": {"coordinates":[151.07937622099999,-33.7920875549],"type":"Point"}
}