{
  "type": "Feature",
  "properties": {
    "addr:full":"Blue St North Sydney NSW 2060",
    "addr:postcode":"2060",
    "addr:street":"Blue St",
    "iso:country":"AU",
    "sg:address":"Blue St",
    "sg:city":"North Sydney",
    "sg:classifiers":[
        {
            "category":"Food & Beverages",
            "subcategory":"Bakery",
            "type":"Retail Goods"
        }
    ],
    "sg:phone":"+61 2 9957 3683",
    "sg:postcode":"2060",
    "sg:province":"NSW",
    "sg:tags":[
        "baker"
    ],
    "wof:name":"Muffin Break",
    "wof:placetype":"venue"
},
  "geometry": {"coordinates":[151.20820617699999,-33.840927124],"type":"Point"}
}