{
  "type": "Feature",
  "properties": {
    "addr:full":"186 Orlando St Coffs Harbour NSW 2450",
    "addr:housenumber":"186",
    "addr:postcode":"2450",
    "addr:street":"Orlando St",
    "iso:country":"AU",
    "sg:address":"186 Orlando St",
    "sg:city":"Coffs Harbour",
    "sg:classifiers":[
        {
            "category":"Home & Garden",
            "subcategory":"Carpets & Floor Coverings",
            "type":"Retail Goods"
        }
    ],
    "sg:phone":"+61 2 6651 1112",
    "sg:postcode":"2450",
    "sg:province":"NSW",
    "sg:tags":[
        "tile",
        "wall"
    ],
    "wof:name":"Tile Wizards",
    "wof:placetype":"venue"
},
  "geometry": {"coordinates":[153.12811300000001,-30.285692],"type":"Point"}
}