{
  "type": "Feature",
  "properties": {
    "addr:full":"34 John St Salisbury SA 5108",
    "addr:housenumber":"34",
    "addr:postcode":"5108",
    "addr:street":"John St",
    "iso:country":"AU",
    "sg:address":"34 John St",
    "sg:city":"Salisbury",
    "sg:classifiers":[
        {
            "category":"Banks & Credit Unions",
            "subcategory":"Financial Services",
            "type":"Services"
        }
    ],
    "sg:phone":"+61 8 8182 0199",
    "sg:postcode":"5108",
    "sg:province":"SA",
    "sg:tags":[
        "loan",
        "finance",
        "mortgage"
    ],
    "wof:name":"Beat Home Loans",
    "wof:placetype":"venue"
},
  "geometry": {"coordinates":[138.64439392099999,-34.7625465393],"type":"Point"}
}