{
  "type": "Feature",
  "properties": {
    "addr:full":"75 Kocho Rd Nambour QLD 4560",
    "addr:housenumber":"75",
    "addr:postcode":"4560",
    "addr:street":"Kocho Rd",
    "iso:country":"AU",
    "sg:address":"75 Kocho Rd",
    "sg:city":"Nambour",
    "sg:classifiers":[
        {
            "category":"Social Services",
            "subcategory":"Retirement Home",
            "type":"Services"
        }
    ],
    "sg:phone":"+61 7 5476 1706",
    "sg:postcode":"4560",
    "sg:province":"QLD",
    "sg:tags":[
        "environmental",
        "consultant",
        "pollution"
    ],
    "wof:name":"Kornaus Industries",
    "wof:placetype":"venue"
},
  "geometry": {"coordinates":[152.95132446299999,-26.6035499573],"type":"Point"}
}