{
  "type": "Feature",
  "properties": {
    "iso:country":"AU",
    "sg:address":"GPO Box 4003",
    "sg:city":"North Curl Curl",
    "sg:classifiers":[
        {
            "category":"Banks & Credit Unions",
            "subcategory":"Financial Services",
            "type":"Services"
        }
    ],
    "sg:phone":"+61 412 106 788",
    "sg:postcode":"2099",
    "sg:province":"NSW",
    "sg:tags":[
        "loan",
        "finance",
        "mortgage"
    ],
    "wof:name":"Australian Money Lenders",
    "wof:placetype":"venue"
},
  "geometry": {"coordinates":[151.29800415,-33.7630081177],"type":"Point"}
}