{
  "type": "Feature",
  "properties": {
    "iso:country":"AU",
    "sg:address":"34 Paterson St",
    "sg:city":"Launceston",
    "sg:classifiers":[
        {
            "category":"Professional",
            "subcategory":"Accounting & Tax Preparation",
            "type":"Services"
        }
    ],
    "sg:phone":"+61 3 6334 4249",
    "sg:postcode":"7250",
    "sg:province":"TAS",
    "sg:tags":[
        "pregnancy",
        "related",
        "counselling"
    ],
    "wof:name":"Pregnant & Young Parent Support (PYPS UnitingCare)",
    "wof:placetype":"venue"
},
  "geometry": {"coordinates":[147.13667297399999,-41.4369621277],"type":"Point"}
}