{
  "type": "Feature",
  "properties": {
    "iso:country":"AU",
    "sg:address":"Unit 1, 100 Park Rd, (Cnr Watland St)",
    "sg:city":"Slacks Creek",
    "sg:classifiers":[
        {
            "category":"Manufacturing",
            "subcategory":"Motor Vehicles & Parts",
            "type":"Manufacturing & Wholesale Goods"
        }
    ],
    "sg:phone":"+61 7 3442 8000",
    "sg:postcode":"4127",
    "sg:province":"QLD",
    "sg:tags":[
        "replacement"
    ],
    "wof:name":"Eagle Auto Parts Pty Ltd",
    "wof:placetype":"venue"
},
  "geometry": {"coordinates":[153.12757873499999,-27.6267662048],"type":"Point"}
}