{
  "type": "Feature",
  "properties": {
    "addr:full":"14 Alfred Rd Chipping Norton NSW 2170",
    "addr:housenumber":"14",
    "addr:postcode":"2170",
    "addr:street":"Alfred Rd",
    "iso:country":"AU",
    "sg:address":"14 Alfred Rd",
    "sg:city":"Chipping Norton",
    "sg:classifiers":[
        {
            "category":"Autos & Motor Vehicles",
            "subcategory":"Auto Supplies",
            "type":"Retail Goods"
        }
    ],
    "sg:phone":"+61 2 9755 3311",
    "sg:postcode":"2170",
    "sg:province":"NSW",
    "sg:tags":[
        "turbochargers"
    ],
    "wof:name":"Honeywell Turbo Technologies",
    "wof:placetype":"venue"
},
  "geometry": {"coordinates":[150.966796875,-33.9231834412],"type":"Point"}
}