{
  "type": "Feature",
  "properties": {
    "iso:country":"AU",
    "sg:address":"31 Orchardleigh St",
    "sg:city":"Yennora",
    "sg:classifiers":[
        {
            "category":"Social Services",
            "subcategory":"Child Care",
            "type":"Services"
        }
    ],
    "sg:phone":"+61 2 9681 1055",
    "sg:postcode":"2161",
    "sg:province":"NSW",
    "wof:name":"Orchardleigh Childcare Centre",
    "wof:placetype":"venue"
},
  "geometry": {"coordinates":[150.973556519,-33.8655166626],"type":"Point"}
}