{
  "type": "Feature",
  "properties": {
    "addr:full":"170 Bell St Coburg VIC 3058",
    "addr:housenumber":"170",
    "addr:postcode":"3058",
    "addr:street":"Bell St",
    "iso:country":"AU",
    "sg:address":"170 Bell St",
    "sg:city":"Coburg",
    "sg:classifiers":[
        {
            "category":"Health Services",
            "subcategory":"Health Practitioner",
            "type":"Services"
        }
    ],
    "sg:phone":"+61 400 114 357",
    "sg:postcode":"3058",
    "sg:province":"VIC",
    "sg:tags":[
        "psychologist"
    ],
    "wof:name":"Anthony M Cichello & Assoc.",
    "wof:placetype":"venue"
},
  "geometry": {"coordinates":[144.96185302699999,-37.7407150269],"type":"Point"}
}