{
  "type": "Feature",
  "properties": {
    "addr:full":"Shp5/ 81 Magill Rd Stepney SA 5069",
    "addr:postcode":"5069",
    "addr:street":"Magill Rd",
    "iso:country":"AU",
    "sg:address":"Shp5/ 81 Magill Rd",
    "sg:city":"Stepney",
    "sg:classifiers":[
        {
            "category":"Cafe",
            "type":"Food & Drink"
        }
    ],
    "sg:phone":"+61 8 8132 0004",
    "sg:postcode":"5069",
    "sg:province":"SA",
    "wof:name":"Stepney Cafe",
    "wof:placetype":"venue"
},
  "geometry": {"coordinates":[138.62940979000001,-34.9152336121],"type":"Point"}
}