{
  "type": "Feature",
  "properties": {
    "iso:country":"AU",
    "sg:address":"Shop G58, Broadmeadows Shopping Centre, Pascoe Vale Rd",
    "sg:city":"Broadmeadows",
    "sg:classifiers":[
        {
            "category":"Food & Beverages",
            "subcategory":"Bakery",
            "type":"Retail Goods"
        }
    ],
    "sg:phone":"+61 3 9309 0155",
    "sg:postcode":"3047",
    "sg:province":"VIC",
    "sg:tags":[
        "baker"
    ],
    "wof:name":"Bakers Delight Ltd",
    "wof:placetype":"venue"
},
  "geometry": {"coordinates":[144.92155456500001,-37.6800804138],"type":"Point"}
}