{
  "type": "Feature",
  "properties": {
    "iso:country":"AU",
    "sg:address":"7 Elizabeth St",
    "sg:city":"Sydney",
    "sg:classifiers":[
        {
            "category":"Travel",
            "subcategory":"Travel Agent",
            "type":"Entertainment"
        }
    ],
    "sg:phone":"+61 2 9233 6666",
    "sg:postcode":"2000",
    "sg:province":"NSW",
    "sg:tags":[
        "consultant"
    ],
    "wof:name":"Sydney City Centre Travel Agent",
    "wof:placetype":"venue"
},
  "geometry": {"coordinates":[151.210540772,-33.8667182922],"type":"Point"}
}