{
  "type": "Feature",
  "properties": {
    "addr:full":"243 New Street St Brighton VIC 3186",
    "addr:housenumber":"243",
    "addr:postcode":"3186",
    "addr:street":"New Street St",
    "iso:country":"AU",
    "sg:address":"243 New Street St",
    "sg:city":"Brighton",
    "sg:classifiers":[
        {
            "category":"Health Services",
            "subcategory":"Doctor",
            "type":"Services"
        }
    ],
    "sg:phone":"+61 3 9553 8255",
    "sg:postcode":"3186",
    "sg:province":"VIC",
    "sg:tags":[
        "medical",
        "practitioner"
    ],
    "wof:name":"Brighton Dialysis Unit",
    "wof:placetype":"venue"
},
  "geometry": {"coordinates":[144.991622925,-37.911781311],"type":"Point"}
}