{
  "type": "Feature",
  "properties": {
    "addr:full":"Cecily Court 68 Nunn St Benalla VIC 3672",
    "addr:housenumber":"68",
    "addr:postcode":"3672",
    "addr:street":"Cecily;Nunn St",
    "iso:country":"AU",
    "sg:address":"Cecily Court 68 Nunn St",
    "sg:city":"Benalla",
    "sg:classifiers":[
        {
            "category":"Banks & Credit Unions",
            "subcategory":"Investment Brokerage",
            "type":"Services"
        }
    ],
    "sg:phone":"+61 3 5762 7133",
    "sg:postcode":"3672",
    "sg:province":"VIC",
    "wof:name":"Retireinvest",
    "wof:placetype":"venue"
},
  "geometry": {"coordinates":[145.98286400000001,-36.550762],"type":"Point"}
}