{
  "type": "Feature",
  "properties": {
    "iso:country":"AU",
    "sg:address":"Cecily Court 68 Nunn St",
    "sg:city":"Benalla",
    "sg:classifiers":[
        {
            "category":"Banks & Credit Unions",
            "subcategory":"Investment Brokerage",
            "type":"Services"
        }
    ],
    "sg:phone":"+61 3 5762 7133",
    "sg:postcode":"3672",
    "sg:province":"VIC",
    "wof:name":"Retireinvest",
    "wof:placetype":"venue"
},
  "geometry": {"coordinates":[145.982864,-36.550762],"type":"Point"}
}