{
  "type": "Feature",
  "properties": {
    "addr:full":"240 Barkly St Ararat VIC 3377",
    "addr:housenumber":"240",
    "addr:postcode":"3377",
    "addr:street":"Barkly St",
    "iso:country":"AU",
    "sg:address":"240 Barkly St",
    "sg:city":"Ararat",
    "sg:classifiers":[
        {
            "category":"Travel",
            "subcategory":"Hotels & Motels",
            "type":"Entertainment"
        }
    ],
    "sg:phone":"+61 3 5352 1280",
    "sg:postcode":"3377",
    "sg:province":"VIC",
    "sg:tags":[
        "accommodation"
    ],
    "wof:name":"Shire Hall Hotel",
    "wof:placetype":"venue"
},
  "geometry": {"coordinates":[142.93363952600001,-37.2840309143],"type":"Point"}
}