{
  "type": "Feature",
  "properties": {
    "iso:country":"AU",
    "sg:address":"Suite 7, 1 Danks St",
    "sg:city":"Waterloo",
    "sg:classifiers":[
        {
            "category":"Professional",
            "subcategory":"Business Services",
            "type":"Services"
        }
    ],
    "sg:phone":"+61 2 9699 7702",
    "sg:postcode":"2017",
    "sg:province":"NSW",
    "sg:tags":[
        "small",
        "advisory"
    ],
    "wof:name":"Condiment Communications",
    "wof:placetype":"venue"
},
  "geometry": {"coordinates":[151.20953369099999,-33.8976707458],"type":"Point"}
}