{
  "type": "Feature",
  "properties": {
    "iso:country":"AU",
    "sg:address":"Shop 1, 198 Gipps Rd",
    "sg:city":"Gwynneville",
    "sg:classifiers":[
        {
            "category":"Personal",
            "subcategory":"Beauty Salon",
            "type":"Services"
        }
    ],
    "sg:phone":"+61 2 4228 0855",
    "sg:postcode":"2500",
    "sg:province":"NSW",
    "wof:name":"Vivante Beauty",
    "wof:placetype":"venue"
},
  "geometry": {"coordinates":[150.88209499999999,-34.415894],"type":"Point"}
}