{
  "type": "Feature",
  "properties": {
    "addr:full":"Shed 13 37 Nobility St, Moolap Moolap VIC 3221",
    "addr:housenumber":"37",
    "addr:postcode":"3221",
    "addr:street":"Nobility St",
    "iso:country":"AU",
    "sg:address":"Shed 13 37 Nobility St, Moolap",
    "sg:city":"Moolap",
    "sg:classifiers":[
        {
            "category":"Retail",
            "subcategory":"Auto Repair",
            "type":"Services"
        }
    ],
    "sg:phone":"+61 3 5248 5475",
    "sg:postcode":"3221",
    "sg:province":"VIC",
    "sg:tags":[
        "repairer",
        "motor",
        "engineer"
    ],
    "wof:name":"Eden R J",
    "wof:placetype":"venue"
},
  "geometry": {"coordinates":[144.41134600000001,-38.16655],"type":"Point"}
}