{
  "type": "Feature",
  "properties": {
    "addr:full":"24 Elm Pl Woolooware NSW 2230",
    "addr:housenumber":"24",
    "addr:postcode":"2230",
    "addr:street":"Elm Pl",
    "iso:country":"AU",
    "sg:address":"24 Elm Pl",
    "sg:city":"Woolooware",
    "sg:classifiers":[
        {
            "category":"Shopping",
            "subcategory":"Computers & Home Electronics",
            "type":"Retail Goods"
        }
    ],
    "sg:phone":"+61 2 8004 2926",
    "sg:postcode":"2230",
    "sg:province":"NSW",
    "sg:tags":[
        "small",
        "equipment",
        "business"
    ],
    "wof:name":"D & F Ingram & Associates",
    "wof:placetype":"venue"
},
  "geometry": {"coordinates":[151.13482665999999,-34.0516090393],"type":"Point"}
}