{
  "type": "Feature",
  "properties": {
    "iso:country":"AU",
    "sg:address":"58- 60 Bridge Rd",
    "sg:city":"Keysborough",
    "sg:classifiers":[
        {
            "category":"Autos & Motor Vehicles",
            "subcategory":"Auto Supplies",
            "type":"Retail Goods"
        }
    ],
    "sg:phone":"+61 422 900 383",
    "sg:postcode":"3173",
    "sg:province":"VIC",
    "sg:tags":[
        "accessory"
    ],
    "wof:name":"New Fujimi Australia",
    "wof:placetype":"venue"
},
  "geometry": {"coordinates":[145.19172668499999,-37.9893531799],"type":"Point"}
}