{
  "type": "Feature",
  "properties": {
    "iso:country":"AU",
    "sg:address":"54 Oxford St",
    "sg:city":"Booval North",
    "sg:classifiers":[
        {
            "category":"Home & Garden",
            "subcategory":"Garden Supply",
            "type":"Retail Goods"
        }
    ],
    "sg:phone":"+61 7 5427 0347",
    "sg:postcode":"4304",
    "sg:province":"QLD",
    "sg:tags":[
        "equipment"
    ],
    "wof:name":"Zanow Earthmovers Pty Ltd",
    "wof:placetype":"venue"
},
  "geometry": {"coordinates":[152.78668212900001,-27.5932788849],"type":"Point"}
}