{
  "type": "Feature",
  "properties": {
    "iso:country":"AU",
    "sg:address":"102- 106 Mahoneys Rd",
    "sg:city":"Thomastown",
    "sg:classifiers":[
        {
            "category":"Shopping",
            "subcategory":"Clothing, Apparel, & Fashions",
            "type":"Retail Goods"
        }
    ],
    "sg:phone":"+61 3 9460 6722",
    "sg:postcode":"3074",
    "sg:province":"VIC",
    "sg:tags":[
        "uniform"
    ],
    "wof:name":"Stylecorp",
    "wof:placetype":"venue"
},
  "geometry": {"coordinates":[144.99818420400001,-37.6932563782],"type":"Point"}
}