{
  "type": "Feature",
  "properties": {
    "iso:country":"AU",
    "sg:address":"69 Pacific Hwy",
    "sg:city":"Urunga",
    "sg:classifiers":[
        {
            "category":"Utilities",
            "type":"Services"
        }
    ],
    "sg:phone":"+61 418 296 495",
    "sg:postcode":"2455",
    "sg:province":"NSW",
    "sg:tags":[
        "refrigeration",
        "industrial",
        "commercial",
        "retail"
    ],
    "wof:name":"Greg Topple",
    "wof:placetype":"venue"
},
  "geometry": {"coordinates":[153.011841,-30.502172],"type":"Point"}
}