{
  "type": "Feature",
  "properties": {
    "addr:full":"1568 Malvern Rd Glen Iris VIC 3146",
    "addr:housenumber":"1568",
    "addr:postcode":"3146",
    "addr:street":"Malvern Rd",
    "iso:country":"AU",
    "sg:address":"1568 Malvern Rd",
    "sg:city":"Glen Iris",
    "sg:classifiers":[
        {
            "category":"Health Services",
            "subcategory":"Dentist",
            "type":"Services"
        }
    ],
    "sg:phone":"+61 3 9885 4591",
    "sg:postcode":"3146",
    "sg:province":"VIC",
    "sg:tags":[
        "prosthodontist"
    ],
    "wof:name":"Prosthodontic Centre",
    "wof:placetype":"venue"
},
  "geometry": {"coordinates":[145.05259704599999,-37.8549575806],"type":"Point"}
}