{
  "type": "Feature",
  "properties": {
    "iso:country":"AU",
    "sg:address":"PO Box 101",
    "sg:city":"Grose Vale",
    "sg:classifiers":[
        {
            "category":"Professional",
            "subcategory":"Computer Services",
            "type":"Services"
        }
    ],
    "sg:phone":"+61 2 9893 1804",
    "sg:postcode":"2753",
    "sg:province":"NSW",
    "sg:tags":[
        "consultant",
        "system"
    ],
    "wof:name":"Sensible Business Solutions Pty Ltd",
    "wof:placetype":"venue"
},
  "geometry": {"coordinates":[150.65107727,-33.5760612488],"type":"Point"}
}