{
  "type": "Feature",
  "properties": {
    "iso:country":"AU",
    "sg:address":"Craigston 217 Wickham Tce",
    "sg:city":"Brisbane",
    "sg:classifiers":[
        {
            "category":"Health Services",
            "subcategory":"Dentist",
            "type":"Services"
        }
    ],
    "sg:phone":"+61 7 3236 9477",
    "sg:postcode":"4000",
    "sg:province":"QLD",
    "wof:name":"Thomson Monica",
    "wof:placetype":"venue"
},
  "geometry": {"coordinates":[153.022872925,-27.4654827118],"type":"Point"}
}