{
  "type": "Feature",
  "properties": {
    "addr:full":"14 Spencer St Toowoomba QLD 4350",
    "addr:housenumber":"14",
    "addr:postcode":"4350",
    "addr:street":"Spencer St",
    "iso:country":"AU",
    "sg:address":"14 Spencer St",
    "sg:city":"Toowoomba",
    "sg:classifiers":[
        {
            "category":"Shopping",
            "subcategory":"Computers & Home Electronics",
            "type":"Retail Goods"
        }
    ],
    "sg:phone":"+61 7 4635 4593",
    "sg:postcode":"4350",
    "sg:province":"QLD",
    "sg:tags":[
        "hardware",
        "equipment"
    ],
    "wof:name":"KIT Computers",
    "wof:placetype":"venue"
},
  "geometry": {"coordinates":[151.92585800000001,-27.579529],"type":"Point"}
}