{
  "type": "Feature",
  "properties": {
    "addr:full":"8 Dawes Crt Ferntree Gully VIC 3156",
    "addr:housenumber":"8",
    "addr:postcode":"3156",
    "addr:street":"Dawes Crt",
    "iso:country":"AU",
    "sg:address":"8 Dawes Crt",
    "sg:city":"Ferntree Gully",
    "sg:classifiers":[
        {
            "category":"Building & Trades",
            "subcategory":"Construction",
            "type":"Services"
        }
    ],
    "sg:phone":"+61 3 9752 3492",
    "sg:postcode":"3156",
    "sg:province":"VIC",
    "sg:tags":[
        "fencing",
        "contractor"
    ],
    "wof:name":"Total Fencing Co",
    "wof:placetype":"venue"
},
  "geometry": {"coordinates":[145.280563355,-37.891960144],"type":"Point"}
}