{
  "type": "Feature",
  "properties": {
    "addr:full":"36a McCartin St Leongatha VIC 3953",
    "addr:housenumber":"36a",
    "addr:postcode":"3953",
    "addr:street":"Mccartin St",
    "iso:country":"AU",
    "sg:address":"36a McCartin St",
    "sg:city":"Leongatha",
    "sg:classifiers":[
        {
            "category":"Personal",
            "subcategory":"Beauty Salon",
            "type":"Services"
        }
    ],
    "sg:phone":"+61 3 5662 3334",
    "sg:postcode":"3953",
    "sg:province":"VIC",
    "wof:name":"Buzz Hair Studio",
    "wof:placetype":"venue"
},
  "geometry": {"coordinates":[145.94490051299999,-38.4769248962],"type":"Point"}
}