{
  "type": "Feature",
  "properties": {
    "iso:country":"AU",
    "sg:address":"32 Liege St",
    "sg:city":"Russell Lea",
    "sg:classifiers":[
        {
            "category":"Banks & Credit Unions",
            "subcategory":"Bank",
            "type":"Services"
        }
    ],
    "sg:phone":"+61 2 9712 8888",
    "sg:postcode":"2046",
    "sg:province":"NSW",
    "sg:tags":[
        "broker",
        "mortgage"
    ],
    "wof:name":"Elite Mortgage Services",
    "wof:placetype":"venue"
},
  "geometry": {"coordinates":[151.141479,-33.856499],"type":"Point"}
}