{
  "type": "Feature",
  "properties": {
    "iso:country":"AU",
    "sg:address":"264 Stanmore Rd",
    "sg:city":"Petersham",
    "sg:classifiers":[
        {
            "category":"Social Services",
            "subcategory":"Child Care",
            "type":"Services"
        }
    ],
    "sg:phone":"+61 2 9560 4040",
    "sg:postcode":"2049",
    "sg:province":"NSW",
    "wof:name":"Greek Orthodox Community Of Sydney & N.S.W.",
    "wof:placetype":"venue"
},
  "geometry": {"coordinates":[151.160767,-33.896629],"type":"Point"}
}