{
  "type": "Feature",
  "properties": {
    "addr:full":"Shp 4, 28 Donald St Nelson Bay NSW 2315",
    "addr:housenumber":"28",
    "addr:postcode":"2315",
    "addr:street":"Donald St",
    "iso:country":"AU",
    "sg:address":"Shp 4, 28 Donald St",
    "sg:city":"Nelson Bay",
    "sg:classifiers":[
        {
            "category":"Professional",
            "subcategory":"Accounting & Tax Preparation",
            "type":"Services"
        }
    ],
    "sg:phone":"+61 2 4984 3124",
    "sg:postcode":"2315",
    "sg:province":"NSW",
    "sg:tags":[
        "consultant",
        "taxation"
    ],
    "wof:name":"H&R Block",
    "wof:placetype":"venue"
},
  "geometry": {"coordinates":[152.14407299999999,-32.721806],"type":"Point"}
}