{
  "type": "Feature",
  "properties": {
    "addr:full":"7/24 Ashley St Reservoir VIC 3073",
    "addr:housenumber":"/ 24",
    "addr:postcode":"3073",
    "addr:street":"Ashley St",
    "iso:country":"AU",
    "sg:address":"7/24 Ashley St",
    "sg:city":"Reservoir",
    "sg:classifiers":[
        {
            "category":"Professional",
            "subcategory":"Secretarial Services",
            "type":"Services"
        }
    ],
    "sg:phone":"+61 3 9469 4835",
    "sg:postcode":"3073",
    "sg:province":"VIC",
    "sg:tags":[
        "typing"
    ],
    "wof:name":"V.A.P Office Outsourcing",
    "wof:placetype":"venue"
},
  "geometry": {"coordinates":[145.00239563,-37.7172660828],"type":"Point"}
}