{
  "type": "Feature",
  "properties": {
    "addr:full":"22a Terry St Blakehurst NSW 2221",
    "addr:housenumber":"22a",
    "addr:postcode":"2221",
    "addr:street":"Terry St",
    "iso:country":"AU",
    "sg:address":"22a Terry St",
    "sg:city":"Blakehurst",
    "sg:classifiers":[
        {
            "category":"Education",
            "subcategory":"Special Training",
            "type":"Public Place"
        }
    ],
    "sg:phone":"+61 2 9546 8913",
    "sg:postcode":"2221",
    "sg:province":"NSW",
    "sg:tags":[
        "tuition-educational"
    ],
    "wof:name":"St George Advance Coaching",
    "wof:placetype":"venue"
},
  "geometry": {"coordinates":[151.11137390100001,-33.9835319519],"type":"Point"}
}