{
  "type": "Feature",
  "properties": {
    "iso:country":"AU",
    "sg:address":"Lvl 1/ 365 Lonsdale St",
    "sg:city":"Melbourne",
    "sg:classifiers":[
        {
            "category":"Shopping",
            "subcategory":"Computers & Home Electronics",
            "type":"Retail Goods"
        }
    ],
    "sg:phone":"+61 3 9670 6135",
    "sg:postcode":"3000",
    "sg:province":"VIC",
    "sg:tags":[
        "equipment",
        "multimedia"
    ],
    "wof:name":"Kurioz Media Production",
    "wof:placetype":"venue"
},
  "geometry": {"coordinates":[144.961669922,-37.8125686646],"type":"Point"}
}