{
  "type": "Feature",
  "properties": {
    "iso:country":"AU",
    "sg:address":"1216 Rollos Rd",
    "sg:city":"Mepunga East",
    "sg:classifiers":[
        {
            "category":"Manufacturing",
            "subcategory":"Metals",
            "type":"Manufacturing & Wholesale Goods"
        }
    ],
    "sg:phone":"+61 3 5566 3227",
    "sg:postcode":"3277",
    "sg:province":"VIC",
    "sg:tags":[
        "steel",
        "fabricator",
        "mfrs"
    ],
    "wof:name":"Innovative Dairy Services",
    "wof:placetype":"venue"
},
  "geometry": {"coordinates":[142.716033936,-38.4500846863],"type":"Point"}
}