{
  "type": "Feature",
  "properties": {
    "iso:country":"AU",
    "sg:address":"47 Montague St",
    "sg:city":"Fairy Meadow",
    "sg:classifiers":[
        {
            "category":"Professional",
            "type":"Services"
        }
    ],
    "sg:phone":"+61 2 4228 7709",
    "sg:postcode":"2519",
    "sg:province":"NSW",
    "sg:tags":[
        "spray",
        "painting"
    ],
    "wof:name":"D.M. Smash Repairs",
    "wof:placetype":"venue"
},
  "geometry": {"coordinates":[150.89640800000001,-34.397614],"type":"Point"}
}