{
  "type": "Feature",
  "properties": {
    "iso:country":"AU",
    "sg:address":"1 Norwich Ave",
    "sg:city":"Thomastown",
    "sg:classifiers":[
        {
            "category":"Retail",
            "subcategory":"Auto Repair",
            "type":"Services"
        }
    ],
    "sg:phone":"+61 3 9462 3622",
    "sg:postcode":"3074",
    "sg:province":"VIC",
    "sg:tags":[
        "car",
        "restoration",
        "supply"
    ],
    "wof:name":"Classics- Mustangs Rod Stop",
    "wof:placetype":"venue"
},
  "geometry": {"coordinates":[144.997848511,-37.6906166077],"type":"Point"}
}