{
  "type": "Feature",
  "properties": {
    "addr:full":"58 Young Rd Baldivis WA 6171",
    "addr:housenumber":"58",
    "addr:postcode":"6171",
    "addr:street":"Young Rd",
    "iso:country":"AU",
    "sg:address":"58 Young Rd",
    "sg:city":"Baldivis",
    "sg:classifiers":[
        {
            "category":"Farming",
            "subcategory":"Farm",
            "type":"Manufacturing & Wholesale Goods"
        }
    ],
    "sg:phone":"+61 8 9524 1636",
    "sg:postcode":"6171",
    "sg:province":"WA",
    "sg:tags":[
        "farmer"
    ],
    "wof:name":"Konynen Farm",
    "wof:placetype":"venue"
},
  "geometry": {"coordinates":[115.83963799999999,-32.370846],"type":"Point"}
}