{
  "type": "Feature",
  "properties": {
    "iso:country":"AU",
    "sg:address":"487 Alvany Hwy",
    "sg:city":"Victoria Park",
    "sg:classifiers":[
        {
            "category":"Airline",
            "type":"Transportation"
        }
    ],
    "sg:phone":"+61 8 9362 5900",
    "sg:postcode":"6979",
    "sg:province":"WA",
    "sg:tags":[
        "agent"
    ],
    "wof:name":"Turkish Airlines",
    "wof:placetype":"venue"
},
  "geometry": {"coordinates":[115.898247,-31.976828],"type":"Point"}
}