{
  "type": "Feature",
  "properties": {
    "addr:full":"Unit6/ 7 Stoddart Rd Prospect NSW 2148",
    "addr:housenumber":"7",
    "addr:postcode":"2148",
    "addr:street":"Stoddart Rd",
    "iso:country":"AU",
    "sg:address":"Unit6/ 7 Stoddart Rd",
    "sg:city":"Prospect",
    "sg:classifiers":[
        {
            "category":"Professional",
            "subcategory":"Detective & Security Services",
            "type":"Services"
        }
    ],
    "sg:phone":"+61 1300 133 456",
    "sg:postcode":"2148",
    "sg:province":"NSW",
    "sg:tags":[
        "domestic",
        "alarm",
        "commercial",
        "burglar"
    ],
    "wof:name":"PSS Security",
    "wof:placetype":"venue"
},
  "geometry": {"coordinates":[150.92288207999999,-33.8003120422],"type":"Point"}
}