{
  "type": "Feature",
  "properties": {
    "addr:full":"4 Bruce Ave Marleston SA 5033",
    "addr:housenumber":"4",
    "addr:postcode":"5033",
    "addr:street":"Bruce Ave",
    "iso:country":"AU",
    "sg:address":"4 Bruce Ave",
    "sg:city":"Marleston",
    "sg:classifiers":[
        {
            "category":"Wholesale",
            "subcategory":"Auto Parts",
            "type":"Manufacturing & Wholesale Goods"
        }
    ],
    "sg:phone":"+61 8 8292 8292",
    "sg:postcode":"5033",
    "sg:province":"SA",
    "sg:tags":[
        "tyre"
    ],
    "wof:name":"Dico Tyres",
    "wof:placetype":"venue"
},
  "geometry": {"coordinates":[138.56556701700001,-34.9429512024],"type":"Point"}
}