{
  "type": "Feature",
  "properties": {
    "addr:full":"8 Alberton St Wishart QLD 4122",
    "addr:housenumber":"8",
    "addr:postcode":"4122",
    "addr:street":"Alberton St",
    "iso:country":"AU",
    "sg:address":"8 Alberton St",
    "sg:city":"Wishart",
    "sg:classifiers":[
        {
            "category":"Real Estate",
            "subcategory":"Architect",
            "type":"Services"
        }
    ],
    "sg:phone":"+61 7 3849 4495",
    "sg:postcode":"4122",
    "sg:province":"QLD",
    "sg:tags":[
        "building",
        "designer"
    ],
    "wof:name":"Ossola Design Consultants",
    "wof:placetype":"venue"
},
  "geometry": {"coordinates":[153.09463500999999,-27.5449638367],"type":"Point"}
}