{
  "type": "Feature",
  "properties": {
    "addr:full":"8b Pearse St Warragul VIC 3820",
    "addr:housenumber":"8b",
    "addr:postcode":"3820",
    "addr:street":"Pearse St",
    "iso:country":"AU",
    "sg:address":"8b Pearse St",
    "sg:city":"Warragul",
    "sg:classifiers":[
        {
            "category":"Farming",
            "subcategory":"Farm & Veterinary Services",
            "type":"Manufacturing & Wholesale Goods"
        }
    ],
    "sg:phone":"+61 3 5633 2009",
    "sg:postcode":"3820",
    "sg:province":"VIC",
    "sg:tags":[
        "contracting"
    ],
    "wof:name":"Solo Resource Recovery Pty Ltd",
    "wof:placetype":"venue"
},
  "geometry": {"coordinates":[145.94352699999999,-38.164425],"type":"Point"}
}