{
  "type": "Feature",
  "properties": {
    "addr:full":"Kiosk K44, Westfield Mt Druitt Carlisle Ave Mt Druitt NSW 2770",
    "addr:postcode":"2770",
    "addr:street":"Carlisle Ave Mt",
    "iso:country":"AU",
    "sg:address":"Kiosk K44, Westfield Mt Druitt Carlisle Ave",
    "sg:city":"Mt Druitt",
    "sg:classifiers":[
        {
            "category":"Food & Beverages",
            "subcategory":"Bakery",
            "type":"Retail Goods"
        }
    ],
    "sg:phone":"+61 2 9675 7444",
    "sg:postcode":"2770",
    "sg:province":"NSW",
    "sg:tags":[
        "cake",
        "shop",
        "pastry"
    ],
    "wof:name":"Cheesecake Shop The",
    "wof:placetype":"venue"
},
  "geometry": {"coordinates":[150.81729125999999,-33.7653083801],"type":"Point"}
}