{
  "type": "Feature",
  "properties": {
    "addr:full":"83 Lysaght St Mitchell ACT 2911",
    "addr:housenumber":"83",
    "addr:postcode":"2911",
    "addr:street":"Lysaght St",
    "iso:country":"AU",
    "sg:address":"83 Lysaght St",
    "sg:city":"Mitchell",
    "sg:classifiers":[
        {
            "category":"Professional",
            "subcategory":"Accounting & Tax Preparation",
            "type":"Services"
        }
    ],
    "sg:phone":"+61 2 6241 6744",
    "sg:postcode":"2911",
    "sg:province":"ACT",
    "sg:tags":[
        "accountant",
        "auditor"
    ],
    "wof:name":"Peter Irving & Co",
    "wof:placetype":"venue"
},
  "geometry": {"coordinates":[149.14137268100001,-35.2156219482],"type":"Point"}
}