{
  "type": "Feature",
  "properties": {
    "addr:full":"159 High St Preston VIC 3072",
    "addr:housenumber":"159",
    "addr:postcode":"3072",
    "addr:street":"High St",
    "iso:country":"AU",
    "sg:address":"159 High St",
    "sg:city":"Preston",
    "sg:classifiers":[
        {
            "category":"Health Services",
            "subcategory":"Health Practitioner",
            "type":"Services"
        }
    ],
    "sg:phone":"+61 3 9480 0277",
    "sg:postcode":"3072",
    "sg:province":"VIC",
    "sg:tags":[
        "naturopath"
    ],
    "wof:name":"Monika O&#039;Leary",
    "wof:placetype":"venue"
},
  "geometry": {"coordinates":[145.00286865199999,-37.7440414429],"type":"Point"}
}