{
  "type": "Feature",
  "properties": {
    "addr:full":"169- 171 Broken Head Rd Suffolk Park NSW 2481",
    "addr:housenumber":"171",
    "addr:postcode":"2481",
    "addr:street":"Broken Head Rd",
    "iso:country":"AU",
    "sg:address":"169- 171 Broken Head Rd",
    "sg:city":"Suffolk Park",
    "sg:classifiers":[
        {
            "category":"Manufacturing",
            "subcategory":"Jewelry",
            "type":"Manufacturing & Wholesale Goods"
        }
    ],
    "sg:phone":"+61 2 6685 3343",
    "sg:postcode":"2481",
    "sg:province":"NSW",
    "sg:tags":[
        "designer",
        "jewellery"
    ],
    "wof:name":"Byron Bay Fine Jewellery",
    "wof:placetype":"venue"
},
  "geometry": {"coordinates":[153.60697937,-28.6907920837],"type":"Point"}
}