{
  "type": "Feature",
  "properties": {
    "addr:full":"31 Victoria St Cobden VIC 3266",
    "addr:housenumber":"31",
    "addr:postcode":"3266",
    "addr:street":"Victoria St",
    "iso:country":"AU",
    "sg:address":"31 Victoria St",
    "sg:city":"Cobden",
    "sg:classifiers":[
        {
            "category":"Social Services",
            "subcategory":"Child Care",
            "type":"Services"
        }
    ],
    "sg:phone":"+61 3 5595 1536",
    "sg:postcode":"3266",
    "sg:province":"VIC",
    "sg:tags":[
        "breeding",
        "artificial"
    ],
    "wof:name":"Cobden A.B. Co-Operative Ltd",
    "wof:placetype":"venue"
},
  "geometry": {"coordinates":[143.07688903799999,-38.3294372559],"type":"Point"}
}