{
  "type": "Feature",
  "properties": {
    "addr:full":"2J Greenway Plz, 222 Church Parramatta NSW 2150",
    "addr:housenumber":"2j;222",
    "addr:postcode":"2150",
    "addr:street":"Greenway Plz;Church",
    "iso:country":"AU",
    "sg:address":"2J Greenway Plz, 222 Church",
    "sg:city":"Parramatta",
    "sg:classifiers":[
        {
            "category":"Health Services",
            "subcategory":"Optometrist",
            "type":"Services"
        }
    ],
    "sg:phone":"+61 2 9891 2020",
    "sg:postcode":"2150",
    "sg:province":"NSW",
    "wof:name":"Nick Papadopoulos",
    "wof:placetype":"venue"
},
  "geometry": {"coordinates":[151.12948608400001,-33.754699707],"type":"Point"}
}