{
  "type": "Feature",
  "properties": {
    "addr:full":"83 Heins Rd Bahrs Scrub QLD 4207",
    "addr:housenumber":"83",
    "addr:postcode":"4207",
    "addr:street":"Heins Rd",
    "iso:country":"AU",
    "sg:address":"83 Heins Rd",
    "sg:city":"Bahrs Scrub",
    "sg:classifiers":[
        {
            "category":"Health Services",
            "subcategory":"Health Practitioner",
            "type":"Services"
        }
    ],
    "sg:phone":"+61 7 3382 6953",
    "sg:postcode":"4207",
    "sg:province":"QLD",
    "sg:tags":[
        "reiki"
    ],
    "wof:name":"Enviro Energy",
    "wof:placetype":"venue"
},
  "geometry": {"coordinates":[153.15406799300001,-27.7372207642],"type":"Point"}
}