{
  "type": "Feature",
  "properties": {
    "addr:full":"155 Warrigal Rd Burwood VIC 3125",
    "addr:housenumber":"155",
    "addr:postcode":"3125",
    "addr:street":"Warrigal Rd",
    "iso:country":"AU",
    "sg:address":"155 Warrigal Rd",
    "sg:city":"Burwood",
    "sg:classifiers":[
        {
            "category":"Social Services",
            "subcategory":"Retirement Home",
            "type":"Services"
        }
    ],
    "sg:phone":"+61 3 9808 6733",
    "sg:postcode":"3125",
    "sg:province":"VIC",
    "sg:tags":[
        "village"
    ],
    "wof:name":"Cameron Close",
    "wof:placetype":"venue"
},
  "geometry": {"coordinates":[145.09724426299999,-37.842300415],"type":"Point"}
}