{
  "type": "Feature",
  "properties": {
    "iso:country":"AU",
    "sg:address":"164 Aumuller St",
    "sg:city":"Cairns",
    "sg:classifiers":[
        {
            "category":"Shopping",
            "subcategory":"Beauty & Cosmetics",
            "type":"Retail Goods"
        }
    ],
    "sg:phone":"+61 7 4041 1200",
    "sg:postcode":"4870",
    "sg:province":"QLD",
    "sg:tags":[
        "equipment",
        "salon",
        "supply"
    ],
    "wof:name":"Norris",
    "wof:placetype":"venue"
},
  "geometry": {"coordinates":[145.76065063499999,-16.9328193665],"type":"Point"}
}