{
  "type": "Feature",
  "properties": {
    "addr:full":"124 Avenue Rd Mosman NSW 2088",
    "addr:housenumber":"124",
    "addr:postcode":"2088",
    "addr:street":"Avenue Rd",
    "iso:country":"AU",
    "sg:address":"124 Avenue Rd",
    "sg:city":"Mosman",
    "sg:classifiers":[
        {
            "category":"Personal",
            "subcategory":"Beauty Salon",
            "type":"Services"
        }
    ],
    "sg:phone":"+61 2 9968 4270",
    "sg:postcode":"2088",
    "sg:province":"NSW",
    "sg:tags":[
        "supply",
        "artist",
        "make-up"
    ],
    "wof:name":"Body Studio The",
    "wof:placetype":"venue"
},
  "geometry": {"coordinates":[151.24249267600001,-33.8304634094],"type":"Point"}
}