{
  "type": "Feature",
  "properties": {
    "addr:full":"91 Perseverance St West Wyalong NSW 2671",
    "addr:housenumber":"91",
    "addr:postcode":"2671",
    "addr:street":"Perseverance St West",
    "iso:country":"AU",
    "sg:address":"91 Perseverance St",
    "sg:city":"West Wyalong",
    "sg:classifiers":[
        {
            "category":"Arena",
            "subcategory":"Sports Club",
            "type":"Entertainment"
        }
    ],
    "sg:phone":"+61 2 6972 3431",
    "sg:postcode":"2671",
    "sg:province":"NSW",
    "sg:tags":[
        "league",
        "rugby"
    ],
    "wof:name":"West Wyalong Rugby League Football Club",
    "wof:placetype":"venue"
},
  "geometry": {"coordinates":[147.21081543,-33.92943573],"type":"Point"}
}