{
  "type": "Feature",
  "properties": {
    "addr:full":"1 Emplacement Crs Hamilton Hill WA 6163",
    "addr:housenumber":"1",
    "addr:postcode":"6163",
    "addr:street":"Emplacement Crs",
    "iso:country":"AU",
    "sg:address":"1 Emplacement Crs",
    "sg:city":"Hamilton Hill",
    "sg:classifiers":[
        {
            "category":"Health Services",
            "subcategory":"Health Practitioner",
            "type":"Services"
        }
    ],
    "sg:phone":"+61 8 9335 3188",
    "sg:postcode":"6163",
    "sg:province":"WA",
    "sg:tags":[
        "naturopath"
    ],
    "wof:name":"Colonic Health Fremantle",
    "wof:placetype":"venue"
},
  "geometry": {"coordinates":[115.77831999999999,-32.080891],"type":"Point"}
}