{
  "type": "Feature",
  "properties": {
    "iso:country":"AU",
    "sg:address":"130 Lake St",
    "sg:city":"Cairns",
    "sg:classifiers":[
        {
            "category":"Health Services",
            "subcategory":"Doctor",
            "type":"Services"
        }
    ],
    "sg:phone":"+61 7 4046 5629",
    "sg:postcode":"4870",
    "sg:province":"QLD",
    "sg:tags":[
        "medical",
        "practitioner"
    ],
    "wof:name":"Natural Family Planning",
    "wof:placetype":"venue"
},
  "geometry": {"coordinates":[145.771774292,-16.9175128937],"type":"Point"}
}