{
  "type": "Feature",
  "properties": {
    "addr:full":"Greenbah Rd Moree NSW 2400",
    "addr:postcode":"2400",
    "addr:street":"Greenbah Rd",
    "iso:country":"AU",
    "sg:address":"Greenbah Rd",
    "sg:city":"Moree",
    "sg:classifiers":[
        {
            "category":"Autos & Motor Vehicles",
            "subcategory":"Auto Supplies",
            "type":"Retail Goods"
        }
    ],
    "sg:phone":"+61 2 6752 7366",
    "sg:postcode":"2400",
    "sg:province":"NSW",
    "sg:tags":[
        "oil",
        "spirit"
    ],
    "wof:name":"Mobil Oil Aust Distributors",
    "wof:placetype":"venue"
},
  "geometry": {"coordinates":[149.82818603499999,-29.4621391296],"type":"Point"}
}