{
  "type": "Feature",
  "properties": {
    "addr:full":"Aap Centre, Level 22, 259 George St Sydney NSW 2000",
    "addr:housenumber":"259",
    "addr:postcode":"2000",
    "addr:street":"George St",
    "iso:country":"AU",
    "sg:address":"Aap Centre, Level 22, 259 George St",
    "sg:city":"Sydney",
    "sg:classifiers":[
        {
            "category":"Professional",
            "subcategory":"Computer Services",
            "type":"Services"
        }
    ],
    "sg:phone":"+61 2 9255 7820",
    "sg:postcode":"2000",
    "sg:province":"NSW",
    "sg:tags":[
        "package",
        "software"
    ],
    "wof:name":"Hyperion Solutions Corporation",
    "wof:placetype":"venue"
},
  "geometry": {"coordinates":[151.207305908,-33.8637084961],"type":"Point"}
}