{
  "type": "Feature",
  "properties": {
    "addr:full":"Kennedy St Condamine QLD 4416",
    "addr:postcode":"4416",
    "addr:street":"Kennedy St",
    "iso:country":"AU",
    "sg:address":"Kennedy St",
    "sg:city":"Condamine",
    "sg:classifiers":[
        {
            "category":"Education",
            "subcategory":"School",
            "type":"Public Place"
        }
    ],
    "sg:phone":"+61 7 4627 7147",
    "sg:postcode":"4416",
    "sg:province":"QLD",
    "sg:tags":[
        "state",
        "except",
        "nsw"
    ],
    "wof:name":"Condamine Primary",
    "wof:placetype":"venue"
},
  "geometry": {"coordinates":[150.13438400000001,-26.92609],"type":"Point"}
}