{
  "type": "Feature",
  "properties": {
    "iso:country":"AU",
    "sg:address":"Lot 31 Statton Drv",
    "sg:city":"Traralgon",
    "sg:classifiers":[
        {
            "category":"Food & Beverages",
            "subcategory":"Bakery",
            "type":"Retail Goods"
        }
    ],
    "sg:phone":"+61 1300 366 379",
    "sg:postcode":"3844",
    "sg:province":"VIC",
    "sg:tags":[
        "baker"
    ],
    "wof:name":"Goodman Fielder",
    "wof:placetype":"venue"
},
  "geometry": {"coordinates":[146.564361572,-38.1884117126],"type":"Point"}
}