{
  "type": "Feature",
  "properties": {
    "addr:full":"36 Grafton St Cairns QLD 4870",
    "addr:housenumber":"36",
    "addr:postcode":"4870",
    "addr:street":"Grafton St",
    "iso:country":"AU",
    "sg:address":"36 Grafton St",
    "sg:city":"Cairns",
    "sg:classifiers":[
        {
            "category":"Professional",
            "subcategory":"Management & Consulting",
            "type":"Services"
        }
    ],
    "sg:phone":"+61 7 4040 7100",
    "sg:postcode":"4870",
    "sg:province":"QLD",
    "sg:tags":[
        "consultant"
    ],
    "wof:name":"Kleinhardt Pty Ltd",
    "wof:placetype":"venue"
},
  "geometry": {"coordinates":[145.771682739,-16.9189968109],"type":"Point"}
}