{
  "type": "Feature",
  "properties": {
    "addr:full":"Fcty 3/ 71 Tulip St Sandringham VIC 3191",
    "addr:housenumber":"/ 71",
    "addr:postcode":"3191",
    "addr:street":"Tulip St",
    "iso:country":"AU",
    "sg:address":"Fcty 3/ 71 Tulip St",
    "sg:city":"Sandringham",
    "sg:classifiers":[
        {
            "category":"Utilities",
            "subcategory":"Electric",
            "type":"Services"
        }
    ],
    "sg:phone":"+61 3 9585 7608",
    "sg:postcode":"3191",
    "sg:province":"VIC",
    "sg:tags":[
        "electrical",
        "contractor"
    ],
    "wof:name":"S.A.S. Electrics Pty Ltd",
    "wof:placetype":"venue"
},
  "geometry": {"coordinates":[145.03114318900001,-37.9632949829],"type":"Point"}
}