{
  "type": "Feature",
  "properties": {
    "addr:full":"PO Box 3182 South Brisbane QLD 4101",
    "addr:postcode":"4101",
    "iso:country":"AU",
    "sg:address":"PO Box 3182",
    "sg:city":"South Brisbane",
    "sg:classifiers":[
        {
            "category":"Health Services",
            "subcategory":"Doctor",
            "type":"Services"
        }
    ],
    "sg:phone":"+61 7 3303 8785",
    "sg:postcode":"4101",
    "sg:province":"QLD",
    "sg:tags":[
        "occupational",
        "safety"
    ],
    "wof:name":"Safety and Security Australia Pty Ltd",
    "wof:placetype":"venue"
},
  "geometry": {"coordinates":[153.01502990700001,-27.4757900238],"type":"Point"}
}