{
  "type": "Feature",
  "properties": {
    "iso:country":"AU",
    "sg:address":"140 Old Bells Line Of Rd",
    "sg:city":"Kurrajong",
    "sg:classifiers":[
        {
            "category":"Education",
            "subcategory":"Kindergarten",
            "type":"Public Place"
        }
    ],
    "sg:phone":"+61 2 4573 1486",
    "sg:postcode":"2758",
    "sg:province":"NSW",
    "sg:tags":[
        "pre-schools"
    ],
    "wof:name":"Bellbird Kindergarten",
    "wof:placetype":"venue"
},
  "geometry": {"coordinates":[150.66131591800001,-33.550994873],"type":"Point"}
}