{
  "type": "Feature",
  "properties": {
    "addr:full":"21 Swan Rd Morwell VIC 3840",
    "addr:housenumber":"21",
    "addr:postcode":"3840",
    "addr:street":"Swan Rd",
    "iso:country":"AU",
    "sg:address":"21 Swan Rd",
    "sg:city":"Morwell",
    "sg:classifiers":[
        {
            "category":"Wholesale",
            "subcategory":"Machinery & Supplies",
            "type":"Manufacturing & Wholesale Goods"
        }
    ],
    "sg:phone":"+61 3 5134 4288",
    "sg:postcode":"3840",
    "sg:province":"VIC",
    "sg:tags":[
        "equipment",
        "system",
        "elevating",
        "conveying"
    ],
    "wof:name":"Sandvik Materials Handling Pty Ltd",
    "wof:placetype":"venue"
},
  "geometry": {"coordinates":[146.44337463400001,-38.239276886],"type":"Point"}
}