{
  "type": "Feature",
  "properties": {
    "addr:full":"3 Acacia Crt Stonyfell SA 5066",
    "addr:housenumber":"3",
    "addr:postcode":"5066",
    "addr:street":"Acacia Crt",
    "iso:country":"AU",
    "sg:address":"3 Acacia Crt",
    "sg:city":"Stonyfell",
    "sg:classifiers":[
        {
            "category":"Building & Trades",
            "subcategory":"Construction",
            "type":"Services"
        }
    ],
    "sg:phone":"+61 8 8273 5150",
    "sg:postcode":"5066",
    "sg:province":"SA",
    "sg:tags":[
        "contractor"
    ],
    "wof:name":"Winkler & Arndt Homes",
    "wof:placetype":"venue"
},
  "geometry": {"coordinates":[138.67376709000001,-34.9376792908],"type":"Point"}
}