{
  "type": "Feature",
  "properties": {
    "iso:country":"AU",
    "sg:address":"46 Crockford St",
    "sg:city":"Northgate",
    "sg:classifiers":[
        {
            "category":"Utilities",
            "subcategory":"Recycling",
            "type":"Services"
        }
    ],
    "sg:phone":"+61 7 3266 6466",
    "sg:postcode":"4013",
    "sg:province":"QLD",
    "wof:name":"SimsMetal",
    "wof:placetype":"venue"
},
  "geometry": {"coordinates":[153.07754516599999,-27.3862133026],"type":"Point"}
}