{
  "type": "Feature",
  "properties": {
    "addr:full":"19 Welby St Eastwood NSW 2122",
    "addr:housenumber":"19",
    "addr:postcode":"2122",
    "addr:street":"Welby St",
    "iso:country":"AU",
    "sg:address":"19 Welby St",
    "sg:city":"Eastwood",
    "sg:classifiers":[
        {
            "category":"Social Services",
            "subcategory":"Child Care",
            "type":"Services"
        }
    ],
    "sg:phone":"+61 2 9874 5717",
    "sg:postcode":"2122",
    "sg:province":"NSW",
    "wof:name":"Red Robin Kindergarten",
    "wof:placetype":"venue"
},
  "geometry": {"coordinates":[151.09054565400001,-33.7903900146],"type":"Point"}
}