{
  "type": "Feature",
  "properties": {
    "iso:country":"AU",
    "sg:address":"PO Box 642",
    "sg:city":"Mitchell",
    "sg:classifiers":[
        {
            "category":"Communications",
            "subcategory":"News Services",
            "type":"Services"
        }
    ],
    "sg:phone":"+61 2 6230 4844",
    "sg:postcode":"2911",
    "sg:province":"ACT",
    "sg:tags":[
        "information",
        "tourist",
        "attractions"
    ],
    "wof:name":"Capital Educational Tours Services",
    "wof:placetype":"venue"
},
  "geometry": {"coordinates":[149.13471984899999,-35.2194900513],"type":"Point"}
}