{
  "type": "Feature",
  "properties": {
    "addr:full":"41 Muskwood St Capalaba QLD 4157",
    "addr:housenumber":"41",
    "addr:postcode":"4157",
    "addr:street":"Muskwood St",
    "iso:country":"AU",
    "sg:address":"41 Muskwood St",
    "sg:city":"Capalaba",
    "sg:classifiers":[
        {
            "category":"Shopping",
            "subcategory":"Party Supplies",
            "type":"Retail Goods"
        }
    ],
    "sg:phone":"+61 7 3245 2247",
    "sg:postcode":"4157",
    "sg:province":"QLD",
    "sg:tags":[
        "toilet",
        "portable"
    ],
    "wof:name":"Knightfield Maintenance & Service",
    "wof:placetype":"venue"
},
  "geometry": {"coordinates":[153.20036315900001,-27.5432662964],"type":"Point"}
}