{
  "type": "Feature",
  "properties": {
    "iso:country":"AU",
    "sg:address":"14 Scullen Ave",
    "sg:city":"Innisfail",
    "sg:classifiers":[
        {
            "category":"Education",
            "subcategory":"Kindergarten",
            "type":"Public Place"
        }
    ],
    "sg:phone":"+61 7 4061 2671",
    "sg:postcode":"4860",
    "sg:province":"QLD",
    "sg:tags":[
        "pre-schools"
    ],
    "wof:name":"C&K Innisfail Community Kindergarten & Preschool",
    "wof:placetype":"venue"
},
  "geometry": {"coordinates":[146.02572631800001,-17.5322914124],"type":"Point"}
}