{
  "type": "Feature",
  "properties": {
    "addr:full":"150 White St Mordialloc VIC 3195",
    "addr:housenumber":"150",
    "addr:postcode":"3195",
    "addr:street":"White St",
    "iso:country":"AU",
    "sg:address":"150 White St",
    "sg:city":"Mordialloc",
    "sg:classifiers":[
        {
            "category":"Retail",
            "subcategory":"Auto Repair",
            "type":"Services"
        }
    ],
    "sg:phone":"+61 3 9580 6996",
    "sg:postcode":"3195",
    "sg:province":"VIC",
    "sg:tags":[
        "beater",
        "painter",
        "panel"
    ],
    "wof:name":"Lombardi Smash Repairs",
    "wof:placetype":"venue"
},
  "geometry": {"coordinates":[145.085327148,-37.9984703064],"type":"Point"}
}