{
  "type": "Feature",
  "properties": {
    "addr:full":"27- 29 Watt St Newcastle NSW 2300",
    "addr:housenumber":"29",
    "addr:postcode":"2300",
    "addr:street":"Watt St",
    "iso:country":"AU",
    "sg:address":"27- 29 Watt St",
    "sg:city":"Newcastle",
    "sg:classifiers":[
        {
            "category":"Insurance",
            "subcategory":"Hazard Insurance",
            "type":"Services"
        }
    ],
    "sg:phone":"+61 1300 302 923",
    "sg:postcode":"2300",
    "sg:province":"NSW",
    "sg:tags":[
        "loss",
        "adjuster",
        "assessor"
    ],
    "wof:name":"Hughes G & Associates",
    "wof:placetype":"venue"
},
  "geometry": {"coordinates":[151.78433200000001,-32.928307],"type":"Point"}
}