{
  "type": "Feature",
  "properties": {
    "iso:country":"AU",
    "sg:address":"78-80 Tasman St",
    "sg:city":"Kurnell",
    "sg:classifiers":[
        {
            "category":"Autos & Motor Vehicles",
            "subcategory":"Boat Sales",
            "type":"Retail Goods"
        }
    ],
    "sg:phone":"+61 2 9668 8488",
    "sg:postcode":"2231",
    "sg:province":"NSW",
    "sg:tags":[
        "equipment",
        "yacht"
    ],
    "wof:name":"CST Composites",
    "wof:placetype":"venue"
},
  "geometry": {"coordinates":[151.201904297,-34.0128250122],"type":"Point"}
}