{
  "type": "Feature",
  "properties": {
    "addr:full":"Unit 4, 8- 10 Yandina Rd Gosford West NSW 2250",
    "addr:housenumber":"8 10",
    "addr:postcode":"2250",
    "addr:street":"Yandina Rd",
    "iso:country":"AU",
    "sg:address":"Unit 4, 8- 10 Yandina Rd",
    "sg:city":"Gosford West",
    "sg:classifiers":[
        {
            "category":"Building & Trades",
            "subcategory":"Plumbing",
            "type":"Services"
        }
    ],
    "sg:phone":"+61 2 4323 4493",
    "sg:postcode":"2250",
    "sg:province":"NSW",
    "sg:tags":[
        "equipment",
        "valves"
    ],
    "wof:name":"Gemu Australia Pty Ltd",
    "wof:placetype":"venue"
},
  "geometry": {"coordinates":[151.31817626899999,-33.4183235168],"type":"Point"}
}