{
  "type": "Feature",
  "properties": {
    "addr:full":"PO Box 8175 Werrington NSW 2747",
    "addr:postcode":"2747",
    "iso:country":"AU",
    "sg:address":"PO Box 8175",
    "sg:city":"Werrington",
    "sg:classifiers":[
        {
            "category":"Organizations",
            "subcategory":"Membership Organization",
            "type":"Services"
        }
    ],
    "sg:phone":"+61 418 447 409",
    "sg:postcode":"2747",
    "sg:province":"NSW",
    "sg:tags":[
        "club",
        "car"
    ],
    "wof:name":"Austin A40 Car Club of Australia",
    "wof:placetype":"venue"
},
  "geometry": {"coordinates":[150.74632263199999,-33.7571716309],"type":"Point"}
}