{
  "type": "Feature",
  "properties": {
    "addr:full":"223 Namatjira Drv Fisher ACT 2611",
    "addr:housenumber":"223",
    "addr:postcode":"2611",
    "addr:street":"Namatjira Drv",
    "iso:country":"AU",
    "sg:address":"223 Namatjira Drv",
    "sg:city":"Fisher",
    "sg:classifiers":[
        {
            "category":"Building & Trades",
            "subcategory":"Plumbing",
            "type":"Services"
        }
    ],
    "sg:phone":"+61 2 6288 1076",
    "sg:postcode":"2611",
    "sg:province":"ACT",
    "sg:tags":[
        "plumber",
        "gasfitters"
    ],
    "wof:name":"Waugh B",
    "wof:placetype":"venue"
},
  "geometry": {"coordinates":[149.05137634299999,-35.3686408997],"type":"Point"}
}