{
  "type": "Feature",
  "properties": {
    "iso:country":"AU",
    "sg:address":"243 Newcastle St",
    "sg:city":"East Maitland",
    "sg:classifiers":[
        {
            "category":"Building & Trades",
            "subcategory":"Landscaping Services",
            "type":"Services"
        }
    ],
    "sg:phone":"+61 2 4934 5400",
    "sg:postcode":"2323",
    "sg:province":"NSW",
    "sg:tags":[
        "consultant"
    ],
    "wof:name":"Smark Ask",
    "wof:placetype":"venue"
},
  "geometry": {"coordinates":[151.58711242699999,-32.7534675598],"type":"Point"}
}