{
  "type": "Feature",
  "properties": {
    "iso:country":"AU",
    "sg:address":"Unit 7 9 Hudson Ave",
    "sg:city":"Castle Hill",
    "sg:classifiers":[
        {
            "category":"Education",
            "subcategory":"Junior College",
            "type":"Public Place"
        }
    ],
    "sg:phone":"+61 2 9899 5741",
    "sg:postcode":"2154",
    "sg:province":"NSW",
    "sg:tags":[
        "wholesaler",
        "school",
        "mfrs",
        "uniform"
    ],
    "wof:name":"Kidcab Clothing Manufacturers",
    "wof:placetype":"venue"
},
  "geometry": {"coordinates":[150.97482299800001,-33.7295227051],"type":"Point"}
}