{
  "type": "Feature",
  "properties": {
    "iso:country":"AU",
    "sg:address":"45 Orth St",
    "sg:city":"Kingswood",
    "sg:classifiers":[
        {
            "category":"Health Services",
            "subcategory":"Doctor",
            "type":"Services"
        }
    ],
    "sg:phone":"+61 2 4721 4077",
    "sg:postcode":"2747",
    "sg:province":"NSW",
    "sg:tags":[
        "medical",
        "practitioner"
    ],
    "wof:name":"McLean A.S. Associate Professor",
    "wof:placetype":"venue"
},
  "geometry": {"coordinates":[150.71888732900001,-33.7604293823],"type":"Point"}
}