{
  "type": "Feature",
  "properties": {
    "iso:country":"AU",
    "sg:address":"PO Box 791 Kyneton",
    "sg:city":"Kyneton",
    "sg:classifiers":[
        {
            "category":"Utilities",
            "subcategory":"Electric",
            "type":"Services"
        }
    ],
    "sg:phone":"+61 408 036 833",
    "sg:postcode":"3444",
    "sg:province":"VIC",
    "sg:tags":[
        "electrical",
        "contractor"
    ],
    "wof:name":"High Beam Electrical",
    "wof:placetype":"venue"
},
  "geometry": {"coordinates":[144.456954956,-37.2511405945],"type":"Point"}
}