{
  "type": "Feature",
  "properties": {
    "addr:full":"151 Macquarie St Sydney NSW 2000",
    "addr:housenumber":"151",
    "addr:postcode":"2000",
    "addr:street":"Macquarie St",
    "iso:country":"AU",
    "sg:address":"151 Macquarie St",
    "sg:city":"Sydney",
    "sg:classifiers":[
        {
            "category":"Banks & Credit Unions",
            "subcategory":"Financial Services",
            "type":"Services"
        }
    ],
    "sg:phone":"+61 2 9241 4576",
    "sg:postcode":"2000",
    "sg:province":"NSW",
    "sg:tags":[
        "financier"
    ],
    "wof:name":"First Sydney Capital Limited",
    "wof:placetype":"venue"
},
  "geometry": {"coordinates":[151.212524414,-33.865032196],"type":"Point"}
}