{
  "type": "Feature",
  "properties": {
    "iso:country":"AU",
    "sg:address":"42B Chetwynd St",
    "sg:city":"Loganholme",
    "sg:classifiers":[
        {
            "category":"Shopping",
            "subcategory":"Stationery & Office Supplies",
            "type":"Retail Goods"
        }
    ],
    "sg:phone":"+61 7 3801 4279",
    "sg:postcode":"4129",
    "sg:province":"QLD",
    "sg:tags":[
        "packaging",
        "equipment",
        "sealing",
        "filling"
    ],
    "wof:name":"Makum Pty Ltd",
    "wof:placetype":"venue"
},
  "geometry": {"coordinates":[153.19036865199999,-27.6788692474],"type":"Point"}
}