{
  "type": "Feature",
  "properties": {
    "addr:full":"Cnr Wright St & Hampton Ave Sunshine VIC 3020",
    "addr:postcode":"3020",
    "addr:street":"Cnr Wright St & Hampton Ave",
    "iso:country":"AU",
    "sg:address":"Cnr Wright St & Hampton Ave",
    "sg:city":"Sunshine",
    "sg:classifiers":[
        {
            "category":"Retail",
            "subcategory":"Auto Repair",
            "type":"Services"
        }
    ],
    "sg:phone":"+61 3 9311 9290",
    "sg:postcode":"3020",
    "sg:province":"VIC",
    "sg:tags":[
        "beater",
        "painter",
        "panel"
    ],
    "wof:name":"F W & M Vehicle Repairs Pty Ltd",
    "wof:placetype":"venue"
},
  "geometry": {"coordinates":[144.83157299999999,-37.795998],"type":"Point"}
}