{
  "type": "Feature",
  "properties": {
    "addr:full":"251 Payneham Rd Joslin SA 5070",
    "addr:housenumber":"251",
    "addr:postcode":"5070",
    "addr:street":"Payneham Rd",
    "iso:country":"AU",
    "sg:address":"251 Payneham Rd",
    "sg:city":"Joslin",
    "sg:classifiers":[
        {
            "category":"Health Services",
            "subcategory":"Nursing And Care Facility",
            "type":"Services"
        }
    ],
    "sg:phone":"+61 8 8362 8974",
    "sg:postcode":"5070",
    "sg:province":"SA",
    "sg:tags":[
        "home"
    ],
    "wof:name":"Roselin Court",
    "wof:placetype":"venue"
},
  "geometry": {"coordinates":[138.633300781,-34.9029388428],"type":"Point"}
}