{
  "type": "Feature",
  "properties": {
    "addr:full":"9 Beulah Rd Norwood SA 5067",
    "addr:housenumber":"9",
    "addr:postcode":"5067",
    "addr:street":"Beulah Rd",
    "iso:country":"AU",
    "sg:address":"9 Beulah Rd",
    "sg:city":"Norwood",
    "sg:classifiers":[
        {
            "category":"Professional",
            "subcategory":"Business Services",
            "type":"Services"
        }
    ],
    "sg:phone":"+61 8 8490 4000",
    "sg:postcode":"5067",
    "sg:province":"SA",
    "sg:tags":[
        "consultant",
        "leasing"
    ],
    "wof:name":"Business Bundles",
    "wof:placetype":"venue"
},
  "geometry": {"coordinates":[138.63163757300001,-34.9181632996],"type":"Point"}
}