{
  "type": "Feature",
  "properties": {
    "iso:country":"AU",
    "sg:address":"Shop 4/ 38 Brantome St",
    "sg:city":"Gisborne",
    "sg:classifiers":[
        {
            "category":"Deli",
            "type":"Food & Drink"
        }
    ],
    "sg:phone":"+61 3 5428 1944",
    "sg:postcode":"3437",
    "sg:province":"VIC",
    "sg:tags":[
        "delicatessen"
    ],
    "wof:name":"The Deli",
    "wof:placetype":"venue"
},
  "geometry": {"coordinates":[144.58949279800001,-37.4872322083],"type":"Point"}
}