{
  "type": "Feature",
  "properties": {
    "addr:full":"32 Brook Rd Darlington WA 6070",
    "addr:housenumber":"32",
    "addr:postcode":"6070",
    "addr:street":"Brook Rd",
    "iso:country":"AU",
    "sg:address":"32 Brook Rd",
    "sg:city":"Darlington",
    "sg:classifiers":[
        {
            "category":"Mining & Drilling",
            "type":"Manufacturing & Wholesale Goods"
        }
    ],
    "sg:phone":"+61 8 9299 7433",
    "sg:postcode":"6070",
    "sg:province":"WA",
    "sg:tags":[
        "geologist"
    ],
    "wof:name":"Chris Arnold Resource Consultants",
    "wof:placetype":"venue"
},
  "geometry": {"coordinates":[116.081001282,-31.9192085266],"type":"Point"}
}