{
  "type": "Feature",
  "properties": {
    "addr:full":"Shops 6/ 5 Lavelle St Nerang QLD 4211",
    "addr:housenumber":"shops 6 / 5",
    "addr:postcode":"4211",
    "addr:street":"Lavelle St",
    "iso:country":"AU",
    "sg:address":"Shops 6/ 5 Lavelle St",
    "sg:city":"Nerang",
    "sg:classifiers":[
        {
            "category":"Real Estate",
            "subcategory":"Real Estate Agent",
            "type":"Services"
        }
    ],
    "sg:phone":"+61 7 5596 3833",
    "sg:postcode":"4211",
    "sg:province":"QLD",
    "wof:name":"Leaders Realty Pty Ltd",
    "wof:placetype":"venue"
},
  "geometry": {"coordinates":[153.33682250999999,-27.9907608032],"type":"Point"}
}