{
  "type": "Feature",
  "properties": {
    "addr:full":"U2/ 20 Duerdin St Clayton VIC 3168",
    "addr:housenumber":"20",
    "addr:postcode":"3168",
    "addr:street":"U2 /;Duerdin St",
    "iso:country":"AU",
    "sg:address":"U2/ 20 Duerdin St",
    "sg:city":"Clayton",
    "sg:classifiers":[
        {
            "category":"Education",
            "subcategory":"Music School",
            "type":"Public Place"
        }
    ],
    "sg:phone":"+61 3 9558 6360",
    "sg:postcode":"3168",
    "sg:province":"VIC",
    "sg:tags":[
        "teacher"
    ],
    "wof:name":"Mr Music",
    "wof:placetype":"venue"
},
  "geometry": {"coordinates":[145.141967773,-37.9100532532],"type":"Point"}
}