{
  "type": "Feature",
  "properties": {
    "addr:full":"PO Box 1040 Stirling SA 5152",
    "addr:postcode":"5152",
    "iso:country":"AU",
    "sg:address":"PO Box 1040",
    "sg:city":"Stirling",
    "sg:classifiers":[
        {
            "category":"Professional",
            "subcategory":"Art Services",
            "type":"Services"
        }
    ],
    "sg:phone":"+61 8 8339 6680",
    "sg:postcode":"5152",
    "sg:province":"SA",
    "sg:tags":[
        "commercial",
        "artist"
    ],
    "wof:name":"Talk Graphics",
    "wof:placetype":"venue"
},
  "geometry": {"coordinates":[138.72253418,-35.0080490112],"type":"Point"}
}