{
  "type": "Feature",
  "properties": {
    "iso:country":"AU",
    "sg:address":"4 Woodlans Rd",
    "sg:city":"Taren Point",
    "sg:classifiers":[
        {
            "category":"Building & Trades",
            "subcategory":"Construction",
            "type":"Services"
        }
    ],
    "sg:phone":"+61 2 9531 1196",
    "sg:postcode":"2229",
    "sg:province":"NSW",
    "sg:tags":[
        "contractor"
    ],
    "wof:name":"Brooks G B K",
    "wof:placetype":"venue"
},
  "geometry": {"coordinates":[151.12701415999999,-34.0117225647],"type":"Point"}
}