{
  "type": "Feature",
  "properties": {
    "addr:full":"9 Damala St Doncaster East VIC 3109",
    "addr:housenumber":"9",
    "addr:postcode":"3109",
    "addr:street":"Damala St",
    "iso:country":"AU",
    "sg:address":"9 Damala St",
    "sg:city":"Doncaster East",
    "sg:classifiers":[
        {
            "category":"Banks & Credit Unions",
            "subcategory":"Financial Services",
            "type":"Services"
        }
    ],
    "sg:phone":"+61 3 9842 2710",
    "sg:postcode":"3109",
    "sg:province":"VIC",
    "sg:tags":[
        "registrar",
        "share"
    ],
    "wof:name":"Registry Services Australia Pty Ltd",
    "wof:placetype":"venue"
},
  "geometry": {"coordinates":[145.15385437,-37.7941894531],"type":"Point"}
}