{
  "type": "Feature",
  "properties": {
    "addr:full":"1 Ward Rd Rockingham WA 6168",
    "addr:housenumber":"1",
    "addr:postcode":"6168",
    "addr:street":"Ward Rd",
    "iso:country":"AU",
    "sg:address":"1 Ward Rd",
    "sg:city":"Rockingham",
    "sg:classifiers":[
        {
            "category":"Manufacturing",
            "subcategory":"Chemicals & Compounds",
            "type":"Manufacturing & Wholesale Goods"
        }
    ],
    "sg:phone":"+61 8 9439 9000",
    "sg:postcode":"6168",
    "sg:province":"WA",
    "sg:tags":[
        "industrial"
    ],
    "wof:name":"Doral Specialty Chemicals Pty Ltd",
    "wof:placetype":"venue"
},
  "geometry": {"coordinates":[115.761871,-32.257683],"type":"Point"}
}