{
  "type": "Feature",
  "properties": {
    "addr:full":"Creighton Rd Katandra West VIC 3634",
    "addr:postcode":"3634",
    "addr:street":"Creighton Rd",
    "iso:country":"AU",
    "sg:address":"Creighton Rd",
    "sg:city":"Katandra West",
    "sg:classifiers":[
        {
            "category":"Professional",
            "subcategory":"Business Services",
            "type":"Services"
        }
    ],
    "sg:phone":"+61 3 5828 3364",
    "sg:postcode":"3634",
    "sg:province":"VIC",
    "sg:tags":[
        "livestock",
        "transport"
    ],
    "wof:name":"N & J.L.M. Senior",
    "wof:placetype":"venue"
},
  "geometry": {"coordinates":[145.54550170900001,-36.2172012329],"type":"Point"}
}