{
  "type": "Feature",
  "properties": {
    "addr:full":"16 Centenary Ave Moorebank NSW 2170",
    "addr:housenumber":"16",
    "addr:postcode":"2170",
    "addr:street":"Centenary Ave",
    "iso:country":"AU",
    "sg:address":"16 Centenary Ave",
    "sg:city":"Moorebank",
    "sg:classifiers":[
        {
            "category":"Shopping",
            "subcategory":"Bicycles & Sporting Goods",
            "type":"Retail Goods"
        }
    ],
    "sg:phone":"+61 2 9824 3724",
    "sg:postcode":"2170",
    "sg:province":"NSW",
    "sg:tags":[
        "chemical",
        "equipment",
        "pool",
        "swimming"
    ],
    "wof:name":"Monarch Pool Systems",
    "wof:placetype":"venue"
},
  "geometry": {"coordinates":[150.93864440900001,-33.9408302307],"type":"Point"}
}