{
  "type": "Feature",
  "properties": {
    "addr:full":"Lady Gowrie Drv ( & Esplanade) Largs Bay SA 5016",
    "addr:postcode":"5016",
    "addr:street":"Gowrie Drv & Esplanade",
    "iso:country":"AU",
    "sg:address":"Lady Gowrie Drv ( & Esplanade)",
    "sg:city":"Largs Bay",
    "sg:classifiers":[
        {
            "category":"Fast Food",
            "type":"Food & Drink"
        }
    ],
    "sg:phone":"+61 8 8449 2580",
    "sg:postcode":"5016",
    "sg:province":"SA",
    "sg:tags":[
        "away",
        "take"
    ],
    "wof:name":"Largs Bay Kiosk",
    "wof:placetype":"venue"
},
  "geometry": {"coordinates":[138.48768615700001,-34.8232765198],"type":"Point"}
}