{
  "type": "Feature",
  "properties": {
    "addr:full":"Shop 16 Aldinga Shopping Centre Aldinga SA 5173",
    "addr:housenumber":"shop 16",
    "addr:postcode":"5173",
    "iso:country":"AU",
    "sg:address":"Shop 16",
    "sg:city":"Aldinga Shopping Centre Aldinga",
    "sg:classifiers":[
        {
            "category":"Fast Food",
            "type":"Food & Drink"
        }
    ],
    "sg:phone":"+61 8 8557 7666",
    "sg:postcode":"5173",
    "sg:province":"SA",
    "sg:tags":[
        "away",
        "take"
    ],
    "wof:name":"Aldinga Central Pizza & Takeaway",
    "wof:placetype":"venue"
},
  "geometry": {"coordinates":[138.49073791500001,-35.268119812],"type":"Point"}
}