{
  "type": "Feature",
  "properties": {
    "addr:full":"52 Osmaston Rd Carine WA 6020",
    "addr:housenumber":"52",
    "addr:postcode":"6020",
    "addr:street":"Osmaston Rd",
    "iso:country":"AU",
    "sg:address":"52 Osmaston Rd",
    "sg:city":"Carine",
    "sg:classifiers":[
        {
            "category":"Home & Garden",
            "subcategory":"Building Materials",
            "type":"Retail Goods"
        }
    ],
    "sg:phone":"+61 8 9243 0243",
    "sg:postcode":"6020",
    "sg:province":"WA",
    "sg:tags":[
        "lawn",
        "cutting",
        "maintenance"
    ],
    "wof:name":"R & L Black",
    "wof:placetype":"venue"
},
  "geometry": {"coordinates":[115.772781372,-31.8499412537],"type":"Point"}
}