{
  "type": "Feature",
  "properties": {
    "addr:full":"1 Park Rd Hurstville NSW 2220",
    "addr:housenumber":"1",
    "addr:postcode":"2220",
    "addr:street":"Park Rd",
    "iso:country":"AU",
    "sg:address":"1 Park Rd",
    "sg:city":"Hurstville",
    "sg:classifiers":[
        {
            "category":"Health Services",
            "subcategory":"Health Practitioner",
            "type":"Services"
        }
    ],
    "sg:phone":"+61 2 9621 7775",
    "sg:postcode":"2220",
    "sg:province":"NSW",
    "sg:tags":[
        "psychologist"
    ],
    "wof:name":"Allen, Peter J & Associates Consulting & Clinical Psychologists",
    "wof:placetype":"venue"
},
  "geometry": {"coordinates":[151.10540771500001,-33.9662475586],"type":"Point"}
}