{
  "type": "Feature",
  "properties": {
    "addr:full":"42 Sanford St Geraldton WA 6530",
    "addr:housenumber":"42",
    "addr:postcode":"6530",
    "addr:street":"Sanford St",
    "iso:country":"AU",
    "sg:address":"42 Sanford St",
    "sg:city":"Geraldton",
    "sg:classifiers":[
        {
            "category":"Retail",
            "subcategory":"Veterinary Services",
            "type":"Services"
        }
    ],
    "sg:phone":"+61 8 9921 1797",
    "sg:postcode":"6530",
    "sg:province":"WA",
    "sg:tags":[
        "surgeon"
    ],
    "wof:name":"Geraldton Veterinary Hospital",
    "wof:placetype":"venue"
},
  "geometry": {"coordinates":[114.613037109,-28.7739658356],"type":"Point"}
}