{
  "type": "Feature",
  "properties": {
    "addr:full":"71 Ruislip St Wembley WA 6014",
    "addr:housenumber":"71",
    "addr:postcode":"6014",
    "addr:street":"Ruislip St",
    "iso:country":"AU",
    "sg:address":"71 Ruislip St",
    "sg:city":"Wembley",
    "sg:classifiers":[
        {
            "category":"Social Services",
            "subcategory":"Retirement Home",
            "type":"Services"
        }
    ],
    "sg:phone":"+61 8 9442 3444",
    "sg:postcode":"6014",
    "sg:province":"WA",
    "sg:tags":[
        "village"
    ],
    "wof:name":"Mercy Village Wembley",
    "wof:placetype":"venue"
},
  "geometry": {"coordinates":[115.822502136,-31.9367275238],"type":"Point"}
}