{
  "type": "Feature",
  "properties": {
    "addr:full":"111 Johnston St Annandale NSW 2038",
    "addr:housenumber":"111",
    "addr:postcode":"2038",
    "addr:street":"Johnston St",
    "iso:country":"AU",
    "sg:address":"111 Johnston St",
    "sg:city":"Annandale",
    "sg:classifiers":[
        {
            "category":"Personal",
            "subcategory":"Beauty Salon",
            "type":"Services"
        }
    ],
    "sg:phone":"+61 2 9660 3198",
    "sg:postcode":"2038",
    "sg:province":"NSW",
    "sg:tags":[
        "hairdresser"
    ],
    "wof:name":"Follicle Hair Studio",
    "wof:placetype":"venue"
},
  "geometry": {"coordinates":[151.17088317899999,-33.8812828064],"type":"Point"}
}