{
  "type": "Feature",
  "properties": {
    "iso:country":"AU",
    "sg:address":"Station St",
    "sg:city":"Allansford",
    "sg:classifiers":[
        {
            "category":"Building & Trades",
            "subcategory":"Equipment Rental",
            "type":"Services"
        }
    ],
    "sg:phone":"+61 3 5565 1420",
    "sg:postcode":"3277",
    "sg:province":"VIC",
    "sg:tags":[
        "demolition",
        "contractor"
    ],
    "wof:name":"Kavanagh M & C",
    "wof:placetype":"venue"
},
  "geometry": {"coordinates":[142.59573364299999,-38.3887825012],"type":"Point"}
}