{
  "type": "Feature",
  "properties": {
    "iso:country":"AU",
    "sg:address":"PO Box 173",
    "sg:city":"Ormond",
    "sg:classifiers":[
        {
            "category":"Education",
            "subcategory":"Music School",
            "type":"Public Place"
        }
    ],
    "sg:phone":"+61 3 9562 8888",
    "sg:postcode":"3204",
    "sg:province":"VIC",
    "sg:tags":[
        "choir",
        "bands",
        "orchestra"
    ],
    "wof:name":"Mop Tops The",
    "wof:placetype":"venue"
},
  "geometry": {"coordinates":[145.040344,-37.90398],"type":"Point"}
}