{
  "type": "Feature",
  "properties": {
    "addr:full":"37- 39 Cambrai Ave Engadine NSW 2233",
    "addr:housenumber":"39",
    "addr:postcode":"2233",
    "addr:street":"Cambrai Ave",
    "iso:country":"AU",
    "sg:address":"37- 39 Cambrai Ave",
    "sg:city":"Engadine",
    "sg:classifiers":[
        {
            "category":"Professional",
            "subcategory":"Printing & Photocopies",
            "type":"Services"
        }
    ],
    "sg:phone":"+61 2 9520 0559",
    "sg:postcode":"2233",
    "sg:province":"NSW",
    "sg:tags":[
        "embroidery"
    ],
    "wof:name":"Kays Custom Sportswear",
    "wof:placetype":"venue"
},
  "geometry": {"coordinates":[151.012817383,-34.0597343445],"type":"Point"}
}