{
  "type": "Feature",
  "properties": {
    "iso:country":"AU",
    "sg:address":"81a May Rd",
    "sg:city":"Lalor",
    "sg:classifiers":[
        {
            "category":"Restaurant",
            "type":"Food & Drink"
        }
    ],
    "sg:phone":"+61 3 9465 0643",
    "sg:postcode":"3075",
    "sg:province":"VIC",
    "wof:name":"Chu Quy Vietnamese Cuisine",
    "wof:placetype":"venue"
},
  "geometry": {"coordinates":[145.01739501899999,-37.67212677],"type":"Point"}
}