{
  "type": "Feature",
  "properties": {
    "iso:country":"AU",
    "sg:address":"Heritage Crt",
    "sg:city":"Oakden",
    "sg:classifiers":[
        {
            "category":"Education",
            "subcategory":"School",
            "type":"Public Place"
        }
    ],
    "sg:phone":"+61 8 8266 5122",
    "sg:postcode":"5086",
    "sg:province":"SA",
    "sg:tags":[
        "co-educational"
    ],
    "wof:name":"Heritage College",
    "wof:placetype":"venue"
},
  "geometry": {"coordinates":[138.64002990700001,-34.852897644],"type":"Point"}
}