{
  "type": "Feature",
  "properties": {
    "iso:country":"AU",
    "sg:address":"49 Main St",
    "sg:city":"Lobethal",
    "sg:classifiers":[
        {
            "category":"Health Services",
            "subcategory":"Optometrist",
            "type":"Services"
        }
    ],
    "sg:phone":"+61 8 8389 6539",
    "sg:postcode":"5241",
    "sg:province":"SA",
    "wof:name":"Upton Mostyn",
    "wof:placetype":"venue"
},
  "geometry": {"coordinates":[138.87440490700001,-34.904624939],"type":"Point"}
}