{
  "type": "Feature",
  "properties": {
    "addr:full":"268 Macquarie Rd Warners Bay NSW 2282",
    "addr:housenumber":"268",
    "addr:postcode":"2282",
    "addr:street":"Macquarie Rd",
    "iso:country":"AU",
    "sg:address":"268 Macquarie Rd",
    "sg:city":"Warners Bay",
    "sg:classifiers":[
        {
            "category":"Building & Trades",
            "subcategory":"Construction",
            "type":"Services"
        }
    ],
    "sg:phone":"+61 2 4954 5799",
    "sg:postcode":"2282",
    "sg:province":"NSW",
    "sg:tags":[
        "roof"
    ],
    "wof:name":"Metroll Building Products Pty Ltd",
    "wof:placetype":"venue"
},
  "geometry": {"coordinates":[151.65269470199999,-32.9662857056],"type":"Point"}
}