{
  "type": "Feature",
  "properties": {
    "addr:full":"77 Alfred St Charleville QLD 4470",
    "addr:housenumber":"77",
    "addr:postcode":"4470",
    "addr:street":"Alfred St",
    "iso:country":"AU",
    "sg:address":"77 Alfred St",
    "sg:city":"Charleville",
    "sg:classifiers":[
        {
            "category":"Food & Beverages",
            "subcategory":"Supermarket",
            "type":"Retail Goods"
        }
    ],
    "sg:phone":"+61 7 4654 1003",
    "sg:postcode":"4470",
    "sg:province":"QLD",
    "sg:tags":[
        "grocery",
        "store"
    ],
    "wof:name":"Food For Less",
    "wof:placetype":"venue"
},
  "geometry": {"coordinates":[146.243743897,-26.398563385],"type":"Point"}
}