{
  "type": "Feature",
  "properties": {
    "addr:full":"65 Oxford St Darlinghurst NSW 2010",
    "addr:housenumber":"65",
    "addr:postcode":"2010",
    "addr:street":"Oxford St",
    "iso:country":"AU",
    "sg:address":"65 Oxford St",
    "sg:city":"Darlinghurst",
    "sg:classifiers":[
        {
            "category":"Education",
            "subcategory":"Dance Studio",
            "type":"Public Place"
        }
    ],
    "sg:phone":"+61 2 9291 9300",
    "sg:postcode":"2010",
    "sg:province":"NSW",
    "sg:tags":[
        "instruction",
        "language"
    ],
    "wof:name":"Embassy CES",
    "wof:placetype":"venue"
},
  "geometry": {"coordinates":[151.213989258,-33.8784255981],"type":"Point"}
}