{
  "type": "Feature",
  "properties": {
    "addr:full":"Cnr Mokare Rd & Nind St Albany WA 6330",
    "addr:postcode":"6330",
    "addr:street":"Cnr Mokare Rd & Nind St",
    "iso:country":"AU",
    "sg:address":"Cnr Mokare Rd & Nind St",
    "sg:city":"Albany",
    "sg:classifiers":[
        {
            "category":"Social Services",
            "subcategory":"Child Care",
            "type":"Services"
        }
    ],
    "sg:phone":"+61 8 9841 3393",
    "sg:postcode":"6330",
    "sg:province":"WA",
    "sg:tags":[
        "support",
        "health"
    ],
    "wof:name":"Child Health Services",
    "wof:placetype":"venue"
},
  "geometry": {"coordinates":[117.899772644,-35.0073852539],"type":"Point"}
}