{
  "type": "Feature",
  "properties": {
    "addr:full":"1st Floor 522 Kingsway Miranda NSW 2228",
    "addr:housenumber":"522",
    "addr:postcode":"2228",
    "addr:street":"Kingsway Miranda",
    "iso:country":"AU",
    "sg:address":"1st Floor 522 Kingsway",
    "sg:city":"Miranda",
    "sg:classifiers":[
        {
            "category":"Professional",
            "subcategory":"Detective & Security Services",
            "type":"Services"
        }
    ],
    "sg:phone":"+61 2 9525 4644",
    "sg:postcode":"2228",
    "sg:province":"NSW",
    "sg:tags":[
        "consultant",
        "system"
    ],
    "wof:name":"Preddeys' Locksmiths",
    "wof:placetype":"venue"
},
  "geometry": {"coordinates":[151.104736328,-34.0346107483],"type":"Point"}
}