{
  "type": "Feature",
  "properties": {
    "addr:full":"51 Balmain Rd McGraths Hill NSW 2756",
    "addr:housenumber":"51",
    "addr:postcode":"2756",
    "addr:street":"Balmain Rd",
    "iso:country":"AU",
    "sg:address":"51 Balmain Rd",
    "sg:city":"McGraths Hill",
    "sg:classifiers":[
        {
            "category":"Building & Trades",
            "subcategory":"Construction",
            "type":"Services"
        }
    ],
    "sg:phone":"+61 2 4577 4321",
    "sg:postcode":"2756",
    "sg:province":"NSW",
    "sg:tags":[
        "contractor"
    ],
    "wof:name":"Tunks Constructions",
    "wof:placetype":"venue"
},
  "geometry": {"coordinates":[150.841796875,-33.6195411682],"type":"Point"}
}