{
  "type": "Feature",
  "properties": {
    "iso:country":"AU",
    "sg:address":"51 Buckingham Drv",
    "sg:city":"Wangara",
    "sg:classifiers":[
        {
            "category":"Home & Garden",
            "subcategory":"Building Materials",
            "type":"Retail Goods"
        }
    ],
    "sg:phone":"+61 8 9309 4570",
    "sg:postcode":"6065",
    "sg:province":"WA",
    "sg:tags":[
        "skylight"
    ],
    "wof:name":"Sola Skylights",
    "wof:placetype":"venue"
},
  "geometry": {"coordinates":[115.82228088399999,-31.7869510651],"type":"Point"}
}