{
  "type": "Feature",
  "properties": {
    "addr:full":"14 Third St Minlaton SA 5575",
    "addr:housenumber":"14",
    "addr:postcode":"5575",
    "addr:street":"Third St",
    "iso:country":"AU",
    "sg:address":"14 Third St",
    "sg:city":"Minlaton",
    "sg:classifiers":[
        {
            "category":"Home & Garden",
            "subcategory":"Garden Supply",
            "type":"Retail Goods"
        }
    ],
    "sg:phone":"+61 8 8853 2844",
    "sg:postcode":"5575",
    "sg:province":"SA",
    "sg:tags":[
        "nursery"
    ],
    "wof:name":"Yorkreation Garden Centre",
    "wof:placetype":"venue"
},
  "geometry": {"coordinates":[137.597732544,-34.7698898315],"type":"Point"}
}