{
  "type": "Feature",
  "properties": {
    "addr:full":"261 Raymond St Sale VIC 3850",
    "addr:housenumber":"261",
    "addr:postcode":"3850",
    "addr:street":"Raymond St",
    "iso:country":"AU",
    "sg:address":"261 Raymond St",
    "sg:city":"Sale",
    "sg:classifiers":[
        {
            "category":"Banks & Credit Unions",
            "subcategory":"Financial Services",
            "type":"Services"
        }
    ],
    "sg:phone":"+61 1800 630 705",
    "sg:postcode":"3850",
    "sg:province":"VIC",
    "sg:tags":[
        "planning"
    ],
    "wof:name":"St Andrew's Financial Services",
    "wof:placetype":"venue"
},
  "geometry": {"coordinates":[147.06544494600001,-38.1077003479],"type":"Point"}
}