{
  "type": "Feature",
  "properties": {
    "addr:full":"729 George St South Windsor NSW 2756",
    "addr:housenumber":"729",
    "addr:postcode":"2756",
    "addr:street":"George St",
    "iso:country":"AU",
    "sg:address":"729 George St",
    "sg:city":"South Windsor",
    "sg:classifiers":[
        {
            "category":"Home & Garden",
            "subcategory":"Garden Supply",
            "type":"Retail Goods"
        }
    ],
    "sg:phone":"+61 2 4572 6666",
    "sg:postcode":"2756",
    "sg:province":"NSW",
    "sg:tags":[
        "landscape"
    ],
    "wof:name":"Hawkesbury Landscape Supplies",
    "wof:placetype":"venue"
},
  "geometry": {"coordinates":[150.780975342,-33.6232566833],"type":"Point"}
}