{
  "type": "Feature",
  "properties": {
    "iso:country":"AU",
    "sg:address":"Towoomba Medical & Dental Centre, Cnr West & James Sts",
    "sg:city":"Toowoomba",
    "sg:classifiers":[
        {
            "category":"Health Services",
            "subcategory":"Health Practitioner",
            "type":"Services"
        }
    ],
    "sg:phone":"+61 7 4638 4988",
    "sg:postcode":"4350",
    "sg:province":"QLD",
    "sg:tags":[
        "physiotherapist"
    ],
    "wof:name":"Sportshouse Physiotherapy Centre",
    "wof:placetype":"venue"
},
  "geometry": {"coordinates":[151.937454,-27.594299],"type":"Point"}
}