{
  "type": "Feature",
  "properties": {
    "addr:full":"128 Burke Rd Malvern East VIC 3145",
    "addr:housenumber":"128",
    "addr:postcode":"3145",
    "addr:street":"Burke Rd",
    "iso:country":"AU",
    "sg:address":"128 Burke Rd",
    "sg:city":"Malvern East",
    "sg:classifiers":[
        {
            "category":"Shopping",
            "subcategory":"Baby Store",
            "type":"Retail Goods"
        }
    ],
    "sg:phone":"+61 3 9885 5460",
    "sg:postcode":"3145",
    "sg:province":"VIC",
    "sg:tags":[
        "wear"
    ],
    "wof:name":"Wattletree Child Childrens Wares",
    "wof:placetype":"venue"
},
  "geometry": {"coordinates":[145.05027770999999,-37.8657531738],"type":"Point"}
}