{
  "type": "Feature",
  "properties": {
    "addr:full":"26 Marigold St Margate QLD 4019",
    "addr:housenumber":"26",
    "addr:postcode":"4019",
    "addr:street":"Marigold St",
    "iso:country":"AU",
    "sg:address":"26 Marigold St",
    "sg:city":"Margate",
    "sg:classifiers":[
        {
            "category":"Professional",
            "subcategory":"Art Services",
            "type":"Services"
        }
    ],
    "sg:phone":"+61 7 3885 6012",
    "sg:postcode":"4019",
    "sg:province":"QLD",
    "sg:tags":[
        "interior",
        "decorator"
    ],
    "wof:name":"Neilson Construction & Interior Design",
    "wof:placetype":"venue"
},
  "geometry": {"coordinates":[153.09722900400001,-27.2409553528],"type":"Point"}
}