{
  "type": "Feature",
  "properties": {
    "addr:full":"PO Box 17 Winston Hills NSW 2153",
    "addr:postcode":"2153",
    "iso:country":"AU",
    "sg:address":"PO Box 17",
    "sg:city":"Winston Hills",
    "sg:classifiers":[
        {
            "category":"Building & Trades",
            "subcategory":"Construction",
            "type":"Services"
        }
    ],
    "sg:phone":"+61 2 9862 6681",
    "sg:postcode":"2153",
    "sg:province":"NSW",
    "sg:tags":[
        "renovation",
        "alterations",
        "extension",
        "contractor"
    ],
    "wof:name":"M & V Building",
    "wof:placetype":"venue"
},
  "geometry": {"coordinates":[150.97482299800001,-33.7780990601],"type":"Point"}
}