{
  "type": "Feature",
  "properties": {
    "addr:full":"619 Doncaster Rd Doncaster VIC 3108",
    "addr:housenumber":"619",
    "addr:postcode":"3108",
    "addr:street":"Doncaster Rd",
    "iso:country":"AU",
    "sg:address":"619 Doncaster Rd",
    "sg:city":"Doncaster",
    "sg:classifiers":[
        {
            "category":"Shopping",
            "subcategory":"Clothing, Apparel, & Fashions",
            "type":"Retail Goods"
        }
    ],
    "sg:phone":"+61 3 9848 2959",
    "sg:postcode":"3108",
    "sg:province":"VIC",
    "sg:tags":[
        "menswear"
    ],
    "wof:name":"Menz Mode",
    "wof:placetype":"venue"
},
  "geometry": {"coordinates":[145.09231567399999,-37.7921524048],"type":"Point"}
}