{
  "type": "Feature",
  "properties": {
    "addr:full":"83 Sturt St Adelaide SA 5000",
    "addr:housenumber":"83",
    "addr:postcode":"5000",
    "addr:street":"Sturt St",
    "iso:country":"AU",
    "sg:address":"83 Sturt St",
    "sg:city":"Adelaide",
    "sg:classifiers":[
        {
            "category":"Shopping",
            "subcategory":"News",
            "type":"Retail Goods"
        }
    ],
    "sg:phone":"+61 8 8212 0406",
    "sg:postcode":"5000",
    "sg:province":"SA",
    "sg:tags":[
        "magazine",
        "periodical"
    ],
    "wof:name":"Jazz Scene",
    "wof:placetype":"venue"
},
  "geometry": {"coordinates":[138.597198486,-34.9332084656],"type":"Point"}
}