{
  "type": "Feature",
  "properties": {
    "iso:country":"AU",
    "sg:address":"61 York St",
    "sg:city":"Subiaco",
    "sg:classifiers":[
        {
            "category":"Manufacturing",
            "subcategory":"Motor Vehicles & Parts",
            "type":"Manufacturing & Wholesale Goods"
        }
    ],
    "sg:phone":"+61 8 9381 5111",
    "sg:postcode":"6008",
    "sg:province":"WA",
    "sg:tags":[
        "replacement"
    ],
    "wof:name":"Lloyds Parts & Service",
    "wof:placetype":"venue"
},
  "geometry": {"coordinates":[115.83310699499999,-31.9463863373],"type":"Point"}
}