{
  "type": "Feature",
  "properties": {
    "addr:full":"2/ 24 Murray St Hobart TAS 7000",
    "addr:housenumber":"/ 24",
    "addr:postcode":"7000",
    "addr:street":"Murray St",
    "iso:country":"AU",
    "sg:address":"2/ 24 Murray St",
    "sg:city":"Hobart",
    "sg:classifiers":[
        {
            "category":"Professional",
            "subcategory":"Management & Consulting",
            "type":"Services"
        }
    ],
    "sg:phone":"+61 3 6223 4334",
    "sg:postcode":"7000",
    "sg:province":"TAS",
    "sg:tags":[
        "consultant"
    ],
    "wof:name":"Dowell Accounting & Business Services",
    "wof:placetype":"venue"
},
  "geometry": {"coordinates":[147.32904052699999,-42.884349823],"type":"Point"}
}