{
  "type": "Feature",
  "properties": {
    "addr:full":"Kirkham Rd Bowral NSW 2576",
    "addr:postcode":"2576",
    "addr:street":"Kirkham Rd",
    "iso:country":"AU",
    "sg:address":"Kirkham Rd",
    "sg:city":"Bowral",
    "sg:classifiers":[
        {
            "category":"Retail",
            "subcategory":"Auto Repair",
            "type":"Services"
        }
    ],
    "sg:phone":"+61 2 4862 2711",
    "sg:postcode":"2576",
    "sg:province":"NSW",
    "sg:tags":[
        "repairer",
        "motor",
        "engineer"
    ],
    "wof:name":"Highlander Off Road Centre",
    "wof:placetype":"venue"
},
  "geometry": {"coordinates":[150.41595459000001,-34.4783248901],"type":"Point"}
}