{
  "type": "Feature",
  "properties": {
    "addr:full":"PO Box 1102 Booragoon WA 6954",
    "addr:postcode":"6954",
    "iso:country":"AU",
    "sg:address":"PO Box 1102",
    "sg:city":"Booragoon",
    "sg:classifiers":[
        {
            "category":"Banks & Credit Unions",
            "subcategory":"Investment Brokerage",
            "type":"Services"
        }
    ],
    "sg:phone":"+61 1300 734 410",
    "sg:postcode":"6954",
    "sg:province":"WA",
    "sg:tags":[
        "finance",
        "broker"
    ],
    "wof:name":"Property Finance Online",
    "wof:placetype":"venue"
},
  "geometry": {"coordinates":[115.832260132,-32.0358505249],"type":"Point"}
}