{
  "type": "Feature",
  "properties": {
    "iso:country":"AU",
    "sg:address":"254 Carlisle St",
    "sg:city":"Balaclava",
    "sg:classifiers":[
        {
            "category":"Food & Beverages",
            "subcategory":"Bakery",
            "type":"Retail Goods"
        }
    ],
    "sg:phone":"+61 3 9534 6583",
    "sg:postcode":"3183",
    "sg:province":"VIC",
    "sg:tags":[
        "baker"
    ],
    "wof:name":"Brumby's Bakeries",
    "wof:placetype":"venue"
},
  "geometry": {"coordinates":[144.992584228,-37.8685035706],"type":"Point"}
}