{
  "type": "Feature",
  "properties": {
    "iso:country":"AU",
    "sg:address":"5/ 128 Beamish St",
    "sg:city":"Campsie",
    "sg:classifiers":[
        {
            "category":"Real Estate",
            "subcategory":"Real Estate Agent",
            "type":"Services"
        }
    ],
    "sg:phone":"+61 2 9718 9188",
    "sg:postcode":"2194",
    "sg:province":"NSW",
    "wof:name":"Laing + Simmons Campsie",
    "wof:placetype":"venue"
},
  "geometry": {"coordinates":[151.10308800000001,-33.908325],"type":"Point"}
}