{
  "type": "Feature",
  "properties": {
    "iso:country":"AU",
    "sg:address":"3/ 8 Odin Rd",
    "sg:city":"Innaloo",
    "sg:classifiers":[
        {
            "category":"Health Services",
            "subcategory":"Dentist",
            "type":"Services"
        }
    ],
    "sg:phone":"+61 8 9445 7788",
    "sg:postcode":"6018",
    "sg:province":"WA",
    "wof:name":"Odin House Dental",
    "wof:placetype":"venue"
},
  "geometry": {"coordinates":[115.79566192599999,-31.9002838135],"type":"Point"}
}