{
  "type": "Feature",
  "properties": {
    "addr:full":"2 Tweed Rd Wanneroo WA 6065",
    "addr:housenumber":"2",
    "addr:postcode":"6065",
    "addr:street":"Tweed Rd",
    "iso:country":"AU",
    "sg:address":"2 Tweed Rd",
    "sg:city":"Wanneroo",
    "sg:classifiers":[
        {
            "category":"Professional",
            "subcategory":"Accounting & Tax Preparation",
            "type":"Services"
        }
    ],
    "sg:phone":"+61 8 9404 5264",
    "sg:postcode":"6065",
    "sg:province":"WA",
    "sg:tags":[
        "bookkeeping"
    ],
    "wof:name":"Bas Plus",
    "wof:placetype":"venue"
},
  "geometry": {"coordinates":[115.805076599,-31.7742404938],"type":"Point"}
}