{
  "type": "Feature",
  "properties": {
    "addr:full":"Shp 25 Quadrant Mall Launceston TAS 7250",
    "addr:housenumber":"25",
    "addr:postcode":"7250",
    "addr:street":"Quadrant Mall",
    "iso:country":"AU",
    "sg:address":"Shp 25 Quadrant Mall",
    "sg:city":"Launceston",
    "sg:classifiers":[
        {
            "category":"Shopping",
            "subcategory":"Clothing, Apparel, & Fashions",
            "type":"Retail Goods"
        }
    ],
    "sg:phone":"+61 3 6331 6888",
    "sg:postcode":"7250",
    "sg:province":"TAS",
    "sg:tags":[
        "lady",
        "wear"
    ],
    "wof:name":"Inspiration Styles Boutique",
    "wof:placetype":"venue"
},
  "geometry": {"coordinates":[147.139892578,-41.4376144409],"type":"Point"}
}