{
  "type": "Feature",
  "properties": {
    "addr:full":"1 Maestra St The Gap QLD 4061",
    "addr:postcode":"4061",
    "addr:street":"Maestra St",
    "iso:country":"AU",
    "sg:address":"1 Maestra St",
    "sg:city":"The Gap",
    "sg:classifiers":[
        {
            "category":"Professional",
            "subcategory":"Management & Consulting",
            "type":"Services"
        }
    ],
    "sg:phone":"+61 7 3300 1489",
    "sg:postcode":"4061",
    "sg:province":"QLD",
    "sg:tags":[
        "consultant",
        "business"
    ],
    "wof:name":"Icon Business Solutions",
    "wof:placetype":"venue"
},
  "geometry": {"coordinates":[152.93589782699999,-27.4426574707],"type":"Point"}
}