{
  "type": "Feature",
  "properties": {
    "addr:full":"3 Kuru St North Narrabeen NSW 2101",
    "addr:housenumber":"3",
    "addr:postcode":"2101",
    "addr:street":"Kuru St",
    "iso:country":"AU",
    "sg:address":"3 Kuru St",
    "sg:city":"North Narrabeen",
    "sg:classifiers":[
        {
            "category":"Retail",
            "subcategory":"Storage",
            "type":"Services"
        }
    ],
    "sg:phone":"+61 2 9913 7198",
    "sg:postcode":"2101",
    "sg:province":"NSW",
    "sg:tags":[
        "removal",
        "furniture"
    ],
    "wof:name":"Efficient Removals",
    "wof:placetype":"venue"
},
  "geometry": {"coordinates":[151.292633,-33.699528],"type":"Point"}
}