{
  "type": "Feature",
  "properties": {
    "addr:full":"39 Popes Rd Keysborough VIC 3173",
    "addr:housenumber":"39",
    "addr:postcode":"3173",
    "addr:street":"Popes Rd",
    "iso:country":"AU",
    "sg:address":"39 Popes Rd",
    "sg:city":"Keysborough",
    "sg:classifiers":[
        {
            "category":"Building & Trades",
            "subcategory":"Construction",
            "type":"Services"
        }
    ],
    "sg:phone":"+61 3 9798 8811",
    "sg:postcode":"3173",
    "sg:province":"VIC",
    "sg:tags":[
        "insulation",
        "contractor"
    ],
    "wof:name":"Melbourne Home Insulation Pty Ltd",
    "wof:placetype":"venue"
},
  "geometry": {"coordinates":[145.18913269000001,-37.9825248718],"type":"Point"}
}