{
  "type": "Feature",
  "properties": {
    "addr:full":"1st Flr 112-116 Tynte St (Cnr O&#039;Connell St North Adelaide SA 5006",
    "addr:housenumber":"112-116",
    "addr:postcode":"5006",
    "addr:street":"Tynte St Cnr O &;Connell St",
    "iso:country":"AU",
    "sg:address":"1st Flr 112-116 Tynte St (Cnr O&#039;Connell St",
    "sg:city":"North Adelaide",
    "sg:classifiers":[
        {
            "category":"Military Area",
            "subcategory":"Air Force Base",
            "type":"Public Place"
        }
    ],
    "sg:phone":"+61 8 8267 3866",
    "sg:postcode":"5006",
    "sg:province":"SA",
    "sg:tags":[
        "men's",
        "tailor"
    ],
    "wof:name":"Chehade Bros",
    "wof:placetype":"venue"
},
  "geometry": {"coordinates":[138.59640502900001,-34.9057159424],"type":"Point"}
}