{
  "type": "Feature",
  "properties": {
    "addr:full":"Factory 6/ 36 Industrial Park Drv Lilydale VIC 3140",
    "addr:housenumber":"/ 36",
    "addr:postcode":"3140",
    "addr:street":"Industrial Park Drv",
    "iso:country":"AU",
    "sg:address":"Factory 6/ 36 Industrial Park Drv",
    "sg:city":"Lilydale",
    "sg:classifiers":[
        {
            "category":"Sports & Exercise",
            "subcategory":"Gym",
            "type":"Entertainment"
        }
    ],
    "sg:phone":"+61 3 9735 4636",
    "sg:postcode":"3140",
    "sg:province":"VIC",
    "sg:tags":[
        "health",
        "fitness"
    ],
    "wof:name":"Curves For Women",
    "wof:placetype":"venue"
},
  "geometry": {"coordinates":[145.348678589,-37.7503967285],"type":"Point"}
}