{
  "type": "Feature",
  "properties": {
    "addr:full":"37 Church St Camperdown VIC 3260",
    "addr:housenumber":"37",
    "addr:postcode":"3260",
    "addr:street":"Church St",
    "iso:country":"AU",
    "sg:address":"37 Church St",
    "sg:city":"Camperdown",
    "sg:classifiers":[
        {
            "category":"Personal",
            "subcategory":"Massage",
            "type":"Services"
        }
    ],
    "sg:phone":"+61 3 5593 2287",
    "sg:postcode":"3260",
    "sg:province":"VIC",
    "sg:tags":[
        "therapy"
    ],
    "wof:name":"Camperdown Remedial Massage Clinic",
    "wof:placetype":"venue"
},
  "geometry": {"coordinates":[143.14752197300001,-38.2268028259],"type":"Point"}
}