{
  "type": "Feature",
  "properties": {
    "iso:country":"AU",
    "sg:address":"26 Oak St",
    "sg:city":"Mt Gambier",
    "sg:classifiers":[
        {
            "category":"Retail",
            "subcategory":"Auto Repair",
            "type":"Services"
        }
    ],
    "sg:phone":"+61 8 8723 1555",
    "sg:postcode":"5290",
    "sg:province":"SA",
    "sg:tags":[
        "beater",
        "painter",
        "panel"
    ],
    "wof:name":"Kevin Neale Panel Shop",
    "wof:placetype":"venue"
},
  "geometry": {"coordinates":[140.752762,-37.820648],"type":"Point"}
}