{
  "type": "Feature",
  "properties": {
    "addr:full":"PO Box 555 Collaroy Beach NSW 2097",
    "addr:postcode":"2097",
    "iso:country":"AU",
    "sg:address":"PO Box 555",
    "sg:city":"Collaroy Beach",
    "sg:classifiers":[
        {
            "category":"Donuts",
            "subcategory":"None",
            "type":"Food & Drink"
        }
    ],
    "sg:phone":"+61 411 872 463",
    "sg:postcode":"2097",
    "sg:province":"NSW",
    "sg:tags":[
        "die",
        "engraver",
        "sinker"
    ],
    "wof:name":"Endeavour Medallions & Castings",
    "wof:placetype":"venue"
},
  "geometry": {"coordinates":[151.301223755,-33.7321205139],"type":"Point"}
}