{
  "type": "Feature",
  "properties": {
    "addr:full":"Bethany Campus 17 Countess St Paralowie SA 5108",
    "addr:housenumber":"17",
    "addr:postcode":"5108",
    "addr:street":"Countess St",
    "iso:country":"AU",
    "sg:address":"Bethany Campus 17 Countess St",
    "sg:city":"Paralowie",
    "sg:classifiers":[
        {
            "category":"Education",
            "subcategory":"School",
            "type":"Public Place"
        }
    ],
    "sg:phone":"+61 8 8283 3854",
    "sg:postcode":"5108",
    "sg:province":"SA",
    "sg:tags":[
        "co-educational"
    ],
    "wof:name":"Temple Christian College",
    "wof:placetype":"venue"
},
  "geometry": {"coordinates":[138.60708618199999,-34.7619171143],"type":"Point"}
}