{
  "type": "Feature",
  "properties": {
    "iso:country":"AU",
    "sg:address":"263 Old Northern Rd",
    "sg:city":"Castle Hill",
    "sg:classifiers":[
        {
            "category":"Health Services",
            "subcategory":"Doctor",
            "type":"Services"
        }
    ],
    "sg:phone":"+61 2 9634 5000",
    "sg:postcode":"2154",
    "sg:province":"NSW",
    "sg:tags":[
        "medical",
        "practitioner"
    ],
    "wof:name":"Nelson-Marshall M G",
    "wof:placetype":"venue"
},
  "geometry": {"coordinates":[151.003814697,-33.7344017029],"type":"Point"}
}