{
  "type": "Feature",
  "properties": {
    "addr:full":"30 Cornish St Carnarvon WA 6701",
    "addr:housenumber":"30",
    "addr:postcode":"6701",
    "addr:street":"Cornish St",
    "iso:country":"AU",
    "sg:address":"30 Cornish St",
    "sg:city":"Carnarvon",
    "sg:classifiers":[
        {
            "category":"Communications",
            "type":"Services"
        }
    ],
    "sg:phone":"+61 8 9941 3444",
    "sg:postcode":"6701",
    "sg:province":"WA",
    "sg:tags":[
        "equipment",
        "radio"
    ],
    "wof:name":"Carnarvon Communications",
    "wof:placetype":"venue"
},
  "geometry": {"coordinates":[113.684562683,-24.8698501587],"type":"Point"}
}