{
  "type": "Feature",
  "properties": {
    "iso:country":"AU",
    "sg:address":"111 Bilsen Rd",
    "sg:city":"Wavell Heights",
    "sg:classifiers":[
        {
            "category":"Home & Garden",
            "subcategory":"Building Materials",
            "type":"Retail Goods"
        }
    ],
    "sg:phone":"+61 7 3266 8271",
    "sg:postcode":"4012",
    "sg:province":"QLD",
    "sg:tags":[
        "lawn",
        "cutting",
        "maintenance"
    ],
    "wof:name":"Azzas Gardenology",
    "wof:placetype":"venue"
},
  "geometry": {"coordinates":[153.052658081,-27.3902263641],"type":"Point"}
}