{
  "type": "Feature",
  "properties": {
    "addr:full":"20A Maple Ave Forestville SA 5035",
    "addr:housenumber":"20a",
    "addr:postcode":"5035",
    "addr:street":"Maple Ave",
    "iso:country":"AU",
    "sg:address":"20A Maple Ave",
    "sg:city":"Forestville",
    "sg:classifiers":[
        {
            "category":"Building & Trades",
            "subcategory":"Equipment Rental",
            "type":"Services"
        }
    ],
    "sg:phone":"+61 417 815 874",
    "sg:postcode":"5035",
    "sg:province":"SA",
    "sg:tags":[
        "hire",
        "catering"
    ],
    "wof:name":"A Licence To Chill",
    "wof:placetype":"venue"
},
  "geometry": {"coordinates":[138.582122803,-34.9478263855],"type":"Point"}
}