{
  "type": "Feature",
  "properties": {
    "addr:full":"22 Washington St Port Lincoln SA 5606",
    "addr:housenumber":"22",
    "addr:postcode":"5606",
    "addr:street":"Washington St",
    "iso:country":"AU",
    "sg:address":"22 Washington St",
    "sg:city":"Port Lincoln",
    "sg:classifiers":[
        {
            "category":"Health Services",
            "subcategory":"Chiropractor",
            "type":"Services"
        }
    ],
    "sg:phone":"+61 8 8682 3708",
    "sg:postcode":"5606",
    "sg:province":"SA",
    "wof:name":"West Coast Chiropractic Centre",
    "wof:placetype":"venue"
},
  "geometry": {"coordinates":[135.856979,-34.72039],"type":"Point"}
}