{
  "type": "Feature",
  "properties": {
    "iso:country":"AU",
    "sg:address":"Unit 1/ 12 Blackmore Rd",
    "sg:city":"Smeaton Grange",
    "sg:classifiers":[
        {
            "category":"Professional",
            "type":"Services"
        }
    ],
    "sg:phone":"+61 2 4648 5064",
    "sg:postcode":"2567",
    "sg:province":"NSW",
    "sg:tags":[
        "spray",
        "painting"
    ],
    "wof:name":"Camden Crash & Restorations",
    "wof:placetype":"venue"
},
  "geometry": {"coordinates":[150.75250244099999,-34.0378952026],"type":"Point"}
}