{
  "type": "Feature",
  "properties": {
    "addr:full":"62 Bundaleer St Brookfield QLD 4069",
    "addr:housenumber":"62",
    "addr:postcode":"4069",
    "addr:street":"Bundaleer St",
    "iso:country":"AU",
    "sg:address":"62 Bundaleer St",
    "sg:city":"Brookfield",
    "sg:classifiers":[
        {
            "category":"Building & Trades",
            "subcategory":"Construction",
            "type":"Services"
        }
    ],
    "sg:phone":"+61 407 125 450",
    "sg:postcode":"4069",
    "sg:province":"QLD",
    "sg:tags":[
        "contractor"
    ],
    "wof:name":"Allan White Constructions",
    "wof:placetype":"venue"
},
  "geometry": {"coordinates":[152.90174865700001,-27.4828777313],"type":"Point"}
}