{
  "type": "Feature",
  "properties": {
    "addr:full":"Station St Fairfield VIC 3078",
    "addr:postcode":"3078",
    "addr:street":"Station St",
    "iso:country":"AU",
    "sg:address":"Station St",
    "sg:city":"Fairfield",
    "sg:classifiers":[
        {
            "category":"Shopping",
            "subcategory":"Computers & Home Electronics",
            "type":"Retail Goods"
        }
    ],
    "sg:phone":"+61 3 9489 6566",
    "sg:postcode":"3078",
    "sg:province":"VIC",
    "sg:tags":[
        "equipment",
        "supply"
    ],
    "wof:name":"Boomerang TCR",
    "wof:placetype":"venue"
},
  "geometry": {"coordinates":[145.019454956,-37.7709197998],"type":"Point"}
}