{
  "type": "Feature",
  "properties": {
    "addr:full":"335 George St Windsor NSW 2756",
    "addr:housenumber":"335",
    "addr:postcode":"2756",
    "addr:street":"George St",
    "iso:country":"AU",
    "sg:address":"335 George St",
    "sg:city":"Windsor",
    "sg:classifiers":[
        {
            "category":"Travel",
            "subcategory":"Hotels & Motels",
            "type":"Entertainment"
        }
    ],
    "sg:phone":"+61 2 4577 3050",
    "sg:postcode":"2756",
    "sg:province":"NSW",
    "sg:tags":[
        "accommodation"
    ],
    "wof:name":"Hawkesbury Hotel",
    "wof:placetype":"venue"
},
  "geometry": {"coordinates":[150.815917969,-33.6098022461],"type":"Point"}
}