{
  "type": "Feature",
  "properties": {
    "addr:full":"Unit 3/ 478 Scottsdale Drv Varsity Lakes QLD 4226",
    "addr:housenumber":"/ 478",
    "addr:postcode":"4226",
    "addr:street":"Scottsdale Drv",
    "iso:country":"AU",
    "sg:address":"Unit 3/ 478 Scottsdale Drv",
    "sg:city":"Varsity Lakes",
    "sg:classifiers":[
        {
            "category":"Industrial Area",
            "type":"Public Place"
        }
    ],
    "sg:phone":"+61 414 281 333",
    "sg:postcode":"4226",
    "sg:province":"QLD",
    "sg:tags":[
        "floor"
    ],
    "wof:name":"Seal Tec Pty Ltd",
    "wof:placetype":"venue"
},
  "geometry": {"coordinates":[153.390380859,-28.0680007935],"type":"Point"}
}