{
  "type": "Feature",
  "properties": {
    "iso:country":"AU",
    "sg:address":"Suite 3/ 11 Forest Rd",
    "sg:city":"Hurstville",
    "sg:classifiers":[
        {
            "category":"Professional",
            "subcategory":"Accounting & Tax Preparation",
            "type":"Services"
        }
    ],
    "sg:phone":"+61 2 9588 5515",
    "sg:postcode":"2220",
    "sg:province":"NSW",
    "sg:tags":[
        "accountant",
        "auditor"
    ],
    "wof:name":"Jeffrey Todd & Associates",
    "wof:placetype":"venue"
},
  "geometry": {"coordinates":[151.10487365700001,-33.9676704407],"type":"Point"}
}