{
  "type": "Feature",
  "properties": {
    "iso:country":"AU",
    "sg:address":"Kelsey Rd",
    "sg:city":"Delta",
    "sg:classifiers":[
        {
            "category":"Farming",
            "subcategory":"Farm",
            "type":"Manufacturing & Wholesale Goods"
        }
    ],
    "sg:phone":"+61 7 4785 2317",
    "sg:postcode":"4805",
    "sg:province":"QLD",
    "sg:tags":[
        "farmer"
    ],
    "wof:name":"Pugh C D & M V",
    "wof:placetype":"venue"
},
  "geometry": {"coordinates":[148.18336486800001,-19.9961891174],"type":"Point"}
}