{
  "type": "Feature",
  "properties": {
    "iso:country":"AU",
    "sg:address":"1st /Floor 68 Jardine St",
    "sg:city":"Kingston",
    "sg:classifiers":[
        {
            "category":"Professional",
            "subcategory":"Management & Consulting",
            "type":"Services"
        }
    ],
    "sg:phone":"+61 413 187 987",
    "sg:postcode":"2604",
    "sg:province":"ACT",
    "sg:tags":[
        "consultant",
        "business"
    ],
    "wof:name":"Psychological Strategy and Insight",
    "wof:placetype":"venue"
},
  "geometry": {"coordinates":[149.14213562,-35.3159675598],"type":"Point"}
}