{
  "type": "Feature",
  "properties": {
    "addr:full":"U 8/ 110 Bundall Rd Bundall QLD 4217",
    "addr:housenumber":"/ 110",
    "addr:postcode":"4217",
    "addr:street":"Bundall Rd",
    "iso:country":"AU",
    "sg:address":"U 8/ 110 Bundall Rd",
    "sg:city":"Bundall",
    "sg:classifiers":[
        {
            "category":"Wholesale",
            "subcategory":"Painting Supplies",
            "type":"Manufacturing & Wholesale Goods"
        }
    ],
    "sg:phone":"+61 7 5592 2221",
    "sg:postcode":"4217",
    "sg:province":"QLD",
    "sg:tags":[
        "product",
        "cleaning"
    ],
    "wof:name":"Global Pacific Distribution",
    "wof:placetype":"venue"
},
  "geometry": {"coordinates":[153.41326904300001,-28.003868103],"type":"Point"}
}