{
  "type": "Feature",
  "properties": {
    "iso:country":"AU",
    "sg:address":"168 Main St",
    "sg:city":"Osborne Park",
    "sg:classifiers":[
        {
            "category":"Health Services",
            "subcategory":"Doctor",
            "type":"Services"
        }
    ],
    "sg:phone":"+61 8 9349 3555",
    "sg:postcode":"6017",
    "sg:province":"WA",
    "sg:tags":[
        "medical",
        "practitioner"
    ],
    "wof:name":"Osborne Park Medical Centre",
    "wof:placetype":"venue"
},
  "geometry": {"coordinates":[115.828422546,-31.8998394012],"type":"Point"}
}