{
  "type": "Feature",
  "properties": {
    "addr:full":"85 Tanundal St Howrah TAS 7018",
    "addr:housenumber":"85",
    "addr:postcode":"7018",
    "addr:street":"Tanundal St",
    "iso:country":"AU",
    "sg:address":"85 Tanundal St",
    "sg:city":"Howrah",
    "sg:classifiers":[
        {
            "category":"Government",
            "subcategory":"Post Office",
            "type":"Public Place"
        }
    ],
    "sg:phone":"+61 3 6245 1476",
    "sg:postcode":"7018",
    "sg:province":"TAS",
    "sg:tags":[
        "yoga"
    ],
    "wof:name":"Sahaja Yoga Meditation",
    "wof:placetype":"venue"
},
  "geometry": {"coordinates":[147.38992309599999,-42.873840332],"type":"Point"}
}