{
  "type": "Feature",
  "properties": {
    "addr:full":"10 Watts Rd Dernancourt SA 5075",
    "addr:housenumber":"10",
    "addr:postcode":"5075",
    "addr:street":"Watts Rd",
    "iso:country":"AU",
    "sg:address":"10 Watts Rd",
    "sg:city":"Dernancourt",
    "sg:classifiers":[
        {
            "category":"Mining & Drilling",
            "type":"Manufacturing & Wholesale Goods"
        }
    ],
    "sg:phone":"+61 8 8165 0660",
    "sg:postcode":"5075",
    "sg:province":"SA",
    "sg:tags":[
        "concrete",
        "breaking",
        "grinding",
        "sawing"
    ],
    "wof:name":"S.A. Concrete Cutting & Coring Pty Ltd",
    "wof:placetype":"venue"
},
  "geometry": {"coordinates":[138.68107605,-34.8619346619],"type":"Point"}
}