{
  "type": "Feature",
  "properties": {
    "iso:country":"AU",
    "sg:address":"59 Howard Rd",
    "sg:city":"Padstow",
    "sg:classifiers":[
        {
            "category":"Personal",
            "subcategory":"Beauty Salon",
            "type":"Services"
        }
    ],
    "sg:phone":"+61 2 9773 8104",
    "sg:postcode":"2211",
    "sg:province":"NSW",
    "sg:tags":[
        "hairdresser"
    ],
    "wof:name":"Hair Dynamics",
    "wof:placetype":"venue"
},
  "geometry": {"coordinates":[151.032104,-33.952309],"type":"Point"}
}