{
  "type": "Feature",
  "properties": {
    "addr:full":"23 Bosworth St Richmond NSW 2753",
    "addr:housenumber":"23",
    "addr:postcode":"2753",
    "addr:street":"Bosworth St",
    "iso:country":"AU",
    "sg:address":"23 Bosworth St",
    "sg:city":"Richmond",
    "sg:classifiers":[
        {
            "category":"Organizations",
            "subcategory":"Non-profit Organization",
            "type":"Services"
        }
    ],
    "sg:phone":"+61 2 4578 4459",
    "sg:postcode":"2753",
    "sg:province":"NSW",
    "sg:tags":[
        "support",
        "disability",
        "organisation"
    ],
    "wof:name":"Hawkesbury Skills Inc",
    "wof:placetype":"venue"
},
  "geometry": {"coordinates":[150.74763488799999,-33.5956077576],"type":"Point"}
}