{
  "type": "Feature",
  "properties": {
    "addr:full":"Unit 1/ 41 Durgadin Drv Albion Park NSW 2527",
    "addr:postcode":"2527",
    "addr:street":"41 Durgadin Drv Albion Park",
    "iso:country":"AU",
    "sg:address":"Unit 1/ 41 Durgadin Drv",
    "sg:city":"Albion Park",
    "sg:classifiers":[
        {
            "category":"Home & Garden",
            "subcategory":"Building Materials",
            "type":"Retail Goods"
        }
    ],
    "sg:phone":"+61 2 4257 1113",
    "sg:postcode":"2527",
    "sg:province":"NSW",
    "sg:tags":[
        "merchant",
        "glass",
        "glazier"
    ],
    "wof:name":"Johnsens Glass",
    "wof:placetype":"venue"
},
  "geometry": {"coordinates":[150.81629943900001,-34.5719108582],"type":"Point"}
}