{
  "type": "Feature",
  "properties": {
    "iso:country":"AU",
    "sg:address":"312 Windermere St",
    "sg:city":"Ballarat",
    "sg:classifiers":[
        {
            "category":"Building & Trades",
            "subcategory":"Construction",
            "type":"Services"
        }
    ],
    "sg:phone":"+61 417 160 078",
    "sg:postcode":"3350",
    "sg:province":"VIC",
    "sg:tags":[
        "contractor"
    ],
    "wof:name":"Ballarat Construction Management Pty Ltd",
    "wof:placetype":"venue"
},
  "geometry": {"coordinates":[143.84449799999999,-37.567951],"type":"Point"}
}