{
  "type": "Feature",
  "properties": {
    "iso:country":"AU",
    "sg:address":"16 Valediction Rd",
    "sg:city":"Kings Park",
    "sg:classifiers":[
        {
            "category":"Shopping",
            "subcategory":"Crafts & Fabrics",
            "type":"Retail Goods"
        }
    ],
    "sg:phone":"+61 2 9672 3807",
    "sg:postcode":"2148",
    "sg:province":"NSW",
    "sg:tags":[
        "quilting"
    ],
    "wof:name":"Sew Easy",
    "wof:placetype":"venue"
},
  "geometry": {"coordinates":[150.91307067899999,-33.745426178],"type":"Point"}
}