{
  "type": "Feature",
  "properties": {
    "addr:full":"1 Albany Hwy Victoria Park WA 6100",
    "addr:housenumber":"1",
    "addr:postcode":"6100",
    "addr:street":"Albany Hwy Victoria",
    "iso:country":"AU",
    "sg:address":"1 Albany Hwy",
    "sg:city":"Victoria Park",
    "sg:classifiers":[
        {
            "category":"Shopping",
            "subcategory":"Clothing, Apparel, & Fashions",
            "type":"Retail Goods"
        }
    ],
    "sg:phone":"+61 415 704 880",
    "sg:postcode":"6100",
    "sg:province":"WA",
    "sg:tags":[
        "lady",
        "wear"
    ],
    "wof:name":"Rayannes Design",
    "wof:placetype":"venue"
},
  "geometry": {"coordinates":[115.899917602,-31.9794464111],"type":"Point"}
}