{
  "type": "Feature",
  "properties": {
    "addr:full":"81 Penkivil St Bondi NSW 2026",
    "addr:housenumber":"81",
    "addr:postcode":"2026",
    "addr:street":"Penkivil St",
    "iso:country":"AU",
    "sg:address":"81 Penkivil St",
    "sg:city":"Bondi",
    "sg:classifiers":[
        {
            "category":"Shopping",
            "subcategory":"News",
            "type":"Retail Goods"
        }
    ],
    "sg:phone":"+61 2 9389 7855",
    "sg:postcode":"2026",
    "sg:province":"NSW",
    "sg:tags":[
        "magazine",
        "periodical"
    ],
    "wof:name":"Filmink Magazine",
    "wof:placetype":"venue"
},
  "geometry": {"coordinates":[151.260894775,-33.8933486938],"type":"Point"}
}