{
  "type": "Feature",
  "properties": {
    "addr:full":"117 Oxide St Broken Hill NSW 2880",
    "addr:housenumber":"117",
    "addr:postcode":"2880",
    "addr:street":"Oxide St",
    "iso:country":"AU",
    "sg:address":"117 Oxide St",
    "sg:city":"Broken Hill",
    "sg:classifiers":[
        {
            "category":"Insurance",
            "subcategory":"Insurance Agent",
            "type":"Services"
        }
    ],
    "sg:phone":"+61 8 8088 3356",
    "sg:postcode":"2880",
    "sg:province":"NSW",
    "wof:name":"Hall Kevin Financial Services & Insurances",
    "wof:placetype":"venue"
},
  "geometry": {"coordinates":[141.464385986,-31.953212738],"type":"Point"}
}