{
  "type": "Feature",
  "properties": {
    "addr:full":"63 Salamanca Pl Hobart TAS 7000",
    "addr:housenumber":"63",
    "addr:postcode":"7000",
    "addr:street":"Salamanca Pl",
    "iso:country":"AU",
    "sg:address":"63 Salamanca Pl",
    "sg:city":"Hobart",
    "sg:classifiers":[
        {
            "category":"Bars & Pubs",
            "subcategory":"Dive Bar",
            "type":"Food & Drink"
        }
    ],
    "sg:phone":"+61 3 6234 6010",
    "sg:postcode":"7000",
    "sg:province":"TAS",
    "sg:tags":[
        "knitwear",
        "retail"
    ],
    "wof:name":"Morrison Country Clothing Australia Pty Ltd",
    "wof:placetype":"venue"
},
  "geometry": {"coordinates":[147.33331298799999,-42.886806488],"type":"Point"}
}