{
  "type": "Feature",
  "properties": {
    "iso:country":"AU",
    "sg:address":"81 Spence Rd",
    "sg:city":"Llandilo",
    "sg:classifiers":[
        {
            "category":"Social Services",
            "subcategory":"Adult Care",
            "type":"Services"
        }
    ],
    "sg:phone":"+61 2 9623 1427",
    "sg:postcode":"2747",
    "sg:province":"NSW",
    "sg:tags":[
        "towing"
    ],
    "wof:name":"Dennis Sims Towing & Tilt Trays",
    "wof:placetype":"venue"
},
  "geometry": {"coordinates":[150.77273559599999,-33.6841201782],"type":"Point"}
}