{
  "type": "Feature",
  "properties": {
    "addr:full":"63 Baringa Park Drv Narre Warren VIC 3805",
    "addr:housenumber":"63",
    "addr:postcode":"3805",
    "addr:street":"Park Drv",
    "iso:country":"AU",
    "sg:address":"63 Baringa Park Drv",
    "sg:city":"Narre Warren",
    "sg:classifiers":[
        {
            "category":"Shopping",
            "subcategory":"Gifts & Souvenirs",
            "type":"Retail Goods"
        }
    ],
    "sg:phone":"+61 3 9704 5214",
    "sg:postcode":"3805",
    "sg:province":"VIC",
    "sg:tags":[
        "shop",
        "supply"
    ],
    "wof:name":"Fuss Pot Ceramics",
    "wof:placetype":"venue"
},
  "geometry": {"coordinates":[145.29385400000001,-38.053539],"type":"Point"}
}