{
  "type": "Feature",
  "properties": {
    "addr:full":"Homemaker Centre Strickland St Bunbury WA 6230",
    "addr:postcode":"6230",
    "addr:street":"Strickland St",
    "iso:country":"AU",
    "sg:address":"Homemaker Centre Strickland St",
    "sg:city":"Bunbury",
    "sg:classifiers":[
        {
            "category":"Deli",
            "type":"Food & Drink"
        }
    ],
    "sg:phone":"+61 8 9791 1228",
    "sg:postcode":"6230",
    "sg:province":"WA",
    "sg:tags":[
        "delicatessen"
    ],
    "wof:name":"Napolis Gourmet Deli & Diner",
    "wof:placetype":"venue"
},
  "geometry": {"coordinates":[115.64118999999999,-33.336498],"type":"Point"}
}