{
  "type": "Feature",
  "properties": {
    "iso:country":"AU",
    "sg:address":"33 Redliffe Gardens Drv",
    "sg:city":"Clontarf",
    "sg:classifiers":[
        {
            "category":"Professional",
            "subcategory":"Printing & Photocopies",
            "type":"Services"
        }
    ],
    "sg:phone":"+61 7 3883 1021",
    "sg:postcode":"4019",
    "sg:province":"QLD",
    "sg:tags":[
        "embroidery"
    ],
    "wof:name":"Country Wide Embroidery",
    "wof:placetype":"venue"
},
  "geometry": {"coordinates":[153.082473755,-27.2592506409],"type":"Point"}
}