{
  "type": "Feature",
  "properties": {
    "iso:country":"AU",
    "sg:address":"66 Torquay Rd",
    "sg:city":"Hervey Bay",
    "sg:classifiers":[
        {
            "category":"Autos & Motor Vehicles",
            "subcategory":"Automobile Sales",
            "type":"Retail Goods"
        }
    ],
    "sg:phone":"+61 7 4128 1668",
    "sg:postcode":"4655",
    "sg:province":"QLD",
    "sg:tags":[
        "car",
        "used"
    ],
    "wof:name":"Craigs Cars",
    "wof:placetype":"venue"
},
  "geometry": {"coordinates":[152.84565699999999,-25.284424],"type":"Point"}
}