{
  "type": "Feature",
  "properties": {
    "iso:country":"AU",
    "sg:address":"117 South Pine Rd",
    "sg:city":"Strathpine",
    "sg:classifiers":[
        {
            "category":"Home & Garden",
            "subcategory":"Carpets & Floor Coverings",
            "type":"Retail Goods"
        }
    ],
    "sg:phone":"+61 7 3205 7811",
    "sg:postcode":"4500",
    "sg:province":"QLD",
    "sg:tags":[
        "tile",
        "wall"
    ],
    "wof:name":"Tile City",
    "wof:placetype":"venue"
},
  "geometry": {"coordinates":[152.98733520499999,-27.3245449066],"type":"Point"}
}