{
  "type": "Feature",
  "properties": {
    "addr:full":"Woodlands Plaza Old Coach Rd Reedy Creek QLD 4228",
    "addr:postcode":"4228",
    "addr:street":"Old Coach Rd",
    "iso:country":"AU",
    "sg:address":"Woodlands Plaza Old Coach Rd",
    "sg:city":"Reedy Creek",
    "sg:classifiers":[
        {
            "category":"Food & Beverages",
            "subcategory":"Liquor & Beverages",
            "type":"Retail Goods"
        }
    ],
    "sg:phone":"+61 7 5522 0406",
    "sg:postcode":"4228",
    "sg:province":"QLD",
    "sg:tags":[
        "store"
    ],
    "wof:name":"Reedy Creek Cellars",
    "wof:placetype":"venue"
},
  "geometry": {"coordinates":[153.370269775,-28.1763000488],"type":"Point"}
}