{
  "type": "Feature",
  "properties": {
    "addr:full":"75 Spine St Sumner Park QLD 4074",
    "addr:housenumber":"75",
    "addr:postcode":"4074",
    "addr:street":"Spine St",
    "iso:country":"AU",
    "sg:address":"75 Spine St",
    "sg:city":"Sumner Park",
    "sg:classifiers":[
        {
            "category":"Shopping",
            "subcategory":"Stationery & Office Supplies",
            "type":"Retail Goods"
        }
    ],
    "sg:phone":"+61 1300 552 333",
    "sg:postcode":"4074",
    "sg:province":"QLD",
    "sg:tags":[
        "packaging",
        "equipment",
        "sealing",
        "filling"
    ],
    "wof:name":"Robotic Automation P/L",
    "wof:placetype":"venue"
},
  "geometry": {"coordinates":[152.935058594,-27.5616760254],"type":"Point"}
}