{
  "type": "Feature",
  "properties": {
    "addr:full":"Shop 1, 525 Kingsway Miranda NSW 2228",
    "addr:housenumber":"shop 1 525",
    "addr:postcode":"2228",
    "addr:street":"Kingsway Miranda",
    "iso:country":"AU",
    "sg:address":"Shop 1, 525",
    "sg:city":"Kingsway Miranda",
    "sg:classifiers":[
        {
            "category":"Banks & Credit Unions",
            "subcategory":"Financial Services",
            "type":"Services"
        }
    ],
    "sg:phone":"+61 2 8004 2222",
    "sg:postcode":"2228",
    "sg:province":"NSW",
    "sg:tags":[
        "loan",
        "finance",
        "mortgage"
    ],
    "wof:name":"RAMS Home Loans",
    "wof:placetype":"venue"
},
  "geometry": {"coordinates":[151.104370117,-34.0341949463],"type":"Point"}
}