{
  "type": "Feature",
  "properties": {
    "iso:country":"AU",
    "sg:address":"82 Lannercost St",
    "sg:city":"Ingham",
    "sg:classifiers":[
        {
            "category":"Banks & Credit Unions",
            "subcategory":"Bureau De Change",
            "type":"Services"
        }
    ],
    "sg:phone":"+61 7 4776 3188",
    "sg:postcode":"4850",
    "sg:province":"QLD",
    "sg:tags":[
        "repairs",
        "part",
        "appliance",
        "electrical"
    ],
    "wof:name":"Ingham Betta Electrical",
    "wof:placetype":"venue"
},
  "geometry": {"coordinates":[146.1534729,-18.650100708],"type":"Point"}
}