{
  "type": "Feature",
  "properties": {
    "addr:full":"PO Box 6053 Riverview QLD 4303",
    "addr:postcode":"4303",
    "iso:country":"AU",
    "sg:address":"PO Box 6053",
    "sg:city":"Riverview",
    "sg:classifiers":[
        {
            "category":"Building & Trades",
            "subcategory":"Plumbing",
            "type":"Services"
        }
    ],
    "sg:phone":"+61 417 789 579",
    "sg:postcode":"4303",
    "sg:province":"QLD",
    "sg:tags":[
        "plumber",
        "gasfitters"
    ],
    "wof:name":"Gas Galore Pty Ltd",
    "wof:placetype":"venue"
},
  "geometry": {"coordinates":[152.85081481899999,-27.5960998535],"type":"Point"}
}