{
  "type": "Feature",
  "properties": {
    "iso:country":"AU",
    "sg:address":"PO Box 108",
    "sg:city":"Ryde Private Boxes",
    "sg:classifiers":[
        {
            "category":"Social Services",
            "type":"Services"
        }
    ],
    "sg:phone":"+61 2 9808 2022",
    "sg:postcode":"1680",
    "sg:province":"NSW",
    "sg:tags":[
        "disabled",
        "person",
        "equipment"
    ],
    "wof:name":"Technical Aid For The Disabled NSW",
    "wof:placetype":"venue"
},
  "geometry": {"coordinates":[151.104934692,-33.8129501343],"type":"Point"}
}