{
  "type": "Feature",
  "properties": {
    "addr:full":"1301 Wynnum Rd Tingalpa QLD 4173",
    "addr:housenumber":"1301",
    "addr:postcode":"4173",
    "addr:street":"Wynnum Rd",
    "iso:country":"AU",
    "sg:address":"1301 Wynnum Rd",
    "sg:city":"Tingalpa",
    "sg:classifiers":[
        {
            "category":"Autos & Motor Vehicles",
            "subcategory":"Automobile Sales",
            "type":"Retail Goods"
        }
    ],
    "sg:phone":"+61 7 3348 8888",
    "sg:postcode":"4173",
    "sg:province":"QLD",
    "sg:tags":[
        "car",
        "used"
    ],
    "wof:name":"Downtown Toyota",
    "wof:placetype":"venue"
},
  "geometry": {"coordinates":[153.12840270999999,-27.4737625122],"type":"Point"}
}