{
  "type": "Feature",
  "properties": {
    "addr:full":"18 Boyce Ave Wyong NSW 2259",
    "addr:housenumber":"18",
    "addr:postcode":"2259",
    "addr:street":"Boyce Ave",
    "iso:country":"AU",
    "sg:address":"18 Boyce Ave",
    "sg:city":"Wyong",
    "sg:classifiers":[
        {
            "category":"Place Of Worship",
            "subcategory":"Monastery",
            "type":"Public Place"
        }
    ],
    "sg:phone":"+61 2 4352 1371",
    "sg:postcode":"2259",
    "sg:province":"NSW",
    "sg:tags":[
        "residential",
        "village"
    ],
    "wof:name":"Meander Village",
    "wof:placetype":"venue"
},
  "geometry": {"coordinates":[151.433517456,-33.2887878418],"type":"Point"}
}