{
  "type": "Feature",
  "properties": {
    "addr:full":"103 Oak St Barcaldine QLD 4725",
    "addr:housenumber":"103",
    "addr:postcode":"4725",
    "addr:street":"Oak St",
    "iso:country":"AU",
    "sg:address":"103 Oak St",
    "sg:city":"Barcaldine",
    "sg:classifiers":[
        {
            "category":"Banks & Credit Unions",
            "subcategory":"Bank",
            "type":"Services"
        }
    ],
    "sg:phone":"+61 13 20 32",
    "sg:postcode":"4725",
    "sg:province":"QLD",
    "wof:name":"Westpac",
    "wof:placetype":"venue"
},
  "geometry": {"coordinates":[145.28315699999999,-23.552086],"type":"Point"}
}