{
  "type": "Feature",
  "properties": {
    "addr:full":"323 Manns Rd Gosford West NSW 2250",
    "addr:housenumber":"323",
    "addr:postcode":"2250",
    "addr:street":"Manns Rd",
    "iso:country":"AU",
    "sg:address":"323 Manns Rd",
    "sg:city":"Gosford West",
    "sg:classifiers":[
        {
            "category":"Manufacturing",
            "subcategory":"Building Materials",
            "type":"Manufacturing & Wholesale Goods"
        }
    ],
    "sg:phone":"+61 2 4324 3590",
    "sg:postcode":"2250",
    "sg:province":"NSW",
    "sg:tags":[
        "concrete",
        "product"
    ],
    "wof:name":"Cement Artistry",
    "wof:placetype":"venue"
},
  "geometry": {"coordinates":[151.31936645499999,-33.424621582],"type":"Point"}
}