{
  "type": "Feature",
  "properties": {
    "iso:country":"AU",
    "sg:address":"Suite 5, 21 Kinghorne St",
    "sg:city":"Nowra",
    "sg:classifiers":[
        {
            "category":"Real Estate",
            "subcategory":"Surveying",
            "type":"Services"
        }
    ],
    "sg:phone":"+61 1300 765 315",
    "sg:postcode":"2540",
    "sg:province":"NSW",
    "sg:tags":[
        "surveyor",
        "land"
    ],
    "wof:name":"Lawrence Group",
    "wof:placetype":"venue"
},
  "geometry": {"coordinates":[150.814849853,-35.016834259],"type":"Point"}
}