{
  "type": "Feature",
  "properties": {
    "addr:full":"270 Warrigal Rd Cheltenham VIC 3192",
    "addr:housenumber":"270",
    "addr:postcode":"3192",
    "addr:street":"Warrigal Rd",
    "iso:country":"AU",
    "sg:address":"270 Warrigal Rd",
    "sg:city":"Cheltenham",
    "sg:classifiers":[
        {
            "category":"Food & Beverages",
            "subcategory":"Bakery",
            "type":"Retail Goods"
        }
    ],
    "sg:phone":"+61 3 9583 9210",
    "sg:postcode":"3192",
    "sg:province":"VIC",
    "sg:tags":[
        "baker"
    ],
    "wof:name":"George's Bakery",
    "wof:placetype":"venue"
},
  "geometry": {"coordinates":[145.07400512699999,-37.9691314697],"type":"Point"}
}