{
  "type": "Feature",
  "properties": {
    "addr:full":"34 Hallet Pl Port Lincoln SA 5606",
    "addr:housenumber":"34",
    "addr:postcode":"5606",
    "addr:street":"Hallet Pl",
    "iso:country":"AU",
    "sg:address":"34 Hallet Pl",
    "sg:city":"Port Lincoln",
    "sg:classifiers":[
        {
            "category":"Travel",
            "subcategory":"Hotels & Motels",
            "type":"Entertainment"
        }
    ],
    "sg:phone":"+61 8 8682 3333",
    "sg:postcode":"5606",
    "sg:province":"SA",
    "sg:tags":[
        "accommodation"
    ],
    "wof:name":"Great Northern HotelPort Lincoln",
    "wof:placetype":"venue"
},
  "geometry": {"coordinates":[135.854782,-34.719269],"type":"Point"}
}