{
  "type": "Feature",
  "properties": {
    "addr:full":"17 Chamberlain St Ingham QLD 4850",
    "addr:housenumber":"17",
    "addr:postcode":"4850",
    "addr:street":"Chamberlain St",
    "iso:country":"AU",
    "sg:address":"17 Chamberlain St",
    "sg:city":"Ingham",
    "sg:classifiers":[
        {
            "category":"Education",
            "subcategory":"School",
            "type":"Public Place"
        }
    ],
    "sg:phone":"+61 7 4776 2888",
    "sg:postcode":"4850",
    "sg:province":"QLD",
    "wof:name":"Gilroy Santa Maria College",
    "wof:placetype":"venue"
},
  "geometry": {"coordinates":[146.15443420400001,-18.6449012756],"type":"Point"}
}