{
  "type": "Feature",
  "properties": {
    "iso:country":"AU",
    "sg:address":"Fact 3/ 4 Cook St",
    "sg:city":"Tamworth",
    "sg:classifiers":[
        {
            "category":"Building & Trades",
            "subcategory":"Construction",
            "type":"Services"
        }
    ],
    "sg:phone":"+61 2 6765 8560",
    "sg:postcode":"2340",
    "sg:province":"NSW",
    "sg:tags":[
        "home",
        "air conditioning"
    ],
    "wof:name":"Peel Refrigeration",
    "wof:placetype":"venue"
},
  "geometry": {"coordinates":[150.89321899399999,-31.0978546143],"type":"Point"}
}