{
  "type": "Feature",
  "properties": {
    "addr:full":"2 Quakers Crt Quakers Hill NSW 2763",
    "addr:housenumber":"2",
    "addr:postcode":"2763",
    "addr:street":"Quakers Crt",
    "iso:country":"AU",
    "sg:address":"2 Quakers Crt",
    "sg:city":"Quakers Hill",
    "sg:classifiers":[
        {
            "category":"Food & Beverages",
            "subcategory":"Bakery",
            "type":"Retail Goods"
        }
    ],
    "sg:phone":"+61 2 9626 0385",
    "sg:postcode":"2763",
    "sg:province":"NSW",
    "sg:tags":[
        "baker"
    ],
    "wof:name":"Phillis Quakers Hill Hot Bread",
    "wof:placetype":"venue"
},
  "geometry": {"coordinates":[150.89976501500001,-33.7463951111],"type":"Point"}
}