{
  "type": "Feature",
  "properties": {
    "addr:full":"Shp12/ 85 Buckland Rd Nundah QLD 4012",
    "addr:housenumber":"85",
    "addr:postcode":"4012",
    "addr:street":"Buckland Rd",
    "iso:country":"AU",
    "sg:address":"Shp12/ 85 Buckland Rd",
    "sg:city":"Nundah",
    "sg:classifiers":[
        {
            "category":"Fast Food",
            "type":"Food & Drink"
        }
    ],
    "sg:phone":"+61 7 3256 8700",
    "sg:postcode":"4012",
    "sg:province":"QLD",
    "sg:tags":[
        "away",
        "take"
    ],
    "wof:name":"Noodle Box Nundah",
    "wof:placetype":"venue"
},
  "geometry": {"coordinates":[153.06153869600001,-27.4034366608],"type":"Point"}
}