{
  "type": "Feature",
  "properties": {
    "addr:full":"Shop 207 East Walk Maude Street Mall Shepparton VIC 3630",
    "addr:housenumber":"207",
    "addr:postcode":"3630",
    "addr:street":"East Walk Maude Street Mall",
    "iso:country":"AU",
    "sg:address":"Shop 207",
    "sg:city":"East Walk Maude Street Mall Shepparton",
    "sg:classifiers":[
        {
            "category":"Shopping",
            "subcategory":"Music",
            "type":"Retail Goods"
        }
    ],
    "sg:phone":"+61 3 5831 7080",
    "sg:postcode":"3630",
    "sg:province":"VIC",
    "sg:tags":[
        "store"
    ],
    "wof:name":"Delta Music Store",
    "wof:placetype":"venue"
},
  "geometry": {"coordinates":[145.39956665,-36.3873443604],"type":"Point"}
}