{
  "type": "Feature",
  "properties": {
    "addr:full":"Midland Hwy Epsom VIC 3551",
    "addr:postcode":"3551",
    "addr:street":"Midland Hwy",
    "iso:country":"AU",
    "sg:address":"Midland Hwy",
    "sg:city":"Epsom",
    "sg:classifiers":[
        {
            "category":"Retail",
            "subcategory":"Auto Repair",
            "type":"Services"
        }
    ],
    "sg:phone":"+61 3 5448 4800",
    "sg:postcode":"3551",
    "sg:province":"VIC",
    "sg:tags":[
        "repairer",
        "motor",
        "engineer"
    ],
    "wof:name":"Northside Autos Windsor Caravans",
    "wof:placetype":"venue"
},
  "geometry": {"coordinates":[144.314544678,-36.7125091553],"type":"Point"}
}