{
  "type": "Feature",
  "properties": {
    "addr:full":"169 Nixon St Shepparton VIC 3630",
    "addr:housenumber":"169",
    "addr:postcode":"3630",
    "addr:street":"Nixon St",
    "iso:country":"AU",
    "sg:address":"169 Nixon St",
    "sg:city":"Shepparton",
    "sg:classifiers":[
        {
            "category":"Health Services",
            "subcategory":"Dentist",
            "type":"Services"
        }
    ],
    "sg:phone":"+61 3 5821 2576",
    "sg:postcode":"3630",
    "sg:province":"VIC",
    "wof:name":"Goulburn Valley Dental Group",
    "wof:placetype":"venue"
},
  "geometry": {"coordinates":[145.411056519,-36.378326416],"type":"Point"}
}