{
  "type": "Feature",
  "properties": {
    "addr:full":"9 Chandos St Cheltenham VIC 3192",
    "addr:housenumber":"9",
    "addr:postcode":"3192",
    "addr:street":"Chandos St",
    "iso:country":"AU",
    "sg:address":"9 Chandos St",
    "sg:city":"Cheltenham",
    "sg:classifiers":[
        {
            "category":"Retail",
            "subcategory":"Auto Repair",
            "type":"Services"
        }
    ],
    "sg:phone":"+61 3 9584 3232",
    "sg:postcode":"3192",
    "sg:province":"VIC",
    "sg:tags":[
        "testing",
        "inspection",
        "motor",
        "vehicle"
    ],
    "wof:name":"Chandos Autos",
    "wof:placetype":"venue"
},
  "geometry": {"coordinates":[145.041305542,-37.957233429],"type":"Point"}
}