{
  "type": "Feature",
  "properties": {
    "addr:full":"140 Church St Richmond VIC 3121",
    "addr:housenumber":"140",
    "addr:postcode":"3121",
    "addr:street":"Church St",
    "iso:country":"AU",
    "sg:address":"140 Church St",
    "sg:city":"Richmond",
    "sg:classifiers":[
        {
            "category":"Health Services",
            "subcategory":"Doctor",
            "type":"Services"
        }
    ],
    "sg:phone":"+61 3 9420 1484",
    "sg:postcode":"3121",
    "sg:province":"VIC",
    "sg:tags":[
        "medical",
        "practitioner"
    ],
    "wof:name":"Scott Colin Dr",
    "wof:placetype":"venue"
},
  "geometry": {"coordinates":[144.999633789,-37.8151512146],"type":"Point"}
}