{
  "type": "Feature",
  "properties": {
    "addr:full":"34 Mourilyan Harbour Rd Mourilyan QLD 4858",
    "addr:housenumber":"34",
    "addr:postcode":"4858",
    "addr:street":"Mourilyan Harbour Rd",
    "iso:country":"AU",
    "sg:address":"34 Mourilyan Harbour Rd",
    "sg:city":"Mourilyan",
    "sg:classifiers":[
        {
            "category":"Education",
            "subcategory":"School",
            "type":"Public Place"
        }
    ],
    "sg:phone":"+61 7 4063 0222",
    "sg:postcode":"4858",
    "sg:province":"QLD",
    "sg:tags":[
        "state",
        "except",
        "nsw"
    ],
    "wof:name":"Mourilyan Primary School",
    "wof:placetype":"venue"
},
  "geometry": {"coordinates":[146.04600524899999,-17.586561203],"type":"Point"}
}