{
  "type": "Feature",
  "properties": {
    "iso:country":"AU",
    "sg:address":"10 Gatehouse Drv",
    "sg:city":"Kensington",
    "sg:classifiers":[
        {
            "category":"Cafe",
            "type":"Food & Drink"
        }
    ],
    "sg:phone":"+61 3 9372 1888",
    "sg:postcode":"3031",
    "sg:province":"VIC",
    "wof:name":"Gatehouse Pizza & Pasta Cafe",
    "wof:placetype":"venue"
},
  "geometry": {"coordinates":[144.919464,-37.792068],"type":"Point"}
}