{
  "type": "Feature",
  "properties": {
    "addr:full":"28 Farm St Newmarket QLD 4051",
    "addr:housenumber":"28",
    "addr:postcode":"4051",
    "addr:street":"Farm St",
    "iso:country":"AU",
    "sg:address":"28 Farm St",
    "sg:city":"Newmarket",
    "sg:classifiers":[
        {
            "category":"Building & Trades",
            "subcategory":"Construction",
            "type":"Services"
        }
    ],
    "sg:phone":"+61 7 3356 2268",
    "sg:postcode":"4051",
    "sg:province":"QLD",
    "sg:tags":[
        "concrete",
        "contractor"
    ],
    "wof:name":"Cannason Industries",
    "wof:placetype":"venue"
},
  "geometry": {"coordinates":[153.008087158,-27.4313774109],"type":"Point"}
}