{
  "type": "Feature",
  "properties": {
    "iso:country":"AU",
    "sg:address":"24 William St",
    "sg:city":"Orange",
    "sg:classifiers":[
        {
            "category":"Social Services",
            "subcategory":"Retirement Home",
            "type":"Services"
        }
    ],
    "sg:phone":"+61 2 6361 4954",
    "sg:postcode":"2800",
    "sg:province":"NSW",
    "sg:tags":[
        "environmental",
        "consultant",
        "pollution"
    ],
    "wof:name":"Envirowest Consulting",
    "wof:placetype":"venue"
},
  "geometry": {"coordinates":[149.10610961899999,-33.282875061],"type":"Point"}
}