{
  "type": "Feature",
  "properties": {
    "addr:full":"Shop 4 320 Cheltenham Rd Keysborough VIC 3173",
    "addr:housenumber":"shop 4 320",
    "addr:postcode":"3173",
    "addr:street":"Cheltenham Rd",
    "iso:country":"AU",
    "sg:address":"Shop 4 320 Cheltenham Rd",
    "sg:city":"Keysborough",
    "sg:classifiers":[
        {
            "category":"Real Estate",
            "subcategory":"Real Estate Agent",
            "type":"Services"
        }
    ],
    "sg:phone":"+61 431 063 855",
    "sg:postcode":"3173",
    "sg:province":"VIC",
    "wof:name":"Michael Choi Real Estate",
    "wof:placetype":"venue"
},
  "geometry": {"coordinates":[145.174224853,-37.9947471619],"type":"Point"}
}