{
  "type": "Feature",
  "properties": {
    "addr:full":"16 Quinlan Ave St Marys SA 5042",
    "addr:housenumber":"16",
    "addr:postcode":"5042",
    "addr:street":"Quinlan Ave",
    "iso:country":"AU",
    "sg:address":"16 Quinlan Ave",
    "sg:city":"St Marys",
    "sg:classifiers":[
        {
            "category":"Professional",
            "subcategory":"Printing & Photocopies",
            "type":"Services"
        }
    ],
    "sg:phone":"+61 8 8277 1011",
    "sg:postcode":"5042",
    "sg:province":"SA",
    "sg:tags":[
        "screen",
        "printer"
    ],
    "wof:name":"Price Screen Process Pty Ltd",
    "wof:placetype":"venue"
},
  "geometry": {"coordinates":[138.57783499999999,-35.005894],"type":"Point"}
}