{
  "type": "Feature",
  "properties": {
    "addr:full":"Beach Rd Noarlunga Centre SA 5168",
    "addr:postcode":"5168",
    "addr:street":"Beach Rd",
    "iso:country":"AU",
    "sg:address":"Beach Rd",
    "sg:city":"Noarlunga Centre",
    "sg:classifiers":[
        {
            "category":"Deli",
            "type":"Food & Drink"
        }
    ],
    "sg:phone":"+61 8 8384 2513",
    "sg:postcode":"5168",
    "sg:province":"SA",
    "sg:tags":[
        "delicatessen"
    ],
    "wof:name":"The Railway Stop",
    "wof:placetype":"venue"
},
  "geometry": {"coordinates":[138.491790772,-35.1383476257],"type":"Point"}
}