{
  "type": "Feature",
  "properties": {
    "iso:country":"AU",
    "sg:address":"PO Box 2474",
    "sg:city":"Taren Point",
    "sg:classifiers":[
        {
            "category":"Government",
            "subcategory":"Fire Station",
            "type":"Public Place"
        }
    ],
    "sg:phone":"+61 2 9542 7722",
    "sg:postcode":"2229",
    "sg:province":"NSW",
    "sg:tags":[
        "equipment",
        "protection",
        "consultant"
    ],
    "wof:name":"OES Pty Ltd",
    "wof:placetype":"venue"
},
  "geometry": {"coordinates":[151.123336792,-34.0180511475],"type":"Point"}
}