{
  "type": "Feature",
  "properties": {
    "iso:country":"AU",
    "sg:address":"30 Rudloc Rd",
    "sg:city":"Morley",
    "sg:classifiers":[
        {
            "category":"Retail",
            "subcategory":"Auto Repair",
            "type":"Services"
        }
    ],
    "sg:phone":"+61 8 9276 1200",
    "sg:postcode":"6062",
    "sg:province":"WA",
    "sg:tags":[
        "repairer",
        "motor",
        "engineer"
    ],
    "wof:name":"Fenmac Automotives",
    "wof:placetype":"venue"
},
  "geometry": {"coordinates":[115.898178101,-31.9007530212],"type":"Point"}
}