{
  "type": "Feature",
  "properties": {
    "addr:full":"21 Sodium St Narangba QLD 4504",
    "addr:housenumber":"21",
    "addr:postcode":"4504",
    "addr:street":"Sodium St",
    "iso:country":"AU",
    "sg:address":"21 Sodium St",
    "sg:city":"Narangba",
    "sg:classifiers":[
        {
            "category":"Manufacturing",
            "subcategory":"Metals",
            "type":"Manufacturing & Wholesale Goods"
        }
    ],
    "sg:phone":"+61 7 3888 5922",
    "sg:postcode":"4504",
    "sg:province":"QLD",
    "sg:tags":[
        "steel",
        "fabricator",
        "mfrs"
    ],
    "wof:name":"Arana Steel Products",
    "wof:placetype":"venue"
},
  "geometry": {"coordinates":[152.9868927,-27.1971321106],"type":"Point"}
}