{
  "type": "Feature",
  "properties": {
    "addr:full":"5 Moss St Slacks Creek QLD 4127",
    "addr:housenumber":"5",
    "addr:postcode":"4127",
    "addr:street":"Moss St",
    "iso:country":"AU",
    "sg:address":"5 Moss St",
    "sg:city":"Slacks Creek",
    "sg:classifiers":[
        {
            "category":"Real Estate",
            "subcategory":"Real Estate Agent",
            "type":"Services"
        }
    ],
    "sg:phone":"+61 7 3208 3977",
    "sg:postcode":"4127",
    "sg:province":"QLD",
    "sg:tags":[
        "handyman's",
        "equipment",
        "hire",
        "builders",
        "contractor"
    ],
    "wof:name":"Builders Hire",
    "wof:placetype":"venue"
},
  "geometry": {"coordinates":[153.11724853499999,-27.6249465942],"type":"Point"}
}