{
  "type": "Feature",
  "properties": {
    "iso:country":"AU",
    "sg:address":"54 Glenormiston Rd",
    "sg:city":"Noorat",
    "sg:classifiers":[
        {
            "category":"Professional",
            "subcategory":"Art Services",
            "type":"Services"
        }
    ],
    "sg:phone":"+61 3 5592 5389",
    "sg:postcode":"3265",
    "sg:province":"VIC",
    "sg:tags":[
        "decorator",
        "painter"
    ],
    "wof:name":"Alls Painting",
    "wof:placetype":"venue"
},
  "geometry": {"coordinates":[142.93617248499999,-38.187625885],"type":"Point"}
}