{
  "type": "Feature",
  "properties": {
    "iso:country":"AU",
    "sg:address":"447 South St",
    "sg:city":"Toowoomba",
    "sg:classifiers":[
        {
            "category":"Professional",
            "subcategory":"Accounting & Tax Preparation",
            "type":"Services"
        }
    ],
    "sg:phone":"+61 7 4634 1044",
    "sg:postcode":"4350",
    "sg:province":"QLD",
    "sg:tags":[
        "accountant",
        "auditor"
    ],
    "wof:name":"Gordon JC",
    "wof:placetype":"venue"
},
  "geometry": {"coordinates":[151.912186,-27.572676],"type":"Point"}
}