{
  "type": "Feature",
  "properties": {
    "addr:full":"447 South St Toowoomba QLD 4350",
    "addr:housenumber":"447",
    "addr:postcode":"4350",
    "addr:street":"South St",
    "iso:country":"AU",
    "sg:address":"447 South St",
    "sg:city":"Toowoomba",
    "sg:classifiers":[
        {
            "category":"Professional",
            "subcategory":"Accounting & Tax Preparation",
            "type":"Services"
        }
    ],
    "sg:phone":"+61 7 4634 1044",
    "sg:postcode":"4350",
    "sg:province":"QLD",
    "sg:tags":[
        "accountant",
        "auditor"
    ],
    "wof:name":"Gordon JC",
    "wof:placetype":"venue"
},
  "geometry": {"coordinates":[151.91218599999999,-27.572676],"type":"Point"}
}