{
  "type": "Feature",
  "properties": {
    "addr:full":"117 Sheridan St Cairns QLD 4870",
    "addr:housenumber":"117",
    "addr:postcode":"4870",
    "addr:street":"Sheridan St",
    "iso:country":"AU",
    "sg:address":"117 Sheridan St",
    "sg:city":"Cairns",
    "sg:classifiers":[
        {
            "category":"Social Services",
            "subcategory":"Retirement Home",
            "type":"Services"
        }
    ],
    "sg:phone":"+61 7 4051 1870",
    "sg:postcode":"4870",
    "sg:province":"QLD",
    "sg:tags":[
        "t-shirt",
        "supplier"
    ],
    "wof:name":"Promo Perfect",
    "wof:placetype":"venue"
},
  "geometry": {"coordinates":[145.77239990199999,-16.9217700958],"type":"Point"}
}