{
  "type": "Feature",
  "properties": {
    "addr:full":"120 Hayward Ave Torrensville SA 5031",
    "addr:housenumber":"120",
    "addr:postcode":"5031",
    "addr:street":"Hayward Ave",
    "iso:country":"AU",
    "sg:address":"120 Hayward Ave",
    "sg:city":"Torrensville",
    "sg:classifiers":[
        {
            "category":"Farming",
            "subcategory":"Fish & Marine Products",
            "type":"Manufacturing & Wholesale Goods"
        }
    ],
    "sg:phone":"+61 8 8351 8455",
    "sg:postcode":"5031",
    "sg:province":"SA",
    "sg:tags":[
        "organic"
    ],
    "wof:name":"BettaLife Distributors Pty Ltd",
    "wof:placetype":"venue"
},
  "geometry": {"coordinates":[138.556549072,-34.9118309021],"type":"Point"}
}