{
  "type": "Feature",
  "properties": {
    "addr:full":"59 Elder St Alice Springs NT 0870",
    "addr:housenumber":"59",
    "addr:postcode":"nt 0870",
    "addr:street":"Elder St",
    "iso:country":"AU",
    "sg:address":"59 Elder St",
    "sg:city":"Alice Springs",
    "sg:classifiers":[
        {
            "category":"Professional",
            "subcategory":"Employment Agencies",
            "type":"Services"
        }
    ],
    "sg:phone":"+61 8 8952 6665",
    "sg:postcode":"0870",
    "sg:province":"NT",
    "wof:name":"Jobs Employment and Training",
    "wof:placetype":"venue"
},
  "geometry": {"coordinates":[133.86456298799999,-23.6949939728],"type":"Point"}
}