{
  "type": "Feature",
  "properties": {
    "addr:full":"547 Blaxland Rd Eastwood NSW 2122",
    "addr:housenumber":"547",
    "addr:postcode":"2122",
    "addr:street":"Blaxland Rd",
    "iso:country":"AU",
    "sg:address":"547 Blaxland Rd",
    "sg:city":"Eastwood",
    "sg:classifiers":[
        {
            "category":"Professional",
            "subcategory":"Art Services",
            "type":"Services"
        }
    ],
    "sg:phone":"+61 2 9802 5314",
    "sg:postcode":"2122",
    "sg:province":"NSW",
    "sg:tags":[
        "interior",
        "designer"
    ],
    "wof:name":"Em Elle & Jay Elle Pty Ltd",
    "wof:placetype":"venue"
},
  "geometry": {"coordinates":[151.090942383,-33.7935066223],"type":"Point"}
}