{
  "type": "Feature",
  "properties": {
    "addr:full":"125 Menin Rd Oakville NSW 2765",
    "addr:housenumber":"125",
    "addr:postcode":"2765",
    "addr:street":"Menin Rd",
    "iso:country":"AU",
    "sg:address":"125 Menin Rd",
    "sg:city":"Oakville",
    "sg:classifiers":[
        {
            "category":"Transit Center",
            "subcategory":"Freight",
            "type":"Transportation"
        }
    ],
    "sg:phone":"+61 2 9627 2869",
    "sg:postcode":"2765",
    "sg:province":"NSW",
    "sg:tags":[
        "turner",
        "wood"
    ],
    "sg:website":"http://www.expresswoodturning.com.au",
    "wof:name":"Express Wood Turning",
    "wof:placetype":"venue"
},
  "geometry": {"coordinates":[150.882125855,-33.6402778625],"type":"Point"}
}