{
  "type": "Feature",
  "properties": {
    "addr:full":"54 Abbey St Forestdale QLD 4118",
    "addr:housenumber":"54",
    "addr:postcode":"4118",
    "addr:street":"Abbey St",
    "iso:country":"AU",
    "sg:address":"54 Abbey St",
    "sg:city":"Forestdale",
    "sg:classifiers":[
        {
            "category":"Shopping",
            "subcategory":"Bicycles & Sporting Goods",
            "type":"Retail Goods"
        }
    ],
    "sg:phone":"+61 412 729 155",
    "sg:postcode":"4118",
    "sg:province":"QLD",
    "sg:tags":[
        "chemical",
        "equipment",
        "pool",
        "swimming"
    ],
    "wof:name":"Abbey Pool Services",
    "wof:placetype":"venue"
},
  "geometry": {"coordinates":[153.013549805,-27.6673812866],"type":"Point"}
}