{
  "type": "Feature",
  "properties": {
    "addr:full":"16 Liverpool Rd Summer Hill (Sydney) NSW 2130",
    "addr:housenumber":"16",
    "addr:postcode":"2130",
    "addr:street":"Liverpool Rd",
    "iso:country":"AU",
    "sg:address":"16 Liverpool Rd",
    "sg:city":"Summer Hill (Sydney)",
    "sg:classifiers":[
        {
            "category":"Personal",
            "subcategory":"Beauty Salon",
            "type":"Services"
        }
    ],
    "sg:phone":"+61 424 623 231",
    "sg:postcode":"2130",
    "sg:province":"NSW",
    "sg:tags":[
        "supply",
        "artist",
        "make-up"
    ],
    "wof:name":"Powder Room 1",
    "wof:placetype":"venue"
},
  "geometry": {"coordinates":[151.11369323700001,-33.8872795105],"type":"Point"}
}