{
  "type": "Feature",
  "properties": {
    "iso:country":"AU",
    "sg:address":"19 Fairlane Drv",
    "sg:city":"Mt Gambier",
    "sg:classifiers":[
        {
            "category":"Home & Garden",
            "subcategory":"Building Materials",
            "type":"Retail Goods"
        }
    ],
    "sg:phone":"+61 8 8725 0755",
    "sg:postcode":"5290",
    "sg:province":"SA",
    "sg:tags":[
        "supply"
    ],
    "wof:name":"S.E. Handymix",
    "wof:placetype":"venue"
},
  "geometry": {"coordinates":[140.75657699999999,-37.817188],"type":"Point"}
}