{
  "type": "Feature",
  "properties": {
    "addr:full":"3 Market St Yarragon VIC 3823",
    "addr:housenumber":"3",
    "addr:postcode":"3823",
    "addr:street":"Market St",
    "iso:country":"AU",
    "sg:address":"3 Market St",
    "sg:city":"Yarragon",
    "sg:classifiers":[
        {
            "category":"Professional",
            "type":"Services"
        }
    ],
    "sg:phone":"+61 3 5634 2192",
    "sg:postcode":"3823",
    "sg:province":"VIC",
    "sg:tags":[
        "transport"
    ],
    "wof:name":"The Trans-Help Foundation",
    "wof:placetype":"venue"
},
  "geometry": {"coordinates":[146.06585699999999,-38.207661],"type":"Point"}
}