{
  "type": "Feature",
  "properties": {
    "addr:full":"14 Wyuna St Brunswick West VIC 3055",
    "addr:housenumber":"14",
    "addr:postcode":"3055",
    "addr:street":"Wyuna St",
    "iso:country":"AU",
    "sg:address":"14 Wyuna St",
    "sg:city":"Brunswick West",
    "sg:classifiers":[
        {
            "category":"Building & Trades",
            "subcategory":"Plumbing",
            "type":"Services"
        }
    ],
    "sg:phone":"+61 412 523 001",
    "sg:postcode":"3055",
    "sg:province":"VIC",
    "sg:tags":[
        "plumber",
        "gasfitters"
    ],
    "wof:name":"PK-1 Plumbing & Gasfitting",
    "wof:placetype":"venue"
},
  "geometry": {"coordinates":[144.938690186,-37.773059845],"type":"Point"}
}