{
  "type": "Feature",
  "properties": {
    "addr:full":"Unit 6 108 Ben Boyd Rd Neutral Bay NSW 2089",
    "addr:housenumber":"108",
    "addr:postcode":"2089",
    "addr:street":"Ben Boyd Rd",
    "iso:country":"AU",
    "sg:address":"Unit 6 108 Ben Boyd Rd",
    "sg:city":"Neutral Bay",
    "sg:classifiers":[
        {
            "category":"Food & Beverages",
            "subcategory":"Specialty",
            "type":"Retail Goods"
        }
    ],
    "sg:phone":"+61 2 9904 9784",
    "sg:postcode":"2089",
    "sg:province":"NSW",
    "sg:tags":[
        "product",
        "health"
    ],
    "wof:name":"Activate Action Marketing Pty Ltd",
    "wof:placetype":"venue"
},
  "geometry": {"coordinates":[151.21856689399999,-33.8344421387],"type":"Point"}
}