{
  "type": "Feature",
  "properties": {
    "addr:full":"Unit 4 208 Walters Rd Blacktown NSW 2148",
    "addr:housenumber":"208",
    "addr:postcode":"2148",
    "addr:street":"Walters Rd",
    "iso:country":"AU",
    "sg:address":"Unit 4 208 Walters Rd",
    "sg:city":"Blacktown",
    "sg:classifiers":[
        {
            "category":"Shopping",
            "subcategory":"Stationery & Office Supplies",
            "type":"Retail Goods"
        }
    ],
    "sg:phone":"+61 2 9672 1845",
    "sg:postcode":"2148",
    "sg:province":"NSW",
    "sg:tags":[
        "packaging",
        "material"
    ],
    "wof:name":"Foam Masters Pty Ltd",
    "wof:placetype":"venue"
},
  "geometry": {"coordinates":[150.88966369600001,-33.7950668335],"type":"Point"}
}