{
  "type": "Feature",
  "properties": {
    "addr:full":"15 Ison Crt Altona Meadows VIC 3028",
    "addr:housenumber":"15",
    "addr:postcode":"3028",
    "addr:street":"Ison Crt",
    "iso:country":"AU",
    "sg:address":"15 Ison Crt",
    "sg:city":"Altona Meadows",
    "sg:classifiers":[
        {
            "category":"Health Services",
            "subcategory":"Dentist",
            "type":"Services"
        }
    ],
    "sg:phone":"+61 3 9315 7912",
    "sg:postcode":"3028",
    "sg:province":"VIC",
    "sg:tags":[
        "dental",
        "prosthetist"
    ],
    "wof:name":"LTJJ Orthodontic Supplies",
    "wof:placetype":"venue"
},
  "geometry": {"coordinates":[144.77192700000001,-37.878433],"type":"Point"}
}