{
  "type": "Feature",
  "properties": {
    "addr:full":"40 Dutton St Dutton Park QLD 4102",
    "addr:housenumber":"40",
    "addr:postcode":"4102",
    "addr:street":"Dutton St",
    "iso:country":"AU",
    "sg:address":"40 Dutton St",
    "sg:city":"Dutton Park",
    "sg:classifiers":[
        {
            "category":"Personal",
            "subcategory":"Beauty Salon",
            "type":"Services"
        }
    ],
    "sg:phone":"+61 7 3846 5758",
    "sg:postcode":"4102",
    "sg:province":"QLD",
    "sg:tags":[
        "supply",
        "artist",
        "make-up"
    ],
    "wof:name":"Beautiful Images By Toula",
    "wof:placetype":"venue"
},
  "geometry": {"coordinates":[153.02970886200001,-27.4982624054],"type":"Point"}
}