{
  "type": "Feature",
  "properties": {
    "addr:full":"80 Highett St Richmond VIC 3121",
    "addr:housenumber":"80",
    "addr:postcode":"3121",
    "addr:street":"Highett St",
    "iso:country":"AU",
    "sg:address":"80 Highett St",
    "sg:city":"Richmond",
    "sg:classifiers":[
        {
            "category":"Health Services",
            "subcategory":"Health Practitioner",
            "type":"Services"
        }
    ],
    "sg:phone":"+61 3 9429 9312",
    "sg:postcode":"3121",
    "sg:province":"VIC",
    "sg:tags":[
        "acupuncture"
    ],
    "wof:name":"Hastie Mark George",
    "wof:placetype":"venue"
},
  "geometry": {"coordinates":[144.99446105999999,-37.8153762817],"type":"Point"}
}