{
  "type": "Feature",
  "properties": {
    "addr:full":"23- 27 Valerie St Kew East VIC 3102",
    "addr:housenumber":"27",
    "addr:postcode":"3102",
    "addr:street":"Valerie St",
    "iso:country":"AU",
    "sg:address":"23- 27 Valerie St",
    "sg:city":"Kew East",
    "sg:classifiers":[
        {
            "category":"Education",
            "subcategory":"Dance Studio",
            "type":"Public Place"
        }
    ],
    "sg:phone":"+61 3 9859 6499",
    "sg:postcode":"3102",
    "sg:province":"VIC",
    "sg:tags":[
        "venue",
        "tuition"
    ],
    "wof:name":"Aus Girls Dance",
    "wof:placetype":"venue"
},
  "geometry": {"coordinates":[145.052337647,-37.7985572815],"type":"Point"}
}