{
  "type": "Feature",
  "properties": {
    "addr:full":"2187 Princes Hwy Clayton VIC 3168",
    "addr:housenumber":"2187",
    "addr:postcode":"3168",
    "addr:street":"Princes Hwy",
    "iso:country":"AU",
    "sg:address":"2187 Princes Hwy",
    "sg:city":"Clayton",
    "sg:classifiers":[
        {
            "category":"Retail",
            "subcategory":"Storage",
            "type":"Services"
        }
    ],
    "sg:phone":"+61 3 9540 3777",
    "sg:postcode":"3168",
    "sg:province":"VIC",
    "wof:name":"Your Self Storage",
    "wof:placetype":"venue"
},
  "geometry": {"coordinates":[145.14593505900001,-37.9257164001],"type":"Point"}
}