{
  "type": "Feature",
  "properties": {
    "addr:full":"1/ 71 William St Caloundra QLD 4551",
    "addr:housenumber":"/ 71",
    "addr:postcode":"4551",
    "addr:street":"William St",
    "iso:country":"AU",
    "sg:address":"1/ 71 William St",
    "sg:city":"Caloundra",
    "sg:classifiers":[
        {
            "category":"Wholesale",
            "subcategory":"Home Furnishings",
            "type":"Manufacturing & Wholesale Goods"
        }
    ],
    "sg:phone":"+61 7 5491 6548",
    "sg:postcode":"4551",
    "sg:province":"QLD",
    "sg:tags":[
        "wholesaler",
        "curtain",
        "mfrs"
    ],
    "wof:name":"Sunrise Track Fitting",
    "wof:placetype":"venue"
},
  "geometry": {"coordinates":[153.13154602,-26.7927265167],"type":"Point"}
}