{
  "type": "Feature",
  "properties": {
    "addr:full":"787 Military Rd Mosman NSW 2088",
    "addr:housenumber":"787",
    "addr:postcode":"2088",
    "addr:street":"Military Rd",
    "iso:country":"AU",
    "sg:address":"787 Military Rd",
    "sg:city":"Mosman",
    "sg:classifiers":[
        {
            "category":"Shopping",
            "subcategory":"Optical Goods",
            "type":"Retail Goods"
        }
    ],
    "sg:phone":"+61 2 9969 4719",
    "sg:postcode":"2088",
    "sg:province":"NSW",
    "sg:tags":[
        "dispenser",
        "prescription"
    ],
    "wof:name":"OPSM",
    "wof:placetype":"venue"
},
  "geometry": {"coordinates":[151.244064331,-33.8305625916],"type":"Point"}
}