{
  "type": "Feature",
  "properties": {
    "addr:full":"Bourke St Alexandria NSW 2015",
    "addr:postcode":"2015",
    "addr:street":"Bourke St",
    "iso:country":"AU",
    "sg:address":"Bourke St",
    "sg:city":"Alexandria",
    "sg:classifiers":[
        {
            "category":"Building & Trades",
            "subcategory":"Plumbing",
            "type":"Services"
        }
    ],
    "sg:phone":"+61 408 619 715",
    "sg:postcode":"2015",
    "sg:province":"NSW",
    "sg:tags":[
        "plumber",
        "gasfitters"
    ],
    "wof:name":"AAAB A Australia Plumbing & Drainage",
    "wof:placetype":"venue"
},
  "geometry": {"coordinates":[151.20297241200001,-33.9054641724],"type":"Point"}
}