{
  "type": "Feature",
  "properties": {
    "addr:full":"Shop 12/ 1 Mons Rd Forest Glen QLD 4556",
    "addr:housenumber":"shop 12 / 1",
    "addr:postcode":"4556",
    "addr:street":"Mons Rd",
    "iso:country":"AU",
    "sg:address":"Shop 12/ 1 Mons Rd",
    "sg:city":"Forest Glen",
    "sg:classifiers":[
        {
            "category":"Government",
            "subcategory":"Court House",
            "type":"Public Place"
        }
    ],
    "sg:phone":"+61 7 5476 5702",
    "sg:postcode":"4556",
    "sg:province":"QLD",
    "sg:tags":[
        "personal",
        "marriage",
        "family",
        "counselling"
    ],
    "wof:name":"Care Network Sunshine Coast Inc",
    "wof:placetype":"venue"
},
  "geometry": {"coordinates":[153.01319885300001,-26.6885147095],"type":"Point"}
}