{
  "type": "Feature",
  "properties": {
    "addr:full":"56 Marie St St George QLD 4487",
    "addr:housenumber":"56",
    "addr:postcode":"4487",
    "addr:street":"Marie St",
    "iso:country":"AU",
    "sg:address":"56 Marie St",
    "sg:city":"St George",
    "sg:classifiers":[
        {
            "category":"Farming",
            "subcategory":"Farm & Veterinary Services",
            "type":"Manufacturing & Wholesale Goods"
        }
    ],
    "sg:phone":"+61 7 4625 5909",
    "sg:postcode":"4487",
    "sg:province":"QLD",
    "sg:tags":[
        "agricultural",
        "advisory"
    ],
    "wof:name":"Haslem A G Pty Ltd",
    "wof:placetype":"venue"
},
  "geometry": {"coordinates":[148.57443237300001,-28.0460529327],"type":"Point"}
}