{
  "type": "Feature",
  "properties": {
    "addr:full":"55 Takalvan St Bundaberg QLD 4670",
    "addr:housenumber":"55",
    "addr:postcode":"4670",
    "addr:street":"Takalvan St",
    "iso:country":"AU",
    "sg:address":"55 Takalvan St",
    "sg:city":"Bundaberg",
    "sg:classifiers":[
        {
            "category":"Travel",
            "subcategory":"Travel Agent",
            "type":"Entertainment"
        }
    ],
    "sg:phone":"+61 7 4153 1037",
    "sg:postcode":"4670",
    "sg:province":"QLD",
    "sg:tags":[
        "consultant"
    ],
    "wof:name":"Bundaberg Coach Tours",
    "wof:placetype":"venue"
},
  "geometry": {"coordinates":[152.32870483400001,-24.8783226013],"type":"Point"}
}