{
  "type": "Feature",
  "properties": {
    "iso:country":"AU",
    "sg:address":"47 Kennedy Drv",
    "sg:city":"Tweed Heads",
    "sg:classifiers":[
        {
            "category":"Fast Food",
            "type":"Food & Drink"
        }
    ],
    "sg:phone":"+61 7 5536 6937",
    "sg:postcode":"2485",
    "sg:province":"NSW",
    "sg:tags":[
        "away",
        "take"
    ],
    "wof:name":"Scale Seafoods",
    "wof:placetype":"venue"
},
  "geometry": {"coordinates":[153.52151489299999,-28.1873989105],"type":"Point"}
}