{
  "type": "Feature",
  "properties": {
    "iso:country":"AU",
    "sg:address":"118 Narrabeen Park Pde",
    "sg:city":"Warriewood",
    "sg:classifiers":[
        {
            "category":"Restaurant",
            "type":"Food & Drink"
        }
    ],
    "sg:phone":"+61 2 9999 5740",
    "sg:postcode":"2102",
    "sg:province":"NSW",
    "wof:name":"Clives Restaurant",
    "wof:placetype":"venue"
},
  "geometry": {"coordinates":[151.307312,-33.691853],"type":"Point"}
}