{
  "type": "Feature",
  "properties": {
    "iso:country":"AU",
    "sg:address":"182 Albion St",
    "sg:city":"Brunswick",
    "sg:classifiers":[
        {
            "category":"Banks & Credit Unions",
            "subcategory":"Financial Services",
            "type":"Services"
        }
    ],
    "sg:phone":"+61 3 9386 4416",
    "sg:postcode":"3056",
    "sg:province":"VIC",
    "sg:tags":[
        "planning"
    ],
    "wof:name":"Superannuation Support Pty Ltd",
    "wof:placetype":"venue"
},
  "geometry": {"coordinates":[144.96484375,-37.7611122131],"type":"Point"}
}