{
  "type": "Feature",
  "properties": {
    "iso:country":"AU",
    "sg:address":"387 Pacific Hwy",
    "sg:city":"Artarmon",
    "sg:classifiers":[
        {
            "category":"Autos & Motor Vehicles",
            "subcategory":"Automobile Sales",
            "type":"Retail Goods"
        }
    ],
    "sg:phone":"+61 2 9439 5877",
    "sg:postcode":"2064",
    "sg:province":"NSW",
    "sg:tags":[
        "car",
        "new"
    ],
    "wof:name":"Autoland Rover",
    "wof:placetype":"venue"
},
  "geometry": {"coordinates":[151.178924561,-33.8163948059],"type":"Point"}
}