{
  "type": "Feature",
  "properties": {
    "addr:full":"Suite 2, Earle House Lavelle St Nerang QLD 4211",
    "addr:postcode":"4211",
    "addr:street":"Lavelle St",
    "iso:country":"AU",
    "sg:address":"Suite 2, Earle House Lavelle St",
    "sg:city":"Nerang",
    "sg:classifiers":[
        {
            "category":"Health Services",
            "subcategory":"Dentist",
            "type":"Services"
        }
    ],
    "sg:phone":"+61 7 5596 0411",
    "sg:postcode":"4211",
    "sg:province":"QLD",
    "sg:tags":[
        "technician",
        "dental"
    ],
    "wof:name":"C Mark Thompson",
    "wof:placetype":"venue"
},
  "geometry": {"coordinates":[153.33526611299999,-27.9900856018],"type":"Point"}
}