{
  "type": "Feature",
  "properties": {
    "addr:full":"9 Willansby Ave Brighton VIC 3186",
    "addr:housenumber":"9",
    "addr:postcode":"3186",
    "addr:street":"Willansby Ave",
    "iso:country":"AU",
    "sg:address":"9 Willansby Ave",
    "sg:city":"Brighton",
    "sg:classifiers":[
        {
            "category":"Health Services",
            "subcategory":"Doctor",
            "type":"Services"
        }
    ],
    "sg:phone":"+61 3 9592 9391",
    "sg:postcode":"3186",
    "sg:province":"VIC",
    "sg:tags":[
        "medical",
        "practitioner"
    ],
    "wof:name":"Hare R M",
    "wof:placetype":"venue"
},
  "geometry": {"coordinates":[145.00318908700001,-37.908416748],"type":"Point"}
}