{
  "type": "Feature",
  "properties": {
    "iso:country":"AU",
    "sg:address":"18 Highfield Ave St",
    "sg:city":"Georges",
    "sg:classifiers":[
        {
            "category":"Mining & Drilling",
            "type":"Manufacturing & Wholesale Goods"
        }
    ],
    "sg:phone":"+61 8 8379 4760",
    "sg:postcode":"5064",
    "sg:province":"SA",
    "sg:tags":[
        "geologist"
    ],
    "wof:name":"Geosurveys Australia",
    "wof:placetype":"venue"
},
  "geometry": {"coordinates":[138.646408081,-34.9488334656],"type":"Point"}
}