{
  "type": "Feature",
  "properties": {
    "addr:full":"52 Beenleigh-Redland Bay Rd Cornubia QLD 4130",
    "addr:housenumber":"52",
    "addr:postcode":"4130",
    "addr:street":"Beenleigh-Redland Bay Rd",
    "iso:country":"AU",
    "sg:address":"52 Beenleigh-Redland Bay Rd",
    "sg:city":"Cornubia",
    "sg:classifiers":[
        {
            "category":"Manufacturing",
            "subcategory":"Electronics",
            "type":"Manufacturing & Wholesale Goods"
        }
    ],
    "sg:phone":"+61 7 3209 8648",
    "sg:postcode":"4130",
    "sg:province":"QLD",
    "sg:tags":[
        "oven",
        "microwave"
    ],
    "wof:name":"Shailer Park Electronics",
    "wof:placetype":"venue"
},
  "geometry": {"coordinates":[153.22659301799999,-27.6755943298],"type":"Point"}
}