{
  "type": "Feature",
  "properties": {
    "iso:country":"AU",
    "sg:address":"PO Box 394",
    "sg:city":"Park Holme",
    "sg:classifiers":[
        {
            "category":"Building & Trades",
            "subcategory":"Cleaning & Sanitation",
            "type":"Services"
        }
    ],
    "sg:phone":"+61 402 362 785",
    "sg:postcode":"5043",
    "sg:province":"SA",
    "sg:tags":[
        "industrial",
        "commercial",
        "contractor"
    ],
    "wof:name":"Infinity Cleaning Services",
    "wof:placetype":"venue"
},
  "geometry": {"coordinates":[138.556793,-34.990849],"type":"Point"}
}