{
  "type": "Feature",
  "properties": {
    "iso:country":"AU",
    "sg:address":"Northgate Shopping Centre Main Rd",
    "sg:city":"Glenorchy",
    "sg:classifiers":[
        {
            "category":"Food & Beverages",
            "subcategory":"Bakery",
            "type":"Retail Goods"
        }
    ],
    "sg:phone":"+61 3 6273 8225",
    "sg:postcode":"7010",
    "sg:province":"TAS",
    "sg:tags":[
        "cake",
        "shop",
        "pastry"
    ],
    "wof:name":"Cheesecake Shop The",
    "wof:placetype":"venue"
},
  "geometry": {"coordinates":[147.27200317399999,-42.8324241638],"type":"Point"}
}