{
  "type": "Feature",
  "properties": {
    "iso:country":"AU",
    "sg:address":"7 Autumn Crt",
    "sg:city":"Duncraig",
    "sg:classifiers":[
        {
            "category":"Professional",
            "subcategory":"Art Services",
            "type":"Services"
        }
    ],
    "sg:phone":"+61 418 925 548",
    "sg:postcode":"6023",
    "sg:province":"WA",
    "sg:tags":[
        "decorator",
        "painter"
    ],
    "wof:name":"Desmond Decor Painter & Decorator",
    "wof:placetype":"venue"
},
  "geometry": {"coordinates":[115.785293579,-31.8386230469],"type":"Point"}
}