{
  "type": "Feature",
  "properties": {
    "iso:country":"AU",
    "sg:address":"107 Mostyn St",
    "sg:city":"Castlemaine",
    "sg:classifiers":[
        {
            "category":"Food & Beverages",
            "subcategory":"Specialty",
            "type":"Retail Goods"
        }
    ],
    "sg:phone":"+61 3 5472 2083",
    "sg:postcode":"3450",
    "sg:province":"VIC",
    "sg:tags":[
        "product",
        "health"
    ],
    "wof:name":"Castlemaine Natural Food Store",
    "wof:placetype":"venue"
},
  "geometry": {"coordinates":[144.21958923299999,-37.0657615662],"type":"Point"}
}