{
  "type": "Feature",
  "properties": {
    "iso:country":"AU",
    "sg:address":"32 Hunter St",
    "sg:city":"Broome",
    "sg:classifiers":[
        {
            "category":"Taxi",
            "type":"Transportation"
        }
    ],
    "sg:phone":"+61 1800 880 330",
    "sg:postcode":"6725",
    "sg:province":"WA",
    "sg:tags":[
        "cab"
    ],
    "wof:name":"Roebuck Taxi's",
    "wof:placetype":"venue"
},
  "geometry": {"coordinates":[122.22203064,-17.9705867767],"type":"Point"}
}