{
  "type": "Feature",
  "properties": {
    "iso:country":"AU",
    "sg:address":"160 Welsford St",
    "sg:city":"Shepparton",
    "sg:classifiers":[
        {
            "category":"Professional",
            "subcategory":"Accounting & Tax Preparation",
            "type":"Services"
        }
    ],
    "sg:phone":"+61 3 5821 4622",
    "sg:postcode":"3630",
    "sg:province":"VIC",
    "sg:tags":[
        "consultant",
        "taxation"
    ],
    "wof:name":"Stubbs Wallace",
    "wof:placetype":"venue"
},
  "geometry": {"coordinates":[145.39759826700001,-36.3813018799],"type":"Point"}
}