{
  "type": "Feature",
  "properties": {
    "iso:country":"AU",
    "sg:address":"75 Sackville St",
    "sg:city":"Lalor Park",
    "sg:classifiers":[
        {
            "category":"Travel",
            "subcategory":"Hotels & Motels",
            "type":"Entertainment"
        }
    ],
    "sg:phone":"+61 2 9671 1675",
    "sg:postcode":"2147",
    "sg:province":"NSW",
    "sg:tags":[
        "accommodation"
    ],
    "wof:name":"The Brewhouse At Lalor Park",
    "wof:placetype":"venue"
},
  "geometry": {"coordinates":[150.91949462900001,-33.7645835876],"type":"Point"}
}