{
  "type": "Feature",
  "properties": {
    "addr:full":"1 Mt Pleasant Rd Monbulk VIC 3793",
    "addr:housenumber":"1",
    "addr:postcode":"3793",
    "addr:street":"Mt Pleasant Rd",
    "iso:country":"AU",
    "sg:address":"1 Mt Pleasant Rd",
    "sg:city":"Monbulk",
    "sg:classifiers":[
        {
            "category":"Health Services",
            "subcategory":"Doctor",
            "type":"Services"
        }
    ],
    "sg:phone":"+61 3 9752 1455",
    "sg:postcode":"3793",
    "sg:province":"VIC",
    "sg:tags":[
        "medical",
        "practitioner"
    ],
    "wof:name":"Gruner John Dr",
    "wof:placetype":"venue"
},
  "geometry": {"coordinates":[145.40713500999999,-37.8742675781],"type":"Point"}
}