{
  "type": "Feature",
  "properties": {
    "addr:full":"Cnr River St & Las Balsas Plz Ballina NSW 2478",
    "addr:postcode":"2478",
    "addr:street":"Cnr River St & Las Balsas Plz",
    "iso:country":"AU",
    "sg:address":"Cnr River St & Las Balsas Plz",
    "sg:city":"Ballina",
    "sg:classifiers":[
        {
            "category":"Communications",
            "subcategory":"News Services",
            "type":"Services"
        }
    ],
    "sg:phone":"+61 2 6686 3484",
    "sg:postcode":"2478",
    "sg:province":"NSW",
    "sg:tags":[
        "information",
        "tourist",
        "attractions"
    ],
    "wof:name":"Ballina Visitor Information Centre",
    "wof:placetype":"venue"
},
  "geometry": {"coordinates":[153.56559753400001,-28.8725948334],"type":"Point"}
}