{
  "type": "Feature",
  "properties": {
    "addr:full":"552 Somerville Rd Sunshine VIC 3020",
    "addr:housenumber":"552",
    "addr:postcode":"3020",
    "addr:street":"Somerville Rd",
    "iso:country":"AU",
    "sg:address":"552 Somerville Rd",
    "sg:city":"Sunshine",
    "sg:classifiers":[
        {
            "category":"Manufacturing",
            "subcategory":"Buildings",
            "type":"Manufacturing & Wholesale Goods"
        }
    ],
    "sg:phone":"+61 3 9312 7300",
    "sg:postcode":"3020",
    "sg:province":"VIC",
    "sg:tags":[
        "transportable",
        "domestic",
        "relocatable"
    ],
    "wof:name":"Sure-Lock Homes Pty Ltd",
    "wof:placetype":"venue"
},
  "geometry": {"coordinates":[144.82856799999999,-37.80658],"type":"Point"}
}