{
  "type": "Feature",
  "properties": {
    "iso:country":"AU",
    "sg:address":"552 Somerville Rd",
    "sg:city":"Sunshine",
    "sg:classifiers":[
        {
            "category":"Manufacturing",
            "subcategory":"Buildings",
            "type":"Manufacturing & Wholesale Goods"
        }
    ],
    "sg:phone":"+61 3 9312 7300",
    "sg:postcode":"3020",
    "sg:province":"VIC",
    "sg:tags":[
        "transportable",
        "domestic",
        "relocatable"
    ],
    "wof:name":"Sure-Lock Homes Pty Ltd",
    "wof:placetype":"venue"
},
  "geometry": {"coordinates":[144.828568,-37.80658],"type":"Point"}
}