{
  "type": "Feature",
  "properties": {
    "iso:country":"AU",
    "sg:address":"Shop 122",
    "sg:city":"B, Stocklands Shopping Centre Burleigh",
    "sg:classifiers":[
        {
            "category":"Health Services",
            "subcategory":"Doctor",
            "type":"Services"
        }
    ],
    "sg:phone":"+61 7 5535 5170",
    "sg:postcode":"4220",
    "sg:province":"QLD",
    "sg:tags":[
        "medical",
        "practitioner"
    ],
    "wof:name":"Martin Bull Dr",
    "wof:placetype":"venue"
},
  "geometry": {"coordinates":[153.432662964,-28.0981998444],"type":"Point"}
}