{
  "type": "Feature",
  "properties": {
    "addr:full":"1 Bowen St Narrabri NSW 2390",
    "addr:housenumber":"1",
    "addr:postcode":"2390",
    "addr:street":"Bowen St",
    "iso:country":"AU",
    "sg:address":"1 Bowen St",
    "sg:city":"Narrabri",
    "sg:classifiers":[
        {
            "category":"Farming",
            "subcategory":"Farm & Veterinary Services",
            "type":"Manufacturing & Wholesale Goods"
        }
    ],
    "sg:phone":"+61 2 6792 2720",
    "sg:postcode":"2390",
    "sg:province":"NSW",
    "sg:tags":[
        "irrigation",
        "reticulation",
        "system"
    ],
    "wof:name":"Gleeson Surveying+",
    "wof:placetype":"venue"
},
  "geometry": {"coordinates":[149.788406372,-30.3270053864],"type":"Point"}
}