{
  "type": "Feature",
  "properties": {
    "iso:country":"AU",
    "sg:address":"480A Elgar Rd",
    "sg:city":"Box Hill",
    "sg:classifiers":[
        {
            "category":"Education",
            "subcategory":"Special Training",
            "type":"Public Place"
        }
    ],
    "sg:phone":"+61 3 9739 7061",
    "sg:postcode":"3128",
    "sg:province":"VIC",
    "sg:tags":[
        "development"
    ],
    "wof:name":"Australian Hypnotherapy Training & Counselling",
    "wof:placetype":"venue"
},
  "geometry": {"coordinates":[145.11570739699999,-37.8140945435],"type":"Point"}
}