{
  "type": "Feature",
  "properties": {
    "addr:full":"35 Firth Street Arncliffe NSW 2205",
    "addr:housenumber":"35",
    "addr:postcode":"2205",
    "addr:street":"Firth Street",
    "iso:country":"AU",
    "sg:address":"35 Firth Street",
    "sg:city":"Arncliffe",
    "sg:classifiers":[
        {
            "category":"Real Estate",
            "subcategory":"Real Estate Agent",
            "type":"Services"
        }
    ],
    "sg:phone":"+61 2 9556 1388",
    "sg:postcode":"2205",
    "sg:province":"NSW",
    "wof:name":"Simon Mandile First National",
    "wof:placetype":"venue"
},
  "geometry": {"coordinates":[151.14660599999999,-33.936703],"type":"Point"}
}