{
  "type": "Feature",
  "properties": {
    "addr:full":"833 Nepean Hwy Moorabbin VIC 3189",
    "addr:housenumber":"833",
    "addr:postcode":"3189",
    "addr:street":"Nepean Hwy",
    "iso:country":"AU",
    "sg:address":"833 Nepean Hwy",
    "sg:city":"Moorabbin",
    "sg:classifiers":[
        {
            "category":"Home & Garden",
            "subcategory":"Building Materials",
            "type":"Retail Goods"
        }
    ],
    "sg:phone":"+61 3 9576 5233",
    "sg:postcode":"3189",
    "sg:province":"VIC",
    "sg:tags":[
        "plaster",
        "plasterboard",
        "supply"
    ],
    "wof:name":"Bayside Plasterworks",
    "wof:placetype":"venue"
},
  "geometry": {"coordinates":[145.026809692,-37.9248657227],"type":"Point"}
}