{
  "type": "Feature",
  "properties": {
    "addr:full":"20/ 60 Manning St Tuncurry NSW 2428",
    "addr:housenumber":"20 / 60",
    "addr:postcode":"2428",
    "addr:street":"Manning St",
    "iso:country":"AU",
    "sg:address":"20/ 60 Manning St",
    "sg:city":"Tuncurry",
    "sg:classifiers":[
        {
            "category":"Building & Trades",
            "subcategory":"Construction",
            "type":"Services"
        }
    ],
    "sg:phone":"+61 2 6554 8171",
    "sg:postcode":"2428",
    "sg:province":"NSW",
    "sg:tags":[
        "management"
    ],
    "wof:name":"Ware Building Pty. Ltd.",
    "wof:placetype":"venue"
},
  "geometry": {"coordinates":[152.49992399999999,-32.176212],"type":"Point"}
}