{
  "type": "Feature",
  "properties": {
    "iso:country":"AU",
    "sg:address":"Level 1/ 2 Rankins La",
    "sg:city":"Melbourne",
    "sg:classifiers":[
        {
            "category":"Professional",
            "subcategory":"Art Services",
            "type":"Services"
        }
    ],
    "sg:phone":"+61 3 9663 6675",
    "sg:postcode":"3000",
    "sg:province":"VIC",
    "sg:tags":[
        "graphic",
        "designer"
    ],
    "wof:name":"Round",
    "wof:placetype":"venue"
},
  "geometry": {"coordinates":[144.96194457999999,-37.8136482239],"type":"Point"}
}