{
  "type": "Feature",
  "properties": {
    "iso:country":"AU",
    "sg:address":"45b Eckersley Ave",
    "sg:city":"Buderim",
    "sg:classifiers":[
        {
            "category":"Utilities",
            "subcategory":"Electric",
            "type":"Services"
        }
    ],
    "sg:phone":"+61 418 712 364",
    "sg:postcode":"4556",
    "sg:province":"QLD",
    "sg:tags":[
        "electrical",
        "contractor"
    ],
    "wof:name":"Craig Charlish",
    "wof:placetype":"venue"
},
  "geometry": {"coordinates":[153.073486328,-26.6806335449],"type":"Point"}
}