{
  "type": "Feature",
  "properties": {
    "addr:full":"4 Linden Crt Doncaster VIC 3108",
    "addr:housenumber":"4",
    "addr:postcode":"3108",
    "addr:street":"Linden Crt",
    "iso:country":"AU",
    "sg:address":"4 Linden Crt",
    "sg:city":"Doncaster",
    "sg:classifiers":[
        {
            "category":"Building & Trades",
            "subcategory":"Plumbing",
            "type":"Services"
        }
    ],
    "sg:phone":"+61 3 9848 2682",
    "sg:postcode":"3108",
    "sg:province":"VIC",
    "sg:tags":[
        "repair",
        "appliance",
        "system",
        "heating"
    ],
    "wof:name":"AGM Heating Service Co",
    "wof:placetype":"venue"
},
  "geometry": {"coordinates":[145.13703918499999,-37.7885932922],"type":"Point"}
}