{
  "type": "Feature",
  "properties": {
    "addr:full":"Lot 75 Lamont St Ongerup WA 6336",
    "addr:postcode":"6336",
    "addr:street":"Lamont St",
    "iso:country":"AU",
    "sg:address":"Lot 75 Lamont St",
    "sg:city":"Ongerup",
    "sg:classifiers":[
        {
            "category":"Education",
            "subcategory":"Kindergarten",
            "type":"Public Place"
        }
    ],
    "sg:phone":"+61 8 9828 2069",
    "sg:postcode":"6336",
    "sg:province":"WA",
    "sg:tags":[
        "pre-schools"
    ],
    "wof:name":"Ongerup 4 Year Old Family Centre",
    "wof:placetype":"venue"
},
  "geometry": {"coordinates":[118.487266541,-33.9639854431],"type":"Point"}
}