{
  "type": "Feature",
  "properties": {
    "addr:full":"Church Rd Curlwaa VIC 2648",
    "addr:postcode":"2648",
    "addr:street":"Church Rd",
    "iso:country":"AU",
    "sg:address":"Church Rd",
    "sg:city":"Curlwaa",
    "sg:classifiers":[
        {
            "category":"Farming",
            "subcategory":"Nursery",
            "type":"Manufacturing & Wholesale Goods"
        }
    ],
    "sg:phone":"+61 3 5027 6310",
    "sg:postcode":"2648",
    "sg:province":"VIC",
    "wof:name":"Sage Grove Citrus Nursery",
    "wof:placetype":"venue"
},
  "geometry": {"coordinates":[141.96603400000001,-34.092007],"type":"Point"}
}