{
  "type": "Feature",
  "properties": {
    "addr:full":"PO Box 2187 Richmond South VIC 3121",
    "addr:postcode":"3121",
    "iso:country":"AU",
    "sg:address":"PO Box 2187",
    "sg:city":"Richmond South",
    "sg:classifiers":[
        {
            "category":"Building & Trades",
            "subcategory":"Equipment Rental",
            "type":"Services"
        }
    ],
    "sg:phone":"+61 400 934 431",
    "sg:postcode":"3121",
    "sg:province":"VIC",
    "sg:tags":[
        "demolition",
        "contractor"
    ],
    "wof:name":"AA Quick Building Services",
    "wof:placetype":"venue"
},
  "geometry": {"coordinates":[145.00822448700001,-37.8229217529],"type":"Point"}
}