{
  "type": "Feature",
  "properties": {
    "addr:full":"3/ 55 Garden Drv Tullamarine VIC 3043",
    "addr:housenumber":"/ 55",
    "addr:postcode":"3043",
    "addr:street":"Garden Drv",
    "iso:country":"AU",
    "sg:address":"3/ 55 Garden Drv",
    "sg:city":"Tullamarine",
    "sg:classifiers":[
        {
            "category":"Professional",
            "type":"Services"
        }
    ],
    "sg:phone":"+61 418 397 907",
    "sg:postcode":"3043",
    "sg:province":"VIC",
    "sg:tags":[
        "courier"
    ],
    "wof:name":"Dome Transport",
    "wof:placetype":"venue"
},
  "geometry": {"coordinates":[144.87713623100001,-37.6903572083],"type":"Point"}
}