{
  "type": "Feature",
  "properties": {
    "addr:full":"Cnr Mologa Rd & Orthla Ave Heidelberg West VIC 3081",
    "addr:postcode":"3081",
    "addr:street":"Cnr Mologa Rd & Orthla Ave",
    "iso:country":"AU",
    "sg:address":"Cnr Mologa Rd & Orthla Ave",
    "sg:city":"Heidelberg West",
    "sg:classifiers":[
        {
            "category":"Government",
            "subcategory":"Fire Station",
            "type":"Public Place"
        }
    ],
    "sg:phone":"+61 3 9459 2859",
    "sg:postcode":"3081",
    "sg:province":"VIC",
    "sg:tags":[
        "spring",
        "shock",
        "absorbers",
        "suspension"
    ],
    "wof:name":"Leslie S G & Sons Pty Ltd",
    "wof:placetype":"venue"
},
  "geometry": {"coordinates":[145.048065186,-37.7336082458],"type":"Point"}
}