{
  "type": "Feature",
  "properties": {
    "iso:country":"AU",
    "sg:address":"Lot2387/ Casuarina St",
    "sg:city":"Katherine East",
    "sg:classifiers":[
        {
            "category":"Banks & Credit Unions",
            "subcategory":"Investment Brokerage",
            "type":"Services"
        }
    ],
    "sg:phone":"+61 8 8971 0079",
    "sg:postcode":"0850",
    "sg:province":"NT",
    "sg:tags":[
        "care",
        "day",
        "family",
        "child"
    ],
    "wof:name":"Katherine Regional Family Child Care",
    "wof:placetype":"venue"
},
  "geometry": {"coordinates":[132.29655500000001,-14.469029],"type":"Point"}
}