{
  "type": "Feature",
  "properties": {
    "addr:full":"82 Sterculia Ave Holland Park QLD 4121",
    "addr:housenumber":"82",
    "addr:postcode":"4121",
    "addr:street":"Sterculia Ave",
    "iso:country":"AU",
    "sg:address":"82 Sterculia Ave",
    "sg:city":"Holland Park",
    "sg:classifiers":[
        {
            "category":"Health Services",
            "subcategory":"Health Practitioner",
            "type":"Services"
        }
    ],
    "sg:phone":"+61 7 3349 3137",
    "sg:postcode":"4121",
    "sg:province":"QLD",
    "sg:tags":[
        "acupuncture"
    ],
    "wof:name":"Kirner Gail",
    "wof:placetype":"venue"
},
  "geometry": {"coordinates":[153.06207275400001,-27.5248794556],"type":"Point"}
}