{
  "type": "Feature",
  "properties": {
    "iso:country":"AU",
    "sg:address":"19 Howick St",
    "sg:city":"Ashgrove",
    "sg:classifiers":[
        {
            "category":"Building & Trades",
            "subcategory":"Construction",
            "type":"Services"
        }
    ],
    "sg:phone":"+61 7 3366 3607",
    "sg:postcode":"4060",
    "sg:province":"QLD",
    "sg:tags":[
        "joiner",
        "carpenter"
    ],
    "wof:name":"J F Marsh",
    "wof:placetype":"venue"
},
  "geometry": {"coordinates":[152.966674805,-27.4471435547],"type":"Point"}
}