{
  "type": "Feature",
  "properties": {
    "iso:country":"AU",
    "sg:address":"Level 1, 57 Hunter St",
    "sg:city":"Newcastle",
    "sg:classifiers":[
        {
            "category":"Utilities",
            "subcategory":"Telephone",
            "type":"Services"
        }
    ],
    "sg:phone":"+61 2 4915 8550",
    "sg:postcode":"2300",
    "sg:province":"NSW",
    "sg:tags":[
        "equipment",
        "system"
    ],
    "wof:name":"Nova Phones",
    "wof:placetype":"venue"
},
  "geometry": {"coordinates":[151.783875,-32.927822],"type":"Point"}
}