{
  "type": "Feature",
  "properties": {
    "addr:full":"Unit 2, 4 Friesian Cl Sandgate NSW 2304",
    "addr:housenumber":"4",
    "addr:postcode":"2304",
    "addr:street":"Friesian Cl",
    "iso:country":"AU",
    "sg:address":"Unit 2, 4 Friesian Cl",
    "sg:city":"Sandgate",
    "sg:classifiers":[
        {
            "category":"Home & Garden",
            "subcategory":"Kitchen Supply",
            "type":"Retail Goods"
        }
    ],
    "sg:phone":"+61 2 4967 6266",
    "sg:postcode":"2304",
    "sg:province":"NSW",
    "sg:tags":[
        "traffic",
        "equipment",
        "safety",
        "road"
    ],
    "wof:name":"Safetymart Newcastle",
    "wof:placetype":"venue"
},
  "geometry": {"coordinates":[151.704711914,-32.8609695435],"type":"Point"}
}