{
  "type": "Feature",
  "properties": {
    "addr:full":"Unit 1, 6 Lyell St Fyshwick ACT 2609",
    "addr:housenumber":"6",
    "addr:postcode":"2609",
    "addr:street":"Lyell St",
    "iso:country":"AU",
    "sg:address":"Unit 1, 6 Lyell St",
    "sg:city":"Fyshwick",
    "sg:classifiers":[
        {
            "category":"Building & Trades",
            "subcategory":"Cleaning & Sanitation",
            "type":"Services"
        }
    ],
    "sg:phone":"+61 2 6280 4045",
    "sg:postcode":"2609",
    "sg:province":"ACT",
    "sg:tags":[
        "industrial",
        "commercial",
        "contractor"
    ],
    "wof:name":"Rose Cleaning Service",
    "wof:placetype":"venue"
},
  "geometry": {"coordinates":[149.17359924300001,-35.3288116455],"type":"Point"}
}