{
  "type": "Feature",
  "properties": {
    "addr:full":"PO Box 78 Keiraville NSW 2500",
    "addr:postcode":"2500",
    "iso:country":"AU",
    "sg:address":"PO Box 78",
    "sg:city":"Keiraville",
    "sg:classifiers":[
        {
            "category":"Professional",
            "subcategory":"Employment Agencies",
            "type":"Services"
        }
    ],
    "sg:phone":"+61 1300 130 393",
    "sg:postcode":"2500",
    "sg:province":"NSW",
    "sg:tags":[
        "model"
    ],
    "wof:name":"Cosh ,Ka models",
    "wof:placetype":"venue"
},
  "geometry": {"coordinates":[150.87129200000001,-34.414478],"type":"Point"}
}