{
  "type": "Feature",
  "properties": {
    "addr:full":"90 Minnie St Southport QLD 4215",
    "addr:housenumber":"90",
    "addr:postcode":"4215",
    "addr:street":"Minnie St",
    "iso:country":"AU",
    "sg:address":"90 Minnie St",
    "sg:city":"Southport",
    "sg:classifiers":[
        {
            "category":"Manufacturing",
            "subcategory":"Wood Products",
            "type":"Manufacturing & Wholesale Goods"
        }
    ],
    "sg:phone":"+61 7 5591 3930",
    "sg:postcode":"4215",
    "sg:province":"QLD",
    "sg:tags":[
        "polisher",
        "french"
    ],
    "wof:name":"Mark Weule Furniture Polishing",
    "wof:placetype":"venue"
},
  "geometry": {"coordinates":[153.402175903,-27.9752006531],"type":"Point"}
}