{
  "type": "Feature",
  "properties": {
    "addr:full":"Lot 97 Wagtail Pl Warner QLD 4500",
    "addr:postcode":"4500",
    "addr:street":"Wagtail Pl",
    "iso:country":"AU",
    "sg:address":"Lot 97 Wagtail Pl",
    "sg:city":"Warner",
    "sg:classifiers":[
        {
            "category":"Building & Trades",
            "subcategory":"Construction",
            "type":"Services"
        }
    ],
    "sg:phone":"+61 7 3298 6666",
    "sg:postcode":"4500",
    "sg:province":"QLD",
    "sg:tags":[
        "home",
        "air conditioning"
    ],
    "sg:website":"http://www.airconditioningadvisorycentre.com.au",
    "wof:name":"Air Conditioning Advisory Centre",
    "wof:placetype":"venue"
},
  "geometry": {"coordinates":[152.94433593799999,-27.3117828369],"type":"Point"}
}