{
  "type": "Feature",
  "properties": {
    "iso:country":"AU",
    "sg:address":"77 Kroombit St",
    "sg:city":"Biloela",
    "sg:classifiers":[
        {
            "category":"Retail",
            "subcategory":"Storage",
            "type":"Services"
        }
    ],
    "sg:phone":"+61 7 4992 5205",
    "sg:postcode":"4715",
    "sg:province":"QLD",
    "sg:tags":[
        "removal",
        "furniture"
    ],
    "wof:name":"Wiltons Transport & Removals",
    "wof:placetype":"venue"
},
  "geometry": {"coordinates":[150.51246643100001,-24.3981571198],"type":"Point"}
}