{
  "type": "Feature",
  "properties": {
    "iso:country":"AU",
    "sg:address":"22 Lowana St",
    "sg:city":"Villawood",
    "sg:classifiers":[
        {
            "category":"Government",
            "subcategory":"Fire Station",
            "type":"Public Place"
        }
    ],
    "sg:phone":"+61 2 9726 9498",
    "sg:postcode":"2163",
    "sg:province":"NSW",
    "sg:tags":[
        "equipment",
        "protection",
        "consultant"
    ],
    "wof:name":"AC DC Fire Protection Pty Ltd",
    "wof:placetype":"venue"
},
  "geometry": {"coordinates":[150.987747192,-33.8890914917],"type":"Point"}
}