{
  "type": "Feature",
  "properties": {
    "addr:full":"34 Glen Innes Rd Inverell NSW 2360",
    "addr:housenumber":"34",
    "addr:postcode":"2360",
    "addr:street":"Glen Innes Rd",
    "iso:country":"AU",
    "sg:address":"34 Glen Innes Rd",
    "sg:city":"Inverell",
    "sg:classifiers":[
        {
            "category":"Travel",
            "subcategory":"Hotels & Motels",
            "type":"Entertainment"
        }
    ],
    "sg:phone":"+61 2 6722 2500",
    "sg:postcode":"2360",
    "sg:province":"NSW",
    "wof:name":"Golden Chain Sapphire City Motor Inn",
    "wof:placetype":"venue"
},
  "geometry": {"coordinates":[151.113555908,-29.776309967],"type":"Point"}
}