{
  "type": "Feature",
  "properties": {
    "addr:full":"144 Hull Rd Croydon VIC 3136",
    "addr:housenumber":"144",
    "addr:postcode":"3136",
    "addr:street":"Hull Rd",
    "iso:country":"AU",
    "sg:address":"144 Hull Rd",
    "sg:city":"Croydon",
    "sg:classifiers":[
        {
            "category":"Building & Trades",
            "subcategory":"Landscaping Services",
            "type":"Services"
        }
    ],
    "sg:phone":"+61 3 9723 8144",
    "sg:postcode":"3136",
    "sg:province":"VIC",
    "sg:tags":[
        "designer",
        "landscape",
        "contractor"
    ],
    "wof:name":"Frances Saunders Design",
    "wof:placetype":"venue"
},
  "geometry": {"coordinates":[145.306716919,-37.7911911011],"type":"Point"}
}