{
  "type": "Feature",
  "properties": {
    "addr:full":"142 Pratten St Dalby QLD 4405",
    "addr:housenumber":"142",
    "addr:postcode":"4405",
    "addr:street":"Pratten St",
    "iso:country":"AU",
    "sg:address":"142 Pratten St",
    "sg:city":"Dalby",
    "sg:classifiers":[
        {
            "category":"Professional",
            "type":"Services"
        }
    ],
    "sg:phone":"+61 7 4662 4709",
    "sg:postcode":"4405",
    "sg:province":"QLD",
    "sg:tags":[
        "transport"
    ],
    "wof:name":"Hardy's Removals",
    "wof:placetype":"venue"
},
  "geometry": {"coordinates":[151.25006103499999,-27.1882629395],"type":"Point"}
}