{
  "type": "Feature",
  "properties": {
    "addr:full":"7- 8 Murray Pl Ringwood VIC 3134",
    "addr:housenumber":"8",
    "addr:postcode":"3134",
    "addr:street":"Murray Pl",
    "iso:country":"AU",
    "sg:address":"7- 8 Murray Pl",
    "sg:city":"Ringwood",
    "sg:classifiers":[
        {
            "category":"Restaurant",
            "type":"Food & Drink"
        }
    ],
    "sg:phone":"+61 3 9870 7907",
    "sg:postcode":"3134",
    "sg:province":"VIC",
    "wof:name":"Canton Restaurant",
    "wof:placetype":"venue"
},
  "geometry": {"coordinates":[145.224685669,-37.8171424866],"type":"Point"}
}