{
  "type": "Feature",
  "properties": {
    "iso:country":"AU",
    "sg:address":"43 Larnoo Drv",
    "sg:city":"Doncaster East",
    "sg:classifiers":[
        {
            "category":"Manufacturing",
            "subcategory":"Glass & Minerals",
            "type":"Manufacturing & Wholesale Goods"
        }
    ],
    "sg:phone":"+61 3 9841 0249",
    "sg:postcode":"3109",
    "sg:province":"VIC",
    "sg:tags":[
        "merchant",
        "granite",
        "marble"
    ],
    "wof:name":"Annurgranite and Sandstone Company",
    "wof:placetype":"venue"
},
  "geometry": {"coordinates":[145.17950439399999,-37.7610626221],"type":"Point"}
}