{
  "type": "Feature",
  "properties": {
    "addr:full":"26 Swan St Richmond VIC 3121",
    "addr:housenumber":"26",
    "addr:postcode":"3121",
    "addr:street":"Swan St",
    "iso:country":"AU",
    "sg:address":"26 Swan St",
    "sg:city":"Richmond",
    "sg:classifiers":[
        {
            "category":"Retail",
            "subcategory":"Auto Rental",
            "type":"Services"
        }
    ],
    "sg:phone":"+61 3 9428 3488",
    "sg:postcode":"3121",
    "sg:province":"VIC",
    "sg:tags":[
        "bus",
        "truck"
    ],
    "wof:name":"Delta Trucks",
    "wof:placetype":"venue"
},
  "geometry": {"coordinates":[144.990036011,-37.8248672485],"type":"Point"}
}