{
  "type": "Feature",
  "properties": {
    "addr:full":"386 Terranora Rd Terranora QLD 2486",
    "addr:housenumber":"386",
    "addr:postcode":"2486",
    "addr:street":"Terranora Rd",
    "iso:country":"AU",
    "sg:address":"386 Terranora Rd",
    "sg:city":"Terranora",
    "sg:classifiers":[
        {
            "category":"Government",
            "subcategory":"Court House",
            "type":"Public Place"
        }
    ],
    "sg:phone":"+61 7 5524 8483",
    "sg:postcode":"2486",
    "sg:province":"QLD",
    "sg:tags":[
        "personal",
        "marriage",
        "family",
        "counselling"
    ],
    "wof:name":"Neil Wilkin",
    "wof:placetype":"venue"
},
  "geometry": {"coordinates":[153.5027771,-28.2405223846],"type":"Point"}
}