{
  "type": "Feature",
  "properties": {
    "iso:country":"AU",
    "sg:address":"95 Monash Ave",
    "sg:city":"Nedlands",
    "sg:classifiers":[
        {
            "category":"Health Services",
            "subcategory":"Health Practitioner",
            "type":"Services"
        }
    ],
    "sg:phone":"+61 8 9333 8067",
    "sg:postcode":"6009",
    "sg:province":"WA",
    "sg:tags":[
        "psychologist"
    ],
    "wof:name":"Hart Mitch",
    "wof:placetype":"venue"
},
  "geometry": {"coordinates":[115.806313,-31.970354],"type":"Point"}
}