{
  "type": "Feature",
  "properties": {
    "addr:full":"62a Lamrock Ave Bondi Beach NSW 2026",
    "addr:housenumber":"62a",
    "addr:postcode":"2026",
    "addr:street":"Lamrock Ave",
    "iso:country":"AU",
    "sg:address":"62a Lamrock Ave",
    "sg:city":"Bondi Beach",
    "sg:classifiers":[
        {
            "category":"Health Services",
            "subcategory":"Health Practitioner",
            "type":"Services"
        }
    ],
    "sg:phone":"+61 2 9365 1764",
    "sg:postcode":"2026",
    "sg:province":"NSW",
    "sg:tags":[
        "acupuncture"
    ],
    "wof:name":"The Mulberry Tree Clinic",
    "wof:placetype":"venue"
},
  "geometry": {"coordinates":[151.26986694300001,-33.8906745911],"type":"Point"}
}