{
  "type": "Feature",
  "properties": {
    "addr:full":"1 Reward Crt Bohle QLD 4818",
    "addr:housenumber":"1",
    "addr:postcode":"4818",
    "addr:street":"Reward Crt",
    "iso:country":"AU",
    "sg:address":"1 Reward Crt",
    "sg:city":"Bohle",
    "sg:classifiers":[
        {
            "category":"Wholesale",
            "subcategory":"Painting Supplies",
            "type":"Manufacturing & Wholesale Goods"
        }
    ],
    "sg:phone":"+61 7 4774 7770",
    "sg:postcode":"4818",
    "sg:province":"QLD",
    "sg:tags":[
        "wholesaler",
        "paint",
        "mfrs"
    ],
    "wof:name":"Asian Paints (Qld) Pty Ltd",
    "wof:placetype":"venue"
},
  "geometry": {"coordinates":[146.72120699999999,-19.260538],"type":"Point"}
}