{
  "type": "Feature",
  "properties": {
    "addr:full":"Lot 4 Clive St Fernvale QLD 4306",
    "addr:postcode":"4306",
    "addr:street":"Clive St",
    "iso:country":"AU",
    "sg:address":"Lot 4 Clive St",
    "sg:city":"Fernvale",
    "sg:classifiers":[
        {
            "category":"Travel",
            "subcategory":"Hostel",
            "type":"Entertainment"
        }
    ],
    "sg:phone":"+61 7 5426 7217",
    "sg:postcode":"4306",
    "sg:province":"QLD",
    "sg:tags":[
        "home"
    ],
    "wof:name":"Fernvale After Care Centre",
    "wof:placetype":"venue"
},
  "geometry": {"coordinates":[152.649780273,-27.4563331604],"type":"Point"}
}