{
  "type": "Feature",
  "properties": {
    "addr:full":"Lot 3 Foord La Dromana VIC 3936",
    "addr:postcode":"3936",
    "addr:street":"Foord La",
    "iso:country":"AU",
    "sg:address":"Lot 3 Foord La",
    "sg:city":"Dromana",
    "sg:classifiers":[
        {
            "category":"Building & Trades",
            "subcategory":"Plumbing",
            "type":"Services"
        }
    ],
    "sg:phone":"+61 3 5987 2537",
    "sg:postcode":"3936",
    "sg:province":"VIC",
    "sg:tags":[
        "plumber",
        "gasfitters"
    ],
    "wof:name":"Warfe L I",
    "wof:placetype":"venue"
},
  "geometry": {"coordinates":[144.943267822,-38.3429031372],"type":"Point"}
}