{
  "type": "Feature",
  "properties": {
    "addr:full":"PO Box 16 Warramboo SA 5650",
    "addr:postcode":"5650",
    "iso:country":"AU",
    "sg:address":"PO Box 16",
    "sg:city":"Warramboo",
    "sg:classifiers":[
        {
            "category":"Farming",
            "subcategory":"Farm",
            "type":"Manufacturing & Wholesale Goods"
        }
    ],
    "sg:phone":"+61 8 8681 8055",
    "sg:postcode":"5650",
    "sg:province":"SA",
    "sg:tags":[
        "farmer"
    ],
    "wof:name":"Sampson C G & C E",
    "wof:placetype":"venue"
},
  "geometry": {"coordinates":[135.59797668499999,-33.2421913147],"type":"Point"}
}