{
  "type": "Feature",
  "properties": {
    "iso:country":"AU",
    "sg:address":"Cnr Percy & Broadwood Sts",
    "sg:city":"Kalgoorlie",
    "sg:classifiers":[
        {
            "category":"Real Estate",
            "subcategory":"Real Estate Agent",
            "type":"Services"
        }
    ],
    "sg:phone":"+61 8 9091 1677",
    "sg:postcode":"6430",
    "sg:province":"WA",
    "sg:tags":[
        "handyman's",
        "equipment",
        "hire",
        "builders",
        "contractor"
    ],
    "wof:name":"KK Diesel Pty Ltd",
    "wof:placetype":"venue"
},
  "geometry": {"coordinates":[121.437530518,-30.7855548859],"type":"Point"}
}