{
  "type": "Feature",
  "properties": {
    "addr:full":"22 Mahar St Kensington Gardens SA 5068",
    "addr:housenumber":"22",
    "addr:postcode":"5068",
    "addr:street":"Mahar St",
    "iso:country":"AU",
    "sg:address":"22 Mahar St",
    "sg:city":"Kensington Gardens",
    "sg:classifiers":[
        {
            "category":"Shopping",
            "subcategory":"Bicycles & Sporting Goods",
            "type":"Retail Goods"
        }
    ],
    "sg:phone":"+61 8 8332 5433",
    "sg:postcode":"5068",
    "sg:province":"SA",
    "sg:tags":[
        "chemical",
        "equipment",
        "pool",
        "swimming"
    ],
    "wof:name":"Balnaves Pools",
    "wof:placetype":"venue"
},
  "geometry": {"coordinates":[138.66319274899999,-34.9167442322],"type":"Point"}
}