{
  "type": "Feature",
  "properties": {
    "iso:country":"AU",
    "sg:address":"PO Box 317",
    "sg:city":"Swansea",
    "sg:classifiers":[
        {
            "category":"Building & Trades",
            "subcategory":"Equipment Rental",
            "type":"Services"
        }
    ],
    "sg:phone":"+61 417 451 125",
    "sg:postcode":"2281",
    "sg:province":"NSW",
    "sg:tags":[
        "party",
        "hire"
    ],
    "wof:name":"Muller's Amusements",
    "wof:placetype":"venue"
},
  "geometry": {"coordinates":[151.63763427699999,-33.0895004272],"type":"Point"}
}