{
  "type": "Feature",
  "properties": {
    "iso:country":"AU",
    "sg:address":"700 Geelong Rd",
    "sg:city":"Brooklyn",
    "sg:classifiers":[
        {
            "category":"Travel",
            "subcategory":"Hotels & Motels",
            "type":"Entertainment"
        }
    ],
    "sg:phone":"+61 3 9314 1133",
    "sg:postcode":"3025",
    "sg:province":"VIC",
    "sg:tags":[
        "accommodation"
    ],
    "wof:name":"Guiding Star Hotel",
    "wof:placetype":"venue"
},
  "geometry": {"coordinates":[144.837585,-37.819733],"type":"Point"}
}