{
  "type": "Feature",
  "properties": {
    "iso:country":"AU",
    "sg:address":"38 Minerva St",
    "sg:city":"Rochedale",
    "sg:classifiers":[
        {
            "category":"Personal",
            "subcategory":"Nail Salon",
            "type":"Services"
        }
    ],
    "sg:phone":"+61 407 841 764",
    "sg:postcode":"4123",
    "sg:province":"QLD",
    "sg:tags":[
        "artificial"
    ],
    "wof:name":"Nails By Lisa Claire",
    "wof:placetype":"venue"
},
  "geometry": {"coordinates":[153.12796020499999,-27.6042823792],"type":"Point"}
}