{
  "type": "Feature",
  "properties": {
    "iso:country":"AU",
    "sg:address":"8 Mosman St",
    "sg:city":"Mosman",
    "sg:classifiers":[
        {
            "category":"Education",
            "subcategory":"Special Training",
            "type":"Public Place"
        }
    ],
    "sg:phone":"+61 2 9968 2311",
    "sg:postcode":"2088",
    "sg:province":"NSW",
    "sg:tags":[
        "development"
    ],
    "wof:name":"Maya Method The",
    "wof:placetype":"venue"
},
  "geometry": {"coordinates":[151.23402404800001,-33.8366470337],"type":"Point"}
}