{
  "type": "Feature",
  "properties": {
    "addr:full":"12 Tallai Rd Tallai QLD 4213",
    "addr:housenumber":"12",
    "addr:postcode":"4213",
    "addr:street":"Tallai Rd",
    "iso:country":"AU",
    "sg:address":"12 Tallai Rd",
    "sg:city":"Tallai",
    "sg:classifiers":[
        {
            "category":"Building & Trades",
            "subcategory":"Construction",
            "type":"Services"
        }
    ],
    "sg:phone":"+61 408 753 220",
    "sg:postcode":"4213",
    "sg:province":"QLD",
    "sg:tags":[
        "earth",
        "excavating",
        "moving",
        "contractor"
    ],
    "wof:name":"Grahame White Grader Hire",
    "wof:placetype":"venue"
},
  "geometry": {"coordinates":[153.34950256400001,-28.0698223114],"type":"Point"}
}