{
  "type": "Feature",
  "properties": {
    "addr:full":"15 Nevada Ave Corio VIC 3214",
    "addr:housenumber":"15",
    "addr:postcode":"3214",
    "addr:street":"Nevada Ave",
    "iso:country":"AU",
    "sg:address":"15 Nevada Ave",
    "sg:city":"Corio",
    "sg:classifiers":[
        {
            "category":"Personal",
            "subcategory":"Beauty Salon",
            "type":"Services"
        }
    ],
    "sg:phone":"+61 3 5274 3122",
    "sg:postcode":"3214",
    "sg:province":"VIC",
    "sg:tags":[
        "hairdresser"
    ],
    "wof:name":"Melange Hair Studio",
    "wof:placetype":"venue"
},
  "geometry": {"coordinates":[144.352859497,-38.0823059082],"type":"Point"}
}