{
  "type": "Feature",
  "properties": {
    "iso:country":"AU",
    "sg:address":"57 West St",
    "sg:city":"Toowoomba",
    "sg:classifiers":[
        {
            "category":"Farming",
            "subcategory":"Livestock Farm",
            "type":"Manufacturing & Wholesale Goods"
        }
    ],
    "sg:phone":"+61 7 4637 8765",
    "sg:postcode":"4350",
    "sg:province":"QLD",
    "sg:tags":[
        "school",
        "theological"
    ],
    "wof:name":"Pure Land Learning College Association Inc",
    "wof:placetype":"venue"
},
  "geometry": {"coordinates":[151.944824,-27.550915],"type":"Point"}
}