{
  "type": "Feature",
  "properties": {
    "addr:full":"9 Clift St Mt Stuart TAS 7000",
    "addr:housenumber":"9",
    "addr:postcode":"7000",
    "addr:street":"Clift St Mt",
    "iso:country":"AU",
    "sg:address":"9 Clift St",
    "sg:city":"Mt Stuart",
    "sg:classifiers":[
        {
            "category":"Professional",
            "subcategory":"Art Services",
            "type":"Services"
        }
    ],
    "sg:phone":"+61 3 6234 1961",
    "sg:postcode":"7000",
    "sg:province":"TAS",
    "sg:tags":[
        "decorator",
        "painter"
    ],
    "wof:name":"Wilson Bros",
    "wof:placetype":"venue"
},
  "geometry": {"coordinates":[147.29994201700001,-42.875743866],"type":"Point"}
}