{
  "type": "Feature",
  "properties": {
    "addr:full":"Box 4 Mt Crosby News Mt Crosby QLD 4306",
    "addr:postcode":"4306",
    "iso:country":"AU",
    "sg:address":"Box 4",
    "sg:city":"Mt Crosby News Mt Crosby",
    "sg:classifiers":[
        {
            "category":"Food & Beverages",
            "subcategory":"Fruits & Vegetables",
            "type":"Retail Goods"
        }
    ],
    "sg:phone":"+61 7 3351 1384",
    "sg:postcode":"4306",
    "sg:province":"QLD",
    "sg:tags":[
        "consultant",
        "catering"
    ],
    "wof:name":"A.H.C. Australasian Hospitality Consultants",
    "wof:placetype":"venue"
},
  "geometry": {"coordinates":[152.79359435999999,-27.5692710876],"type":"Point"}
}