{
  "type": "Feature",
  "properties": {
    "addr:full":"42 Princess St Camp Hill QLD 4152",
    "addr:housenumber":"42",
    "addr:postcode":"4152",
    "addr:street":"Princess St",
    "iso:country":"AU",
    "sg:address":"42 Princess St",
    "sg:city":"Camp Hill",
    "sg:classifiers":[
        {
            "category":"Professional",
            "subcategory":"Art Services",
            "type":"Services"
        }
    ],
    "sg:phone":"+61 418 151 362",
    "sg:postcode":"4152",
    "sg:province":"QLD",
    "sg:tags":[
        "decorator",
        "painter"
    ],
    "wof:name":"Peace Painting Service",
    "wof:placetype":"venue"
},
  "geometry": {"coordinates":[153.074874878,-27.4966583252],"type":"Point"}
}