{
  "type": "Feature",
  "properties": {
    "iso:country":"AU",
    "sg:address":"100 Crawford St",
    "sg:city":"Queanbeyan",
    "sg:classifiers":[
        {
            "category":"Home & Garden",
            "subcategory":"Carpets & Floor Coverings",
            "type":"Retail Goods"
        }
    ],
    "sg:phone":"+61 2 6297 4510",
    "sg:postcode":"2620",
    "sg:province":"ACT",
    "sg:tags":[
        "tile",
        "wall"
    ],
    "wof:name":"Riv-oland Ceramics Pty Ltd T/As Guglielmin Family Trust",
    "wof:placetype":"venue"
},
  "geometry": {"coordinates":[149.230072022,-35.3472518921],"type":"Point"}
}