{
  "type": "Feature",
  "properties": {
    "addr:full":"61 Bold St Laurieton NSW 2443",
    "addr:housenumber":"61",
    "addr:postcode":"2443",
    "addr:street":"Bold St",
    "iso:country":"AU",
    "sg:address":"61 Bold St",
    "sg:city":"Laurieton",
    "sg:classifiers":[
        {
            "category":"Personal",
            "subcategory":"Beauty Salon",
            "type":"Services"
        }
    ],
    "sg:phone":"+61 2 6559 8644",
    "sg:postcode":"2443",
    "sg:province":"NSW",
    "sg:tags":[
        "hairdresser"
    ],
    "wof:name":"Ahead of Style Esmarees",
    "wof:placetype":"venue"
},
  "geometry": {"coordinates":[152.79690600000001,-31.650827],"type":"Point"}
}