{
  "type": "Feature",
  "properties": {
    "addr:full":"473a High St Preston VIC 3072",
    "addr:housenumber":"473a",
    "addr:postcode":"3072",
    "addr:street":"High St",
    "iso:country":"AU",
    "sg:address":"473a High St",
    "sg:city":"Preston",
    "sg:classifiers":[
        {
            "category":"Banks & Credit Unions",
            "subcategory":"Bank",
            "type":"Services"
        }
    ],
    "sg:phone":"+61 1300 660 550",
    "sg:postcode":"3072",
    "sg:province":"VIC",
    "wof:name":"Bank Of Cyprus Australia",
    "wof:placetype":"venue"
},
  "geometry": {"coordinates":[145.00379943900001,-37.7379837036],"type":"Point"}
}