{
  "type": "Feature",
  "properties": {
    "addr:full":"57 Labourchere Rd South Perth WA 6151",
    "addr:housenumber":"57",
    "addr:postcode":"6151",
    "addr:street":"Labourchere Rd",
    "iso:country":"AU",
    "sg:address":"57 Labourchere Rd",
    "sg:city":"South Perth",
    "sg:classifiers":[
        {
            "category":"Manufacturing",
            "subcategory":"Glass & Minerals",
            "type":"Manufacturing & Wholesale Goods"
        }
    ],
    "sg:phone":"+61 8 9482 4182",
    "sg:postcode":"6151",
    "sg:province":"WA",
    "sg:tags":[
        "exploration"
    ],
    "wof:name":"W A Minerals",
    "wof:placetype":"venue"
},
  "geometry": {"coordinates":[115.852188,-31.976875],"type":"Point"}
}