{
  "type": "Feature",
  "properties": {
    "iso:country":"AU",
    "sg:address":"76 Douglas Pde",
    "sg:city":"Williamstown",
    "sg:classifiers":[
        {
            "category":"Personal",
            "subcategory":"Beauty Salon",
            "type":"Services"
        }
    ],
    "sg:phone":"+61 3 9399 9554",
    "sg:postcode":"3016",
    "sg:province":"VIC",
    "wof:name":"Mels Beauty Room",
    "wof:placetype":"venue"
},
  "geometry": {"coordinates":[144.89785766599999,-37.8565330505],"type":"Point"}
}