{
  "type": "Feature",
  "properties": {
    "iso:country":"AU",
    "sg:address":"Shop 3 / 168 Gipps Rd",
    "sg:city":"Gwynneville",
    "sg:classifiers":[
        {
            "category":"Food & Beverages",
            "subcategory":"Bakery",
            "type":"Retail Goods"
        }
    ],
    "sg:phone":"+61 2 4227 2652",
    "sg:postcode":"2500",
    "sg:province":"NSW",
    "sg:tags":[
        "baker"
    ],
    "wof:name":"Gwynneville Bakery",
    "wof:placetype":"venue"
},
  "geometry": {"coordinates":[150.883804,-34.416077],"type":"Point"}
}