{
  "type": "Feature",
  "properties": {
    "iso:country":"AU",
    "sg:address":"187 Stirling Hwy",
    "sg:city":"Nedlands",
    "sg:classifiers":[
        {
            "category":"Health Services",
            "subcategory":"Doctor",
            "type":"Services"
        }
    ],
    "sg:phone":"+61 8 9389 9022",
    "sg:postcode":"6009",
    "sg:province":"WA",
    "sg:tags":[
        "medical",
        "practitioner"
    ],
    "sg:website":"http://www.skyn.com.au",
    "wof:name":"Skyn",
    "wof:placetype":"venue"
},
  "geometry": {"coordinates":[115.815842,-31.976597],"type":"Point"}
}