{
  "type": "Feature",
  "properties": {
    "iso:country":"AU",
    "sg:address":"132 Puckle St",
    "sg:city":"Moonee Ponds",
    "sg:classifiers":[
        {
            "category":"Shopping",
            "subcategory":"Clothing, Apparel, & Fashions",
            "type":"Retail Goods"
        }
    ],
    "sg:phone":"+61 3 9372 9199",
    "sg:postcode":"3039",
    "sg:province":"VIC",
    "sg:tags":[
        "lady",
        "wear"
    ],
    "wof:name":"Silk Lane Boutique",
    "wof:placetype":"venue"
},
  "geometry": {"coordinates":[144.920273,-37.766495],"type":"Point"}
}