{
  "type": "Feature",
  "properties": {
    "iso:country":"AU",
    "sg:address":"227 Wynnum Rd",
    "sg:city":"Norman Park",
    "sg:classifiers":[
        {
            "category":"Fast Food",
            "type":"Food & Drink"
        }
    ],
    "sg:phone":"+61 7 3899 1071",
    "sg:postcode":"4170",
    "sg:province":"QLD",
    "sg:tags":[
        "away",
        "take"
    ],
    "wof:name":"Thai Chiangrai Takeaway",
    "wof:placetype":"venue"
},
  "geometry": {"coordinates":[153.05780029300001,-27.4732227325],"type":"Point"}
}