{
  "type": "Feature",
  "properties": {
    "addr:full":"237 Nepean Hwy Gardenvale VIC 3185",
    "addr:housenumber":"237",
    "addr:postcode":"3185",
    "addr:street":"Nepean Hwy",
    "iso:country":"AU",
    "sg:address":"237 Nepean Hwy",
    "sg:city":"Gardenvale",
    "sg:classifiers":[
        {
            "category":"Government",
            "subcategory":"City Hall",
            "type":"Public Place"
        }
    ],
    "sg:phone":"+61 3 9596 8236",
    "sg:postcode":"3185",
    "sg:province":"VIC",
    "wof:name":"Masonic Centre",
    "wof:placetype":"venue"
},
  "geometry": {"coordinates":[145.00653076200001,-37.8990325928],"type":"Point"}
}