{
  "type": "Feature",
  "properties": {
    "addr:full":"600 Park Rd Park Orchards VIC 3114",
    "addr:housenumber":"600",
    "addr:postcode":"3114",
    "addr:street":"Park Rd",
    "iso:country":"AU",
    "sg:address":"600 Park Rd",
    "sg:city":"Park Orchards",
    "sg:classifiers":[
        {
            "category":"Government",
            "subcategory":"Post Office",
            "type":"Public Place"
        }
    ],
    "sg:phone":"+61 3 9876 1291",
    "sg:postcode":"3114",
    "sg:province":"VIC",
    "sg:tags":[
        "postal"
    ],
    "wof:name":"Australia Post",
    "wof:placetype":"venue"
},
  "geometry": {"coordinates":[145.217407227,-37.7790679932],"type":"Point"}
}