{
  "type": "Feature",
  "properties": {
    "addr:full":"Community Health Centre School Rd Tarwin Lower VIC 3956",
    "addr:postcode":"3956",
    "addr:street":"School Rd",
    "iso:country":"AU",
    "sg:address":"Community Health Centre School Rd",
    "sg:city":"Tarwin Lower",
    "sg:classifiers":[
        {
            "category":"Social Services",
            "subcategory":"Child Care",
            "type":"Services"
        }
    ],
    "sg:phone":"+61 3 5663 5564",
    "sg:postcode":"3956",
    "sg:province":"VIC",
    "sg:tags":[
        "support",
        "health"
    ],
    "wof:name":"Maternal & Child Health Centres",
    "wof:placetype":"venue"
},
  "geometry": {"coordinates":[145.86985778799999,-38.7068481445],"type":"Point"}
}