{
  "type": "Feature",
  "properties": {
    "addr:full":"210 Pacific Hwy Coffs Harbour NSW 2450",
    "addr:housenumber":"210",
    "addr:postcode":"2450",
    "addr:street":"Pacific Hwy",
    "iso:country":"AU",
    "sg:address":"210 Pacific Hwy",
    "sg:city":"Coffs Harbour",
    "sg:classifiers":[
        {
            "category":"Education",
            "subcategory":"Special Training",
            "type":"Public Place"
        }
    ],
    "sg:phone":"+61 2 6651 4369",
    "sg:postcode":"2450",
    "sg:province":"NSW",
    "sg:tags":[
        "tuition-educational"
    ],
    "wof:name":"Kip McGrath Education Centres",
    "wof:placetype":"venue"
},
  "geometry": {"coordinates":[153.101044,-30.307144],"type":"Point"}
}