{
  "type": "Feature",
  "properties": {
    "iso:country":"AU",
    "sg:address":"435 Riversdale Rd",
    "sg:city":"Hawthorn East",
    "sg:classifiers":[
        {
            "category":"Health Services",
            "subcategory":"Health Practitioner",
            "type":"Services"
        }
    ],
    "sg:phone":"+61 3 9882 2255",
    "sg:postcode":"3123",
    "sg:province":"VIC",
    "sg:tags":[
        "acupuncture"
    ],
    "wof:name":"Koukas John James",
    "wof:placetype":"venue"
},
  "geometry": {"coordinates":[145.05426025400001,-37.8309326172],"type":"Point"}
}