{
  "type": "Feature",
  "properties": {
    "addr:full":"3 Ferguson Pl Flynn ACT 2615",
    "addr:housenumber":"3",
    "addr:postcode":"2615",
    "addr:street":"Ferguson Pl",
    "iso:country":"AU",
    "sg:address":"3 Ferguson Pl",
    "sg:city":"Flynn",
    "sg:classifiers":[
        {
            "category":"Building & Trades",
            "subcategory":"Cleaning & Sanitation",
            "type":"Services"
        }
    ],
    "sg:phone":"+61 2 6258 3482",
    "sg:postcode":"2615",
    "sg:province":"ACT",
    "sg:tags":[
        "industrial",
        "commercial",
        "contractor"
    ],
    "wof:name":"Abbesi Agency",
    "wof:placetype":"venue"
},
  "geometry": {"coordinates":[149.04063415499999,-35.213432312],"type":"Point"}
}