{
  "type": "Feature",
  "properties": {
    "addr:full":"30 Carnarvon Ave Redwood Park SA 5097",
    "addr:housenumber":"30",
    "addr:postcode":"5097",
    "addr:street":"Carnarvon Ave",
    "iso:country":"AU",
    "sg:address":"30 Carnarvon Ave",
    "sg:city":"Redwood Park",
    "sg:classifiers":[
        {
            "category":"Wholesale",
            "subcategory":"Machinery & Supplies",
            "type":"Manufacturing & Wholesale Goods"
        }
    ],
    "sg:phone":"+61 419 803 306",
    "sg:postcode":"5097",
    "sg:province":"SA",
    "sg:tags":[
        "equipment",
        "hydraulic"
    ],
    "wof:name":"All Hoist Equipment Services",
    "wof:placetype":"venue"
},
  "geometry": {"coordinates":[138.71484375,-34.8112487793],"type":"Point"}
}