{
  "type": "Feature",
  "properties": {
    "addr:full":"12 Melvin St Wilston QLD 4051",
    "addr:housenumber":"12",
    "addr:postcode":"4051",
    "addr:street":"Melvin St",
    "iso:country":"AU",
    "sg:address":"12 Melvin St",
    "sg:city":"Wilston",
    "sg:classifiers":[
        {
            "category":"Building & Trades",
            "subcategory":"Pest Control",
            "type":"Services"
        }
    ],
    "sg:phone":"+61 7 3352 4371",
    "sg:postcode":"4051",
    "sg:province":"QLD",
    "wof:name":"Possum Bird Rat & Pigeon Removalist With Free Possum Box Offer",
    "wof:placetype":"venue"
},
  "geometry": {"coordinates":[153.01620483400001,-27.4315280914],"type":"Point"}
}