{
  "type": "Feature",
  "properties": {
    "addr:full":"Unit G1/ 33- 37 Murray Road S Welshpool WA 6106",
    "addr:housenumber":"g1 / 33 37",
    "addr:postcode":"6106",
    "addr:street":"Murray Road S",
    "iso:country":"AU",
    "sg:address":"Unit G1/ 33- 37 Murray Road",
    "sg:city":"S Welshpool",
    "sg:classifiers":[
        {
            "category":"Manufacturing",
            "subcategory":"Glass & Minerals",
            "type":"Manufacturing & Wholesale Goods"
        }
    ],
    "sg:phone":"+61 8 9351 5803",
    "sg:postcode":"6106",
    "sg:province":"WA",
    "sg:tags":[
        "mfrg",
        "processing"
    ],
    "wof:name":"Glass Roguery",
    "wof:placetype":"venue"
},
  "geometry": {"coordinates":[115.955703735,-31.9979953766],"type":"Point"}
}