{
  "type": "Feature",
  "properties": {
    "iso:country":"AU",
    "sg:address":"3 Viola Place, Export Park,",
    "sg:city":"Brisbane Airport",
    "sg:classifiers":[
        {
            "category":"Social Services",
            "subcategory":"Child Care",
            "type":"Services"
        }
    ],
    "sg:phone":"+61 7 3624 5000",
    "sg:postcode":"4007",
    "sg:province":"QLD",
    "sg:tags":[
        "fleet",
        "management"
    ],
    "sg:website":"http://www.customfleet.com.au",
    "wof:name":"Custom Fleet",
    "wof:placetype":"venue"
},
  "geometry": {"coordinates":[153.095078,-27.42],"type":"Point"}
}