{
  "type": "Feature",
  "properties": {
    "iso:country":"AU",
    "sg:address":"278 Windermere Drv",
    "sg:city":"Ferntree Gully",
    "sg:classifiers":[
        {
            "category":"Education",
            "subcategory":"Kindergarten",
            "type":"Public Place"
        }
    ],
    "sg:phone":"+61 3 9763 1995",
    "sg:postcode":"3156",
    "sg:province":"VIC",
    "sg:tags":[
        "pre-schools"
    ],
    "wof:name":"Windermere Reserve Pre-School",
    "wof:placetype":"venue"
},
  "geometry": {"coordinates":[145.26527404800001,-37.8926811218],"type":"Point"}
}