{
  "type": "Feature",
  "properties": {
    "addr:full":"1 Ware St Embleton WA 6062",
    "addr:housenumber":"1",
    "addr:postcode":"6062",
    "addr:street":"Ware St",
    "iso:country":"AU",
    "sg:address":"1 Ware St",
    "sg:city":"Embleton",
    "sg:classifiers":[
        {
            "category":"Building & Trades",
            "subcategory":"Landscaping Services",
            "type":"Services"
        }
    ],
    "sg:phone":"+61 411 384 826",
    "sg:postcode":"6062",
    "sg:province":"WA",
    "sg:tags":[
        "stump",
        "tree",
        "felling",
        "removal"
    ],
    "wof:name":"Shane Shenton",
    "wof:placetype":"venue"
},
  "geometry": {"coordinates":[115.910629273,-31.9060287476],"type":"Point"}
}