{
  "type": "Feature",
  "properties": {
    "addr:full":"Anzac Ave Redcliffe QLD 4020",
    "addr:postcode":"4020",
    "addr:street":"Anzac Ave",
    "iso:country":"AU",
    "sg:address":"Anzac Ave",
    "sg:city":"Redcliffe",
    "sg:classifiers":[
        {
            "category":"Autos & Motor Vehicles",
            "subcategory":"Boat Sales",
            "type":"Retail Goods"
        }
    ],
    "sg:phone":"+61 7 3203 3007",
    "sg:postcode":"4020",
    "sg:province":"QLD",
    "sg:tags":[
        "yacht"
    ],
    "wof:name":"Sundown Marine Pty Ltd",
    "wof:placetype":"venue"
},
  "geometry": {"coordinates":[153.10041799999999,-27.228697],"type":"Point"}
}