{
  "type": "Feature",
  "properties": {
    "addr:full":"Unit 1/ 2 Saligna Drv Tullamarine VIC 3043",
    "addr:postcode":"3043",
    "addr:street":"Saligna Drv",
    "iso:country":"AU",
    "sg:address":"Unit 1/ 2 Saligna Drv",
    "sg:city":"Tullamarine",
    "sg:classifiers":[
        {
            "category":"Professional",
            "subcategory":"Employment Agencies",
            "type":"Services"
        }
    ],
    "sg:phone":"+61 3 9338 1355",
    "sg:postcode":"3043",
    "sg:province":"VIC",
    "sg:tags":[
        "broker",
        "custom"
    ],
    "wof:name":"ADT Freight Services Pty Ltd",
    "wof:placetype":"venue"
},
  "geometry": {"coordinates":[144.86730957,-37.7138214111],"type":"Point"}
}