{
  "type": "Feature",
  "properties": {
    "addr:full":"23A Prospect Hill Rd Camberwell VIC 3124",
    "addr:housenumber":"23a",
    "addr:postcode":"3124",
    "addr:street":"Prospect Hill Rd",
    "iso:country":"AU",
    "sg:address":"23A Prospect Hill Rd",
    "sg:city":"Camberwell",
    "sg:classifiers":[
        {
            "category":"Shopping",
            "subcategory":"Computers & Home Electronics",
            "type":"Retail Goods"
        }
    ],
    "sg:phone":"+61 3 9813 0151",
    "sg:postcode":"3124",
    "sg:province":"VIC",
    "sg:tags":[
        "equipment",
        "multimedia"
    ],
    "wof:name":"Dynamic Velocity Production",
    "wof:placetype":"venue"
},
  "geometry": {"coordinates":[145.059326172,-37.8282432556],"type":"Point"}
}