{
  "type": "Feature",
  "properties": {
    "addr:full":"Level 1/ 454 Brunswick St Fortitude Valley QLD 4006",
    "addr:housenumber":"/ 454",
    "addr:postcode":"4006",
    "addr:street":"Brunswick St",
    "iso:country":"AU",
    "sg:address":"Level 1/ 454 Brunswick St",
    "sg:city":"Fortitude Valley",
    "sg:classifiers":[
        {
            "category":"Government",
            "subcategory":"Post Office",
            "type":"Public Place"
        }
    ],
    "sg:phone":"+61 7 3358 3377",
    "sg:postcode":"4006",
    "sg:province":"QLD",
    "sg:tags":[
        "yoga"
    ],
    "wof:name":"Yoga & The Alexander Technique",
    "wof:placetype":"venue"
},
  "geometry": {"coordinates":[153.03744506800001,-27.4602127075],"type":"Point"}
}