{
  "type": "Feature",
  "properties": {
    "addr:full":"PO Box 144 Round Corner NSW 2158",
    "addr:postcode":"2158",
    "iso:country":"AU",
    "sg:address":"PO Box 144",
    "sg:city":"Round Corner",
    "sg:classifiers":[
        {
            "category":"Building & Trades",
            "subcategory":"Landscaping Services",
            "type":"Services"
        }
    ],
    "sg:phone":"+61 2 9654 0809",
    "sg:postcode":"2158",
    "sg:province":"NSW",
    "sg:tags":[
        "designer",
        "landscape",
        "contractor"
    ],
    "wof:name":"Plans For Plants",
    "wof:placetype":"venue"
},
  "geometry": {"coordinates":[151.01791381800001,-33.695098877],"type":"Point"}
}