{
  "type": "Feature",
  "properties": {
    "addr:full":"190 Pacific Hwy Coffs Harbour NSW 2450",
    "addr:housenumber":"190",
    "addr:postcode":"2450",
    "addr:street":"Pacific Hwy",
    "iso:country":"AU",
    "sg:address":"190 Pacific Hwy",
    "sg:city":"Coffs Harbour",
    "sg:classifiers":[
        {
            "category":"Real Estate",
            "subcategory":"Surveying",
            "type":"Services"
        }
    ],
    "sg:phone":"+61 2 6652 5090",
    "sg:postcode":"2450",
    "sg:province":"NSW",
    "sg:tags":[
        "surveyor",
        "land"
    ],
    "wof:name":"Blair & Lanskey",
    "wof:placetype":"venue"
},
  "geometry": {"coordinates":[153.090881,-30.317968],"type":"Point"}
}