{
  "type": "Feature",
  "properties": {
    "iso:country":"AU",
    "sg:address":"Floor 1, 185 Fullarton Rd",
    "sg:city":"Dulwich",
    "sg:classifiers":[
        {
            "category":"Organizations",
            "subcategory":"Professional Association",
            "type":"Services"
        }
    ],
    "sg:phone":"+61 8 8331 8865",
    "sg:postcode":"5065",
    "sg:province":"SA",
    "sg:tags":[
        "organisation",
        "business"
    ],
    "wof:name":"Pharmacy Board Of S.A.",
    "wof:placetype":"venue"
},
  "geometry": {"coordinates":[138.624633789,-34.9377670288],"type":"Point"}
}