{
  "type": "Feature",
  "properties": {
    "addr:full":"95a Karimbla Rd Miranda NSW 2228",
    "addr:housenumber":"95a",
    "addr:postcode":"2228",
    "addr:street":"Karimbla Rd",
    "iso:country":"AU",
    "sg:address":"95a Karimbla Rd",
    "sg:city":"Miranda",
    "sg:classifiers":[
        {
            "category":"Social Services",
            "subcategory":"Adult Care",
            "type":"Services"
        }
    ],
    "sg:phone":"+61 2 9540 2633",
    "sg:postcode":"2228",
    "sg:province":"NSW",
    "sg:tags":[
        "aged"
    ],
    "wof:name":"Miranda District Neighbour Aid Inc",
    "wof:placetype":"venue"
},
  "geometry": {"coordinates":[151.10142517099999,-34.0368347168],"type":"Point"}
}