{
  "type": "Feature",
  "properties": {
    "iso:country":"AU",
    "sg:address":"Flintoff Rd",
    "sg:city":"Bridgetown",
    "sg:classifiers":[
        {
            "category":"Personal",
            "subcategory":"Massage",
            "type":"Services"
        }
    ],
    "sg:phone":"+61 8 9761 1528",
    "sg:postcode":"6255",
    "sg:province":"WA",
    "sg:tags":[
        "therapy"
    ],
    "wof:name":"Robert Smith",
    "wof:placetype":"venue"
},
  "geometry": {"coordinates":[116.12383270300001,-33.9348716736],"type":"Point"}
}