{
  "type": "Feature",
  "properties": {
    "addr:full":"Unit 50/ 1 Millennium Cct Pelican Waters QLD 4551",
    "addr:housenumber":"/ 1",
    "addr:postcode":"4551",
    "addr:street":"Millennium Cct",
    "iso:country":"AU",
    "sg:address":"Unit 50/ 1 Millennium Cct",
    "sg:city":"Pelican Waters",
    "sg:classifiers":[
        {
            "category":"Professional",
            "subcategory":"Computer Services",
            "type":"Services"
        }
    ],
    "sg:phone":"+61 7 5492 4058",
    "sg:postcode":"4551",
    "sg:province":"QLD",
    "sg:tags":[
        "package",
        "software"
    ],
    "wof:name":"Claymont Electrical Pty Ltd",
    "wof:placetype":"venue"
},
  "geometry": {"coordinates":[153.10333251899999,-26.8337497711],"type":"Point"}
}