{
  "type": "Feature",
  "properties": {
    "addr:full":"29 Bluff Rd Black Rock VIC 3193",
    "addr:housenumber":"29",
    "addr:postcode":"3193",
    "addr:street":"Bluff Rd",
    "iso:country":"AU",
    "sg:address":"29 Bluff Rd",
    "sg:city":"Black Rock",
    "sg:classifiers":[
        {
            "category":"Shopping",
            "subcategory":"Shoes",
            "type":"Retail Goods"
        }
    ],
    "sg:phone":"+61 3 9589 4156",
    "sg:postcode":"3193",
    "sg:province":"VIC",
    "sg:tags":[
        "footwear"
    ],
    "wof:name":"Patrick's Shoes",
    "wof:placetype":"venue"
},
  "geometry": {"coordinates":[145.01617431599999,-37.9745254517],"type":"Point"}
}