{
  "type": "Feature",
  "properties": {
    "addr:full":"47 Torquata Drv Mirrabooka WA 6061",
    "addr:housenumber":"47",
    "addr:postcode":"6061",
    "addr:street":"Torquata Drv",
    "iso:country":"AU",
    "sg:address":"47 Torquata Drv",
    "sg:city":"Mirrabooka",
    "sg:classifiers":[
        {
            "category":"Personal",
            "subcategory":"Beauty Salon",
            "type":"Services"
        }
    ],
    "sg:phone":"+61 8 9343 7606",
    "sg:postcode":"6061",
    "sg:province":"WA",
    "sg:tags":[
        "supply",
        "artist",
        "make-up"
    ],
    "wof:name":"Hadfield Carol",
    "wof:placetype":"venue"
},
  "geometry": {"coordinates":[115.858558655,-31.8525905609],"type":"Point"}
}