{
  "type": "Feature",
  "properties": {
    "iso:country":"AU",
    "sg:address":"76 Broadmeadow Rd",
    "sg:city":"Broadmeadow",
    "sg:classifiers":[
        {
            "category":"Utilities",
            "subcategory":"Water",
            "type":"Services"
        }
    ],
    "sg:phone":"+61 13 10 31",
    "sg:postcode":"2292",
    "sg:province":"NSW",
    "sg:tags":[
        "hot",
        "system"
    ],
    "wof:name":"Rheem Australia Pty Ltd",
    "wof:placetype":"venue"
},
  "geometry": {"coordinates":[151.73298645,-32.9181900024],"type":"Point"}
}