{
  "type": "Feature",
  "properties": {
    "addr:full":"Cnr Fitzgerald Rd & The Avenue Ardeer VIC 3022",
    "addr:postcode":"3022",
    "addr:street":"Cnr Fitzgerald Rd & The Avenue",
    "iso:country":"AU",
    "sg:address":"Cnr Fitzgerald Rd",
    "sg:city":"& The Avenue Ardeer",
    "sg:classifiers":[
        {
            "category":"Autos & Motor Vehicles",
            "subcategory":"Fuel & Gas Station",
            "type":"Retail Goods"
        }
    ],
    "sg:phone":"+61 3 9360 5042",
    "sg:postcode":"3022",
    "sg:province":"VIC",
    "wof:name":"Better Choice",
    "wof:placetype":"venue"
},
  "geometry": {"coordinates":[144.789703,-37.795811],"type":"Point"}
}