{
  "type": "Feature",
  "properties": {
    "iso:country":"AU",
    "sg:address":"8 Theobald St",
    "sg:city":"Thornbury",
    "sg:classifiers":[
        {
            "category":"Shopping",
            "subcategory":"Stationery & Office Supplies",
            "type":"Retail Goods"
        }
    ],
    "sg:phone":"+61 3 9484 9999",
    "sg:postcode":"3071",
    "sg:province":"VIC",
    "sg:tags":[
        "packaging",
        "material"
    ],
    "wof:name":"Allpac Packaging Supplies",
    "wof:placetype":"venue"
},
  "geometry": {"coordinates":[145.02738952600001,-37.7562026978],"type":"Point"}
}