{
  "type": "Feature",
  "properties": {
    "addr:full":"20 Queen St Southport QLD 4215",
    "addr:housenumber":"20",
    "addr:postcode":"4215",
    "addr:street":"Queen St",
    "iso:country":"AU",
    "sg:address":"20 Queen St",
    "sg:city":"Southport",
    "sg:classifiers":[
        {
            "category":"Travel",
            "subcategory":"Hotels & Motels",
            "type":"Entertainment"
        }
    ],
    "sg:phone":"+61 7 5532 2111",
    "sg:postcode":"4215",
    "sg:province":"QLD",
    "wof:name":"Motel Sundale",
    "wof:placetype":"venue"
},
  "geometry": {"coordinates":[153.41755676299999,-27.9736042023],"type":"Point"}
}