{
  "type": "Feature",
  "properties": {
    "addr:full":"Belgrave-Gembrook Rd Emerald VIC 3782",
    "addr:postcode":"3782",
    "addr:street":"Belgrave-Gembrook Rd",
    "iso:country":"AU",
    "sg:address":"Belgrave-Gembrook Rd",
    "sg:city":"Emerald",
    "sg:classifiers":[
        {
            "category":"Food & Beverages",
            "subcategory":"Supermarket",
            "type":"Retail Goods"
        }
    ],
    "sg:phone":"+61 3 5968 4753",
    "sg:postcode":"3782",
    "sg:province":"VIC",
    "sg:tags":[
        "grocery",
        "store"
    ],
    "wof:name":"Ritchies Stores Pty Ltd",
    "wof:placetype":"venue"
},
  "geometry": {"coordinates":[145.44099399999999,-37.932072],"type":"Point"}
}