{
  "type": "Feature",
  "properties": {
    "iso:country":"AU",
    "sg:address":"Level 10, 459 Little Collins St",
    "sg:city":"Melbourne",
    "sg:classifiers":[
        {
            "category":"Organizations",
            "subcategory":"Professional Association",
            "type":"Services"
        }
    ],
    "sg:phone":"+61 1300 131 932",
    "sg:postcode":"3000",
    "sg:province":"VIC",
    "sg:tags":[
        "web",
        "internet"
    ],
    "wof:name":"Protcole Networks",
    "wof:placetype":"venue"
},
  "geometry": {"coordinates":[144.95942688,-37.8165664673],"type":"Point"}
}