{
  "type": "Feature",
  "properties": {
    "addr:full":"39 Fern St Arcadia Vale NSW 2283",
    "addr:housenumber":"39",
    "addr:postcode":"2283",
    "addr:street":"Fern St",
    "iso:country":"AU",
    "sg:address":"39 Fern St",
    "sg:city":"Arcadia Vale",
    "sg:classifiers":[
        {
            "category":"Building & Trades",
            "subcategory":"Cleaning & Sanitation",
            "type":"Services"
        }
    ],
    "sg:phone":"+61 2 4975 5149",
    "sg:postcode":"2283",
    "sg:province":"NSW",
    "sg:tags":[
        "industrial",
        "commercial",
        "contractor"
    ],
    "wof:name":"Carpet Cleaning Works",
    "wof:placetype":"venue"
},
  "geometry": {"coordinates":[151.578216553,-33.0623245239],"type":"Point"}
}