{
  "type": "Feature",
  "properties": {
    "addr:full":"47- 49 Cosgrove Rd South Strathfield NSW 2136",
    "addr:housenumber":"49",
    "addr:postcode":"2136",
    "addr:street":"Cosgrove Rd South",
    "iso:country":"AU",
    "sg:address":"47- 49 Cosgrove Rd",
    "sg:city":"South Strathfield",
    "sg:classifiers":[
        {
            "category":"Retail",
            "subcategory":"Auto Repair",
            "type":"Services"
        }
    ],
    "sg:phone":"+61 2 9642 5088",
    "sg:postcode":"2136",
    "sg:province":"NSW",
    "sg:tags":[
        "beater",
        "painter",
        "panel"
    ],
    "wof:name":"Strathfield Smash Repairs Pty Ltd",
    "wof:placetype":"venue"
},
  "geometry": {"coordinates":[151.076660156,-33.9013023376],"type":"Point"}
}