{
  "type": "Feature",
  "properties": {
    "iso:country":"AU",
    "sg:address":"68 Otho St",
    "sg:city":"Inverell",
    "sg:classifiers":[
        {
            "category":"Building & Trades",
            "subcategory":"Equipment Rental",
            "type":"Services"
        }
    ],
    "sg:phone":"+61 2 6722 2798",
    "sg:postcode":"2360",
    "sg:province":"NSW",
    "sg:tags":[
        "fitness"
    ],
    "wof:name":"Sportspower",
    "wof:placetype":"venue"
},
  "geometry": {"coordinates":[151.112792969,-29.7746372223],"type":"Point"}
}