{
  "type": "Feature",
  "properties": {
    "addr:full":"225b Henley Beach Rd Torrensville SA 5031",
    "addr:housenumber":"225b",
    "addr:postcode":"5031",
    "addr:street":"Henley Beach Rd",
    "iso:country":"AU",
    "sg:address":"225b Henley Beach Rd",
    "sg:city":"Torrensville",
    "sg:classifiers":[
        {
            "category":"Personal",
            "subcategory":"Beauty Salon",
            "type":"Services"
        }
    ],
    "sg:phone":"+61 8 8354 0318",
    "sg:postcode":"5031",
    "sg:province":"SA",
    "sg:tags":[
        "hairdresser"
    ],
    "wof:name":"The Hair Resort",
    "wof:placetype":"venue"
},
  "geometry": {"coordinates":[138.55560302699999,-34.9245910645],"type":"Point"}
}