{
  "type": "Feature",
  "properties": {
    "addr:full":"41 Northgate St Mooroopna VIC 3629",
    "addr:housenumber":"41",
    "addr:postcode":"3629",
    "addr:street":"Northgate St",
    "iso:country":"AU",
    "sg:address":"41 Northgate St",
    "sg:city":"Mooroopna",
    "sg:classifiers":[
        {
            "category":"Retail",
            "subcategory":"Auto Repair",
            "type":"Services"
        }
    ],
    "sg:phone":"+61 3 5825 4872",
    "sg:postcode":"3629",
    "sg:province":"VIC",
    "sg:tags":[
        "repairer",
        "motor",
        "engineer"
    ],
    "wof:name":"G V Mobile Brake Service",
    "wof:placetype":"venue"
},
  "geometry": {"coordinates":[145.35667419399999,-36.3900794983],"type":"Point"}
}