{
  "type": "Feature",
  "properties": {
    "addr:full":"78 Bakers Rd Coburg VIC 3058",
    "addr:housenumber":"78",
    "addr:postcode":"3058",
    "addr:street":"Bakers Rd",
    "iso:country":"AU",
    "sg:address":"78 Bakers Rd",
    "sg:city":"Coburg",
    "sg:classifiers":[
        {
            "category":"Autos & Motor Vehicles",
            "subcategory":"Automobile Sales",
            "type":"Retail Goods"
        }
    ],
    "sg:phone":"+61 3 9354 8000",
    "sg:postcode":"3058",
    "sg:province":"VIC",
    "sg:tags":[
        "car",
        "used"
    ],
    "wof:name":"Legend Motors",
    "wof:placetype":"venue"
},
  "geometry": {"coordinates":[144.954986572,-37.7262916565],"type":"Point"}
}