{
  "type": "Feature",
  "properties": {
    "addr:full":"2a Proctor St Flagstaff Hill SA 5159",
    "addr:housenumber":"2a",
    "addr:postcode":"5159",
    "addr:street":"Proctor St",
    "iso:country":"AU",
    "sg:address":"2a Proctor St",
    "sg:city":"Flagstaff Hill",
    "sg:classifiers":[
        {
            "category":"Building & Trades",
            "subcategory":"Cleaning & Sanitation",
            "type":"Services"
        }
    ],
    "sg:phone":"+61 8 8370 5323",
    "sg:postcode":"5159",
    "sg:province":"SA",
    "sg:tags":[
        "window"
    ],
    "wof:name":"Spruce Goose Carpet Cleaning",
    "wof:placetype":"venue"
},
  "geometry": {"coordinates":[138.589569092,-35.0505714417],"type":"Point"}
}