{
  "type": "Feature",
  "properties": {
    "iso:country":"AU",
    "sg:address":"21 Ballantyne Crt",
    "sg:city":"Glenview",
    "sg:classifiers":[
        {
            "category":"Home & Garden",
            "subcategory":"Garden Supply",
            "type":"Retail Goods"
        }
    ],
    "sg:phone":"+61 7 5494 5616",
    "sg:postcode":"4553",
    "sg:province":"QLD",
    "sg:tags":[
        "turf",
        "lawn"
    ],
    "wof:name":"Glenview Turf",
    "wof:placetype":"venue"
},
  "geometry": {"coordinates":[153.04499799999999,-26.762932],"type":"Point"}
}