{
  "type": "Feature",
  "properties": {
    "iso:country":"AU",
    "sg:address":"13 Bridge St",
    "sg:city":"Benalla",
    "sg:classifiers":[
        {
            "category":"Personal",
            "subcategory":"Hair Removal",
            "type":"Services"
        }
    ],
    "sg:phone":"+61 3 5762 4233",
    "sg:postcode":"3672",
    "sg:province":"VIC",
    "wof:name":"Indulgence On Bridge",
    "wof:placetype":"venue"
},
  "geometry": {"coordinates":[145.982666,-36.551807],"type":"Point"}
}