{
  "type": "Feature",
  "properties": {
    "addr:full":"16 Glass St Kew East VIC 3102",
    "addr:housenumber":"16",
    "addr:postcode":"3102",
    "addr:street":"Glass St",
    "iso:country":"AU",
    "sg:address":"16 Glass St",
    "sg:city":"Kew East",
    "sg:classifiers":[
        {
            "category":"Education",
            "subcategory":"Kindergarten",
            "type":"Public Place"
        }
    ],
    "sg:phone":"+61 3 9859 6049",
    "sg:postcode":"3102",
    "sg:province":"VIC",
    "sg:tags":[
        "pre-schools"
    ],
    "wof:name":"Glass Street Kindergarten",
    "wof:placetype":"venue"
},
  "geometry": {"coordinates":[145.061203003,-37.7933158875],"type":"Point"}
}