{
  "type": "Feature",
  "properties": {
    "addr:full":"Ground Floor 101 Currie St Adelaide SA 5000",
    "addr:housenumber":"101",
    "addr:postcode":"5000",
    "addr:street":"Currie St",
    "iso:country":"AU",
    "sg:address":"Ground Floor 101 Currie St",
    "sg:city":"Adelaide",
    "sg:classifiers":[
        {
            "category":"Professional",
            "subcategory":"Computer Services",
            "type":"Services"
        }
    ],
    "sg:phone":"+61 8 8414 6300",
    "sg:postcode":"5000",
    "sg:province":"SA",
    "sg:tags":[
        "package",
        "software"
    ],
    "wof:name":"ESRI Australia Pty Ltd",
    "wof:placetype":"venue"
},
  "geometry": {"coordinates":[138.59565734899999,-34.9247779846],"type":"Point"}
}