{
  "type": "Feature",
  "properties": {
    "addr:full":"Lot4/ Old Sydney Rd Thurgoona NSW 2640",
    "addr:postcode":"2640",
    "addr:street":"Sydney Rd",
    "iso:country":"AU",
    "sg:address":"Lot4/ Old Sydney Rd",
    "sg:city":"Thurgoona",
    "sg:classifiers":[
        {
            "category":"Building & Trades",
            "subcategory":"Construction",
            "type":"Services"
        }
    ],
    "sg:phone":"+61 2 6026 2884",
    "sg:postcode":"2640",
    "sg:province":"NSW",
    "sg:tags":[
        "contractor"
    ],
    "wof:name":"E & V Homes",
    "wof:placetype":"venue"
},
  "geometry": {"coordinates":[146.99064636200001,-36.0582122803],"type":"Point"}
}