{
  "type": "Feature",
  "properties": {
    "iso:country":"AU",
    "sg:address":"19 Lochlarney St",
    "sg:city":"Beenleigh",
    "sg:classifiers":[
        {
            "category":"Utilities",
            "subcategory":"Electric",
            "type":"Services"
        }
    ],
    "sg:phone":"+61 1300 762 701",
    "sg:postcode":"4207",
    "sg:province":"QLD",
    "sg:tags":[
        "electrical",
        "contractor"
    ],
    "wof:name":"Brisbane IT & Electrical",
    "wof:placetype":"venue"
},
  "geometry": {"coordinates":[153.18539428700001,-27.7122821808],"type":"Point"}
}