{
  "type": "Feature",
  "properties": {
    "addr:full":"Ross St Goulburn NSW 2580",
    "addr:postcode":"2580",
    "addr:street":"Ross St",
    "iso:country":"AU",
    "sg:address":"Ross St",
    "sg:city":"Goulburn",
    "sg:classifiers":[
        {
            "category":"Insurance",
            "subcategory":"Insurance Agent",
            "type":"Services"
        }
    ],
    "sg:phone":"+61 2 4821 4889",
    "sg:postcode":"2580",
    "sg:province":"NSW",
    "sg:tags":[
        "wool",
        "broker"
    ],
    "wof:name":"Betta Wool Handlers Pty Ltd",
    "wof:placetype":"venue"
},
  "geometry": {"coordinates":[149.74435424800001,-34.7328491211],"type":"Point"}
}