{
  "type": "Feature",
  "properties": {
    "addr:full":"21 Warner St Port Douglas QLD 4877",
    "addr:housenumber":"21",
    "addr:postcode":"4877",
    "addr:street":"Warner St",
    "iso:country":"AU",
    "sg:address":"21 Warner St",
    "sg:city":"Port Douglas",
    "sg:classifiers":[
        {
            "category":"Retail",
            "subcategory":"Auto Rental",
            "type":"Services"
        }
    ],
    "sg:phone":"+61 7 4099 4123",
    "sg:postcode":"4877",
    "sg:province":"QLD",
    "sg:tags":[
        "car",
        "hire",
        "minibus"
    ],
    "wof:name":"All Car Rentals",
    "wof:placetype":"venue"
},
  "geometry": {"coordinates":[145.46321105999999,-16.4835948944],"type":"Point"}
}