{
  "type": "Feature",
  "properties": {
    "addr:full":"St James Arc 76 Castlereagh Strs Sydney NSW 2000",
    "addr:housenumber":"76",
    "addr:postcode":"2000",
    "addr:street":"Arc;Strs",
    "iso:country":"AU",
    "sg:address":"St James Arc 76 Castlereagh Strs",
    "sg:city":"Sydney",
    "sg:classifiers":[
        {
            "category":"Personal",
            "subcategory":"Beauty Salon",
            "type":"Services"
        }
    ],
    "sg:phone":"+61 2 9232 4808",
    "sg:postcode":"2000",
    "sg:province":"NSW",
    "sg:tags":[
        "hairdresser"
    ],
    "wof:name":"Bruno F Hair Face Body",
    "wof:placetype":"venue"
},
  "geometry": {"coordinates":[151.21104431099999,-33.8698501587],"type":"Point"}
}