{
  "type": "Feature",
  "properties": {
    "addr:full":"Shop 10, Sunshine Plaza Hampshire Rd Sunshine VIC 3020",
    "addr:housenumber":"shop 10",
    "addr:postcode":"3020",
    "addr:street":"Sunshine Plaza Hampshire Rd",
    "iso:country":"AU",
    "sg:address":"Shop 10, Sunshine Plaza Hampshire Rd",
    "sg:city":"Sunshine",
    "sg:classifiers":[
        {
            "category":"Shopping",
            "subcategory":"Mobile Phones",
            "type":"Retail Goods"
        }
    ],
    "sg:phone":"+61 3 9310 2124",
    "sg:postcode":"3020",
    "sg:province":"VIC",
    "sg:tags":[
        "telephone",
        "accessory"
    ],
    "wof:name":"In Your Face Communications",
    "wof:placetype":"venue"
},
  "geometry": {"coordinates":[144.83244300000001,-37.787621],"type":"Point"}
}