{
  "type": "Feature",
  "properties": {
    "addr:full":"10 Phillip St Beenleigh QLD 4207",
    "addr:housenumber":"10",
    "addr:postcode":"4207",
    "addr:street":"Phillip St",
    "iso:country":"AU",
    "sg:address":"10 Phillip St",
    "sg:city":"Beenleigh",
    "sg:classifiers":[
        {
            "category":"Social Services",
            "subcategory":"Child Care",
            "type":"Services"
        }
    ],
    "sg:phone":"+61 7 3807 5297",
    "sg:postcode":"4207",
    "sg:province":"QLD",
    "wof:name":"The Childrens Centre Of Beenleigh",
    "wof:placetype":"venue"
},
  "geometry": {"coordinates":[153.197998047,-27.7178688049],"type":"Point"}
}