{
  "type": "Feature",
  "properties": {
    "iso:country":"AU",
    "sg:address":"35 Swan St",
    "sg:city":"Richmond",
    "sg:classifiers":[
        {
            "category":"Retail",
            "subcategory":"Auto Rental",
            "type":"Services"
        }
    ],
    "sg:phone":"+61 3 9428 8096",
    "sg:postcode":"3121",
    "sg:province":"VIC",
    "sg:tags":[
        "car",
        "hire",
        "minibus"
    ],
    "wof:name":"Affordahire Car",
    "wof:placetype":"venue"
},
  "geometry": {"coordinates":[144.990890503,-37.8247108459],"type":"Point"}
}