{
  "type": "Feature",
  "properties": {
    "addr:full":"PO Box 1680 Ryde NSW 1680",
    "addr:postcode":"1680",
    "iso:country":"AU",
    "sg:address":"PO Box 1680",
    "sg:city":"Ryde",
    "sg:classifiers":[
        {
            "category":"Manufacturing",
            "subcategory":"Tobacco Products",
            "type":"Manufacturing & Wholesale Goods"
        }
    ],
    "sg:phone":"+61 1300 736 432",
    "sg:postcode":"1680",
    "sg:province":"NSW",
    "sg:tags":[
        "car",
        "truck",
        "cleaning",
        "equipment"
    ],
    "wof:name":"Natural Autocare",
    "wof:placetype":"venue"
},
  "geometry": {"coordinates":[151.104934692,-33.8129501343],"type":"Point"}
}