{
  "type": "Feature",
  "properties": {
    "iso:country":"AU",
    "sg:address":"2/ 8 Bay Rd",
    "sg:city":"Taren Point",
    "sg:classifiers":[
        {
            "category":"Professional",
            "type":"Services"
        }
    ],
    "sg:phone":"+61 500 551 755",
    "sg:postcode":"2229",
    "sg:province":"NSW",
    "sg:tags":[
        "spray",
        "painting"
    ],
    "wof:name":"Fibremotive Australia",
    "wof:placetype":"venue"
},
  "geometry": {"coordinates":[151.12762451200001,-34.0239105225],"type":"Point"}
}