{
  "type": "Feature",
  "properties": {
    "addr:full":"120 Wood St Mackay QLD 4740",
    "addr:housenumber":"120",
    "addr:postcode":"4740",
    "addr:street":"Wood St",
    "iso:country":"AU",
    "sg:address":"120 Wood St",
    "sg:city":"Mackay",
    "sg:classifiers":[
        {
            "category":"Organizations",
            "subcategory":"Non-profit Organization",
            "type":"Services"
        }
    ],
    "sg:phone":"+61 7 4953 4267",
    "sg:postcode":"4740",
    "sg:province":"QLD",
    "sg:tags":[
        "environmental",
        "organisation",
        "conservation"
    ],
    "wof:name":"Greening Australia Inc.",
    "wof:placetype":"venue"
},
  "geometry": {"coordinates":[149.18525700000001,-21.14443],"type":"Point"}
}