{
  "type": "Feature",
  "properties": {
    "addr:full":"Lot 2 Wonga Rd Picton NSW 2571",
    "addr:postcode":"2571",
    "addr:street":"Wonga Rd",
    "iso:country":"AU",
    "sg:address":"Lot 2 Wonga Rd",
    "sg:city":"Picton",
    "sg:classifiers":[
        {
            "category":"Farming",
            "subcategory":"Farm & Veterinary Services",
            "type":"Manufacturing & Wholesale Goods"
        }
    ],
    "sg:phone":"+61 2 4677 1333",
    "sg:postcode":"2571",
    "sg:province":"NSW",
    "sg:tags":[
        "irrigation",
        "reticulation",
        "system"
    ],
    "wof:name":"All Picton Sand & Soil",
    "wof:placetype":"venue"
},
  "geometry": {"coordinates":[150.60969543499999,-34.1961135864],"type":"Point"}
}