{
  "type": "Feature",
  "properties": {
    "iso:country":"AU",
    "sg:address":"78 Mica St",
    "sg:city":"Carole Park",
    "sg:classifiers":[
        {
            "category":"Home & Garden",
            "subcategory":"Hardware",
            "type":"Retail Goods"
        }
    ],
    "sg:phone":"+61 7 3879 3111",
    "sg:postcode":"4300",
    "sg:province":"QLD",
    "sg:tags":[
        "compressor",
        "air"
    ],
    "wof:name":"Globe Compressors",
    "wof:placetype":"venue"
},
  "geometry": {"coordinates":[152.93385314899999,-27.6215286255],"type":"Point"}
}