{
  "type": "Feature",
  "properties": {
    "addr:full":"PO Box 156 Wilberforce NSW 2756",
    "addr:postcode":"2756",
    "iso:country":"AU",
    "sg:address":"PO Box 156",
    "sg:city":"Wilberforce",
    "sg:classifiers":[
        {
            "category":"Building & Trades",
            "subcategory":"Construction",
            "type":"Services"
        }
    ],
    "sg:phone":"+61 2 4576 3088",
    "sg:postcode":"2756",
    "sg:province":"NSW",
    "sg:tags":[
        "contractor"
    ],
    "wof:name":"Bullridge Constructions",
    "wof:placetype":"venue"
},
  "geometry": {"coordinates":[150.83720398,-33.5579986572],"type":"Point"}
}