{
  "type": "Feature",
  "properties": {
    "addr:full":"273 B High St Northcote VIC 3070",
    "addr:housenumber":"273 b",
    "addr:postcode":"3070",
    "addr:street":"High St",
    "iso:country":"AU",
    "sg:address":"273 B High St",
    "sg:city":"Northcote",
    "sg:classifiers":[
        {
            "category":"Real Estate",
            "subcategory":"Architect",
            "type":"Services"
        }
    ],
    "sg:phone":"+61 3 9486 6283",
    "sg:postcode":"3070",
    "sg:province":"VIC",
    "wof:name":"Welsch Steffen Architects",
    "wof:placetype":"venue"
},
  "geometry": {"coordinates":[144.998276,-37.772957],"type":"Point"}
}