{
  "type": "Feature",
  "properties": {
    "addr:full":"443 Wagga Rd (Hume Hwy) Lavington NSW 2641",
    "addr:housenumber":"443",
    "addr:postcode":"2641",
    "addr:street":"Wagga Rd Hume Hwy",
    "iso:country":"AU",
    "sg:address":"443 Wagga Rd (Hume Hwy)",
    "sg:city":"Lavington",
    "sg:classifiers":[
        {
            "category":"Travel",
            "subcategory":"Hotels & Motels",
            "type":"Entertainment"
        }
    ],
    "sg:phone":"+61 2 6025 1489",
    "sg:postcode":"2641",
    "sg:province":"NSW",
    "wof:name":"Albury Caravanna Caravan Park",
    "wof:placetype":"venue"
},
  "geometry": {"coordinates":[146.94569397000001,-36.0441093445],"type":"Point"}
}