{
  "type": "Feature",
  "properties": {
    "addr:full":"2 Duxford St Butler WA 6036",
    "addr:housenumber":"2",
    "addr:postcode":"6036",
    "addr:street":"Duxford St",
    "iso:country":"AU",
    "sg:address":"2 Duxford St",
    "sg:city":"Butler",
    "sg:classifiers":[
        {
            "category":"Retail",
            "subcategory":"Car Wash",
            "type":"Services"
        }
    ],
    "sg:phone":"+61 406 616 157",
    "sg:postcode":"6036",
    "sg:province":"WA",
    "sg:tags":[
        "truck",
        "cleaning"
    ],
    "wof:name":"On the Bright Side",
    "wof:placetype":"venue"
},
  "geometry": {"coordinates":[115.69934845,-31.649389267],"type":"Point"}
}