{
  "type": "Feature",
  "properties": {
    "addr:full":"94 Gawler Pl Adelaide SA 5000",
    "addr:housenumber":"94",
    "addr:postcode":"5000",
    "addr:street":"Gawler Pl",
    "iso:country":"AU",
    "sg:address":"94 Gawler Pl",
    "sg:city":"Adelaide",
    "sg:classifiers":[
        {
            "category":"Fast Food",
            "type":"Food & Drink"
        }
    ],
    "sg:phone":"+61 8 8232 8787",
    "sg:postcode":"5000",
    "sg:province":"SA",
    "sg:tags":[
        "away",
        "take"
    ],
    "wof:name":"Taste Of Asia Fresh Noodle Bar",
    "wof:placetype":"venue"
},
  "geometry": {"coordinates":[138.60215759299999,-34.9246292114],"type":"Point"}
}