{
  "type": "Feature",
  "properties": {
    "addr:full":"8 Wright St Clifton Hill VIC 3068",
    "addr:housenumber":"8",
    "addr:postcode":"3068",
    "addr:street":"Wright St",
    "iso:country":"AU",
    "sg:address":"8 Wright St",
    "sg:city":"Clifton Hill",
    "sg:classifiers":[
        {
            "category":"Communications",
            "subcategory":"News Services",
            "type":"Services"
        }
    ],
    "sg:phone":"+61 3 9482 3638",
    "sg:postcode":"3068",
    "sg:province":"VIC",
    "sg:tags":[
        "information",
        "tourist",
        "attractions"
    ],
    "wof:name":"Justin Francis & Associates Cultural & Ecotourism Planning Consultants",
    "wof:placetype":"venue"
},
  "geometry": {"coordinates":[145.00064086899999,-37.7889480591],"type":"Point"}
}