{
  "type": "Feature",
  "properties": {
    "addr:full":"75 Gillies Rd Drysdale VIC 3222",
    "addr:housenumber":"75",
    "addr:postcode":"3222",
    "addr:street":"Gillies Rd",
    "iso:country":"AU",
    "sg:address":"75 Gillies Rd",
    "sg:city":"Drysdale",
    "sg:classifiers":[
        {
            "category":"Farming",
            "subcategory":"Farm & Veterinary Services",
            "type":"Manufacturing & Wholesale Goods"
        }
    ],
    "sg:phone":"+61 415 524 487",
    "sg:postcode":"3222",
    "sg:province":"VIC",
    "sg:tags":[
        "irrigation",
        "reticulation",
        "system"
    ],
    "wof:name":"All Seasons Irrigation & Trenching",
    "wof:placetype":"venue"
},
  "geometry": {"coordinates":[144.56042500000001,-38.187897],"type":"Point"}
}