{
  "type": "Feature",
  "properties": {
    "addr:full":"41 Princes Hwy Sylvania NSW 2224",
    "addr:housenumber":"41",
    "addr:postcode":"2224",
    "addr:street":"Princes Hwy",
    "iso:country":"AU",
    "sg:address":"41 Princes Hwy",
    "sg:city":"Sylvania",
    "sg:classifiers":[
        {
            "category":"Restaurant",
            "type":"Food & Drink"
        }
    ],
    "sg:phone":"+61 2 9544 7477",
    "sg:postcode":"2224",
    "sg:province":"NSW",
    "wof:name":"Zimme Gourmet Woodfire Pizza",
    "wof:placetype":"venue"
},
  "geometry": {"coordinates":[151.1118927,-34.0063438416],"type":"Point"}
}