{
  "type": "Feature",
  "properties": {
    "addr:full":"Factory 22-23 21 Eugene Tce Ringwood VIC 3134",
    "addr:housenumber":"22-23 21",
    "addr:postcode":"3134",
    "addr:street":"Eugene Tce",
    "iso:country":"AU",
    "sg:address":"Factory 22-23 21 Eugene Tce",
    "sg:city":"Ringwood",
    "sg:classifiers":[
        {
            "category":"Shopping",
            "subcategory":"Gifts & Souvenirs",
            "type":"Retail Goods"
        }
    ],
    "sg:phone":"+61 3 9879 3888",
    "sg:postcode":"3134",
    "sg:province":"VIC",
    "sg:tags":[
        "shop",
        "supply"
    ],
    "wof:name":"Inter Austral Orient Co Pty Ltd",
    "wof:placetype":"venue"
},
  "geometry": {"coordinates":[145.21890258799999,-37.8254547119],"type":"Point"}
}