{
  "type": "Feature",
  "properties": {
    "addr:full":"ste 14-15/ 41 Market St Wollongong NSW 2500",
    "addr:housenumber":"14-15 / 41",
    "addr:postcode":"2500",
    "addr:street":"Market St",
    "iso:country":"AU",
    "sg:address":"ste 14-15/ 41 Market St",
    "sg:city":"Wollongong",
    "sg:classifiers":[
        {
            "category":"Professional",
            "subcategory":"Accounting & Tax Preparation",
            "type":"Services"
        }
    ],
    "sg:phone":"+61 2 4226 4877",
    "sg:postcode":"2500",
    "sg:province":"NSW",
    "sg:tags":[
        "accountant",
        "auditor"
    ],
    "wof:name":"Dodd Accountants",
    "wof:placetype":"venue"
},
  "geometry": {"coordinates":[150.89605700000001,-34.432735],"type":"Point"}
}