{
  "type": "Feature",
  "properties": {
    "iso:country":"AU",
    "sg:address":"141 Churchill Rd",
    "sg:city":"Prospect",
    "sg:classifiers":[
        {
            "category":"Deli",
            "type":"Food & Drink"
        }
    ],
    "sg:phone":"+61 8 8344 6079",
    "sg:postcode":"5082",
    "sg:province":"SA",
    "sg:tags":[
        "delicatessen"
    ],
    "wof:name":"Theo's Deli",
    "wof:placetype":"venue"
},
  "geometry": {"coordinates":[138.58502197300001,-34.8853874207],"type":"Point"}
}