{
  "type": "Feature",
  "properties": {
    "iso:country":"AU",
    "sg:address":"Shed 1 / 45 Wises Rd",
    "sg:city":"Buderim",
    "sg:classifiers":[
        {
            "category":"Home & Garden",
            "subcategory":"Carpets & Floor Coverings",
            "type":"Retail Goods"
        }
    ],
    "sg:phone":"+61 7 5443 1122",
    "sg:postcode":"4556",
    "sg:province":"QLD",
    "sg:tags":[
        "tile",
        "wall"
    ],
    "wof:name":"MJS Floorcoverings",
    "wof:placetype":"venue"
},
  "geometry": {"coordinates":[153.09080505399999,-26.6718616486],"type":"Point"}
}