{
  "type": "Feature",
  "properties": {
    "iso:country":"AU",
    "sg:address":"16 Lurline St",
    "sg:city":"Cranbourne",
    "sg:classifiers":[
        {
            "category":"Fast Food",
            "type":"Food & Drink"
        }
    ],
    "sg:phone":"+61 3 5996 6344",
    "sg:postcode":"3977",
    "sg:province":"VIC",
    "sg:tags":[
        "away",
        "take"
    ],
    "wof:name":"IL Porchetto Pizza",
    "wof:placetype":"venue"
},
  "geometry": {"coordinates":[145.275024414,-38.1114501953],"type":"Point"}
}