{
  "type": "Feature",
  "properties": {
    "iso:country":"AU",
    "sg:address":"266 Railway Pde",
    "sg:city":"Noble Park",
    "sg:classifiers":[
        {
            "category":"Professional",
            "subcategory":"Advertising",
            "type":"Services"
        }
    ],
    "sg:phone":"+61 3 9701 3778",
    "sg:postcode":"3174",
    "sg:province":"VIC",
    "sg:tags":[
        "balloon",
        "novelty"
    ],
    "wof:name":"Balloon & Party Specialists",
    "wof:placetype":"venue"
},
  "geometry": {"coordinates":[145.186309814,-37.9737243652],"type":"Point"}
}