{
  "type": "Feature",
  "properties": {
    "iso:country":"AU",
    "sg:address":"Lvl1/ 61 Grote St",
    "sg:city":"Adelaide",
    "sg:classifiers":[
        {
            "category":"Banks & Credit Unions",
            "subcategory":"Financial Services",
            "type":"Services"
        }
    ],
    "sg:phone":"+61 8 8212 1221",
    "sg:postcode":"5000",
    "sg:province":"SA",
    "sg:tags":[
        "loan",
        "finance",
        "mortgage"
    ],
    "wof:name":"Finance 1-2-3",
    "wof:placetype":"venue"
},
  "geometry": {"coordinates":[138.596755981,-34.9304161072],"type":"Point"}
}