{
  "type": "Feature",
  "properties": {
    "iso:country":"AU",
    "sg:address":"18 Railway Pde",
    "sg:city":"Bayswater",
    "sg:classifiers":[
        {
            "category":"Home & Garden",
            "subcategory":"Building Materials",
            "type":"Retail Goods"
        }
    ],
    "sg:phone":"+61 8 9279 0384",
    "sg:postcode":"6053",
    "sg:province":"WA",
    "sg:tags":[
        "supply"
    ],
    "wof:name":"Bradys Building Products",
    "wof:placetype":"venue"
},
  "geometry": {"coordinates":[115.912536621,-31.917678833],"type":"Point"}
}