{
  "type": "Feature",
  "properties": {
    "iso:country":"AU",
    "sg:address":"50 Valencia St",
    "sg:city":"Glenroy",
    "sg:classifiers":[
        {
            "category":"Building & Trades",
            "subcategory":"Landscaping Services",
            "type":"Services"
        }
    ],
    "sg:phone":"+61 3 9304 2459",
    "sg:postcode":"3046",
    "sg:province":"VIC",
    "sg:tags":[
        "gardener"
    ],
    "wof:name":"Thrifty Garden Services",
    "wof:placetype":"venue"
},
  "geometry": {"coordinates":[144.936843872,-37.7024993896],"type":"Point"}
}