{
  "type": "Feature",
  "properties": {
    "addr:full":"10 High St Stanthorpe QLD 4380",
    "addr:housenumber":"10",
    "addr:postcode":"4380",
    "addr:street":"High St",
    "iso:country":"AU",
    "sg:address":"10 High St",
    "sg:city":"Stanthorpe",
    "sg:classifiers":[
        {
            "category":"Travel",
            "subcategory":"Hotels & Motels",
            "type":"Entertainment"
        }
    ],
    "sg:phone":"+61 1800 030 123",
    "sg:postcode":"4380",
    "sg:province":"QLD",
    "wof:name":"Top Of The Town Stanthorpe",
    "wof:placetype":"venue"
},
  "geometry": {"coordinates":[151.946564,-28.645775],"type":"Point"}
}