{
  "type": "Feature",
  "properties": {
    "iso:country":"AU",
    "sg:address":"1 Grange Rd",
    "sg:city":"Toorak",
    "sg:classifiers":[
        {
            "category":"Cafe",
            "type":"Food & Drink"
        }
    ],
    "sg:phone":"+61 3 9804 7700",
    "sg:postcode":"3142",
    "sg:province":"VIC",
    "wof:name":"Pane E Vino",
    "wof:placetype":"venue"
},
  "geometry": {"coordinates":[145.010665894,-37.8409538269],"type":"Point"}
}