{
  "type": "Feature",
  "properties": {
    "iso:country":"AU",
    "sg:address":"14 Waterloo St",
    "sg:city":"Glenelg",
    "sg:classifiers":[
        {
            "category":"Health Services",
            "subcategory":"Health Practitioner",
            "type":"Services"
        }
    ],
    "sg:phone":"+61 8 8295 6500",
    "sg:postcode":"5045",
    "sg:province":"SA",
    "sg:tags":[
        "physiotherapist"
    ],
    "wof:name":"Physiotherapy Private Glenelg",
    "wof:placetype":"venue"
},
  "geometry": {"coordinates":[138.512054,-34.981823],"type":"Point"}
}