{
  "type": "Feature",
  "properties": {
    "addr:full":"Shop 2, 587- 589 Princess Hwy Bairnsdale VIC 3875",
    "addr:housenumber":"shop 2;589",
    "addr:postcode":"587;3875",
    "addr:street":"Princess Hwy",
    "iso:country":"AU",
    "sg:address":"Shop 2, 587- 589 Princess Hwy",
    "sg:city":"Bairnsdale",
    "sg:classifiers":[
        {
            "category":"Wholesale",
            "subcategory":"Home Furnishings",
            "type":"Manufacturing & Wholesale Goods"
        }
    ],
    "sg:phone":"+61 3 5152 1835",
    "sg:postcode":"3875",
    "sg:province":"VIC",
    "sg:tags":[
        "wholesaler",
        "curtain",
        "mfrs"
    ],
    "wof:name":"Riviera Curtains & Blinds",
    "wof:placetype":"venue"
},
  "geometry": {"coordinates":[147.60108947800001,-37.8355636597],"type":"Point"}
}