{
  "type": "Feature",
  "properties": {
    "addr:full":"PO Box 369 Cronulla NSW 2230",
    "addr:postcode":"2230",
    "iso:country":"AU",
    "sg:address":"PO Box 369",
    "sg:city":"Cronulla",
    "sg:classifiers":[
        {
            "category":"Building & Trades",
            "subcategory":"Plumbing",
            "type":"Services"
        }
    ],
    "sg:phone":"+61 414 273 732",
    "sg:postcode":"2230",
    "sg:province":"NSW",
    "sg:tags":[
        "plumber",
        "gasfitters"
    ],
    "wof:name":"Crowley Plumbing & Maintenance Services",
    "wof:placetype":"venue"
},
  "geometry": {"coordinates":[151.15138244600001,-34.0461921692],"type":"Point"}
}