{
  "type": "Feature",
  "properties": {
    "addr:full":"68 Bingara St Pallamallawa NSW 2399",
    "addr:housenumber":"68",
    "addr:postcode":"2399",
    "addr:street":"Bingara St",
    "iso:country":"AU",
    "sg:address":"68 Bingara St",
    "sg:city":"Pallamallawa",
    "sg:classifiers":[
        {
            "category":"Cafe",
            "type":"Food & Drink"
        }
    ],
    "sg:phone":"+61 2 6754 9653",
    "sg:postcode":"2399",
    "sg:province":"NSW",
    "wof:name":"Pally Cafe",
    "wof:placetype":"venue"
},
  "geometry": {"coordinates":[150.13435363799999,-29.4741001129],"type":"Point"}
}