{
  "type": "Feature",
  "properties": {
    "addr:full":"Shop 37 Yamba Shopping Fair, Treelands Drive Yamba NSW 2464",
    "addr:housenumber":"shop 37",
    "addr:postcode":"2464",
    "addr:street":"Drive",
    "iso:country":"AU",
    "sg:address":"Shop 37",
    "sg:city":"Yamba Shopping Fair, Treelands Drive Yamba",
    "sg:classifiers":[
        {
            "category":"Fast Food",
            "type":"Food & Drink"
        }
    ],
    "sg:phone":"+61 2 6646 1164",
    "sg:postcode":"2464",
    "sg:province":"NSW",
    "sg:tags":[
        "away",
        "take"
    ],
    "wof:name":"Yamba Chicken & Seafood",
    "wof:placetype":"venue"
},
  "geometry": {"coordinates":[153.327224731,-29.4290809631],"type":"Point"}
}