{
  "type": "Feature",
  "properties": {
    "addr:full":"433 Logan Rd Stones Corner QLD 4120",
    "addr:housenumber":"433",
    "addr:postcode":"4120",
    "addr:street":"Logan Rd",
    "iso:country":"AU",
    "sg:address":"433 Logan Rd",
    "sg:city":"Stones Corner",
    "sg:classifiers":[
        {
            "category":"Retail",
            "subcategory":"Storage",
            "type":"Services"
        }
    ],
    "sg:phone":"+61 1800 265 291",
    "sg:postcode":"4120",
    "sg:province":"QLD",
    "sg:tags":[
        "shelving",
        "system"
    ],
    "wof:name":"Colby Storage Solutions",
    "wof:placetype":"venue"
},
  "geometry": {"coordinates":[153.04624939000001,-27.5013046265],"type":"Point"}
}