{
  "type": "Feature",
  "properties": {
    "addr:full":"PO Box 669 Lilydale VIC 3140",
    "addr:postcode":"3140",
    "iso:country":"AU",
    "sg:address":"PO Box 669",
    "sg:city":"Lilydale",
    "sg:classifiers":[
        {
            "category":"Farming",
            "subcategory":"Farm & Veterinary Services",
            "type":"Manufacturing & Wholesale Goods"
        }
    ],
    "sg:phone":"+61 412 843 962",
    "sg:postcode":"3140",
    "sg:province":"VIC",
    "sg:tags":[
        "blacksmith",
        "farrier"
    ],
    "wof:name":"Lagrutta Anthony",
    "wof:placetype":"venue"
},
  "geometry": {"coordinates":[145.37161254899999,-37.7617797852],"type":"Point"}
}