{
  "type": "Feature",
  "properties": {
    "addr:full":"U 2/ 135 Great Eastern Hwy Belmont WA 6104",
    "addr:housenumber":"/ 135",
    "addr:postcode":"6104",
    "addr:street":"Great Eastern Hwy",
    "iso:country":"AU",
    "sg:address":"U 2/ 135 Great Eastern Hwy",
    "sg:city":"Belmont",
    "sg:classifiers":[
        {
            "category":"Personal",
            "subcategory":"Adult",
            "type":"Services"
        }
    ],
    "sg:phone":"+61 8 9477 4366",
    "sg:postcode":"6104",
    "sg:province":"WA",
    "sg:tags":[
        "vic",
        "except",
        "state",
        "escort",
        "social",
        "qld"
    ],
    "wof:name":"Blacklace (Australia) Pty Ltd",
    "wof:placetype":"venue"
},
  "geometry": {"coordinates":[115.91970825200001,-31.9459018707],"type":"Point"}
}