{
  "type": "Feature",
  "properties": {
    "iso:country":"AU",
    "sg:address":"32 Alvie Rd",
    "sg:city":"Mt Waverley",
    "sg:classifiers":[
        {
            "category":"Personal",
            "subcategory":"Beauty Salon",
            "type":"Services"
        }
    ],
    "sg:phone":"+61 3 9807 7816",
    "sg:postcode":"3149",
    "sg:province":"VIC",
    "sg:tags":[
        "hairdresser"
    ],
    "wof:name":"The Barber Shop",
    "wof:placetype":"venue"
},
  "geometry": {"coordinates":[145.122283936,-37.8721160889],"type":"Point"}
}