{
  "type": "Feature",
  "properties": {
    "addr:full":"87- 89 Canadian Bay Rd Mt Eliza VIC 3930",
    "addr:housenumber":"89",
    "addr:postcode":"3930",
    "addr:street":"Canadian Bay Rd",
    "iso:country":"AU",
    "sg:address":"87- 89 Canadian Bay Rd",
    "sg:city":"Mt Eliza",
    "sg:classifiers":[
        {
            "category":"Health Services",
            "subcategory":"Dentist",
            "type":"Services"
        }
    ],
    "sg:phone":"+61 3 9787 3355",
    "sg:postcode":"3930",
    "sg:province":"VIC",
    "wof:name":"Wright Graeme Dr.",
    "wof:placetype":"venue"
},
  "geometry": {"coordinates":[145.090744019,-38.1853256226],"type":"Point"}
}