{
  "type": "Feature",
  "properties": {
    "iso:country":"AU",
    "sg:address":"PO Box 2119",
    "sg:city":"South Hedland",
    "sg:classifiers":[
        {
            "category":"Retail",
            "subcategory":"Auto Repair",
            "type":"Services"
        }
    ],
    "sg:phone":"+61 418 937 238",
    "sg:postcode":"6722",
    "sg:province":"WA",
    "sg:tags":[
        "electrical"
    ],
    "wof:name":"All Hours Auto Electrics",
    "wof:placetype":"venue"
},
  "geometry": {"coordinates":[118.60131072999999,-20.4081993103],"type":"Point"}
}