{
  "type": "Feature",
  "properties": {
    "addr:full":"1508 Anderson Rd Karratha WA 6714",
    "addr:housenumber":"1508",
    "addr:postcode":"6714",
    "addr:street":"Anderson Rd",
    "iso:country":"AU",
    "sg:address":"1508 Anderson Rd",
    "sg:city":"Karratha",
    "sg:classifiers":[
        {
            "category":"Home & Garden",
            "subcategory":"Garden Supply",
            "type":"Retail Goods"
        }
    ],
    "sg:phone":"+61 8 9144 4029",
    "sg:postcode":"6714",
    "sg:province":"WA",
    "sg:tags":[
        "equipment"
    ],
    "wof:name":"Poinciana Nursery",
    "wof:placetype":"venue"
},
  "geometry": {"coordinates":[116.87113952599999,-20.769159317],"type":"Point"}
}