{
  "type": "Feature",
  "properties": {
    "addr:full":"9/ 9 HiTech Pl Rowville VIC 3178",
    "addr:housenumber":"/ 9",
    "addr:postcode":"3178",
    "addr:street":"Hitech Pl",
    "iso:country":"AU",
    "sg:address":"9/ 9 HiTech Pl",
    "sg:city":"Rowville",
    "sg:classifiers":[
        {
            "category":"Shopping",
            "subcategory":"Computers & Home Electronics",
            "type":"Retail Goods"
        }
    ],
    "sg:phone":"+61 3 9764 2779",
    "sg:postcode":"3178",
    "sg:province":"VIC",
    "sg:tags":[
        "wholesaler",
        "mfrs",
        "part",
        "electronic"
    ],
    "wof:name":"Alliance Electronics Australia Pty Ltd",
    "wof:placetype":"venue"
},
  "geometry": {"coordinates":[145.24615478499999,-37.9102706909],"type":"Point"}
}