{
  "type": "Feature",
  "properties": {
    "iso:country":"AU",
    "sg:address":"169 King St",
    "sg:city":"Newcastle",
    "sg:classifiers":[
        {
            "category":"Banks & Credit Unions",
            "subcategory":"Financial Services",
            "type":"Services"
        }
    ],
    "sg:phone":"+61 2 4926 2130",
    "sg:postcode":"2300",
    "sg:province":"NSW",
    "sg:tags":[
        "annuity",
        "rollover",
        "superannuation",
        "consultant"
    ],
    "wof:name":"Guardian Financial Planning",
    "wof:placetype":"venue"
},
  "geometry": {"coordinates":[151.77706900000001,-32.927219],"type":"Point"}
}