{
  "type": "Feature",
  "properties": {
    "iso:country":"AU",
    "sg:address":"Suite 4, Playoust Bldg, Hawker Shops, Hawker Pl",
    "sg:city":"Hawker",
    "sg:classifiers":[
        {
            "category":"Health Services",
            "subcategory":"Health Practitioner",
            "type":"Services"
        }
    ],
    "sg:phone":"+61 2 6242 4390",
    "sg:postcode":"2614",
    "sg:province":"ACT",
    "sg:tags":[
        "psychologist"
    ],
    "wof:name":"Dal Molin Louisa",
    "wof:placetype":"venue"
},
  "geometry": {"coordinates":[149.04234314000001,-35.2431564331],"type":"Point"}
}