{
  "type": "Feature",
  "properties": {
    "addr:full":"District Hosptl McKee Drv Bega NSW 2550",
    "addr:postcode":"2550",
    "addr:street":"Mckee Drv",
    "iso:country":"AU",
    "sg:address":"District Hosptl McKee Drv",
    "sg:city":"Bega",
    "sg:classifiers":[
        {
            "category":"Social Services",
            "subcategory":"Child Care",
            "type":"Services"
        }
    ],
    "sg:phone":"+61 2 6492 9620",
    "sg:postcode":"2550",
    "sg:province":"NSW",
    "sg:tags":[
        "support",
        "health"
    ],
    "wof:name":"Early Childhood Clinic",
    "wof:placetype":"venue"
},
  "geometry": {"coordinates":[149.83857727,-36.6812477112],"type":"Point"}
}