{
  "type": "Feature",
  "properties": {
    "addr:full":"455 Campbelltown Rd Ingleburn NSW 2565",
    "addr:housenumber":"455",
    "addr:postcode":"2565",
    "addr:street":"Campbelltown Rd",
    "iso:country":"AU",
    "sg:address":"455 Campbelltown Rd",
    "sg:city":"Ingleburn",
    "sg:classifiers":[
        {
            "category":"Retail",
            "subcategory":"Auto Repair",
            "type":"Services"
        }
    ],
    "sg:phone":"+61 2 9829 4559",
    "sg:postcode":"2565",
    "sg:province":"NSW",
    "sg:tags":[
        "body",
        "builder",
        "motor"
    ],
    "wof:name":"Australian Kit Car",
    "wof:placetype":"venue"
},
  "geometry": {"coordinates":[150.84928894000001,-33.9795227051],"type":"Point"}
}