{
  "type": "Feature",
  "properties": {
    "iso:country":"AU",
    "sg:address":"15b Wharf Rd",
    "sg:city":"Birchgrove",
    "sg:classifiers":[
        {
            "category":"Building & Trades",
            "subcategory":"Landscaping Services",
            "type":"Services"
        }
    ],
    "sg:phone":"+61 2 9810 7805",
    "sg:postcode":"2041",
    "sg:province":"NSW",
    "sg:tags":[
        "consultant"
    ],
    "wof:name":"Planned Environment Pty Ltd",
    "wof:placetype":"venue"
},
  "geometry": {"coordinates":[151.186737,-33.851528],"type":"Point"}
}