{
  "type": "Feature",
  "properties": {
    "addr:full":"27 Kent St Richmond North VIC 3121",
    "addr:housenumber":"27",
    "addr:postcode":"3121",
    "addr:street":"Kent St",
    "iso:country":"AU",
    "sg:address":"27 Kent St",
    "sg:city":"Richmond North",
    "sg:classifiers":[
        {
            "category":"Building & Trades",
            "subcategory":"Cleaning & Sanitation",
            "type":"Services"
        }
    ],
    "sg:phone":"+61 3 9427 7117",
    "sg:postcode":"3121",
    "sg:province":"VIC",
    "sg:tags":[
        "industrial",
        "commercial",
        "contractor"
    ],
    "wof:name":"Class Cleaning Services",
    "wof:placetype":"venue"
},
  "geometry": {"coordinates":[145.00169372600001,-37.8145294189],"type":"Point"}
}