{
  "type": "Feature",
  "properties": {
    "iso:country":"AU",
    "sg:address":"1300 Centre Rd",
    "sg:city":"Clayton",
    "sg:classifiers":[
        {
            "category":"Personal",
            "subcategory":"Beauty Salon",
            "type":"Services"
        }
    ],
    "sg:phone":"+61 3 9544 6857",
    "sg:postcode":"3168",
    "sg:province":"VIC",
    "sg:tags":[
        "hairdresser"
    ],
    "wof:name":"Passion For Hair",
    "wof:placetype":"venue"
},
  "geometry": {"coordinates":[145.11570739699999,-37.9282226562],"type":"Point"}
}