{
  "type": "Feature",
  "properties": {
    "addr:full":"26 Elbow St West Kempsey NSW 2440",
    "addr:housenumber":"26",
    "addr:postcode":"2440",
    "addr:street":"Elbow St West",
    "iso:country":"AU",
    "sg:address":"26 Elbow St",
    "sg:city":"West Kempsey",
    "sg:classifiers":[
        {
            "category":"Health Services",
            "subcategory":"Doctor",
            "type":"Services"
        }
    ],
    "sg:phone":"+61 2 6562 6888",
    "sg:postcode":"2440",
    "sg:province":"NSW",
    "sg:tags":[
        "medical",
        "practitioner"
    ],
    "wof:name":"Ackerley Peter Dr",
    "wof:placetype":"venue"
},
  "geometry": {"coordinates":[152.83084099999999,-31.079756],"type":"Point"}
}