{
  "type": "Feature",
  "properties": {
    "addr:full":"64 Wing St Wingfield SA 5013",
    "addr:housenumber":"64",
    "addr:postcode":"5013",
    "addr:street":"Wing St",
    "iso:country":"AU",
    "sg:address":"64 Wing St",
    "sg:city":"Wingfield",
    "sg:classifiers":[
        {
            "category":"Professional",
            "subcategory":"Engineering",
            "type":"Services"
        }
    ],
    "sg:phone":"+61 418 814 697",
    "sg:postcode":"5013",
    "sg:province":"SA",
    "sg:tags":[
        "engineer"
    ],
    "wof:name":"Instant Metal Fabricators",
    "wof:placetype":"venue"
},
  "geometry": {"coordinates":[138.563995361,-34.8363876343],"type":"Point"}
}