{
  "type": "Feature",
  "properties": {
    "addr:full":"25A County Drv Cherrybrook NSW 2126",
    "addr:housenumber":"25a",
    "addr:postcode":"2126",
    "addr:street":"County Drv",
    "iso:country":"AU",
    "sg:address":"25A County Drv",
    "sg:city":"Cherrybrook",
    "sg:classifiers":[
        {
            "category":"Retail",
            "subcategory":"Driving School",
            "type":"Services"
        }
    ],
    "sg:phone":"+61 2 9634 8857",
    "sg:postcode":"2126",
    "sg:province":"NSW",
    "wof:name":"Accelerated",
    "wof:placetype":"venue"
},
  "geometry": {"coordinates":[151.02886962900001,-33.7307472229],"type":"Point"}
}