{
  "type": "Feature",
  "properties": {
    "addr:full":"14 Elwood Crt Craigie WA 6025",
    "addr:housenumber":"14",
    "addr:postcode":"6025",
    "addr:street":"Elwood Crt",
    "iso:country":"AU",
    "sg:address":"14 Elwood Crt",
    "sg:city":"Craigie",
    "sg:classifiers":[
        {
            "category":"Building & Trades",
            "subcategory":"Construction",
            "type":"Services"
        }
    ],
    "sg:phone":"+61 8 9401 6833",
    "sg:postcode":"6025",
    "sg:province":"WA",
    "sg:tags":[
        "fencing",
        "contractor"
    ],
    "wof:name":"J T Fencing",
    "wof:placetype":"venue"
},
  "geometry": {"coordinates":[115.768730164,-31.7838077545],"type":"Point"}
}