{
  "type": "Feature",
  "properties": {
    "addr:full":"38 Fletcher St Byron Bay NSW 2481",
    "addr:housenumber":"38",
    "addr:postcode":"2481",
    "addr:street":"Fletcher St",
    "iso:country":"AU",
    "sg:address":"38 Fletcher St",
    "sg:city":"Byron Bay",
    "sg:classifiers":[
        {
            "category":"Manufacturing",
            "subcategory":"Textiles",
            "type":"Manufacturing & Wholesale Goods"
        }
    ],
    "sg:phone":"+61 2 6685 7990",
    "sg:postcode":"2481",
    "sg:province":"NSW",
    "sg:tags":[
        "knitted",
        "woven",
        "fabric"
    ],
    "wof:name":"Byron Fabrics",
    "wof:placetype":"venue"
},
  "geometry": {"coordinates":[153.61340332,-28.6446838379],"type":"Point"}
}