{
  "type": "Feature",
  "properties": {
    "iso:country":"AU",
    "sg:address":"14 Browning St",
    "sg:city":"Tea Tree Gully",
    "sg:classifiers":[
        {
            "category":"Manufacturing",
            "subcategory":"Musical Instruments",
            "type":"Manufacturing & Wholesale Goods"
        }
    ],
    "sg:phone":"+61 8 8265 1872",
    "sg:postcode":"5091",
    "sg:province":"SA",
    "sg:tags":[
        "repair",
        "maker"
    ],
    "wof:name":"David S. Brown",
    "wof:placetype":"venue"
},
  "geometry": {"coordinates":[138.72096252399999,-34.8197441101],"type":"Point"}
}