{
  "type": "Feature",
  "properties": {
    "addr:full":"51 Murray St Lower Mitcham SA 5062",
    "addr:housenumber":"51",
    "addr:postcode":"5062",
    "addr:street":"Murray St",
    "iso:country":"AU",
    "sg:address":"51 Murray St",
    "sg:city":"Lower Mitcham",
    "sg:classifiers":[
        {
            "category":"Education",
            "subcategory":"Special Training",
            "type":"Public Place"
        }
    ],
    "sg:phone":"+61 8 8276 9961",
    "sg:postcode":"5062",
    "sg:province":"SA",
    "sg:tags":[
        "development"
    ],
    "wof:name":"With Good Company Pty Ltd",
    "wof:placetype":"venue"
},
  "geometry": {"coordinates":[138.604644775,-34.9852294922],"type":"Point"}
}