{
  "type": "Feature",
  "properties": {
    "iso:country":"AU",
    "sg:address":"14 Naomi Crt",
    "sg:city":"Bayswater",
    "sg:classifiers":[
        {
            "category":"Arts & Performance",
            "subcategory":"Theater",
            "type":"Entertainment"
        }
    ],
    "sg:phone":"+61 3 9720 7689",
    "sg:postcode":"3153",
    "sg:province":"VIC",
    "sg:tags":[
        "theatrical",
        "supply"
    ],
    "wof:name":"Corporate Production Services",
    "wof:placetype":"venue"
},
  "geometry": {"coordinates":[145.24635314899999,-37.8500862122],"type":"Point"}
}