{
  "type": "Feature",
  "properties": {
    "addr:full":"12 Deacon Ave Richmond SA 5033",
    "addr:housenumber":"12",
    "addr:postcode":"5033",
    "addr:street":"Deacon Ave",
    "iso:country":"AU",
    "sg:address":"12 Deacon Ave",
    "sg:city":"Richmond",
    "sg:classifiers":[
        {
            "category":"Food & Beverages",
            "subcategory":"Bakery",
            "type":"Retail Goods"
        }
    ],
    "sg:phone":"+61 8 8352 2899",
    "sg:postcode":"5033",
    "sg:province":"SA",
    "sg:tags":[
        "cake",
        "shop",
        "pastry"
    ],
    "wof:name":"Michel's Patisserie",
    "wof:placetype":"venue"
},
  "geometry": {"coordinates":[138.568893433,-34.939666748],"type":"Point"}
}