{
  "type": "Feature",
  "properties": {
    "addr:full":"Bago Rd Wauchope NSW 2446",
    "addr:postcode":"2446",
    "addr:street":"Bago Rd",
    "iso:country":"AU",
    "sg:address":"Bago Rd",
    "sg:city":"Wauchope",
    "sg:classifiers":[
        {
            "category":"Commercial Area",
            "type":"Public Place"
        }
    ],
    "sg:phone":"+61 2 6585 1807",
    "sg:postcode":"2446",
    "sg:province":"NSW",
    "sg:tags":[
        "heavy",
        "carrier"
    ],
    "wof:name":"Duck J R",
    "wof:placetype":"venue"
},
  "geometry": {"coordinates":[152.72854599999999,-31.485729],"type":"Point"}
}