{
  "type": "Feature",
  "properties": {
    "addr:full":"488 Goodwood Rd Cumberland Park SA 5041",
    "addr:housenumber":"488",
    "addr:postcode":"5041",
    "addr:street":"Goodwood Rd",
    "iso:country":"AU",
    "sg:address":"488 Goodwood Rd",
    "sg:city":"Cumberland Park",
    "sg:classifiers":[
        {
            "category":"Shopping",
            "subcategory":"Mobile Phones",
            "type":"Retail Goods"
        }
    ],
    "sg:phone":"+61 8 8373 5666",
    "sg:postcode":"5041",
    "sg:province":"SA",
    "sg:tags":[
        "telephone",
        "accessory"
    ],
    "wof:name":"Digical",
    "wof:placetype":"venue"
},
  "geometry": {"coordinates":[138.591385,-34.975761],"type":"Point"}
}