{
  "type": "Feature",
  "properties": {
    "addr:full":"16 Bethela St Camberwell VIC 3124",
    "addr:housenumber":"16",
    "addr:postcode":"3124",
    "addr:street":"Bethela St",
    "iso:country":"AU",
    "sg:address":"16 Bethela St",
    "sg:city":"Camberwell",
    "sg:classifiers":[
        {
            "category":"Real Estate",
            "subcategory":"Real Estate Services",
            "type":"Services"
        }
    ],
    "sg:phone":"+61 3 9809 1495",
    "sg:postcode":"3124",
    "sg:province":"VIC",
    "sg:tags":[
        "consultant",
        "property"
    ],
    "wof:name":"G R Woods Group Pty Ltd",
    "wof:placetype":"venue"
},
  "geometry": {"coordinates":[145.09042358400001,-37.847076416],"type":"Point"}
}