{
  "type": "Feature",
  "properties": {
    "addr:full":"9 Burgay Crt Osborne Park WA 6017",
    "addr:housenumber":"9",
    "addr:postcode":"6017",
    "addr:street":"Burgay Crt",
    "iso:country":"AU",
    "sg:address":"9 Burgay Crt",
    "sg:city":"Osborne Park",
    "sg:classifiers":[
        {
            "category":"Wholesale",
            "subcategory":"Apparel",
            "type":"Manufacturing & Wholesale Goods"
        }
    ],
    "sg:phone":"+61 8 9446 7535",
    "sg:postcode":"6017",
    "sg:province":"WA",
    "sg:tags":[
        "wholesaler",
        "mfrs",
        "uniform"
    ],
    "wof:name":"Shiny Pty Ltd",
    "wof:placetype":"venue"
},
  "geometry": {"coordinates":[115.803398132,-31.9065132141],"type":"Point"}
}