{
  "type": "Feature",
  "properties": {
    "addr:full":"7 Opel Ave Paralowie SA 5108",
    "addr:housenumber":"7",
    "addr:postcode":"5108",
    "addr:street":"Opel Ave",
    "iso:country":"AU",
    "sg:address":"7 Opel Ave",
    "sg:city":"Paralowie",
    "sg:classifiers":[
        {
            "category":"Building & Trades",
            "subcategory":"Construction",
            "type":"Services"
        }
    ],
    "sg:phone":"+61 411 502 069",
    "sg:postcode":"5108",
    "sg:province":"SA",
    "sg:tags":[
        "earth",
        "excavating",
        "moving",
        "contractor"
    ],
    "wof:name":"Wilton Earthmoving",
    "wof:placetype":"venue"
},
  "geometry": {"coordinates":[138.61859130900001,-34.7539024353],"type":"Point"}
}