{
  "type": "Feature",
  "properties": {
    "addr:full":"7 River St Macksville NSW 2447",
    "addr:housenumber":"7",
    "addr:postcode":"2447",
    "addr:street":"River St",
    "iso:country":"AU",
    "sg:address":"7 River St",
    "sg:city":"Macksville",
    "sg:classifiers":[
        {
            "category":"Home & Garden",
            "subcategory":"Household Appliances",
            "type":"Retail Goods"
        }
    ],
    "sg:phone":"+61 2 6568 1389",
    "sg:postcode":"2447",
    "sg:province":"NSW",
    "sg:tags":[
        "equipment",
        "gas"
    ],
    "wof:name":"Elwood Upholstery Pty Ltd",
    "wof:placetype":"venue"
},
  "geometry": {"coordinates":[152.91987599999999,-30.70632],"type":"Point"}
}