{
  "type": "Feature",
  "properties": {
    "addr:full":"54 Tudhoe St Wagin WA 6315",
    "addr:housenumber":"54",
    "addr:postcode":"6315",
    "addr:street":"Tudhoe St",
    "iso:country":"AU",
    "sg:address":"54 Tudhoe St",
    "sg:city":"Wagin",
    "sg:classifiers":[
        {
            "category":"Professional",
            "subcategory":"Business Services",
            "type":"Services"
        }
    ],
    "sg:phone":"+61 8 9861 1577",
    "sg:postcode":"6315",
    "sg:province":"WA",
    "sg:tags":[
        "broker"
    ],
    "wof:name":"Great Southern Real Estate",
    "wof:placetype":"venue"
},
  "geometry": {"coordinates":[117.344413757,-33.3087120056],"type":"Point"}
}