{
  "type": "Feature",
  "properties": {
    "addr:full":"136 Glen Osmond Rd Parkside SA 5063",
    "addr:housenumber":"136",
    "addr:postcode":"5063",
    "addr:street":"Glen Osmond Rd",
    "iso:country":"AU",
    "sg:address":"136 Glen Osmond Rd",
    "sg:city":"Parkside",
    "sg:classifiers":[
        {
            "category":"Home & Garden",
            "subcategory":"Household Appliances",
            "type":"Retail Goods"
        }
    ],
    "sg:phone":"+61 8 8271 9806",
    "sg:postcode":"5063",
    "sg:province":"SA",
    "sg:tags":[
        "heating",
        "system"
    ],
    "sg:website":"http://www.derbyheatbanks.com.au",
    "wof:name":"Derby Heat Banks",
    "wof:placetype":"venue"
},
  "geometry": {"coordinates":[138.62428283700001,-34.9459571838],"type":"Point"}
}