{
  "type": "Feature",
  "properties": {
    "addr:full":"Memorial Ave Salisbury SA 5108",
    "addr:postcode":"5108",
    "addr:street":"Ave",
    "iso:country":"AU",
    "sg:address":"Memorial Ave",
    "sg:city":"Salisbury",
    "sg:classifiers":[
        {
            "category":"Manufacturing",
            "subcategory":"Food",
            "type":"Manufacturing & Wholesale Goods"
        }
    ],
    "sg:phone":"+61 8 8285 9200",
    "sg:postcode":"5108",
    "sg:province":"SA",
    "sg:tags":[
        "function",
        "catering"
    ],
    "wof:name":"Annies Kitchen Catering Service",
    "wof:placetype":"venue"
},
  "geometry": {"coordinates":[138.642486572,-34.7657814026],"type":"Point"}
}