{
  "type": "Feature",
  "properties": {
    "iso:country":"AU",
    "sg:address":"Shed 3",
    "sg:city":", Traders Lane Manunda",
    "sg:classifiers":[
        {
            "category":"Shopping",
            "subcategory":"Clothing, Apparel, & Fashions",
            "type":"Retail Goods"
        }
    ],
    "sg:phone":"+61 7 4053 6400",
    "sg:postcode":"4870",
    "sg:province":"QLD",
    "sg:tags":[
        "uniform"
    ],
    "wof:name":"Cardzilla",
    "wof:placetype":"venue"
},
  "geometry": {"coordinates":[145.74989318900001,-16.9132595062],"type":"Point"}
}