{
  "type": "Feature",
  "properties": {
    "addr:full":"23 Emery Drv Dingley VIC 3172",
    "addr:housenumber":"23",
    "addr:postcode":"3172",
    "addr:street":"Emery Drv",
    "iso:country":"AU",
    "sg:address":"23 Emery Drv",
    "sg:city":"Dingley",
    "sg:classifiers":[
        {
            "category":"Real Estate",
            "subcategory":"Architect",
            "type":"Services"
        }
    ],
    "sg:phone":"+61 3 9551 6828",
    "sg:postcode":"3172",
    "sg:province":"VIC",
    "wof:name":"Duff Neville & Associates",
    "wof:placetype":"venue"
},
  "geometry": {"coordinates":[145.136810303,-37.9885864258],"type":"Point"}
}