{
  "type": "Feature",
  "properties": {
    "addr:full":"3/24 Mews Rd Fremantle WA 6160",
    "addr:housenumber":"/ 24",
    "addr:postcode":"6160",
    "addr:street":"Mews Rd",
    "iso:country":"AU",
    "sg:address":"3/24 Mews Rd",
    "sg:city":"Fremantle",
    "sg:classifiers":[
        {
            "category":"Manufacturing",
            "subcategory":"Motor Vehicles & Parts",
            "type":"Manufacturing & Wholesale Goods"
        }
    ],
    "sg:phone":"+61 8 9433 2300",
    "sg:postcode":"6160",
    "sg:province":"WA",
    "sg:tags":[
        "engine",
        "equipment",
        "diesel"
    ],
    "wof:name":"Power Equipment Pty Ltd",
    "wof:placetype":"venue"
},
  "geometry": {"coordinates":[115.747879,-32.060295],"type":"Point"}
}