{
  "type": "Feature",
  "properties": {
    "addr:full":"Lvl 7, Thakral House, 301 George St Sydney NSW 2000",
    "addr:housenumber":"301",
    "addr:postcode":"2000",
    "addr:street":"George St",
    "iso:country":"AU",
    "sg:address":"Lvl 7, Thakral House, 301 George St",
    "sg:city":"Sydney",
    "sg:classifiers":[
        {
            "category":"Banks & Credit Unions",
            "subcategory":"Financial Services",
            "type":"Services"
        }
    ],
    "sg:phone":"+61 2 8296 4999",
    "sg:postcode":"2000",
    "sg:province":"NSW",
    "sg:tags":[
        "planning"
    ],
    "wof:name":"Tasman Financial Planning Pty Ltd",
    "wof:placetype":"venue"
},
  "geometry": {"coordinates":[151.207107544,-33.8658294678],"type":"Point"}
}