{
  "type": "Feature",
  "properties": {
    "addr:full":"17 Vincent Ave Somerton Park SA 5044",
    "addr:housenumber":"17",
    "addr:postcode":"5044",
    "addr:street":"Vincent Ave Somerton",
    "iso:country":"AU",
    "sg:address":"17 Vincent Ave",
    "sg:city":"Somerton Park",
    "sg:classifiers":[
        {
            "category":"Personal",
            "subcategory":"Massage",
            "type":"Services"
        }
    ],
    "sg:phone":"+61 402 831 716",
    "sg:postcode":"5044",
    "sg:province":"SA",
    "sg:tags":[
        "therapy"
    ],
    "wof:name":"Dianne Bradey",
    "wof:placetype":"venue"
},
  "geometry": {"coordinates":[138.52456699999999,-34.99963],"type":"Point"}
}