{
  "type": "Feature",
  "properties": {
    "addr:full":"16 Aisha Crs Dingley Village VIC 3172",
    "addr:housenumber":"16",
    "addr:postcode":"3172",
    "addr:street":"Aisha Crs",
    "iso:country":"AU",
    "sg:address":"16 Aisha Crs",
    "sg:city":"Dingley Village",
    "sg:classifiers":[
        {
            "category":"Retail",
            "subcategory":"Auto Rental",
            "type":"Services"
        }
    ],
    "sg:phone":"+61 1300 730 164",
    "sg:postcode":"3172",
    "sg:province":"VIC",
    "sg:tags":[
        "chauffeur",
        "car",
        "hire",
        "driven",
        "limousine"
    ],
    "wof:name":"Airport Chauffeured Vehicles",
    "wof:placetype":"venue"
},
  "geometry": {"coordinates":[145.13380432100001,-37.9817695618],"type":"Point"}
}