{
  "type": "Feature",
  "properties": {
    "addr:full":"7 Greenbank Crt Lysterfield VIC 3156",
    "addr:housenumber":"7",
    "addr:postcode":"3156",
    "addr:street":"Greenbank Crt",
    "iso:country":"AU",
    "sg:address":"7 Greenbank Crt",
    "sg:city":"Lysterfield",
    "sg:classifiers":[
        {
            "category":"Building & Trades",
            "subcategory":"Pest Control",
            "type":"Services"
        }
    ],
    "sg:phone":"+61 3 9752 8010",
    "sg:postcode":"3156",
    "sg:province":"VIC",
    "wof:name":"South Eastern Pest Control",
    "wof:placetype":"venue"
},
  "geometry": {"coordinates":[145.27960205100001,-37.9181442261],"type":"Point"}
}