{
  "type": "Feature",
  "properties": {
    "addr:full":"Suite 8, Level 3, Como Centre 299 Toorak Road South Yarra VIC 3141",
    "addr:housenumber":"299",
    "addr:postcode":"3141",
    "addr:street":"Level;Toorak Road",
    "iso:country":"AU",
    "sg:address":"Suite 8, Level 3, Como Centre 299 Toorak Road",
    "sg:city":"South Yarra",
    "sg:classifiers":[
        {
            "category":"Banks & Credit Unions",
            "subcategory":"Investment Brokerage",
            "type":"Services"
        }
    ],
    "sg:phone":"+61 3 9826 9111",
    "sg:postcode":"3141",
    "sg:province":"VIC",
    "sg:tags":[
        "finance",
        "broker"
    ],
    "wof:name":"Thomson Finance Corp Pty Ltd",
    "wof:placetype":"venue"
},
  "geometry": {"coordinates":[144.99740600600001,-37.8395729065],"type":"Point"}
}