{
  "type": "Feature",
  "properties": {
    "addr:full":"389 Logan River Rd Bethania QLD 4205",
    "addr:housenumber":"389",
    "addr:postcode":"4205",
    "addr:street":"Logan River Rd",
    "iso:country":"AU",
    "sg:address":"389 Logan River Rd",
    "sg:city":"Bethania",
    "sg:classifiers":[
        {
            "category":"Banks & Credit Unions",
            "subcategory":"Financial Services",
            "type":"Services"
        }
    ],
    "sg:phone":"+61 403 071 173",
    "sg:postcode":"4205",
    "sg:province":"QLD",
    "sg:tags":[
        "loan",
        "finance",
        "mortgage"
    ],
    "wof:name":"Alan Revell",
    "wof:placetype":"venue"
},
  "geometry": {"coordinates":[153.15725707999999,-27.6980857849],"type":"Point"}
}