{
  "type": "Feature",
  "properties": {
    "iso:country":"AU",
    "sg:address":"7 Crown St",
    "sg:city":"Harris Park",
    "sg:classifiers":[
        {
            "category":"Professional",
            "subcategory":"Business Services",
            "type":"Services"
        }
    ],
    "sg:phone":"+61 2 9897 2233",
    "sg:postcode":"2150",
    "sg:province":"NSW",
    "sg:tags":[
        "drafting"
    ],
    "wof:name":"Realserve Pty Ltd",
    "wof:placetype":"venue"
},
  "geometry": {"coordinates":[151.01156616200001,-33.8230552673],"type":"Point"}
}