{
  "type": "Feature",
  "properties": {
    "addr:full":"201 Union Rd Surrey Hills VIC 3127",
    "addr:housenumber":"201",
    "addr:postcode":"3127",
    "addr:street":"Union Rd",
    "iso:country":"AU",
    "sg:address":"201 Union Rd",
    "sg:city":"Surrey Hills",
    "sg:classifiers":[
        {
            "category":"Health Services",
            "subcategory":"Doctor",
            "type":"Services"
        }
    ],
    "sg:phone":"+61 3 9890 6341",
    "sg:postcode":"3127",
    "sg:province":"VIC",
    "sg:tags":[
        "medical",
        "practitioner"
    ],
    "wof:name":"Mont Albert Medical Group",
    "wof:placetype":"venue"
},
  "geometry": {"coordinates":[145.098480225,-37.8203201294],"type":"Point"}
}