{
  "type": "Feature",
  "properties": {
    "iso:country":"AU",
    "sg:address":"7 Park Rd",
    "sg:city":"Cheltenham",
    "sg:classifiers":[
        {
            "category":"Utilities",
            "subcategory":"Electric",
            "type":"Services"
        }
    ],
    "sg:phone":"+61 3 9556 0230",
    "sg:postcode":"3192",
    "sg:province":"VIC",
    "sg:tags":[
        "element"
    ],
    "wof:name":"Helios Electroheat Pty Ltd",
    "wof:placetype":"venue"
},
  "geometry": {"coordinates":[145.038299561,-37.9631233215],"type":"Point"}
}