{
  "type": "Feature",
  "properties": {
    "addr:full":"225 Queensport Rd Murarrie QLD 4172",
    "addr:housenumber":"225",
    "addr:postcode":"4172",
    "addr:street":"Queensport Rd",
    "iso:country":"AU",
    "sg:address":"225 Queensport Rd",
    "sg:city":"Murarrie",
    "sg:classifiers":[
        {
            "category":"Professional",
            "subcategory":"Engineering",
            "type":"Services"
        }
    ],
    "sg:phone":"+61 7 3890 9400",
    "sg:postcode":"4172",
    "sg:province":"QLD",
    "sg:tags":[
        "refrigeration",
        "engineer"
    ],
    "wof:name":"Scantec",
    "wof:placetype":"venue"
},
  "geometry": {"coordinates":[153.10745239299999,-27.4504909515],"type":"Point"}
}