{
  "type": "Feature",
  "properties": {
    "addr:full":"PO Box 380 Hove SA 5048",
    "addr:postcode":"5048",
    "iso:country":"AU",
    "sg:address":"PO Box 380",
    "sg:city":"Hove",
    "sg:classifiers":[
        {
            "category":"Travel",
            "subcategory":"Bed & Breakfast",
            "type":"Entertainment"
        }
    ],
    "sg:phone":"+61 407 392 755",
    "sg:postcode":"5048",
    "sg:province":"SA",
    "sg:tags":[
        "control",
        "system",
        "wetting"
    ],
    "wof:name":"Reliables Australian Incontinence Pads",
    "wof:placetype":"venue"
},
  "geometry": {"coordinates":[138.52238500000001,-35.00964],"type":"Point"}
}