{
  "type": "Feature",
  "properties": {
    "addr:full":"Cnr Hills & Beare Rds Moonta SA 5558",
    "addr:postcode":"5558",
    "addr:street":"Cnr",
    "iso:country":"AU",
    "sg:address":"Cnr Hills & Beare Rds",
    "sg:city":"Moonta",
    "sg:classifiers":[
        {
            "category":"Utilities",
            "subcategory":"Refuse",
            "type":"Services"
        }
    ],
    "sg:phone":"+61 418 859 371",
    "sg:postcode":"5558",
    "sg:province":"SA",
    "sg:tags":[
        "remover",
        "rubbish"
    ],
    "wof:name":"Copper Coast Mini Skips",
    "wof:placetype":"venue"
},
  "geometry": {"coordinates":[137.60098266599999,-34.0625762939],"type":"Point"}
}