{
  "type": "Feature",
  "properties": {
    "addr:full":"917 Logan Rd Holland Park QLD 4121",
    "addr:housenumber":"917",
    "addr:postcode":"4121",
    "addr:street":"Logan Rd",
    "iso:country":"AU",
    "sg:address":"917 Logan Rd",
    "sg:city":"Holland Park",
    "sg:classifiers":[
        {
            "category":"Travel",
            "subcategory":"Hotels & Motels",
            "type":"Entertainment"
        }
    ],
    "sg:phone":"+61 7 3394 4422",
    "sg:postcode":"4121",
    "sg:province":"QLD",
    "wof:name":"Holland Park Motel",
    "wof:placetype":"venue"
},
  "geometry": {"coordinates":[153.06028747600001,-27.5185642242],"type":"Point"}
}