{
  "type": "Feature",
  "properties": {
    "addr:full":"Hume Hwy Picton NSW 2571",
    "addr:postcode":"2571",
    "addr:street":"Hume Hwy",
    "iso:country":"AU",
    "sg:address":"Hume Hwy",
    "sg:city":"Picton",
    "sg:classifiers":[
        {
            "category":"Education",
            "subcategory":"School",
            "type":"Public Place"
        }
    ],
    "sg:phone":"+61 2 4677 1261",
    "sg:postcode":"2571",
    "sg:province":"NSW",
    "wof:name":"Picton High",
    "wof:placetype":"venue"
},
  "geometry": {"coordinates":[150.68075561500001,-34.2173614502],"type":"Point"}
}