{
  "type": "Feature",
  "properties": {
    "addr:full":"114 Jerrold St Sherwood QLD 4075",
    "addr:housenumber":"114",
    "addr:postcode":"4075",
    "addr:street":"Jerrold St",
    "iso:country":"AU",
    "sg:address":"114 Jerrold St",
    "sg:city":"Sherwood",
    "sg:classifiers":[
        {
            "category":"Manufacturing",
            "subcategory":"Glass & Minerals",
            "type":"Manufacturing & Wholesale Goods"
        }
    ],
    "sg:phone":"+61 7 3278 1466",
    "sg:postcode":"4075",
    "sg:province":"QLD",
    "sg:tags":[
        "etching"
    ],
    "wof:name":"AnnaGraphic Designs Pty Ltd",
    "wof:placetype":"venue"
},
  "geometry": {"coordinates":[152.98739624000001,-27.5332565308],"type":"Point"}
}