{
  "type": "Feature",
  "properties": {
    "iso:country":"AU",
    "sg:address":"2/ 100 Terminus St",
    "sg:city":"Liverpool",
    "sg:classifiers":[
        {
            "category":"Social Services",
            "subcategory":"Job Training",
            "type":"Services"
        }
    ],
    "sg:phone":"+61 1300 764 473",
    "sg:postcode":"2170",
    "sg:province":"NSW",
    "sg:tags":[
        "hire",
        "computer",
        "leasing"
    ],
    "sg:website":"http://www.rentalplus.com.au",
    "wof:name":"Rental Plus",
    "wof:placetype":"venue"
},
  "geometry": {"coordinates":[150.922363281,-33.9265022278],"type":"Point"}
}