{
  "type": "Feature",
  "properties": {
    "addr:full":"Adcock Rd Beachmere QLD 4510",
    "addr:postcode":"4510",
    "addr:street":"Adcock Rd",
    "iso:country":"AU",
    "sg:address":"Adcock Rd",
    "sg:city":"Beachmere",
    "sg:classifiers":[
        {
            "category":"Home & Garden",
            "subcategory":"Building Materials",
            "type":"Retail Goods"
        }
    ],
    "sg:phone":"+61 7 5496 8528",
    "sg:postcode":"4510",
    "sg:province":"QLD",
    "sg:tags":[
        "fencing"
    ],
    "wof:name":"K.F.C. Kelson Fence Components",
    "wof:placetype":"venue"
},
  "geometry": {"coordinates":[153.03736900000001,-27.119421],"type":"Point"}
}