{
  "type": "Feature",
  "properties": {
    "addr:full":"68 Little Yarra Rd Yarra Junction VIC 3797",
    "addr:housenumber":"68",
    "addr:postcode":"3797",
    "addr:street":"Little Yarra Rd",
    "iso:country":"AU",
    "sg:address":"68 Little Yarra Rd",
    "sg:city":"Yarra Junction",
    "sg:classifiers":[
        {
            "category":"Professional",
            "subcategory":"Art Services",
            "type":"Services"
        }
    ],
    "sg:phone":"+61 3 5967 1823",
    "sg:postcode":"3797",
    "sg:province":"VIC",
    "sg:tags":[
        "decorator",
        "painter"
    ],
    "wof:name":"Berude John",
    "wof:placetype":"venue"
},
  "geometry": {"coordinates":[145.62086486800001,-37.7904052734],"type":"Point"}
}