{
  "type": "Feature",
  "properties": {
    "addr:full":"10 Strang Crt South Fremantle WA 6162",
    "addr:housenumber":"10",
    "addr:postcode":"6162",
    "addr:street":"Strang Crt",
    "iso:country":"AU",
    "sg:address":"10 Strang Crt",
    "sg:city":"South Fremantle",
    "sg:classifiers":[
        {
            "category":"Autos & Motor Vehicles",
            "subcategory":"Boat Sales",
            "type":"Retail Goods"
        }
    ],
    "sg:phone":"+61 8 9336 4492",
    "sg:postcode":"6162",
    "sg:province":"WA",
    "sg:tags":[
        "builder",
        "yacht",
        "repairer"
    ],
    "wof:name":"Exclusive Coatings",
    "wof:placetype":"venue"
},
  "geometry": {"coordinates":[115.759468,-32.072021],"type":"Point"}
}