{
  "type": "Feature",
  "properties": {
    "iso:country":"AU",
    "sg:address":"59 Casey St",
    "sg:city":"Orange",
    "sg:classifiers":[
        {
            "category":"Health Services",
            "subcategory":"Health Practitioner",
            "type":"Services"
        }
    ],
    "sg:phone":"+61 2 6362 5856",
    "sg:postcode":"2800",
    "sg:province":"NSW",
    "sg:tags":[
        "pathologist",
        "speech"
    ],
    "wof:name":"Cathie Matthews",
    "wof:placetype":"venue"
},
  "geometry": {"coordinates":[149.10197448700001,-33.2743415833],"type":"Point"}
}