{
  "type": "Feature",
  "properties": {
    "iso:country":"AU",
    "sg:address":"38 Pearse St",
    "sg:city":"North Fremantle",
    "sg:classifiers":[
        {
            "category":"Transit Center",
            "subcategory":"Freight",
            "type":"Transportation"
        }
    ],
    "sg:phone":"+61 8 9336 0900",
    "sg:postcode":"6159",
    "sg:province":"WA",
    "sg:tags":[
        "agent",
        "shipping"
    ],
    "wof:name":"Barwil Unitor Ships Service",
    "wof:placetype":"venue"
},
  "geometry": {"coordinates":[115.752022,-32.034275],"type":"Point"}
}