{
  "type": "Feature",
  "properties": {
    "iso:country":"AU",
    "sg:address":"191 North Bonville Rd",
    "sg:city":"Bonville",
    "sg:classifiers":[
        {
            "category":"Building & Trades",
            "subcategory":"Construction",
            "type":"Services"
        }
    ],
    "sg:phone":"+61 408 241 703",
    "sg:postcode":"2441",
    "sg:province":"NSW",
    "sg:tags":[
        "repairing",
        "window"
    ],
    "wof:name":"Wayne White Window Repairs",
    "wof:placetype":"venue"
},
  "geometry": {"coordinates":[153.02417,-30.361797],"type":"Point"}
}