{
  "type": "Feature",
  "properties": {
    "addr:full":"Shop 2 St Johns Ave Springvale VIC 3171",
    "addr:housenumber":"shop 2",
    "addr:postcode":"3171",
    "addr:street":"St Johns Ave",
    "iso:country":"AU",
    "sg:address":"Shop 2 St Johns Ave",
    "sg:city":"Springvale",
    "sg:classifiers":[
        {
            "category":"Communications",
            "subcategory":"Film & Video Production",
            "type":"Services"
        }
    ],
    "sg:phone":"+61 3 9574 6988",
    "sg:postcode":"3171",
    "sg:province":"VIC",
    "sg:tags":[
        "dvd",
        "library"
    ],
    "wof:name":"Vieng Mai",
    "wof:placetype":"venue"
},
  "geometry": {"coordinates":[145.150512695,-37.9485778809],"type":"Point"}
}