{
  "type": "Feature",
  "properties": {
    "iso:country":"AU",
    "sg:address":"Willmott Ave",
    "sg:city":"Winston Hills",
    "sg:classifiers":[
        {
            "category":"Building & Trades",
            "subcategory":"Cleaning & Sanitation",
            "type":"Services"
        }
    ],
    "sg:phone":"+61 412 168 727",
    "sg:postcode":"2153",
    "sg:province":"NSW",
    "sg:tags":[
        "commercial",
        "maintenance"
    ],
    "wof:name":"Xenmar Constractors",
    "wof:placetype":"venue"
},
  "geometry": {"coordinates":[150.98922729500001,-33.7776679993],"type":"Point"}
}