{
  "type": "Feature",
  "properties": {
    "addr:full":"106 Miller St West Melbourne VIC 3003",
    "addr:housenumber":"106",
    "addr:postcode":"3003",
    "addr:street":"Miller St",
    "iso:country":"AU",
    "sg:address":"106 Miller St",
    "sg:city":"West Melbourne",
    "sg:classifiers":[
        {
            "category":"Wholesale",
            "subcategory":"Apparel",
            "type":"Manufacturing & Wholesale Goods"
        }
    ],
    "sg:phone":"+61 3 9329 0911",
    "sg:postcode":"3003",
    "sg:province":"VIC",
    "sg:tags":[
        "wholesaler",
        "mfrs",
        "menswear"
    ],
    "wof:name":"Cook Dean & Co Pty Ltd",
    "wof:placetype":"venue"
},
  "geometry": {"coordinates":[144.94418335,-37.8053092957],"type":"Point"}
}