{
  "type": "Feature",
  "properties": {
    "addr:full":"132 Rowan St Wangaratta VIC 3677",
    "addr:housenumber":"132",
    "addr:postcode":"3677",
    "addr:street":"Rowan St",
    "iso:country":"AU",
    "sg:address":"132 Rowan St",
    "sg:city":"Wangaratta",
    "sg:classifiers":[
        {
            "category":"Building & Trades",
            "subcategory":"Locksmith",
            "type":"Services"
        }
    ],
    "sg:phone":"+61 3 5721 4932",
    "sg:postcode":"3677",
    "sg:province":"VIC",
    "sg:tags":[
        "strongroom",
        "safe",
        "door"
    ],
    "wof:name":"Lucky Howden Lock Supply",
    "wof:placetype":"venue"
},
  "geometry": {"coordinates":[146.31098938,-36.3503189087],"type":"Point"}
}