{
  "type": "Feature",
  "properties": {
    "iso:country":"AU",
    "sg:address":"Shp3/ 47 Railway Rd",
    "sg:city":"Kalamunda",
    "sg:classifiers":[
        {
            "category":"Shopping",
            "type":"Retail Goods"
        }
    ],
    "sg:phone":"+61 8 9293 3562",
    "sg:postcode":"6076",
    "sg:province":"WA",
    "sg:tags":[
        "new age",
        "product"
    ],
    "wof:name":"Ambrosium",
    "wof:placetype":"venue"
},
  "geometry": {"coordinates":[116.06012725799999,-31.9718990326],"type":"Point"}
}