{
  "type": "Feature",
  "properties": {
    "iso:country":"AU",
    "sg:address":"69 South Pine Rd",
    "sg:city":"Brendale",
    "sg:classifiers":[
        {
            "category":"Bars & Pubs",
            "subcategory":"Nightclub",
            "type":"Food & Drink"
        }
    ],
    "sg:phone":"+61 7 3205 7091",
    "sg:postcode":"4500",
    "sg:province":"QLD",
    "sg:tags":[
        "metal",
        "sprayer"
    ],
    "wof:name":"Spray-Tech Engineering",
    "wof:placetype":"venue"
},
  "geometry": {"coordinates":[152.98379516599999,-27.3268680573],"type":"Point"}
}