{
  "type": "Feature",
  "properties": {
    "addr:full":"82 Sudholz Rd Verrierdale QLD 4562",
    "addr:housenumber":"82",
    "addr:postcode":"4562",
    "addr:street":"Sudholz Rd",
    "iso:country":"AU",
    "sg:address":"82 Sudholz Rd",
    "sg:city":"Verrierdale",
    "sg:classifiers":[
        {
            "category":"Personal",
            "subcategory":"Massage",
            "type":"Services"
        }
    ],
    "sg:phone":"+61 7 5449 1813",
    "sg:postcode":"4562",
    "sg:province":"QLD",
    "sg:tags":[
        "therapy"
    ],
    "wof:name":"Niblett Technique",
    "wof:placetype":"venue"
},
  "geometry": {"coordinates":[152.99623107900001,-26.4905261993],"type":"Point"}
}