{
  "type": "Feature",
  "properties": {
    "iso:country":"AU",
    "sg:address":"14 Beddingfield St",
    "sg:city":"Picton",
    "sg:classifiers":[
        {
            "category":"Home & Garden",
            "subcategory":"Building Materials",
            "type":"Retail Goods"
        }
    ],
    "sg:phone":"+61 8 9726 2040",
    "sg:postcode":"6229",
    "sg:province":"WA",
    "sg:tags":[
        "supply"
    ],
    "wof:name":"Warrick Welding",
    "wof:placetype":"venue"
},
  "geometry": {"coordinates":[115.680862,-33.354782],"type":"Point"}
}