{
  "type": "Feature",
  "properties": {
    "addr:full":"6 Ballara Drv Wodonga VIC 3690",
    "addr:housenumber":"6",
    "addr:postcode":"3690",
    "addr:street":"Ballara Drv",
    "iso:country":"AU",
    "sg:address":"6 Ballara Drv",
    "sg:city":"Wodonga",
    "sg:classifiers":[
        {
            "category":"Home & Garden",
            "subcategory":"Building Materials",
            "type":"Retail Goods"
        }
    ],
    "sg:phone":"+61 2 6056 7779",
    "sg:postcode":"3690",
    "sg:province":"VIC",
    "sg:tags":[
        "lawn",
        "cutting",
        "maintenance"
    ],
    "wof:name":"Cloverleaf",
    "wof:placetype":"venue"
},
  "geometry": {"coordinates":[146.86317443900001,-36.1436691284],"type":"Point"}
}