{
  "type": "Feature",
  "properties": {
    "addr:full":"73 Carrington Rd Wahroonga NSW 2076",
    "addr:housenumber":"73",
    "addr:postcode":"2076",
    "addr:street":"Carrington Rd",
    "iso:country":"AU",
    "sg:address":"73 Carrington Rd",
    "sg:city":"Wahroonga",
    "sg:classifiers":[
        {
            "category":"Social Services",
            "subcategory":"Retirement Home",
            "type":"Services"
        }
    ],
    "sg:phone":"+61 2 9943 0009",
    "sg:postcode":"2076",
    "sg:province":"NSW",
    "sg:tags":[
        "environmental",
        "consultant",
        "pollution"
    ],
    "wof:name":"Otta International Pty Ltd",
    "wof:placetype":"venue"
},
  "geometry": {"coordinates":[151.126556397,-33.7080001831],"type":"Point"}
}