{
  "type": "Feature",
  "properties": {
    "addr:full":"Farm 1383 Griffith NSW 2680",
    "addr:housenumber":"1383",
    "addr:postcode":"2680",
    "iso:country":"AU",
    "sg:address":"Farm 1383",
    "sg:city":"Griffith",
    "sg:classifiers":[
        {
            "category":"Farming",
            "subcategory":"Orchard",
            "type":"Manufacturing & Wholesale Goods"
        }
    ],
    "sg:phone":"+61 2 6963 0034",
    "sg:postcode":"2680",
    "sg:province":"NSW",
    "sg:tags":[
        "citrus",
        "fruit",
        "grower"
    ],
    "wof:name":"Gatto G",
    "wof:placetype":"venue"
},
  "geometry": {"coordinates":[146.05032299999999,-34.28944],"type":"Point"}
}