{
  "type": "Feature",
  "properties": {
    "iso:country":"AU",
    "sg:address":"12 Gemini Pl",
    "sg:city":"Bridgeman Downs",
    "sg:classifiers":[
        {
            "category":"Building & Trades",
            "subcategory":"Construction",
            "type":"Services"
        }
    ],
    "sg:phone":"+61 7 3353 2477",
    "sg:postcode":"4035",
    "sg:province":"QLD",
    "sg:tags":[
        "contractor"
    ],
    "wof:name":"David Maguire",
    "wof:placetype":"venue"
},
  "geometry": {"coordinates":[152.98709099999999,-27.366135],"type":"Point"}
}