{
  "type": "Feature",
  "properties": {
    "addr:full":"46 Sydney St Marrickville NSW 2204",
    "addr:housenumber":"46",
    "addr:postcode":"2204",
    "addr:street":"Sydney St",
    "iso:country":"AU",
    "sg:address":"46 Sydney St",
    "sg:city":"Marrickville",
    "sg:classifiers":[
        {
            "category":"Manufacturing",
            "subcategory":"Furniture",
            "type":"Manufacturing & Wholesale Goods"
        }
    ],
    "sg:phone":"+61 2 9557 7130",
    "sg:postcode":"2204",
    "sg:province":"NSW",
    "sg:tags":[
        "builder",
        "designer",
        "custom"
    ],
    "wof:name":"Fresh Furniture",
    "wof:placetype":"venue"
},
  "geometry": {"coordinates":[151.16232299999999,-33.913441],"type":"Point"}
}