{
  "type": "Feature",
  "properties": {
    "iso:country":"AU",
    "sg:address":"Level 1, 158-160 Yarra St",
    "sg:city":"Warrandyte",
    "sg:classifiers":[
        {
            "category":"Banks & Credit Unions",
            "subcategory":"Financial Services",
            "type":"Services"
        }
    ],
    "sg:phone":"+61 3 9844 0300",
    "sg:postcode":"3113",
    "sg:province":"VIC",
    "sg:tags":[
        "planning"
    ],
    "wof:name":"Effective Wealth Managers",
    "wof:placetype":"venue"
},
  "geometry": {"coordinates":[145.21926879899999,-37.7379302979],"type":"Point"}
}