{
  "type": "Feature",
  "properties": {
    "addr:full":"22 Elliott St Midvale WA 6056",
    "addr:housenumber":"22",
    "addr:postcode":"6056",
    "addr:street":"Elliott St",
    "iso:country":"AU",
    "sg:address":"22 Elliott St",
    "sg:city":"Midvale",
    "sg:classifiers":[
        {
            "category":"Home & Garden",
            "subcategory":"Garden Supply",
            "type":"Retail Goods"
        }
    ],
    "sg:phone":"+61 8 9274 8388",
    "sg:postcode":"6056",
    "sg:province":"WA",
    "sg:tags":[
        "equipment",
        "hydroponics"
    ],
    "wof:name":"Greenfingers World Of Hydroponics",
    "wof:placetype":"venue"
},
  "geometry": {"coordinates":[116.03103637700001,-31.8938922882],"type":"Point"}
}