{
  "type": "Feature",
  "properties": {
    "iso:country":"AU",
    "sg:address":"Studios 2.3.4 - 76 Ferry Rd",
    "sg:city":"Southport",
    "sg:classifiers":[
        {
            "category":"Arts & Performance",
            "subcategory":"Dance",
            "type":"Entertainment"
        }
    ],
    "sg:phone":"+61 7 5591 8053",
    "sg:postcode":"4215",
    "sg:province":"QLD",
    "sg:tags":[
        "theatrical",
        "ballet",
        "tuition"
    ],
    "wof:name":"Anne Kingsford Academy Of Dance",
    "wof:placetype":"venue"
},
  "geometry": {"coordinates":[153.41151428200001,-27.9774608612],"type":"Point"}
}