{
  "type": "Feature",
  "properties": {
    "addr:full":"70 Sims Rd Bundaberg QLD 4670",
    "addr:housenumber":"70",
    "addr:postcode":"4670",
    "addr:street":"Sims Rd",
    "iso:country":"AU",
    "sg:address":"70 Sims Rd",
    "sg:city":"Bundaberg",
    "sg:classifiers":[
        {
            "category":"Retail",
            "subcategory":"Auto Repair",
            "type":"Services"
        }
    ],
    "sg:phone":"+61 7 4152 4499",
    "sg:postcode":"4670",
    "sg:province":"QLD",
    "sg:tags":[
        "transmission",
        "automotive",
        "car"
    ],
    "wof:name":"Devlin Eric",
    "wof:placetype":"venue"
},
  "geometry": {"coordinates":[152.36666870100001,-24.885471344],"type":"Point"}
}