{
  "type": "Feature",
  "properties": {
    "addr:full":"108 Cutler Rd Jandakot WA 6164",
    "addr:housenumber":"108",
    "addr:postcode":"6164",
    "addr:street":"Cutler Rd",
    "iso:country":"AU",
    "sg:address":"108 Cutler Rd",
    "sg:city":"Jandakot",
    "sg:classifiers":[
        {
            "category":"Wholesale",
            "subcategory":"Furniture",
            "type":"Manufacturing & Wholesale Goods"
        }
    ],
    "sg:phone":"+61 8 9417 9190",
    "sg:postcode":"6164",
    "sg:province":"WA",
    "sg:tags":[
        "wholesaler",
        "mfrs"
    ],
    "wof:name":"Ergoline Furniture Products",
    "wof:placetype":"venue"
},
  "geometry": {"coordinates":[115.86649300000001,-32.120041],"type":"Point"}
}