{
  "type": "Feature",
  "properties": {
    "addr:full":"11 Wreckyn St North Melbourne VIC 3051",
    "addr:housenumber":"11",
    "addr:postcode":"3051",
    "addr:street":"Wreckyn St",
    "iso:country":"AU",
    "sg:address":"11 Wreckyn St",
    "sg:city":"North Melbourne",
    "sg:classifiers":[
        {
            "category":"Real Estate",
            "subcategory":"Architect",
            "type":"Services"
        }
    ],
    "sg:phone":"+61 3 9326 6866",
    "sg:postcode":"3051",
    "sg:province":"VIC",
    "wof:name":"Latitude Architects",
    "wof:placetype":"venue"
},
  "geometry": {"coordinates":[144.95344543499999,-37.8006134033],"type":"Point"}
}