{
  "type": "Feature",
  "properties": {
    "addr:full":"15 Ninth Ave Austral NSW 2171",
    "addr:housenumber":"15",
    "addr:postcode":"2171",
    "addr:street":"Ninth Ave Austral",
    "iso:country":"AU",
    "sg:address":"15 Ninth Ave",
    "sg:city":"Austral",
    "sg:classifiers":[
        {
            "category":"Professional",
            "subcategory":"Accounting & Tax Preparation",
            "type":"Services"
        }
    ],
    "sg:phone":"+61 2 9606 9131",
    "sg:postcode":"2171",
    "sg:province":"NSW",
    "sg:tags":[
        "accountant",
        "auditor"
    ],
    "wof:name":"Power P J Accounting Pty Ltd",
    "wof:placetype":"venue"
},
  "geometry": {"coordinates":[150.817092895,-33.9364089966],"type":"Point"}
}