{
  "type": "Feature",
  "properties": {
    "addr:full":"455 Peel St Tamworth NSW 2340",
    "addr:housenumber":"455",
    "addr:postcode":"2340",
    "addr:street":"Peel St",
    "iso:country":"AU",
    "sg:address":"455 Peel St",
    "sg:city":"Tamworth",
    "sg:classifiers":[
        {
            "category":"Shopping",
            "subcategory":"Clothing, Apparel, & Fashions",
            "type":"Retail Goods"
        }
    ],
    "sg:phone":"+61 2 6766 7922",
    "sg:postcode":"2340",
    "sg:province":"NSW",
    "sg:tags":[
        "lady",
        "wear"
    ],
    "wof:name":"Possum Pink",
    "wof:placetype":"venue"
},
  "geometry": {"coordinates":[150.93170165999999,-31.0928401947],"type":"Point"}
}