{
  "type": "Feature",
  "properties": {
    "iso:country":"AU",
    "sg:address":"1st Floor 136 Edith St",
    "sg:city":"Wynnum",
    "sg:classifiers":[
        {
            "category":"Government",
            "subcategory":"Court House",
            "type":"Public Place"
        }
    ],
    "sg:phone":"+61 7 3396 4111",
    "sg:postcode":"4178",
    "sg:province":"QLD",
    "sg:tags":[
        "personal",
        "marriage",
        "family",
        "counselling"
    ],
    "wof:name":"Step By Step Counselling",
    "wof:placetype":"venue"
},
  "geometry": {"coordinates":[153.172973633,-27.4454975128],"type":"Point"}
}