{
  "type": "Feature",
  "properties": {
    "iso:country":"AU",
    "sg:address":"187 Kay St",
    "sg:city":"Traralgon",
    "sg:classifiers":[
        {
            "category":"Building & Trades",
            "subcategory":"Construction",
            "type":"Services"
        }
    ],
    "sg:phone":"+61 415 375 206",
    "sg:postcode":"3844",
    "sg:province":"VIC",
    "sg:tags":[
        "polishing",
        "sanding",
        "floor"
    ],
    "wof:name":"Valley Floor Sanding",
    "wof:placetype":"venue"
},
  "geometry": {"coordinates":[146.51673889200001,-38.1956863403],"type":"Point"}
}