{
  "type": "Feature",
  "properties": {
    "addr:full":"PO Box 347 Lindfield NSW 2070",
    "addr:postcode":"2070",
    "iso:country":"AU",
    "sg:address":"PO Box 347",
    "sg:city":"Lindfield",
    "sg:classifiers":[
        {
            "category":"Professional",
            "subcategory":"Management & Consulting",
            "type":"Services"
        }
    ],
    "sg:phone":"+61 2 9416 9690",
    "sg:postcode":"2070",
    "sg:province":"NSW",
    "sg:tags":[
        "consultant"
    ],
    "wof:name":"A B M Development Group Pty Ltd",
    "wof:placetype":"venue"
},
  "geometry": {"coordinates":[151.16867065400001,-33.775188446],"type":"Point"}
}