{
  "type": "Feature",
  "properties": {
    "iso:country":"AU",
    "sg:address":"Lvl 2/ 1 Pulteney St",
    "sg:city":"Taree",
    "sg:classifiers":[
        {
            "category":"Banks & Credit Unions",
            "subcategory":"Investment Brokerage",
            "type":"Services"
        }
    ],
    "sg:phone":"+61 2 6591 3444",
    "sg:postcode":"2430",
    "sg:province":"NSW",
    "sg:tags":[
        "finance",
        "broker"
    ],
    "wof:name":"Australian Brokers Centre",
    "wof:placetype":"venue"
},
  "geometry": {"coordinates":[152.459656,-31.914095],"type":"Point"}
}