{
  "type": "Feature",
  "properties": {
    "addr:full":"Union Rd Wandin North VIC 3139",
    "addr:postcode":"3139",
    "addr:street":"Union Rd",
    "iso:country":"AU",
    "sg:address":"Union Rd",
    "sg:city":"Wandin North",
    "sg:classifiers":[
        {
            "category":"Education",
            "subcategory":"Kindergarten",
            "type":"Public Place"
        }
    ],
    "sg:phone":"+61 3 5964 4532",
    "sg:postcode":"3139",
    "sg:province":"VIC",
    "sg:tags":[
        "pre-schools"
    ],
    "wof:name":"Wandin Pre-School Centre",
    "wof:placetype":"venue"
},
  "geometry": {"coordinates":[145.428009033,-37.7807426453],"type":"Point"}
}