{
  "type": "Feature",
  "properties": {
    "addr:full":"30 Eastwood Ave Eastwood NSW 2122",
    "addr:housenumber":"30",
    "addr:postcode":"2122",
    "addr:street":"Eastwood Ave",
    "iso:country":"AU",
    "sg:address":"30 Eastwood Ave",
    "sg:city":"Eastwood",
    "sg:classifiers":[
        {
            "category":"Professional",
            "subcategory":"Management & Consulting",
            "type":"Services"
        }
    ],
    "sg:phone":"+61 2 9874 2092",
    "sg:postcode":"2122",
    "sg:province":"NSW",
    "sg:tags":[
        "consultant"
    ],
    "wof:name":"A N Loizou & Associates",
    "wof:placetype":"venue"
},
  "geometry": {"coordinates":[151.08082580600001,-33.7844047546],"type":"Point"}
}