{
  "type": "Feature",
  "properties": {
    "addr:full":"1289 South Rd St Marys SA 5042",
    "addr:housenumber":"1289",
    "addr:postcode":"5042",
    "addr:street":"South Rd",
    "iso:country":"AU",
    "sg:address":"1289 South Rd",
    "sg:city":"St Marys",
    "sg:classifiers":[
        {
            "category":"Shopping",
            "subcategory":"Clothing, Apparel, & Fashions",
            "type":"Retail Goods"
        }
    ],
    "sg:phone":"+61 8 8177 0911",
    "sg:postcode":"5042",
    "sg:province":"SA",
    "sg:tags":[
        "maternity",
        "wear"
    ],
    "wof:name":"Sparrows Nest Maternity",
    "wof:placetype":"venue"
},
  "geometry": {"coordinates":[138.57603499999999,-35.005642],"type":"Point"}
}