{
  "type": "Feature",
  "properties": {
    "iso:country":"AU",
    "sg:address":"4 Queen St",
    "sg:city":"Busselton",
    "sg:classifiers":[
        {
            "category":"Professional",
            "subcategory":"Art Services",
            "type":"Services"
        }
    ],
    "sg:phone":"+61 8 9751 1345",
    "sg:postcode":"6280",
    "sg:province":"WA",
    "sg:tags":[
        "interior",
        "decorator"
    ],
    "wof:name":"Bibby Carol Leadlight",
    "wof:placetype":"venue"
},
  "geometry": {"coordinates":[115.343589783,-33.6473884583],"type":"Point"}
}