{
  "type": "Feature",
  "properties": {
    "addr:full":"Oatlands Rd Mt Barker WA 6324",
    "addr:postcode":"6324",
    "addr:street":"Oatlands Rd",
    "iso:country":"AU",
    "sg:address":"Oatlands Rd",
    "sg:city":"Mt Barker",
    "sg:classifiers":[
        {
            "category":"Education",
            "subcategory":"School",
            "type":"Public Place"
        }
    ],
    "sg:phone":"+61 8 9851 1132",
    "sg:postcode":"6324",
    "sg:province":"WA",
    "sg:tags":[
        "state",
        "except",
        "nsw"
    ],
    "wof:name":"Mount Barker Primary School",
    "wof:placetype":"venue"
},
  "geometry": {"coordinates":[117.666236877,-34.6307945251],"type":"Point"}
}