{
  "type": "Feature",
  "properties": {
    "iso:country":"AU",
    "sg:address":"Stephen St",
    "sg:city":"Booleroo Centre",
    "sg:classifiers":[
        {
            "category":"Deli",
            "type":"Food & Drink"
        }
    ],
    "sg:phone":"+61 8 8667 2010",
    "sg:postcode":"5482",
    "sg:province":"SA",
    "sg:tags":[
        "delicatessen"
    ],
    "wof:name":"Booleroo Bakery",
    "wof:placetype":"venue"
},
  "geometry": {"coordinates":[138.350403,-32.884167],"type":"Point"}
}