{
  "type": "Feature",
  "properties": {
    "addr:full":"29 Edgar St Yagoona NSW 2199",
    "addr:housenumber":"29",
    "addr:postcode":"2199",
    "addr:street":"Edgar St",
    "iso:country":"AU",
    "sg:address":"29 Edgar St",
    "sg:city":"Yagoona",
    "sg:classifiers":[
        {
            "category":"Retail",
            "subcategory":"Auto Rental",
            "type":"Services"
        }
    ],
    "sg:phone":"+61 2 9738 1590",
    "sg:postcode":"2199",
    "sg:province":"NSW",
    "sg:tags":[
        "chauffeur",
        "car",
        "hire",
        "driven",
        "limousine"
    ],
    "wof:name":"Axis Auto Rental Group",
    "wof:placetype":"venue"
},
  "geometry": {"coordinates":[151.015366,-33.908501],"type":"Point"}
}