{
  "type": "Feature",
  "properties": {
    "addr:full":"1 Scotland Rd Mile End SA 5031",
    "addr:housenumber":"1",
    "addr:postcode":"5031",
    "addr:street":"Scotland Rd",
    "iso:country":"AU",
    "sg:address":"1 Scotland Rd",
    "sg:city":"Mile End",
    "sg:classifiers":[
        {
            "category":"Building & Trades",
            "subcategory":"Construction",
            "type":"Services"
        }
    ],
    "sg:phone":"+61 8 8354 3133",
    "sg:postcode":"5031",
    "sg:province":"SA",
    "sg:tags":[
        "ceiling"
    ],
    "wof:name":"T W Ingham & Sons",
    "wof:placetype":"venue"
},
  "geometry": {"coordinates":[138.571868897,-34.9361915588],"type":"Point"}
}