{
  "type": "Feature",
  "properties": {
    "iso:country":"AU",
    "sg:address":"4 Riverwood Drv",
    "sg:city":"Bellmere",
    "sg:classifiers":[
        {
            "category":"Building & Trades",
            "subcategory":"Construction",
            "type":"Services"
        }
    ],
    "sg:phone":"+61 411 807 987",
    "sg:postcode":"4510",
    "sg:province":"QLD",
    "sg:tags":[
        "concrete",
        "contractor"
    ],
    "wof:name":"Vin Ford Concreting",
    "wof:placetype":"venue"
},
  "geometry": {"coordinates":[152.918182,-27.094563],"type":"Point"}
}