{
  "type": "Feature",
  "properties": {
    "addr:full":"1/ 57 Munibung Rd Cardiff NSW 2285",
    "addr:housenumber":"/ 57",
    "addr:postcode":"2285",
    "addr:street":"Munibung Rd",
    "iso:country":"AU",
    "sg:address":"1/ 57 Munibung Rd",
    "sg:city":"Cardiff",
    "sg:classifiers":[
        {
            "category":"Manufacturing",
            "subcategory":"Furniture",
            "type":"Manufacturing & Wholesale Goods"
        }
    ],
    "sg:phone":"+61 2 4953 6666",
    "sg:postcode":"2285",
    "sg:province":"NSW",
    "sg:tags":[
        "mfrs",
        "supply"
    ],
    "wof:name":"Lincoln Sentry",
    "wof:placetype":"venue"
},
  "geometry": {"coordinates":[151.64349365199999,-32.9423141479],"type":"Point"}
}