{
  "type": "Feature",
  "properties": {
    "iso:country":"AU",
    "sg:address":"Shop 66, Lake Haven Shopng Cntr",
    "sg:city":"Lake Haven",
    "sg:classifiers":[
        {
            "category":"Food & Beverages",
            "subcategory":"Specialty",
            "type":"Retail Goods"
        }
    ],
    "sg:phone":"+61 2 4393 2888",
    "sg:postcode":"2263",
    "sg:province":"NSW",
    "sg:tags":[
        "product",
        "health"
    ],
    "wof:name":"Go Vita Health & Sports Nutrition Centre",
    "wof:placetype":"venue"
},
  "geometry": {"coordinates":[151.496567,-33.248482],"type":"Point"}
}