{
  "type": "Feature",
  "properties": {
    "addr:full":"McCullough St Sunnybank QLD 4109",
    "addr:postcode":"4109",
    "addr:street":"Mccullough St",
    "iso:country":"AU",
    "sg:address":"McCullough St",
    "sg:city":"Sunnybank",
    "sg:classifiers":[
        {
            "category":"Cafe",
            "type":"Food & Drink"
        }
    ],
    "sg:phone":"+61 7 3345 8188",
    "sg:postcode":"4109",
    "sg:province":"QLD",
    "wof:name":"Cafe Les Amoureux",
    "wof:placetype":"venue"
},
  "geometry": {"coordinates":[153.06271362300001,-27.5717849731],"type":"Point"}
}