{
  "type": "Feature",
  "properties": {
    "addr:full":"PO Box 1342 Upwey VIC 3158",
    "addr:postcode":"3158",
    "iso:country":"AU",
    "sg:address":"PO Box 1342",
    "sg:city":"Upwey",
    "sg:classifiers":[
        {
            "category":"Wholesale",
            "subcategory":"Medical Equipment & Supplies",
            "type":"Manufacturing & Wholesale Goods"
        }
    ],
    "sg:phone":"+61 3 9752 6427",
    "sg:postcode":"3158",
    "sg:province":"VIC",
    "sg:tags":[
        "dental"
    ],
    "wof:name":"William Green Pty Ltd",
    "wof:placetype":"venue"
},
  "geometry": {"coordinates":[145.329956055,-37.9020690918],"type":"Point"}
}