{
  "type": "Feature",
  "properties": {
    "iso:country":"AU",
    "sg:address":"Blackwood Hospital Laffers Rd",
    "sg:city":"Blackwood",
    "sg:classifiers":[
        {
            "category":"Health Services",
            "subcategory":"Doctor",
            "type":"Services"
        }
    ],
    "sg:phone":"+61 8 8297 1476",
    "sg:postcode":"5051",
    "sg:province":"SA",
    "sg:tags":[
        "medical",
        "practitioner"
    ],
    "wof:name":"Silfverskiold Krister L",
    "wof:placetype":"venue"
},
  "geometry": {"coordinates":[138.62579345699999,-35.0062713623],"type":"Point"}
}