{
  "type": "Feature",
  "properties": {
    "iso:country":"AU",
    "sg:address":"44 Ranelagh Drv",
    "sg:city":"Mt Eliza",
    "sg:classifiers":[
        {
            "category":"Shopping",
            "subcategory":"Clothing, Apparel, & Fashions",
            "type":"Retail Goods"
        }
    ],
    "sg:phone":"+61 3 9787 3077",
    "sg:postcode":"3930",
    "sg:province":"VIC",
    "sg:tags":[
        "lady",
        "wear"
    ],
    "wof:name":"Elegance At 42",
    "wof:placetype":"venue"
},
  "geometry": {"coordinates":[145.08888244600001,-38.1839523315],"type":"Point"}
}