{
  "type": "Feature",
  "properties": {
    "addr:full":"45 Elizabeth St Melbourne VIC 3000",
    "addr:housenumber":"45",
    "addr:postcode":"3000",
    "addr:street":"Elizabeth St",
    "iso:country":"AU",
    "sg:address":"45 Elizabeth St",
    "sg:city":"Melbourne",
    "sg:classifiers":[
        {
            "category":"Banks & Credit Unions",
            "subcategory":"Bureau De Change",
            "type":"Services"
        }
    ],
    "sg:phone":"+61 1300 705 050",
    "sg:postcode":"3000",
    "sg:province":"VIC",
    "sg:tags":[
        "currency",
        "exchange",
        "foreign"
    ],
    "wof:name":"Xpress Money",
    "wof:placetype":"venue"
},
  "geometry": {"coordinates":[144.96429443400001,-37.8170318604],"type":"Point"}
}