{
  "type": "Feature",
  "properties": {
    "addr:full":"Milang Rd Strathalbyn SA 5255",
    "addr:postcode":"5255",
    "addr:street":"Milang Rd",
    "iso:country":"AU",
    "sg:address":"Milang Rd",
    "sg:city":"Strathalbyn",
    "sg:classifiers":[
        {
            "category":"Food & Beverages",
            "subcategory":"Fruits & Vegetables",
            "type":"Retail Goods"
        }
    ],
    "sg:phone":"+61 8 8537 0212",
    "sg:postcode":"5255",
    "sg:province":"SA",
    "sg:tags":[
        "grower"
    ],
    "wof:name":"McDonald Ray R & C I",
    "wof:placetype":"venue"
},
  "geometry": {"coordinates":[138.892333984,-35.2590713501],"type":"Point"}
}