{
  "type": "Feature",
  "properties": {
    "addr:full":"Cnr Princes Hwy & Traralgon-Maffra Rd Traralgon VIC 3844",
    "addr:postcode":"3844",
    "addr:street":"Cnr Princes Hwy & Traralgon-Maffra Rd",
    "iso:country":"AU",
    "sg:address":"Cnr Princes Hwy & Traralgon-Maffra Rd",
    "sg:city":"Traralgon",
    "sg:classifiers":[
        {
            "category":"Building & Trades",
            "subcategory":"Equipment Rental",
            "type":"Services"
        }
    ],
    "sg:phone":"+61 3 5176 2177",
    "sg:postcode":"3844",
    "sg:province":"VIC",
    "sg:tags":[
        "party",
        "hire"
    ],
    "wof:name":"Turner Hire",
    "wof:placetype":"venue"
},
  "geometry": {"coordinates":[146.541107178,-38.1958122253],"type":"Point"}
}