{
  "type": "Feature",
  "properties": {
    "addr:full":"625 Hampton St Brighton VIC 3186",
    "addr:housenumber":"625",
    "addr:postcode":"3186",
    "addr:street":"Hampton St",
    "iso:country":"AU",
    "sg:address":"625 Hampton St",
    "sg:city":"Brighton",
    "sg:classifiers":[
        {
            "category":"Education",
            "subcategory":"University",
            "type":"Public Place"
        }
    ],
    "sg:phone":"+61 3 9593 2633",
    "sg:postcode":"3186",
    "sg:province":"VIC",
    "sg:tags":[
        "sewing",
        "dressmaking",
        "tuition"
    ],
    "wof:name":"Bayside Sewing Centre",
    "wof:placetype":"venue"
},
  "geometry": {"coordinates":[145.003997803,-37.9285621643],"type":"Point"}
}