{
  "type": "Feature",
  "properties": {
    "addr:full":"PO Box 353 Smithfield West NSW 2164",
    "addr:postcode":"2164",
    "iso:country":"AU",
    "sg:address":"PO Box 353",
    "sg:city":"Smithfield West",
    "sg:classifiers":[
        {
            "category":"Utilities",
            "subcategory":"Electric",
            "type":"Services"
        }
    ],
    "sg:phone":"+61 414 298 444",
    "sg:postcode":"2164",
    "sg:province":"NSW",
    "sg:tags":[
        "electrical",
        "contractor"
    ],
    "wof:name":"Allstar Power Solutions",
    "wof:placetype":"venue"
},
  "geometry": {"coordinates":[150.92221069300001,-33.8508300781],"type":"Point"}
}