{
  "type": "Feature",
  "properties": {
    "addr:full":"43a Giblett St Manjimup WA 6258",
    "addr:housenumber":"43a",
    "addr:postcode":"6258",
    "addr:street":"Giblett St",
    "iso:country":"AU",
    "sg:address":"43a Giblett St",
    "sg:city":"Manjimup",
    "sg:classifiers":[
        {
            "category":"Cafe",
            "type":"Food & Drink"
        }
    ],
    "sg:phone":"+61 8 9771 2978",
    "sg:postcode":"6258",
    "sg:province":"WA",
    "wof:name":"Deja Vu Cafe",
    "wof:placetype":"venue"
},
  "geometry": {"coordinates":[116.145622253,-34.2425918579],"type":"Point"}
}