{
  "type": "Feature",
  "properties": {
    "addr:full":"Gieseman Rd Black River QLD 4818",
    "addr:postcode":"4818",
    "addr:street":"Gieseman Rd",
    "iso:country":"AU",
    "sg:address":"Gieseman Rd",
    "sg:city":"Black River",
    "sg:classifiers":[
        {
            "category":"Farming",
            "subcategory":"Nursery",
            "type":"Manufacturing & Wholesale Goods"
        }
    ],
    "sg:phone":"+61 418 798 023",
    "sg:postcode":"4818",
    "sg:province":"QLD",
    "wof:name":"Northern Tropical Plants",
    "wof:placetype":"venue"
},
  "geometry": {"coordinates":[146.616837,-19.255665],"type":"Point"}
}