{
  "type": "Feature",
  "properties": {
    "addr:full":"15 Finch St Malvern East VIC 3145",
    "addr:housenumber":"15",
    "addr:postcode":"3145",
    "addr:street":"Finch St",
    "iso:country":"AU",
    "sg:address":"15 Finch St",
    "sg:city":"Malvern East",
    "sg:classifiers":[
        {
            "category":"Retail",
            "subcategory":"Event Space",
            "type":"Services"
        }
    ],
    "sg:phone":"+61 3 9563 6108",
    "sg:postcode":"3145",
    "sg:province":"VIC",
    "sg:tags":[
        "venue",
        "reception",
        "wedding"
    ],
    "wof:name":"Gables The",
    "wof:placetype":"venue"
},
  "geometry": {"coordinates":[145.042694092,-37.873840332],"type":"Point"}
}