{
  "type": "Feature",
  "properties": {
    "addr:full":"38 James St Manunda QLD 4870",
    "addr:housenumber":"38",
    "addr:postcode":"4870",
    "addr:street":"James St",
    "iso:country":"AU",
    "sg:address":"38 James St",
    "sg:city":"Manunda",
    "sg:classifiers":[
        {
            "category":"Social Services",
            "subcategory":"Child Care",
            "type":"Services"
        }
    ],
    "sg:phone":"+61 7 4031 1095",
    "sg:postcode":"4870",
    "sg:province":"QLD",
    "wof:name":"ABC Manunda East",
    "wof:placetype":"venue"
},
  "geometry": {"coordinates":[145.756469727,-16.911277771],"type":"Point"}
}