{
  "type": "Feature",
  "properties": {
    "addr:full":"690 South Rd Moorabbin VIC 3189",
    "addr:housenumber":"690",
    "addr:postcode":"3189",
    "addr:street":"South Rd",
    "iso:country":"AU",
    "sg:address":"690 South Rd",
    "sg:city":"Moorabbin",
    "sg:classifiers":[
        {
            "category":"Retail",
            "subcategory":"Auto Repair",
            "type":"Services"
        }
    ],
    "sg:phone":"+61 3 9532 5558",
    "sg:postcode":"3189",
    "sg:province":"VIC",
    "sg:tags":[
        "testing",
        "inspection",
        "motor",
        "vehicle"
    ],
    "wof:name":"Four Be Four Serv",
    "wof:placetype":"venue"
},
  "geometry": {"coordinates":[145.07728576700001,-37.9387969971],"type":"Point"}
}