{
  "type": "Feature",
  "properties": {
    "iso:country":"AU",
    "sg:address":"Cnr Megalong & Govett Sts",
    "sg:city":"Katoomba",
    "sg:classifiers":[
        {
            "category":"Retail",
            "subcategory":"Auto Repair",
            "type":"Services"
        }
    ],
    "sg:phone":"+61 2 4782 3093",
    "sg:postcode":"2780",
    "sg:province":"NSW",
    "sg:tags":[
        "repairer",
        "motor",
        "engineer"
    ],
    "wof:name":"Brake Pro/Katoomba Brake & Clutch Service",
    "wof:placetype":"venue"
},
  "geometry": {"coordinates":[150.316574097,-33.7124557495],"type":"Point"}
}