{
  "type": "Feature",
  "properties": {
    "addr:full":"30 Church St Ryde NSW 2112",
    "addr:housenumber":"30",
    "addr:postcode":"2112",
    "addr:street":"Church St",
    "iso:country":"AU",
    "sg:address":"30 Church St",
    "sg:city":"Ryde",
    "sg:classifiers":[
        {
            "category":"Professional",
            "subcategory":"Accounting & Tax Preparation",
            "type":"Services"
        }
    ],
    "sg:phone":"+61 2 9807 3677",
    "sg:postcode":"2112",
    "sg:province":"NSW",
    "sg:tags":[
        "accountant",
        "auditor"
    ],
    "wof:name":"Evans John & Co Services Pty",
    "wof:placetype":"venue"
},
  "geometry": {"coordinates":[151.10536193900001,-33.8143577576],"type":"Point"}
}