{
  "type": "Feature",
  "properties": {
    "addr:full":"Paris Creek Rd Strathalbyn SA 5255",
    "addr:postcode":"5255",
    "addr:street":"Creek Rd",
    "iso:country":"AU",
    "sg:address":"Paris Creek Rd",
    "sg:city":"Strathalbyn",
    "sg:classifiers":[
        {
            "category":"Farming",
            "subcategory":"Farm",
            "type":"Manufacturing & Wholesale Goods"
        }
    ],
    "sg:phone":"+61 8 8536 2017",
    "sg:postcode":"5255",
    "sg:province":"SA",
    "sg:tags":[
        "farmer"
    ],
    "wof:name":"Rankine R J & J M",
    "wof:placetype":"venue"
},
  "geometry": {"coordinates":[138.88406372099999,-35.2509765625],"type":"Point"}
}