{
  "type": "Feature",
  "properties": {
    "iso:country":"AU",
    "sg:address":"54 Playford Ave",
    "sg:city":"Whyalla",
    "sg:classifiers":[
        {
            "category":"Utilities",
            "type":"Services"
        }
    ],
    "sg:phone":"+61 8 8645 5711",
    "sg:postcode":"5600",
    "sg:province":"SA",
    "sg:tags":[
        "equipment",
        "towing"
    ],
    "wof:name":"Huey's AutoPro",
    "wof:placetype":"venue"
},
  "geometry": {"coordinates":[137.56791699999999,-33.030079],"type":"Point"}
}