{
  "type": "Feature",
  "properties": {
    "iso:country":"AU",
    "sg:address":"88 Davidson St",
    "sg:city":"Deniliquin",
    "sg:classifiers":[
        {
            "category":"Autos & Motor Vehicles",
            "subcategory":"Auto Supplies",
            "type":"Retail Goods"
        }
    ],
    "sg:phone":"+61 3 5881 7742",
    "sg:postcode":"2710",
    "sg:province":"NSW",
    "sg:tags":[
        "equipment",
        "part",
        "truck"
    ],
    "wof:name":"Truck Connections",
    "wof:placetype":"venue"
},
  "geometry": {"coordinates":[144.97457885700001,-35.5267868042],"type":"Point"}
}