{
  "type": "Feature",
  "properties": {
    "iso:country":"AU",
    "sg:address":"Cnr Farrall & Runyon Rds",
    "sg:city":"Midvale",
    "sg:classifiers":[
        {
            "category":"Shopping",
            "subcategory":"Computers & Home Electronics",
            "type":"Retail Goods"
        }
    ],
    "sg:phone":"+61 8 9250 1234",
    "sg:postcode":"6056",
    "sg:province":"WA",
    "sg:tags":[
        "hardware",
        "equipment"
    ],
    "wof:name":"A A Technology Repair Centre",
    "wof:placetype":"venue"
},
  "geometry": {"coordinates":[116.033447266,-31.8854217529],"type":"Point"}
}