{
  "type": "Feature",
  "properties": {
    "iso:country":"AU",
    "sg:address":"4 Judd St",
    "sg:city":"South Perth",
    "sg:classifiers":[
        {
            "category":"Insurance",
            "subcategory":"Insurance Agent",
            "type":"Services"
        }
    ],
    "sg:phone":"+61 1800 111 456",
    "sg:postcode":"6151",
    "sg:province":"WA",
    "sg:tags":[
        "broker"
    ],
    "wof:name":"Insurance Watch",
    "wof:placetype":"venue"
},
  "geometry": {"coordinates":[115.848869,-31.973331],"type":"Point"}
}