{
  "type": "Feature",
  "properties": {
    "addr:full":"497 Maroondah Hwy Mitcham VIC 3132",
    "addr:housenumber":"497",
    "addr:postcode":"3132",
    "addr:street":"Maroondah Hwy",
    "iso:country":"AU",
    "sg:address":"497 Maroondah Hwy",
    "sg:city":"Mitcham",
    "sg:classifiers":[
        {
            "category":"Fast Food",
            "type":"Food & Drink"
        }
    ],
    "sg:phone":"+61 3 9872 6119",
    "sg:postcode":"3132",
    "sg:province":"VIC",
    "sg:tags":[
        "away",
        "take"
    ],
    "wof:name":"Golden Hen Chicken Bar",
    "wof:placetype":"venue"
},
  "geometry": {"coordinates":[145.25190734899999,-37.7991600037],"type":"Point"}
}