{
  "type": "Feature",
  "properties": {
    "addr:full":"60 Alfred Rd Brookvale NSW 2100",
    "addr:housenumber":"60",
    "addr:postcode":"2100",
    "addr:street":"Alfred Rd",
    "iso:country":"AU",
    "sg:address":"60 Alfred Rd",
    "sg:city":"Brookvale",
    "sg:classifiers":[
        {
            "category":"Retail",
            "subcategory":"Driving School",
            "type":"Services"
        }
    ],
    "sg:phone":"+61 421 780 957",
    "sg:postcode":"2100",
    "sg:province":"NSW",
    "wof:name":"Triple S Driving School",
    "wof:placetype":"venue"
},
  "geometry": {"coordinates":[151.27244567899999,-33.7579345703],"type":"Point"}
}