{
  "type": "Feature",
  "properties": {
    "iso:country":"AU",
    "sg:address":"Eagle St",
    "sg:city":"Pier Brisbane",
    "sg:classifiers":[
        {
            "category":"Restaurant",
            "type":"Food & Drink"
        }
    ],
    "sg:phone":"+61 7 3211 9944",
    "sg:postcode":"4000",
    "sg:province":"QLD",
    "sg:website":"http://www.boutiquevenues.com.au",
    "wof:name":"Cha Cha Char",
    "wof:placetype":"venue"
},
  "geometry": {"coordinates":[153.03103637699999,-27.4688396454],"type":"Point"}
}