{
  "type": "Feature",
  "properties": {
    "addr:full":"402 South St Ballarat VIC 3350",
    "addr:housenumber":"402",
    "addr:postcode":"3350",
    "addr:street":"South St",
    "iso:country":"AU",
    "sg:address":"402 South St",
    "sg:city":"Ballarat",
    "sg:classifiers":[
        {
            "category":"Travel",
            "subcategory":"Hotels & Motels",
            "type":"Entertainment"
        }
    ],
    "sg:phone":"+61 3 5331 5373",
    "sg:postcode":"3350",
    "sg:province":"VIC",
    "sg:tags":[
        "accommodation"
    ],
    "wof:name":"Royal Oak Hotel",
    "wof:placetype":"venue"
},
  "geometry": {"coordinates":[143.84866299999999,-37.569336],"type":"Point"}
}