{
  "type": "Feature",
  "properties": {
    "iso:country":"AU",
    "sg:address":"Shop 41 Rockingham Shopng Cntr",
    "sg:city":"Rockingham",
    "sg:classifiers":[
        {
            "category":"Cafe",
            "type":"Food & Drink"
        }
    ],
    "sg:phone":"+61 8 9527 3057",
    "sg:postcode":"6168",
    "sg:province":"WA",
    "wof:name":"Toledo Coffee Lounge",
    "wof:placetype":"venue"
},
  "geometry": {"coordinates":[115.741028,-32.280399],"type":"Point"}
}