{
  "type": "Feature",
  "properties": {
    "addr:full":"Centrepoint 270 Ross River Rd Aitkenvale QLD 4814",
    "addr:housenumber":"270",
    "addr:postcode":"4814",
    "addr:street":"Ross River Rd",
    "iso:country":"AU",
    "sg:address":"Centrepoint 270 Ross River Rd",
    "sg:city":"Aitkenvale",
    "sg:classifiers":[
        {
            "category":"Banks & Credit Unions",
            "subcategory":"Investment Brokerage",
            "type":"Services"
        }
    ],
    "sg:phone":"+61 7 4725 2525",
    "sg:postcode":"4814",
    "sg:province":"QLD",
    "sg:tags":[
        "management",
        "property"
    ],
    "wof:name":"Aitkenvale Real Estate",
    "wof:placetype":"venue"
},
  "geometry": {"coordinates":[146.76809700000001,-19.297043],"type":"Point"}
}