{
  "type": "Feature",
  "properties": {
    "iso:country":"AU",
    "sg:address":"294 Mt Alexander Rd",
    "sg:city":"Ascot Vale",
    "sg:classifiers":[
        {
            "category":"Professional",
            "subcategory":"Accounting & Tax Preparation",
            "type":"Services"
        }
    ],
    "sg:phone":"+61 3 9326 1177",
    "sg:postcode":"3032",
    "sg:province":"VIC",
    "sg:tags":[
        "accountant",
        "auditor"
    ],
    "wof:name":"O&#039;Connor Joanna",
    "wof:placetype":"venue"
},
  "geometry": {"coordinates":[144.929657,-37.777653],"type":"Point"}
}