{
  "type": "Feature",
  "properties": {
    "iso:country":"AU",
    "sg:address":"Cnr College Ave & Burra Pl",
    "sg:city":"Shellharbour City Cntr Shellharbour",
    "sg:classifiers":[
        {
            "category":"Autos & Motor Vehicles",
            "subcategory":"Auto Supplies",
            "type":"Retail Goods"
        }
    ],
    "sg:phone":"+61 2 4296 7637",
    "sg:postcode":"2529",
    "sg:province":"NSW",
    "sg:tags":[
        "part",
        "cycles",
        "accessory"
    ],
    "wof:name":"Detour Dirt and Snow Casual Wear",
    "wof:placetype":"venue"
},
  "geometry": {"coordinates":[150.83439636200001,-34.5736808777],"type":"Point"}
}