{
  "type": "Feature",
  "properties": {
    "addr:full":"17 Harper St Redwood Park SA 5097",
    "addr:housenumber":"17",
    "addr:postcode":"5097",
    "addr:street":"Harper St",
    "iso:country":"AU",
    "sg:address":"17 Harper St",
    "sg:city":"Redwood Park",
    "sg:classifiers":[
        {
            "category":"Building & Trades",
            "subcategory":"Construction",
            "type":"Services"
        }
    ],
    "sg:phone":"+61 8 8251 1693",
    "sg:postcode":"5097",
    "sg:province":"SA",
    "sg:tags":[
        "home",
        "air conditioning"
    ],
    "wof:name":"Project Air Flow Pty Ltd",
    "wof:placetype":"venue"
},
  "geometry": {"coordinates":[138.70472717300001,-34.8079338074],"type":"Point"}
}