{
  "type": "Feature",
  "properties": {
    "addr:full":"7 Jetty St Grange SA 5022",
    "addr:housenumber":"7",
    "addr:postcode":"5022",
    "addr:street":"Jetty St",
    "iso:country":"AU",
    "sg:address":"7 Jetty St",
    "sg:city":"Grange",
    "sg:classifiers":[
        {
            "category":"Health Services",
            "subcategory":"Dentist",
            "type":"Services"
        }
    ],
    "sg:phone":"+61 8 8353 8221",
    "sg:postcode":"5022",
    "sg:province":"SA",
    "wof:name":"Grange Jetty Street Denture & Dental Clinic",
    "wof:placetype":"venue"
},
  "geometry": {"coordinates":[138.49139404300001,-34.9025268555],"type":"Point"}
}