{
  "type": "Feature",
  "properties": {
    "addr:full":"Unit 4 105 Lobb St Ipswich QLD 4305",
    "addr:housenumber":"105",
    "addr:postcode":"4305",
    "addr:street":"Lobb St",
    "iso:country":"AU",
    "sg:address":"Unit 4 105 Lobb St",
    "sg:city":"Ipswich",
    "sg:classifiers":[
        {
            "category":"Manufacturing",
            "subcategory":"Motor Vehicles & Parts",
            "type":"Manufacturing & Wholesale Goods"
        }
    ],
    "sg:phone":"+61 7 3281 1137",
    "sg:postcode":"4305",
    "sg:province":"QLD",
    "sg:tags":[
        "replacement"
    ],
    "wof:name":"CV Joints Ipswich",
    "wof:placetype":"venue"
},
  "geometry": {"coordinates":[152.747879028,-27.6316814423],"type":"Point"}
}