{
  "type": "Feature",
  "properties": {
    "addr:full":"27 Day St Bendigo VIC 3550",
    "addr:housenumber":"27",
    "addr:postcode":"3550",
    "addr:street":"Day St",
    "iso:country":"AU",
    "sg:address":"27 Day St",
    "sg:city":"Bendigo",
    "sg:classifiers":[
        {
            "category":"Building & Trades",
            "subcategory":"Cleaning & Sanitation",
            "type":"Services"
        }
    ],
    "sg:phone":"+61 411 533 161",
    "sg:postcode":"3550",
    "sg:province":"VIC",
    "sg:tags":[
        "industrial",
        "commercial",
        "contractor"
    ],
    "wof:name":"Peter Camm",
    "wof:placetype":"venue"
},
  "geometry": {"coordinates":[144.299728394,-36.7515296936],"type":"Point"}
}