{
  "type": "Feature",
  "properties": {
    "addr:full":"Unit 3/ 43A Connaught Crs West Launceston TAS 7250",
    "addr:housenumber":"/ 43a",
    "addr:postcode":"7250",
    "addr:street":"Connaught Crs West",
    "iso:country":"AU",
    "sg:address":"Unit 3/ 43A Connaught Crs",
    "sg:city":"West Launceston",
    "sg:classifiers":[
        {
            "category":"Farming",
            "subcategory":"Dairy Farm",
            "type":"Manufacturing & Wholesale Goods"
        }
    ],
    "sg:phone":"+61 3 6334 0069",
    "sg:postcode":"7250",
    "sg:province":"TAS",
    "sg:tags":[
        "wholesaler",
        "product",
        "mfrs"
    ],
    "wof:name":"Yakult Australia Pty Ltd",
    "wof:placetype":"venue"
},
  "geometry": {"coordinates":[147.135894775,-41.4512176514],"type":"Point"}
}