{
  "type": "Feature",
  "properties": {
    "addr:full":"Shop 4, 66 Spit Rd Spit Junction NSW 2088",
    "addr:housenumber":"shop;66",
    "addr:postcode":"2088",
    "addr:street":"Spit Rd",
    "iso:country":"AU",
    "sg:address":"Shop 4, 66 Spit Rd",
    "sg:city":"Spit Junction",
    "sg:classifiers":[
        {
            "category":"Shopping",
            "subcategory":"Clothing, Apparel, & Fashions",
            "type":"Retail Goods"
        }
    ],
    "sg:phone":"+61 2 9960 2694",
    "sg:postcode":"2088",
    "sg:province":"NSW",
    "sg:tags":[
        "hire",
        "men's",
        "wear",
        "formal"
    ],
    "wof:name":"Rosemont Big Night Out Formal Hire",
    "wof:placetype":"venue"
},
  "geometry": {"coordinates":[151.24252319300001,-33.8232574463],"type":"Point"}
}