{
  "type": "Feature",
  "properties": {
    "addr:full":"3 Grevillea Pl Kenthurst NSW 2156",
    "addr:housenumber":"3",
    "addr:postcode":"2156",
    "addr:street":"Grevillea Pl",
    "iso:country":"AU",
    "sg:address":"3 Grevillea Pl",
    "sg:city":"Kenthurst",
    "sg:classifiers":[
        {
            "category":"Building & Trades",
            "subcategory":"Plumbing",
            "type":"Services"
        }
    ],
    "sg:phone":"+61 2 9654 8454",
    "sg:postcode":"2156",
    "sg:province":"NSW",
    "sg:tags":[
        "plumber",
        "gasfitters"
    ],
    "wof:name":"Holland Geoff",
    "wof:placetype":"venue"
},
  "geometry": {"coordinates":[150.973342895,-33.6604347229],"type":"Point"}
}