{
  "type": "Feature",
  "properties": {
    "addr:full":"131 Seebeck Rd Rowville VIC 3178",
    "addr:housenumber":"131",
    "addr:postcode":"3178",
    "addr:street":"Seebeck Rd",
    "iso:country":"AU",
    "sg:address":"131 Seebeck Rd",
    "sg:city":"Rowville",
    "sg:classifiers":[
        {
            "category":"Building & Trades",
            "subcategory":"Construction",
            "type":"Services"
        }
    ],
    "sg:phone":"+61 3 9795 1696",
    "sg:postcode":"3178",
    "sg:province":"VIC",
    "sg:tags":[
        "contractor"
    ],
    "wof:name":"Cranston N J",
    "wof:placetype":"venue"
},
  "geometry": {"coordinates":[145.220626831,-37.9363517761],"type":"Point"}
}