{
  "type": "Feature",
  "properties": {
    "addr:full":"36 Grehan Crs Beenleigh QLD 4207",
    "addr:housenumber":"36",
    "addr:postcode":"4207",
    "addr:street":"Grehan Crs",
    "iso:country":"AU",
    "sg:address":"36 Grehan Crs",
    "sg:city":"Beenleigh",
    "sg:classifiers":[
        {
            "category":"Professional",
            "subcategory":"Printing & Photocopies",
            "type":"Services"
        }
    ],
    "sg:phone":"+61 7 3382 6289",
    "sg:postcode":"4207",
    "sg:province":"QLD",
    "sg:tags":[
        "photocopier"
    ],
    "wof:name":"Photon Copiers",
    "wof:placetype":"venue"
},
  "geometry": {"coordinates":[153.186965942,-27.7139492035],"type":"Point"}
}