{
  "type": "Feature",
  "properties": {
    "iso:country":"AU",
    "sg:address":"111 Dudley Rd",
    "sg:city":"Whitebridge",
    "sg:classifiers":[
        {
            "category":"Utilities",
            "subcategory":"Water",
            "type":"Services"
        }
    ],
    "sg:phone":"+61 2 4942 3518",
    "sg:postcode":"2290",
    "sg:province":"NSW",
    "sg:tags":[
        "hot",
        "system"
    ],
    "wof:name":"JE Electrical",
    "wof:placetype":"venue"
},
  "geometry": {"coordinates":[151.70831298799999,-32.9785003662],"type":"Point"}
}