{
  "type": "Feature",
  "properties": {
    "iso:country":"AU",
    "sg:address":"52 Carter St",
    "sg:city":"Cammeray",
    "sg:classifiers":[
        {
            "category":"Personal",
            "type":"Services"
        }
    ],
    "sg:phone":"+61 2 9953 2508",
    "sg:postcode":"2062",
    "sg:province":"NSW",
    "sg:tags":[
        "dressmaker"
    ],
    "wof:name":"Geor L",
    "wof:placetype":"venue"
},
  "geometry": {"coordinates":[151.22074890100001,-33.8215408325],"type":"Point"}
}