{
  "type": "Feature",
  "properties": {
    "iso:country":"AU",
    "sg:address":"13 Childers St",
    "sg:city":"Cranbourne",
    "sg:classifiers":[
        {
            "category":"Health Services",
            "subcategory":"Health Practitioner",
            "type":"Services"
        }
    ],
    "sg:phone":"+61 3 5996 1688",
    "sg:postcode":"3977",
    "sg:province":"VIC",
    "sg:tags":[
        "physiotherapist"
    ],
    "wof:name":"Cranbourne Central Physiotherapy",
    "wof:placetype":"venue"
},
  "geometry": {"coordinates":[145.28424072300001,-38.111831665],"type":"Point"}
}