{
  "type": "Feature",
  "properties": {
    "iso:country":"AU",
    "sg:address":"5 Marcia Ave",
    "sg:city":"Gilles Plains",
    "sg:classifiers":[
        {
            "category":"Manufacturing",
            "subcategory":"Wood Products",
            "type":"Manufacturing & Wholesale Goods"
        }
    ],
    "sg:phone":"+61 8 8266 0104",
    "sg:postcode":"5086",
    "sg:province":"SA",
    "sg:tags":[
        "polisher",
        "french"
    ],
    "wof:name":"Mario Faugno French Polishers",
    "wof:placetype":"venue"
},
  "geometry": {"coordinates":[138.65992736800001,-34.8543243408],"type":"Point"}
}