{
  "type": "Feature",
  "properties": {
    "addr:full":"35-39 Dickson St Newtown NSW 2042",
    "addr:housenumber":"35-39",
    "addr:postcode":"2042",
    "addr:street":"Dickson St",
    "iso:country":"AU",
    "sg:address":"35-39 Dickson St",
    "sg:city":"Newtown",
    "sg:classifiers":[
        {
            "category":"Government",
            "subcategory":"Post Office",
            "type":"Public Place"
        }
    ],
    "sg:phone":"+61 2 9550 1127",
    "sg:postcode":"2042",
    "sg:province":"NSW",
    "sg:tags":[
        "yoga"
    ],
    "wof:name":"Newtown Yoga Room",
    "wof:placetype":"venue"
},
  "geometry": {"coordinates":[151.180161,-33.904579],"type":"Point"}
}