{
  "type": "Feature",
  "properties": {
    "addr:full":"18 Waranga St Nerrina VIC 3350",
    "addr:housenumber":"18",
    "addr:postcode":"3350",
    "addr:street":"Waranga St",
    "iso:country":"AU",
    "sg:address":"18 Waranga St",
    "sg:city":"Nerrina",
    "sg:classifiers":[
        {
            "category":"Professional",
            "subcategory":"Employment Agencies",
            "type":"Services"
        }
    ],
    "sg:phone":"+61 3 5333 7724",
    "sg:postcode":"3350",
    "sg:province":"VIC",
    "wof:name":"Ken Shearer & Associates Pty Ltd",
    "wof:placetype":"venue"
},
  "geometry": {"coordinates":[143.88374300000001,-37.543804],"type":"Point"}
}