{
  "type": "Feature",
  "properties": {
    "iso:country":"AU",
    "sg:address":"81 Turea St",
    "sg:city":"Blacksmiths",
    "sg:classifiers":[
        {
            "category":"Food & Beverages",
            "subcategory":"Groceries & Convenience Stores",
            "type":"Retail Goods"
        }
    ],
    "sg:phone":"+61 2 4971 1561",
    "sg:postcode":"2281",
    "sg:province":"NSW",
    "wof:name":"Blacksmiths Food Market",
    "wof:placetype":"venue"
},
  "geometry": {"coordinates":[151.649932861,-33.079044342],"type":"Point"}
}