{
  "type": "Feature",
  "properties": {
    "addr:full":"Shop 2 862 Hume Hwy Bass Hill NSW 2197",
    "addr:housenumber":"shop 2 862",
    "addr:postcode":"2197",
    "addr:street":"Hume Hwy",
    "iso:country":"AU",
    "sg:address":"Shop 2 862 Hume Hwy",
    "sg:city":"Bass Hill",
    "sg:classifiers":[
        {
            "category":"Fast Food",
            "type":"Food & Drink"
        }
    ],
    "sg:phone":"+61 2 9644 7888",
    "sg:postcode":"2197",
    "sg:province":"NSW",
    "sg:tags":[
        "away",
        "take"
    ],
    "wof:name":"Dominos Pizza",
    "wof:placetype":"venue"
},
  "geometry": {"coordinates":[150.99426299999999,-33.897751],"type":"Point"}
}