{
  "type": "Feature",
  "properties": {
    "addr:full":"27 Whitbread St Taree NSW 2430",
    "addr:housenumber":"27",
    "addr:postcode":"2430",
    "addr:street":"Whitbread St",
    "iso:country":"AU",
    "sg:address":"27 Whitbread St",
    "sg:city":"Taree",
    "sg:classifiers":[
        {
            "category":"Home & Garden",
            "subcategory":"Building Materials",
            "type":"Retail Goods"
        }
    ],
    "sg:phone":"+61 2 6552 3661",
    "sg:postcode":"2430",
    "sg:province":"NSW",
    "sg:tags":[
        "fitting",
        "door"
    ],
    "wof:name":"Taree Garage Door Services",
    "wof:placetype":"venue"
},
  "geometry": {"coordinates":[152.45950300000001,-31.906786],"type":"Point"}
}