{
  "type": "Feature",
  "properties": {
    "addr:full":"2a Bega Rd Northbridge NSW 2063",
    "addr:housenumber":"2a",
    "addr:postcode":"2063",
    "addr:street":"Bega Rd",
    "iso:country":"AU",
    "sg:address":"2a Bega Rd",
    "sg:city":"Northbridge",
    "sg:classifiers":[
        {
            "category":"Professional",
            "subcategory":"Business Services",
            "type":"Services"
        }
    ],
    "sg:phone":"+61 2 9958 0007",
    "sg:postcode":"2063",
    "sg:province":"NSW",
    "sg:tags":[
        "broker"
    ],
    "wof:name":"Hire Industry Brokers",
    "wof:placetype":"venue"
},
  "geometry": {"coordinates":[151.216506958,-33.8098716736],"type":"Point"}
}