{
  "type": "Feature",
  "properties": {
    "addr:full":"2 Cubbitt St Lethbridge VIC 3332",
    "addr:housenumber":"2",
    "addr:postcode":"3332",
    "addr:street":"Cubbitt St",
    "iso:country":"AU",
    "sg:address":"2 Cubbitt St",
    "sg:city":"Lethbridge",
    "sg:classifiers":[
        {
            "category":"Retail",
            "subcategory":"Auto Repair",
            "type":"Services"
        }
    ],
    "sg:phone":"+61 3 5281 7420",
    "sg:postcode":"3332",
    "sg:province":"VIC",
    "sg:tags":[
        "repairer",
        "motor",
        "engineer"
    ],
    "wof:name":"Full On Chassis Works Street & Strip Modifications",
    "wof:placetype":"venue"
},
  "geometry": {"coordinates":[144.12937927199999,-37.9652938843],"type":"Point"}
}