{
  "type": "Feature",
  "properties": {
    "iso:country":"AU",
    "sg:address":"Yamble Drv",
    "sg:city":"Ocean Shores",
    "sg:classifiers":[
        {
            "category":"Retail",
            "subcategory":"Repair Shop",
            "type":"Services"
        }
    ],
    "sg:phone":"+61 2 6680 1988",
    "sg:postcode":"2483",
    "sg:province":"NSW",
    "sg:tags":[
        "machine",
        "repairs",
        "part",
        "dryer",
        "washing"
    ],
    "wof:name":"Austech Appliance Service",
    "wof:placetype":"venue"
},
  "geometry": {"coordinates":[153.53288269000001,-28.5185184479],"type":"Point"}
}