{
  "type": "Feature",
  "properties": {
    "iso:country":"AU",
    "sg:address":"2a Silverwater Rd",
    "sg:city":"Auburn",
    "sg:classifiers":[
        {
            "category":"Autos & Motor Vehicles",
            "subcategory":"Fuel & Gas Station",
            "type":"Retail Goods"
        }
    ],
    "sg:phone":"+61 2 9748 1911",
    "sg:postcode":"2144",
    "sg:province":"NSW",
    "wof:name":"Caltex Ampol Service Station",
    "wof:placetype":"venue"
},
  "geometry": {"coordinates":[151.04278564399999,-33.8440208435],"type":"Point"}
}