{
  "type": "Feature",
  "properties": {
    "addr:full":"124 Broken Bay Rd Ettalong NSW 2257",
    "addr:housenumber":"124",
    "addr:postcode":"2257",
    "addr:street":"Broken Bay Rd",
    "iso:country":"AU",
    "sg:address":"124 Broken Bay Rd",
    "sg:city":"Ettalong",
    "sg:classifiers":[
        {
            "category":"Building & Trades",
            "subcategory":"Construction",
            "type":"Services"
        }
    ],
    "sg:phone":"+61 2 4341 6370",
    "sg:postcode":"2257",
    "sg:province":"NSW",
    "sg:tags":[
        "concrete",
        "contractor"
    ],
    "wof:name":"Graf Bros Pty Ltd",
    "wof:placetype":"venue"
},
  "geometry": {"coordinates":[151.33038330100001,-33.521270752],"type":"Point"}
}