{
  "type": "Feature",
  "properties": {
    "iso:country":"AU",
    "sg:address":"131 McMahons Rd",
    "sg:city":"Nowra North",
    "sg:classifiers":[
        {
            "category":"Communications",
            "type":"Services"
        }
    ],
    "sg:phone":"+61 2 4423 3677",
    "sg:postcode":"2541",
    "sg:province":"NSW",
    "sg:tags":[
        "public",
        "system",
        "address"
    ],
    "wof:name":"Sight & Sound Installations Pty Ltd",
    "wof:placetype":"venue"
},
  "geometry": {"coordinates":[150.569412231,-34.8597869873],"type":"Point"}
}