{
  "type": "Feature",
  "properties": {
    "addr:full":"4 Hunter Drv Blackburn South VIC 3130",
    "addr:housenumber":"4",
    "addr:postcode":"3130",
    "addr:street":"Hunter Drv",
    "iso:country":"AU",
    "sg:address":"4 Hunter Drv",
    "sg:city":"Blackburn South",
    "sg:classifiers":[
        {
            "category":"Real Estate",
            "subcategory":"Architect",
            "type":"Services"
        }
    ],
    "sg:phone":"+61 3 9878 2588",
    "sg:postcode":"3130",
    "sg:province":"VIC",
    "wof:name":"Jenkins Nigel",
    "wof:placetype":"venue"
},
  "geometry": {"coordinates":[145.14967346200001,-37.8324737549],"type":"Point"}
}