{
  "type": "Feature",
  "properties": {
    "iso:country":"AU",
    "sg:address":"176 King St",
    "sg:city":"Newcastle",
    "sg:classifiers":[
        {
            "category":"Manufacturing",
            "subcategory":"Jewelry",
            "type":"Manufacturing & Wholesale Goods"
        }
    ],
    "sg:phone":"+61 2 4929 1417",
    "sg:postcode":"2300",
    "sg:province":"NSW",
    "sg:tags":[
        "mfrg",
        "jeweller"
    ],
    "wof:name":"Robert Paul",
    "wof:placetype":"venue"
},
  "geometry": {"coordinates":[151.776825,-32.926914],"type":"Point"}
}