{
  "type": "Feature",
  "properties": {
    "iso:country":"AU",
    "sg:address":"26 Violet St",
    "sg:city":"Revesby",
    "sg:classifiers":[
        {
            "category":"Manufacturing",
            "subcategory":"Metals",
            "type":"Manufacturing & Wholesale Goods"
        }
    ],
    "sg:phone":"+61 2 9792 1366",
    "sg:postcode":"2212",
    "sg:province":"NSW",
    "sg:tags":[
        "steel",
        "fabricator",
        "mfrs"
    ],
    "wof:name":"CMD Majestic",
    "wof:placetype":"venue"
},
  "geometry": {"coordinates":[151.006134,-33.935139],"type":"Point"}
}