{
  "type": "Feature",
  "properties": {
    "addr:full":"2 Maddison Crt Bundaberg QLD 4670",
    "addr:housenumber":"2",
    "addr:postcode":"4670",
    "addr:street":"Maddison Crt",
    "iso:country":"AU",
    "sg:address":"2 Maddison Crt",
    "sg:city":"Bundaberg",
    "sg:classifiers":[
        {
            "category":"Autos & Motor Vehicles",
            "subcategory":"Boat Sales",
            "type":"Retail Goods"
        }
    ],
    "sg:phone":"+61 7 4152 2111",
    "sg:postcode":"4670",
    "sg:province":"QLD",
    "sg:tags":[
        "yacht"
    ],
    "wof:name":"Sea Jay Boats",
    "wof:placetype":"venue"
},
  "geometry": {"coordinates":[152.33265685999999,-24.8928470612],"type":"Point"}
}