{
  "type": "Feature",
  "properties": {
    "addr:full":"Flr 1/ 180 Quay St Rockhampton City QLD 4700",
    "addr:housenumber":"/ 180",
    "addr:postcode":"4700",
    "addr:street":"Quay St",
    "iso:country":"AU",
    "sg:address":"Flr 1/ 180 Quay St",
    "sg:city":"Rockhampton City",
    "sg:classifiers":[
        {
            "category":"Professional",
            "subcategory":"Business Services",
            "type":"Services"
        }
    ],
    "sg:phone":"+61 7 4927 2244",
    "sg:postcode":"4700",
    "sg:province":"QLD",
    "sg:tags":[
        "small",
        "advisory"
    ],
    "wof:name":"Action COACH",
    "wof:placetype":"venue"
},
  "geometry": {"coordinates":[150.52513122600001,-23.3920269012],"type":"Point"}
}