{
  "type": "Feature",
  "properties": {
    "addr:full":"41 Evelyn Rd Ringwood North VIC 3134",
    "addr:housenumber":"41",
    "addr:postcode":"3134",
    "addr:street":"Evelyn Rd",
    "iso:country":"AU",
    "sg:address":"41 Evelyn Rd",
    "sg:city":"Ringwood North",
    "sg:classifiers":[
        {
            "category":"Personal",
            "subcategory":"Massage",
            "type":"Services"
        }
    ],
    "sg:phone":"+61 3 8802 1884",
    "sg:postcode":"3134",
    "sg:province":"VIC",
    "sg:tags":[
        "therapy"
    ],
    "wof:name":"Maloney Richard",
    "wof:placetype":"venue"
},
  "geometry": {"coordinates":[145.22558593799999,-37.8003425598],"type":"Point"}
}