{
  "type": "Feature",
  "properties": {
    "addr:full":"3 Edwin Pde Highett VIC 3190",
    "addr:housenumber":"3",
    "addr:postcode":"3190",
    "addr:street":"Edwin Pde",
    "iso:country":"AU",
    "sg:address":"3 Edwin Pde",
    "sg:city":"Highett",
    "sg:classifiers":[
        {
            "category":"Professional",
            "subcategory":"Accounting & Tax Preparation",
            "type":"Services"
        }
    ],
    "sg:phone":"+61 3 9553 7173",
    "sg:postcode":"3190",
    "sg:province":"VIC",
    "sg:tags":[
        "accountant",
        "auditor"
    ],
    "wof:name":"J L R Partners",
    "wof:placetype":"venue"
},
  "geometry": {"coordinates":[145.04450988799999,-37.9484977722],"type":"Point"}
}