{
  "type": "Feature",
  "properties": {
    "addr:full":"592 Princes Hwy Rockdale NSW 2216",
    "addr:housenumber":"592",
    "addr:postcode":"2216",
    "addr:street":"Princes Hwy",
    "iso:country":"AU",
    "sg:address":"592 Princes Hwy",
    "sg:city":"Rockdale",
    "sg:classifiers":[
        {
            "category":"Organizations",
            "subcategory":"Community Association",
            "type":"Services"
        }
    ],
    "sg:phone":"+61 2 9597 4809",
    "sg:postcode":"2216",
    "sg:province":"NSW",
    "sg:tags":[
        "organisation",
        "family",
        "welfare"
    ],
    "wof:name":"St George Womens Housing Inc",
    "wof:placetype":"venue"
},
  "geometry": {"coordinates":[151.13786300000001,-33.955528],"type":"Point"}
}