{
  "type": "Feature",
  "properties": {
    "addr:full":"Village Rd Saratoga NSW 2251",
    "addr:postcode":"2251",
    "addr:street":"Village Rd",
    "iso:country":"AU",
    "sg:address":"Village Rd",
    "sg:city":"Saratoga",
    "sg:classifiers":[
        {
            "category":"Food & Beverages",
            "subcategory":"Liquor & Beverages",
            "type":"Retail Goods"
        }
    ],
    "sg:phone":"+61 2 4369 2142",
    "sg:postcode":"2251",
    "sg:province":"NSW",
    "sg:tags":[
        "store"
    ],
    "wof:name":"Liquorland",
    "wof:placetype":"venue"
},
  "geometry": {"coordinates":[151.35366821299999,-33.4756202698],"type":"Point"}
}