{
  "type": "Feature",
  "properties": {
    "addr:full":"24 Parkway Drv Scarness QLD 4655",
    "addr:housenumber":"24",
    "addr:postcode":"4655",
    "addr:street":"Parkway Drv",
    "iso:country":"AU",
    "sg:address":"24 Parkway Drv",
    "sg:city":"Scarness",
    "sg:classifiers":[
        {
            "category":"Ice Cream",
            "type":"Food & Drink"
        }
    ],
    "sg:phone":"+61 7 4124 2242",
    "sg:postcode":"4655",
    "sg:province":"QLD",
    "sg:tags":[
        "retail"
    ],
    "wof:name":"Staff R.J. & G.I. Mobile Ice Cream Vendors",
    "wof:placetype":"venue"
},
  "geometry": {"coordinates":[152.858215,-25.289261],"type":"Point"}
}