{
  "type": "Feature",
  "properties": {
    "addr:full":"21 Johnson St Kiama Downs NSW 2533",
    "addr:housenumber":"21",
    "addr:postcode":"2533",
    "addr:street":"Johnson St",
    "iso:country":"AU",
    "sg:address":"21 Johnson St",
    "sg:city":"Kiama Downs",
    "sg:classifiers":[
        {
            "category":"Food & Beverages",
            "subcategory":"Bakery",
            "type":"Retail Goods"
        }
    ],
    "sg:phone":"+61 2 4237 6872",
    "sg:postcode":"2533",
    "sg:province":"NSW",
    "sg:tags":[
        "baker"
    ],
    "wof:name":"Black Tulip Patisserie",
    "wof:placetype":"venue"
},
  "geometry": {"coordinates":[150.853805542,-34.6362876892],"type":"Point"}
}