{
  "type": "Feature",
  "properties": {
    "iso:country":"AU",
    "sg:address":"75 Rookwood Rd",
    "sg:city":"Yagoona",
    "sg:classifiers":[
        {
            "category":"Retail",
            "subcategory":"Auto Repair",
            "type":"Services"
        }
    ],
    "sg:phone":"+61 2 9790 0818",
    "sg:postcode":"2199",
    "sg:province":"NSW",
    "sg:tags":[
        "fuel",
        "petrol",
        "injection"
    ],
    "wof:name":"Yagoona Motor Repairs",
    "wof:placetype":"venue"
},
  "geometry": {"coordinates":[151.037003,-33.901932],"type":"Point"}
}