{
  "type": "Feature",
  "properties": {
    "addr:full":"207 Denison St Rockhampton QLD 4700",
    "addr:housenumber":"207",
    "addr:postcode":"4700",
    "addr:street":"Denison St",
    "iso:country":"AU",
    "sg:address":"207 Denison St",
    "sg:city":"Rockhampton",
    "sg:classifiers":[
        {
            "category":"Building & Trades",
            "subcategory":"Construction",
            "type":"Services"
        }
    ],
    "sg:phone":"+61 7 4922 7633",
    "sg:postcode":"4700",
    "sg:province":"QLD",
    "sg:tags":[
        "spouting",
        "guttering"
    ],
    "wof:name":"Rod's Gutter Guardian",
    "wof:placetype":"venue"
},
  "geometry": {"coordinates":[150.514892578,-23.3865356445],"type":"Point"}
}