{
  "type": "Feature",
  "properties": {
    "addr:full":"219 Osborne Ave Clayton VIC 3168",
    "addr:housenumber":"219",
    "addr:postcode":"3168",
    "addr:street":"Osborne Ave",
    "iso:country":"AU",
    "sg:address":"219 Osborne Ave",
    "sg:city":"Clayton",
    "sg:classifiers":[
        {
            "category":"Home & Garden",
            "subcategory":"Building Materials",
            "type":"Retail Goods"
        }
    ],
    "sg:phone":"+61 3 9551 1445",
    "sg:postcode":"3168",
    "sg:province":"VIC",
    "sg:tags":[
        "merchant",
        "glass",
        "glazier"
    ],
    "wof:name":"Alfa Glass & Mirrors",
    "wof:placetype":"venue"
},
  "geometry": {"coordinates":[145.124755859,-37.899181366],"type":"Point"}
}