{
  "type": "Feature",
  "properties": {
    "addr:full":"6 Corunna Rd Eastwood NSW 2122",
    "addr:housenumber":"6",
    "addr:postcode":"2122",
    "addr:street":"Corunna Rd",
    "iso:country":"AU",
    "sg:address":"6 Corunna Rd",
    "sg:city":"Eastwood",
    "sg:classifiers":[
        {
            "category":"Food & Beverages",
            "subcategory":"Liquor & Beverages",
            "type":"Retail Goods"
        }
    ],
    "sg:phone":"+61 2 9858 2520",
    "sg:postcode":"2122",
    "sg:province":"NSW",
    "sg:tags":[
        "store"
    ],
    "wof:name":"Liquorstop",
    "wof:placetype":"venue"
},
  "geometry": {"coordinates":[151.093139648,-33.783454895],"type":"Point"}
}