{
  "type": "Feature",
  "properties": {
    "addr:full":"Cnr 8 Londor Cl & Canberra St Hemmant QLD 4174",
    "addr:housenumber":"8",
    "addr:postcode":"4174",
    "addr:street":"Cnr;Cl & Canberra St",
    "iso:country":"AU",
    "sg:address":"Cnr 8 Londor Cl & Canberra St",
    "sg:city":"Hemmant",
    "sg:classifiers":[
        {
            "category":"Recreation",
            "subcategory":"Fishing",
            "type":"Entertainment"
        }
    ],
    "sg:phone":"+61 7 3390 8300",
    "sg:postcode":"4174",
    "sg:province":"QLD",
    "sg:tags":[
        "bait"
    ],
    "wof:name":"Tweed Bait Pty. Ltd.",
    "wof:placetype":"venue"
},
  "geometry": {"coordinates":[153.12664794899999,-27.4438228607],"type":"Point"}
}