{
  "type": "Feature",
  "properties": {
    "addr:full":"15 Boonabah Pl Caloundra QLD 4551",
    "addr:housenumber":"15",
    "addr:postcode":"4551",
    "addr:street":"Boonabah Pl",
    "iso:country":"AU",
    "sg:address":"15 Boonabah Pl",
    "sg:city":"Caloundra",
    "sg:classifiers":[
        {
            "category":"Recreation",
            "type":"Entertainment"
        }
    ],
    "sg:phone":"+61 7 5499 6333",
    "sg:postcode":"4551",
    "sg:province":"QLD",
    "sg:tags":[
        "supply",
        "outdoor",
        "adventure",
        "activity"
    ],
    "wof:name":"Project Adventure Australia",
    "wof:placetype":"venue"
},
  "geometry": {"coordinates":[153.10806274399999,-26.7874794006],"type":"Point"}
}