{
  "type": "Feature",
  "properties": {
    "addr:full":"Shop 18 - 19 LG, Central Plaza 450 George St Sydney NSW 2000",
    "addr:housenumber":"shop 18 19 lg;450",
    "addr:postcode":"2000",
    "addr:street":"Central Plaza;George St",
    "iso:country":"AU",
    "sg:address":"Shop 18 - 19 LG, Central Plaza 450 George St",
    "sg:city":"Sydney",
    "sg:classifiers":[
        {
            "category":"Transit Center",
            "subcategory":"Passenger",
            "type":"Transportation"
        }
    ],
    "sg:phone":"+61 1300 731 185",
    "sg:postcode":"2000",
    "sg:province":"NSW",
    "sg:tags":[
        "wholesaler",
        "mfrs",
        "toiletry",
        "perfume"
    ],
    "wof:name":"Perfume Empire",
    "wof:placetype":"venue"
},
  "geometry": {"coordinates":[151.20716857900001,-33.8706970215],"type":"Point"}
}