{
  "type": "Feature",
  "properties": {
    "addr:full":"96 Great Eastern Hwy Sawyers Valley WA 6074",
    "addr:housenumber":"96",
    "addr:postcode":"6074",
    "addr:street":"Great Eastern Hwy",
    "iso:country":"AU",
    "sg:address":"96 Great Eastern Hwy",
    "sg:city":"Sawyers Valley",
    "sg:classifiers":[
        {
            "category":"Autos & Motor Vehicles",
            "subcategory":"Fuel & Gas Station",
            "type":"Retail Goods"
        }
    ],
    "sg:phone":"+61 8 9295 6476",
    "sg:postcode":"6074",
    "sg:province":"WA",
    "wof:name":"Peak Petroleum",
    "wof:placetype":"venue"
},
  "geometry": {"coordinates":[116.206092834,-31.9032993317],"type":"Point"}
}