{
  "type": "Feature",
  "properties": {
    "addr:full":"199 Toombul Rd Northgate QLD 4013",
    "addr:housenumber":"199",
    "addr:postcode":"4013",
    "addr:street":"Toombul Rd",
    "iso:country":"AU",
    "sg:address":"199 Toombul Rd",
    "sg:city":"Northgate",
    "sg:classifiers":[
        {
            "category":"Fast Food",
            "type":"Food & Drink"
        }
    ],
    "sg:phone":"+61 7 3260 7102",
    "sg:postcode":"4013",
    "sg:province":"QLD",
    "sg:tags":[
        "away",
        "take"
    ],
    "wof:name":"El Greco's Seafood & Carvery",
    "wof:placetype":"venue"
},
  "geometry": {"coordinates":[153.07249450699999,-27.3931102753],"type":"Point"}
}