{
  "type": "Feature",
  "properties": {
    "addr:full":"24 Hickory St Dorrigo NSW 2453",
    "addr:housenumber":"24",
    "addr:postcode":"2453",
    "addr:street":"Hickory St",
    "iso:country":"AU",
    "sg:address":"24 Hickory St",
    "sg:city":"Dorrigo",
    "sg:classifiers":[
        {
            "category":"Food & Beverages",
            "subcategory":"Liquor & Beverages",
            "type":"Retail Goods"
        }
    ],
    "sg:phone":"+61 2 6657 2080",
    "sg:postcode":"2453",
    "sg:province":"NSW",
    "sg:tags":[
        "store"
    ],
    "wof:name":"Dorrigo Cellars",
    "wof:placetype":"venue"
},
  "geometry": {"coordinates":[152.71170000000001,-30.339846],"type":"Point"}
}