{
  "type": "Feature",
  "properties": {
    "iso:country":"AU",
    "sg:address":"52 Perkins Rd",
    "sg:city":"Gympie",
    "sg:classifiers":[
        {
            "category":"Building & Trades",
            "subcategory":"Equipment Rental",
            "type":"Services"
        }
    ],
    "sg:phone":"+61 428 793 528",
    "sg:postcode":"4570",
    "sg:province":"QLD",
    "sg:tags":[
        "crane",
        "hire"
    ],
    "wof:name":"Alford J & J",
    "wof:placetype":"venue"
},
  "geometry": {"coordinates":[152.66192626899999,-26.2427406311],"type":"Point"}
}