{
  "type": "Feature",
  "properties": {
    "iso:country":"AU",
    "sg:address":"11 Settlers Hill Pl",
    "sg:city":"Narre Warren North",
    "sg:classifiers":[
        {
            "category":"Building & Trades",
            "subcategory":"Landscaping Services",
            "type":"Services"
        }
    ],
    "sg:phone":"+61 412 330 019",
    "sg:postcode":"3804",
    "sg:province":"VIC",
    "sg:tags":[
        "gardener"
    ],
    "wof:name":"Howeys Home Maintenance",
    "wof:placetype":"venue"
},
  "geometry": {"coordinates":[145.288772583,-37.9945793152],"type":"Point"}
}