{
  "type": "Feature",
  "properties": {
    "addr:full":"44 Langton Rd Mt Barker WA 6324",
    "addr:housenumber":"44",
    "addr:postcode":"6324",
    "addr:street":"Langton Rd",
    "iso:country":"AU",
    "sg:address":"44 Langton Rd",
    "sg:city":"Mt Barker",
    "sg:classifiers":[
        {
            "category":"Health Services",
            "subcategory":"Dentist",
            "type":"Services"
        }
    ],
    "sg:phone":"+61 8 9851 1061",
    "sg:postcode":"6324",
    "sg:province":"WA",
    "wof:name":"Messmer Iris B.D.Sc.(WA)",
    "wof:placetype":"venue"
},
  "geometry": {"coordinates":[117.658760071,-34.6272964478],"type":"Point"}
}