{
  "type": "Feature",
  "properties": {
    "iso:country":"AU",
    "sg:address":"36 Emily St",
    "sg:city":"Seymour",
    "sg:classifiers":[
        {
            "category":"Retail",
            "subcategory":"Self-service Laundry",
            "type":"Services"
        }
    ],
    "sg:phone":"+61 3 5792 3340",
    "sg:postcode":"3660",
    "sg:province":"VIC",
    "wof:name":"Lewis Dry Cleaners & Laundry",
    "wof:placetype":"venue"
},
  "geometry": {"coordinates":[145.127807617,-37.0198440552],"type":"Point"}
}