{
  "type": "Feature",
  "properties": {
    "addr:full":"51 Sunrise Crs Goonellabah NSW 2480",
    "addr:housenumber":"51",
    "addr:postcode":"2480",
    "addr:street":"Sunrise Crs",
    "iso:country":"AU",
    "sg:address":"51 Sunrise Crs",
    "sg:city":"Goonellabah",
    "sg:classifiers":[
        {
            "category":"Home & Garden",
            "subcategory":"Home Furnishings",
            "type":"Retail Goods"
        }
    ],
    "sg:phone":"+61 2 6624 2328",
    "sg:postcode":"2480",
    "sg:province":"NSW",
    "sg:tags":[
        "wicker",
        "cane",
        "furniture"
    ],
    "wof:name":"Cane Restoration",
    "wof:placetype":"venue"
},
  "geometry": {"coordinates":[153.339767456,-28.8109073639],"type":"Point"}
}