{
  "type": "Feature",
  "properties": {
    "iso:country":"AU",
    "sg:address":"8 Daly St",
    "sg:city":"South Yarra",
    "sg:classifiers":[
        {
            "category":"Professional",
            "subcategory":"Art Services",
            "type":"Services"
        }
    ],
    "sg:phone":"+61 3 9823 9900",
    "sg:postcode":"3141",
    "sg:province":"VIC",
    "sg:tags":[
        "graphic",
        "designer"
    ],
    "wof:name":"Cornwell Design",
    "wof:placetype":"venue"
},
  "geometry": {"coordinates":[144.994903564,-37.8378677368],"type":"Point"}
}