{
  "type": "Feature",
  "properties": {
    "iso:country":"AU",
    "sg:address":"6 Hampton St",
    "sg:city":"Greenfields",
    "sg:classifiers":[
        {
            "category":"Wholesale",
            "subcategory":"Metals & Minerals",
            "type":"Manufacturing & Wholesale Goods"
        }
    ],
    "sg:phone":"+61 8 9581 8338",
    "sg:postcode":"6210",
    "sg:province":"WA",
    "sg:tags":[
        "steel",
        "stainless",
        "product",
        "equipment"
    ],
    "wof:name":"Stainless Alloy Manufacturing",
    "wof:placetype":"venue"
},
  "geometry": {"coordinates":[115.749748,-32.512405],"type":"Point"}
}