{
  "type": "Feature",
  "properties": {
    "addr:full":"Labrador Park Shopping Centre, 100 Brisbane Rd Labrador QLD 4215",
    "addr:housenumber":"100",
    "addr:postcode":"4215",
    "addr:street":"Brisbane Rd",
    "iso:country":"AU",
    "sg:address":"Labrador Park Shopping Centre, 100 Brisbane Rd",
    "sg:city":"Labrador",
    "sg:classifiers":[
        {
            "category":"Health Services",
            "subcategory":"Doctor",
            "type":"Services"
        }
    ],
    "sg:phone":"+61 7 5563 7555",
    "sg:postcode":"4215",
    "sg:province":"QLD",
    "sg:tags":[
        "medical",
        "practitioner"
    ],
    "wof:name":"Independent Medical Imaging Services (IMIS)",
    "wof:placetype":"venue"
},
  "geometry": {"coordinates":[153.39773559599999,-27.9357662201],"type":"Point"}
}