{
  "type": "Feature",
  "properties": {
    "addr:full":"82 Ash St Barcaldine QLD 4725",
    "addr:housenumber":"82",
    "addr:postcode":"4725",
    "addr:street":"Ash St",
    "iso:country":"AU",
    "sg:address":"82 Ash St",
    "sg:city":"Barcaldine",
    "sg:classifiers":[
        {
            "category":"Organizations",
            "subcategory":"Community Association",
            "type":"Services"
        }
    ],
    "sg:phone":"+61 7 4651 2161",
    "sg:postcode":"4725",
    "sg:province":"QLD",
    "sg:tags":[
        "organisation",
        "family",
        "welfare"
    ],
    "wof:name":"Anglicare Central Queensland",
    "wof:placetype":"venue"
},
  "geometry": {"coordinates":[145.28480500000001,-23.55315],"type":"Point"}
}