{
  "type": "Feature",
  "properties": {
    "addr:full":"25 Belmont Rd Croydon South VIC 3136",
    "addr:housenumber":"25",
    "addr:postcode":"3136",
    "addr:street":"Belmont Rd",
    "iso:country":"AU",
    "sg:address":"25 Belmont Rd",
    "sg:city":"Croydon South",
    "sg:classifiers":[
        {
            "category":"Building & Trades",
            "subcategory":"Construction",
            "type":"Services"
        }
    ],
    "sg:phone":"+61 3 9723 4680",
    "sg:postcode":"3136",
    "sg:province":"VIC",
    "sg:tags":[
        "joiner",
        "carpenter"
    ],
    "wof:name":"Davelaar J",
    "wof:placetype":"venue"
},
  "geometry": {"coordinates":[145.273193359,-37.8145103455],"type":"Point"}
}