{
  "type": "Feature",
  "properties": {
    "addr:full":"179 Warrandyte Rd Ringwood North VIC 3134",
    "addr:housenumber":"179",
    "addr:postcode":"3134",
    "addr:street":"Warrandyte Rd",
    "iso:country":"AU",
    "sg:address":"179 Warrandyte Rd",
    "sg:city":"Ringwood North",
    "sg:classifiers":[
        {
            "category":"Retail",
            "subcategory":"Car Wash",
            "type":"Services"
        }
    ],
    "sg:phone":"+61 3 9876 2700",
    "sg:postcode":"3134",
    "sg:province":"VIC",
    "sg:tags":[
        "truck",
        "cleaning"
    ],
    "wof:name":"Carwash Express",
    "wof:placetype":"venue"
},
  "geometry": {"coordinates":[145.23518371599999,-37.7944869995],"type":"Point"}
}