{
  "type": "Feature",
  "properties": {
    "iso:country":"AU",
    "sg:address":"Cnr Clermont & Borilla Sts",
    "sg:city":"Emerald",
    "sg:classifiers":[
        {
            "category":"Fast Food",
            "type":"Food & Drink"
        }
    ],
    "sg:phone":"+61 7 4982 3404",
    "sg:postcode":"4720",
    "sg:province":"QLD",
    "sg:tags":[
        "away",
        "take"
    ],
    "wof:name":"Dolphin Takeaway",
    "wof:placetype":"venue"
},
  "geometry": {"coordinates":[148.15744,-23.525393],"type":"Point"}
}