{
  "type": "Feature",
  "properties": {
    "iso:country":"AU",
    "sg:address":"PO Box 699",
    "sg:city":"Bathurst Bathurst",
    "sg:classifiers":[
        {
            "category":"Professional",
            "subcategory":"Engineering",
            "type":"Services"
        }
    ],
    "sg:phone":"+61 2 6337 2354",
    "sg:postcode":"2795",
    "sg:province":"NSW",
    "sg:tags":[
        "engineer"
    ],
    "wof:name":"All Fab & Weld",
    "wof:placetype":"venue"
},
  "geometry": {"coordinates":[149.606933594,-33.5515518188],"type":"Point"}
}