{
  "type": "Feature",
  "properties": {
    "iso:country":"AU",
    "sg:address":"4- 67 Skylark St",
    "sg:city":"Inala",
    "sg:classifiers":[
        {
            "category":"Fast Food",
            "type":"Food & Drink"
        }
    ],
    "sg:phone":"+61 7 3372 4507",
    "sg:postcode":"4077",
    "sg:province":"QLD",
    "sg:tags":[
        "away",
        "take"
    ],
    "wof:name":"Tran's Snack Bar",
    "wof:placetype":"venue"
},
  "geometry": {"coordinates":[152.982055664,-27.5978240967],"type":"Point"}
}