{
  "type": "Feature",
  "properties": {
    "addr:full":"22 Toorak Ave Warragul VIC 3820",
    "addr:housenumber":"22",
    "addr:postcode":"3820",
    "addr:street":"Toorak Ave",
    "iso:country":"AU",
    "sg:address":"22 Toorak Ave",
    "sg:city":"Warragul",
    "sg:classifiers":[
        {
            "category":"Home & Garden",
            "subcategory":"Carpets & Floor Coverings",
            "type":"Retail Goods"
        }
    ],
    "sg:phone":"+61 3 5623 6843",
    "sg:postcode":"3820",
    "sg:province":"VIC",
    "sg:tags":[
        "layer",
        "planner"
    ],
    "wof:name":"Kennedy T J & L A",
    "wof:placetype":"venue"
},
  "geometry": {"coordinates":[145.924316,-38.158501],"type":"Point"}
}