{
  "type": "Feature",
  "properties": {
    "addr:full":"802 Sturt St Ballarat VIC 3350",
    "addr:housenumber":"802",
    "addr:postcode":"3350",
    "addr:street":"Sturt St",
    "iso:country":"AU",
    "sg:address":"802 Sturt St",
    "sg:city":"Ballarat",
    "sg:classifiers":[
        {
            "category":"Cafe",
            "type":"Food & Drink"
        }
    ],
    "sg:phone":"+61 3 5334 4744",
    "sg:postcode":"3350",
    "sg:province":"VIC",
    "wof:name":"The Turret Cafe & Catering",
    "wof:placetype":"venue"
},
  "geometry": {"coordinates":[143.84877,-37.560581],"type":"Point"}
}