{
  "type": "Feature",
  "properties": {
    "addr:full":"272 Shepherds Hill Rd Eden Hills SA 5050",
    "addr:housenumber":"272",
    "addr:postcode":"5050",
    "addr:street":"Shepherds Hill Rd",
    "iso:country":"AU",
    "sg:address":"272 Shepherds Hill Rd",
    "sg:city":"Eden Hills",
    "sg:classifiers":[
        {
            "category":"Autos & Motor Vehicles",
            "subcategory":"Fuel & Gas Station",
            "type":"Retail Goods"
        }
    ],
    "sg:phone":"+61 8 8278 4256",
    "sg:postcode":"5050",
    "sg:province":"SA",
    "wof:name":"Plus Petrol",
    "wof:placetype":"venue"
},
  "geometry": {"coordinates":[138.603714,-35.026447],"type":"Point"}
}