{
  "type": "Feature",
  "properties": {
    "iso:country":"AU",
    "sg:address":"Shop 4",
    "sg:city":"Sunnybank Plaza Shopping Centre Sunnybank",
    "sg:classifiers":[
        {
            "category":"Health Services",
            "subcategory":"Health Practitioner",
            "type":"Services"
        }
    ],
    "sg:phone":"+61 7 3344 7388",
    "sg:postcode":"4109",
    "sg:province":"QLD",
    "sg:tags":[
        "acupuncture"
    ],
    "wof:name":"Ren Ji Tang Chinese Medicine",
    "wof:placetype":"venue"
},
  "geometry": {"coordinates":[153.06637573200001,-27.5965461731],"type":"Point"}
}