{
  "type": "Feature",
  "properties": {
    "addr:full":"10 Throssell Rd South Hedland WA 6722",
    "addr:housenumber":"10",
    "addr:postcode":"6722",
    "addr:street":"Throssell Rd",
    "iso:country":"AU",
    "sg:address":"10 Throssell Rd",
    "sg:city":"South Hedland",
    "sg:classifiers":[
        {
            "category":"Fast Food",
            "type":"Food & Drink"
        }
    ],
    "sg:phone":"+61 8 9140 2288",
    "sg:postcode":"6722",
    "sg:province":"WA",
    "sg:tags":[
        "away",
        "take"
    ],
    "wof:name":"Eagle Boys Pizza",
    "wof:placetype":"venue"
},
  "geometry": {"coordinates":[118.601127624,-20.4092636108],"type":"Point"}
}