{
  "type": "Feature",
  "properties": {
    "addr:full":"4/ 88 Kirkland Ave Coorparoo QLD 4151",
    "addr:housenumber":"/ 88",
    "addr:postcode":"4151",
    "addr:street":"Kirkland Ave",
    "iso:country":"AU",
    "sg:address":"4/ 88 Kirkland Ave",
    "sg:city":"Coorparoo",
    "sg:classifiers":[
        {
            "category":"Professional",
            "subcategory":"Business Services",
            "type":"Services"
        }
    ],
    "sg:phone":"+61 422 141 516",
    "sg:postcode":"4151",
    "sg:province":"QLD",
    "sg:tags":[
        "drafting"
    ],
    "wof:name":"B N Drafting",
    "wof:placetype":"venue"
},
  "geometry": {"coordinates":[153.05195617699999,-27.5014533997],"type":"Point"}
}