{
  "type": "Feature",
  "properties": {
    "iso:country":"AU",
    "sg:address":"34 Taylors Rd West",
    "sg:city":"Aberfoyle Park",
    "sg:classifiers":[
        {
            "category":"Social Services",
            "subcategory":"Child Care",
            "type":"Services"
        }
    ],
    "sg:phone":"+61 8 8370 5063",
    "sg:postcode":"5159",
    "sg:province":"SA",
    "wof:name":"Aberfoyle Hub Community Childrens\ufffd Centre",
    "wof:placetype":"venue"
},
  "geometry": {"coordinates":[138.589447022,-35.0732879639],"type":"Point"}
}