{
  "type": "Feature",
  "properties": {
    "addr:full":"47 White Cedar Drv Castle Hill NSW 2154",
    "addr:housenumber":"47",
    "addr:postcode":"2154",
    "addr:street":"White Cedar Drv",
    "iso:country":"AU",
    "sg:address":"47 White Cedar Drv",
    "sg:city":"Castle Hill",
    "sg:classifiers":[
        {
            "category":"Professional",
            "subcategory":"Accounting & Tax Preparation",
            "type":"Services"
        }
    ],
    "sg:phone":"+61 2 9659 1647",
    "sg:postcode":"2154",
    "sg:province":"NSW",
    "sg:tags":[
        "bookkeeping"
    ],
    "wof:name":"Accounting Works For You",
    "wof:placetype":"venue"
},
  "geometry": {"coordinates":[150.98617553700001,-33.7350082397],"type":"Point"}
}