{
  "type": "Feature",
  "properties": {
    "addr:full":"Lvl 17/ 127 Creek St Brisbane QLD 4000",
    "addr:housenumber":"/ 127",
    "addr:postcode":"4000",
    "addr:street":"Creek St",
    "iso:country":"AU",
    "sg:address":"Lvl 17/ 127 Creek St",
    "sg:city":"Brisbane",
    "sg:classifiers":[
        {
            "category":"Banks & Credit Unions",
            "subcategory":"Financial Services",
            "type":"Services"
        }
    ],
    "sg:phone":"+61 7 3229 2827",
    "sg:postcode":"4000",
    "sg:province":"QLD",
    "sg:tags":[
        "planning"
    ],
    "wof:name":"Australian Debt & Financial Solutions Pty Ltd",
    "wof:placetype":"venue"
},
  "geometry": {"coordinates":[153.027709961,-27.4658489227],"type":"Point"}
}