{
  "type": "Feature",
  "properties": {
    "addr:full":"10 Murphy St Invermay TAS 7248",
    "addr:housenumber":"10",
    "addr:postcode":"7248",
    "addr:street":"Murphy St",
    "iso:country":"AU",
    "sg:address":"10 Murphy St",
    "sg:city":"Invermay",
    "sg:classifiers":[
        {
            "category":"Professional",
            "subcategory":"Engineering",
            "type":"Services"
        }
    ],
    "sg:phone":"+61 3 6334 2744",
    "sg:postcode":"7248",
    "sg:province":"TAS",
    "sg:tags":[
        "manufacturing",
        "engineer"
    ],
    "wof:name":"K.R. Machining Pty Ltd",
    "wof:placetype":"venue"
},
  "geometry": {"coordinates":[147.12583923299999,-41.4258728027],"type":"Point"}
}