{
  "type": "Feature",
  "properties": {
    "addr:full":"2 Reginald St Mt Gambier SA 5290",
    "addr:housenumber":"2",
    "addr:postcode":"5290",
    "addr:street":"Reginald St",
    "iso:country":"AU",
    "sg:address":"2 Reginald St",
    "sg:city":"Mt Gambier",
    "sg:classifiers":[
        {
            "category":"Home & Garden",
            "subcategory":"Building Materials",
            "type":"Retail Goods"
        }
    ],
    "sg:phone":"+61 8 8725 3689",
    "sg:postcode":"5290",
    "sg:province":"SA",
    "sg:tags":[
        "retaining",
        "wall"
    ],
    "wof:name":"The Complete Home Care Company",
    "wof:placetype":"venue"
},
  "geometry": {"coordinates":[140.78285199999999,-37.833302],"type":"Point"}
}