{
  "type": "Feature",
  "properties": {
    "addr:full":"1st Floor, 19 East St Rockhampton QLD 4700",
    "addr:housenumber":"19",
    "addr:postcode":"4700",
    "addr:street":"East St",
    "iso:country":"AU",
    "sg:address":"1st Floor, 19 East St",
    "sg:city":"Rockhampton",
    "sg:classifiers":[
        {
            "category":"Shopping",
            "subcategory":"Bridal",
            "type":"Retail Goods"
        }
    ],
    "sg:phone":"+61 7 4921 1857",
    "sg:postcode":"4700",
    "sg:province":"QLD",
    "sg:tags":[
        "hire",
        "wear"
    ],
    "wof:name":"Bridal Reflections",
    "wof:placetype":"venue"
},
  "geometry": {"coordinates":[150.52105712900001,-23.3888053894],"type":"Point"}
}