{
  "type": "Feature",
  "properties": {
    "addr:full":"Shop 2 Palm Waters Shopng Cntr 19th Ave Elanora QLD 4221",
    "addr:housenumber":"shop 2",
    "addr:postcode":"4221",
    "addr:street":"Palm Waters Shopng Cntr 19Th Ave",
    "iso:country":"AU",
    "sg:address":"Shop 2 Palm Waters Shopng Cntr 19th Ave",
    "sg:city":"Elanora",
    "sg:classifiers":[
        {
            "category":"Food & Beverages",
            "subcategory":"Liquor & Beverages",
            "type":"Retail Goods"
        }
    ],
    "sg:phone":"+61 7 5520 0134",
    "sg:postcode":"4221",
    "sg:province":"QLD",
    "sg:tags":[
        "store"
    ],
    "wof:name":"BWS Liquor Stores",
    "wof:placetype":"venue"
},
  "geometry": {"coordinates":[153.452438355,-28.1190128326],"type":"Point"}
}