{
  "type": "Feature",
  "properties": {
    "addr:full":"24 Player Ave St Peters SA 5069",
    "addr:housenumber":"24",
    "addr:postcode":"5069",
    "addr:street":"Player Ave",
    "iso:country":"AU",
    "sg:address":"24 Player Ave St",
    "sg:city":"Peters",
    "sg:classifiers":[
        {
            "category":"Building & Trades",
            "subcategory":"Plumbing",
            "type":"Services"
        }
    ],
    "sg:phone":"+61 411 666 355",
    "sg:postcode":"5069",
    "sg:province":"SA",
    "sg:tags":[
        "plumber",
        "gasfitters"
    ],
    "wof:name":"Campbell Plumbing Service",
    "wof:placetype":"venue"
},
  "geometry": {"coordinates":[138.61497497600001,-34.900642395],"type":"Point"}
}