{
  "type": "Feature",
  "properties": {
    "addr:full":"Maybrook Ave Cromer Heights NSW 2099",
    "addr:postcode":"2099",
    "addr:street":"Maybrook Ave",
    "iso:country":"AU",
    "sg:address":"Maybrook Ave",
    "sg:city":"Cromer Heights",
    "sg:classifiers":[
        {
            "category":"Retail",
            "subcategory":"Auto Repair",
            "type":"Services"
        }
    ],
    "sg:phone":"+61 2 9982 7317",
    "sg:postcode":"2099",
    "sg:province":"NSW",
    "sg:tags":[
        "repairer",
        "motor",
        "engineer"
    ],
    "wof:name":"Cromer Motors",
    "wof:placetype":"venue"
},
  "geometry": {"coordinates":[151.264526367,-33.7350540161],"type":"Point"}
}