{
  "type": "Feature",
  "properties": {
    "addr:full":"120 Murray St Finley NSW 2713",
    "addr:housenumber":"120",
    "addr:postcode":"2713",
    "addr:street":"Murray St",
    "iso:country":"AU",
    "sg:address":"120 Murray St",
    "sg:city":"Finley",
    "sg:classifiers":[
        {
            "category":"Utilities",
            "subcategory":"Water",
            "type":"Services"
        }
    ],
    "sg:phone":"+61 3 5883 2233",
    "sg:postcode":"2713",
    "sg:province":"NSW",
    "sg:tags":[
        "hot",
        "system"
    ],
    "wof:name":"Tarrant R G & J K",
    "wof:placetype":"venue"
},
  "geometry": {"coordinates":[145.578369141,-35.641040802],"type":"Point"}
}