{
  "type": "Feature",
  "properties": {
    "addr:full":"Shp38/ 13 Cantonment St Fremantle WA 6160",
    "addr:housenumber":"13",
    "addr:postcode":"6160",
    "addr:street":"Cantonment St",
    "iso:country":"AU",
    "sg:address":"Shp38/ 13 Cantonment St",
    "sg:city":"Fremantle",
    "sg:classifiers":[
        {
            "category":"Autos & Motor Vehicles",
            "subcategory":"Boat Sales",
            "type":"Retail Goods"
        }
    ],
    "sg:phone":"+61 8 9335 5255",
    "sg:postcode":"6160",
    "sg:province":"WA",
    "sg:tags":[
        "yacht"
    ],
    "wof:name":"Transcontinental Maritime Services Pty Ltd",
    "wof:placetype":"venue"
},
  "geometry": {"coordinates":[115.746803,-32.053467],"type":"Point"}
}