{
  "type": "Feature",
  "properties": {
    "iso:country":"AU",
    "sg:address":"59 Noble Ave",
    "sg:city":"Greenacre",
    "sg:classifiers":[
        {
            "category":"Building & Trades",
            "subcategory":"Construction",
            "type":"Services"
        }
    ],
    "sg:phone":"+61 2 9796 2329",
    "sg:postcode":"2190",
    "sg:province":"NSW",
    "sg:tags":[
        "earth",
        "excavating",
        "moving",
        "contractor"
    ],
    "wof:name":"Art Civil Pty Ltd",
    "wof:placetype":"venue"
},
  "geometry": {"coordinates":[151.05105599999999,-33.914143],"type":"Point"}
}