{
  "type": "Feature",
  "properties": {
    "addr:full":"19 Marsh St Armidale NSW 2350",
    "addr:housenumber":"19",
    "addr:postcode":"2350",
    "addr:street":"Marsh St",
    "iso:country":"AU",
    "sg:address":"19 Marsh St",
    "sg:city":"Armidale",
    "sg:classifiers":[
        {
            "category":"Retail",
            "subcategory":"Veterinary Services",
            "type":"Services"
        }
    ],
    "sg:phone":"+61 2 6772 1686",
    "sg:postcode":"2350",
    "sg:province":"NSW",
    "sg:tags":[
        "surgeon"
    ],
    "wof:name":"North Hill Veterinary Clinic",
    "wof:placetype":"venue"
},
  "geometry": {"coordinates":[151.668533325,-30.5158176422],"type":"Point"}
}