{
  "type": "Feature",
  "properties": {
    "addr:full":"42 Mangaroon Crt Shailer Park QLD 4128",
    "addr:housenumber":"42",
    "addr:postcode":"4128",
    "addr:street":"Mangaroon Crt",
    "iso:country":"AU",
    "sg:address":"42 Mangaroon Crt",
    "sg:city":"Shailer Park",
    "sg:classifiers":[
        {
            "category":"Social Services",
            "type":"Services"
        }
    ],
    "sg:phone":"+61 410 286 077",
    "sg:postcode":"4128",
    "sg:province":"QLD",
    "sg:tags":[
        "kinesiology"
    ],
    "wof:name":"Cameron Sowden",
    "wof:placetype":"venue"
},
  "geometry": {"coordinates":[153.182174683,-27.644317627],"type":"Point"}
}