{
  "type": "Feature",
  "properties": {
    "iso:country":"AU",
    "sg:address":"222 Church St",
    "sg:city":"Parramatta",
    "sg:classifiers":[
        {
            "category":"Fast Food",
            "type":"Food & Drink"
        }
    ],
    "sg:phone":"+61 2 9633 1225",
    "sg:postcode":"2150",
    "sg:province":"NSW",
    "sg:tags":[
        "away",
        "take"
    ],
    "wof:name":"The Hot Food Bar",
    "wof:placetype":"venue"
},
  "geometry": {"coordinates":[151.18026733400001,-33.8932266235],"type":"Point"}
}