{
  "type": "Feature",
  "properties": {
    "addr:full":"101 Brolga Pl Coleambally NSW 2707",
    "addr:housenumber":"101",
    "addr:postcode":"2707",
    "addr:street":"Brolga Pl",
    "iso:country":"AU",
    "sg:address":"101 Brolga Pl",
    "sg:city":"Coleambally",
    "sg:classifiers":[
        {
            "category":"Food & Beverages",
            "subcategory":"Supermarket",
            "type":"Retail Goods"
        }
    ],
    "sg:phone":"+61 2 6954 4174",
    "sg:postcode":"2707",
    "sg:province":"NSW",
    "sg:tags":[
        "grocery",
        "store"
    ],
    "wof:name":"Kellys Supermarket",
    "wof:placetype":"venue"
},
  "geometry": {"coordinates":[145.88096618599999,-34.8058624268],"type":"Point"}
}