{
  "type": "Feature",
  "properties": {
    "addr:full":"109 Chapel Rd South Bankstown NSW 2200",
    "addr:housenumber":"109",
    "addr:postcode":"2200",
    "addr:street":"Chapel Rd South",
    "iso:country":"AU",
    "sg:address":"109 Chapel Rd",
    "sg:city":"South Bankstown",
    "sg:classifiers":[
        {
            "category":"Building & Trades",
            "subcategory":"Construction",
            "type":"Services"
        }
    ],
    "sg:phone":"+61 414 652 004",
    "sg:postcode":"2200",
    "sg:province":"NSW",
    "sg:tags":[
        "concrete",
        "contractor"
    ],
    "wof:name":"Ezy-Crete",
    "wof:placetype":"venue"
},
  "geometry": {"coordinates":[151.03161600000001,-33.920284],"type":"Point"}
}