{
  "type": "Feature",
  "properties": {
    "addr:full":"27 Doncaster East Rd Mitcham VIC 3132",
    "addr:housenumber":"27",
    "addr:postcode":"3132",
    "addr:street":"Doncaster East Rd",
    "iso:country":"AU",
    "sg:address":"27 Doncaster East Rd",
    "sg:city":"Mitcham",
    "sg:classifiers":[
        {
            "category":"Health Services",
            "subcategory":"Doctor",
            "type":"Services"
        }
    ],
    "sg:phone":"+61 3 9801 2846",
    "sg:postcode":"3132",
    "sg:province":"VIC",
    "sg:tags":[
        "medical",
        "practitioner"
    ],
    "wof:name":"Clark Jason",
    "wof:placetype":"venue"
},
  "geometry": {"coordinates":[145.194259644,-37.8103904724],"type":"Point"}
}