{
  "type": "Feature",
  "properties": {
    "addr:full":"Nerrigundah Mt Rd Bodalla NSW 2545",
    "addr:postcode":"2545",
    "addr:street":"Mt Rd",
    "iso:country":"AU",
    "sg:address":"Nerrigundah Mt Rd",
    "sg:city":"Bodalla",
    "sg:classifiers":[
        {
            "category":"Home & Garden",
            "subcategory":"Garden Supply",
            "type":"Retail Goods"
        }
    ],
    "sg:phone":"+61 2 4473 5735",
    "sg:postcode":"2545",
    "sg:province":"NSW",
    "sg:tags":[
        "landscape"
    ],
    "wof:name":"Eurobodalla Quarry",
    "wof:placetype":"venue"
},
  "geometry": {"coordinates":[149.92555236800001,-36.1250419617],"type":"Point"}
}