{
  "type": "Feature",
  "properties": {
    "addr:full":"18 Jade Drv Molendinar QLD 4214",
    "addr:housenumber":"18",
    "addr:postcode":"4214",
    "addr:street":"Jade Drv",
    "iso:country":"AU",
    "sg:address":"18 Jade Drv",
    "sg:city":"Molendinar",
    "sg:classifiers":[
        {
            "category":"Autos & Motor Vehicles",
            "subcategory":"Auto Supplies",
            "type":"Retail Goods"
        }
    ],
    "sg:phone":"+61 7 5597 0077",
    "sg:postcode":"4214",
    "sg:province":"QLD",
    "sg:tags":[
        "equipment",
        "part",
        "truck"
    ],
    "wof:name":"AllDiesels Australia Pty Ltd",
    "wof:placetype":"venue"
},
  "geometry": {"coordinates":[153.36009216299999,-27.9811306],"type":"Point"}
}