{
  "type": "Feature",
  "properties": {
    "addr:full":"Unit 9, 18- 22 Merchant Drv Rockingham WA 6168",
    "addr:housenumber":"18 22",
    "addr:postcode":"6168",
    "addr:street":"Merchant Drv",
    "iso:country":"AU",
    "sg:address":"Unit 9, 18- 22 Merchant Drv",
    "sg:city":"Rockingham",
    "sg:classifiers":[
        {
            "category":"Health Services",
            "subcategory":"Dentist",
            "type":"Services"
        }
    ],
    "sg:phone":"+61 8 9529 3711",
    "sg:postcode":"6168",
    "sg:province":"WA",
    "wof:name":"Siebel Kevin Dr",
    "wof:placetype":"venue"
},
  "geometry": {"coordinates":[115.752197,-32.268581],"type":"Point"}
}