{
  "type": "Feature",
  "properties": {
    "addr:full":"39 Swift Way Dandenong VIC 3175",
    "addr:housenumber":"39",
    "addr:postcode":"3175",
    "addr:street":"Swift Way",
    "iso:country":"AU",
    "sg:address":"39 Swift Way",
    "sg:city":"Dandenong",
    "sg:classifiers":[
        {
            "category":"Professional",
            "subcategory":"Accounting & Tax Preparation",
            "type":"Services"
        }
    ],
    "sg:phone":"+61 3 9768 2865",
    "sg:postcode":"3175",
    "sg:province":"VIC",
    "sg:tags":[
        "broom",
        "brush"
    ],
    "sg:website":"http://www.busybee.com.au",
    "wof:name":"Busy Bee Brushware Pty Ltd Incorporating Busy Bee Plastics",
    "wof:placetype":"venue"
},
  "geometry": {"coordinates":[145.20347595199999,-38.0340652466],"type":"Point"}
}