{
  "type": "Feature",
  "properties": {
    "iso:country":"AU",
    "sg:address":"Duke St",
    "sg:city":"Bridgewater",
    "sg:classifiers":[
        {
            "category":"Professional",
            "subcategory":"Business Services",
            "type":"Services"
        }
    ],
    "sg:phone":"+61 8 8339 2043",
    "sg:postcode":"5155",
    "sg:province":"SA",
    "sg:tags":[
        "drafting"
    ],
    "wof:name":"Adelaide Hills Home Design Service",
    "wof:placetype":"venue"
},
  "geometry": {"coordinates":[138.75047302199999,-35.0118179321],"type":"Point"}
}