{
  "type": "Feature",
  "properties": {
    "iso:country":"AU",
    "sg:address":"111 Douro St",
    "sg:city":"Geelong North",
    "sg:classifiers":[
        {
            "category":"Professional",
            "subcategory":"Engineering",
            "type":"Services"
        }
    ],
    "sg:phone":"+61 3 5278 1931",
    "sg:postcode":"3215",
    "sg:province":"VIC",
    "sg:tags":[
        "engineer"
    ],
    "wof:name":"Lakis Engineering",
    "wof:placetype":"venue"
},
  "geometry": {"coordinates":[144.34918212900001,-38.1138801575],"type":"Point"}
}