{
  "type": "Feature",
  "properties": {
    "addr:full":"31 Bodley St Beaumaris VIC 3193",
    "addr:housenumber":"31",
    "addr:postcode":"3193",
    "addr:street":"Bodley St",
    "iso:country":"AU",
    "sg:address":"31 Bodley St",
    "sg:city":"Beaumaris",
    "sg:classifiers":[
        {
            "category":"Travel",
            "subcategory":"Hotels & Motels",
            "type":"Entertainment"
        }
    ],
    "sg:phone":"+61 3 9589 6044",
    "sg:postcode":"3193",
    "sg:province":"VIC",
    "sg:website":"http://www.beaubay.com.au",
    "wof:name":"Beaumaris Bay Motel.",
    "wof:placetype":"venue"
},
  "geometry": {"coordinates":[145.04145813,-37.9909439087],"type":"Point"}
}