{
  "type": "Feature",
  "properties": {
    "addr:full":"Unit 1 45a Grasmere Rd Cremorne NSW 2090",
    "addr:housenumber":"45a",
    "addr:postcode":"2090",
    "addr:street":"Grasmere Rd",
    "iso:country":"AU",
    "sg:address":"Unit 1 45a Grasmere Rd",
    "sg:city":"Cremorne",
    "sg:classifiers":[
        {
            "category":"Education",
            "subcategory":"Special Training",
            "type":"Public Place"
        }
    ],
    "sg:phone":"+61 2 9953 8810",
    "sg:postcode":"2090",
    "sg:province":"NSW",
    "sg:tags":[
        "development"
    ],
    "wof:name":"Marijke Wright",
    "wof:placetype":"venue"
},
  "geometry": {"coordinates":[151.22169494600001,-33.8265686035],"type":"Point"}
}