{
  "type": "Feature",
  "properties": {
    "addr:full":"Arden St Clovelly NSW 2031",
    "addr:postcode":"2031",
    "addr:street":"Arden St",
    "iso:country":"AU",
    "sg:address":"Arden St",
    "sg:city":"Clovelly",
    "sg:classifiers":[
        {
            "category":"Education",
            "subcategory":"School",
            "type":"Public Place"
        }
    ],
    "sg:phone":"+61 2 9665 7399",
    "sg:postcode":"2031",
    "sg:province":"NSW",
    "wof:name":"St Anthony's School",
    "wof:placetype":"venue"
},
  "geometry": {"coordinates":[151.258834839,-33.9110946655],"type":"Point"}
}