{
  "type": "Feature",
  "properties": {
    "iso:country":"AU",
    "sg:address":"581 Drummond St",
    "sg:city":"Carlton North",
    "sg:classifiers":[
        {
            "category":"Government",
            "subcategory":"Post Office",
            "type":"Public Place"
        }
    ],
    "sg:phone":"+61 3 9347 5036",
    "sg:postcode":"3054",
    "sg:province":"VIC",
    "sg:tags":[
        "yoga"
    ],
    "wof:name":"yogadimensions",
    "wof:placetype":"venue"
},
  "geometry": {"coordinates":[144.96981811500001,-37.7913360596],"type":"Point"}
}