{
  "type": "Feature",
  "properties": {
    "addr:full":"22 Murray St Hobart TAS 7000",
    "addr:housenumber":"22",
    "addr:postcode":"7000",
    "addr:street":"Murray St",
    "iso:country":"AU",
    "sg:address":"22 Murray St",
    "sg:city":"Hobart",
    "sg:classifiers":[
        {
            "category":"Insurance",
            "subcategory":"Insurance Agent",
            "type":"Services"
        }
    ],
    "sg:phone":"+61 3 6231 0033",
    "sg:postcode":"7000",
    "sg:province":"TAS",
    "sg:tags":[
        "broker"
    ],
    "wof:name":"Chris Scarr",
    "wof:placetype":"venue"
},
  "geometry": {"coordinates":[147.32920837399999,-42.8844184875],"type":"Point"}
}