{
  "type": "Feature",
  "properties": {
    "addr:full":"Powell Rd Coogee WA 6166",
    "addr:postcode":"6166",
    "addr:street":"Powell Rd",
    "iso:country":"AU",
    "sg:address":"Powell Rd",
    "sg:city":"Coogee",
    "sg:classifiers":[
        {
            "category":"Train Station",
            "subcategory":"Rail",
            "type":"Transportation"
        }
    ],
    "sg:phone":"+61 419 324 077",
    "sg:postcode":"6166",
    "sg:province":"WA",
    "sg:tags":[
        "repair",
        "vinyl",
        "welding"
    ],
    "wof:name":"Ian Johnson Carpet & Vinyl Repairs",
    "wof:placetype":"venue"
},
  "geometry": {"coordinates":[115.764793,-32.111515],"type":"Point"}
}