{
  "type": "Feature",
  "properties": {
    "addr:full":"33 Campbell Rd Albany WA 6330",
    "addr:housenumber":"33",
    "addr:postcode":"6330",
    "addr:street":"Campbell Rd",
    "iso:country":"AU",
    "sg:address":"33 Campbell Rd",
    "sg:city":"Albany",
    "sg:classifiers":[
        {
            "category":"Retail",
            "subcategory":"Auto Rental",
            "type":"Services"
        }
    ],
    "sg:phone":"+61 8 9841 7130",
    "sg:postcode":"6330",
    "sg:province":"WA",
    "sg:tags":[
        "car",
        "hire",
        "minibus"
    ],
    "wof:name":"Rainbow Coast Car Rentals",
    "wof:placetype":"venue"
},
  "geometry": {"coordinates":[117.893447876,-35.014503479],"type":"Point"}
}