{
  "type": "Feature",
  "properties": {
    "addr:full":"Suite 403, Level 4/ 33 Bligh St Sydney NSW 2000",
    "addr:housenumber":"/ 33",
    "addr:postcode":"2000",
    "addr:street":"403;Bligh St",
    "iso:country":"AU",
    "sg:address":"Suite 403, Level 4/ 33 Bligh St",
    "sg:city":"Sydney",
    "sg:classifiers":[
        {
            "category":"Sports & Exercise",
            "subcategory":"Gym",
            "type":"Entertainment"
        }
    ],
    "sg:phone":"+61 2 9232 0234",
    "sg:postcode":"2000",
    "sg:province":"NSW",
    "sg:tags":[
        "health",
        "fitness"
    ],
    "wof:name":"Vibe It",
    "wof:placetype":"venue"
},
  "geometry": {"coordinates":[151.209915161,-33.8659210205],"type":"Point"}
}