{
  "type": "Feature",
  "properties": {
    "addr:full":"122 Maffra St Coolaroo VIC 3048",
    "addr:housenumber":"122",
    "addr:postcode":"3048",
    "addr:street":"Maffra St",
    "iso:country":"AU",
    "sg:address":"122 Maffra St",
    "sg:city":"Coolaroo",
    "sg:classifiers":[
        {
            "category":"Food & Beverages",
            "subcategory":"Bakery",
            "type":"Retail Goods"
        }
    ],
    "sg:phone":"+61 3 9302 2669",
    "sg:postcode":"3048",
    "sg:province":"VIC",
    "sg:tags":[
        "baker"
    ],
    "wof:name":"King Bakery Pty Ltd",
    "wof:placetype":"venue"
},
  "geometry": {"coordinates":[144.93954500000001,-37.656494],"type":"Point"}
}