{
  "type": "Feature",
  "properties": {
    "addr:full":"39 Howick St Tumut NSW 2720",
    "addr:housenumber":"39",
    "addr:postcode":"2720",
    "addr:street":"Howick St",
    "iso:country":"AU",
    "sg:address":"39 Howick St",
    "sg:city":"Tumut",
    "sg:classifiers":[
        {
            "category":"Utilities",
            "type":"Services"
        }
    ],
    "sg:phone":"+61 2 6947 2110",
    "sg:postcode":"2720",
    "sg:province":"NSW",
    "sg:tags":[
        "refrigeration",
        "industrial",
        "commercial",
        "retail"
    ],
    "wof:name":"Tumut Electrical & Refrigeration",
    "wof:placetype":"venue"
},
  "geometry": {"coordinates":[148.22155799999999,-35.307838],"type":"Point"}
}