{
  "type": "Feature",
  "properties": {
    "addr:full":"200 Mason St Newport VIC 3015",
    "addr:housenumber":"200",
    "addr:postcode":"3015",
    "addr:street":"Mason St",
    "iso:country":"AU",
    "sg:address":"200 Mason St",
    "sg:city":"Newport",
    "sg:classifiers":[
        {
            "category":"Home & Garden",
            "subcategory":"Hardware",
            "type":"Retail Goods"
        }
    ],
    "sg:phone":"+61 3 9391 6111",
    "sg:postcode":"3015",
    "sg:province":"VIC",
    "sg:tags":[
        "plumber",
        "supply"
    ],
    "wof:name":"Reece Pty Ltd",
    "wof:placetype":"venue"
},
  "geometry": {"coordinates":[144.86561584500001,-37.8404121399],"type":"Point"}
}