{
  "type": "Feature",
  "properties": {
    "addr:full":"484 Peel St Tamworth NSW 2340",
    "addr:housenumber":"484",
    "addr:postcode":"2340",
    "addr:street":"Peel St",
    "iso:country":"AU",
    "sg:address":"484 Peel St",
    "sg:city":"Tamworth",
    "sg:classifiers":[
        {
            "category":"Retail",
            "subcategory":"Auto Repair",
            "type":"Services"
        }
    ],
    "sg:phone":"+61 2 6766 2002",
    "sg:postcode":"2340",
    "sg:province":"NSW",
    "sg:tags":[
        "repairer",
        "motor",
        "engineer"
    ],
    "wof:name":"Ultra Tune",
    "wof:placetype":"venue"
},
  "geometry": {"coordinates":[150.934417725,-31.0954017639],"type":"Point"}
}