{
  "type": "Feature",
  "properties": {
    "addr:full":"780 Pittwater Rd Brookvale NSW 2100",
    "addr:housenumber":"780",
    "addr:postcode":"2100",
    "addr:street":"Pittwater Rd",
    "iso:country":"AU",
    "sg:address":"780 Pittwater Rd",
    "sg:city":"Brookvale",
    "sg:classifiers":[
        {
            "category":"Retail",
            "subcategory":"Auto Repair",
            "type":"Services"
        }
    ],
    "sg:phone":"+61 2 9939 2155",
    "sg:postcode":"2100",
    "sg:province":"NSW",
    "sg:tags":[
        "repairer",
        "motor",
        "engineer"
    ],
    "wof:name":"Ford",
    "wof:placetype":"venue"
},
  "geometry": {"coordinates":[151.27865600600001,-33.7601165771],"type":"Point"}
}