{
  "type": "Feature",
  "properties": {
    "addr:full":"Lot 1 Panorama Ridge Rd Buderim QLD 4556",
    "addr:postcode":"4556",
    "addr:street":"Panorama Ridge Rd",
    "iso:country":"AU",
    "sg:address":"Lot 1 Panorama Ridge Rd",
    "sg:city":"Buderim",
    "sg:classifiers":[
        {
            "category":"Recreation",
            "type":"Entertainment"
        }
    ],
    "sg:phone":"+61 7 5476 6126",
    "sg:postcode":"4556",
    "sg:province":"QLD",
    "sg:tags":[
        "recreational",
        "diver"
    ],
    "wof:name":"Sunshine Coast Dive & Boat Charters Pty Ltd",
    "wof:placetype":"venue"
},
  "geometry": {"coordinates":[153.09310913100001,-26.6773891449],"type":"Point"}
}