{
  "type": "Feature",
  "properties": {
    "iso:country":"AU",
    "sg:address":"7 Bond St",
    "sg:city":"Mordialloc",
    "sg:classifiers":[
        {
            "category":"Home & Garden",
            "subcategory":"Garden Supply",
            "type":"Retail Goods"
        }
    ],
    "sg:phone":"+61 3 9580 2510",
    "sg:postcode":"3195",
    "sg:province":"VIC",
    "sg:tags":[
        "shed"
    ],
    "wof:name":"Aus-Wood Sheds",
    "wof:placetype":"venue"
},
  "geometry": {"coordinates":[145.10899352999999,-37.9972801208],"type":"Point"}
}