{
  "type": "Feature",
  "properties": {
    "iso:country":"AU",
    "sg:address":"Hume Hwy",
    "sg:city":"Holbrook",
    "sg:classifiers":[
        {
            "category":"Autos & Motor Vehicles",
            "subcategory":"Fuel & Gas Station",
            "type":"Retail Goods"
        }
    ],
    "sg:phone":"+61 2 6036 2788",
    "sg:postcode":"2644",
    "sg:province":"NSW",
    "wof:name":"Ampol Truck Stop Holbrook",
    "wof:placetype":"venue"
},
  "geometry": {"coordinates":[147.31756591800001,-35.7186088562],"type":"Point"}
}