{
  "type": "Feature",
  "properties": {
    "addr:full":"52 Meilandt St Wynnum North QLD 4178",
    "addr:housenumber":"52",
    "addr:postcode":"4178",
    "addr:street":"Meilandt St",
    "iso:country":"AU",
    "sg:address":"52 Meilandt St",
    "sg:city":"Wynnum North",
    "sg:classifiers":[
        {
            "category":"Building & Trades",
            "subcategory":"Cleaning & Sanitation",
            "type":"Services"
        }
    ],
    "sg:phone":"+61 7 3396 7201",
    "sg:postcode":"4178",
    "sg:province":"QLD",
    "sg:tags":[
        "cleaner",
        "repairer",
        "roof"
    ],
    "wof:name":"Atlast Roofing Services",
    "wof:placetype":"venue"
},
  "geometry": {"coordinates":[153.15602111800001,-27.4327945709],"type":"Point"}
}