{
  "type": "Feature",
  "properties": {
    "addr:full":"519 Toorak Rd Toorak VIC 3142",
    "addr:housenumber":"519",
    "addr:postcode":"3142",
    "addr:street":"Toorak Rd",
    "iso:country":"AU",
    "sg:address":"519 Toorak Rd",
    "sg:city":"Toorak",
    "sg:classifiers":[
        {
            "category":"Shopping",
            "subcategory":"Shoes",
            "type":"Retail Goods"
        }
    ],
    "sg:phone":"+61 3 9826 3444",
    "sg:postcode":"3142",
    "sg:province":"VIC",
    "sg:tags":[
        "footwear"
    ],
    "wof:name":"Mountfords Shoes",
    "wof:placetype":"venue"
},
  "geometry": {"coordinates":[145.00982665999999,-37.8410377502],"type":"Point"}
}