{
  "type": "Feature",
  "properties": {
    "addr:full":"9 Wirraway St Tamworth NSW 2340",
    "addr:housenumber":"9",
    "addr:postcode":"2340",
    "addr:street":"Wirraway St",
    "iso:country":"AU",
    "sg:address":"9 Wirraway St",
    "sg:city":"Tamworth",
    "sg:classifiers":[
        {
            "category":"Building & Trades",
            "subcategory":"Cleaning & Sanitation",
            "type":"Services"
        }
    ],
    "sg:phone":"+61 2 6762 8100",
    "sg:postcode":"2340",
    "sg:province":"NSW",
    "sg:tags":[
        "abrasive",
        "blasting"
    ],
    "wof:name":"Tamworth Powdercoating",
    "wof:placetype":"venue"
},
  "geometry": {"coordinates":[150.90748596200001,-31.0911216736],"type":"Point"}
}