{
  "type": "Feature",
  "properties": {
    "iso:country":"AU",
    "sg:address":"46- 48 Carrington Rd",
    "sg:city":"Toowoomba",
    "sg:classifiers":[
        {
            "category":"Manufacturing",
            "subcategory":"Retail Goods",
            "type":"Manufacturing & Wholesale Goods"
        }
    ],
    "sg:phone":"+61 7 4634 2477",
    "sg:postcode":"4350",
    "sg:province":"QLD",
    "sg:tags":[
        "merchant",
        "pump",
        "mfrs"
    ],
    "wof:name":"Berendsen Fluid Power",
    "wof:placetype":"venue"
},
  "geometry": {"coordinates":[151.876556,-27.54208],"type":"Point"}
}