{
  "type": "Feature",
  "properties": {
    "addr:full":"27 Gibbs St Labrador QLD 4215",
    "addr:housenumber":"27",
    "addr:postcode":"4215",
    "addr:street":"Gibbs St",
    "iso:country":"AU",
    "sg:address":"27 Gibbs St",
    "sg:city":"Labrador",
    "sg:classifiers":[
        {
            "category":"Autos & Motor Vehicles",
            "subcategory":"Boat Sales",
            "type":"Retail Goods"
        }
    ],
    "sg:phone":"+61 7 5563 1222",
    "sg:postcode":"4215",
    "sg:province":"QLD",
    "sg:tags":[
        "equipment",
        "yacht"
    ],
    "wof:name":"West System Brand Epoxy",
    "wof:placetype":"venue"
},
  "geometry": {"coordinates":[153.38284301799999,-27.9365119934],"type":"Point"}
}