{
  "type": "Feature",
  "properties": {
    "addr:full":"PO Box 623 Cotton Tree QLD 4558",
    "addr:postcode":"4558",
    "iso:country":"AU",
    "sg:address":"PO Box 623",
    "sg:city":"Cotton Tree",
    "sg:classifiers":[
        {
            "category":"Manufacturing",
            "subcategory":"Jewelry",
            "type":"Manufacturing & Wholesale Goods"
        }
    ],
    "sg:phone":"+61 7 5443 1955",
    "sg:postcode":"4558",
    "sg:province":"QLD",
    "sg:tags":[
        "mfrg",
        "jeweller"
    ],
    "wof:name":"NY2K",
    "wof:placetype":"venue"
},
  "geometry": {"coordinates":[153.098754883,-26.6551895142],"type":"Point"}
}