{
  "type": "Feature",
  "properties": {
    "iso:country":"AU",
    "sg:address":"115 Lethbridge St",
    "sg:city":"Penrith",
    "sg:classifiers":[
        {
            "category":"Health Services",
            "subcategory":"Doctor",
            "type":"Services"
        }
    ],
    "sg:phone":"+61 2 4731 3099",
    "sg:postcode":"2750",
    "sg:province":"NSW",
    "sg:tags":[
        "medical",
        "practitioner"
    ],
    "wof:name":"Crosson Ulysses",
    "wof:placetype":"venue"
},
  "geometry": {"coordinates":[150.70053100600001,-33.7562408447],"type":"Point"}
}