{
  "type": "Feature",
  "properties": {
    "addr:full":"169 Lake St Northbridge WA 6003",
    "addr:housenumber":"169",
    "addr:postcode":"6003",
    "addr:street":"Lake St",
    "iso:country":"AU",
    "sg:address":"169 Lake St",
    "sg:city":"Northbridge",
    "sg:classifiers":[
        {
            "category":"Professional",
            "subcategory":"Management & Consulting",
            "type":"Services"
        }
    ],
    "sg:phone":"+61 8 9227 5359",
    "sg:postcode":"6003",
    "sg:province":"WA",
    "sg:tags":[
        "consultant"
    ],
    "wof:name":"Harwood Susan & Assoc. Quality Consulting",
    "wof:placetype":"venue"
},
  "geometry": {"coordinates":[115.859611511,-31.9431190491],"type":"Point"}
}