{
  "type": "Feature",
  "properties": {
    "iso:country":"AU",
    "sg:address":"Factory 10/ 6 Holloway Drv",
    "sg:city":"Bayswater",
    "sg:classifiers":[
        {
            "category":"Social Services",
            "subcategory":"Retirement Home",
            "type":"Services"
        }
    ],
    "sg:phone":"+61 1300 366 346",
    "sg:postcode":"3153",
    "sg:province":"VIC",
    "sg:tags":[
        "environmental",
        "consultant",
        "pollution"
    ],
    "wof:name":"Opec Systems Pty. Ltd",
    "wof:placetype":"venue"
},
  "geometry": {"coordinates":[145.284698486,-37.8503112793],"type":"Point"}
}