{
  "type": "Feature",
  "properties": {
    "addr:full":"11 Tantangara St Heckenberg NSW 2168",
    "addr:housenumber":"11",
    "addr:postcode":"2168",
    "addr:street":"Tantangara St",
    "iso:country":"AU",
    "sg:address":"11 Tantangara St",
    "sg:city":"Heckenberg",
    "sg:classifiers":[
        {
            "category":"Organizations",
            "subcategory":"Professional Association",
            "type":"Services"
        }
    ],
    "sg:phone":"+61 2 9607 8980",
    "sg:postcode":"2168",
    "sg:province":"NSW",
    "sg:tags":[
        "organisation",
        "business"
    ],
    "wof:name":"Institution of Gas Engineers (Australia)",
    "wof:placetype":"venue"
},
  "geometry": {"coordinates":[150.885131836,-33.9087562561],"type":"Point"}
}