{
  "type": "Feature",
  "properties": {
    "addr:full":"671a Underwood Rd Rochedale QLD 4123",
    "addr:housenumber":"671a",
    "addr:postcode":"4123",
    "addr:street":"Underwood Rd",
    "iso:country":"AU",
    "sg:address":"671a Underwood Rd",
    "sg:city":"Rochedale",
    "sg:classifiers":[
        {
            "category":"Building & Trades",
            "subcategory":"Construction",
            "type":"Services"
        }
    ],
    "sg:phone":"+61 7 3341 6444",
    "sg:postcode":"4123",
    "sg:province":"QLD",
    "sg:tags":[
        "earth",
        "excavating",
        "moving",
        "contractor"
    ],
    "wof:name":"Beliveau J G & A C",
    "wof:placetype":"venue"
},
  "geometry": {"coordinates":[153.119262695,-27.594909668],"type":"Point"}
}