{
  "type": "Feature",
  "properties": {
    "addr:full":"435 Hammond Rd Dandenong VIC 3175",
    "addr:housenumber":"435",
    "addr:postcode":"3175",
    "addr:street":"Hammond Rd",
    "iso:country":"AU",
    "sg:address":"435 Hammond Rd",
    "sg:city":"Dandenong",
    "sg:classifiers":[
        {
            "category":"Professional",
            "type":"Services"
        }
    ],
    "sg:phone":"+61 3 9768 2628",
    "sg:postcode":"3175",
    "sg:province":"VIC",
    "sg:tags":[
        "transport"
    ],
    "wof:name":"Oscan Couriers & Transport Services",
    "wof:placetype":"venue"
},
  "geometry": {"coordinates":[145.20362854000001,-38.0249595642],"type":"Point"}
}