{
  "type": "Feature",
  "properties": {
    "addr:full":"8 Benenden Ave Butler WA 6032",
    "addr:housenumber":"8",
    "addr:postcode":"6032",
    "addr:street":"Benenden Ave",
    "iso:country":"AU",
    "sg:address":"8 Benenden Ave",
    "sg:city":"Butler",
    "sg:classifiers":[
        {
            "category":"Building & Trades",
            "subcategory":"Construction",
            "type":"Services"
        }
    ],
    "sg:phone":"+61 409 977 169",
    "sg:postcode":"6032",
    "sg:province":"WA",
    "sg:tags":[
        "earth",
        "excavating",
        "moving",
        "contractor"
    ],
    "wof:name":"RJ & SJ Way",
    "wof:placetype":"venue"
},
  "geometry": {"coordinates":[115.75560760499999,-31.6355400085],"type":"Point"}
}