{
  "type": "Feature",
  "properties": {
    "addr:full":"75 Broughton St Camden NSW 2570",
    "addr:housenumber":"75",
    "addr:postcode":"2570",
    "addr:street":"Broughton St",
    "iso:country":"AU",
    "sg:address":"75 Broughton St",
    "sg:city":"Camden",
    "sg:classifiers":[
        {
            "category":"Health Services",
            "subcategory":"Health Practitioner",
            "type":"Services"
        }
    ],
    "sg:phone":"+61 2 4655 9477",
    "sg:postcode":"2570",
    "sg:province":"NSW",
    "sg:tags":[
        "physiotherapist"
    ],
    "wof:name":"Argyle Physiotherapy",
    "wof:placetype":"venue"
},
  "geometry": {"coordinates":[150.693191528,-34.0610809326],"type":"Point"}
}