{
  "type": "Feature",
  "properties": {
    "addr:full":"34 Baldock St Moorooka QLD 4105",
    "addr:housenumber":"34",
    "addr:postcode":"4105",
    "addr:street":"Baldock St",
    "iso:country":"AU",
    "sg:address":"34 Baldock St",
    "sg:city":"Moorooka",
    "sg:classifiers":[
        {
            "category":"Autos & Motor Vehicles",
            "subcategory":"Automobile Sales",
            "type":"Retail Goods"
        }
    ],
    "sg:phone":"+61 7 3892 4813",
    "sg:postcode":"4105",
    "sg:province":"QLD",
    "sg:tags":[
        "bus",
        "used",
        "truck"
    ],
    "wof:name":"Trucks Plus",
    "wof:placetype":"venue"
},
  "geometry": {"coordinates":[153.01528930699999,-27.5320549011],"type":"Point"}
}