{
  "type": "Feature",
  "properties": {
    "iso:country":"AU",
    "sg:address":"155 Stirling Hwy",
    "sg:city":"Nedlands",
    "sg:classifiers":[
        {
            "category":"Shopping",
            "subcategory":"Antiques",
            "type":"Retail Goods"
        }
    ],
    "sg:phone":"+61 8 9386 7088",
    "sg:postcode":"6009",
    "sg:province":"WA",
    "wof:name":"Turnstyle Collectables",
    "wof:placetype":"venue"
},
  "geometry": {"coordinates":[115.815819,-31.976606],"type":"Point"}
}