{
  "type": "Feature",
  "properties": {
    "iso:country":"AU",
    "sg:address":"27 Fernlea St",
    "sg:city":"Geebung",
    "sg:classifiers":[
        {
            "category":"Building & Trades",
            "subcategory":"Construction",
            "type":"Services"
        }
    ],
    "sg:phone":"+61 7 3359 0918",
    "sg:postcode":"4034",
    "sg:province":"QLD",
    "sg:tags":[
        "contractor"
    ],
    "wof:name":"Nolan A J",
    "wof:placetype":"venue"
},
  "geometry": {"coordinates":[153.03692599999999,-27.370045],"type":"Point"}
}