{
  "type": "Feature",
  "properties": {
    "addr:full":"38 Ogilvie St Denman NSW 2328",
    "addr:housenumber":"38",
    "addr:postcode":"2328",
    "addr:street":"Ogilvie St",
    "iso:country":"AU",
    "sg:address":"38 Ogilvie St",
    "sg:city":"Denman",
    "sg:classifiers":[
        {
            "category":"Wholesale",
            "subcategory":"Machinery & Supplies",
            "type":"Manufacturing & Wholesale Goods"
        }
    ],
    "sg:phone":"+61 2 6547 2204",
    "sg:postcode":"2328",
    "sg:province":"NSW",
    "sg:tags":[
        "agricultural"
    ],
    "wof:name":"Denman Dapkos",
    "wof:placetype":"venue"
},
  "geometry": {"coordinates":[150.68606567399999,-32.3891525269],"type":"Point"}
}