{
  "type": "Feature",
  "properties": {
    "iso:country":"AU",
    "sg:address":"461 Crown St",
    "sg:city":"West Wollongong",
    "sg:classifiers":[
        {
            "category":"Retail",
            "subcategory":"Veterinary Services",
            "type":"Services"
        }
    ],
    "sg:phone":"+61 2 4229 8888",
    "sg:postcode":"2500",
    "sg:province":"NSW",
    "sg:tags":[
        "surgeon"
    ],
    "wof:name":"Cannon & Ball",
    "wof:placetype":"venue"
},
  "geometry": {"coordinates":[150.876328,-34.42606],"type":"Point"}
}