{
  "type": "Feature",
  "properties": {
    "addr:full":"327-329 George St Sydney NSW 2000",
    "addr:housenumber":"327-329",
    "addr:postcode":"2000",
    "addr:street":"George St",
    "iso:country":"AU",
    "sg:address":"327-329 George St",
    "sg:city":"Sydney",
    "sg:classifiers":[
        {
            "category":"Travel",
            "subcategory":"Travel Agent",
            "type":"Entertainment"
        }
    ],
    "sg:phone":"+61 1300 738 833",
    "sg:postcode":"2000",
    "sg:province":"NSW",
    "sg:tags":[
        "consultant"
    ],
    "wof:name":"Queensland Travel Centre",
    "wof:placetype":"venue"
},
  "geometry": {"coordinates":[151.20698547399999,-33.8668327332],"type":"Point"}
}