{
  "type": "Feature",
  "properties": {
    "iso:country":"AU",
    "sg:address":"138 Wilson St",
    "sg:city":"Burnie",
    "sg:classifiers":[
        {
            "category":"Insurance",
            "subcategory":"Life Insurance",
            "type":"Services"
        }
    ],
    "sg:phone":"+61 3 6431 7430",
    "sg:postcode":"7320",
    "sg:province":"TAS",
    "wof:name":"Coles Financial Group",
    "wof:placetype":"venue"
},
  "geometry": {"coordinates":[145.90533400000001,-41.056587],"type":"Point"}
}