{
  "type": "Feature",
  "properties": {
    "addr:full":"University Of Canberra Kirinari St Bruce ACT 2617",
    "addr:postcode":"2617",
    "addr:street":"St",
    "iso:country":"AU",
    "sg:address":"University Of Canberra Kirinari St",
    "sg:city":"Bruce",
    "sg:classifiers":[
        {
            "category":"Education",
            "subcategory":"Kindergarten",
            "type":"Public Place"
        }
    ],
    "sg:phone":"+61 2 6201 2339",
    "sg:postcode":"2617",
    "sg:province":"ACT",
    "sg:tags":[
        "pre-schools"
    ],
    "wof:name":"Kirinari Early Childhood Centre",
    "wof:placetype":"venue"
},
  "geometry": {"coordinates":[149.085281372,-35.2424201965],"type":"Point"}
}