{
  "type": "Feature",
  "properties": {
    "addr:full":"133 Main Rd Neerim South VIC 3831",
    "addr:housenumber":"133",
    "addr:postcode":"3831",
    "addr:street":"Main Rd",
    "iso:country":"AU",
    "sg:address":"133 Main Rd",
    "sg:city":"Neerim South",
    "sg:classifiers":[
        {
            "category":"Food & Beverages",
            "subcategory":"Supermarket",
            "type":"Retail Goods"
        }
    ],
    "sg:phone":"+61 3 5628 1462",
    "sg:postcode":"3831",
    "sg:province":"VIC",
    "sg:tags":[
        "grocery",
        "store"
    ],
    "wof:name":"Smittys Supermarket",
    "wof:placetype":"venue"
},
  "geometry": {"coordinates":[145.95416299999999,-38.01688],"type":"Point"}
}