{
  "type": "Feature",
  "properties": {
    "addr:full":"31 South St Ipswich QLD 4305",
    "addr:housenumber":"31",
    "addr:postcode":"4305",
    "addr:street":"South St",
    "iso:country":"AU",
    "sg:address":"31 South St",
    "sg:city":"Ipswich",
    "sg:classifiers":[
        {
            "category":"Health Services",
            "subcategory":"Health Practitioner",
            "type":"Services"
        }
    ],
    "sg:phone":"+61 7 3812 0141",
    "sg:postcode":"4305",
    "sg:province":"QLD",
    "sg:tags":[
        "acupuncture"
    ],
    "wof:name":"Johnson Graham James",
    "wof:placetype":"venue"
},
  "geometry": {"coordinates":[152.76092529300001,-27.6165008545],"type":"Point"}
}