{
  "type": "Feature",
  "properties": {
    "addr:full":"29 William St Mannum SA 5238",
    "addr:housenumber":"29",
    "addr:postcode":"5238",
    "addr:street":"William St",
    "iso:country":"AU",
    "sg:address":"29 William St",
    "sg:city":"Mannum",
    "sg:classifiers":[
        {
            "category":"Personal",
            "subcategory":"Beauty Salon",
            "type":"Services"
        }
    ],
    "sg:phone":"+61 8 8569 1972",
    "sg:postcode":"5238",
    "sg:province":"SA",
    "wof:name":"Murray View Beauty Therapy",
    "wof:placetype":"venue"
},
  "geometry": {"coordinates":[139.31019592300001,-34.9144287109],"type":"Point"}
}