{
  "type": "Feature",
  "properties": {
    "iso:country":"AU",
    "sg:address":"191 Collins St",
    "sg:city":"Melbourne",
    "sg:classifiers":[
        {
            "category":"Arts & Performance",
            "subcategory":"Theater",
            "type":"Entertainment"
        }
    ],
    "sg:phone":"+61 3 9299 9500",
    "sg:postcode":"3000",
    "sg:province":"VIC",
    "sg:tags":[
        "theatre"
    ],
    "wof:name":"Regent Theatre",
    "wof:placetype":"venue"
},
  "geometry": {"coordinates":[144.967697144,-37.8152694702],"type":"Point"}
}