{
  "type": "Feature",
  "properties": {
    "addr:full":"PO Box 6190 Malabar NSW 2036",
    "addr:postcode":"2036",
    "iso:country":"AU",
    "sg:address":"PO Box 6190",
    "sg:city":"Malabar",
    "sg:classifiers":[
        {
            "category":"Social Services",
            "subcategory":"Child Care",
            "type":"Services"
        }
    ],
    "sg:phone":"+61 2 9345 4458",
    "sg:postcode":"2036",
    "sg:province":"NSW",
    "sg:tags":[
        "equipment",
        "identification"
    ],
    "wof:name":"Card Solutions Pty Ltd",
    "wof:placetype":"venue"
},
  "geometry": {"coordinates":[151.246994019,-33.9623413086],"type":"Point"}
}