{
  "type": "Feature",
  "properties": {
    "iso:country":"AU",
    "sg:address":"Unit 2/ 67 Meadow Ave",
    "sg:city":"Coopers Plains",
    "sg:classifiers":[
        {
            "category":"Home & Garden",
            "subcategory":"Hardware",
            "type":"Retail Goods"
        }
    ],
    "sg:phone":"+61 7 3274 3879",
    "sg:postcode":"4108",
    "sg:province":"QLD",
    "sg:tags":[
        "compressor",
        "air"
    ],
    "sg:website":"http://www.abcaircompressors.com.au",
    "wof:name":"ABC Air Compressors",
    "wof:placetype":"venue"
},
  "geometry": {"coordinates":[153.026443481,-27.5660667419],"type":"Point"}
}