{
  "type": "Feature",
  "properties": {
    "addr:full":"23 Fitzpatrick St Revesby NSW 2212",
    "addr:housenumber":"23",
    "addr:postcode":"2212",
    "addr:street":"Fitzpatrick St",
    "iso:country":"AU",
    "sg:address":"23 Fitzpatrick St",
    "sg:city":"Revesby",
    "sg:classifiers":[
        {
            "category":"Home & Garden",
            "subcategory":"Building Materials",
            "type":"Retail Goods"
        }
    ],
    "sg:phone":"+61 2 9792 2001",
    "sg:postcode":"2212",
    "sg:province":"NSW",
    "sg:tags":[
        "shutter",
        "roller",
        "grille"
    ],
    "sg:website":"http://www.rollashieldnsw.com",
    "wof:name":"Rollashield",
    "wof:placetype":"venue"
},
  "geometry": {"coordinates":[151.003387,-33.93597],"type":"Point"}
}