{
  "type": "Feature",
  "properties": {
    "addr:full":"34b Sunbeam Rd Glynde SA 5070",
    "addr:housenumber":"34b",
    "addr:postcode":"5070",
    "addr:street":"Sunbeam Rd",
    "iso:country":"AU",
    "sg:address":"34b Sunbeam Rd",
    "sg:city":"Glynde",
    "sg:classifiers":[
        {
            "category":"Food & Beverages",
            "subcategory":"Bakery",
            "type":"Retail Goods"
        }
    ],
    "sg:phone":"+61 8 8365 8183",
    "sg:postcode":"5070",
    "sg:province":"SA",
    "sg:tags":[
        "baker"
    ],
    "wof:name":"CiCia Batta",
    "wof:placetype":"venue"
},
  "geometry": {"coordinates":[138.65156555199999,-34.8954162598],"type":"Point"}
}