{
  "type": "Feature",
  "properties": {
    "addr:full":"178 Princes Hwy Nowra South NSW 2541",
    "addr:housenumber":"178",
    "addr:postcode":"2541",
    "addr:street":"Princes Hwy",
    "iso:country":"AU",
    "sg:address":"178 Princes Hwy",
    "sg:city":"Nowra South",
    "sg:classifiers":[
        {
            "category":"Home & Garden",
            "subcategory":"Home Furnishings",
            "type":"Retail Goods"
        }
    ],
    "sg:phone":"+61 2 4423 1866",
    "sg:postcode":"2541",
    "sg:province":"NSW",
    "sg:tags":[
        "candle"
    ],
    "wof:name":"Classic Candles",
    "wof:placetype":"venue"
},
  "geometry": {"coordinates":[150.60365295400001,-34.9141654968],"type":"Point"}
}