{
  "type": "Feature",
  "properties": {
    "iso:country":"AU",
    "sg:address":"26 Reserve Drv",
    "sg:city":"Mandurah",
    "sg:classifiers":[
        {
            "category":"Professional",
            "subcategory":"Engineering",
            "type":"Services"
        }
    ],
    "sg:phone":"+61 8 9535 8884",
    "sg:postcode":"6210",
    "sg:province":"WA",
    "sg:tags":[
        "engineer"
    ],
    "wof:name":"Steve Murray Engineering",
    "wof:placetype":"venue"
},
  "geometry": {"coordinates":[115.74305,-32.517578],"type":"Point"}
}