{
  "type": "Feature",
  "properties": {
    "addr:full":"1st Flr, 662 Newcastle St Leederville WA 6007",
    "addr:housenumber":"662",
    "addr:postcode":"6007",
    "addr:street":"Newcastle St",
    "iso:country":"AU",
    "sg:address":"1st Flr, 662 Newcastle St",
    "sg:city":"Leederville",
    "sg:classifiers":[
        {
            "category":"Real Estate",
            "subcategory":"Real Estate Agent",
            "type":"Services"
        }
    ],
    "sg:phone":"+61 8 9328 0909",
    "sg:postcode":"6007",
    "sg:province":"WA",
    "wof:name":"REMAX Australia (WA) Pty Ltd",
    "wof:placetype":"venue"
},
  "geometry": {"coordinates":[115.84261322,-31.9376468658],"type":"Point"}
}