{
  "type": "Feature",
  "properties": {
    "addr:full":"503 High St Prahran VIC 3181",
    "addr:housenumber":"503",
    "addr:postcode":"3181",
    "addr:street":"High St",
    "iso:country":"AU",
    "sg:address":"503 High St",
    "sg:city":"Prahran",
    "sg:classifiers":[
        {
            "category":"Wholesale",
            "subcategory":"Home Furnishings",
            "type":"Manufacturing & Wholesale Goods"
        }
    ],
    "sg:phone":"+61 3 9529 6211",
    "sg:postcode":"3181",
    "sg:province":"VIC",
    "wof:name":"Westbury Textiles",
    "wof:placetype":"venue"
},
  "geometry": {"coordinates":[145.00517273,-37.8533210754],"type":"Point"}
}