{
  "type": "Feature",
  "properties": {
    "addr:full":"5/ 209 Toorak Rd South Yarra VIC 3141",
    "addr:housenumber":"/ 209",
    "addr:postcode":"3141",
    "addr:street":"Toorak Rd",
    "iso:country":"AU",
    "sg:address":"5/ 209 Toorak Rd",
    "sg:city":"South Yarra",
    "sg:classifiers":[
        {
            "category":"Home & Garden",
            "subcategory":"Furniture",
            "type":"Retail Goods"
        }
    ],
    "sg:phone":"+61 3 9826 6652",
    "sg:postcode":"3141",
    "sg:province":"VIC",
    "sg:tags":[
        "business"
    ],
    "wof:name":"Ambient Contract Interiors",
    "wof:placetype":"venue"
},
  "geometry": {"coordinates":[144.994308472,-37.8391723633],"type":"Point"}
}