{
  "type": "Feature",
  "properties": {
    "addr:full":"15 Zillman Rd Hendra QLD 4011",
    "addr:housenumber":"15",
    "addr:postcode":"4011",
    "addr:street":"Zillman Rd",
    "iso:country":"AU",
    "sg:address":"15 Zillman Rd",
    "sg:city":"Hendra",
    "sg:classifiers":[
        {
            "category":"Food & Beverages",
            "subcategory":"Supermarket",
            "type":"Retail Goods"
        }
    ],
    "sg:phone":"+61 7 3268 1481",
    "sg:postcode":"4011",
    "sg:province":"QLD",
    "sg:tags":[
        "grocery",
        "store"
    ],
    "wof:name":"Foodstore",
    "wof:placetype":"venue"
},
  "geometry": {"coordinates":[153.06367499999999,-27.422138],"type":"Point"}
}