{
  "type": "Feature",
  "properties": {
    "addr:full":"2 Auaba Pl Warriewood NSW 2102",
    "addr:housenumber":"2",
    "addr:postcode":"2102",
    "addr:street":"Auaba Pl",
    "iso:country":"AU",
    "sg:address":"2 Auaba Pl",
    "sg:city":"Warriewood",
    "sg:classifiers":[
        {
            "category":"Building & Trades",
            "subcategory":"Plumbing",
            "type":"Services"
        }
    ],
    "sg:phone":"+61 419 231 476",
    "sg:postcode":"2102",
    "sg:province":"NSW",
    "sg:tags":[
        "plumber",
        "gasfitters"
    ],
    "wof:name":"M J Aspery",
    "wof:placetype":"venue"
},
  "geometry": {"coordinates":[151.301849,-33.688805],"type":"Point"}
}