{
  "type": "Feature",
  "properties": {
    "addr:full":"7- 9 Elm St Burwood Heights NSW 2136",
    "addr:housenumber":"9",
    "addr:postcode":"2136",
    "addr:street":"Elm St",
    "iso:country":"AU",
    "sg:address":"7- 9 Elm St",
    "sg:city":"Burwood Heights",
    "sg:classifiers":[
        {
            "category":"Social Services",
            "subcategory":"Child Care",
            "type":"Services"
        }
    ],
    "sg:phone":"+61 2 9745 1141",
    "sg:postcode":"2136",
    "sg:province":"NSW",
    "wof:name":"Burwood Neighbourhood Child Care Co-Op Ltd Long Day Care",
    "wof:placetype":"venue"
},
  "geometry": {"coordinates":[151.10243225100001,-33.8890228271],"type":"Point"}
}