{
  "type": "Feature",
  "properties": {
    "addr:full":"Sales Cottage, 1a Gawler St Nuriootpa SA 5355",
    "addr:housenumber":"1a",
    "addr:postcode":"5355",
    "addr:street":"Gawler St",
    "iso:country":"AU",
    "sg:address":"Sales Cottage, 1a Gawler St",
    "sg:city":"Nuriootpa",
    "sg:classifiers":[
        {
            "category":"Social Services",
            "subcategory":"Retirement Home",
            "type":"Services"
        }
    ],
    "sg:phone":"+61 8 8561 0400",
    "sg:postcode":"5355",
    "sg:province":"SA",
    "sg:tags":[
        "village"
    ],
    "wof:name":"Barossa Village Incorporated",
    "wof:placetype":"venue"
},
  "geometry": {"coordinates":[138.99545288100001,-34.4730529785],"type":"Point"}
}