{
  "type": "Feature",
  "properties": {
    "iso:country":"AU",
    "sg:address":"14 Bryants Rd",
    "sg:city":"Dandenong",
    "sg:classifiers":[
        {
            "category":"Building & Trades",
            "subcategory":"Cleaning & Sanitation",
            "type":"Services"
        }
    ],
    "sg:phone":"+61 3 9794 8604",
    "sg:postcode":"3175",
    "sg:province":"VIC",
    "sg:tags":[
        "window"
    ],
    "wof:name":"Crystal Clear Window Services",
    "wof:placetype":"venue"
},
  "geometry": {"coordinates":[145.21421814000001,-37.9943275452],"type":"Point"}
}