{
  "type": "Feature",
  "properties": {
    "addr:full":"15- 21 Kennedy St Bendigo VIC 3550",
    "addr:housenumber":"21",
    "addr:postcode":"3550",
    "addr:street":"Kennedy St",
    "iso:country":"AU",
    "sg:address":"15- 21 Kennedy St",
    "sg:city":"Bendigo",
    "sg:classifiers":[
        {
            "category":"Home & Garden",
            "subcategory":"Hardware",
            "type":"Retail Goods"
        }
    ],
    "sg:phone":"+61 3 5444 5477",
    "sg:postcode":"3550",
    "sg:province":"VIC",
    "sg:tags":[
        "plumber",
        "supply"
    ],
    "wof:name":"Burgundy Plumbtec",
    "wof:placetype":"venue"
},
  "geometry": {"coordinates":[144.29217529300001,-36.75598526],"type":"Point"}
}