{
  "type": "Feature",
  "properties": {
    "addr:full":"Groper Creek Rd Home Hill QLD 4806",
    "addr:postcode":"4806",
    "addr:street":"Creek Rd",
    "iso:country":"AU",
    "sg:address":"Groper Creek Rd",
    "sg:city":"Home Hill",
    "sg:classifiers":[
        {
            "category":"Farming",
            "subcategory":"Farm",
            "type":"Manufacturing & Wholesale Goods"
        }
    ],
    "sg:phone":"+61 7 4782 1661",
    "sg:postcode":"4806",
    "sg:province":"QLD",
    "sg:tags":[
        "farmer"
    ],
    "wof:name":"Papale M & M",
    "wof:placetype":"venue"
},
  "geometry": {"coordinates":[147.43261718799999,-19.6660423279],"type":"Point"}
}