{
  "type": "Feature",
  "properties": {
    "addr:full":"Rear of 4 O&#039;Neill St Leongatha VIC 3953",
    "addr:housenumber":"rear",
    "addr:postcode":"3953",
    "addr:street":"Of;Neill St",
    "iso:country":"AU",
    "sg:address":"Rear of 4 O&#039;Neill St",
    "sg:city":"Leongatha",
    "sg:classifiers":[
        {
            "category":"Professional",
            "subcategory":"Engineering",
            "type":"Services"
        }
    ],
    "sg:phone":"+61 418 121 097",
    "sg:postcode":"3953",
    "sg:province":"VIC",
    "sg:tags":[
        "engineer"
    ],
    "wof:name":"D M V Engineering",
    "wof:placetype":"venue"
},
  "geometry": {"coordinates":[145.94992065400001,-38.4703865051],"type":"Point"}
}