{
  "type": "Feature",
  "properties": {
    "addr:full":"Shop 4 Metcentre 273 George St Sydney NSW 2000",
    "addr:housenumber":"shop 4;273",
    "addr:postcode":"2000",
    "addr:street":"Metcentre;George St",
    "iso:country":"AU",
    "sg:address":"Shop 4 Metcentre 273 George St",
    "sg:city":"Sydney",
    "sg:classifiers":[
        {
            "category":"Shopping",
            "subcategory":"Clothing, Apparel, & Fashions",
            "type":"Retail Goods"
        }
    ],
    "sg:phone":"+61 2 9252 2933",
    "sg:postcode":"2000",
    "sg:province":"NSW",
    "sg:tags":[
        "lady",
        "wear"
    ],
    "wof:name":"Sheike & Co Pty Ltd",
    "wof:placetype":"venue"
},
  "geometry": {"coordinates":[151.20718383799999,-33.8650398254],"type":"Point"}
}