{
  "type": "Feature",
  "properties": {
    "addr:full":"96 Stirling Hwy North Fremantle WA 6159",
    "addr:housenumber":"96",
    "addr:postcode":"6159",
    "addr:street":"Stirling Hwy",
    "iso:country":"AU",
    "sg:address":"96 Stirling Hwy",
    "sg:city":"North Fremantle",
    "sg:classifiers":[
        {
            "category":"Shopping",
            "subcategory":"Pets & Pet Supplies",
            "type":"Retail Goods"
        }
    ],
    "sg:phone":"+61 8 9335 8200",
    "sg:postcode":"6159",
    "sg:province":"WA",
    "sg:tags":[
        "food"
    ],
    "sg:website":"http://www.naturalbalance.net.au",
    "wof:name":"Natural Balance (WA)",
    "wof:placetype":"venue"
},
  "geometry": {"coordinates":[115.75273900000001,-32.031254],"type":"Point"}
}