{
  "type": "Feature",
  "properties": {
    "iso:country":"AU",
    "sg:address":"34 Goobar St",
    "sg:city":"Narrabri",
    "sg:classifiers":[
        {
            "category":"Wholesale",
            "subcategory":"Scrap",
            "type":"Manufacturing & Wholesale Goods"
        }
    ],
    "sg:phone":"+61 2 6792 1195",
    "sg:postcode":"2390",
    "sg:province":"NSW",
    "sg:tags":[
        "merchant",
        "metal"
    ],
    "wof:name":"French's Scrap Metal",
    "wof:placetype":"venue"
},
  "geometry": {"coordinates":[149.75471496599999,-30.3386306763],"type":"Point"}
}