{
  "type": "Feature",
  "properties": {
    "addr:full":"158 Booran Rd Glen Huntly VIC 3163",
    "addr:housenumber":"158",
    "addr:postcode":"3163",
    "addr:street":"Booran Rd",
    "iso:country":"AU",
    "sg:address":"158 Booran Rd",
    "sg:city":"Glen Huntly",
    "sg:classifiers":[
        {
            "category":"Professional",
            "subcategory":"Computer Services",
            "type":"Services"
        }
    ],
    "sg:phone":"+61 3 9578 3737",
    "sg:postcode":"3163",
    "sg:province":"VIC",
    "sg:tags":[
        "consultant",
        "system"
    ],
    "wof:name":"Perseus Systems IT P/L",
    "wof:placetype":"venue"
},
  "geometry": {"coordinates":[145.03692626899999,-37.8934707642],"type":"Point"}
}