{
  "type": "Feature",
  "properties": {
    "addr:full":"Level 1, 600 Nicholson St Fitzroy North VIC 3068",
    "addr:housenumber":"600",
    "addr:postcode":"3068",
    "addr:street":"Nicholson St",
    "iso:country":"AU",
    "sg:address":"Level 1, 600 Nicholson St",
    "sg:city":"Fitzroy North",
    "sg:classifiers":[
        {
            "category":"Professional",
            "subcategory":"Employment Agencies",
            "type":"Services"
        }
    ],
    "sg:phone":"+61 3 9482 7774",
    "sg:postcode":"3068",
    "sg:province":"VIC",
    "wof:name":"Bluestone Personnel",
    "wof:placetype":"venue"
},
  "geometry": {"coordinates":[144.97723388700001,-37.7863006592],"type":"Point"}
}