{
  "type": "Feature",
  "properties": {
    "iso:country":"AU",
    "sg:address":"97- 99 Balfour St",
    "sg:city":"Launceston",
    "sg:classifiers":[
        {
            "category":"Retail",
            "subcategory":"Car Wash",
            "type":"Services"
        }
    ],
    "sg:phone":"+61 3 6334 3358",
    "sg:postcode":"7250",
    "sg:province":"TAS",
    "sg:tags":[
        "truck",
        "cleaning"
    ],
    "wof:name":"Bumpatech",
    "wof:placetype":"venue"
},
  "geometry": {"coordinates":[147.13822937,-41.4454078674],"type":"Point"}
}