{
  "type": "Feature",
  "properties": {
    "addr:full":"78- 82 Megalong St Katoomba NSW 2780",
    "addr:housenumber":"82",
    "addr:postcode":"2780",
    "addr:street":"Megalong St",
    "iso:country":"AU",
    "sg:address":"78- 82 Megalong St",
    "sg:city":"Katoomba",
    "sg:classifiers":[
        {
            "category":"Manufacturing",
            "subcategory":"Motor Vehicles & Parts",
            "type":"Manufacturing & Wholesale Goods"
        }
    ],
    "sg:phone":"+61 2 4784 2400",
    "sg:postcode":"2780",
    "sg:province":"NSW",
    "sg:tags":[
        "replacement"
    ],
    "wof:name":"Scott's Auto One",
    "wof:placetype":"venue"
},
  "geometry": {"coordinates":[150.323562622,-33.7131271362],"type":"Point"}
}