{
  "type": "Feature",
  "properties": {
    "addr:full":"Shop 16, Currimundi Market Pl, Nicklin Way Currimundi QLD 4551",
    "addr:housenumber":"shop 16",
    "addr:postcode":"4551",
    "addr:street":"Currimundi Market Pl Nicklin Way",
    "iso:country":"AU",
    "sg:address":"Shop 16, Currimundi Market Pl, Nicklin Way",
    "sg:city":"Currimundi",
    "sg:classifiers":[
        {
            "category":"Shopping",
            "subcategory":"Bicycles & Sporting Goods",
            "type":"Retail Goods"
        }
    ],
    "sg:phone":"+61 7 5493 2550",
    "sg:postcode":"4551",
    "sg:province":"QLD",
    "sg:tags":[
        "chemical",
        "equipment",
        "pool",
        "swimming"
    ],
    "wof:name":"Swimart Pool & Spa Services",
    "wof:placetype":"venue"
},
  "geometry": {"coordinates":[153.12217712399999,-26.7688045502],"type":"Point"}
}