{
  "type": "Feature",
  "properties": {
    "addr:full":"Suite 401 350 Latrobe St Melbourne VIC 3000",
    "addr:housenumber":"350",
    "addr:postcode":"3000",
    "addr:street":"Latrobe St",
    "iso:country":"AU",
    "sg:address":"Suite 401 350 Latrobe St",
    "sg:city":"Melbourne",
    "sg:classifiers":[
        {
            "category":"Professional",
            "subcategory":"Management & Consulting",
            "type":"Services"
        }
    ],
    "sg:phone":"+61 3 9328 1133",
    "sg:postcode":"3000",
    "sg:province":"VIC",
    "sg:tags":[
        "consultant"
    ],
    "wof:name":"CentreBrain Pty Ltd",
    "wof:placetype":"venue"
},
  "geometry": {"coordinates":[144.95941162099999,-37.810760498],"type":"Point"}
}