{
  "type": "Feature",
  "properties": {
    "addr:full":"Unit G7, 7 Hepher Rd Campbelltown NSW 2560",
    "addr:housenumber":"7",
    "addr:postcode":"2560",
    "addr:street":"Hepher Rd",
    "iso:country":"AU",
    "sg:address":"Unit G7, 7 Hepher Rd",
    "sg:city":"Campbelltown",
    "sg:classifiers":[
        {
            "category":"Autos & Motor Vehicles",
            "subcategory":"Auto Supplies",
            "type":"Retail Goods"
        }
    ],
    "sg:phone":"+61 2 4620 9777",
    "sg:postcode":"2560",
    "sg:province":"NSW",
    "sg:tags":[
        "garage",
        "equipment"
    ],
    "wof:name":"Automotive Workshop Equipment Pty Ltd",
    "wof:placetype":"venue"
},
  "geometry": {"coordinates":[150.80874633799999,-34.0566978455],"type":"Point"}
}