{
  "type": "Feature",
  "properties": {
    "addr:full":"698 Beaudesert Rd Rocklea QLD 4106",
    "addr:housenumber":"698",
    "addr:postcode":"4106",
    "addr:street":"Beaudesert Rd",
    "iso:country":"AU",
    "sg:address":"698 Beaudesert Rd",
    "sg:city":"Rocklea",
    "sg:classifiers":[
        {
            "category":"Manufacturing",
            "subcategory":"Tools & Machinery",
            "type":"Manufacturing & Wholesale Goods"
        }
    ],
    "sg:phone":"+61 7 3277 7955",
    "sg:postcode":"4106",
    "sg:province":"QLD",
    "sg:tags":[
        "earth",
        "excavating",
        "moving",
        "equipment"
    ],
    "wof:name":"Alljap Machinery",
    "wof:placetype":"venue"
},
  "geometry": {"coordinates":[153.02084350600001,-27.5563259125],"type":"Point"}
}