{
  "type": "Feature",
  "properties": {
    "iso:country":"AU",
    "sg:address":"197 Old South Rd",
    "sg:city":"Reynella",
    "sg:classifiers":[
        {
            "category":"Cafe",
            "type":"Food & Drink"
        }
    ],
    "sg:phone":"+61 8 8381 1268",
    "sg:postcode":"5161",
    "sg:province":"SA",
    "wof:name":"Jules Snack Bar",
    "wof:placetype":"venue"
},
  "geometry": {"coordinates":[138.53613281200001,-35.096572876],"type":"Point"}
}