{
  "type": "Feature",
  "properties": {
    "iso:country":"AU",
    "sg:address":"290 The Entrance Rd",
    "sg:city":"Long Jetty",
    "sg:classifiers":[
        {
            "category":"Retail",
            "subcategory":"Auto Repair",
            "type":"Services"
        }
    ],
    "sg:phone":"+61 2 4333 3000",
    "sg:postcode":"2261",
    "sg:province":"NSW",
    "sg:tags":[
        "repairer",
        "motor",
        "engineer"
    ],
    "wof:name":"ANI Automotive",
    "wof:placetype":"venue"
},
  "geometry": {"coordinates":[151.484436,-33.359089],"type":"Point"}
}