{
  "type": "Feature",
  "properties": {
    "addr:full":"Shop 3 7 Bonner Drv Malaga WA 6090",
    "addr:housenumber":"shop;7",
    "addr:postcode":"6090",
    "addr:street":"Bonner Drv",
    "iso:country":"AU",
    "sg:address":"Shop 3 7 Bonner Drv",
    "sg:city":"Malaga",
    "sg:classifiers":[
        {
            "category":"Fast Food",
            "type":"Food & Drink"
        }
    ],
    "sg:phone":"+61 8 9248 5158",
    "sg:postcode":"6090",
    "sg:province":"WA",
    "sg:tags":[
        "away",
        "take"
    ],
    "wof:name":"Sunshine Hong Kong Chinese",
    "wof:placetype":"venue"
},
  "geometry": {"coordinates":[115.880470276,-31.8507328033],"type":"Point"}
}