{
  "type": "Feature",
  "properties": {
    "iso:country":"AU",
    "sg:address":"882 Oxley Rd",
    "sg:city":"Oxley",
    "sg:classifiers":[
        {
            "category":"Manufacturing",
            "subcategory":"Jewelry",
            "type":"Manufacturing & Wholesale Goods"
        }
    ],
    "sg:phone":"+61 7 3379 9442",
    "sg:postcode":"4075",
    "sg:province":"QLD",
    "sg:tags":[
        "designer",
        "jewellery"
    ],
    "wof:name":"Oxley Designs",
    "wof:placetype":"venue"
},
  "geometry": {"coordinates":[152.97966003400001,-27.5512313843],"type":"Point"}
}