{
  "type": "Feature",
  "properties": {
    "iso:country":"AU",
    "sg:address":"22 Tillegra St",
    "sg:city":"Maryland",
    "sg:classifiers":[
        {
            "category":"Professional",
            "subcategory":"Art Services",
            "type":"Services"
        }
    ],
    "sg:phone":"+61 2 4951 3304",
    "sg:postcode":"2287",
    "sg:province":"NSW",
    "sg:tags":[
        "decorator",
        "painter"
    ],
    "wof:name":"Cooke K J & L D",
    "wof:placetype":"venue"
},
  "geometry": {"coordinates":[151.65536499000001,-32.8846740723],"type":"Point"}
}