{
  "type": "Feature",
  "properties": {
    "addr:full":"Level 2, 802 Pacific Hwy Gordon NSW 2072",
    "addr:housenumber":"802",
    "addr:postcode":"2072",
    "addr:street":"Pacific Hwy",
    "iso:country":"AU",
    "sg:address":"Level 2, 802 Pacific Hwy",
    "sg:city":"Gordon",
    "sg:classifiers":[
        {
            "category":"Real Estate",
            "subcategory":"Real Estate Agent",
            "type":"Services"
        }
    ],
    "sg:phone":"+61 2 9499 4999",
    "sg:postcode":"2072",
    "sg:province":"NSW",
    "wof:name":"Quartile Research",
    "wof:placetype":"venue"
},
  "geometry": {"coordinates":[151.15237426799999,-33.7550544739],"type":"Point"}
}