{
  "type": "Feature",
  "properties": {
    "iso:country":"AU",
    "sg:address":"25 Mitchell St",
    "sg:city":"Bourke",
    "sg:classifiers":[
        {
            "category":"Government",
            "subcategory":"Fire Station",
            "type":"Public Place"
        }
    ],
    "sg:phone":"+61 2 6872 2568",
    "sg:postcode":"2840",
    "sg:province":"NSW",
    "sg:tags":[
        "brigade"
    ],
    "wof:name":"Fire Brigades-NSW",
    "wof:placetype":"venue"
},
  "geometry": {"coordinates":[145.937286,-30.088612],"type":"Point"}
}