{
  "type": "Feature",
  "properties": {
    "addr:full":"18 Iris St Guildford NSW 2161",
    "addr:housenumber":"18",
    "addr:postcode":"2161",
    "addr:street":"Iris St",
    "iso:country":"AU",
    "sg:address":"18 Iris St",
    "sg:city":"Guildford",
    "sg:classifiers":[
        {
            "category":"Building & Trades",
            "subcategory":"Construction",
            "type":"Services"
        }
    ],
    "sg:phone":"+61 2 9892 1314",
    "sg:postcode":"2161",
    "sg:province":"NSW",
    "sg:tags":[
        "home",
        "air conditioning"
    ],
    "wof:name":"Top Line Installations",
    "wof:placetype":"venue"
},
  "geometry": {"coordinates":[150.959152222,-33.8490753174],"type":"Point"}
}