{
  "type": "Feature",
  "properties": {
    "addr:full":"3 Bray St Hastings VIC 3915",
    "addr:housenumber":"3",
    "addr:postcode":"3915",
    "addr:street":"Bray St",
    "iso:country":"AU",
    "sg:address":"3 Bray St",
    "sg:city":"Hastings",
    "sg:classifiers":[
        {
            "category":"Manufacturing",
            "subcategory":"Metals",
            "type":"Manufacturing & Wholesale Goods"
        }
    ],
    "sg:phone":"+61 3 5979 7133",
    "sg:postcode":"3915",
    "sg:province":"VIC",
    "sg:tags":[
        "steel",
        "fabricator",
        "mfrs"
    ],
    "wof:name":"R M G Engineering Pty Ltd",
    "wof:placetype":"venue"
},
  "geometry": {"coordinates":[145.182296753,-38.3142242432],"type":"Point"}
}