{
  "type": "Feature",
  "properties": {
    "iso:country":"AU",
    "sg:address":"Shop 1, 35 Lloyd Ave",
    "sg:city":"Chain Valley Bay",
    "sg:classifiers":[
        {
            "category":"Food & Beverages",
            "subcategory":"Liquor & Beverages",
            "type":"Retail Goods"
        }
    ],
    "sg:phone":"+61 2 4358 1430",
    "sg:postcode":"2259",
    "sg:province":"NSW",
    "sg:tags":[
        "store"
    ],
    "wof:name":"Chain Valley Bay Liquor Shop",
    "wof:placetype":"venue"
},
  "geometry": {"coordinates":[151.56373596200001,-33.1747245789],"type":"Point"}
}