{
  "type": "Feature",
  "properties": {
    "addr:full":"Unit 3/ 13 Resolution Drv Unanderra NSW 2526",
    "addr:housenumber":"13",
    "addr:postcode":"2526",
    "addr:street":"Resolution Drv",
    "iso:country":"AU",
    "sg:address":"Unit 3/ 13 Resolution Drv",
    "sg:city":"Unanderra",
    "sg:classifiers":[
        {
            "category":"Professional",
            "type":"Services"
        }
    ],
    "sg:phone":"+61 2 4272 7626",
    "sg:postcode":"2526",
    "sg:province":"NSW",
    "sg:tags":[
        "shop",
        "fitting"
    ],
    "wof:name":"Kyrio's Kitchens",
    "wof:placetype":"venue"
},
  "geometry": {"coordinates":[150.85385131800001,-34.4559211731],"type":"Point"}
}