{
  "type": "Feature",
  "properties": {
    "addr:full":"18 Everest St Sunnybank QLD 4109",
    "addr:housenumber":"18",
    "addr:postcode":"4109",
    "addr:street":"Everest St",
    "iso:country":"AU",
    "sg:address":"18 Everest St",
    "sg:city":"Sunnybank",
    "sg:classifiers":[
        {
            "category":"Utilities",
            "subcategory":"Electric",
            "type":"Services"
        }
    ],
    "sg:phone":"+61 7 3345 8761",
    "sg:postcode":"4109",
    "sg:province":"QLD",
    "sg:tags":[
        "electrical",
        "contractor"
    ],
    "wof:name":"Angus Electrical",
    "wof:placetype":"venue"
},
  "geometry": {"coordinates":[153.047607422,-27.5760440826],"type":"Point"}
}