{
  "type": "Feature",
  "properties": {
    "addr:full":"10 Churchill Ave Strathfield NSW 2135",
    "addr:housenumber":"10",
    "addr:postcode":"2135",
    "addr:street":"Churchill Ave",
    "iso:country":"AU",
    "sg:address":"10 Churchill Ave",
    "sg:city":"Strathfield",
    "sg:classifiers":[
        {
            "category":"Cafe",
            "type":"Food & Drink"
        }
    ],
    "sg:phone":"+61 2 9764 5811",
    "sg:postcode":"2135",
    "sg:province":"NSW",
    "wof:name":"Gloria Jeans Coffees",
    "wof:placetype":"venue"
},
  "geometry": {"coordinates":[151.09080505399999,-33.8724784851],"type":"Point"}
}