{
  "type": "Feature",
  "properties": {
    "iso:country":"AU",
    "sg:address":"2217 Arthur Hwy",
    "sg:city":"Copping",
    "sg:classifiers":[
        {
            "category":"Travel",
            "subcategory":"Hotels & Motels",
            "type":"Entertainment"
        }
    ],
    "sg:phone":"+61 3 6253 5373",
    "sg:postcode":"7174",
    "sg:province":"TAS",
    "wof:name":"Copping Colonial & Convict Collection",
    "wof:placetype":"venue"
},
  "geometry": {"coordinates":[147.800461,-42.819645],"type":"Point"}
}