{
  "type": "Feature",
  "properties": {
    "addr:full":"599- 601 Pacific Hwy Belmont North NSW 2280",
    "addr:housenumber":"601",
    "addr:postcode":"2280",
    "addr:street":"Pacific Hwy",
    "iso:country":"AU",
    "sg:address":"599- 601 Pacific Hwy",
    "sg:city":"Belmont North",
    "sg:classifiers":[
        {
            "category":"Building & Trades",
            "subcategory":"Cleaning & Sanitation",
            "type":"Services"
        }
    ],
    "sg:phone":"+61 1800 455 577",
    "sg:postcode":"2280",
    "sg:province":"NSW",
    "sg:tags":[
        "cleaner",
        "repairer",
        "roof"
    ],
    "wof:name":"Belmont Home Improvements",
    "wof:placetype":"venue"
},
  "geometry": {"coordinates":[151.66021728499999,-33.0371246338],"type":"Point"}
}