{
  "type": "Feature",
  "properties": {
    "iso:country":"AU",
    "sg:address":"64 Pender St",
    "sg:city":"Preston",
    "sg:classifiers":[
        {
            "category":"Home & Garden",
            "subcategory":"Carpets & Floor Coverings",
            "type":"Retail Goods"
        }
    ],
    "sg:phone":"+61 3 9478 6281",
    "sg:postcode":"3072",
    "sg:province":"VIC",
    "sg:tags":[
        "layer",
        "planner"
    ],
    "wof:name":"Neil I W",
    "wof:placetype":"venue"
},
  "geometry": {"coordinates":[145.006912231,-37.7365188599],"type":"Point"}
}