{
  "type": "Feature",
  "properties": {
    "addr:full":"200 Campbell St Darlinghurst NSW 2010",
    "addr:housenumber":"200",
    "addr:postcode":"2010",
    "addr:street":"Campbell St",
    "iso:country":"AU",
    "sg:address":"200 Campbell St",
    "sg:city":"Darlinghurst",
    "sg:classifiers":[
        {
            "category":"Health Services",
            "subcategory":"Health Practitioner",
            "type":"Services"
        }
    ],
    "sg:phone":"+61 2 9326 0314",
    "sg:postcode":"2010",
    "sg:province":"NSW",
    "sg:tags":[
        "physiotherapist"
    ],
    "wof:name":"Raftery Simon",
    "wof:placetype":"venue"
},
  "geometry": {"coordinates":[151.215896606,-33.880897522],"type":"Point"}
}