{
  "type": "Feature",
  "properties": {
    "addr:full":"Webster St Mortlake VIC 3272",
    "addr:postcode":"3272",
    "addr:street":"Webster St",
    "iso:country":"AU",
    "sg:address":"Webster St",
    "sg:city":"Mortlake",
    "sg:classifiers":[
        {
            "category":"Arena",
            "subcategory":"Sports Club",
            "type":"Entertainment"
        }
    ],
    "sg:phone":"+61 3 5599 2275",
    "sg:postcode":"3272",
    "sg:province":"VIC",
    "sg:tags":[
        "australian",
        "football",
        "rule"
    ],
    "wof:name":"Mortlake Football Club",
    "wof:placetype":"venue"
},
  "geometry": {"coordinates":[142.80549621599999,-38.0801925659],"type":"Point"}
}