{
  "type": "Feature",
  "properties": {
    "addr:full":"Homemakers Supa Centre Cnr Wyong Rd & Bryant Drv Tuggerah NSW 2259",
    "addr:postcode":"2259",
    "addr:street":"Cnr Wyong Rd & Bryant Drv",
    "iso:country":"AU",
    "sg:address":"Homemakers Supa Centre Cnr Wyong Rd & Bryant Drv",
    "sg:city":"Tuggerah",
    "sg:classifiers":[
        {
            "category":"Home & Garden",
            "subcategory":"Hardware",
            "type":"Retail Goods"
        }
    ],
    "sg:phone":"+61 2 4353 4335",
    "sg:postcode":"2259",
    "sg:province":"NSW",
    "sg:tags":[
        "tarpaulin"
    ],
    "wof:name":"Kangaroo Tent City & BBQs#",
    "wof:placetype":"venue"
},
  "geometry": {"coordinates":[151.41911315900001,-33.3097610474],"type":"Point"}
}