{
  "type": "Feature",
  "properties": {
    "addr:full":"Lakeside Joondalup Shopping City 420 Joondalup Drv Joondalup WA 6027",
    "addr:housenumber":"420",
    "addr:postcode":"6027",
    "addr:street":"Joondalup Drv",
    "iso:country":"AU",
    "sg:address":"Lakeside Joondalup Shopping City 420 Joondalup Drv",
    "sg:city":"Joondalup",
    "sg:classifiers":[
        {
            "category":"Fast Food",
            "type":"Food & Drink"
        }
    ],
    "sg:phone":"+61 8 9301 0303",
    "sg:postcode":"6027",
    "sg:province":"WA",
    "sg:tags":[
        "away",
        "take"
    ],
    "wof:name":"Wokinabox",
    "wof:placetype":"venue"
},
  "geometry": {"coordinates":[115.764228821,-31.7353992462],"type":"Point"}
}