{
  "type": "Feature",
  "properties": {
    "addr:full":"Shp 5/ 228 James St Northbridge WA 6003",
    "addr:housenumber":"/ 228",
    "addr:postcode":"6003",
    "addr:street":"James St",
    "iso:country":"AU",
    "sg:address":"Shp 5/ 228 James St",
    "sg:city":"Northbridge",
    "sg:classifiers":[
        {
            "category":"Travel",
            "subcategory":"Travel Agent",
            "type":"Entertainment"
        }
    ],
    "sg:phone":"+61 8 9227 9779",
    "sg:postcode":"6003",
    "sg:province":"WA",
    "sg:tags":[
        "consultant"
    ],
    "wof:name":"The Holiday Stop",
    "wof:placetype":"venue"
},
  "geometry": {"coordinates":[115.853919983,-31.9463386536],"type":"Point"}
}