{
  "type": "Feature",
  "properties": {
    "iso:country":"AU",
    "sg:address":"Unit 4/ 5 Secam St",
    "sg:city":"Mansfield",
    "sg:classifiers":[
        {
            "category":"Government",
            "subcategory":"Fire Station",
            "type":"Public Place"
        }
    ],
    "sg:phone":"+61 7 3849 8309",
    "sg:postcode":"4122",
    "sg:province":"QLD",
    "sg:tags":[
        "equipment",
        "protection",
        "consultant"
    ],
    "wof:name":"Foamguard Vehicle Suppression Systems",
    "wof:placetype":"venue"
},
  "geometry": {"coordinates":[153.097900391,-27.5326652527],"type":"Point"}
}