{
  "type": "Feature",
  "properties": {
    "iso:country":"AU",
    "sg:address":"26 Stephenson St",
    "sg:city":"Yuleba",
    "sg:classifiers":[
        {
            "category":"Food & Beverages",
            "subcategory":"Groceries & Convenience Stores",
            "type":"Retail Goods"
        }
    ],
    "sg:phone":"+61 7 4623 5102",
    "sg:postcode":"4427",
    "sg:province":"QLD",
    "wof:name":"Yuleba General Store",
    "wof:placetype":"venue"
},
  "geometry": {"coordinates":[149.37597656200001,-26.6116466522],"type":"Point"}
}