{
  "type": "Feature",
  "properties": {
    "addr:full":"319 Beamish St Campsie NSW 2194",
    "addr:housenumber":"319",
    "addr:postcode":"2194",
    "addr:street":"Beamish St",
    "iso:country":"AU",
    "sg:address":"319 Beamish St",
    "sg:city":"Campsie",
    "sg:classifiers":[
        {
            "category":"Health Services",
            "subcategory":"Doctor",
            "type":"Services"
        }
    ],
    "sg:phone":"+61 2 9718 7333",
    "sg:postcode":"2194",
    "sg:province":"NSW",
    "sg:tags":[
        "medical",
        "practitioner"
    ],
    "wof:name":"Rapaport Adam Dr",
    "wof:placetype":"venue"
},
  "geometry": {"coordinates":[151.10429400000001,-33.913815],"type":"Point"}
}