{
  "type": "Feature",
  "properties": {
    "addr:full":"162 Federal St Narrogin WA 6312",
    "addr:housenumber":"162",
    "addr:postcode":"6312",
    "addr:street":"Federal St",
    "iso:country":"AU",
    "sg:address":"162 Federal St",
    "sg:city":"Narrogin",
    "sg:classifiers":[
        {
            "category":"Autos & Motor Vehicles",
            "subcategory":"Automobile Sales",
            "type":"Retail Goods"
        }
    ],
    "sg:phone":"+61 8 9881 2405",
    "sg:postcode":"6312",
    "sg:province":"WA",
    "sg:tags":[
        "car",
        "new"
    ],
    "wof:name":"Mazda Country",
    "wof:placetype":"venue"
},
  "geometry": {"coordinates":[117.17841339100001,-32.9423408508],"type":"Point"}
}