{
  "type": "Feature",
  "properties": {
    "iso:country":"AU",
    "sg:address":"20 Fourth Ave",
    "sg:city":"Sunshine",
    "sg:classifiers":[
        {
            "category":"Manufacturing",
            "subcategory":"Chemicals & Compounds",
            "type":"Manufacturing & Wholesale Goods"
        }
    ],
    "sg:phone":"+61 3 9311 3313",
    "sg:postcode":"3020",
    "sg:province":"VIC",
    "sg:tags":[
        "electroplating"
    ],
    "wof:name":"In Motion Metal Finishing",
    "wof:placetype":"venue"
},
  "geometry": {"coordinates":[144.83599899999999,-37.80064],"type":"Point"}
}