{
  "type": "Feature",
  "properties": {
    "iso:country":"AU",
    "sg:address":"29 Commercial Rd",
    "sg:city":"Maroochydore",
    "sg:classifiers":[
        {
            "category":"Professional",
            "type":"Services"
        }
    ],
    "sg:phone":"+61 7 5443 3799",
    "sg:postcode":"4558",
    "sg:province":"QLD",
    "sg:tags":[
        "auctioneer"
    ],
    "wof:name":"Sunshine Coast Auctions",
    "wof:placetype":"venue"
},
  "geometry": {"coordinates":[153.06442260700001,-26.6539497375],"type":"Point"}
}