{
  "type": "Feature",
  "properties": {
    "addr:full":"20 Airy St Wacol QLD 4076",
    "addr:housenumber":"20",
    "addr:postcode":"4076",
    "addr:street":"Airy St",
    "iso:country":"AU",
    "sg:address":"20 Airy St",
    "sg:city":"Wacol",
    "sg:classifiers":[
        {
            "category":"Building & Trades",
            "subcategory":"Construction",
            "type":"Services"
        }
    ],
    "sg:phone":"+61 7 3271 2233",
    "sg:postcode":"4076",
    "sg:province":"QLD",
    "sg:tags":[
        "bridge",
        "contractor"
    ],
    "wof:name":"Dowstress Pty Ltd",
    "wof:placetype":"venue"
},
  "geometry": {"coordinates":[152.924957275,-27.587480545],"type":"Point"}
}