{
  "type": "Feature",
  "properties": {
    "addr:full":"40 Ocean View Drv Wamberal NSW 2260",
    "addr:housenumber":"40",
    "addr:postcode":"2260",
    "addr:street":"Ocean View Drv",
    "iso:country":"AU",
    "sg:address":"40 Ocean View Drv",
    "sg:city":"Wamberal",
    "sg:classifiers":[
        {
            "category":"Real Estate",
            "subcategory":"Real Estate Agent",
            "type":"Services"
        }
    ],
    "sg:phone":"+61 2 4384 1944",
    "sg:postcode":"2260",
    "sg:province":"NSW",
    "wof:name":"Brand George Real Estate Pty Ltd",
    "wof:placetype":"venue"
},
  "geometry": {"coordinates":[151.44236799999999,-33.436867],"type":"Point"}
}