{
  "type": "Feature",
  "properties": {
    "iso:country":"AU",
    "sg:address":"Shop 13, Marsden Park Shopping Centre/Chambers Flat Road",
    "sg:city":"Marsden",
    "sg:classifiers":[
        {
            "category":"Health Services",
            "subcategory":"Optometrist",
            "type":"Services"
        }
    ],
    "sg:phone":"+61 7 3200 9843",
    "sg:postcode":"4132",
    "sg:province":"QLD",
    "wof:name":"Foresto David",
    "wof:placetype":"venue"
},
  "geometry": {"coordinates":[153.10736084000001,-27.6858100891],"type":"Point"}
}