{
  "type": "Feature",
  "properties": {
    "iso:country":"AU",
    "sg:address":"Shop 6/ Grand Pacific Resort 38",
    "sg:city":"Esplanade Bulcock Beach",
    "sg:classifiers":[
        {
            "category":"Personal",
            "subcategory":"Massage",
            "type":"Services"
        }
    ],
    "sg:phone":"+61 7 5437 2489",
    "sg:postcode":"4551",
    "sg:province":"QLD",
    "sg:tags":[
        "therapy"
    ],
    "wof:name":"Aquarius Massage & Body Treatment Centre",
    "wof:placetype":"venue"
},
  "geometry": {"coordinates":[153.121368408,-26.8147735596],"type":"Point"}
}