{
  "type": "Feature",
  "properties": {
    "addr:full":"U4/ 90 Central Ave Oak Flats NSW 2529",
    "addr:housenumber":"90",
    "addr:postcode":"2529",
    "addr:street":"U4 /;Central Ave Oak Flats",
    "iso:country":"AU",
    "sg:address":"U4/ 90 Central Ave",
    "sg:city":"Oak Flats",
    "sg:classifiers":[
        {
            "category":"Professional",
            "type":"Services"
        }
    ],
    "sg:phone":"+61 2 4257 7382",
    "sg:postcode":"2529",
    "sg:province":"NSW",
    "sg:tags":[
        "courier"
    ],
    "wof:name":"Bay Express",
    "wof:placetype":"venue"
},
  "geometry": {"coordinates":[150.819122314,-34.5620307922],"type":"Point"}
}