{
  "type": "Feature",
  "properties": {
    "addr:full":"1 Wembley Rd Logan Central QLD 4114",
    "addr:housenumber":"1",
    "addr:postcode":"4114",
    "addr:street":"Wembley Rd",
    "iso:country":"AU",
    "sg:address":"1 Wembley Rd",
    "sg:city":"Logan Central",
    "sg:classifiers":[
        {
            "category":"Health Services",
            "subcategory":"Health Practitioner",
            "type":"Services"
        }
    ],
    "sg:phone":"+61 7 3299 5444",
    "sg:postcode":"4114",
    "sg:province":"QLD",
    "sg:tags":[
        "physiotherapist"
    ],
    "wof:name":"Coleman Katrina",
    "wof:placetype":"venue"
},
  "geometry": {"coordinates":[153.11085510300001,-27.6416072845],"type":"Point"}
}