{
  "type": "Feature",
  "properties": {
    "addr:full":"21 Almurta St Nollamara WA 6061",
    "addr:housenumber":"21",
    "addr:postcode":"6061",
    "addr:street":"Almurta St",
    "iso:country":"AU",
    "sg:address":"21 Almurta St",
    "sg:city":"Nollamara",
    "sg:classifiers":[
        {
            "category":"Building & Trades",
            "subcategory":"Construction",
            "type":"Services"
        }
    ],
    "sg:phone":"+61 408 904 544",
    "sg:postcode":"6061",
    "sg:province":"WA",
    "sg:tags":[
        "contractor"
    ],
    "wof:name":"Anthony Campbell Constructions",
    "wof:placetype":"venue"
},
  "geometry": {"coordinates":[115.844047546,-31.875377655],"type":"Point"}
}