{
  "type": "Feature",
  "properties": {
    "addr:full":"1/ 6 Commerce Crt Forster NSW 2428",
    "addr:housenumber":"/ 6",
    "addr:postcode":"2428",
    "addr:street":"Commerce Crt",
    "iso:country":"AU",
    "sg:address":"1/ 6 Commerce Crt",
    "sg:city":"Forster",
    "sg:classifiers":[
        {
            "category":"Retail",
            "subcategory":"Repair Shop",
            "type":"Services"
        }
    ],
    "sg:phone":"+61 2 6554 9766",
    "sg:postcode":"2428",
    "sg:province":"NSW",
    "sg:tags":[
        "machine",
        "repairs",
        "part",
        "dryer",
        "washing"
    ],
    "wof:name":"Great Lakes Appliance Service",
    "wof:placetype":"venue"
},
  "geometry": {"coordinates":[152.52514600000001,-32.197102],"type":"Point"}
}