{
  "type": "Feature",
  "properties": {
    "addr:full":"1 Burton Crt Bayswater VIC 3153",
    "addr:housenumber":"1",
    "addr:postcode":"3153",
    "addr:street":"Burton Crt",
    "iso:country":"AU",
    "sg:address":"1 Burton Crt",
    "sg:city":"Bayswater",
    "sg:classifiers":[
        {
            "category":"Building & Trades",
            "subcategory":"Pest Control",
            "type":"Services"
        }
    ],
    "sg:phone":"+61 3 9720 9099",
    "sg:postcode":"3153",
    "sg:province":"VIC",
    "wof:name":"R & R Fumigation Services Pty Ltd",
    "wof:placetype":"venue"
},
  "geometry": {"coordinates":[145.270019531,-37.8462753296],"type":"Point"}
}