{
  "type": "Feature",
  "properties": {
    "iso:country":"AU",
    "sg:address":"4 Margaret St",
    "sg:city":"Tweed Heads",
    "sg:classifiers":[
        {
            "category":"Personal",
            "subcategory":"Massage",
            "type":"Services"
        }
    ],
    "sg:phone":"+61 419 715 730",
    "sg:postcode":"2485",
    "sg:province":"NSW",
    "sg:tags":[
        "therapy"
    ],
    "wof:name":"Colin Morley",
    "wof:placetype":"venue"
},
  "geometry": {"coordinates":[153.533035278,-28.18501091],"type":"Point"}
}