{
  "type": "Feature",
  "properties": {
    "addr:full":"Level 10 99 Bathurst St Sydney NSW 2000",
    "addr:housenumber":"99",
    "addr:postcode":"2000",
    "addr:street":"Bathurst St",
    "iso:country":"AU",
    "sg:address":"Level 10 99 Bathurst St",
    "sg:city":"Sydney",
    "sg:classifiers":[
        {
            "category":"Professional",
            "subcategory":"Business Services",
            "type":"Services"
        }
    ],
    "sg:phone":"+61 2 9286 0200",
    "sg:postcode":"2000",
    "sg:province":"NSW",
    "sg:tags":[
        "consultant",
        "promoter",
        "entertainment"
    ],
    "wof:name":"Cinema Plus Limited",
    "wof:placetype":"venue"
},
  "geometry": {"coordinates":[151.20602417000001,-33.8743896484],"type":"Point"}
}