{
  "type": "Feature",
  "properties": {
    "iso:country":"AU",
    "sg:address":"Gibson Crt",
    "sg:city":"Riddells Creek",
    "sg:classifiers":[
        {
            "category":"Building & Trades",
            "subcategory":"Construction",
            "type":"Services"
        }
    ],
    "sg:phone":"+61 417 983 736",
    "sg:postcode":"3431",
    "sg:province":"VIC",
    "sg:tags":[
        "contractor"
    ],
    "wof:name":"Marks G & J Bros",
    "wof:placetype":"venue"
},
  "geometry": {"coordinates":[144.68141174300001,-37.4530792236],"type":"Point"}
}