{
  "type": "Feature",
  "properties": {
    "addr:full":"Parkside Drv Koonawarra NSW 2530",
    "addr:postcode":"2530",
    "addr:street":"Parkside Drv",
    "iso:country":"AU",
    "sg:address":"Parkside Drv",
    "sg:city":"Koonawarra",
    "sg:classifiers":[
        {
            "category":"Food & Beverages",
            "subcategory":"Supermarket",
            "type":"Retail Goods"
        }
    ],
    "sg:phone":"+61 2 4261 3987",
    "sg:postcode":"2530",
    "sg:province":"NSW",
    "sg:tags":[
        "grocery",
        "store"
    ],
    "wof:name":"Jewel Food Stores Pty Ltd",
    "wof:placetype":"venue"
},
  "geometry": {"coordinates":[150.80198669399999,-34.5041007996],"type":"Point"}
}