{
  "type": "Feature",
  "properties": {
    "iso:country":"AU",
    "sg:address":"240 Main Rd",
    "sg:city":"Blackwood",
    "sg:classifiers":[
        {
            "category":"Food & Beverages",
            "subcategory":"Supermarket",
            "type":"Retail Goods"
        }
    ],
    "sg:phone":"+61 8 8278 4175",
    "sg:postcode":"5051",
    "sg:province":"SA",
    "sg:tags":[
        "grocery",
        "store"
    ],
    "wof:name":"Blackwood Foodland",
    "wof:placetype":"venue"
},
  "geometry": {"coordinates":[138.616211,-35.019924],"type":"Point"}
}