{
  "type": "Feature",
  "properties": {
    "iso:country":"AU",
    "sg:address":"Unit 8 45 Commerical Drv",
    "sg:city":"Shailer Park",
    "sg:classifiers":[
        {
            "category":"Building & Trades",
            "subcategory":"Pest Control",
            "type":"Services"
        }
    ],
    "sg:phone":"+61 7 3209 8663",
    "sg:postcode":"4128",
    "sg:province":"QLD",
    "wof:name":"Hitman",
    "wof:placetype":"venue"
},
  "geometry": {"coordinates":[153.167480469,-27.6536083221],"type":"Point"}
}