{
  "type": "Feature",
  "properties": {
    "iso:country":"AU",
    "sg:address":"4 Boxers Creek Rd",
    "sg:city":"Goulburn",
    "sg:classifiers":[
        {
            "category":"Shopping",
            "subcategory":"Antiques",
            "type":"Retail Goods"
        }
    ],
    "sg:phone":"+61 2 4829 8100",
    "sg:postcode":"2580",
    "sg:province":"NSW",
    "sg:tags":[
        "restoration",
        "reproduction"
    ],
    "wof:name":"Shaws Antiques",
    "wof:placetype":"venue"
},
  "geometry": {"coordinates":[149.73336792000001,-34.7776832581],"type":"Point"}
}