{
  "type": "Feature",
  "properties": {
    "iso:country":"AU",
    "sg:address":"Level 4/ 100 Christie St St",
    "sg:city":"Leonards",
    "sg:classifiers":[
        {
            "category":"Travel",
            "subcategory":"Travel Agent",
            "type":"Entertainment"
        }
    ],
    "sg:phone":"+61 2 9928 2565",
    "sg:postcode":"2065",
    "sg:province":"NSW",
    "sg:tags":[
        "consultant"
    ],
    "wof:name":"Bay Travel",
    "wof:placetype":"venue"
},
  "geometry": {"coordinates":[151.19526672399999,-33.8226242065],"type":"Point"}
}