{
  "type": "Feature",
  "properties": {
    "addr:full":"1 Handley St Wangaratta VIC 3677",
    "addr:housenumber":"1",
    "addr:postcode":"3677",
    "addr:street":"Handley St",
    "iso:country":"AU",
    "sg:address":"1 Handley St",
    "sg:city":"Wangaratta",
    "sg:classifiers":[
        {
            "category":"Social Services",
            "subcategory":"Child Care",
            "type":"Services"
        }
    ],
    "sg:phone":"+61 3 5721 2635",
    "sg:postcode":"3677",
    "sg:province":"VIC",
    "wof:name":"Wangaratta Child Care Centre",
    "wof:placetype":"venue"
},
  "geometry": {"coordinates":[146.318847656,-36.3561668396],"type":"Point"}
}