{
  "type": "Feature",
  "properties": {
    "addr:full":"Main St Yongala SA 5493",
    "addr:postcode":"5493",
    "addr:street":"Main St",
    "iso:country":"AU",
    "sg:address":"Main St",
    "sg:city":"Yongala",
    "sg:classifiers":[
        {
            "category":"Travel",
            "subcategory":"Hotels & Motels",
            "type":"Entertainment"
        }
    ],
    "sg:phone":"+61 8 8651 4201",
    "sg:postcode":"5493",
    "sg:province":"SA",
    "sg:tags":[
        "accommodation"
    ],
    "wof:name":"Globe Hotel Yongala",
    "wof:placetype":"venue"
},
  "geometry": {"coordinates":[138.74957275400001,-33.02866745],"type":"Point"}
}