{
  "type": "Feature",
  "properties": {
    "addr:full":"2/ 32 Princes Hwy Narooma NSW 2546",
    "addr:housenumber":"/ 32",
    "addr:postcode":"2546",
    "addr:street":"Princes Hwy",
    "iso:country":"AU",
    "sg:address":"2/ 32 Princes Hwy",
    "sg:city":"Narooma",
    "sg:classifiers":[
        {
            "category":"Cafe",
            "type":"Food & Drink"
        }
    ],
    "sg:phone":"+61 2 4476 2218",
    "sg:postcode":"2546",
    "sg:province":"NSW",
    "wof:name":"Ojays Cafe",
    "wof:placetype":"venue"
},
  "geometry": {"coordinates":[150.124465942,-36.2143058777],"type":"Point"}
}