{
  "type": "Feature",
  "properties": {
    "iso:country":"AU",
    "sg:address":"174 Brooker Ave",
    "sg:city":"Hobart",
    "sg:classifiers":[
        {
            "category":"Organizations",
            "subcategory":"Non-profit Organization",
            "type":"Services"
        }
    ],
    "sg:phone":"+61 3 6231 1625",
    "sg:postcode":"7000",
    "sg:province":"TAS",
    "sg:tags":[
        "support",
        "disability",
        "organisation"
    ],
    "wof:name":"Early Childhood Intervention Service",
    "wof:placetype":"venue"
},
  "geometry": {"coordinates":[147.32212829599999,-42.870639801],"type":"Point"}
}