{
  "type": "Feature",
  "properties": {
    "iso:country":"AU",
    "sg:address":"Unit 3/ 32",
    "sg:city":"Hurrell Way Rockingham",
    "sg:classifiers":[
        {
            "category":"Retail",
            "subcategory":"Auto Repair",
            "type":"Services"
        }
    ],
    "sg:phone":"+61 8 9528 1347",
    "sg:postcode":"6168",
    "sg:province":"WA",
    "sg:tags":[
        "repairer",
        "motor",
        "engineer"
    ],
    "wof:name":"Rockingham Auto Repairs",
    "wof:placetype":"venue"
},
  "geometry": {"coordinates":[115.758347,-32.274532],"type":"Point"}
}