{
  "type": "Feature",
  "properties": {
    "iso:country":"AU",
    "sg:address":"10 Bunton St",
    "sg:city":"Werribee",
    "sg:classifiers":[
        {
            "category":"Home & Garden",
            "subcategory":"Building Materials",
            "type":"Retail Goods"
        }
    ],
    "sg:phone":"+61 413 593 885",
    "sg:postcode":"3030",
    "sg:province":"VIC",
    "sg:tags":[
        "merchant",
        "glass",
        "glazier"
    ],
    "wof:name":"Taylor's Glass Fix",
    "wof:placetype":"venue"
},
  "geometry": {"coordinates":[144.646729,-37.889011],"type":"Point"}
}