{
  "type": "Feature",
  "properties": {
    "addr:full":"9 Stanley Hill Drv Surfers Paradise QLD 4217",
    "addr:housenumber":"9",
    "addr:postcode":"4217",
    "addr:street":"Stanley Hill Drv",
    "iso:country":"AU",
    "sg:address":"9 Stanley Hill Drv",
    "sg:city":"Surfers Paradise",
    "sg:classifiers":[
        {
            "category":"Shopping",
            "type":"Retail Goods"
        }
    ],
    "sg:phone":"+61 428 355 439",
    "sg:postcode":"4217",
    "sg:province":"QLD",
    "sg:tags":[
        "new age",
        "product"
    ],
    "wof:name":"Dreams-Online",
    "wof:placetype":"venue"
},
  "geometry": {"coordinates":[153.42675781200001,-27.9907436371],"type":"Point"}
}