{
  "type": "Feature",
  "properties": {
    "iso:country":"AU",
    "sg:address":"2 Magid Ave",
    "sg:city":"Mulgrave",
    "sg:classifiers":[
        {
            "category":"Health Services",
            "subcategory":"Doctor",
            "type":"Services"
        }
    ],
    "sg:phone":"+61 3 9562 2288",
    "sg:postcode":"3170",
    "sg:province":"VIC",
    "sg:tags":[
        "medical",
        "practitioner"
    ],
    "wof:name":"Yee Mean-Chi",
    "wof:placetype":"venue"
},
  "geometry": {"coordinates":[145.161209106,-37.9066810608],"type":"Point"}
}