{
  "type": "Feature",
  "properties": {
    "addr:full":"63 Memorial Ave Maroochydore QLD 4558",
    "addr:housenumber":"63",
    "addr:postcode":"4558",
    "addr:street":"Memorial Ave",
    "iso:country":"AU",
    "sg:address":"63 Memorial Ave",
    "sg:city":"Maroochydore",
    "sg:classifiers":[
        {
            "category":"Health Services",
            "subcategory":"Doctor",
            "type":"Services"
        }
    ],
    "sg:phone":"+61 7 3350 5677",
    "sg:postcode":"4558",
    "sg:province":"QLD",
    "sg:tags":[
        "medical",
        "practitioner"
    ],
    "wof:name":"Cavaye Douglas",
    "wof:placetype":"venue"
},
  "geometry": {"coordinates":[153.09727477999999,-26.656047821],"type":"Point"}
}