{
  "type": "Feature",
  "properties": {
    "addr:full":"60 Washington Ave Tingalpa QLD 4173",
    "addr:housenumber":"60",
    "addr:postcode":"4173",
    "addr:street":"Washington Ave",
    "iso:country":"AU",
    "sg:address":"60 Washington Ave",
    "sg:city":"Tingalpa",
    "sg:classifiers":[
        {
            "category":"Wholesale",
            "subcategory":"Construction Materials",
            "type":"Manufacturing & Wholesale Goods"
        }
    ],
    "sg:phone":"+61 7 3390 5759",
    "sg:postcode":"4173",
    "sg:province":"QLD",
    "sg:tags":[
        "protective",
        "coating"
    ],
    "wof:name":"Mobile Abrasive Blasting & Industrial Coatings",
    "wof:placetype":"venue"
},
  "geometry": {"coordinates":[153.121749878,-27.4763278961],"type":"Point"}
}