{
  "type": "Feature",
  "properties": {
    "addr:full":"3- 23 Lathe St Virginia QLD 4014",
    "addr:housenumber":"23",
    "addr:postcode":"4014",
    "addr:street":"3;Lathe St",
    "iso:country":"AU",
    "sg:address":"3- 23 Lathe St",
    "sg:city":"Virginia",
    "sg:classifiers":[
        {
            "category":"Building & Trades",
            "subcategory":"Plumbing",
            "type":"Services"
        }
    ],
    "sg:phone":"+61 412 153 063",
    "sg:postcode":"4014",
    "sg:province":"QLD",
    "sg:tags":[
        "pipe",
        "line",
        "contractor"
    ],
    "wof:name":"Bernardi Engineering",
    "wof:placetype":"venue"
},
  "geometry": {"coordinates":[153.060180664,-27.3668766022],"type":"Point"}
}