{
  "type": "Feature",
  "properties": {
    "addr:full":"28 Queen St Nambour QLD 4560",
    "addr:housenumber":"28",
    "addr:postcode":"4560",
    "addr:street":"Queen St",
    "iso:country":"AU",
    "sg:address":"28 Queen St",
    "sg:city":"Nambour",
    "sg:classifiers":[
        {
            "category":"Travel",
            "subcategory":"Travel Agent",
            "type":"Entertainment"
        }
    ],
    "sg:phone":"+61 7 5441 7866",
    "sg:postcode":"4560",
    "sg:province":"QLD",
    "sg:tags":[
        "consultant"
    ],
    "wof:name":"Travelbug Tour Service",
    "wof:placetype":"venue"
},
  "geometry": {"coordinates":[152.960083008,-26.6259059906],"type":"Point"}
}