{
  "type": "Feature",
  "properties": {
    "addr:full":"Factory 2/ Keam Crs Cape Woolamai VIC 3925",
    "addr:postcode":"3925",
    "addr:street":"/ Keam Crs",
    "iso:country":"AU",
    "sg:address":"Factory 2/ Keam Crs",
    "sg:city":"Cape Woolamai",
    "sg:classifiers":[
        {
            "category":"Home & Garden",
            "subcategory":"Building Materials",
            "type":"Retail Goods"
        }
    ],
    "sg:phone":"+61 3 5956 6208",
    "sg:postcode":"3925",
    "sg:province":"VIC",
    "sg:tags":[
        "balustrading"
    ],
    "wof:name":"Cape Woolamai Welding And Fabrication",
    "wof:placetype":"venue"
},
  "geometry": {"coordinates":[145.334075928,-38.5213508606],"type":"Point"}
}