{
  "type": "Feature",
  "properties": {
    "addr:full":"40 Moss St Slacks Creek QLD 4127",
    "addr:housenumber":"40",
    "addr:postcode":"4127",
    "addr:street":"Moss St",
    "iso:country":"AU",
    "sg:address":"40 Moss St",
    "sg:city":"Slacks Creek",
    "sg:classifiers":[
        {
            "category":"Banks & Credit Unions",
            "subcategory":"Investment Brokerage",
            "type":"Services"
        }
    ],
    "sg:phone":"+61 7 3808 7238",
    "sg:postcode":"4127",
    "sg:province":"QLD",
    "sg:tags":[
        "radiator",
        "motor"
    ],
    "wof:name":"Moss Street Radiators",
    "wof:placetype":"venue"
},
  "geometry": {"coordinates":[153.12078857399999,-27.6224555969],"type":"Point"}
}