{
  "type": "Feature",
  "properties": {
    "addr:full":"Suite 203 3 Spring St Chatswood NSW 2067",
    "addr:housenumber":"3",
    "addr:postcode":"2067",
    "addr:street":"Spring St",
    "iso:country":"AU",
    "sg:address":"Suite 203 3 Spring St",
    "sg:city":"Chatswood",
    "sg:classifiers":[
        {
            "category":"Professional",
            "subcategory":"Employment Agencies",
            "type":"Services"
        }
    ],
    "sg:phone":"+61 2 9415 4733",
    "sg:postcode":"2067",
    "sg:province":"NSW",
    "sg:tags":[
        "provider",
        "internet"
    ],
    "wof:name":"Value Connect",
    "wof:placetype":"venue"
},
  "geometry": {"coordinates":[151.18513488799999,-33.7970695496],"type":"Point"}
}