{
  "type": "Feature",
  "properties": {
    "addr:full":"348a Bilsen Rd Geebung QLD 4034",
    "addr:housenumber":"348a",
    "addr:postcode":"4034",
    "addr:street":"Bilsen Rd",
    "iso:country":"AU",
    "sg:address":"348a Bilsen Rd",
    "sg:city":"Geebung",
    "sg:classifiers":[
        {
            "category":"Home & Garden",
            "subcategory":"Carpets & Floor Coverings",
            "type":"Retail Goods"
        }
    ],
    "sg:phone":"+61 1800 777 425",
    "sg:postcode":"4034",
    "sg:province":"QLD",
    "wof:name":"Polyflor Australia Pty Ltd",
    "wof:placetype":"venue"
},
  "geometry": {"coordinates":[153.054993,-27.375954],"type":"Point"}
}