{
  "type": "Feature",
  "properties": {
    "addr:full":"Factory 3, 57- 59 Malverton Drv Hallam VIC 3803",
    "addr:housenumber":"57 59",
    "addr:postcode":"3803",
    "addr:street":"Malverton Drv",
    "iso:country":"AU",
    "sg:address":"Factory 3, 57- 59 Malverton Drv",
    "sg:city":"Hallam",
    "sg:classifiers":[
        {
            "category":"Retail",
            "subcategory":"Auto Repair",
            "type":"Services"
        }
    ],
    "sg:phone":"+61 3 9702 3111",
    "sg:postcode":"3803",
    "sg:province":"VIC",
    "sg:tags":[
        "repairer",
        "motor",
        "engineer"
    ],
    "wof:name":"TBF Automotive",
    "wof:placetype":"venue"
},
  "geometry": {"coordinates":[145.272537231,-38.0115852356],"type":"Point"}
}