{
  "type": "Feature",
  "properties": {
    "addr:full":"Unit 11 77 Howe St Osborne Park WA 6017",
    "addr:housenumber":"77",
    "addr:postcode":"6017",
    "addr:street":"Howe St",
    "iso:country":"AU",
    "sg:address":"Unit 11 77 Howe St",
    "sg:city":"Osborne Park",
    "sg:classifiers":[
        {
            "category":"Building & Trades",
            "subcategory":"Construction",
            "type":"Services"
        }
    ],
    "sg:phone":"+61 8 9242 1798",
    "sg:postcode":"6017",
    "sg:province":"WA",
    "sg:tags":[
        "industrial",
        "commercial",
        "air conditioning"
    ],
    "wof:name":"Ronley Holdings Pty Ltd",
    "wof:placetype":"venue"
},
  "geometry": {"coordinates":[115.81446838399999,-31.9077987671],"type":"Point"}
}