{
  "type": "Feature",
  "properties": {
    "iso:country":"AU",
    "sg:address":"U2/ 283 Thompson Rd",
    "sg:city":"North Geelong",
    "sg:classifiers":[
        {
            "category":"Wholesale",
            "subcategory":"Furniture",
            "type":"Manufacturing & Wholesale Goods"
        }
    ],
    "sg:phone":"+61 3 5277 9431",
    "sg:postcode":"3215",
    "sg:province":"VIC",
    "sg:tags":[
        "wholesaler",
        "mfrs"
    ],
    "wof:name":"Country Alternative Pty Ltd",
    "wof:placetype":"venue"
},
  "geometry": {"coordinates":[144.34425354000001,-38.1054420471],"type":"Point"}
}