{
  "type": "Feature",
  "properties": {
    "iso:country":"AU",
    "sg:address":"4 Swan Rd",
    "sg:city":"Morwell",
    "sg:classifiers":[
        {
            "category":"Professional",
            "subcategory":"Engineering",
            "type":"Services"
        }
    ],
    "sg:phone":"+61 3 5134 2777",
    "sg:postcode":"3840",
    "sg:province":"VIC",
    "sg:tags":[
        "civil",
        "engineer"
    ],
    "wof:name":"H C M Constructions",
    "wof:placetype":"venue"
},
  "geometry": {"coordinates":[146.43849182100001,-38.2420310974],"type":"Point"}
}