{
  "type": "Feature",
  "properties": {
    "addr:full":"100 Kundle Kundle Rd Cundletown NSW 2430",
    "addr:housenumber":"100",
    "addr:postcode":"2430",
    "addr:street":"Kundle Kundle Rd",
    "iso:country":"AU",
    "sg:address":"100 Kundle Kundle Rd",
    "sg:city":"Cundletown",
    "sg:classifiers":[
        {
            "category":"Shopping",
            "subcategory":"Clothing, Apparel, & Fashions",
            "type":"Retail Goods"
        }
    ],
    "sg:phone":"+61 2 6553 8175",
    "sg:postcode":"2430",
    "sg:province":"NSW",
    "sg:tags":[
        "millinery"
    ],
    "wof:name":"R.J's Millinery",
    "wof:placetype":"venue"
},
  "geometry": {"coordinates":[152.55070499999999,-31.857325],"type":"Point"}
}