{
  "type": "Feature",
  "properties": {
    "iso:country":"AU",
    "sg:address":"55 Albany Hwy",
    "sg:city":"Albany",
    "sg:classifiers":[
        {
            "category":"Banks & Credit Unions",
            "subcategory":"Financial Services",
            "type":"Services"
        }
    ],
    "sg:phone":"+61 8 9842 3122",
    "sg:postcode":"6330",
    "sg:province":"WA",
    "sg:tags":[
        "planning"
    ],
    "wof:name":"Barbican Financial Services",
    "wof:placetype":"venue"
},
  "geometry": {"coordinates":[117.881752014,-35.0202102661],"type":"Point"}
}