{
  "type": "Feature",
  "properties": {
    "addr:full":"280 Chapman Rd Geraldton WA 6530",
    "addr:housenumber":"280",
    "addr:postcode":"6530",
    "addr:street":"Chapman Rd",
    "iso:country":"AU",
    "sg:address":"280 Chapman Rd",
    "sg:city":"Geraldton",
    "sg:classifiers":[
        {
            "category":"Utilities",
            "subcategory":"Electric",
            "type":"Services"
        }
    ],
    "sg:phone":"+61 8 9921 5521",
    "sg:postcode":"6530",
    "sg:province":"WA",
    "sg:tags":[
        "electrical",
        "contractor"
    ],
    "wof:name":"Bluff Point Electrical Contractors",
    "wof:placetype":"venue"
},
  "geometry": {"coordinates":[114.61844635,-28.7507457733],"type":"Point"}
}