{
  "type": "Feature",
  "properties": {
    "addr:full":"7 Melaleuca St Newport NSW 2106",
    "addr:housenumber":"7",
    "addr:postcode":"2106",
    "addr:street":"Melaleuca St",
    "iso:country":"AU",
    "sg:address":"7 Melaleuca St",
    "sg:city":"Newport",
    "sg:classifiers":[
        {
            "category":"Shopping",
            "subcategory":"Clothing, Apparel, & Fashions",
            "type":"Retail Goods"
        }
    ],
    "sg:phone":"+61 2 9999 5967",
    "sg:postcode":"2106",
    "sg:province":"NSW",
    "sg:tags":[
        "sportswear"
    ],
    "wof:name":"Active Sportz Pty Ltd",
    "wof:placetype":"venue"
},
  "geometry": {"coordinates":[151.322463989,-33.6605949402],"type":"Point"}
}