{
  "type": "Feature",
  "properties": {
    "iso:country":"AU",
    "sg:address":"Shop 7 Winthrop Vlge Shopping Centre Somerville Blv",
    "sg:city":"Winthrop",
    "sg:classifiers":[
        {
            "category":"Health Services",
            "subcategory":"Optometrist",
            "type":"Services"
        }
    ],
    "sg:phone":"+61 8 9310 5488",
    "sg:postcode":"6150",
    "sg:province":"WA",
    "wof:name":"Ayesa Andrew",
    "wof:placetype":"venue"
},
  "geometry": {"coordinates":[115.831886,-32.066017],"type":"Point"}
}