{
  "type": "Feature",
  "properties": {
    "iso:country":"AU",
    "sg:address":"24 Herries St",
    "sg:city":"Toowoomba",
    "sg:classifiers":[
        {
            "category":"Health Services",
            "subcategory":"Doctor",
            "type":"Services"
        }
    ],
    "sg:phone":"+61 7 4659 9955",
    "sg:postcode":"4350",
    "sg:province":"QLD",
    "sg:tags":[
        "medical",
        "practitioner"
    ],
    "wof:name":"Cox John W",
    "wof:placetype":"venue"
},
  "geometry": {"coordinates":[151.93937700000001,-27.562429],"type":"Point"}
}