{
  "type": "Feature",
  "properties": {
    "addr:full":"20- 22 Ovata Drv Tullamarine VIC 3043",
    "addr:housenumber":"22",
    "addr:postcode":"3043",
    "addr:street":"Ovata Drv",
    "iso:country":"AU",
    "sg:address":"20- 22 Ovata Drv",
    "sg:city":"Tullamarine",
    "sg:classifiers":[
        {
            "category":"Home & Garden",
            "subcategory":"Hardware",
            "type":"Retail Goods"
        }
    ],
    "sg:phone":"+61 3 9330 4444",
    "sg:postcode":"3043",
    "sg:province":"VIC",
    "sg:tags":[
        "compressor",
        "air"
    ],
    "wof:name":"Maxair Air Pipe Systems",
    "wof:placetype":"venue"
},
  "geometry": {"coordinates":[144.86598205600001,-37.709980011],"type":"Point"}
}