{
  "type": "Feature",
  "properties": {
    "iso:country":"AU",
    "sg:address":"U1",
    "sg:city":"084/ 1 Cove Cres Carrara",
    "sg:classifiers":[
        {
            "category":"Retail",
            "subcategory":"Repair Shop",
            "type":"Services"
        }
    ],
    "sg:phone":"+61 411 137 182",
    "sg:postcode":"4211",
    "sg:province":"QLD",
    "sg:tags":[
        "maintenance",
        "pool",
        "swimming"
    ],
    "wof:name":"South East Queensland Pool Services",
    "wof:placetype":"venue"
},
  "geometry": {"coordinates":[153.35905456500001,-28.0566482544],"type":"Point"}
}