{
  "type": "Feature",
  "properties": {
    "addr:full":"86 Chapman Ave Glenroy VIC 3046",
    "addr:housenumber":"86",
    "addr:postcode":"3046",
    "addr:street":"Chapman Ave",
    "iso:country":"AU",
    "sg:address":"86 Chapman Ave",
    "sg:city":"Glenroy",
    "sg:classifiers":[
        {
            "category":"Building & Trades",
            "subcategory":"Construction",
            "type":"Services"
        }
    ],
    "sg:phone":"+61 418 370 050",
    "sg:postcode":"3046",
    "sg:province":"VIC",
    "sg:tags":[
        "contractor"
    ],
    "wof:name":"K.S.T. Constructions Pty Ltd",
    "wof:placetype":"venue"
},
  "geometry": {"coordinates":[144.911819458,-37.704334259],"type":"Point"}
}