{
  "type": "Feature",
  "properties": {
    "addr:full":"156 Wattle St Malvern SA 5061",
    "addr:housenumber":"156",
    "addr:postcode":"5061",
    "addr:street":"Wattle St",
    "iso:country":"AU",
    "sg:address":"156 Wattle St",
    "sg:city":"Malvern",
    "sg:classifiers":[
        {
            "category":"Professional",
            "subcategory":"Business Services",
            "type":"Services"
        }
    ],
    "sg:phone":"+61 8 8271 1173",
    "sg:postcode":"5061",
    "sg:province":"SA",
    "sg:tags":[
        "small",
        "advisory"
    ],
    "wof:name":"Timemaker",
    "wof:placetype":"venue"
},
  "geometry": {"coordinates":[138.614212036,-34.9543037415],"type":"Point"}
}