{
  "type": "Feature",
  "properties": {
    "iso:country":"AU",
    "sg:address":"418 Bluff Rd",
    "sg:city":"Hampton East",
    "sg:classifiers":[
        {
            "category":"Health Services",
            "subcategory":"Chiropractor",
            "type":"Services"
        }
    ],
    "sg:phone":"+61 3 9852 0425",
    "sg:postcode":"3188",
    "sg:province":"VIC",
    "wof:name":"A Ultra Health Care",
    "wof:placetype":"venue"
},
  "geometry": {"coordinates":[145.02308654800001,-37.9406509399],"type":"Point"}
}