{
  "type": "Feature",
  "properties": {
    "iso:country":"AU",
    "sg:address":"Shd2/ 6 Drovers Way",
    "sg:city":"Dungog",
    "sg:classifiers":[
        {
            "category":"Freight",
            "type":"Transportation"
        }
    ],
    "sg:phone":"+61 2 4992 2168",
    "sg:postcode":"2420",
    "sg:province":"NSW",
    "sg:tags":[
        "light",
        "carrier"
    ],
    "wof:name":"Dungog Parcel Express",
    "wof:placetype":"venue"
},
  "geometry": {"coordinates":[151.75796500000001,-32.400139],"type":"Point"}
}