{
  "type": "Feature",
  "properties": {
    "addr:full":"PO Box 971 Kingsford NSW 2032",
    "addr:postcode":"2032",
    "iso:country":"AU",
    "sg:address":"PO Box 971",
    "sg:city":"Kingsford",
    "sg:classifiers":[
        {
            "category":"Building & Trades",
            "subcategory":"Landscaping Services",
            "type":"Services"
        }
    ],
    "sg:phone":"+61 2 9553 6628",
    "sg:postcode":"2032",
    "sg:province":"NSW",
    "sg:tags":[
        "stump",
        "tree",
        "felling",
        "removal"
    ],
    "wof:name":"Aston Group Pty Ltd",
    "wof:placetype":"venue"
},
  "geometry": {"coordinates":[151.227493286,-33.9234886169],"type":"Point"}
}