{
  "type": "Feature",
  "properties": {
    "iso:country":"AU",
    "sg:address":"30 Findon Rd",
    "sg:city":"Woodville West",
    "sg:classifiers":[
        {
            "category":"Home & Garden",
            "subcategory":"Furniture",
            "type":"Retail Goods"
        }
    ],
    "sg:phone":"+61 8 8445 1013",
    "sg:postcode":"5011",
    "sg:province":"SA",
    "sg:tags":[
        "repair",
        "restoration"
    ],
    "wof:name":"Woodville Upholsterers",
    "wof:placetype":"venue"
},
  "geometry": {"coordinates":[138.530715942,-34.8809547424],"type":"Point"}
}