{
  "type": "Feature",
  "properties": {
    "addr:full":"Mactier St (Cnr Fig Tree Pocket Rd) Fig Tree Pocket QLD 4069",
    "addr:postcode":"4069",
    "addr:street":"Mactier St Cnr Fig;Pocket Rd",
    "iso:country":"AU",
    "sg:address":"Mactier St (Cnr Fig Tree Pocket Rd)",
    "sg:city":"Fig Tree Pocket",
    "sg:classifiers":[
        {
            "category":"Education",
            "subcategory":"School",
            "type":"Public Place"
        }
    ],
    "sg:phone":"+61 7 3878 1666",
    "sg:postcode":"4069",
    "sg:province":"QLD",
    "wof:name":"Montessori School Ltd",
    "wof:placetype":"venue"
},
  "geometry": {"coordinates":[152.960861206,-27.5318489075],"type":"Point"}
}