{
  "type": "Feature",
  "properties": {
    "addr:full":"Level 1/ 218 Caroline Springs Blv Caroline Springs VIC 3023",
    "addr:housenumber":"/ 218",
    "addr:postcode":"3023",
    "addr:street":"Caroline Springs Blv",
    "iso:country":"AU",
    "sg:address":"Level 1/ 218",
    "sg:city":"Caroline Springs Blv Caroline Springs",
    "sg:classifiers":[
        {
            "category":"Building & Trades",
            "subcategory":"Landscaping Services",
            "type":"Services"
        }
    ],
    "sg:phone":"+61 3 9361 9400",
    "sg:postcode":"3023",
    "sg:province":"VIC",
    "sg:tags":[
        "consultant"
    ],
    "wof:name":"Northridge Homes",
    "wof:placetype":"venue"
},
  "geometry": {"coordinates":[144.73519899999999,-37.744972],"type":"Point"}
}