{
  "type": "Feature",
  "properties": {
    "addr:full":"PO Box 537 Scone NSW 2337",
    "addr:postcode":"2337",
    "iso:country":"AU",
    "sg:address":"PO Box 537",
    "sg:city":"Scone",
    "sg:classifiers":[
        {
            "category":"Building & Trades",
            "subcategory":"Construction",
            "type":"Services"
        }
    ],
    "sg:phone":"+61 2 6545 0174",
    "sg:postcode":"2337",
    "sg:province":"NSW",
    "sg:tags":[
        "joiner",
        "carpenter"
    ],
    "wof:name":"C & T Warner-Building Contractors",
    "wof:placetype":"venue"
},
  "geometry": {"coordinates":[150.86781310999999,-32.0457496643],"type":"Point"}
}