{
  "type": "Feature",
  "properties": {
    "addr:full":"Strathpine Specialist Cntr Dixon St Strathpine QLD 4500",
    "addr:postcode":"4500",
    "addr:street":"Dixon St",
    "iso:country":"AU",
    "sg:address":"Strathpine Specialist Cntr Dixon St",
    "sg:city":"Strathpine",
    "sg:classifiers":[
        {
            "category":"Health Services",
            "subcategory":"Doctor",
            "type":"Services"
        }
    ],
    "sg:phone":"+61 7 3832 6328",
    "sg:postcode":"4500",
    "sg:province":"QLD",
    "sg:tags":[
        "medical",
        "practitioner"
    ],
    "wof:name":"Siu Simon",
    "wof:placetype":"venue"
},
  "geometry": {"coordinates":[152.99095153799999,-27.3089866638],"type":"Point"}
}