{
  "type": "Feature",
  "properties": {
    "addr:full":"131 Wellington St Mosman Park WA 6012",
    "addr:housenumber":"131",
    "addr:postcode":"6012",
    "addr:street":"Wellington St",
    "iso:country":"AU",
    "sg:address":"131 Wellington St",
    "sg:city":"Mosman Park",
    "sg:classifiers":[
        {
            "category":"Building & Trades",
            "subcategory":"Construction",
            "type":"Services"
        }
    ],
    "sg:phone":"+61 8 9383 2733",
    "sg:postcode":"6012",
    "sg:province":"WA",
    "sg:tags":[
        "brick",
        "paving"
    ],
    "wof:name":"Kelly's Brickpaving",
    "wof:placetype":"venue"
},
  "geometry": {"coordinates":[115.771217346,-32.014995575],"type":"Point"}
}