{
  "type": "Feature",
  "properties": {
    "addr:full":"12 Kingfisher Ave Coleambally NSW 2707",
    "addr:housenumber":"12",
    "addr:postcode":"2707",
    "addr:street":"Kingfisher Ave",
    "iso:country":"AU",
    "sg:address":"12 Kingfisher Ave",
    "sg:city":"Coleambally",
    "sg:classifiers":[
        {
            "category":"Autos & Motor Vehicles",
            "subcategory":"Auto Supplies",
            "type":"Retail Goods"
        }
    ],
    "sg:phone":"+61 2 6954 4153",
    "sg:postcode":"2707",
    "sg:province":"NSW",
    "sg:tags":[
        "oil",
        "spirit"
    ],
    "wof:name":"NEP- Shell Distributor",
    "wof:placetype":"venue"
},
  "geometry": {"coordinates":[145.880249023,-34.802028656],"type":"Point"}
}