{
  "type": "Feature",
  "properties": {
    "addr:full":"1 McLean St Dianella WA 6059",
    "addr:housenumber":"1",
    "addr:postcode":"6059",
    "addr:street":"Mclean St",
    "iso:country":"AU",
    "sg:address":"1 McLean St",
    "sg:city":"Dianella",
    "sg:classifiers":[
        {
            "category":"Utilities",
            "subcategory":"Refuse",
            "type":"Services"
        }
    ],
    "sg:phone":"+61 8 9276 4801",
    "sg:postcode":"6059",
    "sg:province":"WA",
    "sg:tags":[
        "remover",
        "rubbish"
    ],
    "wof:name":"PHONE A BAG",
    "wof:placetype":"venue"
},
  "geometry": {"coordinates":[115.798469544,-32.0398597717],"type":"Point"}
}