{
  "type": "Feature",
  "properties": {
    "addr:full":"Esplanade Rd Truro SA 5356",
    "addr:postcode":"5356",
    "addr:street":"Esplanade Rd",
    "iso:country":"AU",
    "sg:address":"Esplanade Rd",
    "sg:city":"Truro",
    "sg:classifiers":[
        {
            "category":"Personal",
            "type":"Services"
        }
    ],
    "sg:phone":"+61 8 8564 0315",
    "sg:postcode":"5356",
    "sg:province":"SA",
    "sg:tags":[
        "wallpapering",
        "wallcovering"
    ],
    "wof:name":"Steinert K M & M K",
    "wof:placetype":"venue"
},
  "geometry": {"coordinates":[139.12974548299999,-34.4095916748],"type":"Point"}
}