{
  "type": "Feature",
  "properties": {
    "iso:country":"AU",
    "sg:address":"2/ 3 Lancaster St",
    "sg:city":"Ingleburn",
    "sg:classifiers":[
        {
            "category":"Manufacturing",
            "subcategory":"Tools & Machinery",
            "type":"Manufacturing & Wholesale Goods"
        }
    ],
    "sg:phone":"+61 2 9829 5077",
    "sg:postcode":"2565",
    "sg:province":"NSW",
    "sg:tags":[
        "toolmaker"
    ],
    "wof:name":"JIS Industries Pty Ltd",
    "wof:placetype":"venue"
},
  "geometry": {"coordinates":[150.867263794,-33.989730835],"type":"Point"}
}