{
  "type": "Feature",
  "properties": {
    "iso:country":"AU",
    "sg:address":"99 Wills St",
    "sg:city":"Bendigo",
    "sg:classifiers":[
        {
            "category":"Health Services",
            "subcategory":"Health Practitioner",
            "type":"Services"
        }
    ],
    "sg:phone":"+61 3 5442 6757",
    "sg:postcode":"3550",
    "sg:province":"VIC",
    "sg:tags":[
        "hypnotherapy"
    ],
    "wof:name":"Celia Kakoschke Clinical Hypnotherapist",
    "wof:placetype":"venue"
},
  "geometry": {"coordinates":[144.280563355,-36.7632865906],"type":"Point"}
}