{
  "type": "Feature",
  "properties": {
    "addr:full":"Gilles St Adelaide SA 5000",
    "addr:postcode":"5000",
    "addr:street":"Gilles St",
    "iso:country":"AU",
    "sg:address":"Gilles St",
    "sg:city":"Adelaide",
    "sg:classifiers":[
        {
            "category":"Sports & Exercise",
            "subcategory":"Gym",
            "type":"Entertainment"
        }
    ],
    "sg:phone":"+61 400 115 210",
    "sg:postcode":"5000",
    "sg:province":"SA",
    "sg:tags":[
        "health",
        "fitness"
    ],
    "wof:name":"EFM Health Clubs",
    "wof:placetype":"venue"
},
  "geometry": {"coordinates":[138.601272583,-34.9342536926],"type":"Point"}
}