{
  "type": "Feature",
  "properties": {
    "addr:full":"Shop 15 Ulladulla Plaza Princes Hwy Ulladulla NSW 2539",
    "addr:housenumber":"shop 15",
    "addr:postcode":"2539",
    "addr:street":"Ulladulla Plaza Princes Hwy",
    "iso:country":"AU",
    "sg:address":"Shop 15 Ulladulla Plaza Princes Hwy",
    "sg:city":"Ulladulla",
    "sg:classifiers":[
        {
            "category":"Shopping",
            "subcategory":"Clothing, Apparel, & Fashions",
            "type":"Retail Goods"
        }
    ],
    "sg:phone":"+61 2 4455 4598",
    "sg:postcode":"2539",
    "sg:province":"NSW",
    "sg:tags":[
        "lady",
        "wear"
    ],
    "wof:name":"Whims Ladies Wear",
    "wof:placetype":"venue"
},
  "geometry": {"coordinates":[150.47564697300001,-35.3510398865],"type":"Point"}
}