{
  "type": "Feature",
  "properties": {
    "addr:full":"Shop 12, Strathfield Plaza Strathfield NSW 2135",
    "addr:housenumber":"shop 12",
    "addr:postcode":"2135",
    "addr:street":"Strathfield Plaza",
    "iso:country":"AU",
    "sg:address":"Shop 12, Strathfield Plaza",
    "sg:city":"Strathfield",
    "sg:classifiers":[
        {
            "category":"Transit Center",
            "subcategory":"Passenger",
            "type":"Transportation"
        }
    ],
    "sg:phone":"+61 2 9746 8115",
    "sg:postcode":"2135",
    "sg:province":"NSW",
    "sg:tags":[
        "retail",
        "toiletry",
        "perfume"
    ],
    "wof:name":"A Touch Of Paris",
    "wof:placetype":"venue"
},
  "geometry": {"coordinates":[151.09222412099999,-33.8768501282],"type":"Point"}
}