{
  "type": "Feature",
  "properties": {
    "addr:full":"31- 33 Ari Drv Campbellfield VIC 3061",
    "addr:housenumber":"33",
    "addr:postcode":"3061",
    "addr:street":"Ari Drv",
    "iso:country":"AU",
    "sg:address":"31- 33 Ari Drv",
    "sg:city":"Campbellfield",
    "sg:classifiers":[
        {
            "category":"Retail",
            "subcategory":"Auto Repair",
            "type":"Services"
        }
    ],
    "sg:phone":"+61 3 9357 0887",
    "sg:postcode":"3061",
    "sg:province":"VIC",
    "sg:tags":[
        "repairer",
        "motor",
        "engineer"
    ],
    "wof:name":"Masri Motor Wreckers",
    "wof:placetype":"venue"
},
  "geometry": {"coordinates":[144.96864318900001,-37.6686973572],"type":"Point"}
}