{
  "type": "Feature",
  "properties": {
    "addr:full":"Level 1/93- 97 Plenty Rd Bundoora VIC 3083",
    "addr:housenumber":"/;97",
    "addr:postcode":"3083",
    "addr:street":"93;Plenty Rd",
    "iso:country":"AU",
    "sg:address":"Level 1/93- 97 Plenty Rd",
    "sg:city":"Bundoora",
    "sg:classifiers":[
        {
            "category":"Education",
            "subcategory":"Dance Studio",
            "type":"Public Place"
        }
    ],
    "sg:phone":"+61 3 9467 8400",
    "sg:postcode":"3083",
    "sg:province":"VIC",
    "sg:tags":[
        "training",
        "video",
        "film"
    ],
    "wof:name":"WiseOwl Multimedia",
    "wof:placetype":"venue"
},
  "geometry": {"coordinates":[145.060302734,-37.694316864],"type":"Point"}
}