{
  "type": "Feature",
  "properties": {
    "iso:country":"AU",
    "sg:address":"Rex Rd",
    "sg:city":"Rocky Creek",
    "sg:classifiers":[
        {
            "category":"Building & Trades",
            "subcategory":"Construction",
            "type":"Services"
        }
    ],
    "sg:phone":"+61 7 4095 4263",
    "sg:postcode":"4882",
    "sg:province":"QLD",
    "sg:tags":[
        "earth",
        "excavating",
        "moving",
        "contractor"
    ],
    "wof:name":"Tomerini M J",
    "wof:placetype":"venue"
},
  "geometry": {"coordinates":[145.44088745100001,-17.1803817749],"type":"Point"}
}