{
  "type": "Feature",
  "properties": {
    "addr:full":"16 Watt St Newcastle NSW 2300",
    "addr:housenumber":"16",
    "addr:postcode":"2300",
    "addr:street":"Watt St",
    "iso:country":"AU",
    "sg:address":"16 Watt St",
    "sg:city":"Newcastle",
    "sg:classifiers":[
        {
            "category":"Restaurant",
            "type":"Food & Drink"
        }
    ],
    "sg:phone":"+61 2 4927 5622",
    "sg:postcode":"2300",
    "sg:province":"NSW",
    "wof:name":"Cafe 16",
    "wof:placetype":"venue"
},
  "geometry": {"coordinates":[151.78413399999999,-32.928017],"type":"Point"}
}