{
  "type": "Feature",
  "properties": {
    "iso:country":"AU",
    "sg:address":"Suite 35, Ashley Cntr 1a Ashley La",
    "sg:city":"Westmead",
    "sg:classifiers":[
        {
            "category":"Health Services",
            "subcategory":"Doctor",
            "type":"Services"
        }
    ],
    "sg:phone":"+61 2 9689 3588",
    "sg:postcode":"2145",
    "sg:province":"NSW",
    "sg:tags":[
        "medical",
        "practitioner"
    ],
    "wof:name":"Nuclear Medicine & Ultrasound Associates",
    "wof:placetype":"venue"
},
  "geometry": {"coordinates":[150.98919677699999,-33.8064880371],"type":"Point"}
}