{
  "type": "Feature",
  "properties": {
    "addr:full":"146 Marsden St Parramatta NSW 2150",
    "addr:housenumber":"146",
    "addr:postcode":"2150",
    "addr:street":"Marsden St",
    "iso:country":"AU",
    "sg:address":"146 Marsden St",
    "sg:city":"Parramatta",
    "sg:classifiers":[
        {
            "category":"Professional",
            "subcategory":"Secretarial Services",
            "type":"Services"
        }
    ],
    "sg:phone":"+61 2 9633 9912",
    "sg:postcode":"2150",
    "sg:province":"NSW",
    "sg:tags":[
        "typing"
    ],
    "wof:name":"M.A.F. Services Pty Ltd",
    "wof:placetype":"venue"
},
  "geometry": {"coordinates":[151.00173950199999,-33.8142662048],"type":"Point"}
}