{
  "type": "Feature",
  "properties": {
    "addr:full":"137 West St Mt Isa QLD 4825",
    "addr:housenumber":"137",
    "addr:postcode":"4825",
    "addr:street":"West St",
    "iso:country":"AU",
    "sg:address":"137 West St",
    "sg:city":"Mt Isa",
    "sg:classifiers":[
        {
            "category":"Real Estate",
            "subcategory":"Surveying",
            "type":"Services"
        }
    ],
    "sg:phone":"+61 7 4743 7710",
    "sg:postcode":"4825",
    "sg:province":"QLD",
    "sg:tags":[
        "geophysicist"
    ],
    "wof:name":"EJR Holdings Pty Ltd",
    "wof:placetype":"venue"
},
  "geometry": {"coordinates":[139.494034,-20.713362],"type":"Point"}
}