{
  "type": "Feature",
  "properties": {
    "addr:full":"Shop 8 / 7 Trees Rd Tallebudgera QLD 4228",
    "addr:housenumber":"shop 8 / 7",
    "addr:postcode":"4228",
    "addr:street":"Trees Rd",
    "iso:country":"AU",
    "sg:address":"Shop 8 / 7 Trees Rd",
    "sg:city":"Tallebudgera",
    "sg:classifiers":[
        {
            "category":"Communications",
            "subcategory":"Film & Video Production",
            "type":"Services"
        }
    ],
    "sg:phone":"+61 7 5522 6444",
    "sg:postcode":"4228",
    "sg:province":"QLD",
    "sg:tags":[
        "dvd",
        "library"
    ],
    "wof:name":"Nu-Worx Video Cafe",
    "wof:placetype":"venue"
},
  "geometry": {"coordinates":[153.42825317399999,-28.1407356262],"type":"Point"}
}