{
  "type": "Feature",
  "properties": {
    "addr:full":"PO Box 749 Kiama NSW 2533",
    "addr:postcode":"2533",
    "iso:country":"AU",
    "sg:address":"PO Box 749",
    "sg:city":"Kiama",
    "sg:classifiers":[
        {
            "category":"Utilities",
            "subcategory":"Water",
            "type":"Services"
        }
    ],
    "sg:phone":"+61 412 420 166",
    "sg:postcode":"2533",
    "sg:province":"NSW",
    "sg:tags":[
        "hot",
        "system"
    ],
    "wof:name":"Wheeler T & S",
    "wof:placetype":"venue"
},
  "geometry": {"coordinates":[150.851806641,-34.6771583557],"type":"Point"}
}