{
  "type": "Feature",
  "properties": {
    "addr:full":"PO Box 153 Morpeth NSW 2321",
    "addr:postcode":"2321",
    "iso:country":"AU",
    "sg:address":"PO Box 153",
    "sg:city":"Morpeth",
    "sg:classifiers":[
        {
            "category":"Shopping",
            "subcategory":"Hobbies, Toys, & Games",
            "type":"Retail Goods"
        }
    ],
    "sg:phone":"+61 2 4930 1011",
    "sg:postcode":"2321",
    "sg:province":"NSW",
    "sg:tags":[
        "bag",
        "sack"
    ],
    "wof:name":"Paterson River Turf Supplies",
    "wof:placetype":"venue"
},
  "geometry": {"coordinates":[151.627044678,-32.7248497009],"type":"Point"}
}