{
  "type": "Feature",
  "properties": {
    "addr:full":"Bus Stop 6, 192 Henley Beach Rd Torrensville SA 5031",
    "addr:housenumber":"192",
    "addr:postcode":"5031",
    "addr:street":"Henley Beach Rd",
    "iso:country":"AU",
    "sg:address":"Bus Stop 6, 192 Henley Beach Rd",
    "sg:city":"Torrensville",
    "sg:classifiers":[
        {
            "category":"Shopping",
            "subcategory":"Baby Store",
            "type":"Retail Goods"
        }
    ],
    "sg:phone":"+61 8 8443 5434",
    "sg:postcode":"5031",
    "sg:province":"SA",
    "sg:tags":[
        "wear"
    ],
    "wof:name":"Papas Emporium",
    "wof:placetype":"venue"
},
  "geometry": {"coordinates":[138.5597229,-34.9239997864],"type":"Point"}
}