{
  "type": "Feature",
  "properties": {
    "iso:country":"AU",
    "sg:address":"86 Downs St",
    "sg:city":"North Ipswich",
    "sg:classifiers":[
        {
            "category":"Shopping",
            "subcategory":"Clothing, Apparel, & Fashions",
            "type":"Retail Goods"
        }
    ],
    "sg:phone":"+61 7 3281 0475",
    "sg:postcode":"4305",
    "sg:province":"QLD",
    "sg:tags":[
        "lady",
        "wear"
    ],
    "wof:name":"Alamode Boutique",
    "wof:placetype":"venue"
},
  "geometry": {"coordinates":[152.76286315900001,-27.5997180939],"type":"Point"}
}