{
  "type": "Feature",
  "properties": {
    "iso:country":"AU",
    "sg:address":"368 Rossmoyne St",
    "sg:city":"Thornbury",
    "sg:classifiers":[
        {
            "category":"Professional",
            "type":"Services"
        }
    ],
    "sg:phone":"+61 3 9416 8731",
    "sg:postcode":"3071",
    "sg:province":"VIC",
    "sg:tags":[
        "transport"
    ],
    "wof:name":"Australian Link Pty Ltd",
    "wof:placetype":"venue"
},
  "geometry": {"coordinates":[145.02804565400001,-37.7601356506],"type":"Point"}
}