{
  "type": "Feature",
  "properties": {
    "addr:full":"482 Macauley St Albury NSW 2640",
    "addr:housenumber":"482",
    "addr:postcode":"2640",
    "addr:street":"Macauley St",
    "iso:country":"AU",
    "sg:address":"482 Macauley St",
    "sg:city":"Albury",
    "sg:classifiers":[
        {
            "category":"Health Services",
            "subcategory":"Health Practitioner",
            "type":"Services"
        }
    ],
    "sg:phone":"+61 2 6041 4494",
    "sg:postcode":"2640",
    "sg:province":"NSW",
    "sg:tags":[
        "psychologist"
    ],
    "wof:name":"Interpsych Services",
    "wof:placetype":"venue"
},
  "geometry": {"coordinates":[146.92210388199999,-36.0822753906],"type":"Point"}
}