{
  "type": "Feature",
  "properties": {
    "iso:country":"AU",
    "sg:address":"89 Heal St",
    "sg:city":"New Farm",
    "sg:classifiers":[
        {
            "category":"Personal",
            "subcategory":"Beauty Salon",
            "type":"Services"
        }
    ],
    "sg:phone":"+61 7 3358 4455",
    "sg:postcode":"4005",
    "sg:province":"QLD",
    "sg:tags":[
        "hairdresser"
    ],
    "wof:name":"Sculpture On Clay",
    "wof:placetype":"venue"
},
  "geometry": {"coordinates":[153.043579102,-27.4619293213],"type":"Point"}
}