{
  "type": "Feature",
  "properties": {
    "addr:full":"46 Nepean Hwy Mentone VIC 3194",
    "addr:housenumber":"46",
    "addr:postcode":"3194",
    "addr:street":"Nepean Hwy",
    "iso:country":"AU",
    "sg:address":"46 Nepean Hwy",
    "sg:city":"Mentone",
    "sg:classifiers":[
        {
            "category":"Shopping",
            "subcategory":"Bicycles & Sporting Goods",
            "type":"Retail Goods"
        }
    ],
    "sg:phone":"+61 3 9584 8422",
    "sg:postcode":"3194",
    "sg:province":"VIC",
    "sg:tags":[
        "chemical",
        "equipment",
        "pool",
        "swimming"
    ],
    "wof:name":"Kreepy Krauly",
    "wof:placetype":"venue"
},
  "geometry": {"coordinates":[145.06605529800001,-37.9764709473],"type":"Point"}
}