{
  "type": "Feature",
  "properties": {
    "addr:full":"Shp 17, 33 Hollywell Rd Biggera Waters QLD 4216",
    "addr:housenumber":"33",
    "addr:postcode":"4216",
    "addr:street":"Hollywell Rd",
    "iso:country":"AU",
    "sg:address":"Shp 17, 33 Hollywell Rd",
    "sg:city":"Biggera Waters",
    "sg:classifiers":[
        {
            "category":"Shopping",
            "subcategory":"Clothing, Apparel, & Fashions",
            "type":"Retail Goods"
        }
    ],
    "sg:phone":"+61 7 5537 1012",
    "sg:postcode":"4216",
    "sg:province":"QLD",
    "sg:tags":[
        "lady",
        "wear"
    ],
    "wof:name":"What Women Want",
    "wof:placetype":"venue"
},
  "geometry": {"coordinates":[153.39996337900001,-27.9329586029],"type":"Point"}
}