{
  "type": "Feature",
  "properties": {
    "addr:full":"Unit 4, 90 Northlink Pl Virginia QLD 4014",
    "addr:housenumber":"90",
    "addr:postcode":"4014",
    "addr:street":"Northlink Pl",
    "iso:country":"AU",
    "sg:address":"Unit 4, 90 Northlink Pl",
    "sg:city":"Virginia",
    "sg:classifiers":[
        {
            "category":"Health Services",
            "subcategory":"Clinic",
            "type":"Services"
        }
    ],
    "sg:phone":"+61 7 3256 8500",
    "sg:postcode":"4014",
    "sg:province":"QLD",
    "sg:tags":[
        "aromatherapy"
    ],
    "wof:name":"Perfect Potion",
    "wof:placetype":"venue"
},
  "geometry": {"coordinates":[153.07066345199999,-27.3844032288],"type":"Point"}
}