{
  "type": "Feature",
  "properties": {
    "iso:country":"AU",
    "sg:address":"5th Floor Bradford House 195 North Tce",
    "sg:city":"Adelaide",
    "sg:classifiers":[
        {
            "category":"Health Services",
            "subcategory":"Dentist",
            "type":"Services"
        }
    ],
    "sg:phone":"+61 8 8223 3644",
    "sg:postcode":"5000",
    "sg:province":"SA",
    "wof:name":"Gallagher Damian P",
    "wof:placetype":"venue"
},
  "geometry": {"coordinates":[138.60076904300001,-34.9256401062],"type":"Point"}
}