{
  "type": "Feature",
  "properties": {
    "iso:country":"AU",
    "sg:address":"1/ 160 Shepherd St",
    "sg:city":"North Rockhampton",
    "sg:classifiers":[
        {
            "category":"Building & Trades",
            "subcategory":"Construction",
            "type":"Services"
        }
    ],
    "sg:phone":"+61 438 821 228",
    "sg:postcode":"4701",
    "sg:province":"QLD",
    "sg:tags":[
        "joiner",
        "carpenter"
    ],
    "wof:name":"Moren M S",
    "wof:placetype":"venue"
},
  "geometry": {"coordinates":[150.54159545900001,-23.3660888672],"type":"Point"}
}