{
  "type": "Feature",
  "properties": {
    "addr:full":"PO Box 599 Willetton WA 6955",
    "addr:postcode":"6955",
    "iso:country":"AU",
    "sg:address":"PO Box 599",
    "sg:city":"Willetton",
    "sg:classifiers":[
        {
            "category":"Shopping",
            "subcategory":"Bicycles & Sporting Goods",
            "type":"Retail Goods"
        }
    ],
    "sg:phone":"+61 428 398 528",
    "sg:postcode":"6955",
    "sg:province":"WA",
    "sg:tags":[
        "chemical",
        "equipment",
        "pool",
        "swimming"
    ],
    "wof:name":"South West Cafe Blinds & Shade Solutions",
    "wof:placetype":"venue"
},
  "geometry": {"coordinates":[115.881530762,-32.053150177],"type":"Point"}
}