{
  "type": "Feature",
  "properties": {
    "addr:full":"8- 10 Warren Pl Silverdale NSW 2752",
    "addr:housenumber":"10",
    "addr:postcode":"2752",
    "addr:street":"8",
    "iso:country":"AU",
    "sg:address":"8- 10 Warren Pl",
    "sg:city":"Silverdale",
    "sg:classifiers":[
        {
            "category":"Professional",
            "subcategory":"Engineering",
            "type":"Services"
        }
    ],
    "sg:phone":"+61 2 4774 2633",
    "sg:postcode":"2752",
    "sg:province":"NSW",
    "sg:tags":[
        "engineer",
        "mechanical"
    ],
    "wof:name":"Walden Motorsport",
    "wof:placetype":"venue"
},
  "geometry": {"coordinates":[150.612625122,-33.892906189],"type":"Point"}
}