{
  "type": "Feature",
  "properties": {
    "iso:country":"AU",
    "sg:address":"169 Sydney St",
    "sg:city":"Mackay",
    "sg:classifiers":[
        {
            "category":"Health Services",
            "subcategory":"Doctor",
            "type":"Services"
        }
    ],
    "sg:phone":"+61 7 4957 4077",
    "sg:postcode":"4740",
    "sg:province":"QLD",
    "sg:tags":[
        "occupational",
        "safety"
    ],
    "wof:name":"Simtars",
    "wof:placetype":"venue"
},
  "geometry": {"coordinates":[149.185791,-21.151234],"type":"Point"}
}