{
  "type": "Feature",
  "properties": {
    "iso:country":"AU",
    "sg:address":"Level 1, 102 Albert",
    "sg:city":"South Melbourne",
    "sg:classifiers":[
        {
            "category":"Banks & Credit Unions",
            "subcategory":"Bank",
            "type":"Services"
        }
    ],
    "sg:phone":"+61 13 28 88",
    "sg:postcode":"3205",
    "sg:province":"VIC",
    "sg:tags":[
        "society"
    ],
    "wof:name":"Members Australia Credit Union.",
    "wof:placetype":"venue"
},
  "geometry": {"coordinates":[144.962357,-37.840492],"type":"Point"}
}