{
  "type": "Feature",
  "properties": {
    "addr:full":"Unit 2/32- 60 Alice St Newtown NSW 2042",
    "addr:housenumber":"60",
    "addr:postcode":"2042",
    "addr:street":"Alice St",
    "iso:country":"AU",
    "sg:address":"Unit 2/32- 60 Alice St",
    "sg:city":"Newtown",
    "sg:classifiers":[
        {
            "category":"Professional",
            "subcategory":"Printing & Photocopies",
            "type":"Services"
        }
    ],
    "sg:phone":"+61 2 9565 1498",
    "sg:postcode":"2042",
    "sg:province":"NSW",
    "sg:tags":[
        "screen",
        "printer"
    ],
    "wof:name":"Ockapella Print & Design",
    "wof:placetype":"venue"
},
  "geometry": {"coordinates":[151.177628,-33.903648],"type":"Point"}
}