{
  "type": "Feature",
  "properties": {
    "iso:country":"AU",
    "sg:address":"Shop 3/ 42 Princes Hwy",
    "sg:city":"Meningie",
    "sg:classifiers":[
        {
            "category":"Personal",
            "subcategory":"Beauty Salon",
            "type":"Services"
        }
    ],
    "sg:phone":"+61 8 8575 1190",
    "sg:postcode":"5264",
    "sg:province":"SA",
    "sg:tags":[
        "hairdresser"
    ],
    "wof:name":"Hair Stranz",
    "wof:placetype":"venue"
},
  "geometry": {"coordinates":[139.338394,-35.687622],"type":"Point"}
}