{
  "type": "Feature",
  "properties": {
    "iso:country":"AU",
    "sg:address":"531 Bickley Rd",
    "sg:city":"Maddington",
    "sg:classifiers":[
        {
            "category":"Professional",
            "subcategory":"Testing Lab",
            "type":"Services"
        }
    ],
    "sg:phone":"+61 8 9459 2785",
    "sg:postcode":"6109",
    "sg:province":"WA",
    "sg:tags":[
        "soil",
        "investigation"
    ],
    "wof:name":"Rainstorm",
    "wof:placetype":"venue"
},
  "geometry": {"coordinates":[116.001029968,-32.0339241028],"type":"Point"}
}