{
  "type": "Feature",
  "properties": {
    "addr:full":"10 Evans St Fairfield NSW 2165",
    "addr:housenumber":"10",
    "addr:postcode":"2165",
    "addr:street":"Evans St",
    "iso:country":"AU",
    "sg:address":"10 Evans St",
    "sg:city":"Fairfield",
    "sg:classifiers":[
        {
            "category":"Manufacturing",
            "subcategory":"Tools & Machinery",
            "type":"Manufacturing & Wholesale Goods"
        }
    ],
    "sg:phone":"+61 407 257 746",
    "sg:postcode":"2165",
    "sg:province":"NSW",
    "sg:tags":[
        "earth",
        "excavating",
        "moving",
        "equipment"
    ],
    "wof:name":"Easy Hire Plant",
    "wof:placetype":"venue"
},
  "geometry": {"coordinates":[150.94023132300001,-33.8690185547],"type":"Point"}
}