{
  "type": "Feature",
  "properties": {
    "addr:full":"1332 Anzac Ave Kallangur QLD 4503",
    "addr:housenumber":"1332",
    "addr:postcode":"4503",
    "addr:street":"Anzac Ave",
    "iso:country":"AU",
    "sg:address":"1332 Anzac Ave",
    "sg:city":"Kallangur",
    "sg:classifiers":[
        {
            "category":"Professional",
            "subcategory":"Art Services",
            "type":"Services"
        }
    ],
    "sg:phone":"+61 7 3886 5186",
    "sg:postcode":"4503",
    "sg:province":"QLD",
    "sg:tags":[
        "decorator",
        "painter"
    ],
    "wof:name":"J W McDonald Film & Video Conversions",
    "wof:placetype":"venue"
},
  "geometry": {"coordinates":[152.99737548799999,-27.2495975494],"type":"Point"}
}