{
  "type": "Feature",
  "properties": {
    "addr:full":"Level 3, 174 Victoria Pde East Melbourne VIC 3002",
    "addr:housenumber":"174",
    "addr:postcode":"3002",
    "addr:street":"Victoria Pde",
    "iso:country":"AU",
    "sg:address":"Level 3, 174 Victoria Pde",
    "sg:city":"East Melbourne",
    "sg:classifiers":[
        {
            "category":"Professional",
            "subcategory":"Accounting & Tax Preparation",
            "type":"Services"
        }
    ],
    "sg:phone":"+61 3 9663 8788",
    "sg:postcode":"3002",
    "sg:province":"VIC",
    "sg:tags":[
        "consultant",
        "taxation"
    ],
    "wof:name":"Stanwycks",
    "wof:placetype":"venue"
},
  "geometry": {"coordinates":[144.97769165,-37.808681488],"type":"Point"}
}