{
  "type": "Feature",
  "properties": {
    "addr:full":"Building 140, Entertainment Quarter Fox Studios Moore Park NSW 2021",
    "addr:housenumber":"140",
    "addr:postcode":"2021",
    "addr:street":"Entertainment Quarter",
    "iso:country":"AU",
    "sg:address":"Building 140, Entertainment Quarter Fox Studios",
    "sg:city":"Moore Park",
    "sg:classifiers":[
        {
            "category":"Communications",
            "type":"Services"
        }
    ],
    "sg:phone":"+61 1300 852 150",
    "sg:postcode":"2021",
    "sg:province":"NSW",
    "sg:tags":[
        "equipment",
        "radio"
    ],
    "wof:name":"Tin Can Telecom",
    "wof:placetype":"venue"
},
  "geometry": {"coordinates":[151.22596740700001,-33.8964805603],"type":"Point"}
}