{
  "type": "Feature",
  "properties": {
    "iso:country":"AU",
    "sg:address":"1286 Dandenong Rd",
    "sg:city":"Murrumbeena",
    "sg:classifiers":[
        {
            "category":"Health Services",
            "subcategory":"Dentist",
            "type":"Services"
        }
    ],
    "sg:phone":"+61 3 9568 3100",
    "sg:postcode":"3163",
    "sg:province":"VIC",
    "wof:name":"Sable Daniel Dr",
    "wof:placetype":"venue"
},
  "geometry": {"coordinates":[145.076538086,-37.886844635],"type":"Point"}
}