{
  "type": "Feature",
  "properties": {
    "addr:full":"49 Stevenson St Yeppoon QLD 4703",
    "addr:housenumber":"49",
    "addr:postcode":"4703",
    "addr:street":"Stevenson St",
    "iso:country":"AU",
    "sg:address":"49 Stevenson St",
    "sg:city":"Yeppoon",
    "sg:classifiers":[
        {
            "category":"Professional",
            "subcategory":"Art Services",
            "type":"Services"
        }
    ],
    "sg:phone":"+61 7 4939 1764",
    "sg:postcode":"4703",
    "sg:province":"QLD",
    "sg:tags":[
        "decorator",
        "painter"
    ],
    "wof:name":"Woodward D & H E",
    "wof:placetype":"venue"
},
  "geometry": {"coordinates":[150.745407105,-23.1063957214],"type":"Point"}
}