{
  "type": "Feature",
  "properties": {
    "iso:country":"AU",
    "sg:address":"95 Ringwood Rd",
    "sg:city":"Gatton",
    "sg:classifiers":[
        {
            "category":"Building & Trades",
            "subcategory":"Construction",
            "type":"Services"
        }
    ],
    "sg:phone":"+61 7 5462 2986",
    "sg:postcode":"4343",
    "sg:province":"QLD",
    "sg:tags":[
        "earth",
        "excavating",
        "moving",
        "contractor"
    ],
    "wof:name":"Bernie O&#039;Keeffe",
    "wof:placetype":"venue"
},
  "geometry": {"coordinates":[152.22821044899999,-27.5480422974],"type":"Point"}
}