{
  "type": "Feature",
  "properties": {
    "addr:full":"1 Bowen Rd Moonah TAS 7009",
    "addr:housenumber":"1",
    "addr:postcode":"7009",
    "addr:street":"Bowen Rd",
    "iso:country":"AU",
    "sg:address":"1 Bowen Rd",
    "sg:city":"Moonah",
    "sg:classifiers":[
        {
            "category":"Organizations",
            "subcategory":"Non-profit Organization",
            "type":"Services"
        }
    ],
    "sg:phone":"+61 3 6228 9099",
    "sg:postcode":"7009",
    "sg:province":"TAS",
    "sg:tags":[
        "support",
        "disability",
        "organisation"
    ],
    "wof:name":"Langford Support Services Inc",
    "wof:placetype":"venue"
},
  "geometry": {"coordinates":[147.30596923799999,-42.8500556946],"type":"Point"}
}