{
  "type": "Feature",
  "properties": {
    "iso:country":"AU",
    "sg:address":"54 Barnard St",
    "sg:city":"Gladstone",
    "sg:classifiers":[
        {
            "category":"Autos & Motor Vehicles",
            "subcategory":"Fuel & Gas Station",
            "type":"Retail Goods"
        }
    ],
    "sg:phone":"+61 2 6567 4591",
    "sg:postcode":"2440",
    "sg:province":"NSW",
    "wof:name":"Barbers Auto-Port",
    "wof:placetype":"venue"
},
  "geometry": {"coordinates":[152.948578,-31.022655],"type":"Point"}
}