{
  "type": "Feature",
  "properties": {
    "addr:full":"1 New Britain Rd Robinvale VIC 3549",
    "addr:housenumber":"1",
    "addr:postcode":"3549",
    "addr:street":"New Britain Rd",
    "iso:country":"AU",
    "sg:address":"1 New Britain Rd",
    "sg:city":"Robinvale",
    "sg:classifiers":[
        {
            "category":"Farming",
            "subcategory":"Berry Farm",
            "type":"Manufacturing & Wholesale Goods"
        }
    ],
    "sg:phone":"+61 3 5026 4050",
    "sg:postcode":"3549",
    "sg:province":"VIC",
    "sg:tags":[
        "fruit",
        "grower"
    ],
    "wof:name":"Zappia G & C",
    "wof:placetype":"venue"
},
  "geometry": {"coordinates":[142.76824951200001,-34.6126556396],"type":"Point"}
}