{
  "type": "Feature",
  "properties": {
    "addr:full":"10 Allenby Ave Glen Iris VIC 3146",
    "addr:housenumber":"10",
    "addr:postcode":"3146",
    "addr:street":"Allenby Ave",
    "iso:country":"AU",
    "sg:address":"10 Allenby Ave",
    "sg:city":"Glen Iris",
    "sg:classifiers":[
        {
            "category":"Building & Trades",
            "subcategory":"Construction",
            "type":"Services"
        }
    ],
    "sg:phone":"+61 3 9885 7005",
    "sg:postcode":"3146",
    "sg:province":"VIC",
    "sg:tags":[
        "contractor"
    ],
    "wof:name":"A & C Quality Constructions",
    "wof:placetype":"venue"
},
  "geometry": {"coordinates":[145.059036255,-37.8640441895],"type":"Point"}
}