{
  "type": "Feature",
  "properties": {
    "addr:full":"Shop 5/ 3 Dennis Rd Springwood QLD 4127",
    "addr:housenumber":"shop 5 / 3",
    "addr:postcode":"4127",
    "addr:street":"Dennis Rd",
    "iso:country":"AU",
    "sg:address":"Shop 5/ 3 Dennis Rd",
    "sg:city":"Springwood",
    "sg:classifiers":[
        {
            "category":"Health Services",
            "subcategory":"Health Practitioner",
            "type":"Services"
        }
    ],
    "sg:phone":"+61 1300 762 312",
    "sg:postcode":"4127",
    "sg:province":"QLD",
    "sg:tags":[
        "physiotherapist"
    ],
    "sg:website":"http://www.proactivetherapy.com.au",
    "wof:name":"Proactive Therapy",
    "wof:placetype":"venue"
},
  "geometry": {"coordinates":[153.127853394,-27.6215267181],"type":"Point"}
}