{
  "type": "Feature",
  "properties": {
    "addr:full":"Mosman St Mosman NSW 2088",
    "addr:postcode":"2088",
    "addr:street":"Mosman St",
    "iso:country":"AU",
    "sg:address":"Mosman St",
    "sg:city":"Mosman",
    "sg:classifiers":[
        {
            "category":"Personal",
            "type":"Services"
        }
    ],
    "sg:phone":"+61 2 9960 5115",
    "sg:postcode":"2088",
    "sg:province":"NSW",
    "sg:tags":[
        "introduction",
        "social"
    ],
    "wof:name":"JuliannaAndFriends.com.au",
    "wof:placetype":"venue"
},
  "geometry": {"coordinates":[151.235565186,-33.8372116089],"type":"Point"}
}