{
  "type": "Feature",
  "properties": {
    "addr:full":"121/ 8 Koorala St Manly Vale NSW 2093",
    "addr:housenumber":"121 / 8",
    "addr:postcode":"2093",
    "addr:street":"Koorala St",
    "iso:country":"AU",
    "sg:address":"121/ 8 Koorala St",
    "sg:city":"Manly Vale",
    "sg:classifiers":[
        {
            "category":"Professional",
            "subcategory":"Art Services",
            "type":"Services"
        }
    ],
    "sg:phone":"+61 410 867 703",
    "sg:postcode":"2093",
    "sg:province":"NSW",
    "sg:tags":[
        "interior",
        "designer"
    ],
    "wof:name":"Tahlia Creative Colour",
    "wof:placetype":"venue"
},
  "geometry": {"coordinates":[151.26800537099999,-33.7852859497],"type":"Point"}
}