{
  "type": "Feature",
  "properties": {
    "addr:full":"7 Watland St Springwood QLD 4127",
    "addr:housenumber":"7",
    "addr:postcode":"4127",
    "addr:street":"Watland St",
    "iso:country":"AU",
    "sg:address":"7 Watland St",
    "sg:city":"Springwood",
    "sg:classifiers":[
        {
            "category":"Autos & Motor Vehicles",
            "subcategory":"Automobile Sales",
            "type":"Retail Goods"
        }
    ],
    "sg:phone":"+61 7 3208 2099",
    "sg:postcode":"4127",
    "sg:province":"QLD",
    "sg:tags":[
        "car",
        "new"
    ],
    "wof:name":"Vicon Enterprises Pty Ltd",
    "wof:placetype":"venue"
},
  "geometry": {"coordinates":[153.12997436500001,-27.6247615814],"type":"Point"}
}