{
  "type": "Feature",
  "properties": {
    "addr:full":"405 Rifle Range Rd Alstonville NSW 2477",
    "addr:housenumber":"405",
    "addr:postcode":"2477",
    "addr:street":"Rifle Range Rd",
    "iso:country":"AU",
    "sg:address":"405 Rifle Range Rd",
    "sg:city":"Alstonville",
    "sg:classifiers":[
        {
            "category":"Farming",
            "subcategory":"Farm",
            "type":"Manufacturing & Wholesale Goods"
        }
    ],
    "sg:phone":"+61 410 662 856",
    "sg:postcode":"2477",
    "sg:province":"NSW",
    "sg:tags":[
        "farmer"
    ],
    "wof:name":"BARDWELL'S BERRY FARM",
    "wof:placetype":"venue"
},
  "geometry": {"coordinates":[153.44825744600001,-28.8171482086],"type":"Point"}
}