{
  "type": "Feature",
  "properties": {
    "iso:country":"AU",
    "sg:address":"5 Jaybel St",
    "sg:city":"Salisbury",
    "sg:classifiers":[
        {
            "category":"Shopping",
            "subcategory":"Party Supplies",
            "type":"Retail Goods"
        }
    ],
    "sg:phone":"+61 7 3274 1171",
    "sg:postcode":"4107",
    "sg:province":"QLD",
    "sg:tags":[
        "hire",
        "costume"
    ],
    "wof:name":"Sweidas",
    "wof:placetype":"venue"
},
  "geometry": {"coordinates":[153.037841797,-27.5425205231],"type":"Point"}
}