{
  "type": "Feature",
  "properties": {
    "iso:country":"AU",
    "sg:address":"92 Pier St",
    "sg:city":"Altona",
    "sg:classifiers":[
        {
            "category":"Shopping",
            "subcategory":"Optical Goods",
            "type":"Retail Goods"
        }
    ],
    "sg:phone":"+61 3 9315 0499",
    "sg:postcode":"3018",
    "sg:province":"VIC",
    "sg:tags":[
        "dispenser",
        "prescription"
    ],
    "wof:name":"Australian Eyecare",
    "wof:placetype":"venue"
},
  "geometry": {"coordinates":[144.83071899399999,-37.8675498962],"type":"Point"}
}