{
  "type": "Feature",
  "properties": {
    "addr:full":"Cnr Fitzroy & Bolsover Sts Rockhampton QLD 4700",
    "addr:postcode":"4700",
    "addr:street":"Cnr",
    "iso:country":"AU",
    "sg:address":"Cnr Fitzroy & Bolsover Sts",
    "sg:city":"Rockhampton",
    "sg:classifiers":[
        {
            "category":"Insurance",
            "subcategory":"Hazard Insurance",
            "type":"Services"
        }
    ],
    "sg:phone":"+61 7 4927 6266",
    "sg:postcode":"4700",
    "sg:province":"QLD",
    "sg:tags":[
        "fire",
        "accident",
        "marine"
    ],
    "wof:name":"CGU",
    "wof:placetype":"venue"
},
  "geometry": {"coordinates":[150.49977111800001,-23.3842449188],"type":"Point"}
}