{
  "type": "Feature",
  "properties": {
    "iso:country":"AU",
    "sg:address":"395 St Paul's Tce",
    "sg:city":"Fortitude Valley",
    "sg:classifiers":[
        {
            "category":"Real Estate",
            "subcategory":"Real Estate Services",
            "type":"Services"
        }
    ],
    "sg:phone":"+61 7 3251 3000",
    "sg:postcode":"4006",
    "sg:province":"QLD",
    "sg:tags":[
        "consultant",
        "property"
    ],
    "wof:name":"Retailers Assoc. Qld Ltd Business Consulting Group",
    "wof:placetype":"venue"
},
  "geometry": {"coordinates":[153.035324097,-27.4581394196],"type":"Point"}
}