{
  "type": "Feature",
  "properties": {
    "addr:full":"194 Bellarine Hwy Newcomb VIC 3219",
    "addr:housenumber":"194",
    "addr:postcode":"3219",
    "addr:street":"Bellarine Hwy",
    "iso:country":"AU",
    "sg:address":"194 Bellarine Hwy",
    "sg:city":"Newcomb",
    "sg:classifiers":[
        {
            "category":"Autos & Motor Vehicles",
            "subcategory":"Auto Supplies",
            "type":"Retail Goods"
        }
    ],
    "sg:phone":"+61 13 21 91",
    "sg:postcode":"3219",
    "sg:province":"VIC",
    "sg:tags":[
        "tyre"
    ],
    "wof:name":"Lewis Tyrepower",
    "wof:placetype":"venue"
},
  "geometry": {"coordinates":[144.39312744099999,-38.170879364],"type":"Point"}
}