{
  "type": "Feature",
  "properties": {
    "addr:full":"Level 3/ 50 York Sydney NSW 2000",
    "addr:housenumber":"/ 50",
    "addr:postcode":"2000",
    "iso:country":"AU",
    "sg:address":"Level 3/ 50 York",
    "sg:city":"Sydney",
    "sg:classifiers":[
        {
            "category":"Personal",
            "type":"Services"
        }
    ],
    "sg:phone":"+61 1300 885 402",
    "sg:postcode":"2000",
    "sg:province":"NSW",
    "sg:tags":[
        "introduction",
        "social"
    ],
    "wof:name":"Elite Introductions International",
    "wof:placetype":"venue"
},
  "geometry": {"coordinates":[151.206344605,-33.8696937561],"type":"Point"}
}