{
  "type": "Feature",
  "properties": {
    "addr:full":"14 Hehir St Belmont WA 6104",
    "addr:housenumber":"14",
    "addr:postcode":"6104",
    "addr:street":"Hehir St",
    "iso:country":"AU",
    "sg:address":"14 Hehir St",
    "sg:city":"Belmont",
    "sg:classifiers":[
        {
            "category":"Manufacturing",
            "subcategory":"Paper Products",
            "type":"Manufacturing & Wholesale Goods"
        }
    ],
    "sg:phone":"+61 8 9277 1400",
    "sg:postcode":"6104",
    "sg:province":"WA",
    "sg:tags":[
        "box",
        "fibre",
        "carton",
        "cardboard"
    ],
    "sg:website":"http://www.colortype.com.au",
    "wof:name":"Colortype Press",
    "wof:placetype":"venue"
},
  "geometry": {"coordinates":[115.92263794,-31.9468002319],"type":"Point"}
}