{
  "type": "Feature",
  "properties": {
    "iso:country":"AU",
    "sg:address":"18 Foundry Rd",
    "sg:city":"Seven Hills",
    "sg:classifiers":[
        {
            "category":"Shopping",
            "subcategory":"Stationery & Office Supplies",
            "type":"Retail Goods"
        }
    ],
    "sg:phone":"+61 2 9674 2222",
    "sg:postcode":"2147",
    "sg:province":"NSW",
    "sg:tags":[
        "pottery",
        "equipment"
    ],
    "wof:name":"Portugal Cork Co Pty Ltd",
    "wof:placetype":"venue"
},
  "geometry": {"coordinates":[150.95596313499999,-33.7694892883],"type":"Point"}
}