{
  "type": "Feature",
  "properties": {
    "iso:country":"AU",
    "sg:address":"215 Charles St",
    "sg:city":"Heatley",
    "sg:classifiers":[
        {
            "category":"Building & Trades",
            "subcategory":"Construction",
            "type":"Services"
        }
    ],
    "sg:phone":"+61 7 4728 4744",
    "sg:postcode":"4814",
    "sg:province":"QLD",
    "sg:tags":[
        "roof"
    ],
    "wof:name":"Extreme Roofing",
    "wof:placetype":"venue"
},
  "geometry": {"coordinates":[146.75259399999999,-19.295504],"type":"Point"}
}