{
  "type": "Feature",
  "properties": {
    "iso:country":"AU",
    "sg:address":"103 Reservoir St",
    "sg:city":"Surry Hills",
    "sg:classifiers":[
        {
            "category":"Shopping",
            "subcategory":"Clothing, Apparel, & Fashions",
            "type":"Retail Goods"
        }
    ],
    "sg:phone":"+61 2 9281 7605",
    "sg:postcode":"2010",
    "sg:province":"NSW",
    "sg:tags":[
        "accessory"
    ],
    "wof:name":"Sydney Park Fashion Warehouse",
    "wof:placetype":"venue"
},
  "geometry": {"coordinates":[151.21205139200001,-33.8814506531],"type":"Point"}
}