{
  "type": "Feature",
  "properties": {
    "iso:country":"AU",
    "sg:address":"2 Cassia Crt",
    "sg:city":"Annandale",
    "sg:classifiers":[
        {
            "category":"Professional",
            "subcategory":"Accounting & Tax Preparation",
            "type":"Services"
        }
    ],
    "sg:phone":"+61 7 4728 6033",
    "sg:postcode":"4814",
    "sg:province":"QLD",
    "sg:tags":[
        "bookkeeping"
    ],
    "wof:name":"Admin Angel (NQ)",
    "wof:placetype":"venue"
},
  "geometry": {"coordinates":[146.772354,-19.316828],"type":"Point"}
}