{
  "type": "Feature",
  "properties": {
    "addr:full":"15 Sloss St Horsham VIC 3400",
    "addr:housenumber":"15",
    "addr:postcode":"3400",
    "addr:street":"Sloss St",
    "iso:country":"AU",
    "sg:address":"15 Sloss St",
    "sg:city":"Horsham",
    "sg:classifiers":[
        {
            "category":"Professional",
            "subcategory":"Printing & Photocopies",
            "type":"Services"
        }
    ],
    "sg:phone":"+61 3 5381 1721",
    "sg:postcode":"3400",
    "sg:province":"VIC",
    "sg:tags":[
        "textile",
        "clothing"
    ],
    "wof:name":"Dags Quality Screenprinting",
    "wof:placetype":"venue"
},
  "geometry": {"coordinates":[142.20466613799999,-36.7195320129],"type":"Point"}
}