{
  "type": "Feature",
  "properties": {
    "addr:full":"2 Frederick St Frewville SA 5063",
    "addr:housenumber":"2",
    "addr:postcode":"5063",
    "addr:street":"Frederick St",
    "iso:country":"AU",
    "sg:address":"2 Frederick St",
    "sg:city":"Frewville",
    "sg:classifiers":[
        {
            "category":"Health Services",
            "subcategory":"Health Practitioner",
            "type":"Services"
        }
    ],
    "sg:phone":"+61 8 8379 6892",
    "sg:postcode":"5063",
    "sg:province":"SA",
    "sg:tags":[
        "physiotherapist"
    ],
    "wof:name":"Arkaba Physiotherapy Clinic",
    "wof:placetype":"venue"
},
  "geometry": {"coordinates":[138.630584717,-34.9489402771],"type":"Point"}
}