{
  "type": "Feature",
  "properties": {
    "addr:full":"54 Considine St Ellen Grove QLD 4078",
    "addr:housenumber":"54",
    "addr:postcode":"4078",
    "addr:street":"Considine St Ellen Grove",
    "iso:country":"AU",
    "sg:address":"54 Considine St",
    "sg:city":"Ellen Grove",
    "sg:classifiers":[
        {
            "category":"Farming",
            "subcategory":"Nursery",
            "type":"Manufacturing & Wholesale Goods"
        }
    ],
    "sg:phone":"+61 7 3271 2585",
    "sg:postcode":"4078",
    "sg:province":"QLD",
    "wof:name":"Ellen Grove Wholesale Nursery",
    "wof:placetype":"venue"
},
  "geometry": {"coordinates":[152.94430542000001,-27.615655899],"type":"Point"}
}