{
  "type": "Feature",
  "properties": {
    "iso:country":"AU",
    "sg:address":"18- 20 Waterloo St",
    "sg:city":"Narrabeen",
    "sg:classifiers":[
        {
            "category":"Professional",
            "subcategory":"Accounting & Tax Preparation",
            "type":"Services"
        }
    ],
    "sg:phone":"+61 1300 727 082",
    "sg:postcode":"2101",
    "sg:province":"NSW",
    "sg:tags":[
        "accountant",
        "auditor"
    ],
    "wof:name":"Osborne Yuille (NSW) Pty Ltd",
    "wof:placetype":"venue"
},
  "geometry": {"coordinates":[151.298157,-33.71315],"type":"Point"}
}