{
  "type": "Feature",
  "properties": {
    "iso:country":"AU",
    "sg:address":"3/ 25 Moore St",
    "sg:city":"Brighton East",
    "sg:classifiers":[
        {
            "category":"Professional",
            "subcategory":"Accounting & Tax Preparation",
            "type":"Services"
        }
    ],
    "sg:phone":"+61 3 9596 8442",
    "sg:postcode":"3187",
    "sg:province":"VIC",
    "sg:tags":[
        "bookkeeping"
    ],
    "wof:name":"Southern Bookkeeping Services",
    "wof:placetype":"venue"
},
  "geometry": {"coordinates":[145.01017761200001,-37.902141571],"type":"Point"}
}