{
  "type": "Feature",
  "properties": {
    "iso:country":"AU",
    "sg:address":"23 Kavieng St",
    "sg:city":"Trinity Beach",
    "sg:classifiers":[
        {
            "category":"Building & Trades",
            "subcategory":"Plumbing",
            "type":"Services"
        }
    ],
    "sg:phone":"+61 409 518 418",
    "sg:postcode":"4879",
    "sg:province":"QLD",
    "sg:tags":[
        "plumber",
        "gasfitters"
    ],
    "wof:name":"Pisces Plumbing",
    "wof:placetype":"venue"
},
  "geometry": {"coordinates":[145.68923950199999,-16.7934494019],"type":"Point"}
}