{
  "type": "Feature",
  "properties": {
    "iso:country":"AU",
    "sg:address":"17 Prindle St",
    "sg:city":"Oatlands",
    "sg:classifiers":[
        {
            "category":"Professional",
            "subcategory":"Engineering",
            "type":"Services"
        }
    ],
    "sg:phone":"+61 2 9890 1451",
    "sg:postcode":"2117",
    "sg:province":"NSW",
    "sg:tags":[
        "consulting",
        "engineer"
    ],
    "wof:name":"Greg Simpson Structural Engineer",
    "wof:placetype":"venue"
},
  "geometry": {"coordinates":[151.02503967300001,-33.7948722839],"type":"Point"}
}