{
  "type": "Feature",
  "properties": {
    "addr:full":"163 Woodpark Rd Smithfield NSW 2164",
    "addr:housenumber":"163",
    "addr:postcode":"2164",
    "addr:street":"Woodpark Rd",
    "iso:country":"AU",
    "sg:address":"163 Woodpark Rd",
    "sg:city":"Smithfield",
    "sg:classifiers":[
        {
            "category":"Home & Garden",
            "subcategory":"Building Materials",
            "type":"Retail Goods"
        }
    ],
    "sg:phone":"+61 2 9757 2366",
    "sg:postcode":"2164",
    "sg:province":"NSW",
    "sg:tags":[
        "laminate",
        "laminated",
        "panel"
    ],
    "wof:name":"Master Benchtops",
    "wof:placetype":"venue"
},
  "geometry": {"coordinates":[150.93360900900001,-33.8363037109],"type":"Point"}
}