{
  "type": "Feature",
  "properties": {
    "addr:full":"Suite 213B 250 McCullough St Sunnybank QLD 4109",
    "addr:housenumber":"250",
    "addr:postcode":"4109",
    "addr:street":"Mccullough St",
    "iso:country":"AU",
    "sg:address":"Suite 213B 250 McCullough St",
    "sg:city":"Sunnybank",
    "sg:classifiers":[
        {
            "category":"Health Services",
            "subcategory":"Doctor",
            "type":"Services"
        }
    ],
    "sg:phone":"+61 7 3216 9211",
    "sg:postcode":"4109",
    "sg:province":"QLD",
    "sg:tags":[
        "medical",
        "practitioner"
    ],
    "wof:name":"Carmody Dr Frank",
    "wof:placetype":"venue"
},
  "geometry": {"coordinates":[153.061157227,-27.5790500641],"type":"Point"}
}