{
  "type": "Feature",
  "properties": {
    "iso:country":"AU",
    "sg:address":"2 Florence St",
    "sg:city":"Moonah",
    "sg:classifiers":[
        {
            "category":"Autos & Motor Vehicles",
            "subcategory":"Auto Supplies",
            "type":"Retail Goods"
        }
    ],
    "sg:phone":"+61 3 6228 6626",
    "sg:postcode":"7009",
    "sg:province":"TAS",
    "sg:tags":[
        "part",
        "cycles",
        "accessory"
    ],
    "wof:name":"Suzuki Motorcycles",
    "wof:placetype":"venue"
},
  "geometry": {"coordinates":[147.29664611800001,-42.8494148254],"type":"Point"}
}