{
  "type": "Feature",
  "properties": {
    "addr:full":"Park Ridge Shopping Village Park Ridge QLD 4125",
    "addr:postcode":"4125",
    "iso:country":"AU",
    "sg:address":"Park Ridge Shopping Village",
    "sg:city":"Park Ridge",
    "sg:classifiers":[
        {
            "category":"Health Services",
            "subcategory":"Optometrist",
            "type":"Services"
        }
    ],
    "sg:phone":"+61 7 3802 2299",
    "sg:postcode":"4125",
    "sg:province":"QLD",
    "wof:name":"Park Ridge Eyewear",
    "wof:placetype":"venue"
},
  "geometry": {"coordinates":[153.03749084500001,-27.6962432861],"type":"Point"}
}