{
  "type": "Feature",
  "properties": {
    "addr:full":"Showcase On The Beach (under Cinema) Griffith St Coolangatta QLD 4225",
    "addr:postcode":"4225",
    "addr:street":"Griffith St",
    "iso:country":"AU",
    "sg:address":"Showcase On The Beach (under Cinema) Griffith St",
    "sg:city":"Coolangatta",
    "sg:classifiers":[
        {
            "category":"Health Services",
            "subcategory":"Doctor",
            "type":"Services"
        }
    ],
    "sg:phone":"+61 7 5536 6771",
    "sg:postcode":"4225",
    "sg:province":"QLD",
    "sg:tags":[
        "medical",
        "practitioner"
    ],
    "wof:name":"Clements Dr Tony",
    "wof:placetype":"venue"
},
  "geometry": {"coordinates":[153.53785705600001,-28.1684036255],"type":"Point"}
}