{
  "type": "Feature",
  "properties": {
    "addr:full":"16 Pineligh Rd Seven Hills NSW 2147",
    "addr:housenumber":"16",
    "addr:postcode":"2147",
    "addr:street":"Pineligh Rd",
    "iso:country":"AU",
    "sg:address":"16 Pineligh Rd",
    "sg:city":"Seven Hills",
    "sg:classifiers":[
        {
            "category":"Professional",
            "subcategory":"Art Services",
            "type":"Services"
        }
    ],
    "sg:phone":"+61 2 9674 3760",
    "sg:postcode":"2147",
    "sg:province":"NSW",
    "sg:tags":[
        "decorator",
        "painter"
    ],
    "wof:name":"Absolute Quality Service",
    "wof:placetype":"venue"
},
  "geometry": {"coordinates":[150.94181823700001,-33.7643890381],"type":"Point"}
}