{
  "type": "Feature",
  "properties": {
    "iso:country":"AU",
    "sg:address":"Village Centre Shop, LG 1-2, 206",
    "sg:city":"Bourke Street Melbourne",
    "sg:classifiers":[
        {
            "category":"Shopping",
            "subcategory":"Music",
            "type":"Retail Goods"
        }
    ],
    "sg:phone":"+61 3 9650 0788",
    "sg:postcode":"3000",
    "sg:province":"VIC",
    "sg:tags":[
        "store"
    ],
    "wof:name":"JB HI-FI",
    "wof:placetype":"venue"
},
  "geometry": {"coordinates":[144.96693420400001,-37.8130073547],"type":"Point"}
}