{
  "type": "Feature",
  "properties": {
    "addr:full":"New England Hwy Severnlea QLD 4352",
    "addr:postcode":"4352",
    "addr:street":"England Hwy",
    "iso:country":"AU",
    "sg:address":"New England Hwy",
    "sg:city":"Severnlea",
    "sg:classifiers":[
        {
            "category":"Building & Trades",
            "subcategory":"Construction",
            "type":"Services"
        }
    ],
    "sg:phone":"+61 7 4683 5343",
    "sg:postcode":"4352",
    "sg:province":"QLD",
    "sg:tags":[
        "welding"
    ],
    "wof:name":"Speranza Mobile Welding",
    "wof:placetype":"venue"
},
  "geometry": {"coordinates":[151.902252,-28.705273],"type":"Point"}
}