{
  "type": "Feature",
  "properties": {
    "addr:full":"Shed 1/ 33 Hicks St Emerald QLD 4720",
    "addr:housenumber":"1 / 33",
    "addr:postcode":"4720",
    "addr:street":"Hicks St",
    "iso:country":"AU",
    "sg:address":"Shed 1/ 33 Hicks St",
    "sg:city":"Emerald",
    "sg:classifiers":[
        {
            "category":"Retail",
            "subcategory":"Auto Repair",
            "type":"Services"
        }
    ],
    "sg:phone":"+61 7 4982 1712",
    "sg:postcode":"4720",
    "sg:province":"QLD",
    "sg:tags":[
        "repairer",
        "motor",
        "engineer"
    ],
    "wof:name":"Peter Wheeler Automotive",
    "wof:placetype":"venue"
},
  "geometry": {"coordinates":[148.14465300000001,-23.525146],"type":"Point"}
}