{
  "type": "Feature",
  "properties": {
    "addr:full":"1 Ridley Ave Leeton NSW 2705",
    "addr:housenumber":"1",
    "addr:postcode":"2705",
    "addr:street":"Ridley Ave",
    "iso:country":"AU",
    "sg:address":"1 Ridley Ave",
    "sg:city":"Leeton",
    "sg:classifiers":[
        {
            "category":"Autos & Motor Vehicles",
            "subcategory":"Automobile Sales",
            "type":"Retail Goods"
        }
    ],
    "sg:phone":"+61 2 6953 3533",
    "sg:postcode":"2705",
    "sg:province":"NSW",
    "sg:tags":[
        "car",
        "new"
    ],
    "wof:name":"Owen Motor (Leeton) Pty Ltd",
    "wof:placetype":"venue"
},
  "geometry": {"coordinates":[146.38687133799999,-34.5502204895],"type":"Point"}
}