{
  "type": "Feature",
  "properties": {
    "iso:country":"AU",
    "sg:address":"Parsons Rd",
    "sg:city":"Dernancourt",
    "sg:classifiers":[
        {
            "category":"Education",
            "subcategory":"School",
            "type":"Public Place"
        }
    ],
    "sg:phone":"+61 8 8261 5006",
    "sg:postcode":"5075",
    "sg:province":"SA",
    "sg:tags":[
        "state",
        "except",
        "nsw"
    ],
    "wof:name":"Dernancourt Junior Primary",
    "wof:placetype":"venue"
},
  "geometry": {"coordinates":[138.671142578,-34.8615989685],"type":"Point"}
}