{
  "type": "Feature",
  "properties": {
    "iso:country":"AU",
    "sg:address":"Shop 3",
    "sg:city":"Medical Centre, Townsville Hospital Douglas",
    "sg:classifiers":[
        {
            "category":"Food & Beverages",
            "subcategory":"Bakery",
            "type":"Retail Goods"
        }
    ],
    "sg:phone":"+61 7 4775 6184",
    "sg:postcode":"4814",
    "sg:province":"QLD",
    "sg:tags":[
        "baker"
    ],
    "wof:name":"Brumbys Bakeries",
    "wof:placetype":"venue"
},
  "geometry": {"coordinates":[146.79028299999999,-19.266489],"type":"Point"}
}