{
  "type": "Feature",
  "properties": {
    "addr:full":"42 Churchill Rd East Killara NSW 2071",
    "addr:housenumber":"42",
    "addr:postcode":"2071",
    "addr:street":"Churchill Rd",
    "iso:country":"AU",
    "sg:address":"42 Churchill Rd",
    "sg:city":"East Killara",
    "sg:classifiers":[
        {
            "category":"Insurance",
            "subcategory":"Life Insurance",
            "type":"Services"
        }
    ],
    "sg:phone":"+61 2 9498 6578",
    "sg:postcode":"2071",
    "sg:province":"NSW",
    "wof:name":"Guarino Mario & Associates",
    "wof:placetype":"venue"
},
  "geometry": {"coordinates":[151.17805480999999,-33.7597198486],"type":"Point"}
}