{
  "type": "Feature",
  "properties": {
    "addr:full":"7 Council La Fairfield NSW 2165",
    "addr:housenumber":"7",
    "addr:postcode":"2165",
    "addr:street":"Council La",
    "iso:country":"AU",
    "sg:address":"7 Council La",
    "sg:city":"Fairfield",
    "sg:classifiers":[
        {
            "category":"Health Services",
            "subcategory":"Health Practitioner",
            "type":"Services"
        }
    ],
    "sg:phone":"+61 2 9728 9988",
    "sg:postcode":"2165",
    "sg:province":"NSW",
    "sg:tags":[
        "physiotherapist"
    ],
    "wof:name":"Rehab Solutions Australia",
    "wof:placetype":"venue"
},
  "geometry": {"coordinates":[150.955535889,-33.8710594177],"type":"Point"}
}