{
  "type": "Feature",
  "properties": {
    "addr:full":"81 Temple St Ballina NSW 2478",
    "addr:housenumber":"81",
    "addr:postcode":"2478",
    "addr:street":"Temple St",
    "iso:country":"AU",
    "sg:address":"81 Temple St",
    "sg:city":"Ballina",
    "sg:classifiers":[
        {
            "category":"Home & Garden",
            "subcategory":"Carpets & Floor Coverings",
            "type":"Retail Goods"
        }
    ],
    "sg:phone":"+61 2 6686 2176",
    "sg:postcode":"2478",
    "sg:province":"NSW",
    "sg:tags":[
        "tile",
        "wall",
        "layer"
    ],
    "wof:name":"Rainnie G A",
    "wof:placetype":"venue"
},
  "geometry": {"coordinates":[153.55560302699999,-28.8573303223],"type":"Point"}
}