{
  "type": "Feature",
  "properties": {
    "iso:country":"AU",
    "sg:address":"346 Hursley Rd",
    "sg:city":"Toowoomba",
    "sg:classifiers":[
        {
            "category":"Home & Garden",
            "subcategory":"Garden Supply",
            "type":"Retail Goods"
        }
    ],
    "sg:phone":"+61 7 4630 4211",
    "sg:postcode":"4350",
    "sg:province":"QLD",
    "sg:tags":[
        "landscape"
    ],
    "wof:name":"Torrington Landscape Centre",
    "wof:placetype":"venue"
},
  "geometry": {"coordinates":[151.879578,-27.550558],"type":"Point"}
}