{
  "type": "Feature",
  "properties": {
    "iso:country":"AU",
    "sg:address":"Shop 6 Gowrie St",
    "sg:city":"Singleton",
    "sg:classifiers":[
        {
            "category":"Professional",
            "subcategory":"Art Services",
            "type":"Services"
        }
    ],
    "sg:phone":"+61 2 6571 3101",
    "sg:postcode":"2330",
    "sg:province":"NSW",
    "sg:tags":[
        "graphic",
        "designer"
    ],
    "wof:name":"Artsmad Design And Print",
    "wof:placetype":"venue"
},
  "geometry": {"coordinates":[151.163956,-32.567196],"type":"Point"}
}