{
  "type": "Feature",
  "properties": {
    "addr:full":"Ste 3, 532 Station St Box Hill VIC 3128",
    "addr:housenumber":"532",
    "addr:postcode":"3128",
    "addr:street":"Station St",
    "iso:country":"AU",
    "sg:address":"Ste 3, 532 Station St",
    "sg:city":"Box Hill",
    "sg:classifiers":[
        {
            "category":"Professional",
            "subcategory":"Accounting & Tax Preparation",
            "type":"Services"
        }
    ],
    "sg:phone":"+61 3 9890 7471",
    "sg:postcode":"3128",
    "sg:province":"VIC",
    "sg:tags":[
        "consultant",
        "taxation"
    ],
    "wof:name":"H&R Block",
    "wof:placetype":"venue"
},
  "geometry": {"coordinates":[145.12338256800001,-37.8212051392],"type":"Point"}
}