{
  "type": "Feature",
  "properties": {
    "iso:country":"AU",
    "sg:address":"1080 Cambridge Rd",
    "sg:city":"Cambridge",
    "sg:classifiers":[
        {
            "category":"Building & Trades",
            "subcategory":"Construction",
            "type":"Services"
        }
    ],
    "sg:phone":"+61 3 6248 4363",
    "sg:postcode":"7170",
    "sg:province":"TAS",
    "sg:tags":[
        "joinery"
    ],
    "wof:name":"Wonderful Wardrobes",
    "wof:placetype":"venue"
},
  "geometry": {"coordinates":[147.45155334500001,-42.8342704773],"type":"Point"}
}