{
  "type": "Feature",
  "properties": {
    "iso:country":"AU",
    "sg:address":"207 Great North Rd",
    "sg:city":"Five Dock",
    "sg:classifiers":[
        {
            "category":"Personal",
            "subcategory":"Beauty Salon",
            "type":"Services"
        }
    ],
    "sg:phone":"+61 2 9712 0214",
    "sg:postcode":"2046",
    "sg:province":"NSW",
    "sg:tags":[
        "hairdresser"
    ],
    "wof:name":"High Mod Unisex Hair Design",
    "wof:placetype":"venue"
},
  "geometry": {"coordinates":[151.13002,-33.865952],"type":"Point"}
}