{
  "type": "Feature",
  "properties": {
    "addr:full":"Shop 4, Manuka Crt, 17 Bougainville St Manuka ACT 2603",
    "addr:housenumber":"shop 4;17",
    "addr:postcode":"2603",
    "addr:street":"Manuka Crt;Bougainville St",
    "iso:country":"AU",
    "sg:address":"Shop 4, Manuka Crt, 17 Bougainville St",
    "sg:city":"Manuka",
    "sg:classifiers":[
        {
            "category":"Shopping",
            "subcategory":"Clothing, Apparel, & Fashions",
            "type":"Retail Goods"
        }
    ],
    "sg:phone":"+61 2 6295 1146",
    "sg:postcode":"2603",
    "sg:province":"ACT",
    "sg:tags":[
        "lady",
        "wear"
    ],
    "wof:name":"Momento Dezigns",
    "wof:placetype":"venue"
},
  "geometry": {"coordinates":[149.13258361800001,-35.3208770752],"type":"Point"}
}