{
  "type": "Feature",
  "properties": {
    "iso:country":"AU",
    "sg:address":"Cnr Wake Rd & Golf Drv",
    "sg:city":"Cleve",
    "sg:classifiers":[
        {
            "category":"Wholesale",
            "subcategory":"Farm Supplies",
            "type":"Manufacturing & Wholesale Goods"
        }
    ],
    "sg:phone":"+61 8 8628 2278",
    "sg:postcode":"5640",
    "sg:province":"SA",
    "sg:tags":[
        "equipment"
    ],
    "wof:name":"Sherwell Ahrens (S.A.)",
    "wof:placetype":"venue"
},
  "geometry": {"coordinates":[136.47666931099999,-33.7033843994],"type":"Point"}
}