{
  "type": "Feature",
  "properties": {
    "addr:full":"Unit 2 594 Hovell St Albury NSW 2640",
    "addr:housenumber":"594",
    "addr:postcode":"2640",
    "addr:street":"Hovell St",
    "iso:country":"AU",
    "sg:address":"Unit 2 594 Hovell St",
    "sg:city":"Albury",
    "sg:classifiers":[
        {
            "category":"Retail",
            "subcategory":"Laundry & Dry Cleaning",
            "type":"Services"
        }
    ],
    "sg:phone":"+61 2 6021 6811",
    "sg:postcode":"2640",
    "sg:province":"NSW",
    "sg:tags":[
        "machine",
        "commercial",
        "industrial",
        "washing"
    ],
    "wof:name":"Aldonga Electrical Service Pty. Ltd.",
    "wof:placetype":"venue"
},
  "geometry": {"coordinates":[146.909988403,-36.0862045288],"type":"Point"}
}