{
  "type": "Feature",
  "properties": {
    "addr:full":"Lvl 2/ 18 Finchley St Milton QLD 4064",
    "addr:housenumber":"/ 18",
    "addr:postcode":"4064",
    "addr:street":"Finchley St",
    "iso:country":"AU",
    "sg:address":"Lvl 2/ 18 Finchley St",
    "sg:city":"Milton",
    "sg:classifiers":[
        {
            "category":"Health Services",
            "subcategory":"Doctor",
            "type":"Services"
        }
    ],
    "sg:phone":"+61 7 3514 9600",
    "sg:postcode":"4064",
    "sg:province":"QLD",
    "sg:tags":[
        "occupational",
        "safety"
    ],
    "wof:name":"Strive Occupational Rehabilitation",
    "wof:placetype":"venue"
},
  "geometry": {"coordinates":[153.005767822,-27.4654903412],"type":"Point"}
}