{
  "type": "Feature",
  "properties": {
    "addr:full":"Main South Rd Aldinga SA 5173",
    "addr:postcode":"5173",
    "addr:street":"South Rd",
    "iso:country":"AU",
    "sg:address":"Main South Rd",
    "sg:city":"Aldinga",
    "sg:classifiers":[
        {
            "category":"Farming",
            "subcategory":"Vineyard",
            "type":"Manufacturing & Wholesale Goods"
        }
    ],
    "sg:phone":"+61 8 8556 3179",
    "sg:postcode":"5173",
    "sg:province":"SA",
    "sg:tags":[
        "winery"
    ],
    "wof:name":"Aldinga Bay Winery",
    "wof:placetype":"venue"
},
  "geometry": {"coordinates":[138.48440551799999,-35.2686386108],"type":"Point"}
}