{
  "type": "Feature",
  "properties": {
    "addr:full":"2 Regent Ave Springvale VIC 3171",
    "addr:housenumber":"2",
    "addr:postcode":"3171",
    "addr:street":"Regent Ave",
    "iso:country":"AU",
    "sg:address":"2 Regent Ave",
    "sg:city":"Springvale",
    "sg:classifiers":[
        {
            "category":"Building & Trades",
            "subcategory":"Construction",
            "type":"Services"
        }
    ],
    "sg:phone":"+61 1800 447 464",
    "sg:postcode":"3171",
    "sg:province":"VIC",
    "sg:tags":[
        "scaffolding"
    ],
    "wof:name":"Concept Hiring Services Pty Ltd",
    "wof:placetype":"venue"
},
  "geometry": {"coordinates":[145.145141602,-37.943775177],"type":"Point"}
}