{
  "type": "Feature",
  "properties": {
    "iso:country":"AU",
    "sg:address":"13 Wimbie St",
    "sg:city":"Surf Beach",
    "sg:classifiers":[
        {
            "category":"Building & Trades",
            "subcategory":"Pest Control",
            "type":"Services"
        }
    ],
    "sg:phone":"+61 2 4471 1701",
    "sg:postcode":"2536",
    "sg:province":"NSW",
    "wof:name":"Bates Pest Control",
    "wof:placetype":"venue"
},
  "geometry": {"coordinates":[150.21131897000001,-35.761806488],"type":"Point"}
}