{
  "type": "Feature",
  "properties": {
    "addr:full":"2/ 41 William St Kilcoy QLD 4515",
    "addr:housenumber":"/ 41",
    "addr:postcode":"4515",
    "addr:street":"William St",
    "iso:country":"AU",
    "sg:address":"2/ 41 William St",
    "sg:city":"Kilcoy",
    "sg:classifiers":[
        {
            "category":"Retail",
            "subcategory":"Auto Repair",
            "type":"Services"
        }
    ],
    "sg:phone":"+61 7 5422 0020",
    "sg:postcode":"4515",
    "sg:province":"QLD",
    "sg:tags":[
        "beater",
        "painter",
        "panel"
    ],
    "wof:name":"Kilcoy Smash Repairs Pty Ltd",
    "wof:placetype":"venue"
},
  "geometry": {"coordinates":[152.561508,-26.943508],"type":"Point"}
}