{
  "type": "Feature",
  "properties": {
    "iso:country":"AU",
    "sg:address":"11 Lathams Rd",
    "sg:city":"Carrum Downs",
    "sg:classifiers":[
        {
            "category":"Shopping",
            "subcategory":"Mobile Phones",
            "type":"Retail Goods"
        }
    ],
    "sg:phone":"+61 3 9775 1211",
    "sg:postcode":"3201",
    "sg:province":"VIC",
    "sg:tags":[
        "telephone",
        "accessory"
    ],
    "wof:name":"A.W.B. Radio Communications",
    "wof:placetype":"venue"
},
  "geometry": {"coordinates":[145.170715,-38.099297],"type":"Point"}
}