{
  "type": "Feature",
  "properties": {
    "addr:full":"21 Pacific Hwy Ourimbah NSW 2258",
    "addr:housenumber":"21",
    "addr:postcode":"2258",
    "addr:street":"Pacific Hwy",
    "iso:country":"AU",
    "sg:address":"21 Pacific Hwy",
    "sg:city":"Ourimbah",
    "sg:classifiers":[
        {
            "category":"Fast Food",
            "type":"Food & Drink"
        }
    ],
    "sg:phone":"+61 2 4362 1895",
    "sg:postcode":"2258",
    "sg:province":"NSW",
    "sg:tags":[
        "away",
        "take"
    ],
    "wof:name":"Country Fried Chicken",
    "wof:placetype":"venue"
},
  "geometry": {"coordinates":[151.371917725,-33.3429222107],"type":"Point"}
}