{
  "type": "Feature",
  "properties": {
    "iso:country":"AU",
    "sg:address":"142 Princes Hwy",
    "sg:city":"Narre Warren",
    "sg:classifiers":[
        {
            "category":"Building & Trades",
            "subcategory":"Cleaning & Sanitation",
            "type":"Services"
        }
    ],
    "sg:phone":"+61 410 500 326",
    "sg:postcode":"3805",
    "sg:province":"VIC",
    "sg:tags":[
        "cleaner",
        "repairer",
        "roof"
    ],
    "wof:name":"Jay N Jay Pty Ltd",
    "wof:placetype":"venue"
},
  "geometry": {"coordinates":[145.30183400000001,-38.02269],"type":"Point"}
}