{
  "type": "Feature",
  "properties": {
    "addr:full":"PO Box 5099 Hallam VIC 3803",
    "addr:postcode":"3803",
    "iso:country":"AU",
    "sg:address":"PO Box 5099",
    "sg:city":"Hallam",
    "sg:classifiers":[
        {
            "category":"Home & Garden",
            "subcategory":"Furniture",
            "type":"Retail Goods"
        }
    ],
    "sg:phone":"+61 3 9769 9158",
    "sg:postcode":"3803",
    "sg:province":"VIC",
    "sg:tags":[
        "business"
    ],
    "wof:name":"Momentum Office Design",
    "wof:placetype":"venue"
},
  "geometry": {"coordinates":[145.269256592,-38.0042991638],"type":"Point"}
}