{
  "type": "Feature",
  "properties": {
    "addr:full":"282 Princes Hwy Nowra South NSW 2541",
    "addr:housenumber":"282",
    "addr:postcode":"2541",
    "addr:street":"Princes Hwy",
    "iso:country":"AU",
    "sg:address":"282 Princes Hwy",
    "sg:city":"Nowra South",
    "sg:classifiers":[
        {
            "category":"Social Services",
            "subcategory":"Adult Care",
            "type":"Services"
        }
    ],
    "sg:phone":"+61 2 4421 2804",
    "sg:postcode":"2541",
    "sg:province":"NSW",
    "sg:tags":[
        "towing"
    ],
    "wof:name":"D&Y Superfinish Smash Repairs",
    "wof:placetype":"venue"
},
  "geometry": {"coordinates":[150.59446716299999,-34.8419151306],"type":"Point"}
}