{
  "type": "Feature",
  "properties": {
    "addr:full":"13 Radiant Crs Forest Hill VIC 3131",
    "addr:housenumber":"13",
    "addr:postcode":"3131",
    "addr:street":"Radiant Crs",
    "iso:country":"AU",
    "sg:address":"13 Radiant Crs",
    "sg:city":"Forest Hill",
    "sg:classifiers":[
        {
            "category":"Wholesale",
            "subcategory":"Scrap",
            "type":"Manufacturing & Wholesale Goods"
        }
    ],
    "sg:phone":"+61 419 858 128",
    "sg:postcode":"3131",
    "sg:province":"VIC",
    "sg:tags":[
        "merchant",
        "metal"
    ],
    "wof:name":"Scrap Dogs",
    "wof:placetype":"venue"
},
  "geometry": {"coordinates":[145.17112731899999,-37.8427810669],"type":"Point"}
}