{
  "type": "Feature",
  "properties": {
    "iso:country":"AU",
    "sg:address":"Tharwa Drv",
    "sg:city":"Tharwa",
    "sg:classifiers":[
        {
            "category":"Cafe",
            "type":"Food & Drink"
        }
    ],
    "sg:phone":"+61 2 6237 5268",
    "sg:postcode":"2620",
    "sg:province":"ACT",
    "wof:name":"Lanyon Cafe",
    "wof:placetype":"venue"
},
  "geometry": {"coordinates":[149.06767273,-35.5090293884],"type":"Point"}
}