{
  "type": "Feature",
  "properties": {
    "iso:country":"AU",
    "sg:address":"Fairland Hall, 14 Church St",
    "sg:city":"Hunters Hill",
    "sg:classifiers":[
        {
            "category":"Organizations",
            "subcategory":"Membership Organization",
            "type":"Services"
        }
    ],
    "sg:phone":"+61 2 9328 5460",
    "sg:postcode":"2110",
    "sg:province":"NSW",
    "sg:tags":[
        "club",
        "bridge"
    ],
    "wof:name":"Hunters Hill Bridge Club",
    "wof:placetype":"venue"
},
  "geometry": {"coordinates":[151.14712524399999,-33.8343811035],"type":"Point"}
}