{
  "type": "Feature",
  "properties": {
    "addr:full":"PO Box 76 Ringwood East VIC 3135",
    "addr:postcode":"3135",
    "iso:country":"AU",
    "sg:address":"PO Box 76",
    "sg:city":"Ringwood East",
    "sg:classifiers":[
        {
            "category":"Banks & Credit Unions",
            "subcategory":"Financial Services",
            "type":"Services"
        }
    ],
    "sg:phone":"+61 3 9870 6486",
    "sg:postcode":"3135",
    "sg:province":"VIC",
    "sg:tags":[
        "loan",
        "finance",
        "mortgage"
    ],
    "wof:name":"One Loan",
    "wof:placetype":"venue"
},
  "geometry": {"coordinates":[145.24940490700001,-37.8085784912],"type":"Point"}
}