{
  "type": "Feature",
  "properties": {
    "addr:full":"1a Epping Rd (Cnr Centennial Ave) Lane Cove NSW 2066",
    "addr:housenumber":"1a",
    "addr:postcode":"2066",
    "addr:street":"Epping Rd Cnr Centennial Ave",
    "iso:country":"AU",
    "sg:address":"1a Epping Rd (Cnr Centennial Ave)",
    "sg:city":"Lane Cove",
    "sg:classifiers":[
        {
            "category":"Autos & Motor Vehicles",
            "subcategory":"Auto Supplies",
            "type":"Retail Goods"
        }
    ],
    "sg:phone":"+61 2 9418 3000",
    "sg:postcode":"2066",
    "sg:province":"NSW",
    "sg:tags":[
        "part",
        "cycles",
        "accessory"
    ],
    "wof:name":"Sydney City Motorcycles",
    "wof:placetype":"venue"
},
  "geometry": {"coordinates":[151.165725708,-33.8110237122],"type":"Point"}
}