{
  "type": "Feature",
  "properties": {
    "addr:full":"Lvl 4/ 3 Smail St Ultimo NSW 2007",
    "addr:housenumber":"/ 3",
    "addr:postcode":"2007",
    "addr:street":"Smail St",
    "iso:country":"AU",
    "sg:address":"Lvl 4/ 3 Smail St",
    "sg:city":"Ultimo",
    "sg:classifiers":[
        {
            "category":"Shopping",
            "subcategory":"Computers & Home Electronics",
            "type":"Retail Goods"
        }
    ],
    "sg:phone":"+61 2 9281 6392",
    "sg:postcode":"2007",
    "sg:province":"NSW",
    "sg:tags":[
        "small",
        "equipment",
        "business"
    ],
    "wof:name":"Apple Hardware",
    "wof:placetype":"venue"
},
  "geometry": {"coordinates":[151.19566345199999,-33.8829650879],"type":"Point"}
}