{
  "type": "Feature",
  "properties": {
    "iso:country":"AU",
    "sg:address":"\"Lagoon Park\" Bruce Hwy",
    "sg:city":"Wallaville",
    "sg:classifiers":[
        {
            "category":"Landmark",
            "subcategory":"Square",
            "type":"Public Place"
        }
    ],
    "sg:phone":"+61 7 4157 6330",
    "sg:postcode":"4671",
    "sg:province":"QLD",
    "sg:tags":[
        "product",
        "ostrich",
        "farmer"
    ],
    "wof:name":"Australian Ostrich & Emu Co",
    "wof:placetype":"venue"
},
  "geometry": {"coordinates":[151.916824,-24.91538],"type":"Point"}
}