{
  "type": "Feature",
  "properties": {
    "iso:country":"AU",
    "sg:address":"209 Pittwater Rd",
    "sg:city":"Manly",
    "sg:classifiers":[
        {
            "category":"Retail",
            "subcategory":"Auto Repair",
            "type":"Services"
        }
    ],
    "sg:phone":"+61 2 9976 3255",
    "sg:postcode":"2095",
    "sg:province":"NSW",
    "sg:tags":[
        "repairer",
        "motor",
        "engineer"
    ],
    "wof:name":"Autolab Mechanical Workshop",
    "wof:placetype":"venue"
},
  "geometry": {"coordinates":[151.284057617,-33.7873954773],"type":"Point"}
}