{
  "type": "Feature",
  "properties": {
    "iso:country":"AU",
    "sg:address":"1896 Malvern Rd",
    "sg:city":"Malvern East",
    "sg:classifiers":[
        {
            "category":"Home & Garden",
            "subcategory":"Hardware",
            "type":"Retail Goods"
        }
    ],
    "sg:phone":"+61 3 9572 0242",
    "sg:postcode":"3145",
    "sg:province":"VIC",
    "sg:tags":[
        "woodworking",
        "machinery"
    ],
    "wof:name":"AP Workshop",
    "wof:placetype":"venue"
},
  "geometry": {"coordinates":[145.06297302199999,-37.8724479675],"type":"Point"}
}