{
  "type": "Feature",
  "properties": {
    "iso:country":"AU",
    "sg:address":"Rmb 494 Wingham Rd",
    "sg:city":"Taree",
    "sg:classifiers":[
        {
            "category":"Education",
            "subcategory":"School",
            "type":"Public Place"
        }
    ],
    "sg:phone":"+61 2 6552 3177",
    "sg:postcode":"2430",
    "sg:province":"NSW",
    "wof:name":"Taree Christian Community School",
    "wof:placetype":"venue"
},
  "geometry": {"coordinates":[152.42868,-31.878902],"type":"Point"}
}