{
  "type": "Feature",
  "properties": {
    "addr:full":"234 Marius St Tamworth NSW 2340",
    "addr:housenumber":"234",
    "addr:postcode":"2340",
    "addr:street":"Marius St",
    "iso:country":"AU",
    "sg:address":"234 Marius St",
    "sg:city":"Tamworth",
    "sg:classifiers":[
        {
            "category":"Professional",
            "subcategory":"Secretarial Services",
            "type":"Services"
        }
    ],
    "sg:phone":"+61 2 6766 4878",
    "sg:postcode":"2340",
    "sg:province":"NSW",
    "sg:tags":[
        "typing"
    ],
    "wof:name":"Tamworth Office Services",
    "wof:placetype":"venue"
},
  "geometry": {"coordinates":[150.93507385300001,-31.092590332],"type":"Point"}
}