{
  "type": "Feature",
  "properties": {
    "addr:full":"38 Roberna St Moorabbin VIC 3189",
    "addr:housenumber":"38",
    "addr:postcode":"3189",
    "addr:street":"Roberna St",
    "iso:country":"AU",
    "sg:address":"38 Roberna St",
    "sg:city":"Moorabbin",
    "sg:classifiers":[
        {
            "category":"Autos & Motor Vehicles",
            "subcategory":"Auto Supplies",
            "type":"Retail Goods"
        }
    ],
    "sg:phone":"+61 3 9555 0331",
    "sg:postcode":"3189",
    "sg:province":"VIC",
    "sg:tags":[
        "electric"
    ],
    "wof:name":"J Gardner Electric Motor Repairs Pty Ltd",
    "wof:placetype":"venue"
},
  "geometry": {"coordinates":[145.06814575199999,-37.9443130493],"type":"Point"}
}