{
  "type": "Feature",
  "properties": {
    "addr:full":"56 Evergreen Ave Loganlea QLD 4131",
    "addr:housenumber":"56",
    "addr:postcode":"4131",
    "addr:street":"Evergreen Ave",
    "iso:country":"AU",
    "sg:address":"56 Evergreen Ave",
    "sg:city":"Loganlea",
    "sg:classifiers":[
        {
            "category":"Utilities",
            "subcategory":"Electric",
            "type":"Services"
        }
    ],
    "sg:phone":"+61 416 225 771",
    "sg:postcode":"4131",
    "sg:province":"QLD",
    "sg:tags":[
        "electrical",
        "contractor"
    ],
    "wof:name":"Silect Electrical Pty Ltd",
    "wof:placetype":"venue"
},
  "geometry": {"coordinates":[153.128173828,-27.6833705902],"type":"Point"}
}