{
  "type": "Feature",
  "properties": {
    "iso:country":"AU",
    "sg:address":"1 Souter St",
    "sg:city":"Beaconsfield",
    "sg:classifiers":[
        {
            "category":"Travel",
            "subcategory":"Hotels & Motels",
            "type":"Entertainment"
        }
    ],
    "sg:phone":"+61 3 9707 1454",
    "sg:postcode":"3807",
    "sg:province":"VIC",
    "wof:name":"Beaconsfield Lodge Motel",
    "wof:placetype":"venue"
},
  "geometry": {"coordinates":[145.36993408199999,-38.0481948853],"type":"Point"}
}