{
  "type": "Feature",
  "properties": {
    "addr:full":"319- 325 Trafalgar St Petersham NSW 2049",
    "addr:housenumber":"325",
    "addr:postcode":"2049",
    "addr:street":"Trafalgar St",
    "iso:country":"AU",
    "sg:address":"319- 325 Trafalgar St",
    "sg:city":"Petersham",
    "sg:classifiers":[
        {
            "category":"Shopping",
            "subcategory":"Comic Books",
            "type":"Retail Goods"
        }
    ],
    "sg:phone":"+61 2 9550 0990",
    "sg:postcode":"2049",
    "sg:province":"NSW",
    "sg:tags":[
        "wholesaler",
        "mfrs",
        "tape",
        "ribbon"
    ],
    "wof:name":"J T Curry & Co Pty Ltd",
    "wof:placetype":"venue"
},
  "geometry": {"coordinates":[151.153244,-33.894867],"type":"Point"}
}