{
  "type": "Feature",
  "properties": {
    "addr:full":"1267 Pacific Hwy Turramurra NSW 2074",
    "addr:housenumber":"1267",
    "addr:postcode":"2074",
    "addr:street":"Pacific Hwy",
    "iso:country":"AU",
    "sg:address":"1267 Pacific Hwy",
    "sg:city":"Turramurra",
    "sg:classifiers":[
        {
            "category":"Education",
            "subcategory":"Music School",
            "type":"Public Place"
        }
    ],
    "sg:phone":"+61 412 220 990",
    "sg:postcode":"2074",
    "sg:province":"NSW",
    "sg:tags":[
        "choir",
        "bands",
        "orchestra"
    ],
    "wof:name":"The 3B's Show",
    "wof:placetype":"venue"
},
  "geometry": {"coordinates":[151.130203247,-33.7330474854],"type":"Point"}
}