{
  "type": "Feature",
  "properties": {
    "addr:full":"Raven Rd Longreach QLD 4730",
    "addr:postcode":"4730",
    "addr:street":"Raven Rd",
    "iso:country":"AU",
    "sg:address":"Raven Rd",
    "sg:city":"Longreach",
    "sg:classifiers":[
        {
            "category":"Communications",
            "subcategory":"News Services",
            "type":"Services"
        }
    ],
    "sg:phone":"+61 7 4658 2360",
    "sg:postcode":"4730",
    "sg:province":"QLD",
    "sg:tags":[
        "information",
        "tourist",
        "attractions"
    ],
    "wof:name":"Banjos Outback Theatre & Wool Shed",
    "wof:placetype":"venue"
},
  "geometry": {"coordinates":[144.26216099999999,-23.448721],"type":"Point"}
}