{
  "type": "Feature",
  "properties": {
    "iso:country":"AU",
    "sg:address":"191- 201 Ramsgate Rd",
    "sg:city":"Ramsgate",
    "sg:classifiers":[
        {
            "category":"Health Services",
            "subcategory":"Doctor",
            "type":"Services"
        }
    ],
    "sg:phone":"+61 2 9529 2020",
    "sg:postcode":"2217",
    "sg:province":"NSW",
    "sg:tags":[
        "medical",
        "practitioner"
    ],
    "wof:name":"Hampson Sugerman Macquarie Pathology",
    "wof:placetype":"venue"
},
  "geometry": {"coordinates":[151.14381399999999,-33.985722],"type":"Point"}
}