{
  "type": "Feature",
  "properties": {
    "addr:full":"Shop 16 Karratha City Shpng Cntr Karratha WA 6714",
    "addr:housenumber":"shop 16",
    "addr:postcode":"6714",
    "addr:street":"Karratha City Shpng Cntr",
    "iso:country":"AU",
    "sg:address":"Shop 16 Karratha City Shpng Cntr",
    "sg:city":"Karratha",
    "sg:classifiers":[
        {
            "category":"Shopping",
            "subcategory":"Clothing, Apparel, & Fashions",
            "type":"Retail Goods"
        }
    ],
    "sg:phone":"+61 8 9185 2712",
    "sg:postcode":"6714",
    "sg:province":"WA",
    "sg:tags":[
        "jean"
    ],
    "wof:name":"JeansWest",
    "wof:placetype":"venue"
},
  "geometry": {"coordinates":[116.84902954099999,-20.7548427582],"type":"Point"}
}