{
  "type": "Feature",
  "properties": {
    "addr:full":"122 Parry St Newcastle NSW 2300",
    "addr:housenumber":"122",
    "addr:postcode":"2300",
    "addr:street":"Parry St",
    "iso:country":"AU",
    "sg:address":"122 Parry St",
    "sg:city":"Newcastle",
    "sg:classifiers":[
        {
            "category":"Social Services",
            "subcategory":"Retirement Home",
            "type":"Services"
        }
    ],
    "sg:phone":"+61 2 9988 4422",
    "sg:postcode":"2300",
    "sg:province":"NSW",
    "sg:tags":[
        "environmental",
        "consultant",
        "pollution"
    ],
    "wof:name":"HLA-Envirosciences Pty Ltd",
    "wof:placetype":"venue"
},
  "geometry": {"coordinates":[151.763474,-32.930153],"type":"Point"}
}