{
  "type": "Feature",
  "properties": {
    "addr:full":"2057- 2059 Frankston-Flinders Rd Hastings VIC 3915",
    "addr:housenumber":"2057 2059",
    "addr:postcode":"3915",
    "addr:street":"Frankston-Flinders Rd",
    "iso:country":"AU",
    "sg:address":"2057- 2059 Frankston-Flinders Rd",
    "sg:city":"Hastings",
    "sg:classifiers":[
        {
            "category":"Autos & Motor Vehicles",
            "subcategory":"Auto Supplies",
            "type":"Retail Goods"
        }
    ],
    "sg:phone":"+61 3 5979 1400",
    "sg:postcode":"3915",
    "sg:province":"VIC",
    "sg:tags":[
        "tyre"
    ],
    "wof:name":"Bridgestone Tyre And Automotive Centre",
    "wof:placetype":"venue"
},
  "geometry": {"coordinates":[145.18380737300001,-38.3045196533],"type":"Point"}
}