{
  "type": "Feature",
  "properties": {
    "addr:full":"1 Amelia Pl East North Narrabeen NSW 2101",
    "addr:housenumber":"1",
    "addr:postcode":"2101",
    "addr:street":"Amelia Pl East",
    "iso:country":"AU",
    "sg:address":"1 Amelia Pl East",
    "sg:city":"North Narrabeen",
    "sg:classifiers":[
        {
            "category":"Professional",
            "subcategory":"Art Services",
            "type":"Services"
        }
    ],
    "sg:phone":"+61 2 9944 6884",
    "sg:postcode":"2101",
    "sg:province":"NSW",
    "sg:tags":[
        "interior",
        "decorator"
    ],
    "wof:name":"Northern Beaches Interior Design",
    "wof:placetype":"venue"
},
  "geometry": {"coordinates":[151.28793300000001,-33.699169],"type":"Point"}
}