{
  "type": "Feature",
  "properties": {
    "addr:full":"307 Burnley Centre Rd Clayton VIC 3168",
    "addr:housenumber":"307",
    "addr:postcode":"3168",
    "addr:street":"Burnley Centre Rd",
    "iso:country":"AU",
    "sg:address":"307 Burnley Centre Rd",
    "sg:city":"Clayton",
    "sg:classifiers":[
        {
            "category":"Health Services",
            "subcategory":"Chiropractor",
            "type":"Services"
        }
    ],
    "sg:phone":"+61 3 9544 9734",
    "sg:postcode":"3168",
    "sg:province":"VIC",
    "wof:name":"Burnley St Chiropractic Clinic",
    "wof:placetype":"venue"
},
  "geometry": {"coordinates":[145.11839294399999,-37.9284362793],"type":"Point"}
}