{
  "type": "Feature",
  "properties": {
    "addr:full":"U19/ 4 Chaplin Drv Lane Cove NSW 2066",
    "addr:housenumber":"4",
    "addr:postcode":"2066",
    "addr:street":"/;Chaplin Drv",
    "iso:country":"AU",
    "sg:address":"U19/ 4 Chaplin Drv",
    "sg:city":"Lane Cove",
    "sg:classifiers":[
        {
            "category":"Parking",
            "subcategory":"Garage",
            "type":"Transportation"
        }
    ],
    "sg:phone":"+61 2 9420 1620",
    "sg:postcode":"2066",
    "sg:province":"NSW",
    "sg:tags":[
        "radiographer"
    ],
    "wof:name":"Sectra Pty Ltd",
    "wof:placetype":"venue"
},
  "geometry": {"coordinates":[151.147872925,-33.8101348877],"type":"Point"}
}