{
  "type": "Feature",
  "properties": {
    "addr:full":"1003 Botany Rd Mascot NSW 2020",
    "addr:housenumber":"1003",
    "addr:postcode":"2020",
    "addr:street":"Botany Rd",
    "iso:country":"AU",
    "sg:address":"1003 Botany Rd",
    "sg:city":"Mascot",
    "sg:classifiers":[
        {
            "category":"Shopping",
            "subcategory":"Mobile Phones",
            "type":"Retail Goods"
        }
    ],
    "sg:phone":"+61 414 235 252",
    "sg:postcode":"2020",
    "sg:province":"NSW",
    "sg:tags":[
        "telephone",
        "accessory"
    ],
    "wof:name":"Auto Safe and Sound",
    "wof:placetype":"venue"
},
  "geometry": {"coordinates":[151.19566345199999,-33.9253616333],"type":"Point"}
}