{
  "type": "Feature",
  "properties": {
    "addr:full":"4 Marsterson St Mutchilba QLD 4872",
    "addr:housenumber":"4",
    "addr:postcode":"4872",
    "addr:street":"Marsterson St",
    "iso:country":"AU",
    "sg:address":"4 Marsterson St",
    "sg:city":"Mutchilba",
    "sg:classifiers":[
        {
            "category":"Commercial Area",
            "type":"Public Place"
        }
    ],
    "sg:phone":"+61 429 931 208",
    "sg:postcode":"4872",
    "sg:province":"QLD",
    "sg:tags":[
        "heavy",
        "carrier"
    ],
    "wof:name":"Davis Transport Pty Ltd",
    "wof:placetype":"venue"
},
  "geometry": {"coordinates":[145.209228516,-17.1386871338],"type":"Point"}
}