{
  "type": "Feature",
  "properties": {
    "addr:full":"115 Plenty Rd Preston VIC 3072",
    "addr:housenumber":"115",
    "addr:postcode":"3072",
    "addr:street":"Plenty Rd",
    "iso:country":"AU",
    "sg:address":"115 Plenty Rd",
    "sg:city":"Preston",
    "sg:classifiers":[
        {
            "category":"Home & Garden",
            "subcategory":"Furniture",
            "type":"Retail Goods"
        }
    ],
    "sg:phone":"+61 3 9416 9135",
    "sg:postcode":"3072",
    "sg:province":"VIC",
    "sg:tags":[
        "business"
    ],
    "wof:name":"Exact Business Furniture & Shelving P/L",
    "wof:placetype":"venue"
},
  "geometry": {"coordinates":[145.061157227,-37.6933784485],"type":"Point"}
}