{
  "type": "Feature",
  "properties": {
    "addr:full":"70 Alleyne Ave North Narrabeen NSW 2101",
    "addr:housenumber":"70",
    "addr:postcode":"2101",
    "addr:street":"Alleyne Ave",
    "iso:country":"AU",
    "sg:address":"70 Alleyne Ave",
    "sg:city":"North Narrabeen",
    "sg:classifiers":[
        {
            "category":"Real Estate",
            "subcategory":"Architect",
            "type":"Services"
        }
    ],
    "sg:phone":"+61 2 9913 9208",
    "sg:postcode":"2101",
    "sg:province":"NSW",
    "wof:name":"Ross D D G",
    "wof:placetype":"venue"
},
  "geometry": {"coordinates":[151.29505900000001,-33.704731],"type":"Point"}
}