{
  "type": "Feature",
  "properties": {
    "iso:country":"AU",
    "sg:address":"6 Railway Pde",
    "sg:city":"Kurri Kurri",
    "sg:classifiers":[
        {
            "category":"Banks & Credit Unions",
            "subcategory":"Financial Services",
            "type":"Services"
        }
    ],
    "sg:phone":"+61 2 4936 4266",
    "sg:postcode":"2327",
    "sg:province":"NSW",
    "sg:tags":[
        "equipment",
        "chain"
    ],
    "wof:name":"J & J Chain & Pulley Drives Pty",
    "wof:placetype":"venue"
},
  "geometry": {"coordinates":[151.47517395,-32.8092460632],"type":"Point"}
}