{
  "type": "Feature",
  "properties": {
    "addr:full":"Shop 4B Cnr Dundas & Wittenoom Rds High Wycombe WA 6057",
    "addr:housenumber":"shop 4b cnr",
    "addr:postcode":"6057",
    "iso:country":"AU",
    "sg:address":"Shop 4B Cnr Dundas & Wittenoom Rds",
    "sg:city":"High Wycombe",
    "sg:classifiers":[
        {
            "category":"Personal",
            "subcategory":"Beauty Salon",
            "type":"Services"
        }
    ],
    "sg:phone":"+61 8 9454 9664",
    "sg:postcode":"6057",
    "sg:province":"WA",
    "sg:tags":[
        "hairdresser"
    ],
    "wof:name":"Flaunt It Hair Design",
    "wof:placetype":"venue"
},
  "geometry": {"coordinates":[115.991523743,-31.9393768311],"type":"Point"}
}