{
  "type": "Feature",
  "properties": {
    "iso:country":"AU",
    "sg:address":"PO Box 145",
    "sg:city":"Bairnsdale",
    "sg:classifiers":[
        {
            "category":"Professional",
            "subcategory":"Art Services",
            "type":"Services"
        }
    ],
    "sg:phone":"+61 412 516 500",
    "sg:postcode":"3875",
    "sg:province":"VIC",
    "sg:tags":[
        "decorator",
        "painter"
    ],
    "wof:name":"Shepherd Robert",
    "wof:placetype":"venue"
},
  "geometry": {"coordinates":[147.61129760700001,-37.8314208984],"type":"Point"}
}