{
  "type": "Feature",
  "properties": {
    "iso:country":"AU",
    "sg:address":"953 Forest Rd",
    "sg:city":"Lugarno",
    "sg:classifiers":[
        {
            "category":"Building & Trades",
            "subcategory":"Construction",
            "type":"Services"
        }
    ],
    "sg:phone":"+61 412 964 795",
    "sg:postcode":"2210",
    "sg:province":"NSW",
    "sg:tags":[
        "waterproofing",
        "contractor"
    ],
    "wof:name":"The Ultimate Connection",
    "wof:placetype":"venue"
},
  "geometry": {"coordinates":[151.046387,-33.979385],"type":"Point"}
}