{
  "type": "Feature",
  "properties": {
    "iso:country":"AU",
    "sg:address":"Sturt Hwy",
    "sg:city":"Waikerie",
    "sg:classifiers":[
        {
            "category":"Professional",
            "subcategory":"Detective & Security Services",
            "type":"Services"
        }
    ],
    "sg:phone":"+61 418 893 100",
    "sg:postcode":"5330",
    "sg:province":"SA",
    "sg:tags":[
        "consultant",
        "system"
    ],
    "wof:name":"Lowbank Electrical",
    "wof:placetype":"venue"
},
  "geometry": {"coordinates":[140.00225830100001,-34.1883811951],"type":"Point"}
}