{
  "type": "Feature",
  "properties": {
    "addr:full":"Unit 2, 1236 Grand Junction Rd Hope Valley SA 5090",
    "addr:housenumber":"1236",
    "addr:postcode":"5090",
    "addr:street":"Grand Junction Rd",
    "iso:country":"AU",
    "sg:address":"Unit 2, 1236 Grand Junction Rd",
    "sg:city":"Hope Valley",
    "sg:classifiers":[
        {
            "category":"Social Services",
            "subcategory":"Child Care",
            "type":"Services"
        }
    ],
    "sg:phone":"+61 8 8395 3466",
    "sg:postcode":"5090",
    "sg:province":"SA",
    "sg:tags":[
        "fleet",
        "management"
    ],
    "wof:name":"Vehtec Pty Ltd",
    "wof:placetype":"venue"
},
  "geometry": {"coordinates":[138.70335388199999,-34.8432846069],"type":"Point"}
}