{
  "type": "Feature",
  "properties": {
    "iso:country":"AU",
    "sg:address":"GPO Box 2692",
    "sg:city":"Brisbane",
    "sg:classifiers":[
        {
            "category":"Banks & Credit Unions",
            "subcategory":"Financial Services",
            "type":"Services"
        }
    ],
    "sg:phone":"+61 405 018 480",
    "sg:postcode":"4001",
    "sg:province":"QLD",
    "sg:tags":[
        "financier"
    ],
    "wof:name":"Venture Capital Specialists Pty Ltd",
    "wof:placetype":"venue"
},
  "geometry": {"coordinates":[152.88862609899999,-27.5975971222],"type":"Point"}
}