{
  "type": "Feature",
  "properties": {
    "addr:full":"173a Huntriss Rd Doubleview WA 6018",
    "addr:housenumber":"173a",
    "addr:postcode":"6018",
    "addr:street":"Huntriss Rd",
    "iso:country":"AU",
    "sg:address":"173a Huntriss Rd",
    "sg:city":"Doubleview",
    "sg:classifiers":[
        {
            "category":"Banks & Credit Unions",
            "subcategory":"Investment Brokerage",
            "type":"Services"
        }
    ],
    "sg:phone":"+61 8 9244 1079",
    "sg:postcode":"6018",
    "sg:province":"WA",
    "wof:name":"AR Mashado Investment",
    "wof:placetype":"venue"
},
  "geometry": {"coordinates":[115.786972046,-31.8896560669],"type":"Point"}
}