{
  "type": "Feature",
  "properties": {
    "addr:full":"5 Orchard St Toowong QLD 4066",
    "addr:housenumber":"5",
    "addr:postcode":"4066",
    "addr:street":"Orchard St",
    "iso:country":"AU",
    "sg:address":"5 Orchard St",
    "sg:city":"Toowong",
    "sg:classifiers":[
        {
            "category":"Professional",
            "subcategory":"Art Services",
            "type":"Services"
        }
    ],
    "sg:phone":"+61 7 3870 3365",
    "sg:postcode":"4066",
    "sg:province":"QLD",
    "sg:tags":[
        "artist"
    ],
    "wof:name":"Artman",
    "wof:placetype":"venue"
},
  "geometry": {"coordinates":[152.979705811,-27.4847583771],"type":"Point"}
}