{
  "type": "Feature",
  "properties": {
    "addr:full":"St Judes Rd Ballandean QLD 4382",
    "addr:postcode":"4382",
    "addr:street":"St Judes Rd",
    "iso:country":"AU",
    "sg:address":"St Judes Rd",
    "sg:city":"Ballandean",
    "sg:classifiers":[
        {
            "category":"Farming",
            "subcategory":"Berry Farm",
            "type":"Manufacturing & Wholesale Goods"
        }
    ],
    "sg:phone":"+61 7 4684 1118",
    "sg:postcode":"4382",
    "sg:province":"QLD",
    "sg:tags":[
        "fruit",
        "grower"
    ],
    "wof:name":"Taylor A E",
    "wof:placetype":"venue"
},
  "geometry": {"coordinates":[151.842163,-28.797543],"type":"Point"}
}