{
  "type": "Feature",
  "properties": {
    "addr:full":"Litchfield Park Rd Batchelor NT 0845",
    "addr:postcode":"nt 0845",
    "addr:street":"Litchfield Park Rd",
    "iso:country":"AU",
    "sg:address":"Litchfield Park Rd",
    "sg:city":"Batchelor",
    "sg:classifiers":[
        {
            "category":"Communications",
            "subcategory":"News Services",
            "type":"Services"
        }
    ],
    "sg:phone":"+61 8 8978 2185",
    "sg:postcode":"0845",
    "sg:province":"NT",
    "sg:tags":[
        "information",
        "tourist",
        "attractions"
    ],
    "wof:name":"Wangi Tourist Park",
    "wof:placetype":"venue"
},
  "geometry": {"coordinates":[130.99101257300001,-13.0225410461],"type":"Point"}
}