{
  "type": "Feature",
  "properties": {
    "iso:country":"AU",
    "sg:address":"2-4 Great North Rd",
    "sg:city":"(Cnr Pacific Hwy) Frederickton",
    "sg:classifiers":[
        {
            "category":"Autos & Motor Vehicles",
            "subcategory":"Auto Supplies",
            "type":"Retail Goods"
        }
    ],
    "sg:phone":"+61 2 6566 8801",
    "sg:postcode":"2440",
    "sg:province":"NSW",
    "sg:tags":[
        "part",
        "cycles",
        "accessory"
    ],
    "wof:name":"MacLeay Motorcycles",
    "wof:placetype":"venue"
},
  "geometry": {"coordinates":[152.879654,-31.034735],"type":"Point"}
}