{
  "type": "Feature",
  "properties": {
    "addr:full":"2-4 Great North Rd (Cnr Pacific Hwy) Frederickton NSW 2440",
    "addr:housenumber":"2-4",
    "addr:postcode":"2440",
    "addr:street":"Great North Rd Cnr Pacific Hwy",
    "iso:country":"AU",
    "sg:address":"2-4 Great North Rd",
    "sg:city":"(Cnr Pacific Hwy) Frederickton",
    "sg:classifiers":[
        {
            "category":"Autos & Motor Vehicles",
            "subcategory":"Auto Supplies",
            "type":"Retail Goods"
        }
    ],
    "sg:phone":"+61 2 6566 8801",
    "sg:postcode":"2440",
    "sg:province":"NSW",
    "sg:tags":[
        "part",
        "cycles",
        "accessory"
    ],
    "wof:name":"MacLeay Motorcycles",
    "wof:placetype":"venue"
},
  "geometry": {"coordinates":[152.87965399999999,-31.034735],"type":"Point"}
}