{
  "type": "Feature",
  "properties": {
    "addr:full":"880 Pacific Hwy Gordon NSW 2072",
    "addr:housenumber":"880",
    "addr:postcode":"2072",
    "addr:street":"Pacific Hwy",
    "iso:country":"AU",
    "sg:address":"880 Pacific Hwy",
    "sg:city":"Gordon",
    "sg:classifiers":[
        {
            "category":"Retail",
            "subcategory":"Car Wash",
            "type":"Services"
        }
    ],
    "sg:phone":"+61 2 9499 9523",
    "sg:postcode":"2072",
    "sg:province":"NSW",
    "sg:tags":[
        "truck",
        "cleaning"
    ],
    "wof:name":"Clear View Hand Car Wash & Cafe",
    "wof:placetype":"venue"
},
  "geometry": {"coordinates":[151.148803711,-33.7521934509],"type":"Point"}
}