{
  "type": "Feature",
  "properties": {
    "iso:country":"AU",
    "sg:address":"K Mart Plaza",
    "sg:city":"Toowoomba",
    "sg:classifiers":[
        {
            "category":"Shopping",
            "type":"Retail Goods"
        }
    ],
    "sg:phone":"+61 7 4635 7319",
    "sg:postcode":"4350",
    "sg:province":"QLD",
    "sg:tags":[
        "repair",
        "travel"
    ],
    "wof:name":"Colorado Bag Co",
    "wof:placetype":"venue"
},
  "geometry": {"coordinates":[151.951904,-27.569506],"type":"Point"}
}