{
  "type": "Feature",
  "properties": {
    "addr:full":"50 James Rd Middle Swan WA 6056",
    "addr:housenumber":"50",
    "addr:postcode":"6056",
    "addr:street":"James Rd",
    "iso:country":"AU",
    "sg:address":"50 James Rd",
    "sg:city":"Middle Swan",
    "sg:classifiers":[
        {
            "category":"Professional",
            "subcategory":"Art Services",
            "type":"Services"
        }
    ],
    "sg:phone":"+61 8 9274 3996",
    "sg:postcode":"6056",
    "sg:province":"WA",
    "sg:tags":[
        "sculptor"
    ],
    "wof:name":"Gomboc Gallery Sculpture Park",
    "wof:placetype":"venue"
},
  "geometry": {"coordinates":[116.026641846,-31.8624668121],"type":"Point"}
}