{
  "type": "Feature",
  "properties": {
    "iso:country":"AU",
    "sg:address":"Grahams Bridge Rd",
    "sg:city":"Horsham",
    "sg:classifiers":[
        {
            "category":"Commercial Area",
            "type":"Public Place"
        }
    ],
    "sg:phone":"+61 3 5382 1874",
    "sg:postcode":"3400",
    "sg:province":"VIC",
    "sg:tags":[
        "heavy",
        "carrier"
    ],
    "wof:name":"Simpson Transport",
    "wof:placetype":"venue"
},
  "geometry": {"coordinates":[142.21241760300001,-36.7424545288],"type":"Point"}
}