{
  "type": "Feature",
  "properties": {
    "addr:full":"206 Glengala Rd Sunshine West VIC 3020",
    "addr:housenumber":"206",
    "addr:postcode":"3020",
    "addr:street":"Glengala Rd",
    "iso:country":"AU",
    "sg:address":"206 Glengala Rd",
    "sg:city":"Sunshine West",
    "sg:classifiers":[
        {
            "category":"Sports & Exercise",
            "subcategory":"Sports Center",
            "type":"Entertainment"
        }
    ],
    "sg:phone":"+61 3 9363 5230",
    "sg:postcode":"3020",
    "sg:province":"VIC",
    "sg:tags":[
        "ground"
    ],
    "wof:name":"Greek Cypriot Parent & Youth Club Western Suburbs of Melbourne INC",
    "wof:placetype":"venue"
},
  "geometry": {"coordinates":[144.80387899999999,-37.787579],"type":"Point"}
}