{
  "type": "Feature",
  "properties": {
    "addr:full":"9 Primrose St Wingham NSW 2429",
    "addr:housenumber":"9",
    "addr:postcode":"2429",
    "addr:street":"Primrose St",
    "iso:country":"AU",
    "sg:address":"9 Primrose St",
    "sg:city":"Wingham",
    "sg:classifiers":[
        {
            "category":"Health Services",
            "subcategory":"Doctor",
            "type":"Services"
        }
    ],
    "sg:phone":"+61 2 6553 4811",
    "sg:postcode":"2429",
    "sg:province":"NSW",
    "sg:tags":[
        "medical",
        "practitioner"
    ],
    "wof:name":"Brooks Amanda Dr",
    "wof:placetype":"venue"
},
  "geometry": {"coordinates":[152.371735,-31.87001],"type":"Point"}
}