{
  "type": "Feature",
  "properties": {
    "addr:full":"39 Short St Rocklea QLD 4106",
    "addr:housenumber":"39",
    "addr:postcode":"4106",
    "addr:street":"Short St",
    "iso:country":"AU",
    "sg:address":"39 Short St",
    "sg:city":"Rocklea",
    "sg:classifiers":[
        {
            "category":"Fast Food",
            "type":"Food & Drink"
        }
    ],
    "sg:phone":"+61 7 3216 7353",
    "sg:postcode":"4106",
    "sg:province":"QLD",
    "sg:tags":[
        "away",
        "take"
    ],
    "wof:name":"McDonald's Family Restaurants",
    "wof:placetype":"venue"
},
  "geometry": {"coordinates":[153.01771545400001,-27.5578784943],"type":"Point"}
}