{
  "type": "Feature",
  "properties": {
    "iso:country":"AU",
    "sg:address":"13 Curraghmore Ave",
    "sg:city":"Burnie",
    "sg:classifiers":[
        {
            "category":"Professional",
            "subcategory":"Art Services",
            "type":"Services"
        }
    ],
    "sg:phone":"+61 3 6431 4228",
    "sg:postcode":"7320",
    "sg:province":"TAS",
    "sg:tags":[
        "decorator",
        "painter"
    ],
    "wof:name":"Greg Archer & Tony White Painters & Decorators",
    "wof:placetype":"venue"
},
  "geometry": {"coordinates":[145.885757,-41.056885],"type":"Point"}
}