{
  "type": "Feature",
  "properties": {
    "addr:full":"102a Main St Yankalilla SA 5203",
    "addr:housenumber":"102a",
    "addr:postcode":"5203",
    "addr:street":"Main St",
    "iso:country":"AU",
    "sg:address":"102a Main St",
    "sg:city":"Yankalilla",
    "sg:classifiers":[
        {
            "category":"Food & Beverages",
            "subcategory":"Bakery",
            "type":"Retail Goods"
        }
    ],
    "sg:phone":"+61 8 8558 3413",
    "sg:postcode":"5203",
    "sg:province":"SA",
    "sg:tags":[
        "baker"
    ],
    "wof:name":"Yankalilla Bakery",
    "wof:placetype":"venue"
},
  "geometry": {"coordinates":[138.35040283199999,-35.457775116],"type":"Point"}
}