{
  "type": "Feature",
  "properties": {
    "addr:full":"U4/ 900 South Rd Edwardstown SA 5039",
    "addr:housenumber":"900",
    "addr:postcode":"5039",
    "addr:street":"U4 /;South Rd",
    "iso:country":"AU",
    "sg:address":"U4/ 900 South Rd",
    "sg:city":"Edwardstown",
    "sg:classifiers":[
        {
            "category":"Retail",
            "subcategory":"Event Space",
            "type":"Services"
        }
    ],
    "sg:phone":"+61 8 8371 0505",
    "sg:postcode":"5039",
    "sg:province":"SA",
    "sg:tags":[
        "venue",
        "reception",
        "wedding"
    ],
    "wof:name":"No Fuss Catering Co",
    "wof:placetype":"venue"
},
  "geometry": {"coordinates":[138.573287964,-34.9744758606],"type":"Point"}
}