{
  "type": "Feature",
  "properties": {
    "addr:full":"3 Ethell Rd Kirrawee NSW 2232",
    "addr:housenumber":"3",
    "addr:postcode":"2232",
    "addr:street":"Ethell Rd",
    "iso:country":"AU",
    "sg:address":"3 Ethell Rd",
    "sg:city":"Kirrawee",
    "sg:classifiers":[
        {
            "category":"Building & Trades",
            "subcategory":"Construction",
            "type":"Services"
        }
    ],
    "sg:phone":"+61 2 9545 1433",
    "sg:postcode":"2232",
    "sg:province":"NSW",
    "sg:tags":[
        "contractor"
    ],
    "wof:name":"McIntosh Constructions Pty Ltd",
    "wof:placetype":"venue"
},
  "geometry": {"coordinates":[151.08116149899999,-34.0243110657],"type":"Point"}
}