{
  "type": "Feature",
  "properties": {
    "iso:country":"AU",
    "sg:address":"PO Box 262",
    "sg:city":"Moorebank Private Bxs",
    "sg:classifiers":[
        {
            "category":"Professional",
            "type":"Services"
        }
    ],
    "sg:phone":"+61 417 018 528",
    "sg:postcode":"1875",
    "sg:province":"NSW",
    "sg:tags":[
        "transport"
    ],
    "wof:name":"C L & V C Transport",
    "wof:placetype":"venue"
},
  "geometry": {"coordinates":[150.92904663100001,-33.9323272705],"type":"Point"}
}