{
  "type": "Feature",
  "properties": {
    "addr:full":"48 Alfred St Maffra VIC 3860",
    "addr:housenumber":"48",
    "addr:postcode":"3860",
    "addr:street":"Alfred St",
    "iso:country":"AU",
    "sg:address":"48 Alfred St",
    "sg:city":"Maffra",
    "sg:classifiers":[
        {
            "category":"Personal",
            "subcategory":"Beauty Salon",
            "type":"Services"
        }
    ],
    "sg:phone":"+61 3 5141 1207",
    "sg:postcode":"3860",
    "sg:province":"VIC",
    "sg:tags":[
        "hairdresser"
    ],
    "wof:name":"Enjaneer Of Hair",
    "wof:placetype":"venue"
},
  "geometry": {"coordinates":[146.98472595199999,-37.9608688354],"type":"Point"}
}