{
  "type": "Feature",
  "properties": {
    "addr:full":"45 Raglan St Port Melbourne VIC 3207",
    "addr:housenumber":"45",
    "addr:postcode":"3207",
    "addr:street":"Raglan St",
    "iso:country":"AU",
    "sg:address":"45 Raglan St",
    "sg:city":"Port Melbourne",
    "sg:classifiers":[
        {
            "category":"Professional",
            "subcategory":"Business Services",
            "type":"Services"
        }
    ],
    "sg:phone":"+61 3 9646 4168",
    "sg:postcode":"3207",
    "sg:province":"VIC",
    "sg:tags":[
        "consultant",
        "promoter",
        "entertainment"
    ],
    "wof:name":"Hummingbird Productions",
    "wof:placetype":"venue"
},
  "geometry": {"coordinates":[144.94714400000001,-37.835381],"type":"Point"}
}