{
  "type": "Feature",
  "properties": {
    "addr:full":"Stawall Rd Ararat VIC 3377",
    "addr:postcode":"3377",
    "addr:street":"Stawall Rd",
    "iso:country":"AU",
    "sg:address":"Stawall Rd",
    "sg:city":"Ararat",
    "sg:classifiers":[
        {
            "category":"Autos & Motor Vehicles",
            "subcategory":"Fuel & Gas Station",
            "type":"Retail Goods"
        }
    ],
    "sg:phone":"+61 3 5352 4199",
    "sg:postcode":"3377",
    "sg:province":"VIC",
    "wof:name":"BP Australia Limited",
    "wof:placetype":"venue"
},
  "geometry": {"coordinates":[142.93130493199999,-37.2824211121],"type":"Point"}
}