{
  "type": "Feature",
  "properties": {
    "addr:full":"198 Anzac Ave Kippa-Ring QLD 4021",
    "addr:housenumber":"198",
    "addr:postcode":"4021",
    "addr:street":"Anzac Ave",
    "iso:country":"AU",
    "sg:address":"198 Anzac Ave",
    "sg:city":"Kippa-Ring",
    "sg:classifiers":[
        {
            "category":"Autos & Motor Vehicles",
            "subcategory":"Auto Supplies",
            "type":"Retail Goods"
        }
    ],
    "sg:phone":"+61 7 3283 1233",
    "sg:postcode":"4021",
    "sg:province":"QLD",
    "sg:tags":[
        "paint",
        "automotive"
    ],
    "wof:name":"3D Kippa Ring Paint & Hardware",
    "wof:placetype":"venue"
},
  "geometry": {"coordinates":[153.08660900000001,-27.226835],"type":"Point"}
}