{
  "type": "Feature",
  "properties": {
    "addr:full":"Gus Winckel Rd Broome WA 6725",
    "addr:postcode":"6725",
    "addr:street":"Winckel Rd",
    "iso:country":"AU",
    "sg:address":"Gus Winckel Rd",
    "sg:city":"Broome",
    "sg:classifiers":[
        {
            "category":"Manufacturing",
            "subcategory":"Aerospace",
            "type":"Manufacturing & Wholesale Goods"
        }
    ],
    "sg:phone":"+61 8 9192 8064",
    "sg:postcode":"6725",
    "sg:province":"WA",
    "sg:tags":[
        "equipment",
        "aircraft",
        "maintenance"
    ],
    "wof:name":"Cable Beach Air Maintenance",
    "wof:placetype":"venue"
},
  "geometry": {"coordinates":[122.233322144,-17.9476737976],"type":"Point"}
}