{
  "type": "Feature",
  "properties": {
    "addr:full":"1025 Pinnacles St South Hedland WA 6722",
    "addr:housenumber":"1025",
    "addr:postcode":"6722",
    "addr:street":"Pinnacles St South",
    "iso:country":"AU",
    "sg:address":"1025 Pinnacles St",
    "sg:city":"South Hedland",
    "sg:classifiers":[
        {
            "category":"Autos & Motor Vehicles",
            "subcategory":"Auto Supplies",
            "type":"Retail Goods"
        }
    ],
    "sg:phone":"+61 8 9172 3055",
    "sg:postcode":"6722",
    "sg:province":"WA",
    "sg:tags":[
        "tyre"
    ],
    "wof:name":"Boral Tyres Pty Ltd",
    "wof:placetype":"venue"
},
  "geometry": {"coordinates":[118.592330933,-20.3749542236],"type":"Point"}
}