{
  "type": "Feature",
  "properties": {
    "addr:full":"Shop 5/ 114 Wagonga St Narooma NSW 2546",
    "addr:housenumber":"shop 5 / 114",
    "addr:postcode":"2546",
    "addr:street":"Wagonga St",
    "iso:country":"AU",
    "sg:address":"Shop 5/ 114 Wagonga St",
    "sg:city":"Narooma",
    "sg:classifiers":[
        {
            "category":"Health Services",
            "subcategory":"Health Practitioner",
            "type":"Services"
        }
    ],
    "sg:phone":"+61 2 4476 1866",
    "sg:postcode":"2546",
    "sg:province":"NSW",
    "sg:tags":[
        "physiotherapist"
    ],
    "wof:name":"Narooma Physiotherapy Centre",
    "wof:placetype":"venue"
},
  "geometry": {"coordinates":[150.13203430199999,-36.2180633545],"type":"Point"}
}