{
  "type": "Feature",
  "properties": {
    "addr:full":"60 Ross Pl Wakerley QLD 4154",
    "addr:housenumber":"60",
    "addr:postcode":"4154",
    "addr:street":"Ross Pl",
    "iso:country":"AU",
    "sg:address":"60 Ross Pl",
    "sg:city":"Wakerley",
    "sg:classifiers":[
        {
            "category":"Real Estate",
            "subcategory":"Real Estate Agent",
            "type":"Services"
        }
    ],
    "sg:phone":"+61 7 3890 4392",
    "sg:postcode":"4154",
    "sg:province":"QLD",
    "sg:tags":[
        "export"
    ],
    "wof:name":"Universal Suppliers Pty Ltd",
    "wof:placetype":"venue"
},
  "geometry": {"coordinates":[153.15145874000001,-27.4886608124],"type":"Point"}
}