{
  "type": "Feature",
  "properties": {
    "addr:full":"51/ 40 Riverview Pde Surfers Paradise QLD 4217",
    "addr:housenumber":"51 / 40",
    "addr:postcode":"4217",
    "addr:street":"Riverview Pde",
    "iso:country":"AU",
    "sg:address":"51/ 40 Riverview Pde",
    "sg:city":"Surfers Paradise",
    "sg:classifiers":[
        {
            "category":"Real Estate",
            "subcategory":"Developer",
            "type":"Services"
        }
    ],
    "sg:phone":"+61 7 5538 9036",
    "sg:postcode":"4217",
    "sg:province":"QLD",
    "sg:tags":[
        "development"
    ],
    "wof:name":"Sunseeker Property Development Pty Ltd",
    "wof:placetype":"venue"
},
  "geometry": {"coordinates":[153.425704956,-27.9967327118],"type":"Point"}
}