{
  "type": "Feature",
  "properties": {
    "addr:full":"Church Rd Hazelwood North VIC 3840",
    "addr:postcode":"3840",
    "addr:street":"Church Rd",
    "iso:country":"AU",
    "sg:address":"Church Rd",
    "sg:city":"Hazelwood North",
    "sg:classifiers":[
        {
            "category":"Professional",
            "type":"Services"
        }
    ],
    "sg:phone":"+61 427 512 880",
    "sg:postcode":"3840",
    "sg:province":"VIC",
    "sg:tags":[
        "transport"
    ],
    "wof:name":"Redline Tilt Trays",
    "wof:placetype":"venue"
},
  "geometry": {"coordinates":[146.44265747099999,-38.2677230835],"type":"Point"}
}