{
  "type": "Feature",
  "properties": {
    "addr:full":"Mt. Warren Park Shopping Centre Mt Warren Park QLD 4207",
    "addr:postcode":"4207",
    "addr:street":"Mt",
    "iso:country":"AU",
    "sg:address":"Mt. Warren Park Shopping Centre",
    "sg:city":"Mt Warren Park",
    "sg:classifiers":[
        {
            "category":"Retail",
            "subcategory":"Self-service Laundry",
            "type":"Services"
        }
    ],
    "sg:phone":"+61 419 019 108",
    "sg:postcode":"4207",
    "sg:province":"QLD",
    "wof:name":"Mt Warren Laundromat",
    "wof:placetype":"venue"
},
  "geometry": {"coordinates":[153.207931519,-27.7285881042],"type":"Point"}
}