{
  "type": "Feature",
  "properties": {
    "iso:country":"AU",
    "sg:address":"87 Boundary Rd",
    "sg:city":"Mackay",
    "sg:classifiers":[
        {
            "category":"Professional",
            "type":"Services"
        }
    ],
    "sg:phone":"+61 7 4952 5551",
    "sg:postcode":"4740",
    "sg:province":"QLD",
    "sg:tags":[
        "transport"
    ],
    "wof:name":"Deeson Heavy Haulage Pty Ltd",
    "wof:placetype":"venue"
},
  "geometry": {"coordinates":[149.139725,-21.172485],"type":"Point"}
}