{
  "type": "Feature",
  "properties": {
    "iso:country":"AU",
    "sg:address":"18 Myoora Rd",
    "sg:city":"Terrey Hills",
    "sg:classifiers":[
        {
            "category":"Home & Garden",
            "subcategory":"Garden Supply",
            "type":"Retail Goods"
        }
    ],
    "sg:phone":"+61 2 9450 2455",
    "sg:postcode":"2084",
    "sg:province":"NSW",
    "sg:tags":[
        "landscape"
    ],
    "wof:name":"Imperial Gardens Landscapes Pty Ltd",
    "wof:placetype":"venue"
},
  "geometry": {"coordinates":[151.21470642099999,-33.6968002319],"type":"Point"}
}