{
  "type": "Feature",
  "properties": {
    "addr:full":"1a Martin St Wagga Wagga NSW 2650",
    "addr:housenumber":"1a",
    "addr:postcode":"2650",
    "addr:street":"Martin St",
    "iso:country":"AU",
    "sg:address":"1a Martin St",
    "sg:city":"Wagga Wagga",
    "sg:classifiers":[
        {
            "category":"Retail",
            "subcategory":"Repair Shop",
            "type":"Services"
        }
    ],
    "sg:phone":"+61 2 6931 2240",
    "sg:postcode":"2650",
    "sg:province":"NSW",
    "sg:tags":[
        "machine",
        "sewing"
    ],
    "wof:name":"Rusconi Peter Sewing Machine Service & Repair",
    "wof:placetype":"venue"
},
  "geometry": {"coordinates":[147.346359253,-35.14087677],"type":"Point"}
}