{
  "type": "Feature",
  "properties": {
    "addr:full":"Suite 25 168 Melbourne St North Adelaide SA 5006",
    "addr:housenumber":"168",
    "addr:postcode":"5006",
    "addr:street":"Melbourne St",
    "iso:country":"AU",
    "sg:address":"Suite 25 168 Melbourne St",
    "sg:city":"North Adelaide",
    "sg:classifiers":[
        {
            "category":"Real Estate",
            "subcategory":"Real Estate Services",
            "type":"Services"
        }
    ],
    "sg:phone":"+61 8 8267 2112",
    "sg:postcode":"5006",
    "sg:province":"SA",
    "sg:tags":[
        "valuer"
    ],
    "wof:name":"SA Lease Consultants",
    "wof:placetype":"venue"
},
  "geometry": {"coordinates":[138.60546875,-34.9079360962],"type":"Point"}
}