{
  "type": "Feature",
  "properties": {
    "addr:full":"1 Illuminate Crt Kilsyth South VIC 3137",
    "addr:housenumber":"1",
    "addr:postcode":"3137",
    "addr:street":"Illuminate Crt",
    "iso:country":"AU",
    "sg:address":"1 Illuminate Crt",
    "sg:city":"Kilsyth South",
    "sg:classifiers":[
        {
            "category":"Shopping",
            "subcategory":"Clothing, Apparel, & Fashions",
            "type":"Retail Goods"
        }
    ],
    "sg:phone":"+61 418 583 540",
    "sg:postcode":"3137",
    "sg:province":"VIC",
    "sg:tags":[
        "uniform"
    ],
    "wof:name":"SLR Uniforms & Promotional Supplies",
    "wof:placetype":"venue"
},
  "geometry": {"coordinates":[145.30926513700001,-37.8363189697],"type":"Point"}
}