{
  "type": "Feature",
  "properties": {
    "addr:full":"523 North Rd Ormond VIC 3204",
    "addr:housenumber":"523",
    "addr:postcode":"3204",
    "addr:street":"North Rd",
    "iso:country":"AU",
    "sg:address":"523 North Rd",
    "sg:city":"Ormond",
    "sg:classifiers":[
        {
            "category":"Shopping",
            "subcategory":"Music",
            "type":"Retail Goods"
        }
    ],
    "sg:phone":"+61 3 9578 2426",
    "sg:postcode":"3204",
    "sg:province":"VIC",
    "sg:tags":[
        "instrument",
        "musical"
    ],
    "wof:name":"Melbourne Music Centre",
    "wof:placetype":"venue"
},
  "geometry": {"coordinates":[145.041382,-37.903976],"type":"Point"}
}