{
  "type": "Feature",
  "properties": {
    "addr:full":"Shop 13, Woodcroft Town Center, Cnr Bains & Panala Woodcroft SA 5162",
    "addr:housenumber":"shop 13",
    "addr:postcode":"5162",
    "addr:street":"Cnr",
    "iso:country":"AU",
    "sg:address":"Shop 13, Woodcroft Town Center, Cnr Bains & Panala",
    "sg:city":"Woodcroft",
    "sg:classifiers":[
        {
            "category":"Travel",
            "subcategory":"Travel Agent",
            "type":"Entertainment"
        }
    ],
    "sg:phone":"+61 13 18 66",
    "sg:postcode":"5162",
    "sg:province":"SA",
    "sg:tags":[
        "consultant"
    ],
    "wof:name":"Flight Centre",
    "wof:placetype":"venue"
},
  "geometry": {"coordinates":[138.55723571799999,-35.1140708923],"type":"Point"}
}