{
  "type": "Feature",
  "properties": {
    "iso:country":"AU",
    "sg:address":"192 King St",
    "sg:city":"Newtown",
    "sg:classifiers":[
        {
            "category":"Personal",
            "subcategory":"Piercing",
            "type":"Services"
        }
    ],
    "sg:phone":"+61 2 9516 2266",
    "sg:postcode":"2042",
    "sg:province":"NSW",
    "sg:tags":[
        "body",
        "ear"
    ],
    "wof:name":"Industrial Strength Australia",
    "wof:placetype":"venue"
},
  "geometry": {"coordinates":[151.182526,-33.894581],"type":"Point"}
}