{
  "type": "Feature",
  "properties": {
    "addr:full":"3/ 818 Whitehorse Rd Box Hill VIC 3128",
    "addr:housenumber":"/ 818",
    "addr:postcode":"3128",
    "addr:street":"Whitehorse Rd",
    "iso:country":"AU",
    "sg:address":"3/ 818 Whitehorse Rd",
    "sg:city":"Box Hill",
    "sg:classifiers":[
        {
            "category":"Professional",
            "subcategory":"Computer Services",
            "type":"Services"
        }
    ],
    "sg:phone":"+61 3 9899 6233",
    "sg:postcode":"3128",
    "sg:province":"VIC",
    "sg:tags":[
        "package",
        "software"
    ],
    "wof:name":"IBA Technologies",
    "wof:placetype":"venue"
},
  "geometry": {"coordinates":[145.11602783199999,-37.8171768188],"type":"Point"}
}