{
  "type": "Feature",
  "properties": {
    "iso:country":"AU",
    "sg:address":"62 McPherson St",
    "sg:city":"Hyden",
    "sg:classifiers":[
        {
            "category":"Autos & Motor Vehicles",
            "subcategory":"Fuel & Gas Station",
            "type":"Retail Goods"
        }
    ],
    "sg:phone":"+61 8 9880 5074",
    "sg:postcode":"6359",
    "sg:province":"WA",
    "wof:name":"Shell Co Of Australia Ltd The",
    "wof:placetype":"venue"
},
  "geometry": {"coordinates":[118.862877,-32.449379],"type":"Point"}
}