{
  "type": "Feature",
  "properties": {
    "addr:full":"537- 539 Raglan Pde Warrnambool VIC 3280",
    "addr:housenumber":"539",
    "addr:postcode":"3280",
    "addr:street":"Raglan Pde",
    "iso:country":"AU",
    "sg:address":"537- 539 Raglan Pde",
    "sg:city":"Warrnambool",
    "sg:classifiers":[
        {
            "category":"Retail",
            "subcategory":"Auto Repair",
            "type":"Services"
        }
    ],
    "sg:phone":"+61 3 5562 8888",
    "sg:postcode":"3280",
    "sg:province":"VIC",
    "sg:tags":[
        "clutch",
        "brake"
    ],
    "wof:name":"Goodyear Auto Service Centre",
    "wof:placetype":"venue"
},
  "geometry": {"coordinates":[142.48703002900001,-38.3815803528],"type":"Point"}
}