{
  "type": "Feature",
  "properties": {
    "iso:country":"AU",
    "sg:address":"35C Malton Rd",
    "sg:city":"Beecroft",
    "sg:classifiers":[
        {
            "category":"Government",
            "subcategory":"Court House",
            "type":"Public Place"
        }
    ],
    "sg:phone":"+61 416 112 249",
    "sg:postcode":"2119",
    "sg:province":"NSW",
    "sg:tags":[
        "personal",
        "marriage",
        "family",
        "counselling"
    ],
    "wof:name":"A.A.R.C.",
    "wof:placetype":"venue"
},
  "geometry": {"coordinates":[151.07159423799999,-33.7480278015],"type":"Point"}
}