{
  "type": "Feature",
  "properties": {
    "addr:full":"76 Gale St Busselton WA 6280",
    "addr:housenumber":"76",
    "addr:postcode":"6280",
    "addr:street":"Gale St",
    "iso:country":"AU",
    "sg:address":"76 Gale St",
    "sg:city":"Busselton",
    "sg:classifiers":[
        {
            "category":"Health Services",
            "subcategory":"Health Practitioner",
            "type":"Services"
        }
    ],
    "sg:phone":"+61 8 9751 3600",
    "sg:postcode":"6280",
    "sg:province":"WA",
    "sg:tags":[
        "audiologists"
    ],
    "wof:name":"South West Audiology & Hearing Services",
    "wof:placetype":"venue"
},
  "geometry": {"coordinates":[115.33872985799999,-33.6528358459],"type":"Point"}
}