{
  "type": "Feature",
  "properties": {
    "addr:full":"Shop 8, The Trak Arcade Ocean Grove VIC 3226",
    "addr:housenumber":"shop 8",
    "addr:postcode":"3226",
    "addr:street":"The Trak Arcade",
    "iso:country":"AU",
    "sg:address":"Shop 8, The Trak Arcade",
    "sg:city":"Ocean Grove",
    "sg:classifiers":[
        {
            "category":"Shopping",
            "subcategory":"Clothing, Apparel, & Fashions",
            "type":"Retail Goods"
        }
    ],
    "sg:phone":"+61 3 5256 1590",
    "sg:postcode":"3226",
    "sg:province":"VIC",
    "sg:tags":[
        "lady",
        "wear"
    ],
    "wof:name":"Brontes Boutique",
    "wof:placetype":"venue"
},
  "geometry": {"coordinates":[144.53233299999999,-38.265778],"type":"Point"}
}