{
  "type": "Feature",
  "properties": {
    "addr:full":"177 Burwood Rd Croydon Park NSW 2133",
    "addr:housenumber":"177",
    "addr:postcode":"2133",
    "addr:street":"Burwood Rd",
    "iso:country":"AU",
    "sg:address":"177 Burwood Rd",
    "sg:city":"Croydon Park",
    "sg:classifiers":[
        {
            "category":"Building & Trades",
            "subcategory":"Plumbing",
            "type":"Services"
        }
    ],
    "sg:phone":"+61 2 9747 5544",
    "sg:postcode":"2133",
    "sg:province":"NSW",
    "sg:tags":[
        "plumber",
        "gasfitters"
    ],
    "wof:name":"Connect Plumbing Services",
    "wof:placetype":"venue"
},
  "geometry": {"coordinates":[151.099151611,-33.898979187],"type":"Point"}
}