{
  "type": "Feature",
  "properties": {
    "addr:full":"30 Gothernburg Crs Stuart Park NT 0820",
    "addr:housenumber":"30",
    "addr:postcode":"nt 0820",
    "addr:street":"Gothernburg Crs Stuart",
    "iso:country":"AU",
    "sg:address":"30 Gothernburg Crs",
    "sg:city":"Stuart Park",
    "sg:classifiers":[
        {
            "category":"Building & Trades",
            "subcategory":"Construction",
            "type":"Services"
        }
    ],
    "sg:phone":"+61 8 8981 0833",
    "sg:postcode":"0820",
    "sg:province":"NT",
    "sg:tags":[
        "contractor"
    ],
    "wof:name":"St Hilliers (NT) Pty Ltd",
    "wof:placetype":"venue"
},
  "geometry": {"coordinates":[130.84913635300001,-12.4458599091],"type":"Point"}
}