{
  "type": "Feature",
  "properties": {
    "iso:country":"AU",
    "sg:address":"4 Ford Drv",
    "sg:city":"Mansfield",
    "sg:classifiers":[
        {
            "category":"Retail",
            "subcategory":"Laundry & Dry Cleaning",
            "type":"Services"
        }
    ],
    "sg:phone":"+61 3 5775 3030",
    "sg:postcode":"3722",
    "sg:province":"VIC",
    "sg:tags":[
        "breeder",
        "alpaca",
        "llama"
    ],
    "wof:name":"Tarrant Ridge Alpacas",
    "wof:placetype":"venue"
},
  "geometry": {"coordinates":[146.002487183,-37.0575714111],"type":"Point"}
}