{
  "type": "Feature",
  "properties": {
    "addr:full":"45 Burwood Drv Blackmans Bay TAS 7052",
    "addr:housenumber":"45",
    "addr:postcode":"7052",
    "addr:street":"Burwood Drv",
    "iso:country":"AU",
    "sg:address":"45 Burwood Drv",
    "sg:city":"Blackmans Bay",
    "sg:classifiers":[
        {
            "category":"Building & Trades",
            "subcategory":"Construction",
            "type":"Services"
        }
    ],
    "sg:phone":"+61 418 123 498",
    "sg:postcode":"7052",
    "sg:province":"TAS",
    "sg:tags":[
        "earth",
        "excavating",
        "moving",
        "contractor"
    ],
    "wof:name":"Shadbolt Leigh & Jan Earthmoving Contractors",
    "wof:placetype":"venue"
},
  "geometry": {"coordinates":[147.311035,-43.003975],"type":"Point"}
}