{
  "type": "Feature",
  "properties": {
    "iso:country":"AU",
    "sg:address":"372 Newbridge Rd",
    "sg:city":"Moorebank",
    "sg:classifiers":[
        {
            "category":"Professional",
            "subcategory":"Detective & Security Services",
            "type":"Services"
        }
    ],
    "sg:phone":"+61 1300 303 017",
    "sg:postcode":"2170",
    "sg:province":"NSW",
    "sg:tags":[
        "domestic",
        "alarm",
        "commercial",
        "burglar"
    ],
    "wof:name":"Alarm Factory The",
    "wof:placetype":"venue"
},
  "geometry": {"coordinates":[150.93394470199999,-33.9292602539],"type":"Point"}
}