{
  "type": "Feature",
  "properties": {
    "addr:full":"PO Box 1062 Surfers Paradise QLD 4217",
    "addr:postcode":"4217",
    "iso:country":"AU",
    "sg:address":"PO Box 1062",
    "sg:city":"Surfers Paradise",
    "sg:classifiers":[
        {
            "category":"Real Estate",
            "subcategory":"Real Estate Services",
            "type":"Services"
        }
    ],
    "sg:phone":"+61 7 5538 9055",
    "sg:postcode":"4217",
    "sg:province":"QLD",
    "sg:tags":[
        "valuer"
    ],
    "wof:name":"Accede Valuation & Property Services Pty Ltd",
    "wof:placetype":"venue"
},
  "geometry": {"coordinates":[153.430541992,-28.0124225616],"type":"Point"}
}