{
  "type": "Feature",
  "properties": {
    "addr:full":"276 Kingsgrove Rd Kingsgrove NSW 2208",
    "addr:housenumber":"276",
    "addr:postcode":"2208",
    "addr:street":"Kingsgrove Rd",
    "iso:country":"AU",
    "sg:address":"276 Kingsgrove Rd",
    "sg:city":"Kingsgrove",
    "sg:classifiers":[
        {
            "category":"Food & Beverages",
            "subcategory":"Liquor & Beverages",
            "type":"Retail Goods"
        }
    ],
    "sg:phone":"+61 2 9150 5599",
    "sg:postcode":"2208",
    "sg:province":"NSW",
    "sg:tags":[
        "store"
    ],
    "wof:name":"Cinar Cellars Pty Ltd",
    "wof:placetype":"venue"
},
  "geometry": {"coordinates":[151.101562,-33.942188],"type":"Point"}
}