{
  "type": "Feature",
  "properties": {
    "iso:country":"AU",
    "sg:address":"26 Westhaven Drv",
    "sg:city":"Woodvale",
    "sg:classifiers":[
        {
            "category":"Building & Trades",
            "subcategory":"Construction",
            "type":"Services"
        }
    ],
    "sg:phone":"+61 8 9409 6818",
    "sg:postcode":"6026",
    "sg:province":"WA",
    "sg:tags":[
        "fencing",
        "contractor"
    ],
    "wof:name":"Woodvale Fencing",
    "wof:placetype":"venue"
},
  "geometry": {"coordinates":[115.785453796,-31.7908649445],"type":"Point"}
}