{
  "type": "Feature",
  "properties": {
    "iso:country":"AU",
    "sg:address":"Level 3, Suite 3.03, 550 Stanley St",
    "sg:city":"South Brisbane",
    "sg:classifiers":[
        {
            "category":"Health Services",
            "subcategory":"Doctor",
            "type":"Services"
        }
    ],
    "sg:phone":"+61 7 3010 3333",
    "sg:postcode":"4101",
    "sg:province":"QLD",
    "sg:tags":[
        "medical",
        "practitioner"
    ],
    "wof:name":"Swindle Peter Dr",
    "wof:placetype":"venue"
},
  "geometry": {"coordinates":[153.02854919399999,-27.4848499298],"type":"Point"}
}