{
  "type": "Feature",
  "properties": {
    "addr:full":"7c Hunter St Kalgoorlie WA 6430",
    "addr:housenumber":"7c",
    "addr:postcode":"6430",
    "addr:street":"Hunter St",
    "iso:country":"AU",
    "sg:address":"7c Hunter St",
    "sg:city":"Kalgoorlie",
    "sg:classifiers":[
        {
            "category":"Social Services",
            "subcategory":"Adult Care",
            "type":"Services"
        }
    ],
    "sg:phone":"+61 419 860 145",
    "sg:postcode":"6430",
    "sg:province":"WA",
    "sg:tags":[
        "towing"
    ],
    "wof:name":"Parkesys Towing",
    "wof:placetype":"venue"
},
  "geometry": {"coordinates":[121.438186645,-30.7755126953],"type":"Point"}
}