{
  "type": "Feature",
  "properties": {
    "addr:full":"417 Anzac Pde Kingsford NSW 2032",
    "addr:housenumber":"417",
    "addr:postcode":"2032",
    "addr:street":"Anzac Pde",
    "iso:country":"AU",
    "sg:address":"417 Anzac Pde",
    "sg:city":"Kingsford",
    "sg:classifiers":[
        {
            "category":"Retail",
            "subcategory":"Car Wash",
            "type":"Services"
        }
    ],
    "sg:phone":"+61 2 9313 6666",
    "sg:postcode":"2032",
    "sg:province":"NSW",
    "sg:tags":[
        "truck",
        "cleaning"
    ],
    "wof:name":"Crystal Car Wash Cafe",
    "wof:placetype":"venue"
},
  "geometry": {"coordinates":[151.23016357399999,-33.9261398315],"type":"Point"}
}