{
  "type": "Feature",
  "properties": {
    "iso:country":"AU",
    "sg:address":"Harriet St",
    "sg:city":"Toora",
    "sg:classifiers":[
        {
            "category":"Education",
            "subcategory":"School",
            "type":"Public Place"
        }
    ],
    "sg:phone":"+61 3 5686 2283",
    "sg:postcode":"3962",
    "sg:province":"VIC",
    "sg:tags":[
        "state",
        "except",
        "nsw"
    ],
    "wof:name":"Toora Primary School",
    "wof:placetype":"venue"
},
  "geometry": {"coordinates":[146.327636719,-38.6632270813],"type":"Point"}
}