{
  "type": "Feature",
  "properties": {
    "iso:country":"AU",
    "sg:address":"45 Linden St",
    "sg:city":"Kirrawee",
    "sg:classifiers":[
        {
            "category":"Social Services",
            "subcategory":"Adult Care",
            "type":"Services"
        }
    ],
    "sg:phone":"+61 2 9521 1111",
    "sg:postcode":"2232",
    "sg:province":"NSW",
    "sg:tags":[
        "towing"
    ],
    "wof:name":"Kingsway Towing",
    "wof:placetype":"venue"
},
  "geometry": {"coordinates":[151.055130005,-34.0304145813],"type":"Point"}
}