{
  "type": "Feature",
  "properties": {
    "iso:country":"AU",
    "sg:address":"Shop 10 Winston Hills Mall",
    "sg:city":"Winston Hills",
    "sg:classifiers":[
        {
            "category":"Cafe",
            "type":"Food & Drink"
        }
    ],
    "sg:phone":"+61 2 9624 1159",
    "sg:postcode":"2153",
    "sg:province":"NSW",
    "wof:name":"Chat Time Cafe",
    "wof:placetype":"venue"
},
  "geometry": {"coordinates":[150.99879455600001,-33.7545852661],"type":"Point"}
}