{
  "type": "Feature",
  "properties": {
    "addr:full":"U3/ 45 Prindiville Drv Wangara WA 6065",
    "addr:housenumber":"45",
    "addr:postcode":"6065",
    "addr:street":"U3 /;Prindiville Drv",
    "iso:country":"AU",
    "sg:address":"U3/ 45 Prindiville Drv",
    "sg:city":"Wangara",
    "sg:classifiers":[
        {
            "category":"Retail",
            "subcategory":"Auto Repair",
            "type":"Services"
        }
    ],
    "sg:phone":"+61 8 9309 1579",
    "sg:postcode":"6065",
    "sg:province":"WA",
    "sg:tags":[
        "repairer",
        "motor",
        "engineer"
    ],
    "wof:name":"N & S Mechanical Repairs",
    "wof:placetype":"venue"
},
  "geometry": {"coordinates":[115.822738648,-31.7908382416],"type":"Point"}
}