{
  "type": "Feature",
  "properties": {
    "addr:full":"2- 12 William Henry St Ultimo NSW 2007",
    "addr:housenumber":"12",
    "addr:postcode":"2007",
    "addr:street":"2;William Henry St",
    "iso:country":"AU",
    "sg:address":"2- 12 William Henry St",
    "sg:city":"Ultimo",
    "sg:classifiers":[
        {
            "category":"Arts & Performance",
            "subcategory":"Theater",
            "type":"Entertainment"
        }
    ],
    "sg:phone":"+61 2 9571 5733",
    "sg:postcode":"2007",
    "sg:province":"NSW",
    "sg:tags":[
        "agency",
        "booking",
        "theatre"
    ],
    "wof:name":"All Star Agency",
    "wof:placetype":"venue"
},
  "geometry": {"coordinates":[151.195755005,-33.8789024353],"type":"Point"}
}