{
  "type": "Feature",
  "properties": {
    "addr:full":"Factory 5/ 227 Wells Rd Chelsea Heights VIC 3196",
    "addr:housenumber":"/ 227",
    "addr:postcode":"3196",
    "addr:street":"Wells Rd",
    "iso:country":"AU",
    "sg:address":"Factory 5/ 227 Wells Rd",
    "sg:city":"Chelsea Heights",
    "sg:classifiers":[
        {
            "category":"Professional",
            "subcategory":"Art Services",
            "type":"Services"
        }
    ],
    "sg:phone":"+61 1300 723 924",
    "sg:postcode":"3196",
    "sg:province":"VIC",
    "sg:tags":[
        "decorator",
        "painter"
    ],
    "sg:website":"http://www.cipsltd.com",
    "wof:name":"CIPS Commercial Industrial Painting Services",
    "wof:placetype":"venue"
},
  "geometry": {"coordinates":[145.13870239299999,-38.0415420532],"type":"Point"}
}