{
  "type": "Feature",
  "properties": {
    "addr:full":"50 Woods St Darwin NT 0800",
    "addr:housenumber":"50",
    "addr:postcode":"nt 0800",
    "addr:street":"Woods St",
    "iso:country":"AU",
    "sg:address":"50 Woods St",
    "sg:city":"Darwin",
    "sg:classifiers":[
        {
            "category":"Health Services",
            "subcategory":"Doctor",
            "type":"Services"
        }
    ],
    "sg:phone":"+61 8 8981 8566",
    "sg:postcode":"0800",
    "sg:province":"NT",
    "sg:tags":[
        "medical",
        "practitioner"
    ],
    "wof:name":"Karen Stringer Dr",
    "wof:placetype":"venue"
},
  "geometry": {"coordinates":[130.84251403799999,-12.4596862793],"type":"Point"}
}