{
  "type": "Feature",
  "properties": {
    "addr:full":"Unit 1, 112- 116 Lambec Drv Tullamarine VIC 3043",
    "addr:housenumber":"112 116",
    "addr:postcode":"3043",
    "addr:street":"Lambec Drv",
    "iso:country":"AU",
    "sg:address":"Unit 1, 112- 116 Lambec Drv",
    "sg:city":"Tullamarine",
    "sg:classifiers":[
        {
            "category":"Professional",
            "subcategory":"Employment Agencies",
            "type":"Services"
        }
    ],
    "sg:phone":"+61 3 9330 3033",
    "sg:postcode":"3043",
    "sg:province":"VIC",
    "sg:tags":[
        "broker",
        "custom"
    ],
    "wof:name":"Nippon Express (Australia) Pty Ltd",
    "wof:placetype":"venue"
},
  "geometry": {"coordinates":[144.857711792,-37.7095794678],"type":"Point"}
}