{
  "type": "Feature",
  "properties": {
    "iso:country":"AU",
    "sg:address":"156 Princes Hwy",
    "sg:city":"St Peters",
    "sg:classifiers":[
        {
            "category":"Retail",
            "subcategory":"Auto Repair",
            "type":"Services"
        }
    ],
    "sg:phone":"+61 2 9519 9138",
    "sg:postcode":"2044",
    "sg:province":"NSW",
    "sg:tags":[
        "repairer",
        "motor",
        "engineer"
    ],
    "wof:name":"Msk Service Centre",
    "wof:placetype":"venue"
},
  "geometry": {"coordinates":[151.178406,-33.913696],"type":"Point"}
}