{
  "type": "Feature",
  "properties": {
    "iso:country":"AU",
    "sg:address":"New England Hwy",
    "sg:city":"Applethorpe",
    "sg:classifiers":[
        {
            "category":"Food & Beverages",
            "subcategory":"Fruits & Vegetables",
            "type":"Retail Goods"
        }
    ],
    "sg:phone":"+61 7 4683 2448",
    "sg:postcode":"4378",
    "sg:province":"QLD",
    "sg:tags":[
        "greengrocer",
        "fruiterer"
    ],
    "wof:name":"Lancuba's Fruit Mart",
    "wof:placetype":"venue"
},
  "geometry": {"coordinates":[151.955535889,-28.6184406281],"type":"Point"}
}