{
  "type": "Feature",
  "properties": {
    "iso:country":"AU",
    "sg:address":"Distinctive Homes Dome 44",
    "sg:city":"a Crittenden Rd, Findon",
    "sg:classifiers":[
        {
            "category":"Sports & Exercise",
            "subcategory":"Gym",
            "type":"Entertainment"
        }
    ],
    "sg:phone":"+61 434 561 583",
    "sg:postcode":"5023",
    "sg:province":"SA",
    "sg:tags":[
        "health",
        "fitness"
    ],
    "wof:name":"EFM Health Clubs",
    "wof:placetype":"venue"
},
  "geometry": {"coordinates":[138.54328918499999,-34.9026184082],"type":"Point"}
}