{
  "type": "Feature",
  "properties": {
    "addr:full":"26/28 Trade Pl Coburg North VIC 3058",
    "addr:housenumber":"26 / 28",
    "addr:postcode":"3058",
    "addr:street":"Trade Pl",
    "iso:country":"AU",
    "sg:address":"26/28 Trade Pl",
    "sg:city":"Coburg North",
    "sg:classifiers":[
        {
            "category":"Manufacturing",
            "subcategory":"Tools & Machinery",
            "type":"Manufacturing & Wholesale Goods"
        }
    ],
    "sg:phone":"+61 3 9354 4165",
    "sg:postcode":"3058",
    "sg:province":"VIC",
    "sg:tags":[
        "wholesaler",
        "mfrs",
        "hosiery"
    ],
    "wof:name":"La Socs Pty Ltd",
    "wof:placetype":"venue"
},
  "geometry": {"coordinates":[144.97215270999999,-37.7242622375],"type":"Point"}
}