{
  "type": "Feature",
  "properties": {
    "iso:country":"AU",
    "sg:address":"16 Thiele Rd",
    "sg:city":"Murray Bridge",
    "sg:classifiers":[
        {
            "category":"Building & Trades",
            "subcategory":"Construction",
            "type":"Services"
        }
    ],
    "sg:phone":"+61 403 248 667",
    "sg:postcode":"5253",
    "sg:province":"SA",
    "sg:tags":[
        "joiner",
        "carpenter"
    ],
    "wof:name":"DJays Carpentry",
    "wof:placetype":"venue"
},
  "geometry": {"coordinates":[139.28091430699999,-35.1054420471],"type":"Point"}
}