{
  "type": "Feature",
  "properties": {
    "addr:full":"54 Stephen Tce St Peters SA 5069",
    "addr:housenumber":"54",
    "addr:postcode":"5069",
    "addr:street":"Stephen Tce",
    "iso:country":"AU",
    "sg:address":"54 Stephen Tce",
    "sg:city":"St Peters",
    "sg:classifiers":[
        {
            "category":"Food & Beverages",
            "subcategory":"Fruits & Vegetables",
            "type":"Retail Goods"
        }
    ],
    "sg:phone":"+61 8 8363 1340",
    "sg:postcode":"5069",
    "sg:province":"SA",
    "sg:tags":[
        "consultant",
        "catering"
    ],
    "wof:name":"Epicurean Events",
    "wof:placetype":"venue"
},
  "geometry": {"coordinates":[138.623504639,-34.9047203064],"type":"Point"}
}