{
  "type": "Feature",
  "properties": {
    "addr:full":"13 Studley St Abbotsford VIC 3067",
    "addr:housenumber":"13",
    "addr:postcode":"3067",
    "addr:street":"Studley St",
    "iso:country":"AU",
    "sg:address":"13 Studley St",
    "sg:city":"Abbotsford",
    "sg:classifiers":[
        {
            "category":"Professional",
            "subcategory":"Detective & Security Services",
            "type":"Services"
        }
    ],
    "sg:phone":"+61 3 9418 4444",
    "sg:postcode":"3067",
    "sg:province":"VIC",
    "sg:tags":[
        "consultant",
        "system"
    ],
    "wof:name":"Tricom Network & Communication Solutions Pty Ltd",
    "wof:placetype":"venue"
},
  "geometry": {"coordinates":[144.99356079099999,-37.8013839722],"type":"Point"}
}