{
  "type": "Feature",
  "properties": {
    "addr:full":"Shp 9, 386 Wanneroo Rd Balcatta WA 6021",
    "addr:housenumber":"386",
    "addr:postcode":"6021",
    "addr:street":"Wanneroo Rd",
    "iso:country":"AU",
    "sg:address":"Shp 9, 386 Wanneroo Rd",
    "sg:city":"Balcatta",
    "sg:classifiers":[
        {
            "category":"Retail",
            "subcategory":"Repair Shop",
            "type":"Services"
        }
    ],
    "sg:phone":"+61 8 9344 7455",
    "sg:postcode":"6021",
    "sg:province":"WA",
    "sg:tags":[
        "cleaner",
        "part",
        "vacuum"
    ],
    "wof:name":"Godfreys",
    "wof:placetype":"venue"
},
  "geometry": {"coordinates":[115.83187866199999,-31.8732395172],"type":"Point"}
}