{
  "type": "Feature",
  "properties": {
    "iso:country":"AU",
    "sg:address":"29 Canning Hwy",
    "sg:city":"East Fremantle",
    "sg:classifiers":[
        {
            "category":"Real Estate",
            "subcategory":"Real Estate Agent",
            "type":"Services"
        }
    ],
    "sg:phone":"+61 8 9339 7777",
    "sg:postcode":"6158",
    "sg:province":"WA",
    "wof:name":"Ray Fuller Real Estate",
    "wof:placetype":"venue"
},
  "geometry": {"coordinates":[115.80603000000001,-32.032555],"type":"Point"}
}