{
  "type": "Feature",
  "properties": {
    "iso:country":"AU",
    "sg:address":"45 Iowanna Ave",
    "sg:city":"Forresters Beach",
    "sg:classifiers":[
        {
            "category":"Building & Trades",
            "subcategory":"Construction",
            "type":"Services"
        }
    ],
    "sg:phone":"+61 2 4384 6389",
    "sg:postcode":"2260",
    "sg:province":"NSW",
    "sg:tags":[
        "contractor"
    ],
    "wof:name":"Murray Newman",
    "wof:placetype":"venue"
},
  "geometry": {"coordinates":[151.464569,-33.406319],"type":"Point"}
}