{
  "type": "Feature",
  "properties": {
    "iso:country":"AU",
    "sg:address":"Marina Shopping Village 10 Santa Barbara Rd",
    "sg:city":"Hope Island",
    "sg:classifiers":[
        {
            "category":"Health Services",
            "subcategory":"Doctor",
            "type":"Services"
        }
    ],
    "sg:phone":"+61 7 5510 8199",
    "sg:postcode":"4212",
    "sg:province":"QLD",
    "sg:tags":[
        "medical",
        "practitioner"
    ],
    "wof:name":"Weissenberger Andrew Dr",
    "wof:placetype":"venue"
},
  "geometry": {"coordinates":[153.35055542000001,-27.8670959473],"type":"Point"}
}