{
  "type": "Feature",
  "properties": {
    "iso:country":"AU",
    "sg:address":"Shp 95",
    "sg:city":"Chermside Shopng Cntr, Cnr Gympie & Hamilton",
    "sg:classifiers":[
        {
            "category":"Insurance",
            "subcategory":"Health Insurance",
            "type":"Services"
        }
    ],
    "sg:phone":"+61 13 11 37",
    "sg:postcode":"4032",
    "sg:province":"QLD",
    "wof:name":"MBF",
    "wof:placetype":"venue"
},
  "geometry": {"coordinates":[153.031113,-27.386387],"type":"Point"}
}