{
  "type": "Feature",
  "properties": {
    "addr:full":"1 Wharf St Cannington WA 6107",
    "addr:housenumber":"1",
    "addr:postcode":"6107",
    "addr:street":"Wharf St",
    "iso:country":"AU",
    "sg:address":"1 Wharf St",
    "sg:city":"Cannington",
    "sg:classifiers":[
        {
            "category":"Arena",
            "subcategory":"Sports Club",
            "type":"Entertainment"
        }
    ],
    "sg:phone":"+61 8 9358 3000",
    "sg:postcode":"6107",
    "sg:province":"WA",
    "sg:tags":[
        "defence",
        "supply",
        "self",
        "instruction",
        "martial art"
    ],
    "sg:website":"http://www.cobramartialarts.com.au",
    "wof:name":"Cobra Martial Arts & Fitness Centre",
    "wof:placetype":"venue"
},
  "geometry": {"coordinates":[115.932998657,-32.0160636902],"type":"Point"}
}