{
  "type": "Feature",
  "properties": {
    "addr:full":"32- 34 Rosa St Goodwood SA 5034",
    "addr:housenumber":"34",
    "addr:postcode":"5034",
    "addr:street":"Rosa St",
    "iso:country":"AU",
    "sg:address":"32- 34 Rosa St",
    "sg:city":"Goodwood",
    "sg:classifiers":[
        {
            "category":"Recreation",
            "type":"Entertainment"
        }
    ],
    "sg:phone":"+61 8 8272 7148",
    "sg:postcode":"5034",
    "sg:province":"SA",
    "sg:tags":[
        "children's",
        "play",
        "programme"
    ],
    "wof:name":"Goodwood Kindergym",
    "wof:placetype":"venue"
},
  "geometry": {"coordinates":[138.58987426799999,-34.9511146545],"type":"Point"}
}