{
  "type": "Feature",
  "properties": {
    "addr:full":"227- 233 Mickleham Rd Tullamarine VIC 3043",
    "addr:housenumber":"233",
    "addr:postcode":"3043",
    "addr:street":"Mickleham Rd",
    "iso:country":"AU",
    "sg:address":"227- 233 Mickleham Rd",
    "sg:city":"Tullamarine",
    "sg:classifiers":[
        {
            "category":"Food & Beverages",
            "subcategory":"Groceries & Convenience Stores",
            "type":"Retail Goods"
        }
    ],
    "sg:phone":"+61 3 9330 1702",
    "sg:postcode":"3043",
    "sg:province":"VIC",
    "wof:name":"Ampol Shop Stop",
    "wof:placetype":"venue"
},
  "geometry": {"coordinates":[144.882644653,-37.6847381592],"type":"Point"}
}