{
  "type": "Feature",
  "properties": {
    "addr:full":"204 Oyster Bay Rd Oyster Bay NSW 2225",
    "addr:housenumber":"204",
    "addr:postcode":"2225",
    "addr:street":"Oyster Bay Rd",
    "iso:country":"AU",
    "sg:address":"204 Oyster Bay Rd",
    "sg:city":"Oyster Bay",
    "sg:classifiers":[
        {
            "category":"Utilities",
            "subcategory":"Electric",
            "type":"Services"
        }
    ],
    "sg:phone":"+61 2 9528 5483",
    "sg:postcode":"2225",
    "sg:province":"NSW",
    "sg:tags":[
        "electrical",
        "contractor"
    ],
    "wof:name":"Beazley Steve Electrician",
    "wof:placetype":"venue"
},
  "geometry": {"coordinates":[151.07423400900001,-34.0080795288],"type":"Point"}
}