{
  "type": "Feature",
  "properties": {
    "iso:country":"AU",
    "sg:address":"27 Tralee Ave",
    "sg:city":"Killarney Heights",
    "sg:classifiers":[
        {
            "category":"Health Services",
            "subcategory":"Health Practitioner",
            "type":"Services"
        }
    ],
    "sg:phone":"+61 2 9452 1318",
    "sg:postcode":"2087",
    "sg:province":"NSW",
    "sg:tags":[
        "psychologist"
    ],
    "wof:name":"Palmer Lorraine",
    "wof:placetype":"venue"
},
  "geometry": {"coordinates":[151.21905517600001,-33.7758407593],"type":"Point"}
}