{
  "type": "Feature",
  "properties": {
    "addr:full":"PO Box 421 Arundel QLD 4214",
    "addr:postcode":"4214",
    "iso:country":"AU",
    "sg:address":"PO Box 421",
    "sg:city":"Arundel",
    "sg:classifiers":[
        {
            "category":"Real Estate",
            "subcategory":"Real Estate Agent",
            "type":"Services"
        }
    ],
    "sg:phone":"+61 7 5529 2595",
    "sg:postcode":"4214",
    "sg:province":"QLD",
    "sg:tags":[
        "buyer"
    ],
    "wof:name":"Prime Australia Consultants",
    "wof:placetype":"venue"
},
  "geometry": {"coordinates":[153.38641357399999,-27.9434700012],"type":"Point"}
}