{
  "type": "Feature",
  "properties": {
    "addr:full":"23 Silicon Pl Tullamarine VIC 3043",
    "addr:housenumber":"23",
    "addr:postcode":"3043",
    "addr:street":"Silicon Pl",
    "iso:country":"AU",
    "sg:address":"23 Silicon Pl",
    "sg:city":"Tullamarine",
    "sg:classifiers":[
        {
            "category":"Building & Trades",
            "subcategory":"Construction",
            "type":"Services"
        }
    ],
    "sg:phone":"+61 3 9330 2200",
    "sg:postcode":"3043",
    "sg:province":"VIC",
    "sg:tags":[
        "ceiling"
    ],
    "wof:name":"Office Partitioning Systems",
    "wof:placetype":"venue"
},
  "geometry": {"coordinates":[144.87612915,-37.7131118774],"type":"Point"}
}