{
  "type": "Feature",
  "properties": {
    "addr:full":"10 Torrington Rd Maroubra NSW 2035",
    "addr:housenumber":"10",
    "addr:postcode":"2035",
    "addr:street":"Torrington Rd",
    "iso:country":"AU",
    "sg:address":"10 Torrington Rd",
    "sg:city":"Maroubra",
    "sg:classifiers":[
        {
            "category":"Professional",
            "subcategory":"Accounting & Tax Preparation",
            "type":"Services"
        }
    ],
    "sg:phone":"+61 2 9349 7930",
    "sg:postcode":"2035",
    "sg:province":"NSW",
    "sg:tags":[
        "accountant",
        "auditor"
    ],
    "wof:name":"J S O&#039;Brien & Associates",
    "wof:placetype":"venue"
},
  "geometry": {"coordinates":[151.2578125,-33.9393234253],"type":"Point"}
}