{
  "type": "Feature",
  "properties": {
    "addr:full":"47 Fraser Rd Killcare NSW 2257",
    "addr:housenumber":"47",
    "addr:postcode":"2257",
    "addr:street":"Fraser Rd",
    "iso:country":"AU",
    "sg:address":"47 Fraser Rd",
    "sg:city":"Killcare",
    "sg:classifiers":[
        {
            "category":"Utilities",
            "subcategory":"Electric",
            "type":"Services"
        }
    ],
    "sg:phone":"+61 414 015 726",
    "sg:postcode":"2257",
    "sg:province":"NSW",
    "sg:tags":[
        "electrical",
        "contractor"
    ],
    "wof:name":"John Kearnes (Electrical)",
    "wof:placetype":"venue"
},
  "geometry": {"coordinates":[151.36488342300001,-33.518787384],"type":"Point"}
}