{
  "type": "Feature",
  "properties": {
    "addr:full":"3 Saunders Pl Raby NSW 2566",
    "addr:housenumber":"3",
    "addr:postcode":"2566",
    "addr:street":"Saunders Pl Raby",
    "iso:country":"AU",
    "sg:address":"3 Saunders Pl",
    "sg:city":"Raby",
    "sg:classifiers":[
        {
            "category":"Building & Trades",
            "subcategory":"Construction",
            "type":"Services"
        }
    ],
    "sg:phone":"+61 414 849 869",
    "sg:postcode":"2566",
    "sg:province":"NSW",
    "sg:tags":[
        "earth",
        "excavating",
        "moving",
        "contractor"
    ],
    "wof:name":"W & A Adams Excavations",
    "wof:placetype":"venue"
},
  "geometry": {"coordinates":[150.81307983400001,-34.0113105774],"type":"Point"}
}