{
  "type": "Feature",
  "properties": {
    "iso:country":"AU",
    "sg:address":"298 Ruthven St",
    "sg:city":"Toowoomba",
    "sg:classifiers":[
        {
            "category":"Professional",
            "subcategory":"Accounting & Tax Preparation",
            "type":"Services"
        }
    ],
    "sg:phone":"+61 7 4632 8733",
    "sg:postcode":"4350",
    "sg:province":"QLD",
    "sg:tags":[
        "accountant",
        "auditor"
    ],
    "wof:name":"Power Tynan Pty Ltd",
    "wof:placetype":"venue"
},
  "geometry": {"coordinates":[151.952271,-27.568365],"type":"Point"}
}