{
  "type": "Feature",
  "properties": {
    "iso:country":"AU",
    "sg:address":"4/ 95 Lear Jet Drv",
    "sg:city":"Caboolture",
    "sg:classifiers":[
        {
            "category":"Coffee & Tea",
            "type":"Food & Drink"
        }
    ],
    "sg:phone":"+61 7 5498 9011",
    "sg:postcode":"4510",
    "sg:province":"QLD",
    "sg:tags":[
        "kayak",
        "canoe"
    ],
    "wof:name":"Extreme Kayaks & Watersports",
    "wof:placetype":"venue"
},
  "geometry": {"coordinates":[152.979477,-27.079996],"type":"Point"}
}