{
  "type": "Feature",
  "properties": {
    "addr:full":"Shop 4 176 Ellen St Port Pirie SA 5540",
    "addr:housenumber":"shop 4 176",
    "addr:postcode":"5540",
    "addr:street":"Ellen St",
    "iso:country":"AU",
    "sg:address":"Shop 4 176 Ellen St",
    "sg:city":"Port Pirie",
    "sg:classifiers":[
        {
            "category":"Health Services",
            "subcategory":"Optometrist",
            "type":"Services"
        }
    ],
    "sg:phone":"+61 8 8633 0055",
    "sg:postcode":"5540",
    "sg:province":"SA",
    "wof:name":"Gonsalves, Jose",
    "wof:placetype":"venue"
},
  "geometry": {"coordinates":[138.01109314000001,-33.1793174744],"type":"Point"}
}