{
  "type": "Feature",
  "properties": {
    "iso:country":"AU",
    "sg:address":"5 Loaring Rd",
    "sg:city":"Bickley",
    "sg:classifiers":[
        {
            "category":"Farming",
            "subcategory":"Vineyard",
            "type":"Manufacturing & Wholesale Goods"
        }
    ],
    "sg:phone":"+61 8 9291 8705",
    "sg:postcode":"6076",
    "sg:province":"WA",
    "sg:tags":[
        "winery"
    ],
    "wof:name":"Brookside Vineyard",
    "wof:placetype":"venue"
},
  "geometry": {"coordinates":[116.099533081,-32.0004997253],"type":"Point"}
}