{
  "type": "Feature",
  "properties": {
    "addr:full":"Sandringham St St Johns Park NSW 2176",
    "addr:postcode":"2176",
    "addr:street":"Sandringham St St",
    "iso:country":"AU",
    "sg:address":"Sandringham St",
    "sg:city":"St Johns Park",
    "sg:classifiers":[
        {
            "category":"Education",
            "subcategory":"School",
            "type":"Public Place"
        }
    ],
    "sg:phone":"+61 2 9610 1311",
    "sg:postcode":"2176",
    "sg:province":"NSW",
    "sg:tags":[
        "state",
        "-",
        "nsw"
    ],
    "wof:name":"St Johns Park Public School",
    "wof:placetype":"venue"
},
  "geometry": {"coordinates":[150.89839172399999,-33.8867645264],"type":"Point"}
}