{
  "type": "Feature",
  "properties": {
    "iso:country":"AU",
    "sg:address":"55 Mills St",
    "sg:city":"Warners Bay",
    "sg:classifiers":[
        {
            "category":"Arts & Performance",
            "subcategory":"Music",
            "type":"Entertainment"
        }
    ],
    "sg:phone":"+61 2 4948 8734",
    "sg:postcode":"2282",
    "sg:province":"NSW",
    "sg:tags":[
        "mobile",
        "jockey",
        "disc"
    ],
    "wof:name":"Phil Siever",
    "wof:placetype":"venue"
},
  "geometry": {"coordinates":[151.651046753,-32.9797935486],"type":"Point"}
}