{
  "type": "Feature",
  "properties": {
    "iso:country":"AU",
    "sg:address":"170 Hampden Rd",
    "sg:city":"Nedlands",
    "sg:classifiers":[
        {
            "category":"Personal",
            "subcategory":"Beauty Salon",
            "type":"Services"
        }
    ],
    "sg:phone":"+61 8 9386 7900",
    "sg:postcode":"6009",
    "sg:province":"WA",
    "sg:tags":[
        "hairdresser"
    ],
    "wof:name":"Lexingtons",
    "wof:placetype":"venue"
},
  "geometry": {"coordinates":[115.813622,-31.972633],"type":"Point"}
}