{
  "type": "Feature",
  "properties": {
    "addr:full":"2A Fernleigh Ave Beaumont SA 5066",
    "addr:housenumber":"2a",
    "addr:postcode":"5066",
    "addr:street":"Fernleigh Ave",
    "iso:country":"AU",
    "sg:address":"2A Fernleigh Ave",
    "sg:city":"Beaumont",
    "sg:classifiers":[
        {
            "category":"Banks & Credit Unions",
            "subcategory":"Financial Services",
            "type":"Services"
        }
    ],
    "sg:phone":"+61 8 8338 2610",
    "sg:postcode":"5066",
    "sg:province":"SA",
    "sg:tags":[
        "financier"
    ],
    "wof:name":"Peters Robert",
    "wof:placetype":"venue"
},
  "geometry": {"coordinates":[138.653167725,-34.9451408386],"type":"Point"}
}