{
  "type": "Feature",
  "properties": {
    "addr:full":"52 Seventh St Railway Estate QLD 4810",
    "addr:housenumber":"52",
    "addr:postcode":"4810",
    "addr:street":"Seventh St",
    "iso:country":"AU",
    "sg:address":"52 Seventh St",
    "sg:city":"Railway Estate",
    "sg:classifiers":[
        {
            "category":"Retail",
            "subcategory":"Laundry & Dry Cleaning",
            "type":"Services"
        }
    ],
    "sg:phone":"+61 428 712 096",
    "sg:postcode":"4810",
    "sg:province":"QLD",
    "sg:tags":[
        "truck",
        "tip",
        "contractor"
    ],
    "wof:name":"Alistair Robertson & K L Baine",
    "wof:placetype":"venue"
},
  "geometry": {"coordinates":[146.821732,-19.271091],"type":"Point"}
}