{
  "type": "Feature",
  "properties": {
    "addr:full":"101 Belmont Ave Belmont WA 6104",
    "addr:housenumber":"101",
    "addr:postcode":"6104",
    "addr:street":"Belmont Ave",
    "iso:country":"AU",
    "sg:address":"101 Belmont Ave",
    "sg:city":"Belmont",
    "sg:classifiers":[
        {
            "category":"Professional",
            "subcategory":"Employment Agencies",
            "type":"Services"
        }
    ],
    "sg:phone":"+61 8 9479 4455",
    "sg:postcode":"6104",
    "sg:province":"WA",
    "wof:name":"Steelweld Personnel",
    "wof:placetype":"venue"
},
  "geometry": {"coordinates":[115.925613403,-31.9591960907],"type":"Point"}
}