{
  "type": "Feature",
  "properties": {
    "addr:full":"29 Napier St Deniliquin NSW 2710",
    "addr:housenumber":"29",
    "addr:postcode":"2710",
    "addr:street":"Napier St",
    "iso:country":"AU",
    "sg:address":"29 Napier St",
    "sg:city":"Deniliquin",
    "sg:classifiers":[
        {
            "category":"Shopping",
            "subcategory":"Baby Store",
            "type":"Retail Goods"
        }
    ],
    "sg:phone":"+61 3 5881 7501",
    "sg:postcode":"2710",
    "sg:province":"NSW",
    "sg:tags":[
        "children's",
        "wear"
    ],
    "wof:name":"Blanie Castle",
    "wof:placetype":"venue"
},
  "geometry": {"coordinates":[144.95895385700001,-35.5313301086],"type":"Point"}
}