{
  "type": "Feature",
  "properties": {
    "addr:full":"Shop 5, The Courtyard 67 O'Connell Tce Bowen Hills QLD 4006",
    "addr:housenumber":"shop 5;67",
    "addr:postcode":"4006",
    "addr:street":"The Courtyard;O'Connell Tce",
    "iso:country":"AU",
    "sg:address":"Shop 5, The Courtyard 67 O'Connell Tce",
    "sg:city":"Bowen Hills",
    "sg:classifiers":[
        {
            "category":"Building & Trades",
            "subcategory":"Construction",
            "type":"Services"
        }
    ],
    "sg:phone":"+61 1300 360 169",
    "sg:postcode":"4006",
    "sg:province":"QLD",
    "sg:tags":[
        "concrete",
        "contractor"
    ],
    "wof:name":"Cobblestone Paving Brisbane",
    "wof:placetype":"venue"
},
  "geometry": {"coordinates":[153.03707885700001,-27.4476394653],"type":"Point"}
}