{
  "type": "Feature",
  "properties": {
    "addr:full":"37 Marana Rd Earlwood NSW 2206",
    "addr:housenumber":"37",
    "addr:postcode":"2206",
    "addr:street":"Marana Rd",
    "iso:country":"AU",
    "sg:address":"37 Marana Rd",
    "sg:city":"Earlwood",
    "sg:classifiers":[
        {
            "category":"Professional",
            "subcategory":"Accounting & Tax Preparation",
            "type":"Services"
        }
    ],
    "sg:phone":"+61 2 9806 0006",
    "sg:postcode":"2206",
    "sg:province":"NSW",
    "sg:tags":[
        "consultant",
        "taxation"
    ],
    "wof:name":"Litsas & Co-Chartered Accountant & Taxation Consultant",
    "wof:placetype":"venue"
},
  "geometry": {"coordinates":[151.11085499999999,-33.92601],"type":"Point"}
}