{
  "type": "Feature",
  "properties": {
    "iso:country":"AU",
    "sg:address":"Lot 10/ 8 McLarens Rd",
    "sg:city":"Lake Cathie",
    "sg:classifiers":[
        {
            "category":"Communications",
            "subcategory":"News Services",
            "type":"Services"
        }
    ],
    "sg:phone":"+61 2 6585 4213",
    "sg:postcode":"2445",
    "sg:province":"NSW",
    "sg:tags":[
        "information",
        "tourist",
        "attractions"
    ],
    "wof:name":"Gerard Vander Jagt",
    "wof:placetype":"venue"
},
  "geometry": {"coordinates":[152.81448399999999,-31.524567],"type":"Point"}
}