{
  "type": "Feature",
  "properties": {
    "iso:country":"AU",
    "sg:address":"Unit 3/ 33 Anvil Rd",
    "sg:city":"Seven Hills",
    "sg:classifiers":[
        {
            "category":"Building & Trades",
            "subcategory":"Construction",
            "type":"Services"
        }
    ],
    "sg:phone":"+61 2 9838 0032",
    "sg:postcode":"2147",
    "sg:province":"NSW",
    "sg:tags":[
        "welding"
    ],
    "wof:name":"Andrew's Race Cars",
    "wof:placetype":"venue"
},
  "geometry": {"coordinates":[150.95773315400001,-33.7790794373],"type":"Point"}
}