{
  "type": "Feature",
  "properties": {
    "iso:country":"AU",
    "sg:address":"Dougal St",
    "sg:city":"Bororen",
    "sg:classifiers":[
        {
            "category":"Cafe",
            "type":"Food & Drink"
        }
    ],
    "sg:phone":"+61 7 4974 4151",
    "sg:postcode":"4678",
    "sg:province":"QLD",
    "wof:name":"Shirls Snackbar",
    "wof:placetype":"venue"
},
  "geometry": {"coordinates":[151.49558999999999,-24.242813],"type":"Point"}
}