{
  "type": "Feature",
  "properties": {
    "addr:full":"2/135- 141 Queen St Campbelltown NSW 2560",
    "addr:housenumber":"/ 135 141",
    "addr:postcode":"2560",
    "addr:street":"Queen St",
    "iso:country":"AU",
    "sg:address":"2/135- 141 Queen St",
    "sg:city":"Campbelltown",
    "sg:classifiers":[
        {
            "category":"Shopping",
            "subcategory":"Clothing, Apparel, & Fashions",
            "type":"Retail Goods"
        }
    ],
    "sg:phone":"+61 2 4628 9366",
    "sg:postcode":"2560",
    "sg:province":"NSW",
    "sg:tags":[
        "recycled",
        "clothing"
    ],
    "wof:name":"Look The",
    "wof:placetype":"venue"
},
  "geometry": {"coordinates":[150.81460571299999,-34.0660820007],"type":"Point"}
}