{
  "type": "Feature",
  "properties": {
    "addr:full":"211 Nicholson Rd Subiaco WA 6008",
    "addr:housenumber":"211",
    "addr:postcode":"6008",
    "addr:street":"Nicholson Rd",
    "iso:country":"AU",
    "sg:address":"211 Nicholson Rd",
    "sg:city":"Subiaco",
    "sg:classifiers":[
        {
            "category":"Health Services",
            "subcategory":"Doctor",
            "type":"Services"
        }
    ],
    "sg:phone":"+61 8 9388 9999",
    "sg:postcode":"6008",
    "sg:province":"WA",
    "sg:tags":[
        "podiatrist"
    ],
    "wof:name":"Peak Podiatry Subiaco",
    "wof:placetype":"venue"
},
  "geometry": {"coordinates":[115.81433868400001,-31.9564304352],"type":"Point"}
}