{
  "type": "Feature",
  "properties": {
    "addr:full":"Shop 6 Royal Crs Hillside VIC 3875",
    "addr:housenumber":"shop 6",
    "addr:postcode":"3875",
    "addr:street":"Royal Crs",
    "iso:country":"AU",
    "sg:address":"Shop 6 Royal Crs",
    "sg:city":"Hillside",
    "sg:classifiers":[
        {
            "category":"Fast Food",
            "type":"Food & Drink"
        }
    ],
    "sg:phone":"+61 3 9449 1113",
    "sg:postcode":"3875",
    "sg:province":"VIC",
    "sg:tags":[
        "away",
        "take"
    ],
    "wof:name":"Hillside Pizza & Pasta Takeaway",
    "wof:placetype":"venue"
},
  "geometry": {"coordinates":[147.525146484,-37.8583984375],"type":"Point"}
}