{
  "type": "Feature",
  "properties": {
    "addr:full":"PO Box 162 Wellington NSW 2820",
    "addr:postcode":"2820",
    "iso:country":"AU",
    "sg:address":"PO Box 162",
    "sg:city":"Wellington",
    "sg:classifiers":[
        {
            "category":"Professional",
            "type":"Services"
        }
    ],
    "sg:phone":"+61 2 6846 6286",
    "sg:postcode":"2820",
    "sg:province":"NSW",
    "sg:tags":[
        "transport"
    ],
    "wof:name":"G E & D J Todd",
    "wof:placetype":"venue"
},
  "geometry": {"coordinates":[148.942962647,-32.5556411743],"type":"Point"}
}