{
  "type": "Feature",
  "properties": {
    "iso:country":"AU",
    "sg:address":"524 Hay St",
    "sg:city":"Perth",
    "sg:classifiers":[
        {
            "category":"Real Estate",
            "subcategory":"Real Estate Agent",
            "type":"Services"
        }
    ],
    "sg:phone":"+61 8 9325 0000",
    "sg:postcode":"6000",
    "sg:province":"WA",
    "sg:website":"http://www.tylerandsons.com.au",
    "wof:name":"Tyler & Sons",
    "wof:placetype":"venue"
},
  "geometry": {"coordinates":[115.85555267300001,-31.9532089233],"type":"Point"}
}