{
  "type": "Feature",
  "properties": {
    "iso:country":"AU",
    "sg:address":"PO Box 125",
    "sg:city":"Herne Hill",
    "sg:classifiers":[
        {
            "category":"Building & Trades",
            "subcategory":"Construction",
            "type":"Services"
        }
    ],
    "sg:phone":"+61 437 208 343",
    "sg:postcode":"6056",
    "sg:province":"WA",
    "sg:tags":[
        "insulation",
        "contractor"
    ],
    "wof:name":"Polyurethane Sprayed Foam Insulation Technology",
    "wof:placetype":"venue"
},
  "geometry": {"coordinates":[116.01689910899999,-31.8260307312],"type":"Point"}
}