{
  "type": "Feature",
  "properties": {
    "addr:full":"409 Pacific Hwy Belmont NSW 2280",
    "addr:housenumber":"409",
    "addr:postcode":"2280",
    "addr:street":"Pacific Hwy",
    "iso:country":"AU",
    "sg:address":"409 Pacific Hwy",
    "sg:city":"Belmont",
    "sg:classifiers":[
        {
            "category":"Retail",
            "subcategory":"Repair Shop",
            "type":"Services"
        }
    ],
    "sg:phone":"+61 2 4947 0222",
    "sg:postcode":"2280",
    "sg:province":"NSW",
    "sg:tags":[
        "windscreen"
    ],
    "wof:name":"All Areas Windscreens",
    "wof:placetype":"venue"
},
  "geometry": {"coordinates":[151.661087036,-33.0284614563],"type":"Point"}
}