{
  "type": "Feature",
  "properties": {
    "iso:country":"AU",
    "sg:address":"77 Mains St",
    "sg:city":"Stawell",
    "sg:classifiers":[
        {
            "category":"Retail",
            "subcategory":"Repair Shop",
            "type":"Services"
        }
    ],
    "sg:phone":"+61 419 800 708",
    "sg:postcode":"3380",
    "sg:province":"VIC",
    "sg:tags":[
        "mending",
        "clothing",
        "alteration"
    ],
    "wof:name":"Sew Well Stawell",
    "wof:placetype":"venue"
},
  "geometry": {"coordinates":[142.78558349599999,-37.0525588989],"type":"Point"}
}