{
  "type": "Feature",
  "properties": {
    "addr:full":"1244 Malvern Rd Malvern VIC 3144",
    "addr:housenumber":"1244",
    "addr:postcode":"3144",
    "addr:street":"Malvern Rd",
    "iso:country":"AU",
    "sg:address":"1244 Malvern Rd",
    "sg:city":"Malvern",
    "sg:classifiers":[
        {
            "category":"Professional",
            "subcategory":"Art Services",
            "type":"Services"
        }
    ],
    "sg:phone":"+61 407 532 195",
    "sg:postcode":"3144",
    "sg:province":"VIC",
    "sg:tags":[
        "interior",
        "decorator"
    ],
    "wof:name":"Cooper Robinson Interiors",
    "wof:placetype":"venue"
},
  "geometry": {"coordinates":[145.03599548299999,-37.8525428772],"type":"Point"}
}