{
  "type": "Feature",
  "properties": {
    "addr:full":"78 Grove Ave Narwee NSW 2209",
    "addr:housenumber":"78",
    "addr:postcode":"2209",
    "addr:street":"Grove Ave",
    "iso:country":"AU",
    "sg:address":"78 Grove Ave",
    "sg:city":"Narwee",
    "sg:classifiers":[
        {
            "category":"Professional",
            "subcategory":"Business Services",
            "type":"Services"
        }
    ],
    "sg:phone":"+61 2 9533 8470",
    "sg:postcode":"2209",
    "sg:province":"NSW",
    "sg:tags":[
        "drafting"
    ],
    "wof:name":"P.A. Romeos & Associates",
    "wof:placetype":"venue"
},
  "geometry": {"coordinates":[151.06572,-33.942158],"type":"Point"}
}