{
  "type": "Feature",
  "properties": {
    "addr:full":"1 Keys St Frankston VIC 3199",
    "addr:housenumber":"1",
    "addr:postcode":"3199",
    "addr:street":"Keys St",
    "iso:country":"AU",
    "sg:address":"1 Keys St",
    "sg:city":"Frankston",
    "sg:classifiers":[
        {
            "category":"Recreation",
            "type":"Entertainment"
        }
    ],
    "sg:phone":"+61 3 9770 0144",
    "sg:postcode":"3199",
    "sg:province":"VIC",
    "sg:tags":[
        "supply",
        "outdoor",
        "adventure",
        "activity"
    ],
    "wof:name":"Mitchells Adventure",
    "wof:placetype":"venue"
},
  "geometry": {"coordinates":[145.04165649399999,-37.9922599792],"type":"Point"}
}