{
  "type": "Feature",
  "properties": {
    "addr:full":"Cnr Griffith & New England Hwy Toowoomba QLD 4350",
    "addr:postcode":"4350",
    "addr:street":"Cnr;Hwy",
    "iso:country":"AU",
    "sg:address":"Cnr Griffith & New England Hwy",
    "sg:city":"Toowoomba",
    "sg:classifiers":[
        {
            "category":"Fast Food",
            "type":"Food & Drink"
        }
    ],
    "sg:phone":"+61 7 4638 0244",
    "sg:postcode":"4350",
    "sg:province":"QLD",
    "sg:tags":[
        "away",
        "take"
    ],
    "wof:name":"Red Rooster (Toowoomba)",
    "wof:placetype":"venue"
},
  "geometry": {"coordinates":[151.957458,-27.529217],"type":"Point"}
}