{
  "type": "Feature",
  "properties": {
    "iso:country":"AU",
    "sg:address":"34 Kelly St",
    "sg:city":"Beveridge",
    "sg:classifiers":[
        {
            "category":"Building & Trades",
            "subcategory":"Construction",
            "type":"Services"
        }
    ],
    "sg:phone":"+61 418 567 226",
    "sg:postcode":"3753",
    "sg:province":"VIC",
    "sg:tags":[
        "earth",
        "excavating",
        "moving",
        "contractor"
    ],
    "wof:name":"Lockley Lane Pty Ltd",
    "wof:placetype":"venue"
},
  "geometry": {"coordinates":[144.977783,-37.478622],"type":"Point"}
}