{
  "type": "Feature",
  "properties": {
    "addr:full":"1 Pandanus Ave Eagle Farm QLD 4009",
    "addr:housenumber":"1",
    "addr:postcode":"4009",
    "addr:street":"Pandanus Ave",
    "iso:country":"AU",
    "sg:address":"1 Pandanus Ave",
    "sg:city":"Eagle Farm",
    "sg:classifiers":[
        {
            "category":"Airline",
            "type":"Transportation"
        }
    ],
    "sg:phone":"+61 7 3860 8237",
    "sg:postcode":"4009",
    "sg:province":"QLD",
    "sg:tags":[
        "aircraft",
        "rental",
        "charter"
    ],
    "wof:name":"National Jet Systems Group Pty Ltd",
    "wof:placetype":"venue"
},
  "geometry": {"coordinates":[153.12875366200001,-27.4015922546],"type":"Point"}
}