{
  "type": "Feature",
  "properties": {
    "iso:country":"AU",
    "sg:address":"Quattromani Rd",
    "sg:city":"Eton",
    "sg:classifiers":[
        {
            "category":"Farming",
            "subcategory":"Farm",
            "type":"Manufacturing & Wholesale Goods"
        }
    ],
    "sg:phone":"+61 7 4954 1144",
    "sg:postcode":"4741",
    "sg:province":"QLD",
    "sg:tags":[
        "farmer"
    ],
    "wof:name":"Quattromani DC & CA",
    "wof:placetype":"venue"
},
  "geometry": {"coordinates":[148.971619,-21.26549],"type":"Point"}
}