{
  "type": "Feature",
  "properties": {
    "addr:full":"Bowral St Bowral NSW 2576",
    "addr:postcode":"2576",
    "addr:street":"Bowral St",
    "iso:country":"AU",
    "sg:address":"Bowral St",
    "sg:city":"Bowral",
    "sg:classifiers":[
        {
            "category":"Home & Garden",
            "subcategory":"Building Materials",
            "type":"Retail Goods"
        }
    ],
    "sg:phone":"+61 2 4861 1266",
    "sg:postcode":"2576",
    "sg:province":"NSW",
    "sg:tags":[
        "pre-mixed",
        "concrete"
    ],
    "wof:name":"Readymix",
    "wof:placetype":"venue"
},
  "geometry": {"coordinates":[150.413574219,-34.4828948975],"type":"Point"}
}