{
  "type": "Feature",
  "properties": {
    "addr:full":"46 Kidman Ave Belmont VIC 3216",
    "addr:housenumber":"46",
    "addr:postcode":"3216",
    "addr:street":"Kidman Ave",
    "iso:country":"AU",
    "sg:address":"46 Kidman Ave",
    "sg:city":"Belmont",
    "sg:classifiers":[
        {
            "category":"Retail",
            "subcategory":"Laundry & Dry Cleaning",
            "type":"Services"
        }
    ],
    "sg:phone":"+61 3 5244 2995",
    "sg:postcode":"3216",
    "sg:province":"VIC",
    "sg:tags":[
        "manicurist"
    ],
    "wof:name":"Special Effects",
    "wof:placetype":"venue"
},
  "geometry": {"coordinates":[144.34129333499999,-38.1852836609],"type":"Point"}
}