{
  "type": "Feature",
  "properties": {
    "addr:full":"Lot 4 Wallamore Rd Tamworth NSW 2340",
    "addr:postcode":"2340",
    "addr:street":"Wallamore Rd",
    "iso:country":"AU",
    "sg:address":"Lot 4 Wallamore Rd",
    "sg:city":"Tamworth",
    "sg:classifiers":[
        {
            "category":"Building & Trades",
            "subcategory":"Equipment Rental",
            "type":"Services"
        }
    ],
    "sg:phone":"+61 2 6761 5743",
    "sg:postcode":"2340",
    "sg:province":"NSW",
    "sg:tags":[
        "demolition",
        "contractor"
    ],
    "wof:name":"R & M Drain Earthmoving",
    "wof:placetype":"venue"
},
  "geometry": {"coordinates":[150.87254333499999,-31.0801734924],"type":"Point"}
}