{
  "type": "Feature",
  "properties": {
    "iso:country":"AU",
    "sg:address":"2 Railway Pde",
    "sg:city":"Belmore",
    "sg:classifiers":[
        {
            "category":"Home & Garden",
            "subcategory":"Building Materials",
            "type":"Retail Goods"
        }
    ],
    "sg:phone":"+61 425 362 368",
    "sg:postcode":"2192",
    "sg:province":"NSW",
    "sg:tags":[
        "lawn",
        "cutting",
        "maintenance"
    ],
    "wof:name":"24/7 Lawn Mowing & Garden Care",
    "wof:placetype":"venue"
},
  "geometry": {"coordinates":[151.085114,-33.91721],"type":"Point"}
}