{
  "type": "Feature",
  "properties": {
    "addr:full":"78 Harris Rd Klemzig SA 5087",
    "addr:housenumber":"78",
    "addr:postcode":"5087",
    "addr:street":"Harris Rd",
    "iso:country":"AU",
    "sg:address":"78 Harris Rd",
    "sg:city":"Klemzig",
    "sg:classifiers":[
        {
            "category":"Professional",
            "subcategory":"Art Services",
            "type":"Services"
        }
    ],
    "sg:phone":"+61 8 8261 9258",
    "sg:postcode":"5087",
    "sg:province":"SA",
    "sg:tags":[
        "graphic",
        "designer"
    ],
    "wof:name":"Thiel Graphix",
    "wof:placetype":"venue"
},
  "geometry": {"coordinates":[138.6353302,-34.8835372925],"type":"Point"}
}