{
  "type": "Feature",
  "properties": {
    "iso:country":"AU",
    "sg:address":"McArthur House 8",
    "sg:city":"Melville Parramatta",
    "sg:classifiers":[
        {
            "category":"Professional",
            "subcategory":"Detective & Security Services",
            "type":"Services"
        }
    ],
    "sg:phone":"+61 2 9890 6915",
    "sg:postcode":"2150",
    "sg:province":"NSW",
    "sg:tags":[
        "consultant",
        "system"
    ],
    "wof:name":"Keri (Australia) Pty Ltd",
    "wof:placetype":"venue"
},
  "geometry": {"coordinates":[151.09898376500001,-33.8074378967],"type":"Point"}
}