{
  "type": "Feature",
  "properties": {
    "addr:full":"Shop 18 Cnr Down Rd & North Tce North Ipswich QLD 4305",
    "addr:housenumber":"shop 18",
    "addr:postcode":"4305",
    "addr:street":"Cnr Down Rd & North Tce",
    "iso:country":"AU",
    "sg:address":"Shop 18 Cnr Down Rd",
    "sg:city":"& North Tce North Ipswich",
    "sg:classifiers":[
        {
            "category":"Travel",
            "subcategory":"Travel Agent",
            "type":"Entertainment"
        }
    ],
    "sg:phone":"+61 13 18 66",
    "sg:postcode":"4305",
    "sg:province":"QLD",
    "sg:tags":[
        "consultant"
    ],
    "wof:name":"Flight Centre",
    "wof:placetype":"venue"
},
  "geometry": {"coordinates":[152.76356506400001,-27.5974407196],"type":"Point"}
}