{
  "type": "Feature",
  "properties": {
    "iso:country":"AU",
    "sg:address":"PO Box 52",
    "sg:city":"Fyshwick",
    "sg:classifiers":[
        {
            "category":"Building & Trades",
            "subcategory":"Plumbing",
            "type":"Services"
        }
    ],
    "sg:phone":"+61 418 486 900",
    "sg:postcode":"2609",
    "sg:province":"ACT",
    "sg:tags":[
        "plumber",
        "gasfitters"
    ],
    "wof:name":"Four &#034;A&#034; Pty Ltd",
    "wof:placetype":"venue"
},
  "geometry": {"coordinates":[149.17616272000001,-35.3273696899],"type":"Point"}
}