{
  "type": "Feature",
  "properties": {
    "addr:full":"Great Northern Hwy Fitzroy Crossing WA 6765",
    "addr:postcode":"6765",
    "addr:street":"Northern Hwy",
    "iso:country":"AU",
    "sg:address":"Great Northern Hwy",
    "sg:city":"Fitzroy Crossing",
    "sg:classifiers":[
        {
            "category":"Travel",
            "subcategory":"Hotels & Motels",
            "type":"Entertainment"
        }
    ],
    "sg:phone":"+61 8 9191 5141",
    "sg:postcode":"6765",
    "sg:province":"WA",
    "wof:name":"Fitzroy River Lodge",
    "wof:placetype":"venue"
},
  "geometry": {"coordinates":[125.56672668500001,-18.1976032257],"type":"Point"}
}