{
  "type": "Feature",
  "properties": {
    "addr:full":"Mona Vale Hospital Coronation St Mona Vale NSW 2103",
    "addr:postcode":"2103",
    "addr:street":"Coronation St",
    "iso:country":"AU",
    "sg:address":"Mona Vale Hospital Coronation St",
    "sg:city":"Mona Vale",
    "sg:classifiers":[
        {
            "category":"Health Services",
            "subcategory":"Doctor",
            "type":"Services"
        }
    ],
    "sg:phone":"+61 2 9998 0555",
    "sg:postcode":"2103",
    "sg:province":"NSW",
    "sg:tags":[
        "nurse",
        "nursing"
    ],
    "wof:name":"Northern Sydney Home Nursing Service - Mona Vale",
    "wof:placetype":"venue"
},
  "geometry": {"coordinates":[151.30690002399999,-33.6866416931],"type":"Point"}
}