{
  "type": "Feature",
  "properties": {
    "addr:full":"226 Commercial St East Mt Gambier SA 5290",
    "addr:housenumber":"226",
    "addr:postcode":"5290",
    "addr:street":"Commercial St East Mt",
    "iso:country":"AU",
    "sg:address":"226 Commercial St East",
    "sg:city":"Mt Gambier",
    "sg:classifiers":[
        {
            "category":"Government",
            "subcategory":"Post Office",
            "type":"Public Place"
        }
    ],
    "sg:phone":"+61 8 8725 2049",
    "sg:postcode":"5290",
    "sg:province":"SA",
    "sg:tags":[
        "postal"
    ],
    "wof:name":"Australia Post",
    "wof:placetype":"venue"
},
  "geometry": {"coordinates":[140.79856899999999,-37.834236],"type":"Point"}
}