{
  "type": "Feature",
  "properties": {
    "iso:country":"AU",
    "sg:address":"12 Florence St",
    "sg:city":"Hornsby",
    "sg:classifiers":[
        {
            "category":"Manufacturing",
            "subcategory":"Food",
            "type":"Manufacturing & Wholesale Goods"
        }
    ],
    "sg:phone":"+61 2 9482 4249",
    "sg:postcode":"2077",
    "sg:province":"NSW",
    "sg:tags":[
        "function",
        "catering"
    ],
    "wof:name":"Adam's Rip Roaring Spit Roast",
    "wof:placetype":"venue"
},
  "geometry": {"coordinates":[151.09992980999999,-33.7040061951],"type":"Point"}
}