{
  "type": "Feature",
  "properties": {
    "addr:full":"189 Liverpool Rd Ashfield NSW 2131",
    "addr:housenumber":"189",
    "addr:postcode":"2131",
    "addr:street":"Liverpool Rd",
    "iso:country":"AU",
    "sg:address":"189 Liverpool Rd",
    "sg:city":"Ashfield",
    "sg:classifiers":[
        {
            "category":"Shopping",
            "subcategory":"Beauty & Cosmetics",
            "type":"Retail Goods"
        }
    ],
    "sg:phone":"+61 2 9798 4333",
    "sg:postcode":"2131",
    "sg:province":"NSW",
    "sg:tags":[
        "equipment",
        "salon",
        "supply"
    ],
    "wof:name":"Ashfield Suntronic Centre",
    "wof:placetype":"venue"
},
  "geometry": {"coordinates":[151.12701415999999,-33.8897514343],"type":"Point"}
}