{
  "type": "Feature",
  "properties": {
    "addr:full":"6 Farnham Ave Mulgrave VIC 3170",
    "addr:housenumber":"6",
    "addr:postcode":"3170",
    "addr:street":"Farnham Ave",
    "iso:country":"AU",
    "sg:address":"6 Farnham Ave",
    "sg:city":"Mulgrave",
    "sg:classifiers":[
        {
            "category":"Education",
            "subcategory":"Kindergarten",
            "type":"Public Place"
        }
    ],
    "sg:phone":"+61 3 9560 2791",
    "sg:postcode":"3170",
    "sg:province":"VIC",
    "sg:tags":[
        "pre-schools"
    ],
    "wof:name":"Waverley Meadows Pre-School",
    "wof:placetype":"venue"
},
  "geometry": {"coordinates":[145.174362183,-37.9118766785],"type":"Point"}
}