{
  "type": "Feature",
  "properties": {
    "addr:full":"26 Yanko Rd Pymble NSW 2073",
    "addr:housenumber":"26",
    "addr:postcode":"2073",
    "addr:street":"Yanko Rd",
    "iso:country":"AU",
    "sg:address":"26 Yanko Rd",
    "sg:city":"Pymble",
    "sg:classifiers":[
        {
            "category":"Professional",
            "subcategory":"Art Services",
            "type":"Services"
        }
    ],
    "sg:phone":"+61 2 9498 5027",
    "sg:postcode":"2073",
    "sg:province":"NSW",
    "sg:tags":[
        "decorator",
        "painter"
    ],
    "wof:name":"A Premium Painting",
    "wof:placetype":"venue"
},
  "geometry": {"coordinates":[151.13287353499999,-33.766494751],"type":"Point"}
}