{
  "type": "Feature",
  "properties": {
    "iso:country":"AU",
    "sg:address":"77 Main St",
    "sg:city":"Nairne",
    "sg:classifiers":[
        {
            "category":"Travel",
            "subcategory":"Hotels & Motels",
            "type":"Entertainment"
        }
    ],
    "sg:phone":"+61 8 8388 6228",
    "sg:postcode":"5252",
    "sg:province":"SA",
    "sg:tags":[
        "pub"
    ],
    "wof:name":"District Hotel",
    "wof:placetype":"venue"
},
  "geometry": {"coordinates":[138.912307739,-35.0357704163],"type":"Point"}
}