{
  "type": "Feature",
  "properties": {
    "addr:full":"31 Lensworth St Coopers Plains QLD 4108",
    "addr:housenumber":"31",
    "addr:postcode":"4108",
    "addr:street":"Lensworth St",
    "iso:country":"AU",
    "sg:address":"31 Lensworth St",
    "sg:city":"Coopers Plains",
    "sg:classifiers":[
        {
            "category":"Wholesale",
            "subcategory":"Machinery & Supplies",
            "type":"Manufacturing & Wholesale Goods"
        }
    ],
    "sg:phone":"+61 7 3347 0560",
    "sg:postcode":"4108",
    "sg:province":"QLD",
    "sg:tags":[
        "equipment",
        "welding"
    ],
    "wof:name":"Sandvik Australia Pty Limited",
    "wof:placetype":"venue"
},
  "geometry": {"coordinates":[153.03485107399999,-27.5721473694],"type":"Point"}
}