{
  "type": "Feature",
  "properties": {
    "addr:full":"150 Eastleigh Pl Mt Helena WA 6082",
    "addr:housenumber":"150",
    "addr:postcode":"6082",
    "addr:street":"Eastleigh Pl",
    "iso:country":"AU",
    "sg:address":"150 Eastleigh Pl",
    "sg:city":"Mt Helena",
    "sg:classifiers":[
        {
            "category":"Landmark",
            "subcategory":"City Walls",
            "type":"Public Place"
        }
    ],
    "sg:phone":"+61 8 9572 2767",
    "sg:postcode":"6082",
    "sg:province":"WA",
    "sg:tags":[
        "finish"
    ],
    "wof:name":"All Dec Ceiling & Wall Specialists",
    "wof:placetype":"venue"
},
  "geometry": {"coordinates":[116.21671295199999,-31.8670825958],"type":"Point"}
}