{
  "type": "Feature",
  "properties": {
    "iso:country":"AU",
    "sg:address":"4 Constable St",
    "sg:city":"Gingin",
    "sg:classifiers":[
        {
            "category":"Banks & Credit Unions",
            "subcategory":"Bank",
            "type":"Services"
        }
    ],
    "sg:phone":"+61 13 20 32",
    "sg:postcode":"6503",
    "sg:province":"WA",
    "wof:name":"Westpac",
    "wof:placetype":"venue"
},
  "geometry": {"coordinates":[115.904831,-31.34622],"type":"Point"}
}