{
  "type": "Feature",
  "properties": {
    "addr:full":"Shop 4 Head st Shopng Cntr Alice Springs NT 0871",
    "addr:housenumber":"shop 4",
    "addr:postcode":"nt 0871",
    "addr:street":"Head St Shopng Cntr",
    "iso:country":"AU",
    "sg:address":"Shop 4",
    "sg:city":"Head st Shopng Cntr Alice Springs",
    "sg:classifiers":[
        {
            "category":"Professional",
            "subcategory":"Accounting & Tax Preparation",
            "type":"Services"
        }
    ],
    "sg:phone":"+61 8 8952 2647",
    "sg:postcode":"0871",
    "sg:province":"NT",
    "sg:tags":[
        "bookkeeping"
    ],
    "wof:name":"Centre Accounting Services",
    "wof:placetype":"venue"
},
  "geometry": {"coordinates":[133.87309265100001,-23.6807918549],"type":"Point"}
}