{
  "type": "Feature",
  "properties": {
    "iso:country":"AU",
    "sg:address":"462 Warral Rd",
    "sg:city":"Tamworth",
    "sg:classifiers":[
        {
            "category":"Professional",
            "subcategory":"Detective & Security Services",
            "type":"Services"
        }
    ],
    "sg:phone":"+61 2 6762 4674",
    "sg:postcode":"2340",
    "sg:province":"NSW",
    "sg:tags":[
        "consultant",
        "system"
    ],
    "wof:name":"J.C-S Big Country Security",
    "wof:placetype":"venue"
},
  "geometry": {"coordinates":[150.87399292000001,-31.1485748291],"type":"Point"}
}