{
  "type": "Feature",
  "properties": {
    "addr:full":"16 Tipperary Ave Killarney Heights NSW 2087",
    "addr:housenumber":"16",
    "addr:postcode":"2087",
    "addr:street":"Tipperary Ave",
    "iso:country":"AU",
    "sg:address":"16 Tipperary Ave",
    "sg:city":"Killarney Heights",
    "sg:classifiers":[
        {
            "category":"Social Services",
            "type":"Services"
        }
    ],
    "sg:phone":"+61 2 9975 1460",
    "sg:postcode":"2087",
    "sg:province":"NSW",
    "sg:tags":[
        "kinesiology"
    ],
    "wof:name":"Self Centred Kinesiology",
    "wof:placetype":"venue"
},
  "geometry": {"coordinates":[151.22300720199999,-33.7727928162],"type":"Point"}
}