{
  "type": "Feature",
  "properties": {
    "addr:full":"187 Kendal St Cowra NSW 2794",
    "addr:housenumber":"187",
    "addr:postcode":"2794",
    "addr:street":"Kendal St",
    "iso:country":"AU",
    "sg:address":"187 Kendal St",
    "sg:city":"Cowra",
    "sg:classifiers":[
        {
            "category":"Autos & Motor Vehicles",
            "subcategory":"Automobile Sales",
            "type":"Retail Goods"
        }
    ],
    "sg:phone":"+61 2 6342 1889",
    "sg:postcode":"2794",
    "sg:province":"NSW",
    "sg:tags":[
        "car",
        "new"
    ],
    "wof:name":"WD O&#039;Connell Auto Co.",
    "wof:placetype":"venue"
},
  "geometry": {"coordinates":[148.696990967,-33.8356132507],"type":"Point"}
}