{
  "type": "Feature",
  "properties": {
    "addr:full":"13 Croydon Rd Keswick SA 5035",
    "addr:housenumber":"13",
    "addr:postcode":"5035",
    "addr:street":"Croydon Rd",
    "iso:country":"AU",
    "sg:address":"13 Croydon Rd",
    "sg:city":"Keswick",
    "sg:classifiers":[
        {
            "category":"Utilities",
            "subcategory":"Water",
            "type":"Services"
        }
    ],
    "sg:phone":"+61 8 8297 4099",
    "sg:postcode":"5035",
    "sg:province":"SA",
    "sg:tags":[
        "equipment",
        "treatment"
    ],
    "wof:name":"Hydro-Chem",
    "wof:placetype":"venue"
},
  "geometry": {"coordinates":[138.57844543499999,-34.9433898926],"type":"Point"}
}