{
  "type": "Feature",
  "properties": {
    "iso:country":"AU",
    "sg:address":"185 Ramsgate Rd",
    "sg:city":"Ramsgate",
    "sg:classifiers":[
        {
            "category":"Real Estate",
            "subcategory":"Real Estate Agent",
            "type":"Services"
        }
    ],
    "sg:phone":"+61 2 9529 0111",
    "sg:postcode":"2217",
    "sg:province":"NSW",
    "wof:name":"Professionals Ramsgate Sydney Home",
    "wof:placetype":"venue"
},
  "geometry": {"coordinates":[151.143936,-33.985733],"type":"Point"}
}