{
  "type": "Feature",
  "properties": {
    "addr:full":"PO Box 261 Waratah NSW 2298",
    "addr:postcode":"2298",
    "iso:country":"AU",
    "sg:address":"PO Box 261",
    "sg:city":"Waratah",
    "sg:classifiers":[
        {
            "category":"Home & Garden",
            "subcategory":"Carpets & Floor Coverings",
            "type":"Retail Goods"
        }
    ],
    "sg:phone":"+61 412 688 048",
    "sg:postcode":"2298",
    "sg:province":"NSW",
    "wof:name":"AWS Property Maintenance",
    "wof:placetype":"venue"
},
  "geometry": {"coordinates":[151.722854614,-32.904209137],"type":"Point"}
}