{
  "type": "Feature",
  "properties": {
    "addr:full":"720 Nicholson St Fitzroy North VIC 3068",
    "addr:housenumber":"720",
    "addr:postcode":"3068",
    "addr:street":"Nicholson St",
    "iso:country":"AU",
    "sg:address":"720 Nicholson St",
    "sg:city":"Fitzroy North",
    "sg:classifiers":[
        {
            "category":"Education",
            "subcategory":"Dance Studio",
            "type":"Public Place"
        }
    ],
    "sg:phone":"+61 3 9855 0044",
    "sg:postcode":"3068",
    "sg:province":"VIC",
    "sg:tags":[
        "instruction",
        "language"
    ],
    "wof:name":"Lyceum Language Centre.",
    "wof:placetype":"venue"
},
  "geometry": {"coordinates":[144.97792053200001,-37.7825622559],"type":"Point"}
}