{
  "type": "Feature",
  "properties": {
    "addr:full":"268 Dundas St Thornbury VIC 3071",
    "addr:housenumber":"268",
    "addr:postcode":"3071",
    "addr:street":"Dundas St",
    "iso:country":"AU",
    "sg:address":"268 Dundas St",
    "sg:city":"Thornbury",
    "sg:classifiers":[
        {
            "category":"Shopping",
            "type":"Retail Goods"
        }
    ],
    "sg:phone":"+61 3 9480 0157",
    "sg:postcode":"3071",
    "sg:province":"VIC",
    "sg:tags":[
        "product",
        "plastic"
    ],
    "wof:name":"Plastic Pak",
    "wof:placetype":"venue"
},
  "geometry": {"coordinates":[145.027877808,-37.7553100586],"type":"Point"}
}