{
  "type": "Feature",
  "properties": {
    "addr:full":"212 Latrobe St Melbourne VIC 3000",
    "addr:housenumber":"212",
    "addr:postcode":"3000",
    "addr:street":"Latrobe St",
    "iso:country":"AU",
    "sg:address":"212 Latrobe St",
    "sg:city":"Melbourne",
    "sg:classifiers":[
        {
            "category":"Structure",
            "subcategory":"Office Building",
            "type":"Public Place"
        }
    ],
    "sg:phone":"+61 3 9667 0224",
    "sg:postcode":"3000",
    "sg:province":"VIC",
    "sg:tags":[
        "serviced"
    ],
    "wof:name":"A Shared Office",
    "wof:placetype":"venue"
},
  "geometry": {"coordinates":[144.96330261200001,-37.8095932007],"type":"Point"}
}