{
  "type": "Feature",
  "properties": {
    "iso:country":"AU",
    "sg:address":"Shop 3, 205- 227 Main North Rd",
    "sg:city":"Clare",
    "sg:classifiers":[
        {
            "category":"Insurance",
            "subcategory":"Hazard Insurance",
            "type":"Services"
        }
    ],
    "sg:phone":"+61 8 8842 2231",
    "sg:postcode":"5453",
    "sg:province":"SA",
    "sg:tags":[
        "fire",
        "accident",
        "marine"
    ],
    "wof:name":"Alliance One Credit Union",
    "wof:placetype":"venue"
},
  "geometry": {"coordinates":[138.611374,-33.832756],"type":"Point"}
}