{
  "type": "Feature",
  "properties": {
    "iso:country":"AU",
    "sg:address":"32 Morphett Rd",
    "sg:city":"Novar Gardens",
    "sg:classifiers":[
        {
            "category":"Education",
            "subcategory":"School",
            "type":"Public Place"
        }
    ],
    "sg:phone":"+61 8 8294 3588",
    "sg:postcode":"5040",
    "sg:province":"SA",
    "wof:name":"Immanuel College",
    "wof:placetype":"venue"
},
  "geometry": {"coordinates":[138.53727699999999,-34.971371],"type":"Point"}
}