{
  "type": "Feature",
  "properties": {
    "addr:full":"Suite 9, 12- 14 Thelma St West Perth WA 6005",
    "addr:housenumber":"12 14",
    "addr:postcode":"6005",
    "addr:street":"Thelma St",
    "iso:country":"AU",
    "sg:address":"Suite 9, 12- 14 Thelma St",
    "sg:city":"West Perth",
    "sg:classifiers":[
        {
            "category":"Professional",
            "subcategory":"Engineering",
            "type":"Services"
        }
    ],
    "sg:phone":"+61 8 9481 8211",
    "sg:postcode":"6005",
    "sg:province":"WA",
    "sg:tags":[
        "consulting",
        "engineer"
    ],
    "wof:name":"Combined Resource Engineering",
    "wof:placetype":"venue"
},
  "geometry": {"coordinates":[115.843406677,-31.947303772],"type":"Point"}
}