{
  "type": "Feature",
  "properties": {
    "addr:full":"1 Fromhold Drv Doncaster VIC 3108",
    "addr:housenumber":"1",
    "addr:postcode":"3108",
    "addr:street":"Fromhold Drv",
    "iso:country":"AU",
    "sg:address":"1 Fromhold Drv",
    "sg:city":"Doncaster",
    "sg:classifiers":[
        {
            "category":"Health Services",
            "subcategory":"Health Practitioner",
            "type":"Services"
        }
    ],
    "sg:phone":"+61 3 9840 2554",
    "sg:postcode":"3108",
    "sg:province":"VIC",
    "sg:tags":[
        "naturopath"
    ],
    "wof:name":"Tsindos S",
    "wof:placetype":"venue"
},
  "geometry": {"coordinates":[145.13908386200001,-37.781375885],"type":"Point"}
}