{
  "type": "Feature",
  "properties": {
    "addr:full":"12 Cawarra Rd Caringbah NSW 2229",
    "addr:housenumber":"12",
    "addr:postcode":"2229",
    "addr:street":"Cawarra Rd",
    "iso:country":"AU",
    "sg:address":"12 Cawarra Rd",
    "sg:city":"Caringbah",
    "sg:classifiers":[
        {
            "category":"Wholesale",
            "subcategory":"Chemicals & Plastics",
            "type":"Manufacturing & Wholesale Goods"
        }
    ],
    "sg:phone":"+61 2 9527 8800",
    "sg:postcode":"2229",
    "sg:province":"NSW",
    "sg:tags":[
        "extruders"
    ],
    "wof:name":"Australian Plastic Profiles",
    "wof:placetype":"venue"
},
  "geometry": {"coordinates":[151.126495361,-34.0277175903],"type":"Point"}
}