{
  "type": "Feature",
  "properties": {
    "iso:country":"AU",
    "sg:address":"43 Cameron St",
    "sg:city":"Wauchope",
    "sg:classifiers":[
        {
            "category":"Professional",
            "subcategory":"Accounting & Tax Preparation",
            "type":"Services"
        }
    ],
    "sg:phone":"+61 2 6586 1120",
    "sg:postcode":"2446",
    "sg:province":"NSW",
    "sg:tags":[
        "consultant",
        "taxation"
    ],
    "wof:name":"Holiday Coast Business Partners",
    "wof:placetype":"venue"
},
  "geometry": {"coordinates":[152.73468,-31.456123],"type":"Point"}
}