{
  "type": "Feature",
  "properties": {
    "addr:full":"70- 72 Pym St Dudley Park SA 5008",
    "addr:housenumber":"72",
    "addr:postcode":"5008",
    "addr:street":"Pym St",
    "iso:country":"AU",
    "sg:address":"70- 72 Pym St",
    "sg:city":"Dudley Park",
    "sg:classifiers":[
        {
            "category":"Farming",
            "subcategory":"Crops",
            "type":"Manufacturing & Wholesale Goods"
        }
    ],
    "sg:phone":"+61 8 8342 1177",
    "sg:postcode":"5008",
    "sg:province":"SA",
    "sg:tags":[
        "warehousing"
    ],
    "wof:name":"Middleton's Distribution",
    "wof:placetype":"venue"
},
  "geometry": {"coordinates":[138.58084099999999,-34.881912],"type":"Point"}
}