{
  "type": "Feature",
  "properties": {
    "iso:country":"AU",
    "sg:address":"Cnr The Esplanade & King St",
    "sg:city":"Warners Bay",
    "sg:classifiers":[
        {
            "category":"Manufacturing",
            "subcategory":"Food",
            "type":"Manufacturing & Wholesale Goods"
        }
    ],
    "sg:phone":"+61 2 4947 1144",
    "sg:postcode":"2282",
    "sg:province":"NSW",
    "sg:tags":[
        "function",
        "catering"
    ],
    "wof:name":"Bay Views Catering",
    "wof:placetype":"venue"
},
  "geometry": {"coordinates":[151.64422607399999,-32.9743270874],"type":"Point"}
}