{
  "type": "Feature",
  "properties": {
    "iso:country":"AU",
    "sg:address":"113 Church St",
    "sg:city":"Wollongong",
    "sg:classifiers":[
        {
            "category":"Health Services",
            "subcategory":"Health Practitioner",
            "type":"Services"
        }
    ],
    "sg:phone":"+61 2 4229 4836",
    "sg:postcode":"2500",
    "sg:province":"NSW",
    "sg:tags":[
        "psychologist"
    ],
    "wof:name":"Leicester Sue Dr",
    "wof:placetype":"venue"
},
  "geometry": {"coordinates":[150.89485199999999,-34.427994],"type":"Point"}
}