{
  "type": "Feature",
  "properties": {
    "iso:country":"AU",
    "sg:address":"1015 South Gippsland Hwy",
    "sg:city":"Cranbourne",
    "sg:classifiers":[
        {
            "category":"Retail",
            "subcategory":"Auto Repair",
            "type":"Services"
        }
    ],
    "sg:phone":"+61 3 5991 4030",
    "sg:postcode":"3977",
    "sg:province":"VIC",
    "sg:tags":[
        "repairer",
        "motor",
        "engineer"
    ],
    "wof:name":"Cranbourne Service Centre",
    "wof:placetype":"venue"
},
  "geometry": {"coordinates":[145.27691650400001,-38.0827102661],"type":"Point"}
}