{
  "type": "Feature",
  "properties": {
    "addr:full":"217 Fitzgerald St Northam WA 6401",
    "addr:housenumber":"217",
    "addr:postcode":"6401",
    "addr:street":"Fitzgerald St",
    "iso:country":"AU",
    "sg:address":"217 Fitzgerald St",
    "sg:city":"Northam",
    "sg:classifiers":[
        {
            "category":"Food & Beverages",
            "subcategory":"Bakery",
            "type":"Retail Goods"
        }
    ],
    "sg:phone":"+61 8 9622 5272",
    "sg:postcode":"6401",
    "sg:province":"WA",
    "sg:tags":[
        "cake",
        "shop",
        "pastry"
    ],
    "wof:name":"Avon Valley Bakery",
    "wof:placetype":"venue"
},
  "geometry": {"coordinates":[116.670509338,-31.6547794342],"type":"Point"}
}