{
  "type": "Feature",
  "properties": {
    "addr:full":"Cnr James Ruse Drive & River Road West Rosehill NSW 2142",
    "addr:postcode":"2142",
    "addr:street":"Cnr James Ruse Drive & River Road West",
    "iso:country":"AU",
    "sg:address":"Cnr James Ruse Drive & River Road",
    "sg:city":"West Rosehill",
    "sg:classifiers":[
        {
            "category":"Government",
            "subcategory":"Department Of Motor Vehicles",
            "type":"Public Place"
        }
    ],
    "sg:phone":"+61 13 33 09",
    "sg:postcode":"2142",
    "sg:province":"NSW",
    "sg:tags":[
        "wholesaler",
        "mfrs",
        "accessory"
    ],
    "wof:name":"Central Parts",
    "wof:placetype":"venue"
},
  "geometry": {"coordinates":[151.021575928,-33.8221244812],"type":"Point"}
}