{
  "type": "Feature",
  "properties": {
    "addr:full":"94 Smith St Collingwood VIC 3066",
    "addr:housenumber":"94",
    "addr:postcode":"3066",
    "addr:street":"Smith St",
    "iso:country":"AU",
    "sg:address":"94 Smith St",
    "sg:city":"Collingwood",
    "sg:classifiers":[
        {
            "category":"Organizations",
            "subcategory":"Community Association",
            "type":"Services"
        }
    ],
    "sg:phone":"+61 423 123 909",
    "sg:postcode":"3066",
    "sg:province":"VIC",
    "sg:tags":[
        "shiatsu",
        "therapy"
    ],
    "wof:name":"Rowena Charnley Shiatsu",
    "wof:placetype":"venue"
},
  "geometry": {"coordinates":[144.98330688499999,-37.8055114746],"type":"Point"}
}