{
  "type": "Feature",
  "properties": {
    "iso:country":"AU",
    "sg:address":"Shop 12/ 49 Wattle Valley Drv",
    "sg:city":"Hillside",
    "sg:classifiers":[
        {
            "category":"Personal",
            "subcategory":"Beauty Salon",
            "type":"Services"
        }
    ],
    "sg:phone":"+61 3 9449 8338",
    "sg:postcode":"3037",
    "sg:province":"VIC",
    "sg:tags":[
        "hairdresser"
    ],
    "wof:name":"The Groom Room",
    "wof:placetype":"venue"
},
  "geometry": {"coordinates":[144.741562,-37.686214],"type":"Point"}
}