{
  "type": "Feature",
  "properties": {
    "addr:full":"1 Roberts St West Osborne Park WA 6017",
    "addr:housenumber":"1",
    "addr:postcode":"6017",
    "addr:street":"Roberts St West",
    "iso:country":"AU",
    "sg:address":"1 Roberts St",
    "sg:city":"West Osborne Park",
    "sg:classifiers":[
        {
            "category":"Wholesale",
            "subcategory":"Machinery & Supplies",
            "type":"Manufacturing & Wholesale Goods"
        }
    ],
    "sg:phone":"+61 8 9244 1850",
    "sg:postcode":"6017",
    "sg:province":"WA",
    "sg:tags":[
        "equipment",
        "welding"
    ],
    "sg:website":"http://www.weld.com.au",
    "wof:name":"Osborne Park Welding",
    "wof:placetype":"venue"
},
  "geometry": {"coordinates":[115.817771912,-31.9076366425],"type":"Point"}
}