{
  "type": "Feature",
  "properties": {
    "addr:full":"665 Anzac Pde Maroubra NSW 2035",
    "addr:housenumber":"665",
    "addr:postcode":"2035",
    "addr:street":"Anzac Pde",
    "iso:country":"AU",
    "sg:address":"665 Anzac Pde",
    "sg:city":"Maroubra",
    "sg:classifiers":[
        {
            "category":"Health Services",
            "subcategory":"Health Practitioner",
            "type":"Services"
        }
    ],
    "sg:phone":"+61 2 9344 3678",
    "sg:postcode":"2035",
    "sg:province":"NSW",
    "sg:tags":[
        "homoeopath"
    ],
    "wof:name":"Frances Sheffield",
    "wof:placetype":"venue"
},
  "geometry": {"coordinates":[151.23806762699999,-33.9378013611],"type":"Point"}
}