{
  "type": "Feature",
  "properties": {
    "iso:country":"AU",
    "sg:address":"356 Macquarie St",
    "sg:city":"South Hobart",
    "sg:classifiers":[
        {
            "category":"Cafe",
            "type":"Food & Drink"
        }
    ],
    "sg:phone":"+61 3 6224 6862",
    "sg:postcode":"7004",
    "sg:province":"TAS",
    "wof:name":"Macquarie Street Foodstore",
    "wof:placetype":"venue"
},
  "geometry": {"coordinates":[147.31597900400001,-42.8927536011],"type":"Point"}
}