{
  "type": "Feature",
  "properties": {
    "iso:country":"AU",
    "sg:address":"41 Broadarrow Rd",
    "sg:city":"Narwee",
    "sg:classifiers":[
        {
            "category":"Retail",
            "subcategory":"Auto Rental",
            "type":"Services"
        }
    ],
    "sg:phone":"+61 2 9153 8857",
    "sg:postcode":"2209",
    "sg:province":"NSW",
    "sg:tags":[
        "car",
        "hire",
        "minibus"
    ],
    "wof:name":"Exel Car Rental",
    "wof:placetype":"venue"
},
  "geometry": {"coordinates":[151.07032799999999,-33.948364],"type":"Point"}
}