{
  "type": "Feature",
  "properties": {
    "iso:country":"AU",
    "sg:address":"63 Henderson St",
    "sg:city":"Clayton North",
    "sg:classifiers":[
        {
            "category":"Retail",
            "subcategory":"Auto Repair",
            "type":"Services"
        }
    ],
    "sg:phone":"+61 3 9562 5000",
    "sg:postcode":"3168",
    "sg:province":"VIC",
    "sg:tags":[
        "testing",
        "inspection",
        "motor",
        "vehicle"
    ],
    "wof:name":"V.A.C.C.",
    "wof:placetype":"venue"
},
  "geometry": {"coordinates":[145.12176513700001,-37.914516449],"type":"Point"}
}