{
  "type": "Feature",
  "properties": {
    "iso:country":"AU",
    "sg:address":"5 Hardy St",
    "sg:city":"Bullcreek",
    "sg:classifiers":[
        {
            "category":"Professional",
            "subcategory":"Engineering",
            "type":"Services"
        }
    ],
    "sg:phone":"+61 8 9313 5557",
    "sg:postcode":"6149",
    "sg:province":"WA",
    "sg:tags":[
        "consulting",
        "engineer"
    ],
    "wof:name":"Gaete & Munoz Pty Ltd",
    "wof:placetype":"venue"
},
  "geometry": {"coordinates":[115.858658,-32.058029],"type":"Point"}
}