{
  "type": "Feature",
  "properties": {
    "addr:full":"Cnr Canning Hwy & Riseley St Applecross WA 6153",
    "addr:postcode":"6153",
    "addr:street":"Canning Hwy & Riseley St",
    "iso:country":"AU",
    "sg:address":"Cnr Canning Hwy & Riseley St",
    "sg:city":"Applecross",
    "sg:classifiers":[
        {
            "category":"Health Services",
            "subcategory":"Health Practitioner",
            "type":"Services"
        }
    ],
    "sg:phone":"+61 8 9316 1186",
    "sg:postcode":"6153",
    "sg:province":"WA",
    "sg:tags":[
        "physiotherapist"
    ],
    "wof:name":"Applecross Physiotherapy",
    "wof:placetype":"venue"
},
  "geometry": {"coordinates":[115.839996,-32.017002],"type":"Point"}
}