{
  "type": "Feature",
  "properties": {
    "addr:full":"Shop 1110 Westfield Galleria Collier Rd Morley WA 6062",
    "addr:housenumber":"1110",
    "addr:postcode":"6062",
    "addr:street":"Westfield Galleria Collier Rd",
    "iso:country":"AU",
    "sg:address":"Shop 1110 Westfield Galleria Collier Rd",
    "sg:city":"Morley",
    "sg:classifiers":[
        {
            "category":"Shopping",
            "subcategory":"Jewelry",
            "type":"Retail Goods"
        }
    ],
    "sg:phone":"+61 8 9276 6222",
    "sg:postcode":"6062",
    "sg:province":"WA",
    "sg:tags":[
        "jeweller"
    ],
    "wof:name":"Michael Hill Jeweller",
    "wof:placetype":"venue"
},
  "geometry": {"coordinates":[115.90247345,-31.894908905],"type":"Point"}
}