{
  "type": "Feature",
  "properties": {
    "addr:full":"139 Ormond Rd Elwood VIC 3184",
    "addr:housenumber":"139",
    "addr:postcode":"3184",
    "addr:street":"Ormond Rd",
    "iso:country":"AU",
    "sg:address":"139 Ormond Rd",
    "sg:city":"Elwood",
    "sg:classifiers":[
        {
            "category":"Health Services",
            "subcategory":"Doctor",
            "type":"Services"
        }
    ],
    "sg:phone":"+61 3 9531 8911",
    "sg:postcode":"3184",
    "sg:province":"VIC",
    "sg:tags":[
        "occupational",
        "safety"
    ],
    "sg:website":"http://www.noisemanagement.com.au",
    "wof:name":"Hearing Conservation Services Of Australia Pty Ltd (Trading As Noise Management",
    "wof:placetype":"venue"
},
  "geometry": {"coordinates":[144.98870849599999,-37.8858757019],"type":"Point"}
}