{
  "type": "Feature",
  "properties": {
    "addr:full":"59 Edward St Osborne Park WA 6017",
    "addr:housenumber":"59",
    "addr:postcode":"6017",
    "addr:street":"Edward St",
    "iso:country":"AU",
    "sg:address":"59 Edward St",
    "sg:city":"Osborne Park",
    "sg:classifiers":[
        {
            "category":"Shopping",
            "subcategory":"Clothing, Apparel, & Fashions",
            "type":"Retail Goods"
        }
    ],
    "sg:phone":"+61 8 9443 3364",
    "sg:postcode":"6017",
    "sg:province":"WA",
    "sg:tags":[
        "recycled",
        "clothing"
    ],
    "wof:name":"Vinnies Retail Centres",
    "wof:placetype":"venue"
},
  "geometry": {"coordinates":[115.82673645,-31.9015960693],"type":"Point"}
}