{
  "type": "Feature",
  "properties": {
    "iso:country":"AU",
    "sg:address":"Hall Gallery 105 Swan St",
    "sg:city":"Guildford",
    "sg:classifiers":[
        {
            "category":"Professional",
            "subcategory":"Art Services",
            "type":"Services"
        }
    ],
    "sg:phone":"+61 8 9279 7033",
    "sg:postcode":"6055",
    "sg:province":"WA",
    "sg:tags":[
        "interior",
        "decorator"
    ],
    "wof:name":"MWDesign",
    "wof:placetype":"venue"
},
  "geometry": {"coordinates":[115.969353,-31.897156],"type":"Point"}
}