{
  "type": "Feature",
  "properties": {
    "addr:full":"Barrack St Jetty Perth WA 6000",
    "addr:postcode":"6000",
    "addr:street":"Barrack St Jetty",
    "iso:country":"AU",
    "sg:address":"Barrack St Jetty",
    "sg:city":"Perth",
    "sg:classifiers":[
        {
            "category":"Ice Cream",
            "type":"Food & Drink"
        }
    ],
    "sg:phone":"+61 8 9221 1638",
    "sg:postcode":"6000",
    "sg:province":"WA",
    "sg:tags":[
        "retail"
    ],
    "wof:name":"Old Perth Port Ice Cream Kiosk",
    "wof:placetype":"venue"
},
  "geometry": {"coordinates":[115.859107971,-31.9571228027],"type":"Point"}
}