{
  "type": "Feature",
  "properties": {
    "addr:full":"104 Conway St Lismore NSW 2480",
    "addr:housenumber":"104",
    "addr:postcode":"2480",
    "addr:street":"Conway St",
    "iso:country":"AU",
    "sg:address":"104 Conway St",
    "sg:city":"Lismore",
    "sg:classifiers":[
        {
            "category":"Banks & Credit Unions",
            "subcategory":"Financial Services",
            "type":"Services"
        }
    ],
    "sg:phone":"+61 2 6621 9488",
    "sg:postcode":"2480",
    "sg:province":"NSW",
    "sg:tags":[
        "planning"
    ],
    "wof:name":"Conways & Co",
    "wof:placetype":"venue"
},
  "geometry": {"coordinates":[153.28216552699999,-28.8143672943],"type":"Point"}
}