{
  "type": "Feature",
  "properties": {
    "addr:full":"24 Brooks Drv Mildura VIC 3500",
    "addr:housenumber":"24",
    "addr:postcode":"3500",
    "addr:street":"Brooks Drv",
    "iso:country":"AU",
    "sg:address":"24 Brooks Drv",
    "sg:city":"Mildura",
    "sg:classifiers":[
        {
            "category":"Retail",
            "subcategory":"Repair Shop",
            "type":"Services"
        }
    ],
    "sg:phone":"+61 427 248 932",
    "sg:postcode":"3500",
    "sg:province":"VIC",
    "sg:tags":[
        "repairing",
        "piano",
        "tuning"
    ],
    "wof:name":"Quennell Geoff",
    "wof:placetype":"venue"
},
  "geometry": {"coordinates":[142.13560485799999,-34.2048721313],"type":"Point"}
}