{
  "type": "Feature",
  "properties": {
    "addr:full":"Level 1, 73 High St Belmont VIC 3216",
    "addr:housenumber":"73",
    "addr:postcode":"3216",
    "addr:street":"High St",
    "iso:country":"AU",
    "sg:address":"Level 1, 73 High St",
    "sg:city":"Belmont",
    "sg:classifiers":[
        {
            "category":"Health Services",
            "subcategory":"Dentist",
            "type":"Services"
        }
    ],
    "sg:phone":"+61 3 5243 9111",
    "sg:postcode":"3216",
    "sg:province":"VIC",
    "wof:name":"Van Den Berg James",
    "wof:placetype":"venue"
},
  "geometry": {"coordinates":[144.34715270999999,-38.1710891724],"type":"Point"}
}