{
  "type": "Feature",
  "properties": {
    "iso:country":"AU",
    "sg:address":"800 Zillmere Rd",
    "sg:city":"Aspley",
    "sg:classifiers":[
        {
            "category":"Banks & Credit Unions",
            "subcategory":"Investment Brokerage",
            "type":"Services"
        }
    ],
    "sg:phone":"+61 7 3863 9435",
    "sg:postcode":"4034",
    "sg:province":"QLD",
    "sg:tags":[
        "finance",
        "broker"
    ],
    "wof:name":"Complete Finance Brisbane",
    "wof:placetype":"venue"
},
  "geometry": {"coordinates":[153.01709,-27.356403],"type":"Point"}
}