{
  "type": "Feature",
  "properties": {
    "iso:country":"AU",
    "sg:address":"500 Beaufort St",
    "sg:city":"Mt Lawley",
    "sg:classifiers":[
        {
            "category":"Cafe",
            "type":"Food & Drink"
        }
    ],
    "sg:phone":"+61 8 9227 6991",
    "sg:postcode":"6050",
    "sg:province":"WA",
    "wof:name":"Siena's Pizzeria & Caffe",
    "wof:placetype":"venue"
},
  "geometry": {"coordinates":[115.86962127699999,-31.9386386871],"type":"Point"}
}