{
  "type": "Feature",
  "properties": {
    "addr:full":"480 Pacific Hwy Killara NSW 2071",
    "addr:housenumber":"480",
    "addr:postcode":"2071",
    "addr:street":"Pacific Hwy",
    "iso:country":"AU",
    "sg:address":"480 Pacific Hwy",
    "sg:city":"Killara",
    "sg:classifiers":[
        {
            "category":"Travel",
            "subcategory":"Hotels & Motels",
            "type":"Entertainment"
        }
    ],
    "sg:phone":"+61 2 9416 1344",
    "sg:postcode":"2071",
    "sg:province":"NSW",
    "wof:name":"Killara Inn Hotel & Conference Centre",
    "wof:placetype":"venue"
},
  "geometry": {"coordinates":[151.16140747099999,-33.7717437744],"type":"Point"}
}