{
  "type": "Feature",
  "properties": {
    "addr:full":"218 Crawford St Queanbeyan ACT 2620",
    "addr:housenumber":"218",
    "addr:postcode":"2620",
    "addr:street":"Crawford St",
    "iso:country":"AU",
    "sg:address":"218 Crawford St",
    "sg:city":"Queanbeyan",
    "sg:classifiers":[
        {
            "category":"Fast Food",
            "type":"Food & Drink"
        }
    ],
    "sg:phone":"+61 2 6297 6833",
    "sg:postcode":"2620",
    "sg:province":"ACT",
    "sg:tags":[
        "away",
        "take"
    ],
    "wof:name":"Pizza Hut",
    "wof:placetype":"venue"
},
  "geometry": {"coordinates":[149.23377990700001,-35.3522911072],"type":"Point"}
}