{
  "type": "Feature",
  "properties": {
    "addr:full":"Shp1/ 390 Mcdonalds Rd South Morang VIC 3752",
    "addr:housenumber":"390",
    "addr:postcode":"3752",
    "addr:street":"Mcdonalds Rd",
    "iso:country":"AU",
    "sg:address":"Shp1/ 390 Mcdonalds Rd",
    "sg:city":"South Morang",
    "sg:classifiers":[
        {
            "category":"Fast Food",
            "type":"Food & Drink"
        }
    ],
    "sg:phone":"+61 3 9404 3100",
    "sg:postcode":"3752",
    "sg:province":"VIC",
    "sg:tags":[
        "away",
        "take"
    ],
    "wof:name":"Pier 31 Fish And Chippery",
    "wof:placetype":"venue"
},
  "geometry": {"coordinates":[145.07148699999999,-37.64959],"type":"Point"}
}