{
  "type": "Feature",
  "properties": {
    "iso:country":"AU",
    "sg:address":"47 Stephen Tce St",
    "sg:city":"Peters",
    "sg:classifiers":[
        {
            "category":"Health Services",
            "subcategory":"Chiropractor",
            "type":"Services"
        }
    ],
    "sg:phone":"+61 8 8363 4700",
    "sg:postcode":"5069",
    "sg:province":"SA",
    "wof:name":"Arcady Turczynowicz Dr",
    "wof:placetype":"venue"
},
  "geometry": {"coordinates":[138.623504639,-34.9047203064],"type":"Point"}
}