{
  "type": "Feature",
  "properties": {
    "addr:full":"43 Oxford St Ingleburn NSW 2565",
    "addr:housenumber":"43",
    "addr:postcode":"2565",
    "addr:street":"Oxford St",
    "iso:country":"AU",
    "sg:address":"43 Oxford St",
    "sg:city":"Ingleburn",
    "sg:classifiers":[
        {
            "category":"Personal",
            "subcategory":"Beauty Salon",
            "type":"Services"
        }
    ],
    "sg:phone":"+61 2 9605 1232",
    "sg:postcode":"2565",
    "sg:province":"NSW",
    "sg:tags":[
        "hairdresser"
    ],
    "wof:name":"For Men Only",
    "wof:placetype":"venue"
},
  "geometry": {"coordinates":[150.86659240700001,-33.9990768433],"type":"Point"}
}