{
  "type": "Feature",
  "properties": {
    "addr:full":"Shop 116 A Westfield Shoppingtown, Airport West VIC 3042",
    "addr:housenumber":"116 a",
    "addr:postcode":"3042",
    "addr:street":"Westfield",
    "iso:country":"AU",
    "sg:address":"Shop 116",
    "sg:city":"A Westfield Shoppingtown, Airport West",
    "sg:classifiers":[
        {
            "category":"Shopping",
            "subcategory":"Mobile Phones",
            "type":"Retail Goods"
        }
    ],
    "sg:phone":"+61 3 9335 1800",
    "sg:postcode":"3042",
    "sg:province":"VIC",
    "sg:tags":[
        "telephone",
        "accessory"
    ],
    "wof:name":"Vodafone",
    "wof:placetype":"venue"
},
  "geometry": {"coordinates":[144.88563537600001,-37.7126159668],"type":"Point"}
}