{
  "type": "Feature",
  "properties": {
    "iso:country":"AU",
    "sg:address":"31 Sarah St",
    "sg:city":"Campbellfield",
    "sg:classifiers":[
        {
            "category":"Wholesale",
            "subcategory":"Auto Parts",
            "type":"Manufacturing & Wholesale Goods"
        }
    ],
    "sg:phone":"+61 3 9357 6333",
    "sg:postcode":"3061",
    "sg:province":"VIC",
    "sg:tags":[
        "recyclers"
    ],
    "wof:name":"Classic Auto Recycling Sales",
    "wof:placetype":"venue"
},
  "geometry": {"coordinates":[144.96989440900001,-37.6711502075],"type":"Point"}
}