{
  "type": "Feature",
  "properties": {
    "iso:country":"AU",
    "sg:address":"Unit 2 23 Production Ave",
    "sg:city":"Kawana Waters",
    "sg:classifiers":[
        {
            "category":"Retail",
            "subcategory":"Auto Repair",
            "type":"Services"
        }
    ],
    "sg:phone":"+61 7 5493 8522",
    "sg:postcode":"4575",
    "sg:province":"QLD",
    "sg:tags":[
        "repairer",
        "motor",
        "engineer"
    ],
    "wof:name":"Kawana Brake & Clutch",
    "wof:placetype":"venue"
},
  "geometry": {"coordinates":[153.125854,-26.727577],"type":"Point"}
}