{
  "type": "Feature",
  "properties": {
    "iso:country":"AU",
    "sg:address":"48 Kurrajong Ave",
    "sg:city":"Leeton",
    "sg:classifiers":[
        {
            "category":"Personal",
            "subcategory":"Beauty Salon",
            "type":"Services"
        }
    ],
    "sg:phone":"+61 2 6953 2003",
    "sg:postcode":"2705",
    "sg:province":"NSW",
    "sg:tags":[
        "hairdresser"
    ],
    "wof:name":"Hairmasters",
    "wof:placetype":"venue"
},
  "geometry": {"coordinates":[146.40736389200001,-34.5532035828],"type":"Point"}
}