{
  "type": "Feature",
  "properties": {
    "addr:full":"22 Clifton St Malvern SA 5061",
    "addr:housenumber":"22",
    "addr:postcode":"5061",
    "addr:street":"Clifton St",
    "iso:country":"AU",
    "sg:address":"22 Clifton St",
    "sg:city":"Malvern",
    "sg:classifiers":[
        {
            "category":"Professional",
            "subcategory":"Computer Services",
            "type":"Services"
        }
    ],
    "sg:phone":"+61 411 845 465",
    "sg:postcode":"5061",
    "sg:province":"SA",
    "sg:tags":[
        "repairs",
        "upgrade",
        "equipment"
    ],
    "wof:name":"Dr Bob PC Repair Services",
    "wof:placetype":"venue"
},
  "geometry": {"coordinates":[138.61480712900001,-34.9552574158],"type":"Point"}
}