{
  "type": "Feature",
  "properties": {
    "addr:full":"139 Hobart Rd Kings Meadows TAS 7249",
    "addr:housenumber":"139",
    "addr:postcode":"7249",
    "addr:street":"Hobart Rd",
    "iso:country":"AU",
    "sg:address":"139 Hobart Rd",
    "sg:city":"Kings Meadows",
    "sg:classifiers":[
        {
            "category":"Shopping",
            "subcategory":"Optical Goods",
            "type":"Retail Goods"
        }
    ],
    "sg:phone":"+61 3 6343 6333",
    "sg:postcode":"7249",
    "sg:province":"TAS",
    "sg:tags":[
        "dispenser",
        "prescription"
    ],
    "wof:name":"Eye Lines",
    "wof:placetype":"venue"
},
  "geometry": {"coordinates":[147.160400391,-41.4678688049],"type":"Point"}
}