{
  "type": "Feature",
  "properties": {
    "iso:country":"AU",
    "sg:address":"392 North Rd",
    "sg:city":"Brighton",
    "sg:classifiers":[
        {
            "category":"Professional",
            "subcategory":"Art Services",
            "type":"Services"
        }
    ],
    "sg:phone":"+61 418 347 337",
    "sg:postcode":"3186",
    "sg:province":"VIC",
    "sg:tags":[
        "decorator",
        "painter"
    ],
    "wof:name":"Protec Painting Group",
    "wof:placetype":"venue"
},
  "geometry": {"coordinates":[144.99598693900001,-37.8985023499],"type":"Point"}
}