{
  "type": "Feature",
  "properties": {
    "addr:full":"Gunson St Olympic Dam SA 5725",
    "addr:postcode":"5725",
    "addr:street":"St",
    "iso:country":"AU",
    "sg:address":"Gunson St",
    "sg:city":"Olympic Dam",
    "sg:classifiers":[
        {
            "category":"Professional",
            "subcategory":"Engineering",
            "type":"Services"
        }
    ],
    "sg:phone":"+61 8 8671 0015",
    "sg:postcode":"5725",
    "sg:province":"SA",
    "sg:tags":[
        "manufacturing",
        "engineer"
    ],
    "wof:name":"Sandvik Mining & Construction Adelaide Ltd",
    "wof:placetype":"venue"
},
  "geometry": {"coordinates":[136.872955322,-30.5030097961],"type":"Point"}
}