{
  "type": "Feature",
  "properties": {
    "addr:full":"22 Filburn St Scarborough WA 6019",
    "addr:housenumber":"22",
    "addr:postcode":"6019",
    "addr:street":"Filburn St",
    "iso:country":"AU",
    "sg:address":"22 Filburn St",
    "sg:city":"Scarborough",
    "sg:classifiers":[
        {
            "category":"Building & Trades",
            "subcategory":"Plumbing",
            "type":"Services"
        }
    ],
    "sg:phone":"+61 419 914 466",
    "sg:postcode":"6019",
    "sg:province":"WA",
    "sg:tags":[
        "plumber",
        "gasfitters"
    ],
    "wof:name":"Scarboro Plumbing & Gas",
    "wof:placetype":"venue"
},
  "geometry": {"coordinates":[115.75907135,-31.8912029266],"type":"Point"}
}