{
  "type": "Feature",
  "properties": {
    "addr:full":"Latrobe University Medical Cen Corner Plenty Rd & Kingsbury Drv (Bundoora) La Trobe University VIC 3086",
    "addr:postcode":"3086",
    "addr:street":"Plenty Rd & Kingsbury Drv;La",
    "iso:country":"AU",
    "sg:address":"Latrobe University Medical Cen Corner Plenty Rd & Kingsbury Drv (Bundoora)",
    "sg:city":"La Trobe University",
    "sg:classifiers":[
        {
            "category":"Health Services",
            "subcategory":"Doctor",
            "type":"Services"
        }
    ],
    "sg:phone":"+61 3 9473 8837",
    "sg:postcode":"3086",
    "sg:province":"VIC",
    "sg:tags":[
        "medical",
        "practitioner"
    ],
    "wof:name":"Goldwasser Nicki",
    "wof:placetype":"venue"
},
  "geometry": {"coordinates":[145.042755,-37.717457],"type":"Point"}
}