{
  "type": "Feature",
  "properties": {
    "addr:full":"Unit 8, 8 Dowling Pl Windsor South NSW 2756",
    "addr:housenumber":"8",
    "addr:postcode":"2756",
    "addr:street":"Dowling Pl",
    "iso:country":"AU",
    "sg:address":"Unit 8, 8 Dowling Pl",
    "sg:city":"Windsor South",
    "sg:classifiers":[
        {
            "category":"Bars & Pubs",
            "subcategory":"Biergarten",
            "type":"Food & Drink"
        }
    ],
    "sg:phone":"+61 2 4577 7111",
    "sg:postcode":"2756",
    "sg:province":"NSW",
    "sg:tags":[
        "eucalyptus",
        "oil",
        "tree",
        "essential",
        "tea"
    ],
    "wof:name":"Pastel Pines Australia",
    "wof:placetype":"venue"
},
  "geometry": {"coordinates":[150.81124877900001,-33.6210327148],"type":"Point"}
}