{
  "type": "Feature",
  "properties": {
    "addr:full":"202 Moorabool St Geelong VIC 3220",
    "addr:housenumber":"202",
    "addr:postcode":"3220",
    "addr:street":"Moorabool St",
    "iso:country":"AU",
    "sg:address":"202 Moorabool St",
    "sg:city":"Geelong",
    "sg:classifiers":[
        {
            "category":"Shopping",
            "subcategory":"Mobile Phones",
            "type":"Retail Goods"
        }
    ],
    "sg:phone":"+61 3 5224 2877",
    "sg:postcode":"3220",
    "sg:province":"VIC",
    "sg:tags":[
        "telephone",
        "accessory"
    ],
    "wof:name":"Strathfield",
    "wof:placetype":"venue"
},
  "geometry": {"coordinates":[144.35888700000001,-38.150928],"type":"Point"}
}