{
  "type": "Feature",
  "properties": {
    "iso:country":"AU",
    "sg:address":"273 Union Rd",
    "sg:city":"Balwyn",
    "sg:classifiers":[
        {
            "category":"Professional",
            "subcategory":"Engineering",
            "type":"Services"
        }
    ],
    "sg:phone":"+61 3 9899 4511",
    "sg:postcode":"3103",
    "sg:province":"VIC",
    "sg:tags":[
        "consulting",
        "engineer"
    ],
    "wof:name":"Formtech Pty Ltd",
    "wof:placetype":"venue"
},
  "geometry": {"coordinates":[145.099853516,-37.8133621216],"type":"Point"}
}