{
  "type": "Feature",
  "properties": {
    "addr:full":"1017 Lower North East Rd Highbury SA 5089",
    "addr:housenumber":"1017",
    "addr:postcode":"5089",
    "addr:street":"Lower North East Rd",
    "iso:country":"AU",
    "sg:address":"1017 Lower North East Rd",
    "sg:city":"Highbury",
    "sg:classifiers":[
        {
            "category":"Food & Beverages",
            "subcategory":"Liquor & Beverages",
            "type":"Retail Goods"
        }
    ],
    "sg:phone":"+61 8 8265 6666",
    "sg:postcode":"5089",
    "sg:province":"SA",
    "sg:tags":[
        "store"
    ],
    "wof:name":"BWS Liquor Stores",
    "wof:placetype":"venue"
},
  "geometry": {"coordinates":[138.70048523,-34.8526725769],"type":"Point"}
}