{
  "type": "Feature",
  "properties": {
    "addr:full":"Cnr Albany Hwy & William St Cannington WA 6107",
    "addr:postcode":"6107",
    "addr:street":"Cnr Albany Hwy & William St",
    "iso:country":"AU",
    "sg:address":"Cnr Albany Hwy & William St",
    "sg:city":"Cannington",
    "sg:classifiers":[
        {
            "category":"Real Estate",
            "subcategory":"Real Estate Agent",
            "type":"Services"
        }
    ],
    "sg:phone":"+61 8 9451 5211",
    "sg:postcode":"6107",
    "sg:province":"WA",
    "sg:tags":[
        "handyman's",
        "equipment",
        "hire",
        "builders",
        "contractor"
    ],
    "wof:name":"Wreckair",
    "wof:placetype":"venue"
},
  "geometry": {"coordinates":[115.933120727,-32.016960144],"type":"Point"}
}