{
  "type": "Feature",
  "properties": {
    "addr:full":"18 Ambrose St Rockingham WA 6168",
    "addr:housenumber":"18",
    "addr:postcode":"6168",
    "addr:street":"Ambrose St",
    "iso:country":"AU",
    "sg:address":"18 Ambrose St",
    "sg:city":"Rockingham",
    "sg:classifiers":[
        {
            "category":"Building & Trades",
            "subcategory":"Construction",
            "type":"Services"
        }
    ],
    "sg:phone":"+61 8 9592 6780",
    "sg:postcode":"6168",
    "sg:province":"WA",
    "sg:tags":[
        "scaffolding"
    ],
    "wof:name":"Orvad (WA) Pty Ltd",
    "wof:placetype":"venue"
},
  "geometry": {"coordinates":[115.747559,-32.276852],"type":"Point"}
}