{
  "type": "Feature",
  "properties": {
    "addr:full":"6 Picola Crt Coolaroo VIC 3048",
    "addr:housenumber":"6",
    "addr:postcode":"3048",
    "addr:street":"Picola Crt",
    "iso:country":"AU",
    "sg:address":"6 Picola Crt",
    "sg:city":"Coolaroo",
    "sg:classifiers":[
        {
            "category":"Shopping",
            "subcategory":"Antiques",
            "type":"Retail Goods"
        }
    ],
    "sg:phone":"+61 414 739 268",
    "sg:postcode":"3048",
    "sg:province":"VIC",
    "sg:tags":[
        "collectable",
        "memorabilia"
    ],
    "wof:name":"Anthony Graham",
    "wof:placetype":"venue"
},
  "geometry": {"coordinates":[144.91978499999999,-37.657207],"type":"Point"}
}