{
  "type": "Feature",
  "properties": {
    "addr:full":"209 Gilmore Rd Queanbeyan NSW 2620",
    "addr:housenumber":"209",
    "addr:postcode":"2620",
    "addr:street":"Gilmore Rd",
    "iso:country":"AU",
    "sg:address":"209 Gilmore Rd",
    "sg:city":"Queanbeyan",
    "sg:classifiers":[
        {
            "category":"Fast Food",
            "type":"Food & Drink"
        }
    ],
    "sg:phone":"+61 2 6297 3430",
    "sg:postcode":"2620",
    "sg:province":"NSW",
    "sg:tags":[
        "away",
        "take"
    ],
    "wof:name":"West Side Snack Bar",
    "wof:placetype":"venue"
},
  "geometry": {"coordinates":[149.20585632300001,-35.3470993042],"type":"Point"}
}