{
  "type": "Feature",
  "properties": {
    "addr:full":"PO Box 2843 Southport QLD 4215",
    "addr:postcode":"4215",
    "iso:country":"AU",
    "sg:address":"PO Box 2843",
    "sg:city":"Southport",
    "sg:classifiers":[
        {
            "category":"Building & Trades",
            "subcategory":"Construction",
            "type":"Services"
        }
    ],
    "sg:phone":"+61 7 3208 1208",
    "sg:postcode":"4215",
    "sg:province":"QLD",
    "sg:tags":[
        "insulation",
        "contractor"
    ],
    "wof:name":"Insulationbatts.com",
    "wof:placetype":"venue"
},
  "geometry": {"coordinates":[153.415557861,-27.9655303955],"type":"Point"}
}