{
  "type": "Feature",
  "properties": {
    "addr:full":"3 Murdock St Coffs Harbour NSW 2450",
    "addr:housenumber":"3",
    "addr:postcode":"2450",
    "addr:street":"Murdock St",
    "iso:country":"AU",
    "sg:address":"3 Murdock St",
    "sg:city":"Coffs Harbour",
    "sg:classifiers":[
        {
            "category":"Utilities",
            "subcategory":"Telephone",
            "type":"Services"
        }
    ],
    "sg:phone":"+61 2 6651 5118",
    "sg:postcode":"2450",
    "sg:province":"NSW",
    "sg:tags":[
        "installation",
        "system",
        "maintenance"
    ],
    "wof:name":"Telstra Shop",
    "wof:placetype":"venue"
},
  "geometry": {"coordinates":[153.11085499999999,-30.295374],"type":"Point"}
}