{
  "type": "Feature",
  "properties": {
    "addr:full":"Lot 3 William Bailey St Raymond Terrace NSW 2324",
    "addr:housenumber":"3",
    "addr:postcode":"2324",
    "addr:street":"William Bailey St",
    "iso:country":"AU",
    "sg:address":"Lot 3 William Bailey St",
    "sg:city":"Raymond Terrace",
    "sg:classifiers":[
        {
            "category":"Building & Trades",
            "subcategory":"Plumbing",
            "type":"Services"
        }
    ],
    "sg:phone":"+61 2 4987 1514",
    "sg:postcode":"2324",
    "sg:province":"NSW",
    "sg:tags":[
        "pump",
        "repairer"
    ],
    "wof:name":"Marden Electric Motor Rewinds",
    "wof:placetype":"venue"
},
  "geometry": {"coordinates":[151.75001525900001,-32.7592582703],"type":"Point"}
}