{
  "type": "Feature",
  "properties": {
    "addr:full":"6/20 Pendlebury Rd Cardiff NSW 2285",
    "addr:housenumber":"/ 20",
    "addr:postcode":"2285",
    "addr:street":"Pendlebury Rd",
    "iso:country":"AU",
    "sg:address":"6/20 Pendlebury Rd",
    "sg:city":"Cardiff",
    "sg:classifiers":[
        {
            "category":"Social Services",
            "type":"Services"
        }
    ],
    "sg:phone":"+61 2 4954 2444",
    "sg:postcode":"2285",
    "sg:province":"NSW",
    "sg:tags":[
        "disabled",
        "person",
        "equipment"
    ],
    "wof:name":"Total Transport Solutions",
    "wof:placetype":"venue"
},
  "geometry": {"coordinates":[151.653564453,-32.9480895996],"type":"Point"}
}