{
  "type": "Feature",
  "properties": {
    "iso:country":"AU",
    "sg:address":"Cnr Beerwah Pde & Swan St",
    "sg:city":"Beerwah",
    "sg:classifiers":[
        {
            "category":"Fast Food",
            "type":"Food & Drink"
        }
    ],
    "sg:phone":"+61 7 5494 6856",
    "sg:postcode":"4519",
    "sg:province":"QLD",
    "sg:tags":[
        "away",
        "take"
    ],
    "wof:name":"Sierra Takeaway Foods",
    "wof:placetype":"venue"
},
  "geometry": {"coordinates":[152.960968,-26.860552],"type":"Point"}
}