{
  "type": "Feature",
  "properties": {
    "addr:full":"Lot 23 Cams Blv Summerland Point NSW 2259",
    "addr:postcode":"2259",
    "addr:street":"Blv Summerland",
    "iso:country":"AU",
    "sg:address":"Lot 23",
    "sg:city":"Cams Blv Summerland Point",
    "sg:classifiers":[
        {
            "category":"Food & Beverages",
            "subcategory":"Liquor & Beverages",
            "type":"Retail Goods"
        }
    ],
    "sg:phone":"+61 2 4976 3141",
    "sg:postcode":"2259",
    "sg:province":"NSW",
    "sg:tags":[
        "store"
    ],
    "wof:name":"Cellarbrations",
    "wof:placetype":"venue"
},
  "geometry": {"coordinates":[151.56953430199999,-33.1389694214],"type":"Point"}
}