{
  "type": "Feature",
  "properties": {
    "addr:full":"6 Jarman St Yeppoon QLD 4703",
    "addr:housenumber":"6",
    "addr:postcode":"4703",
    "addr:street":"Jarman St",
    "iso:country":"AU",
    "sg:address":"6 Jarman St",
    "sg:city":"Yeppoon",
    "sg:classifiers":[
        {
            "category":"Professional",
            "subcategory":"Engineering",
            "type":"Services"
        }
    ],
    "sg:phone":"+61 417 702 029",
    "sg:postcode":"4703",
    "sg:province":"QLD",
    "sg:tags":[
        "consulting",
        "engineer"
    ],
    "wof:name":"IMD & Assoc",
    "wof:placetype":"venue"
},
  "geometry": {"coordinates":[150.74598693900001,-23.108045578],"type":"Point"}
}