{
  "type": "Feature",
  "properties": {
    "addr:full":"PO Box 348 Eumundi QLD 4562",
    "addr:postcode":"4562",
    "iso:country":"AU",
    "sg:address":"PO Box 348",
    "sg:city":"Eumundi",
    "sg:classifiers":[
        {
            "category":"Education",
            "subcategory":"Special Training",
            "type":"Public Place"
        }
    ],
    "sg:phone":"+61 7 5442 7880",
    "sg:postcode":"4562",
    "sg:province":"QLD",
    "sg:tags":[
        "development"
    ],
    "wof:name":"ICS Learning Group",
    "wof:placetype":"venue"
},
  "geometry": {"coordinates":[152.95066833499999,-26.4752693176],"type":"Point"}
}