{
  "type": "Feature",
  "properties": {
    "iso:country":"AU",
    "sg:address":"1496- 1500 South Rd",
    "sg:city":"Darlington",
    "sg:classifiers":[
        {
            "category":"Professional",
            "subcategory":"Detective & Security Services",
            "type":"Services"
        }
    ],
    "sg:phone":"+61 1300 856 990",
    "sg:postcode":"5047",
    "sg:province":"SA",
    "sg:tags":[
        "guard",
        "patrol"
    ],
    "sg:website":"http://www.talonprotectionservices.com.au",
    "wof:name":"Talon Protection Services",
    "wof:placetype":"venue"
},
  "geometry": {"coordinates":[138.551559,-35.028568],"type":"Point"}
}