{
  "type": "Feature",
  "properties": {
    "iso:country":"AU",
    "sg:address":"PO Box 688",
    "sg:city":"Noosa Heads",
    "sg:classifiers":[
        {
            "category":"Real Estate",
            "subcategory":"Architect",
            "type":"Services"
        }
    ],
    "sg:phone":"+61 419 158 404",
    "sg:postcode":"4567",
    "sg:province":"QLD",
    "sg:tags":[
        "house",
        "damp",
        "waterproofing",
        "repair"
    ],
    "wof:name":"New Age Waterproofing & Floor Treatments",
    "wof:placetype":"venue"
},
  "geometry": {"coordinates":[153.086105347,-26.3990192413],"type":"Point"}
}