{
  "type": "Feature",
  "properties": {
    "addr:full":"Shed 3, 60 Marjorie St Pinelands NT 0829",
    "addr:housenumber":"60",
    "addr:postcode":"nt 0829",
    "addr:street":"Marjorie St",
    "iso:country":"AU",
    "sg:address":"Shed 3, 60 Marjorie St",
    "sg:city":"Pinelands",
    "sg:classifiers":[
        {
            "category":"Building & Trades",
            "subcategory":"Construction",
            "type":"Services"
        }
    ],
    "sg:phone":"+61 8 8931 3907",
    "sg:postcode":"0829",
    "sg:province":"NT",
    "sg:tags":[
        "contractor"
    ],
    "wof:name":"Top End Homes",
    "wof:placetype":"venue"
},
  "geometry": {"coordinates":[130.96751403799999,-12.4617452621],"type":"Point"}
}