{
  "type": "Feature",
  "properties": {
    "iso:country":"AU",
    "sg:address":"1249 Anzac Ave",
    "sg:city":"Kallangur",
    "sg:classifiers":[
        {
            "category":"Autos & Motor Vehicles",
            "subcategory":"Auto Supplies",
            "type":"Retail Goods"
        }
    ],
    "sg:phone":"+61 7 3285 8100",
    "sg:postcode":"4503",
    "sg:province":"QLD",
    "sg:tags":[
        "wheel",
        "automotive",
        "rim"
    ],
    "wof:name":"Dog Tyred",
    "wof:placetype":"venue"
},
  "geometry": {"coordinates":[152.99732971200001,-27.2496070862],"type":"Point"}
}