{
  "type": "Feature",
  "properties": {
    "addr:full":"Freshwater Arcade, Shop 4, 12- 14 Lawrence St Harbord NSW 2096",
    "addr:housenumber":"4;14",
    "addr:postcode":"2096",
    "addr:street":"Lawrence St",
    "iso:country":"AU",
    "sg:address":"Freshwater Arcade, Shop 4, 12- 14 Lawrence St",
    "sg:city":"Harbord",
    "sg:classifiers":[
        {
            "category":"Personal",
            "subcategory":"Massage",
            "type":"Services"
        }
    ],
    "sg:phone":"+61 2 9907 3521",
    "sg:postcode":"2096",
    "sg:province":"NSW",
    "sg:tags":[
        "therapy"
    ],
    "wof:name":"Echoes of Healing",
    "wof:placetype":"venue"
},
  "geometry": {"coordinates":[151.284545898,-33.779006958],"type":"Point"}
}