{
  "type": "Feature",
  "properties": {
    "iso:country":"AU",
    "sg:address":"33 Smart Rd",
    "sg:city":"Modbury",
    "sg:classifiers":[
        {
            "category":"Professional",
            "subcategory":"Employment Agencies",
            "type":"Services"
        }
    ],
    "sg:phone":"+61 8 8395 1766",
    "sg:postcode":"5092",
    "sg:province":"SA",
    "wof:name":"Employment Plus",
    "wof:placetype":"venue"
},
  "geometry": {"coordinates":[138.686935425,-34.833694458],"type":"Point"}
}