{
  "type": "Feature",
  "properties": {
    "iso:country":"AU",
    "sg:address":"3 Bastings St",
    "sg:city":"Northcote",
    "sg:classifiers":[
        {
            "category":"Education",
            "subcategory":"Special Training",
            "type":"Public Place"
        }
    ],
    "sg:phone":"+61 3 9482 5841",
    "sg:postcode":"3070",
    "sg:province":"VIC",
    "sg:tags":[
        "development"
    ],
    "wof:name":"NLP Training With Leadervision",
    "wof:placetype":"venue"
},
  "geometry": {"coordinates":[144.99908400000001,-37.773888],"type":"Point"}
}