{
  "type": "Feature",
  "properties": {
    "addr:full":"87 Lime Ave Mildura VIC 3500",
    "addr:housenumber":"87",
    "addr:postcode":"3500",
    "addr:street":"Lime Ave",
    "iso:country":"AU",
    "sg:address":"87 Lime Ave",
    "sg:city":"Mildura",
    "sg:classifiers":[
        {
            "category":"Building & Trades",
            "subcategory":"Construction",
            "type":"Services"
        }
    ],
    "sg:phone":"+61 3 5023 1199",
    "sg:postcode":"3500",
    "sg:province":"VIC",
    "sg:tags":[
        "contractor"
    ],
    "wof:name":"G.J. Gardner.Homes",
    "wof:placetype":"venue"
},
  "geometry": {"coordinates":[142.15852355999999,-34.1847648621],"type":"Point"}
}