{
  "type": "Feature",
  "properties": {
    "addr:full":"Cnr Hammond Ave & Lawson St Wagga Wagga NSW 2650",
    "addr:postcode":"2650",
    "addr:street":"Cnr Hammond Ave & Lawson St",
    "iso:country":"AU",
    "sg:address":"Cnr Hammond Ave & Lawson St",
    "sg:city":"Wagga Wagga",
    "sg:classifiers":[
        {
            "category":"Manufacturing",
            "subcategory":"Buildings",
            "type":"Manufacturing & Wholesale Goods"
        }
    ],
    "sg:phone":"+61 2 6921 4988",
    "sg:postcode":"2650",
    "sg:province":"NSW",
    "sg:tags":[
        "transportable",
        "domestic",
        "relocatable"
    ],
    "wof:name":"Lloyds Transportable Homes",
    "wof:placetype":"venue"
},
  "geometry": {"coordinates":[147.37730407699999,-35.1417884827],"type":"Point"}
}