{
  "type": "Feature",
  "properties": {
    "addr:full":"Stockland Shopping Centre, Mulgrave Rd Cairns QLD 4870",
    "addr:postcode":"4870",
    "addr:street":"Mulgrave Rd",
    "iso:country":"AU",
    "sg:address":"Stockland Shopping Centre, Mulgrave Rd",
    "sg:city":"Cairns",
    "sg:classifiers":[
        {
            "category":"Health Services",
            "subcategory":"Health Practitioner",
            "type":"Services"
        }
    ],
    "sg:phone":"+61 403 847 814",
    "sg:postcode":"4870",
    "sg:province":"QLD",
    "sg:tags":[
        "naturopath"
    ],
    "wof:name":"B J McDean",
    "wof:placetype":"venue"
},
  "geometry": {"coordinates":[145.746780395,-16.9546756744],"type":"Point"}
}