{
  "type": "Feature",
  "properties": {
    "iso:country":"AU",
    "sg:address":"Hume Hwy",
    "sg:city":"Warwick Farm",
    "sg:classifiers":[
        {
            "category":"Arena",
            "subcategory":"Sports Club",
            "type":"Entertainment"
        }
    ],
    "sg:phone":"+61 2 9821 3234",
    "sg:postcode":"2170",
    "sg:province":"NSW",
    "sg:tags":[
        "organisation",
        "sporting"
    ],
    "wof:name":"Southern District Softball Asscn",
    "wof:placetype":"venue"
},
  "geometry": {"coordinates":[150.93775939899999,-33.9115333557],"type":"Point"}
}