{
  "type": "Feature",
  "properties": {
    "addr:full":"143 Laurel Ave Lismore NSW 2480",
    "addr:housenumber":"143",
    "addr:postcode":"2480",
    "addr:street":"Laurel Ave",
    "iso:country":"AU",
    "sg:address":"143 Laurel Ave",
    "sg:city":"Lismore",
    "sg:classifiers":[
        {
            "category":"Organizations",
            "subcategory":"Community Association",
            "type":"Services"
        }
    ],
    "sg:phone":"+61 2 6621 4970",
    "sg:postcode":"2480",
    "sg:province":"NSW",
    "sg:tags":[
        "organisation",
        "family",
        "welfare"
    ],
    "wof:name":"Interrelate Family Centres",
    "wof:placetype":"venue"
},
  "geometry": {"coordinates":[153.28973388700001,-28.8086013794],"type":"Point"}
}