{
  "type": "Feature",
  "properties": {
    "addr:full":"Levels 2, 3 & 4, 78 Queen St Brisbane QLD 4000",
    "addr:housenumber":"3 &;78",
    "addr:postcode":"4000",
    "addr:street":"4;Queen St",
    "iso:country":"AU",
    "sg:address":"Levels 2, 3 & 4, 78 Queen St",
    "sg:city":"Brisbane",
    "sg:classifiers":[
        {
            "category":"Sports & Exercise",
            "subcategory":"Gym",
            "type":"Entertainment"
        }
    ],
    "sg:phone":"+61 7 3211 0060",
    "sg:postcode":"4000",
    "sg:province":"QLD",
    "sg:tags":[
        "pilate",
        "method"
    ],
    "sg:website":"http://www.purehealthclubs.com.au",
    "wof:name":"Pure Health Clubs",
    "wof:placetype":"venue"
},
  "geometry": {"coordinates":[153.02421569800001,-27.4702262878],"type":"Point"}
}