{
  "type": "Feature",
  "properties": {
    "addr:full":"McNeilly Ave Orange NSW 2800",
    "addr:postcode":"2800",
    "addr:street":"Mcneilly Ave",
    "iso:country":"AU",
    "sg:address":"McNeilly Ave",
    "sg:city":"Orange",
    "sg:classifiers":[
        {
            "category":"Wholesale",
            "subcategory":"Farm Supplies",
            "type":"Manufacturing & Wholesale Goods"
        }
    ],
    "sg:phone":"+61 2 6362 5566",
    "sg:postcode":"2800",
    "sg:province":"NSW",
    "sg:tags":[
        "equipment"
    ],
    "wof:name":"On-Trac Ag Pty Ltd",
    "wof:placetype":"venue"
},
  "geometry": {"coordinates":[149.10316467300001,-33.3030662537],"type":"Point"}
}