{
  "type": "Feature",
  "properties": {
    "iso:country":"AU",
    "sg:address":"427 Ballarat Rd",
    "sg:city":"Sunshine",
    "sg:classifiers":[
        {
            "category":"Fast Food",
            "type":"Food & Drink"
        }
    ],
    "sg:phone":"+61 13 11 66",
    "sg:postcode":"3020",
    "sg:province":"VIC",
    "sg:tags":[
        "away",
        "take"
    ],
    "wof:name":"Pizza Hut Delivery",
    "wof:placetype":"venue"
},
  "geometry": {"coordinates":[144.84065246599999,-37.7785568237],"type":"Point"}
}