{
  "type": "Feature",
  "properties": {
    "iso:country":"AU",
    "sg:address":"22 Lawry St",
    "sg:city":"Northcote",
    "sg:classifiers":[
        {
            "category":"Personal",
            "subcategory":"Massage",
            "type":"Services"
        }
    ],
    "sg:phone":"+61 3 9481 2982",
    "sg:postcode":"3070",
    "sg:province":"VIC",
    "sg:tags":[
        "therapy"
    ],
    "wof:name":"Frank Robyn",
    "wof:placetype":"venue"
},
  "geometry": {"coordinates":[145.000046,-37.77103],"type":"Point"}
}