{
  "type": "Feature",
  "properties": {
    "iso:country":"AU",
    "sg:address":"1135 Frankston-Dandenong Rd",
    "sg:city":"Carrum Downs",
    "sg:classifiers":[
        {
            "category":"Health Services",
            "subcategory":"Nursing And Care Facility",
            "type":"Services"
        }
    ],
    "sg:phone":"+61 3 9782 1411",
    "sg:postcode":"3201",
    "sg:province":"VIC",
    "sg:tags":[
        "home"
    ],
    "wof:name":"Carrum Downs Private Nursing Home",
    "wof:placetype":"venue"
},
  "geometry": {"coordinates":[145.177429,-38.094055],"type":"Point"}
}