{
  "type": "Feature",
  "properties": {
    "addr:full":"Unit 2 14 Reichert Drv Molendinar QLD 4214",
    "addr:housenumber":"14",
    "addr:postcode":"4214",
    "addr:street":"Reichert Drv",
    "iso:country":"AU",
    "sg:address":"Unit 2 14 Reichert Drv",
    "sg:city":"Molendinar",
    "sg:classifiers":[
        {
            "category":"Home & Garden",
            "subcategory":"Furniture",
            "type":"Retail Goods"
        }
    ],
    "sg:phone":"+61 7 5574 4355",
    "sg:postcode":"4214",
    "sg:province":"QLD",
    "sg:tags":[
        "business"
    ],
    "wof:name":"Impact Commercial Furniture",
    "wof:placetype":"venue"
},
  "geometry": {"coordinates":[153.35942077600001,-27.9638633728],"type":"Point"}
}