{
  "type": "Feature",
  "properties": {
    "addr:full":"PO Box 3127 Bateau Bay NSW 2261",
    "addr:postcode":"2261",
    "iso:country":"AU",
    "sg:address":"PO Box 3127",
    "sg:city":"Bateau Bay",
    "sg:classifiers":[
        {
            "category":"Professional",
            "subcategory":"Detective & Security Services",
            "type":"Services"
        }
    ],
    "sg:phone":"+61 2 4334 1269",
    "sg:postcode":"2261",
    "sg:province":"NSW",
    "sg:tags":[
        "equipment",
        "window",
        "doors"
    ],
    "wof:name":"Clive Sargeant's Blinds & Awnings",
    "wof:placetype":"venue"
},
  "geometry": {"coordinates":[151.49671900000001,-33.344479],"type":"Point"}
}