{
  "type": "Feature",
  "properties": {
    "addr:full":"71 Constitution Ave Campbell ACT 2612",
    "addr:housenumber":"71",
    "addr:postcode":"2612",
    "addr:street":"Constitution Ave",
    "iso:country":"AU",
    "sg:address":"71 Constitution Ave",
    "sg:city":"Campbell",
    "sg:classifiers":[
        {
            "category":"Building & Trades",
            "subcategory":"Construction",
            "type":"Services"
        }
    ],
    "sg:phone":"+61 2 6247 4999",
    "sg:postcode":"2612",
    "sg:province":"ACT",
    "sg:tags":[
        "management"
    ],
    "wof:name":"Hindmarsh",
    "wof:placetype":"venue"
},
  "geometry": {"coordinates":[149.14550781200001,-35.2916641235],"type":"Point"}
}