{
  "type": "Feature",
  "properties": {
    "addr:full":"5 Woongarra St Bundaberg QLD 4670",
    "addr:housenumber":"5",
    "addr:postcode":"4670",
    "addr:street":"Woongarra St",
    "iso:country":"AU",
    "sg:address":"5 Woongarra St",
    "sg:city":"Bundaberg",
    "sg:classifiers":[
        {
            "category":"Manufacturing",
            "subcategory":"Motor Vehicles & Parts",
            "type":"Manufacturing & Wholesale Goods"
        }
    ],
    "sg:phone":"+61 7 4151 3036",
    "sg:postcode":"4670",
    "sg:province":"QLD",
    "sg:tags":[
        "engine",
        "equipment",
        "diesel"
    ],
    "wof:name":"Jacobsens Automotive Engineers",
    "wof:placetype":"venue"
},
  "geometry": {"coordinates":[152.35551452600001,-24.8654499054],"type":"Point"}
}