{
  "type": "Feature",
  "properties": {
    "addr:full":"186 Molesworth St Lismore NSW 2480",
    "addr:housenumber":"186",
    "addr:postcode":"2480",
    "addr:street":"Molesworth St",
    "iso:country":"AU",
    "sg:address":"186 Molesworth St",
    "sg:city":"Lismore",
    "sg:classifiers":[
        {
            "category":"Health Services",
            "subcategory":"Doctor",
            "type":"Services"
        }
    ],
    "sg:phone":"+61 2 6621 3500",
    "sg:postcode":"2480",
    "sg:province":"NSW",
    "sg:tags":[
        "medical",
        "practitioner"
    ],
    "wof:name":"Gudmundsen Ken Dr",
    "wof:placetype":"venue"
},
  "geometry": {"coordinates":[153.27670288100001,-28.8077373505],"type":"Point"}
}