{
  "type": "Feature",
  "properties": {
    "iso:country":"AU",
    "sg:address":"Neon St",
    "sg:city":"Narangba",
    "sg:classifiers":[
        {
            "category":"Military Area",
            "subcategory":"Air Force Base",
            "type":"Public Place"
        }
    ],
    "sg:phone":"+61 7 3203 3797",
    "sg:postcode":"4504",
    "sg:province":"QLD",
    "sg:tags":[
        "pole",
        "lighting",
        "power"
    ],
    "wof:name":"All Treated Timbers",
    "wof:placetype":"venue"
},
  "geometry": {"coordinates":[153.00624084500001,-27.1974277496],"type":"Point"}
}