{
  "type": "Feature",
  "properties": {
    "iso:country":"AU",
    "sg:address":"360 Settlement Rd",
    "sg:city":"Thomastown",
    "sg:classifiers":[
        {
            "category":"Manufacturing",
            "subcategory":"Food",
            "type":"Manufacturing & Wholesale Goods"
        }
    ],
    "sg:phone":"+61 3 9474 3544",
    "sg:postcode":"3074",
    "sg:province":"VIC",
    "sg:tags":[
        "product",
        "nut",
        "edible"
    ],
    "wof:name":"Lucky Candy",
    "wof:placetype":"venue"
},
  "geometry": {"coordinates":[145.01753234899999,-37.6882171631],"type":"Point"}
}