{
  "type": "Feature",
  "properties": {
    "iso:country":"AU",
    "sg:address":"PO Box 9555",
    "sg:city":"Park Avenue",
    "sg:classifiers":[
        {
            "category":"Building & Trades",
            "subcategory":"Construction",
            "type":"Services"
        }
    ],
    "sg:phone":"+61 411 664 762",
    "sg:postcode":"4701",
    "sg:province":"QLD",
    "sg:tags":[
        "ceiling"
    ],
    "wof:name":"Agius T & T Plasterers",
    "wof:placetype":"venue"
},
  "geometry": {"coordinates":[150.513427734,-23.3675498962],"type":"Point"}
}