{
  "type": "Feature",
  "properties": {
    "addr:full":"Unit 16 Lakeside Corporate 24 Parkland Rd Osborne Park WA 6017",
    "addr:housenumber":"24",
    "addr:postcode":"6017",
    "addr:street":"Parkland Rd",
    "iso:country":"AU",
    "sg:address":"Unit 16 Lakeside Corporate 24 Parkland Rd",
    "sg:city":"Osborne Park",
    "sg:classifiers":[
        {
            "category":"Professional",
            "subcategory":"Accounting & Tax Preparation",
            "type":"Services"
        }
    ],
    "sg:phone":"+61 8 9444 3400",
    "sg:postcode":"6017",
    "sg:province":"WA",
    "sg:tags":[
        "accountant",
        "auditor"
    ],
    "wof:name":"Haines Norton",
    "wof:placetype":"venue"
},
  "geometry": {"coordinates":[115.79763031,-31.9250106812],"type":"Point"}
}