{
  "type": "Feature",
  "properties": {
    "iso:country":"AU",
    "sg:address":"18 Dargie Crt",
    "sg:city":"Dallas",
    "sg:classifiers":[
        {
            "category":"Food & Beverages",
            "subcategory":"Bakery",
            "type":"Retail Goods"
        }
    ],
    "sg:phone":"+61 3 9309 1421",
    "sg:postcode":"3047",
    "sg:province":"VIC",
    "sg:tags":[
        "cake",
        "shop",
        "pastry"
    ],
    "wof:name":"Roy's Cake Shop",
    "wof:placetype":"venue"
},
  "geometry": {"coordinates":[144.93067932100001,-37.6728477478],"type":"Point"}
}