{
  "type": "Feature",
  "properties": {
    "iso:country":"AU",
    "sg:address":"1 Byron St",
    "sg:city":"Glenelg",
    "sg:classifiers":[
        {
            "category":"Wholesale",
            "subcategory":"Medical Equipment & Supplies",
            "type":"Manufacturing & Wholesale Goods"
        }
    ],
    "sg:phone":"+61 8 8376 8787",
    "sg:postcode":"5045",
    "sg:province":"SA",
    "sg:tags":[
        "aids",
        "hearing"
    ],
    "wof:name":"National Hearing Care",
    "wof:placetype":"venue"
},
  "geometry": {"coordinates":[138.51666299999999,-34.980061],"type":"Point"}
}