{
  "type": "Feature",
  "properties": {
    "addr:full":"31 Barooga Rd Wamberal NSW 2260",
    "addr:housenumber":"31",
    "addr:postcode":"2260",
    "addr:street":"Barooga Rd",
    "iso:country":"AU",
    "sg:address":"31 Barooga Rd",
    "sg:city":"Wamberal",
    "sg:classifiers":[
        {
            "category":"Building & Trades",
            "subcategory":"Construction",
            "type":"Services"
        }
    ],
    "sg:phone":"+61 2 4385 3437",
    "sg:postcode":"2260",
    "sg:province":"NSW",
    "sg:tags":[
        "home",
        "air conditioning"
    ],
    "wof:name":"Warick Calleia",
    "wof:placetype":"venue"
},
  "geometry": {"coordinates":[151.44787600000001,-33.415783],"type":"Point"}
}