{
  "type": "Feature",
  "properties": {
    "addr:full":"110 Princes Hwy Figtree NSW 2525",
    "addr:housenumber":"110",
    "addr:postcode":"2525",
    "addr:street":"Princes Hwy",
    "iso:country":"AU",
    "sg:address":"110 Princes Hwy",
    "sg:city":"Figtree",
    "sg:classifiers":[
        {
            "category":"Retail",
            "subcategory":"Auto Repair",
            "type":"Services"
        }
    ],
    "sg:phone":"+61 2 4272 1215",
    "sg:postcode":"2525",
    "sg:province":"NSW",
    "sg:tags":[
        "beater",
        "painter",
        "panel"
    ],
    "wof:name":"Peter Smash Repairs",
    "wof:placetype":"venue"
},
  "geometry": {"coordinates":[150.85658264200001,-34.439743042],"type":"Point"}
}