{
  "type": "Feature",
  "properties": {
    "addr:full":"Shop 28, 57 Chambers Flat Rd Marsden QLD 4132",
    "addr:housenumber":"shop 28 57",
    "addr:postcode":"4132",
    "addr:street":"Chambers Flat Rd",
    "iso:country":"AU",
    "sg:address":"Shop 28, 57 Chambers Flat Rd",
    "sg:city":"Marsden",
    "sg:classifiers":[
        {
            "category":"Manufacturing",
            "subcategory":"Textiles",
            "type":"Manufacturing & Wholesale Goods"
        }
    ],
    "sg:phone":"+61 7 3200 6489",
    "sg:postcode":"4132",
    "sg:province":"QLD",
    "sg:tags":[
        "knitted",
        "woven",
        "fabric"
    ],
    "wof:name":"Polynesian Fashions & Fabrics",
    "wof:placetype":"venue"
},
  "geometry": {"coordinates":[153.11065673799999,-27.6838645935],"type":"Point"}
}