{
  "type": "Feature",
  "properties": {
    "iso:country":"AU",
    "sg:address":"190 Beveridge St",
    "sg:city":"Swan Hill",
    "sg:classifiers":[
        {
            "category":"Organizations",
            "subcategory":"Community Association",
            "type":"Services"
        }
    ],
    "sg:phone":"+61 3 5033 1718",
    "sg:postcode":"3585",
    "sg:province":"VIC",
    "sg:tags":[
        "organisation",
        "family",
        "welfare"
    ],
    "wof:name":"Salvation Army Family Support Services",
    "wof:placetype":"venue"
},
  "geometry": {"coordinates":[143.55865478499999,-35.3414344788],"type":"Point"}
}