{
  "type": "Feature",
  "properties": {
    "iso:country":"AU",
    "sg:address":"50 Clark St",
    "sg:city":"Clifton",
    "sg:classifiers":[
        {
            "category":"Travel",
            "subcategory":"Hotels & Motels",
            "type":"Entertainment"
        }
    ],
    "sg:phone":"+61 7 4697 3288",
    "sg:postcode":"4361",
    "sg:province":"QLD",
    "sg:tags":[
        "accommodation"
    ],
    "wof:name":"O&#039;Shanleys Irish Bar",
    "wof:placetype":"venue"
},
  "geometry": {"coordinates":[151.907546997,-27.9250907898],"type":"Point"}
}