{
  "type": "Feature",
  "properties": {
    "addr:full":"Shop 22 Bunbury Centrepoint Blair St Bunbury WA 6230",
    "addr:housenumber":"shop 22",
    "addr:postcode":"6230",
    "addr:street":"Blair St",
    "iso:country":"AU",
    "sg:address":"Shop 22 Bunbury Centrepoint Blair St",
    "sg:city":"Bunbury",
    "sg:classifiers":[
        {
            "category":"Food & Beverages",
            "subcategory":"Bakery",
            "type":"Retail Goods"
        }
    ],
    "sg:phone":"+61 8 9792 5026",
    "sg:postcode":"6230",
    "sg:province":"WA",
    "sg:tags":[
        "baker"
    ],
    "wof:name":"Muffin Break",
    "wof:placetype":"venue"
},
  "geometry": {"coordinates":[115.642151,-33.352398],"type":"Point"}
}