{
  "type": "Feature",
  "properties": {
    "addr:full":"42 Wirrang Drv Dondingalong NSW 2440",
    "addr:housenumber":"42",
    "addr:postcode":"2440",
    "addr:street":"Wirrang Drv",
    "iso:country":"AU",
    "sg:address":"42 Wirrang Drv",
    "sg:city":"Dondingalong",
    "sg:classifiers":[
        {
            "category":"Building & Trades",
            "subcategory":"Construction",
            "type":"Services"
        }
    ],
    "sg:phone":"+61 2 6566 9042",
    "sg:postcode":"2440",
    "sg:province":"NSW",
    "sg:tags":[
        "rendering",
        "cement"
    ],
    "wof:name":"North Coast Rendering",
    "wof:placetype":"venue"
},
  "geometry": {"coordinates":[152.738068,-31.11418],"type":"Point"}
}