{
  "type": "Feature",
  "properties": {
    "iso:country":"AU",
    "sg:address":"PO box 272 Agery Road",
    "sg:city":"Kadina",
    "sg:classifiers":[
        {
            "category":"Farming",
            "subcategory":"Farm & Veterinary Services",
            "type":"Manufacturing & Wholesale Goods"
        }
    ],
    "sg:phone":"+61 429 671 203",
    "sg:postcode":"5554",
    "sg:province":"SA",
    "sg:tags":[
        "drying",
        "seed",
        "cleaning",
        "grading"
    ],
    "wof:name":"Sobey, Kevin & Karen",
    "wof:placetype":"venue"
},
  "geometry": {"coordinates":[137.71551513700001,-33.965877533],"type":"Point"}
}