{
  "type": "Feature",
  "properties": {
    "addr:full":"48 Newlands Rd Reservoir VIC 3073",
    "addr:housenumber":"48",
    "addr:postcode":"3073",
    "addr:street":"Newlands Rd",
    "iso:country":"AU",
    "sg:address":"48 Newlands Rd",
    "sg:city":"Reservoir",
    "sg:classifiers":[
        {
            "category":"Wholesale",
            "subcategory":"Auto Parts",
            "type":"Manufacturing & Wholesale Goods"
        }
    ],
    "sg:phone":"+61 3 9460 7797",
    "sg:postcode":"3073",
    "sg:province":"VIC",
    "sg:tags":[
        "recyclers"
    ],
    "wof:name":"Jap Heaven Auto Recyclers",
    "wof:placetype":"venue"
},
  "geometry": {"coordinates":[144.980377197,-37.719039917],"type":"Point"}
}