{
  "type": "Feature",
  "properties": {
    "iso:country":"AU",
    "sg:address":"401 Boston St",
    "sg:city":"Moree",
    "sg:classifiers":[
        {
            "category":"Professional",
            "subcategory":"Computer Services",
            "type":"Services"
        }
    ],
    "sg:phone":"+61 428 657 100",
    "sg:postcode":"2400",
    "sg:province":"NSW",
    "sg:tags":[
        "tele-communications",
        "consultant"
    ],
    "wof:name":"Groth Des Radiotronics",
    "wof:placetype":"venue"
},
  "geometry": {"coordinates":[149.8387146,-29.483455658],"type":"Point"}
}