{
  "type": "Feature",
  "properties": {
    "addr:full":"19 Marian St Mt Isa QLD 4825",
    "addr:housenumber":"19",
    "addr:postcode":"4825",
    "addr:street":"Marian St",
    "iso:country":"AU",
    "sg:address":"19 Marian St",
    "sg:city":"Mt Isa",
    "sg:classifiers":[
        {
            "category":"Communications",
            "subcategory":"News Services",
            "type":"Services"
        }
    ],
    "sg:phone":"+61 7 4749 1555",
    "sg:postcode":"4825",
    "sg:province":"QLD",
    "sg:tags":[
        "information",
        "tourist",
        "attractions"
    ],
    "wof:name":"Outback at Isa",
    "wof:placetype":"venue"
},
  "geometry": {"coordinates":[139.49659700000001,-20.725941],"type":"Point"}
}