{
  "type": "Feature",
  "properties": {
    "addr:full":"Martin St Dongara WA 6525",
    "addr:postcode":"6525",
    "addr:street":"Martin St",
    "iso:country":"AU",
    "sg:address":"Martin St",
    "sg:city":"Dongara",
    "sg:classifiers":[
        {
            "category":"Building & Trades",
            "subcategory":"Construction",
            "type":"Services"
        }
    ],
    "sg:phone":"+61 8 9927 1096",
    "sg:postcode":"6525",
    "sg:province":"WA",
    "sg:tags":[
        "concrete",
        "contractor"
    ],
    "wof:name":"Dongara Concrete Services",
    "wof:placetype":"venue"
},
  "geometry": {"coordinates":[114.93496704099999,-29.2507915497],"type":"Point"}
}