{
  "type": "Feature",
  "properties": {
    "iso:country":"AU",
    "sg:address":"102 Toorak Rd",
    "sg:city":"South Yarra",
    "sg:classifiers":[
        {
            "category":"Shopping",
            "subcategory":"News",
            "type":"Retail Goods"
        }
    ],
    "sg:phone":"+61 3 9823 6333",
    "sg:postcode":"3141",
    "sg:province":"VIC",
    "sg:tags":[
        "magazine",
        "periodical"
    ],
    "wof:name":"Take 5",
    "wof:placetype":"venue"
},
  "geometry": {"coordinates":[144.98956298799999,-37.8388366699],"type":"Point"}
}