{
  "type": "Feature",
  "properties": {
    "addr:full":"1/ 80 Winton Rd Joondalup WA 6027",
    "addr:housenumber":"/ 80",
    "addr:postcode":"6027",
    "addr:street":"Winton Rd",
    "iso:country":"AU",
    "sg:address":"1/ 80 Winton Rd",
    "sg:city":"Joondalup",
    "sg:classifiers":[
        {
            "category":"Retail",
            "subcategory":"Auto Repair",
            "type":"Services"
        }
    ],
    "sg:phone":"+61 8 9300 3637",
    "sg:postcode":"6027",
    "sg:province":"WA",
    "sg:tags":[
        "repairer",
        "motor",
        "engineer"
    ],
    "wof:name":"CAR Factory",
    "wof:placetype":"venue"
},
  "geometry": {"coordinates":[115.760108948,-31.7450332642],"type":"Point"}
}