{
  "type": "Feature",
  "properties": {
    "addr:full":"280 Ann St Brisbane QLD 4000",
    "addr:housenumber":"280",
    "addr:postcode":"4000",
    "addr:street":"Ann St",
    "iso:country":"AU",
    "sg:address":"280 Ann St",
    "sg:city":"Brisbane",
    "sg:classifiers":[
        {
            "category":"Health Services",
            "subcategory":"Doctor",
            "type":"Services"
        }
    ],
    "sg:phone":"+61 7 3229 1344",
    "sg:postcode":"4000",
    "sg:province":"QLD",
    "sg:tags":[
        "medical",
        "practitioner"
    ],
    "wof:name":"Anzac Square Medical Centre",
    "wof:placetype":"venue"
},
  "geometry": {"coordinates":[153.026779175,-27.4656257629],"type":"Point"}
}