{
  "type": "Feature",
  "properties": {
    "iso:country":"AU",
    "sg:address":"136 Glebe Rd",
    "sg:city":"Merewether",
    "sg:classifiers":[
        {
            "category":"Personal",
            "subcategory":"Massage",
            "type":"Services"
        }
    ],
    "sg:phone":"+61 2 4961 2561",
    "sg:postcode":"2291",
    "sg:province":"NSW",
    "sg:tags":[
        "therapy"
    ],
    "wof:name":"Merewether Medical Practice",
    "wof:placetype":"venue"
},
  "geometry": {"coordinates":[151.754470825,-32.9384078979],"type":"Point"}
}