{
  "type": "Feature",
  "properties": {
    "addr:full":"26 Shearer Drv Rowville VIC 3178",
    "addr:housenumber":"26",
    "addr:postcode":"3178",
    "addr:street":"Shearer Drv",
    "iso:country":"AU",
    "sg:address":"26 Shearer Drv",
    "sg:city":"Rowville",
    "sg:classifiers":[
        {
            "category":"Building & Trades",
            "subcategory":"Landscaping Services",
            "type":"Services"
        }
    ],
    "sg:phone":"+61 3 9755 6465",
    "sg:postcode":"3178",
    "sg:province":"VIC",
    "sg:tags":[
        "designer",
        "landscape",
        "contractor"
    ],
    "wof:name":"A Tailored Garden",
    "wof:placetype":"venue"
},
  "geometry": {"coordinates":[145.241912842,-37.937171936],"type":"Point"}
}