{
  "type": "Feature",
  "properties": {
    "addr:full":"Unit 6 172 Redland Bay Rd Capalaba QLD 4157",
    "addr:housenumber":"172",
    "addr:postcode":"4157",
    "addr:street":"Redland Bay Rd",
    "iso:country":"AU",
    "sg:address":"Unit 6 172 Redland Bay Rd",
    "sg:city":"Capalaba",
    "sg:classifiers":[
        {
            "category":"Wholesale",
            "subcategory":"Apparel",
            "type":"Manufacturing & Wholesale Goods"
        }
    ],
    "sg:phone":"+61 7 3390 3888",
    "sg:postcode":"4157",
    "sg:province":"QLD",
    "sg:tags":[
        "wholesaler",
        "mfrs",
        "uniform"
    ],
    "wof:name":"Corporate Designs Pty Ltd",
    "wof:placetype":"venue"
},
  "geometry": {"coordinates":[153.20155334500001,-27.5342597961],"type":"Point"}
}