{
  "type": "Feature",
  "properties": {
    "addr:full":"826 Pittwater Rd Dee Why NSW 2099",
    "addr:housenumber":"826",
    "addr:postcode":"2099",
    "addr:street":"Pittwater Rd",
    "iso:country":"AU",
    "sg:address":"826 Pittwater Rd",
    "sg:city":"Dee Why",
    "sg:classifiers":[
        {
            "category":"Fast Food",
            "type":"Food & Drink"
        }
    ],
    "sg:phone":"+61 2 9982 2443",
    "sg:postcode":"2099",
    "sg:province":"NSW",
    "sg:tags":[
        "away",
        "take"
    ],
    "wof:name":"Kebab World",
    "wof:placetype":"venue"
},
  "geometry": {"coordinates":[151.283111572,-33.7559738159],"type":"Point"}
}