{
  "type": "Feature",
  "properties": {
    "addr:full":"Shop 9 Gainsborough Centre 1032 Meehan Drv Kiama Downs NSW 2533",
    "addr:housenumber":"shop 9;1032",
    "addr:postcode":"2533",
    "addr:street":"Gainsborough Centre;Meehan Drv",
    "iso:country":"AU",
    "sg:address":"Shop 9 Gainsborough Centre 1032 Meehan Drv",
    "sg:city":"Kiama Downs",
    "sg:classifiers":[
        {
            "category":"Food & Beverages",
            "subcategory":"Liquor & Beverages",
            "type":"Retail Goods"
        }
    ],
    "sg:phone":"+61 2 4237 8608",
    "sg:postcode":"2533",
    "sg:province":"NSW",
    "sg:tags":[
        "store"
    ],
    "wof:name":"Liquorstop",
    "wof:placetype":"venue"
},
  "geometry": {"coordinates":[150.85018920900001,-34.6408691406],"type":"Point"}
}