{
  "type": "Feature",
  "properties": {
    "iso:country":"AU",
    "sg:address":"3/ 16 Hill St",
    "sg:city":"Camden",
    "sg:classifiers":[
        {
            "category":"Shopping",
            "subcategory":"Antiques",
            "type":"Retail Goods"
        }
    ],
    "sg:phone":"+61 2 4655 3853",
    "sg:postcode":"2570",
    "sg:province":"NSW",
    "wof:name":"Little Lane Books",
    "wof:placetype":"venue"
},
  "geometry": {"coordinates":[150.697555542,-34.0546646118],"type":"Point"}
}