{
  "type": "Feature",
  "properties": {
    "addr:full":"Unit 1, 14 Provident Ave Glynde SA 5070",
    "addr:housenumber":"14",
    "addr:postcode":"5070",
    "addr:street":"Provident Ave",
    "iso:country":"AU",
    "sg:address":"Unit 1, 14 Provident Ave",
    "sg:city":"Glynde",
    "sg:classifiers":[
        {
            "category":"Building & Trades",
            "subcategory":"Cleaning & Sanitation",
            "type":"Services"
        }
    ],
    "sg:phone":"+61 8 8365 4300",
    "sg:postcode":"5070",
    "sg:province":"SA",
    "sg:tags":[
        "industrial",
        "commercial",
        "contractor"
    ],
    "wof:name":"Berry Cleaning, Restoration Services",
    "wof:placetype":"venue"
},
  "geometry": {"coordinates":[138.65315246599999,-34.8947753906],"type":"Point"}
}