{
  "type": "Feature",
  "properties": {
    "iso:country":"AU",
    "sg:address":"674 Drummond St",
    "sg:city":"Carlton",
    "sg:classifiers":[
        {
            "category":"Professional",
            "subcategory":"Accounting & Tax Preparation",
            "type":"Services"
        }
    ],
    "sg:phone":"+61 403 300 721",
    "sg:postcode":"3053",
    "sg:province":"VIC",
    "sg:tags":[
        "bookkeeping"
    ],
    "wof:name":"Carlton Business Essentials",
    "wof:placetype":"venue"
},
  "geometry": {"coordinates":[144.96751403799999,-37.8037872314],"type":"Point"}
}