{
  "type": "Feature",
  "properties": {
    "addr:full":"6 Anderson Rd Malanda QLD 4885",
    "addr:housenumber":"6",
    "addr:postcode":"4885",
    "addr:street":"Anderson Rd",
    "iso:country":"AU",
    "sg:address":"6 Anderson Rd",
    "sg:city":"Malanda",
    "sg:classifiers":[
        {
            "category":"Shopping",
            "subcategory":"Computers & Home Electronics",
            "type":"Retail Goods"
        }
    ],
    "sg:phone":"+61 7 4096 5775",
    "sg:postcode":"4885",
    "sg:province":"QLD",
    "sg:tags":[
        "equipment",
        "multimedia"
    ],
    "wof:name":"Tabcom CD Rom Cards",
    "wof:placetype":"venue"
},
  "geometry": {"coordinates":[145.62448120100001,-17.3372249603],"type":"Point"}
}