{
  "type": "Feature",
  "properties": {
    "iso:country":"AU",
    "sg:address":"8 Belvedere Crs",
    "sg:city":"Bellmere",
    "sg:classifiers":[
        {
            "category":"Travel",
            "subcategory":"Hotels & Motels",
            "type":"Entertainment"
        }
    ],
    "sg:phone":"+61 7 5499 4060",
    "sg:postcode":"4510",
    "sg:province":"QLD",
    "sg:tags":[
        "accommodation"
    ],
    "wof:name":"Choice Hotels Australia",
    "wof:placetype":"venue"
},
  "geometry": {"coordinates":[152.868027,-27.08515],"type":"Point"}
}