{
  "type": "Feature",
  "properties": {
    "iso:country":"AU",
    "sg:address":"PO Box 1518",
    "sg:city":"Emerald",
    "sg:classifiers":[
        {
            "category":"Building & Trades",
            "subcategory":"Construction",
            "type":"Services"
        }
    ],
    "sg:phone":"+61 7 4982 4690",
    "sg:postcode":"4720",
    "sg:province":"QLD",
    "sg:tags":[
        "contractor"
    ],
    "wof:name":"Cardav Constructions",
    "wof:placetype":"venue"
},
  "geometry": {"coordinates":[148.15815699999999,-23.52487],"type":"Point"}
}