{
  "type": "Feature",
  "properties": {
    "addr:full":"9/ 5 Freda St Inverloch VIC 3996",
    "addr:housenumber":"/ 5",
    "addr:postcode":"3996",
    "addr:street":"Freda St",
    "iso:country":"AU",
    "sg:address":"9/ 5 Freda St",
    "sg:city":"Inverloch",
    "sg:classifiers":[
        {
            "category":"Professional",
            "subcategory":"Engineering",
            "type":"Services"
        }
    ],
    "sg:phone":"+61 3 5674 2220",
    "sg:postcode":"3996",
    "sg:province":"VIC",
    "sg:tags":[
        "consulting",
        "engineer"
    ],
    "wof:name":"Bloomfield Engineering Consultancy",
    "wof:placetype":"venue"
},
  "geometry": {"coordinates":[145.721024,-38.636795],"type":"Point"}
}