{
  "type": "Feature",
  "properties": {
    "addr:full":"Gate 3/421- 437 Grieve Pde Altona North VIC 3025",
    "addr:housenumber":"3 / 421 437",
    "addr:postcode":"3025",
    "addr:street":"Gate;Grieve Pde",
    "iso:country":"AU",
    "sg:address":"Gate 3/421- 437 Grieve Pde",
    "sg:city":"Altona North",
    "sg:classifiers":[
        {
            "category":"Professional",
            "subcategory":"Employment Agencies",
            "type":"Services"
        }
    ],
    "sg:phone":"+61 3 9369 0222",
    "sg:postcode":"3025",
    "sg:province":"VIC",
    "sg:tags":[
        "hire",
        "labour",
        "contractor"
    ],
    "wof:name":"Action Workforce",
    "wof:placetype":"venue"
},
  "geometry": {"coordinates":[144.82556199999999,-37.838017],"type":"Point"}
}