{
  "type": "Feature",
  "properties": {
    "addr:full":"36 Terrence Rd Brendale QLD 4500",
    "addr:housenumber":"36",
    "addr:postcode":"4500",
    "addr:street":"Terrence Rd",
    "iso:country":"AU",
    "sg:address":"36 Terrence Rd",
    "sg:city":"Brendale",
    "sg:classifiers":[
        {
            "category":"Professional",
            "type":"Services"
        }
    ],
    "sg:phone":"+61 7 3205 5535",
    "sg:postcode":"4500",
    "sg:province":"QLD",
    "sg:tags":[
        "shop",
        "fitting"
    ],
    "wof:name":"BSF",
    "wof:placetype":"venue"
},
  "geometry": {"coordinates":[152.98161315900001,-27.3199901581],"type":"Point"}
}