{
  "type": "Feature",
  "properties": {
    "iso:country":"AU",
    "sg:address":"Level 11, Corporate Centre",
    "sg:city":"Bundall",
    "sg:classifiers":[
        {
            "category":"Professional",
            "subcategory":"Accounting & Tax Preparation",
            "type":"Services"
        }
    ],
    "sg:phone":"+61 7 5577 7555",
    "sg:postcode":"4217",
    "sg:province":"QLD",
    "sg:tags":[
        "accountant",
        "auditor"
    ],
    "wof:name":"KPMG",
    "wof:placetype":"venue"
},
  "geometry": {"coordinates":[153.40594482399999,-28.0103492737],"type":"Point"}
}