{
  "type": "Feature",
  "properties": {
    "addr:full":"Cnr Bennett & Mirrenn Sts Hawks Nest NSW 2324",
    "addr:postcode":"2324",
    "addr:street":"Cnr",
    "iso:country":"AU",
    "sg:address":"Cnr Bennett & Mirrenn Sts",
    "sg:city":"Hawks Nest",
    "sg:classifiers":[
        {
            "category":"Real Estate",
            "subcategory":"Real Estate Services",
            "type":"Services"
        }
    ],
    "sg:phone":"+61 2 4997 9661",
    "sg:postcode":"2324",
    "sg:province":"NSW",
    "sg:tags":[
        "valuer"
    ],
    "wof:name":"McMonigal Valuations",
    "wof:placetype":"venue"
},
  "geometry": {"coordinates":[152.18211364699999,-32.6596183777],"type":"Point"}
}