{
  "type": "Feature",
  "properties": {
    "iso:country":"AU",
    "sg:address":"9 Link Rd St",
    "sg:city":"Ives",
    "sg:classifiers":[
        {
            "category":"Manufacturing",
            "subcategory":"Food",
            "type":"Manufacturing & Wholesale Goods"
        }
    ],
    "sg:phone":"+61 2 9488 7222",
    "sg:postcode":"2075",
    "sg:province":"NSW",
    "sg:tags":[
        "function",
        "catering"
    ],
    "wof:name":"Cherry Bim Kosher Catering",
    "wof:placetype":"venue"
},
  "geometry": {"coordinates":[151.16612243599999,-33.7292442322],"type":"Point"}
}