{
  "type": "Feature",
  "properties": {
    "iso:country":"AU",
    "sg:address":"Shp 1/ 2 Moresby St",
    "sg:city":"Kensington",
    "sg:classifiers":[
        {
            "category":"Food & Beverages",
            "subcategory":"Meat & Fish",
            "type":"Retail Goods"
        }
    ],
    "sg:phone":"+61 8 9367 7000",
    "sg:postcode":"6151",
    "sg:province":"WA",
    "sg:tags":[
        "seafood"
    ],
    "wof:name":"Battered and a&#039;Salted",
    "wof:placetype":"venue"
},
  "geometry": {"coordinates":[115.879936,-31.988668],"type":"Point"}
}