{
  "type": "Feature",
  "properties": {
    "addr:full":"9 Arunga St Alice Springs NT 0870",
    "addr:housenumber":"9",
    "addr:postcode":"nt 0870",
    "addr:street":"Arunga St",
    "iso:country":"AU",
    "sg:address":"9 Arunga St",
    "sg:city":"Alice Springs",
    "sg:classifiers":[
        {
            "category":"Restaurant",
            "type":"Food & Drink"
        }
    ],
    "sg:phone":"+61 8 8952 2922",
    "sg:postcode":"0870",
    "sg:province":"NT",
    "wof:name":"Camp Oven Kitchen The",
    "wof:placetype":"venue"
},
  "geometry": {"coordinates":[133.871185303,-23.7165603638],"type":"Point"}
}