{
  "type": "Feature",
  "properties": {
    "iso:country":"AU",
    "sg:address":"35 Warrawee Rd",
    "sg:city":"Mt Evelyn",
    "sg:classifiers":[
        {
            "category":"Utilities",
            "subcategory":"Electric",
            "type":"Services"
        }
    ],
    "sg:phone":"+61 418 383 868",
    "sg:postcode":"3796",
    "sg:province":"VIC",
    "sg:tags":[
        "electrical",
        "contractor"
    ],
    "wof:name":"Heritage Electrics Pty Ltd",
    "wof:placetype":"venue"
},
  "geometry": {"coordinates":[145.378295898,-37.8025398254],"type":"Point"}
}