{
  "type": "Feature",
  "properties": {
    "addr:full":"Suite 1A, 899 Whitehorse Rd Box Hill VIC 3128",
    "addr:housenumber":"899",
    "addr:postcode":"3128",
    "addr:street":"Whitehorse Rd",
    "iso:country":"AU",
    "sg:address":"Suite 1A, 899 Whitehorse Rd",
    "sg:city":"Box Hill",
    "sg:classifiers":[
        {
            "category":"Travel",
            "subcategory":"Travel Agent",
            "type":"Entertainment"
        }
    ],
    "sg:phone":"+61 3 9898 2011",
    "sg:postcode":"3128",
    "sg:province":"VIC",
    "sg:tags":[
        "consultant"
    ],
    "wof:name":"Cruise Consultants",
    "wof:placetype":"venue"
},
  "geometry": {"coordinates":[145.120803833,-37.8173980713],"type":"Point"}
}