{
  "type": "Feature",
  "properties": {
    "addr:full":"229 Punt Rd Richmond VIC 3121",
    "addr:housenumber":"229",
    "addr:postcode":"3121",
    "addr:street":"Punt Rd",
    "iso:country":"AU",
    "sg:address":"229 Punt Rd",
    "sg:city":"Richmond",
    "sg:classifiers":[
        {
            "category":"Real Estate",
            "subcategory":"Architect",
            "type":"Services"
        }
    ],
    "sg:phone":"+61 3 9421 1811",
    "sg:postcode":"3121",
    "sg:province":"VIC",
    "wof:name":"Zone Design",
    "wof:placetype":"venue"
},
  "geometry": {"coordinates":[144.98991394000001,-37.8192558289],"type":"Point"}
}