{
  "type": "Feature",
  "properties": {
    "addr:full":"2/ 35 Barry Ave Mortdale NSW 2223",
    "addr:housenumber":"/ 35",
    "addr:postcode":"2223",
    "addr:street":"Barry Ave",
    "iso:country":"AU",
    "sg:address":"2/ 35 Barry Ave",
    "sg:city":"Mortdale",
    "sg:classifiers":[
        {
            "category":"Shopping",
            "subcategory":"Party Supplies",
            "type":"Retail Goods"
        }
    ],
    "sg:phone":"+61 2 9534 3333",
    "sg:postcode":"2223",
    "sg:province":"NSW",
    "sg:tags":[
        "children's"
    ],
    "wof:name":"Fun House Adventure Play and Party Centre",
    "wof:placetype":"venue"
},
  "geometry": {"coordinates":[151.068725586,-33.9670257568],"type":"Point"}
}