{
  "type": "Feature",
  "properties": {
    "iso:country":"AU",
    "sg:address":"2 Vost St",
    "sg:city":"Coffs Harbour",
    "sg:classifiers":[
        {
            "category":"Real Estate",
            "subcategory":"Real Estate Agent",
            "type":"Services"
        }
    ],
    "sg:phone":"+61 2 6651 4812",
    "sg:postcode":"2450",
    "sg:province":"NSW",
    "wof:name":"Nautique Property Sales",
    "wof:placetype":"venue"
},
  "geometry": {"coordinates":[153.134827,-30.296577],"type":"Point"}
}