{
  "type": "Feature",
  "properties": {
    "addr:full":"Driscoll Rd Narrandera NSW 2700",
    "addr:postcode":"2700",
    "addr:street":"Driscoll Rd",
    "iso:country":"AU",
    "sg:address":"Driscoll Rd",
    "sg:city":"Narrandera",
    "sg:classifiers":[
        {
            "category":"Manufacturing",
            "subcategory":"Building Materials",
            "type":"Manufacturing & Wholesale Goods"
        }
    ],
    "sg:phone":"+61 2 6959 9115",
    "sg:postcode":"2700",
    "sg:province":"NSW",
    "sg:tags":[
        "aggregate",
        "concrete"
    ],
    "wof:name":"Area Pre-Mix",
    "wof:placetype":"venue"
},
  "geometry": {"coordinates":[146.57211303700001,-34.7278862],"type":"Point"}
}