{
  "type": "Feature",
  "properties": {
    "addr:full":"Council Pl Esperance WA 6450",
    "addr:postcode":"6450",
    "addr:street":"Council Pl",
    "iso:country":"AU",
    "sg:address":"Council Pl",
    "sg:city":"Esperance",
    "sg:classifiers":[
        {
            "category":"Retail",
            "subcategory":"Event Space",
            "type":"Services"
        }
    ],
    "sg:phone":"+61 8 9083 1566",
    "sg:postcode":"6450",
    "sg:province":"WA",
    "sg:tags":[
        "venue",
        "reception",
        "wedding"
    ],
    "wof:name":"Esperance Civic Centre",
    "wof:placetype":"venue"
},
  "geometry": {"coordinates":[121.889907837,-33.860584259],"type":"Point"}
}