{
  "type": "Feature",
  "properties": {
    "iso:country":"AU",
    "sg:address":"PO Box 3178",
    "sg:city":"Asquith",
    "sg:classifiers":[
        {
            "category":"Building & Trades",
            "subcategory":"Equipment Rental",
            "type":"Services"
        }
    ],
    "sg:phone":"+61 411 431 593",
    "sg:postcode":"2077",
    "sg:province":"NSW",
    "sg:tags":[
        "demolition",
        "contractor"
    ],
    "wof:name":"Precision Demolition",
    "wof:placetype":"venue"
},
  "geometry": {"coordinates":[151.10940551799999,-33.6891212463],"type":"Point"}
}