{
  "type": "Feature",
  "properties": {
    "addr:full":"Bath La Bendigo VIC 3550",
    "addr:postcode":"3550",
    "iso:country":"AU",
    "sg:address":"Bath La",
    "sg:city":"Bendigo",
    "sg:classifiers":[
        {
            "category":"Personal",
            "subcategory":"Massage",
            "type":"Services"
        }
    ],
    "sg:phone":"+61 3 5441 3354",
    "sg:postcode":"3550",
    "sg:province":"VIC",
    "sg:tags":[
        "therapy"
    ],
    "wof:name":"Fernwood Massage Clinic",
    "wof:placetype":"venue"
},
  "geometry": {"coordinates":[144.27815246599999,-36.7608032227],"type":"Point"}
}