{
  "type": "Feature",
  "properties": {
    "addr:full":"1st Floor, 108 Stirling Tce Albany WA 6330",
    "addr:housenumber":"108",
    "addr:postcode":"6330",
    "addr:street":"Stirling Tce",
    "iso:country":"AU",
    "sg:address":"1st Floor, 108 Stirling Tce",
    "sg:city":"Albany",
    "sg:classifiers":[
        {
            "category":"Professional",
            "subcategory":"Computer Services",
            "type":"Services"
        }
    ],
    "sg:phone":"+61 8 9842 1377",
    "sg:postcode":"6330",
    "sg:province":"WA",
    "sg:tags":[
        "equipment",
        "networking",
        "installation"
    ],
    "wof:name":"Alphawest",
    "wof:placetype":"venue"
},
  "geometry": {"coordinates":[117.88471984900001,-35.0268745422],"type":"Point"}
}