{
  "type": "Feature",
  "properties": {
    "iso:country":"AU",
    "sg:address":"214a Great Western Hwy",
    "sg:city":"Kingswood",
    "sg:classifiers":[
        {
            "category":"Banks & Credit Unions",
            "subcategory":"Investment Brokerage",
            "type":"Services"
        }
    ],
    "sg:phone":"+61 2 4736 5600",
    "sg:postcode":"2747",
    "sg:province":"NSW",
    "sg:tags":[
        "management",
        "property"
    ],
    "wof:name":"Vernon Realty Penrith",
    "wof:placetype":"venue"
},
  "geometry": {"coordinates":[150.71875,-33.7585220337],"type":"Point"}
}