{
  "type": "Feature",
  "properties": {
    "addr:full":"48 Clyde Ave Moorebank NSW 2170",
    "addr:housenumber":"48",
    "addr:postcode":"2170",
    "addr:street":"Clyde Ave",
    "iso:country":"AU",
    "sg:address":"48 Clyde Ave",
    "sg:city":"Moorebank",
    "sg:classifiers":[
        {
            "category":"Travel",
            "subcategory":"Travel Agent",
            "type":"Entertainment"
        }
    ],
    "sg:phone":"+61 2 9018 9184",
    "sg:postcode":"2170",
    "sg:province":"NSW",
    "sg:tags":[
        "consultant"
    ],
    "wof:name":"Accom.Com.Au",
    "wof:placetype":"venue"
},
  "geometry": {"coordinates":[150.95338439899999,-33.9422607422],"type":"Point"}
}