{
  "type": "Feature",
  "properties": {
    "addr:full":"Springfield Lakes Natural Medicine Building Sumner Springfield QLD 4300",
    "addr:postcode":"4300",
    "iso:country":"AU",
    "sg:address":"Springfield Lakes Natural Medicine Building Sumner",
    "sg:city":"Springfield",
    "sg:classifiers":[
        {
            "category":"Health Services",
            "subcategory":"Health Practitioner",
            "type":"Services"
        }
    ],
    "sg:phone":"+61 7 3818 9199",
    "sg:postcode":"4300",
    "sg:province":"QLD",
    "sg:tags":[
        "acupuncture"
    ],
    "wof:name":"Master Nina",
    "wof:placetype":"venue"
},
  "geometry": {"coordinates":[152.900024414,-27.5629310608],"type":"Point"}
}