{
  "type": "Feature",
  "properties": {
    "addr:full":"Cnr Ninabah & Clarence Sts Howrah TAS 7018",
    "addr:postcode":"7018",
    "addr:street":"Cnr Ninabah",
    "iso:country":"AU",
    "sg:address":"Cnr Ninabah & Clarence Sts",
    "sg:city":"Howrah",
    "sg:classifiers":[
        {
            "category":"Health Services",
            "subcategory":"Dentist",
            "type":"Services"
        }
    ],
    "sg:phone":"+61 3 6244 1661",
    "sg:postcode":"7018",
    "sg:province":"TAS",
    "sg:tags":[
        "dental",
        "prosthetist"
    ],
    "wof:name":"Peter H Skeggs",
    "wof:placetype":"venue"
},
  "geometry": {"coordinates":[147.397994995,-42.8777542114],"type":"Point"}
}