{
  "type": "Feature",
  "properties": {
    "iso:country":"AU",
    "sg:address":"19 Hallstrom Pl",
    "sg:city":"Wetherill Park",
    "sg:classifiers":[
        {
            "category":"Manufacturing",
            "subcategory":"Building Materials",
            "type":"Manufacturing & Wholesale Goods"
        }
    ],
    "sg:phone":"+61 1300 650 035",
    "sg:postcode":"2164",
    "sg:province":"NSW",
    "sg:tags":[
        "equipment",
        "handling"
    ],
    "wof:name":"Materials Handling Pty Ltd",
    "wof:placetype":"venue"
},
  "geometry": {"coordinates":[150.885055542,-33.8449172974],"type":"Point"}
}