{
  "type": "Feature",
  "properties": {
    "iso:country":"AU",
    "sg:address":"181 Tower St",
    "sg:city":"Panania",
    "sg:classifiers":[
        {
            "category":"Retail",
            "subcategory":"Funeral Services",
            "type":"Services"
        }
    ],
    "sg:phone":"+61 2 9792 4777",
    "sg:postcode":"2213",
    "sg:province":"NSW",
    "sg:tags":[
        "director"
    ],
    "wof:name":"John Wheatley Funeral Services",
    "wof:placetype":"venue"
},
  "geometry": {"coordinates":[151.001434,-33.956657],"type":"Point"}
}