{
  "type": "Feature",
  "properties": {
    "addr:full":"84 Wallace St Braidwood NSW 2622",
    "addr:housenumber":"84",
    "addr:postcode":"2622",
    "addr:street":"Wallace St",
    "iso:country":"AU",
    "sg:address":"84 Wallace St",
    "sg:city":"Braidwood",
    "sg:classifiers":[
        {
            "category":"Arts & Performance",
            "subcategory":"Art Gallery",
            "type":"Entertainment"
        }
    ],
    "sg:phone":"+61 2 4842 1142",
    "sg:postcode":"2622",
    "sg:province":"NSW",
    "wof:name":"Hannah Fyre Enterprises",
    "wof:placetype":"venue"
},
  "geometry": {"coordinates":[149.80111694300001,-35.4372406006],"type":"Point"}
}