{
  "type": "Feature",
  "properties": {
    "addr:full":"Shp2/ 130a Waterloo Rd Greenacre NSW 2190",
    "addr:housenumber":"130a",
    "addr:postcode":"2190",
    "addr:street":"Waterloo Rd",
    "iso:country":"AU",
    "sg:address":"Shp2/ 130a Waterloo Rd",
    "sg:city":"Greenacre",
    "sg:classifiers":[
        {
            "category":"Fast Food",
            "type":"Food & Drink"
        }
    ],
    "sg:phone":"+61 2 9758 1855",
    "sg:postcode":"2190",
    "sg:province":"NSW",
    "sg:tags":[
        "away",
        "take"
    ],
    "wof:name":"Ziggys Kebabs & Coffee Shop",
    "wof:placetype":"venue"
},
  "geometry": {"coordinates":[151.05819700000001,-33.90205],"type":"Point"}
}