{
  "type": "Feature",
  "properties": {
    "iso:country":"AU",
    "sg:address":"Factory 3 Lot 3, Ozone Street",
    "sg:city":"Chinderah",
    "sg:classifiers":[
        {
            "category":"Retail",
            "subcategory":"Auto Repair",
            "type":"Services"
        }
    ],
    "sg:phone":"+61 2 6674 0529",
    "sg:postcode":"2487",
    "sg:province":"NSW",
    "sg:tags":[
        "beater",
        "painter",
        "panel"
    ],
    "wof:name":"Chinderah Smash Repairs",
    "wof:placetype":"venue"
},
  "geometry": {"coordinates":[153.55592346200001,-28.2443256378],"type":"Point"}
}