{
  "type": "Feature",
  "properties": {
    "addr:full":"23 Bronte Rd Bondi Junction NSW 2022",
    "addr:housenumber":"23",
    "addr:postcode":"2022",
    "addr:street":"Bronte Rd",
    "iso:country":"AU",
    "sg:address":"23 Bronte Rd",
    "sg:city":"Bondi Junction",
    "sg:classifiers":[
        {
            "category":"Shopping",
            "subcategory":"News",
            "type":"Retail Goods"
        }
    ],
    "sg:phone":"+61 2 9369 3344",
    "sg:postcode":"2022",
    "sg:province":"NSW",
    "sg:tags":[
        "magazine",
        "periodical"
    ],
    "wof:name":"Sky & Space Magazine & Discovery Shop",
    "wof:placetype":"venue"
},
  "geometry": {"coordinates":[151.24949645999999,-33.8929328918],"type":"Point"}
}