{
  "type": "Feature",
  "properties": {
    "iso:country":"AU",
    "sg:address":"123 Highland Ave",
    "sg:city":"Yagoona",
    "sg:classifiers":[
        {
            "category":"Retail",
            "subcategory":"Auto Repair",
            "type":"Services"
        }
    ],
    "sg:phone":"+61 414 673 150",
    "sg:postcode":"2199",
    "sg:province":"NSW",
    "sg:tags":[
        "repairer",
        "motor",
        "engineer"
    ],
    "wof:name":"Metromech",
    "wof:placetype":"venue"
},
  "geometry": {"coordinates":[151.023697,-33.909492],"type":"Point"}
}