{
  "type": "Feature",
  "properties": {
    "addr:full":"10 Alexander St Avondale Heights VIC 3034",
    "addr:housenumber":"10",
    "addr:postcode":"3034",
    "addr:street":"Alexander St",
    "iso:country":"AU",
    "sg:address":"10 Alexander St",
    "sg:city":"Avondale Heights",
    "sg:classifiers":[
        {
            "category":"Building & Trades",
            "subcategory":"Construction",
            "type":"Services"
        }
    ],
    "sg:phone":"+61 3 9318 4440",
    "sg:postcode":"3034",
    "sg:province":"VIC",
    "sg:tags":[
        "plasterboard",
        "plasterer",
        "fixer"
    ],
    "wof:name":"Moonee Valley Plastering",
    "wof:placetype":"venue"
},
  "geometry": {"coordinates":[144.86802700000001,-37.766903],"type":"Point"}
}