{
  "type": "Feature",
  "properties": {
    "addr:full":"Suite 7, 277 Mann St Gosford NSW 2250",
    "addr:housenumber":"277",
    "addr:postcode":"2250",
    "addr:street":"Mann St",
    "iso:country":"AU",
    "sg:address":"Suite 7, 277 Mann St",
    "sg:city":"Gosford",
    "sg:classifiers":[
        {
            "category":"Education",
            "subcategory":"Special Training",
            "type":"Public Place"
        }
    ],
    "sg:phone":"+61 2 4322 0466",
    "sg:postcode":"2250",
    "sg:province":"NSW",
    "sg:tags":[
        "development"
    ],
    "wof:name":"Central Coast Auto",
    "wof:placetype":"venue"
},
  "geometry": {"coordinates":[151.342987061,-33.4220962524],"type":"Point"}
}