{
  "type": "Feature",
  "properties": {
    "addr:full":"8 / 30 Heathcote Rd Moorebank NSW 2170",
    "addr:housenumber":"/ 30",
    "addr:postcode":"2170",
    "addr:street":"Heathcote Rd",
    "iso:country":"AU",
    "sg:address":"8 / 30 Heathcote Rd",
    "sg:city":"Moorebank",
    "sg:classifiers":[
        {
            "category":"Military Area",
            "subcategory":"Naval Base",
            "type":"Public Place"
        }
    ],
    "sg:phone":"+61 2 9824 3844",
    "sg:postcode":"2170",
    "sg:province":"NSW",
    "sg:tags":[
        "stand",
        "rack"
    ],
    "wof:name":"Schaefer Systems International Pty Ltd",
    "wof:placetype":"venue"
},
  "geometry": {"coordinates":[150.93348693900001,-33.9315338135],"type":"Point"}
}