{
  "type": "Feature",
  "properties": {
    "iso:country":"AU",
    "sg:address":"10 Faucett St",
    "sg:city":"Blackalls Park",
    "sg:classifiers":[
        {
            "category":"Sports & Exercise",
            "subcategory":"Sports Center",
            "type":"Entertainment"
        }
    ],
    "sg:phone":"+61 2 4950 5099",
    "sg:postcode":"2283",
    "sg:province":"NSW",
    "sg:tags":[
        "coach",
        "tennis"
    ],
    "wof:name":"Silveradoh",
    "wof:placetype":"venue"
},
  "geometry": {"coordinates":[151.579177856,-33.000869751],"type":"Point"}
}