{
  "type": "Feature",
  "properties": {
    "iso:country":"AU",
    "sg:address":"168 Marine Pde",
    "sg:city":"Southport",
    "sg:classifiers":[
        {
            "category":"Autos & Motor Vehicles",
            "subcategory":"Auto Supplies",
            "type":"Retail Goods"
        }
    ],
    "sg:phone":"+61 7 5591 2655",
    "sg:postcode":"4215",
    "sg:province":"QLD",
    "sg:tags":[
        "tyre"
    ],
    "wof:name":"Bob Jane T-Mart",
    "wof:placetype":"venue"
},
  "geometry": {"coordinates":[153.4090271,-27.9562149048],"type":"Point"}
}