{
  "type": "Feature",
  "properties": {
    "iso:country":"AU",
    "sg:address":"Unit 13 99 Moore St",
    "sg:city":"Leichhardt",
    "sg:classifiers":[
        {
            "category":"Manufacturing",
            "subcategory":"Motor Vehicles & Parts",
            "type":"Manufacturing & Wholesale Goods"
        }
    ],
    "sg:phone":"+61 2 9518 0866",
    "sg:postcode":"2040",
    "sg:province":"NSW",
    "sg:tags":[
        "replacement"
    ],
    "wof:name":"Sydney Drive Shaft",
    "wof:placetype":"venue"
},
  "geometry": {"coordinates":[151.161057,-33.878403],"type":"Point"}
}