{
  "type": "Feature",
  "properties": {
    "iso:country":"AU",
    "sg:address":"187 Lyons Rd",
    "sg:city":"Drummoyne",
    "sg:classifiers":[
        {
            "category":"Cafe",
            "type":"Food & Drink"
        }
    ],
    "sg:phone":"+61 2 9181 1922",
    "sg:postcode":"2047",
    "sg:province":"NSW",
    "wof:name":"Reginaldos Pizza Bar",
    "wof:placetype":"venue"
},
  "geometry": {"coordinates":[151.146317,-33.856655],"type":"Point"}
}