{
  "type": "Feature",
  "properties": {
    "addr:full":"Cnr Hapdem Ave & Marrah St Wagga Wagga North NSW 2650",
    "addr:postcode":"2650",
    "addr:street":"Cnr Hapdem Ave & Marrah St",
    "iso:country":"AU",
    "sg:address":"Cnr Hapdem Ave & Marrah St",
    "sg:city":"Wagga Wagga North",
    "sg:classifiers":[
        {
            "category":"Autos & Motor Vehicles",
            "subcategory":"Fuel & Gas Station",
            "type":"Retail Goods"
        }
    ],
    "sg:phone":"+61 2 6921 3829",
    "sg:postcode":"2650",
    "sg:province":"NSW",
    "wof:name":"Ampol Petroleum (Vic) Pty Ltd",
    "wof:placetype":"venue"
},
  "geometry": {"coordinates":[147.542144775,-35.1158332825],"type":"Point"}
}