{
  "type": "Feature",
  "properties": {
    "addr:full":"Cnr Allen St & Princes Hwy Bexley NSW 2207",
    "addr:postcode":"2207",
    "addr:street":"Cnr Allen St & Princes Hwy",
    "iso:country":"AU",
    "sg:address":"Cnr Allen St & Princes Hwy",
    "sg:city":"Bexley",
    "sg:classifiers":[
        {
            "category":"Home & Garden",
            "subcategory":"Hardware",
            "type":"Retail Goods"
        }
    ],
    "sg:phone":"+61 13 63 36",
    "sg:postcode":"2207",
    "sg:province":"NSW",
    "sg:tags":[
        "generating",
        "set",
        "generator"
    ],
    "wof:name":"National Hire The Cat Rental Store",
    "wof:placetype":"venue"
},
  "geometry": {"coordinates":[151.15062,-33.935543],"type":"Point"}
}