{
  "type": "Feature",
  "properties": {
    "iso:country":"AU",
    "sg:address":"135 Julia Flynn Ave",
    "sg:city":"Isaacs",
    "sg:classifiers":[
        {
            "category":"Personal",
            "subcategory":"Beauty Salon",
            "type":"Services"
        }
    ],
    "sg:phone":"+61 2 6286 8178",
    "sg:postcode":"2607",
    "sg:province":"ACT",
    "wof:name":"Beauty By The Pines",
    "wof:placetype":"venue"
},
  "geometry": {"coordinates":[149.115722656,-35.3724784851],"type":"Point"}
}