{
  "type": "Feature",
  "properties": {
    "iso:country":"AU",
    "sg:address":"Suite 10811, AMP Centre, 24 Gordon St",
    "sg:city":"Coffs Harbour",
    "sg:classifiers":[
        {
            "category":"Professional",
            "subcategory":"Employment Agencies",
            "type":"Services"
        }
    ],
    "sg:phone":"+61 2 6658 0299",
    "sg:postcode":"2450",
    "sg:province":"NSW",
    "wof:name":"H & H Accredited Training",
    "wof:placetype":"venue"
},
  "geometry": {"coordinates":[153.116302,-30.298239],"type":"Point"}
}