{
  "type": "Feature",
  "properties": {
    "addr:full":"Suite 10811, AMP Centre, 24 Gordon St Coffs Harbour NSW 2450",
    "addr:housenumber":"24",
    "addr:postcode":"2450",
    "addr:street":"Gordon St",
    "iso:country":"AU",
    "sg:address":"Suite 10811, AMP Centre, 24 Gordon St",
    "sg:city":"Coffs Harbour",
    "sg:classifiers":[
        {
            "category":"Professional",
            "subcategory":"Employment Agencies",
            "type":"Services"
        }
    ],
    "sg:phone":"+61 2 6658 0299",
    "sg:postcode":"2450",
    "sg:province":"NSW",
    "wof:name":"H & H Accredited Training",
    "wof:placetype":"venue"
},
  "geometry": {"coordinates":[153.11630199999999,-30.298239],"type":"Point"}
}