{
  "type": "Feature",
  "properties": {
    "iso:country":"AU",
    "sg:address":"470 Main St",
    "sg:city":"Kangaroo Point",
    "sg:classifiers":[
        {
            "category":"Personal",
            "subcategory":"Massage",
            "type":"Services"
        }
    ],
    "sg:phone":"+61 7 3391 3111",
    "sg:postcode":"4169",
    "sg:province":"QLD",
    "sg:tags":[
        "therapy"
    ],
    "sg:website":"http://www.bodiesateez.com.au",
    "wof:name":"Bodies @ Eez",
    "wof:placetype":"venue"
},
  "geometry": {"coordinates":[153.035842895,-27.4756946564],"type":"Point"}
}