{
  "type": "Feature",
  "properties": {
    "iso:country":"AU",
    "sg:address":"1/ 22 Commercial Drv",
    "sg:city":"Southport",
    "sg:classifiers":[
        {
            "category":"Food & Beverages",
            "subcategory":"Fruits & Vegetables",
            "type":"Retail Goods"
        }
    ],
    "sg:phone":"+61 7 5532 3434",
    "sg:postcode":"4215",
    "sg:province":"QLD",
    "sg:tags":[
        "wholesale"
    ],
    "wof:name":"Ashmore Wholesale Markets",
    "wof:placetype":"venue"
},
  "geometry": {"coordinates":[153.38929748499999,-27.9800796509],"type":"Point"}
}