{
  "type": "Feature",
  "properties": {
    "iso:country":"AU",
    "sg:address":"164 Lime Ave",
    "sg:city":"Mildura",
    "sg:classifiers":[
        {
            "category":"Professional",
            "subcategory":"Accounting & Tax Preparation",
            "type":"Services"
        }
    ],
    "sg:phone":"+61 3 5021 1110",
    "sg:postcode":"3500",
    "sg:province":"VIC",
    "sg:tags":[
        "accountant",
        "auditor"
    ],
    "wof:name":"DHM Partners",
    "wof:placetype":"venue"
},
  "geometry": {"coordinates":[142.15544128400001,-34.1877098083],"type":"Point"}
}