{
  "type": "Feature",
  "properties": {
    "iso:country":"AU",
    "sg:address":"24- 28 Courtney St",
    "sg:city":"North Melbourne",
    "sg:classifiers":[
        {
            "category":"Retail",
            "subcategory":"Auto Rental",
            "type":"Services"
        }
    ],
    "sg:phone":"+61 3 9328 1800",
    "sg:postcode":"3051",
    "sg:province":"VIC",
    "sg:tags":[
        "car",
        "hire",
        "minibus"
    ],
    "wof:name":"Hertz",
    "wof:placetype":"venue"
},
  "geometry": {"coordinates":[144.95460510300001,-37.8022766113],"type":"Point"}
}