{
  "type": "Feature",
  "properties": {
    "addr:full":"7 Kamiri St Seaforth NSW 2092",
    "addr:housenumber":"7",
    "addr:postcode":"2092",
    "addr:street":"Kamiri St",
    "iso:country":"AU",
    "sg:address":"7 Kamiri St",
    "sg:city":"Seaforth",
    "sg:classifiers":[
        {
            "category":"Professional",
            "subcategory":"Accounting & Tax Preparation",
            "type":"Services"
        }
    ],
    "sg:phone":"+61 2 9948 5945",
    "sg:postcode":"2092",
    "sg:province":"NSW",
    "sg:tags":[
        "accountant",
        "auditor"
    ],
    "wof:name":"C J Farley Financial Services",
    "wof:placetype":"venue"
},
  "geometry": {"coordinates":[151.24395751899999,-33.7877349854],"type":"Point"}
}