{
  "type": "Feature",
  "properties": {
    "addr:full":"1/ 102 Islander Rd Hervey Bay QLD 4655",
    "addr:housenumber":"/ 102",
    "addr:postcode":"4655",
    "addr:street":"Islander Rd",
    "iso:country":"AU",
    "sg:address":"1/ 102 Islander Rd",
    "sg:city":"Hervey Bay",
    "sg:classifiers":[
        {
            "category":"Professional",
            "subcategory":"Detective & Security Services",
            "type":"Services"
        }
    ],
    "sg:phone":"+61 7 4124 5666",
    "sg:postcode":"4655",
    "sg:province":"QLD",
    "sg:tags":[
        "equipment",
        "window",
        "doors"
    ],
    "wof:name":"Advantage Screens & Blinds",
    "wof:placetype":"venue"
},
  "geometry": {"coordinates":[152.831467,-25.285175],"type":"Point"}
}