{
  "type": "Feature",
  "properties": {
    "iso:country":"AU",
    "sg:address":"17- 21 Cockburn Rd",
    "sg:city":"Albany",
    "sg:classifiers":[
        {
            "category":"Home & Garden",
            "subcategory":"Building Materials",
            "type":"Retail Goods"
        }
    ],
    "sg:phone":"+61 8 9842 1533",
    "sg:postcode":"6330",
    "sg:province":"WA",
    "sg:tags":[
        "wall",
        "frame",
        "truss",
        "roof"
    ],
    "wof:name":"Rainbow Frame & Truss Co",
    "wof:placetype":"venue"
},
  "geometry": {"coordinates":[117.895652771,-35.0156936646],"type":"Point"}
}