{
  "type": "Feature",
  "properties": {
    "addr:full":"32 Low St Bundaberg QLD 4670",
    "addr:housenumber":"32",
    "addr:postcode":"4670",
    "addr:street":"Low St",
    "iso:country":"AU",
    "sg:address":"32 Low St",
    "sg:city":"Bundaberg",
    "sg:classifiers":[
        {
            "category":"Building & Trades",
            "subcategory":"Construction",
            "type":"Services"
        }
    ],
    "sg:phone":"+61 7 4155 1218",
    "sg:postcode":"4670",
    "sg:province":"QLD",
    "sg:tags":[
        "earth",
        "excavating",
        "moving",
        "contractor"
    ],
    "wof:name":"Russell McCracken Backhoe & Tip Truck Hire",
    "wof:placetype":"venue"
},
  "geometry": {"coordinates":[152.32241821299999,-24.9129219055],"type":"Point"}
}