{
  "type": "Feature",
  "properties": {
    "addr:full":"Main St Crafers SA 5152",
    "addr:postcode":"5152",
    "addr:street":"Main St",
    "iso:country":"AU",
    "sg:address":"Main St",
    "sg:city":"Crafers",
    "sg:classifiers":[
        {
            "category":"Building & Trades",
            "subcategory":"Construction",
            "type":"Services"
        }
    ],
    "sg:phone":"+61 8 8370 1400",
    "sg:postcode":"5152",
    "sg:province":"SA",
    "sg:tags":[
        "contractor"
    ],
    "wof:name":"Johansen F P & Sons",
    "wof:placetype":"venue"
},
  "geometry": {"coordinates":[138.70338439899999,-34.9971847534],"type":"Point"}
}