{
  "type": "Feature",
  "properties": {
    "iso:country":"AU",
    "sg:address":"The Wheel House 14/37 Nicholson St",
    "sg:city":"Balmain",
    "sg:classifiers":[
        {
            "category":"Professional",
            "subcategory":"Business Services",
            "type":"Services"
        }
    ],
    "sg:phone":"+61 419 497 853",
    "sg:postcode":"2041",
    "sg:province":"NSW",
    "sg:tags":[
        "management",
        "event"
    ],
    "wof:name":"Peter Lee Enterprises Pty Ltd",
    "wof:placetype":"venue"
},
  "geometry": {"coordinates":[151.192337,-33.8554],"type":"Point"}
}