{
  "type": "Feature",
  "properties": {
    "iso:country":"AU",
    "sg:address":"57 Edith St",
    "sg:city":"Wynnum",
    "sg:classifiers":[
        {
            "category":"Shopping",
            "subcategory":"Clothing, Apparel, & Fashions",
            "type":"Retail Goods"
        }
    ],
    "sg:phone":"+61 7 3396 2432",
    "sg:postcode":"4178",
    "sg:province":"QLD",
    "sg:tags":[
        "menswear"
    ],
    "wof:name":"D.B.S. Mensland",
    "wof:placetype":"venue"
},
  "geometry": {"coordinates":[153.17405700699999,-27.4443511963],"type":"Point"}
}