{
  "type": "Feature",
  "properties": {
    "addr:full":"Unit 6/ 160 Lytton Rd Morningside QLD 4170",
    "addr:housenumber":"/ 160",
    "addr:postcode":"4170",
    "addr:street":"Lytton Rd",
    "iso:country":"AU",
    "sg:address":"Unit 6/ 160 Lytton Rd",
    "sg:city":"Morningside",
    "sg:classifiers":[
        {
            "category":"Professional",
            "subcategory":"Detective & Security Services",
            "type":"Services"
        }
    ],
    "sg:phone":"+61 7 3908 2222",
    "sg:postcode":"4170",
    "sg:province":"QLD",
    "sg:tags":[
        "consultant",
        "system"
    ],
    "wof:name":"Lamson",
    "wof:placetype":"venue"
},
  "geometry": {"coordinates":[153.06915283199999,-27.4500694275],"type":"Point"}
}