{
  "type": "Feature",
  "properties": {
    "addr:full":"159 Grays Point Rd Grays Point NSW 2232",
    "addr:housenumber":"159",
    "addr:postcode":"2232",
    "addr:street":"Grays Point Rd",
    "iso:country":"AU",
    "sg:address":"159 Grays Point Rd",
    "sg:city":"Grays Point",
    "sg:classifiers":[
        {
            "category":"Professional",
            "subcategory":"Art Services",
            "type":"Services"
        }
    ],
    "sg:phone":"+61 2 9526 2759",
    "sg:postcode":"2232",
    "sg:province":"NSW",
    "sg:tags":[
        "picture",
        "frame",
        "framing"
    ],
    "wof:name":"Arts Desire",
    "wof:placetype":"venue"
},
  "geometry": {"coordinates":[151.07557678200001,-34.058265686],"type":"Point"}
}