{
  "type": "Feature",
  "properties": {
    "addr:full":"Shop 63 Warwick Grove Shopng Cntr Warwick WA 6024",
    "addr:housenumber":"shop 63",
    "addr:postcode":"6024",
    "addr:street":"Warwick Grove Shopng Cntr",
    "iso:country":"AU",
    "sg:address":"Shop 63 Warwick Grove Shopng Cntr",
    "sg:city":"Warwick",
    "sg:classifiers":[
        {
            "category":"Food & Beverages",
            "subcategory":"Bakery",
            "type":"Retail Goods"
        }
    ],
    "sg:phone":"+61 8 9447 0520",
    "sg:postcode":"6024",
    "sg:province":"WA",
    "sg:tags":[
        "baker"
    ],
    "wof:name":"Krusty Kob",
    "wof:placetype":"venue"
},
  "geometry": {"coordinates":[115.804283142,-31.8337459564],"type":"Point"}
}