{
  "type": "Feature",
  "properties": {
    "addr:full":"PO Box 1119 Burleigh Heads QLD 4220",
    "addr:postcode":"4220",
    "iso:country":"AU",
    "sg:address":"PO Box 1119",
    "sg:city":"Burleigh Heads",
    "sg:classifiers":[
        {
            "category":"Building & Trades",
            "subcategory":"Landscaping Services",
            "type":"Services"
        }
    ],
    "sg:phone":"+61 411 743 251",
    "sg:postcode":"4220",
    "sg:province":"QLD",
    "sg:tags":[
        "designer",
        "landscape",
        "contractor"
    ],
    "wof:name":"Japanese Feature Gardens",
    "wof:placetype":"venue"
},
  "geometry": {"coordinates":[153.449752808,-28.0879096985],"type":"Point"}
}