{
  "type": "Feature",
  "properties": {
    "addr:full":"1409 Anzac Ave Kallangur QLD 4503",
    "addr:housenumber":"1409",
    "addr:postcode":"4503",
    "addr:street":"Anzac Ave",
    "iso:country":"AU",
    "sg:address":"1409 Anzac Ave",
    "sg:city":"Kallangur",
    "sg:classifiers":[
        {
            "category":"Real Estate",
            "subcategory":"Real Estate Agent",
            "type":"Services"
        }
    ],
    "sg:phone":"+61 7 3204 5411",
    "sg:postcode":"4503",
    "sg:province":"QLD",
    "wof:name":"Raine & Horne",
    "wof:placetype":"venue"
},
  "geometry": {"coordinates":[152.994140625,-27.250585556],"type":"Point"}
}