{
  "type": "Feature",
  "properties": {
    "addr:full":"26 Drummond St Carlton VIC 3053",
    "addr:housenumber":"26",
    "addr:postcode":"3053",
    "addr:street":"Drummond St",
    "iso:country":"AU",
    "sg:address":"26 Drummond St",
    "sg:city":"Carlton",
    "sg:classifiers":[
        {
            "category":"Communications",
            "subcategory":"News Services",
            "type":"Services"
        }
    ],
    "sg:phone":"+61 3 9662 9010",
    "sg:postcode":"3053",
    "sg:province":"VIC",
    "sg:tags":[
        "information",
        "tourist",
        "attractions"
    ],
    "wof:name":"White Hat Tours",
    "wof:placetype":"venue"
},
  "geometry": {"coordinates":[144.96762085,-37.8063545227],"type":"Point"}
}