{
  "type": "Feature",
  "properties": {
    "iso:country":"AU",
    "sg:address":"7 Banyula Drv",
    "sg:city":"Toowoomba",
    "sg:classifiers":[
        {
            "category":"Building & Trades",
            "subcategory":"Construction",
            "type":"Services"
        }
    ],
    "sg:phone":"+61 418 716 513",
    "sg:postcode":"4350",
    "sg:province":"QLD",
    "sg:tags":[
        "contractor"
    ],
    "wof:name":"Taylor Greg & Kim Builder",
    "wof:placetype":"venue"
},
  "geometry": {"coordinates":[151.892807,-27.535561],"type":"Point"}
}