{
  "type": "Feature",
  "properties": {
    "iso:country":"AU",
    "sg:address":"99 Bazaar St",
    "sg:city":"Maryborough",
    "sg:classifiers":[
        {
            "category":"Organizations",
            "subcategory":"Non-profit Organization",
            "type":"Services"
        }
    ],
    "sg:phone":"+61 7 4123 3361",
    "sg:postcode":"4650",
    "sg:province":"QLD",
    "sg:tags":[
        "environmental",
        "organisation",
        "conservation"
    ],
    "wof:name":"Wide Bay Burnett Conservation Council Inc",
    "wof:placetype":"venue"
},
  "geometry": {"coordinates":[152.700851,-25.541489],"type":"Point"}
}