{
  "type": "Feature",
  "properties": {
    "iso:country":"AU",
    "sg:address":"66 Bridge St",
    "sg:city":"Picton",
    "sg:classifiers":[
        {
            "category":"Wholesale",
            "subcategory":"Medical Equipment & Supplies",
            "type":"Manufacturing & Wholesale Goods"
        }
    ],
    "sg:phone":"+61 2 4677 0860",
    "sg:postcode":"2571",
    "sg:province":"NSW",
    "sg:tags":[
        "dental"
    ],
    "wof:name":"Asco Industries Pty Ltd",
    "wof:placetype":"venue"
},
  "geometry": {"coordinates":[150.60032653799999,-34.1928291321],"type":"Point"}
}