{
  "type": "Feature",
  "properties": {
    "addr:full":"304 Chesterville Rd Moorabbin VIC 3189",
    "addr:housenumber":"304",
    "addr:postcode":"3189",
    "addr:street":"Chesterville Rd",
    "iso:country":"AU",
    "sg:address":"304 Chesterville Rd",
    "sg:city":"Moorabbin",
    "sg:classifiers":[
        {
            "category":"Building & Trades",
            "subcategory":"Equipment Rental",
            "type":"Services"
        }
    ],
    "sg:phone":"+61 3 9555 9443",
    "sg:postcode":"3189",
    "sg:province":"VIC",
    "sg:tags":[
        "platform",
        "hire",
        "work",
        "elevating"
    ],
    "sg:website":"http://www.scotia.com.au",
    "wof:name":"Scotia Hire Pty Ltd",
    "wof:placetype":"venue"
},
  "geometry": {"coordinates":[145.06097412099999,-37.9389762878],"type":"Point"}
}