{
  "type": "Feature",
  "properties": {
    "addr:full":"14 Leonard Ave Noble Park VIC 3174",
    "addr:housenumber":"14",
    "addr:postcode":"3174",
    "addr:street":"Leonard Ave",
    "iso:country":"AU",
    "sg:address":"14 Leonard Ave",
    "sg:city":"Noble Park",
    "sg:classifiers":[
        {
            "category":"Food & Beverages",
            "subcategory":"Bakery",
            "type":"Retail Goods"
        }
    ],
    "sg:phone":"+61 3 9546 2118",
    "sg:postcode":"3174",
    "sg:province":"VIC",
    "sg:tags":[
        "baker"
    ],
    "wof:name":"Sun Star Hot Bread Kitchen",
    "wof:placetype":"venue"
},
  "geometry": {"coordinates":[145.175704956,-37.9687156677],"type":"Point"}
}