{
  "type": "Feature",
  "properties": {
    "addr:full":"2 Redbank Rd Killara NSW 2071",
    "addr:housenumber":"2",
    "addr:postcode":"2071",
    "addr:street":"Redbank Rd",
    "iso:country":"AU",
    "sg:address":"2 Redbank Rd",
    "sg:city":"Killara",
    "sg:classifiers":[
        {
            "category":"Professional",
            "subcategory":"Computer Services",
            "type":"Services"
        }
    ],
    "sg:phone":"+61 2 9416 7600",
    "sg:postcode":"2071",
    "sg:province":"NSW",
    "sg:tags":[
        "consultant",
        "system"
    ],
    "wof:name":"Pelquest-Hunt Howard",
    "wof:placetype":"venue"
},
  "geometry": {"coordinates":[151.15806579599999,-33.774055481],"type":"Point"}
}