{
  "type": "Feature",
  "properties": {
    "iso:country":"AU",
    "sg:address":"61 Webster St",
    "sg:city":"Wycheproof",
    "sg:classifiers":[
        {
            "category":"Education",
            "subcategory":"School",
            "type":"Public Place"
        }
    ],
    "sg:phone":"+61 3 5493 7257",
    "sg:postcode":"3527",
    "sg:province":"VIC",
    "sg:tags":[
        "co-educational"
    ],
    "wof:name":"St Michael's School",
    "wof:placetype":"venue"
},
  "geometry": {"coordinates":[143.21859699999999,-36.076035],"type":"Point"}
}