{
  "type": "Feature",
  "properties": {
    "iso:country":"AU",
    "sg:address":"365 Hampton St",
    "sg:city":"Hampton",
    "sg:classifiers":[
        {
            "category":"Wholesale",
            "subcategory":"Apparel",
            "type":"Manufacturing & Wholesale Goods"
        }
    ],
    "sg:phone":"+61 3 9521 0711",
    "sg:postcode":"3188",
    "sg:province":"VIC",
    "sg:tags":[
        "wholesaler",
        "mfrs",
        "uniform"
    ],
    "wof:name":"Motto",
    "wof:placetype":"venue"
},
  "geometry": {"coordinates":[145.00242614699999,-37.9369621277],"type":"Point"}
}