{
  "type": "Feature",
  "properties": {
    "addr:full":"37 Randall St Slacks Creek QLD 4127",
    "addr:housenumber":"37",
    "addr:postcode":"4127",
    "addr:street":"Randall St",
    "iso:country":"AU",
    "sg:address":"37 Randall St",
    "sg:city":"Slacks Creek",
    "sg:classifiers":[
        {
            "category":"Retail",
            "subcategory":"Auto Repair",
            "type":"Services"
        }
    ],
    "sg:phone":"+61 7 3208 0781",
    "sg:postcode":"4127",
    "sg:province":"QLD",
    "sg:tags":[
        "repairer",
        "motor",
        "engineer"
    ],
    "wof:name":"AOK Automotive Repairs",
    "wof:placetype":"venue"
},
  "geometry": {"coordinates":[153.121459961,-27.6252002716],"type":"Point"}
}