{
  "type": "Feature",
  "properties": {
    "iso:country":"AU",
    "sg:address":"Steel Rudd Rd",
    "sg:city":"Greenmount East",
    "sg:classifiers":[
        {
            "category":"Building & Trades",
            "subcategory":"Construction",
            "type":"Services"
        }
    ],
    "sg:phone":"+61 418 718 623",
    "sg:postcode":"4359",
    "sg:province":"QLD",
    "sg:tags":[
        "management"
    ],
    "wof:name":"Dick Thies Constructions",
    "wof:placetype":"venue"
},
  "geometry": {"coordinates":[151.947189,-27.783627],"type":"Point"}
}