{
  "type": "Feature",
  "properties": {
    "iso:country":"AU",
    "sg:address":"1 Grange Rd",
    "sg:city":"Tomerong",
    "sg:classifiers":[
        {
            "category":"Retail",
            "subcategory":"Veterinary Services",
            "type":"Services"
        }
    ],
    "sg:phone":"+61 2 4443 6677",
    "sg:postcode":"2540",
    "sg:province":"NSW",
    "sg:tags":[
        "surgeon"
    ],
    "wof:name":"Bay and Basin Animal Hospital",
    "wof:placetype":"venue"
},
  "geometry": {"coordinates":[150.57369995100001,-35.0648345947],"type":"Point"}
}