{
  "type": "Feature",
  "properties": {
    "iso:country":"AU",
    "sg:address":"112 Parry St",
    "sg:city":"Charleville",
    "sg:classifiers":[
        {
            "category":"Home & Garden",
            "subcategory":"Hardware",
            "type":"Retail Goods"
        }
    ],
    "sg:phone":"+61 7 4654 1940",
    "sg:postcode":"4470",
    "sg:province":"QLD",
    "sg:tags":[
        "generating",
        "set",
        "generator"
    ],
    "wof:name":"J.P. Motorcycles & Armory",
    "wof:placetype":"venue"
},
  "geometry": {"coordinates":[146.24922180199999,-26.4011878967],"type":"Point"}
}