{
  "type": "Feature",
  "properties": {
    "addr:full":"U 2/ 57 Anderson Rd Mortdale NSW 2223",
    "addr:housenumber":"57",
    "addr:postcode":"2223",
    "addr:street":"Anderson Rd",
    "iso:country":"AU",
    "sg:address":"U 2/ 57 Anderson Rd",
    "sg:city":"Mortdale",
    "sg:classifiers":[
        {
            "category":"Wholesale",
            "subcategory":"Home Furnishings",
            "type":"Manufacturing & Wholesale Goods"
        }
    ],
    "sg:phone":"+61 2 9533 3292",
    "sg:postcode":"2223",
    "sg:province":"NSW",
    "wof:name":"Jonax International Pty Ltd",
    "wof:placetype":"venue"
},
  "geometry": {"coordinates":[151.06608581500001,-33.9674034119],"type":"Point"}
}