{
  "type": "Feature",
  "properties": {
    "iso:country":"AU",
    "sg:address":"Shop 3/ 21 Campbell St",
    "sg:city":"Blacktown",
    "sg:classifiers":[
        {
            "category":"Health Services",
            "subcategory":"Health Practitioner",
            "type":"Services"
        }
    ],
    "sg:phone":"+61 2 9621 7555",
    "sg:postcode":"2148",
    "sg:province":"NSW",
    "sg:tags":[
        "physiotherapist"
    ],
    "wof:name":"Bajaj Neena",
    "wof:placetype":"venue"
},
  "geometry": {"coordinates":[150.90927124000001,-33.7714271545],"type":"Point"}
}