{
  "type": "Feature",
  "properties": {
    "addr:full":"22 Jersey Rd Bayswater VIC 3153",
    "addr:housenumber":"22",
    "addr:postcode":"3153",
    "addr:street":"Jersey Rd",
    "iso:country":"AU",
    "sg:address":"22 Jersey Rd",
    "sg:city":"Bayswater",
    "sg:classifiers":[
        {
            "category":"Wholesale",
            "subcategory":"Construction Materials",
            "type":"Manufacturing & Wholesale Goods"
        }
    ],
    "sg:phone":"+61 3 9729 6777",
    "sg:postcode":"3153",
    "sg:province":"VIC",
    "sg:tags":[
        "wholesaler",
        "equipment",
        "bathroom",
        "mfrs",
        "accessory"
    ],
    "wof:name":"Marbletrend Bathroom Industries",
    "wof:placetype":"venue"
},
  "geometry": {"coordinates":[145.27947998100001,-37.8411369324],"type":"Point"}
}