{
  "type": "Feature",
  "properties": {
    "addr:full":"34 Bridge St Murray Bridge SA 5253",
    "addr:housenumber":"34",
    "addr:postcode":"5253",
    "addr:street":"Bridge St",
    "iso:country":"AU",
    "sg:address":"34 Bridge St",
    "sg:city":"Murray Bridge",
    "sg:classifiers":[
        {
            "category":"Health Services",
            "subcategory":"Dentist",
            "type":"Services"
        }
    ],
    "sg:phone":"+61 8 8532 2511",
    "sg:postcode":"5253",
    "sg:province":"SA",
    "wof:name":"Tindall Andrew",
    "wof:placetype":"venue"
},
  "geometry": {"coordinates":[139.275787353,-35.1190223694],"type":"Point"}
}