{
  "type": "Feature",
  "properties": {
    "addr:full":"18 Water St Cairns QLD 4870",
    "addr:housenumber":"18",
    "addr:postcode":"4870",
    "addr:street":"Water St",
    "iso:country":"AU",
    "sg:address":"18 Water St",
    "sg:city":"Cairns",
    "sg:classifiers":[
        {
            "category":"Retail",
            "subcategory":"Auto Repair",
            "type":"Services"
        }
    ],
    "sg:phone":"+61 7 4031 6000",
    "sg:postcode":"4870",
    "sg:province":"QLD",
    "sg:tags":[
        "repairer",
        "motor",
        "engineer"
    ],
    "wof:name":"Midas",
    "wof:placetype":"venue"
},
  "geometry": {"coordinates":[145.76947021500001,-16.9220638275],"type":"Point"}
}