{
  "type": "Feature",
  "properties": {
    "addr:full":"120 Main St Romsey VIC 3434",
    "addr:housenumber":"120",
    "addr:postcode":"3434",
    "addr:street":"Main St",
    "iso:country":"AU",
    "sg:address":"120 Main St",
    "sg:city":"Romsey",
    "sg:classifiers":[
        {
            "category":"Cafe",
            "type":"Food & Drink"
        }
    ],
    "sg:phone":"+61 3 5429 3535",
    "sg:postcode":"3434",
    "sg:province":"VIC",
    "wof:name":"The Courtyard Cafe",
    "wof:placetype":"venue"
},
  "geometry": {"coordinates":[144.743011475,-37.3479576111],"type":"Point"}
}