{
  "type": "Feature",
  "properties": {
    "iso:country":"AU",
    "sg:address":"123 McKean St",
    "sg:city":"Fitzroy North",
    "sg:classifiers":[
        {
            "category":"Real Estate",
            "subcategory":"Architect",
            "type":"Services"
        }
    ],
    "sg:phone":"+61 3 9481 3820",
    "sg:postcode":"3068",
    "sg:province":"VIC",
    "wof:name":"McPhee Antony",
    "wof:placetype":"venue"
},
  "geometry": {"coordinates":[144.98675537099999,-37.7887191772],"type":"Point"}
}