{
  "type": "Feature",
  "properties": {
    "addr:full":"43 Willoring St Jamisontown NSW 2750",
    "addr:housenumber":"43",
    "addr:postcode":"2750",
    "addr:street":"Willoring St",
    "iso:country":"AU",
    "sg:address":"43 Willoring St",
    "sg:city":"Jamisontown",
    "sg:classifiers":[
        {
            "category":"Building & Trades",
            "subcategory":"Construction",
            "type":"Services"
        }
    ],
    "sg:phone":"+61 411 703 811",
    "sg:postcode":"2750",
    "sg:province":"NSW",
    "sg:tags":[
        "renovation",
        "alterations",
        "extension",
        "contractor"
    ],
    "wof:name":"R.F.C. Home Improvements",
    "wof:placetype":"venue"
},
  "geometry": {"coordinates":[150.67778015100001,-33.7623558044],"type":"Point"}
}