{
  "type": "Feature",
  "properties": {
    "addr:full":"1 Chaplin Drv Lane Cove West NSW 2066",
    "addr:housenumber":"1",
    "addr:postcode":"2066",
    "addr:street":"Chaplin Drv",
    "iso:country":"AU",
    "sg:address":"1 Chaplin Drv",
    "sg:city":"Lane Cove West",
    "sg:classifiers":[
        {
            "category":"Retail",
            "subcategory":"Storage",
            "type":"Services"
        }
    ],
    "sg:phone":"+61 2 9490 7300",
    "sg:postcode":"2066",
    "sg:province":"NSW",
    "wof:name":"Preferred Media Pty Ltd",
    "wof:placetype":"venue"
},
  "geometry": {"coordinates":[151.147506714,-33.8104858398],"type":"Point"}
}