{
  "type": "Feature",
  "properties": {
    "iso:country":"AU",
    "sg:address":"Erina Shopping Centre Terrigal Drv",
    "sg:city":"Erina",
    "sg:classifiers":[
        {
            "category":"Food & Beverages",
            "subcategory":"Liquor & Beverages",
            "type":"Retail Goods"
        }
    ],
    "sg:phone":"+61 2 4365 1982",
    "sg:postcode":"2250",
    "sg:province":"NSW",
    "sg:tags":[
        "store"
    ],
    "wof:name":"Liquorland",
    "wof:placetype":"venue"
},
  "geometry": {"coordinates":[151.39523315400001,-33.4345855713],"type":"Point"}
}