{
  "type": "Feature",
  "properties": {
    "iso:country":"AU",
    "sg:address":"1/ 148 Brunswick St",
    "sg:city":"Fortitude Valley",
    "sg:classifiers":[
        {
            "category":"Professional",
            "subcategory":"Employment Agencies",
            "type":"Services"
        }
    ],
    "sg:phone":"+61 7 3832 5544",
    "sg:postcode":"4006",
    "sg:province":"QLD",
    "wof:name":"iGATE Australia Pty Ltd",
    "wof:placetype":"venue"
},
  "geometry": {"coordinates":[153.03123474099999,-27.4556446075],"type":"Point"}
}