{
  "type": "Feature",
  "properties": {
    "addr:full":"Cnr 27 Medway & Abercrombie Sts Rocklea QLD 4106",
    "addr:housenumber":"27",
    "addr:postcode":"4106",
    "addr:street":"Cnr;&;Sts",
    "iso:country":"AU",
    "sg:address":"Cnr 27 Medway & Abercrombie Sts",
    "sg:city":"Rocklea",
    "sg:classifiers":[
        {
            "category":"Freight",
            "type":"Transportation"
        }
    ],
    "sg:phone":"+61 2 6926 1454",
    "sg:postcode":"4106",
    "sg:province":"QLD",
    "sg:tags":[
        "light",
        "carrier"
    ],
    "wof:name":"Phil MacIntoshs Transport Pty Ltd",
    "wof:placetype":"venue"
},
  "geometry": {"coordinates":[153.00987243599999,-27.5426025391],"type":"Point"}
}