{
  "type": "Feature",
  "properties": {
    "iso:country":"AU",
    "sg:address":"28 Pevensey Pl",
    "sg:city":"Echuca",
    "sg:classifiers":[
        {
            "category":"Professional",
            "subcategory":"Business Services",
            "type":"Services"
        }
    ],
    "sg:phone":"+61 3 5482 6820",
    "sg:postcode":"3564",
    "sg:province":"VIC",
    "sg:tags":[
        "drafting"
    ],
    "wof:name":"Plans + Design",
    "wof:placetype":"venue"
},
  "geometry": {"coordinates":[144.73110961899999,-36.1355209351],"type":"Point"}
}