{
  "type": "Feature",
  "properties": {
    "addr:full":"10 Bray St Port Pirie SA 5540",
    "addr:housenumber":"10",
    "addr:postcode":"5540",
    "addr:street":"Bray St",
    "iso:country":"AU",
    "sg:address":"10 Bray St",
    "sg:city":"Port Pirie",
    "sg:classifiers":[
        {
            "category":"Building & Trades",
            "subcategory":"Construction",
            "type":"Services"
        }
    ],
    "sg:phone":"+61 8 8633 1324",
    "sg:postcode":"5540",
    "sg:province":"SA",
    "sg:tags":[
        "contractor"
    ],
    "wof:name":"MJ & CE Oehms",
    "wof:placetype":"venue"
},
  "geometry": {"coordinates":[137.99212646500001,-33.1912269592],"type":"Point"}
}