{
  "type": "Feature",
  "properties": {
    "iso:country":"AU",
    "sg:address":"11 Yeatman St",
    "sg:city":"Hyde Park",
    "sg:classifiers":[
        {
            "category":"Retail",
            "subcategory":"Auto Repair",
            "type":"Services"
        }
    ],
    "sg:phone":"+61 7 4771 3526",
    "sg:postcode":"4812",
    "sg:province":"QLD",
    "sg:tags":[
        "repairer",
        "motor",
        "engineer"
    ],
    "wof:name":"Rails Auto Repairs",
    "wof:placetype":"venue"
},
  "geometry": {"coordinates":[146.80200199999999,-19.272552],"type":"Point"}
}