{
  "type": "Feature",
  "properties": {
    "addr:full":"Burgess Drv Langwarrin VIC 3910",
    "addr:postcode":"3910",
    "addr:street":"Burgess Drv",
    "iso:country":"AU",
    "sg:address":"Burgess Drv",
    "sg:city":"Langwarrin",
    "sg:classifiers":[
        {
            "category":"Education",
            "subcategory":"Kindergarten",
            "type":"Public Place"
        }
    ],
    "sg:phone":"+61 3 9775 7088",
    "sg:postcode":"3910",
    "sg:province":"VIC",
    "sg:tags":[
        "pre-schools"
    ],
    "wof:name":"Langwarrin Park Pre School",
    "wof:placetype":"venue"
},
  "geometry": {"coordinates":[145.203048706,-38.1473350525],"type":"Point"}
}