{
  "type": "Feature",
  "properties": {
    "addr:full":"302 St Georges Rd Northcote VIC 3070",
    "addr:housenumber":"302",
    "addr:postcode":"3070",
    "addr:street":"St Georges Rd",
    "iso:country":"AU",
    "sg:address":"302 St Georges Rd",
    "sg:city":"Northcote",
    "sg:classifiers":[
        {
            "category":"Retail",
            "subcategory":"Event Space",
            "type":"Services"
        }
    ],
    "sg:phone":"+61 3 9484 3567",
    "sg:postcode":"3070",
    "sg:province":"VIC",
    "sg:tags":[
        "venue",
        "reception",
        "wedding"
    ],
    "wof:name":"The Sovereign",
    "wof:placetype":"venue"
},
  "geometry": {"coordinates":[144.99336199999999,-37.760555],"type":"Point"}
}