{
  "type": "Feature",
  "properties": {
    "iso:country":"AU",
    "sg:address":"236 Humffray St",
    "sg:city":"North Ballarat",
    "sg:classifiers":[
        {
            "category":"Personal",
            "subcategory":"Massage",
            "type":"Services"
        }
    ],
    "sg:phone":"+61 3 5332 3326",
    "sg:postcode":"3350",
    "sg:province":"VIC",
    "sg:tags":[
        "therapy"
    ],
    "wof:name":"Suzanne Walker",
    "wof:placetype":"venue"
},
  "geometry": {"coordinates":[143.886505,-37.553909],"type":"Point"}
}