{
  "type": "Feature",
  "properties": {
    "iso:country":"AU",
    "sg:address":"5 Nelson St",
    "sg:city":"Moorabbin",
    "sg:classifiers":[
        {
            "category":"Manufacturing",
            "subcategory":"Food",
            "type":"Manufacturing & Wholesale Goods"
        }
    ],
    "sg:phone":"+61 3 9532 1588",
    "sg:postcode":"3189",
    "sg:province":"VIC",
    "sg:tags":[
        "product",
        "nut",
        "edible"
    ],
    "wof:name":"Snax With Attitude Pty Ltd",
    "wof:placetype":"venue"
},
  "geometry": {"coordinates":[145.06877136200001,-37.9440612793],"type":"Point"}
}