{
  "type": "Feature",
  "properties": {
    "addr:full":"99 Coode Rd West Melbourne VIC 3003",
    "addr:housenumber":"99",
    "addr:postcode":"3003",
    "addr:street":"Coode Rd",
    "iso:country":"AU",
    "sg:address":"99 Coode Rd",
    "sg:city":"West Melbourne",
    "sg:classifiers":[
        {
            "category":"Professional",
            "type":"Services"
        }
    ],
    "sg:phone":"+61 3 9389 3088",
    "sg:postcode":"3003",
    "sg:province":"VIC",
    "sg:tags":[
        "transport"
    ],
    "wof:name":"Patrick Logistics",
    "wof:placetype":"venue"
},
  "geometry": {"coordinates":[144.923828125,-37.8101348877],"type":"Point"}
}