{
  "type": "Feature",
  "properties": {
    "addr:full":"1 Victoria St Mackay QLD 4740",
    "addr:housenumber":"1",
    "addr:postcode":"4740",
    "addr:street":"Victoria St",
    "iso:country":"AU",
    "sg:address":"1 Victoria St",
    "sg:city":"Mackay",
    "sg:classifiers":[
        {
            "category":"Manufacturing",
            "subcategory":"Tools & Machinery",
            "type":"Manufacturing & Wholesale Goods"
        }
    ],
    "sg:phone":"+61 7 4953 1633",
    "sg:postcode":"4740",
    "sg:province":"QLD",
    "sg:tags":[
        "earth",
        "excavating",
        "moving",
        "equipment"
    ],
    "wof:name":"Coates Hire",
    "wof:placetype":"venue"
},
  "geometry": {"coordinates":[149.190811,-21.141676],"type":"Point"}
}