{
  "type": "Feature",
  "properties": {
    "addr:full":"Shop 12, City Plaza 436 Peel St Tamworth NSW 2340",
    "addr:housenumber":"shop 12;436",
    "addr:postcode":"2340",
    "addr:street":"City Plaza;Peel St",
    "iso:country":"AU",
    "sg:address":"Shop 12, City Plaza 436 Peel St",
    "sg:city":"Tamworth",
    "sg:classifiers":[
        {
            "category":"Travel",
            "subcategory":"Travel Agent",
            "type":"Entertainment"
        }
    ],
    "sg:phone":"+61 13 18 66",
    "sg:postcode":"2340",
    "sg:province":"NSW",
    "sg:tags":[
        "consultant"
    ],
    "wof:name":"Flight Centre",
    "wof:placetype":"venue"
},
  "geometry": {"coordinates":[150.932693481,-31.0935745239],"type":"Point"}
}