{
  "type": "Feature",
  "properties": {
    "iso:country":"AU",
    "sg:address":"15 Armstrong St North",
    "sg:city":"Ballarat",
    "sg:classifiers":[
        {
            "category":"Personal",
            "subcategory":"Beauty Salon",
            "type":"Services"
        }
    ],
    "sg:phone":"+61 3 5331 1763",
    "sg:postcode":"3350",
    "sg:province":"VIC",
    "sg:tags":[
        "hairdresser"
    ],
    "wof:name":"Darrian's",
    "wof:placetype":"venue"
},
  "geometry": {"coordinates":[143.856323,-37.560703],"type":"Point"}
}