{
  "type": "Feature",
  "properties": {
    "addr:full":"130 Dudley St Punchbowl NSW 2196",
    "addr:housenumber":"130",
    "addr:postcode":"2196",
    "addr:street":"Dudley St",
    "iso:country":"AU",
    "sg:address":"130 Dudley St",
    "sg:city":"Punchbowl",
    "sg:classifiers":[
        {
            "category":"Communications",
            "subcategory":"Film & Video Production",
            "type":"Services"
        }
    ],
    "sg:phone":"+61 2 9750 7005",
    "sg:postcode":"2196",
    "sg:province":"NSW",
    "sg:tags":[
        "dvd",
        "library"
    ],
    "wof:name":"Karnak Video",
    "wof:placetype":"venue"
},
  "geometry": {"coordinates":[151.06321700000001,-33.931133],"type":"Point"}
}