{
  "type": "Feature",
  "properties": {
    "addr:full":"75 Norseman Rd Esperance WA 6450",
    "addr:housenumber":"75",
    "addr:postcode":"6450",
    "addr:street":"Norseman Rd",
    "iso:country":"AU",
    "sg:address":"75 Norseman Rd",
    "sg:city":"Esperance",
    "sg:classifiers":[
        {
            "category":"Manufacturing",
            "subcategory":"Metals",
            "type":"Manufacturing & Wholesale Goods"
        }
    ],
    "sg:phone":"+61 8 9071 1048",
    "sg:postcode":"6450",
    "sg:province":"WA",
    "sg:tags":[
        "sheet",
        "worker"
    ],
    "wof:name":"Esperance Sheetmetal Service",
    "wof:placetype":"venue"
},
  "geometry": {"coordinates":[121.90007782000001,-33.8443412781],"type":"Point"}
}