{
  "type": "Feature",
  "properties": {
    "iso:country":"AU",
    "sg:address":"8/ 95 Canning Hwy",
    "sg:city":"South Perth",
    "sg:classifiers":[
        {
            "category":"Utilities",
            "subcategory":"Telephone",
            "type":"Services"
        }
    ],
    "sg:phone":"+61 8 9474 1111",
    "sg:postcode":"6151",
    "sg:province":"WA",
    "sg:tags":[
        "installation",
        "system",
        "maintenance"
    ],
    "wof:name":"Efficient Communication Services Pty. Ltd.",
    "wof:placetype":"venue"
},
  "geometry": {"coordinates":[115.877693,-31.980055],"type":"Point"}
}