{
  "type": "Feature",
  "properties": {
    "addr:full":"82 Norton St Leichhardt NSW 2040",
    "addr:housenumber":"82",
    "addr:postcode":"2040",
    "addr:street":"Norton St",
    "iso:country":"AU",
    "sg:address":"82 Norton St",
    "sg:city":"Leichhardt",
    "sg:classifiers":[
        {
            "category":"Shopping",
            "subcategory":"Clothing, Apparel, & Fashions",
            "type":"Retail Goods"
        }
    ],
    "sg:phone":"+61 2 9569 6098",
    "sg:postcode":"2040",
    "sg:province":"NSW",
    "sg:tags":[
        "boutique"
    ],
    "wof:name":"Bb On Norton",
    "wof:placetype":"venue"
},
  "geometry": {"coordinates":[151.157104,-33.885178],"type":"Point"}
}