{
  "type": "Feature",
  "properties": {
    "addr:full":"Queens Pde Newport NSW 2106",
    "addr:postcode":"2106",
    "addr:street":"Queens Pde",
    "iso:country":"AU",
    "sg:address":"Queens Pde",
    "sg:city":"Newport",
    "sg:classifiers":[
        {
            "category":"Education",
            "subcategory":"Special Training",
            "type":"Public Place"
        }
    ],
    "sg:phone":"+61 2 9979 5877",
    "sg:postcode":"2106",
    "sg:province":"NSW",
    "sg:tags":[
        "school",
        "sailing"
    ],
    "wof:name":"Pittwater Sailing School",
    "wof:placetype":"venue"
},
  "geometry": {"coordinates":[151.31622314399999,-33.6598625183],"type":"Point"}
}