{
  "type": "Feature",
  "properties": {
    "addr:full":"Level 1 Targo St Bundaberg QLD 4670",
    "addr:postcode":"4670",
    "addr:street":"Targo St",
    "iso:country":"AU",
    "sg:address":"Level 1 Targo St",
    "sg:city":"Bundaberg",
    "sg:classifiers":[
        {
            "category":"Organizations",
            "subcategory":"Professional Association",
            "type":"Services"
        }
    ],
    "sg:phone":"+61 7 4152 0115",
    "sg:postcode":"4670",
    "sg:province":"QLD",
    "sg:tags":[
        "web",
        "internet"
    ],
    "wof:name":"Best Enterprises",
    "wof:placetype":"venue"
},
  "geometry": {"coordinates":[152.35061645499999,-24.8645992279],"type":"Point"}
}