{
  "type": "Feature",
  "properties": {
    "iso:country":"AU",
    "sg:address":"Cnr Korong Rd & Orthla Ave",
    "sg:city":"Heidelberg West",
    "sg:classifiers":[
        {
            "category":"Professional",
            "subcategory":"Detective & Security Services",
            "type":"Services"
        }
    ],
    "sg:phone":"+61 3 9459 5500",
    "sg:postcode":"3081",
    "sg:province":"VIC",
    "sg:tags":[
        "protective",
        "rustproofing"
    ],
    "wof:name":"All-Brite Plating",
    "wof:placetype":"venue"
},
  "geometry": {"coordinates":[145.04690551799999,-37.7335166931],"type":"Point"}
}