{
  "type": "Feature",
  "properties": {
    "iso:country":"AU",
    "sg:address":"12 Elizabeth St",
    "sg:city":"Kenilworth",
    "sg:classifiers":[
        {
            "category":"Cafe",
            "type":"Food & Drink"
        }
    ],
    "sg:phone":"+61 7 5446 0231",
    "sg:postcode":"4574",
    "sg:province":"QLD",
    "wof:name":"Top Cafe",
    "wof:placetype":"venue"
},
  "geometry": {"coordinates":[152.72756999999999,-26.595827],"type":"Point"}
}