{
  "type": "Feature",
  "properties": {
    "addr:full":"Guppy St Pemberton WA 6260",
    "addr:postcode":"6260",
    "addr:street":"Guppy St",
    "iso:country":"AU",
    "sg:address":"Guppy St",
    "sg:city":"Pemberton",
    "sg:classifiers":[
        {
            "category":"Education",
            "subcategory":"School",
            "type":"Public Place"
        }
    ],
    "sg:phone":"+61 8 9776 1180",
    "sg:postcode":"6260",
    "sg:province":"WA",
    "wof:name":"St Joseph's School",
    "wof:placetype":"venue"
},
  "geometry": {"coordinates":[116.034881592,-34.446018219],"type":"Point"}
}