{
  "type": "Feature",
  "properties": {
    "addr:full":"Level 1/ 11 Randles St Surry Hills NSW 2010",
    "addr:housenumber":"/ 11",
    "addr:postcode":"2010",
    "addr:street":"Randles St",
    "iso:country":"AU",
    "sg:address":"Level 1/ 11 Randles St",
    "sg:city":"Surry Hills",
    "sg:classifiers":[
        {
            "category":"Sports & Exercise",
            "subcategory":"Gym",
            "type":"Entertainment"
        }
    ],
    "sg:phone":"+61 2 9130 1326",
    "sg:postcode":"2010",
    "sg:province":"NSW",
    "sg:tags":[
        "health",
        "fitness"
    ],
    "sg:website":"http://www.capoeira.com.au",
    "wof:name":"Capoeira Brazil",
    "wof:placetype":"venue"
},
  "geometry": {"coordinates":[151.207565308,-33.8851356506],"type":"Point"}
}