{
  "type": "Feature",
  "properties": {
    "addr:full":"9 Victor Pl Raby NSW 2566",
    "addr:housenumber":"9",
    "addr:postcode":"2566",
    "addr:street":"Victor Pl Raby",
    "iso:country":"AU",
    "sg:address":"9 Victor Pl",
    "sg:city":"Raby",
    "sg:classifiers":[
        {
            "category":"Building & Trades",
            "subcategory":"Locksmith",
            "type":"Services"
        }
    ],
    "sg:phone":"+61 2 9824 7633",
    "sg:postcode":"2566",
    "sg:province":"NSW",
    "sg:tags":[
        "lock"
    ],
    "wof:name":"A & S Locksmiths",
    "wof:placetype":"venue"
},
  "geometry": {"coordinates":[150.81724548299999,-34.0195350647],"type":"Point"}
}