{
  "type": "Feature",
  "properties": {
    "iso:country":"AU",
    "sg:address":"120 Griffith St",
    "sg:city":"Mannering Park",
    "sg:classifiers":[
        {
            "category":"Professional",
            "subcategory":"Printing & Photocopies",
            "type":"Services"
        }
    ],
    "sg:phone":"+61 2 4359 3777",
    "sg:postcode":"2259",
    "sg:province":"NSW",
    "sg:tags":[
        "trophy"
    ],
    "wof:name":"Central Coast Trophies",
    "wof:placetype":"venue"
},
  "geometry": {"coordinates":[151.54292297399999,-33.1532897949],"type":"Point"}
}