{
  "type": "Feature",
  "properties": {
    "addr:full":"7b Walker St Helensburgh NSW 2508",
    "addr:housenumber":"7b",
    "addr:postcode":"2508",
    "addr:street":"Walker St",
    "iso:country":"AU",
    "sg:address":"7b Walker St",
    "sg:city":"Helensburgh",
    "sg:classifiers":[
        {
            "category":"Food & Beverages",
            "subcategory":"Liquor & Beverages",
            "type":"Retail Goods"
        }
    ],
    "sg:phone":"+61 2 4294 1838",
    "sg:postcode":"2508",
    "sg:province":"NSW",
    "sg:tags":[
        "store"
    ],
    "wof:name":"Helensburgh Cellars",
    "wof:placetype":"venue"
},
  "geometry": {"coordinates":[150.982193,-34.190979],"type":"Point"}
}