{
  "type": "Feature",
  "properties": {
    "addr:full":"1 Hartley St Blyth SA 5462",
    "addr:housenumber":"1",
    "addr:postcode":"5462",
    "addr:street":"Hartley St",
    "iso:country":"AU",
    "sg:address":"1 Hartley St",
    "sg:city":"Blyth",
    "sg:classifiers":[
        {
            "category":"Home & Garden",
            "subcategory":"Building Materials",
            "type":"Retail Goods"
        }
    ],
    "sg:phone":"+61 8 8844 5144",
    "sg:postcode":"5462",
    "sg:province":"SA",
    "sg:tags":[
        "merchant",
        "glass",
        "glazier"
    ],
    "wof:name":"Roger Barp T/AS Northern Windscreens",
    "wof:placetype":"venue"
},
  "geometry": {"coordinates":[138.48889199999999,-33.84758],"type":"Point"}
}