{
  "type": "Feature",
  "properties": {
    "iso:country":"AU",
    "sg:address":"60-70 States Rd",
    "sg:city":"Morphett Vale",
    "sg:classifiers":[
        {
            "category":"Health Services",
            "subcategory":"Health Practitioner",
            "type":"Services"
        }
    ],
    "sg:phone":"+61 439 817 715",
    "sg:postcode":"5162",
    "sg:province":"SA",
    "sg:tags":[
        "pathologist",
        "speech"
    ],
    "wof:name":"Walter Anne",
    "wof:placetype":"venue"
},
  "geometry": {"coordinates":[138.535400391,-35.1146774292],"type":"Point"}
}