{
  "type": "Feature",
  "properties": {
    "iso:country":"AU",
    "sg:address":"PO Box 2080",
    "sg:city":"South Plympton",
    "sg:classifiers":[
        {
            "category":"Farming",
            "subcategory":"Livestock Farm",
            "type":"Manufacturing & Wholesale Goods"
        }
    ],
    "sg:phone":"+61 8 8297 0733",
    "sg:postcode":"5038",
    "sg:province":"SA",
    "sg:tags":[
        "breeder",
        "horse",
        "stud"
    ],
    "wof:name":"South Australian Thoroughbred Breeders Inc.",
    "wof:placetype":"venue"
},
  "geometry": {"coordinates":[138.56356811500001,-34.9629707336],"type":"Point"}
}