{
  "type": "Feature",
  "properties": {
    "addr:full":"Shop 5 / 7 Station St Cottesloe WA 6011",
    "addr:housenumber":"shop 5 / 7",
    "addr:postcode":"6011",
    "addr:street":"Station St",
    "iso:country":"AU",
    "sg:address":"Shop 5 / 7 Station St",
    "sg:city":"Cottesloe",
    "sg:classifiers":[
        {
            "category":"Manufacturing",
            "subcategory":"Food",
            "type":"Manufacturing & Wholesale Goods"
        }
    ],
    "sg:phone":"+61 8 9383 3535",
    "sg:postcode":"6011",
    "sg:province":"WA",
    "sg:tags":[
        "function",
        "catering"
    ],
    "wof:name":"Cottesloe Crave",
    "wof:placetype":"venue"
},
  "geometry": {"coordinates":[115.76203155499999,-31.9972248077],"type":"Point"}
}