{
  "type": "Feature",
  "properties": {
    "iso:country":"AU",
    "sg:address":"Lot 1125 22 Georgina Crs",
    "sg:city":"Yarrawonga",
    "sg:classifiers":[
        {
            "category":"Retail",
            "subcategory":"Auto Repair",
            "type":"Services"
        }
    ],
    "sg:phone":"+61 8 8931 0783",
    "sg:postcode":"0830",
    "sg:province":"NT",
    "sg:tags":[
        "repairer",
        "motor",
        "engineer"
    ],
    "wof:name":"Warrens Automatic Transmissions",
    "wof:placetype":"venue"
},
  "geometry": {"coordinates":[130.987076,-12.47033],"type":"Point"}
}