{
  "type": "Feature",
  "properties": {
    "addr:full":"42 Lawrence Drv Nerang QLD 4211",
    "addr:housenumber":"42",
    "addr:postcode":"4211",
    "addr:street":"Lawrence Drv",
    "iso:country":"AU",
    "sg:address":"42 Lawrence Drv",
    "sg:city":"Nerang",
    "sg:classifiers":[
        {
            "category":"Home & Garden",
            "subcategory":"Garden Supply",
            "type":"Retail Goods"
        }
    ],
    "sg:phone":"+61 7 5596 2250",
    "sg:postcode":"4211",
    "sg:province":"QLD",
    "sg:tags":[
        "equipment",
        "hydroponics"
    ],
    "wof:name":"Simply Hydro & Garden Supplies",
    "wof:placetype":"venue"
},
  "geometry": {"coordinates":[153.34678649899999,-27.9972438812],"type":"Point"}
}