{
  "type": "Feature",
  "properties": {
    "addr:full":"855 Eumundi Noosa Rd Doonan QLD 4562",
    "addr:housenumber":"855",
    "addr:postcode":"4562",
    "addr:street":"Eumundi Noosa Rd",
    "iso:country":"AU",
    "sg:address":"855 Eumundi Noosa Rd",
    "sg:city":"Doonan",
    "sg:classifiers":[
        {
            "category":"Farming",
            "subcategory":"Vineyard",
            "type":"Manufacturing & Wholesale Goods"
        }
    ],
    "sg:phone":"+61 7 5471 1129",
    "sg:postcode":"4562",
    "sg:province":"QLD",
    "sg:tags":[
        "winery"
    ],
    "wof:name":"Robinsons Family Vineyards",
    "wof:placetype":"venue"
},
  "geometry": {"coordinates":[152.95614624000001,-26.4736766815],"type":"Point"}
}