{
  "type": "Feature",
  "properties": {
    "iso:country":"AU",
    "sg:address":"15 Paynes Rd",
    "sg:city":"Chirnside Park",
    "sg:classifiers":[
        {
            "category":"Farming",
            "subcategory":"Vineyard",
            "type":"Manufacturing & Wholesale Goods"
        }
    ],
    "sg:phone":"+61 3 9735 0224",
    "sg:postcode":"3116",
    "sg:province":"VIC",
    "sg:tags":[
        "winery"
    ],
    "wof:name":"Lirralirra Estate",
    "wof:placetype":"venue"
},
  "geometry": {"coordinates":[145.302536011,-37.734336853],"type":"Point"}
}