{
  "type": "Feature",
  "properties": {
    "addr:full":"201 Bulleen Rd Bulleen VIC 3105",
    "addr:housenumber":"201",
    "addr:postcode":"3105",
    "addr:street":"Bulleen Rd",
    "iso:country":"AU",
    "sg:address":"201 Bulleen Rd",
    "sg:city":"Bulleen",
    "sg:classifiers":[
        {
            "category":"Restaurant",
            "type":"Food & Drink"
        }
    ],
    "sg:phone":"+61 3 9852 0541",
    "sg:postcode":"3105",
    "sg:province":"VIC",
    "wof:name":"Bamboo Terrace Chinese Restaurant",
    "wof:placetype":"venue"
},
  "geometry": {"coordinates":[145.08099365199999,-37.7658538818],"type":"Point"}
}