{
  "type": "Feature",
  "properties": {
    "addr:full":"104 Ward St North Adelaide SA 5006",
    "addr:housenumber":"104",
    "addr:postcode":"5006",
    "addr:street":"Ward St",
    "iso:country":"AU",
    "sg:address":"104 Ward St",
    "sg:city":"North Adelaide",
    "sg:classifiers":[
        {
            "category":"Health Services",
            "subcategory":"Dentist",
            "type":"Services"
        }
    ],
    "sg:phone":"+61 8 8267 2622",
    "sg:postcode":"5006",
    "sg:province":"SA",
    "wof:name":"Bartholomaeus Anthony Dr",
    "wof:placetype":"venue"
},
  "geometry": {"coordinates":[138.59733581500001,-34.9083862305],"type":"Point"}
}