{
  "type": "Feature",
  "properties": {
    "iso:country":"AU",
    "sg:address":"98 Murray St",
    "sg:city":"Tanunda",
    "sg:classifiers":[
        {
            "category":"Health Services",
            "subcategory":"Health Practitioner",
            "type":"Services"
        }
    ],
    "sg:phone":"+61 8 8563 0244",
    "sg:postcode":"5352",
    "sg:province":"SA",
    "sg:tags":[
        "naturopath"
    ],
    "wof:name":"Healthy Glow",
    "wof:placetype":"venue"
},
  "geometry": {"coordinates":[138.96612548799999,-34.5195732117],"type":"Point"}
}