{
  "type": "Feature",
  "properties": {
    "addr:full":"24 Wellington Rd Lindisfarne TAS 7015",
    "addr:housenumber":"24",
    "addr:postcode":"7015",
    "addr:street":"Wellington Rd",
    "iso:country":"AU",
    "sg:address":"24 Wellington Rd",
    "sg:city":"Lindisfarne",
    "sg:classifiers":[
        {
            "category":"Health Services",
            "subcategory":"Health Practitioner",
            "type":"Services"
        }
    ],
    "sg:phone":"+61 3 6243 9362",
    "sg:postcode":"7015",
    "sg:province":"TAS",
    "sg:tags":[
        "physiotherapist"
    ],
    "wof:name":"Connell S",
    "wof:placetype":"venue"
},
  "geometry": {"coordinates":[147.35287475600001,-42.8482208252],"type":"Point"}
}