{
  "type": "Feature",
  "properties": {
    "iso:country":"AU",
    "sg:address":"PO Box 987",
    "sg:city":"Hawthorn",
    "sg:classifiers":[
        {
            "category":"Organizations",
            "subcategory":"Professional Association",
            "type":"Services"
        }
    ],
    "sg:phone":"+61 409 070 678",
    "sg:postcode":"8623",
    "sg:province":"SA",
    "sg:tags":[
        "web",
        "internet"
    ],
    "wof:name":"Round IT",
    "wof:placetype":"venue"
},
  "geometry": {"coordinates":[145.035294,-37.822861],"type":"Point"}
}