{
  "type": "Feature",
  "properties": {
    "iso:country":"AU",
    "sg:address":"105 McDougall St",
    "sg:city":"Toowoomba",
    "sg:classifiers":[
        {
            "category":"Retail",
            "subcategory":"Auto Repair",
            "type":"Services"
        }
    ],
    "sg:phone":"+61 7 4634 9347",
    "sg:postcode":"4350",
    "sg:province":"QLD",
    "sg:tags":[
        "electrical"
    ],
    "wof:name":"Hot Wired Auto Electrical",
    "wof:placetype":"venue"
},
  "geometry": {"coordinates":[151.909348,-27.55411],"type":"Point"}
}