{
  "type": "Feature",
  "properties": {
    "iso:country":"AU",
    "sg:address":"12 Norman Drv",
    "sg:city":"Yeppoon",
    "sg:classifiers":[
        {
            "category":"Building & Trades",
            "subcategory":"Construction",
            "type":"Services"
        }
    ],
    "sg:phone":"+61 7 4939 4350",
    "sg:postcode":"4703",
    "sg:province":"QLD",
    "sg:tags":[
        "contractor"
    ],
    "wof:name":"Alexander G & P Pty Ltd",
    "wof:placetype":"venue"
},
  "geometry": {"coordinates":[150.716262817,-23.1480102539],"type":"Point"}
}