{
  "type": "Feature",
  "properties": {
    "addr:full":"168 Kembla St Wollongong NSW 2500",
    "addr:housenumber":"168",
    "addr:postcode":"2500",
    "addr:street":"Kembla St",
    "iso:country":"AU",
    "sg:address":"168 Kembla St",
    "sg:city":"Wollongong",
    "sg:classifiers":[
        {
            "category":"Autos & Motor Vehicles",
            "subcategory":"Auto Supplies",
            "type":"Retail Goods"
        }
    ],
    "sg:phone":"+61 2 4229 1030",
    "sg:postcode":"2500",
    "sg:province":"NSW",
    "sg:tags":[
        "part",
        "cycles",
        "accessory"
    ],
    "wof:name":"Shipp Noel",
    "wof:placetype":"venue"
},
  "geometry": {"coordinates":[150.895737,-34.432812],"type":"Point"}
}