{
  "type": "Feature",
  "properties": {
    "addr:full":"2/ 8 Coleman Ave Carlingford NSW 2118",
    "addr:housenumber":"/ 8",
    "addr:postcode":"2118",
    "addr:street":"Coleman Ave",
    "iso:country":"AU",
    "sg:address":"2/ 8 Coleman Ave",
    "sg:city":"Carlingford",
    "sg:classifiers":[
        {
            "category":"Professional",
            "subcategory":"Detective & Security Services",
            "type":"Services"
        }
    ],
    "sg:phone":"+61 2 9871 7393",
    "sg:postcode":"2118",
    "sg:province":"NSW",
    "sg:tags":[
        "domestic",
        "alarm",
        "commercial",
        "burglar"
    ],
    "wof:name":"Audio and Electronics",
    "wof:placetype":"venue"
},
  "geometry": {"coordinates":[151.04776000999999,-33.7838554382],"type":"Point"}
}