{
  "type": "Feature",
  "properties": {
    "addr:full":"PO Box 3479 Helensvale Town Centre QLD 4212",
    "addr:postcode":"4212",
    "iso:country":"AU",
    "sg:address":"PO Box 3479",
    "sg:city":"Helensvale Town Centre",
    "sg:classifiers":[
        {
            "category":"Wholesale",
            "subcategory":"Painting Supplies",
            "type":"Manufacturing & Wholesale Goods"
        }
    ],
    "sg:phone":"+61 7 5665 8918",
    "sg:postcode":"4212",
    "sg:province":"QLD",
    "sg:tags":[
        "product",
        "cleaning"
    ],
    "wof:name":"Eurovap Products Pty Ltd",
    "wof:placetype":"venue"
},
  "geometry": {"coordinates":[153.338500977,-27.9226665497],"type":"Point"}
}