{
  "type": "Feature",
  "properties": {
    "iso:country":"AU",
    "sg:address":"Shp1/ 6 Booralie Rd",
    "sg:city":"Terrey Hills",
    "sg:classifiers":[
        {
            "category":"Cafe",
            "type":"Food & Drink"
        }
    ],
    "sg:phone":"+61 2 9450 0016",
    "sg:postcode":"2084",
    "sg:province":"NSW",
    "wof:name":"Expresso Sandwich Cafe",
    "wof:placetype":"venue"
},
  "geometry": {"coordinates":[151.22799682600001,-33.6829338074],"type":"Point"}
}