{
  "type": "Feature",
  "properties": {
    "iso:country":"AU",
    "sg:address":"PO Box 3203",
    "sg:city":"Clontarf BC",
    "sg:classifiers":[
        {
            "category":"Building & Trades",
            "subcategory":"Construction",
            "type":"Services"
        }
    ],
    "sg:phone":"+61 413 380 452",
    "sg:postcode":"4019",
    "sg:province":"QLD",
    "sg:tags":[
        "contractor"
    ],
    "wof:name":"MSM Building & Carpentry",
    "wof:placetype":"venue"
},
  "geometry": {"coordinates":[153.08006286599999,-27.2398395538],"type":"Point"}
}