{
  "type": "Feature",
  "properties": {
    "iso:country":"AU",
    "sg:address":"Factory 2, 11 Molan St",
    "sg:city":"Ringwood",
    "sg:classifiers":[
        {
            "category":"Manufacturing",
            "subcategory":"Food",
            "type":"Manufacturing & Wholesale Goods"
        }
    ],
    "sg:phone":"+61 3 9879 1046",
    "sg:postcode":"3134",
    "sg:province":"VIC",
    "sg:tags":[
        "function",
        "catering"
    ],
    "wof:name":"Party Food Shop The",
    "wof:placetype":"venue"
},
  "geometry": {"coordinates":[145.21815490700001,-37.8193855286],"type":"Point"}
}