{
  "type": "Feature",
  "properties": {
    "iso:country":"AU",
    "sg:address":"Northern Rd",
    "sg:city":"(Cnr Eastern Rd) Monash",
    "sg:classifiers":[
        {
            "category":"Farming",
            "subcategory":"Berry Farm",
            "type":"Manufacturing & Wholesale Goods"
        }
    ],
    "sg:phone":"+61 8 8583 5213",
    "sg:postcode":"5342",
    "sg:province":"SA",
    "sg:tags":[
        "fruit",
        "grower"
    ],
    "wof:name":"Muller S L & M K",
    "wof:placetype":"venue"
},
  "geometry": {"coordinates":[140.57000732399999,-34.2113113403],"type":"Point"}
}