{
  "type": "Feature",
  "properties": {
    "addr:full":"220 Williams Rd Toorak VIC 3142",
    "addr:housenumber":"220",
    "addr:postcode":"3142",
    "addr:street":"Williams Rd",
    "iso:country":"AU",
    "sg:address":"220 Williams Rd",
    "sg:city":"Toorak",
    "sg:classifiers":[
        {
            "category":"Travel",
            "subcategory":"Hotels & Motels",
            "type":"Entertainment"
        }
    ],
    "sg:phone":"+61 3 9827 2689",
    "sg:postcode":"3142",
    "sg:province":"VIC",
    "wof:name":"Comfort Inn Toorak Manor",
    "wof:placetype":"venue"
},
  "geometry": {"coordinates":[145.00395202600001,-37.8451957703],"type":"Point"}
}