{
  "type": "Feature",
  "properties": {
    "addr:full":"427 Lake Rd Argenton NSW 2284",
    "addr:housenumber":"427",
    "addr:postcode":"2284",
    "addr:street":"Lake Rd",
    "iso:country":"AU",
    "sg:address":"427 Lake Rd",
    "sg:city":"Argenton",
    "sg:classifiers":[
        {
            "category":"Professional",
            "subcategory":"Art Services",
            "type":"Services"
        }
    ],
    "sg:phone":"+61 2 4958 4403",
    "sg:postcode":"2284",
    "sg:province":"NSW",
    "sg:tags":[
        "decorator",
        "painter"
    ],
    "wof:name":"Mazzantini G and Bacci R",
    "wof:placetype":"venue"
},
  "geometry": {"coordinates":[151.630584717,-32.9350624084],"type":"Point"}
}