{
  "type": "Feature",
  "properties": {
    "addr:full":"104-110 Lyon Drv New Beith QLD 4124",
    "addr:housenumber":"104-110",
    "addr:postcode":"4124",
    "addr:street":"Lyon Drv",
    "iso:country":"AU",
    "sg:address":"104-110 Lyon Drv",
    "sg:city":"New Beith",
    "sg:classifiers":[
        {
            "category":"Farming",
            "subcategory":"Nursery",
            "type":"Manufacturing & Wholesale Goods"
        }
    ],
    "sg:phone":"+61 7 3200 0613",
    "sg:postcode":"4124",
    "sg:province":"QLD",
    "wof:name":"Rainbow Mist Wholesale Nursery",
    "wof:placetype":"venue"
},
  "geometry": {"coordinates":[152.95155334500001,-27.7431507111],"type":"Point"}
}