{
  "type": "Feature",
  "properties": {
    "addr:full":"Unit 11, 8 O&#039;Hart Cl Charmhaven NSW 2263",
    "addr:housenumber":"8",
    "addr:postcode":"2263",
    "addr:street":"O &;Hart Cl Charmhaven",
    "iso:country":"AU",
    "sg:address":"Unit 11, 8",
    "sg:city":"O&#039;Hart Cl Charmhaven",
    "sg:classifiers":[
        {
            "category":"Shopping",
            "subcategory":"Stationery & Office Supplies",
            "type":"Retail Goods"
        }
    ],
    "sg:phone":"+61 2 4392 8647",
    "sg:postcode":"2263",
    "sg:province":"NSW",
    "sg:tags":[
        "packaging",
        "material"
    ],
    "wof:name":"Manebridge Packaging",
    "wof:placetype":"venue"
},
  "geometry": {"coordinates":[151.501068,-33.236889],"type":"Point"}
}