{
  "type": "Feature",
  "properties": {
    "addr:full":"11- 13 Hunter St Stuart QLD 4811",
    "addr:housenumber":"13",
    "addr:postcode":"4811",
    "addr:street":"Hunter St",
    "iso:country":"AU",
    "sg:address":"11- 13 Hunter St",
    "sg:city":"Stuart",
    "sg:classifiers":[
        {
            "category":"Transit Center",
            "subcategory":"Freight",
            "type":"Transportation"
        }
    ],
    "sg:phone":"+61 7 4778 4155",
    "sg:postcode":"4811",
    "sg:province":"QLD",
    "sg:tags":[
        "weighbridge"
    ],
    "wof:name":"Northern Metal Recyclers",
    "wof:placetype":"venue"
},
  "geometry": {"coordinates":[146.85192900000001,-19.346121],"type":"Point"}
}