{
  "type": "Feature",
  "properties": {
    "addr:full":"Unit 2, Lot 7 Cnr Celebration & Lexington Drvs Norwest Esta NSW 2153",
    "addr:housenumber":"lot 7 cnr",
    "addr:postcode":"2153",
    "iso:country":"AU",
    "sg:address":"Unit 2, Lot 7",
    "sg:city":"Cnr Celebration & Lexington Drvs Norwest Esta",
    "sg:classifiers":[
        {
            "category":"Home & Garden",
            "subcategory":"Building Materials",
            "type":"Retail Goods"
        }
    ],
    "sg:phone":"+61 2 9629 1418",
    "sg:postcode":"2153",
    "sg:province":"NSW",
    "sg:tags":[
        "fitting",
        "door"
    ],
    "wof:name":"World Magic Doors",
    "wof:placetype":"venue"
},
  "geometry": {"coordinates":[150.94598388700001,-33.7317848206],"type":"Point"}
}