{
  "type": "Feature",
  "properties": {
    "addr:full":"62 Hill St West Launceston TAS 7250",
    "addr:housenumber":"62",
    "addr:postcode":"7250",
    "addr:street":"Hill St West",
    "iso:country":"AU",
    "sg:address":"62 Hill St",
    "sg:city":"West Launceston",
    "sg:classifiers":[
        {
            "category":"Education",
            "subcategory":"Music School",
            "type":"Public Place"
        }
    ],
    "sg:phone":"+61 3 6331 9367",
    "sg:postcode":"7250",
    "sg:province":"TAS",
    "sg:tags":[
        "teacher"
    ],
    "wof:name":"John F Leggett",
    "wof:placetype":"venue"
},
  "geometry": {"coordinates":[147.13165283199999,-41.4471931458],"type":"Point"}
}