{
  "type": "Feature",
  "properties": {
    "iso:country":"AU",
    "sg:address":"1 Manchester Crt",
    "sg:city":"Dundowran",
    "sg:classifiers":[
        {
            "category":"Professional",
            "subcategory":"Art Services",
            "type":"Services"
        }
    ],
    "sg:phone":"+61 7 4128 8118",
    "sg:postcode":"4655",
    "sg:province":"QLD",
    "sg:tags":[
        "interior",
        "decorator"
    ],
    "wof:name":"J R Lifestyles & Interiors",
    "wof:placetype":"venue"
},
  "geometry": {"coordinates":[152.759445,-25.284945],"type":"Point"}
}