{
  "type": "Feature",
  "properties": {
    "addr:full":"Unit 5/ 10 Babdoyle St Loganholme QLD 4129",
    "addr:postcode":"4129",
    "addr:street":"10 Babdoyle St",
    "iso:country":"AU",
    "sg:address":"Unit 5/ 10 Babdoyle St",
    "sg:city":"Loganholme",
    "sg:phone":"+61 7 3806 0020",
    "sg:postcode":"4129",
    "sg:province":"QLD",
    "sg:website":"http://www.rainwater-tanks.com.au",
    "wof:name":"Water Falls",
    "wof:placetype":"venue"
},
  "geometry": {"coordinates":[153.191314697,-27.6806049347],"type":"Point"}
}