{
  "type": "Feature",
  "properties": {
    "iso:country":"AU",
    "sg:address":"24 Elizabeth St",
    "sg:city":"Argenton",
    "sg:classifiers":[
        {
            "category":"Commercial Area",
            "type":"Public Place"
        }
    ],
    "sg:phone":"+61 427 685 511",
    "sg:postcode":"2284",
    "sg:province":"NSW",
    "sg:tags":[
        "heavy",
        "carrier"
    ],
    "wof:name":"Weowna Pilot Service Pty Ltd",
    "wof:placetype":"venue"
},
  "geometry": {"coordinates":[151.63229370100001,-32.9369926453],"type":"Point"}
}