{
  "type": "Feature",
  "properties": {
    "addr:full":"10 Goses St Roxby Downs SA 5725",
    "addr:housenumber":"10",
    "addr:postcode":"5725",
    "addr:street":"Goses St",
    "iso:country":"AU",
    "sg:address":"10 Goses St",
    "sg:city":"Roxby Downs",
    "sg:classifiers":[
        {
            "category":"Utilities",
            "subcategory":"Refuse",
            "type":"Services"
        }
    ],
    "sg:phone":"+61 8 8671 1001",
    "sg:postcode":"5725",
    "sg:province":"SA",
    "sg:tags":[
        "disposal",
        "reduction",
        "waste"
    ],
    "wof:name":"Collex Pty Ltd",
    "wof:placetype":"venue"
},
  "geometry": {"coordinates":[136.89515685999999,-30.5535697937],"type":"Point"}
}