{
  "type": "Feature",
  "properties": {
    "addr:full":"52 Elizabeth St Paddington QLD 4064",
    "addr:housenumber":"52",
    "addr:postcode":"4064",
    "addr:street":"Elizabeth St",
    "iso:country":"AU",
    "sg:address":"52 Elizabeth St",
    "sg:city":"Paddington",
    "sg:classifiers":[
        {
            "category":"Professional",
            "subcategory":"Computer Services",
            "type":"Services"
        }
    ],
    "sg:phone":"+61 7 3367 1982",
    "sg:postcode":"4064",
    "sg:province":"QLD",
    "sg:tags":[
        "package",
        "software"
    ],
    "wof:name":"ADL Software",
    "wof:placetype":"venue"
},
  "geometry": {"coordinates":[152.99639892600001,-27.4651603699],"type":"Point"}
}