{
  "type": "Feature",
  "properties": {
    "addr:full":"Shp6/ 99 Musgrave St North Rockhampton QLD 4701",
    "addr:housenumber":"99",
    "addr:postcode":"4701",
    "addr:street":"Musgrave St North",
    "iso:country":"AU",
    "sg:address":"Shp6/ 99 Musgrave St",
    "sg:city":"North Rockhampton",
    "sg:classifiers":[
        {
            "category":"Education",
            "subcategory":"Special Training",
            "type":"Public Place"
        }
    ],
    "sg:phone":"+61 7 4922 3800",
    "sg:postcode":"4701",
    "sg:province":"QLD",
    "sg:tags":[
        "development"
    ],
    "wof:name":"Morrissey Training & Consulting Pty Ltd",
    "wof:placetype":"venue"
},
  "geometry": {"coordinates":[150.52189636200001,-23.3659191132],"type":"Point"}
}