{
  "type": "Feature",
  "properties": {
    "addr:full":"Queen St Barraba NSW 2347",
    "addr:postcode":"2347",
    "addr:street":"Queen St",
    "iso:country":"AU",
    "sg:address":"Queen St",
    "sg:city":"Barraba",
    "sg:classifiers":[
        {
            "category":"Travel",
            "subcategory":"Hotels & Motels",
            "type":"Entertainment"
        }
    ],
    "sg:phone":"+61 2 6782 1109",
    "sg:postcode":"2347",
    "sg:province":"NSW",
    "sg:tags":[
        "accommodation"
    ],
    "wof:name":"Central Hotel",
    "wof:placetype":"venue"
},
  "geometry": {"coordinates":[150.610031128,-30.3815441132],"type":"Point"}
}