{
  "type": "Feature",
  "properties": {
    "addr:full":"156a Burke Crs Dampier WA 6713",
    "addr:housenumber":"156a",
    "addr:postcode":"6713",
    "addr:street":"Burke Crs",
    "iso:country":"AU",
    "sg:address":"156a Burke Crs",
    "sg:city":"Dampier",
    "sg:classifiers":[
        {
            "category":"Professional",
            "subcategory":"Engineering",
            "type":"Services"
        }
    ],
    "sg:phone":"+61 8 9183 0777",
    "sg:postcode":"6713",
    "sg:province":"WA",
    "sg:tags":[
        "consulting",
        "engineer"
    ],
    "wof:name":"Redgrave Developments Pty Ltd",
    "wof:placetype":"venue"
},
  "geometry": {"coordinates":[116.711601257,-20.6621799469],"type":"Point"}
}