{
  "type": "Feature",
  "properties": {
    "addr:full":"Shop 3, Woodcroft Town Centre, Bains Rd Woodcroft SA 5162",
    "addr:housenumber":"shop 3",
    "addr:postcode":"5162",
    "addr:street":"Bains Rd",
    "iso:country":"AU",
    "sg:address":"Shop 3, Woodcroft Town Centre, Bains Rd",
    "sg:city":"Woodcroft",
    "sg:classifiers":[
        {
            "category":"Fast Food",
            "type":"Food & Drink"
        }
    ],
    "sg:phone":"+61 8 8325 0064",
    "sg:postcode":"5162",
    "sg:province":"SA",
    "sg:tags":[
        "away",
        "take"
    ],
    "wof:name":"Wok In A Box",
    "wof:placetype":"venue"
},
  "geometry": {"coordinates":[138.55723571799999,-35.1140708923],"type":"Point"}
}