{
  "type": "Feature",
  "properties": {
    "addr:full":"617- 623 Glenferrie Rd Hawthorn VIC 3122",
    "addr:housenumber":"623",
    "addr:postcode":"3122",
    "addr:street":"Glenferrie Rd",
    "iso:country":"AU",
    "sg:address":"617- 623 Glenferrie Rd",
    "sg:city":"Hawthorn",
    "sg:classifiers":[
        {
            "category":"Real Estate",
            "subcategory":"Real Estate Agent",
            "type":"Services"
        }
    ],
    "sg:phone":"+61 3 9818 3988",
    "sg:postcode":"3122",
    "sg:province":"VIC",
    "sg:website":"http://www.hockingstuart.com.au",
    "wof:name":"Hocking Stuart Hawthorn",
    "wof:placetype":"venue"
},
  "geometry": {"coordinates":[145.03501892099999,-37.8234176636],"type":"Point"}
}