{
  "type": "Feature",
  "properties": {
    "iso:country":"AU",
    "sg:address":"Long La",
    "sg:city":"Barwite",
    "sg:classifiers":[
        {
            "category":"Farming",
            "subcategory":"Farm",
            "type":"Manufacturing & Wholesale Goods"
        }
    ],
    "sg:phone":"+61 3 5776 9519",
    "sg:postcode":"3722",
    "sg:province":"VIC",
    "sg:tags":[
        "farmer"
    ],
    "wof:name":"Mahoney M",
    "wof:placetype":"venue"
},
  "geometry": {"coordinates":[146.16921997099999,-37.0024223328],"type":"Point"}
}