{
  "type": "Feature",
  "properties": {
    "addr:full":"467b Hawthorn Rd Caulfield South VIC 3162",
    "addr:housenumber":"467b",
    "addr:postcode":"3162",
    "addr:street":"Hawthorn Rd",
    "iso:country":"AU",
    "sg:address":"467b Hawthorn Rd",
    "sg:city":"Caulfield South",
    "sg:classifiers":[
        {
            "category":"Professional",
            "subcategory":"Business Services",
            "type":"Services"
        }
    ],
    "sg:phone":"+61 3 9523 8208",
    "sg:postcode":"3162",
    "sg:province":"VIC",
    "sg:tags":[
        "management",
        "event"
    ],
    "wof:name":"Newstreet Management Pty Ltd",
    "wof:placetype":"venue"
},
  "geometry": {"coordinates":[145.02070617699999,-37.8944396973],"type":"Point"}
}