{
  "type": "Feature",
  "properties": {
    "iso:country":"AU",
    "sg:address":"Macauley Rd",
    "sg:city":"Emerald",
    "sg:classifiers":[
        {
            "category":"Industrial Area",
            "type":"Public Place"
        }
    ],
    "sg:phone":"+61 1800 076 999",
    "sg:postcode":"4720",
    "sg:province":"QLD",
    "sg:tags":[
        "rural",
        "shed"
    ],
    "wof:name":"Outback Sheds Emerald",
    "wof:placetype":"venue"
},
  "geometry": {"coordinates":[148.154465,-23.505688],"type":"Point"}
}