{
  "type": "Feature",
  "properties": {
    "iso:country":"AU",
    "sg:address":"1505 Albany Hwy",
    "sg:city":"Cannington",
    "sg:classifiers":[
        {
            "category":"Shopping",
            "subcategory":"Computers & Home Electronics",
            "type":"Retail Goods"
        }
    ],
    "sg:phone":"+61 8 9258 7733",
    "sg:postcode":"6107",
    "sg:province":"WA",
    "sg:tags":[
        "hardware",
        "equipment"
    ],
    "wof:name":"Arrow Computers",
    "wof:placetype":"venue"
},
  "geometry": {"coordinates":[115.92653656,-32.0118980408],"type":"Point"}
}