{
  "type": "Feature",
  "properties": {
    "iso:country":"AU",
    "sg:address":"23 Missenden Rd",
    "sg:city":"Camperdown",
    "sg:classifiers":[
        {
            "category":"Retail",
            "subcategory":"Self-service Laundry",
            "type":"Services"
        }
    ],
    "sg:phone":"+61 2 9565 5808",
    "sg:postcode":"2050",
    "sg:province":"NSW",
    "wof:name":"Washington Laundry",
    "wof:placetype":"venue"
},
  "geometry": {"coordinates":[151.179855,-33.88726],"type":"Point"}
}