{
  "type": "Feature",
  "properties": {
    "addr:full":"2 Fleming St Muswellbrook NSW 2333",
    "addr:housenumber":"2",
    "addr:postcode":"2333",
    "addr:street":"Fleming St",
    "iso:country":"AU",
    "sg:address":"2 Fleming St",
    "sg:city":"Muswellbrook",
    "sg:classifiers":[
        {
            "category":"Building & Trades",
            "subcategory":"Construction",
            "type":"Services"
        }
    ],
    "sg:phone":"+61 2 6541 1456",
    "sg:postcode":"2333",
    "sg:province":"NSW",
    "sg:tags":[
        "ceiling"
    ],
    "wof:name":"Jonas Merrick Plasterer",
    "wof:placetype":"venue"
},
  "geometry": {"coordinates":[150.89337158199999,-32.2605438232],"type":"Point"}
}