{
  "type": "Feature",
  "properties": {
    "addr:full":"39 Woolshed Creek Rd Hatton Vale QLD 4341",
    "addr:housenumber":"39",
    "addr:postcode":"4341",
    "addr:street":"Woolshed Creek Rd",
    "iso:country":"AU",
    "sg:address":"39 Woolshed Creek Rd",
    "sg:city":"Hatton Vale",
    "sg:classifiers":[
        {
            "category":"Personal",
            "subcategory":"Beauty Salon",
            "type":"Services"
        }
    ],
    "sg:phone":"+61 7 5465 6741",
    "sg:postcode":"4341",
    "sg:province":"QLD",
    "sg:tags":[
        "supply",
        "artist",
        "make-up"
    ],
    "wof:name":"Edwards Lynne",
    "wof:placetype":"venue"
},
  "geometry": {"coordinates":[152.464355469,-27.5750312805],"type":"Point"}
}