{
  "type": "Feature",
  "properties": {
    "addr:full":"Cnr Kent & Argyle Sts The Rocks NSW 2000",
    "addr:postcode":"2000",
    "addr:street":"Cnr",
    "iso:country":"AU",
    "sg:address":"Cnr Kent & Argyle Sts",
    "sg:city":"The Rocks",
    "sg:classifiers":[
        {
            "category":"Travel",
            "subcategory":"Hotels & Motels",
            "type":"Entertainment"
        }
    ],
    "sg:phone":"+61 2 9251 4044",
    "sg:postcode":"2000",
    "sg:province":"NSW",
    "sg:tags":[
        "accommodation"
    ],
    "wof:name":"Lord Nelson Brewery Hotel The",
    "wof:placetype":"venue"
},
  "geometry": {"coordinates":[151.203582764,-33.8590545654],"type":"Point"}
}