{
  "type": "Feature",
  "properties": {
    "addr:full":"27 Flaxmill Rd Morphett Vale SA 5162",
    "addr:housenumber":"27",
    "addr:postcode":"5162",
    "addr:street":"Flaxmill Rd",
    "iso:country":"AU",
    "sg:address":"27 Flaxmill Rd",
    "sg:city":"Morphett Vale",
    "sg:classifiers":[
        {
            "category":"Personal",
            "subcategory":"Beauty Salon",
            "type":"Services"
        }
    ],
    "sg:phone":"+61 8 8186 4866",
    "sg:postcode":"5162",
    "sg:province":"SA",
    "sg:tags":[
        "hairdresser"
    ],
    "wof:name":"Southern Trichology Clinic",
    "wof:placetype":"venue"
},
  "geometry": {"coordinates":[138.51910400400001,-35.1266784668],"type":"Point"}
}