{
  "type": "Feature",
  "properties": {
    "addr:full":"Suite 202, 3- 9 Spring St Chatswood NSW 2057",
    "addr:housenumber":"3 9",
    "addr:postcode":"2057",
    "addr:street":"Spring St",
    "iso:country":"AU",
    "sg:address":"Suite 202, 3- 9 Spring St",
    "sg:city":"Chatswood",
    "sg:classifiers":[
        {
            "category":"Sports & Exercise",
            "subcategory":"Gym",
            "type":"Entertainment"
        }
    ],
    "sg:phone":"+61 412 619 860",
    "sg:postcode":"2057",
    "sg:province":"NSW",
    "sg:tags":[
        "meditation"
    ],
    "wof:name":"Drion Maggie",
    "wof:placetype":"venue"
},
  "geometry": {"coordinates":[151.184936523,-33.7966842651],"type":"Point"}
}