{
  "type": "Feature",
  "properties": {
    "addr:full":"134 Hampden Rd Artarmon NSW 2064",
    "addr:housenumber":"134",
    "addr:postcode":"2064",
    "addr:street":"Hampden Rd",
    "iso:country":"AU",
    "sg:address":"134 Hampden Rd",
    "sg:city":"Artarmon",
    "sg:classifiers":[
        {
            "category":"Organizations",
            "subcategory":"Professional Association",
            "type":"Services"
        }
    ],
    "sg:phone":"+61 2 9411 2733",
    "sg:postcode":"2064",
    "sg:province":"NSW",
    "sg:tags":[
        "organisation",
        "business"
    ],
    "wof:name":"Australian Veterinary Asscn Ltd (National Office)",
    "wof:placetype":"venue"
},
  "geometry": {"coordinates":[151.183303833,-33.8079605103],"type":"Point"}
}