{
  "type": "Feature",
  "properties": {
    "addr:full":"196- 234 Albany Hwy Victoria Park WA 6100",
    "addr:housenumber":"234",
    "addr:postcode":"6100",
    "addr:street":"Albany Hwy Victoria",
    "iso:country":"AU",
    "sg:address":"196- 234 Albany Hwy",
    "sg:city":"Victoria Park",
    "sg:classifiers":[
        {
            "category":"Retail",
            "subcategory":"Auto Repair",
            "type":"Services"
        }
    ],
    "sg:phone":"+61 8 9334 3333",
    "sg:postcode":"6100",
    "sg:province":"WA",
    "sg:tags":[
        "repairer",
        "motor",
        "engineer"
    ],
    "wof:name":"Skipper Mitsubishi",
    "wof:placetype":"venue"
},
  "geometry": {"coordinates":[115.892608643,-31.969827652],"type":"Point"}
}