{
  "type": "Feature",
  "properties": {
    "addr:full":"216 Urana St Wagga Wagga NSW 2650",
    "addr:housenumber":"216",
    "addr:postcode":"2650",
    "addr:street":"Urana St",
    "iso:country":"AU",
    "sg:address":"216 Urana St",
    "sg:city":"Wagga Wagga",
    "sg:classifiers":[
        {
            "category":"Building & Trades",
            "subcategory":"Construction",
            "type":"Services"
        }
    ],
    "sg:phone":"+61 2 6925 5714",
    "sg:postcode":"2650",
    "sg:province":"NSW",
    "sg:tags":[
        "window",
        "aluminium"
    ],
    "wof:name":"Rainbow Windows & Doors",
    "wof:placetype":"venue"
},
  "geometry": {"coordinates":[147.34211730999999,-35.1249847412],"type":"Point"}
}