{
  "type": "Feature",
  "properties": {
    "addr:full":"Shp 5/ 61 Grant St Bacchus Marsh VIC 3340",
    "addr:housenumber":"/ 61",
    "addr:postcode":"3340",
    "addr:street":"Grant St",
    "iso:country":"AU",
    "sg:address":"Shp 5/ 61 Grant St",
    "sg:city":"Bacchus Marsh",
    "sg:classifiers":[
        {
            "category":"Food & Beverages",
            "subcategory":"Groceries & Convenience Stores",
            "type":"Retail Goods"
        }
    ],
    "sg:phone":"+61 3 5367 8408",
    "sg:postcode":"3340",
    "sg:province":"VIC",
    "wof:name":"Grant Street Corner Store",
    "wof:placetype":"venue"
},
  "geometry": {"coordinates":[144.43344099999999,-37.684078],"type":"Point"}
}