{
  "type": "Feature",
  "properties": {
    "iso:country":"AU",
    "sg:address":"11 Kavieng St",
    "sg:city":"Trinity Beach",
    "sg:classifiers":[
        {
            "category":"Real Estate",
            "subcategory":"Surveying",
            "type":"Services"
        }
    ],
    "sg:phone":"+61 7 4057 7177",
    "sg:postcode":"4879",
    "sg:province":"QLD",
    "sg:tags":[
        "surveyor",
        "land"
    ],
    "wof:name":"Pozzi Gary",
    "wof:placetype":"venue"
},
  "geometry": {"coordinates":[145.69073486299999,-16.7926445007],"type":"Point"}
}