{
  "type": "Feature",
  "properties": {
    "addr:full":"Level 7, 121 Walker St North Sydney NSW 2059",
    "addr:housenumber":"121",
    "addr:postcode":"2059",
    "addr:street":"Walker St",
    "iso:country":"AU",
    "sg:address":"Level 7, 121 Walker St",
    "sg:city":"North Sydney",
    "sg:classifiers":[
        {
            "category":"Banks & Credit Unions",
            "subcategory":"Financial Services",
            "type":"Services"
        }
    ],
    "sg:phone":"+61 2 9929 6222",
    "sg:postcode":"2059",
    "sg:province":"NSW",
    "sg:tags":[
        "planning"
    ],
    "wof:name":"Associated Planners Financial Services Limited",
    "wof:placetype":"venue"
},
  "geometry": {"coordinates":[151.20903000000001,-33.838844],"type":"Point"}
}