{
  "type": "Feature",
  "properties": {
    "addr:full":"5 Arden Crt Seaford VIC 3198",
    "addr:housenumber":"5",
    "addr:postcode":"3198",
    "addr:street":"Arden Crt",
    "iso:country":"AU",
    "sg:address":"5 Arden Crt",
    "sg:city":"Seaford",
    "sg:classifiers":[
        {
            "category":"Building & Trades",
            "subcategory":"Construction",
            "type":"Services"
        }
    ],
    "sg:phone":"+61 418 546 846",
    "sg:postcode":"3198",
    "sg:province":"VIC",
    "sg:tags":[
        "builder",
        "designer",
        "room",
        "cool"
    ],
    "wof:name":"Aerocool",
    "wof:placetype":"venue"
},
  "geometry": {"coordinates":[145.13407898,-38.10754776],"type":"Point"}
}