{
  "type": "Feature",
  "properties": {
    "addr:full":"1st Floor, 544 Hay St Perth WA 6000",
    "addr:housenumber":"544",
    "addr:postcode":"6000",
    "addr:street":"Hay St",
    "iso:country":"AU",
    "sg:address":"1st Floor, 544 Hay St",
    "sg:city":"Perth",
    "sg:classifiers":[
        {
            "category":"Professional",
            "subcategory":"Management & Consulting",
            "type":"Services"
        }
    ],
    "sg:phone":"+61 8 9325 3828",
    "sg:postcode":"6000",
    "sg:province":"WA",
    "sg:tags":[
        "consultant",
        "migration"
    ],
    "wof:name":"National Australia Migration Services",
    "wof:placetype":"venue"
},
  "geometry": {"coordinates":[115.855499268,-31.9531917572],"type":"Point"}
}