{
  "type": "Feature",
  "properties": {
    "iso:country":"AU",
    "sg:address":"Level 9 490 Bourke St",
    "sg:city":"Melbourne",
    "sg:classifiers":[
        {
            "category":"Banks & Credit Unions",
            "subcategory":"Atm",
            "type":"Services"
        }
    ],
    "sg:phone":"+61 3 9670 0699",
    "sg:postcode":"3000",
    "sg:province":"VIC",
    "sg:tags":[
        "shelf"
    ],
    "wof:name":"MMD Commercial Legal Services",
    "wof:placetype":"venue"
},
  "geometry": {"coordinates":[144.95912170400001,-37.815284729],"type":"Point"}
}