{
  "type": "Feature",
  "properties": {
    "iso:country":"AU",
    "sg:address":"117 Redfern St",
    "sg:city":"Macquarie",
    "sg:classifiers":[
        {
            "category":"Retail",
            "subcategory":"Auto Rental",
            "type":"Services"
        }
    ],
    "sg:phone":"+61 2 6251 8111",
    "sg:postcode":"2614",
    "sg:province":"ACT",
    "sg:tags":[
        "car",
        "hire",
        "minibus"
    ],
    "wof:name":"Twenty Four-Seven Car & Truck Rentals",
    "wof:placetype":"venue"
},
  "geometry": {"coordinates":[149.07371520999999,-35.2532806396],"type":"Point"}
}