{
  "type": "Feature",
  "properties": {
    "addr:full":"4 Woodlot Crt Buderim QLD 4556",
    "addr:housenumber":"4",
    "addr:postcode":"4556",
    "addr:street":"Woodlot Crt",
    "iso:country":"AU",
    "sg:address":"4 Woodlot Crt",
    "sg:city":"Buderim",
    "sg:classifiers":[
        {
            "category":"Utilities",
            "subcategory":"Electric",
            "type":"Services"
        }
    ],
    "sg:phone":"+61 7 5445 6156",
    "sg:postcode":"4556",
    "sg:province":"QLD",
    "sg:tags":[
        "electrical",
        "contractor"
    ],
    "wof:name":"Pead Ron",
    "wof:placetype":"venue"
},
  "geometry": {"coordinates":[153.066940308,-26.6681728363],"type":"Point"}
}