{
  "type": "Feature",
  "properties": {
    "addr:full":"1 Naver St Middle Park QLD 4074",
    "addr:housenumber":"1",
    "addr:postcode":"4074",
    "addr:street":"Naver St",
    "iso:country":"AU",
    "sg:address":"1 Naver St",
    "sg:city":"Middle Park",
    "sg:classifiers":[
        {
            "category":"Shopping",
            "subcategory":"Clothing, Apparel, & Fashions",
            "type":"Retail Goods"
        }
    ],
    "sg:phone":"+61 7 3376 8854",
    "sg:postcode":"4074",
    "sg:province":"QLD",
    "sg:tags":[
        "wholesaler",
        "children's",
        "mfrs",
        "wear"
    ],
    "wof:name":"Lizzard Kidz",
    "wof:placetype":"venue"
},
  "geometry": {"coordinates":[152.926177978,-27.5541286469],"type":"Point"}
}