{
  "type": "Feature",
  "properties": {
    "addr:full":"24 Pearl St Derwent Park TAS 7009",
    "addr:housenumber":"24",
    "addr:postcode":"7009",
    "addr:street":"Pearl St",
    "iso:country":"AU",
    "sg:address":"24 Pearl St",
    "sg:city":"Derwent Park",
    "sg:classifiers":[
        {
            "category":"Home & Garden",
            "subcategory":"Garden Supply",
            "type":"Retail Goods"
        }
    ],
    "sg:phone":"+61 3 6272 3105",
    "sg:postcode":"7009",
    "sg:province":"TAS",
    "sg:tags":[
        "equipment"
    ],
    "wof:name":"Polythene Company Pty Ltd",
    "wof:placetype":"venue"
},
  "geometry": {"coordinates":[147.29971313499999,-42.8376083374],"type":"Point"}
}