{
  "type": "Feature",
  "properties": {
    "addr:full":"PO Box 1500 Wangara Private Boxes WA 6947",
    "addr:postcode":"6947",
    "iso:country":"AU",
    "sg:address":"PO Box 1500",
    "sg:city":"Wangara Private Boxes",
    "sg:classifiers":[
        {
            "category":"Building & Trades",
            "subcategory":"Construction",
            "type":"Services"
        }
    ],
    "sg:phone":"+61 8 9409 9948",
    "sg:postcode":"6947",
    "sg:province":"WA",
    "sg:tags":[
        "tennis court",
        "repair"
    ],
    "wof:name":"Sportcoat",
    "wof:placetype":"venue"
},
  "geometry": {"coordinates":[115.83036041299999,-31.7966709137],"type":"Point"}
}