{
  "type": "Feature",
  "properties": {
    "iso:country":"AU",
    "sg:address":"Shop 8 The Homemaker Cntr 171 Princes Hwy",
    "sg:city":"Ulladulla",
    "sg:classifiers":[
        {
            "category":"Shopping",
            "subcategory":"Computers & Home Electronics",
            "type":"Retail Goods"
        }
    ],
    "sg:phone":"+61 2 4454 4522",
    "sg:postcode":"2539",
    "sg:province":"NSW",
    "sg:tags":[
        "hardware",
        "equipment"
    ],
    "wof:name":"CompuPort",
    "wof:placetype":"venue"
},
  "geometry": {"coordinates":[150.47564697300001,-35.3510398865],"type":"Point"}
}