{
  "type": "Feature",
  "properties": {
    "addr:full":"77 Norwood Rd Maida Vale WA 6057",
    "addr:housenumber":"77",
    "addr:postcode":"6057",
    "addr:street":"Norwood Rd",
    "iso:country":"AU",
    "sg:address":"77 Norwood Rd",
    "sg:city":"Maida Vale",
    "sg:classifiers":[
        {
            "category":"Commercial Area",
            "type":"Public Place"
        }
    ],
    "sg:phone":"+61 8 9454 7659",
    "sg:postcode":"6057",
    "sg:province":"WA",
    "sg:tags":[
        "heavy",
        "carrier"
    ],
    "wof:name":"Jones G S & G A",
    "wof:placetype":"venue"
},
  "geometry": {"coordinates":[116.02185821499999,-31.9606456757],"type":"Point"}
}