{
  "type": "Feature",
  "properties": {
    "iso:country":"AU",
    "sg:address":"16 Hamilton Pl",
    "sg:city":"Bowen Hills",
    "sg:classifiers":[
        {
            "category":"Organizations",
            "subcategory":"Non-profit Organization",
            "type":"Services"
        }
    ],
    "sg:phone":"+61 7 3367 7433",
    "sg:postcode":"4006",
    "sg:province":"QLD",
    "sg:tags":[
        "support",
        "disability",
        "organisation"
    ],
    "sg:website":"http://www.redcross.org.au",
    "wof:name":"Red Cross Employment Services",
    "wof:placetype":"venue"
},
  "geometry": {"coordinates":[153.03579711899999,-27.4477806091],"type":"Point"}
}