{
  "type": "Feature",
  "properties": {
    "addr:full":"Larrys Mountain Rd Moruya NSW 2537",
    "addr:postcode":"2537",
    "addr:street":"Larrys Mountain Rd",
    "iso:country":"AU",
    "sg:address":"Larrys Mountain Rd",
    "sg:city":"Moruya",
    "sg:classifiers":[
        {
            "category":"Building & Trades",
            "subcategory":"Construction",
            "type":"Services"
        }
    ],
    "sg:phone":"+61 2 4474 3438",
    "sg:postcode":"2537",
    "sg:province":"NSW",
    "sg:tags":[
        "fencing",
        "contractor"
    ],
    "wof:name":"Cody T & E",
    "wof:placetype":"venue"
},
  "geometry": {"coordinates":[150.083786011,-35.8879776001],"type":"Point"}
}