{
  "type": "Feature",
  "properties": {
    "iso:country":"AU",
    "sg:address":"Unit 2/ 331 Newbridge Rd",
    "sg:city":"Moorebank",
    "sg:classifiers":[
        {
            "category":"Retail",
            "subcategory":"Auto Repair",
            "type":"Services"
        }
    ],
    "sg:phone":"+61 2 9600 6843",
    "sg:postcode":"2170",
    "sg:province":"NSW",
    "sg:tags":[
        "repairer",
        "motor",
        "engineer"
    ],
    "wof:name":"Auto Vet Automotive Repairs",
    "wof:placetype":"venue"
},
  "geometry": {"coordinates":[150.936843872,-33.9356193542],"type":"Point"}
}