{
  "type": "Feature",
  "properties": {
    "addr:full":"37 Campsie St Wilton NSW 2571",
    "addr:housenumber":"37",
    "addr:postcode":"2571",
    "addr:street":"Campsie St",
    "iso:country":"AU",
    "sg:address":"37 Campsie St",
    "sg:city":"Wilton",
    "sg:classifiers":[
        {
            "category":"Utilities",
            "subcategory":"Water",
            "type":"Services"
        }
    ],
    "sg:phone":"+61 402 055 698",
    "sg:postcode":"2571",
    "sg:province":"NSW",
    "sg:tags":[
        "cartage"
    ],
    "wof:name":"Wollondilly Watertruck",
    "wof:placetype":"venue"
},
  "geometry": {"coordinates":[150.694915772,-34.2349319458],"type":"Point"}
}