{
  "type": "Feature",
  "properties": {
    "addr:full":"245 Victoria St Darlinghurst NSW 2010",
    "addr:housenumber":"245",
    "addr:postcode":"2010",
    "addr:street":"Victoria St",
    "iso:country":"AU",
    "sg:address":"245 Victoria St",
    "sg:city":"Darlinghurst",
    "sg:classifiers":[
        {
            "category":"Fast Food",
            "type":"Food & Drink"
        }
    ],
    "sg:phone":"+61 2 9360 6455",
    "sg:postcode":"2010",
    "sg:province":"NSW",
    "sg:tags":[
        "away",
        "take"
    ],
    "wof:name":"Thada Thai Cuisine",
    "wof:placetype":"venue"
},
  "geometry": {"coordinates":[151.22128295900001,-33.8781318665],"type":"Point"}
}