{
  "type": "Feature",
  "properties": {
    "iso:country":"AU",
    "sg:address":"Shp4/ Murray St",
    "sg:city":"Wonthaggi",
    "sg:classifiers":[
        {
            "category":"Personal",
            "subcategory":"Beauty Salon",
            "type":"Services"
        }
    ],
    "sg:phone":"+61 3 5672 2583",
    "sg:postcode":"3995",
    "sg:province":"VIC",
    "sg:tags":[
        "hairdresser"
    ],
    "wof:name":"Scissortrix",
    "wof:placetype":"venue"
},
  "geometry": {"coordinates":[145.59251399999999,-38.604733],"type":"Point"}
}