{
  "type": "Feature",
  "properties": {
    "iso:country":"AU",
    "sg:address":"12 Dunnage Crt",
    "sg:city":"Atwell",
    "sg:classifiers":[
        {
            "category":"Professional",
            "subcategory":"Computer Services",
            "type":"Services"
        }
    ],
    "sg:phone":"+61 8 9498 6858",
    "sg:postcode":"6164",
    "sg:province":"WA",
    "sg:tags":[
        "consultant",
        "system"
    ],
    "wof:name":"Harmony Digital",
    "wof:placetype":"venue"
},
  "geometry": {"coordinates":[115.866951,-32.137993],"type":"Point"}
}