{
  "type": "Feature",
  "properties": {
    "addr:full":"49 First Ave Bickley WA 6076",
    "addr:housenumber":"49",
    "addr:postcode":"6076",
    "addr:street":"First Ave",
    "iso:country":"AU",
    "sg:address":"49 First Ave",
    "sg:city":"Bickley",
    "sg:classifiers":[
        {
            "category":"Home & Garden",
            "subcategory":"Building Materials",
            "type":"Retail Goods"
        }
    ],
    "sg:phone":"+61 8 9291 6107",
    "sg:postcode":"6076",
    "sg:province":"WA",
    "sg:tags":[
        "lawn",
        "cutting",
        "maintenance"
    ],
    "wof:name":"N.J. Lawnmowing",
    "wof:placetype":"venue"
},
  "geometry": {"coordinates":[116.092231751,-32.0093193054],"type":"Point"}
}