{
  "type": "Feature",
  "properties": {
    "addr:full":"146 Palace St Denman NSW 2328",
    "addr:housenumber":"146",
    "addr:postcode":"2328",
    "addr:street":"Palace St",
    "iso:country":"AU",
    "sg:address":"146 Palace St",
    "sg:city":"Denman",
    "sg:classifiers":[
        {
            "category":"Building & Trades",
            "subcategory":"Construction",
            "type":"Services"
        }
    ],
    "sg:phone":"+61 2 6547 2513",
    "sg:postcode":"2328",
    "sg:province":"NSW",
    "sg:tags":[
        "earth",
        "excavating",
        "moving",
        "contractor"
    ],
    "wof:name":"Denman Bobcat Service",
    "wof:placetype":"venue"
},
  "geometry": {"coordinates":[150.689849853,-32.3848228455],"type":"Point"}
}