{
  "type": "Feature",
  "properties": {
    "addr:full":"31 Teddington Rd Burswood WA 6100",
    "addr:housenumber":"31",
    "addr:postcode":"6100",
    "addr:street":"Teddington Rd",
    "iso:country":"AU",
    "sg:address":"31 Teddington Rd",
    "sg:city":"Burswood",
    "sg:classifiers":[
        {
            "category":"Professional",
            "subcategory":"Computer Services",
            "type":"Services"
        }
    ],
    "sg:phone":"+61 8 9355 3399",
    "sg:postcode":"6100",
    "sg:province":"WA",
    "sg:tags":[
        "package",
        "software"
    ],
    "wof:name":"Avanti Projects",
    "wof:placetype":"venue"
},
  "geometry": {"coordinates":[115.893928528,-31.9690227509],"type":"Point"}
}