{
  "type": "Feature",
  "properties": {
    "addr:full":"Cnr Craigan St & Samsonvale Rd Bray Park QLD 4500",
    "addr:postcode":"4500",
    "addr:street":"Cnr Craigan St & Samsonvale Rd",
    "iso:country":"AU",
    "sg:address":"Cnr Craigan St & Samsonvale Rd",
    "sg:city":"Bray Park",
    "sg:classifiers":[
        {
            "category":"Communications",
            "subcategory":"Film & Video Production",
            "type":"Services"
        }
    ],
    "sg:phone":"+61 7 3881 3281",
    "sg:postcode":"4500",
    "sg:province":"QLD",
    "sg:tags":[
        "dvd",
        "library"
    ],
    "wof:name":"Video 2000",
    "wof:placetype":"venue"
},
  "geometry": {"coordinates":[152.97390747099999,-27.3013973236],"type":"Point"}
}