{
  "type": "Feature",
  "properties": {
    "addr:full":"45 Ross St Belmont NSW 2280",
    "addr:housenumber":"45",
    "addr:postcode":"2280",
    "addr:street":"Ross St",
    "iso:country":"AU",
    "sg:address":"45 Ross St",
    "sg:city":"Belmont",
    "sg:classifiers":[
        {
            "category":"Building & Trades",
            "subcategory":"Construction",
            "type":"Services"
        }
    ],
    "sg:phone":"+61 2 4945 3457",
    "sg:postcode":"2280",
    "sg:province":"NSW",
    "sg:tags":[
        "renovation",
        "alterations",
        "extension",
        "contractor"
    ],
    "wof:name":"Yager S J",
    "wof:placetype":"venue"
},
  "geometry": {"coordinates":[151.647994995,-33.0296211243],"type":"Point"}
}