{
  "type": "Feature",
  "properties": {
    "addr:full":"44 Burnett St North Hobart TAS 7000",
    "addr:housenumber":"44",
    "addr:postcode":"7000",
    "addr:street":"Burnett St",
    "iso:country":"AU",
    "sg:address":"44 Burnett St",
    "sg:city":"North Hobart",
    "sg:classifiers":[
        {
            "category":"Retail",
            "subcategory":"Repair Shop",
            "type":"Services"
        }
    ],
    "sg:phone":"+61 3 6231 3599",
    "sg:postcode":"7000",
    "sg:province":"TAS",
    "sg:tags":[
        "windscreen"
    ],
    "sg:website":"http://www.novus.com.au",
    "wof:name":"Novus Windscreen Repairs (Hobart)",
    "wof:placetype":"venue"
},
  "geometry": {"coordinates":[147.31877136200001,-42.8738479614],"type":"Point"}
}