{
  "type": "Feature",
  "properties": {
    "addr:full":"2 Thames St West Wollongong NSW 2500",
    "addr:housenumber":"2",
    "addr:postcode":"2500",
    "addr:street":"Thames St West",
    "iso:country":"AU",
    "sg:address":"2 Thames St",
    "sg:city":"West Wollongong",
    "sg:classifiers":[
        {
            "category":"Building & Trades",
            "subcategory":"Plumbing",
            "type":"Services"
        }
    ],
    "sg:phone":"+61 2 4228 7547",
    "sg:postcode":"2500",
    "sg:province":"NSW",
    "sg:tags":[
        "plumber",
        "gasfitters"
    ],
    "wof:name":"Scott Hiltons Plumbing Service",
    "wof:placetype":"venue"
},
  "geometry": {"coordinates":[150.86459400000001,-34.432602],"type":"Point"}
}