{
  "type": "Feature",
  "properties": {
    "iso:country":"AU",
    "sg:address":"PO Box 395",
    "sg:city":"Daylesford",
    "sg:classifiers":[
        {
            "category":"Food & Beverages",
            "subcategory":"Fruits & Vegetables",
            "type":"Retail Goods"
        }
    ],
    "sg:phone":"+61 3 5348 4133",
    "sg:postcode":"3460",
    "sg:province":"VIC",
    "sg:tags":[
        "bush",
        "ingredient"
    ],
    "wof:name":"Gentle Earth Foods",
    "wof:placetype":"venue"
},
  "geometry": {"coordinates":[144.143035889,-37.3413505554],"type":"Point"}
}