{
  "type": "Feature",
  "properties": {
    "addr:full":"Shop 1A 70 Princes Hwy Corner Souter St Beaconsfield VIC 3807",
    "addr:housenumber":"shop 1a 70",
    "addr:postcode":"3807",
    "addr:street":"Princes Hwy Corner Souter St",
    "iso:country":"AU",
    "sg:address":"Shop 1A 70 Princes Hwy Corner Souter St",
    "sg:city":"Beaconsfield",
    "sg:classifiers":[
        {
            "category":"Health Services",
            "subcategory":"Dentist",
            "type":"Services"
        }
    ],
    "sg:phone":"+61 3 9707 4015",
    "sg:postcode":"3807",
    "sg:province":"VIC",
    "sg:tags":[
        "dental",
        "prosthetist"
    ],
    "wof:name":"Reed Paul",
    "wof:placetype":"venue"
},
  "geometry": {"coordinates":[145.36965942399999,-38.0486755371],"type":"Point"}
}