{
  "type": "Feature",
  "properties": {
    "addr:full":"60 Mulgowie Rd Laidley QLD 4341",
    "addr:housenumber":"60",
    "addr:postcode":"4341",
    "addr:street":"Mulgowie Rd",
    "iso:country":"AU",
    "sg:address":"60 Mulgowie Rd",
    "sg:city":"Laidley",
    "sg:classifiers":[
        {
            "category":"Farming",
            "subcategory":"Farm",
            "type":"Manufacturing & Wholesale Goods"
        }
    ],
    "sg:phone":"+61 7 5465 9153",
    "sg:postcode":"4341",
    "sg:province":"QLD",
    "sg:tags":[
        "farmer"
    ],
    "wof:name":"Sutton M J & S E",
    "wof:placetype":"venue"
},
  "geometry": {"coordinates":[152.373703003,-27.6570129395],"type":"Point"}
}