{
  "type": "Feature",
  "properties": {
    "addr:full":"PO Box 373 Jannali NSW 2226",
    "addr:postcode":"2226",
    "iso:country":"AU",
    "sg:address":"PO Box 373",
    "sg:city":"Jannali",
    "sg:classifiers":[
        {
            "category":"Retail",
            "subcategory":"Auto Rental",
            "type":"Services"
        }
    ],
    "sg:phone":"+61 2 9531 8081",
    "sg:postcode":"2226",
    "sg:province":"NSW",
    "sg:tags":[
        "car",
        "hire",
        "minibus"
    ],
    "wof:name":"All Ocassions Minibus Hire",
    "wof:placetype":"venue"
},
  "geometry": {"coordinates":[151.06605529800001,-34.0162887573],"type":"Point"}
}