{
  "type": "Feature",
  "properties": {
    "addr:full":"26 Luland St Botany NSW 2019",
    "addr:housenumber":"26",
    "addr:postcode":"2019",
    "addr:street":"Luland St",
    "iso:country":"AU",
    "sg:address":"26 Luland St",
    "sg:city":"Botany",
    "sg:classifiers":[
        {
            "category":"Professional",
            "subcategory":"Art Services",
            "type":"Services"
        }
    ],
    "sg:phone":"+61 2 9666 8388",
    "sg:postcode":"2019",
    "sg:province":"NSW",
    "sg:tags":[
        "interior",
        "designer"
    ],
    "wof:name":"GMM Pty Ltd",
    "wof:placetype":"venue"
},
  "geometry": {"coordinates":[151.191848755,-33.9465675354],"type":"Point"}
}