{
  "type": "Feature",
  "properties": {
    "addr:full":"Shop 3 6 Bringelly Rd Kingswood NSW 2747",
    "addr:housenumber":"shop;6",
    "addr:postcode":"2747",
    "addr:street":"Bringelly Rd",
    "iso:country":"AU",
    "sg:address":"Shop 3 6 Bringelly Rd",
    "sg:city":"Kingswood",
    "sg:classifiers":[
        {
            "category":"Real Estate",
            "subcategory":"Real Estate Agent",
            "type":"Services"
        }
    ],
    "sg:phone":"+61 2 4736 8555",
    "sg:postcode":"2747",
    "sg:province":"NSW",
    "wof:name":"Homes R Us",
    "wof:placetype":"venue"
},
  "geometry": {"coordinates":[150.72047424300001,-33.7607040405],"type":"Point"}
}