{
  "type": "Feature",
  "properties": {
    "iso:country":"AU",
    "sg:address":"Shop 3 132 Katoomba St",
    "sg:city":"Blaxland",
    "sg:classifiers":[
        {
            "category":"Shopping",
            "subcategory":"Mobile Phones",
            "type":"Retail Goods"
        }
    ],
    "sg:phone":"+61 2 4751 5510",
    "sg:postcode":"2774",
    "sg:province":"NSW",
    "sg:tags":[
        "telephone",
        "accessory"
    ],
    "wof:name":"Cellular One Katoomba",
    "wof:placetype":"venue"
},
  "geometry": {"coordinates":[150.60708618199999,-33.7418785095],"type":"Point"}
}