{
  "type": "Feature",
  "properties": {
    "iso:country":"AU",
    "sg:address":"1 Keats St",
    "sg:city":"Sandringham",
    "sg:classifiers":[
        {
            "category":"Real Estate",
            "subcategory":"Architect",
            "type":"Services"
        }
    ],
    "sg:phone":"+61 3 9598 0389",
    "sg:postcode":"3191",
    "sg:province":"VIC",
    "wof:name":"Sanderson Edward",
    "wof:placetype":"venue"
},
  "geometry": {"coordinates":[145.01272582999999,-37.9549942017],"type":"Point"}
}