{
  "type": "Feature",
  "properties": {
    "addr:full":"Cnr Nincoola & White Sts Guyra NSW 2365",
    "addr:postcode":"2365",
    "addr:street":"Cnr Nincoola & White Sts",
    "iso:country":"AU",
    "sg:address":"Cnr Nincoola & White Sts",
    "sg:city":"Guyra",
    "sg:classifiers":[
        {
            "category":"Professional",
            "type":"Services"
        }
    ],
    "sg:phone":"+61 2 6779 2228",
    "sg:postcode":"2365",
    "sg:province":"NSW",
    "sg:tags":[
        "buyer",
        "merchant",
        "wool"
    ],
    "wof:name":"Guyra Jackson",
    "wof:placetype":"venue"
},
  "geometry": {"coordinates":[151.67135620100001,-30.2192592621],"type":"Point"}
}