{
  "type": "Feature",
  "properties": {
    "addr:full":"5 Hampden Park Rd Kelso NSW 2795",
    "addr:housenumber":"5",
    "addr:postcode":"2795",
    "addr:street":"Hampden Park Rd",
    "iso:country":"AU",
    "sg:address":"5 Hampden Park Rd",
    "sg:city":"Kelso",
    "sg:classifiers":[
        {
            "category":"Home & Garden",
            "subcategory":"Furniture",
            "type":"Retail Goods"
        }
    ],
    "sg:phone":"+61 2 6332 3122",
    "sg:postcode":"2795",
    "sg:province":"NSW",
    "sg:tags":[
        "business"
    ],
    "wof:name":"Ironbark Joinery & Kitchens",
    "wof:placetype":"venue"
},
  "geometry": {"coordinates":[149.610931397,-33.4252967834],"type":"Point"}
}