{
  "type": "Feature",
  "properties": {
    "iso:country":"AU",
    "sg:address":"Shop 4 85 Joseph Banks Ave",
    "sg:city":"Forest Lake",
    "sg:classifiers":[
        {
            "category":"Food & Beverages",
            "subcategory":"Liquor & Beverages",
            "type":"Retail Goods"
        }
    ],
    "sg:phone":"+61 7 3372 3055",
    "sg:postcode":"4078",
    "sg:province":"QLD",
    "sg:tags":[
        "store"
    ],
    "wof:name":"Banks Wine Barrell",
    "wof:placetype":"venue"
},
  "geometry": {"coordinates":[152.97254943900001,-27.6115913391],"type":"Point"}
}