{
  "type": "Feature",
  "properties": {
    "iso:country":"AU",
    "sg:address":"58 Tamar St",
    "sg:city":"Ballina",
    "sg:classifiers":[
        {
            "category":"Professional",
            "subcategory":"Employment Agencies",
            "type":"Services"
        }
    ],
    "sg:phone":"+61 2 6681 6188",
    "sg:postcode":"2478",
    "sg:province":"NSW",
    "wof:name":"EastCoast Training",
    "wof:placetype":"venue"
},
  "geometry": {"coordinates":[153.55668640100001,-28.8675861359],"type":"Point"}
}