{
  "type": "Feature",
  "properties": {
    "iso:country":"AU",
    "sg:address":"112 Bacchus Marsh Rd",
    "sg:city":"Corio",
    "sg:classifiers":[
        {
            "category":"Health Services",
            "subcategory":"Dentist",
            "type":"Services"
        }
    ],
    "sg:phone":"+61 3 5275 3444",
    "sg:postcode":"3214",
    "sg:province":"VIC",
    "wof:name":"Tran D Dr",
    "wof:placetype":"venue"
},
  "geometry": {"coordinates":[144.35906982399999,-38.0746040344],"type":"Point"}
}