{
  "type": "Feature",
  "properties": {
    "iso:country":"AU",
    "sg:address":"1 Doyle St",
    "sg:city":"Collie",
    "sg:classifiers":[
        {
            "category":"Utilities",
            "subcategory":"Refuse",
            "type":"Services"
        }
    ],
    "sg:phone":"+61 427 102 054",
    "sg:postcode":"6225",
    "sg:province":"WA",
    "sg:tags":[
        "remover",
        "rubbish"
    ],
    "wof:name":"A1 Bin Hire + Collie Bin Hire",
    "wof:placetype":"venue"
},
  "geometry": {"coordinates":[116.14814,-33.351921],"type":"Point"}
}