{
  "type": "Feature",
  "properties": {
    "iso:country":"AU",
    "sg:address":"Eighth St",
    "sg:city":"Geraldton",
    "sg:classifiers":[
        {
            "category":"Arena",
            "subcategory":"Sports Club",
            "type":"Entertainment"
        }
    ],
    "sg:phone":"+61 8 9964 5255",
    "sg:postcode":"6530",
    "sg:province":"WA",
    "sg:tags":[
        "organisation",
        "sporting"
    ],
    "wof:name":"Geraldton Amateur Basketball Association",
    "wof:placetype":"venue"
},
  "geometry": {"coordinates":[114.635696411,-28.7683029175],"type":"Point"}
}