{
  "type": "Feature",
  "properties": {
    "addr:full":"47a High St New Norfolk TAS 7140",
    "addr:housenumber":"47a",
    "addr:postcode":"7140",
    "addr:street":"High St",
    "iso:country":"AU",
    "sg:address":"47a High St",
    "sg:city":"New Norfolk",
    "sg:classifiers":[
        {
            "category":"Restaurant",
            "type":"Food & Drink"
        }
    ],
    "sg:phone":"+61 3 6261 2924",
    "sg:postcode":"7140",
    "sg:province":"TAS",
    "wof:name":"Chats Restaurant",
    "wof:placetype":"venue"
},
  "geometry": {"coordinates":[147.06358299999999,-42.780834],"type":"Point"}
}