{
  "type": "Feature",
  "properties": {
    "addr:full":"PO Box 323 Derby WA 6728",
    "addr:postcode":"6728",
    "iso:country":"AU",
    "sg:address":"PO Box 323",
    "sg:city":"Derby",
    "sg:classifiers":[
        {
            "category":"Train Station",
            "subcategory":"Light Rail",
            "type":"Transportation"
        }
    ],
    "sg:phone":"+61 8 9193 1682",
    "sg:postcode":"6728",
    "sg:province":"WA",
    "sg:tags":[
        "equipment",
        "energy",
        "solar"
    ],
    "wof:name":"Progressive Engery Systems",
    "wof:placetype":"venue"
},
  "geometry": {"coordinates":[123.665222168,-17.3448696136],"type":"Point"}
}