{
  "type": "Feature",
  "properties": {
    "addr:full":"Shop 2/ 51 Murdoch Drv Greenfields WA 6210",
    "addr:housenumber":"shop 2 / 51",
    "addr:postcode":"6210",
    "addr:street":"Murdoch Drv",
    "iso:country":"AU",
    "sg:address":"Shop 2/ 51 Murdoch Drv",
    "sg:city":"Greenfields",
    "sg:classifiers":[
        {
            "category":"Food & Beverages",
            "subcategory":"Liquor & Beverages",
            "type":"Retail Goods"
        }
    ],
    "sg:phone":"+61 8 9534 7444",
    "sg:postcode":"6210",
    "sg:province":"WA",
    "sg:tags":[
        "store"
    ],
    "wof:name":"Greenfields Liquor Store",
    "wof:placetype":"venue"
},
  "geometry": {"coordinates":[115.755531,-32.529823],"type":"Point"}
}