{
  "type": "Feature",
  "properties": {
    "iso:country":"AU",
    "sg:address":"PO Box 8151",
    "sg:city":"Warnbro",
    "sg:classifiers":[
        {
            "category":"Utilities",
            "subcategory":"Fuel Oil & Lpg",
            "type":"Services"
        }
    ],
    "sg:phone":"+61 407 788 236",
    "sg:postcode":"6169",
    "sg:province":"WA",
    "sg:tags":[
        "combustion",
        "engineer"
    ],
    "wof:name":"G-Therm",
    "wof:placetype":"venue"
},
  "geometry": {"coordinates":[115.759407,-32.347149],"type":"Point"}
}