{
  "type": "Feature",
  "properties": {
    "addr:full":"Unit 3/ 26 Ellingworth Pde Box Hill VIC 3128",
    "addr:postcode":"3128",
    "addr:street":"26 Ellingworth Pde",
    "iso:country":"AU",
    "sg:address":"Unit 3/ 26 Ellingworth Pde",
    "sg:city":"Box Hill",
    "sg:classifiers":[
        {
            "category":"Building & Trades",
            "subcategory":"Pest Control",
            "type":"Services"
        }
    ],
    "sg:phone":"+61 3 8892 2777",
    "sg:postcode":"3128",
    "sg:province":"VIC",
    "wof:name":"Sporting Shooters Association Of Australia (Victoria)",
    "wof:placetype":"venue"
},
  "geometry": {"coordinates":[145.126296997,-37.8208694458],"type":"Point"}
}