{
  "type": "Feature",
  "properties": {
    "addr:full":"1 Twenty-First Ave Mt Isa QLD 4825",
    "addr:housenumber":"1",
    "addr:postcode":"4825",
    "addr:street":"Twenty-First Ave",
    "iso:country":"AU",
    "sg:address":"1 Twenty-First Ave",
    "sg:city":"Mt Isa",
    "sg:classifiers":[
        {
            "category":"Food & Beverages",
            "subcategory":"Groceries & Convenience Stores",
            "type":"Retail Goods"
        }
    ],
    "sg:phone":"+61 7 4743 3038",
    "sg:postcode":"4825",
    "sg:province":"QLD",
    "wof:name":"Happy Valley General Store",
    "wof:placetype":"venue"
},
  "geometry": {"coordinates":[139.48556500000001,-20.743727],"type":"Point"}
}