{
  "type": "Feature",
  "properties": {
    "iso:country":"AU",
    "sg:address":"52 Market Pl",
    "sg:city":"Smithfield",
    "sg:classifiers":[
        {
            "category":"Building & Trades",
            "subcategory":"Construction",
            "type":"Services"
        }
    ],
    "sg:phone":"+61 418 250 110",
    "sg:postcode":"2164",
    "sg:province":"NSW",
    "sg:tags":[
        "concrete",
        "contractor"
    ],
    "wof:name":"World Concrete Company Pty Ltd",
    "wof:placetype":"venue"
},
  "geometry": {"coordinates":[150.93197631800001,-33.850933075],"type":"Point"}
}