{
  "type": "Feature",
  "properties": {
    "iso:country":"AU",
    "sg:address":"2664 Logan Rd",
    "sg:city":"Eight Mile Plains",
    "sg:classifiers":[
        {
            "category":"Home & Garden",
            "subcategory":"Garden Supply",
            "type":"Retail Goods"
        }
    ],
    "sg:phone":"+61 7 3341 7005",
    "sg:postcode":"4113",
    "sg:province":"QLD",
    "sg:tags":[
        "landscape"
    ],
    "wof:name":"Aamar Transport & Garden Supplies",
    "wof:placetype":"venue"
},
  "geometry": {"coordinates":[153.107955933,-27.5961742401],"type":"Point"}
}