{
  "type": "Feature",
  "properties": {
    "addr:full":"29 Elizabeth St Melbourne VIC 3000",
    "addr:housenumber":"29",
    "addr:postcode":"3000",
    "addr:street":"Elizabeth St",
    "iso:country":"AU",
    "sg:address":"29 Elizabeth St",
    "sg:city":"Melbourne",
    "sg:classifiers":[
        {
            "category":"Shopping",
            "subcategory":"Discount & Variety Stores",
            "type":"Retail Goods"
        }
    ],
    "sg:phone":"+61 3 9629 1096",
    "sg:postcode":"3000",
    "sg:province":"VIC",
    "sg:tags":[
        "shop",
        "adult"
    ],
    "wof:name":"Liberated Adult Centres XXX",
    "wof:placetype":"venue"
},
  "geometry": {"coordinates":[144.96449279800001,-37.817489624],"type":"Point"}
}