{
  "type": "Feature",
  "properties": {
    "iso:country":"AU",
    "sg:address":"78 Mill Point Rd",
    "sg:city":"South Perth",
    "sg:classifiers":[
        {
            "category":"Banks & Credit Unions",
            "subcategory":"Financial Services",
            "type":"Services"
        }
    ],
    "sg:phone":"+61 8 9368 2100",
    "sg:postcode":"6151",
    "sg:province":"WA",
    "sg:tags":[
        "settlement",
        "nt",
        "agent",
        "wa"
    ],
    "wof:name":"Supreme Settlements",
    "wof:placetype":"venue"
},
  "geometry": {"coordinates":[115.850067,-31.971207],"type":"Point"}
}