{
  "type": "Feature",
  "properties": {
    "addr:full":"193 Perrymans La Table Top NSW 2640",
    "addr:housenumber":"193",
    "addr:postcode":"2640",
    "addr:street":"Perrymans La",
    "iso:country":"AU",
    "sg:address":"193 Perrymans La",
    "sg:city":"Table Top",
    "sg:classifiers":[
        {
            "category":"Health Services",
            "subcategory":"Health Practitioner",
            "type":"Services"
        }
    ],
    "sg:phone":"+61 2 6026 2802",
    "sg:postcode":"2640",
    "sg:province":"NSW",
    "sg:tags":[
        "pathologist",
        "speech"
    ],
    "wof:name":"Freida van Staden",
    "wof:placetype":"venue"
},
  "geometry": {"coordinates":[147.00401306099999,-35.954498291],"type":"Point"}
}