{
  "type": "Feature",
  "properties": {
    "addr:full":"Shop 2, 5 Webber Esp Cooktown QLD 4895",
    "addr:housenumber":"shop;5",
    "addr:postcode":"4895",
    "addr:street":"Webber",
    "iso:country":"AU",
    "sg:address":"Shop 2, 5 Webber Esp",
    "sg:city":"Cooktown",
    "sg:classifiers":[
        {
            "category":"Retail",
            "subcategory":"Laundry & Dry Cleaning",
            "type":"Services"
        }
    ],
    "sg:phone":"+61 7 4069 6799",
    "sg:postcode":"4895",
    "sg:province":"QLD",
    "wof:name":"Cooktown Sea Breeze Laundry Mat",
    "wof:placetype":"venue"
},
  "geometry": {"coordinates":[145.249237061,-15.4774303436],"type":"Point"}
}