{
  "type": "Feature",
  "properties": {
    "iso:country":"AU",
    "sg:address":"388 Pacific Hwy",
    "sg:city":"Lindfield",
    "sg:classifiers":[
        {
            "category":"Social Services",
            "type":"Services"
        }
    ],
    "sg:phone":"+61 2 9416 6900",
    "sg:postcode":"2070",
    "sg:province":"NSW",
    "sg:tags":[
        "domestic",
        "help"
    ],
    "sg:website":"http://www.opnannies.com.au",
    "wof:name":"Occasional & Permanent Eldercare & Housekeepers",
    "wof:placetype":"venue"
},
  "geometry": {"coordinates":[151.167312622,-33.7739143372],"type":"Point"}
}