{
  "type": "Feature",
  "properties": {
    "addr:full":"224 Moorabool St Geelong VIC 3220",
    "addr:housenumber":"224",
    "addr:postcode":"3220",
    "addr:street":"Moorabool St",
    "iso:country":"AU",
    "sg:address":"224 Moorabool St",
    "sg:city":"Geelong",
    "sg:classifiers":[
        {
            "category":"Personal",
            "subcategory":"Beauty Salon",
            "type":"Services"
        }
    ],
    "sg:phone":"+61 3 5221 0588",
    "sg:postcode":"3220",
    "sg:province":"VIC",
    "wof:name":"Lavender & Lime",
    "wof:placetype":"venue"
},
  "geometry": {"coordinates":[144.35855100000001,-38.151684],"type":"Point"}
}