{
  "type": "Feature",
  "properties": {
    "addr:full":"Unit 6/ 31 Sabre Drv Port Melbourne VIC 3207",
    "addr:postcode":"3207",
    "addr:street":"Sabre Drv",
    "iso:country":"AU",
    "sg:address":"Unit 6/ 31 Sabre Drv",
    "sg:city":"Port Melbourne",
    "sg:classifiers":[
        {
            "category":"Shopping",
            "subcategory":"Clothing, Apparel, & Fashions",
            "type":"Retail Goods"
        }
    ],
    "sg:phone":"+61 3 9646 3444",
    "sg:postcode":"3207",
    "sg:province":"VIC",
    "sg:tags":[
        "lady",
        "wear"
    ],
    "wof:name":"Sumoton Pty Ltd",
    "wof:placetype":"venue"
},
  "geometry": {"coordinates":[144.90696700000001,-37.827694],"type":"Point"}
}