{
  "type": "Feature",
  "properties": {
    "addr:full":"9 Caley Pl Barden Ridge NSW 2234",
    "addr:housenumber":"9",
    "addr:postcode":"2234",
    "addr:street":"Caley Pl",
    "iso:country":"AU",
    "sg:address":"9 Caley Pl",
    "sg:city":"Barden Ridge",
    "sg:classifiers":[
        {
            "category":"Utilities",
            "type":"Services"
        }
    ],
    "sg:phone":"+61 2 9543 5588",
    "sg:postcode":"2234",
    "sg:province":"NSW",
    "sg:tags":[
        "refrigeration",
        "industrial",
        "commercial",
        "retail"
    ],
    "wof:name":"K & S Refrigeration",
    "wof:placetype":"venue"
},
  "geometry": {"coordinates":[151.009963989,-34.0270118713],"type":"Point"}
}