{
  "type": "Feature",
  "properties": {
    "iso:country":"AU",
    "sg:address":"122 Crown St",
    "sg:city":"Wollongong",
    "sg:classifiers":[
        {
            "category":"Shopping",
            "type":"Retail Goods"
        }
    ],
    "sg:phone":"+61 2 4229 7077",
    "sg:postcode":"2500",
    "sg:province":"NSW",
    "sg:tags":[
        "clearance",
        "factory",
        "outlet"
    ],
    "wof:name":"Givoni",
    "wof:placetype":"venue"
},
  "geometry": {"coordinates":[150.871735,-34.425396],"type":"Point"}
}