{
  "type": "Feature",
  "properties": {
    "iso:country":"AU",
    "sg:address":"Peninsula Fair Shpg. Ctr. Shop 1",
    "sg:city":"Kippa-Ring",
    "sg:classifiers":[
        {
            "category":"Education",
            "subcategory":"Special Training",
            "type":"Public Place"
        }
    ],
    "sg:phone":"+61 7 3880 2626",
    "sg:postcode":"4021",
    "sg:province":"QLD",
    "sg:tags":[
        "diving",
        "school",
        "scuba"
    ],
    "wof:name":"A W Redcliffe Dive Centre",
    "wof:placetype":"venue"
},
  "geometry": {"coordinates":[153.080276,-27.21719],"type":"Point"}
}