{
  "type": "Feature",
  "properties": {
    "addr:full":"272 Dundas St Thornbury VIC 3071",
    "addr:housenumber":"272",
    "addr:postcode":"3071",
    "addr:street":"Dundas St",
    "iso:country":"AU",
    "sg:address":"272 Dundas St",
    "sg:city":"Thornbury",
    "sg:classifiers":[
        {
            "category":"Retail",
            "subcategory":"Auto Repair",
            "type":"Services"
        }
    ],
    "sg:phone":"+61 3 9480 0633",
    "sg:postcode":"3071",
    "sg:province":"VIC",
    "sg:tags":[
        "repairer",
        "motor",
        "engineer"
    ],
    "wof:name":"Supertrac Engineering & Automotive Services Pty Ltd",
    "wof:placetype":"venue"
},
  "geometry": {"coordinates":[145.028366089,-37.7553710938],"type":"Point"}
}