{
  "type": "Feature",
  "properties": {
    "iso:country":"AU",
    "sg:address":"1/ 125 Flores Rd",
    "sg:city":"Geraldton",
    "sg:classifiers":[
        {
            "category":"Manufacturing",
            "subcategory":"Food",
            "type":"Manufacturing & Wholesale Goods"
        }
    ],
    "sg:phone":"+61 8 9964 4463",
    "sg:postcode":"6530",
    "sg:province":"WA",
    "sg:tags":[
        "function",
        "catering"
    ],
    "wof:name":"Le Cafe Flores Rd",
    "wof:placetype":"venue"
},
  "geometry": {"coordinates":[114.627922058,-28.7509536743],"type":"Point"}
}