{
  "type": "Feature",
  "properties": {
    "addr:full":"157 Willarong Road (Cnr Flide St) Caringbah NSW 2229",
    "addr:housenumber":"157",
    "addr:postcode":"2229",
    "addr:street":"Willarong Road Cnr Flide St",
    "iso:country":"AU",
    "sg:address":"157 Willarong Road",
    "sg:city":"(Cnr Flide St) Caringbah",
    "sg:classifiers":[
        {
            "category":"Health Services",
            "subcategory":"Health Practitioner",
            "type":"Services"
        }
    ],
    "sg:phone":"+61 2 9501 4552",
    "sg:postcode":"2229",
    "sg:province":"NSW",
    "sg:tags":[
        "hypnotherapy"
    ],
    "wof:name":"Helena Simon",
    "wof:placetype":"venue"
},
  "geometry": {"coordinates":[151.12008667000001,-34.0404663086],"type":"Point"}
}