{
  "type": "Feature",
  "properties": {
    "addr:full":"PO Box 146 Malvern VIC 3144",
    "addr:postcode":"3144",
    "iso:country":"AU",
    "sg:address":"PO Box 146",
    "sg:city":"Malvern",
    "sg:classifiers":[
        {
            "category":"Professional",
            "subcategory":"Computer Services",
            "type":"Services"
        }
    ],
    "sg:phone":"+61 411 095 279",
    "sg:postcode":"3144",
    "sg:province":"VIC",
    "sg:tags":[
        "consultant",
        "system"
    ],
    "wof:name":"MLF Contracting Services",
    "wof:placetype":"venue"
},
  "geometry": {"coordinates":[145.03689575199999,-37.8525390625],"type":"Point"}
}