{
  "type": "Feature",
  "properties": {
    "iso:country":"AU",
    "sg:address":"3-7 Chamberlain St",
    "sg:city":"Wingfield",
    "sg:classifiers":[
        {
            "category":"Banks & Credit Unions",
            "subcategory":"Atm",
            "type":"Services"
        }
    ],
    "sg:phone":"+61 8 8244 4171",
    "sg:postcode":"5013",
    "sg:province":"SA",
    "sg:tags":[
        "reconditioners",
        "drum",
        "manufacturers"
    ],
    "wof:name":"CRS Container Reconditioning Services Pty Ltd",
    "wof:placetype":"venue"
},
  "geometry": {"coordinates":[138.546951294,-34.8382720947],"type":"Point"}
}