{
  "type": "Feature",
  "properties": {
    "addr:full":"PO Box 44 Bayswater WA 6933",
    "addr:postcode":"6933",
    "iso:country":"AU",
    "sg:address":"PO Box 44",
    "sg:city":"Bayswater",
    "sg:classifiers":[
        {
            "category":"Professional",
            "subcategory":"Accounting & Tax Preparation",
            "type":"Services"
        }
    ],
    "sg:phone":"+61 8 9370 1811",
    "sg:postcode":"6933",
    "sg:province":"WA",
    "sg:tags":[
        "consultant",
        "taxation"
    ],
    "wof:name":"Blakers Pty Ltd",
    "wof:placetype":"venue"
},
  "geometry": {"coordinates":[115.91280365,-31.9184703827],"type":"Point"}
}