{
  "type": "Feature",
  "properties": {
    "addr:full":"32 Hamilton St Oakleigh VIC 3166",
    "addr:housenumber":"32",
    "addr:postcode":"3166",
    "addr:street":"Hamilton St",
    "iso:country":"AU",
    "sg:address":"32 Hamilton St",
    "sg:city":"Oakleigh",
    "sg:classifiers":[
        {
            "category":"Manufacturing",
            "subcategory":"Tools & Machinery",
            "type":"Manufacturing & Wholesale Goods"
        }
    ],
    "sg:phone":"+61 3 9568 6899",
    "sg:postcode":"3166",
    "sg:province":"VIC",
    "sg:tags":[
        "manufactured",
        "specially",
        "designed"
    ],
    "wof:name":"Flex Pack Services & Supplies",
    "wof:placetype":"venue"
},
  "geometry": {"coordinates":[145.100906372,-37.9078674316],"type":"Point"}
}