{
  "type": "Feature",
  "properties": {
    "addr:full":"264 Goyder St Narrabundah ACT 2604",
    "addr:housenumber":"264",
    "addr:postcode":"2604",
    "addr:street":"Goyder St",
    "iso:country":"AU",
    "sg:address":"264 Goyder St",
    "sg:city":"Narrabundah",
    "sg:classifiers":[
        {
            "category":"Professional",
            "subcategory":"Art Services",
            "type":"Services"
        }
    ],
    "sg:phone":"+61 2 6260 7270",
    "sg:postcode":"2604",
    "sg:province":"ACT",
    "sg:tags":[
        "graphic",
        "designer"
    ],
    "wof:name":"Cachet",
    "wof:placetype":"venue"
},
  "geometry": {"coordinates":[149.144729614,-35.3401908875],"type":"Point"}
}