{
  "type": "Feature",
  "properties": {
    "iso:country":"AU",
    "sg:address":"97 Kinghorn St",
    "sg:city":"Nowra",
    "sg:classifiers":[
        {
            "category":"Autos & Motor Vehicles",
            "subcategory":"Fuel & Gas Station",
            "type":"Retail Goods"
        }
    ],
    "sg:phone":"+61 2 4421 4132",
    "sg:postcode":"2541",
    "sg:province":"NSW",
    "wof:name":"Volume Plus Nowra",
    "wof:placetype":"venue"
},
  "geometry": {"coordinates":[150.601837158,-34.8796157837],"type":"Point"}
}