{
  "type": "Feature",
  "properties": {
    "addr:full":"Cement Works Rd Railton TAS 7305",
    "addr:postcode":"7305",
    "addr:street":"Works Rd",
    "iso:country":"AU",
    "sg:address":"Cement Works Rd",
    "sg:city":"Railton",
    "sg:classifiers":[
        {
            "category":"Military Area",
            "subcategory":"Army Base",
            "type":"Public Place"
        }
    ],
    "sg:phone":"+61 3 6491 0111",
    "sg:postcode":"7305",
    "sg:province":"TAS",
    "sg:tags":[
        "wholesaler",
        "mfrs",
        "cement",
        "supply"
    ],
    "wof:name":"Cement Australia Holdings Pty Ltd",
    "wof:placetype":"venue"
},
  "geometry": {"coordinates":[146.41424599999999,-41.328423],"type":"Point"}
}