{
  "type": "Feature",
  "properties": {
    "iso:country":"AU",
    "sg:address":"PO Box 5096",
    "sg:city":"Dalkeith",
    "sg:classifiers":[
        {
            "category":"Mining & Drilling",
            "type":"Manufacturing & Wholesale Goods"
        }
    ],
    "sg:phone":"+61 8 9389 8484",
    "sg:postcode":"6009",
    "sg:province":"WA",
    "sg:tags":[
        "equipment",
        "quarrying",
        "supply"
    ],
    "wof:name":"Aussiequip Pty Ltd",
    "wof:placetype":"venue"
},
  "geometry": {"coordinates":[115.800232,-31.994789],"type":"Point"}
}