{
  "type": "Feature",
  "properties": {
    "addr:full":"109 Northgate Drv Thomastown VIC 3074",
    "addr:housenumber":"109",
    "addr:postcode":"3074",
    "addr:street":"Northgate Drv",
    "iso:country":"AU",
    "sg:address":"109 Northgate Drv",
    "sg:city":"Thomastown",
    "sg:classifiers":[
        {
            "category":"Building & Trades",
            "subcategory":"Construction",
            "type":"Services"
        }
    ],
    "sg:phone":"+61 3 9464 0944",
    "sg:postcode":"3074",
    "sg:province":"VIC",
    "sg:tags":[
        "fencing",
        "contractor"
    ],
    "wof:name":"The Fence Factory Pty Ltd",
    "wof:placetype":"venue"
},
  "geometry": {"coordinates":[145.03021240199999,-37.6886940002],"type":"Point"}
}