{
  "type": "Feature",
  "properties": {
    "addr:full":"13 Separation St Geelong North VIC 3215",
    "addr:housenumber":"13",
    "addr:postcode":"3215",
    "addr:street":"Separation St",
    "iso:country":"AU",
    "sg:address":"13 Separation St",
    "sg:city":"Geelong North",
    "sg:classifiers":[
        {
            "category":"Education",
            "subcategory":"Special Training",
            "type":"Public Place"
        }
    ],
    "sg:phone":"+61 3 5272 3355",
    "sg:postcode":"3215",
    "sg:province":"VIC",
    "sg:tags":[
        "development"
    ],
    "wof:name":"Statewide Fire Protection",
    "wof:placetype":"venue"
},
  "geometry": {"coordinates":[144.34919738799999,-38.1115608215],"type":"Point"}
}