{
  "type": "Feature",
  "properties": {
    "addr:full":"5 Ferndell St South Granville NSW 2142",
    "addr:housenumber":"5",
    "addr:postcode":"2142",
    "addr:street":"Ferndell St",
    "iso:country":"AU",
    "sg:address":"5 Ferndell St",
    "sg:city":"South Granville",
    "sg:classifiers":[
        {
            "category":"Home & Garden",
            "subcategory":"Furniture",
            "type":"Retail Goods"
        }
    ],
    "sg:phone":"+61 2 9632 5599",
    "sg:postcode":"2142",
    "sg:province":"NSW",
    "sg:tags":[
        "business"
    ],
    "wof:name":"Batger R.E. Pty Ltd",
    "wof:placetype":"venue"
},
  "geometry": {"coordinates":[151.009033203,-33.8651161194],"type":"Point"}
}