{
  "type": "Feature",
  "properties": {
    "addr:full":"14 William St Emerald VIC 3782",
    "addr:housenumber":"14",
    "addr:postcode":"3782",
    "addr:street":"William St",
    "iso:country":"AU",
    "sg:address":"14 William St",
    "sg:city":"Emerald",
    "sg:classifiers":[
        {
            "category":"Health Services",
            "subcategory":"Health Practitioner",
            "type":"Services"
        }
    ],
    "sg:phone":"+61 3 5968 5248",
    "sg:postcode":"3782",
    "sg:province":"VIC",
    "sg:tags":[
        "naturopath"
    ],
    "wof:name":"Alison Kane Natural Medicine",
    "wof:placetype":"venue"
},
  "geometry": {"coordinates":[145.457596,-37.934795],"type":"Point"}
}