{
  "type": "Feature",
  "properties": {
    "addr:full":"136 South Rd Torrensville SA 5031",
    "addr:housenumber":"136",
    "addr:postcode":"5031",
    "addr:street":"South Rd",
    "iso:country":"AU",
    "sg:address":"136 South Rd",
    "sg:city":"Torrensville",
    "sg:classifiers":[
        {
            "category":"Organizations",
            "subcategory":"Professional Association",
            "type":"Services"
        }
    ],
    "sg:phone":"+61 8 8234 9522",
    "sg:postcode":"5031",
    "sg:province":"SA",
    "sg:tags":[
        "organisation",
        "business"
    ],
    "wof:name":"Self Insurers Of South Australia Inc",
    "wof:placetype":"venue"
},
  "geometry": {"coordinates":[138.56898498499999,-34.9209213257],"type":"Point"}
}