{
  "type": "Feature",
  "properties": {
    "addr:full":"Unit 3-5, 20 Chain St Mackay QLD 4740",
    "addr:housenumber":"20",
    "addr:postcode":"4740",
    "addr:street":"Chain St",
    "iso:country":"AU",
    "sg:address":"Unit 3-5, 20 Chain St",
    "sg:city":"Mackay",
    "sg:classifiers":[
        {
            "category":"Building & Trades",
            "subcategory":"Plumbing",
            "type":"Services"
        }
    ],
    "sg:phone":"+61 7 4951 4355",
    "sg:postcode":"4740",
    "sg:province":"QLD",
    "sg:tags":[
        "fitting",
        "hose",
        "supply"
    ],
    "wof:name":"Tony Powell Hose & Fittings Pty Ltd",
    "wof:placetype":"venue"
},
  "geometry": {"coordinates":[149.19708299999999,-21.145199],"type":"Point"}
}