{
  "type": "Feature",
  "properties": {
    "addr:full":"58 Whitehorse Rd Balwyn VIC 3103",
    "addr:housenumber":"58",
    "addr:postcode":"3103",
    "addr:street":"Whitehorse Rd",
    "iso:country":"AU",
    "sg:address":"58 Whitehorse Rd",
    "sg:city":"Balwyn",
    "sg:classifiers":[
        {
            "category":"Building & Trades",
            "subcategory":"Plumbing",
            "type":"Services"
        }
    ],
    "sg:phone":"+61 3 9817 1988",
    "sg:postcode":"3103",
    "sg:province":"VIC",
    "sg:tags":[
        "repair",
        "appliance",
        "system",
        "heating"
    ],
    "wof:name":"Super Quick Plumbing",
    "wof:placetype":"venue"
},
  "geometry": {"coordinates":[145.06503295900001,-37.8109893799],"type":"Point"}
}