{
  "type": "Feature",
  "properties": {
    "addr:full":"20 - 24 Wentworth St Parramatta NSW 2150",
    "addr:housenumber":"24",
    "addr:postcode":"2150",
    "addr:street":"Wentworth St",
    "iso:country":"AU",
    "sg:address":"20 - 24 Wentworth St",
    "sg:city":"Parramatta",
    "sg:classifiers":[
        {
            "category":"Professional",
            "subcategory":"Accounting & Tax Preparation",
            "type":"Services"
        }
    ],
    "sg:phone":"+61 2 9635 1833",
    "sg:postcode":"2150",
    "sg:province":"NSW",
    "sg:tags":[
        "accountant",
        "auditor"
    ],
    "wof:name":"Bulgeries David J & Co",
    "wof:placetype":"venue"
},
  "geometry": {"coordinates":[151.022583008,-33.8313484192],"type":"Point"}
}