{
  "type": "Feature",
  "properties": {
    "addr:full":"127 Main St Zeehan TAS 7469",
    "addr:housenumber":"127",
    "addr:postcode":"7469",
    "addr:street":"Main St",
    "iso:country":"AU",
    "sg:address":"127 Main St",
    "sg:city":"Zeehan",
    "sg:classifiers":[
        {
            "category":"Food & Beverages",
            "subcategory":"Supermarket",
            "type":"Retail Goods"
        }
    ],
    "sg:phone":"+61 3 6471 6232",
    "sg:postcode":"7469",
    "sg:province":"TAS",
    "sg:tags":[
        "grocery",
        "store"
    ],
    "wof:name":"Value Plus IGA Stores",
    "wof:placetype":"venue"
},
  "geometry": {"coordinates":[145.33552551299999,-41.8828277588],"type":"Point"}
}