{
  "type": "Feature",
  "properties": {
    "addr:full":"Cnr Wanneroo & Gnangara Rds Wanneroo WA 6065",
    "addr:postcode":"6065",
    "addr:street":"Cnr",
    "iso:country":"AU",
    "sg:address":"Cnr Wanneroo & Gnangara Rds",
    "sg:city":"Wanneroo",
    "sg:classifiers":[
        {
            "category":"Health Services",
            "subcategory":"Chiropractor",
            "type":"Services"
        }
    ],
    "sg:phone":"+61 8 9409 9855",
    "sg:postcode":"6065",
    "sg:province":"WA",
    "wof:name":"Emergency Chiropractic Care",
    "wof:placetype":"venue"
},
  "geometry": {"coordinates":[115.784667969,-31.7202148438],"type":"Point"}
}