{
  "type": "Feature",
  "properties": {
    "addr:full":"North West Coastal Hwy Carnarvon WA 6701",
    "addr:postcode":"6701",
    "addr:street":"North West Coastal Hwy",
    "iso:country":"AU",
    "sg:address":"North West Coastal Hwy",
    "sg:city":"Carnarvon",
    "sg:classifiers":[
        {
            "category":"Autos & Motor Vehicles",
            "subcategory":"Fuel & Gas Station",
            "type":"Retail Goods"
        }
    ],
    "sg:phone":"+61 8 9941 8140",
    "sg:postcode":"6701",
    "sg:province":"WA",
    "wof:name":"Ampol",
    "wof:placetype":"venue"
},
  "geometry": {"coordinates":[113.701789856,-24.8675823212],"type":"Point"}
}