{
  "type": "Feature",
  "properties": {
    "addr:full":"11- 13 Stamford Rd Oakleigh VIC 3166",
    "addr:housenumber":"13",
    "addr:postcode":"3166",
    "addr:street":"Stamford Rd",
    "iso:country":"AU",
    "sg:address":"11- 13 Stamford Rd",
    "sg:city":"Oakleigh",
    "sg:classifiers":[
        {
            "category":"Manufacturing",
            "subcategory":"Rubber & Plastics",
            "type":"Manufacturing & Wholesale Goods"
        }
    ],
    "sg:phone":"+61 3 9567 1900",
    "sg:postcode":"3166",
    "sg:province":"VIC",
    "sg:tags":[
        "equipment",
        "card"
    ],
    "wof:name":"Peacock Bros Pty Ltd",
    "wof:placetype":"venue"
},
  "geometry": {"coordinates":[145.10058593799999,-37.8933143616],"type":"Point"}
}