{
  "type": "Feature",
  "properties": {
    "iso:country":"AU",
    "sg:address":"69 Ramsey St",
    "sg:city":"Haberfield",
    "sg:classifiers":[
        {
            "category":"Building & Trades",
            "subcategory":"Landscaping Services",
            "type":"Services"
        }
    ],
    "sg:phone":"+61 412 564 340",
    "sg:postcode":"2045",
    "sg:province":"NSW",
    "sg:tags":[
        "designer",
        "landscape",
        "contractor"
    ],
    "wof:name":"Mike Sheriff Landscape Design",
    "wof:placetype":"venue"
},
  "geometry": {"coordinates":[151.14128099999999,-33.883213],"type":"Point"}
}