{
  "type": "Feature",
  "properties": {
    "addr:full":"44 Kirkford Drv Mooroolbark VIC 3138",
    "addr:housenumber":"44",
    "addr:postcode":"3138",
    "addr:street":"Kirkford Drv",
    "iso:country":"AU",
    "sg:address":"44 Kirkford Drv",
    "sg:city":"Mooroolbark",
    "sg:classifiers":[
        {
            "category":"Professional",
            "subcategory":"Business Services",
            "type":"Services"
        }
    ],
    "sg:phone":"+61 3 9727 2226",
    "sg:postcode":"3138",
    "sg:province":"VIC",
    "sg:tags":[
        "drafting"
    ],
    "wof:name":"Witty Designs Pty Ltd",
    "wof:placetype":"venue"
},
  "geometry": {"coordinates":[145.316894531,-37.7609596252],"type":"Point"}
}