{
  "type": "Feature",
  "properties": {
    "iso:country":"AU",
    "sg:address":"3 Mary St",
    "sg:city":"Windsor",
    "sg:classifiers":[
        {
            "category":"Real Estate",
            "subcategory":"Architect",
            "type":"Services"
        }
    ],
    "sg:phone":"+61 3 9533 7828",
    "sg:postcode":"3181",
    "sg:province":"VIC",
    "sg:website":"http://www.aequi.com.au",
    "wof:name":"Aequi Design",
    "wof:placetype":"venue"
},
  "geometry": {"coordinates":[144.996383667,-37.8540992737],"type":"Point"}
}