{
  "type": "Feature",
  "properties": {
    "iso:country":"AU",
    "sg:address":"76 Bay Rd",
    "sg:city":"Berrilee",
    "sg:classifiers":[
        {
            "category":"Home & Garden",
            "subcategory":"Garden Supply",
            "type":"Retail Goods"
        }
    ],
    "sg:phone":"+61 2 9655 1603",
    "sg:postcode":"2159",
    "sg:province":"NSW",
    "sg:tags":[
        "landscape"
    ],
    "wof:name":"Erana Timber Products",
    "wof:placetype":"venue"
},
  "geometry": {"coordinates":[151.09327697800001,-33.6172981262],"type":"Point"}
}