{
  "type": "Feature",
  "properties": {
    "addr:full":"Second Ave Maroochydore QLD 4558",
    "addr:postcode":"4558",
    "addr:street":"Second Ave",
    "iso:country":"AU",
    "sg:address":"Second Ave",
    "sg:city":"Maroochydore",
    "sg:classifiers":[
        {
            "category":"Sports & Exercise",
            "subcategory":"Gym",
            "type":"Entertainment"
        }
    ],
    "sg:phone":"+61 7 5479 1529",
    "sg:postcode":"4558",
    "sg:province":"QLD",
    "sg:tags":[
        "health",
        "fitness"
    ],
    "wof:name":"Beach House Gym",
    "wof:placetype":"venue"
},
  "geometry": {"coordinates":[153.09390258799999,-26.6590766907],"type":"Point"}
}