{
  "type": "Feature",
  "properties": {
    "addr:full":"36 McPherson St Banksmeadow NSW 2019",
    "addr:housenumber":"36",
    "addr:postcode":"2019",
    "addr:street":"Mcpherson St",
    "iso:country":"AU",
    "sg:address":"36 McPherson St",
    "sg:city":"Banksmeadow",
    "sg:classifiers":[
        {
            "category":"Building & Trades",
            "subcategory":"Pest Control",
            "type":"Services"
        }
    ],
    "sg:phone":"+61 2 9316 9042",
    "sg:postcode":"2019",
    "sg:province":"NSW",
    "sg:tags":[
        "equipment",
        "abattoir",
        "machinery"
    ],
    "wof:name":"Keith Engineering (Australia) Pty Ltd",
    "wof:placetype":"venue"
},
  "geometry": {"coordinates":[151.21942138700001,-33.9587745667],"type":"Point"}
}