{
  "type": "Feature",
  "properties": {
    "addr:full":"327 Bay St Port Melbourne VIC 3207",
    "addr:housenumber":"327",
    "addr:postcode":"3207",
    "addr:street":"Bay St",
    "iso:country":"AU",
    "sg:address":"327 Bay St",
    "sg:city":"Port Melbourne",
    "sg:classifiers":[
        {
            "category":"Fast Food",
            "type":"Food & Drink"
        }
    ],
    "sg:phone":"+61 3 9646 4110",
    "sg:postcode":"3207",
    "sg:province":"VIC",
    "sg:tags":[
        "away",
        "take"
    ],
    "wof:name":"Pedro's Pit Pizza & Pasta",
    "wof:placetype":"venue"
},
  "geometry": {"coordinates":[144.944366,-37.836151],"type":"Point"}
}