{
  "type": "Feature",
  "properties": {
    "iso:country":"AU",
    "sg:address":"16/ 16 Dalmeny Drv",
    "sg:city":"Prestons",
    "sg:classifiers":[
        {
            "category":"Building & Trades",
            "subcategory":"Construction",
            "type":"Services"
        }
    ],
    "sg:phone":"+61 2 9607 0324",
    "sg:postcode":"2170",
    "sg:province":"NSW",
    "sg:tags":[
        "concrete",
        "contractor"
    ],
    "wof:name":"San Marino Concreting",
    "wof:placetype":"venue"
},
  "geometry": {"coordinates":[150.86982727,-33.9466552734],"type":"Point"}
}