{
  "type": "Feature",
  "properties": {
    "addr:full":"32 Tennyson St Beresfield NSW 2322",
    "addr:housenumber":"32",
    "addr:postcode":"2322",
    "addr:street":"Tennyson St",
    "iso:country":"AU",
    "sg:address":"32 Tennyson St",
    "sg:city":"Beresfield",
    "sg:classifiers":[
        {
            "category":"Home & Garden",
            "subcategory":"Carpets & Floor Coverings",
            "type":"Retail Goods"
        }
    ],
    "sg:phone":"+61 2 4966 1647",
    "sg:postcode":"2322",
    "sg:province":"NSW",
    "sg:tags":[
        "layer",
        "planner"
    ],
    "wof:name":"Price D & P M",
    "wof:placetype":"venue"
},
  "geometry": {"coordinates":[151.65855407699999,-32.8032913208],"type":"Point"}
}