{
  "type": "Feature",
  "properties": {
    "addr:full":"5/ 59 Walters Drv Osborne Park WA 6017",
    "addr:housenumber":"/ 59",
    "addr:postcode":"6017",
    "addr:street":"Walters Drv",
    "iso:country":"AU",
    "sg:address":"5/ 59 Walters Drv",
    "sg:city":"Osborne Park",
    "sg:classifiers":[
        {
            "category":"Real Estate",
            "subcategory":"Real Estate Services",
            "type":"Services"
        }
    ],
    "sg:phone":"+61 8 9443 7300",
    "sg:postcode":"6017",
    "sg:province":"WA",
    "sg:tags":[
        "valuer"
    ],
    "wof:name":"Agnello Property Valuations",
    "wof:placetype":"venue"
},
  "geometry": {"coordinates":[115.828323364,-31.9128417969],"type":"Point"}
}