{
  "type": "Feature",
  "properties": {
    "addr:full":"2 Kanandah Rd Broken Hill NSW 2880",
    "addr:housenumber":"2",
    "addr:postcode":"2880",
    "addr:street":"Kanandah Rd",
    "iso:country":"AU",
    "sg:address":"2 Kanandah Rd",
    "sg:city":"Broken Hill",
    "sg:classifiers":[
        {
            "category":"Wholesale",
            "subcategory":"Durable Goods & Equipment",
            "type":"Manufacturing & Wholesale Goods"
        }
    ],
    "sg:phone":"+61 8 8087 9712",
    "sg:postcode":"2880",
    "sg:province":"NSW",
    "sg:tags":[
        "wholesaler",
        "mfrs",
        "lubrication"
    ],
    "wof:name":"Sullivans Mining & Hardware",
    "wof:placetype":"venue"
},
  "geometry": {"coordinates":[141.43325805699999,-31.9820919037],"type":"Point"}
}