{
  "type": "Feature",
  "properties": {
    "addr:full":"Suite 101 127 York St Sydney NSW 2000",
    "addr:housenumber":"127",
    "addr:postcode":"2000",
    "addr:street":"York St",
    "iso:country":"AU",
    "sg:address":"Suite 101 127 York St",
    "sg:city":"Sydney",
    "sg:classifiers":[
        {
            "category":"Health Services",
            "subcategory":"Dentist",
            "type":"Services"
        }
    ],
    "sg:phone":"+61 2 9262 7080",
    "sg:postcode":"2000",
    "sg:province":"NSW",
    "wof:name":"A New World of Dentistry",
    "wof:placetype":"venue"
},
  "geometry": {"coordinates":[151.20623779300001,-33.8717155457],"type":"Point"}
}