{
  "type": "Feature",
  "properties": {
    "iso:country":"AU",
    "sg:address":"2 Manikato Ave",
    "sg:city":"Mordialloc",
    "sg:classifiers":[
        {
            "category":"Wholesale",
            "subcategory":"Metals & Minerals",
            "type":"Manufacturing & Wholesale Goods"
        }
    ],
    "sg:phone":"+61 3 9587 9205",
    "sg:postcode":"3195",
    "sg:province":"VIC",
    "sg:tags":[
        "steel",
        "merchant"
    ],
    "wof:name":"Orrcon",
    "wof:placetype":"venue"
},
  "geometry": {"coordinates":[145.09564209000001,-38.0001068115],"type":"Point"}
}