{
  "type": "Feature",
  "properties": {
    "addr:full":"114 Gate Rd Dumbleyung WA 6350",
    "addr:housenumber":"114",
    "addr:postcode":"6350",
    "addr:street":"Gate Rd",
    "iso:country":"AU",
    "sg:address":"114 Gate Rd",
    "sg:city":"Dumbleyung",
    "sg:classifiers":[
        {
            "category":"Farming",
            "subcategory":"Farm",
            "type":"Manufacturing & Wholesale Goods"
        }
    ],
    "sg:phone":"+61 8 9863 7201",
    "sg:postcode":"6350",
    "sg:province":"WA",
    "sg:tags":[
        "farmer"
    ],
    "wof:name":"Smith B B & B",
    "wof:placetype":"venue"
},
  "geometry": {"coordinates":[117.74099699999999,-33.314659],"type":"Point"}
}