{
  "type": "Feature",
  "properties": {
    "iso:country":"AU",
    "sg:address":"Shop 3, 193 Morayfield Rd",
    "sg:city":"Morayfield",
    "sg:classifiers":[
        {
            "category":"Health Services",
            "subcategory":"Health Practitioner",
            "type":"Services"
        }
    ],
    "sg:phone":"+61 7 5499 3322",
    "sg:postcode":"4506",
    "sg:province":"QLD",
    "sg:tags":[
        "physiotherapist"
    ],
    "wof:name":"Morayfield Gardens Physiotherapy",
    "wof:placetype":"venue"
},
  "geometry": {"coordinates":[152.95095825199999,-27.1116085052],"type":"Point"}
}