{
  "type": "Feature",
  "properties": {
    "iso:country":"AU",
    "sg:address":"87 Main St",
    "sg:city":"Proserpine",
    "sg:classifiers":[
        {
            "category":"Retail",
            "subcategory":"Funeral Services",
            "type":"Services"
        }
    ],
    "sg:phone":"+61 7 4945 3448",
    "sg:postcode":"4800",
    "sg:province":"QLD",
    "sg:tags":[
        "director"
    ],
    "wof:name":"Funeral Services Whitsunday",
    "wof:placetype":"venue"
},
  "geometry": {"coordinates":[148.589599609,-20.4034729004],"type":"Point"}
}