{
  "type": "Feature",
  "properties": {
    "iso:country":"AU",
    "sg:address":"Unit 10/ 37 Main St",
    "sg:city":"Samford",
    "sg:classifiers":[
        {
            "category":"Insurance",
            "subcategory":"Insurance Agent",
            "type":"Services"
        }
    ],
    "sg:phone":"+61 411 551 411",
    "sg:postcode":"4520",
    "sg:province":"QLD",
    "wof:name":"Diamond Life Financial Services Pty Ltd",
    "wof:placetype":"venue"
},
  "geometry": {"coordinates":[152.886948,-27.370361],"type":"Point"}
}