{
  "type": "Feature",
  "properties": {
    "addr:full":"Shop 3/ 98 Longueville Rd Lane Cove NSW 2066",
    "addr:housenumber":"shop 3 / 98",
    "addr:postcode":"2066",
    "addr:street":"Longueville Rd",
    "iso:country":"AU",
    "sg:address":"Shop 3/ 98 Longueville Rd",
    "sg:city":"Lane Cove",
    "sg:classifiers":[
        {
            "category":"Personal",
            "subcategory":"Beauty Salon",
            "type":"Services"
        }
    ],
    "sg:phone":"+61 2 9427 6333",
    "sg:postcode":"2066",
    "sg:province":"NSW",
    "sg:tags":[
        "hairdresser"
    ],
    "wof:name":"Gambino Hair",
    "wof:placetype":"venue"
},
  "geometry": {"coordinates":[151.17005920400001,-33.8141593933],"type":"Point"}
}