{
  "type": "Feature",
  "properties": {
    "addr:full":"40 Mcclures Rd Bayles VIC 3981",
    "addr:housenumber":"40",
    "addr:postcode":"3981",
    "addr:street":"Mcclures Rd",
    "iso:country":"AU",
    "sg:address":"40 Mcclures Rd",
    "sg:city":"Bayles",
    "sg:classifiers":[
        {
            "category":"Wholesale",
            "subcategory":"Machinery & Supplies",
            "type":"Manufacturing & Wholesale Goods"
        }
    ],
    "sg:phone":"+61 3 5997 7620",
    "sg:postcode":"3981",
    "sg:province":"VIC",
    "sg:tags":[
        "equipment",
        "laboratory"
    ],
    "wof:name":"Equicell",
    "wof:placetype":"venue"
},
  "geometry": {"coordinates":[145.60137939399999,-38.1778831482],"type":"Point"}
}