{
  "type": "Feature",
  "properties": {
    "addr:full":"PO Box 6688 Blacktown BC NSW 2148",
    "addr:postcode":"nsw 2148",
    "iso:country":"AU",
    "sg:address":"PO Box 6688",
    "sg:city":"Blacktown BC",
    "sg:classifiers":[
        {
            "category":"Professional",
            "subcategory":"Employment Agencies",
            "type":"Services"
        }
    ],
    "sg:phone":"+61 2 9831 7800",
    "sg:postcode":"2148",
    "sg:province":"NSW",
    "sg:tags":[
        "provider",
        "internet"
    ],
    "wof:name":"Internet Factory The",
    "wof:placetype":"venue"
},
  "geometry": {"coordinates":[150.908813477,-33.7629585266],"type":"Point"}
}