{
  "type": "Feature",
  "properties": {
    "iso:country":"AU",
    "sg:address":"99 Anzac Hwy",
    "sg:city":"Ashford",
    "sg:classifiers":[
        {
            "category":"Insurance",
            "subcategory":"Insurance Agent",
            "type":"Services"
        }
    ],
    "sg:phone":"+61 8 8351 1777",
    "sg:postcode":"5035",
    "sg:province":"SA",
    "wof:name":"Butler & Butler Pty Ltd",
    "wof:placetype":"venue"
},
  "geometry": {"coordinates":[138.57337951700001,-34.9516792297],"type":"Point"}
}