{
  "type": "Feature",
  "properties": {
    "addr:full":"8 Borola Crt Croydon VIC 3136",
    "addr:housenumber":"8",
    "addr:postcode":"3136",
    "addr:street":"Borola Crt",
    "iso:country":"AU",
    "sg:address":"8 Borola Crt",
    "sg:city":"Croydon",
    "sg:classifiers":[
        {
            "category":"Autos & Motor Vehicles",
            "subcategory":"Auto Supplies",
            "type":"Retail Goods"
        }
    ],
    "sg:phone":"+61 402 855 801",
    "sg:postcode":"3136",
    "sg:province":"VIC",
    "sg:tags":[
        "automotive",
        "stereo",
        "radio"
    ],
    "wof:name":"Eastside Installs",
    "wof:placetype":"venue"
},
  "geometry": {"coordinates":[145.28224182100001,-37.7789382935],"type":"Point"}
}