{
  "type": "Feature",
  "properties": {
    "iso:country":"AU",
    "sg:address":"Shop 4, 238 Young Rd",
    "sg:city":"Narangba",
    "sg:classifiers":[
        {
            "category":"Retail",
            "subcategory":"Veterinary Services",
            "type":"Services"
        }
    ],
    "sg:phone":"+61 7 3385 5855",
    "sg:postcode":"4504",
    "sg:province":"QLD",
    "sg:tags":[
        "surgeon"
    ],
    "wof:name":"Narangba Veterinary Clinic",
    "wof:placetype":"venue"
},
  "geometry": {"coordinates":[152.93885803200001,-27.1735038757],"type":"Point"}
}