{
  "type": "Feature",
  "properties": {
    "addr:full":"7 Mareno Rd Tullamarine VIC 3043",
    "addr:housenumber":"7",
    "addr:postcode":"3043",
    "addr:street":"Mareno Rd",
    "iso:country":"AU",
    "sg:address":"7 Mareno Rd",
    "sg:city":"Tullamarine",
    "sg:classifiers":[
        {
            "category":"Manufacturing",
            "subcategory":"Motor Vehicles & Parts",
            "type":"Manufacturing & Wholesale Goods"
        }
    ],
    "sg:phone":"+61 1300 663 266",
    "sg:postcode":"3043",
    "sg:province":"VIC",
    "sg:tags":[
        "wholesaler",
        "cycle",
        "mfrs",
        "accessory"
    ],
    "wof:name":"Bandit Accessories",
    "wof:placetype":"venue"
},
  "geometry": {"coordinates":[144.85174560600001,-37.7063674927],"type":"Point"}
}