{
  "type": "Feature",
  "properties": {
    "addr:full":"Shp 5/ 497 Beechboro Rd North Beechboro WA 6063",
    "addr:housenumber":"/ 497",
    "addr:postcode":"6063",
    "addr:street":"Beechboro Rd North",
    "iso:country":"AU",
    "sg:address":"Shp 5/ 497 Beechboro Rd",
    "sg:city":"North Beechboro",
    "sg:classifiers":[
        {
            "category":"Personal",
            "subcategory":"Beauty Salon",
            "type":"Services"
        }
    ],
    "sg:phone":"+61 8 9377 7102",
    "sg:postcode":"6063",
    "sg:province":"WA",
    "sg:tags":[
        "hairdresser"
    ],
    "wof:name":"Best Head For Hair",
    "wof:placetype":"venue"
},
  "geometry": {"coordinates":[115.924621582,-31.8687114716],"type":"Point"}
}