{
  "type": "Feature",
  "properties": {
    "addr:full":"34 Taurama St Enoggera QLD 4051",
    "addr:housenumber":"34",
    "addr:postcode":"4051",
    "addr:street":"Taurama St",
    "iso:country":"AU",
    "sg:address":"34 Taurama St",
    "sg:city":"Enoggera",
    "sg:classifiers":[
        {
            "category":"Social Services",
            "subcategory":"Child Care",
            "type":"Services"
        }
    ],
    "sg:phone":"+61 7 3355 6181",
    "sg:postcode":"4051",
    "sg:province":"QLD",
    "wof:name":"Gaythorne Community Kindergarten",
    "wof:placetype":"venue"
},
  "geometry": {"coordinates":[152.97958374000001,-27.4226150513],"type":"Point"}
}