{
  "type": "Feature",
  "properties": {
    "iso:country":"AU",
    "sg:address":"407 Progress Rd",
    "sg:city":"Wacol",
    "sg:classifiers":[
        {
            "category":"Manufacturing",
            "subcategory":"Pottery",
            "type":"Manufacturing & Wholesale Goods"
        }
    ],
    "sg:phone":"+61 7 3271 5661",
    "sg:postcode":"4076",
    "sg:province":"QLD",
    "wof:name":"Pot Centre",
    "wof:placetype":"venue"
},
  "geometry": {"coordinates":[152.94099426299999,-27.5954437256],"type":"Point"}
}