{
  "type": "Feature",
  "properties": {
    "iso:country":"AU",
    "sg:address":"22 Norton Rd",
    "sg:city":"High Wycombe",
    "sg:classifiers":[
        {
            "category":"Building & Trades",
            "subcategory":"Plumbing",
            "type":"Services"
        }
    ],
    "sg:phone":"+61 407 998 115",
    "sg:postcode":"6057",
    "sg:province":"WA",
    "sg:tags":[
        "plumber",
        "gasfitters"
    ],
    "wof:name":"Nathans Plumbing & Gas",
    "wof:placetype":"venue"
},
  "geometry": {"coordinates":[115.996162415,-31.9481754303],"type":"Point"}
}