{
  "type": "Feature",
  "properties": {
    "iso:country":"AU",
    "sg:address":"PO Box 169",
    "sg:city":"Red Hill",
    "sg:classifiers":[
        {
            "category":"Farming",
            "subcategory":"Vineyard",
            "type":"Manufacturing & Wholesale Goods"
        }
    ],
    "sg:phone":"+61 3 5989 2187",
    "sg:postcode":"3937",
    "sg:province":"VIC",
    "sg:tags":[
        "winery"
    ],
    "wof:name":"Vineyard Construction & Maintenance",
    "wof:placetype":"venue"
},
  "geometry": {"coordinates":[145.01951599099999,-38.3720397949],"type":"Point"}
}