{
  "type": "Feature",
  "properties": {
    "addr:full":"1 Diamond Ave Kallangur QLD 4503",
    "addr:housenumber":"1",
    "addr:postcode":"4503",
    "addr:street":"Diamond Ave",
    "iso:country":"AU",
    "sg:address":"1 Diamond Ave",
    "sg:city":"Kallangur",
    "sg:classifiers":[
        {
            "category":"Professional",
            "subcategory":"Accounting & Tax Preparation",
            "type":"Services"
        }
    ],
    "sg:phone":"+61 7 3886 3588",
    "sg:postcode":"4503",
    "sg:province":"QLD",
    "sg:tags":[
        "bookkeeping"
    ],
    "wof:name":"Bloemers J",
    "wof:placetype":"venue"
},
  "geometry": {"coordinates":[153.00296020499999,-27.2501544952],"type":"Point"}
}