{
  "type": "Feature",
  "properties": {
    "addr:full":"Cnr Hume Hwy & Ducks La Goulburn NSW 2580",
    "addr:postcode":"2580",
    "addr:street":"Cnr Hume Hwy & Ducks La",
    "iso:country":"AU",
    "sg:address":"Cnr Hume Hwy & Ducks La",
    "sg:city":"Goulburn",
    "sg:classifiers":[
        {
            "category":"Farming",
            "subcategory":"Nursery",
            "type":"Manufacturing & Wholesale Goods"
        }
    ],
    "sg:phone":"+61 2 4821 8700",
    "sg:postcode":"2580",
    "sg:province":"NSW",
    "wof:name":"Goulburn Wholesale Nursery",
    "wof:placetype":"venue"
},
  "geometry": {"coordinates":[149.71542358400001,-34.7759361267],"type":"Point"}
}