{
  "type": "Feature",
  "properties": {
    "addr:full":"4/ 3 Rhodes St West Ryde NSW 2114",
    "addr:housenumber":"/ 3",
    "addr:postcode":"2114",
    "addr:street":"Rhodes St",
    "iso:country":"AU",
    "sg:address":"4/ 3 Rhodes St",
    "sg:city":"West Ryde",
    "sg:classifiers":[
        {
            "category":"Professional",
            "subcategory":"Art Services",
            "type":"Services"
        }
    ],
    "sg:phone":"+61 2 9809 7100",
    "sg:postcode":"2114",
    "sg:province":"NSW",
    "sg:tags":[
        "interior",
        "decorator"
    ],
    "wof:name":"Creative By Design Home Offices",
    "wof:placetype":"venue"
},
  "geometry": {"coordinates":[151.09236145,-33.8124160767],"type":"Point"}
}