{
  "type": "Feature",
  "properties": {
    "addr:full":"103 Banna Ave Griffith NSW 2680",
    "addr:housenumber":"103",
    "addr:postcode":"2680",
    "addr:street":"Banna Ave",
    "iso:country":"AU",
    "sg:address":"103 Banna Ave",
    "sg:city":"Griffith",
    "sg:classifiers":[
        {
            "category":"Organizations",
            "subcategory":"Labor Organization",
            "type":"Services"
        }
    ],
    "sg:phone":"+61 2 6962 1763",
    "sg:postcode":"2680",
    "sg:province":"NSW",
    "sg:tags":[
        "union"
    ],
    "wof:name":"Australian Workers' Union",
    "wof:placetype":"venue"
},
  "geometry": {"coordinates":[146.05221599999999,-34.288429],"type":"Point"}
}