{
  "type": "Feature",
  "properties": {
    "addr:full":"Lake Hume Weir St Ebden VIC 3691",
    "addr:postcode":"3691",
    "addr:street":"Weir St",
    "iso:country":"AU",
    "sg:address":"Lake Hume Weir St",
    "sg:city":"Ebden",
    "sg:classifiers":[
        {
            "category":"Recreation",
            "subcategory":"Sailing Club",
            "type":"Entertainment"
        }
    ],
    "sg:phone":"+61 2 6020 6133",
    "sg:postcode":"3691",
    "sg:province":"VIC",
    "sg:tags":[
        "yacht"
    ],
    "wof:name":"Albury-Wodonga Yacht Club",
    "wof:placetype":"venue"
},
  "geometry": {"coordinates":[147.021591,-36.099522],"type":"Point"}
}