{
  "type": "Feature",
  "properties": {
    "iso:country":"AU",
    "sg:address":"3 Farrow St",
    "sg:city":"McDowall",
    "sg:phone":"+61 7 3353 3168",
    "sg:postcode":"4053",
    "sg:province":"QLD",
    "wof:name":"Superior Aquatic Systems",
    "wof:placetype":"venue"
},
  "geometry": {"coordinates":[152.99444580100001,-27.3837013245],"type":"Point"}
}