{
  "type": "Feature",
  "properties": {
    "addr:full":"PO Box 226 Avoca Beach NSW 2251",
    "addr:postcode":"2251",
    "iso:country":"AU",
    "sg:address":"PO Box 226",
    "sg:city":"Avoca Beach",
    "sg:classifiers":[
        {
            "category":"Education",
            "subcategory":"Dance Studio",
            "type":"Public Place"
        }
    ],
    "sg:phone":"+61 2 4382 2789",
    "sg:postcode":"2251",
    "sg:province":"NSW",
    "sg:tags":[
        "venue",
        "tuition"
    ],
    "wof:name":"Studio M",
    "wof:placetype":"venue"
},
  "geometry": {"coordinates":[151.43377685600001,-33.4669303894],"type":"Point"}
}