{
  "type": "Feature",
  "properties": {
    "addr:full":"35e Princes Hwy Fairy Meadow NSW 2519",
    "addr:housenumber":"35e",
    "addr:postcode":"2519",
    "addr:street":"Princes Hwy",
    "iso:country":"AU",
    "sg:address":"35e Princes Hwy",
    "sg:city":"Fairy Meadow",
    "sg:classifiers":[
        {
            "category":"Fast Food",
            "type":"Food & Drink"
        }
    ],
    "sg:phone":"+61 2 4283 1301",
    "sg:postcode":"2519",
    "sg:province":"NSW",
    "sg:tags":[
        "away",
        "take"
    ],
    "wof:name":"May-King Chinese Take-Away",
    "wof:placetype":"venue"
},
  "geometry": {"coordinates":[150.892853,-34.393311],"type":"Point"}
}