{
  "type": "Feature",
  "properties": {
    "iso:country":"AU",
    "sg:address":"558a Anzac Pde",
    "sg:city":"Kingsford",
    "sg:classifiers":[
        {
            "category":"Arena",
            "subcategory":"Sports Club",
            "type":"Entertainment"
        }
    ],
    "sg:phone":"+61 2 9349 7555",
    "sg:postcode":"2032",
    "sg:province":"NSW",
    "sg:tags":[
        "league",
        "rugby"
    ],
    "wof:name":"South Sydney Junior Rugby League Club",
    "wof:placetype":"venue"
},
  "geometry": {"coordinates":[151.229370117,-33.9247550964],"type":"Point"}
}