{
  "type": "Feature",
  "properties": {
    "iso:country":"AU",
    "sg:address":"348 Gaffney St",
    "sg:city":"Pascoe Vale",
    "sg:classifiers":[
        {
            "category":"Health Services",
            "subcategory":"Health Practitioner",
            "type":"Services"
        }
    ],
    "sg:phone":"+61 3 9354 2634",
    "sg:postcode":"3044",
    "sg:province":"VIC",
    "sg:tags":[
        "physiotherapist"
    ],
    "wof:name":"Pascoe Vale Physiotherapy Centre",
    "wof:placetype":"venue"
},
  "geometry": {"coordinates":[144.93911743199999,-37.7314071655],"type":"Point"}
}