{
  "type": "Feature",
  "properties": {
    "addr:full":"Cnr Sunderland & Hale Sts Derwent Park TAS 7009",
    "addr:postcode":"7009",
    "addr:street":"Cnr",
    "iso:country":"AU",
    "sg:address":"Cnr Sunderland & Hale Sts",
    "sg:city":"Derwent Park",
    "sg:classifiers":[
        {
            "category":"Shopping",
            "type":"Retail Goods"
        }
    ],
    "sg:phone":"+61 3 6208 1777",
    "sg:postcode":"7009",
    "sg:province":"TAS",
    "sg:tags":[
        "equipment",
        "safety",
        "accessory"
    ],
    "wof:name":"Tasweld",
    "wof:placetype":"venue"
},
  "geometry": {"coordinates":[147.29229736299999,-42.8356361389],"type":"Point"}
}