{
  "type": "Feature",
  "properties": {
    "addr:full":"20 Burgundy Drv Werribee VIC 3030",
    "addr:housenumber":"20",
    "addr:postcode":"3030",
    "addr:street":"Burgundy Drv",
    "iso:country":"AU",
    "sg:address":"20 Burgundy Drv",
    "sg:city":"Werribee",
    "sg:classifiers":[
        {
            "category":"Personal",
            "subcategory":"Beauty Salon",
            "type":"Services"
        }
    ],
    "sg:phone":"+61 401 033 988",
    "sg:postcode":"3030",
    "sg:province":"VIC",
    "wof:name":"Michelles Nails",
    "wof:placetype":"venue"
},
  "geometry": {"coordinates":[144.628265,-37.887405],"type":"Point"}
}