{
  "type": "Feature",
  "properties": {
    "addr:full":"707 Wellington St Perth WA 6000",
    "addr:housenumber":"707",
    "addr:postcode":"6000",
    "addr:street":"Wellington St",
    "iso:country":"AU",
    "sg:address":"707 Wellington St",
    "sg:city":"Perth",
    "sg:classifiers":[
        {
            "category":"Travel",
            "subcategory":"Hotels & Motels",
            "type":"Entertainment"
        }
    ],
    "sg:phone":"+61 1800 999 144",
    "sg:postcode":"6000",
    "sg:province":"WA",
    "sg:tags":[
        "accommodation"
    ],
    "wof:name":"Citigate Perth",
    "wof:placetype":"venue"
},
  "geometry": {"coordinates":[115.850540161,-31.9489212036],"type":"Point"}
}