{
  "type": "Feature",
  "properties": {
    "iso:country":"AU",
    "sg:address":"Courtyard Level, Centenary Squ Currie St",
    "sg:city":"Nambour",
    "sg:classifiers":[
        {
            "category":"Wholesale",
            "subcategory":"Medical Equipment & Supplies",
            "type":"Manufacturing & Wholesale Goods"
        }
    ],
    "sg:phone":"+61 7 5476 1500",
    "sg:postcode":"4560",
    "sg:province":"QLD",
    "sg:tags":[
        "aids",
        "hearing"
    ],
    "wof:name":"Queensland Hearing.",
    "wof:placetype":"venue"
},
  "geometry": {"coordinates":[152.95921325699999,-26.6250762939],"type":"Point"}
}