{
  "type": "Feature",
  "properties": {
    "iso:country":"AU",
    "sg:address":"Wool Wool Rd",
    "sg:city":"Alvie",
    "sg:classifiers":[
        {
            "category":"Farming",
            "subcategory":"Farm",
            "type":"Manufacturing & Wholesale Goods"
        }
    ],
    "sg:phone":"+61 3 5234 8213",
    "sg:postcode":"3249",
    "sg:province":"VIC",
    "sg:tags":[
        "farmer"
    ],
    "wof:name":"Eldridge H W",
    "wof:placetype":"venue"
},
  "geometry": {"coordinates":[143.504302978,-38.2427368164],"type":"Point"}
}