{
  "type": "Feature",
  "properties": {
    "iso:country":"AU",
    "sg:address":"2 First St",
    "sg:city":"Booragul",
    "sg:classifiers":[
        {
            "category":"Professional",
            "subcategory":"Printing & Photocopies",
            "type":"Services"
        }
    ],
    "sg:phone":"+61 2 4950 8227",
    "sg:postcode":"2284",
    "sg:province":"NSW",
    "sg:tags":[
        "trophy"
    ],
    "wof:name":"Deepwood Enterprises",
    "wof:placetype":"venue"
},
  "geometry": {"coordinates":[151.62318420400001,-32.9498176575],"type":"Point"}
}