{
  "type": "Feature",
  "properties": {
    "iso:country":"AU",
    "sg:address":"62 Church St",
    "sg:city":"Brighton",
    "sg:classifiers":[
        {
            "category":"Shopping",
            "subcategory":"Clothing, Apparel, & Fashions",
            "type":"Retail Goods"
        }
    ],
    "sg:phone":"+61 3 9592 1694",
    "sg:postcode":"3186",
    "sg:province":"VIC",
    "sg:tags":[
        "menswear"
    ],
    "wof:name":"Raoul Of Brighton Pty Ltd",
    "wof:placetype":"venue"
},
  "geometry": {"coordinates":[144.99481201200001,-37.9144134521],"type":"Point"}
}