{
  "type": "Feature",
  "properties": {
    "iso:country":"AU",
    "sg:address":"57 The Parkway St",
    "sg:city":"Kellyville",
    "sg:classifiers":[
        {
            "category":"Building & Trades",
            "subcategory":"Construction",
            "type":"Services"
        }
    ],
    "sg:phone":"+61 2 9629 5102",
    "sg:postcode":"2155",
    "sg:province":"NSW",
    "sg:tags":[
        "concrete",
        "contractor"
    ],
    "wof:name":"Stallion Concretors Pty Ltd",
    "wof:placetype":"venue"
},
  "geometry": {"coordinates":[150.945068359,-33.6976661682],"type":"Point"}
}