{
  "type": "Feature",
  "properties": {
    "iso:country":"AU",
    "sg:address":"64 Fitzgerald St",
    "sg:city":"Northbridge",
    "sg:classifiers":[
        {
            "category":"Real Estate",
            "subcategory":"Architect",
            "type":"Services"
        }
    ],
    "sg:phone":"+61 8 9227 0900",
    "sg:postcode":"6003",
    "sg:province":"WA",
    "wof:name":"Overman & Zuideveld Pty Ltd",
    "wof:placetype":"venue"
},
  "geometry": {"coordinates":[115.853477478,-31.9445648193],"type":"Point"}
}