{
  "type": "Feature",
  "properties": {
    "addr:full":"43 Kembla St Fyshwick ACT 2609",
    "addr:housenumber":"43",
    "addr:postcode":"2609",
    "addr:street":"Kembla St",
    "iso:country":"AU",
    "sg:address":"43 Kembla St",
    "sg:city":"Fyshwick",
    "sg:classifiers":[
        {
            "category":"Building & Trades",
            "subcategory":"Construction",
            "type":"Services"
        }
    ],
    "sg:phone":"+61 2 6280 6080",
    "sg:postcode":"2609",
    "sg:province":"ACT",
    "sg:tags":[
        "brick",
        "paving"
    ],
    "wof:name":"Tilecraft Ceramics",
    "wof:placetype":"venue"
},
  "geometry": {"coordinates":[149.175704956,-35.324054718],"type":"Point"}
}