{
  "type": "Feature",
  "properties": {
    "iso:country":"AU",
    "sg:address":"63 O'Reilly Drv",
    "sg:city":"Caloundra West",
    "sg:classifiers":[
        {
            "category":"Food & Beverages",
            "subcategory":"Specialty",
            "type":"Retail Goods"
        }
    ],
    "sg:phone":"+61 412 821 350",
    "sg:postcode":"4551",
    "sg:province":"QLD",
    "sg:tags":[
        "product",
        "health"
    ],
    "wof:name":"USANA Independent Distributor-Kath Cadman",
    "wof:placetype":"venue"
},
  "geometry": {"coordinates":[153.09072875999999,-26.7960624695],"type":"Point"}
}