{
  "type": "Feature",
  "properties": {
    "iso:country":"AU",
    "sg:address":"10 Barnesby Rd",
    "sg:city":"Yakamia",
    "sg:classifiers":[
        {
            "category":"Social Services",
            "subcategory":"Retirement Home",
            "type":"Services"
        }
    ],
    "sg:phone":"+61 8 9842 8433",
    "sg:postcode":"6330",
    "sg:province":"WA",
    "sg:tags":[
        "village"
    ],
    "wof:name":"Village Life",
    "wof:placetype":"venue"
},
  "geometry": {"coordinates":[117.875106812,-35.0057144165],"type":"Point"}
}