{
  "type": "Feature",
  "properties": {
    "iso:country":"AU",
    "sg:address":"PO Box 1151",
    "sg:city":"Bowen",
    "sg:classifiers":[
        {
            "category":"Professional",
            "subcategory":"Engineering",
            "type":"Services"
        }
    ],
    "sg:phone":"+61 7 4786 3128",
    "sg:postcode":"4805",
    "sg:province":"QLD",
    "sg:tags":[
        "manufacturing",
        "engineer"
    ],
    "wof:name":"Fruit Commander International",
    "wof:placetype":"venue"
},
  "geometry": {"coordinates":[148.22084045400001,-20.0146598816],"type":"Point"}
}