{
  "type": "Feature",
  "properties": {
    "addr:full":"Unit 1 48 Station St Nunawading VIC 3131",
    "addr:housenumber":"48",
    "addr:postcode":"3131",
    "addr:street":"Station St",
    "iso:country":"AU",
    "sg:address":"Unit 1 48 Station St",
    "sg:city":"Nunawading",
    "sg:classifiers":[
        {
            "category":"Education",
            "subcategory":"Music School",
            "type":"Public Place"
        }
    ],
    "sg:phone":"+61 3 9878 9338",
    "sg:postcode":"3131",
    "sg:province":"VIC",
    "sg:tags":[
        "singing",
        "teacher"
    ],
    "wof:name":"Ward Suzanne",
    "wof:placetype":"venue"
},
  "geometry": {"coordinates":[145.178268433,-37.8203811646],"type":"Point"}
}