{
  "type": "Feature",
  "properties": {
    "iso:country":"AU",
    "sg:address":"Manly Yacht Club, East Esplanade 2095",
    "sg:city":"Manly",
    "sg:classifiers":[
        {
            "category":"Education",
            "subcategory":"Special Training",
            "type":"Public Place"
        }
    ],
    "sg:phone":"+61 2 9977 4000",
    "sg:postcode":"2095",
    "sg:province":"NSW",
    "sg:tags":[
        "school",
        "sailing"
    ],
    "wof:name":"The Big Blue Sailing School",
    "wof:placetype":"venue"
},
  "geometry": {"coordinates":[151.28456115700001,-33.7992553711],"type":"Point"}
}