{
  "type": "Feature",
  "properties": {
    "addr:full":"93 River Rd Emu Plains NSW 2750",
    "addr:housenumber":"93",
    "addr:postcode":"2750",
    "addr:street":"River Rd",
    "iso:country":"AU",
    "sg:address":"93 River Rd",
    "sg:city":"Emu Plains",
    "sg:classifiers":[
        {
            "category":"Manufacturing",
            "subcategory":"Metals",
            "type":"Manufacturing & Wholesale Goods"
        }
    ],
    "sg:phone":"+61 2 4735 7887",
    "sg:postcode":"2750",
    "sg:province":"NSW",
    "sg:tags":[
        "steel",
        "fabricator",
        "mfrs"
    ],
    "wof:name":"Motive Power Pty Ltd",
    "wof:placetype":"venue"
},
  "geometry": {"coordinates":[150.66409301799999,-33.7590942383],"type":"Point"}
}