{
  "type": "Feature",
  "properties": {
    "iso:country":"AU",
    "sg:address":"7 Herston Rd",
    "sg:city":"Kelvin Grove",
    "sg:classifiers":[
        {
            "category":"Fast Food",
            "type":"Food & Drink"
        }
    ],
    "sg:phone":"+61 7 3856 0919",
    "sg:postcode":"4059",
    "sg:province":"QLD",
    "sg:tags":[
        "away",
        "take"
    ],
    "wof:name":"Kelvin Grove Seafood & Takeaway",
    "wof:placetype":"venue"
},
  "geometry": {"coordinates":[153.00895690900001,-27.4456672668],"type":"Point"}
}