{
  "type": "Feature",
  "properties": {
    "addr:full":"684 Glenhuntly Rd Caulfield South VIC 3162",
    "addr:housenumber":"684",
    "addr:postcode":"3162",
    "addr:street":"Glenhuntly Rd",
    "iso:country":"AU",
    "sg:address":"684 Glenhuntly Rd",
    "sg:city":"Caulfield South",
    "sg:classifiers":[
        {
            "category":"Personal",
            "subcategory":"Beauty Salon",
            "type":"Services"
        }
    ],
    "sg:phone":"+61 3 9523 0588",
    "sg:postcode":"3162",
    "sg:province":"VIC",
    "sg:tags":[
        "hairdresser"
    ],
    "wof:name":"Offir Meoded Hair Studio",
    "wof:placetype":"venue"
},
  "geometry": {"coordinates":[145.02027893100001,-37.8957214355],"type":"Point"}
}