{
  "type": "Feature",
  "properties": {
    "addr:full":"Unit 2, 72 Torrens St Braddon ACT 2612",
    "addr:housenumber":"72",
    "addr:postcode":"2612",
    "addr:street":"Torrens St",
    "iso:country":"AU",
    "sg:address":"Unit 2, 72 Torrens St",
    "sg:city":"Braddon",
    "sg:classifiers":[
        {
            "category":"Banks & Credit Unions",
            "subcategory":"Bank",
            "type":"Services"
        }
    ],
    "sg:phone":"+61 2 6257 5520",
    "sg:postcode":"2612",
    "sg:province":"ACT",
    "sg:tags":[
        "broker",
        "mortgage"
    ],
    "wof:name":"ACT Mortgages",
    "wof:placetype":"venue"
},
  "geometry": {"coordinates":[149.13517761200001,-35.2676773071],"type":"Point"}
}