{
  "type": "Feature",
  "properties": {
    "addr:full":"U 4/ 177 Pacific Hwy North Sydney NSW 2060",
    "addr:housenumber":"/ 177",
    "addr:postcode":"2060",
    "addr:street":"Pacific Hwy",
    "iso:country":"AU",
    "sg:address":"U 4/ 177 Pacific Hwy",
    "sg:city":"North Sydney",
    "sg:classifiers":[
        {
            "category":"Wholesale",
            "subcategory":"Metals & Minerals",
            "type":"Manufacturing & Wholesale Goods"
        }
    ],
    "sg:phone":"+61 2 9925 0755",
    "sg:postcode":"2060",
    "sg:province":"NSW",
    "sg:tags":[
        "steel",
        "merchant"
    ],
    "wof:name":"G P Marketing International Pty Ltd",
    "wof:placetype":"venue"
},
  "geometry": {"coordinates":[151.20631408700001,-33.8376502991],"type":"Point"}
}