{
  "type": "Feature",
  "properties": {
    "addr:full":"106 George St East Maitland NSW 2323",
    "addr:housenumber":"106",
    "addr:postcode":"2323",
    "addr:street":"George St",
    "iso:country":"AU",
    "sg:address":"106 George St",
    "sg:city":"East Maitland",
    "sg:classifiers":[
        {
            "category":"Fast Food",
            "type":"Food & Drink"
        }
    ],
    "sg:phone":"+61 2 4933 1721",
    "sg:postcode":"2323",
    "sg:province":"NSW",
    "sg:tags":[
        "away",
        "take"
    ],
    "wof:name":"Pier Takeaway",
    "wof:placetype":"venue"
},
  "geometry": {"coordinates":[151.58815002399999,-32.7509803772],"type":"Point"}
}