{
  "type": "Feature",
  "properties": {
    "iso:country":"AU",
    "sg:address":"Mail Svc 331",
    "sg:city":"Goomeri",
    "sg:classifiers":[
        {
            "category":"Farming",
            "subcategory":"Dairy Farm",
            "type":"Manufacturing & Wholesale Goods"
        }
    ],
    "sg:phone":"+61 7 4168 7198",
    "sg:postcode":"4601",
    "sg:province":"QLD",
    "wof:name":"Bischoff B E & J C",
    "wof:placetype":"venue"
},
  "geometry": {"coordinates":[152.06887800000001,-26.19809],"type":"Point"}
}