{
  "type": "Feature",
  "properties": {
    "addr:full":"40 Gormanston Rd Moonah TAS 7009",
    "addr:housenumber":"40",
    "addr:postcode":"7009",
    "addr:street":"Gormanston Rd",
    "iso:country":"AU",
    "sg:address":"40 Gormanston Rd",
    "sg:city":"Moonah",
    "sg:classifiers":[
        {
            "category":"Home & Garden",
            "subcategory":"Home Furnishings",
            "type":"Retail Goods"
        }
    ],
    "sg:phone":"+61 3 6279 4111",
    "sg:postcode":"7009",
    "sg:province":"TAS",
    "sg:tags":[
        "shower",
        "screen"
    ],
    "wof:name":"Glass Supplies Pty Ltd",
    "wof:placetype":"venue"
},
  "geometry": {"coordinates":[147.29867553700001,-42.8444824219],"type":"Point"}
}