{
  "type": "Feature",
  "properties": {
    "addr:full":"2- 18 Canterbury Rd Kilsyth VIC 3137",
    "addr:housenumber":"18",
    "addr:postcode":"3137",
    "addr:street":"2;Canterbury Rd",
    "iso:country":"AU",
    "sg:address":"2- 18 Canterbury Rd",
    "sg:city":"Kilsyth",
    "sg:classifiers":[
        {
            "category":"Manufacturing",
            "subcategory":"Rubber & Plastics",
            "type":"Manufacturing & Wholesale Goods"
        }
    ],
    "sg:phone":"+61 3 9751 8004",
    "sg:postcode":"3137",
    "sg:province":"VIC",
    "sg:tags":[
        "moulders"
    ],
    "wof:name":"Burn Brite Plastics",
    "wof:placetype":"venue"
},
  "geometry": {"coordinates":[145.33538818400001,-37.8129119873],"type":"Point"}
}