{
  "type": "Feature",
  "properties": {
    "addr:full":"150 Gladstone St Melbourne VIC 3000",
    "addr:housenumber":"150",
    "addr:postcode":"3000",
    "addr:street":"Gladstone St",
    "iso:country":"AU",
    "sg:address":"150 Gladstone St",
    "sg:city":"Melbourne",
    "sg:classifiers":[
        {
            "category":"Professional",
            "subcategory":"Computer Services",
            "type":"Services"
        }
    ],
    "sg:phone":"+61 3 9685 9166",
    "sg:postcode":"3000",
    "sg:province":"VIC",
    "sg:tags":[
        "tele-communications",
        "consultant"
    ],
    "wof:name":"National Telecoms Group",
    "wof:placetype":"venue"
},
  "geometry": {"coordinates":[144.94851684599999,-37.8306808472],"type":"Point"}
}