{
  "type": "Feature",
  "properties": {
    "addr:full":"7 Chamberlain Ave Caringbah NSW 2229",
    "addr:housenumber":"7",
    "addr:postcode":"2229",
    "addr:street":"Chamberlain Ave",
    "iso:country":"AU",
    "sg:address":"7 Chamberlain Ave",
    "sg:city":"Caringbah",
    "sg:classifiers":[
        {
            "category":"Health Services",
            "subcategory":"Health Practitioner",
            "type":"Services"
        }
    ],
    "sg:phone":"+61 2 9525 9911",
    "sg:postcode":"2229",
    "sg:province":"NSW",
    "sg:tags":[
        "alternative"
    ],
    "wof:name":"Reiki Seminars",
    "wof:placetype":"venue"
},
  "geometry": {"coordinates":[151.117385864,-34.0346298218],"type":"Point"}
}