{
  "type": "Feature",
  "properties": {
    "addr:full":"Shop 17- 19 Stockland Bay Village The Entrance Rd Bateau Bay NSW 2261",
    "addr:housenumber":"shop 17 19",
    "addr:postcode":"2261",
    "addr:street":"Stockland Bay;The Entrance Rd",
    "iso:country":"AU",
    "sg:address":"Shop 17- 19 Stockland Bay Village The Entrance Rd",
    "sg:city":"Bateau Bay",
    "sg:classifiers":[
        {
            "category":"Shopping",
            "subcategory":"Clothing, Apparel, & Fashions",
            "type":"Retail Goods"
        }
    ],
    "sg:phone":"+61 2 4332 0081",
    "sg:postcode":"2261",
    "sg:province":"NSW",
    "sg:tags":[
        "menswear"
    ],
    "wof:name":"Lowes",
    "wof:placetype":"venue"
},
  "geometry": {"coordinates":[151.47340399999999,-33.380699],"type":"Point"}
}