{
  "type": "Feature",
  "properties": {
    "addr:full":"88 Main St Rutherglen NSW 3685",
    "addr:housenumber":"88",
    "addr:postcode":"3685",
    "addr:street":"Main St",
    "iso:country":"AU",
    "sg:address":"88 Main St",
    "sg:city":"Rutherglen",
    "sg:classifiers":[
        {
            "category":"Food & Beverages",
            "subcategory":"Bakery",
            "type":"Retail Goods"
        }
    ],
    "sg:phone":"+61 2 6032 9605",
    "sg:postcode":"3685",
    "sg:province":"NSW",
    "sg:tags":[
        "baker"
    ],
    "wof:name":"Parker Pies",
    "wof:placetype":"venue"
},
  "geometry": {"coordinates":[146.460861206,-36.0547523499],"type":"Point"}
}