{
  "type": "Feature",
  "properties": {
    "iso:country":"AU",
    "sg:address":"PO Box 102",
    "sg:city":"Riddells Creek",
    "sg:classifiers":[
        {
            "category":"Communications",
            "type":"Services"
        }
    ],
    "sg:phone":"+61 3 5428 6366",
    "sg:postcode":"3431",
    "sg:province":"VIC",
    "sg:tags":[
        "translation"
    ],
    "wof:name":"Abbey Translations",
    "wof:placetype":"venue"
},
  "geometry": {"coordinates":[144.682937622,-37.4472885132],"type":"Point"}
}