{
  "type": "Feature",
  "properties": {
    "addr:full":"36 Sherbrook Ave Ringwood VIC 3134",
    "addr:housenumber":"36",
    "addr:postcode":"3134",
    "addr:street":"Sherbrook Ave",
    "iso:country":"AU",
    "sg:address":"36 Sherbrook Ave",
    "sg:city":"Ringwood",
    "sg:classifiers":[
        {
            "category":"Personal",
            "subcategory":"Beauty Salon",
            "type":"Services"
        }
    ],
    "sg:phone":"+61 3 9870 7422",
    "sg:postcode":"3134",
    "sg:province":"VIC",
    "sg:tags":[
        "hairdresser"
    ],
    "wof:name":"Colorworks Hairdressing",
    "wof:placetype":"venue"
},
  "geometry": {"coordinates":[145.21875,-37.813533783],"type":"Point"}
}