{
  "type": "Feature",
  "properties": {
    "addr:full":"144 Gilmore Rd Berrinba QLD 4117",
    "addr:housenumber":"144",
    "addr:postcode":"4117",
    "addr:street":"Gilmore Rd",
    "iso:country":"AU",
    "sg:address":"144 Gilmore Rd",
    "sg:city":"Berrinba",
    "sg:classifiers":[
        {
            "category":"Building & Trades",
            "subcategory":"Landscaping Services",
            "type":"Services"
        }
    ],
    "sg:phone":"+61 412 271 381",
    "sg:postcode":"4117",
    "sg:province":"QLD",
    "sg:tags":[
        "stump",
        "tree",
        "felling",
        "removal"
    ],
    "sg:website":"http://www.woodfx.com.au",
    "wof:name":"Wood FX",
    "wof:placetype":"venue"
},
  "geometry": {"coordinates":[153.08920288100001,-27.6520252228],"type":"Point"}
}