{
  "type": "Feature",
  "properties": {
    "iso:country":"AU",
    "sg:address":"150 Beaconsfield-Emerald Rd",
    "sg:city":"Beaconsfield Upper",
    "sg:classifiers":[
        {
            "category":"Mining & Drilling",
            "type":"Manufacturing & Wholesale Goods"
        }
    ],
    "sg:phone":"+61 408 326 418",
    "sg:postcode":"3808",
    "sg:province":"VIC",
    "sg:tags":[
        "concrete",
        "breaking",
        "grinding",
        "sawing"
    ],
    "wof:name":"Commission Concrete Cutting & Drilling",
    "wof:placetype":"venue"
},
  "geometry": {"coordinates":[145.458694,-37.979755],"type":"Point"}
}