{
  "type": "Feature",
  "properties": {
    "addr:full":"Shop 142 West Lakes Mall West Lakes SA 5021",
    "addr:housenumber":"142",
    "addr:postcode":"5021",
    "addr:street":"West",
    "iso:country":"AU",
    "sg:address":"Shop 142 West Lakes Mall",
    "sg:city":"West Lakes",
    "sg:classifiers":[
        {
            "category":"Shopping",
            "subcategory":"Computers & Home Electronics",
            "type":"Retail Goods"
        }
    ],
    "sg:phone":"+61 8 8353 3999",
    "sg:postcode":"5021",
    "sg:province":"SA",
    "sg:tags":[
        "plate",
        "name"
    ],
    "wof:name":"West Lakes Engraving",
    "wof:placetype":"venue"
},
  "geometry": {"coordinates":[138.487823486,-34.8722686768],"type":"Point"}
}