{
  "type": "Feature",
  "properties": {
    "iso:country":"AU",
    "sg:address":"170 Princes Hwy",
    "sg:city":"Port Fairy",
    "sg:classifiers":[
        {
            "category":"Building & Trades",
            "subcategory":"Landscaping Services",
            "type":"Services"
        }
    ],
    "sg:phone":"+61 3 5568 1390",
    "sg:postcode":"3284",
    "sg:province":"VIC",
    "sg:tags":[
        "firebreak",
        "clearing",
        "land",
        "contractor"
    ],
    "wof:name":"Belfast Bobcat Services Pty Ltd",
    "wof:placetype":"venue"
},
  "geometry": {"coordinates":[142.231964111,-38.3699264526],"type":"Point"}
}