{
  "type": "Feature",
  "properties": {
    "addr:full":"142 Tepequar Drv Maroochydore QLD 4558",
    "addr:housenumber":"142",
    "addr:postcode":"4558",
    "addr:street":"Tepequar Drv",
    "iso:country":"AU",
    "sg:address":"142 Tepequar Drv",
    "sg:city":"Maroochydore",
    "sg:classifiers":[
        {
            "category":"Wholesale",
            "subcategory":"Apparel",
            "type":"Manufacturing & Wholesale Goods"
        }
    ],
    "sg:phone":"+61 7 5479 4522",
    "sg:postcode":"4558",
    "sg:province":"QLD",
    "sg:tags":[
        "wholesaler",
        "mfrs",
        "sportswear",
        "women's"
    ],
    "wof:name":"S C Q Sports & Leisure",
    "wof:placetype":"venue"
},
  "geometry": {"coordinates":[153.07293701200001,-26.6489963531],"type":"Point"}
}