{
  "type": "Feature",
  "properties": {
    "addr:full":"15 Adams St Deagon QLD 4017",
    "addr:housenumber":"15",
    "addr:postcode":"4017",
    "addr:street":"Adams St",
    "iso:country":"AU",
    "sg:address":"15 Adams St",
    "sg:city":"Deagon",
    "sg:classifiers":[
        {
            "category":"Farming",
            "subcategory":"Farm & Veterinary Services",
            "type":"Manufacturing & Wholesale Goods"
        }
    ],
    "sg:phone":"+61 7 3269 3465",
    "sg:postcode":"4017",
    "sg:province":"QLD",
    "sg:tags":[
        "blacksmith",
        "farrier"
    ],
    "wof:name":"Burns P A",
    "wof:placetype":"venue"
},
  "geometry": {"coordinates":[153.05986023,-27.3251438141],"type":"Point"}
}