{
  "type": "Feature",
  "properties": {
    "iso:country":"AU",
    "sg:address":"4 Erina St",
    "sg:city":"Scottsdale",
    "sg:classifiers":[
        {
            "category":"Shopping",
            "subcategory":"Computers & Home Electronics",
            "type":"Retail Goods"
        }
    ],
    "sg:phone":"+61 419 887 438",
    "sg:postcode":"7260",
    "sg:province":"TAS",
    "sg:tags":[
        "cleaning"
    ],
    "wof:name":"Hi-Tech Environments",
    "wof:placetype":"venue"
},
  "geometry": {"coordinates":[147.51850899999999,-41.162304],"type":"Point"}
}