{
  "type": "Feature",
  "properties": {
    "iso:country":"AU",
    "sg:address":"Wollongong University Northfields Ave",
    "sg:city":"Wollongong",
    "sg:classifiers":[
        {
            "category":"Government",
            "subcategory":"Post Office",
            "type":"Public Place"
        }
    ],
    "sg:phone":"+61 2 4221 8070",
    "sg:postcode":"2500",
    "sg:province":"NSW",
    "sg:tags":[
        "postal"
    ],
    "wof:name":"Australia Post",
    "wof:placetype":"venue"
},
  "geometry": {"coordinates":[150.87344400000001,-34.407421],"type":"Point"}
}