{
  "type": "Feature",
  "properties": {
    "addr:full":"F-9, 22 Bridge St Eltham VIC 3095",
    "addr:housenumber":"22",
    "addr:postcode":"3095",
    "addr:street":"F-9;Bridge St",
    "iso:country":"AU",
    "sg:address":"F-9, 22 Bridge St",
    "sg:city":"Eltham",
    "sg:classifiers":[
        {
            "category":"Wholesale",
            "subcategory":"Auto Parts",
            "type":"Manufacturing & Wholesale Goods"
        }
    ],
    "sg:phone":"+61 3 9431 2277",
    "sg:postcode":"3095",
    "sg:province":"VIC",
    "sg:tags":[
        "recyclers"
    ],
    "wof:name":"Eltham Falcon Parts",
    "wof:placetype":"venue"
},
  "geometry": {"coordinates":[145.14007568400001,-37.7184028625],"type":"Point"}
}