{
  "type": "Feature",
  "properties": {
    "iso:country":"AU",
    "sg:address":"F1A, 310 Boundary Rd",
    "sg:city":"Dingley",
    "sg:classifiers":[
        {
            "category":"Shopping",
            "subcategory":"Bicycles & Sporting Goods",
            "type":"Retail Goods"
        }
    ],
    "sg:phone":"+61 3 9551 0477",
    "sg:postcode":"3172",
    "sg:province":"VIC",
    "sg:tags":[
        "chemical",
        "equipment",
        "pool",
        "swimming"
    ],
    "wof:name":"Swimming POOL & Spa Pump Centre",
    "wof:placetype":"venue"
},
  "geometry": {"coordinates":[145.11015319800001,-37.9842796326],"type":"Point"}
}