{
  "type": "Feature",
  "properties": {
    "addr:full":"17 Fishermans Crs Narooma North NSW 2546",
    "addr:housenumber":"17",
    "addr:postcode":"2546",
    "addr:street":"Fishermans Crs",
    "iso:country":"AU",
    "sg:address":"17 Fishermans Crs",
    "sg:city":"Narooma North",
    "sg:classifiers":[
        {
            "category":"Utilities",
            "subcategory":"Water",
            "type":"Services"
        }
    ],
    "sg:phone":"+61 2 4476 1499",
    "sg:postcode":"2546",
    "sg:province":"NSW",
    "sg:tags":[
        "hot",
        "system"
    ],
    "wof:name":"Cathor's Electrical Service",
    "wof:placetype":"venue"
},
  "geometry": {"coordinates":[149.98043823200001,-36.333278656],"type":"Point"}
}