{
  "type": "Feature",
  "properties": {
    "iso:country":"AU",
    "sg:address":"119a Sturt St",
    "sg:city":"Ballarat Central",
    "sg:classifiers":[
        {
            "category":"Fast Food",
            "type":"Food & Drink"
        }
    ],
    "sg:phone":"+61 3 5333 7053",
    "sg:postcode":"3350",
    "sg:province":"VIC",
    "sg:tags":[
        "away",
        "take"
    ],
    "wof:name":"Golden Pan",
    "wof:placetype":"venue"
},
  "geometry": {"coordinates":[143.858673,-37.562382],"type":"Point"}
}