{
  "type": "Feature",
  "properties": {
    "iso:country":"AU",
    "sg:address":"31 Cutler Ave",
    "sg:city":"Cootamundra",
    "sg:classifiers":[
        {
            "category":"Building & Trades",
            "subcategory":"Construction",
            "type":"Services"
        }
    ],
    "sg:phone":"+61 2 6942 1061",
    "sg:postcode":"2590",
    "sg:province":"NSW",
    "sg:tags":[
        "earth",
        "excavating",
        "moving",
        "contractor"
    ],
    "wof:name":"Dunk's Bobcat & Mini Excavator Hire",
    "wof:placetype":"venue"
},
  "geometry": {"coordinates":[148.016281128,-34.6321983337],"type":"Point"}
}