{
  "type": "Feature",
  "properties": {
    "addr:full":"311 Belmont Ave Cloverdale WA 6105",
    "addr:housenumber":"311",
    "addr:postcode":"6105",
    "addr:street":"Belmont Ave",
    "iso:country":"AU",
    "sg:address":"311 Belmont Ave",
    "sg:city":"Cloverdale",
    "sg:classifiers":[
        {
            "category":"Professional",
            "subcategory":"Business Services",
            "type":"Services"
        }
    ],
    "sg:phone":"+61 8 9477 3665",
    "sg:postcode":"6105",
    "sg:province":"WA",
    "sg:tags":[
        "drafting"
    ],
    "wof:name":"Ashleith Pty Ltd",
    "wof:placetype":"venue"
},
  "geometry": {"coordinates":[115.938720703,-31.969953537],"type":"Point"}
}