{
  "type": "Feature",
  "properties": {
    "addr:full":"Shop 1/ 2095 Moggill Rd Kenmore QLD 4069",
    "addr:housenumber":"shop 1 / 2095",
    "addr:postcode":"4069",
    "addr:street":"Moggill Rd",
    "iso:country":"AU",
    "sg:address":"Shop 1/ 2095 Moggill Rd",
    "sg:city":"Kenmore",
    "sg:classifiers":[
        {
            "category":"Restaurant",
            "type":"Food & Drink"
        }
    ],
    "sg:phone":"+61 7 3878 4722",
    "sg:postcode":"4069",
    "sg:province":"QLD",
    "wof:name":"Citar Indian Restaurant",
    "wof:placetype":"venue"
},
  "geometry": {"coordinates":[152.93791198700001,-27.5095443726],"type":"Point"}
}