{
  "type": "Feature",
  "properties": {
    "addr:full":"16 Mariem St Shepparton VIC 3630",
    "addr:housenumber":"16",
    "addr:postcode":"3630",
    "addr:street":"Mariem St",
    "iso:country":"AU",
    "sg:address":"16 Mariem St",
    "sg:city":"Shepparton",
    "sg:classifiers":[
        {
            "category":"Personal",
            "subcategory":"Beauty Salon",
            "type":"Services"
        }
    ],
    "sg:phone":"+61 3 5831 8141",
    "sg:postcode":"3630",
    "sg:province":"VIC",
    "wof:name":"Anne's Body Waxing Studio",
    "wof:placetype":"venue"
},
  "geometry": {"coordinates":[145.41827392600001,-36.3798027039],"type":"Point"}
}