{
  "type": "Feature",
  "properties": {
    "addr:full":"57 Clarence St Port Macquarie NSW 2444",
    "addr:housenumber":"57",
    "addr:postcode":"2444",
    "addr:street":"Clarence St",
    "iso:country":"AU",
    "sg:address":"57 Clarence St",
    "sg:city":"Port Macquarie",
    "sg:classifiers":[
        {
            "category":"Internet Cafe",
            "subcategory":"None",
            "type":"Food & Drink"
        }
    ],
    "sg:phone":"+61 2 6584 4744",
    "sg:postcode":"2444",
    "sg:province":"NSW",
    "wof:name":"Port Surf Hub",
    "wof:placetype":"venue"
},
  "geometry": {"coordinates":[152.908005,-31.429298],"type":"Point"}
}