{
  "type": "Feature",
  "properties": {
    "addr:full":"Canterbury St Casino NSW 2470",
    "addr:postcode":"2470",
    "addr:street":"Canterbury St",
    "iso:country":"AU",
    "sg:address":"Canterbury St",
    "sg:city":"Casino",
    "sg:classifiers":[
        {
            "category":"Shopping",
            "subcategory":"Crafts & Fabrics",
            "type":"Retail Goods"
        }
    ],
    "sg:phone":"+61 2 6662 6045",
    "sg:postcode":"2470",
    "sg:province":"NSW",
    "sg:tags":[
        "supply"
    ],
    "wof:name":"Normas Arts & Crafts",
    "wof:placetype":"venue"
},
  "geometry": {"coordinates":[153.04722595199999,-28.8626422882],"type":"Point"}
}