{
  "type": "Feature",
  "properties": {
    "iso:country":"AU",
    "sg:address":"7 Cameron Ave",
    "sg:city":"Manly",
    "sg:classifiers":[
        {
            "category":"Professional",
            "subcategory":"Research",
            "type":"Services"
        }
    ],
    "sg:phone":"+61 2 9976 2538",
    "sg:postcode":"2095",
    "sg:province":"NSW",
    "sg:tags":[
        "market"
    ],
    "wof:name":"Benchmark Planning & Research Pty Ltd",
    "wof:placetype":"venue"
},
  "geometry": {"coordinates":[151.287185669,-33.7858123779],"type":"Point"}
}