{
  "type": "Feature",
  "properties": {
    "addr:full":"246 Kinghorne St Nowra NSW 2541",
    "addr:housenumber":"246",
    "addr:postcode":"2541",
    "addr:street":"Kinghorne St",
    "iso:country":"AU",
    "sg:address":"246 Kinghorne St",
    "sg:city":"Nowra",
    "sg:classifiers":[
        {
            "category":"Building & Trades",
            "subcategory":"Construction",
            "type":"Services"
        }
    ],
    "sg:phone":"+61 2 4421 2272",
    "sg:postcode":"2541",
    "sg:province":"NSW",
    "sg:tags":[
        "plasterboard",
        "plasterer",
        "fixer"
    ],
    "wof:name":"Abernethy A R",
    "wof:placetype":"venue"
},
  "geometry": {"coordinates":[150.60206604000001,-34.8921508789],"type":"Point"}
}