{
  "type": "Feature",
  "properties": {
    "iso:country":"AU",
    "sg:address":"408 Forest Rd",
    "sg:city":"Bexley",
    "sg:classifiers":[
        {
            "category":"Food & Beverages",
            "subcategory":"Bakery",
            "type":"Retail Goods"
        }
    ],
    "sg:phone":"+61 2 9599 3191",
    "sg:postcode":"2207",
    "sg:province":"NSW",
    "sg:tags":[
        "baker"
    ],
    "wof:name":"Danny's Hot Bread Shop",
    "wof:placetype":"venue"
},
  "geometry": {"coordinates":[151.124268,-33.951778],"type":"Point"}
}