{
  "type": "Feature",
  "properties": {
    "addr:full":"187 Henley Beach Rd Mile End SA 5031",
    "addr:housenumber":"187",
    "addr:postcode":"5031",
    "addr:street":"Henley Beach Rd",
    "iso:country":"AU",
    "sg:address":"187 Henley Beach Rd",
    "sg:city":"Mile End",
    "sg:classifiers":[
        {
            "category":"Personal",
            "subcategory":"Beauty Salon",
            "type":"Services"
        }
    ],
    "sg:phone":"+61 8 8443 9072",
    "sg:postcode":"5031",
    "sg:province":"SA",
    "sg:tags":[
        "hairdresser"
    ],
    "wof:name":"Polito A",
    "wof:placetype":"venue"
},
  "geometry": {"coordinates":[138.55963134800001,-34.9244041443],"type":"Point"}
}