{
  "type": "Feature",
  "properties": {
    "iso:country":"AU",
    "sg:address":"11 Hammond Rd",
    "sg:city":"Caboolture",
    "sg:classifiers":[
        {
            "category":"Retail",
            "subcategory":"Driving School",
            "type":"Services"
        }
    ],
    "sg:phone":"+61 7 5495 1395",
    "sg:postcode":"4510",
    "sg:province":"QLD",
    "wof:name":"Morayfield Driving School",
    "wof:placetype":"venue"
},
  "geometry": {"coordinates":[152.935852,-27.044924],"type":"Point"}
}