{
  "type": "Feature",
  "properties": {
    "iso:country":"AU",
    "sg:address":"6a Lawson St",
    "sg:city":"Mackay",
    "sg:classifiers":[
        {
            "category":"Education",
            "subcategory":"Special Training",
            "type":"Public Place"
        }
    ],
    "sg:phone":"+61 1300 766 188",
    "sg:postcode":"4740",
    "sg:province":"QLD",
    "sg:tags":[
        "development"
    ],
    "wof:name":"ACE",
    "wof:placetype":"venue"
},
  "geometry": {"coordinates":[149.19181800000001,-21.143019],"type":"Point"}
}