{
  "type": "Feature",
  "properties": {
    "iso:country":"AU",
    "sg:address":"17 Waterfall Rd",
    "sg:city":"Oatley",
    "sg:classifiers":[
        {
            "category":"Utilities",
            "subcategory":"Electric",
            "type":"Services"
        }
    ],
    "sg:phone":"+61 2 9570 3072",
    "sg:postcode":"2223",
    "sg:province":"NSW",
    "sg:tags":[
        "electrical",
        "contractor"
    ],
    "wof:name":"J & T Electrics",
    "wof:placetype":"venue"
},
  "geometry": {"coordinates":[151.068756103,-33.9753265381],"type":"Point"}
}