{
  "type": "Feature",
  "properties": {
    "addr:full":"65 Nealdon Drv Meadowbrook QLD 4131",
    "addr:housenumber":"65",
    "addr:postcode":"4131",
    "addr:street":"Nealdon Drv",
    "iso:country":"AU",
    "sg:address":"65 Nealdon Drv",
    "sg:city":"Meadowbrook",
    "sg:classifiers":[
        {
            "category":"Autos & Motor Vehicles",
            "subcategory":"Automobile Sales",
            "type":"Retail Goods"
        }
    ],
    "sg:phone":"+61 7 3200 6555",
    "sg:postcode":"4131",
    "sg:province":"QLD",
    "sg:tags":[
        "equipment",
        "trailer"
    ],
    "wof:name":"Samin Sheet Metal Pty Ltd",
    "wof:placetype":"venue"
},
  "geometry": {"coordinates":[153.133712769,-27.666847229],"type":"Point"}
}