{
  "type": "Feature",
  "properties": {
    "iso:country":"AU",
    "sg:address":"110 Victoria St",
    "sg:city":"Mackay",
    "sg:classifiers":[
        {
            "category":"Arena",
            "subcategory":"Horse Racetrack",
            "type":"Entertainment"
        }
    ],
    "sg:phone":"+61 7 4957 4037",
    "sg:postcode":"4740",
    "sg:province":"QLD",
    "sg:tags":[
        "retail",
        "swimwear"
    ],
    "wof:name":"She Sells",
    "wof:placetype":"venue"
},
  "geometry": {"coordinates":[149.186264,-21.141077],"type":"Point"}
}