{
  "type": "Feature",
  "properties": {
    "iso:country":"AU",
    "sg:address":"Robinson St",
    "sg:city":"Camperdown",
    "sg:classifiers":[
        {
            "category":"Health Services",
            "subcategory":"Doctor",
            "type":"Services"
        }
    ],
    "sg:phone":"+61 3 5593 7070",
    "sg:postcode":"3260",
    "sg:province":"VIC",
    "sg:tags":[
        "medical",
        "practitioner"
    ],
    "wof:name":"Robinson Street Medical Centre",
    "wof:placetype":"venue"
},
  "geometry": {"coordinates":[143.137817383,-38.2365837097],"type":"Point"}
}