{
  "type": "Feature",
  "properties": {
    "addr:full":"Cnr Ham & Drummond Sts Windsor South NSW 2756",
    "addr:postcode":"2756",
    "addr:street":"Cnr Ham & Drummond Sts",
    "iso:country":"AU",
    "sg:address":"Cnr Ham & Drummond Sts",
    "sg:city":"Windsor South",
    "sg:classifiers":[
        {
            "category":"Retail",
            "subcategory":"Auto Repair",
            "type":"Services"
        }
    ],
    "sg:phone":"+61 13 28 68",
    "sg:postcode":"2756",
    "sg:province":"NSW",
    "sg:tags":[
        "repairer",
        "motor",
        "engineer"
    ],
    "wof:name":"Repco Authorised Service",
    "wof:placetype":"venue"
},
  "geometry": {"coordinates":[150.79916381800001,-33.6224555969],"type":"Point"}
}