{
  "type": "Feature",
  "properties": {
    "iso:country":"AU",
    "sg:address":"4 Thomas Drv",
    "sg:city":"Mt Burr",
    "sg:classifiers":[
        {
            "category":"Food & Beverages",
            "subcategory":"Supermarket",
            "type":"Retail Goods"
        }
    ],
    "sg:phone":"+61 8 8734 8220",
    "sg:postcode":"5279",
    "sg:province":"SA",
    "sg:tags":[
        "grocery",
        "store"
    ],
    "wof:name":"Mount Burr General Store",
    "wof:placetype":"venue"
},
  "geometry": {"coordinates":[140.457764,-37.541611],"type":"Point"}
}