{
  "type": "Feature",
  "properties": {
    "iso:country":"AU",
    "sg:address":"20 Southwood Rd",
    "sg:city":"Stuart",
    "sg:classifiers":[
        {
            "category":"Building & Trades",
            "subcategory":"Construction",
            "type":"Services"
        }
    ],
    "sg:phone":"+61 419 747 135",
    "sg:postcode":"4811",
    "sg:province":"QLD",
    "sg:tags":[
        "earth",
        "excavating",
        "moving",
        "contractor"
    ],
    "wof:name":"Hardrock Earth Works",
    "wof:placetype":"venue"
},
  "geometry": {"coordinates":[146.842255,-19.346581],"type":"Point"}
}