{
  "type": "Feature",
  "properties": {
    "addr:full":"919 High St Reservoir VIC 3073",
    "addr:housenumber":"919",
    "addr:postcode":"3073",
    "addr:street":"High St",
    "iso:country":"AU",
    "sg:address":"919 High St",
    "sg:city":"Reservoir",
    "sg:classifiers":[
        {
            "category":"Fast Food",
            "type":"Food & Drink"
        }
    ],
    "sg:phone":"+61 3 9460 2857",
    "sg:postcode":"3073",
    "sg:province":"VIC",
    "sg:tags":[
        "away",
        "take"
    ],
    "wof:name":"KFC",
    "wof:placetype":"venue"
},
  "geometry": {"coordinates":[145.00796508799999,-37.7129821777],"type":"Point"}
}