{
  "type": "Feature",
  "properties": {
    "addr:full":"125 Dalley St Mullumbimby NSW 2482",
    "addr:housenumber":"125",
    "addr:postcode":"2482",
    "addr:street":"Dalley St",
    "iso:country":"AU",
    "sg:address":"125 Dalley St",
    "sg:city":"Mullumbimby",
    "sg:classifiers":[
        {
            "category":"Health Services",
            "subcategory":"Medical Lab",
            "type":"Services"
        }
    ],
    "sg:phone":"+61 2 6684 1390",
    "sg:postcode":"2482",
    "sg:province":"NSW",
    "sg:tags":[
        "laboratory",
        "pathology"
    ],
    "wof:name":"Sullivan Nicolaides Pathology Laboratories",
    "wof:placetype":"venue"
},
  "geometry": {"coordinates":[153.49916076700001,-28.5550632477],"type":"Point"}
}