{
  "type": "Feature",
  "properties": {
    "addr:full":"Parafield Commercial Estate Lot 8, Unit 1, Main North Rd Parafield SA 5106",
    "addr:housenumber":"unit 1",
    "addr:postcode":"5106",
    "addr:street":"Main North Rd",
    "iso:country":"AU",
    "sg:address":"Parafield Commercial Estate Lot 8, Unit 1, Main North Rd",
    "sg:city":"Parafield",
    "sg:classifiers":[
        {
            "category":"Autos & Motor Vehicles",
            "subcategory":"Auto Supplies",
            "type":"Retail Goods"
        }
    ],
    "sg:phone":"+61 8 8182 3688",
    "sg:postcode":"5106",
    "sg:province":"SA",
    "sg:tags":[
        "tyre"
    ],
    "wof:name":"Cluse Bros Tyres",
    "wof:placetype":"venue"
},
  "geometry": {"coordinates":[138.63720699999999,-34.803101],"type":"Point"}
}