{
  "type": "Feature",
  "properties": {
    "addr:full":"81 Boolcarrol Rd Wee Waa NSW 2388",
    "addr:housenumber":"81",
    "addr:postcode":"2388",
    "addr:street":"Boolcarrol Rd",
    "iso:country":"AU",
    "sg:address":"81 Boolcarrol Rd",
    "sg:city":"Wee Waa",
    "sg:classifiers":[
        {
            "category":"Manufacturing",
            "subcategory":"Textiles",
            "type":"Manufacturing & Wholesale Goods"
        }
    ],
    "sg:phone":"+61 2 6795 3422",
    "sg:postcode":"2388",
    "sg:province":"NSW",
    "sg:tags":[
        "cotton"
    ],
    "wof:name":"Queensland Cotton Corp",
    "wof:placetype":"venue"
},
  "geometry": {"coordinates":[149.437591553,-30.2241535187],"type":"Point"}
}