{
  "type": "Feature",
  "properties": {
    "addr:full":"37 Brisbane St Launceston TAS 7250",
    "addr:housenumber":"37",
    "addr:postcode":"7250",
    "addr:street":"Brisbane St",
    "iso:country":"AU",
    "sg:address":"37 Brisbane St",
    "sg:city":"Launceston",
    "sg:classifiers":[
        {
            "category":"Professional",
            "subcategory":"Accounting & Tax Preparation",
            "type":"Services"
        }
    ],
    "sg:phone":"+61 3 6334 4387",
    "sg:postcode":"7250",
    "sg:province":"TAS",
    "sg:tags":[
        "accountant",
        "auditor"
    ],
    "wof:name":"Shreeve Michael",
    "wof:placetype":"venue"
},
  "geometry": {"coordinates":[147.14227294899999,-41.4349822998],"type":"Point"}
}