{
  "type": "Feature",
  "properties": {
    "iso:country":"AU",
    "sg:address":"Suite 7 Medical Centre 357 Gympie Rd",
    "sg:city":"Strathpine",
    "sg:classifiers":[
        {
            "category":"Health Services",
            "subcategory":"Dentist",
            "type":"Services"
        }
    ],
    "sg:phone":"+61 7 3205 5811",
    "sg:postcode":"4500",
    "sg:province":"QLD",
    "wof:name":"Cole Dental",
    "wof:placetype":"venue"
},
  "geometry": {"coordinates":[152.988845825,-27.3024082184],"type":"Point"}
}