{
  "type": "Feature",
  "properties": {
    "iso:country":"AU",
    "sg:address":"62 Littlefield St",
    "sg:city":"Blackwater",
    "sg:classifiers":[
        {
            "category":"Banks & Credit Unions",
            "subcategory":"Bureau De Change",
            "type":"Services"
        }
    ],
    "sg:phone":"+61 7 4982 6963",
    "sg:postcode":"4717",
    "sg:province":"QLD",
    "sg:tags":[
        "escort",
        "transport",
        "pilot"
    ],
    "wof:name":"Luxford D A & C L",
    "wof:placetype":"venue"
},
  "geometry": {"coordinates":[148.872375,-23.584698],"type":"Point"}
}