{
  "type": "Feature",
  "properties": {
    "iso:country":"AU",
    "sg:address":"PO Box 2535",
    "sg:city":"Whyalla Norrie",
    "sg:classifiers":[
        {
            "category":"Building & Trades",
            "subcategory":"Construction",
            "type":"Services"
        }
    ],
    "sg:phone":"+61 412 810 935",
    "sg:postcode":"5608",
    "sg:province":"SA",
    "sg:tags":[
        "ceiling"
    ],
    "wof:name":"Hauser Ceilings",
    "wof:placetype":"venue"
},
  "geometry": {"coordinates":[137.551117,-33.029064],"type":"Point"}
}