{
  "type": "Feature",
  "properties": {
    "iso:country":"AU",
    "sg:address":"46 Neptune Ave",
    "sg:city":"Newcomb",
    "sg:classifiers":[
        {
            "category":"Shopping",
            "subcategory":"Clothing, Apparel, & Fashions",
            "type":"Retail Goods"
        }
    ],
    "sg:phone":"+61 3 5248 4335",
    "sg:postcode":"3219",
    "sg:province":"VIC",
    "sg:tags":[
        "style",
        "clothing",
        "western",
        "accessory"
    ],
    "wof:name":"Poldervan Western Gear",
    "wof:placetype":"venue"
},
  "geometry": {"coordinates":[144.397674561,-38.1636314392],"type":"Point"}
}