{
  "type": "Feature",
  "properties": {
    "addr:full":"66b Doncaster Rd Balwyn North VIC 3104",
    "addr:housenumber":"66b",
    "addr:postcode":"3104",
    "addr:street":"Doncaster Rd",
    "iso:country":"AU",
    "sg:address":"66b Doncaster Rd",
    "sg:city":"Balwyn North",
    "sg:classifiers":[
        {
            "category":"Food & Beverages",
            "subcategory":"Bakery",
            "type":"Retail Goods"
        }
    ],
    "sg:phone":"+61 3 9859 1671",
    "sg:postcode":"3104",
    "sg:province":"VIC",
    "sg:tags":[
        "cake",
        "shop",
        "pastry"
    ],
    "wof:name":"Monsieur Dupon",
    "wof:placetype":"venue"
},
  "geometry": {"coordinates":[145.071075439,-37.7928085327],"type":"Point"}
}