{
  "type": "Feature",
  "properties": {
    "addr:full":"3- 5 Mary St Blackburn VIC 3130",
    "addr:housenumber":"5",
    "addr:postcode":"3130",
    "addr:street":"Mary St",
    "iso:country":"AU",
    "sg:address":"3- 5 Mary St",
    "sg:city":"Blackburn",
    "sg:classifiers":[
        {
            "category":"Wholesale",
            "subcategory":"Seafood",
            "type":"Manufacturing & Wholesale Goods"
        }
    ],
    "sg:phone":"+61 3 9877 0400",
    "sg:postcode":"3130",
    "sg:province":"VIC",
    "sg:tags":[
        "fish"
    ],
    "wof:name":"Anassis Seafoods",
    "wof:placetype":"venue"
},
  "geometry": {"coordinates":[145.15530395499999,-37.8196868896],"type":"Point"}
}