{
  "type": "Feature",
  "properties": {
    "iso:country":"AU",
    "sg:address":"672 Brighton Rd",
    "sg:city":"Seacliff",
    "sg:classifiers":[
        {
            "category":"Health Services",
            "subcategory":"Health Practitioner",
            "type":"Services"
        }
    ],
    "sg:phone":"+61 8 8298 8664",
    "sg:postcode":"5049",
    "sg:province":"SA",
    "sg:tags":[
        "physiotherapist"
    ],
    "wof:name":"Smith Damian",
    "wof:placetype":"venue"
},
  "geometry": {"coordinates":[138.524734,-35.03685],"type":"Point"}
}