{
  "type": "Feature",
  "properties": {
    "addr:full":"56 Alderley Sq Wilson WA 6107",
    "addr:housenumber":"56",
    "addr:postcode":"6107",
    "addr:street":"Alderley Sq",
    "iso:country":"AU",
    "sg:address":"56 Alderley Sq",
    "sg:city":"Wilson",
    "sg:classifiers":[
        {
            "category":"Building & Trades",
            "subcategory":"Plumbing",
            "type":"Services"
        }
    ],
    "sg:phone":"+61 407 451 011",
    "sg:postcode":"6107",
    "sg:province":"WA",
    "sg:tags":[
        "plumber",
        "gasfitters"
    ],
    "wof:name":"Blennerhassett Troy",
    "wof:placetype":"venue"
},
  "geometry": {"coordinates":[115.91490173299999,-32.0187988281],"type":"Point"}
}