{
  "type": "Feature",
  "properties": {
    "iso:country":"AU",
    "sg:address":"44 Bridge Rd",
    "sg:city":"Richmond",
    "sg:classifiers":[
        {
            "category":"Personal",
            "subcategory":"Beauty Salon",
            "type":"Services"
        }
    ],
    "sg:phone":"+61 3 9429 9678",
    "sg:postcode":"3121",
    "sg:province":"VIC",
    "sg:website":"http://www.artsalbeautyroom.com.au",
    "wof:name":"Advance Beauty",
    "wof:placetype":"venue"
},
  "geometry": {"coordinates":[144.991424561,-37.8178138733],"type":"Point"}
}