{
  "type": "Feature",
  "properties": {
    "addr:full":"7/24 McCourt St Leederville WA 6007",
    "addr:housenumber":"/ 24",
    "addr:postcode":"6007",
    "addr:street":"Mccourt St",
    "iso:country":"AU",
    "sg:address":"7/24 McCourt St",
    "sg:city":"Leederville",
    "sg:classifiers":[
        {
            "category":"Health Services",
            "subcategory":"Doctor",
            "type":"Services"
        }
    ],
    "sg:phone":"+61 8 9381 8220",
    "sg:postcode":"6007",
    "sg:province":"WA",
    "sg:tags":[
        "medical",
        "practitioner"
    ],
    "wof:name":"Ahmat K P",
    "wof:placetype":"venue"
},
  "geometry": {"coordinates":[115.827819824,-31.9416866302],"type":"Point"}
}