{
  "type": "Feature",
  "properties": {
    "addr:full":"Springs Rd Mt Barker SA 5251",
    "addr:postcode":"5251",
    "addr:street":"Springs Rd",
    "iso:country":"AU",
    "sg:address":"Springs Rd",
    "sg:city":"Mt Barker",
    "sg:classifiers":[
        {
            "category":"Building & Trades",
            "subcategory":"Equipment Rental",
            "type":"Services"
        }
    ],
    "sg:phone":"+61 8 8391 6161",
    "sg:postcode":"5251",
    "sg:province":"SA",
    "sg:tags":[
        "hire",
        "catering"
    ],
    "wof:name":"Adelaide Hills Big Fridge Hire",
    "wof:placetype":"venue"
},
  "geometry": {"coordinates":[138.867675781,-35.0650405884],"type":"Point"}
}