{
  "type": "Feature",
  "properties": {
    "addr:full":"Pine Camp Rd Beerwah QLD 4519",
    "addr:postcode":"4519",
    "addr:street":"Pine Camp Rd",
    "iso:country":"AU",
    "sg:address":"Pine Camp Rd",
    "sg:city":"Beerwah",
    "sg:classifiers":[
        {
            "category":"Wholesale",
            "subcategory":"Tobacco Products",
            "type":"Manufacturing & Wholesale Goods"
        }
    ],
    "sg:phone":"+61 7 5494 6212",
    "sg:postcode":"4519",
    "sg:province":"QLD",
    "sg:tags":[
        "grower"
    ],
    "wof:name":"Squaldino L",
    "wof:placetype":"venue"
},
  "geometry": {"coordinates":[152.95695499999999,-26.854933],"type":"Point"}
}