{
  "type": "Feature",
  "properties": {
    "addr:full":"24 Akenside St Wacol QLD 4076",
    "addr:housenumber":"24",
    "addr:postcode":"4076",
    "addr:street":"Akenside St",
    "iso:country":"AU",
    "sg:address":"24 Akenside St",
    "sg:city":"Wacol",
    "sg:classifiers":[
        {
            "category":"Retail",
            "subcategory":"Auto Repair",
            "type":"Services"
        }
    ],
    "sg:phone":"+61 408 872 277",
    "sg:postcode":"4076",
    "sg:province":"QLD",
    "sg:tags":[
        "electrical"
    ],
    "wof:name":"Boss Auto Electrics Pty Ltd",
    "wof:placetype":"venue"
},
  "geometry": {"coordinates":[152.92433166500001,-27.5909004211],"type":"Point"}
}