{
  "type": "Feature",
  "properties": {
    "addr:full":"83 Nicholson St Footscray VIC 3011",
    "addr:housenumber":"83",
    "addr:postcode":"3011",
    "addr:street":"Nicholson St",
    "iso:country":"AU",
    "sg:address":"83 Nicholson St",
    "sg:city":"Footscray",
    "sg:classifiers":[
        {
            "category":"Shopping",
            "subcategory":"Mobile Phones",
            "type":"Retail Goods"
        }
    ],
    "sg:phone":"+61 3 9689 4555",
    "sg:postcode":"3011",
    "sg:province":"VIC",
    "sg:tags":[
        "telephone",
        "accessory"
    ],
    "wof:name":"V D T Telecommunications",
    "wof:placetype":"venue"
},
  "geometry": {"coordinates":[144.89915466299999,-37.8010864258],"type":"Point"}
}