{
  "type": "Feature",
  "properties": {
    "addr:full":"Plaza Arcade Shp 2-3 Wilson St Burnie TAS 7320",
    "addr:housenumber":"2-3",
    "addr:postcode":"7320",
    "addr:street":"Wilson St",
    "iso:country":"AU",
    "sg:address":"Plaza Arcade Shp 2-3 Wilson St",
    "sg:city":"Burnie",
    "sg:classifiers":[
        {
            "category":"Professional",
            "subcategory":"Printing & Photocopies",
            "type":"Services"
        }
    ],
    "sg:phone":"+61 3 6431 5896",
    "sg:postcode":"7320",
    "sg:province":"TAS",
    "sg:tags":[
        "trophy"
    ],
    "wof:name":"Burnie Trophy Centre",
    "wof:placetype":"venue"
},
  "geometry": {"coordinates":[145.905136,-41.060074],"type":"Point"}
}