{
  "type": "Feature",
  "properties": {
    "addr:full":"Unit 4/ 9 Bonnal Rd Erina NSW 2250",
    "addr:housenumber":"9",
    "addr:postcode":"2250",
    "addr:street":"Bonnal Rd",
    "iso:country":"AU",
    "sg:address":"Unit 4/ 9 Bonnal Rd",
    "sg:city":"Erina",
    "sg:classifiers":[
        {
            "category":"Parking",
            "type":"Transportation"
        }
    ],
    "sg:phone":"+61 2 4365 3913",
    "sg:postcode":"2250",
    "sg:province":"NSW",
    "sg:tags":[
        "equipment",
        "system"
    ],
    "wof:name":"Barry Smith Garage Doors Pty Ltd",
    "wof:placetype":"venue"
},
  "geometry": {"coordinates":[151.38385009800001,-33.4349441528],"type":"Point"}
}