{
  "type": "Feature",
  "properties": {
    "iso:country":"AU",
    "sg:address":"Unit 10/ 1 Commercial Rd",
    "sg:city":"Highett",
    "sg:classifiers":[
        {
            "category":"Home & Garden",
            "subcategory":"Home Furnishings",
            "type":"Retail Goods"
        }
    ],
    "sg:phone":"+61 3 9553 4911",
    "sg:postcode":"3190",
    "sg:province":"VIC",
    "sg:tags":[
        "candle"
    ],
    "wof:name":"Hands At Work/Zensations",
    "wof:placetype":"venue"
},
  "geometry": {"coordinates":[145.055908203,-37.9485702515],"type":"Point"}
}