{
  "type": "Feature",
  "properties": {
    "addr:full":"Cnr Derby St & Kent Rd Pascoe Vale VIC 3044",
    "addr:postcode":"3044",
    "addr:street":"Cnr Derby St & Kent Rd",
    "iso:country":"AU",
    "sg:address":"Cnr Derby St & Kent Rd",
    "sg:city":"Pascoe Vale",
    "sg:classifiers":[
        {
            "category":"Retail",
            "subcategory":"Veterinary Services",
            "type":"Services"
        }
    ],
    "sg:phone":"+61 3 9350 2955",
    "sg:postcode":"3044",
    "sg:province":"VIC",
    "sg:tags":[
        "surgeon"
    ],
    "wof:name":"Alexander Julian Dr",
    "wof:placetype":"venue"
},
  "geometry": {"coordinates":[144.94685363799999,-37.725479126],"type":"Point"}
}