{
  "type": "Feature",
  "properties": {
    "iso:country":"AU",
    "sg:address":"15 Cara St",
    "sg:city":"Greenmount",
    "sg:classifiers":[
        {
            "category":"Home & Garden",
            "subcategory":"Building Materials",
            "type":"Retail Goods"
        }
    ],
    "sg:phone":"+61 8 9255 1887",
    "sg:postcode":"6056",
    "sg:province":"WA",
    "sg:tags":[
        "concrete",
        "gutter",
        "kerb"
    ],
    "wof:name":"Barry Kallawk",
    "wof:placetype":"venue"
},
  "geometry": {"coordinates":[116.043197632,-31.8993968964],"type":"Point"}
}