{
  "type": "Feature",
  "properties": {
    "addr:full":"38 Parkes St Nelson Bay NSW 2315",
    "addr:housenumber":"38",
    "addr:postcode":"2315",
    "addr:street":"Parkes St",
    "iso:country":"AU",
    "sg:address":"38 Parkes St",
    "sg:city":"Nelson Bay",
    "sg:classifiers":[
        {
            "category":"Utilities",
            "subcategory":"Electric",
            "type":"Services"
        }
    ],
    "sg:phone":"+61 2 4981 2689",
    "sg:postcode":"2315",
    "sg:province":"NSW",
    "sg:tags":[
        "electrical",
        "contractor"
    ],
    "wof:name":"Bay Electrical & Airconditioning",
    "wof:placetype":"venue"
},
  "geometry": {"coordinates":[152.15535,-32.724319],"type":"Point"}
}