{
  "type": "Feature",
  "properties": {
    "addr:full":"10 Platypus Ave Bundall QLD 4217",
    "addr:housenumber":"10",
    "addr:postcode":"4217",
    "addr:street":"Platypus Ave",
    "iso:country":"AU",
    "sg:address":"10 Platypus Ave",
    "sg:city":"Bundall",
    "sg:classifiers":[
        {
            "category":"Shopping",
            "subcategory":"Crafts & Fabrics",
            "type":"Retail Goods"
        }
    ],
    "sg:phone":"+61 7 5526 7787",
    "sg:postcode":"4217",
    "sg:province":"QLD",
    "sg:tags":[
        "material",
        "dress"
    ],
    "wof:name":"Ribalta Fabric Sales",
    "wof:placetype":"venue"
},
  "geometry": {"coordinates":[153.40460205100001,-28.0171546936],"type":"Point"}
}