{
  "type": "Feature",
  "properties": {
    "iso:country":"AU",
    "sg:address":"27 Keating St",
    "sg:city":"Maroubra",
    "sg:classifiers":[
        {
            "category":"Shopping",
            "subcategory":"Clothing, Apparel, & Fashions",
            "type":"Retail Goods"
        }
    ],
    "sg:phone":"+61 2 9344 5476",
    "sg:postcode":"2035",
    "sg:province":"NSW",
    "sg:tags":[
        "lady",
        "wear"
    ],
    "wof:name":"Mobile Frock Shop",
    "wof:placetype":"venue"
},
  "geometry": {"coordinates":[151.24476623499999,-33.9368438721],"type":"Point"}
}