{
  "type": "Feature",
  "properties": {
    "addr:full":"23 Armstrong St Middle Park VIC 3206",
    "addr:housenumber":"23",
    "addr:postcode":"3206",
    "addr:street":"Armstrong St",
    "iso:country":"AU",
    "sg:address":"23 Armstrong St",
    "sg:city":"Middle Park",
    "sg:classifiers":[
        {
            "category":"Fast Food",
            "type":"Food & Drink"
        }
    ],
    "sg:phone":"+61 3 9699 8116",
    "sg:postcode":"3206",
    "sg:province":"VIC",
    "sg:tags":[
        "away",
        "take"
    ],
    "wof:name":"Armstrong Street Milkbar",
    "wof:placetype":"venue"
},
  "geometry": {"coordinates":[144.96435500000001,-37.850594],"type":"Point"}
}