{
  "type": "Feature",
  "properties": {
    "addr:full":"227 Bailey St Grovedale VIC 3216",
    "addr:housenumber":"227",
    "addr:postcode":"3216",
    "addr:street":"Bailey St",
    "iso:country":"AU",
    "sg:address":"227 Bailey St",
    "sg:city":"Grovedale",
    "sg:classifiers":[
        {
            "category":"Health Services",
            "subcategory":"Doctor",
            "type":"Services"
        }
    ],
    "sg:phone":"+61 3 5243 2156",
    "sg:postcode":"3216",
    "sg:province":"VIC",
    "sg:tags":[
        "podiatrist"
    ],
    "wof:name":"Bev Taylor's Podiatry Service",
    "wof:placetype":"venue"
},
  "geometry": {"coordinates":[144.3462677,-38.2054290771],"type":"Point"}
}