{
  "type": "Feature",
  "properties": {
    "addr:full":"2 Persse Rd Runcorn QLD 4113",
    "addr:housenumber":"2",
    "addr:postcode":"4113",
    "addr:street":"Persse Rd",
    "iso:country":"AU",
    "sg:address":"2 Persse Rd",
    "sg:city":"Runcorn",
    "sg:classifiers":[
        {
            "category":"Health Services",
            "subcategory":"Dentist",
            "type":"Services"
        }
    ],
    "sg:phone":"+61 7 3841 8998",
    "sg:postcode":"4113",
    "sg:province":"QLD",
    "wof:name":"Au Tony Dr",
    "wof:placetype":"venue"
},
  "geometry": {"coordinates":[153.08106994600001,-27.5995674133],"type":"Point"}
}