{
  "type": "Feature",
  "properties": {
    "iso:country":"AU",
    "sg:address":"2 Commercial Pl",
    "sg:city":"Drouin",
    "sg:classifiers":[
        {
            "category":"Professional",
            "subcategory":"Accounting & Tax Preparation",
            "type":"Services"
        }
    ],
    "sg:phone":"+61 3 5625 1373",
    "sg:postcode":"3818",
    "sg:province":"VIC",
    "sg:tags":[
        "consultant",
        "taxation"
    ],
    "wof:name":"Hill V.B.",
    "wof:placetype":"venue"
},
  "geometry": {"coordinates":[145.85817,-38.13623],"type":"Point"}
}