{
  "type": "Feature",
  "properties": {
    "addr:full":"69 Prince Edward Park Rd Woronora NSW 2232",
    "addr:housenumber":"69",
    "addr:postcode":"2232",
    "addr:street":"Prince;Park Rd",
    "iso:country":"AU",
    "sg:address":"69 Prince Edward Park Rd",
    "sg:city":"Woronora",
    "sg:classifiers":[
        {
            "category":"Transit Center",
            "subcategory":"Passenger",
            "type":"Transportation"
        }
    ],
    "sg:phone":"+61 2 9542 6136",
    "sg:postcode":"2232",
    "sg:province":"NSW",
    "sg:tags":[
        "frozen",
        "food",
        "retail"
    ],
    "wof:name":"The Factory Shop",
    "wof:placetype":"venue"
},
  "geometry": {"coordinates":[151.049682617,-34.0244102478],"type":"Point"}
}