{
  "type": "Feature",
  "properties": {
    "iso:country":"AU",
    "sg:address":"8/ 10 Sara St",
    "sg:city":"Toronto",
    "sg:classifiers":[
        {
            "category":"Utilities",
            "subcategory":"Electric",
            "type":"Services"
        }
    ],
    "sg:phone":"+61 2 4959 2226",
    "sg:postcode":"2283",
    "sg:province":"NSW",
    "sg:tags":[
        "tube",
        "lamps",
        "globe"
    ],
    "wof:name":"Rovert Pty Ltd",
    "wof:placetype":"venue"
},
  "geometry": {"coordinates":[151.59193420400001,-33.0054626465],"type":"Point"}
}