{
  "type": "Feature",
  "properties": {
    "iso:country":"AU",
    "sg:address":"3/ 73 Pinetree Gully Rd",
    "sg:city":"Willetton",
    "sg:classifiers":[
        {
            "category":"Retail",
            "subcategory":"Repair Shop",
            "type":"Services"
        }
    ],
    "sg:phone":"+61 8 9332 8277",
    "sg:postcode":"6155",
    "sg:province":"WA",
    "sg:tags":[
        "machine",
        "sewing"
    ],
    "wof:name":"Southlands Fabric & Sewing Centre",
    "wof:placetype":"venue"
},
  "geometry": {"coordinates":[115.881668,-32.058567],"type":"Point"}
}