{
  "type": "Feature",
  "properties": {
    "addr:full":"1/ 8 Coombes Drv Penrith NSW 2750",
    "addr:housenumber":"/ 8",
    "addr:postcode":"2750",
    "addr:street":"Coombes Drv",
    "iso:country":"AU",
    "sg:address":"1/ 8 Coombes Drv",
    "sg:city":"Penrith",
    "sg:classifiers":[
        {
            "category":"Retail",
            "subcategory":"Auto Repair",
            "type":"Services"
        }
    ],
    "sg:phone":"+61 2 4731 5695",
    "sg:postcode":"2750",
    "sg:province":"NSW",
    "sg:tags":[
        "wheel",
        "balancing",
        "alignment"
    ],
    "wof:name":"Precision Wheel Alignment Graham's",
    "wof:placetype":"venue"
},
  "geometry": {"coordinates":[150.696365356,-33.7430038452],"type":"Point"}
}