{
  "type": "Feature",
  "properties": {
    "iso:country":"AU",
    "sg:address":"10 Graham Pl",
    "sg:city":"Picnic Point",
    "sg:classifiers":[
        {
            "category":"Retail",
            "subcategory":"Auto Rental",
            "type":"Services"
        }
    ],
    "sg:phone":"+61 2 9771 4068",
    "sg:postcode":"2213",
    "sg:province":"NSW",
    "sg:tags":[
        "camper-trailers",
        "caravan",
        "hire"
    ],
    "wof:name":"Douglass J M Caravan Hire",
    "wof:placetype":"venue"
},
  "geometry": {"coordinates":[151.013138,-33.967831],"type":"Point"}
}