{
  "type": "Feature",
  "properties": {
    "addr:full":"126 Bourke Rd Alexandria NSW 2015",
    "addr:housenumber":"126",
    "addr:postcode":"2015",
    "addr:street":"Bourke Rd",
    "iso:country":"AU",
    "sg:address":"126 Bourke Rd",
    "sg:city":"Alexandria",
    "sg:classifiers":[
        {
            "category":"Professional",
            "type":"Services"
        }
    ],
    "sg:phone":"+61 2 9693 2600",
    "sg:postcode":"2015",
    "sg:province":"NSW",
    "sg:tags":[
        "forwarding",
        "agent",
        "transport"
    ],
    "wof:name":"Panalpina World Transport Pty Ltd",
    "wof:placetype":"venue"
},
  "geometry": {"coordinates":[151.193283081,-33.9129943848],"type":"Point"}
}