{
  "type": "Feature",
  "properties": {
    "addr:full":"14 Katanning St Bayswater WA 6053",
    "addr:housenumber":"14",
    "addr:postcode":"6053",
    "addr:street":"Katanning St",
    "iso:country":"AU",
    "sg:address":"14 Katanning St",
    "sg:city":"Bayswater",
    "sg:classifiers":[
        {
            "category":"Retail",
            "subcategory":"Auto Repair",
            "type":"Services"
        }
    ],
    "sg:phone":"+61 8 9378 1088",
    "sg:postcode":"6053",
    "sg:province":"WA",
    "sg:tags":[
        "bus",
        "truck"
    ],
    "wof:name":"Bayswater Truck Repairs",
    "wof:placetype":"venue"
},
  "geometry": {"coordinates":[115.930519104,-31.9204311371],"type":"Point"}
}