{
  "type": "Feature",
  "properties": {
    "addr:full":"18 Colin Jamieson Drv Welshpool WA 6106",
    "addr:housenumber":"18",
    "addr:postcode":"6106",
    "addr:street":"Colin Jamieson Drv",
    "iso:country":"AU",
    "sg:address":"18 Colin Jamieson Drv",
    "sg:city":"Welshpool",
    "sg:classifiers":[
        {
            "category":"Professional",
            "type":"Services"
        }
    ],
    "sg:phone":"+61 8 9258 3233",
    "sg:postcode":"6106",
    "sg:province":"WA",
    "sg:tags":[
        "industrial",
        "commercial",
        "catering"
    ],
    "wof:name":"Coffee Biz",
    "wof:placetype":"venue"
},
  "geometry": {"coordinates":[115.937049866,-31.9927406311],"type":"Point"}
}