{
  "type": "Feature",
  "properties": {
    "addr:full":"PO Box 432 Stirling SA 5152",
    "addr:postcode":"5152",
    "iso:country":"AU",
    "sg:address":"PO Box 432",
    "sg:city":"Stirling",
    "sg:classifiers":[
        {
            "category":"Building & Trades",
            "subcategory":"Equipment Rental",
            "type":"Services"
        }
    ],
    "sg:phone":"+61 8 8339 5967",
    "sg:postcode":"5152",
    "sg:province":"SA",
    "sg:tags":[
        "demolition",
        "contractor"
    ],
    "wof:name":"Adelaide & Hills Concrete Cutting",
    "wof:placetype":"venue"
},
  "geometry": {"coordinates":[138.72253418,-35.0080490112],"type":"Point"}
}