{
  "type": "Feature",
  "properties": {
    "addr:full":"Suite 3 Benowa Mansions 183 Ashmore Rd Benowa QLD 4217",
    "addr:housenumber":"183",
    "addr:postcode":"4217",
    "addr:street":"Ashmore Rd",
    "iso:country":"AU",
    "sg:address":"Suite 3 Benowa Mansions 183 Ashmore Rd",
    "sg:city":"Benowa",
    "sg:classifiers":[
        {
            "category":"Health Services",
            "subcategory":"Dentist",
            "type":"Services"
        }
    ],
    "sg:phone":"+61 1800 652 811",
    "sg:postcode":"4217",
    "sg:province":"QLD",
    "wof:name":"Latcham Neil",
    "wof:placetype":"venue"
},
  "geometry": {"coordinates":[153.393707275,-28.0097198486],"type":"Point"}
}