{
  "type": "Feature",
  "properties": {
    "iso:country":"AU",
    "sg:address":"16 Willow St",
    "sg:city":"Killarney",
    "sg:classifiers":[
        {
            "category":"Utilities",
            "subcategory":"Electric",
            "type":"Services"
        }
    ],
    "sg:phone":"+61 7 4664 1168",
    "sg:postcode":"4373",
    "sg:province":"QLD",
    "sg:tags":[
        "electrical",
        "contractor"
    ],
    "wof:name":"Killarney & District Electrical Service",
    "wof:placetype":"venue"
},
  "geometry": {"coordinates":[152.295776367,-28.3347988129],"type":"Point"}
}