{
  "type": "Feature",
  "properties": {
    "iso:country":"AU",
    "sg:address":"26 Station St",
    "sg:city":"Dandenong",
    "sg:classifiers":[
        {
            "category":"Manufacturing",
            "subcategory":"Tools & Machinery",
            "type":"Manufacturing & Wholesale Goods"
        }
    ],
    "sg:phone":"+61 3 9792 3278",
    "sg:postcode":"3175",
    "sg:province":"VIC",
    "sg:tags":[
        "abrasive"
    ],
    "wof:name":"G.T.R. Australia Pty Ltd",
    "wof:placetype":"venue"
},
  "geometry": {"coordinates":[145.20860290499999,-37.9925727844],"type":"Point"}
}