{
  "type": "Feature",
  "properties": {
    "addr:full":"31 Clermont Ave North Strathfield NSW 2137",
    "addr:housenumber":"31",
    "addr:postcode":"2137",
    "addr:street":"Clermont Ave",
    "iso:country":"AU",
    "sg:address":"31 Clermont Ave",
    "sg:city":"North Strathfield",
    "sg:classifiers":[
        {
            "category":"Social Services",
            "subcategory":"Child Care",
            "type":"Services"
        }
    ],
    "sg:phone":"+61 2 9743 6591",
    "sg:postcode":"2137",
    "sg:province":"NSW",
    "wof:name":"Concord Occasional Child Care",
    "wof:placetype":"venue"
},
  "geometry": {"coordinates":[151.09263610799999,-33.8571815491],"type":"Point"}
}