{
  "type": "Feature",
  "properties": {
    "addr:full":"2 St Columbs St Hawthorn VIC 3122",
    "addr:housenumber":"2",
    "addr:postcode":"3122",
    "addr:street":"St Columbs St",
    "iso:country":"AU",
    "sg:address":"2 St Columbs St",
    "sg:city":"Hawthorn",
    "sg:classifiers":[
        {
            "category":"Travel",
            "subcategory":"Hostel",
            "type":"Entertainment"
        }
    ],
    "sg:phone":"+61 3 9815 1074",
    "sg:postcode":"3122",
    "sg:province":"VIC",
    "sg:tags":[
        "home"
    ],
    "wof:name":"St Columbs Hostel",
    "wof:placetype":"venue"
},
  "geometry": {"coordinates":[145.03909301799999,-37.8237266541],"type":"Point"}
}