{
  "type": "Feature",
  "properties": {
    "addr:full":"282 Ritchie Rd Pallara QLD 4110",
    "addr:housenumber":"282",
    "addr:postcode":"4110",
    "addr:street":"Ritchie Rd",
    "iso:country":"AU",
    "sg:address":"282 Ritchie Rd",
    "sg:city":"Pallara",
    "sg:classifiers":[
        {
            "category":"Education",
            "subcategory":"School",
            "type":"Public Place"
        }
    ],
    "sg:phone":"+61 7 3723 6333",
    "sg:postcode":"4110",
    "sg:province":"QLD",
    "sg:tags":[
        "state",
        "except",
        "nsw"
    ],
    "wof:name":"Pallara State School",
    "wof:placetype":"venue"
},
  "geometry": {"coordinates":[153.00358581500001,-27.6155891418],"type":"Point"}
}