{
  "type": "Feature",
  "properties": {
    "addr:full":"93 Fiddaman Rd Emerald Beach NSW 2456",
    "addr:housenumber":"93",
    "addr:postcode":"2456",
    "addr:street":"Fiddaman Rd",
    "iso:country":"AU",
    "sg:address":"93 Fiddaman Rd",
    "sg:city":"Emerald Beach",
    "sg:classifiers":[
        {
            "category":"Building & Trades",
            "subcategory":"Landscaping Services",
            "type":"Services"
        }
    ],
    "sg:phone":"+61 2 6656 1293",
    "sg:postcode":"2456",
    "sg:province":"NSW",
    "sg:tags":[
        "horticultural",
        "consultant"
    ],
    "wof:name":"Brockwell & Co",
    "wof:placetype":"venue"
},
  "geometry": {"coordinates":[153.18055699999999,-30.165808],"type":"Point"}
}