{
  "type": "Feature",
  "properties": {
    "iso:country":"AU",
    "sg:address":"Koola Ave",
    "sg:city":"Killara",
    "sg:classifiers":[
        {
            "category":"Education",
            "subcategory":"School",
            "type":"Public Place"
        }
    ],
    "sg:phone":"+61 2 9498 3722",
    "sg:postcode":"2071",
    "sg:province":"NSW",
    "sg:tags":[
        "state",
        "-",
        "nsw"
    ],
    "wof:name":"Killara High School",
    "wof:placetype":"venue"
},
  "geometry": {"coordinates":[151.17025756800001,-33.7592964172],"type":"Point"}
}