{
  "type": "Feature",
  "properties": {
    "addr:full":"Shop 2063-2064 Westfield Shpng Twn Cnr Florence & Hunter Sts Hornsby NSW 2077",
    "addr:housenumber":"2063-2064",
    "addr:postcode":"2077",
    "addr:street":"Westfield Shpng;Cnr Florence",
    "iso:country":"AU",
    "sg:address":"Shop 2063-2064 Westfield Shpng Twn Cnr Florence & Hunter Sts",
    "sg:city":"Hornsby",
    "sg:classifiers":[
        {
            "category":"Shopping",
            "type":"Retail Goods"
        }
    ],
    "sg:phone":"+61 2 9476 0747",
    "sg:postcode":"2077",
    "sg:province":"NSW",
    "sg:tags":[
        "repair",
        "travel"
    ],
    "wof:name":"Strandbags Group Pty Limited",
    "wof:placetype":"venue"
},
  "geometry": {"coordinates":[151.104644775,-33.7045173645],"type":"Point"}
}