{
  "type": "Feature",
  "properties": {
    "addr:full":"8 Verco St Hackett ACT 2602",
    "addr:housenumber":"8",
    "addr:postcode":"2602",
    "addr:street":"Verco St",
    "iso:country":"AU",
    "sg:address":"8 Verco St",
    "sg:city":"Hackett",
    "sg:classifiers":[
        {
            "category":"Building & Trades",
            "subcategory":"Construction",
            "type":"Services"
        }
    ],
    "sg:phone":"+61 2 6249 7859",
    "sg:postcode":"2602",
    "sg:province":"ACT",
    "sg:tags":[
        "contractor"
    ],
    "wof:name":"Walden J",
    "wof:placetype":"venue"
},
  "geometry": {"coordinates":[149.16659545900001,-35.2423706055],"type":"Point"}
}