{
  "type": "Feature",
  "properties": {
    "addr:full":"Princess Royal Drv Albany WA 6330",
    "addr:postcode":"6330",
    "addr:street":"Princess Royal Drv",
    "iso:country":"AU",
    "sg:address":"Princess Royal Drv",
    "sg:city":"Albany",
    "sg:classifiers":[
        {
            "category":"Professional",
            "subcategory":"Engineering",
            "type":"Services"
        }
    ],
    "sg:phone":"+61 8 9841 1472",
    "sg:postcode":"6330",
    "sg:province":"WA",
    "sg:tags":[
        "manufacturing",
        "engineer"
    ],
    "wof:name":"Wallace Engineering",
    "wof:placetype":"venue"
},
  "geometry": {"coordinates":[117.89325714100001,-35.0325050354],"type":"Point"}
}