{
  "type": "Feature",
  "properties": {
    "iso:country":"AU",
    "sg:address":"5 Darcy Crt",
    "sg:city":"Mooroopna",
    "sg:classifiers":[
        {
            "category":"Professional",
            "subcategory":"Accounting & Tax Preparation",
            "type":"Services"
        }
    ],
    "sg:phone":"+61 3 5825 2680",
    "sg:postcode":"3629",
    "sg:province":"VIC",
    "sg:tags":[
        "accountant",
        "auditor"
    ],
    "wof:name":"Baldwin C J",
    "wof:placetype":"venue"
},
  "geometry": {"coordinates":[145.34437560999999,-36.4008255005],"type":"Point"}
}