{
  "type": "Feature",
  "properties": {
    "iso:country":"AU",
    "sg:address":"1 Bellavista Rd",
    "sg:city":"Glen Iris",
    "sg:classifiers":[
        {
            "category":"Professional",
            "subcategory":"Computer Services",
            "type":"Services"
        }
    ],
    "sg:phone":"+61 3 9885 8361",
    "sg:postcode":"3146",
    "sg:province":"VIC",
    "sg:tags":[
        "consultant",
        "system"
    ],
    "wof:name":"Logic Engineering Pty Ltd",
    "wof:placetype":"venue"
},
  "geometry": {"coordinates":[145.07138061500001,-37.8622436523],"type":"Point"}
}