{
  "type": "Feature",
  "properties": {
    "addr:full":"16 Robertson St Coonabarabran NSW 2357",
    "addr:housenumber":"16",
    "addr:postcode":"2357",
    "addr:street":"Robertson St",
    "iso:country":"AU",
    "sg:address":"16 Robertson St",
    "sg:city":"Coonabarabran",
    "sg:classifiers":[
        {
            "category":"Education",
            "subcategory":"Vocational School",
            "type":"Public Place"
        }
    ],
    "sg:phone":"+61 2 6842 1351",
    "sg:postcode":"2357",
    "sg:province":"NSW",
    "sg:tags":[
        "technical",
        "college",
        "trade"
    ],
    "wof:name":"New England Institute of TAFE Coonabarabran Campus",
    "wof:placetype":"venue"
},
  "geometry": {"coordinates":[149.27507019000001,-31.2746524811],"type":"Point"}
}