{
  "type": "Feature",
  "properties": {
    "addr:full":"3, 155 Oxley St Camden NSW 2570",
    "addr:housenumber":"3 155",
    "addr:postcode":"2570",
    "addr:street":"Oxley St",
    "iso:country":"AU",
    "sg:address":"3, 155 Oxley St",
    "sg:city":"Camden",
    "sg:classifiers":[
        {
            "category":"Wholesale",
            "subcategory":"Medical Equipment & Supplies",
            "type":"Manufacturing & Wholesale Goods"
        }
    ],
    "sg:phone":"+61 2 4655 1648",
    "sg:postcode":"2570",
    "sg:province":"NSW",
    "sg:tags":[
        "aids",
        "hearing"
    ],
    "wof:name":"The Hearing Aid Clinic",
    "wof:placetype":"venue"
},
  "geometry": {"coordinates":[150.69369506800001,-34.0560684204],"type":"Point"}
}