{
  "type": "Feature",
  "properties": {
    "iso:country":"AU",
    "sg:address":"20 Grieve Pde",
    "sg:city":"Altona",
    "sg:classifiers":[
        {
            "category":"Manufacturing",
            "subcategory":"Tools & Machinery",
            "type":"Manufacturing & Wholesale Goods"
        }
    ],
    "sg:phone":"+61 3 9315 9628",
    "sg:postcode":"3018",
    "sg:province":"VIC",
    "sg:tags":[
        "supplier",
        "diamond"
    ],
    "wof:name":"Industrial Diamond Saw Co (Australia) Pty Ltd",
    "wof:placetype":"venue"
},
  "geometry": {"coordinates":[144.81761169399999,-37.8700141907],"type":"Point"}
}