{
  "type": "Feature",
  "properties": {
    "addr:full":"Shp3/ 1 Lipson Rd Tumby Bay SA 5605",
    "addr:housenumber":"1",
    "addr:postcode":"5605",
    "addr:street":"Lipson Rd",
    "iso:country":"AU",
    "sg:address":"Shp3/ 1 Lipson Rd",
    "sg:city":"Tumby Bay",
    "sg:classifiers":[
        {
            "category":"Shopping",
            "subcategory":"Crafts & Fabrics",
            "type":"Retail Goods"
        }
    ],
    "sg:phone":"+61 8 8688 2999",
    "sg:postcode":"5605",
    "sg:province":"SA",
    "sg:tags":[
        "material",
        "dress"
    ],
    "wof:name":"Patches At The Bay",
    "wof:placetype":"venue"
},
  "geometry": {"coordinates":[136.102844,-34.374992],"type":"Point"}
}