{
  "type": "Feature",
  "properties": {
    "iso:country":"AU",
    "sg:address":"Level 2, 86 Punt Rd St",
    "sg:city":"Kilda",
    "sg:classifiers":[
        {
            "category":"Sports & Exercise",
            "subcategory":"Gym",
            "type":"Entertainment"
        }
    ],
    "sg:phone":"+61 419 959 599",
    "sg:postcode":"3182",
    "sg:province":"VIC",
    "sg:tags":[
        "personal",
        "trainer",
        "fitness"
    ],
    "wof:name":"Body By Brett Personal Training",
    "wof:placetype":"venue"
},
  "geometry": {"coordinates":[144.983840942,-37.8536758423],"type":"Point"}
}