{
  "type": "Feature",
  "properties": {
    "iso:country":"AU",
    "sg:address":"71 Semaphore Rd",
    "sg:city":"Semaphore",
    "sg:classifiers":[
        {
            "category":"Communications",
            "subcategory":"Film & Video Production",
            "type":"Services"
        }
    ],
    "sg:phone":"+61 8 8242 2965",
    "sg:postcode":"5019",
    "sg:province":"SA",
    "sg:tags":[
        "made",
        "clothing",
        "custom"
    ],
    "wof:name":"3rd Dimension",
    "wof:placetype":"venue"
},
  "geometry": {"coordinates":[138.48518371599999,-34.838924408],"type":"Point"}
}