{
  "type": "Feature",
  "properties": {
    "iso:country":"AU",
    "sg:address":"54 Leyland St",
    "sg:city":"Garbutt",
    "sg:classifiers":[
        {
            "category":"Manufacturing",
            "subcategory":"Retail Goods",
            "type":"Manufacturing & Wholesale Goods"
        }
    ],
    "sg:phone":"+61 1300 551 473",
    "sg:postcode":"4814",
    "sg:province":"QLD",
    "sg:tags":[
        "merchant",
        "pump",
        "mfrs"
    ],
    "wof:name":"Pump Engineers (Queensland)",
    "wof:placetype":"venue"
},
  "geometry": {"coordinates":[146.763489,-19.272406],"type":"Point"}
}