{
  "type": "Feature",
  "properties": {
    "addr:full":"43 Felspar St Welshpool WA 6106",
    "addr:housenumber":"43",
    "addr:postcode":"6106",
    "addr:street":"Felspar St",
    "iso:country":"AU",
    "sg:address":"43 Felspar St",
    "sg:city":"Welshpool",
    "sg:classifiers":[
        {
            "category":"Home & Garden",
            "subcategory":"Building Materials",
            "type":"Retail Goods"
        }
    ],
    "sg:phone":"+61 8 9458 2111",
    "sg:postcode":"6106",
    "sg:province":"WA",
    "sg:tags":[
        "roofing"
    ],
    "wof:name":"Westflex Pty Ltd",
    "wof:placetype":"venue"
},
  "geometry": {"coordinates":[115.97329711899999,-31.9979228973],"type":"Point"}
}