{
  "type": "Feature",
  "properties": {
    "addr:full":"Shop 4011, Level 4 West Point Shpng Cntr Patrick S Blacktown NSW 2148",
    "addr:housenumber":"4011 level 4",
    "addr:postcode":"2148",
    "iso:country":"AU",
    "sg:address":"Shop 4011, Level 4 West Point Shpng Cntr Patrick S",
    "sg:city":"Blacktown",
    "sg:classifiers":[
        {
            "category":"Shopping",
            "subcategory":"Party Supplies",
            "type":"Retail Goods"
        }
    ],
    "sg:phone":"+61 2 9622 8950",
    "sg:postcode":"2148",
    "sg:province":"NSW",
    "sg:tags":[
        "children's"
    ],
    "wof:name":"AMF Bowling Centres",
    "wof:placetype":"venue"
},
  "geometry": {"coordinates":[150.90428161599999,-33.7760505676],"type":"Point"}
}