{
  "type": "Feature",
  "properties": {
    "addr:full":"2 Reid Mews Berwick VIC 3806",
    "addr:housenumber":"2",
    "addr:postcode":"3806",
    "addr:street":"Reid Mews",
    "iso:country":"AU",
    "sg:address":"2 Reid Mews",
    "sg:city":"Berwick",
    "sg:classifiers":[
        {
            "category":"Professional",
            "subcategory":"Employment Agencies",
            "type":"Services"
        }
    ],
    "sg:phone":"+61 1300 888 581",
    "sg:postcode":"3806",
    "sg:province":"VIC",
    "sg:tags":[
        "entertainer",
        "agent"
    ],
    "wof:name":"Juke Box Australia",
    "wof:placetype":"venue"
},
  "geometry": {"coordinates":[145.351486206,-38.0539207458],"type":"Point"}
}