{
  "type": "Feature",
  "properties": {
    "addr:full":"7 Perlan House 50 Aerodrome Rd Maroochydore QLD 4558",
    "addr:housenumber":"7;house 50",
    "addr:postcode":"4558",
    "addr:street":"Aerodrome Rd",
    "iso:country":"AU",
    "sg:address":"7 Perlan House 50 Aerodrome Rd",
    "sg:city":"Maroochydore",
    "sg:classifiers":[
        {
            "category":"Professional",
            "subcategory":"Accounting & Tax Preparation",
            "type":"Services"
        }
    ],
    "sg:phone":"+61 7 5452 7205",
    "sg:postcode":"4558",
    "sg:province":"QLD",
    "sg:tags":[
        "accountant",
        "auditor"
    ],
    "wof:name":"Scambler Kevin P & Associates",
    "wof:placetype":"venue"
},
  "geometry": {"coordinates":[153.100341797,-26.6605834961],"type":"Point"}
}