{
  "type": "Feature",
  "properties": {
    "addr:full":"Suite 5 lev 10 Walker St North Sydney NSW 2060",
    "addr:housenumber":"10",
    "addr:postcode":"2060",
    "addr:street":"Walker St",
    "iso:country":"AU",
    "sg:address":"Suite 5 lev 10 Walker St",
    "sg:city":"North Sydney",
    "sg:classifiers":[
        {
            "category":"Professional",
            "subcategory":"Computer Services",
            "type":"Services"
        }
    ],
    "sg:phone":"+61 2 9460 4200",
    "sg:postcode":"2060",
    "sg:province":"NSW",
    "sg:tags":[
        "package",
        "software"
    ],
    "wof:name":"ManageSoft Corporation Pty Ltd",
    "wof:placetype":"venue"
},
  "geometry": {"coordinates":[151.20797729500001,-33.8425598145],"type":"Point"}
}