{
  "type": "Feature",
  "properties": {
    "addr:full":"Level 2, Dapto Leagues Club, Bong Bong Rd Dapto NSW 2530",
    "addr:postcode":"2530",
    "addr:street":"Bong Rd",
    "iso:country":"AU",
    "sg:address":"Level 2, Dapto Leagues Club, Bong Bong Rd",
    "sg:city":"Dapto",
    "sg:classifiers":[
        {
            "category":"Retail",
            "subcategory":"Event Space",
            "type":"Services"
        }
    ],
    "sg:phone":"+61 2 4261 1333",
    "sg:postcode":"2530",
    "sg:province":"NSW",
    "sg:tags":[
        "venue",
        "reception",
        "wedding"
    ],
    "wof:name":"The Sinclair Function Centre",
    "wof:placetype":"venue"
},
  "geometry": {"coordinates":[150.79351806599999,-34.4941368103],"type":"Point"}
}