{
  "type": "Feature",
  "properties": {
    "addr:full":"2 Hillcrest Ave Moorebank NSW 2170",
    "addr:housenumber":"2",
    "addr:postcode":"2170",
    "addr:street":"Hillcrest Ave",
    "iso:country":"AU",
    "sg:address":"2 Hillcrest Ave",
    "sg:city":"Moorebank",
    "sg:classifiers":[
        {
            "category":"Shopping",
            "subcategory":"Computers & Home Electronics",
            "type":"Retail Goods"
        }
    ],
    "sg:phone":"+61 2 9822 5778",
    "sg:postcode":"2170",
    "sg:province":"NSW",
    "sg:tags":[
        "equipment",
        "multimedia"
    ],
    "wof:name":"Allan Sergent",
    "wof:placetype":"venue"
},
  "geometry": {"coordinates":[150.94973754899999,-33.9394035339],"type":"Point"}
}