{
  "type": "Feature",
  "properties": {
    "iso:country":"AU",
    "sg:address":"1 Horner St",
    "sg:city":"Beaconsfield",
    "sg:classifiers":[
        {
            "category":"Real Estate",
            "subcategory":"Surveying",
            "type":"Services"
        }
    ],
    "sg:phone":"+61 3 9707 4117",
    "sg:postcode":"3807",
    "sg:province":"VIC",
    "sg:tags":[
        "surveyor",
        "land"
    ],
    "wof:name":"M.J. Reddie Surveys Pty Ltd",
    "wof:placetype":"venue"
},
  "geometry": {"coordinates":[145.37071227999999,-38.0487518311],"type":"Point"}
}