{
  "type": "Feature",
  "properties": {
    "iso:country":"AU",
    "sg:address":"57 Wingfield Rd",
    "sg:city":"Wingfield",
    "sg:classifiers":[
        {
            "category":"Retail",
            "subcategory":"Driving School",
            "type":"Services"
        }
    ],
    "sg:phone":"+61 8 8345 4911",
    "sg:postcode":"5013",
    "sg:province":"SA",
    "wof:name":"Courtesy Driving School",
    "wof:placetype":"venue"
},
  "geometry": {"coordinates":[138.55075073200001,-34.8453445435],"type":"Point"}
}