{
  "type": "Feature",
  "properties": {
    "addr:full":"Fctry 1/ 222 Governor Rd Braeside VIC 3195",
    "addr:housenumber":"1 / 222",
    "addr:postcode":"3195",
    "addr:street":"Fctry;Governor Rd",
    "iso:country":"AU",
    "sg:address":"Fctry 1/ 222 Governor Rd",
    "sg:city":"Braeside",
    "sg:classifiers":[
        {
            "category":"Shopping",
            "subcategory":"Crafts & Fabrics",
            "type":"Retail Goods"
        }
    ],
    "sg:phone":"+61 3 9587 9931",
    "sg:postcode":"3195",
    "sg:province":"VIC",
    "sg:tags":[
        "florist",
        "supply"
    ],
    "wof:name":"Zwapak Pty Ltd",
    "wof:placetype":"venue"
},
  "geometry": {"coordinates":[145.109985352,-38.0080299377],"type":"Point"}
}