{
  "type": "Feature",
  "properties": {
    "addr:full":"381 Whitehorse Rd Balwyn VIC 3103",
    "addr:housenumber":"381",
    "addr:postcode":"3103",
    "addr:street":"Whitehorse Rd",
    "iso:country":"AU",
    "sg:address":"381 Whitehorse Rd",
    "sg:city":"Balwyn",
    "sg:classifiers":[
        {
            "category":"Restaurant",
            "type":"Food & Drink"
        }
    ],
    "sg:phone":"+61 3 9888 6408",
    "sg:postcode":"3103",
    "sg:province":"VIC",
    "wof:name":"Ambrosia Greek Cuisine",
    "wof:placetype":"venue"
},
  "geometry": {"coordinates":[145.08267211899999,-37.8128547668],"type":"Point"}
}