{
  "type": "Feature",
  "properties": {
    "addr:full":"478 Wanneroo Rd Westminster WA 6061",
    "addr:housenumber":"478",
    "addr:postcode":"6061",
    "addr:street":"Wanneroo Rd",
    "iso:country":"AU",
    "sg:address":"478 Wanneroo Rd",
    "sg:city":"Westminster",
    "sg:classifiers":[
        {
            "category":"Shopping",
            "subcategory":"Clothing, Apparel, & Fashions",
            "type":"Retail Goods"
        }
    ],
    "sg:phone":"+61 8 9345 0351",
    "sg:postcode":"6061",
    "sg:province":"WA",
    "sg:tags":[
        "maternity",
        "wear"
    ],
    "wof:name":"Sunflower West & Maternity",
    "wof:placetype":"venue"
},
  "geometry": {"coordinates":[115.82797241199999,-31.8632564545],"type":"Point"}
}