{
  "type": "Feature",
  "properties": {
    "addr:full":"36 Bolivia St Cabramatta NSW 2166",
    "addr:housenumber":"36",
    "addr:postcode":"2166",
    "addr:street":"Bolivia St",
    "iso:country":"AU",
    "sg:address":"36 Bolivia St",
    "sg:city":"Cabramatta",
    "sg:classifiers":[
        {
            "category":"Food & Beverages",
            "subcategory":"Groceries & Convenience Stores",
            "type":"Retail Goods"
        }
    ],
    "sg:phone":"+61 2 9728 3659",
    "sg:postcode":"2166",
    "sg:province":"NSW",
    "wof:name":"Nguyen Thai Thuac",
    "wof:placetype":"venue"
},
  "geometry": {"coordinates":[150.93284606899999,-33.897857666],"type":"Point"}
}