{
  "type": "Feature",
  "properties": {
    "iso:country":"AU",
    "sg:address":"PO Box 331",
    "sg:city":"Canterbury",
    "sg:classifiers":[
        {
            "category":"Professional",
            "subcategory":"Art Services",
            "type":"Services"
        }
    ],
    "sg:phone":"+61 433 667 966",
    "sg:postcode":"3126",
    "sg:province":"VIC",
    "sg:tags":[
        "graphic",
        "designer"
    ],
    "wof:name":"Equest Design",
    "wof:placetype":"venue"
},
  "geometry": {"coordinates":[145.07310485799999,-37.8242492676],"type":"Point"}
}