{
  "type": "Feature",
  "properties": {
    "iso:country":"AU",
    "sg:address":"12 Elizabeth St",
    "sg:city":"Kensington",
    "sg:classifiers":[
        {
            "category":"Retail",
            "subcategory":"Event Space",
            "type":"Services"
        }
    ],
    "sg:phone":"+61 3 9376 2177",
    "sg:postcode":"3031",
    "sg:province":"VIC",
    "sg:tags":[
        "function",
        "organiser"
    ],
    "wof:name":"Number 12",
    "wof:placetype":"venue"
},
  "geometry": {"coordinates":[144.932953,-37.797985],"type":"Point"}
}