{
  "type": "Feature",
  "properties": {
    "addr:full":"46 Malbon St Bungendore NSW 2621",
    "addr:housenumber":"46",
    "addr:postcode":"2621",
    "addr:street":"Malbon St",
    "iso:country":"AU",
    "sg:address":"46 Malbon St",
    "sg:city":"Bungendore",
    "sg:classifiers":[
        {
            "category":"Communications",
            "subcategory":"News Services",
            "type":"Services"
        }
    ],
    "sg:phone":"+61 2 6238 0724",
    "sg:postcode":"2621",
    "sg:province":"NSW",
    "sg:tags":[
        "information",
        "tourist",
        "attractions"
    ],
    "wof:name":"Bungendore and Region Visitors Centre",
    "wof:placetype":"venue"
},
  "geometry": {"coordinates":[149.43406677199999,-35.2524909973],"type":"Point"}
}