{
  "type": "Feature",
  "properties": {
    "addr:full":"Suite 9 339 Ipswich Rd Annerley QLD 4103",
    "addr:housenumber":"339",
    "addr:postcode":"4103",
    "addr:street":"Ipswich Rd",
    "iso:country":"AU",
    "sg:address":"Suite 9 339 Ipswich Rd",
    "sg:city":"Annerley",
    "sg:classifiers":[
        {
            "category":"Professional",
            "subcategory":"Computer Services",
            "type":"Services"
        }
    ],
    "sg:phone":"+61 404 432 990",
    "sg:postcode":"4103",
    "sg:province":"QLD",
    "sg:tags":[
        "repairs",
        "upgrade",
        "equipment"
    ],
    "wof:name":"Lab Tech Computer services",
    "wof:placetype":"venue"
},
  "geometry": {"coordinates":[153.03428649899999,-27.5053920746],"type":"Point"}
}