{
  "type": "Feature",
  "properties": {
    "addr:full":"12 Yorkshire Pl Stretton QLD 4116",
    "addr:housenumber":"12",
    "addr:postcode":"4116",
    "addr:street":"Yorkshire Pl",
    "iso:country":"AU",
    "sg:address":"12 Yorkshire Pl",
    "sg:city":"Stretton",
    "sg:classifiers":[
        {
            "category":"Home & Garden",
            "subcategory":"Building Materials",
            "type":"Retail Goods"
        }
    ],
    "sg:phone":"+61 402 124 051",
    "sg:postcode":"4116",
    "sg:province":"QLD",
    "sg:tags":[
        "lawn",
        "cutting",
        "maintenance"
    ],
    "wof:name":"Snip n&#039; Mow",
    "wof:placetype":"venue"
},
  "geometry": {"coordinates":[153.074142456,-27.6183872223],"type":"Point"}
}