{
  "type": "Feature",
  "properties": {
    "addr:full":"23 Charles St Five Dock NSW 2046",
    "addr:housenumber":"23",
    "addr:postcode":"2046",
    "addr:street":"Charles St",
    "iso:country":"AU",
    "sg:address":"23 Charles St",
    "sg:city":"Five Dock",
    "sg:classifiers":[
        {
            "category":"Government",
            "subcategory":"Post Office",
            "type":"Public Place"
        }
    ],
    "sg:phone":"+61 404 033 798",
    "sg:postcode":"2046",
    "sg:province":"NSW",
    "sg:tags":[
        "yoga"
    ],
    "wof:name":"Yoga with Enid Guthrie",
    "wof:placetype":"venue"
},
  "geometry": {"coordinates":[151.131317,-33.86245],"type":"Point"}
}