{
  "type": "Feature",
  "properties": {
    "addr:full":"3 Sawyer St Leongatha VIC 3953",
    "addr:housenumber":"3",
    "addr:postcode":"3953",
    "addr:street":"Sawyer St",
    "iso:country":"AU",
    "sg:address":"3 Sawyer St",
    "sg:city":"Leongatha",
    "sg:classifiers":[
        {
            "category":"Home & Garden",
            "subcategory":"Building Materials",
            "type":"Retail Goods"
        }
    ],
    "sg:phone":"+61 3 5662 3889",
    "sg:postcode":"3953",
    "sg:province":"VIC",
    "sg:tags":[
        "lawn",
        "cutting",
        "maintenance"
    ],
    "wof:name":"Kerry's Mowing & Garden Maintenance",
    "wof:placetype":"venue"
},
  "geometry": {"coordinates":[145.937957764,-38.4697685242],"type":"Point"}
}