{
  "type": "Feature",
  "properties": {
    "iso:country":"AU",
    "sg:address":"4 Malabar Rd",
    "sg:city":"Claremont",
    "sg:classifiers":[
        {
            "category":"Building & Trades",
            "subcategory":"Construction",
            "type":"Services"
        }
    ],
    "sg:phone":"+61 404 211 157",
    "sg:postcode":"7011",
    "sg:province":"TAS",
    "sg:tags":[
        "rendering",
        "cement"
    ],
    "wof:name":"D & B Rendering",
    "wof:placetype":"venue"
},
  "geometry": {"coordinates":[147.24147033700001,-42.7840118408],"type":"Point"}
}