{
  "type": "Feature",
  "properties": {
    "addr:full":"48 Weld St Beaconsfield TAS 7270",
    "addr:housenumber":"48",
    "addr:postcode":"7270",
    "addr:street":"Weld St",
    "iso:country":"AU",
    "sg:address":"48 Weld St",
    "sg:city":"Beaconsfield",
    "sg:classifiers":[
        {
            "category":"Retail",
            "subcategory":"Veterinary Services",
            "type":"Services"
        }
    ],
    "sg:phone":"+61 3 6383 1477",
    "sg:postcode":"7270",
    "sg:province":"TAS",
    "sg:tags":[
        "surgeon"
    ],
    "wof:name":"Beaconsfield Veterinary Centre",
    "wof:placetype":"venue"
},
  "geometry": {"coordinates":[146.82371520999999,-41.2066421509],"type":"Point"}
}