{
  "type": "Feature",
  "properties": {
    "iso:country":"AU",
    "sg:address":"71- 79 Morphett Rd",
    "sg:city":"Camden Park",
    "sg:classifiers":[
        {
            "category":"Shopping",
            "subcategory":"Stationery & Office Supplies",
            "type":"Retail Goods"
        }
    ],
    "sg:phone":"+61 8 8375 1888",
    "sg:postcode":"5038",
    "sg:province":"SA",
    "wof:name":"Boise Cascade Office Products",
    "wof:placetype":"venue"
},
  "geometry": {"coordinates":[138.53721618599999,-34.9663047791],"type":"Point"}
}