{
  "type": "Feature",
  "properties": {
    "iso:country":"AU",
    "sg:address":"2 Margaret St",
    "sg:city":"Mirani",
    "sg:classifiers":[
        {
            "category":"Retail",
            "subcategory":"Auto Repair",
            "type":"Services"
        }
    ],
    "sg:phone":"+61 427 591 977",
    "sg:postcode":"4754",
    "sg:province":"QLD",
    "sg:tags":[
        "automotive",
        "air conditioning"
    ],
    "wof:name":"Ace Mining Service Pty Ltd",
    "wof:placetype":"venue"
},
  "geometry": {"coordinates":[148.86900299999999,-21.160152],"type":"Point"}
}