{
  "type": "Feature",
  "properties": {
    "addr:full":"61a Gouger St Adelaide SA 5000",
    "addr:housenumber":"61a",
    "addr:postcode":"5000",
    "addr:street":"Gouger St",
    "iso:country":"AU",
    "sg:address":"61a Gouger St",
    "sg:city":"Adelaide",
    "sg:classifiers":[
        {
            "category":"Personal",
            "subcategory":"Barber",
            "type":"Services"
        }
    ],
    "sg:phone":"+61 8 8212 0174",
    "sg:postcode":"5000",
    "sg:province":"SA",
    "wof:name":"Short Black &#039;N&#039; Sides",
    "wof:placetype":"venue"
},
  "geometry": {"coordinates":[138.59695434599999,-34.9304084778],"type":"Point"}
}