{
  "type": "Feature",
  "properties": {
    "addr:full":"Unit 8/ 3 Ocean St Woollahra NSW 2025",
    "addr:postcode":"2025",
    "addr:street":"Ocean St",
    "iso:country":"AU",
    "sg:address":"Unit 8/ 3 Ocean St",
    "sg:city":"Woollahra",
    "sg:classifiers":[
        {
            "category":"Shopping",
            "subcategory":"Computers & Home Electronics",
            "type":"Retail Goods"
        }
    ],
    "sg:phone":"+61 2 9362 9820",
    "sg:postcode":"2025",
    "sg:province":"NSW",
    "sg:tags":[
        "wholesaler",
        "mfrs",
        "part",
        "electronic"
    ],
    "wof:name":"Worldtronic Australia Co",
    "wof:placetype":"venue"
},
  "geometry": {"coordinates":[151.24049377399999,-33.889377594],"type":"Point"}
}