{
  "type": "Feature",
  "properties": {
    "addr:full":"22 Penhryn Ave Croydon VIC 3136",
    "addr:housenumber":"22",
    "addr:postcode":"3136",
    "addr:street":"Penhryn Ave",
    "iso:country":"AU",
    "sg:address":"22 Penhryn Ave",
    "sg:city":"Croydon",
    "sg:classifiers":[
        {
            "category":"Shopping",
            "subcategory":"Stationery & Office Supplies",
            "type":"Retail Goods"
        }
    ],
    "sg:phone":"+61 3 9723 4300",
    "sg:postcode":"3136",
    "sg:province":"VIC",
    "sg:tags":[
        "packaging",
        "material"
    ],
    "wof:name":"Eastern Tape & Packaging",
    "wof:placetype":"venue"
},
  "geometry": {"coordinates":[145.27000427199999,-37.7942657471],"type":"Point"}
}