{
  "type": "Feature",
  "properties": {
    "addr:full":"262A Glenferrie Rd Malvern VIC 3144",
    "addr:housenumber":"262a",
    "addr:postcode":"3144",
    "addr:street":"Glenferrie Rd",
    "iso:country":"AU",
    "sg:address":"262A Glenferrie Rd",
    "sg:city":"Malvern",
    "sg:classifiers":[
        {
            "category":"Professional",
            "subcategory":"Accounting & Tax Preparation",
            "type":"Services"
        }
    ],
    "sg:phone":"+61 3 9509 4037",
    "sg:postcode":"3144",
    "sg:province":"VIC",
    "sg:tags":[
        "accountant",
        "auditor"
    ],
    "wof:name":"Lionel A. Burke & Associates",
    "wof:placetype":"venue"
},
  "geometry": {"coordinates":[145.029296875,-37.8575439453],"type":"Point"}
}