{
  "type": "Feature",
  "properties": {
    "addr:full":"Suite 36, Level 3/ 12 Collins St Melbourne VIC 3000",
    "addr:housenumber":"/ 12",
    "addr:postcode":"3000",
    "addr:street":"Collins St",
    "iso:country":"AU",
    "sg:address":"Suite 36, Level 3/ 12 Collins St",
    "sg:city":"Melbourne",
    "sg:classifiers":[
        {
            "category":"Health Services",
            "subcategory":"Chiropractor",
            "type":"Services"
        }
    ],
    "sg:phone":"+61 3 9663 9162",
    "sg:postcode":"3000",
    "sg:province":"VIC",
    "wof:name":"Melbourne Natural Health Group",
    "wof:placetype":"venue"
},
  "geometry": {"coordinates":[144.97343444800001,-37.813331604],"type":"Point"}
}