{
  "type": "Feature",
  "properties": {
    "iso:country":"AU",
    "sg:address":"Mari St",
    "sg:city":"Alexandra Headland",
    "sg:classifiers":[
        {
            "category":"Conference Center",
            "type":"Public Place"
        }
    ],
    "sg:phone":"+61 7 5443 8966",
    "sg:postcode":"4572",
    "sg:province":"QLD",
    "sg:tags":[
        "venue",
        "convention"
    ],
    "wof:name":"Alexandra Park Conference Centre",
    "wof:placetype":"venue"
},
  "geometry": {"coordinates":[153.105255,-26.668308],"type":"Point"}
}