{
  "type": "Feature",
  "properties": {
    "iso:country":"AU",
    "sg:address":"13 Barrie St",
    "sg:city":"Coffs Harbour",
    "sg:classifiers":[
        {
            "category":"Real Estate",
            "subcategory":"Architect",
            "type":"Services"
        }
    ],
    "sg:phone":"+61 2 6651 4104",
    "sg:postcode":"2450",
    "sg:province":"NSW",
    "sg:website":"http://www.designstudio22.com.au",
    "wof:name":"Design Studio 22",
    "wof:placetype":"venue"
},
  "geometry": {"coordinates":[153.12471,-30.302778],"type":"Point"}
}