{
  "type": "Feature",
  "properties": {
    "addr:full":"106 Tingal Rd Wynnum QLD 4178",
    "addr:housenumber":"106",
    "addr:postcode":"4178",
    "addr:street":"Tingal Rd",
    "iso:country":"AU",
    "sg:address":"106 Tingal Rd",
    "sg:city":"Wynnum",
    "sg:classifiers":[
        {
            "category":"Fast Food",
            "type":"Food & Drink"
        }
    ],
    "sg:phone":"+61 7 3892 1111",
    "sg:postcode":"4178",
    "sg:province":"QLD",
    "sg:tags":[
        "away",
        "take"
    ],
    "wof:name":"Pizza Hut",
    "wof:placetype":"venue"
},
  "geometry": {"coordinates":[153.171310425,-27.4458885193],"type":"Point"}
}