{
  "type": "Feature",
  "properties": {
    "addr:full":"111 Bradley St Guyra NSW 2365",
    "addr:housenumber":"111",
    "addr:postcode":"2365",
    "addr:street":"Bradley St",
    "iso:country":"AU",
    "sg:address":"111 Bradley St",
    "sg:city":"Guyra",
    "sg:classifiers":[
        {
            "category":"Shopping",
            "type":"Retail Goods"
        }
    ],
    "sg:phone":"+61 2 6779 1999",
    "sg:postcode":"2365",
    "sg:province":"NSW",
    "sg:tags":[
        "agent",
        "stock"
    ],
    "wof:name":"Pearson W John & Co Pty Ltd",
    "wof:placetype":"venue"
},
  "geometry": {"coordinates":[151.671966553,-30.2184677124],"type":"Point"}
}