{
  "type": "Feature",
  "properties": {
    "addr:full":"72 Learmonth St Strathpine QLD 4500",
    "addr:housenumber":"72",
    "addr:postcode":"4500",
    "addr:street":"Learmonth St",
    "iso:country":"AU",
    "sg:address":"72 Learmonth St",
    "sg:city":"Strathpine",
    "sg:classifiers":[
        {
            "category":"Building & Trades",
            "subcategory":"Pest Control",
            "type":"Services"
        }
    ],
    "sg:phone":"+61 1300 133 243",
    "sg:postcode":"4500",
    "sg:province":"QLD",
    "wof:name":"Abandon Pest Control",
    "wof:placetype":"venue"
},
  "geometry": {"coordinates":[152.99327087399999,-27.3050231934],"type":"Point"}
}