{
  "type": "Feature",
  "properties": {
    "iso:country":"AU",
    "sg:address":"2 Blackdown St",
    "sg:city":"Toowoomba",
    "sg:classifiers":[
        {
            "category":"Professional",
            "subcategory":"Art Services",
            "type":"Services"
        }
    ],
    "sg:phone":"+61 7 4635 1538",
    "sg:postcode":"4350",
    "sg:province":"QLD",
    "sg:tags":[
        "artist"
    ],
    "wof:name":"Victoria Royds",
    "wof:placetype":"venue"
},
  "geometry": {"coordinates":[151.93974299999999,-27.572243],"type":"Point"}
}