{
  "type": "Feature",
  "properties": {
    "iso:country":"AU",
    "sg:address":"80 Dodds St",
    "sg:city":"Southbank",
    "sg:classifiers":[
        {
            "category":"Organizations",
            "subcategory":"Membership Organization",
            "type":"Services"
        }
    ],
    "sg:phone":"+61 3 9686 1811",
    "sg:postcode":"3006",
    "sg:province":"VIC",
    "sg:tags":[
        "support",
        "health",
        "organisation"
    ],
    "wof:name":"Cystic Fibrosis Victoria",
    "wof:placetype":"venue"
},
  "geometry": {"coordinates":[144.96731567399999,-37.827507019],"type":"Point"}
}