{
  "type": "Feature",
  "properties": {
    "addr:full":"The path to Better Health 6 Karou Crt Doncaster East VIC 3109",
    "addr:housenumber":"6",
    "addr:postcode":"3109",
    "addr:street":"Karou Crt",
    "iso:country":"AU",
    "sg:address":"The path to Better Health 6 Karou Crt",
    "sg:city":"Doncaster East",
    "sg:classifiers":[
        {
            "category":"Health Services",
            "subcategory":"Doctor",
            "type":"Services"
        }
    ],
    "sg:phone":"+61 3 9886 7687",
    "sg:postcode":"3109",
    "sg:province":"VIC",
    "sg:tags":[
        "reflexology"
    ],
    "wof:name":"Olive Lane",
    "wof:placetype":"venue"
},
  "geometry": {"coordinates":[145.153076172,-37.7878913879],"type":"Point"}
}