{
  "type": "Feature",
  "properties": {
    "addr:full":"14 McCoy St Waikerie SA 5330",
    "addr:housenumber":"14",
    "addr:postcode":"5330",
    "addr:street":"Mccoy St",
    "iso:country":"AU",
    "sg:address":"14 McCoy St",
    "sg:city":"Waikerie",
    "sg:classifiers":[
        {
            "category":"Cafe",
            "type":"Food & Drink"
        }
    ],
    "sg:phone":"+61 8 8541 2162",
    "sg:postcode":"5330",
    "sg:province":"SA",
    "wof:name":"Waikerie Cafe",
    "wof:placetype":"venue"
},
  "geometry": {"coordinates":[139.98541259800001,-34.1810798645],"type":"Point"}
}