{
  "type": "Feature",
  "properties": {
    "iso:country":"AU",
    "sg:address":"255 Port Rd",
    "sg:city":"Gawler",
    "sg:classifiers":[
        {
            "category":"Home & Garden",
            "subcategory":"Building Materials",
            "type":"Retail Goods"
        }
    ],
    "sg:phone":"+61 13 11 88",
    "sg:postcode":"5118",
    "sg:province":"SA",
    "sg:tags":[
        "pre-mixed",
        "concrete"
    ],
    "wof:name":"CSR Readymix",
    "wof:placetype":"venue"
},
  "geometry": {"coordinates":[138.72822600000001,-34.596329],"type":"Point"}
}