{
  "type": "Feature",
  "properties": {
    "addr:full":"325 North East Rd Hillcrest SA 5086",
    "addr:housenumber":"325",
    "addr:postcode":"5086",
    "addr:street":"North East Rd",
    "iso:country":"AU",
    "sg:address":"325 North East Rd",
    "sg:city":"Hillcrest",
    "sg:classifiers":[
        {
            "category":"Autos & Motor Vehicles",
            "subcategory":"Fuel & Gas Station",
            "type":"Retail Goods"
        }
    ],
    "sg:phone":"+61 8 8261 3957",
    "sg:postcode":"5086",
    "sg:province":"SA",
    "wof:name":"Mobil Oil Australia Pty Ltd",
    "wof:placetype":"venue"
},
  "geometry": {"coordinates":[138.63964843799999,-34.86901474],"type":"Point"}
}