{
  "type": "Feature",
  "properties": {
    "iso:country":"AU",
    "sg:address":"153- 155 Regent St",
    "sg:city":"Redfern",
    "sg:classifiers":[
        {
            "category":"Shopping",
            "subcategory":"Music",
            "type":"Retail Goods"
        }
    ],
    "sg:phone":"+61 2 9698 1300",
    "sg:postcode":"2016",
    "sg:province":"NSW",
    "sg:tags":[
        "instrument",
        "musical"
    ],
    "wof:name":"Guitar Jungle",
    "wof:placetype":"venue"
},
  "geometry": {"coordinates":[151.19989013700001,-33.8938751221],"type":"Point"}
}