{
  "type": "Feature",
  "properties": {
    "iso:country":"AU",
    "sg:address":"24 Homebush Drv",
    "sg:city":"Robina",
    "sg:classifiers":[
        {
            "category":"Building & Trades",
            "subcategory":"Plumbing",
            "type":"Services"
        }
    ],
    "sg:phone":"+61 418 762 396",
    "sg:postcode":"4226",
    "sg:province":"QLD",
    "sg:tags":[
        "plumber",
        "gasfitters"
    ],
    "wof:name":"R.A.M. Plumbing (Qld) Pty Ltd",
    "wof:placetype":"venue"
},
  "geometry": {"coordinates":[153.409225464,-28.0593738556],"type":"Point"}
}