{
  "type": "Feature",
  "properties": {
    "iso:country":"AU",
    "sg:address":"Olinda-Monbulk Rd",
    "sg:city":"Monbulk",
    "sg:classifiers":[
        {
            "category":"Insurance",
            "subcategory":"Hazard Insurance",
            "type":"Services"
        }
    ],
    "sg:phone":"+61 3 9756 7336",
    "sg:postcode":"3793",
    "sg:province":"VIC",
    "sg:tags":[
        "loss",
        "adjuster",
        "assessor"
    ],
    "wof:name":"McPhee James N",
    "wof:placetype":"venue"
},
  "geometry": {"coordinates":[145.40036010700001,-37.8736000061],"type":"Point"}
}