{
  "type": "Feature",
  "properties": {
    "addr:full":"195 Jensen St Edge Hill QLD 4870",
    "addr:housenumber":"195",
    "addr:postcode":"4870",
    "addr:street":"Jensen St",
    "iso:country":"AU",
    "sg:address":"195 Jensen St",
    "sg:city":"Edge Hill",
    "sg:classifiers":[
        {
            "category":"Utilities",
            "type":"Services"
        }
    ],
    "sg:phone":"+61 419 645 436",
    "sg:postcode":"4870",
    "sg:province":"QLD",
    "sg:tags":[
        "refrigeration",
        "industrial",
        "commercial",
        "retail"
    ],
    "wof:name":"Beare Air",
    "wof:placetype":"venue"
},
  "geometry": {"coordinates":[145.734542847,-16.8974227905],"type":"Point"}
}