{
  "type": "Feature",
  "properties": {
    "addr:full":"Lot 3 Cessnock Rd Sunshine NSW 2264",
    "addr:postcode":"2264",
    "addr:street":"Cessnock Rd",
    "iso:country":"AU",
    "sg:address":"Lot 3 Cessnock Rd",
    "sg:city":"Sunshine",
    "sg:classifiers":[
        {
            "category":"Farming",
            "subcategory":"Nursery",
            "type":"Manufacturing & Wholesale Goods"
        }
    ],
    "sg:phone":"+61 2 4973 3778",
    "sg:postcode":"2264",
    "sg:province":"NSW",
    "wof:name":"Australian Cactus & Succulent Supplies Pty Ltd",
    "wof:placetype":"venue"
},
  "geometry": {"coordinates":[151.565079,-33.112942],"type":"Point"}
}