{
  "type": "Feature",
  "properties": {
    "addr:full":"PO Box 2845 Mildura Centre Plaza VIC 3501",
    "addr:postcode":"3501",
    "iso:country":"AU",
    "sg:address":"PO Box 2845",
    "sg:city":"Mildura Centre Plaza",
    "sg:classifiers":[
        {
            "category":"Farming",
            "subcategory":"Farm & Veterinary Services",
            "type":"Manufacturing & Wholesale Goods"
        }
    ],
    "sg:phone":"+61 3 5023 7219",
    "sg:postcode":"3501",
    "sg:province":"VIC",
    "sg:tags":[
        "irrigation",
        "reticulation",
        "system"
    ],
    "wof:name":"G.J. & C. Mattschoss",
    "wof:placetype":"venue"
},
  "geometry": {"coordinates":[142.13630676299999,-34.2071113586],"type":"Point"}
}