{
  "type": "Feature",
  "properties": {
    "iso:country":"AU",
    "sg:address":"42 Norton St",
    "sg:city":"Leichhardt",
    "sg:classifiers":[
        {
            "category":"Health Services",
            "subcategory":"Dentist",
            "type":"Services"
        }
    ],
    "sg:phone":"+61 2 9560 9998",
    "sg:postcode":"2040",
    "sg:province":"NSW",
    "wof:name":"Brabant John L",
    "wof:placetype":"venue"
},
  "geometry": {"coordinates":[151.157288,-33.886559],"type":"Point"}
}