{
  "type": "Feature",
  "properties": {
    "addr:full":"Learmonth St Ballarat VIC 3350",
    "addr:postcode":"3350",
    "addr:street":"Learmonth St",
    "iso:country":"AU",
    "sg:address":"Learmonth St",
    "sg:city":"Ballarat",
    "sg:classifiers":[
        {
            "category":"Government",
            "subcategory":"Department Of Motor Vehicles",
            "type":"Public Place"
        }
    ],
    "sg:phone":"+61 3 5334 1213",
    "sg:postcode":"3350",
    "sg:province":"VIC",
    "sg:tags":[
        "wholesaler",
        "mfrs",
        "accessory"
    ],
    "wof:name":"Hemco Industries Pty Ltd",
    "wof:placetype":"venue"
},
  "geometry": {"coordinates":[143.810654,-37.568817],"type":"Point"}
}