{
  "type": "Feature",
  "properties": {
    "addr:full":"Cottage 1 Villiers St North Parramatta NSW 2151",
    "addr:housenumber":"1",
    "addr:postcode":"2151",
    "addr:street":"Villiers St",
    "iso:country":"AU",
    "sg:address":"Cottage 1 Villiers St",
    "sg:city":"North Parramatta",
    "sg:classifiers":[
        {
            "category":"Health Services",
            "subcategory":"Dentist",
            "type":"Services"
        }
    ],
    "sg:phone":"+61 2 9890 1822",
    "sg:postcode":"2151",
    "sg:province":"NSW",
    "wof:name":"Irving Mark A",
    "wof:placetype":"venue"
},
  "geometry": {"coordinates":[151.004364014,-33.8063201904],"type":"Point"}
}