{
  "type": "Feature",
  "properties": {
    "addr:full":"Factory 4/ 71 Brunel Rd Seaford VIC 3198",
    "addr:housenumber":"/ 71",
    "addr:postcode":"3198",
    "addr:street":"Brunel Rd",
    "iso:country":"AU",
    "sg:address":"Factory 4/ 71 Brunel Rd",
    "sg:city":"Seaford",
    "sg:classifiers":[
        {
            "category":"Retail",
            "subcategory":"Repair Shop",
            "type":"Services"
        }
    ],
    "sg:phone":"+61 417 051 221",
    "sg:postcode":"3198",
    "sg:province":"VIC",
    "sg:tags":[
        "windscreen"
    ],
    "wof:name":"Upfront Windscreens",
    "wof:placetype":"venue"
},
  "geometry": {"coordinates":[145.150787353,-38.1013946533],"type":"Point"}
}