{
  "type": "Feature",
  "properties": {
    "addr:full":"1072 Centre Rd Oakleigh South VIC 3167",
    "addr:housenumber":"1072",
    "addr:postcode":"3167",
    "addr:street":"Centre Rd",
    "iso:country":"AU",
    "sg:address":"1072 Centre Rd",
    "sg:city":"Oakleigh South",
    "sg:classifiers":[
        {
            "category":"Autos & Motor Vehicles",
            "subcategory":"Auto Supplies",
            "type":"Retail Goods"
        }
    ],
    "sg:phone":"+61 3 9575 1000",
    "sg:postcode":"3167",
    "sg:province":"VIC",
    "sg:tags":[
        "accessory"
    ],
    "wof:name":"Seat Cover World",
    "wof:placetype":"venue"
},
  "geometry": {"coordinates":[145.092895508,-37.9254226685],"type":"Point"}
}