{
  "type": "Feature",
  "properties": {
    "addr:full":"206 Walter Rd West Morley WA 6062",
    "addr:housenumber":"206",
    "addr:postcode":"6062",
    "addr:street":"Walter Rd West",
    "iso:country":"AU",
    "sg:address":"206 Walter Rd West",
    "sg:city":"Morley",
    "sg:classifiers":[
        {
            "category":"Military Area",
            "subcategory":"Army Base",
            "type":"Public Place"
        }
    ],
    "sg:phone":"+61 8 9276 5355",
    "sg:postcode":"6062",
    "sg:province":"WA",
    "sg:tags":[
        "wholesaler",
        "clutch",
        "brake",
        "mfrs",
        "equipment"
    ],
    "wof:name":"Goodyear Tyre & Brake Service",
    "wof:placetype":"venue"
},
  "geometry": {"coordinates":[115.89276886,-31.8973064423],"type":"Point"}
}