{
  "type": "Feature",
  "properties": {
    "addr:full":"3 Tea Tree Pl Moree NSW 2400",
    "addr:housenumber":"3",
    "addr:postcode":"2400",
    "addr:street":"Tea Tree Pl",
    "iso:country":"AU",
    "sg:address":"3 Tea Tree Pl",
    "sg:city":"Moree",
    "sg:classifiers":[
        {
            "category":"Building & Trades",
            "subcategory":"Construction",
            "type":"Services"
        }
    ],
    "sg:phone":"+61 2 6752 4001",
    "sg:postcode":"2400",
    "sg:province":"NSW",
    "sg:tags":[
        "contractor"
    ],
    "wof:name":"Gomilaroi Building & Construction Pty Ltd",
    "wof:placetype":"venue"
},
  "geometry": {"coordinates":[149.833694458,-29.47448349],"type":"Point"}
}