{
  "type": "Feature",
  "properties": {
    "iso:country":"AU",
    "sg:address":"37 Curlew Drv",
    "sg:city":"Rosebud West",
    "sg:classifiers":[
        {
            "category":"Insurance",
            "subcategory":"Life Insurance",
            "type":"Services"
        }
    ],
    "sg:phone":"+61 411 555 930",
    "sg:postcode":"3940",
    "sg:province":"VIC",
    "wof:name":"Maling Marketing Services Pty Ltd",
    "wof:placetype":"venue"
},
  "geometry": {"coordinates":[144.87965393100001,-38.3763313293],"type":"Point"}
}