{
  "type": "Feature",
  "properties": {
    "iso:country":"AU",
    "sg:address":"23 Aranda St",
    "sg:city":"Slacks Creek",
    "sg:classifiers":[
        {
            "category":"Manufacturing",
            "subcategory":"Furniture",
            "type":"Manufacturing & Wholesale Goods"
        }
    ],
    "sg:phone":"+61 7 3808 4704",
    "sg:postcode":"4127",
    "sg:province":"QLD",
    "sg:tags":[
        "builder",
        "designer",
        "custom"
    ],
    "wof:name":"Ambrose Furniture Manufacturers",
    "wof:placetype":"venue"
},
  "geometry": {"coordinates":[153.12725830100001,-27.6309013367],"type":"Point"}
}