{
  "type": "Feature",
  "properties": {
    "iso:country":"AU",
    "sg:address":"86 Bells Rd",
    "sg:city":"Glengowrie",
    "sg:classifiers":[
        {
            "category":"Professional",
            "subcategory":"Art Services",
            "type":"Services"
        }
    ],
    "sg:phone":"+61 8 8294 7607",
    "sg:postcode":"5044",
    "sg:province":"SA",
    "sg:tags":[
        "decorator",
        "painter"
    ],
    "wof:name":"Farmer R B & P S",
    "wof:placetype":"venue"
},
  "geometry": {"coordinates":[138.536713,-34.99099],"type":"Point"}
}