{
  "type": "Feature",
  "properties": {
    "iso:country":"AU",
    "sg:address":"Ste 607/ 1 Princess St",
    "sg:city":"Kew",
    "sg:classifiers":[
        {
            "category":"Personal",
            "subcategory":"Beauty Salon",
            "type":"Services"
        }
    ],
    "sg:phone":"+61 1300 660 607",
    "sg:postcode":"3101",
    "sg:province":"VIC",
    "wof:name":"Instant Laser Clinic",
    "wof:placetype":"venue"
},
  "geometry": {"coordinates":[145.028762817,-37.8073196411],"type":"Point"}
}