{
  "type": "Feature",
  "properties": {
    "addr:full":"5 Yowie Ave Caringbah NSW 2229",
    "addr:housenumber":"5",
    "addr:postcode":"2229",
    "addr:street":"Yowie Ave",
    "iso:country":"AU",
    "sg:address":"5 Yowie Ave",
    "sg:city":"Caringbah",
    "sg:classifiers":[
        {
            "category":"Building & Trades",
            "subcategory":"Plumbing",
            "type":"Services"
        }
    ],
    "sg:phone":"+61 2 9524 8105",
    "sg:postcode":"2229",
    "sg:province":"NSW",
    "sg:tags":[
        "plumber",
        "gasfitters"
    ],
    "wof:name":"Fleming Plumbing",
    "wof:placetype":"venue"
},
  "geometry": {"coordinates":[151.11456298799999,-34.0496101379],"type":"Point"}
}