{
  "type": "Feature",
  "properties": {
    "addr:full":"Lot 23 Brockman St Pemberton WA 6260",
    "addr:postcode":"6260",
    "addr:street":"Brockman St",
    "iso:country":"AU",
    "sg:address":"Lot 23 Brockman St",
    "sg:city":"Pemberton",
    "sg:classifiers":[
        {
            "category":"Autos & Motor Vehicles",
            "subcategory":"Fuel & Gas Station",
            "type":"Retail Goods"
        }
    ],
    "sg:phone":"+61 8 9776 1087",
    "sg:postcode":"6260",
    "sg:province":"WA",
    "wof:name":"Central Service Station",
    "wof:placetype":"venue"
},
  "geometry": {"coordinates":[116.031517029,-34.4464569092],"type":"Point"}
}