{
  "type": "Feature",
  "properties": {
    "addr:full":"14 Roberts Ave Hoppers Crossing VIC 3029",
    "addr:housenumber":"14",
    "addr:postcode":"3029",
    "addr:street":"Roberts Ave",
    "iso:country":"AU",
    "sg:address":"14 Roberts Ave",
    "sg:city":"Hoppers Crossing",
    "sg:classifiers":[
        {
            "category":"Personal",
            "subcategory":"Beauty Salon",
            "type":"Services"
        }
    ],
    "sg:phone":"+61 3 9748 3368",
    "sg:postcode":"3029",
    "sg:province":"VIC",
    "wof:name":"The Beauty House",
    "wof:placetype":"venue"
},
  "geometry": {"coordinates":[144.70100400000001,-37.869839],"type":"Point"}
}