{
  "type": "Feature",
  "properties": {
    "addr:full":"2/ 31 Brabyn St Windsor NSW 2756",
    "addr:housenumber":"/ 31",
    "addr:postcode":"2756",
    "addr:street":"Brabyn St",
    "iso:country":"AU",
    "sg:address":"2/ 31 Brabyn St",
    "sg:city":"Windsor",
    "sg:classifiers":[
        {
            "category":"Fast Food",
            "type":"Food & Drink"
        }
    ],
    "sg:phone":"+61 2 4570 8844",
    "sg:postcode":"2756",
    "sg:province":"NSW",
    "sg:tags":[
        "away",
        "take"
    ],
    "wof:name":"Domino's Pizza",
    "wof:placetype":"venue"
},
  "geometry": {"coordinates":[150.81260681099999,-33.6137771606],"type":"Point"}
}