{
  "type": "Feature",
  "properties": {
    "addr:full":"150 Beaconsfield-Emerald Rd Beaconsfield Upper VIC 3808",
    "addr:housenumber":"150",
    "addr:postcode":"3808",
    "addr:street":"Beaconsfield-Emerald Rd",
    "iso:country":"AU",
    "sg:address":"150 Beaconsfield-Emerald Rd",
    "sg:city":"Beaconsfield Upper",
    "sg:classifiers":[
        {
            "category":"Health Services",
            "subcategory":"Health Practitioner",
            "type":"Services"
        }
    ],
    "sg:phone":"+61 3 5944 3123",
    "sg:postcode":"3808",
    "sg:province":"VIC",
    "sg:tags":[
        "alternative"
    ],
    "wof:name":"Lakeview Healing Centre",
    "wof:placetype":"venue"
},
  "geometry": {"coordinates":[145.45869400000001,-37.979755],"type":"Point"}
}