{
  "type": "Feature",
  "properties": {
    "addr:full":"Wallaroo St Dunedoo NSW 2844",
    "addr:postcode":"2844",
    "addr:street":"Wallaroo St",
    "iso:country":"AU",
    "sg:address":"Wallaroo St",
    "sg:city":"Dunedoo",
    "sg:classifiers":[
        {
            "category":"Travel",
            "subcategory":"Hostel",
            "type":"Entertainment"
        }
    ],
    "sg:phone":"+61 2 6375 1477",
    "sg:postcode":"2844",
    "sg:province":"NSW",
    "sg:tags":[
        "home"
    ],
    "wof:name":"Dunedoo Mendooran Age Hostel",
    "wof:placetype":"venue"
},
  "geometry": {"coordinates":[149.39819299999999,-32.016487],"type":"Point"}
}