{
  "type": "Feature",
  "properties": {
    "addr:full":"1/ 13 Eramosa Rd West Somerville VIC 3912",
    "addr:housenumber":"/ 13",
    "addr:postcode":"3912",
    "addr:street":"Eramosa Rd",
    "iso:country":"AU",
    "sg:address":"1/ 13 Eramosa Rd",
    "sg:city":"West Somerville",
    "sg:classifiers":[
        {
            "category":"Real Estate",
            "subcategory":"Real Estate Agent",
            "type":"Services"
        }
    ],
    "sg:phone":"+61 3 5973 1111",
    "sg:postcode":"3912",
    "sg:province":"VIC",
    "wof:name":"MPRE",
    "wof:placetype":"venue"
},
  "geometry": {"coordinates":[145.17327880900001,-38.2234573364],"type":"Point"}
}