{
  "type": "Feature",
  "properties": {
    "iso:country":"AU",
    "sg:address":"134 Victoria St",
    "sg:city":"Mackay",
    "sg:classifiers":[
        {
            "category":"Retail",
            "subcategory":"Event Space",
            "type":"Services"
        }
    ],
    "sg:phone":"+61 7 4957 5225",
    "sg:postcode":"4740",
    "sg:province":"QLD",
    "sg:tags":[
        "tab's"
    ],
    "wof:name":"T.A.B.",
    "wof:placetype":"venue"
},
  "geometry": {"coordinates":[149.185226,-21.140928],"type":"Point"}
}