{
  "type": "Feature",
  "properties": {
    "addr:full":"\"Kooringa Park\" 48 Schulzs Rd Coolana QLD 4311",
    "addr:housenumber":"48",
    "addr:postcode":"4311",
    "addr:street":"Schulzs Rd",
    "iso:country":"AU",
    "sg:address":"\"Kooringa Park\" 48 Schulzs Rd",
    "sg:city":"Coolana",
    "sg:classifiers":[
        {
            "category":"Farming",
            "subcategory":"Farm & Veterinary Services",
            "type":"Manufacturing & Wholesale Goods"
        }
    ],
    "sg:phone":"+61 7 5426 8276",
    "sg:postcode":"4311",
    "sg:province":"QLD",
    "sg:tags":[
        "blacksmith",
        "farrier"
    ],
    "wof:name":"Australian Farriers & Blacksmiths Association Queensland",
    "wof:placetype":"venue"
},
  "geometry": {"coordinates":[152.53724670400001,-27.5156707764],"type":"Point"}
}