{
  "type": "Feature",
  "properties": {
    "addr:full":"Suite 6, 20- 24 Castlereagh St Penrith NSW 2740",
    "addr:housenumber":"20 24",
    "addr:postcode":"2740",
    "addr:street":"Castlereagh St",
    "iso:country":"AU",
    "sg:address":"Suite 6, 20- 24 Castlereagh St",
    "sg:city":"Penrith",
    "sg:classifiers":[
        {
            "category":"Banks & Credit Unions",
            "subcategory":"Financial Services",
            "type":"Services"
        }
    ],
    "sg:phone":"+61 2 4722 5112",
    "sg:postcode":"2740",
    "sg:province":"NSW",
    "sg:tags":[
        "planning"
    ],
    "wof:name":"WB & MT Bowler Pty Ltd",
    "wof:placetype":"venue"
},
  "geometry": {"coordinates":[150.69914199999999,-33.754959],"type":"Point"}
}