{
  "type": "Feature",
  "properties": {
    "iso:country":"AU",
    "sg:address":"17 Fern St",
    "sg:city":"Gerringong",
    "sg:classifiers":[
        {
            "category":"Utilities",
            "type":"Services"
        }
    ],
    "sg:phone":"+61 408 420 655",
    "sg:postcode":"2534",
    "sg:province":"NSW",
    "sg:tags":[
        "refrigeration",
        "industrial",
        "commercial",
        "retail"
    ],
    "wof:name":"Connerty Murray",
    "wof:placetype":"venue"
},
  "geometry": {"coordinates":[150.826904297,-34.7386703491],"type":"Point"}
}