{
  "type": "Feature",
  "properties": {
    "addr:full":"65 Laura St Clontarf QLD 4019",
    "addr:housenumber":"65",
    "addr:postcode":"4019",
    "addr:street":"Laura St",
    "iso:country":"AU",
    "sg:address":"65 Laura St",
    "sg:city":"Clontarf",
    "sg:classifiers":[
        {
            "category":"Food & Beverages",
            "subcategory":"Groceries & Convenience Stores",
            "type":"Retail Goods"
        }
    ],
    "sg:phone":"+61 7 3283 3767",
    "sg:postcode":"4019",
    "sg:province":"QLD",
    "wof:name":"Cathy's Corner Store",
    "wof:placetype":"venue"
},
  "geometry": {"coordinates":[153.087799072,-27.2518920898],"type":"Point"}
}