{
  "type": "Feature",
  "properties": {
    "addr:full":"33 Ireland St West Melbourne VIC 3003",
    "addr:housenumber":"33",
    "addr:postcode":"3003",
    "addr:street":"Ireland St",
    "iso:country":"AU",
    "sg:address":"33 Ireland St",
    "sg:city":"West Melbourne",
    "sg:classifiers":[
        {
            "category":"Personal",
            "type":"Services"
        }
    ],
    "sg:phone":"+61 3 9329 1665",
    "sg:postcode":"3003",
    "sg:province":"VIC",
    "sg:tags":[
        "gift"
    ],
    "wof:name":"Ripple Products Pty Ltd",
    "wof:placetype":"venue"
},
  "geometry": {"coordinates":[144.94493102999999,-37.807598114],"type":"Point"}
}