{
  "type": "Feature",
  "properties": {
    "addr:full":"Shop 3, 26 Baynes St Margate QLD 4019",
    "addr:housenumber":"shop;26",
    "addr:postcode":"4019",
    "addr:street":"Baynes St",
    "iso:country":"AU",
    "sg:address":"Shop 3, 26 Baynes St",
    "sg:city":"Margate",
    "sg:classifiers":[
        {
            "category":"Personal",
            "subcategory":"Beauty Salon",
            "type":"Services"
        }
    ],
    "sg:phone":"+61 7 3883 1414",
    "sg:postcode":"4019",
    "sg:province":"QLD",
    "sg:tags":[
        "hairdresser"
    ],
    "wof:name":"Silhouette Hair Design",
    "wof:placetype":"venue"
},
  "geometry": {"coordinates":[153.108154297,-27.243812561],"type":"Point"}
}