{
  "type": "Feature",
  "properties": {
    "addr:full":"3 Ross St Lennox Head NSW 2478",
    "addr:housenumber":"3",
    "addr:postcode":"2478",
    "addr:street":"Ross St",
    "iso:country":"AU",
    "sg:address":"3 Ross St",
    "sg:city":"Lennox Head",
    "sg:classifiers":[
        {
            "category":"Health Services",
            "subcategory":"Doctor",
            "type":"Services"
        }
    ],
    "sg:phone":"+61 2 6687 7636",
    "sg:postcode":"2478",
    "sg:province":"NSW",
    "sg:tags":[
        "reflexology"
    ],
    "wof:name":"Graeme Dicker",
    "wof:placetype":"venue"
},
  "geometry": {"coordinates":[153.59254455600001,-28.7865524292],"type":"Point"}
}