{
  "type": "Feature",
  "properties": {
    "addr:full":"2 Ghersi Ave Wamberal NSW 2260",
    "addr:housenumber":"2",
    "addr:postcode":"2260",
    "addr:street":"Ghersi Ave",
    "iso:country":"AU",
    "sg:address":"2 Ghersi Ave",
    "sg:city":"Wamberal",
    "sg:classifiers":[
        {
            "category":"Communications",
            "subcategory":"Film & Video Production",
            "type":"Services"
        }
    ],
    "sg:phone":"+61 2 4384 5980",
    "sg:postcode":"2260",
    "sg:province":"NSW",
    "sg:tags":[
        "dvd",
        "library"
    ],
    "wof:name":"Local Video",
    "wof:placetype":"venue"
},
  "geometry": {"coordinates":[151.437927,-33.423145],"type":"Point"}
}