{
  "type": "Feature",
  "properties": {
    "iso:country":"AU",
    "sg:address":"Factory 19, Cave Hill Industrial Gardens, Cave Hill Rd",
    "sg:city":"Lilydale",
    "sg:classifiers":[
        {
            "category":"Farming",
            "subcategory":"Farm & Veterinary Services",
            "type":"Manufacturing & Wholesale Goods"
        }
    ],
    "sg:phone":"+61 3 9735 9077",
    "sg:postcode":"3140",
    "sg:province":"VIC",
    "sg:tags":[
        "irrigation",
        "reticulation",
        "system"
    ],
    "wof:name":"Chapman & Rivett (VIC) Pty Ltd",
    "wof:placetype":"venue"
},
  "geometry": {"coordinates":[145.34283447300001,-37.7578964233],"type":"Point"}
}