{
  "type": "Feature",
  "properties": {
    "addr:full":"2 Yan Yean St Beenleigh QLD 4207",
    "addr:housenumber":"2",
    "addr:postcode":"4207",
    "addr:street":"Yan Yean St",
    "iso:country":"AU",
    "sg:address":"2 Yan Yean St",
    "sg:city":"Beenleigh",
    "sg:classifiers":[
        {
            "category":"Health Services",
            "subcategory":"Clinic",
            "type":"Services"
        }
    ],
    "sg:phone":"+61 7 3287 1543",
    "sg:postcode":"4207",
    "sg:province":"QLD",
    "sg:tags":[
        "aromatherapy"
    ],
    "wof:name":"Lazy Lizard Products",
    "wof:placetype":"venue"
},
  "geometry": {"coordinates":[153.189941406,-27.7257976532],"type":"Point"}
}