{
  "type": "Feature",
  "properties": {
    "addr:full":"76 Harcourt Pde Rosebery NSW 2018",
    "addr:housenumber":"76",
    "addr:postcode":"2018",
    "addr:street":"Harcourt Pde",
    "iso:country":"AU",
    "sg:address":"76 Harcourt Pde",
    "sg:city":"Rosebery",
    "sg:classifiers":[
        {
            "category":"Utilities",
            "subcategory":"Refuse",
            "type":"Services"
        }
    ],
    "sg:phone":"+61 411 361 865",
    "sg:postcode":"2018",
    "sg:province":"NSW",
    "sg:tags":[
        "remover",
        "rubbish"
    ],
    "wof:name":"Clean &#039;N&#039; Go Rubbish Removal",
    "wof:placetype":"venue"
},
  "geometry": {"coordinates":[151.206176758,-33.9206161499],"type":"Point"}
}