{
  "type": "Feature",
  "properties": {
    "addr:full":"1-3 Geddes St Mulgrave VIC 3170",
    "addr:housenumber":"1-3",
    "addr:postcode":"3170",
    "addr:street":"Geddes St",
    "iso:country":"AU",
    "sg:address":"1-3 Geddes St",
    "sg:city":"Mulgrave",
    "sg:classifiers":[
        {
            "category":"Arts & Performance",
            "subcategory":"Art Gallery",
            "type":"Entertainment"
        }
    ],
    "sg:phone":"+61 3 9560 1788",
    "sg:postcode":"3170",
    "sg:province":"VIC",
    "sg:tags":[
        "aboriginal",
        "craft"
    ],
    "wof:name":"Nucolorvue Productions Pty Ltd",
    "wof:placetype":"venue"
},
  "geometry": {"coordinates":[145.15609741200001,-37.9068260193],"type":"Point"}
}