{
  "type": "Feature",
  "properties": {
    "addr:full":"Shop 38 Capalaba Shopping Centre Capalaba QLD 4157",
    "addr:housenumber":"shop 38",
    "addr:postcode":"4157",
    "iso:country":"AU",
    "sg:address":"Shop 38 Capalaba Shopping Centre",
    "sg:city":"Capalaba",
    "sg:classifiers":[
        {
            "category":"Shopping",
            "subcategory":"Clothing, Apparel, & Fashions",
            "type":"Retail Goods"
        }
    ],
    "sg:phone":"+61 7 3390 1844",
    "sg:postcode":"4157",
    "sg:province":"QLD",
    "sg:tags":[
        "lady",
        "wear"
    ],
    "wof:name":"Jacqui E",
    "wof:placetype":"venue"
},
  "geometry": {"coordinates":[153.21090698200001,-27.5379695892],"type":"Point"}
}