{
  "type": "Feature",
  "properties": {
    "iso:country":"AU",
    "sg:address":"55 Surrey St",
    "sg:city":"Nundah",
    "sg:classifiers":[
        {
            "category":"Building & Trades",
            "subcategory":"Construction",
            "type":"Services"
        }
    ],
    "sg:phone":"+61 7 3256 8566",
    "sg:postcode":"4012",
    "sg:province":"QLD",
    "sg:tags":[
        "installation",
        "air conditioning"
    ],
    "wof:name":"Cresdee & Co.",
    "wof:placetype":"venue"
},
  "geometry": {"coordinates":[153.062942505,-27.3953781128],"type":"Point"}
}