{
  "type": "Feature",
  "properties": {
    "addr:full":"1/ 9 Commercial Drv Ashmore QLD 4214",
    "addr:housenumber":"/ 9",
    "addr:postcode":"4214",
    "addr:street":"Commercial Drv",
    "iso:country":"AU",
    "sg:address":"1/ 9 Commercial Drv",
    "sg:city":"Ashmore",
    "sg:classifiers":[
        {
            "category":"Retail",
            "subcategory":"Repair Shop",
            "type":"Services"
        }
    ],
    "sg:phone":"+61 7 5532 1080",
    "sg:postcode":"4214",
    "sg:province":"QLD",
    "sg:tags":[
        "cleaner",
        "part",
        "vacuum"
    ],
    "wof:name":"Appliance Repair Centre",
    "wof:placetype":"venue"
},
  "geometry": {"coordinates":[153.39019775400001,-27.9803733826],"type":"Point"}
}