{
  "type": "Feature",
  "properties": {
    "iso:country":"AU",
    "sg:address":"PO Box 4020",
    "sg:city":"Lake Haven",
    "sg:classifiers":[
        {
            "category":"Professional",
            "subcategory":"Accounting & Tax Preparation",
            "type":"Services"
        }
    ],
    "sg:phone":"+61 408 246 681",
    "sg:postcode":"2263",
    "sg:province":"NSW",
    "sg:tags":[
        "consultant",
        "taxation"
    ],
    "wof:name":"Ring-A-Refund",
    "wof:placetype":"venue"
},
  "geometry": {"coordinates":[151.500137,-33.243938],"type":"Point"}
}