{
  "type": "Feature",
  "properties": {
    "addr:full":"55 Burgess St Bicheno TAS 7215",
    "addr:housenumber":"55",
    "addr:postcode":"7215",
    "addr:street":"Burgess St",
    "iso:country":"AU",
    "sg:address":"55 Burgess St",
    "sg:city":"Bicheno",
    "sg:classifiers":[
        {
            "category":"Cafe",
            "type":"Food & Drink"
        }
    ],
    "sg:phone":"+61 3 6375 1972",
    "sg:postcode":"7215",
    "sg:province":"TAS",
    "wof:name":"Blue Edge Bakery Bicheno",
    "wof:placetype":"venue"
},
  "geometry": {"coordinates":[148.30418399999999,-41.875877],"type":"Point"}
}