{
  "type": "Feature",
  "properties": {
    "iso:country":"AU",
    "sg:address":"80 Beacon Pt Rd",
    "sg:city":"Clifton Springs",
    "sg:classifiers":[
        {
            "category":"Building & Trades",
            "subcategory":"Plumbing",
            "type":"Services"
        }
    ],
    "sg:phone":"+61 3 5253 2744",
    "sg:postcode":"3222",
    "sg:province":"VIC",
    "sg:tags":[
        "plumber",
        "gasfitters"
    ],
    "wof:name":"C A & D J Trewin",
    "wof:placetype":"venue"
},
  "geometry": {"coordinates":[144.57382200000001,-38.157562],"type":"Point"}
}