{
  "type": "Feature",
  "properties": {
    "addr:full":"111d Goodwood Rd Goodwood SA 5034",
    "addr:housenumber":"111d",
    "addr:postcode":"5034",
    "addr:street":"Goodwood Rd",
    "iso:country":"AU",
    "sg:address":"111d Goodwood Rd",
    "sg:city":"Goodwood",
    "sg:classifiers":[
        {
            "category":"Personal",
            "subcategory":"Beauty Salon",
            "type":"Services"
        }
    ],
    "sg:phone":"+61 8 8357 8882",
    "sg:postcode":"5034",
    "sg:province":"SA",
    "sg:tags":[
        "hairdresser"
    ],
    "wof:name":"Top Notch Haircutters",
    "wof:placetype":"venue"
},
  "geometry": {"coordinates":[138.58979797399999,-34.9513893127],"type":"Point"}
}