{
  "type": "Feature",
  "properties": {
    "addr:full":"513 Old Cleveland Rd Birkdale QLD 4159",
    "addr:housenumber":"513",
    "addr:postcode":"4159",
    "addr:street":"Old Cleveland Rd",
    "iso:country":"AU",
    "sg:address":"513 Old Cleveland Rd",
    "sg:city":"Birkdale",
    "sg:classifiers":[
        {
            "category":"Health Services",
            "subcategory":"Health Practitioner",
            "type":"Services"
        }
    ],
    "sg:phone":"+61 7 3822 9944",
    "sg:postcode":"4159",
    "sg:province":"QLD",
    "sg:tags":[
        "physiotherapist"
    ],
    "wof:name":"Driver Stephan",
    "wof:placetype":"venue"
},
  "geometry": {"coordinates":[153.21966552699999,-27.5067806244],"type":"Point"}
}