{
  "type": "Feature",
  "properties": {
    "iso:country":"AU",
    "sg:address":"212 Oxford St",
    "sg:city":"Paddington",
    "sg:classifiers":[
        {
            "category":"Cafe",
            "type":"Food & Drink"
        }
    ],
    "sg:phone":"+61 2 9380 5554",
    "sg:postcode":"2021",
    "sg:province":"NSW",
    "wof:name":"Red Rock Cafe & Thai Restaurant",
    "wof:placetype":"venue"
},
  "geometry": {"coordinates":[151.22528076200001,-33.8847618103],"type":"Point"}
}