{
  "type": "Feature",
  "properties": {
    "addr:full":"20 - 22 Ronald Crt Bohle QLD 4818",
    "addr:housenumber":"22",
    "addr:postcode":"4818",
    "addr:street":"Ronald Crt",
    "iso:country":"AU",
    "sg:address":"20 - 22 Ronald Crt",
    "sg:city":"Bohle",
    "sg:classifiers":[
        {
            "category":"Commercial Area",
            "type":"Public Place"
        }
    ],
    "sg:phone":"+61 7 4774 8119",
    "sg:postcode":"4818",
    "sg:province":"QLD",
    "sg:tags":[
        "heavy",
        "carrier"
    ],
    "wof:name":"Simon National Carriers",
    "wof:placetype":"venue"
},
  "geometry": {"coordinates":[146.731628,-19.263115],"type":"Point"}
}