{
  "type": "Feature",
  "properties": {
    "addr:full":"294 Marion Rd North Plympton SA 5037",
    "addr:housenumber":"294",
    "addr:postcode":"5037",
    "addr:street":"Marion Rd",
    "iso:country":"AU",
    "sg:address":"294 Marion Rd",
    "sg:city":"North Plympton",
    "sg:classifiers":[
        {
            "category":"Autos & Motor Vehicles",
            "subcategory":"Fuel & Gas Station",
            "type":"Retail Goods"
        }
    ],
    "sg:phone":"+61 8 8351 0511",
    "sg:postcode":"5037",
    "sg:province":"SA",
    "wof:name":"Ampol",
    "wof:placetype":"venue"
},
  "geometry": {"coordinates":[138.55372619600001,-34.9513816833],"type":"Point"}
}