{
  "type": "Feature",
  "properties": {
    "addr:full":"Suite 1 Level 2 North Tower 1-5 Railway St Chatswood NSW 2067",
    "addr:housenumber":"1-5",
    "addr:postcode":"2067",
    "addr:street":"Railway St",
    "iso:country":"AU",
    "sg:address":"Suite 1 Level 2 North Tower 1-5 Railway St",
    "sg:city":"Chatswood",
    "sg:classifiers":[
        {
            "category":"Education",
            "subcategory":"Special Training",
            "type":"Public Place"
        }
    ],
    "sg:phone":"+61 2 9411 1841",
    "sg:postcode":"2067",
    "sg:province":"NSW",
    "sg:tags":[
        "development"
    ],
    "wof:name":"Management Development Institute The",
    "wof:placetype":"venue"
},
  "geometry": {"coordinates":[151.18046569800001,-33.7945022583],"type":"Point"}
}