{
  "type": "Feature",
  "properties": {
    "addr:full":"17 Keymer St Ascot WA 6104",
    "addr:housenumber":"17",
    "addr:postcode":"6104",
    "addr:street":"Keymer St",
    "iso:country":"AU",
    "sg:address":"17 Keymer St",
    "sg:city":"Ascot",
    "sg:classifiers":[
        {
            "category":"Retail",
            "subcategory":"Veterinary Services",
            "type":"Services"
        }
    ],
    "sg:phone":"+61 8 9478 4029",
    "sg:postcode":"6104",
    "sg:province":"WA",
    "sg:tags":[
        "surgeon"
    ],
    "wof:name":"Ahern Tom",
    "wof:placetype":"venue"
},
  "geometry": {"coordinates":[115.928260803,-31.937002182],"type":"Point"}
}