{
  "type": "Feature",
  "properties": {
    "addr:full":"35 Carmichael St Hamilton VIC 3300",
    "addr:housenumber":"35",
    "addr:postcode":"3300",
    "addr:street":"Carmichael St",
    "iso:country":"AU",
    "sg:address":"35 Carmichael St",
    "sg:city":"Hamilton",
    "sg:classifiers":[
        {
            "category":"Professional",
            "subcategory":"Art Services",
            "type":"Services"
        }
    ],
    "sg:phone":"+61 3 5572 2851",
    "sg:postcode":"3300",
    "sg:province":"VIC",
    "wof:name":"Elizabeth Arthur Fine Art Gallery & Sculpture Garden",
    "wof:placetype":"venue"
},
  "geometry": {"coordinates":[142.01646423299999,-37.7468986511],"type":"Point"}
}