{
  "type": "Feature",
  "properties": {
    "addr:full":"12 Gregory St Sandy Bay TAS 7005",
    "addr:housenumber":"12",
    "addr:postcode":"7005",
    "addr:street":"Gregory St",
    "iso:country":"AU",
    "sg:address":"12 Gregory St",
    "sg:city":"Sandy Bay",
    "sg:classifiers":[
        {
            "category":"Health Services",
            "subcategory":"Doctor",
            "type":"Services"
        }
    ],
    "sg:phone":"+61 3 6224 8920",
    "sg:postcode":"7005",
    "sg:province":"TAS",
    "sg:tags":[
        "podiatrist"
    ],
    "wof:name":"Hemmings David",
    "wof:placetype":"venue"
},
  "geometry": {"coordinates":[147.326568603,-42.8956680298],"type":"Point"}
}