{
  "type": "Feature",
  "properties": {
    "addr:full":"Quick St Ainslie ACT 2602",
    "addr:postcode":"2602",
    "addr:street":"St",
    "iso:country":"AU",
    "sg:address":"Quick St",
    "sg:city":"Ainslie",
    "sg:classifiers":[
        {
            "category":"Retail",
            "subcategory":"Auto Rental",
            "type":"Services"
        }
    ],
    "sg:phone":"+61 2 6247 3601",
    "sg:postcode":"2602",
    "sg:province":"ACT",
    "sg:tags":[
        "car",
        "hire",
        "minibus"
    ],
    "wof:name":"C.W.C. Auto Services",
    "wof:placetype":"venue"
},
  "geometry": {"coordinates":[149.14556884800001,-35.2742233276],"type":"Point"}
}