{
  "type": "Feature",
  "properties": {
    "iso:country":"AU",
    "sg:address":"Unit 3/13- 15 Wollongong Rd",
    "sg:city":"Arncliffe",
    "sg:classifiers":[
        {
            "category":"Utilities",
            "subcategory":"Electric",
            "type":"Services"
        }
    ],
    "sg:phone":"+61 2 9599 3885",
    "sg:postcode":"2205",
    "sg:province":"NSW",
    "sg:tags":[
        "electrical",
        "contractor"
    ],
    "wof:name":"Palmer R W Electrical Service Pty Ltd",
    "wof:placetype":"venue"
},
  "geometry": {"coordinates":[151.147964,-33.933784],"type":"Point"}
}