{
  "type": "Feature",
  "properties": {
    "addr:full":"Unit 2/ 24-28 Glennie St Gosford North NSW 2250",
    "addr:housenumber":"/ 24-28",
    "addr:postcode":"2250",
    "addr:street":"Glennie St",
    "iso:country":"AU",
    "sg:address":"Unit 2/ 24-28 Glennie St",
    "sg:city":"Gosford North",
    "sg:classifiers":[
        {
            "category":"Building & Trades",
            "subcategory":"Pest Control",
            "type":"Services"
        }
    ],
    "sg:phone":"+61 2 4323 9111",
    "sg:postcode":"2250",
    "sg:province":"NSW",
    "wof:name":"Pro Master Pest Control",
    "wof:placetype":"venue"
},
  "geometry": {"coordinates":[151.34645080600001,-33.4124488831],"type":"Point"}
}