{
  "type": "Feature",
  "properties": {
    "iso:country":"AU",
    "sg:address":"1 Barloa Rd",
    "sg:city":"Mont Albert",
    "sg:classifiers":[
        {
            "category":"Mining & Drilling",
            "type":"Manufacturing & Wholesale Goods"
        }
    ],
    "sg:phone":"+61 3 9890 2368",
    "sg:postcode":"3127",
    "sg:province":"VIC",
    "sg:tags":[
        "geologist"
    ],
    "wof:name":"Couper J K & G M",
    "wof:placetype":"venue"
},
  "geometry": {"coordinates":[145.10194397000001,-37.8151054382],"type":"Point"}
}