{
  "type": "Feature",
  "properties": {
    "addr:full":"61 East Pde Sutherland NSW 2232",
    "addr:housenumber":"61",
    "addr:postcode":"2232",
    "addr:street":"East Pde",
    "iso:country":"AU",
    "sg:address":"61 East Pde",
    "sg:city":"Sutherland",
    "sg:classifiers":[
        {
            "category":"Shopping",
            "subcategory":"Pets & Pet Supplies",
            "type":"Retail Goods"
        }
    ],
    "sg:phone":"+61 2 9545 0122",
    "sg:postcode":"2232",
    "sg:province":"NSW",
    "sg:tags":[
        "food"
    ],
    "wof:name":"Pets Force",
    "wof:placetype":"venue"
},
  "geometry": {"coordinates":[151.05601501500001,-34.0324554443],"type":"Point"}
}