{
  "type": "Feature",
  "properties": {
    "addr:full":"Unit 5/ 12 William St Cavan SA 5094",
    "addr:housenumber":"12",
    "addr:postcode":"5094",
    "addr:street":"William St",
    "iso:country":"AU",
    "sg:address":"Unit 5/ 12 William St",
    "sg:city":"Cavan",
    "sg:classifiers":[
        {
            "category":"Retail",
            "subcategory":"Auto Repair",
            "type":"Services"
        }
    ],
    "sg:phone":"+61 418 899 907",
    "sg:postcode":"5094",
    "sg:province":"SA",
    "sg:tags":[
        "repairer",
        "motor",
        "engineer"
    ],
    "wof:name":"Velocity Sports Cars",
    "wof:placetype":"venue"
},
  "geometry": {"coordinates":[138.60032653799999,-34.8296470642],"type":"Point"}
}