{
  "type": "Feature",
  "properties": {
    "addr:full":"164 Middleborough Rd Blackburn South VIC 3130",
    "addr:housenumber":"164",
    "addr:postcode":"3130",
    "addr:street":"Middleborough Rd",
    "iso:country":"AU",
    "sg:address":"164 Middleborough Rd",
    "sg:city":"Blackburn South",
    "sg:classifiers":[
        {
            "category":"Health Services",
            "subcategory":"Health Practitioner",
            "type":"Services"
        }
    ],
    "sg:phone":"+61 3 9899 8300",
    "sg:postcode":"3130",
    "sg:province":"VIC",
    "sg:tags":[
        "physiotherapist"
    ],
    "wof:name":"McRae Catherine",
    "wof:placetype":"venue"
},
  "geometry": {"coordinates":[145.134307861,-37.8422355652],"type":"Point"}
}