{
  "type": "Feature",
  "properties": {
    "addr:full":"Penrice Rd Nuriootpa SA 5355",
    "addr:postcode":"5355",
    "addr:street":"Penrice Rd",
    "iso:country":"AU",
    "sg:address":"Penrice Rd",
    "sg:city":"Nuriootpa",
    "sg:classifiers":[
        {
            "category":"Education",
            "subcategory":"School",
            "type":"Public Place"
        }
    ],
    "sg:phone":"+61 8 8562 2022",
    "sg:postcode":"5355",
    "sg:province":"SA",
    "sg:tags":[
        "state",
        "except",
        "nsw"
    ],
    "wof:name":"Nuriootpa High School",
    "wof:placetype":"venue"
},
  "geometry": {"coordinates":[138.99848938,-34.4686279297],"type":"Point"}
}