{
  "type": "Feature",
  "properties": {
    "addr:full":"22 Bambra St Mt Eliza VIC 3930",
    "addr:housenumber":"22",
    "addr:postcode":"3930",
    "addr:street":"Bambra St",
    "iso:country":"AU",
    "sg:address":"22 Bambra St",
    "sg:city":"Mt Eliza",
    "sg:classifiers":[
        {
            "category":"Professional",
            "subcategory":"Business Services",
            "type":"Services"
        }
    ],
    "sg:phone":"+61 3 9775 3800",
    "sg:postcode":"3930",
    "sg:province":"VIC",
    "sg:tags":[
        "fashion",
        "agent"
    ],
    "wof:name":"Curnow Agency Pty Ltd",
    "wof:placetype":"venue"
},
  "geometry": {"coordinates":[145.087814331,-38.1958045959],"type":"Point"}
}