{
  "type": "Feature",
  "properties": {
    "addr:full":"42 Berwick St Fortitude Valley QLD 4006",
    "addr:housenumber":"42",
    "addr:postcode":"4006",
    "addr:street":"Berwick St",
    "iso:country":"AU",
    "sg:address":"42 Berwick St",
    "sg:city":"Fortitude Valley",
    "sg:classifiers":[
        {
            "category":"Wholesale",
            "subcategory":"Home Furnishings",
            "type":"Manufacturing & Wholesale Goods"
        }
    ],
    "sg:phone":"+61 7 3252 2780",
    "sg:postcode":"4006",
    "sg:province":"QLD",
    "wof:name":"Redelman Fabrics",
    "wof:placetype":"venue"
},
  "geometry": {"coordinates":[153.03689575199999,-27.4588375092],"type":"Point"}
}