{
  "type": "Feature",
  "properties": {
    "addr:full":"56 Mulkarra Drv Chelsea VIC 3196",
    "addr:housenumber":"56",
    "addr:postcode":"3196",
    "addr:street":"Mulkarra Drv",
    "iso:country":"AU",
    "sg:address":"56 Mulkarra Drv",
    "sg:city":"Chelsea",
    "sg:classifiers":[
        {
            "category":"Building & Trades",
            "subcategory":"Plumbing",
            "type":"Services"
        }
    ],
    "sg:phone":"+61 3 9774 3443",
    "sg:postcode":"3196",
    "sg:province":"VIC",
    "sg:tags":[
        "consultant"
    ],
    "wof:name":"J.W.A. Consultants & Associates",
    "wof:placetype":"venue"
},
  "geometry": {"coordinates":[145.128372192,-38.0460662842],"type":"Point"}
}