{
  "type": "Feature",
  "properties": {
    "addr:full":"160 Maudsland Rd null QLD 4210",
    "addr:housenumber":"160",
    "addr:postcode":"4210",
    "addr:street":"Maudsland Rd",
    "iso:country":"AU",
    "sg:address":"160 Maudsland Rd",
    "sg:city":"null",
    "sg:classifiers":[
        {
            "category":"Food & Beverages",
            "subcategory":"Groceries & Convenience Stores",
            "type":"Retail Goods"
        }
    ],
    "sg:phone":"+61 7 5573 2700",
    "sg:postcode":"4210",
    "sg:province":"QLD",
    "wof:name":"BYO Bottleshop",
    "wof:placetype":"venue"
},
  "geometry": {"coordinates":[153.282348633,-27.9140262604],"type":"Point"}
}