{
  "type": "Feature",
  "properties": {
    "iso:country":"AU",
    "sg:address":"320 Invermay Rd",
    "sg:city":"Mowbray",
    "sg:classifiers":[
        {
            "category":"Professional",
            "subcategory":"Detective & Security Services",
            "type":"Services"
        }
    ],
    "sg:phone":"+61 3 6326 7542",
    "sg:postcode":"7248",
    "sg:province":"TAS",
    "sg:tags":[
        "equipment",
        "window",
        "doors"
    ],
    "wof:name":"Statewide Glass",
    "wof:placetype":"venue"
},
  "geometry": {"coordinates":[147.13043212900001,-41.401309967],"type":"Point"}
}