{
  "type": "Feature",
  "properties": {
    "addr:full":"Somerville Centre 144 Smith St Darwin NT 0800",
    "addr:housenumber":"144",
    "addr:postcode":"nt 0800",
    "addr:street":"Smith St",
    "iso:country":"AU",
    "sg:address":"Somerville Centre 144 Smith St",
    "sg:city":"Darwin",
    "sg:classifiers":[
        {
            "category":"Manufacturing",
            "subcategory":"Buildings",
            "type":"Manufacturing & Wholesale Goods"
        }
    ],
    "sg:phone":"+61 1800 800 078",
    "sg:postcode":"0800",
    "sg:province":"NT",
    "sg:tags":[
        "transportable",
        "domestic",
        "relocatable"
    ],
    "wof:name":"Ark Homes",
    "wof:placetype":"venue"
},
  "geometry": {"coordinates":[130.83465576200001,-12.4559688568],"type":"Point"}
}