{
  "type": "Feature",
  "properties": {
    "addr:full":"73 Thomsons Rd Kingsholme QLD 4208",
    "addr:housenumber":"73",
    "addr:postcode":"4208",
    "addr:street":"Thomsons Rd",
    "iso:country":"AU",
    "sg:address":"73 Thomsons Rd",
    "sg:city":"Kingsholme",
    "sg:classifiers":[
        {
            "category":"Building & Trades",
            "subcategory":"Construction",
            "type":"Services"
        }
    ],
    "sg:phone":"+61 7 5547 6111",
    "sg:postcode":"4208",
    "sg:province":"QLD",
    "sg:tags":[
        "earth",
        "excavating",
        "moving",
        "contractor"
    ],
    "wof:name":"Caswell Civil & Landscape",
    "wof:placetype":"venue"
},
  "geometry": {"coordinates":[153.24104309099999,-27.8156929016],"type":"Point"}
}