{
  "type": "Feature",
  "properties": {
    "addr:full":"14 Henstock Rd Arcadia NSW 2159",
    "addr:housenumber":"14",
    "addr:postcode":"2159",
    "addr:street":"Henstock Rd",
    "iso:country":"AU",
    "sg:address":"14 Henstock Rd",
    "sg:city":"Arcadia",
    "sg:classifiers":[
        {
            "category":"Professional",
            "subcategory":"Engineering",
            "type":"Services"
        }
    ],
    "sg:phone":"+61 2 9621 7000",
    "sg:postcode":"2159",
    "sg:province":"NSW",
    "sg:tags":[
        "engineer"
    ],
    "wof:name":"G.A. Watt Engineering",
    "wof:placetype":"venue"
},
  "geometry": {"coordinates":[151.03434753400001,-33.6157493591],"type":"Point"}
}