{
  "type": "Feature",
  "properties": {
    "addr:full":"12 Filbert St Caulfield South VIC 3162",
    "addr:housenumber":"12",
    "addr:postcode":"3162",
    "addr:street":"Filbert St",
    "iso:country":"AU",
    "sg:address":"12 Filbert St",
    "sg:city":"Caulfield South",
    "sg:classifiers":[
        {
            "category":"Professional",
            "subcategory":"Accounting & Tax Preparation",
            "type":"Services"
        }
    ],
    "sg:phone":"+61 3 9505 3329",
    "sg:postcode":"3162",
    "sg:province":"VIC",
    "sg:tags":[
        "bookkeeping"
    ],
    "wof:name":"Figuratively Speaking Bookkeeping Service",
    "wof:placetype":"venue"
},
  "geometry": {"coordinates":[145.02226257300001,-37.890838623],"type":"Point"}
}