{
  "type": "Feature",
  "properties": {
    "addr:full":"2 Guilfoyle Ave Coburg VIC 3058",
    "addr:housenumber":"2",
    "addr:postcode":"3058",
    "addr:street":"Guilfoyle Ave",
    "iso:country":"AU",
    "sg:address":"2 Guilfoyle Ave",
    "sg:city":"Coburg",
    "sg:classifiers":[
        {
            "category":"Wholesale",
            "subcategory":"Furniture",
            "type":"Manufacturing & Wholesale Goods"
        }
    ],
    "sg:phone":"+61 3 9354 7750",
    "sg:postcode":"3058",
    "sg:province":"VIC",
    "sg:tags":[
        "wholesaler",
        "mfrs"
    ],
    "wof:name":"Veneerform Pty Ltd",
    "wof:placetype":"venue"
},
  "geometry": {"coordinates":[144.953689575,-37.7276382446],"type":"Point"}
}