{
  "type": "Feature",
  "properties": {
    "addr:full":"Nabawa Rd Nabawa WA 6532",
    "addr:postcode":"6532",
    "addr:street":"Nabawa Rd",
    "iso:country":"AU",
    "sg:address":"Nabawa Rd",
    "sg:city":"Nabawa",
    "sg:classifiers":[
        {
            "category":"Farming",
            "subcategory":"Farm",
            "type":"Manufacturing & Wholesale Goods"
        }
    ],
    "sg:phone":"+61 8 9920 5010",
    "sg:postcode":"6532",
    "sg:province":"WA",
    "sg:tags":[
        "farmer"
    ],
    "wof:name":"Barnetson G M & E M",
    "wof:placetype":"venue"
},
  "geometry": {"coordinates":[114.832603455,-28.4954376221],"type":"Point"}
}