{
  "type": "Feature",
  "properties": {
    "iso:country":"AU",
    "sg:address":"21 Rooke St",
    "sg:city":"Devonport",
    "sg:classifiers":[
        {
            "category":"Manufacturing",
            "subcategory":"Jewelry",
            "type":"Manufacturing & Wholesale Goods"
        }
    ],
    "sg:phone":"+61 3 6424 1052",
    "sg:postcode":"7310",
    "sg:province":"TAS",
    "sg:tags":[
        "designer",
        "jewellery"
    ],
    "wof:name":"Matthews Jewellers",
    "wof:placetype":"venue"
},
  "geometry": {"coordinates":[146.36021423299999,-41.1809158325],"type":"Point"}
}