{
  "type": "Feature",
  "properties": {
    "addr:full":"797 Port Rd Woodville SA 5011",
    "addr:housenumber":"797",
    "addr:postcode":"5011",
    "addr:street":"Port Rd",
    "iso:country":"AU",
    "sg:address":"797 Port Rd",
    "sg:city":"Woodville",
    "sg:classifiers":[
        {
            "category":"Home & Garden",
            "subcategory":"Building Materials",
            "type":"Retail Goods"
        }
    ],
    "sg:phone":"+61 8 8244 2200",
    "sg:postcode":"5011",
    "sg:province":"SA",
    "sg:tags":[
        "shutter",
        "roller",
        "grille"
    ],
    "wof:name":"Burns For Blinds",
    "wof:placetype":"venue"
},
  "geometry": {"coordinates":[138.53465270999999,-34.8799362183],"type":"Point"}
}