{
  "type": "Feature",
  "properties": {
    "addr:full":"10 Alexanders Rd Morwell VIC 3840",
    "addr:housenumber":"10",
    "addr:postcode":"3840",
    "addr:street":"Alexanders Rd",
    "iso:country":"AU",
    "sg:address":"10 Alexanders Rd",
    "sg:city":"Morwell",
    "sg:classifiers":[
        {
            "category":"Retail",
            "subcategory":"Car Wash",
            "type":"Services"
        }
    ],
    "sg:phone":"+61 3 5134 4141",
    "sg:postcode":"3840",
    "sg:province":"VIC",
    "sg:tags":[
        "truck",
        "cleaning"
    ],
    "wof:name":"Modern Panelworks & Detailing",
    "wof:placetype":"venue"
},
  "geometry": {"coordinates":[146.44140625,-38.2305831909],"type":"Point"}
}