{
  "type": "Feature",
  "properties": {
    "addr:full":"29 Agatha Ave Lake Munmorah NSW 2259",
    "addr:housenumber":"29",
    "addr:postcode":"2259",
    "addr:street":"Agatha Ave",
    "iso:country":"AU",
    "sg:address":"29 Agatha Ave",
    "sg:city":"Lake Munmorah",
    "sg:classifiers":[
        {
            "category":"Utilities",
            "subcategory":"Electric",
            "type":"Services"
        }
    ],
    "sg:phone":"+61 2 4358 3124",
    "sg:postcode":"2259",
    "sg:province":"NSW",
    "sg:tags":[
        "electrical",
        "contractor"
    ],
    "wof:name":"Eastern Seaboard Electrical",
    "wof:placetype":"venue"
},
  "geometry": {"coordinates":[151.57559204099999,-33.19272995],"type":"Point"}
}