{
  "type": "Feature",
  "properties": {
    "addr:full":"43 Clarendon St Cranbourne VIC 3977",
    "addr:housenumber":"43",
    "addr:postcode":"3977",
    "addr:street":"Clarendon St",
    "iso:country":"AU",
    "sg:address":"43 Clarendon St",
    "sg:city":"Cranbourne",
    "sg:classifiers":[
        {
            "category":"Education",
            "subcategory":"Kindergarten",
            "type":"Public Place"
        }
    ],
    "sg:phone":"+61 3 5996 3117",
    "sg:postcode":"3977",
    "sg:province":"VIC",
    "sg:tags":[
        "pre-schools"
    ],
    "wof:name":"Clarendon St Pre-School",
    "wof:placetype":"venue"
},
  "geometry": {"coordinates":[145.27543640100001,-38.1045227051],"type":"Point"}
}