{
  "type": "Feature",
  "properties": {
    "iso:country":"AU",
    "sg:address":"99 Ohio St",
    "sg:city":"Armidale",
    "sg:classifiers":[
        {
            "category":"Shopping",
            "subcategory":"Clothing, Apparel, & Fashions",
            "type":"Retail Goods"
        }
    ],
    "sg:phone":"+61 2 6772 1677",
    "sg:postcode":"2350",
    "sg:province":"NSW",
    "sg:tags":[
        "recycled",
        "clothing"
    ],
    "wof:name":"Salvation Army Family Stores",
    "wof:placetype":"venue"
},
  "geometry": {"coordinates":[151.652069092,-30.5114364624],"type":"Point"}
}