{
  "type": "Feature",
  "properties": {
    "iso:country":"AU",
    "sg:address":"55 Jennaberring Rd",
    "sg:city":"Quairading",
    "sg:classifiers":[
        {
            "category":"Travel",
            "subcategory":"Hotels & Motels",
            "type":"Entertainment"
        }
    ],
    "sg:phone":"+61 8 9645 1054",
    "sg:postcode":"6383",
    "sg:province":"WA",
    "wof:name":"Quairading Motel",
    "wof:placetype":"venue"
},
  "geometry": {"coordinates":[117.40759300000001,-32.005997],"type":"Point"}
}