{
  "type": "Feature",
  "properties": {
    "addr:full":"Colbee Crt Phillip ACT 2606",
    "addr:postcode":"2606",
    "addr:street":"Colbee Crt",
    "iso:country":"AU",
    "sg:address":"Colbee Crt",
    "sg:city":"Phillip",
    "sg:classifiers":[
        {
            "category":"Professional",
            "subcategory":"Employment Agencies",
            "type":"Services"
        }
    ],
    "sg:phone":"+61 2 6282 1736",
    "sg:postcode":"2606",
    "sg:province":"ACT",
    "wof:name":"Caloola Skills Training & Job Placements",
    "wof:placetype":"venue"
},
  "geometry": {"coordinates":[149.08880615199999,-35.3518486023],"type":"Point"}
}