{
  "type": "Feature",
  "properties": {
    "addr:full":"37 Mitchell St Bourke NSW 2840",
    "addr:housenumber":"37",
    "addr:postcode":"2840",
    "addr:street":"Mitchell St",
    "iso:country":"AU",
    "sg:address":"37 Mitchell St",
    "sg:city":"Bourke",
    "sg:classifiers":[
        {
            "category":"Food & Beverages",
            "subcategory":"Bakery",
            "type":"Retail Goods"
        }
    ],
    "sg:phone":"+61 2 6872 2086",
    "sg:postcode":"2840",
    "sg:province":"NSW",
    "sg:tags":[
        "baker"
    ],
    "wof:name":"Morrall's Bakery",
    "wof:placetype":"venue"
},
  "geometry": {"coordinates":[145.937454,-30.088892],"type":"Point"}
}