{
  "type": "Feature",
  "properties": {
    "addr:full":"13 Allnutt Pde Cheltenham VIC 3192",
    "addr:housenumber":"13",
    "addr:postcode":"3192",
    "addr:street":"Allnutt Pde",
    "iso:country":"AU",
    "sg:address":"13 Allnutt Pde",
    "sg:city":"Cheltenham",
    "sg:classifiers":[
        {
            "category":"Sports & Exercise",
            "subcategory":"Gym",
            "type":"Entertainment"
        }
    ],
    "sg:phone":"+61 3 9584 5986",
    "sg:postcode":"3192",
    "sg:province":"VIC",
    "sg:tags":[
        "meditation"
    ],
    "wof:name":"Mind Body Synergy",
    "wof:placetype":"venue"
},
  "geometry": {"coordinates":[145.074874878,-37.9695625305],"type":"Point"}
}