{
  "type": "Feature",
  "properties": {
    "addr:full":"2A Midera Ave Edwardstown SA 5039",
    "addr:housenumber":"2a",
    "addr:postcode":"5039",
    "addr:street":"Midera Ave",
    "iso:country":"AU",
    "sg:address":"2A Midera Ave",
    "sg:city":"Edwardstown",
    "sg:classifiers":[
        {
            "category":"Arena",
            "subcategory":"Sports Club",
            "type":"Entertainment"
        }
    ],
    "sg:phone":"+61 8 8277 2522",
    "sg:postcode":"5039",
    "sg:province":"SA",
    "sg:tags":[
        "organisation",
        "sporting"
    ],
    "wof:name":"Squash SA",
    "wof:placetype":"venue"
},
  "geometry": {"coordinates":[138.57005310100001,-34.9927597046],"type":"Point"}
}