{
  "type": "Feature",
  "properties": {
    "addr:full":"2 Murrell St Wangaratta VIC 3677",
    "addr:housenumber":"2",
    "addr:postcode":"3677",
    "addr:street":"Murrell St",
    "iso:country":"AU",
    "sg:address":"2 Murrell St",
    "sg:city":"Wangaratta",
    "sg:classifiers":[
        {
            "category":"Commercial Area",
            "type":"Public Place"
        }
    ],
    "sg:phone":"+61 3 5721 3612",
    "sg:postcode":"3677",
    "sg:province":"VIC",
    "sg:tags":[
        "heavy",
        "carrier"
    ],
    "wof:name":"Canny Carrying Co Pty Ltd",
    "wof:placetype":"venue"
},
  "geometry": {"coordinates":[146.292282105,-36.3703155518],"type":"Point"}
}