{
  "type": "Feature",
  "properties": {
    "addr:full":"1st Flr S-Coast Day Surgery Bldg Cnr Second & Memorial Aves Maroochydore QLD 4558",
    "addr:postcode":"4558",
    "addr:street":"Cnr",
    "iso:country":"AU",
    "sg:address":"1st Flr S-Coast Day Surgery Bldg Cnr Second & Memorial Aves",
    "sg:city":"Maroochydore",
    "sg:classifiers":[
        {
            "category":"Health Services",
            "subcategory":"Doctor",
            "type":"Services"
        }
    ],
    "sg:phone":"+61 7 5444 9000",
    "sg:postcode":"4558",
    "sg:province":"QLD",
    "sg:tags":[
        "medical",
        "practitioner"
    ],
    "wof:name":"Walker James",
    "wof:placetype":"venue"
},
  "geometry": {"coordinates":[153.094284058,-26.655544281],"type":"Point"}
}