{
  "type": "Feature",
  "properties": {
    "addr:full":"29 Curdie St Cobden VIC 3266",
    "addr:housenumber":"29",
    "addr:postcode":"3266",
    "addr:street":"Curdie St",
    "iso:country":"AU",
    "sg:address":"29 Curdie St",
    "sg:city":"Cobden",
    "sg:classifiers":[
        {
            "category":"Personal",
            "subcategory":"Beauty Salon",
            "type":"Services"
        }
    ],
    "sg:phone":"+61 3 5595 1836",
    "sg:postcode":"3266",
    "sg:province":"VIC",
    "sg:tags":[
        "hairdresser"
    ],
    "wof:name":"Cobden Mens Hair Room",
    "wof:placetype":"venue"
},
  "geometry": {"coordinates":[143.077667236,-38.3286972046],"type":"Point"}
}