{
  "type": "Feature",
  "properties": {
    "addr:full":"69 Kalinda Rd Ringwood VIC 3134",
    "addr:housenumber":"69",
    "addr:postcode":"3134",
    "addr:street":"Kalinda Rd",
    "iso:country":"AU",
    "sg:address":"69 Kalinda Rd",
    "sg:city":"Ringwood",
    "sg:classifiers":[
        {
            "category":"Professional",
            "subcategory":"Lawyer & Legal Services",
            "type":"Services"
        }
    ],
    "sg:phone":"+61 3 9812 2298",
    "sg:postcode":"3134",
    "sg:province":"VIC",
    "sg:tags":[
        "wills",
        "probate",
        "estate"
    ],
    "wof:name":"Maroney Douglas C W",
    "wof:placetype":"venue"
},
  "geometry": {"coordinates":[145.255126953,-37.7870597839],"type":"Point"}
}