{
  "type": "Feature",
  "properties": {
    "addr:full":"17 Adams Pl Geelong VIC 3220",
    "addr:housenumber":"17",
    "addr:postcode":"3220",
    "addr:street":"Adams Pl",
    "iso:country":"AU",
    "sg:address":"17 Adams Pl",
    "sg:city":"Geelong",
    "sg:classifiers":[
        {
            "category":"Government",
            "subcategory":"Court House",
            "type":"Public Place"
        }
    ],
    "sg:phone":"+61 1800 440 540",
    "sg:postcode":"3220",
    "sg:province":"VIC",
    "sg:tags":[
        "personal",
        "marriage",
        "family",
        "counselling"
    ],
    "wof:name":"Pregnancy Help Geelong Inc.",
    "wof:placetype":"venue"
},
  "geometry": {"coordinates":[144.362335,-38.151806],"type":"Point"}
}