{
  "type": "Feature",
  "properties": {
    "addr:full":"10 Hallet Rd Wattle Park SA 5066",
    "addr:housenumber":"10",
    "addr:postcode":"5066",
    "addr:street":"Hallet Rd",
    "iso:country":"AU",
    "sg:address":"10 Hallet Rd",
    "sg:city":"Wattle Park",
    "sg:classifiers":[
        {
            "category":"Building & Trades",
            "subcategory":"Landscaping Services",
            "type":"Services"
        }
    ],
    "sg:phone":"+61 412 392 927",
    "sg:postcode":"5066",
    "sg:province":"SA",
    "sg:tags":[
        "designer",
        "landscape",
        "contractor"
    ],
    "wof:name":"Urban Gardens",
    "wof:placetype":"venue"
},
  "geometry": {"coordinates":[138.66830444300001,-34.9263916016],"type":"Point"}
}