{
  "type": "Feature",
  "properties": {
    "addr:full":"Unit 1/ 30 Oxleigh Drv Malaga WA 6090",
    "addr:postcode":"6090",
    "addr:street":"30 Oxleigh Drv",
    "iso:country":"AU",
    "sg:address":"Unit 1/ 30 Oxleigh Drv",
    "sg:city":"Malaga",
    "sg:classifiers":[
        {
            "category":"Wholesale",
            "subcategory":"Apparel",
            "type":"Manufacturing & Wholesale Goods"
        }
    ],
    "sg:phone":"+61 8 9249 1447",
    "sg:postcode":"6090",
    "sg:province":"WA",
    "sg:tags":[
        "wholesaler",
        "mfrs",
        "uniform"
    ],
    "wof:name":"Get Smart Clothing",
    "wof:placetype":"venue"
},
  "geometry": {"coordinates":[115.88609314,-31.8491630554],"type":"Point"}
}