{
  "type": "Feature",
  "properties": {
    "addr:full":"452 Victoria St North Melbourne VIC 3051",
    "addr:housenumber":"452",
    "addr:postcode":"3051",
    "addr:street":"Victoria St",
    "iso:country":"AU",
    "sg:address":"452 Victoria St",
    "sg:city":"North Melbourne",
    "sg:classifiers":[
        {
            "category":"Health Services",
            "subcategory":"Doctor",
            "type":"Services"
        }
    ],
    "sg:phone":"+61 3 9328 1151",
    "sg:postcode":"3051",
    "sg:province":"VIC",
    "sg:tags":[
        "medical",
        "practitioner"
    ],
    "wof:name":"North Melbourne Medical Centre",
    "wof:placetype":"venue"
},
  "geometry": {"coordinates":[144.951095581,-37.8051834106],"type":"Point"}
}