{
  "type": "Feature",
  "properties": {
    "addr:full":"70 Old Rd Franklin TAS 7113",
    "addr:housenumber":"70",
    "addr:postcode":"7113",
    "addr:street":"Old Rd",
    "iso:country":"AU",
    "sg:address":"70 Old Rd",
    "sg:city":"Franklin",
    "sg:classifiers":[
        {
            "category":"Shopping",
            "subcategory":"Crafts & Fabrics",
            "type":"Retail Goods"
        }
    ],
    "sg:phone":"+61 3 6266 3847",
    "sg:postcode":"7113",
    "sg:province":"TAS",
    "sg:tags":[
        "silk"
    ],
    "wof:name":"Huon Silks",
    "wof:placetype":"venue"
},
  "geometry": {"coordinates":[147.00250244099999,-43.0857963562],"type":"Point"}
}