{
  "type": "Feature",
  "properties": {
    "addr:full":"Shop 3 Cnr Industrial Rd & Central Avenue Oak Flats NSW 2529",
    "addr:housenumber":"shop 3",
    "addr:postcode":"2529",
    "addr:street":"Cnr Industrial Rd & Central Avenue Oak Flats",
    "iso:country":"AU",
    "sg:address":"Shop 3 Cnr Industrial Rd & Central Avenue",
    "sg:city":"Oak Flats",
    "sg:classifiers":[
        {
            "category":"Manufacturing",
            "subcategory":"Glass & Minerals",
            "type":"Manufacturing & Wholesale Goods"
        }
    ],
    "sg:phone":"+61 2 4256 5619",
    "sg:postcode":"2529",
    "sg:province":"NSW",
    "sg:tags":[
        "stained"
    ],
    "wof:name":"Federation Stained Glass",
    "wof:placetype":"venue"
},
  "geometry": {"coordinates":[150.81942749000001,-34.565410614],"type":"Point"}
}