{
  "type": "Feature",
  "properties": {
    "iso:country":"AU",
    "sg:address":"67 Snook St",
    "sg:city":"Clontarf",
    "sg:classifiers":[
        {
            "category":"Retail",
            "subcategory":"Auto Repair",
            "type":"Services"
        }
    ],
    "sg:phone":"+61 7 3283 3201",
    "sg:postcode":"4019",
    "sg:province":"QLD",
    "sg:tags":[
        "beater",
        "painter",
        "panel"
    ],
    "wof:name":"Flay's Smash Repairs",
    "wof:placetype":"venue"
},
  "geometry": {"coordinates":[153.08433532699999,-27.241147995],"type":"Point"}
}