{
  "type": "Feature",
  "properties": {
    "addr:full":"190 Abernethy Rd Belmont WA 6104",
    "addr:housenumber":"190",
    "addr:postcode":"6104",
    "addr:street":"Abernethy Rd",
    "iso:country":"AU",
    "sg:address":"190 Abernethy Rd",
    "sg:city":"Belmont",
    "sg:classifiers":[
        {
            "category":"Fast Food",
            "type":"Food & Drink"
        }
    ],
    "sg:phone":"+61 8 9277 7727",
    "sg:postcode":"6104",
    "sg:province":"WA",
    "sg:tags":[
        "away",
        "take"
    ],
    "wof:name":"Abernethy Lunch Bar",
    "wof:placetype":"venue"
},
  "geometry": {"coordinates":[115.93031311,-31.9576377869],"type":"Point"}
}