{
  "type": "Feature",
  "properties": {
    "addr:full":"674 Yan Yean Rd Yarrambat VIC 3091",
    "addr:housenumber":"674",
    "addr:postcode":"3091",
    "addr:street":"Yan Yean Rd",
    "iso:country":"AU",
    "sg:address":"674 Yan Yean Rd",
    "sg:city":"Yarrambat",
    "sg:classifiers":[
        {
            "category":"Organizations",
            "subcategory":"Professional Association",
            "type":"Services"
        }
    ],
    "sg:phone":"+61 3 9436 1106",
    "sg:postcode":"3091",
    "sg:province":"VIC",
    "sg:tags":[
        "organisation",
        "business"
    ],
    "wof:name":"Business Diagnostics & Solutions",
    "wof:placetype":"venue"
},
  "geometry": {"coordinates":[145.13398742699999,-37.6304931641],"type":"Point"}
}