{
  "type": "Feature",
  "properties": {
    "addr:full":"Ste1/ 155 King William Rd Hyde Park SA 5061",
    "addr:housenumber":"155",
    "addr:postcode":"5061",
    "addr:street":"King William Rd",
    "iso:country":"AU",
    "sg:address":"Ste1/ 155 King William Rd",
    "sg:city":"Hyde Park",
    "sg:classifiers":[
        {
            "category":"Personal",
            "subcategory":"Massage",
            "type":"Services"
        }
    ],
    "sg:phone":"+61 408 899 467",
    "sg:postcode":"5061",
    "sg:province":"SA",
    "sg:tags":[
        "therapy"
    ],
    "wof:name":"Massage Therapy at Hyde Park",
    "wof:placetype":"venue"
},
  "geometry": {"coordinates":[138.60038757300001,-34.9564590454],"type":"Point"}
}