{
  "type": "Feature",
  "properties": {
    "iso:country":"AU",
    "sg:address":"45 Military Rd",
    "sg:city":"Avondale Heights",
    "sg:classifiers":[
        {
            "category":"Health Services",
            "subcategory":"Dentist",
            "type":"Services"
        }
    ],
    "sg:phone":"+61 3 9318 5804",
    "sg:postcode":"3034",
    "sg:province":"VIC",
    "wof:name":"Lipshutz Jeffrey Dr",
    "wof:placetype":"venue"
},
  "geometry": {"coordinates":[144.864594,-37.768593],"type":"Point"}
}