{
  "type": "Feature",
  "properties": {
    "addr:full":"483 Whitehorse Rd Mitcham VIC 3132",
    "addr:housenumber":"483",
    "addr:postcode":"3132",
    "addr:street":"Whitehorse Rd",
    "iso:country":"AU",
    "sg:address":"483 Whitehorse Rd",
    "sg:city":"Mitcham",
    "sg:classifiers":[
        {
            "category":"Real Estate",
            "subcategory":"Real Estate Agent",
            "type":"Services"
        }
    ],
    "sg:phone":"+61 3 9874 3355",
    "sg:postcode":"3132",
    "sg:province":"VIC",
    "wof:name":"Professionals",
    "wof:placetype":"venue"
},
  "geometry": {"coordinates":[145.19212341299999,-37.8162651062],"type":"Point"}
}