{
  "type": "Feature",
  "properties": {
    "iso:country":"AU",
    "sg:address":"12 Robert St",
    "sg:city":"Collingwood",
    "sg:classifiers":[
        {
            "category":"Professional",
            "type":"Services"
        }
    ],
    "sg:phone":"+61 3 9417 4272",
    "sg:postcode":"3066",
    "sg:province":"VIC",
    "sg:tags":[
        "shop",
        "fitting"
    ],
    "wof:name":"Zone Design & Construction P/L",
    "wof:placetype":"venue"
},
  "geometry": {"coordinates":[144.987594605,-37.8055953979],"type":"Point"}
}