{
  "type": "Feature",
  "properties": {
    "addr:full":"Shop 1 230 Main St Osborne Park WA 6017",
    "addr:housenumber":"shop 1 230",
    "addr:postcode":"6017",
    "addr:street":"Main St",
    "iso:country":"AU",
    "sg:address":"Shop 1 230 Main St",
    "sg:city":"Osborne Park",
    "sg:classifiers":[
        {
            "category":"Personal",
            "subcategory":"Beauty Salon",
            "type":"Services"
        }
    ],
    "sg:phone":"+61 8 9349 5448",
    "sg:postcode":"6017",
    "sg:province":"WA",
    "sg:tags":[
        "hairdresser"
    ],
    "wof:name":"Divine Hair Studio",
    "wof:placetype":"venue"
},
  "geometry": {"coordinates":[115.82840728799999,-31.8954105377],"type":"Point"}
}