{
  "type": "Feature",
  "properties": {
    "addr:full":"29 Blue Jay St Burleigh Heads QLD 4220",
    "addr:housenumber":"29",
    "addr:postcode":"4220",
    "addr:street":"Blue Jay St",
    "iso:country":"AU",
    "sg:address":"29 Blue Jay St",
    "sg:city":"Burleigh Heads",
    "sg:classifiers":[
        {
            "category":"Building & Trades",
            "subcategory":"Construction",
            "type":"Services"
        }
    ],
    "sg:phone":"+61 417 749 120",
    "sg:postcode":"4220",
    "sg:province":"QLD",
    "sg:tags":[
        "concrete",
        "contractor"
    ],
    "wof:name":"Flatline Concreting",
    "wof:placetype":"venue"
},
  "geometry": {"coordinates":[153.44181823700001,-28.0843009949],"type":"Point"}
}