{
  "type": "Feature",
  "properties": {
    "iso:country":"AU",
    "sg:address":"Shop G30 Earl Plaza Cnr White & Price St",
    "sg:city":"Nerang",
    "sg:classifiers":[
        {
            "category":"Retail",
            "subcategory":"Laundry & Dry Cleaning",
            "type":"Services"
        }
    ],
    "sg:phone":"+61 405 384 744",
    "sg:postcode":"4211",
    "sg:province":"QLD",
    "wof:name":"Nerang Super Suds Coin Laudrette",
    "wof:placetype":"venue"
},
  "geometry": {"coordinates":[153.336425781,-27.9894447327],"type":"Point"}
}