{
  "type": "Feature",
  "properties": {
    "iso:country":"AU",
    "sg:address":"U17, 95 Kelvin Rd",
    "sg:city":"Maddington",
    "sg:classifiers":[
        {
            "category":"Utilities",
            "subcategory":"Electric",
            "type":"Services"
        }
    ],
    "sg:phone":"+61 8 9459 1538",
    "sg:postcode":"6109",
    "sg:province":"WA",
    "sg:tags":[
        "electrical",
        "contractor"
    ],
    "wof:name":"Holdens Electrical",
    "wof:placetype":"venue"
},
  "geometry": {"coordinates":[115.993972778,-32.0404205322],"type":"Point"}
}