{
  "type": "Feature",
  "properties": {
    "addr:full":"PO Box 397 Wallsend NSW 2287",
    "addr:postcode":"2287",
    "iso:country":"AU",
    "sg:address":"PO Box 397",
    "sg:city":"Wallsend",
    "sg:classifiers":[
        {
            "category":"Building & Trades",
            "subcategory":"Pest Control",
            "type":"Services"
        }
    ],
    "sg:phone":"+61 2 4951 1131",
    "sg:postcode":"2287",
    "sg:province":"NSW",
    "wof:name":"Adam West Pest Control",
    "wof:placetype":"venue"
},
  "geometry": {"coordinates":[151.66819763199999,-32.9037284851],"type":"Point"}
}