{
  "type": "Feature",
  "properties": {
    "addr:full":"1 Booth Pl Balcatta WA 6021",
    "addr:housenumber":"1",
    "addr:postcode":"6021",
    "addr:street":"Booth Pl",
    "iso:country":"AU",
    "sg:address":"1 Booth Pl",
    "sg:city":"Balcatta",
    "sg:classifiers":[
        {
            "category":"Home & Garden",
            "subcategory":"Hardware",
            "type":"Retail Goods"
        }
    ],
    "sg:phone":"+61 8 6241 0555",
    "sg:postcode":"6021",
    "sg:province":"WA",
    "sg:tags":[
        "part",
        "air conditioning"
    ],
    "wof:name":"Polyaire Pty Ltd",
    "wof:placetype":"venue"
},
  "geometry": {"coordinates":[115.803283691,-31.8655376434],"type":"Point"}
}