{
  "type": "Feature",
  "properties": {
    "addr:full":"434 King St Newtown NSW 2042",
    "addr:housenumber":"434",
    "addr:postcode":"2042",
    "addr:street":"King St",
    "iso:country":"AU",
    "sg:address":"434 King St",
    "sg:city":"Newtown",
    "sg:classifiers":[
        {
            "category":"Government",
            "subcategory":"Court House",
            "type":"Public Place"
        }
    ],
    "sg:phone":"+61 418 447 600",
    "sg:postcode":"2042",
    "sg:province":"NSW",
    "sg:tags":[
        "personal",
        "marriage",
        "family",
        "counselling"
    ],
    "wof:name":"Katy Fitzgerald",
    "wof:placetype":"venue"
},
  "geometry": {"coordinates":[151.17836,-33.900372],"type":"Point"}
}