{
  "type": "Feature",
  "properties": {
    "addr:full":"3 Spall St Carrara QLD 4211",
    "addr:housenumber":"3",
    "addr:postcode":"4211",
    "addr:street":"Spall St",
    "iso:country":"AU",
    "sg:address":"3 Spall St",
    "sg:city":"Carrara",
    "sg:classifiers":[
        {
            "category":"Military Area",
            "subcategory":"Army Base",
            "type":"Public Place"
        }
    ],
    "sg:phone":"+61 7 5530 5754",
    "sg:postcode":"4211",
    "sg:province":"QLD",
    "sg:tags":[
        "wholesaler",
        "mfrs",
        "cement",
        "supply"
    ],
    "wof:name":"Cement Australia Packaged Products (Qld) Pty Ltd",
    "wof:placetype":"venue"
},
  "geometry": {"coordinates":[153.354248047,-28.0330467224],"type":"Point"}
}