{
  "type": "Feature",
  "properties": {
    "iso:country":"AU",
    "sg:address":"123 Main St",
    "sg:city":"Stawell",
    "sg:classifiers":[
        {
            "category":"Shopping",
            "subcategory":"Clothing, Apparel, & Fashions",
            "type":"Retail Goods"
        }
    ],
    "sg:phone":"+61 3 5358 5183",
    "sg:postcode":"3380",
    "sg:province":"VIC",
    "sg:tags":[
        "menswear"
    ],
    "wof:name":"Gunmetal Grey",
    "wof:placetype":"venue"
},
  "geometry": {"coordinates":[142.78558349599999,-37.0525588989],"type":"Point"}
}