{
  "type": "Feature",
  "properties": {
    "addr:full":"8 Devon St Lonsdale SA 5160",
    "addr:housenumber":"8",
    "addr:postcode":"5160",
    "addr:street":"Devon St",
    "iso:country":"AU",
    "sg:address":"8 Devon St",
    "sg:city":"Lonsdale",
    "sg:classifiers":[
        {
            "category":"Retail",
            "subcategory":"Storage",
            "type":"Services"
        }
    ],
    "sg:phone":"+61 8 8326 0009",
    "sg:postcode":"5160",
    "sg:province":"SA",
    "sg:tags":[
        "removal",
        "furniture"
    ],
    "wof:name":"A AAISelf Storage 2000",
    "wof:placetype":"venue"
},
  "geometry": {"coordinates":[138.50097656200001,-35.1160812378],"type":"Point"}
}