{
  "type": "Feature",
  "properties": {
    "iso:country":"AU",
    "sg:address":"1/ 1 Powderworks Rd",
    "sg:city":"North Narrabeen",
    "sg:classifiers":[
        {
            "category":"Personal",
            "subcategory":"Beauty Salon",
            "type":"Services"
        }
    ],
    "sg:phone":"+61 2 9913 7746",
    "sg:postcode":"2101",
    "sg:province":"NSW",
    "sg:tags":[
        "hairdresser"
    ],
    "wof:name":"Hot Gossip Hair & Beauty",
    "wof:placetype":"venue"
},
  "geometry": {"coordinates":[151.29565400000001,-33.702545],"type":"Point"}
}