{
  "type": "Feature",
  "properties": {
    "iso:country":"AU",
    "sg:address":"29 Hope St",
    "sg:city":"Ermington",
    "sg:classifiers":[
        {
            "category":"Shopping Center",
            "type":"Public Place"
        }
    ],
    "sg:phone":"+61 2 9877 8219",
    "sg:postcode":"2115",
    "sg:province":"NSW",
    "sg:tags":[
        "riveting",
        "equipment",
        "rivet"
    ],
    "wof:name":"Sydney Rivet Centre",
    "wof:placetype":"venue"
},
  "geometry": {"coordinates":[151.06619262699999,-33.8153419495],"type":"Point"}
}