{
  "type": "Feature",
  "properties": {
    "iso:country":"AU",
    "sg:address":"2 Kelvinside Rd",
    "sg:city":"Noble Park",
    "sg:classifiers":[
        {
            "category":"Home & Garden",
            "subcategory":"Building Materials",
            "type":"Retail Goods"
        }
    ],
    "sg:phone":"+61 3 9548 2020",
    "sg:postcode":"3174",
    "sg:province":"VIC",
    "sg:tags":[
        "merchant",
        "glass",
        "glazier"
    ],
    "wof:name":"Noble Glass",
    "wof:placetype":"venue"
},
  "geometry": {"coordinates":[145.178634644,-37.9655151367],"type":"Point"}
}