{
  "type": "Feature",
  "properties": {
    "addr:full":"25 Cottam Ave Bankstown NSW 2200",
    "addr:housenumber":"25",
    "addr:postcode":"2200",
    "addr:street":"Cottam Ave",
    "iso:country":"AU",
    "sg:address":"25 Cottam Ave",
    "sg:city":"Bankstown",
    "sg:classifiers":[
        {
            "category":"Home & Garden",
            "subcategory":"Building Materials",
            "type":"Retail Goods"
        }
    ],
    "sg:phone":"+61 2 9791 5244",
    "sg:postcode":"2200",
    "sg:province":"NSW",
    "sg:tags":[
        "concrete",
        "additive"
    ],
    "wof:name":"Effective Concrete Pty Ltd",
    "wof:placetype":"venue"
},
  "geometry": {"coordinates":[151.034302,-33.932457],"type":"Point"}
}