{
  "type": "Feature",
  "properties": {
    "addr:full":"Unit 3/ 45 Rule St North Fremantle WA 6159",
    "addr:housenumber":"45",
    "addr:postcode":"6159",
    "addr:street":"Rule St",
    "iso:country":"AU",
    "sg:address":"Unit 3/ 45 Rule St",
    "sg:city":"North Fremantle",
    "sg:classifiers":[
        {
            "category":"Wholesale",
            "subcategory":"Machinery & Supplies",
            "type":"Manufacturing & Wholesale Goods"
        }
    ],
    "sg:phone":"+61 418 910 086",
    "sg:postcode":"6159",
    "sg:province":"WA",
    "sg:tags":[
        "equipment",
        "rustproofing"
    ],
    "wof:name":"Roe Marketing & Consulting Pty Ltd",
    "wof:placetype":"venue"
},
  "geometry": {"coordinates":[115.755363,-32.029228],"type":"Point"}
}