{
  "type": "Feature",
  "properties": {
    "addr:full":"131 Heddles Rd Loorana TAS 7256",
    "addr:housenumber":"131",
    "addr:postcode":"7256",
    "addr:street":"Heddles Rd",
    "iso:country":"AU",
    "sg:address":"131 Heddles Rd",
    "sg:city":"Loorana",
    "sg:classifiers":[
        {
            "category":"Farming",
            "subcategory":"Farm",
            "type":"Manufacturing & Wholesale Goods"
        }
    ],
    "sg:phone":"+61 3 6463 1148",
    "sg:postcode":"7256",
    "sg:province":"TAS",
    "sg:tags":[
        "farmer"
    ],
    "wof:name":"Crack Ron",
    "wof:placetype":"venue"
},
  "geometry": {"coordinates":[143.8984375,-39.8264350891],"type":"Point"}
}