{
  "type": "Feature",
  "properties": {
    "addr:full":"Cnr Connell Rd & Marine Tce Geraldton WA 6530",
    "addr:postcode":"6530",
    "addr:street":"Cnr Connell Rd & Marine Tce",
    "iso:country":"AU",
    "sg:address":"Cnr Connell Rd & Marine Tce",
    "sg:city":"Geraldton",
    "sg:classifiers":[
        {
            "category":"Professional",
            "subcategory":"Employment Agencies",
            "type":"Services"
        }
    ],
    "sg:phone":"+61 8 9964 0200",
    "sg:postcode":"6530",
    "sg:province":"WA",
    "sg:tags":[
        "hire",
        "labour",
        "contractor"
    ],
    "wof:name":"Maicon Engineering",
    "wof:placetype":"venue"
},
  "geometry": {"coordinates":[114.588119507,-28.7726783752],"type":"Point"}
}