{
  "type": "Feature",
  "properties": {
    "iso:country":"AU",
    "sg:address":"Shop 7, 36- 40 Mason St",
    "sg:city":"Warragul",
    "sg:classifiers":[
        {
            "category":"Shopping",
            "subcategory":"Crafts & Fabrics",
            "type":"Retail Goods"
        }
    ],
    "sg:phone":"+61 3 5622 1655",
    "sg:postcode":"3820",
    "sg:province":"VIC",
    "sg:tags":[
        "supply"
    ],
    "wof:name":"Bizzy Bees Crafts & Supplies",
    "wof:placetype":"venue"
},
  "geometry": {"coordinates":[145.934158,-38.161427],"type":"Point"}
}