{
  "type": "Feature",
  "properties": {
    "iso:country":"AU",
    "sg:address":"Fernleigh St",
    "sg:city":"Newtown",
    "sg:classifiers":[
        {
            "category":"Communications",
            "subcategory":"News Services",
            "type":"Services"
        }
    ],
    "sg:phone":"+61 3 5221 3906",
    "sg:postcode":"3220",
    "sg:province":"VIC",
    "sg:tags":[
        "information",
        "tourist",
        "attractions"
    ],
    "wof:name":"Barwon Grange",
    "wof:placetype":"venue"
},
  "geometry": {"coordinates":[144.347672,-38.160877],"type":"Point"}
}