{
  "type": "Feature",
  "properties": {
    "iso:country":"AU",
    "sg:address":"258 Jasper Rd",
    "sg:city":"McKinnon",
    "sg:classifiers":[
        {
            "category":"Sports & Exercise",
            "subcategory":"Gym",
            "type":"Entertainment"
        }
    ],
    "sg:phone":"+61 3 9576 8881",
    "sg:postcode":"3204",
    "sg:province":"VIC",
    "sg:tags":[
        "health",
        "fitness"
    ],
    "wof:name":"Contours Bentleigh",
    "wof:placetype":"venue"
},
  "geometry": {"coordinates":[145.043045,-37.911396],"type":"Point"}
}