{
  "type": "Feature",
  "properties": {
    "addr:full":"663 Pt Nepean Rd McCrae VIC 3938",
    "addr:housenumber":"663",
    "addr:postcode":"3938",
    "addr:street":"Pt Nepean Rd",
    "iso:country":"AU",
    "sg:address":"663 Pt Nepean Rd",
    "sg:city":"McCrae",
    "sg:classifiers":[
        {
            "category":"Professional",
            "subcategory":"Art Services",
            "type":"Services"
        }
    ],
    "sg:phone":"+61 3 5986 5020",
    "sg:postcode":"3938",
    "sg:province":"VIC",
    "sg:tags":[
        "picture",
        "frame",
        "framing"
    ],
    "wof:name":"Sea Pictures",
    "wof:placetype":"venue"
},
  "geometry": {"coordinates":[144.92964172399999,-38.3480453491],"type":"Point"}
}