{
  "type": "Feature",
  "properties": {
    "addr:full":"94 Percy St Portland VIC 3305",
    "addr:housenumber":"94",
    "addr:postcode":"3305",
    "addr:street":"Percy St",
    "iso:country":"AU",
    "sg:address":"94 Percy St",
    "sg:city":"Portland",
    "sg:classifiers":[
        {
            "category":"Shopping",
            "subcategory":"Clothing, Apparel, & Fashions",
            "type":"Retail Goods"
        }
    ],
    "sg:phone":"+61 3 5521 7358",
    "sg:postcode":"3305",
    "sg:province":"VIC",
    "sg:tags":[
        "lady",
        "wear"
    ],
    "wof:name":"Aynsley Fashions",
    "wof:placetype":"venue"
},
  "geometry": {"coordinates":[141.60392761200001,-38.3459281921],"type":"Point"}
}