{
  "type": "Feature",
  "properties": {
    "iso:country":"AU",
    "sg:address":"4 Erica St",
    "sg:city":"Pascoe Vale South",
    "sg:classifiers":[
        {
            "category":"Retail",
            "subcategory":"Auto Repair",
            "type":"Services"
        }
    ],
    "sg:phone":"+61 3 9350 1503",
    "sg:postcode":"3044",
    "sg:province":"VIC",
    "sg:tags":[
        "hire",
        "go-kart"
    ],
    "wof:name":"Woodgate Racing",
    "wof:placetype":"venue"
},
  "geometry": {"coordinates":[144.947433472,-37.7350578308],"type":"Point"}
}