{
  "type": "Feature",
  "properties": {
    "addr:full":"93 Hammond Rd Cockburn Central WA 6164",
    "addr:housenumber":"93",
    "addr:postcode":"6164",
    "addr:street":"Hammond Rd",
    "iso:country":"AU",
    "sg:address":"93 Hammond Rd",
    "sg:city":"Cockburn Central",
    "sg:classifiers":[
        {
            "category":"Retail",
            "subcategory":"Veterinary Services",
            "type":"Services"
        }
    ],
    "sg:phone":"+61 8 9414 9888",
    "sg:postcode":"6164",
    "sg:province":"WA",
    "sg:tags":[
        "surgeon"
    ],
    "wof:name":"Success Veterinary Hospital",
    "wof:placetype":"venue"
},
  "geometry": {"coordinates":[115.845596,-32.144073],"type":"Point"}
}