{
  "type": "Feature",
  "properties": {
    "addr:full":"Cnr Elizabeth Ave & Whitbread St Taree NSW 2430",
    "addr:postcode":"2430",
    "addr:street":"Cnr Elizabeth Ave & Whitbread St",
    "iso:country":"AU",
    "sg:address":"Cnr Elizabeth Ave & Whitbread St",
    "sg:city":"Taree",
    "sg:classifiers":[
        {
            "category":"Wholesale",
            "subcategory":"Machinery & Supplies",
            "type":"Manufacturing & Wholesale Goods"
        }
    ],
    "sg:phone":"+61 2 6552 3699",
    "sg:postcode":"2430",
    "sg:province":"NSW",
    "sg:tags":[
        "bearing",
        "bushing"
    ],
    "wof:name":"Bearing & Engine Parts Centre",
    "wof:placetype":"venue"
},
  "geometry": {"coordinates":[152.453598,-31.902765],"type":"Point"}
}