{
  "type": "Feature",
  "properties": {
    "addr:full":"Shp1/ 723 Stanley St Woolloongabba QLD 4102",
    "addr:housenumber":"723",
    "addr:postcode":"4102",
    "addr:street":"Stanley St",
    "iso:country":"AU",
    "sg:address":"Shp1/ 723 Stanley St",
    "sg:city":"Woolloongabba",
    "sg:classifiers":[
        {
            "category":"Personal",
            "subcategory":"Tattoo Parlor",
            "type":"Services"
        }
    ],
    "sg:phone":"+61 7 3891 3666",
    "sg:postcode":"4102",
    "sg:province":"QLD",
    "sg:tags":[
        "tattooing"
    ],
    "wof:name":"Gabba Tattoo Studio",
    "wof:placetype":"venue"
},
  "geometry": {"coordinates":[153.03289794899999,-27.4861793518],"type":"Point"}
}