{
  "type": "Feature",
  "properties": {
    "iso:country":"AU",
    "sg:address":"206 Mornington-Tyabb Rd",
    "sg:city":"Tyabb",
    "sg:classifiers":[
        {
            "category":"Farming",
            "subcategory":"Farm & Veterinary Services",
            "type":"Manufacturing & Wholesale Goods"
        }
    ],
    "sg:phone":"+61 3 5978 8489",
    "sg:postcode":"3913",
    "sg:province":"VIC",
    "sg:tags":[
        "blacksmith",
        "farrier"
    ],
    "wof:name":"Grant Mitchell",
    "wof:placetype":"venue"
},
  "geometry": {"coordinates":[145.14961242699999,-38.2592430115],"type":"Point"}
}