{
  "type": "Feature",
  "properties": {
    "addr:full":"376 Pittwater Rd North Manly NSW 2100",
    "addr:housenumber":"376",
    "addr:postcode":"2100",
    "addr:street":"Pittwater Rd",
    "iso:country":"AU",
    "sg:address":"376 Pittwater Rd",
    "sg:city":"North Manly",
    "sg:classifiers":[
        {
            "category":"Retail",
            "subcategory":"Auto Repair",
            "type":"Services"
        }
    ],
    "sg:phone":"+61 2 9907 1000",
    "sg:postcode":"2100",
    "sg:province":"NSW",
    "sg:tags":[
        "beater",
        "painter",
        "panel"
    ],
    "wof:name":"Mark Stewart Smash Repairs Pty Ltd",
    "wof:placetype":"venue"
},
  "geometry": {"coordinates":[151.27862548799999,-33.7815666199],"type":"Point"}
}