{
  "type": "Feature",
  "properties": {
    "iso:country":"AU",
    "sg:address":"Broadwater & Crescent Ave",
    "sg:city":"Hope Island",
    "sg:classifiers":[
        {
            "category":"Autos & Motor Vehicles",
            "subcategory":"Fuel & Gas Station",
            "type":"Retail Goods"
        }
    ],
    "sg:phone":"+61 7 5530 1122",
    "sg:postcode":"4212",
    "sg:province":"QLD",
    "wof:name":"BP Australia Limited",
    "wof:placetype":"venue"
},
  "geometry": {"coordinates":[153.36268615700001,-27.878112793],"type":"Point"}
}