{
  "type": "Feature",
  "properties": {
    "iso:country":"AU",
    "sg:address":"25 Markwell St",
    "sg:city":"Kingaroy",
    "sg:classifiers":[
        {
            "category":"Health Services",
            "subcategory":"Doctor",
            "type":"Services"
        }
    ],
    "sg:phone":"+61 7 4162 2033",
    "sg:postcode":"4610",
    "sg:province":"QLD",
    "sg:tags":[
        "medical",
        "practitioner"
    ],
    "wof:name":"Ruscoe Family Practice",
    "wof:placetype":"venue"
},
  "geometry": {"coordinates":[151.83744812,-26.5426445007],"type":"Point"}
}