{
  "type": "Feature",
  "properties": {
    "addr:full":"1 Liberator Drv Paralowie SA 5108",
    "addr:housenumber":"1",
    "addr:postcode":"5108",
    "addr:street":"Liberator Drv",
    "iso:country":"AU",
    "sg:address":"1 Liberator Drv",
    "sg:city":"Paralowie",
    "sg:classifiers":[
        {
            "category":"Fast Food",
            "type":"Food & Drink"
        }
    ],
    "sg:phone":"+61 8 8280 5566",
    "sg:postcode":"5108",
    "sg:province":"SA",
    "sg:tags":[
        "away",
        "take"
    ],
    "wof:name":"Hungry Jacks Pty Ltd",
    "wof:placetype":"venue"
},
  "geometry": {"coordinates":[138.59455871599999,-34.758731842],"type":"Point"}
}