{
  "type": "Feature",
  "properties": {
    "addr:full":"Shop 5 Barberry Sq Kalamunda WA 6076",
    "addr:housenumber":"shop 5",
    "addr:postcode":"6076",
    "addr:street":"Barberry Sq",
    "iso:country":"AU",
    "sg:address":"Shop 5",
    "sg:city":"Barberry Sq Kalamunda",
    "sg:classifiers":[
        {
            "category":"Shopping",
            "subcategory":"Music",
            "type":"Retail Goods"
        }
    ],
    "sg:phone":"+61 8 9293 4833",
    "sg:postcode":"6076",
    "sg:province":"WA",
    "sg:tags":[
        "instrument",
        "musical"
    ],
    "wof:name":"R.A. Jazz",
    "wof:placetype":"venue"
},
  "geometry": {"coordinates":[116.05783081,-31.972568512],"type":"Point"}
}