{
  "type": "Feature",
  "properties": {
    "addr:full":"Bellwood St Darra QLD 4076",
    "addr:postcode":"4076",
    "addr:street":"Bellwood St",
    "iso:country":"AU",
    "sg:address":"Bellwood St",
    "sg:city":"Darra",
    "sg:classifiers":[
        {
            "category":"Building & Trades",
            "subcategory":"Construction",
            "type":"Services"
        }
    ],
    "sg:phone":"+61 7 3246 5600",
    "sg:postcode":"4076",
    "sg:province":"QLD",
    "sg:tags":[
        "brick",
        "paving"
    ],
    "wof:name":"PGH",
    "wof:placetype":"venue"
},
  "geometry": {"coordinates":[152.95042419399999,-27.5620574951],"type":"Point"}
}