{
  "type": "Feature",
  "properties": {
    "iso:country":"AU",
    "sg:address":"17 Bunbury St",
    "sg:city":"Newport",
    "sg:classifiers":[
        {
            "category":"Banks & Credit Unions",
            "subcategory":"Financial Services",
            "type":"Services"
        }
    ],
    "sg:phone":"+61 3 9017 0626",
    "sg:postcode":"3015",
    "sg:province":"VIC",
    "sg:tags":[
        "loan",
        "finance",
        "mortgage"
    ],
    "wof:name":"Choice Home Loans",
    "wof:placetype":"venue"
},
  "geometry": {"coordinates":[144.89160156200001,-37.8496284485],"type":"Point"}
}