{
  "type": "Feature",
  "properties": {
    "iso:country":"AU",
    "sg:address":"58a Avenue Rd",
    "sg:city":"Mosman",
    "sg:classifiers":[
        {
            "category":"Food & Beverages",
            "subcategory":"Fruits & Vegetables",
            "type":"Retail Goods"
        }
    ],
    "sg:phone":"+61 2 9969 8021",
    "sg:postcode":"2088",
    "sg:province":"NSW",
    "sg:tags":[
        "greengrocer",
        "fruiterer"
    ],
    "wof:name":"Johnnies Fruit Shop",
    "wof:placetype":"venue"
},
  "geometry": {"coordinates":[151.238525391,-33.8317565918],"type":"Point"}
}