{
  "type": "Feature",
  "properties": {
    "iso:country":"AU",
    "sg:address":"PO Box 671",
    "sg:city":"+ Dunsborough",
    "sg:classifiers":[
        {
            "category":"Professional",
            "subcategory":"Detective & Security Services",
            "type":"Services"
        }
    ],
    "sg:phone":"+61 8 9756 7814",
    "sg:postcode":"6281",
    "sg:province":"WA",
    "sg:tags":[
        "guard",
        "patrol"
    ],
    "wof:name":"Safe & Sure Security",
    "wof:placetype":"venue"
},
  "geometry": {"coordinates":[115.102020264,-33.6174812317],"type":"Point"}
}