{
  "type": "Feature",
  "properties": {
    "addr:full":"Cnr Pascoe Vale Rd & 80 Taggerty Crs Meadow Heights VIC 3048",
    "addr:postcode":"3048",
    "addr:street":"Pascoe Vale Rd & 80 Taggerty Crs",
    "iso:country":"AU",
    "sg:address":"Cnr Pascoe Vale Rd & 80 Taggerty Crs",
    "sg:city":"Meadow Heights",
    "sg:classifiers":[
        {
            "category":"Retail",
            "subcategory":"Veterinary Services",
            "type":"Services"
        }
    ],
    "sg:phone":"+61 3 9309 3199",
    "sg:postcode":"3048",
    "sg:province":"VIC",
    "sg:tags":[
        "surgeon"
    ],
    "wof:name":"Meadow Heights Vet Clinic",
    "wof:placetype":"venue"
},
  "geometry": {"coordinates":[144.92849699999999,-37.642315],"type":"Point"}
}