{
  "type": "Feature",
  "properties": {
    "addr:full":"Unit 4 17 Hilldon Crt Nerang QLD 4211",
    "addr:housenumber":"17",
    "addr:postcode":"4211",
    "addr:street":"Hilldon Crt",
    "iso:country":"AU",
    "sg:address":"Unit 4 17 Hilldon Crt",
    "sg:city":"Nerang",
    "sg:classifiers":[
        {
            "category":"Retail",
            "subcategory":"Auto Repair",
            "type":"Services"
        }
    ],
    "sg:phone":"+61 7 5596 2640",
    "sg:postcode":"4211",
    "sg:province":"QLD",
    "sg:tags":[
        "beater",
        "painter",
        "panel"
    ],
    "wof:name":"Nerang Panel & Paint",
    "wof:placetype":"venue"
},
  "geometry": {"coordinates":[153.34016418499999,-28.0002574921],"type":"Point"}
}