{
  "type": "Feature",
  "properties": {
    "iso:country":"AU",
    "sg:address":"Unit 1 36",
    "sg:city":"Achievement Cres Acacia Ridge",
    "sg:classifiers":[
        {
            "category":"Shopping",
            "subcategory":"Computers & Home Electronics",
            "type":"Retail Goods"
        }
    ],
    "sg:phone":"+61 7 3277 2100",
    "sg:postcode":"4110",
    "sg:province":"QLD",
    "sg:tags":[
        "global",
        "positioning",
        "system"
    ],
    "wof:name":"Automated Positioning Systems",
    "wof:placetype":"venue"
},
  "geometry": {"coordinates":[153.01084899899999,-27.5821933746],"type":"Point"}
}