{
  "type": "Feature",
  "properties": {
    "addr:full":"4 Alexander Crt Creswick VIC 3363",
    "addr:housenumber":"4",
    "addr:postcode":"3363",
    "addr:street":"Alexander Crt",
    "iso:country":"AU",
    "sg:address":"4 Alexander Crt",
    "sg:city":"Creswick",
    "sg:classifiers":[
        {
            "category":"Bars & Pubs",
            "subcategory":"Nightclub",
            "type":"Food & Drink"
        }
    ],
    "sg:phone":"+61 3 5345 8287",
    "sg:postcode":"3363",
    "sg:province":"VIC",
    "sg:tags":[
        "karaoke"
    ],
    "wof:name":"Verseatility Karaoke & Disco",
    "wof:placetype":"venue"
},
  "geometry": {"coordinates":[143.89556884800001,-37.4143218994],"type":"Point"}
}