{
  "type": "Feature",
  "properties": {
    "addr:full":"8 Fern Pl Woollahra NSW 2025",
    "addr:housenumber":"8",
    "addr:postcode":"2025",
    "addr:street":"Fern Pl",
    "iso:country":"AU",
    "sg:address":"8 Fern Pl",
    "sg:city":"Woollahra",
    "sg:classifiers":[
        {
            "category":"Shopping",
            "subcategory":"Clothing, Apparel, & Fashions",
            "type":"Retail Goods"
        }
    ],
    "sg:phone":"+61 2 9369 2944",
    "sg:postcode":"2025",
    "sg:province":"NSW",
    "sg:tags":[
        "lady",
        "wear"
    ],
    "wof:name":"Alex Adams Classic Fashions",
    "wof:placetype":"venue"
},
  "geometry": {"coordinates":[151.253051758,-33.8902397156],"type":"Point"}
}