{
  "type": "Feature",
  "properties": {
    "iso:country":"AU",
    "sg:address":"85 Main St",
    "sg:city":"Osborne Park",
    "sg:classifiers":[
        {
            "category":"Shopping",
            "subcategory":"Computers & Home Electronics",
            "type":"Retail Goods"
        }
    ],
    "sg:phone":"+61 8 9444 6088",
    "sg:postcode":"6017",
    "sg:province":"WA",
    "sg:tags":[
        "hardware",
        "equipment"
    ],
    "wof:name":"Harry Tan Electronics",
    "wof:placetype":"venue"
},
  "geometry": {"coordinates":[115.828048706,-31.9065628052],"type":"Point"}
}