{
  "type": "Feature",
  "properties": {
    "addr:full":"19 Loder St Atherton QLD 4883",
    "addr:housenumber":"19",
    "addr:postcode":"4883",
    "addr:street":"Loder St",
    "iso:country":"AU",
    "sg:address":"19 Loder St",
    "sg:city":"Atherton",
    "sg:classifiers":[
        {
            "category":"Professional",
            "subcategory":"Art Services",
            "type":"Services"
        }
    ],
    "sg:phone":"+61 418 710 974",
    "sg:postcode":"4883",
    "sg:province":"QLD",
    "sg:tags":[
        "decorator",
        "painter"
    ],
    "wof:name":"Harper IB & EH",
    "wof:placetype":"venue"
},
  "geometry": {"coordinates":[145.47578430199999,-17.2736911774],"type":"Point"}
}