{
  "type": "Feature",
  "properties": {
    "addr:full":"437 Moorabool St Geelong VIC 3220",
    "addr:housenumber":"437",
    "addr:postcode":"3220",
    "addr:street":"Moorabool St",
    "iso:country":"AU",
    "sg:address":"437 Moorabool St",
    "sg:city":"Geelong",
    "sg:classifiers":[
        {
            "category":"Retail",
            "subcategory":"Auto Rental",
            "type":"Services"
        }
    ],
    "sg:phone":"+61 3 5222 3030",
    "sg:postcode":"3220",
    "sg:province":"VIC",
    "sg:tags":[
        "car",
        "armoured"
    ],
    "wof:name":"Southern Protection Services (Vic) Pty Ltd",
    "wof:placetype":"venue"
},
  "geometry": {"coordinates":[144.35484299999999,-38.160404],"type":"Point"}
}