{
  "type": "Feature",
  "properties": {
    "addr:full":"5783 Bass Hwy Elizabeth Town TAS 7304",
    "addr:housenumber":"5783",
    "addr:postcode":"7304",
    "addr:street":"Bass Hwy Elizabeth",
    "iso:country":"AU",
    "sg:address":"5783 Bass Hwy",
    "sg:city":"Elizabeth Town",
    "sg:classifiers":[
        {
            "category":"Travel",
            "subcategory":"Hotels & Motels",
            "type":"Entertainment"
        }
    ],
    "sg:phone":"+61 3 6368 1103",
    "sg:postcode":"7304",
    "sg:province":"TAS",
    "sg:tags":[
        "accommodation"
    ],
    "wof:name":"Elizabeth Town Hotel",
    "wof:placetype":"venue"
},
  "geometry": {"coordinates":[146.56260700000001,-41.462418],"type":"Point"}
}