{
  "type": "Feature",
  "properties": {
    "addr:full":"42- 50 Parke St Katoomba NSW 2780",
    "addr:housenumber":"50",
    "addr:postcode":"2780",
    "addr:street":"Parke St",
    "iso:country":"AU",
    "sg:address":"42- 50 Parke St",
    "sg:city":"Katoomba",
    "sg:classifiers":[
        {
            "category":"Food & Beverages",
            "subcategory":"Fruits & Vegetables",
            "type":"Retail Goods"
        }
    ],
    "sg:phone":"+61 2 4782 4128",
    "sg:postcode":"2780",
    "sg:province":"NSW",
    "sg:tags":[
        "greengrocer",
        "fruiterer"
    ],
    "wof:name":"Katoomba Fresh Fruits",
    "wof:placetype":"venue"
},
  "geometry": {"coordinates":[150.309524536,-33.716632843],"type":"Point"}
}