{
  "type": "Feature",
  "properties": {
    "iso:country":"AU",
    "sg:address":"1 King William Rd",
    "sg:city":"Unley",
    "sg:classifiers":[
        {
            "category":"Building & Trades",
            "subcategory":"Landscaping Services",
            "type":"Services"
        }
    ],
    "sg:phone":"+61 1300 134 513",
    "sg:postcode":"5061",
    "sg:province":"SA",
    "sg:tags":[
        "inspection"
    ],
    "wof:name":"Archicentre",
    "wof:placetype":"venue"
},
  "geometry": {"coordinates":[138.60069274899999,-34.9415588379],"type":"Point"}
}