{
  "type": "Feature",
  "properties": {
    "iso:country":"AU",
    "sg:address":"Shop 2017 Westfield Shopng Centre, 500 Oxford St",
    "sg:city":"Bondi Junction Bondi",
    "sg:classifiers":[
        {
            "category":"Shopping",
            "subcategory":"Beauty & Cosmetics",
            "type":"Retail Goods"
        }
    ],
    "sg:phone":"+61 2 9387 2908",
    "sg:postcode":"2026",
    "sg:province":"NSW",
    "wof:name":"The Body Shop",
    "wof:placetype":"venue"
},
  "geometry": {"coordinates":[151.26304626500001,-33.8937911987],"type":"Point"}
}