{
  "type": "Feature",
  "properties": {
    "addr:full":"8th Flr,Dymocks Bldg, 428 George St Sydney NSW 2000",
    "addr:housenumber":"428",
    "addr:postcode":"2000",
    "addr:street":"George St",
    "iso:country":"AU",
    "sg:address":"8th Flr,Dymocks Bldg, 428 George St",
    "sg:city":"Sydney",
    "sg:classifiers":[
        {
            "category":"Manufacturing",
            "subcategory":"Rubber & Plastics",
            "type":"Manufacturing & Wholesale Goods"
        }
    ],
    "sg:phone":"+61 2 9223 4566",
    "sg:postcode":"2000",
    "sg:province":"NSW",
    "sg:tags":[
        "stamp",
        "equipment",
        "metal",
        "maker",
        "supply"
    ],
    "wof:name":"Sydney City Rubber Stamps",
    "wof:placetype":"venue"
},
  "geometry": {"coordinates":[151.207122803,-33.8700141907],"type":"Point"}
}