{
  "type": "Feature",
  "properties": {
    "addr:full":"14 Berry St North Sydney NSW 2060",
    "addr:housenumber":"14",
    "addr:postcode":"2060",
    "addr:street":"Berry St",
    "iso:country":"AU",
    "sg:address":"14 Berry St",
    "sg:city":"North Sydney",
    "sg:classifiers":[
        {
            "category":"Cafe",
            "type":"Food & Drink"
        }
    ],
    "sg:phone":"+61 2 9954 9289",
    "sg:postcode":"2060",
    "sg:province":"NSW",
    "wof:name":"Berry Delicious",
    "wof:placetype":"venue"
},
  "geometry": {"coordinates":[151.20501709000001,-33.8367195129],"type":"Point"}
}