{
  "type": "Feature",
  "properties": {
    "iso:country":"AU",
    "sg:address":"20/ 4",
    "sg:city":"Rifle Range Northmead",
    "sg:classifiers":[
        {
            "category":"Health Services",
            "subcategory":"Health Practitioner",
            "type":"Services"
        }
    ],
    "sg:phone":"+61 1800 686 006",
    "sg:postcode":"2152",
    "sg:province":"NSW",
    "sg:tags":[
        "hypnotherapy"
    ],
    "wof:name":"Sinan Koray",
    "wof:placetype":"venue"
},
  "geometry": {"coordinates":[151.00262451200001,-33.7744941711],"type":"Point"}
}