{
  "type": "Feature",
  "properties": {
    "iso:country":"AU",
    "sg:address":"51 New Lindum Rd",
    "sg:city":"Wynnum West",
    "sg:classifiers":[
        {
            "category":"Social Services",
            "subcategory":"Retirement Home",
            "type":"Services"
        }
    ],
    "sg:phone":"+61 7 3893 2172",
    "sg:postcode":"4178",
    "sg:province":"QLD",
    "sg:tags":[
        "village"
    ],
    "wof:name":"Village Life",
    "wof:placetype":"venue"
},
  "geometry": {"coordinates":[153.15362548799999,-27.4511470795],"type":"Point"}
}