{
  "type": "Feature",
  "properties": {
    "iso:country":"AU",
    "sg:address":"541 Hampton St",
    "sg:city":"Hampton",
    "sg:classifiers":[
        {
            "category":"Personal",
            "subcategory":"Day Spa",
            "type":"Services"
        }
    ],
    "sg:phone":"+61 3 9598 7866",
    "sg:postcode":"3188",
    "sg:province":"VIC",
    "wof:name":"Endota Spa",
    "wof:placetype":"venue"
},
  "geometry": {"coordinates":[145.00352477999999,-37.9311141968],"type":"Point"}
}