{
  "type": "Feature",
  "properties": {
    "iso:country":"AU",
    "sg:address":"99 Lahrs Rd",
    "sg:city":"Ormeau",
    "sg:classifiers":[
        {
            "category":"Professional",
            "subcategory":"Detective & Security Services",
            "type":"Services"
        }
    ],
    "sg:phone":"+61 7 5547 5388",
    "sg:postcode":"4208",
    "sg:province":"QLD",
    "sg:tags":[
        "consultant",
        "laser"
    ],
    "wof:name":"GC Lasercutting",
    "wof:placetype":"venue"
},
  "geometry": {"coordinates":[153.24888610799999,-27.7610664368],"type":"Point"}
}