{
  "type": "Feature",
  "properties": {
    "addr:full":"65 Inverness Ave Penshurst NSW 2222",
    "addr:housenumber":"65",
    "addr:postcode":"2222",
    "addr:street":"Inverness Ave",
    "iso:country":"AU",
    "sg:address":"65 Inverness Ave",
    "sg:city":"Penshurst",
    "sg:classifiers":[
        {
            "category":"Professional",
            "subcategory":"Detective & Security Services",
            "type":"Services"
        }
    ],
    "sg:phone":"+61 2 9580 5062",
    "sg:postcode":"2222",
    "sg:province":"NSW",
    "sg:tags":[
        "equipment",
        "window",
        "doors"
    ],
    "wof:name":"Fort Knox Security",
    "wof:placetype":"venue"
},
  "geometry": {"coordinates":[151.08050537099999,-33.9602165222],"type":"Point"}
}