{
  "type": "Feature",
  "properties": {
    "iso:country":"AU",
    "sg:address":"240 West Coast Hwy",
    "sg:city":"Scarborough",
    "sg:classifiers":[
        {
            "category":"Travel",
            "subcategory":"Hotels & Motels",
            "type":"Entertainment"
        }
    ],
    "sg:phone":"+61 8 9341 1119",
    "sg:postcode":"6019",
    "sg:province":"WA",
    "sg:tags":[
        "pub"
    ],
    "wof:name":"White Sands Tavern",
    "wof:placetype":"venue"
},
  "geometry": {"coordinates":[115.758079529,-31.8982849121],"type":"Point"}
}