{
  "type": "Feature",
  "properties": {
    "iso:country":"AU",
    "sg:address":"Unit 17 135 Mooringe Ave",
    "sg:city":"Camden Park",
    "sg:classifiers":[
        {
            "category":"Manufacturing",
            "subcategory":"Wood Products",
            "type":"Manufacturing & Wholesale Goods"
        }
    ],
    "sg:phone":"+61 8 8295 3393",
    "sg:postcode":"5038",
    "sg:province":"SA",
    "sg:tags":[
        "polisher",
        "french"
    ],
    "wof:name":"Renshaw Furniture Polishing",
    "wof:placetype":"venue"
},
  "geometry": {"coordinates":[138.53909301799999,-34.9606056213],"type":"Point"}
}