{
  "type": "Feature",
  "properties": {
    "iso:country":"AU",
    "sg:address":"Shop M30 Werribee Plaza, Cnr Derrimut Rd",
    "sg:city":"Hoppers Crossing",
    "sg:classifiers":[
        {
            "category":"Food & Beverages",
            "subcategory":"Bakery",
            "type":"Retail Goods"
        }
    ],
    "sg:phone":"+61 3 9749 6863",
    "sg:postcode":"3029",
    "sg:province":"VIC",
    "sg:tags":[
        "baker"
    ],
    "wof:name":"Bakers Delight Ltd",
    "wof:placetype":"venue"
},
  "geometry": {"coordinates":[144.685394,-37.864441],"type":"Point"}
}