{
  "type": "Feature",
  "properties": {
    "addr:full":"29 Mason Rd D&#039;Aguilar QLD 4514",
    "addr:housenumber":"29",
    "addr:postcode":"4514",
    "addr:street":"Mason Rd;Aguilar",
    "iso:country":"AU",
    "sg:address":"29 Mason Rd",
    "sg:city":"D&#039;Aguilar",
    "sg:classifiers":[
        {
            "category":"Home & Garden",
            "subcategory":"Building Materials",
            "type":"Retail Goods"
        }
    ],
    "sg:phone":"+61 7 5496 1517",
    "sg:postcode":"4514",
    "sg:province":"QLD",
    "sg:tags":[
        "lawn",
        "cutting",
        "maintenance"
    ],
    "wof:name":"Pebbles & Bam Bams Cleaning & Mowing Services",
    "wof:placetype":"venue"
},
  "geometry": {"coordinates":[152.79049699999999,-26.974051],"type":"Point"}
}