{
  "type": "Feature",
  "properties": {
    "addr:full":"911 Beaufort St Inglewood WA 6052",
    "addr:housenumber":"911",
    "addr:postcode":"6052",
    "addr:street":"Beaufort St",
    "iso:country":"AU",
    "sg:address":"911 Beaufort St",
    "sg:city":"Inglewood",
    "sg:classifiers":[
        {
            "category":"Home & Garden",
            "subcategory":"Household Appliances",
            "type":"Retail Goods"
        }
    ],
    "sg:phone":"+61 8 9370 1133",
    "sg:postcode":"6052",
    "sg:province":"WA",
    "sg:tags":[
        "equipment",
        "gas"
    ],
    "wof:name":"Inglewood Gas & Electrical Discounters",
    "wof:placetype":"venue"
},
  "geometry": {"coordinates":[115.886642456,-31.9209861755],"type":"Point"}
}