{
  "type": "Feature",
  "properties": {
    "addr:full":"U5/ 3 Carnegie Pl Blacktown NSW 2148",
    "addr:housenumber":"3",
    "addr:postcode":"2148",
    "addr:street":"U5 /;Pl",
    "iso:country":"AU",
    "sg:address":"U5/ 3 Carnegie Pl",
    "sg:city":"Blacktown",
    "sg:classifiers":[
        {
            "category":"Building & Trades",
            "subcategory":"Construction",
            "type":"Services"
        }
    ],
    "sg:phone":"+61 2 9621 1483",
    "sg:postcode":"2148",
    "sg:province":"NSW",
    "sg:tags":[
        "spouting",
        "guttering"
    ],
    "wof:name":"Profix Guteering",
    "wof:placetype":"venue"
},
  "geometry": {"coordinates":[150.90618896500001,-33.7542877197],"type":"Point"}
}