{
  "type": "Feature",
  "properties": {
    "addr:full":"9 parsons St Alice Springs NT 0870",
    "addr:housenumber":"9",
    "addr:postcode":"nt 0870",
    "addr:street":"Parsons St",
    "iso:country":"AU",
    "sg:address":"9 parsons St",
    "sg:city":"Alice Springs",
    "sg:classifiers":[
        {
            "category":"Professional",
            "subcategory":"Accounting & Tax Preparation",
            "type":"Services"
        }
    ],
    "sg:phone":"+61 8 8950 7000",
    "sg:postcode":"0870",
    "sg:province":"NT",
    "sg:tags":[
        "consultant",
        "taxation"
    ],
    "wof:name":"Deloitte",
    "wof:placetype":"venue"
},
  "geometry": {"coordinates":[133.88153076200001,-23.6983337402],"type":"Point"}
}