{
  "type": "Feature",
  "properties": {
    "iso:country":"AU",
    "sg:address":"5 Bight Crt",
    "sg:city":"San Remo",
    "sg:classifiers":[
        {
            "category":"Professional",
            "subcategory":"Business Services",
            "type":"Services"
        }
    ],
    "sg:phone":"+61 8 9581 6677",
    "sg:postcode":"6210",
    "sg:province":"WA",
    "sg:tags":[
        "drafting"
    ],
    "wof:name":"Dolphin Design & Drafting",
    "wof:placetype":"venue"
},
  "geometry": {"coordinates":[115.74237100000001,-32.495178],"type":"Point"}
}