{
  "type": "Feature",
  "properties": {
    "addr:full":"21 Main Rd Boolaroo NSW 2284",
    "addr:housenumber":"21",
    "addr:postcode":"2284",
    "addr:street":"Main Rd",
    "iso:country":"AU",
    "sg:address":"21 Main Rd",
    "sg:city":"Boolaroo",
    "sg:classifiers":[
        {
            "category":"Fast Food",
            "type":"Food & Drink"
        }
    ],
    "sg:phone":"+61 2 4958 1543",
    "sg:postcode":"2284",
    "sg:province":"NSW",
    "sg:tags":[
        "away",
        "take"
    ],
    "wof:name":"Boolaroo Pie Cake & Sandwich Shop",
    "wof:placetype":"venue"
},
  "geometry": {"coordinates":[151.62310790999999,-32.9524765015],"type":"Point"}
}