{
  "type": "Feature",
  "properties": {
    "addr:full":"25 Barrie Rd Tullamarine VIC 3043",
    "addr:housenumber":"25",
    "addr:postcode":"3043",
    "addr:street":"Barrie Rd",
    "iso:country":"AU",
    "sg:address":"25 Barrie Rd",
    "sg:city":"Tullamarine",
    "sg:classifiers":[
        {
            "category":"Wholesale",
            "subcategory":"Machinery & Supplies",
            "type":"Manufacturing & Wholesale Goods"
        }
    ],
    "sg:phone":"+61 3 9330 4953",
    "sg:postcode":"3043",
    "sg:province":"VIC",
    "sg:tags":[
        "engineer"
    ],
    "wof:name":"Alltrade Industrial Supplies",
    "wof:placetype":"venue"
},
  "geometry": {"coordinates":[144.87835693400001,-37.6922683716],"type":"Point"}
}