{
  "type": "Feature",
  "properties": {
    "iso:country":"AU",
    "sg:address":"Shop 87",
    "sg:city":", Watergardens Shopping Centre Taylors Lakes",
    "sg:classifiers":[
        {
            "category":"Personal",
            "subcategory":"Beauty Salon",
            "type":"Services"
        }
    ],
    "sg:phone":"+61 3 8361 5400",
    "sg:postcode":"3038",
    "sg:province":"VIC",
    "sg:tags":[
        "hairdresser"
    ],
    "wof:name":"Hairhouse Warehouse",
    "wof:placetype":"venue"
},
  "geometry": {"coordinates":[144.78132600000001,-37.696911],"type":"Point"}
}