{
  "type": "Feature",
  "properties": {
    "iso:country":"AU",
    "sg:address":"78 Macqueen St",
    "sg:city":"Aberdeen",
    "sg:classifiers":[
        {
            "category":"Health Services",
            "subcategory":"Doctor",
            "type":"Services"
        }
    ],
    "sg:phone":"+61 2 6543 7201",
    "sg:postcode":"2336",
    "sg:province":"NSW",
    "sg:tags":[
        "medical",
        "practitioner"
    ],
    "wof:name":"Surman Services Pty Ltd",
    "wof:placetype":"venue"
},
  "geometry": {"coordinates":[150.89076232900001,-32.1628837585],"type":"Point"}
}