{
  "type": "Feature",
  "properties": {
    "iso:country":"AU",
    "sg:address":"2 Laurie Rd",
    "sg:city":"Manly Vale",
    "sg:classifiers":[
        {
            "category":"Arena",
            "subcategory":"Indoor Arena",
            "type":"Entertainment"
        }
    ],
    "sg:phone":"+61 2 9949 3939",
    "sg:postcode":"2093",
    "sg:province":"NSW",
    "sg:tags":[
        "modelmakers"
    ],
    "wof:name":"Dennewald Ian",
    "wof:placetype":"venue"
},
  "geometry": {"coordinates":[151.27041625999999,-33.7861404419],"type":"Point"}
}