{
  "type": "Feature",
  "properties": {
    "addr:full":"243 Park St Ballarat West VIC 3350",
    "addr:housenumber":"243",
    "addr:postcode":"3350",
    "addr:street":"Park St",
    "iso:country":"AU",
    "sg:address":"243 Park St",
    "sg:city":"Ballarat West",
    "sg:classifiers":[
        {
            "category":"Retail",
            "subcategory":"Auto Repair",
            "type":"Services"
        }
    ],
    "sg:phone":"+61 3 5336 1600",
    "sg:postcode":"3350",
    "sg:province":"VIC",
    "sg:tags":[
        "beater",
        "painter",
        "panel"
    ],
    "wof:name":"3P Automotive",
    "wof:placetype":"venue"
},
  "geometry": {"coordinates":[143.824387,-37.57061],"type":"Point"}
}