{
  "type": "Feature",
  "properties": {
    "iso:country":"AU",
    "sg:address":"34 Beecroft Rd",
    "sg:city":"Epping",
    "sg:classifiers":[
        {
            "category":"Education",
            "subcategory":"Music School",
            "type":"Public Place"
        }
    ],
    "sg:phone":"+61 2 9868 6711",
    "sg:postcode":"2121",
    "sg:province":"NSW",
    "sg:tags":[
        "teacher"
    ],
    "wof:name":"Vivaldi's",
    "wof:placetype":"venue"
},
  "geometry": {"coordinates":[151.08200073200001,-33.7737312317],"type":"Point"}
}