{
  "type": "Feature",
  "properties": {
    "iso:country":"AU",
    "sg:address":"Unit 6/ 11 Donkin St",
    "sg:city":"West End (Brisbane)",
    "sg:classifiers":[
        {
            "category":"Communications",
            "subcategory":"Television Station",
            "type":"Services"
        }
    ],
    "sg:phone":"+61 7 3844 9883",
    "sg:postcode":"4101",
    "sg:province":"QLD",
    "sg:tags":[
        "equipment",
        "laser"
    ],
    "wof:name":"Queensland Survey Instrument Services",
    "wof:placetype":"venue"
},
  "geometry": {"coordinates":[153.00823974599999,-27.4763336182],"type":"Point"}
}