{
  "type": "Feature",
  "properties": {
    "addr:full":"103 Bridge St Uralla NSW 2358",
    "addr:housenumber":"103",
    "addr:postcode":"2358",
    "addr:street":"Bridge St",
    "iso:country":"AU",
    "sg:address":"103 Bridge St",
    "sg:city":"Uralla",
    "sg:classifiers":[
        {
            "category":"Retail",
            "subcategory":"Car Wash",
            "type":"Services"
        }
    ],
    "sg:phone":"+61 2 6778 3600",
    "sg:postcode":"2358",
    "sg:province":"NSW",
    "sg:tags":[
        "merchant",
        "oil",
        "refiner"
    ],
    "wof:name":"Caltex",
    "wof:placetype":"venue"
},
  "geometry": {"coordinates":[151.498214722,-30.642950058],"type":"Point"}
}