{
  "type": "Feature",
  "properties": {
    "addr:full":"Shop 1/22 Murray St Port Macquarie NSW 2444",
    "addr:housenumber":"shop 1 / 22",
    "addr:postcode":"2444",
    "addr:street":"Murray St",
    "iso:country":"AU",
    "sg:address":"Shop 1/22 Murray St",
    "sg:city":"Port Macquarie",
    "sg:classifiers":[
        {
            "category":"Shopping",
            "subcategory":"Crafts & Fabrics",
            "type":"Retail Goods"
        }
    ],
    "sg:phone":"+61 2 6583 3257",
    "sg:postcode":"2444",
    "sg:province":"NSW",
    "sg:tags":[
        "supply"
    ],
    "wof:name":"Retallacks Creative Sewing Centre",
    "wof:placetype":"venue"
},
  "geometry": {"coordinates":[152.910965,-31.428513],"type":"Point"}
}