{
  "type": "Feature",
  "properties": {
    "addr:full":"18 Sheridan Crt Dingley Village VIC 3172",
    "addr:housenumber":"18",
    "addr:postcode":"3172",
    "addr:street":"Sheridan Crt",
    "iso:country":"AU",
    "sg:address":"18 Sheridan Crt",
    "sg:city":"Dingley Village",
    "sg:classifiers":[
        {
            "category":"Utilities",
            "subcategory":"Electric",
            "type":"Services"
        }
    ],
    "sg:phone":"+61 415 527 665",
    "sg:postcode":"3172",
    "sg:province":"VIC",
    "sg:tags":[
        "electrical",
        "contractor"
    ],
    "wof:name":"Oz Electrics",
    "wof:placetype":"venue"
},
  "geometry": {"coordinates":[145.11965942399999,-37.9758644104],"type":"Point"}
}