{
  "type": "Feature",
  "properties": {
    "addr:full":"31 Hastings Pde North Bondi NSW 2026",
    "addr:housenumber":"31",
    "addr:postcode":"2026",
    "addr:street":"Hastings Pde",
    "iso:country":"AU",
    "sg:address":"31 Hastings Pde",
    "sg:city":"North Bondi",
    "sg:classifiers":[
        {
            "category":"Retail",
            "subcategory":"Laundry & Dry Cleaning",
            "type":"Services"
        }
    ],
    "sg:phone":"+61 2 9130 8711",
    "sg:postcode":"2026",
    "sg:province":"NSW",
    "wof:name":"Bondi North Quick Wash",
    "wof:placetype":"venue"
},
  "geometry": {"coordinates":[151.279022217,-33.8864479065],"type":"Point"}
}