{
  "type": "Feature",
  "properties": {
    "addr:full":"Lot 2082 Hassal St Wetherill Park NSW 2164",
    "addr:housenumber":"2082",
    "addr:postcode":"2164",
    "addr:street":"Hassal St",
    "iso:country":"AU",
    "sg:address":"Lot 2082 Hassal St",
    "sg:city":"Wetherill Park",
    "sg:classifiers":[
        {
            "category":"Manufacturing",
            "subcategory":"Metals",
            "type":"Manufacturing & Wholesale Goods"
        }
    ],
    "sg:phone":"+61 2 9724 1568",
    "sg:postcode":"2164",
    "sg:province":"NSW",
    "sg:tags":[
        "wholesaler",
        "aluminium",
        "mfrs"
    ],
    "wof:name":"PanAsia Aluminium (Sydney) Pty Ltd",
    "wof:placetype":"venue"
},
  "geometry": {"coordinates":[150.91270446799999,-33.8397026062],"type":"Point"}
}