{
  "type": "Feature",
  "properties": {
    "iso:country":"AU",
    "sg:address":"1 Glenbrook Rd",
    "sg:city":"Clematis",
    "sg:classifiers":[
        {
            "category":"Building & Trades",
            "subcategory":"Plumbing",
            "type":"Services"
        }
    ],
    "sg:phone":"+61 413 422 842",
    "sg:postcode":"3782",
    "sg:province":"VIC",
    "sg:tags":[
        "plumber",
        "gasfitters"
    ],
    "wof:name":"Sangsters Plumbing Service",
    "wof:placetype":"venue"
},
  "geometry": {"coordinates":[145.418396,-37.934471],"type":"Point"}
}