{
  "type": "Feature",
  "properties": {
    "addr:full":"21 Minerva Rd Herne Hill VIC 3218",
    "addr:housenumber":"21",
    "addr:postcode":"3218",
    "addr:street":"Minerva Rd",
    "iso:country":"AU",
    "sg:address":"21 Minerva Rd",
    "sg:city":"Herne Hill",
    "sg:classifiers":[
        {
            "category":"Shopping",
            "subcategory":"Stationery & Office Supplies",
            "type":"Retail Goods"
        }
    ],
    "sg:phone":"+61 3 5224 1970",
    "sg:postcode":"3218",
    "sg:province":"VIC",
    "wof:name":"Ink Again",
    "wof:placetype":"venue"
},
  "geometry": {"coordinates":[144.331634522,-38.1304969788],"type":"Point"}
}