{
  "type": "Feature",
  "properties": {
    "addr:full":"15 Felspar St Welshpool WA 6106",
    "addr:housenumber":"15",
    "addr:postcode":"6106",
    "addr:street":"Felspar St",
    "iso:country":"AU",
    "sg:address":"15 Felspar St",
    "sg:city":"Welshpool",
    "sg:classifiers":[
        {
            "category":"Retail",
            "subcategory":"Storage",
            "type":"Services"
        }
    ],
    "sg:phone":"+61 8 9258 7166",
    "sg:postcode":"6106",
    "sg:province":"WA",
    "sg:tags":[
        "shelving",
        "system"
    ],
    "wof:name":"Budget Racking & Storage Systems",
    "wof:placetype":"venue"
},
  "geometry": {"coordinates":[115.97081756599999,-32.0006027222],"type":"Point"}
}