{
  "type": "Feature",
  "properties": {
    "addr:full":"50 Normandy Pl Port Lincoln SA 5606",
    "addr:housenumber":"50",
    "addr:postcode":"5606",
    "addr:street":"Normandy Pl",
    "iso:country":"AU",
    "sg:address":"50 Normandy Pl",
    "sg:city":"Port Lincoln",
    "sg:classifiers":[
        {
            "category":"Retail",
            "subcategory":"Auto Repair",
            "type":"Services"
        }
    ],
    "sg:phone":"+61 8 8682 2368",
    "sg:postcode":"5606",
    "sg:province":"SA",
    "sg:tags":[
        "repairer",
        "motor",
        "engineer"
    ],
    "wof:name":"Smith W A & M F",
    "wof:placetype":"venue"
},
  "geometry": {"coordinates":[135.846237,-34.714397],"type":"Point"}
}