{
  "type": "Feature",
  "properties": {
    "iso:country":"AU",
    "sg:address":"550 Smollett St",
    "sg:city":"Albury",
    "sg:classifiers":[
        {
            "category":"Professional",
            "subcategory":"Computer Services",
            "type":"Services"
        }
    ],
    "sg:phone":"+61 2 6041 4624",
    "sg:postcode":"2640",
    "sg:province":"NSW",
    "sg:tags":[
        "technical",
        "support"
    ],
    "wof:name":"Netrics",
    "wof:placetype":"venue"
},
  "geometry": {"coordinates":[146.91160583499999,-36.0824356079],"type":"Point"}
}