{
  "type": "Feature",
  "properties": {
    "addr:full":"44 Formby Rd Devonport TAS 7310",
    "addr:housenumber":"44",
    "addr:postcode":"7310",
    "addr:street":"Formby Rd",
    "iso:country":"AU",
    "sg:address":"44 Formby Rd",
    "sg:city":"Devonport",
    "sg:classifiers":[
        {
            "category":"Professional",
            "subcategory":"Accounting & Tax Preparation",
            "type":"Services"
        }
    ],
    "sg:phone":"+61 3 6423 3404",
    "sg:postcode":"7310",
    "sg:province":"TAS",
    "sg:tags":[
        "accountant",
        "auditor"
    ],
    "wof:name":"Lakeden Business Services Pty Ltd",
    "wof:placetype":"venue"
},
  "geometry": {"coordinates":[146.347045898,-41.1763572693],"type":"Point"}
}