{
  "type": "Feature",
  "properties": {
    "addr:full":"Stall 44 Central Market Adelaide SA 5000",
    "addr:housenumber":"44",
    "addr:postcode":"5000",
    "addr:street":"Central Market",
    "iso:country":"AU",
    "sg:address":"Stall 44 Central Market",
    "sg:city":"Adelaide",
    "sg:classifiers":[
        {
            "category":"Organizations",
            "subcategory":"Community Association",
            "type":"Services"
        }
    ],
    "sg:phone":"+61 8 8231 0347",
    "sg:postcode":"5000",
    "sg:province":"SA",
    "sg:tags":[
        "cheese",
        "product"
    ],
    "wof:name":"Smelly Cheese Shop The",
    "wof:placetype":"venue"
},
  "geometry": {"coordinates":[138.597854614,-34.9216308594],"type":"Point"}
}