{
  "type": "Feature",
  "properties": {
    "addr:full":"133 Hawdon St Heidelberg VIC 3084",
    "addr:housenumber":"133",
    "addr:postcode":"3084",
    "addr:street":"Hawdon St",
    "iso:country":"AU",
    "sg:address":"133 Hawdon St",
    "sg:city":"Heidelberg",
    "sg:classifiers":[
        {
            "category":"Health Services",
            "subcategory":"Health Practitioner",
            "type":"Services"
        }
    ],
    "sg:phone":"+61 3 9455 1160",
    "sg:postcode":"3084",
    "sg:province":"VIC",
    "sg:tags":[
        "psychologist"
    ],
    "wof:name":"Nichols Jenny",
    "wof:placetype":"venue"
},
  "geometry": {"coordinates":[145.06509399399999,-37.7525367737],"type":"Point"}
}