{
  "type": "Feature",
  "properties": {
    "addr:full":"255 President Ave Miranda NSW 2228",
    "addr:housenumber":"255",
    "addr:postcode":"2228",
    "addr:street":"President Ave Miranda",
    "iso:country":"AU",
    "sg:address":"255 President Ave",
    "sg:city":"Miranda",
    "sg:classifiers":[
        {
            "category":"Building & Trades",
            "subcategory":"Landscaping Services",
            "type":"Services"
        }
    ],
    "sg:phone":"+61 415 262 013",
    "sg:postcode":"2228",
    "sg:province":"NSW",
    "sg:tags":[
        "designer",
        "landscape",
        "contractor"
    ],
    "wof:name":"Illawong Landscape & Paving",
    "wof:placetype":"venue"
},
  "geometry": {"coordinates":[151.09445190400001,-34.0389442444],"type":"Point"}
}