{
  "type": "Feature",
  "properties": {
    "addr:full":"Shop 223 Redbank Plaza Collingwood Drv Redbank QLD 4301",
    "addr:housenumber":"223",
    "addr:postcode":"4301",
    "addr:street":"Redbank Plaza Collingwood Drv",
    "iso:country":"AU",
    "sg:address":"Shop 223 Redbank Plaza Collingwood Drv",
    "sg:city":"Redbank",
    "sg:classifiers":[
        {
            "category":"Shopping",
            "subcategory":"Music",
            "type":"Retail Goods"
        }
    ],
    "sg:phone":"+61 7 3818 0766",
    "sg:postcode":"4301",
    "sg:province":"QLD",
    "sg:tags":[
        "store"
    ],
    "wof:name":"Sanity",
    "wof:placetype":"venue"
},
  "geometry": {"coordinates":[152.870407105,-27.6047439575],"type":"Point"}
}