{
  "type": "Feature",
  "properties": {
    "addr:full":"Cnr Charlotte & Walker Sts Cooktown QLD 4895",
    "addr:postcode":"4895",
    "iso:country":"AU",
    "sg:address":"Cnr Charlotte & Walker Sts",
    "sg:city":"Cooktown",
    "sg:classifiers":[
        {
            "category":"Food & Beverages",
            "subcategory":"Liquor & Beverages",
            "type":"Retail Goods"
        }
    ],
    "sg:phone":"+61 7 4069 5614",
    "sg:postcode":"4895",
    "sg:province":"QLD",
    "sg:tags":[
        "store"
    ],
    "wof:name":"Cooktown Hotel Bottle Shop",
    "wof:placetype":"venue"
},
  "geometry": {"coordinates":[145.24740600600001,-15.4748363495],"type":"Point"}
}