{
  "type": "Feature",
  "properties": {
    "addr:full":"258 Sheridan St Cairns QLD 4870",
    "addr:housenumber":"258",
    "addr:postcode":"4870",
    "addr:street":"Sheridan St",
    "iso:country":"AU",
    "sg:address":"258 Sheridan St",
    "sg:city":"Cairns",
    "sg:classifiers":[
        {
            "category":"Professional",
            "subcategory":"Art Services",
            "type":"Services"
        }
    ],
    "sg:phone":"+61 7 4051 4039",
    "sg:postcode":"4870",
    "sg:province":"QLD",
    "sg:tags":[
        "interior",
        "designer"
    ],
    "wof:name":"Deasy Interiors",
    "wof:placetype":"venue"
},
  "geometry": {"coordinates":[145.761917114,-16.9093551636],"type":"Point"}
}