{
  "type": "Feature",
  "properties": {
    "addr:full":"Ste7/ 363 Crown St Wollongong NSW 2500",
    "addr:housenumber":"363",
    "addr:postcode":"2500",
    "addr:street":"Crown St",
    "iso:country":"AU",
    "sg:address":"Ste7/ 363 Crown St",
    "sg:city":"Wollongong",
    "sg:classifiers":[
        {
            "category":"Health Services",
            "subcategory":"Dentist",
            "type":"Services"
        }
    ],
    "sg:phone":"+61 2 4229 9182",
    "sg:postcode":"2500",
    "sg:province":"NSW",
    "wof:name":"Everyday Family Dental Care",
    "wof:placetype":"venue"
},
  "geometry": {"coordinates":[150.890289,-34.426338],"type":"Point"}
}