{
  "type": "Feature",
  "properties": {
    "iso:country":"AU",
    "sg:address":"226 Corrimal St",
    "sg:city":"Wollongong",
    "sg:classifiers":[
        {
            "category":"Shopping",
            "subcategory":"Mobile Phones",
            "type":"Retail Goods"
        }
    ],
    "sg:phone":"+61 1300 769 000",
    "sg:postcode":"2500",
    "sg:province":"NSW",
    "sg:tags":[
        "telephone",
        "accessory"
    ],
    "wof:name":"Endeavour Connect",
    "wof:placetype":"venue"
},
  "geometry": {"coordinates":[150.89773600000001,-34.435043],"type":"Point"}
}