{
  "type": "Feature",
  "properties": {
    "addr:full":"32 Chopping St Manjimup WA 6258",
    "addr:housenumber":"32",
    "addr:postcode":"6258",
    "addr:street":"Chopping St",
    "iso:country":"AU",
    "sg:address":"32 Chopping St",
    "sg:city":"Manjimup",
    "sg:classifiers":[
        {
            "category":"Farming",
            "subcategory":"Farm & Veterinary Services",
            "type":"Manufacturing & Wholesale Goods"
        }
    ],
    "sg:phone":"+61 8 9777 1580",
    "sg:postcode":"6258",
    "sg:province":"WA",
    "sg:tags":[
        "irrigation",
        "reticulation",
        "system"
    ],
    "wof:name":"Rob Kuzich & Co",
    "wof:placetype":"venue"
},
  "geometry": {"coordinates":[116.138397217,-34.2514190674],"type":"Point"}
}