{
  "type": "Feature",
  "properties": {
    "iso:country":"AU",
    "sg:address":"3 Amayla Crs",
    "sg:city":"Carrum Downs",
    "sg:classifiers":[
        {
            "category":"Building & Trades",
            "subcategory":"Construction",
            "type":"Services"
        }
    ],
    "sg:phone":"+61 3 9776 8355",
    "sg:postcode":"3201",
    "sg:province":"VIC",
    "sg:tags":[
        "home",
        "air conditioning"
    ],
    "wof:name":"A AAAB Precision Heating & Cooling",
    "wof:placetype":"venue"
},
  "geometry": {"coordinates":[145.17598,-38.09708],"type":"Point"}
}