{
  "type": "Feature",
  "properties": {
    "addr:full":"1301 Botany Rd Mascot NSW 2020",
    "addr:housenumber":"1301",
    "addr:postcode":"2020",
    "addr:street":"Botany Rd",
    "iso:country":"AU",
    "sg:address":"1301 Botany Rd",
    "sg:city":"Mascot",
    "sg:classifiers":[
        {
            "category":"Retail",
            "subcategory":"Event Space",
            "type":"Services"
        }
    ],
    "sg:phone":"+61 2 9700 9822",
    "sg:postcode":"2020",
    "sg:province":"NSW",
    "sg:tags":[
        "function",
        "organiser"
    ],
    "wof:name":"International Corporate Events Pty Ltd",
    "wof:placetype":"venue"
},
  "geometry": {"coordinates":[151.194458008,-33.9358711243],"type":"Point"}
}