{
  "type": "Feature",
  "properties": {
    "addr:full":"Lvl 1 2 Martin Pl Sydney NSW 2000",
    "addr:housenumber":"2",
    "addr:postcode":"2000",
    "addr:street":"Martin Pl",
    "iso:country":"AU",
    "sg:address":"Lvl 1 2 Martin Pl",
    "sg:city":"Sydney",
    "sg:classifiers":[
        {
            "category":"Manufacturing",
            "subcategory":"Jewelry",
            "type":"Manufacturing & Wholesale Goods"
        }
    ],
    "sg:phone":"+61 2 9775 1000",
    "sg:postcode":"2000",
    "sg:province":"NSW",
    "sg:tags":[
        "mfrg",
        "jeweller"
    ],
    "wof:name":"Australian Pearl Centre Pty Ltd",
    "wof:placetype":"venue"
},
  "geometry": {"coordinates":[151.207275391,-33.8673057556],"type":"Point"}
}