{
  "type": "Feature",
  "properties": {
    "addr:full":"223 Reservoir Drv Wynyard TAS 7325",
    "addr:housenumber":"223",
    "addr:postcode":"7325",
    "addr:street":"Reservoir Drv",
    "iso:country":"AU",
    "sg:address":"223 Reservoir Drv",
    "sg:city":"Wynyard",
    "sg:classifiers":[
        {
            "category":"Farming",
            "subcategory":"Poultry Farm",
            "type":"Manufacturing & Wholesale Goods"
        }
    ],
    "sg:phone":"+61 3 6442 2415",
    "sg:postcode":"7325",
    "sg:province":"TAS",
    "sg:tags":[
        "farmer"
    ],
    "wof:name":"Wilson's Hatchery",
    "wof:placetype":"venue"
},
  "geometry": {"coordinates":[145.72100800000001,-41.010868],"type":"Point"}
}