{
  "type": "Feature",
  "properties": {
    "addr:full":"UA3/ 2a Westall Rd Clayton VIC 3168",
    "addr:housenumber":"/ 2a",
    "addr:postcode":"3168",
    "addr:street":"Westall Rd",
    "iso:country":"AU",
    "sg:address":"UA3/ 2a Westall Rd",
    "sg:city":"Clayton",
    "sg:classifiers":[
        {
            "category":"Organizations",
            "subcategory":"Professional Association",
            "type":"Services"
        }
    ],
    "sg:phone":"+61 3 9544 7588",
    "sg:postcode":"3168",
    "sg:province":"VIC",
    "sg:tags":[
        "web",
        "internet"
    ],
    "wof:name":"I.T. Deluxe Pty Ltd",
    "wof:placetype":"venue"
},
  "geometry": {"coordinates":[145.14338684099999,-37.9245376587],"type":"Point"}
}