{
  "type": "Feature",
  "properties": {
    "addr:full":"31 Belmont St Sutherland NSW 2232",
    "addr:housenumber":"31",
    "addr:postcode":"2232",
    "addr:street":"Belmont St",
    "iso:country":"AU",
    "sg:address":"31 Belmont St",
    "sg:city":"Sutherland",
    "sg:classifiers":[
        {
            "category":"Building & Trades",
            "subcategory":"Construction",
            "type":"Services"
        }
    ],
    "sg:phone":"+61 2 9521 6577",
    "sg:postcode":"2232",
    "sg:province":"NSW",
    "sg:tags":[
        "contractor"
    ],
    "wof:name":"Alvaro Homes",
    "wof:placetype":"venue"
},
  "geometry": {"coordinates":[151.06179809599999,-34.030002594],"type":"Point"}
}