{
  "type": "Feature",
  "properties": {
    "iso:country":"AU",
    "sg:address":"23 Rosalie St",
    "sg:city":"Springvale",
    "sg:classifiers":[
        {
            "category":"Organizations",
            "subcategory":"Membership Organization",
            "type":"Services"
        }
    ],
    "sg:phone":"+61 3 9558 5434",
    "sg:postcode":"3171",
    "sg:province":"VIC",
    "sg:tags":[
        "club",
        "car"
    ],
    "wof:name":"Jaguar Car Club Victoria",
    "wof:placetype":"venue"
},
  "geometry": {"coordinates":[145.156646728,-37.9449806213],"type":"Point"}
}