{
  "type": "Feature",
  "properties": {
    "iso:country":"AU",
    "sg:address":"U2/ 8",
    "sg:city":"Helmshore Way Port Kennedy",
    "sg:classifiers":[
        {
            "category":"Utilities",
            "type":"Services"
        }
    ],
    "sg:phone":"+61 8 9524 6080",
    "sg:postcode":"6172",
    "sg:province":"WA",
    "sg:tags":[
        "refrigeration",
        "industrial",
        "commercial",
        "retail"
    ],
    "wof:name":"All Genera Refridgeration & Washer Services",
    "wof:placetype":"venue"
},
  "geometry": {"coordinates":[115.758827,-32.36829],"type":"Point"}
}