{
  "type": "Feature",
  "properties": {
    "addr:full":"14 Cranwell Rd Balcatta WA 6021",
    "addr:housenumber":"14",
    "addr:postcode":"6021",
    "addr:street":"Cranwell Rd",
    "iso:country":"AU",
    "sg:address":"14 Cranwell Rd",
    "sg:city":"Balcatta",
    "sg:classifiers":[
        {
            "category":"Home & Garden",
            "subcategory":"Kitchen Supply",
            "type":"Retail Goods"
        }
    ],
    "sg:phone":"+61 412 095 702",
    "sg:postcode":"6021",
    "sg:province":"WA",
    "sg:tags":[
        "sharpening"
    ],
    "wof:name":"A1 Saw Sharpening Services",
    "wof:placetype":"venue"
},
  "geometry": {"coordinates":[115.823959351,-31.8747940063],"type":"Point"}
}