{
  "type": "Feature",
  "properties": {
    "addr:full":"39 Storey St Curtin ACT 2605",
    "addr:housenumber":"39",
    "addr:postcode":"2605",
    "addr:street":"Storey St",
    "iso:country":"AU",
    "sg:address":"39 Storey St",
    "sg:city":"Curtin",
    "sg:classifiers":[
        {
            "category":"Building & Trades",
            "subcategory":"Construction",
            "type":"Services"
        }
    ],
    "sg:phone":"+61 2 6281 1215",
    "sg:postcode":"2605",
    "sg:province":"ACT",
    "sg:tags":[
        "contractor"
    ],
    "wof:name":"Clissold A H",
    "wof:placetype":"venue"
},
  "geometry": {"coordinates":[149.07916259800001,-35.3218536377],"type":"Point"}
}