{
  "type": "Feature",
  "properties": {
    "iso:country":"AU",
    "sg:address":"16 Mavros Rd",
    "sg:city":"Elizabeth Downs",
    "sg:classifiers":[
        {
            "category":"Professional",
            "subcategory":"Employment Agencies",
            "type":"Services"
        }
    ],
    "sg:phone":"+61 434 874 833",
    "sg:postcode":"5113",
    "sg:province":"SA",
    "sg:tags":[
        "hire",
        "labour",
        "contractor"
    ],
    "wof:name":"Freedom Chores",
    "wof:placetype":"venue"
},
  "geometry": {"coordinates":[138.68595886200001,-34.7036590576],"type":"Point"}
}