{
  "type": "Feature",
  "properties": {
    "addr:full":"203 Lake Albert Rd Wagga Wagga NSW 2650",
    "addr:housenumber":"203",
    "addr:postcode":"2650",
    "addr:street":"Lake Albert Rd",
    "iso:country":"AU",
    "sg:address":"203 Lake Albert Rd",
    "sg:city":"Wagga Wagga",
    "sg:classifiers":[
        {
            "category":"Personal",
            "subcategory":"Beauty Salon",
            "type":"Services"
        }
    ],
    "sg:phone":"+61 2 6921 4101",
    "sg:postcode":"2650",
    "sg:province":"NSW",
    "sg:tags":[
        "hairdresser"
    ],
    "wof:name":"Kooringal Headstart Haircutters",
    "wof:placetype":"venue"
},
  "geometry": {"coordinates":[147.37234497099999,-35.1480064392],"type":"Point"}
}