{
  "type": "Feature",
  "properties": {
    "addr:full":"Unit 4/ 92 Seville St Fairfield East NSW 2165",
    "addr:housenumber":"92",
    "addr:postcode":"2165",
    "addr:street":"Seville St",
    "iso:country":"AU",
    "sg:address":"Unit 4/ 92 Seville St",
    "sg:city":"Fairfield East",
    "sg:classifiers":[
        {
            "category":"Wholesale",
            "subcategory":"Metals & Minerals",
            "type":"Manufacturing & Wholesale Goods"
        }
    ],
    "sg:phone":"+61 2 9726 0044",
    "sg:postcode":"2165",
    "sg:province":"NSW",
    "sg:tags":[
        "steel",
        "stainless",
        "product",
        "equipment"
    ],
    "wof:name":"E.M. Shopfitters",
    "wof:placetype":"venue"
},
  "geometry": {"coordinates":[150.97781372099999,-33.8730049133],"type":"Point"}
}