{
  "type": "Feature",
  "properties": {
    "addr:full":"Studio 201/ 50 Marshall St Surry Hills NSW 2010",
    "addr:housenumber":"201 / 50",
    "addr:postcode":"2010",
    "addr:street":"Marshall St",
    "iso:country":"AU",
    "sg:address":"Studio 201/ 50 Marshall St",
    "sg:city":"Surry Hills",
    "sg:classifiers":[
        {
            "category":"Professional",
            "subcategory":"Art Services",
            "type":"Services"
        }
    ],
    "sg:phone":"+61 2 8356 9257",
    "sg:postcode":"2010",
    "sg:province":"NSW",
    "sg:tags":[
        "interior",
        "designer"
    ],
    "wof:name":"Grice Lynch Architecture & Interiors",
    "wof:placetype":"venue"
},
  "geometry": {"coordinates":[151.21611023,-33.8869018555],"type":"Point"}
}