{
  "type": "Feature",
  "properties": {
    "iso:country":"AU",
    "sg:address":"559 Barkly St",
    "sg:city":"West Footscray",
    "sg:classifiers":[
        {
            "category":"Restaurant",
            "type":"Food & Drink"
        }
    ],
    "sg:phone":"+61 3 9689 4175",
    "sg:postcode":"3012",
    "sg:province":"VIC",
    "wof:name":"Aangan The Courtyard of India",
    "wof:placetype":"venue"
},
  "geometry": {"coordinates":[144.87661743199999,-37.7973670959],"type":"Point"}
}