{
  "type": "Feature",
  "properties": {
    "addr:full":"12 Ken Tubman Drv Maitland NSW 2320",
    "addr:housenumber":"12",
    "addr:postcode":"2320",
    "addr:street":"Ken Tubman Drv",
    "iso:country":"AU",
    "sg:address":"12 Ken Tubman Drv",
    "sg:city":"Maitland",
    "sg:classifiers":[
        {
            "category":"Health Services",
            "subcategory":"Doctor",
            "type":"Services"
        }
    ],
    "sg:phone":"+61 2 4933 2364",
    "sg:postcode":"2320",
    "sg:province":"NSW",
    "sg:tags":[
        "occupational",
        "safety"
    ],
    "wof:name":"PsychWorks Partnership",
    "wof:placetype":"venue"
},
  "geometry": {"coordinates":[151.55329895,-32.7308998108],"type":"Point"}
}