{
  "type": "Feature",
  "properties": {
    "addr:full":"54 Sackville St Port Fairy VIC 3284",
    "addr:housenumber":"54",
    "addr:postcode":"3284",
    "addr:street":"Sackville St",
    "iso:country":"AU",
    "sg:address":"54 Sackville St",
    "sg:city":"Port Fairy",
    "sg:classifiers":[
        {
            "category":"Building & Trades",
            "subcategory":"Construction",
            "type":"Services"
        }
    ],
    "sg:phone":"+61 3 5568 1745",
    "sg:postcode":"3284",
    "sg:province":"VIC",
    "sg:tags":[
        "contractor"
    ],
    "wof:name":"M M Hearn Architectural Homes",
    "wof:placetype":"venue"
},
  "geometry": {"coordinates":[142.23675537099999,-38.3841972351],"type":"Point"}
}