{
  "type": "Feature",
  "properties": {
    "addr:full":"58 Oldfield Rd Sinnamon Park QLD 4073",
    "addr:housenumber":"58",
    "addr:postcode":"4073",
    "addr:street":"Oldfield Rd",
    "iso:country":"AU",
    "sg:address":"58 Oldfield Rd",
    "sg:city":"Sinnamon Park",
    "sg:classifiers":[
        {
            "category":"Health Services",
            "subcategory":"Doctor",
            "type":"Services"
        }
    ],
    "sg:phone":"+61 7 3279 0444",
    "sg:postcode":"4073",
    "sg:province":"QLD",
    "sg:tags":[
        "medical",
        "practitioner"
    ],
    "wof:name":"Scott Peter Dr",
    "wof:placetype":"venue"
},
  "geometry": {"coordinates":[152.953201294,-27.5455589294],"type":"Point"}
}