{
  "type": "Feature",
  "properties": {
    "iso:country":"AU",
    "sg:address":"9 Blackburn St",
    "sg:city":"St Ives",
    "sg:classifiers":[
        {
            "category":"Health Services",
            "subcategory":"Doctor",
            "type":"Services"
        }
    ],
    "sg:phone":"+61 2 9449 9797",
    "sg:postcode":"2075",
    "sg:province":"NSW",
    "sg:tags":[
        "medical",
        "practitioner"
    ],
    "wof:name":"V Sivaloganathan",
    "wof:placetype":"venue"
},
  "geometry": {"coordinates":[151.177001953,-33.7188148499],"type":"Point"}
}