{
  "type": "Feature",
  "properties": {
    "addr:full":"Shp 3 / 21 Fearn Ave Margaret River WA 6285",
    "addr:housenumber":"/ 21",
    "addr:postcode":"6285",
    "addr:street":"Fearn Ave",
    "iso:country":"AU",
    "sg:address":"Shp 3 / 21 Fearn Ave",
    "sg:city":"Margaret River",
    "sg:classifiers":[
        {
            "category":"Fast Food",
            "type":"Food & Drink"
        }
    ],
    "sg:phone":"+61 8 9757 9000",
    "sg:postcode":"6285",
    "sg:province":"WA",
    "sg:tags":[
        "away",
        "take"
    ],
    "wof:name":"Chow Cuisine To Go",
    "wof:placetype":"venue"
},
  "geometry": {"coordinates":[115.072738648,-33.9517669678],"type":"Point"}
}