{
  "type": "Feature",
  "properties": {
    "iso:country":"AU",
    "sg:address":"PO Box 1076",
    "sg:city":"Howard Springs",
    "sg:classifiers":[
        {
            "category":"Building & Trades",
            "subcategory":"Construction",
            "type":"Services"
        }
    ],
    "sg:phone":"+61 404 486 922",
    "sg:postcode":"0835",
    "sg:province":"NT",
    "sg:tags":[
        "roof"
    ],
    "wof:name":"Mick Taylor Construction",
    "wof:placetype":"venue"
},
  "geometry": {"coordinates":[131.045792,-12.49626],"type":"Point"}
}