{
  "type": "Feature",
  "properties": {
    "addr:full":"PO Box 1076 Howard Springs NT 0835",
    "addr:postcode":"0835",
    "iso:country":"AU",
    "sg:address":"PO Box 1076",
    "sg:city":"Howard Springs",
    "sg:classifiers":[
        {
            "category":"Building & Trades",
            "subcategory":"Construction",
            "type":"Services"
        }
    ],
    "sg:phone":"+61 404 486 922",
    "sg:postcode":"0835",
    "sg:province":"NT",
    "sg:tags":[
        "roof"
    ],
    "wof:name":"Mick Taylor Construction",
    "wof:placetype":"venue"
},
  "geometry": {"coordinates":[131.04579200000001,-12.49626],"type":"Point"}
}