{
  "type": "Feature",
  "properties": {
    "addr:full":"96 Harrington St Hobart TAS 7000",
    "addr:housenumber":"96",
    "addr:postcode":"7000",
    "addr:street":"Harrington St",
    "iso:country":"AU",
    "sg:address":"96 Harrington St",
    "sg:city":"Hobart",
    "sg:classifiers":[
        {
            "category":"Retail",
            "subcategory":"Auto Rental",
            "type":"Services"
        }
    ],
    "sg:phone":"+61 3 6234 5222",
    "sg:postcode":"7000",
    "sg:province":"TAS",
    "sg:tags":[
        "car",
        "hire",
        "minibus"
    ],
    "wof:name":"Budget Truck Rentals",
    "wof:placetype":"venue"
},
  "geometry": {"coordinates":[147.32426452600001,-42.884185791],"type":"Point"}
}