{
  "type": "Feature",
  "properties": {
    "addr:full":"14 Ilmenite Crs Capel WA 6271",
    "addr:housenumber":"14",
    "addr:postcode":"6271",
    "addr:street":"Ilmenite Crs",
    "iso:country":"AU",
    "sg:address":"14 Ilmenite Crs",
    "sg:city":"Capel",
    "sg:classifiers":[
        {
            "category":"Building & Trades",
            "subcategory":"Construction",
            "type":"Services"
        }
    ],
    "sg:phone":"+61 8 9727 2620",
    "sg:postcode":"6271",
    "sg:province":"WA",
    "sg:tags":[
        "earth",
        "excavating",
        "moving",
        "contractor"
    ],
    "wof:name":"Payne D.L. & H.R.",
    "wof:placetype":"venue"
},
  "geometry": {"coordinates":[115.55467224100001,-33.5524711609],"type":"Point"}
}