{
  "type": "Feature",
  "properties": {
    "iso:country":"AU",
    "sg:address":"Hangar 6",
    "sg:city":", Beatty Rd, Archerfield Airport, Archerfield",
    "sg:classifiers":[
        {
            "category":"Manufacturing",
            "subcategory":"Aerospace",
            "type":"Manufacturing & Wholesale Goods"
        }
    ],
    "sg:phone":"+61 7 3277 3833",
    "sg:postcode":"4108",
    "sg:province":"QLD",
    "sg:tags":[
        "equipment",
        "aircraft",
        "maintenance"
    ],
    "wof:name":"Hawker Pacific Pty Ltd",
    "wof:placetype":"venue"
},
  "geometry": {"coordinates":[153.01422119099999,-27.5719165802],"type":"Point"}
}