{
  "type": "Feature",
  "properties": {
    "addr:full":"580 Goodwood Rd Daw Park SA 5041",
    "addr:housenumber":"580",
    "addr:postcode":"5041",
    "addr:street":"Goodwood Rd",
    "iso:country":"AU",
    "sg:address":"580 Goodwood Rd",
    "sg:city":"Daw Park",
    "sg:classifiers":[
        {
            "category":"Fast Food",
            "type":"Food & Drink"
        }
    ],
    "sg:phone":"+61 8 8277 0907",
    "sg:postcode":"5041",
    "sg:province":"SA",
    "sg:tags":[
        "away",
        "take"
    ],
    "wof:name":"Chicken Mate",
    "wof:placetype":"venue"
},
  "geometry": {"coordinates":[138.59179700000001,-34.981682],"type":"Point"}
}