{
  "type": "Feature",
  "properties": {
    "addr:full":"32 Wandella Rd Mornington VIC 3931",
    "addr:housenumber":"32",
    "addr:postcode":"3931",
    "addr:street":"Wandella Rd",
    "iso:country":"AU",
    "sg:address":"32 Wandella Rd",
    "sg:city":"Mornington",
    "sg:classifiers":[
        {
            "category":"Building & Trades",
            "subcategory":"Construction",
            "type":"Services"
        }
    ],
    "sg:phone":"+61 407 927 407",
    "sg:postcode":"3931",
    "sg:province":"VIC",
    "sg:tags":[
        "rendering",
        "cement"
    ],
    "wof:name":"Render Link",
    "wof:placetype":"venue"
},
  "geometry": {"coordinates":[145.04461669899999,-38.2429466248],"type":"Point"}
}