{
  "type": "Feature",
  "properties": {
    "addr:full":"15 Wadhurst Drv Boronia VIC 3155",
    "addr:housenumber":"15",
    "addr:postcode":"3155",
    "addr:street":"Wadhurst Drv",
    "iso:country":"AU",
    "sg:address":"15 Wadhurst Drv",
    "sg:city":"Boronia",
    "sg:classifiers":[
        {
            "category":"Professional",
            "subcategory":"Testing Lab",
            "type":"Services"
        }
    ],
    "sg:phone":"+61 3 9800 3622",
    "sg:postcode":"3155",
    "sg:province":"VIC",
    "sg:tags":[
        "inspection"
    ],
    "wof:name":"Enertech Australia Pty Ltd",
    "wof:placetype":"venue"
},
  "geometry": {"coordinates":[145.253738403,-37.8661003113],"type":"Point"}
}