{
  "type": "Feature",
  "properties": {
    "iso:country":"AU",
    "sg:address":"1 Francis St",
    "sg:city":"Castle Hill",
    "sg:classifiers":[
        {
            "category":"Retail",
            "subcategory":"Veterinary Services",
            "type":"Services"
        }
    ],
    "sg:phone":"+61 2 9634 2712",
    "sg:postcode":"2154",
    "sg:province":"NSW",
    "sg:tags":[
        "surgeon"
    ],
    "wof:name":"Castle Hill Veterinary Hospital",
    "wof:placetype":"venue"
},
  "geometry": {"coordinates":[151.00192260700001,-33.7373085022],"type":"Point"}
}