{
  "type": "Feature",
  "properties": {
    "addr:full":"950 Pacific Hwy Pymble NSW 2073",
    "addr:housenumber":"950",
    "addr:postcode":"2073",
    "addr:street":"Pacific Hwy",
    "iso:country":"AU",
    "sg:address":"950 Pacific Hwy",
    "sg:city":"Pymble",
    "sg:classifiers":[
        {
            "category":"Shopping",
            "subcategory":"Computers & Home Electronics",
            "type":"Retail Goods"
        }
    ],
    "sg:phone":"+61 2 9498 9705",
    "sg:postcode":"2073",
    "sg:province":"NSW",
    "sg:tags":[
        "hardware",
        "equipment"
    ],
    "wof:name":"3M Touch Systems Pty Ltd",
    "wof:placetype":"venue"
},
  "geometry": {"coordinates":[151.14607238799999,-33.7494850159],"type":"Point"}
}