{
  "type": "Feature",
  "properties": {
    "addr:full":"2480 Gold Coast Hwy Mermaid Beach QLD 4218",
    "addr:housenumber":"2480",
    "addr:postcode":"4218",
    "addr:street":"Gold Coast Hwy",
    "iso:country":"AU",
    "sg:address":"2480 Gold Coast Hwy",
    "sg:city":"Mermaid Beach",
    "sg:classifiers":[
        {
            "category":"Personal",
            "subcategory":"Adult",
            "type":"Services"
        }
    ],
    "sg:phone":"+61 7 5575 6777",
    "sg:postcode":"4218",
    "sg:province":"QLD",
    "sg:tags":[
        "product"
    ],
    "wof:name":"Adult X",
    "wof:placetype":"venue"
},
  "geometry": {"coordinates":[153.43447875999999,-28.0439395905],"type":"Point"}
}