{
  "type": "Feature",
  "properties": {
    "iso:country":"AU",
    "sg:address":"56 Enterprise Drv",
    "sg:city":"Beresfield",
    "sg:classifiers":[
        {
            "category":"Building & Trades",
            "subcategory":"Construction",
            "type":"Services"
        }
    ],
    "sg:phone":"+61 2 4964 4888",
    "sg:postcode":"2322",
    "sg:province":"NSW",
    "sg:tags":[
        "welding"
    ],
    "wof:name":"Triple M Sheetmetal Pty Limited",
    "wof:placetype":"venue"
},
  "geometry": {"coordinates":[151.64120483400001,-32.8074188232],"type":"Point"}
}