{
  "type": "Feature",
  "properties": {
    "addr:full":"162 Marius St Tamworth NSW 2340",
    "addr:housenumber":"162",
    "addr:postcode":"2340",
    "addr:street":"Marius St",
    "iso:country":"AU",
    "sg:address":"162 Marius St",
    "sg:city":"Tamworth",
    "sg:classifiers":[
        {
            "category":"Social Services",
            "subcategory":"Retirement Home",
            "type":"Services"
        }
    ],
    "sg:phone":"+61 2 6766 1944",
    "sg:postcode":"2340",
    "sg:province":"NSW",
    "sg:tags":[
        "environmental",
        "consultant",
        "pollution"
    ],
    "wof:name":"Kelley Covey Group Pty Ltd",
    "wof:placetype":"venue"
},
  "geometry": {"coordinates":[150.93244934099999,-31.089679718],"type":"Point"}
}