{
  "type": "Feature",
  "properties": {
    "addr:full":"45 Neville Rd Bridgeman Downs QLD 4035",
    "addr:housenumber":"45",
    "addr:postcode":"4035",
    "addr:street":"Neville Rd",
    "iso:country":"AU",
    "sg:address":"45 Neville Rd",
    "sg:city":"Bridgeman Downs",
    "sg:classifiers":[
        {
            "category":"Building & Trades",
            "subcategory":"Construction",
            "type":"Services"
        }
    ],
    "sg:phone":"+61 7 3263 6344",
    "sg:postcode":"4035",
    "sg:province":"QLD",
    "sg:tags":[
        "contractor"
    ],
    "wof:name":"Corbett N F Pty Ltd",
    "wof:placetype":"venue"
},
  "geometry": {"coordinates":[152.99310299999999,-27.339579],"type":"Point"}
}