{
  "type": "Feature",
  "properties": {
    "iso:country":"AU",
    "sg:address":"9 Virginia St",
    "sg:city":"Mornington",
    "sg:classifiers":[
        {
            "category":"Retail",
            "subcategory":"Auto Repair",
            "type":"Services"
        }
    ],
    "sg:phone":"+61 3 5975 3999",
    "sg:postcode":"3931",
    "sg:province":"VIC",
    "sg:tags":[
        "testing",
        "inspection",
        "motor",
        "vehicle"
    ],
    "wof:name":"Kendall Auto's",
    "wof:placetype":"venue"
},
  "geometry": {"coordinates":[145.046783447,-38.2317504883],"type":"Point"}
}