{
  "type": "Feature",
  "properties": {
    "addr:full":"78 Yaranga Rd Castle Hill NSW 2154",
    "addr:housenumber":"78",
    "addr:postcode":"2154",
    "addr:street":"Yaranga Rd",
    "iso:country":"AU",
    "sg:address":"78 Yaranga Rd",
    "sg:city":"Castle Hill",
    "sg:classifiers":[
        {
            "category":"Building & Trades",
            "subcategory":"Construction",
            "type":"Services"
        }
    ],
    "sg:phone":"+61 418 418 564",
    "sg:postcode":"2154",
    "sg:province":"NSW",
    "sg:tags":[
        "contractor"
    ],
    "wof:name":"Specified Building Services",
    "wof:placetype":"venue"
},
  "geometry": {"coordinates":[151.00624084500001,-33.7182159424],"type":"Point"}
}