{
  "type": "Feature",
  "properties": {
    "addr:full":"67 Bowman Rd Caloundra QLD 4551",
    "addr:housenumber":"67",
    "addr:postcode":"4551",
    "addr:street":"Bowman Rd",
    "iso:country":"AU",
    "sg:address":"67 Bowman Rd",
    "sg:city":"Caloundra",
    "sg:classifiers":[
        {
            "category":"Parking",
            "subcategory":"Garage",
            "type":"Transportation"
        }
    ],
    "sg:phone":"+61 7 5438 2088",
    "sg:postcode":"4551",
    "sg:province":"QLD",
    "sg:tags":[
        "radiographer"
    ],
    "wof:name":"X-Ray And Imaging Caloundra Pty Ltd",
    "wof:placetype":"venue"
},
  "geometry": {"coordinates":[153.12985229500001,-26.8006496429],"type":"Point"}
}