{
  "type": "Feature",
  "properties": {
    "addr:full":"64 Mahoneys Rd Forest Hill VIC 3131",
    "addr:housenumber":"64",
    "addr:postcode":"3131",
    "addr:street":"Mahoneys Rd",
    "iso:country":"AU",
    "sg:address":"64 Mahoneys Rd",
    "sg:city":"Forest Hill",
    "sg:classifiers":[
        {
            "category":"Personal",
            "subcategory":"Sauna",
            "type":"Services"
        }
    ],
    "sg:phone":"+61 1300 663 228",
    "sg:postcode":"3131",
    "sg:province":"VIC",
    "sg:tags":[
        "equipment",
        "accessory"
    ],
    "wof:name":"New Era Imports Pty Ltd",
    "wof:placetype":"venue"
},
  "geometry": {"coordinates":[145.16583251899999,-37.8373413086],"type":"Point"}
}