{
  "type": "Feature",
  "properties": {
    "iso:country":"AU",
    "sg:address":"13 Normoyle Crs",
    "sg:city":"Young",
    "sg:classifiers":[
        {
            "category":"Building & Trades",
            "subcategory":"Plumbing",
            "type":"Services"
        }
    ],
    "sg:phone":"+61 2 6382 1873",
    "sg:postcode":"2594",
    "sg:province":"NSW",
    "sg:tags":[
        "plumber",
        "gasfitters"
    ],
    "wof:name":"S & S Plumbing",
    "wof:placetype":"venue"
},
  "geometry": {"coordinates":[148.29434204099999,-34.3139686584],"type":"Point"}
}