{
  "type": "Feature",
  "properties": {
    "addr:full":"123 Commercial St (West) Mt Gambier SA 5290",
    "addr:housenumber":"123",
    "addr:postcode":"5290",
    "addr:street":"Commercial St West",
    "iso:country":"AU",
    "sg:address":"123 Commercial St",
    "sg:city":"(West) Mt Gambier",
    "sg:classifiers":[
        {
            "category":"Autos & Motor Vehicles",
            "subcategory":"Motorcycle Sales",
            "type":"Retail Goods"
        }
    ],
    "sg:phone":"+61 8 8723 1025",
    "sg:postcode":"5290",
    "sg:province":"SA",
    "sg:tags":[
        "part",
        "recyclers",
        "cycle"
    ],
    "wof:name":"100 % Motorcycle Accessories",
    "wof:placetype":"venue"
},
  "geometry": {"coordinates":[140.78779599999999,-37.830536],"type":"Point"}
}