{
  "type": "Feature",
  "properties": {
    "addr:full":"64 Terry Rd Eastwood NSW 2122",
    "addr:housenumber":"64",
    "addr:postcode":"2122",
    "addr:street":"Terry Rd",
    "iso:country":"AU",
    "sg:address":"64 Terry Rd",
    "sg:city":"Eastwood",
    "sg:classifiers":[
        {
            "category":"Shopping",
            "subcategory":"Bicycles & Sporting Goods",
            "type":"Retail Goods"
        }
    ],
    "sg:phone":"+61 2 9874 2456",
    "sg:postcode":"2122",
    "sg:province":"NSW",
    "sg:tags":[
        "chemical",
        "equipment",
        "pool",
        "swimming"
    ],
    "wof:name":"Eastwood Pool Shop",
    "wof:placetype":"venue"
},
  "geometry": {"coordinates":[151.06785583499999,-33.7904434204],"type":"Point"}
}