{
  "type": "Feature",
  "properties": {
    "addr:full":"4 Return St Dodges Ferry TAS 7173",
    "addr:housenumber":"4",
    "addr:postcode":"7173",
    "addr:street":"Return St",
    "iso:country":"AU",
    "sg:address":"4 Return St",
    "sg:city":"Dodges Ferry",
    "sg:classifiers":[
        {
            "category":"Professional",
            "subcategory":"Accounting & Tax Preparation",
            "type":"Services"
        }
    ],
    "sg:phone":"+61 3 6265 7850",
    "sg:postcode":"7173",
    "sg:province":"TAS",
    "sg:tags":[
        "accountant",
        "auditor"
    ],
    "wof:name":"Absolom C L",
    "wof:placetype":"venue"
},
  "geometry": {"coordinates":[147.62167358400001,-42.8659667969],"type":"Point"}
}