{
  "type": "Feature",
  "properties": {
    "iso:country":"AU",
    "sg:address":"2 Brant Rd",
    "sg:city":"Kelmscott",
    "sg:classifiers":[
        {
            "category":"Home & Garden",
            "subcategory":"Hardware",
            "type":"Retail Goods"
        }
    ],
    "sg:phone":"+61 8 9390 1400",
    "sg:postcode":"6111",
    "sg:province":"WA",
    "sg:tags":[
        "plumber",
        "supply"
    ],
    "wof:name":"Galvins Plumbing Plus",
    "wof:placetype":"venue"
},
  "geometry": {"coordinates":[116.004096985,-32.1281547546],"type":"Point"}
}