{
  "type": "Feature",
  "properties": {
    "iso:country":"AU",
    "sg:address":"5 Toonburra St",
    "sg:city":"Bundaberg Central",
    "sg:classifiers":[
        {
            "category":"Professional",
            "subcategory":"Computer Services",
            "type":"Services"
        }
    ],
    "sg:phone":"+61 7 4152 6800",
    "sg:postcode":"4670",
    "sg:province":"QLD",
    "sg:tags":[
        "package",
        "software"
    ],
    "wof:name":"Computer Market The",
    "wof:placetype":"venue"
},
  "geometry": {"coordinates":[152.35624694800001,-24.8636703491],"type":"Point"}
}