{
  "type": "Feature",
  "properties": {
    "iso:country":"AU",
    "sg:address":"140 Central Ave",
    "sg:city":"Indooroopilly",
    "sg:classifiers":[
        {
            "category":"Travel",
            "subcategory":"Hotels & Motels",
            "type":"Entertainment"
        }
    ],
    "sg:phone":"+61 7 3371 6600",
    "sg:postcode":"4068",
    "sg:province":"QLD",
    "sg:website":"http://www.forestlodge1.com.au",
    "wof:name":"FOREST LODGE APARTMENTS",
    "wof:placetype":"venue"
},
  "geometry": {"coordinates":[152.978683472,-27.5018577576],"type":"Point"}
}