{
  "type": "Feature",
  "properties": {
    "iso:country":"AU",
    "sg:address":"Suite 2, 1632 High St",
    "sg:city":"Glen Iris",
    "sg:classifiers":[
        {
            "category":"Travel",
            "subcategory":"Travel Agent",
            "type":"Entertainment"
        }
    ],
    "sg:phone":"+61 3 9809 8777",
    "sg:postcode":"3146",
    "sg:province":"VIC",
    "sg:tags":[
        "consultant"
    ],
    "wof:name":"Fiji Getaways",
    "wof:placetype":"venue"
},
  "geometry": {"coordinates":[145.05825805699999,-37.8601799011],"type":"Point"}
}