{
  "type": "Feature",
  "properties": {
    "iso:country":"AU",
    "sg:address":"49 Baden Powell St",
    "sg:city":"Maroochydore",
    "sg:classifiers":[
        {
            "category":"Health Services",
            "subcategory":"Doctor",
            "type":"Services"
        }
    ],
    "sg:phone":"+61 7 5409 5700",
    "sg:postcode":"4558",
    "sg:province":"QLD",
    "sg:tags":[
        "medical",
        "practitioner"
    ],
    "wof:name":"Southern X-Ray Clinics",
    "wof:placetype":"venue"
},
  "geometry": {"coordinates":[153.08724975600001,-26.652381897],"type":"Point"}
}