{
  "type": "Feature",
  "properties": {
    "addr:full":"33 Foster St Lake Cargelligo NSW 2672",
    "addr:housenumber":"33",
    "addr:postcode":"2672",
    "addr:street":"Foster St",
    "iso:country":"AU",
    "sg:address":"33 Foster St",
    "sg:city":"Lake Cargelligo",
    "sg:classifiers":[
        {
            "category":"Government",
            "subcategory":"Post Office",
            "type":"Public Place"
        }
    ],
    "sg:phone":"+61 2 6898 1007",
    "sg:postcode":"2672",
    "sg:province":"NSW",
    "sg:tags":[
        "postal"
    ],
    "wof:name":"Australia Post",
    "wof:placetype":"venue"
},
  "geometry": {"coordinates":[146.37403869600001,-33.2982254028],"type":"Point"}
}