{
  "type": "Feature",
  "properties": {
    "iso:country":"AU",
    "sg:address":"64 Peverill St",
    "sg:city":"Tinonee",
    "sg:classifiers":[
        {
            "category":"Professional",
            "subcategory":"Art Services",
            "type":"Services"
        }
    ],
    "sg:phone":"+61 2 6553 1042",
    "sg:postcode":"2430",
    "sg:province":"NSW",
    "sg:tags":[
        "graphic",
        "designer"
    ],
    "wof:name":"Burton Signs & Design",
    "wof:placetype":"venue"
},
  "geometry": {"coordinates":[152.409073,-31.937201],"type":"Point"}
}