{
  "type": "Feature",
  "properties": {
    "addr:full":"398 Taylor St Toowoomba West QLD 4350",
    "addr:housenumber":"398",
    "addr:postcode":"4350",
    "addr:street":"Taylor St",
    "iso:country":"AU",
    "sg:address":"398 Taylor St",
    "sg:city":"Toowoomba West",
    "sg:classifiers":[
        {
            "category":"Retail",
            "subcategory":"Auto Repair",
            "type":"Services"
        }
    ],
    "sg:phone":"+61 7 4634 0954",
    "sg:postcode":"4350",
    "sg:province":"QLD",
    "sg:tags":[
        "engine",
        "reconditioning"
    ],
    "wof:name":"Repco",
    "wof:placetype":"venue"
},
  "geometry": {"coordinates":[151.90353400000001,-27.550394],"type":"Point"}
}