{
  "type": "Feature",
  "properties": {
    "addr:full":"Level 1, 17 Spence St Cairns QLD 4870",
    "addr:housenumber":"17",
    "addr:postcode":"4870",
    "addr:street":"Spence St",
    "iso:country":"AU",
    "sg:address":"Level 1, 17 Spence St",
    "sg:city":"Cairns",
    "sg:classifiers":[
        {
            "category":"Professional",
            "subcategory":"Employment Agencies",
            "type":"Services"
        }
    ],
    "sg:phone":"+61 7 4031 8755",
    "sg:postcode":"4870",
    "sg:province":"QLD",
    "wof:name":"Nurseworldwide",
    "wof:placetype":"venue"
},
  "geometry": {"coordinates":[145.777877808,-16.9235115051],"type":"Point"}
}