{
  "type": "Feature",
  "properties": {
    "iso:country":"AU",
    "sg:address":"21 Bainbridge St",
    "sg:city":"Ormiston",
    "sg:classifiers":[
        {
            "category":"Fast Food",
            "type":"Food & Drink"
        }
    ],
    "sg:phone":"+61 7 3286 2265",
    "sg:postcode":"4160",
    "sg:province":"QLD",
    "sg:tags":[
        "away",
        "take"
    ],
    "wof:name":"Marlyns",
    "wof:placetype":"venue"
},
  "geometry": {"coordinates":[153.25929260300001,-27.5199356079],"type":"Point"}
}