{
  "type": "Feature",
  "properties": {
    "addr:full":"Shop 1/ 109 Kendal St Cowra NSW 2794",
    "addr:housenumber":"shop 1 / 109",
    "addr:postcode":"2794",
    "addr:street":"Kendal St",
    "iso:country":"AU",
    "sg:address":"Shop 1/ 109 Kendal St",
    "sg:city":"Cowra",
    "sg:classifiers":[
        {
            "category":"Shopping",
            "subcategory":"Baby Store",
            "type":"Retail Goods"
        }
    ],
    "sg:phone":"+61 2 6342 1599",
    "sg:postcode":"2794",
    "sg:province":"NSW",
    "sg:tags":[
        "children's",
        "wear"
    ],
    "wof:name":"Hippity Hop The Kids Shop",
    "wof:placetype":"venue"
},
  "geometry": {"coordinates":[148.69776916500001,-33.8355636597],"type":"Point"}
}