{
  "type": "Feature",
  "properties": {
    "addr:full":"PO Box 302 Bexley NSW 2207",
    "addr:postcode":"2207",
    "iso:country":"AU",
    "sg:address":"PO Box 302",
    "sg:city":"Bexley",
    "sg:classifiers":[
        {
            "category":"Farming",
            "subcategory":"Fish & Marine Products",
            "type":"Manufacturing & Wholesale Goods"
        }
    ],
    "sg:phone":"+61 1300 559 902",
    "sg:postcode":"2207",
    "sg:province":"NSW",
    "sg:tags":[
        "organic"
    ],
    "wof:name":"Mizaan Organics Pty Ltd",
    "wof:placetype":"venue"
},
  "geometry": {"coordinates":[151.12481689399999,-33.9513206482],"type":"Point"}
}