{
  "type": "Feature",
  "properties": {
    "addr:full":"245a Great North Rd Five Dock NSW 2046",
    "addr:housenumber":"245a",
    "addr:postcode":"2046",
    "addr:street":"Great North Rd",
    "iso:country":"AU",
    "sg:address":"245a Great North Rd",
    "sg:city":"Five Dock",
    "sg:classifiers":[
        {
            "category":"Personal",
            "subcategory":"Beauty Salon",
            "type":"Services"
        }
    ],
    "sg:phone":"+61 2 9713 2089",
    "sg:postcode":"2046",
    "sg:province":"NSW",
    "sg:tags":[
        "hairdresser"
    ],
    "wof:name":"Tony's International Mens Hair Stylist",
    "wof:placetype":"venue"
},
  "geometry": {"coordinates":[151.13017300000001,-33.864437],"type":"Point"}
}