{
  "type": "Feature",
  "properties": {
    "iso:country":"AU",
    "sg:address":"109 Plateau Rd",
    "sg:city":"Bilgola",
    "sg:classifiers":[
        {
            "category":"Building & Trades",
            "subcategory":"Plumbing",
            "type":"Services"
        }
    ],
    "sg:phone":"+61 410 566 807",
    "sg:postcode":"2107",
    "sg:province":"NSW",
    "sg:tags":[
        "plumber",
        "gasfitters"
    ],
    "wof:name":"AAA Value Plumbing & Renovations",
    "wof:placetype":"venue"
},
  "geometry": {"coordinates":[151.31968689000001,-33.6429405212],"type":"Point"}
}