{
  "type": "Feature",
  "properties": {
    "iso:country":"AU",
    "sg:address":"Telecommunications & Services Branch 71 Cromwell",
    "sg:city":"Collingwood",
    "sg:classifiers":[
        {
            "category":"Organizations",
            "subcategory":"Labor Organization",
            "type":"Services"
        }
    ],
    "sg:phone":"+61 3 9419 0000",
    "sg:postcode":"3066",
    "sg:province":"VIC",
    "sg:tags":[
        "union"
    ],
    "wof:name":"CEPU (Communications Electrical Plumbing Union) Communications Division",
    "wof:placetype":"venue"
},
  "geometry": {"coordinates":[144.98980712900001,-37.8064155579],"type":"Point"}
}