{
  "type": "Feature",
  "properties": {
    "addr:full":"Factory 4 Cnr London Drv and Dorset Road, Boronia 3155 Boronia VIC 3155",
    "addr:housenumber":"4",
    "addr:postcode":"3155;3155",
    "addr:street":"Cnr London Drv;Dorset Road",
    "iso:country":"AU",
    "sg:address":"Factory 4 Cnr London Drv and Dorset Road, Boronia 3155",
    "sg:city":"Boronia",
    "sg:classifiers":[
        {
            "category":"Retail",
            "subcategory":"Car Wash",
            "type":"Services"
        }
    ],
    "sg:phone":"+61 3 9762 5500",
    "sg:postcode":"3155",
    "sg:province":"VIC",
    "sg:tags":[
        "truck",
        "cleaning"
    ],
    "wof:name":"Protech Car Care Centre",
    "wof:placetype":"venue"
},
  "geometry": {"coordinates":[145.28602600100001,-37.8550491333],"type":"Point"}
}