{
  "type": "Feature",
  "properties": {
    "addr:full":"58a Helen St Bellevue WA 6056",
    "addr:housenumber":"58a",
    "addr:postcode":"6056",
    "addr:street":"Helen St",
    "iso:country":"AU",
    "sg:address":"58a Helen St",
    "sg:city":"Bellevue",
    "sg:classifiers":[
        {
            "category":"Organizations",
            "subcategory":"Membership Organization",
            "type":"Services"
        }
    ],
    "sg:phone":"+61 8 9250 1148",
    "sg:postcode":"6056",
    "sg:province":"WA",
    "sg:tags":[
        "equipment",
        "inter-communication",
        "system"
    ],
    "wof:name":"Universal Admin Pty Ltd",
    "wof:placetype":"venue"
},
  "geometry": {"coordinates":[116.02185821499999,-31.8981170654],"type":"Point"}
}