{
  "type": "Feature",
  "properties": {
    "addr:full":"12 / 1353 The Horsley Drv Wetherill Park NSW 2164",
    "addr:housenumber":"12 / 1353",
    "addr:postcode":"2164",
    "addr:street":"The Horsley Drv",
    "iso:country":"AU",
    "sg:address":"12 / 1353 The Horsley Drv",
    "sg:city":"Wetherill Park",
    "sg:classifiers":[
        {
            "category":"Building & Trades",
            "subcategory":"Cleaning & Sanitation",
            "type":"Services"
        }
    ],
    "sg:phone":"+61 2 9756 0588",
    "sg:postcode":"2164",
    "sg:province":"NSW",
    "sg:tags":[
        "asbestos",
        "treatment",
        "removal"
    ],
    "wof:name":"DMS Contracting Pty Ltd",
    "wof:placetype":"venue"
},
  "geometry": {"coordinates":[150.882125855,-33.8522949219],"type":"Point"}
}