{
  "type": "Feature",
  "properties": {
    "addr:full":"331 Eaglehawk Rd California Gully VIC 3556",
    "addr:housenumber":"331",
    "addr:postcode":"3556",
    "addr:street":"Eaglehawk Rd",
    "iso:country":"AU",
    "sg:address":"331 Eaglehawk Rd",
    "sg:city":"California Gully",
    "sg:classifiers":[
        {
            "category":"Sports & Exercise",
            "subcategory":"Gym",
            "type":"Entertainment"
        }
    ],
    "sg:phone":"+61 3 5446 8577",
    "sg:postcode":"3556",
    "sg:province":"VIC",
    "sg:tags":[
        "health",
        "fitness"
    ],
    "wof:name":"Bendigo Therapies",
    "wof:placetype":"venue"
},
  "geometry": {"coordinates":[144.25848388700001,-36.7360076904],"type":"Point"}
}