{
  "type": "Feature",
  "properties": {
    "addr:full":"18 Steptoe St East Bundaberg QLD 4670",
    "addr:housenumber":"18",
    "addr:postcode":"4670",
    "addr:street":"Steptoe St East",
    "iso:country":"AU",
    "sg:address":"18 Steptoe St",
    "sg:city":"East Bundaberg",
    "sg:classifiers":[
        {
            "category":"Building & Trades",
            "subcategory":"Construction",
            "type":"Services"
        }
    ],
    "sg:phone":"+61 7 4152 6305",
    "sg:postcode":"4670",
    "sg:province":"QLD",
    "sg:tags":[
        "welding"
    ],
    "wof:name":"Oakwood Sheet Metal Works",
    "wof:placetype":"venue"
},
  "geometry": {"coordinates":[152.376296997,-24.8652801514],"type":"Point"}
}