{
  "type": "Feature",
  "properties": {
    "addr:full":"375 Guildford Rd Bayswater WA 6053",
    "addr:housenumber":"375",
    "addr:postcode":"6053",
    "addr:street":"Guildford Rd",
    "iso:country":"AU",
    "sg:address":"375 Guildford Rd",
    "sg:city":"Bayswater",
    "sg:classifiers":[
        {
            "category":"Autos & Motor Vehicles",
            "subcategory":"Automobile Sales",
            "type":"Retail Goods"
        }
    ],
    "sg:phone":"+61 419 444 588",
    "sg:postcode":"6053",
    "sg:province":"WA",
    "sg:tags":[
        "bus",
        "used",
        "truck"
    ],
    "wof:name":"All Terrain Auto Brokers Pty Ltd",
    "wof:placetype":"venue"
},
  "geometry": {"coordinates":[115.918960571,-31.9242248535],"type":"Point"}
}