{
  "type": "Feature",
  "properties": {
    "addr:full":"McGeehan Crs Myrtleford VIC 3737",
    "addr:postcode":"3737",
    "addr:street":"Mcgeehan Crs",
    "iso:country":"AU",
    "sg:address":"McGeehan Crs",
    "sg:city":"Myrtleford",
    "sg:classifiers":[
        {
            "category":"Home & Garden",
            "subcategory":"Garden Supply",
            "type":"Retail Goods"
        }
    ],
    "sg:phone":"+61 3 5752 2333",
    "sg:postcode":"3737",
    "sg:province":"VIC",
    "sg:tags":[
        "equipment"
    ],
    "wof:name":"McPherson Earthmoving Contractors Pty Ltd",
    "wof:placetype":"venue"
},
  "geometry": {"coordinates":[146.72108459500001,-36.5560493469],"type":"Point"}
}