{
  "type": "Feature",
  "properties": {
    "iso:country":"AU",
    "sg:address":"126 End St",
    "sg:city":"Deniliquin",
    "sg:classifiers":[
        {
            "category":"Professional",
            "subcategory":"Accounting & Tax Preparation",
            "type":"Services"
        }
    ],
    "sg:phone":"+61 3 5881 7999",
    "sg:postcode":"2710",
    "sg:province":"VIC",
    "sg:tags":[
        "consultant",
        "taxation"
    ],
    "wof:name":"Brian McCleary & Co",
    "wof:placetype":"venue"
},
  "geometry": {"coordinates":[144.965240478,-35.5329093933],"type":"Point"}
}