{
  "type": "Feature",
  "properties": {
    "addr:full":"1 Albury St Tumbarumba NSW 2653",
    "addr:housenumber":"1",
    "addr:postcode":"2653",
    "addr:street":"Albury St",
    "iso:country":"AU",
    "sg:address":"1 Albury St",
    "sg:city":"Tumbarumba",
    "sg:classifiers":[
        {
            "category":"Manufacturing",
            "subcategory":"Rubber & Plastics",
            "type":"Manufacturing & Wholesale Goods"
        }
    ],
    "sg:phone":"+61 408 865 497",
    "sg:postcode":"2653",
    "sg:province":"NSW",
    "sg:tags":[
        "lime"
    ],
    "wof:name":"Southern Gateway Concrete",
    "wof:placetype":"venue"
},
  "geometry": {"coordinates":[148.00953674300001,-35.7766876221],"type":"Point"}
}