{
  "type": "Feature",
  "properties": {
    "iso:country":"AU",
    "sg:address":"4 Wylie St",
    "sg:city":"Toowoomba",
    "sg:classifiers":[
        {
            "category":"Retail",
            "subcategory":"Auto Repair",
            "type":"Services"
        }
    ],
    "sg:phone":"+61 7 4638 2848",
    "sg:postcode":"4350",
    "sg:province":"QLD",
    "sg:tags":[
        "repairer",
        "motor",
        "engineer"
    ],
    "wof:name":"Hassco Motors",
    "wof:placetype":"venue"
},
  "geometry": {"coordinates":[151.95057700000001,-27.565016],"type":"Point"}
}