{
  "type": "Feature",
  "properties": {
    "addr:full":"4 / 4 Riley Cl Ngunnawal ACT 2913",
    "addr:housenumber":"/ 4",
    "addr:postcode":"2913",
    "addr:street":"Riley Cl Ngunnawal",
    "iso:country":"AU",
    "sg:address":"4",
    "sg:city":"/ 4 Riley Cl Ngunnawal",
    "sg:classifiers":[
        {
            "category":"Health Services",
            "subcategory":"Chiropractor",
            "type":"Services"
        }
    ],
    "sg:phone":"+61 2 6241 6060",
    "sg:postcode":"2913",
    "sg:province":"ACT",
    "wof:name":"Clark Jennifer",
    "wof:placetype":"venue"
},
  "geometry": {"coordinates":[149.108032227,-35.173160553],"type":"Point"}
}