{
  "type": "Feature",
  "properties": {
    "addr:full":"Austin Ave Terang VIC 3264",
    "addr:postcode":"3264",
    "addr:street":"Austin Ave",
    "iso:country":"AU",
    "sg:address":"Austin Ave",
    "sg:city":"Terang",
    "sg:classifiers":[
        {
            "category":"Building & Trades",
            "subcategory":"Construction",
            "type":"Services"
        }
    ],
    "sg:phone":"+61 419 350 552",
    "sg:postcode":"3264",
    "sg:province":"VIC",
    "sg:tags":[
        "fencing",
        "contractor"
    ],
    "wof:name":"Attrill G & J M",
    "wof:placetype":"venue"
},
  "geometry": {"coordinates":[142.90257263199999,-38.2400550842],"type":"Point"}
}