{
  "type": "Feature",
  "properties": {
    "addr:full":"136 Botanic Rd Warrnambool VIC 3280",
    "addr:housenumber":"136",
    "addr:postcode":"3280",
    "addr:street":"Botanic Rd",
    "iso:country":"AU",
    "sg:address":"136 Botanic Rd",
    "sg:city":"Warrnambool",
    "sg:classifiers":[
        {
            "category":"Health Services",
            "subcategory":"Doctor",
            "type":"Services"
        }
    ],
    "sg:phone":"+61 3 5561 1440",
    "sg:postcode":"3280",
    "sg:province":"VIC",
    "sg:tags":[
        "medical",
        "practitioner"
    ],
    "wof:name":"Western District Radiology",
    "wof:placetype":"venue"
},
  "geometry": {"coordinates":[142.47955322300001,-38.3721618652],"type":"Point"}
}