{
  "type": "Feature",
  "properties": {
    "iso:country":"AU",
    "sg:address":"Civic Plaza 6/ 43 Ware St",
    "sg:city":"Fairfield",
    "sg:classifiers":[
        {
            "category":"Health Services",
            "subcategory":"Dentist",
            "type":"Services"
        }
    ],
    "sg:phone":"+61 2 9727 0364",
    "sg:postcode":"2165",
    "sg:province":"NSW",
    "wof:name":"Gomez Roger M",
    "wof:placetype":"venue"
},
  "geometry": {"coordinates":[150.95510864299999,-33.8711433411],"type":"Point"}
}