{
  "type": "Feature",
  "properties": {
    "addr:full":"146 Anderson St Manunda QLD 4870",
    "addr:housenumber":"146",
    "addr:postcode":"4870",
    "addr:street":"Anderson St",
    "iso:country":"AU",
    "sg:address":"146 Anderson St",
    "sg:city":"Manunda",
    "sg:classifiers":[
        {
            "category":"Health Services",
            "subcategory":"Optometrist",
            "type":"Services"
        }
    ],
    "sg:phone":"+61 7 4053 2974",
    "sg:postcode":"4870",
    "sg:province":"QLD",
    "wof:name":"Affordable Specs",
    "wof:placetype":"venue"
},
  "geometry": {"coordinates":[145.74288940400001,-16.9166431427],"type":"Point"}
}