{
  "type": "Feature",
  "properties": {
    "iso:country":"AU",
    "sg:address":"79 Hawkesbury Rd",
    "sg:city":"Springwood",
    "sg:classifiers":[
        {
            "category":"Travel",
            "subcategory":"Hostel",
            "type":"Entertainment"
        }
    ],
    "sg:phone":"+61 2 4751 1000",
    "sg:postcode":"2777",
    "sg:province":"NSW",
    "sg:tags":[
        "home"
    ],
    "wof:name":"Endeavour Assisted Living Apartments",
    "wof:placetype":"venue"
},
  "geometry": {"coordinates":[150.582595825,-33.6910018921],"type":"Point"}
}