{
  "type": "Feature",
  "properties": {
    "iso:country":"AU",
    "sg:address":"Shed 2 - 11 Thorne St",
    "sg:city":"Wynnum",
    "sg:classifiers":[
        {
            "category":"Utilities",
            "subcategory":"Natural Gas",
            "type":"Services"
        }
    ],
    "sg:phone":"+61 409 636 106",
    "sg:postcode":"4178",
    "sg:province":"QLD",
    "sg:tags":[
        "pontoon"
    ],
    "wof:name":"Complete Marine Services Qld",
    "wof:placetype":"venue"
},
  "geometry": {"coordinates":[153.167694092,-27.4393920898],"type":"Point"}
}