{
  "type": "Feature",
  "properties": {
    "iso:country":"AU",
    "sg:address":"Lot 22 Lakelands Rd",
    "sg:city":"Barragup Mandurah",
    "sg:classifiers":[
        {
            "category":"Autos & Motor Vehicles",
            "subcategory":"Auto Supplies",
            "type":"Retail Goods"
        }
    ],
    "sg:phone":"+61 8 9581 6890",
    "sg:postcode":"6210",
    "sg:province":"WA",
    "sg:tags":[
        "part",
        "cycles",
        "accessory"
    ],
    "wof:name":"KDK Engines",
    "wof:placetype":"venue"
},
  "geometry": {"coordinates":[115.798912,-32.516064],"type":"Point"}
}