{
  "type": "Feature",
  "properties": {
    "iso:country":"AU",
    "sg:address":"Shop 5, Mudgeeraba Market 1 Swan La",
    "sg:city":"Mudgeeraba",
    "sg:classifiers":[
        {
            "category":"Food & Beverages",
            "subcategory":"Specialty",
            "type":"Retail Goods"
        }
    ],
    "sg:phone":"+61 7 5530 7677",
    "sg:postcode":"4213",
    "sg:province":"QLD",
    "sg:tags":[
        "product",
        "health"
    ],
    "wof:name":"Natural Choice Health Foods",
    "wof:placetype":"venue"
},
  "geometry": {"coordinates":[153.36528015100001,-28.0784645081],"type":"Point"}
}