{
  "type": "Feature",
  "properties": {
    "iso:country":"AU",
    "sg:address":"Princes Hwy",
    "sg:city":"Larpent",
    "sg:classifiers":[
        {
            "category":"Farming",
            "subcategory":"Dairy Farm",
            "type":"Manufacturing & Wholesale Goods"
        }
    ],
    "sg:phone":"+61 3 5232 2470",
    "sg:postcode":"3249",
    "sg:province":"VIC",
    "wof:name":"Craiglands Partnership",
    "wof:placetype":"venue"
},
  "geometry": {"coordinates":[143.50579834000001,-38.3370437622],"type":"Point"}
}