{
  "type": "Feature",
  "properties": {
    "addr:full":"20 Woodville St Hurstville NSW 2220",
    "addr:housenumber":"20",
    "addr:postcode":"2220",
    "addr:street":"Woodville St",
    "iso:country":"AU",
    "sg:address":"20 Woodville St",
    "sg:city":"Hurstville",
    "sg:classifiers":[
        {
            "category":"Real Estate",
            "subcategory":"Real Estate Agent",
            "type":"Services"
        }
    ],
    "sg:phone":"+61 412 892 208",
    "sg:postcode":"2220",
    "sg:province":"NSW",
    "wof:name":"Universal Pacific Real Estate Pty Ltd",
    "wof:placetype":"venue"
},
  "geometry": {"coordinates":[151.10272216800001,-33.965549469],"type":"Point"}
}