{
  "type": "Feature",
  "properties": {
    "addr:full":"11 Hillview Rd Eastwood NSW 2122",
    "addr:housenumber":"11",
    "addr:postcode":"2122",
    "addr:street":"Hillview Rd",
    "iso:country":"AU",
    "sg:address":"11 Hillview Rd",
    "sg:city":"Eastwood",
    "sg:classifiers":[
        {
            "category":"Health Services",
            "subcategory":"Health Practitioner",
            "type":"Services"
        }
    ],
    "sg:phone":"+61 2 9874 0111",
    "sg:postcode":"2122",
    "sg:province":"NSW",
    "sg:tags":[
        "bowen",
        "therapy"
    ],
    "wof:name":"Chris & Monireh Barnard",
    "wof:placetype":"venue"
},
  "geometry": {"coordinates":[151.07937622099999,-33.789226532],"type":"Point"}
}