{
  "type": "Feature",
  "properties": {
    "iso:country":"AU",
    "sg:address":"43 Maida Ave",
    "sg:city":"Sunshine North",
    "sg:classifiers":[
        {
            "category":"Home & Garden",
            "subcategory":"Garden Supply",
            "type":"Retail Goods"
        }
    ],
    "sg:phone":"+61 414 900 317",
    "sg:postcode":"3020",
    "sg:province":"VIC",
    "sg:tags":[
        "equipment"
    ],
    "wof:name":"Taylors Hill Garden Supply",
    "wof:placetype":"venue"
},
  "geometry": {"coordinates":[144.834915,-37.753822],"type":"Point"}
}