{
  "type": "Feature",
  "properties": {
    "iso:country":"AU",
    "sg:address":"Real Estate House, 1st Floor, 344 High St",
    "sg:city":"Penrith",
    "sg:classifiers":[
        {
            "category":"Real Estate",
            "subcategory":"Real Estate Agent",
            "type":"Services"
        }
    ],
    "sg:phone":"+61 2 4722 8500",
    "sg:postcode":"2750",
    "sg:province":"NSW",
    "wof:name":"Raine & Horne Commercial Penrith",
    "wof:placetype":"venue"
},
  "geometry": {"coordinates":[150.91558837900001,-33.8947944641],"type":"Point"}
}