{
  "type": "Feature",
  "properties": {
    "iso:country":"AU",
    "sg:address":"416 Sydney Rd",
    "sg:city":"Coburg",
    "sg:classifiers":[
        {
            "category":"Shopping",
            "subcategory":"Crafts & Fabrics",
            "type":"Retail Goods"
        }
    ],
    "sg:phone":"+61 3 9354 5101",
    "sg:postcode":"3058",
    "sg:province":"VIC",
    "sg:tags":[
        "material",
        "dress"
    ],
    "wof:name":"Coburg Fabrics",
    "wof:placetype":"venue"
},
  "geometry": {"coordinates":[144.96632385300001,-37.7436027527],"type":"Point"}
}