{
  "type": "Feature",
  "properties": {
    "iso:country":"AU",
    "sg:address":"23 Hill St",
    "sg:city":"Pittsworth",
    "sg:classifiers":[
        {
            "category":"Farming",
            "subcategory":"Farm & Veterinary Services",
            "type":"Manufacturing & Wholesale Goods"
        }
    ],
    "sg:phone":"+61 7 4693 1996",
    "sg:postcode":"4356",
    "sg:province":"QLD",
    "sg:tags":[
        "agricultural",
        "advisory"
    ],
    "wof:name":"Tatzenko Consultancies Pty Ltd",
    "wof:placetype":"venue"
},
  "geometry": {"coordinates":[151.62867700000001,-27.723141],"type":"Point"}
}