{
  "type": "Feature",
  "properties": {
    "addr:full":"505 Chapel St South Yarra VIC 3141",
    "addr:housenumber":"505",
    "addr:postcode":"3141",
    "addr:street":"Chapel St",
    "iso:country":"AU",
    "sg:address":"505 Chapel St",
    "sg:city":"South Yarra",
    "sg:classifiers":[
        {
            "category":"Shopping",
            "subcategory":"Clothing, Apparel, & Fashions",
            "type":"Retail Goods"
        }
    ],
    "sg:phone":"+61 3 9804 7037",
    "sg:postcode":"3141",
    "sg:province":"VIC",
    "sg:tags":[
        "jean"
    ],
    "wof:name":"Just Jeans",
    "wof:placetype":"venue"
},
  "geometry": {"coordinates":[144.99484252900001,-37.8425140381],"type":"Point"}
}