{
  "type": "Feature",
  "properties": {
    "addr:full":"24 Outram St Lota QLD 4179",
    "addr:housenumber":"24",
    "addr:postcode":"4179",
    "addr:street":"Outram St",
    "iso:country":"AU",
    "sg:address":"24 Outram St",
    "sg:city":"Lota",
    "sg:classifiers":[
        {
            "category":"Organizations",
            "subcategory":"Professional Association",
            "type":"Services"
        }
    ],
    "sg:phone":"+61 423 311 839",
    "sg:postcode":"4179",
    "sg:province":"QLD",
    "sg:tags":[
        "web",
        "internet"
    ],
    "wof:name":"Barnes Open",
    "wof:placetype":"venue"
},
  "geometry": {"coordinates":[153.19137573200001,-27.4692840576],"type":"Point"}
}