{
  "type": "Feature",
  "properties": {
    "addr:full":"Dart St Oberon NSW 2787",
    "addr:postcode":"2787",
    "addr:street":"Dart St",
    "iso:country":"AU",
    "sg:address":"Dart St",
    "sg:city":"Oberon",
    "sg:classifiers":[
        {
            "category":"Education",
            "subcategory":"School",
            "type":"Public Place"
        }
    ],
    "sg:phone":"+61 2 6336 0093",
    "sg:postcode":"2787",
    "sg:province":"NSW",
    "sg:tags":[
        "state",
        "-",
        "nsw"
    ],
    "wof:name":"Oberon Public School",
    "wof:placetype":"venue"
},
  "geometry": {"coordinates":[149.86436462399999,-33.7038650513],"type":"Point"}
}