{
  "type": "Feature",
  "properties": {
    "addr:full":"20b White Rd Gepps Cross SA 5094",
    "addr:housenumber":"20b",
    "addr:postcode":"5094",
    "addr:street":"White Rd",
    "iso:country":"AU",
    "sg:address":"20b White Rd",
    "sg:city":"Gepps Cross",
    "sg:classifiers":[
        {
            "category":"Cafe",
            "type":"Food & Drink"
        }
    ],
    "sg:phone":"+61 8 8260 2119",
    "sg:postcode":"5094",
    "sg:province":"SA",
    "wof:name":"Gepps Cross Snack Bar",
    "wof:placetype":"venue"
},
  "geometry": {"coordinates":[138.593093872,-34.8427391052],"type":"Point"}
}