{
  "type": "Feature",
  "properties": {
    "iso:country":"AU",
    "sg:address":"22a Milne Ave",
    "sg:city":"Seaford",
    "sg:classifiers":[
        {
            "category":"Building & Trades",
            "subcategory":"Construction",
            "type":"Services"
        }
    ],
    "sg:phone":"+61 3 9786 5224",
    "sg:postcode":"3198",
    "sg:province":"VIC",
    "sg:tags":[
        "fencing",
        "contractor"
    ],
    "wof:name":"Frankston Fencing",
    "wof:placetype":"venue"
},
  "geometry": {"coordinates":[145.133087158,-38.1174049377],"type":"Point"}
}