{
  "type": "Feature",
  "properties": {
    "iso:country":"AU",
    "sg:address":"56 Gordon St",
    "sg:city":"Mackay",
    "sg:classifiers":[
        {
            "category":"Insurance",
            "subcategory":"Life Insurance",
            "type":"Services"
        }
    ],
    "sg:phone":"+61 7 4951 3866",
    "sg:postcode":"4740",
    "sg:province":"QLD",
    "wof:name":"Brian Field Pty Ltd",
    "wof:placetype":"venue"
},
  "geometry": {"coordinates":[149.181213,-21.142523],"type":"Point"}
}