{
  "type": "Feature",
  "properties": {
    "addr:full":"56 Gordon St Mackay QLD 4740",
    "addr:housenumber":"56",
    "addr:postcode":"4740",
    "addr:street":"Gordon St",
    "iso:country":"AU",
    "sg:address":"56 Gordon St",
    "sg:city":"Mackay",
    "sg:classifiers":[
        {
            "category":"Insurance",
            "subcategory":"Life Insurance",
            "type":"Services"
        }
    ],
    "sg:phone":"+61 7 4951 3866",
    "sg:postcode":"4740",
    "sg:province":"QLD",
    "wof:name":"Brian Field Pty Ltd",
    "wof:placetype":"venue"
},
  "geometry": {"coordinates":[149.18121300000001,-21.142523],"type":"Point"}
}