{
  "type": "Feature",
  "properties": {
    "addr:full":"34 Holmes Rd Moonee Ponds VIC 3039",
    "addr:housenumber":"34",
    "addr:postcode":"3039",
    "addr:street":"Holmes Rd",
    "iso:country":"AU",
    "sg:address":"34 Holmes Rd",
    "sg:city":"Moonee Ponds",
    "sg:classifiers":[
        {
            "category":"Communications",
            "subcategory":"Film & Video Production",
            "type":"Services"
        }
    ],
    "sg:phone":"+61 3 9326 2775",
    "sg:postcode":"3039",
    "sg:province":"VIC",
    "sg:tags":[
        "dvd",
        "library"
    ],
    "wof:name":"Movieland Video Libraries",
    "wof:placetype":"venue"
},
  "geometry": {"coordinates":[144.91810599999999,-37.766544],"type":"Point"}
}