{
  "type": "Feature",
  "properties": {
    "addr:full":"1/ 67 Russell St Goondiwindi QLD 4390",
    "addr:housenumber":"/ 67",
    "addr:postcode":"4390",
    "addr:street":"Russell St",
    "iso:country":"AU",
    "sg:address":"1/ 67 Russell St",
    "sg:city":"Goondiwindi",
    "sg:classifiers":[
        {
            "category":"Manufacturing",
            "subcategory":"Signs",
            "type":"Manufacturing & Wholesale Goods"
        }
    ],
    "sg:phone":"+61 7 4671 4022",
    "sg:postcode":"4390",
    "sg:province":"QLD",
    "sg:tags":[
        "traffic",
        "safety"
    ],
    "wof:name":"Nick's Signs Goondiwindi",
    "wof:placetype":"venue"
},
  "geometry": {"coordinates":[150.30323791500001,-28.5436706543],"type":"Point"}
}