{
  "type": "Feature",
  "properties": {
    "addr:full":"443a Cambridge St Floreat WA 6014",
    "addr:housenumber":"443a",
    "addr:postcode":"6014",
    "addr:street":"Cambridge St",
    "iso:country":"AU",
    "sg:address":"443a Cambridge St",
    "sg:city":"Floreat",
    "sg:classifiers":[
        {
            "category":"Personal",
            "subcategory":"Beauty Salon",
            "type":"Services"
        }
    ],
    "sg:phone":"+61 8 9387 1931",
    "sg:postcode":"6014",
    "sg:province":"WA",
    "sg:tags":[
        "hairdresser"
    ],
    "wof:name":"Ganesha Hair Options",
    "wof:placetype":"venue"
},
  "geometry": {"coordinates":[115.80153656,-31.9409141541],"type":"Point"}
}