{
  "type": "Feature",
  "properties": {
    "iso:country":"AU",
    "sg:address":"4/ 27 George Rd",
    "sg:city":"Salamander Bay",
    "sg:classifiers":[
        {
            "category":"Building & Trades",
            "subcategory":"Construction",
            "type":"Services"
        }
    ],
    "sg:phone":"+61 2 4982 2414",
    "sg:postcode":"2317",
    "sg:province":"NSW",
    "sg:tags":[
        "fencing",
        "contractor"
    ],
    "wof:name":"Profencing Pty Ltd",
    "wof:placetype":"venue"
},
  "geometry": {"coordinates":[152.07504299999999,-32.726852],"type":"Point"}
}