{
  "type": "Feature",
  "properties": {
    "iso:country":"AU",
    "sg:address":"45 Stanley St",
    "sg:city":"Wallan",
    "sg:classifiers":[
        {
            "category":"Home & Garden",
            "subcategory":"Carpets & Floor Coverings",
            "type":"Retail Goods"
        }
    ],
    "sg:phone":"+61 3 5783 1014",
    "sg:postcode":"3756",
    "sg:province":"VIC",
    "sg:tags":[
        "layer",
        "planner"
    ],
    "wof:name":"A Walsh",
    "wof:placetype":"venue"
},
  "geometry": {"coordinates":[144.976166,-37.413956],"type":"Point"}
}