{
  "type": "Feature",
  "properties": {
    "iso:country":"AU",
    "sg:address":"Suite 1/ 12 Leghorn St",
    "sg:city":"Rockingham",
    "sg:classifiers":[
        {
            "category":"Professional",
            "subcategory":"Employment Agencies",
            "type":"Services"
        }
    ],
    "sg:phone":"+61 8 9592 9259",
    "sg:postcode":"6168",
    "sg:province":"WA",
    "sg:tags":[
        "occupational",
        "therapist"
    ],
    "wof:name":"Alex Retallick",
    "wof:placetype":"venue"
},
  "geometry": {"coordinates":[115.74149300000001,-32.285564],"type":"Point"}
}