{
  "type": "Feature",
  "properties": {
    "addr:full":"Factory 4/ 23 Bunney Rd Oakleigh South VIC 3167",
    "addr:housenumber":"/ 23",
    "addr:postcode":"3167",
    "addr:street":"Bunney Rd",
    "iso:country":"AU",
    "sg:address":"Factory 4/ 23 Bunney Rd",
    "sg:city":"Oakleigh South",
    "sg:classifiers":[
        {
            "category":"Home & Garden",
            "subcategory":"Furniture",
            "type":"Retail Goods"
        }
    ],
    "sg:phone":"+61 3 9558 1454",
    "sg:postcode":"3167",
    "sg:province":"VIC",
    "sg:tags":[
        "outdoor"
    ],
    "wof:name":"Enviroplas Products Pty Ltd",
    "wof:placetype":"venue"
},
  "geometry": {"coordinates":[145.097290039,-37.9331626892],"type":"Point"}
}