{
  "type": "Feature",
  "properties": {
    "addr:full":"3 Woodward St Hamilton VIC 3300",
    "addr:housenumber":"3",
    "addr:postcode":"3300",
    "addr:street":"Woodward St",
    "iso:country":"AU",
    "sg:address":"3 Woodward St",
    "sg:city":"Hamilton",
    "sg:classifiers":[
        {
            "category":"Wholesale",
            "subcategory":"Farm Supplies",
            "type":"Manufacturing & Wholesale Goods"
        }
    ],
    "sg:phone":"+61 3 5572 4145",
    "sg:postcode":"3300",
    "sg:province":"VIC",
    "sg:tags":[
        "equipment"
    ],
    "wof:name":"Hamilton Sheetmetal and Rainwater Tanks Pty Ltd",
    "wof:placetype":"venue"
},
  "geometry": {"coordinates":[142.00462341299999,-37.7258605957],"type":"Point"}
}