{
  "type": "Feature",
  "properties": {
    "iso:country":"AU",
    "sg:address":"Ingle Farm Shopping Centre Beovich Rd",
    "sg:city":"Ingle Farm",
    "sg:classifiers":[
        {
            "category":"Professional",
            "subcategory":"Testing Lab",
            "type":"Services"
        }
    ],
    "sg:phone":"+61 439 840 402",
    "sg:postcode":"5098",
    "sg:province":"SA",
    "sg:tags":[
        "inspection"
    ],
    "wof:name":"A1 Tool Test & Tag",
    "wof:placetype":"venue"
},
  "geometry": {"coordinates":[138.64706420900001,-34.8311233521],"type":"Point"}
}