{
  "type": "Feature",
  "properties": {
    "addr:full":"43 Knock Pl Jandakot WA 6164",
    "addr:housenumber":"43",
    "addr:postcode":"6164",
    "addr:street":"Knock Pl",
    "iso:country":"AU",
    "sg:address":"43 Knock Pl",
    "sg:city":"Jandakot",
    "sg:classifiers":[
        {
            "category":"Home & Garden",
            "subcategory":"Garden Supply",
            "type":"Retail Goods"
        }
    ],
    "sg:phone":"+61 8 9414 7779",
    "sg:postcode":"6164",
    "sg:province":"WA",
    "sg:tags":[
        "equipment"
    ],
    "wof:name":"Jandakot Garden Supplies",
    "wof:placetype":"venue"
},
  "geometry": {"coordinates":[115.860123,-32.125195],"type":"Point"}
}