{
  "type": "Feature",
  "properties": {
    "addr:full":"796 Main Rd Hurstbridge VIC 3099",
    "addr:housenumber":"796",
    "addr:postcode":"3099",
    "addr:street":"Main Rd",
    "iso:country":"AU",
    "sg:address":"796 Main Rd",
    "sg:city":"Hurstbridge",
    "sg:classifiers":[
        {
            "category":"Food & Beverages",
            "subcategory":"Liquor & Beverages",
            "type":"Retail Goods"
        }
    ],
    "sg:phone":"+61 3 9718 2808",
    "sg:postcode":"3099",
    "sg:province":"VIC",
    "sg:tags":[
        "store"
    ],
    "wof:name":"Hurstbridge Cellars",
    "wof:placetype":"venue"
},
  "geometry": {"coordinates":[145.192871094,-37.6397743225],"type":"Point"}
}