{
  "type": "Feature",
  "properties": {
    "iso:country":"AU",
    "sg:address":"176 Lloyd St",
    "sg:city":"Enoggera",
    "sg:classifiers":[
        {
            "category":"Health Services",
            "subcategory":"Health Practitioner",
            "type":"Services"
        }
    ],
    "sg:phone":"+61 7 3355 6674",
    "sg:postcode":"4051",
    "sg:province":"QLD",
    "sg:tags":[
        "acupuncture"
    ],
    "wof:name":"Roy Sybil",
    "wof:placetype":"venue"
},
  "geometry": {"coordinates":[152.99206543,-27.4257640839],"type":"Point"}
}