{
  "type": "Feature",
  "properties": {
    "addr:full":"10 Princess St Beverley SA 5009",
    "addr:housenumber":"10",
    "addr:postcode":"5009",
    "addr:street":"Princess St",
    "iso:country":"AU",
    "sg:address":"10 Princess St",
    "sg:city":"Beverley",
    "sg:classifiers":[
        {
            "category":"Social Services",
            "subcategory":"Adult Care",
            "type":"Services"
        }
    ],
    "sg:phone":"+61 8 8244 6366",
    "sg:postcode":"5009",
    "sg:province":"SA",
    "sg:tags":[
        "towing"
    ],
    "wof:name":"SA Towing Service",
    "wof:placetype":"venue"
},
  "geometry": {"coordinates":[138.546676636,-34.9023170471],"type":"Point"}
}