{
  "type": "Feature",
  "properties": {
    "iso:country":"AU",
    "sg:address":"Unit 1/ 7 Green St",
    "sg:city":"Picnic Point",
    "sg:classifiers":[
        {
            "category":"Building & Trades",
            "subcategory":"Construction",
            "type":"Services"
        }
    ],
    "sg:phone":"+61 2 9774 2714",
    "sg:postcode":"2213",
    "sg:province":"NSW",
    "sg:tags":[
        "contractor"
    ],
    "wof:name":"R & J Building Contractors",
    "wof:placetype":"venue"
},
  "geometry": {"coordinates":[150.987411,-33.967251],"type":"Point"}
}