{
  "type": "Feature",
  "properties": {
    "addr:full":"Unit 3, 170 Coonawarra Rd Winnellie NT 0820",
    "addr:housenumber":"170",
    "addr:postcode":"nt 0820",
    "addr:street":"Coonawarra Rd",
    "iso:country":"AU",
    "sg:address":"Unit 3, 170 Coonawarra Rd",
    "sg:city":"Winnellie",
    "sg:classifiers":[
        {
            "category":"Food & Beverages",
            "subcategory":"Liquor & Beverages",
            "type":"Retail Goods"
        }
    ],
    "sg:phone":"+61 8 8947 2811",
    "sg:postcode":"0820",
    "sg:province":"NT",
    "sg:tags":[
        "merchant",
        "spirit",
        "wine"
    ],
    "wof:name":"Independent Brands Australia",
    "wof:placetype":"venue"
},
  "geometry": {"coordinates":[130.89247131400001,-12.4309720993],"type":"Point"}
}