{
  "type": "Feature",
  "properties": {
    "addr:full":"80 Hughes Ave Ermington NSW 2115",
    "addr:housenumber":"80",
    "addr:postcode":"2115",
    "addr:street":"Hughes Ave",
    "iso:country":"AU",
    "sg:address":"80 Hughes Ave",
    "sg:city":"Ermington",
    "sg:classifiers":[
        {
            "category":"Manufacturing",
            "subcategory":"Building Materials",
            "type":"Manufacturing & Wholesale Goods"
        }
    ],
    "sg:phone":"+61 1300 306 754",
    "sg:postcode":"2115",
    "sg:province":"NSW",
    "sg:tags":[
        "equipment",
        "handling"
    ],
    "wof:name":"Safe Quip Industrial Supplies",
    "wof:placetype":"venue"
},
  "geometry": {"coordinates":[151.06735229500001,-33.8162574768],"type":"Point"}
}