{
  "type": "Feature",
  "properties": {
    "iso:country":"AU",
    "sg:address":"70 Main Rd",
    "sg:city":"Reynella",
    "sg:classifiers":[
        {
            "category":"Professional",
            "subcategory":"Employment Agencies",
            "type":"Services"
        }
    ],
    "sg:phone":"+61 8 8307 1000",
    "sg:postcode":"5161",
    "sg:province":"SA",
    "sg:tags":[
        "hire",
        "labour",
        "contractor"
    ],
    "wof:name":"Skilled",
    "wof:placetype":"venue"
},
  "geometry": {"coordinates":[138.532073975,-35.0997619629],"type":"Point"}
}