{
  "type": "Feature",
  "properties": {
    "addr:full":"4/ 98 Marine Pde Maroubra NSW 2035",
    "addr:housenumber":"/ 98",
    "addr:postcode":"2035",
    "addr:street":"Marine Pde",
    "iso:country":"AU",
    "sg:address":"4/ 98 Marine Pde",
    "sg:city":"Maroubra",
    "sg:classifiers":[
        {
            "category":"Professional",
            "subcategory":"Engineering",
            "type":"Services"
        }
    ],
    "sg:phone":"+61 2 9349 5184",
    "sg:postcode":"2035",
    "sg:province":"NSW",
    "sg:tags":[
        "engineer"
    ],
    "wof:name":"LBI Australia Pty Ltd",
    "wof:placetype":"venue"
},
  "geometry": {"coordinates":[151.26205444300001,-33.943107605],"type":"Point"}
}