{
  "type": "Feature",
  "properties": {
    "addr:full":"Unit 411/ 15 Caravel Lane New Quay Docklands VIC 3008",
    "addr:housenumber":"/ 15",
    "addr:postcode":"3008",
    "addr:street":"Caravel Lane",
    "iso:country":"AU",
    "sg:address":"Unit 411/ 15 Caravel Lane New Quay",
    "sg:city":"Docklands",
    "sg:classifiers":[
        {
            "category":"Education",
            "subcategory":"Special Training",
            "type":"Public Place"
        }
    ],
    "sg:phone":"+61 3 9670 7995",
    "sg:postcode":"3008",
    "sg:province":"VIC",
    "sg:tags":[
        "development"
    ],
    "wof:name":"David Kay Training & Development Services Pty Ltd",
    "wof:placetype":"venue"
},
  "geometry": {"coordinates":[144.94195556599999,-37.8140602112],"type":"Point"}
}