{
  "type": "Feature",
  "properties": {
    "iso:country":"AU",
    "sg:address":"Shed 8/ 406 Main North Rd",
    "sg:city":"Blair Athol",
    "sg:classifiers":[
        {
            "category":"Retail",
            "subcategory":"Auto Repair",
            "type":"Services"
        }
    ],
    "sg:phone":"+61 8 8359 6437",
    "sg:postcode":"5084",
    "sg:province":"SA",
    "sg:tags":[
        "gas",
        "conversion",
        "natural",
        "lp",
        "vehicle"
    ],
    "wof:name":"Mobigas",
    "wof:placetype":"venue"
},
  "geometry": {"coordinates":[138.60084533700001,-34.8611221313],"type":"Point"}
}