{
  "type": "Feature",
  "properties": {
    "addr:full":"3/ 15 Halifax Drv Bunbury WA 6230",
    "addr:housenumber":"/ 15",
    "addr:postcode":"6230",
    "addr:street":"Halifax Drv",
    "iso:country":"AU",
    "sg:address":"3/ 15 Halifax Drv",
    "sg:city":"Bunbury",
    "sg:classifiers":[
        {
            "category":"Building & Trades",
            "subcategory":"Plumbing",
            "type":"Services"
        }
    ],
    "sg:phone":"+61 8 9725 6449",
    "sg:postcode":"6230",
    "sg:province":"WA",
    "sg:tags":[
        "tool",
        "air",
        "accessory",
        "supply"
    ],
    "wof:name":"South West Compressors",
    "wof:placetype":"venue"
},
  "geometry": {"coordinates":[115.67041,-33.36166],"type":"Point"}
}