{
  "type": "Feature",
  "properties": {
    "addr:full":"10 Production Ave Ernest QLD 4214",
    "addr:housenumber":"10",
    "addr:postcode":"4214",
    "addr:street":"Production Ave Ernest",
    "iso:country":"AU",
    "sg:address":"10 Production Ave",
    "sg:city":"Ernest",
    "sg:classifiers":[
        {
            "category":"Manufacturing",
            "subcategory":"Jewelry",
            "type":"Manufacturing & Wholesale Goods"
        }
    ],
    "sg:phone":"+61 7 5594 9749",
    "sg:postcode":"4214",
    "sg:province":"QLD",
    "sg:tags":[
        "mfrg",
        "jeweller"
    ],
    "wof:name":"Chainmakers Of Australia Pty Ltd",
    "wof:placetype":"venue"
},
  "geometry": {"coordinates":[153.362060547,-27.9678077698],"type":"Point"}
}