{
  "type": "Feature",
  "properties": {
    "iso:country":"AU",
    "sg:address":"Unit 1 4 Rosewood Drv",
    "sg:city":"Caloundra",
    "sg:classifiers":[
        {
            "category":"Utilities",
            "subcategory":"Water",
            "type":"Services"
        }
    ],
    "sg:phone":"+61 7 5437 2930",
    "sg:postcode":"4551",
    "sg:province":"QLD",
    "sg:tags":[
        "equipment",
        "treatment"
    ],
    "wof:name":"Clear Life Water (Qld)",
    "wof:placetype":"venue"
},
  "geometry": {"coordinates":[153.109130859,-26.786901474],"type":"Point"}
}