{
  "type": "Feature",
  "properties": {
    "addr:full":"37 Captain Cook Drv Caringbah NSW 2229",
    "addr:housenumber":"37",
    "addr:postcode":"2229",
    "addr:street":"Captain Cook Drv",
    "iso:country":"AU",
    "sg:address":"37 Captain Cook Drv",
    "sg:city":"Caringbah",
    "sg:classifiers":[
        {
            "category":"Airport",
            "subcategory":"International",
            "type":"Transportation"
        }
    ],
    "sg:phone":"+61 2 9526 2800",
    "sg:postcode":"2229",
    "sg:province":"NSW",
    "sg:tags":[
        "diving",
        "commercial"
    ],
    "sg:website":"http://www.graydiving.com.au",
    "wof:name":"Gray Diving Services Pty Ltd",
    "wof:placetype":"venue"
},
  "geometry": {"coordinates":[151.12681579599999,-34.0326728821],"type":"Point"}
}