{
  "type": "Feature",
  "properties": {
    "addr:full":"9 Wren Crt Wodonga VIC 3690",
    "addr:housenumber":"9",
    "addr:postcode":"3690",
    "addr:street":"Wren Crt",
    "iso:country":"AU",
    "sg:address":"9 Wren Crt",
    "sg:city":"Wodonga",
    "sg:classifiers":[
        {
            "category":"Professional",
            "subcategory":"Art Services",
            "type":"Services"
        }
    ],
    "sg:phone":"+61 402 323 371",
    "sg:postcode":"3690",
    "sg:province":"VIC",
    "sg:tags":[
        "decorator",
        "painter"
    ],
    "wof:name":"Brent Seach Painting & Decorating",
    "wof:placetype":"venue"
},
  "geometry": {"coordinates":[146.85505676299999,-36.1301231384],"type":"Point"}
}