{
  "type": "Feature",
  "properties": {
    "addr:full":"32 Riverdale Drv Sandfly TAS 7150",
    "addr:housenumber":"32",
    "addr:postcode":"7150",
    "addr:street":"Riverdale Drv",
    "iso:country":"AU",
    "sg:address":"32 Riverdale Drv",
    "sg:city":"Sandfly",
    "sg:classifiers":[
        {
            "category":"Building & Trades",
            "subcategory":"Construction",
            "type":"Services"
        }
    ],
    "sg:phone":"+61 408 125 290",
    "sg:postcode":"7150",
    "sg:province":"TAS",
    "sg:tags":[
        "renovation",
        "alterations",
        "extension",
        "contractor"
    ],
    "wof:name":"Vision Housing",
    "wof:placetype":"venue"
},
  "geometry": {"coordinates":[147.21856689399999,-42.9903755188],"type":"Point"}
}