{
  "type": "Feature",
  "properties": {
    "addr:full":"30 Corris St Yarraville VIC 3013",
    "addr:housenumber":"30",
    "addr:postcode":"3013",
    "addr:street":"Corris St",
    "iso:country":"AU",
    "sg:address":"30 Corris St",
    "sg:city":"Yarraville",
    "sg:classifiers":[
        {
            "category":"Home & Garden",
            "subcategory":"Furniture",
            "type":"Retail Goods"
        }
    ],
    "sg:phone":"+61 3 9315 2230",
    "sg:postcode":"3013",
    "sg:province":"VIC",
    "sg:tags":[
        "repair",
        "restoration"
    ],
    "wof:name":"Woodsmart Furniture Restoration & Repairs",
    "wof:placetype":"venue"
},
  "geometry": {"coordinates":[144.87826538100001,-37.8172721863],"type":"Point"}
}