{
  "type": "Feature",
  "properties": {
    "addr:full":"28 Donald St North Ryde NSW 2113",
    "addr:housenumber":"28",
    "addr:postcode":"2113",
    "addr:street":"Donald St",
    "iso:country":"AU",
    "sg:address":"28 Donald St",
    "sg:city":"North Ryde",
    "sg:classifiers":[
        {
            "category":"Building & Trades",
            "subcategory":"Construction",
            "type":"Services"
        }
    ],
    "sg:phone":"+61 438 874 299",
    "sg:postcode":"2113",
    "sg:province":"NSW",
    "sg:tags":[
        "joinery"
    ],
    "wof:name":"Access Kitchens",
    "wof:placetype":"venue"
},
  "geometry": {"coordinates":[151.13265991200001,-33.7968902588],"type":"Point"}
}