{
  "type": "Feature",
  "properties": {
    "addr:full":"167 Oxley Station Rd Oxley QLD 4075",
    "addr:housenumber":"167",
    "addr:postcode":"4075",
    "addr:street":"Oxley Station Rd",
    "iso:country":"AU",
    "sg:address":"167 Oxley Station Rd",
    "sg:city":"Oxley",
    "sg:classifiers":[
        {
            "category":"Retail",
            "subcategory":"Repair Shop",
            "type":"Services"
        }
    ],
    "sg:phone":"+61 7 3278 5423",
    "sg:postcode":"4075",
    "sg:province":"QLD",
    "sg:tags":[
        "upholsterer"
    ],
    "wof:name":"Amma Soft Furnishing",
    "wof:placetype":"venue"
},
  "geometry": {"coordinates":[152.97422790499999,-27.5532798767],"type":"Point"}
}