{
  "type": "Feature",
  "properties": {
    "addr:full":"92 Harrington St Hobart TAS 7000",
    "addr:housenumber":"92",
    "addr:postcode":"7000",
    "addr:street":"Harrington St",
    "iso:country":"AU",
    "sg:address":"92 Harrington St",
    "sg:city":"Hobart",
    "sg:classifiers":[
        {
            "category":"Retail",
            "subcategory":"Auto Rental",
            "type":"Services"
        }
    ],
    "sg:phone":"+61 1300 883 728",
    "sg:postcode":"7000",
    "sg:province":"TAS",
    "sg:tags":[
        "car",
        "hire",
        "minibus"
    ],
    "sg:website":"http://www.rentforless.com",
    "wof:name":"Rentforless",
    "wof:placetype":"venue"
},
  "geometry": {"coordinates":[147.324676514,-42.884437561],"type":"Point"}
}