{
  "type": "Feature",
  "properties": {
    "iso:country":"AU",
    "sg:address":"28 Robinson Rd",
    "sg:city":"East Virginia",
    "sg:classifiers":[
        {
            "category":"Shopping",
            "subcategory":"Crafts & Fabrics",
            "type":"Retail Goods"
        }
    ],
    "sg:phone":"+61 7 3865 7495",
    "sg:postcode":"4014",
    "sg:province":"QLD",
    "sg:tags":[
        "material",
        "dress"
    ],
    "wof:name":"Make-It Fabrics Pty Ltd",
    "wof:placetype":"venue"
},
  "geometry": {"coordinates":[153.060424805,-27.3704605103],"type":"Point"}
}