{
  "type": "Feature",
  "properties": {
    "addr:full":"253 Mulgrave Rd Cairns QLD 4870",
    "addr:housenumber":"253",
    "addr:postcode":"4870",
    "addr:street":"Mulgrave Rd",
    "iso:country":"AU",
    "sg:address":"253 Mulgrave Rd",
    "sg:city":"Cairns",
    "sg:classifiers":[
        {
            "category":"Personal",
            "subcategory":"Barber",
            "type":"Services"
        }
    ],
    "sg:phone":"+61 7 4031 7044",
    "sg:postcode":"4870",
    "sg:province":"QLD",
    "wof:name":"Quick Trim Men's Barber",
    "wof:placetype":"venue"
},
  "geometry": {"coordinates":[145.74342346200001,-16.9399929047],"type":"Point"}
}