{
  "type": "Feature",
  "properties": {
    "iso:country":"AU",
    "sg:address":"U3/ 51 Division St",
    "sg:city":"Welshpool",
    "sg:classifiers":[
        {
            "category":"Professional",
            "subcategory":"Engineering",
            "type":"Services"
        }
    ],
    "sg:phone":"+61 8 9258 7700",
    "sg:postcode":"6106",
    "sg:province":"WA",
    "sg:tags":[
        "manufacturing",
        "engineer"
    ],
    "wof:name":"BDG Custom Parts",
    "wof:placetype":"venue"
},
  "geometry": {"coordinates":[115.9451828,-31.9935722351],"type":"Point"}
}