{
  "type": "Feature",
  "properties": {
    "addr:full":"Unit 1/ 242 Ben Boyd Rd Neutral Bay NSW 2089",
    "addr:housenumber":"/ 242",
    "addr:postcode":"2089",
    "addr:street":"Ben Boyd Rd",
    "iso:country":"AU",
    "sg:address":"Unit 1/ 242 Ben Boyd Rd",
    "sg:city":"Neutral Bay",
    "sg:classifiers":[
        {
            "category":"Building & Trades",
            "subcategory":"Pest Control",
            "type":"Services"
        }
    ],
    "sg:phone":"+61 2 9953 5988",
    "sg:postcode":"2089",
    "sg:province":"NSW",
    "sg:tags":[
        "technical",
        "consultant"
    ],
    "wof:name":"Videoconference Enterprises",
    "wof:placetype":"venue"
},
  "geometry": {"coordinates":[151.22012329099999,-33.8285827637],"type":"Point"}
}