{
  "type": "Feature",
  "properties": {
    "iso:country":"AU",
    "sg:address":"G3, 49 - 53 Regent St",
    "sg:city":"Chippendale",
    "sg:classifiers":[
        {
            "category":"Building & Trades",
            "subcategory":"Equipment Rental",
            "type":"Services"
        }
    ],
    "sg:phone":"+61 410 568 537",
    "sg:postcode":"2008",
    "sg:province":"NSW",
    "sg:tags":[
        "crane",
        "hire"
    ],
    "wof:name":"Ganellen Construction Services Pty Ltd",
    "wof:placetype":"venue"
},
  "geometry": {"coordinates":[151.202667236,-33.8855514526],"type":"Point"}
}