{
  "type": "Feature",
  "properties": {
    "iso:country":"AU",
    "sg:address":"PO Box 163",
    "sg:city":"Montrose",
    "sg:classifiers":[
        {
            "category":"Professional",
            "subcategory":"Art Services",
            "type":"Services"
        }
    ],
    "sg:phone":"+61 3 9761 9372",
    "sg:postcode":"3765",
    "sg:province":"VIC",
    "sg:tags":[
        "decorator",
        "painter"
    ],
    "wof:name":"A.P.J. Coating Services Pty Ltd",
    "wof:placetype":"venue"
},
  "geometry": {"coordinates":[145.340377808,-37.8080368042],"type":"Point"}
}