{
  "type": "Feature",
  "properties": {
    "iso:country":"AU",
    "sg:address":"229 High St",
    "sg:city":"Fremantle",
    "sg:classifiers":[
        {
            "category":"Health Services",
            "subcategory":"Doctor",
            "type":"Services"
        }
    ],
    "sg:phone":"+61 8 9430 4488",
    "sg:postcode":"6160",
    "sg:province":"WA",
    "sg:tags":[
        "medical",
        "practitioner"
    ],
    "wof:name":"Gebauer Hannes DR",
    "wof:placetype":"venue"
},
  "geometry": {"coordinates":[115.753807,-32.052292],"type":"Point"}
}