{
  "type": "Feature",
  "properties": {
    "addr:full":"33 Grubb St Beaconsfield TAS 7270",
    "addr:housenumber":"33",
    "addr:postcode":"7270",
    "addr:street":"Grubb St",
    "iso:country":"AU",
    "sg:address":"33 Grubb St",
    "sg:city":"Beaconsfield",
    "sg:classifiers":[
        {
            "category":"Education",
            "subcategory":"School",
            "type":"Public Place"
        }
    ],
    "sg:phone":"+61 3 6383 1215",
    "sg:postcode":"7270",
    "sg:province":"TAS",
    "sg:tags":[
        "state",
        "except",
        "nsw"
    ],
    "wof:name":"Beaconsfield Primary School",
    "wof:placetype":"venue"
},
  "geometry": {"coordinates":[146.81922912600001,-41.2012748718],"type":"Point"}
}