{
  "type": "Feature",
  "properties": {
    "addr:full":"17 Botany St Phillip ACT 2606",
    "addr:housenumber":"17",
    "addr:postcode":"2606",
    "addr:street":"Botany St",
    "iso:country":"AU",
    "sg:address":"17 Botany St",
    "sg:city":"Phillip",
    "sg:classifiers":[
        {
            "category":"Fast Food",
            "type":"Food & Drink"
        }
    ],
    "sg:phone":"+61 2 6282 1303",
    "sg:postcode":"2606",
    "sg:province":"ACT",
    "sg:tags":[
        "away",
        "take"
    ],
    "wof:name":"Phillip Snack Bar",
    "wof:placetype":"venue"
},
  "geometry": {"coordinates":[149.08689880399999,-35.3506965637],"type":"Point"}
}