{
  "type": "Feature",
  "properties": {
    "addr:full":"4th Floor 231 Adelaide Tce Perth WA 6000",
    "addr:housenumber":"231",
    "addr:postcode":"6000",
    "addr:street":"Adelaide Tce",
    "iso:country":"AU",
    "sg:address":"4th Floor 231",
    "sg:city":"Adelaide Tce Perth",
    "sg:classifiers":[
        {
            "category":"Professional",
            "subcategory":"Employment Agencies",
            "type":"Services"
        }
    ],
    "sg:phone":"+61 8 9202 1088",
    "sg:postcode":"6000",
    "sg:province":"WA",
    "sg:tags":[
        "provider",
        "internet"
    ],
    "wof:name":"Touch88 Internet",
    "wof:placetype":"venue"
},
  "geometry": {"coordinates":[115.867576599,-31.958486557],"type":"Point"}
}