{
  "type": "Feature",
  "properties": {
    "addr:full":"61B Tyers St Stratford VIC 3862",
    "addr:housenumber":"61b",
    "addr:postcode":"3862",
    "addr:street":"Tyers St",
    "iso:country":"AU",
    "sg:address":"61B Tyers St",
    "sg:city":"Stratford",
    "sg:classifiers":[
        {
            "category":"Food & Beverages",
            "subcategory":"Bakery",
            "type":"Retail Goods"
        }
    ],
    "sg:phone":"+61 3 5145 6777",
    "sg:postcode":"3862",
    "sg:province":"VIC",
    "sg:tags":[
        "cake",
        "shop",
        "pastry"
    ],
    "wof:name":"Sugar Coated",
    "wof:placetype":"venue"
},
  "geometry": {"coordinates":[147.08607482900001,-37.9613838196],"type":"Point"}
}