{
  "type": "Feature",
  "properties": {
    "addr:full":"71 Victoria St Mackay QLD 4740",
    "addr:housenumber":"71",
    "addr:postcode":"4740",
    "addr:street":"Victoria St",
    "iso:country":"AU",
    "sg:address":"71 Victoria St",
    "sg:city":"Mackay",
    "sg:classifiers":[
        {
            "category":"Banks & Credit Unions",
            "subcategory":"Financial Services",
            "type":"Services"
        }
    ],
    "sg:phone":"+61 7 4944 0449",
    "sg:postcode":"4740",
    "sg:province":"QLD",
    "sg:tags":[
        "planning"
    ],
    "wof:name":"DGL Financial Planning Services",
    "wof:placetype":"venue"
},
  "geometry": {"coordinates":[149.186691,-21.14152],"type":"Point"}
}