{
  "type": "Feature",
  "properties": {
    "addr:full":"50 Alfred St North Sydney NSW 2060",
    "addr:housenumber":"50",
    "addr:postcode":"2060",
    "addr:street":"Alfred St",
    "iso:country":"AU",
    "sg:address":"50 Alfred St",
    "sg:city":"North Sydney",
    "sg:classifiers":[
        {
            "category":"Cafe",
            "type":"Food & Drink"
        }
    ],
    "sg:phone":"+61 2 9964 0032",
    "sg:postcode":"2060",
    "sg:province":"NSW",
    "wof:name":"Bar Ezanetti",
    "wof:placetype":"venue"
},
  "geometry": {"coordinates":[151.211334228,-33.8391456604],"type":"Point"}
}