{
  "type": "Feature",
  "properties": {
    "iso:country":"AU",
    "sg:address":"Lot 66 Riverbanks Rd",
    "sg:city":"Hillier",
    "sg:classifiers":[
        {
            "category":"Building & Trades",
            "subcategory":"Construction",
            "type":"Services"
        }
    ],
    "sg:phone":"+61 8 8284 8112",
    "sg:postcode":"5116",
    "sg:province":"SA",
    "sg:tags":[
        "concrete",
        "treatment",
        "repair"
    ],
    "wof:name":"A.A.A. Concrete Cutting & Floor Repairs",
    "wof:placetype":"venue"
},
  "geometry": {"coordinates":[138.66424560600001,-34.6283760071],"type":"Point"}
}