{
  "type": "Feature",
  "properties": {
    "addr:full":"2/Lot 41 Enterprise Drv Berkeley Vale NSW 2261",
    "addr:housenumber":"/;41",
    "addr:postcode":"2261",
    "addr:street":"Lot;Enterprise Drv",
    "iso:country":"AU",
    "sg:address":"2/Lot 41 Enterprise Drv",
    "sg:city":"Berkeley Vale",
    "sg:classifiers":[
        {
            "category":"Industrial Area",
            "type":"Public Place"
        }
    ],
    "sg:phone":"+61 2 4389 1434",
    "sg:postcode":"2261",
    "sg:province":"NSW",
    "sg:tags":[
        "protective",
        "clothing"
    ],
    "wof:name":"Lawrence & Hanson",
    "wof:placetype":"venue"
},
  "geometry": {"coordinates":[151.42749000000001,-33.328785],"type":"Point"}
}