{
  "type": "Feature",
  "properties": {
    "iso:country":"AU",
    "sg:address":"2/Lot 41 Enterprise Drv",
    "sg:city":"Berkeley Vale",
    "sg:classifiers":[
        {
            "category":"Industrial Area",
            "type":"Public Place"
        }
    ],
    "sg:phone":"+61 2 4389 1434",
    "sg:postcode":"2261",
    "sg:province":"NSW",
    "sg:tags":[
        "protective",
        "clothing"
    ],
    "wof:name":"Lawrence & Hanson",
    "wof:placetype":"venue"
},
  "geometry": {"coordinates":[151.42749,-33.328785],"type":"Point"}
}