{
  "type": "Feature",
  "properties": {
    "addr:full":"824 Laurie St Ballarat VIC 3350",
    "addr:housenumber":"824",
    "addr:postcode":"3350",
    "addr:street":"Laurie St",
    "iso:country":"AU",
    "sg:address":"824 Laurie St",
    "sg:city":"Ballarat",
    "sg:classifiers":[
        {
            "category":"Professional",
            "subcategory":"Printing & Photocopies",
            "type":"Services"
        }
    ],
    "sg:phone":"+61 3 5333 5513",
    "sg:postcode":"3350",
    "sg:province":"VIC",
    "sg:tags":[
        "textile",
        "clothing"
    ],
    "wof:name":"B & D Troughton Screen Printers",
    "wof:placetype":"venue"
},
  "geometry": {"coordinates":[143.854309,-37.577908],"type":"Point"}
}