{
  "type": "Feature",
  "properties": {
    "iso:country":"AU",
    "sg:address":"18 Halifax Drv",
    "sg:city":"Bunbury",
    "sg:classifiers":[
        {
            "category":"Wholesale",
            "subcategory":"Painting Supplies",
            "type":"Manufacturing & Wholesale Goods"
        }
    ],
    "sg:phone":"+61 8 9721 1433",
    "sg:postcode":"6230",
    "sg:province":"WA",
    "sg:tags":[
        "product",
        "cleaning"
    ],
    "wof:name":"Klen International Pty Ltd",
    "wof:placetype":"venue"
},
  "geometry": {"coordinates":[115.669052,-33.359585],"type":"Point"}
}