{
  "type": "Feature",
  "properties": {
    "addr:full":"1/ 57 Mountbatten Drv Dubbo NSW 2830",
    "addr:housenumber":"/ 57",
    "addr:postcode":"2830",
    "addr:street":"Mountbatten Drv",
    "iso:country":"AU",
    "sg:address":"1/ 57 Mountbatten Drv",
    "sg:city":"Dubbo",
    "sg:classifiers":[
        {
            "category":"Professional",
            "subcategory":"Art Services",
            "type":"Services"
        }
    ],
    "sg:phone":"+61 2 6885 5753",
    "sg:postcode":"2830",
    "sg:province":"NSW",
    "sg:tags":[
        "graphic",
        "designer"
    ],
    "wof:name":"Western Xpress Printing",
    "wof:placetype":"venue"
},
  "geometry": {"coordinates":[148.64755249000001,-32.2530250549],"type":"Point"}
}