{
  "type": "Feature",
  "properties": {
    "addr:full":"90 Kingston Rd Underwood QLD 4119",
    "addr:housenumber":"90",
    "addr:postcode":"4119",
    "addr:street":"Kingston Rd",
    "iso:country":"AU",
    "sg:address":"90 Kingston Rd",
    "sg:city":"Underwood",
    "sg:classifiers":[
        {
            "category":"Home & Garden",
            "subcategory":"Hardware",
            "type":"Retail Goods"
        }
    ],
    "sg:phone":"+61 7 3208 8022",
    "sg:postcode":"4119",
    "sg:province":"QLD",
    "sg:tags":[
        "plumber",
        "supply"
    ],
    "wof:name":"Tradelink Plumbing Centres",
    "wof:placetype":"venue"
},
  "geometry": {"coordinates":[153.11488342300001,-27.6156253815],"type":"Point"}
}