{
  "type": "Feature",
  "properties": {
    "addr:full":"Lvl 1, Pacific Square Shopng Cntr, 737 Anzac Parade Maroubra NSW 2035",
    "addr:housenumber":"737",
    "addr:postcode":"2035",
    "addr:street":"Pacific;Anzac Parade",
    "iso:country":"AU",
    "sg:address":"Lvl 1, Pacific Square Shopng Cntr, 737 Anzac Parade",
    "sg:city":"Maroubra",
    "sg:classifiers":[
        {
            "category":"Sports & Exercise",
            "subcategory":"Gym",
            "type":"Entertainment"
        }
    ],
    "sg:phone":"+61 1300 557 799",
    "sg:postcode":"2035",
    "sg:province":"NSW",
    "sg:tags":[
        "health",
        "fitness"
    ],
    "wof:name":"Fitness First Maroubra",
    "wof:placetype":"venue"
},
  "geometry": {"coordinates":[151.23887634299999,-33.9410896301],"type":"Point"}
}