{
  "type": "Feature",
  "properties": {
    "iso:country":"AU",
    "sg:address":"519 Kessels Rd",
    "sg:city":"MacGregor",
    "sg:classifiers":[
        {
            "category":"Utilities",
            "subcategory":"Cable",
            "type":"Services"
        }
    ],
    "sg:phone":"+61 7 3849 9900",
    "sg:postcode":"4109",
    "sg:province":"QLD",
    "sg:tags":[
        "headset"
    ],
    "wof:name":"BTC Direct",
    "wof:placetype":"venue"
},
  "geometry": {"coordinates":[153.06712341299999,-27.561340332],"type":"Point"}
}