{
  "type": "Feature",
  "properties": {
    "addr:full":"205 Stuart Drv Wulguru QLD 4811",
    "addr:housenumber":"205",
    "addr:postcode":"4811",
    "addr:street":"Stuart Drv",
    "iso:country":"AU",
    "sg:address":"205 Stuart Drv",
    "sg:city":"Wulguru",
    "sg:classifiers":[
        {
            "category":"Building & Trades",
            "subcategory":"Landscaping Services",
            "type":"Services"
        }
    ],
    "sg:phone":"+61 7 4778 4357",
    "sg:postcode":"4811",
    "sg:province":"QLD",
    "sg:tags":[
        "grazier"
    ],
    "wof:name":"Edwin Francis",
    "wof:placetype":"venue"
},
  "geometry": {"coordinates":[146.817093,-19.322212],"type":"Point"}
}