{
  "type": "Feature",
  "properties": {
    "iso:country":"AU",
    "sg:address":"Seamark 29 First Ave",
    "sg:city":"Mooloolaba",
    "sg:classifiers":[
        {
            "category":"Shopping",
            "subcategory":"Clothing, Apparel, & Fashions",
            "type":"Retail Goods"
        }
    ],
    "sg:phone":"+61 7 5444 4200",
    "sg:postcode":"4557",
    "sg:province":"QLD",
    "sg:tags":[
        "menswear"
    ],
    "wof:name":"Klingers Menswear",
    "wof:placetype":"venue"
},
  "geometry": {"coordinates":[153.119506836,-26.6803569794],"type":"Point"}
}