{
  "type": "Feature",
  "properties": {
    "addr:full":"11 Walan St Mooloolaba QLD 4557",
    "addr:housenumber":"11",
    "addr:postcode":"4557",
    "addr:street":"Walan St",
    "iso:country":"AU",
    "sg:address":"11 Walan St",
    "sg:city":"Mooloolaba",
    "sg:classifiers":[
        {
            "category":"Professional",
            "subcategory":"Business Services",
            "type":"Services"
        }
    ],
    "sg:phone":"+61 7 5444 3300",
    "sg:postcode":"4557",
    "sg:province":"QLD",
    "sg:tags":[
        "broker"
    ],
    "wof:name":"Savvy Business Sales",
    "wof:placetype":"venue"
},
  "geometry": {"coordinates":[153.11846923799999,-26.6817073822],"type":"Point"}
}