{
  "type": "Feature",
  "properties": {
    "addr:full":"12 Oliver Crt Fawkner VIC 3060",
    "addr:housenumber":"12",
    "addr:postcode":"3060",
    "addr:street":"Oliver Crt",
    "iso:country":"AU",
    "sg:address":"12 Oliver Crt",
    "sg:city":"Fawkner",
    "sg:classifiers":[
        {
            "category":"Manufacturing",
            "subcategory":"Tools & Machinery",
            "type":"Manufacturing & Wholesale Goods"
        }
    ],
    "sg:phone":"+61 3 9357 1939",
    "sg:postcode":"3060",
    "sg:province":"VIC",
    "sg:tags":[
        "toolmaker"
    ],
    "wof:name":"J.D. Service Centre",
    "wof:placetype":"venue"
},
  "geometry": {"coordinates":[144.96005249000001,-37.6907196045],"type":"Point"}
}