{
  "type": "Feature",
  "properties": {
    "addr:full":"Stuart Hwy Darwin NT 0800",
    "addr:postcode":"nt 0800",
    "addr:street":"Stuart Hwy",
    "iso:country":"AU",
    "sg:address":"Stuart Hwy",
    "sg:city":"Darwin",
    "sg:classifiers":[
        {
            "category":"Autos & Motor Vehicles",
            "subcategory":"Fuel & Gas Station",
            "type":"Retail Goods"
        }
    ],
    "sg:phone":"+61 8 8932 2835",
    "sg:postcode":"0800",
    "sg:province":"NT",
    "wof:name":"BP Australia Limited",
    "wof:placetype":"venue"
},
  "geometry": {"coordinates":[130.83981323200001,-12.4540805817],"type":"Point"}
}