{
  "type": "Feature",
  "properties": {
    "iso:country":"AU",
    "sg:address":"30 Mitchell Rd",
    "sg:city":"Woonona",
    "sg:classifiers":[
        {
            "category":"Building & Trades",
            "subcategory":"Construction",
            "type":"Services"
        }
    ],
    "sg:phone":"+61 2 4284 8543",
    "sg:postcode":"2517",
    "sg:province":"NSW",
    "sg:tags":[
        "rendering",
        "cement"
    ],
    "wof:name":"El-Faham Cement Rendering",
    "wof:placetype":"venue"
},
  "geometry": {"coordinates":[150.910965,-34.349365],"type":"Point"}
}