{
  "type": "Feature",
  "properties": {
    "addr:full":"Cnr Forest Rd & Cronulla St Hurstville NSW 2220",
    "addr:postcode":"2220",
    "addr:street":"Cnr Forest Rd & Cronulla St",
    "iso:country":"AU",
    "sg:address":"Cnr Forest Rd & Cronulla St",
    "sg:city":"Hurstville",
    "sg:classifiers":[
        {
            "category":"Structure",
            "subcategory":"Bridge",
            "type":"Public Place"
        }
    ],
    "sg:phone":"+61 2 9587 2744",
    "sg:postcode":"2220",
    "sg:province":"NSW",
    "sg:tags":[
        "chainsaw",
        "brushcutters"
    ],
    "wof:name":"Lawrence Bros Power Equipment",
    "wof:placetype":"venue"
},
  "geometry": {"coordinates":[151.10104370100001,-33.9671897888],"type":"Point"}
}