{
  "type": "Feature",
  "properties": {
    "iso:country":"AU",
    "sg:address":"Shop 4 56-64 Church St",
    "sg:city":"Whittlesea",
    "sg:classifiers":[
        {
            "category":"Banks & Credit Unions",
            "subcategory":"Bank",
            "type":"Services"
        }
    ],
    "sg:phone":"+61 3 9716 2855",
    "sg:postcode":"3757",
    "sg:province":"VIC",
    "sg:tags":[
        "society"
    ],
    "wof:name":"Plenty Credit Co-Operative Ltd",
    "wof:placetype":"venue"
},
  "geometry": {"coordinates":[145.118301,-37.51149],"type":"Point"}
}