{
  "type": "Feature",
  "properties": {
    "iso:country":"AU",
    "sg:address":"Shop 3/ 162 John St",
    "sg:city":"Singleton",
    "sg:classifiers":[
        {
            "category":"Home & Garden",
            "subcategory":"Furniture",
            "type":"Retail Goods"
        }
    ],
    "sg:phone":"+61 2 6572 4162",
    "sg:postcode":"2330",
    "sg:province":"NSW",
    "sg:tags":[
        "business"
    ],
    "wof:name":"Singleton Office Furniture",
    "wof:placetype":"venue"
},
  "geometry": {"coordinates":[151.175568,-32.562233],"type":"Point"}
}