{
  "type": "Feature",
  "properties": {
    "addr:full":"The Mighty Quinn, 112 Wanneroo Rd Tuart Hill WA 6060",
    "addr:housenumber":"112",
    "addr:postcode":"6060",
    "addr:street":"Wanneroo Rd",
    "iso:country":"AU",
    "sg:address":"The Mighty Quinn, 112 Wanneroo Rd",
    "sg:city":"Tuart Hill",
    "sg:classifiers":[
        {
            "category":"Food & Beverages",
            "subcategory":"Liquor & Beverages",
            "type":"Retail Goods"
        }
    ],
    "sg:phone":"+61 8 9349 9600",
    "sg:postcode":"6060",
    "sg:province":"WA",
    "sg:tags":[
        "store"
    ],
    "wof:name":"Sip'n Save Tuart Hill",
    "wof:placetype":"venue"
},
  "geometry": {"coordinates":[115.842460632,-31.9006385803],"type":"Point"}
}