{
  "type": "Feature",
  "properties": {
    "addr:full":"9/ 101 Winton Rd Joondalup WA 6027",
    "addr:housenumber":"/ 101",
    "addr:postcode":"6027",
    "addr:street":"Winton Rd",
    "iso:country":"AU",
    "sg:address":"9/ 101 Winton Rd",
    "sg:city":"Joondalup",
    "sg:classifiers":[
        {
            "category":"Retail",
            "subcategory":"Auto Repair",
            "type":"Services"
        }
    ],
    "sg:phone":"+61 8 9300 3693",
    "sg:postcode":"6027",
    "sg:province":"WA",
    "sg:tags":[
        "automotive",
        "air conditioning"
    ],
    "wof:name":"AAA The Auto Clinic",
    "wof:placetype":"venue"
},
  "geometry": {"coordinates":[115.759498596,-31.743024826],"type":"Point"}
}