{
  "type": "Feature",
  "properties": {
    "iso:country":"AU",
    "sg:address":"344 B Main Rd West",
    "sg:city":"St Albans",
    "sg:classifiers":[
        {
            "category":"Food & Beverages",
            "subcategory":"Groceries & Convenience Stores",
            "type":"Retail Goods"
        }
    ],
    "sg:phone":"+61 3 9310 7256",
    "sg:postcode":"3021",
    "sg:province":"VIC",
    "wof:name":"Next Mart",
    "wof:placetype":"venue"
},
  "geometry": {"coordinates":[144.778946,-37.741882],"type":"Point"}
}