{
  "type": "Feature",
  "properties": {
    "addr:full":"344 B Main Rd West St Albans VIC 3021",
    "addr:housenumber":"344 b",
    "addr:postcode":"3021",
    "addr:street":"Main Rd",
    "iso:country":"AU",
    "sg:address":"344 B Main Rd West",
    "sg:city":"St Albans",
    "sg:classifiers":[
        {
            "category":"Food & Beverages",
            "subcategory":"Groceries & Convenience Stores",
            "type":"Retail Goods"
        }
    ],
    "sg:phone":"+61 3 9310 7256",
    "sg:postcode":"3021",
    "sg:province":"VIC",
    "wof:name":"Next Mart",
    "wof:placetype":"venue"
},
  "geometry": {"coordinates":[144.77894599999999,-37.741882],"type":"Point"}
}