{
  "type": "Feature",
  "properties": {
    "addr:full":"96-100 Governor Rd Mordialloc VIC 3195",
    "addr:housenumber":"96-100",
    "addr:postcode":"3195",
    "addr:street":"Governor Rd",
    "iso:country":"AU",
    "sg:address":"96-100 Governor Rd",
    "sg:city":"Mordialloc",
    "sg:classifiers":[
        {
            "category":"Retail",
            "subcategory":"Repair Shop",
            "type":"Services"
        }
    ],
    "sg:phone":"+61 3 9588 1502",
    "sg:postcode":"3195",
    "sg:province":"VIC",
    "sg:tags":[
        "maintenance",
        "pool",
        "swimming"
    ],
    "wof:name":"Melbournes Pool & Spa Centre",
    "wof:placetype":"venue"
},
  "geometry": {"coordinates":[145.10310363799999,-38.0075798035],"type":"Point"}
}