{
  "type": "Feature",
  "properties": {
    "iso:country":"AU",
    "sg:address":"20 Isabella St",
    "sg:city":"Wingham",
    "sg:classifiers":[
        {
            "category":"Personal",
            "subcategory":"Beauty Salon",
            "type":"Services"
        }
    ],
    "sg:phone":"+61 2 6553 5366",
    "sg:postcode":"2429",
    "sg:province":"NSW",
    "sg:tags":[
        "hairdresser"
    ],
    "wof:name":"Suzie Bee",
    "wof:placetype":"venue"
},
  "geometry": {"coordinates":[152.37294,-31.868919],"type":"Point"}
}