{
  "type": "Feature",
  "properties": {
    "iso:country":"AU",
    "sg:address":"239 Fitzgerald St",
    "sg:city":"West Perth",
    "sg:classifiers":[
        {
            "category":"Professional",
            "subcategory":"Art Services",
            "type":"Services"
        }
    ],
    "sg:phone":"+61 8 9228 4060",
    "sg:postcode":"6005",
    "sg:province":"WA",
    "sg:tags":[
        "graphic",
        "designer"
    ],
    "wof:name":"Full.Stop Graphic Design",
    "wof:placetype":"venue"
},
  "geometry": {"coordinates":[115.85585021999999,-31.940202713],"type":"Point"}
}