{
  "type": "Feature",
  "properties": {
    "iso:country":"AU",
    "sg:address":"13- 39 Pilbara St",
    "sg:city":"Welshpool",
    "sg:classifiers":[
        {
            "category":"Autos & Motor Vehicles",
            "subcategory":"Auto Supplies",
            "type":"Retail Goods"
        }
    ],
    "sg:phone":"+61 8 9351 6677",
    "sg:postcode":"6106",
    "sg:province":"WA",
    "sg:tags":[
        "equipment",
        "part",
        "truck"
    ],
    "wof:name":"Skipper Trucks Parts",
    "wof:placetype":"venue"
},
  "geometry": {"coordinates":[115.939987183,-31.9925918579],"type":"Point"}
}