{
  "type": "Feature",
  "properties": {
    "addr:full":"Unit 3, 8 Thornborough Rd Mandurah WA 6210",
    "addr:housenumber":"8",
    "addr:postcode":"6210",
    "addr:street":"Thornborough Rd",
    "iso:country":"AU",
    "sg:address":"Unit 3, 8 Thornborough Rd",
    "sg:city":"Mandurah",
    "sg:classifiers":[
        {
            "category":"Building & Trades",
            "subcategory":"Construction",
            "type":"Services"
        }
    ],
    "sg:phone":"+61 8 9583 3511",
    "sg:postcode":"6210",
    "sg:province":"WA",
    "sg:tags":[
        "brick",
        "paving"
    ],
    "wof:name":"Blokpave",
    "wof:placetype":"venue"
},
  "geometry": {"coordinates":[115.75273900000001,-32.512726],"type":"Point"}
}