{
  "type": "Feature",
  "properties": {
    "addr:full":"27 Mundarra Rd Echuca VIC 3564",
    "addr:housenumber":"27",
    "addr:postcode":"3564",
    "addr:street":"Mundarra Rd",
    "iso:country":"AU",
    "sg:address":"27 Mundarra Rd",
    "sg:city":"Echuca",
    "sg:classifiers":[
        {
            "category":"Retail",
            "subcategory":"Auto Repair",
            "type":"Services"
        }
    ],
    "sg:phone":"+61 3 5482 4644",
    "sg:postcode":"3564",
    "sg:province":"VIC",
    "sg:tags":[
        "wheel",
        "balancing",
        "alignment"
    ],
    "wof:name":"Mayes Tyrepower",
    "wof:placetype":"venue"
},
  "geometry": {"coordinates":[144.76075744600001,-36.1420021057],"type":"Point"}
}