{
  "type": "Feature",
  "properties": {
    "addr:full":"Fcty2/ 180 Northgate Rd Northgate QLD 4013",
    "addr:housenumber":"180",
    "addr:postcode":"4013",
    "addr:street":"Northgate Rd",
    "iso:country":"AU",
    "sg:address":"Fcty2/ 180 Northgate Rd",
    "sg:city":"Northgate",
    "sg:classifiers":[
        {
            "category":"Home & Garden",
            "subcategory":"Carpets & Floor Coverings",
            "type":"Retail Goods"
        }
    ],
    "sg:phone":"+61 7 3266 9900",
    "sg:postcode":"4013",
    "sg:province":"QLD",
    "sg:tags":[
        "tile",
        "wall"
    ],
    "wof:name":"Venizea Tiles",
    "wof:placetype":"venue"
},
  "geometry": {"coordinates":[153.06773376500001,-27.3886203766],"type":"Point"}
}