{
  "type": "Feature",
  "properties": {
    "iso:country":"AU",
    "sg:address":"110 Queenscliff Drv",
    "sg:city":"Woodbine",
    "sg:classifiers":[
        {
            "category":"Health Services",
            "subcategory":"Health Practitioner",
            "type":"Services"
        }
    ],
    "sg:phone":"+61 2 4625 0545",
    "sg:postcode":"2560",
    "sg:province":"NSW",
    "sg:tags":[
        "naturopath"
    ],
    "wof:name":"Macarthur Homoeopathic Centre",
    "wof:placetype":"venue"
},
  "geometry": {"coordinates":[150.82344055199999,-34.0450057983],"type":"Point"}
}