{
  "type": "Feature",
  "properties": {
    "addr:full":"73 Wilson St Brighton VIC 3186",
    "addr:housenumber":"73",
    "addr:postcode":"3186",
    "addr:street":"Wilson St",
    "iso:country":"AU",
    "sg:address":"73 Wilson St",
    "sg:city":"Brighton",
    "sg:classifiers":[
        {
            "category":"Building & Trades",
            "subcategory":"Landscaping Services",
            "type":"Services"
        }
    ],
    "sg:phone":"+61 3 9592 7090",
    "sg:postcode":"3186",
    "sg:province":"VIC",
    "sg:tags":[
        "timing",
        "equipment"
    ],
    "wof:name":"R P ( ARPEE ) Developments",
    "wof:placetype":"venue"
},
  "geometry": {"coordinates":[145.00221252399999,-37.9137115479],"type":"Point"}
}