{
  "type": "Feature",
  "properties": {
    "addr:full":"183 Gymea Bay Rd Gymea NSW 2227",
    "addr:housenumber":"183",
    "addr:postcode":"2227",
    "addr:street":"Gymea Bay Rd",
    "iso:country":"AU",
    "sg:address":"183 Gymea Bay Rd",
    "sg:city":"Gymea",
    "sg:classifiers":[
        {
            "category":"Transit Center",
            "subcategory":"Freight",
            "type":"Transportation"
        }
    ],
    "sg:phone":"+61 419 265 896",
    "sg:postcode":"2227",
    "sg:province":"NSW",
    "sg:tags":[
        "forklift",
        "truck"
    ],
    "wof:name":"W G Forklift Services",
    "wof:placetype":"venue"
},
  "geometry": {"coordinates":[151.08323669399999,-34.0431480408],"type":"Point"}
}