{
  "type": "Feature",
  "properties": {
    "addr:full":"32 Chapel St Norwood SA 5067",
    "addr:housenumber":"32",
    "addr:postcode":"5067",
    "addr:street":"Chapel St",
    "iso:country":"AU",
    "sg:address":"32 Chapel St",
    "sg:city":"Norwood",
    "sg:classifiers":[
        {
            "category":"Shopping",
            "subcategory":"Stationery & Office Supplies",
            "type":"Retail Goods"
        }
    ],
    "sg:phone":"+61 8 8363 1655",
    "sg:postcode":"5067",
    "sg:province":"SA",
    "sg:tags":[
        "equipment",
        "badge",
        "making"
    ],
    "wof:name":"Badge Factory The",
    "wof:placetype":"venue"
},
  "geometry": {"coordinates":[138.62510681099999,-34.9167442322],"type":"Point"}
}