{
  "type": "Feature",
  "properties": {
    "addr:full":"55 Glencoe Rd Murwillumbah NSW 2484",
    "addr:housenumber":"55",
    "addr:postcode":"2484",
    "addr:street":"Glencoe Rd",
    "iso:country":"AU",
    "sg:address":"55 Glencoe Rd",
    "sg:city":"Murwillumbah",
    "sg:classifiers":[
        {
            "category":"Shopping",
            "subcategory":"Musical Instruments",
            "type":"Retail Goods"
        }
    ],
    "sg:phone":"+61 2 6672 6719",
    "sg:postcode":"2484",
    "sg:province":"NSW",
    "sg:tags":[
        "musician",
        "agent"
    ],
    "wof:name":"Cattanach Rob",
    "wof:placetype":"venue"
},
  "geometry": {"coordinates":[153.34149169899999,-28.331205368],"type":"Point"}
}