{
  "type": "Feature",
  "properties": {
    "addr:full":"Level 3, Septimus Roe Square, 256 Adelaide Tce, Pe Perth WA 6000",
    "addr:housenumber":"256",
    "addr:postcode":"6000",
    "addr:street":"Septimus Roe;Adelaide Tce",
    "iso:country":"AU",
    "sg:address":"Level 3, Septimus Roe Square, 256 Adelaide Tce, Pe",
    "sg:city":"Perth",
    "sg:classifiers":[
        {
            "category":"Professional",
            "subcategory":"Computer Services",
            "type":"Services"
        }
    ],
    "sg:phone":"+61 8 9282 9200",
    "sg:postcode":"6000",
    "sg:province":"WA",
    "sg:tags":[
        "package",
        "software"
    ],
    "wof:name":"OSIsoft Australia Pty Ltd",
    "wof:placetype":"venue"
},
  "geometry": {"coordinates":[115.865730286,-31.9576511383],"type":"Point"}
}