{
  "type": "Feature",
  "properties": {
    "addr:full":"189- 191 Queen St Ayr QLD 4807",
    "addr:housenumber":"191",
    "addr:postcode":"4807",
    "addr:street":"Queen St",
    "iso:country":"AU",
    "sg:address":"189- 191 Queen St",
    "sg:city":"Ayr",
    "sg:classifiers":[
        {
            "category":"Autos & Motor Vehicles",
            "subcategory":"Auto Supplies",
            "type":"Retail Goods"
        }
    ],
    "sg:phone":"+61 7 4783 1352",
    "sg:postcode":"4807",
    "sg:province":"QLD",
    "sg:tags":[
        "accessory"
    ],
    "wof:name":"Autopro",
    "wof:placetype":"venue"
},
  "geometry": {"coordinates":[147.40229797399999,-19.5789279938],"type":"Point"}
}