{
  "type": "Feature",
  "properties": {
    "addr:full":"18 Hudson Ave Castle Hill NSW 2154",
    "addr:housenumber":"18",
    "addr:postcode":"2154",
    "addr:street":"Hudson Ave",
    "iso:country":"AU",
    "sg:address":"18 Hudson Ave",
    "sg:city":"Castle Hill",
    "sg:phone":"+61 2 9354 8222",
    "sg:postcode":"2154",
    "sg:province":"NSW",
    "wof:name":"Shoketsu Pneumatic Equipment",
    "wof:placetype":"venue"
},
  "geometry": {"coordinates":[150.97454834000001,-33.7291030884],"type":"Point"}
}