{
  "type": "Feature",
  "properties": {
    "addr:full":"38 Russell St West End (Brisbane) QLD 4101",
    "addr:housenumber":"38",
    "addr:postcode":"4101",
    "addr:street":"Russell St",
    "iso:country":"AU",
    "sg:address":"38 Russell St",
    "sg:city":"West End (Brisbane)",
    "sg:classifiers":[
        {
            "category":"Health Services",
            "subcategory":"Doctor",
            "type":"Services"
        }
    ],
    "sg:phone":"+61 7 3846 4888",
    "sg:postcode":"4101",
    "sg:province":"QLD",
    "sg:tags":[
        "medical",
        "practitioner"
    ],
    "wof:name":"West End Medical Practice",
    "wof:placetype":"venue"
},
  "geometry": {"coordinates":[153.01362609899999,-27.4790878296],"type":"Point"}
}