{
  "type": "Feature",
  "properties": {
    "iso:country":"AU",
    "sg:address":"1st Floor 102 Kembla St",
    "sg:city":"Wollongong",
    "sg:classifiers":[
        {
            "category":"Social Services",
            "type":"Services"
        }
    ],
    "sg:phone":"+61 2 4227 5559",
    "sg:postcode":"2500",
    "sg:province":"NSW",
    "sg:tags":[
        "kinesiology"
    ],
    "wof:name":"Karyl Cave",
    "wof:placetype":"venue"
},
  "geometry": {"coordinates":[150.89665199999999,-34.428307],"type":"Point"}
}