{
  "type": "Feature",
  "properties": {
    "addr:full":"82 Wychbury La Croydon NSW 2132",
    "addr:housenumber":"82",
    "addr:postcode":"2132",
    "addr:street":"Wychbury La",
    "iso:country":"AU",
    "sg:address":"82 Wychbury La",
    "sg:city":"Croydon",
    "sg:classifiers":[
        {
            "category":"Autos & Motor Vehicles",
            "subcategory":"Auto Supplies",
            "type":"Retail Goods"
        }
    ],
    "sg:phone":"+61 2 9701 0274",
    "sg:postcode":"2132",
    "sg:province":"NSW",
    "sg:tags":[
        "part",
        "cycles",
        "accessory"
    ],
    "wof:name":"Skidz Motorcycle Tyres",
    "wof:placetype":"venue"
},
  "geometry": {"coordinates":[151.11451721200001,-33.8712043762],"type":"Point"}
}