{
  "type": "Feature",
  "properties": {
    "addr:full":"10 Carson Ave Keysborough VIC 3173",
    "addr:housenumber":"10",
    "addr:postcode":"3173",
    "addr:street":"Carson Ave",
    "iso:country":"AU",
    "sg:address":"10 Carson Ave",
    "sg:city":"Keysborough",
    "sg:classifiers":[
        {
            "category":"Manufacturing",
            "subcategory":"Metals",
            "type":"Manufacturing & Wholesale Goods"
        }
    ],
    "sg:phone":"+61 3 9798 4433",
    "sg:postcode":"3173",
    "sg:province":"VIC",
    "sg:tags":[
        "wholesaler",
        "aluminium",
        "mfrs"
    ],
    "wof:name":"Pivotech",
    "wof:placetype":"venue"
},
  "geometry": {"coordinates":[145.148803711,-37.9899406433],"type":"Point"}
}