{
  "type": "Feature",
  "properties": {
    "addr:full":"Lot 2 Baileys La Abermain NSW 2326",
    "addr:housenumber":"2",
    "addr:postcode":"2326",
    "addr:street":"Baileys La Abermain",
    "iso:country":"AU",
    "sg:address":"Lot 2 Baileys La",
    "sg:city":"Abermain",
    "sg:classifiers":[
        {
            "category":"Professional",
            "subcategory":"Art Services",
            "type":"Services"
        }
    ],
    "sg:phone":"+61 2 4930 4670",
    "sg:postcode":"2326",
    "sg:province":"NSW",
    "sg:tags":[
        "decorator",
        "painter"
    ],
    "wof:name":"Coalfields Signs",
    "wof:placetype":"venue"
},
  "geometry": {"coordinates":[151.44070434599999,-32.8013343811],"type":"Point"}
}