{
  "type": "Feature",
  "properties": {
    "iso:country":"AU",
    "sg:address":"13 Nelson St",
    "sg:city":"Mackay",
    "sg:classifiers":[
        {
            "category":"Health Services",
            "subcategory":"Doctor",
            "type":"Services"
        }
    ],
    "sg:phone":"+61 7 4953 1088",
    "sg:postcode":"4740",
    "sg:province":"QLD",
    "sg:tags":[
        "occupational",
        "safety"
    ],
    "wof:name":"National Safety Council Of Australia Ltd",
    "wof:placetype":"venue"
},
  "geometry": {"coordinates":[149.18249499999999,-21.13917],"type":"Point"}
}