{
  "type": "Feature",
  "properties": {
    "addr:full":"PO Box 54 Lutwyche QLD 4030",
    "addr:postcode":"4030",
    "iso:country":"AU",
    "sg:address":"PO Box 54",
    "sg:city":"Lutwyche",
    "sg:classifiers":[
        {
            "category":"Home & Garden",
            "subcategory":"Hardware",
            "type":"Retail Goods"
        }
    ],
    "sg:phone":"+61 7 3357 6519",
    "sg:postcode":"4030",
    "sg:province":"QLD",
    "sg:tags":[
        "trolley",
        "truck",
        "hand"
    ],
    "wof:name":"Handi-Cart Trolley Centre",
    "wof:placetype":"venue"
},
  "geometry": {"coordinates":[153.033905,-27.42214],"type":"Point"}
}