{
  "type": "Feature",
  "properties": {
    "iso:country":"AU",
    "sg:address":"428 Princes Hwy",
    "sg:city":"Officer",
    "sg:classifiers":[
        {
            "category":"Retail",
            "subcategory":"Auto Repair",
            "type":"Services"
        }
    ],
    "sg:phone":"+61 3 5943 2375",
    "sg:postcode":"3809",
    "sg:province":"VIC",
    "sg:tags":[
        "repairer",
        "motor",
        "engineer"
    ],
    "wof:name":"Rawson Motors",
    "wof:placetype":"venue"
},
  "geometry": {"coordinates":[145.406036,-38.059364],"type":"Point"}
}