{
  "type": "Feature",
  "properties": {
    "iso:country":"AU",
    "sg:address":"1 Foundry St",
    "sg:city":"Wickham",
    "sg:classifiers":[
        {
            "category":"Building & Trades",
            "subcategory":"Construction",
            "type":"Services"
        }
    ],
    "sg:phone":"+61 2 4962 3298",
    "sg:postcode":"2293",
    "sg:province":"NSW",
    "sg:tags":[
        "welding"
    ],
    "wof:name":"C & J Sheetmetal Fabrications",
    "wof:placetype":"venue"
},
  "geometry": {"coordinates":[151.758255005,-32.9188690186],"type":"Point"}
}