{
  "type": "Feature",
  "properties": {
    "addr:full":"13 Outlook Pde Bray Park QLD 4500",
    "addr:housenumber":"13",
    "addr:postcode":"4500",
    "addr:street":"Outlook Pde Bray Park",
    "iso:country":"AU",
    "sg:address":"13 Outlook Pde",
    "sg:city":"Bray Park",
    "sg:classifiers":[
        {
            "category":"Retail",
            "subcategory":"Repair Shop",
            "type":"Services"
        }
    ],
    "sg:phone":"+61 7 3205 3008",
    "sg:postcode":"4500",
    "sg:province":"QLD",
    "sg:tags":[
        "upholsterer"
    ],
    "wof:name":"Blake B J",
    "wof:placetype":"venue"
},
  "geometry": {"coordinates":[152.97543335,-27.2887058258],"type":"Point"}
}