{
  "type": "Feature",
  "properties": {
    "addr:full":"Illaroo Rd Nowra North NSW 2541",
    "addr:postcode":"2541",
    "addr:street":"Illaroo Rd",
    "iso:country":"AU",
    "sg:address":"Illaroo Rd",
    "sg:city":"Nowra North",
    "sg:classifiers":[
        {
            "category":"Autos & Motor Vehicles",
            "subcategory":"Fuel & Gas Station",
            "type":"Retail Goods"
        }
    ],
    "sg:phone":"+61 2 4421 4268",
    "sg:postcode":"2541",
    "sg:province":"NSW",
    "wof:name":"Mobil Oil Australia Limited",
    "wof:placetype":"venue"
},
  "geometry": {"coordinates":[150.59246826200001,-34.8610153198],"type":"Point"}
}