{
  "type": "Feature",
  "properties": {
    "iso:country":"AU",
    "sg:address":"55- 57 Holbeche Rd",
    "sg:city":"Blacktown",
    "sg:classifiers":[
        {
            "category":"Building & Trades",
            "subcategory":"Construction",
            "type":"Services"
        }
    ],
    "sg:phone":"+61 2 9672 1465",
    "sg:postcode":"2148",
    "sg:province":"NSW",
    "sg:tags":[
        "fencing",
        "contractor"
    ],
    "sg:website":"http://www.billgibsonfencing.com.au",
    "wof:name":"Bill Gibson Fencing Pty Ltd",
    "wof:placetype":"venue"
},
  "geometry": {"coordinates":[150.889892578,-33.7896575928],"type":"Point"}
}