{
  "type": "Feature",
  "properties": {
    "addr:full":"PO Box 120 Warwick QLD 4370",
    "addr:postcode":"4370",
    "iso:country":"AU",
    "sg:address":"PO Box 120",
    "sg:city":"Warwick",
    "sg:classifiers":[
        {
            "category":"Building & Trades",
            "subcategory":"Construction",
            "type":"Services"
        }
    ],
    "sg:phone":"+61 7 4661 8873",
    "sg:postcode":"4370",
    "sg:province":"QLD",
    "sg:tags":[
        "earth",
        "excavating",
        "moving",
        "contractor"
    ],
    "wof:name":"Warwick Skid Steer & Backhoe Hire",
    "wof:placetype":"venue"
},
  "geometry": {"coordinates":[152.03465270999999,-28.2181301117],"type":"Point"}
}