{
  "type": "Feature",
  "properties": {
    "addr:full":"133 South St Tuncurry NSW 2428",
    "addr:housenumber":"133",
    "addr:postcode":"2428",
    "addr:street":"South St",
    "iso:country":"AU",
    "sg:address":"133 South St",
    "sg:city":"Tuncurry",
    "sg:classifiers":[
        {
            "category":"Place Of Worship",
            "subcategory":"Monastery",
            "type":"Public Place"
        }
    ],
    "sg:phone":"+61 2 6554 7447",
    "sg:postcode":"2428",
    "sg:province":"NSW",
    "sg:tags":[
        "residential",
        "village"
    ],
    "wof:name":"Crystal Waters Estate",
    "wof:placetype":"venue"
},
  "geometry": {"coordinates":[152.490387,-32.174137],"type":"Point"}
}