{
  "type": "Feature",
  "properties": {
    "addr:full":"27 Redwood Rd Kingston TAS 7050",
    "addr:housenumber":"27",
    "addr:postcode":"7050",
    "addr:street":"Redwood Rd",
    "iso:country":"AU",
    "sg:address":"27 Redwood Rd",
    "sg:city":"Kingston",
    "sg:classifiers":[
        {
            "category":"Health Services",
            "subcategory":"Nursing And Care Facility",
            "type":"Services"
        }
    ],
    "sg:phone":"+61 3 6229 5355",
    "sg:postcode":"7050",
    "sg:province":"TAS",
    "sg:tags":[
        "home"
    ],
    "wof:name":"Bishop Davies Court",
    "wof:placetype":"venue"
},
  "geometry": {"coordinates":[147.301086,-42.984299],"type":"Point"}
}