{
  "type": "Feature",
  "properties": {
    "addr:full":"104a Clairville Rd Campbelltown SA 5074",
    "addr:housenumber":"104a",
    "addr:postcode":"5074",
    "addr:street":"Clairville Rd",
    "iso:country":"AU",
    "sg:address":"104a Clairville Rd",
    "sg:city":"Campbelltown",
    "sg:classifiers":[
        {
            "category":"Building & Trades",
            "subcategory":"Construction",
            "type":"Services"
        }
    ],
    "sg:phone":"+61 437 001 180",
    "sg:postcode":"5074",
    "sg:province":"SA",
    "sg:tags":[
        "industrial",
        "commercial",
        "air conditioning"
    ],
    "wof:name":"SGK Electrical",
    "wof:placetype":"venue"
},
  "geometry": {"coordinates":[138.66978454599999,-34.8814315796],"type":"Point"}
}