{
  "type": "Feature",
  "properties": {
    "addr:full":"Level 18, 2 Park (Citicorp Centre) St Sydney NSW 2000",
    "addr:housenumber":"2",
    "addr:postcode":"2000",
    "addr:street":"Park Citicorp Centre St",
    "iso:country":"AU",
    "sg:address":"Level 18, 2 Park (Citicorp Centre) St",
    "sg:city":"Sydney",
    "sg:classifiers":[
        {
            "category":"Banks & Credit Unions",
            "subcategory":"Bureau De Change",
            "type":"Services"
        }
    ],
    "sg:phone":"+61 2 8263 0188",
    "sg:postcode":"2000",
    "sg:province":"NSW",
    "sg:tags":[
        "currency",
        "exchange",
        "foreign"
    ],
    "wof:name":"KVB KunLun Pty",
    "wof:placetype":"venue"
},
  "geometry": {"coordinates":[151.20773315400001,-33.8729286194],"type":"Point"}
}