{
  "type": "Feature",
  "properties": {
    "iso:country":"AU",
    "sg:address":"4 Falconer St",
    "sg:city":"Gatton",
    "sg:classifiers":[
        {
            "category":"Building & Trades",
            "subcategory":"Cleaning & Sanitation",
            "type":"Services"
        }
    ],
    "sg:phone":"+61 7 5462 4200",
    "sg:postcode":"4343",
    "sg:province":"QLD",
    "sg:tags":[
        "industrial",
        "commercial",
        "contractor"
    ],
    "wof:name":"Lockyer Valley Cleaning Services",
    "wof:placetype":"venue"
},
  "geometry": {"coordinates":[152.28500366200001,-27.5657157898],"type":"Point"}
}