{
  "type": "Feature",
  "properties": {
    "addr:full":"95 Campbell Rd Greenbank QLD 4124",
    "addr:housenumber":"95",
    "addr:postcode":"4124",
    "addr:street":"Campbell Rd",
    "iso:country":"AU",
    "sg:address":"95 Campbell Rd",
    "sg:city":"Greenbank",
    "sg:classifiers":[
        {
            "category":"Manufacturing",
            "subcategory":"Wood Products",
            "type":"Manufacturing & Wholesale Goods"
        }
    ],
    "sg:phone":"+61 7 3200 0477",
    "sg:postcode":"4124",
    "sg:province":"QLD",
    "sg:tags":[
        "polisher",
        "french"
    ],
    "wof:name":"Mitaros J P & F N",
    "wof:placetype":"venue"
},
  "geometry": {"coordinates":[152.998443603,-27.7274837494],"type":"Point"}
}