{
  "type": "Feature",
  "properties": {
    "addr:full":"Gordan Luck Ave Altona VIC 3018",
    "addr:postcode":"3018",
    "addr:street":"Ave",
    "iso:country":"AU",
    "sg:address":"Gordan Luck Ave",
    "sg:city":"Altona",
    "sg:classifiers":[
        {
            "category":"Professional",
            "type":"Services"
        }
    ],
    "sg:phone":"+61 1300 739 544",
    "sg:postcode":"3018",
    "sg:province":"VIC",
    "sg:tags":[
        "auctioneer"
    ],
    "wof:name":"Manheim Fowles",
    "wof:placetype":"venue"
},
  "geometry": {"coordinates":[144.82481384299999,-37.8638114929],"type":"Point"}
}