{
  "type": "Feature",
  "properties": {
    "iso:country":"AU",
    "sg:address":"201 Miller St",
    "sg:city":"North Sydney",
    "sg:classifiers":[
        {
            "category":"Banks & Credit Unions",
            "subcategory":"Financial Services",
            "type":"Services"
        }
    ],
    "sg:phone":"+61 2 9957 2207",
    "sg:postcode":"2060",
    "sg:province":"NSW",
    "sg:tags":[
        "planning"
    ],
    "wof:name":"Guest McLeod Pty Ltd",
    "wof:placetype":"venue"
},
  "geometry": {"coordinates":[151.20744323700001,-33.8366394043],"type":"Point"}
}