{
  "type": "Feature",
  "properties": {
    "addr:full":"5 Newlands Rd Reservoir VIC 3073",
    "addr:housenumber":"5",
    "addr:postcode":"3073",
    "addr:street":"Newlands Rd",
    "iso:country":"AU",
    "sg:address":"5 Newlands Rd",
    "sg:city":"Reservoir",
    "sg:classifiers":[
        {
            "category":"Home & Garden",
            "subcategory":"Hardware",
            "type":"Retail Goods"
        }
    ],
    "sg:phone":"+61 3 9462 2411",
    "sg:postcode":"3073",
    "sg:province":"VIC",
    "sg:tags":[
        "supply",
        "maker",
        "cabinet"
    ],
    "wof:name":"Kesko A Grade White Boards",
    "wof:placetype":"venue"
},
  "geometry": {"coordinates":[144.98320007300001,-37.7158737183],"type":"Point"}
}