{
  "type": "Feature",
  "properties": {
    "iso:country":"AU",
    "sg:address":"Unit 1/ 44 Boorea St",
    "sg:city":"Lidcombe",
    "sg:classifiers":[
        {
            "category":"Manufacturing",
            "subcategory":"Glass & Minerals",
            "type":"Manufacturing & Wholesale Goods"
        }
    ],
    "sg:phone":"+61 2 9649 7000",
    "sg:postcode":"2141",
    "sg:province":"NSW",
    "sg:tags":[
        "merchant",
        "granite",
        "marble"
    ],
    "wof:name":"Stone Connection Australia",
    "wof:placetype":"venue"
},
  "geometry": {"coordinates":[151.04226684599999,-33.853969574],"type":"Point"}
}