{
  "type": "Feature",
  "properties": {
    "iso:country":"AU",
    "sg:address":"2b- 9 Enterprise St",
    "sg:city":"Molendinar",
    "sg:classifiers":[
        {
            "category":"Banks & Credit Unions",
            "subcategory":"Financial Services",
            "type":"Services"
        }
    ],
    "sg:phone":"+61 7 5564 6908",
    "sg:postcode":"4214",
    "sg:province":"QLD",
    "sg:tags":[
        "equipment",
        "chain"
    ],
    "wof:name":"Southport Trawler Supplies",
    "wof:placetype":"venue"
},
  "geometry": {"coordinates":[153.37773132300001,-27.9773101807],"type":"Point"}
}