{
  "type": "Feature",
  "properties": {
    "iso:country":"AU",
    "sg:address":"87 Sheridan St",
    "sg:city":"Gundagai",
    "sg:classifiers":[
        {
            "category":"Organizations",
            "subcategory":"Professional Association",
            "type":"Services"
        }
    ],
    "sg:phone":"+61 2 6944 1588",
    "sg:postcode":"2722",
    "sg:province":"NSW",
    "sg:tags":[
        "rural",
        "organisation",
        "production",
        "primary"
    ],
    "wof:name":"Rural Lands Protection Board",
    "wof:placetype":"venue"
},
  "geometry": {"coordinates":[148.100143,-35.062359],"type":"Point"}
}