{
  "type": "Feature",
  "properties": {
    "addr:full":"13/ 83 Leichardt St Spring Hill QLD 4000",
    "addr:housenumber":"13 / 83",
    "addr:postcode":"4000",
    "addr:street":"Leichardt St",
    "iso:country":"AU",
    "sg:address":"13/ 83 Leichardt St",
    "sg:city":"Spring Hill",
    "sg:classifiers":[
        {
            "category":"Real Estate",
            "subcategory":"Surveying",
            "type":"Services"
        }
    ],
    "sg:phone":"+61 7 3839 7744",
    "sg:postcode":"4000",
    "sg:province":"QLD",
    "sg:tags":[
        "surveyor",
        "land"
    ],
    "wof:name":"Surveyors Board of Queensland",
    "wof:placetype":"venue"
},
  "geometry": {"coordinates":[153.02339172399999,-27.4624538422],"type":"Point"}
}