{
  "type": "Feature",
  "properties": {
    "iso:country":"AU",
    "sg:address":"9 Bong Bong St",
    "sg:city":"Kiama",
    "sg:classifiers":[
        {
            "category":"Travel",
            "subcategory":"Hotels & Motels",
            "type":"Entertainment"
        }
    ],
    "sg:phone":"+61 2 4232 1966",
    "sg:postcode":"2533",
    "sg:province":"NSW",
    "wof:name":"Kiama Ocean View Motor Inn",
    "wof:placetype":"venue"
},
  "geometry": {"coordinates":[150.85638427699999,-34.6739273071],"type":"Point"}
}