{
  "type": "Feature",
  "properties": {
    "iso:country":"AU",
    "sg:address":"RMB 3422 Butlers Rd",
    "sg:city":"Horsham",
    "sg:classifiers":[
        {
            "category":"Utilities",
            "subcategory":"Water",
            "type":"Services"
        }
    ],
    "sg:phone":"+61 419 323 118",
    "sg:postcode":"3400",
    "sg:province":"VIC",
    "sg:tags":[
        "cartage"
    ],
    "wof:name":"S & J Mackley Water Cartage",
    "wof:placetype":"venue"
},
  "geometry": {"coordinates":[142.19619750999999,-36.7172393799],"type":"Point"}
}