{
  "type": "Feature",
  "properties": {
    "addr:full":"3a Apsley Pl Seaford VIC 3198",
    "addr:housenumber":"3a",
    "addr:postcode":"3198",
    "iso:country":"AU",
    "sg:address":"3a Apsley Pl",
    "sg:city":"Seaford",
    "sg:classifiers":[
        {
            "category":"Shopping",
            "subcategory":"Pets & Pet Supplies",
            "type":"Retail Goods"
        }
    ],
    "sg:phone":"+61 3 9786 4603",
    "sg:postcode":"3198",
    "sg:province":"VIC",
    "sg:tags":[
        "shop",
        "supplier"
    ],
    "wof:name":"D & D Pet Foods Pty Ltd",
    "wof:placetype":"venue"
},
  "geometry": {"coordinates":[145.142654419,-38.1132164001],"type":"Point"}
}