{
  "type": "Feature",
  "properties": {
    "addr:full":"Cnr Welshpool & Lewis Rds Wattle Grove WA 6107",
    "addr:postcode":"6107",
    "addr:street":"Cnr",
    "iso:country":"AU",
    "sg:address":"Cnr Welshpool & Lewis Rds",
    "sg:city":"Wattle Grove",
    "sg:classifiers":[
        {
            "category":"Shopping",
            "subcategory":"Pets & Pet Supplies",
            "type":"Retail Goods"
        }
    ],
    "sg:phone":"+61 8 9453 2933",
    "sg:postcode":"6107",
    "sg:province":"WA",
    "sg:tags":[
        "shop",
        "supplier"
    ],
    "wof:name":"West Coast Pet Supplies Pty Ltd",
    "wof:placetype":"venue"
},
  "geometry": {"coordinates":[115.983337402,-32.0052947998],"type":"Point"}
}