{
  "type": "Feature",
  "properties": {
    "addr:full":"60 William St Rockhampton QLD 4700",
    "addr:housenumber":"60",
    "addr:postcode":"4700",
    "addr:street":"William St",
    "iso:country":"AU",
    "sg:address":"60 William St",
    "sg:city":"Rockhampton",
    "sg:classifiers":[
        {
            "category":"Industrial Area",
            "type":"Public Place"
        }
    ],
    "sg:phone":"+61 7 4922 3445",
    "sg:postcode":"4700",
    "sg:province":"QLD",
    "sg:tags":[
        "protective",
        "clothing"
    ],
    "wof:name":"Heilbronn & Co",
    "wof:placetype":"venue"
},
  "geometry": {"coordinates":[150.508712769,-23.3835391998],"type":"Point"}
}