{
  "type": "Feature",
  "properties": {
    "addr:full":"12 Bridge St Eltham VIC 3095",
    "addr:housenumber":"12",
    "addr:postcode":"3095",
    "addr:street":"Bridge St",
    "iso:country":"AU",
    "sg:address":"12 Bridge St",
    "sg:city":"Eltham",
    "sg:classifiers":[
        {
            "category":"Real Estate",
            "subcategory":"Real Estate Agent",
            "type":"Services"
        }
    ],
    "sg:phone":"+61 3 9431 0122",
    "sg:postcode":"3095",
    "sg:province":"VIC",
    "wof:name":"Wentworth Real Estate & Property Management",
    "wof:placetype":"venue"
},
  "geometry": {"coordinates":[145.13929748499999,-37.7183113098],"type":"Point"}
}