{
  "type": "Feature",
  "properties": {
    "addr:full":"2/ 31 Norfolk Ave Nowra South NSW 2541",
    "addr:housenumber":"/ 31",
    "addr:postcode":"2541",
    "addr:street":"Norfolk Ave",
    "iso:country":"AU",
    "sg:address":"2/ 31 Norfolk Ave",
    "sg:city":"Nowra South",
    "sg:classifiers":[
        {
            "category":"Wholesale",
            "subcategory":"Stationery",
            "type":"Manufacturing & Wholesale Goods"
        }
    ],
    "sg:phone":"+61 2 4421 0071",
    "sg:postcode":"2541",
    "sg:province":"NSW",
    "sg:tags":[
        "mfrg"
    ],
    "wof:name":"Tafeda Paper Embossing Specialists",
    "wof:placetype":"venue"
},
  "geometry": {"coordinates":[150.57814025900001,-34.9136390686],"type":"Point"}
}