{
  "type": "Feature",
  "properties": {
    "addr:full":"12 White St Crookwell NSW 2583",
    "addr:housenumber":"12",
    "addr:postcode":"2583",
    "addr:street":"White St",
    "iso:country":"AU",
    "sg:address":"12 White St",
    "sg:city":"Crookwell",
    "sg:classifiers":[
        {
            "category":"Building & Trades",
            "subcategory":"Construction",
            "type":"Services"
        }
    ],
    "sg:phone":"+61 2 4832 1160",
    "sg:postcode":"2583",
    "sg:province":"NSW",
    "sg:tags":[
        "earth",
        "excavating",
        "moving",
        "contractor"
    ],
    "wof:name":"G.M. & R.A. McIntosh Plumbing",
    "wof:placetype":"venue"
},
  "geometry": {"coordinates":[149.462814331,-34.4522132874],"type":"Point"}
}