{
  "type": "Feature",
  "properties": {
    "iso:country":"AU",
    "sg:address":"PO Box 034",
    "sg:city":"Wilberforce",
    "sg:classifiers":[
        {
            "category":"Shopping",
            "subcategory":"Pets & Pet Supplies",
            "type":"Retail Goods"
        }
    ],
    "sg:phone":"+61 2 4576 3491",
    "sg:postcode":"2756",
    "sg:province":"NSW",
    "sg:tags":[
        "shop",
        "supplier"
    ],
    "wof:name":"Australian Fauna Supplies",
    "wof:placetype":"venue"
},
  "geometry": {"coordinates":[150.83720398,-33.5579986572],"type":"Point"}
}