{
  "type": "Feature",
  "properties": {
    "addr:full":"Shop 30 Burleigh Town Marketplace West Burleigh Rd Burleigh Heads QLD 4220",
    "addr:housenumber":"shop 30",
    "addr:postcode":"4220",
    "addr:street":"Burleigh Rd",
    "iso:country":"AU",
    "sg:address":"Shop 30 Burleigh Town Marketplace West Burleigh Rd",
    "sg:city":"Burleigh Heads",
    "sg:classifiers":[
        {
            "category":"Shopping",
            "subcategory":"Mobile Phones",
            "type":"Retail Goods"
        }
    ],
    "sg:phone":"+61 7 5576 8111",
    "sg:postcode":"4220",
    "sg:province":"QLD",
    "sg:tags":[
        "telephone",
        "accessory"
    ],
    "wof:name":"One Zero Telstra Dealer",
    "wof:placetype":"venue"
},
  "geometry": {"coordinates":[153.449752808,-28.0879230499],"type":"Point"}
}