{
  "type": "Feature",
  "properties": {
    "iso:country":"AU",
    "sg:address":"30 Weston St",
    "sg:city":"Naval Base",
    "sg:classifiers":[
        {
            "category":"Fast Food",
            "type":"Food & Drink"
        }
    ],
    "sg:phone":"+61 8 9410 2912",
    "sg:postcode":"6165",
    "sg:province":"WA",
    "sg:tags":[
        "away",
        "take"
    ],
    "wof:name":"Captain Jae's",
    "wof:placetype":"venue"
},
  "geometry": {"coordinates":[115.781937,-32.203384],"type":"Point"}
}