{
  "type": "Feature",
  "properties": {
    "addr:full":"419 North Rd Ormond VIC 3204",
    "addr:housenumber":"419",
    "addr:postcode":"3204",
    "addr:street":"North Rd",
    "iso:country":"AU",
    "sg:address":"419 North Rd",
    "sg:city":"Ormond",
    "sg:classifiers":[
        {
            "category":"Professional",
            "subcategory":"Management & Consulting",
            "type":"Services"
        }
    ],
    "sg:phone":"+61 3 9578 8996",
    "sg:postcode":"3204",
    "sg:province":"VIC",
    "sg:tags":[
        "consultant",
        "educational"
    ],
    "wof:name":"Glen Eira Adult Learning Centre Inc.",
    "wof:placetype":"venue"
},
  "geometry": {"coordinates":[145.035751,-37.903244],"type":"Point"}
}