{
  "type": "Feature",
  "properties": {
    "iso:country":"AU",
    "sg:address":"717 Victoria Rd",
    "sg:city":"Ryde",
    "sg:classifiers":[
        {
            "category":"Professional",
            "subcategory":"Detective & Security Services",
            "type":"Services"
        }
    ],
    "sg:phone":"+61 2 9807 4417",
    "sg:postcode":"2112",
    "sg:province":"NSW",
    "sg:tags":[
        "investigator"
    ],
    "wof:name":"Askew George & Associates Pty Ltd",
    "wof:placetype":"venue"
},
  "geometry": {"coordinates":[151.105957031,-33.816570282],"type":"Point"}
}