{
  "type": "Feature",
  "properties": {
    "addr:full":"Cnr. John St & Rupertswood Rd Rooty Hill NSW 2766",
    "addr:postcode":"2766",
    "addr:street":"John St & Rupertswood Rd",
    "iso:country":"AU",
    "sg:address":"Cnr. John St & Rupertswood Rd",
    "sg:city":"Rooty Hill",
    "sg:classifiers":[
        {
            "category":"Health Services",
            "subcategory":"Nursing And Care Facility",
            "type":"Services"
        }
    ],
    "sg:phone":"+61 2 9832 5800",
    "sg:postcode":"2766",
    "sg:province":"NSW",
    "sg:tags":[
        "home"
    ],
    "wof:name":"Minchinbury Manor",
    "wof:placetype":"venue"
},
  "geometry": {"coordinates":[150.83018493599999,-33.7810516357],"type":"Point"}
}