{
  "type": "Feature",
  "properties": {
    "iso:country":"AU",
    "sg:address":"Cnr Kunara Crs & Ring Rd",
    "sg:city":"Portland",
    "sg:classifiers":[
        {
            "category":"Retail",
            "subcategory":"Auto Repair",
            "type":"Services"
        }
    ],
    "sg:phone":"+61 3 5523 5562",
    "sg:postcode":"3305",
    "sg:province":"VIC",
    "sg:tags":[
        "electrical"
    ],
    "wof:name":"Portland Mechanical & Electrical Services",
    "wof:placetype":"venue"
},
  "geometry": {"coordinates":[141.597045898,-38.3452148438],"type":"Point"}
}