{
  "type": "Feature",
  "properties": {
    "iso:country":"AU",
    "sg:address":"Shop 5A, Leeming Forum Farrington Rd",
    "sg:city":"Leeming",
    "sg:classifiers":[
        {
            "category":"Personal",
            "subcategory":"Beauty Salon",
            "type":"Services"
        }
    ],
    "sg:phone":"+61 8 9313 5580",
    "sg:postcode":"6149",
    "sg:province":"WA",
    "wof:name":"Clear Image",
    "wof:placetype":"venue"
},
  "geometry": {"coordinates":[115.85984000000001,-32.079472],"type":"Point"}
}