{
  "type": "Feature",
  "properties": {
    "addr:full":"16a Gregory St Sandy Bay TAS 7005",
    "addr:housenumber":"16a",
    "addr:postcode":"7005",
    "addr:street":"Gregory St",
    "iso:country":"AU",
    "sg:address":"16a Gregory St",
    "sg:city":"Sandy Bay",
    "sg:classifiers":[
        {
            "category":"Real Estate",
            "subcategory":"Real Estate Agent",
            "type":"Services"
        }
    ],
    "sg:phone":"+61 3 6224 2004",
    "sg:postcode":"7005",
    "sg:province":"TAS",
    "sg:website":"http://www.nestproperty.com.au",
    "wof:name":"Nest Property",
    "wof:placetype":"venue"
},
  "geometry": {"coordinates":[147.326263428,-42.8957328796],"type":"Point"}
}