{
  "type": "Feature",
  "properties": {
    "addr:full":"147 Argyle St Traralgon VIC 3844",
    "addr:housenumber":"147",
    "addr:postcode":"3844",
    "addr:street":"Argyle St",
    "iso:country":"AU",
    "sg:address":"147 Argyle St",
    "sg:city":"Traralgon",
    "sg:classifiers":[
        {
            "category":"Real Estate",
            "subcategory":"Real Estate Agent",
            "type":"Services"
        }
    ],
    "sg:phone":"+61 3 5174 4544",
    "sg:postcode":"3844",
    "sg:province":"VIC",
    "sg:tags":[
        "handyman's",
        "equipment",
        "hire",
        "builders",
        "contractor"
    ],
    "wof:name":"Traralgon Handy Hire",
    "wof:placetype":"venue"
},
  "geometry": {"coordinates":[146.536743164,-38.2008476257],"type":"Point"}
}