{
  "type": "Feature",
  "properties": {
    "iso:country":"AU",
    "sg:address":"8 Peel St",
    "sg:city":"Dover Heights",
    "sg:classifiers":[
        {
            "category":"Professional",
            "subcategory":"Accounting & Tax Preparation",
            "type":"Services"
        }
    ],
    "sg:phone":"+61 2 9223 7848",
    "sg:postcode":"2030",
    "sg:province":"NSW",
    "sg:tags":[
        "consultant",
        "taxation"
    ],
    "wof:name":"Vasin Maurice",
    "wof:placetype":"venue"
},
  "geometry": {"coordinates":[151.28004455600001,-33.867816925],"type":"Point"}
}