{
  "type": "Feature",
  "properties": {
    "addr:full":"66 Newton Rd Young NSW 2594",
    "addr:housenumber":"66",
    "addr:postcode":"2594",
    "addr:street":"Newton Rd",
    "iso:country":"AU",
    "sg:address":"66 Newton Rd",
    "sg:city":"Young",
    "sg:classifiers":[
        {
            "category":"Building & Trades",
            "subcategory":"Construction",
            "type":"Services"
        }
    ],
    "sg:phone":"+61 2 6382 2654",
    "sg:postcode":"2594",
    "sg:province":"NSW",
    "sg:tags":[
        "contractor"
    ],
    "wof:name":"Lacey Clive Builder",
    "wof:placetype":"venue"
},
  "geometry": {"coordinates":[148.287963867,-34.3149375916],"type":"Point"}
}