{
  "type": "Feature",
  "properties": {
    "addr:full":"12 Dewey Pl St Helens Park NSW 2560",
    "addr:housenumber":"12",
    "addr:postcode":"2560",
    "addr:street":"Dewey Pl",
    "iso:country":"AU",
    "sg:address":"12 Dewey Pl St",
    "sg:city":"Helens Park",
    "sg:classifiers":[
        {
            "category":"Building & Trades",
            "subcategory":"Construction",
            "type":"Services"
        }
    ],
    "sg:phone":"+61 2 4621 2077",
    "sg:postcode":"2560",
    "sg:province":"NSW",
    "sg:tags":[
        "contractor"
    ],
    "wof:name":"Dream House Design",
    "wof:placetype":"venue"
},
  "geometry": {"coordinates":[150.79878234899999,-34.1174430847],"type":"Point"}
}