{
  "type": "Feature",
  "properties": {
    "iso:country":"AU",
    "sg:address":"11 High St",
    "sg:city":"Morgan",
    "sg:classifiers":[
        {
            "category":"Autos & Motor Vehicles",
            "subcategory":"Fuel & Gas Station",
            "type":"Retail Goods"
        }
    ],
    "sg:phone":"+61 8 8540 2477",
    "sg:postcode":"5320",
    "sg:province":"SA",
    "wof:name":"Morgan Highway Service Station",
    "wof:placetype":"venue"
},
  "geometry": {"coordinates":[139.666183472,-34.033405304],"type":"Point"}
}