{
  "type": "Feature",
  "properties": {
    "iso:country":"AU",
    "sg:address":"45 Orr St",
    "sg:city":"Port Macquarie",
    "sg:classifiers":[
        {
            "category":"Home & Garden",
            "subcategory":"Carpets & Floor Coverings",
            "type":"Retail Goods"
        }
    ],
    "sg:phone":"+61 2 6582 2168",
    "sg:postcode":"2444",
    "sg:province":"NSW",
    "sg:tags":[
        "tile",
        "wall",
        "layer"
    ],
    "wof:name":"MIG Ceramics",
    "wof:placetype":"venue"
},
  "geometry": {"coordinates":[152.92143200000001,-31.46554],"type":"Point"}
}