{
  "type": "Feature",
  "properties": {
    "iso:country":"AU",
    "sg:address":"Shop 13, Midland Gate Shopping Brockman Rd",
    "sg:city":"Midland",
    "sg:classifiers":[
        {
            "category":"Shopping",
            "subcategory":"Mobile Phones",
            "type":"Retail Goods"
        }
    ],
    "sg:phone":"+61 8 9250 3200",
    "sg:postcode":"6056",
    "sg:province":"WA",
    "sg:tags":[
        "telephone",
        "accessory"
    ],
    "wof:name":"Vodafone",
    "wof:placetype":"venue"
},
  "geometry": {"coordinates":[116.02348327599999,-31.9312286377],"type":"Point"}
}