{
  "type": "Feature",
  "properties": {
    "iso:country":"AU",
    "sg:address":"18 Wilfred St",
    "sg:city":"Toowoomba",
    "sg:classifiers":[
        {
            "category":"Home & Garden",
            "subcategory":"Building Materials",
            "type":"Retail Goods"
        }
    ],
    "sg:phone":"+61 7 4635 9687",
    "sg:postcode":"4350",
    "sg:province":"QLD",
    "sg:tags":[
        "lawn",
        "cutting",
        "maintenance"
    ],
    "wof:name":"Brazier's Garden & Lawn Perfection",
    "wof:placetype":"venue"
},
  "geometry": {"coordinates":[151.93168600000001,-27.58872],"type":"Point"}
}