{
  "type": "Feature",
  "properties": {
    "addr:full":"120 Seaworld Drv Main Beach QLD 4217",
    "addr:housenumber":"120",
    "addr:postcode":"4217",
    "addr:street":"Seaworld Drv",
    "iso:country":"AU",
    "sg:address":"120 Seaworld Drv",
    "sg:city":"Main Beach",
    "sg:classifiers":[
        {
            "category":"Fast Food",
            "type":"Food & Drink"
        }
    ],
    "sg:phone":"+61 7 5591 7747",
    "sg:postcode":"4217",
    "sg:province":"QLD",
    "sg:tags":[
        "away",
        "take"
    ],
    "wof:name":"Peters Fish Market",
    "wof:placetype":"venue"
},
  "geometry": {"coordinates":[153.42739868199999,-27.9683647156],"type":"Point"}
}