{
  "type": "Feature",
  "properties": {
    "addr:full":"84 Bridge St Boyanup WA 6237",
    "addr:housenumber":"84",
    "addr:postcode":"6237",
    "addr:street":"Bridge St",
    "iso:country":"AU",
    "sg:address":"84 Bridge St",
    "sg:city":"Boyanup",
    "sg:classifiers":[
        {
            "category":"Farming",
            "subcategory":"Farm",
            "type":"Manufacturing & Wholesale Goods"
        }
    ],
    "sg:phone":"+61 8 9731 5183",
    "sg:postcode":"6237",
    "sg:province":"WA",
    "sg:tags":[
        "farmer"
    ],
    "wof:name":"Leach D J & M E",
    "wof:placetype":"venue"
},
  "geometry": {"coordinates":[115.729736,-33.481777],"type":"Point"}
}