{
  "type": "Feature",
  "properties": {
    "addr:full":"Units 2-4/ 28 Hales Drv Lonsdale SA 5160",
    "addr:housenumber":"units 2-4 / 28",
    "addr:postcode":"5160",
    "addr:street":"Hales Drv",
    "iso:country":"AU",
    "sg:address":"Units 2-4/ 28 Hales Drv",
    "sg:city":"Lonsdale",
    "sg:classifiers":[
        {
            "category":"Manufacturing",
            "subcategory":"Tools & Machinery",
            "type":"Manufacturing & Wholesale Goods"
        }
    ],
    "sg:phone":"+61 8 8326 7822",
    "sg:postcode":"5160",
    "sg:province":"SA",
    "sg:tags":[
        "manufactured",
        "specially",
        "designed"
    ],
    "wof:name":"Schofield Engineering",
    "wof:placetype":"venue"
},
  "geometry": {"coordinates":[138.48524475100001,-35.1203956604],"type":"Point"}
}