{
  "type": "Feature",
  "properties": {
    "addr:full":"PO Box 7228 Gold Coast QLD 9726",
    "addr:postcode":"9726",
    "iso:country":"AU",
    "sg:address":"PO Box 7228",
    "sg:city":"Gold Coast",
    "sg:classifiers":[
        {
            "category":"Building & Trades",
            "subcategory":"Locksmith",
            "type":"Services"
        }
    ],
    "sg:phone":"+61 408 777 626",
    "sg:postcode":"9726",
    "sg:province":"QLD",
    "sg:tags":[
        "lock"
    ],
    "wof:name":"Express Locksmiths Gold Coast",
    "wof:placetype":"venue"
},
  "geometry": {"coordinates":[153.44924926799999,-28.0854701996],"type":"Point"}
}