{
  "type": "Feature",
  "properties": {
    "addr:full":"Bingle Rd Dunwich QLD 4183",
    "addr:postcode":"4183",
    "addr:street":"Bingle Rd",
    "iso:country":"AU",
    "sg:address":"Bingle Rd",
    "sg:city":"Dunwich",
    "sg:classifiers":[
        {
            "category":"Education",
            "subcategory":"School",
            "type":"Public Place"
        }
    ],
    "sg:phone":"+61 7 3409 6333",
    "sg:postcode":"4183",
    "sg:province":"QLD",
    "sg:tags":[
        "state",
        "except",
        "nsw"
    ],
    "wof:name":"Dunwich Primary",
    "wof:placetype":"venue"
},
  "geometry": {"coordinates":[153.40455627399999,-27.4952049255],"type":"Point"}
}