{
  "type": "Feature",
  "properties": {
    "iso:country":"AU",
    "sg:address":"Suite 104 AMA House 69 Christie St",
    "sg:city":"St Leonards",
    "sg:classifiers":[
        {
            "category":"Health Services",
            "subcategory":"Doctor",
            "type":"Services"
        }
    ],
    "sg:phone":"+61 2 9966 9971",
    "sg:postcode":"2065",
    "sg:province":"NSW",
    "sg:tags":[
        "medical",
        "practitioner"
    ],
    "wof:name":"Casper Gabrielle Dr",
    "wof:placetype":"venue"
},
  "geometry": {"coordinates":[151.195755005,-33.8237457275],"type":"Point"}
}