{
  "type": "Feature",
  "properties": {
    "addr:full":"924 Cambridge Rd Cambridge TAS 7170",
    "addr:housenumber":"924",
    "addr:postcode":"7170",
    "addr:street":"Cambridge Rd",
    "iso:country":"AU",
    "sg:address":"924 Cambridge Rd",
    "sg:city":"Cambridge",
    "sg:classifiers":[
        {
            "category":"Professional",
            "subcategory":"Art Services",
            "type":"Services"
        }
    ],
    "sg:phone":"+61 417 314 348",
    "sg:postcode":"7170",
    "sg:province":"TAS",
    "sg:tags":[
        "decorator",
        "painter"
    ],
    "wof:name":"Young R J",
    "wof:placetype":"venue"
},
  "geometry": {"coordinates":[147.43771362300001,-42.8382949829],"type":"Point"}
}