{
  "type": "Feature",
  "properties": {
    "addr:full":"30 Carabooda Rd Carabooda WA 6033",
    "addr:housenumber":"30",
    "addr:postcode":"6033",
    "addr:street":"Carabooda Rd",
    "iso:country":"AU",
    "sg:address":"30 Carabooda Rd",
    "sg:city":"Carabooda",
    "sg:classifiers":[
        {
            "category":"Food & Beverages",
            "subcategory":"Fruits & Vegetables",
            "type":"Retail Goods"
        }
    ],
    "sg:phone":"+61 8 9407 5274",
    "sg:postcode":"6033",
    "sg:province":"WA",
    "sg:tags":[
        "grower"
    ],
    "wof:name":"Nanovich M & P & M",
    "wof:placetype":"venue"
},
  "geometry": {"coordinates":[115.722091675,-31.6077747345],"type":"Point"}
}