{
  "type": "Feature",
  "properties": {
    "addr:full":"Dawson St Brunswick VIC 3056",
    "addr:postcode":"3056",
    "addr:street":"Dawson St",
    "iso:country":"AU",
    "sg:address":"Dawson St",
    "sg:city":"Brunswick",
    "sg:classifiers":[
        {
            "category":"Education",
            "subcategory":"School",
            "type":"Public Place"
        }
    ],
    "sg:phone":"+61 3 9387 6133",
    "sg:postcode":"3056",
    "sg:province":"VIC",
    "sg:tags":[
        "state",
        "except",
        "nsw"
    ],
    "wof:name":"Brunswick Secondary College",
    "wof:placetype":"venue"
},
  "geometry": {"coordinates":[144.96095275900001,-37.7714576721],"type":"Point"}
}