{
  "type": "Feature",
  "properties": {
    "addr:full":"Mail Service 1945 Kulpi QLD 4352",
    "addr:postcode":"4352",
    "iso:country":"AU",
    "sg:address":"Mail Service 1945",
    "sg:city":"Kulpi",
    "sg:classifiers":[
        {
            "category":"Home & Garden",
            "subcategory":"Carpets & Floor Coverings",
            "type":"Retail Goods"
        }
    ],
    "sg:phone":"+61 7 4692 8002",
    "sg:postcode":"4352",
    "sg:province":"QLD",
    "sg:tags":[
        "tile",
        "wall",
        "layer"
    ],
    "wof:name":"Link Reimers Tiling",
    "wof:placetype":"venue"
},
  "geometry": {"coordinates":[151.70036300000001,-27.187889],"type":"Point"}
}