{
  "type": "Feature",
  "properties": {
    "iso:country":"AU",
    "sg:address":"2a Bellambi St",
    "sg:city":"Northbridge",
    "sg:classifiers":[
        {
            "category":"Retail",
            "subcategory":"Auto Repair",
            "type":"Services"
        }
    ],
    "sg:phone":"+61 2 9967 3122",
    "sg:postcode":"2063",
    "sg:province":"NSW",
    "sg:tags":[
        "beater",
        "painter",
        "panel"
    ],
    "wof:name":"Color Tech",
    "wof:placetype":"venue"
},
  "geometry": {"coordinates":[151.2109375,-33.810710907],"type":"Point"}
}