{
  "type": "Feature",
  "properties": {
    "addr:full":"Shop G80, Pascoe Vale Rd Broadmeadows VIC 3047",
    "addr:housenumber":"g80",
    "addr:postcode":"3047",
    "addr:street":"Pascoe Vale Rd",
    "iso:country":"AU",
    "sg:address":"Shop G80, Pascoe Vale Rd",
    "sg:city":"Broadmeadows",
    "sg:classifiers":[
        {
            "category":"Shopping",
            "subcategory":"Clothing, Apparel, & Fashions",
            "type":"Retail Goods"
        }
    ],
    "sg:phone":"+61 3 9302 4037",
    "sg:postcode":"3047",
    "sg:province":"VIC",
    "sg:tags":[
        "jean"
    ],
    "wof:name":"Westco Jeans (Aust) Pty Ltd",
    "wof:placetype":"venue"
},
  "geometry": {"coordinates":[144.91957092300001,-37.6823272705],"type":"Point"}
}