{
  "type": "Feature",
  "properties": {
    "addr:full":"130 Ramsgate Rd Ramsgate NSW 2217",
    "addr:housenumber":"130",
    "addr:postcode":"2217",
    "addr:street":"Ramsgate Rd",
    "iso:country":"AU",
    "sg:address":"130 Ramsgate Rd",
    "sg:city":"Ramsgate",
    "sg:classifiers":[
        {
            "category":"Health Services",
            "subcategory":"Health Practitioner",
            "type":"Services"
        }
    ],
    "sg:phone":"+61 2 9529 8878",
    "sg:postcode":"2217",
    "sg:province":"NSW",
    "sg:tags":[
        "physiotherapist"
    ],
    "wof:name":"Ramsgate Physiotherapy Centre",
    "wof:placetype":"venue"
},
  "geometry": {"coordinates":[151.14134200000001,-33.984737],"type":"Point"}
}