{
  "type": "Feature",
  "properties": {
    "addr:full":"185 Percy St Portland VIC 3305",
    "addr:housenumber":"185",
    "addr:postcode":"3305",
    "addr:street":"Percy St",
    "iso:country":"AU",
    "sg:address":"185 Percy St",
    "sg:city":"Portland",
    "sg:classifiers":[
        {
            "category":"Professional",
            "subcategory":"Printing & Photocopies",
            "type":"Services"
        }
    ],
    "sg:phone":"+61 3 5521 7788",
    "sg:postcode":"3305",
    "sg:province":"VIC",
    "sg:tags":[
        "screen",
        "printer"
    ],
    "wof:name":"All-Star Graphics",
    "wof:placetype":"venue"
},
  "geometry": {"coordinates":[141.604003906,-38.3372039795],"type":"Point"}
}