{
  "type": "Feature",
  "properties": {
    "addr:full":"15 Campbell St Swan Hill VIC 3585",
    "addr:housenumber":"15",
    "addr:postcode":"3585",
    "addr:street":"Campbell St",
    "iso:country":"AU",
    "sg:address":"15 Campbell St",
    "sg:city":"Swan Hill",
    "sg:classifiers":[
        {
            "category":"Autos & Motor Vehicles",
            "subcategory":"Auto Supplies",
            "type":"Retail Goods"
        }
    ],
    "sg:phone":"+61 3 5033 1390",
    "sg:postcode":"3585",
    "sg:province":"VIC",
    "sg:tags":[
        "tyre"
    ],
    "wof:name":"Tyre Co",
    "wof:placetype":"venue"
},
  "geometry": {"coordinates":[143.558334,-35.3344],"type":"Point"}
}