{
  "type": "Feature",
  "properties": {
    "iso:country":"AU",
    "sg:address":"195 Gilles St",
    "sg:city":"Adelaide",
    "sg:classifiers":[
        {
            "category":"Organizations",
            "subcategory":"Non-profit Organization",
            "type":"Services"
        }
    ],
    "sg:phone":"+61 8 8449 2472",
    "sg:postcode":"5000",
    "sg:province":"SA",
    "sg:tags":[
        "support",
        "disability",
        "organisation"
    ],
    "wof:name":"Narcolepsy & Overwhelming Daytime Sleep Society of South Australia",
    "wof:placetype":"venue"
},
  "geometry": {"coordinates":[138.60743713400001,-34.9340858459],"type":"Point"}
}