{
  "type": "Feature",
  "properties": {
    "iso:country":"AU",
    "sg:address":"5A Grenfell St",
    "sg:city":"Parkes",
    "sg:classifiers":[
        {
            "category":"Wholesale",
            "subcategory":"Medical Equipment & Supplies",
            "type":"Manufacturing & Wholesale Goods"
        }
    ],
    "sg:phone":"+61 1800 675 434",
    "sg:postcode":"2870",
    "sg:province":"NSW",
    "sg:tags":[
        "aid",
        "care",
        "health",
        "home"
    ],
    "wof:name":"Regency Mediquip Centre",
    "wof:placetype":"venue"
},
  "geometry": {"coordinates":[148.17240899999999,-33.141037],"type":"Point"}
}