{
  "type": "Feature",
  "properties": {
    "iso:country":"AU",
    "sg:address":"Shp4/ 39 Winifred Jane Crs",
    "sg:city":"Hadspen",
    "sg:classifiers":[
        {
            "category":"Personal",
            "subcategory":"Beauty Salon",
            "type":"Services"
        }
    ],
    "sg:phone":"+61 3 6393 6066",
    "sg:postcode":"7290",
    "sg:province":"TAS",
    "wof:name":"Heavenly Comforts",
    "wof:placetype":"venue"
},
  "geometry": {"coordinates":[147.05953979500001,-41.5104408264],"type":"Point"}
}