{
  "type": "Feature",
  "properties": {
    "addr:full":"Shop 9 & 10 Adamstown Plaza, 281-293 Bunker Rd Adamstown NSW 2289",
    "addr:housenumber":"shop 9 & 10;281-293",
    "addr:postcode":"2289",
    "addr:street":"Adamstown Plaza;Bunker Rd",
    "iso:country":"AU",
    "sg:address":"Shop 9 & 10 Adamstown Plaza, 281-293 Bunker Rd",
    "sg:city":"Adamstown",
    "sg:classifiers":[
        {
            "category":"Manufacturing",
            "subcategory":"Food",
            "type":"Manufacturing & Wholesale Goods"
        }
    ],
    "sg:phone":"+61 2 4952 3420",
    "sg:postcode":"2289",
    "sg:province":"NSW",
    "sg:tags":[
        "function",
        "catering"
    ],
    "wof:name":"Henny Penny Foods",
    "wof:placetype":"venue"
},
  "geometry": {"coordinates":[151.72625732399999,-32.9332733154],"type":"Point"}
}