{
  "type": "Feature",
  "properties": {
    "addr:full":"91 Hampton St Bridgetown WA 6255",
    "addr:housenumber":"91",
    "addr:postcode":"6255",
    "addr:street":"Hampton St",
    "iso:country":"AU",
    "sg:address":"91 Hampton St",
    "sg:city":"Bridgetown",
    "sg:classifiers":[
        {
            "category":"Shopping",
            "subcategory":"Crafts & Fabrics",
            "type":"Retail Goods"
        }
    ],
    "sg:phone":"+61 8 9761 1490",
    "sg:postcode":"6255",
    "sg:province":"WA",
    "sg:tags":[
        "supply"
    ],
    "wof:name":"Gentle Era",
    "wof:placetype":"venue"
},
  "geometry": {"coordinates":[116.137046814,-33.957775116],"type":"Point"}
}