{
  "type": "Feature",
  "properties": {
    "addr:full":"Mail Service 379 Redridge QLD 4660",
    "addr:postcode":"4660",
    "iso:country":"AU",
    "sg:address":"Mail Service 379",
    "sg:city":"Redridge",
    "sg:classifiers":[
        {
            "category":"Farming",
            "subcategory":"Farm",
            "type":"Manufacturing & Wholesale Goods"
        }
    ],
    "sg:phone":"+61 7 4126 8141",
    "sg:postcode":"4660",
    "sg:province":"QLD",
    "sg:tags":[
        "farmer"
    ],
    "wof:name":"Redridge Farms",
    "wof:placetype":"venue"
},
  "geometry": {"coordinates":[152.37330627399999,-25.1581096649],"type":"Point"}
}