{
  "type": "Feature",
  "properties": {
    "iso:country":"AU",
    "sg:address":"4 Hill St",
    "sg:city":"Esperance",
    "sg:classifiers":[
        {
            "category":"Building & Trades",
            "subcategory":"Construction",
            "type":"Services"
        }
    ],
    "sg:phone":"+61 8 9071 2785",
    "sg:postcode":"6450",
    "sg:province":"WA",
    "sg:tags":[
        "contractor"
    ],
    "wof:name":"Timmins & Timmins",
    "wof:placetype":"venue"
},
  "geometry": {"coordinates":[121.892440796,-33.8384475708],"type":"Point"}
}