{
  "type": "Feature",
  "properties": {
    "iso:country":"AU",
    "sg:address":"36 North Pde",
    "sg:city":"Campsie",
    "sg:classifiers":[
        {
            "category":"Health Services",
            "subcategory":"Doctor",
            "type":"Services"
        }
    ],
    "sg:phone":"+61 2 9789 6011",
    "sg:postcode":"2194",
    "sg:province":"NSW",
    "sg:tags":[
        "medical",
        "practitioner"
    ],
    "wof:name":"Skalicky John M",
    "wof:placetype":"venue"
},
  "geometry": {"coordinates":[151.104416,-33.909798],"type":"Point"}
}