{
  "type": "Feature",
  "properties": {
    "addr:full":"305 Lawrence Hargrave Drv Thirroul NSW 2515",
    "addr:housenumber":"305",
    "addr:postcode":"2515",
    "addr:street":"Lawrence Hargrave Drv",
    "iso:country":"AU",
    "sg:address":"305 Lawrence Hargrave Drv",
    "sg:city":"Thirroul",
    "sg:classifiers":[
        {
            "category":"Real Estate",
            "subcategory":"Real Estate Agent",
            "type":"Services"
        }
    ],
    "sg:phone":"+61 2 4267 3444",
    "sg:postcode":"2515",
    "sg:province":"NSW",
    "wof:name":"Bevans Real Estate Group - Illawarra",
    "wof:placetype":"venue"
},
  "geometry": {"coordinates":[150.92236299999999,-34.31562],"type":"Point"}
}