{
  "type": "Feature",
  "properties": {
    "addr:full":"381 Pacific Hwy Asquith NSW 2077",
    "addr:housenumber":"381",
    "addr:postcode":"2077",
    "addr:street":"Pacific Hwy",
    "iso:country":"AU",
    "sg:address":"381 Pacific Hwy",
    "sg:city":"Asquith",
    "sg:classifiers":[
        {
            "category":"Food & Beverages",
            "subcategory":"Bakery",
            "type":"Retail Goods"
        }
    ],
    "sg:phone":"+61 2 9477 3786",
    "sg:postcode":"2077",
    "sg:province":"NSW",
    "sg:tags":[
        "baker"
    ],
    "wof:name":"Asquith Bakery",
    "wof:placetype":"venue"
},
  "geometry": {"coordinates":[151.10801696799999,-33.6880569458],"type":"Point"}
}