{
  "type": "Feature",
  "properties": {
    "addr:full":"Bayliss Rd Heritage Park QLD 4118",
    "addr:postcode":"4118",
    "addr:street":"Bayliss Rd",
    "iso:country":"AU",
    "sg:address":"Bayliss Rd",
    "sg:city":"Heritage Park",
    "sg:classifiers":[
        {
            "category":"Personal",
            "subcategory":"Beauty Salon",
            "type":"Services"
        }
    ],
    "sg:phone":"+61 7 3800 8422",
    "sg:postcode":"4118",
    "sg:province":"QLD",
    "sg:tags":[
        "hairdresser"
    ],
    "wof:name":"Ambitions Hair & Beauty Studio",
    "wof:placetype":"venue"
},
  "geometry": {"coordinates":[153.05885314899999,-27.6835727692],"type":"Point"}
}