{
  "type": "Feature",
  "properties": {
    "addr:full":"Wimbridge Rd Bunbury WA 6230",
    "addr:postcode":"6230",
    "addr:street":"Wimbridge Rd",
    "iso:country":"AU",
    "sg:address":"Wimbridge Rd",
    "sg:city":"Bunbury",
    "sg:classifiers":[
        {
            "category":"Utilities",
            "subcategory":"Fuel Oil & Lpg",
            "type":"Services"
        }
    ],
    "sg:phone":"+61 8 9725 4399",
    "sg:postcode":"6230",
    "sg:province":"WA",
    "sg:tags":[
        "merchant"
    ],
    "wof:name":"Direct Fuel Supplies",
    "wof:placetype":"venue"
},
  "geometry": {"coordinates":[115.698532,-33.348682],"type":"Point"}
}