{
  "type": "Feature",
  "properties": {
    "iso:country":"AU",
    "sg:address":"6 Gundah Rd",
    "sg:city":"Mt Kuring-gai",
    "sg:classifiers":[
        {
            "category":"Building & Trades",
            "subcategory":"Construction",
            "type":"Services"
        }
    ],
    "sg:phone":"+61 428 219 152",
    "sg:postcode":"2080",
    "sg:province":"NSW",
    "sg:tags":[
        "brick",
        "paving"
    ],
    "wof:name":"Propave",
    "wof:placetype":"venue"
},
  "geometry": {"coordinates":[151.13201904300001,-33.6413383484],"type":"Point"}
}