{
  "type": "Feature",
  "properties": {
    "addr:full":"165 Franklin St Adelaide SA 5000",
    "addr:housenumber":"165",
    "addr:postcode":"5000",
    "addr:street":"Franklin St",
    "iso:country":"AU",
    "sg:address":"165 Franklin St",
    "sg:city":"Adelaide",
    "sg:classifiers":[
        {
            "category":"Home & Garden",
            "subcategory":"Hardware",
            "type":"Retail Goods"
        }
    ],
    "sg:phone":"+61 1300 550 555",
    "sg:postcode":"5000",
    "sg:province":"SA",
    "sg:tags":[
        "plumber",
        "supply"
    ],
    "wof:name":"Tradelink Plumbing Centres",
    "wof:placetype":"venue"
},
  "geometry": {"coordinates":[138.592926025,-34.9276504517],"type":"Point"}
}