{
  "type": "Feature",
  "properties": {
    "iso:country":"AU",
    "sg:address":"35 Eveleigh St",
    "sg:city":"Wooloowin",
    "sg:classifiers":[
        {
            "category":"Social Services",
            "subcategory":"Retirement Home",
            "type":"Services"
        }
    ],
    "sg:phone":"+61 7 3857 4908",
    "sg:postcode":"4030",
    "sg:province":"QLD",
    "sg:tags":[
        "village"
    ],
    "wof:name":"Eveleigh Retirement Village",
    "wof:placetype":"venue"
},
  "geometry": {"coordinates":[153.04139699999999,-27.415039],"type":"Point"}
}