{
  "type": "Feature",
  "properties": {
    "addr:full":"17 Smiths Rd Goodna QLD 4300",
    "addr:housenumber":"17",
    "addr:postcode":"4300",
    "addr:street":"Smiths Rd",
    "iso:country":"AU",
    "sg:address":"17 Smiths Rd",
    "sg:city":"Goodna",
    "sg:classifiers":[
        {
            "category":"Retail",
            "subcategory":"Laundry & Dry Cleaning",
            "type":"Services"
        }
    ],
    "sg:phone":"+61 7 3816 9633",
    "sg:postcode":"4300",
    "sg:province":"QLD",
    "sg:tags":[
        "cloth",
        "supply"
    ],
    "wof:name":"LifeLine Goodna",
    "wof:placetype":"venue"
},
  "geometry": {"coordinates":[152.899002075,-27.6093769073],"type":"Point"}
}