{
  "type": "Feature",
  "properties": {
    "addr:full":"Office 18; C/O Dandenong Saleyards Brighton Rd Dandenong VIC 3175",
    "addr:housenumber":"saleyards",
    "addr:postcode":"3175",
    "addr:street":"C / O;Brighton Rd",
    "iso:country":"AU",
    "sg:address":"Office 18; C/O Dandenong Saleyards Brighton Rd",
    "sg:city":"Dandenong",
    "sg:classifiers":[
        {
            "category":"Real Estate",
            "subcategory":"Real Estate Services",
            "type":"Services"
        }
    ],
    "sg:phone":"+61 3 9792 5898",
    "sg:postcode":"3175",
    "sg:province":"VIC",
    "sg:tags":[
        "auctioneer"
    ],
    "wof:name":"Victorian Producers Co-Op",
    "wof:placetype":"venue"
},
  "geometry": {"coordinates":[145.20750427199999,-37.9909095764],"type":"Point"}
}