{
  "type": "Feature",
  "properties": {
    "addr:full":"111 Hill St West Hobart TAS 7000",
    "addr:housenumber":"111",
    "addr:postcode":"7000",
    "addr:street":"Hill St",
    "iso:country":"AU",
    "sg:address":"111 Hill St",
    "sg:city":"West Hobart",
    "sg:classifiers":[
        {
            "category":"Health Services",
            "subcategory":"Doctor",
            "type":"Services"
        }
    ],
    "sg:phone":"+61 3 6231 5100",
    "sg:postcode":"7000",
    "sg:province":"TAS",
    "sg:tags":[
        "medical",
        "practitioner"
    ],
    "wof:name":"Suttar Arlene",
    "wof:placetype":"venue"
},
  "geometry": {"coordinates":[147.31134033199999,-42.8793449402],"type":"Point"}
}