{
  "type": "Feature",
  "properties": {
    "addr:full":"12 Walker St Dalyston VIC 3992",
    "addr:housenumber":"12",
    "addr:postcode":"3992",
    "addr:street":"Walker St",
    "iso:country":"AU",
    "sg:address":"12 Walker St",
    "sg:city":"Dalyston",
    "sg:classifiers":[
        {
            "category":"Home & Garden",
            "subcategory":"Building Materials",
            "type":"Retail Goods"
        }
    ],
    "sg:phone":"+61 3 5678 7208",
    "sg:postcode":"3992",
    "sg:province":"VIC",
    "sg:tags":[
        "lawn",
        "cutting",
        "maintenance"
    ],
    "wof:name":"Charlton's Maintenance Service",
    "wof:placetype":"venue"
},
  "geometry": {"coordinates":[145.54707300000001,-38.564262],"type":"Point"}
}