{
  "type": "Feature",
  "properties": {
    "iso:country":"AU",
    "sg:address":"310 Main Rd",
    "sg:city":"Toukley",
    "sg:classifiers":[
        {
            "category":"Retail",
            "subcategory":"Auto Repair",
            "type":"Services"
        }
    ],
    "sg:phone":"+61 2 4396 4187",
    "sg:postcode":"2263",
    "sg:province":"NSW",
    "sg:tags":[
        "muffler",
        "exhaust",
        "system"
    ],
    "wof:name":"Affordable Car Muffler And Exhaust's",
    "wof:placetype":"venue"
},
  "geometry": {"coordinates":[151.54542499999999,-33.264297],"type":"Point"}
}