{
  "type": "Feature",
  "properties": {
    "addr:full":"152 Bunnerong Rd Pagewood NSW 2035",
    "addr:housenumber":"152",
    "addr:postcode":"2035",
    "addr:street":"Bunnerong Rd",
    "iso:country":"AU",
    "sg:address":"152 Bunnerong Rd",
    "sg:city":"Pagewood",
    "sg:classifiers":[
        {
            "category":"Fast Food",
            "type":"Food & Drink"
        }
    ],
    "sg:phone":"+61 13 12 41",
    "sg:postcode":"2035",
    "sg:province":"NSW",
    "sg:tags":[
        "away",
        "take"
    ],
    "wof:name":"Pizza Haven",
    "wof:placetype":"venue"
},
  "geometry": {"coordinates":[151.226486206,-33.9449501038],"type":"Point"}
}