{
  "type": "Feature",
  "properties": {
    "addr:full":"5 Walker Rd Mt Waverley VIC 3149",
    "addr:housenumber":"5",
    "addr:postcode":"3149",
    "addr:street":"Walker Rd",
    "iso:country":"AU",
    "sg:address":"5 Walker Rd",
    "sg:city":"Mt Waverley",
    "sg:classifiers":[
        {
            "category":"Building & Trades",
            "subcategory":"Plumbing",
            "type":"Services"
        }
    ],
    "sg:phone":"+61 3 9886 3563",
    "sg:postcode":"3149",
    "sg:province":"VIC",
    "sg:tags":[
        "plumber",
        "gasfitters"
    ],
    "wof:name":"A Drain Doctor 24 Hrs",
    "wof:placetype":"venue"
},
  "geometry": {"coordinates":[145.13638305699999,-37.8615913391],"type":"Point"}
}