{
  "type": "Feature",
  "properties": {
    "iso:country":"AU",
    "sg:address":"2 Jambaroo St",
    "sg:city":"Albany Creek",
    "sg:classifiers":[
        {
            "category":"Utilities",
            "subcategory":"Water",
            "type":"Services"
        }
    ],
    "sg:phone":"+61 7 3264 7835",
    "sg:postcode":"4035",
    "sg:province":"QLD",
    "sg:tags":[
        "hot",
        "system"
    ],
    "wof:name":"Fowler Scott",
    "wof:placetype":"venue"
},
  "geometry": {"coordinates":[152.975586,-27.356138],"type":"Point"}
}