{
  "type": "Feature",
  "properties": {
    "iso:country":"AU",
    "sg:address":"94 Chum St",
    "sg:city":"Golden Square",
    "sg:classifiers":[
        {
            "category":"Banks & Credit Unions",
            "subcategory":"Bureau De Change",
            "type":"Services"
        }
    ],
    "sg:phone":"+61 3 5443 1977",
    "sg:postcode":"3555",
    "sg:province":"VIC",
    "sg:tags":[
        "repairs",
        "part",
        "appliance",
        "electrical"
    ],
    "wof:name":"Shaverman Pty Ltd",
    "wof:placetype":"venue"
},
  "geometry": {"coordinates":[144.25062560999999,-36.7636489868],"type":"Point"}
}