{
  "type": "Feature",
  "properties": {
    "addr:full":"Fcty 1/ 3 Industrial Ave Hoppers Crossing VIC 3029",
    "addr:housenumber":"/ 3",
    "addr:postcode":"3029",
    "addr:street":"Industrial Ave",
    "iso:country":"AU",
    "sg:address":"Fcty 1/ 3 Industrial Ave",
    "sg:city":"Hoppers Crossing",
    "sg:classifiers":[
        {
            "category":"Professional",
            "subcategory":"Engineering",
            "type":"Services"
        }
    ],
    "sg:phone":"+61 3 9360 9317",
    "sg:postcode":"3029",
    "sg:province":"VIC",
    "sg:tags":[
        "engineer"
    ],
    "wof:name":"24/7 Engineering pty ltd",
    "wof:placetype":"venue"
},
  "geometry": {"coordinates":[144.72456399999999,-37.869267],"type":"Point"}
}