{
  "type": "Feature",
  "properties": {
    "addr:full":"Ste 302/ 236 Hyperdome Loganholme QLD 4129",
    "addr:housenumber":"/ 236",
    "addr:postcode":"4129",
    "addr:street":"Hyperdome",
    "iso:country":"AU",
    "sg:address":"Ste 302/ 236 Hyperdome",
    "sg:city":"Loganholme",
    "sg:classifiers":[
        {
            "category":"Professional",
            "subcategory":"Detective & Security Services",
            "type":"Services"
        }
    ],
    "sg:phone":"+61 423 325 855",
    "sg:postcode":"4129",
    "sg:province":"QLD",
    "sg:tags":[
        "investigator"
    ],
    "wof:name":"International Investigations",
    "wof:placetype":"venue"
},
  "geometry": {"coordinates":[153.185791016,-27.6725502014],"type":"Point"}
}