{
  "type": "Feature",
  "properties": {
    "addr:full":"Balgownie Community Centre Balgownie Rd Balgownie NSW 2519",
    "addr:postcode":"2519",
    "addr:street":"Balgownie Rd",
    "iso:country":"AU",
    "sg:address":"Balgownie Community Centre Balgownie Rd",
    "sg:city":"Balgownie",
    "sg:classifiers":[
        {
            "category":"Recreation",
            "type":"Entertainment"
        }
    ],
    "sg:phone":"+61 2 4257 6814",
    "sg:postcode":"2519",
    "sg:province":"NSW",
    "sg:tags":[
        "children's",
        "play",
        "programme"
    ],
    "wof:name":"GymbaROO",
    "wof:placetype":"venue"
},
  "geometry": {"coordinates":[150.878174,-34.388645],"type":"Point"}
}