{
  "type": "Feature",
  "properties": {
    "iso:country":"AU",
    "sg:address":"PO Box 416",
    "sg:city":"Balgowlah",
    "sg:classifiers":[
        {
            "category":"Building & Trades",
            "subcategory":"Plumbing",
            "type":"Services"
        }
    ],
    "sg:phone":"+61 2 9948 8599",
    "sg:postcode":"2093",
    "sg:province":"NSW",
    "sg:tags":[
        "plumber",
        "gasfitters"
    ],
    "wof:name":"Waterex Plumbing Pty Ltd",
    "wof:placetype":"venue"
},
  "geometry": {"coordinates":[151.26158142099999,-33.7939300537],"type":"Point"}
}