{
  "type": "Feature",
  "properties": {
    "addr:full":"319 Annerley Rd Annerley QLD 4103",
    "addr:housenumber":"319",
    "addr:postcode":"4103",
    "addr:street":"Annerley Rd",
    "iso:country":"AU",
    "sg:address":"319 Annerley Rd",
    "sg:city":"Annerley",
    "sg:classifiers":[
        {
            "category":"Building & Trades",
            "subcategory":"Construction",
            "type":"Services"
        }
    ],
    "sg:phone":"+61 7 3391 1244",
    "sg:postcode":"4103",
    "sg:province":"QLD",
    "sg:tags":[
        "management"
    ],
    "wof:name":"Pitman Properties Pty Ltd",
    "wof:placetype":"venue"
},
  "geometry": {"coordinates":[153.03138732900001,-27.5037975311],"type":"Point"}
}