{
  "type": "Feature",
  "properties": {
    "iso:country":"AU",
    "sg:address":"209 Victoria Rd",
    "sg:city":"Coldstream",
    "sg:classifiers":[
        {
            "category":"Professional",
            "subcategory":"Business Services",
            "type":"Services"
        }
    ],
    "sg:phone":"+61 3 9739 0170",
    "sg:postcode":"3770",
    "sg:province":"VIC",
    "sg:tags":[
        "livestock",
        "transport"
    ],
    "wof:name":"Eclipse Equine Chauffeurs",
    "wof:placetype":"venue"
},
  "geometry": {"coordinates":[145.347214,-37.686989],"type":"Point"}
}