{
  "type": "Feature",
  "properties": {
    "addr:full":"209 Victoria Rd Coldstream VIC 3770",
    "addr:housenumber":"209",
    "addr:postcode":"3770",
    "addr:street":"Victoria Rd",
    "iso:country":"AU",
    "sg:address":"209 Victoria Rd",
    "sg:city":"Coldstream",
    "sg:classifiers":[
        {
            "category":"Professional",
            "subcategory":"Business Services",
            "type":"Services"
        }
    ],
    "sg:phone":"+61 3 9739 0170",
    "sg:postcode":"3770",
    "sg:province":"VIC",
    "sg:tags":[
        "livestock",
        "transport"
    ],
    "wof:name":"Eclipse Equine Chauffeurs",
    "wof:placetype":"venue"
},
  "geometry": {"coordinates":[145.34721400000001,-37.686989],"type":"Point"}
}