{
  "type": "Feature",
  "properties": {
    "addr:full":"3 Polat Crt Mt Evelyn VIC 3796",
    "addr:housenumber":"3",
    "addr:postcode":"3796",
    "addr:street":"Polat Crt",
    "iso:country":"AU",
    "sg:address":"3 Polat Crt",
    "sg:city":"Mt Evelyn",
    "sg:classifiers":[
        {
            "category":"Professional",
            "type":"Services"
        }
    ],
    "sg:phone":"+61 3 9736 1133",
    "sg:postcode":"3796",
    "sg:province":"VIC",
    "sg:tags":[
        "transport"
    ],
    "wof:name":"Evelyn Transport",
    "wof:placetype":"venue"
},
  "geometry": {"coordinates":[145.395065308,-37.7809944153],"type":"Point"}
}