{
  "type": "Feature",
  "properties": {
    "iso:country":"AU",
    "sg:address":"Level 1 116 Darby Rd",
    "sg:city":"Newcastle",
    "sg:classifiers":[
        {
            "category":"Insurance",
            "subcategory":"Life Insurance",
            "type":"Services"
        }
    ],
    "sg:phone":"+61 2 4929 2188",
    "sg:postcode":"2300",
    "sg:province":"NSW",
    "wof:name":"Brown Neil.J",
    "wof:placetype":"venue"
},
  "geometry": {"coordinates":[151.77191199999999,-32.931015],"type":"Point"}
}