{
  "type": "Feature",
  "properties": {
    "iso:country":"AU",
    "sg:address":"24 Miles Rd",
    "sg:city":"Kewdale",
    "sg:classifiers":[
        {
            "category":"Building & Trades",
            "subcategory":"Construction",
            "type":"Services"
        }
    ],
    "sg:phone":"+61 8 9353 5480",
    "sg:postcode":"6105",
    "sg:province":"WA",
    "sg:tags":[
        "concrete",
        "treatment",
        "repair"
    ],
    "wof:name":"Denso Australia Pty Ltd",
    "wof:placetype":"venue"
},
  "geometry": {"coordinates":[115.953422546,-31.982919693],"type":"Point"}
}