{
  "type": "Feature",
  "properties": {
    "addr:full":"2/ 21 Oxleigh Drv Malaga WA 6090",
    "addr:housenumber":"/ 21",
    "addr:postcode":"6090",
    "addr:street":"Oxleigh Drv",
    "iso:country":"AU",
    "sg:address":"2/ 21 Oxleigh Drv",
    "sg:city":"Malaga",
    "sg:classifiers":[
        {
            "category":"Building & Trades",
            "subcategory":"Cleaning & Sanitation",
            "type":"Services"
        }
    ],
    "sg:phone":"+61 1300 137 663",
    "sg:postcode":"6090",
    "sg:province":"WA",
    "sg:tags":[
        "asbestos",
        "treatment",
        "removal"
    ],
    "sg:website":"http://www.advancedroofs.com",
    "wof:name":"Advanced Roof Restoration",
    "wof:placetype":"venue"
},
  "geometry": {"coordinates":[115.88583374,-31.8511352539],"type":"Point"}
}