{
  "type": "Feature",
  "properties": {
    "addr:full":"22 Railway Pde Logan Central QLD 4114",
    "addr:housenumber":"22",
    "addr:postcode":"4114",
    "addr:street":"Railway Pde",
    "iso:country":"AU",
    "sg:address":"22 Railway Pde",
    "sg:city":"Logan Central",
    "sg:classifiers":[
        {
            "category":"Retail",
            "subcategory":"Auto Repair",
            "type":"Services"
        }
    ],
    "sg:phone":"+61 412 570 473",
    "sg:postcode":"4114",
    "sg:province":"QLD",
    "sg:tags":[
        "automotive",
        "air conditioning"
    ],
    "wof:name":"Total Mobile Airconditioning",
    "wof:placetype":"venue"
},
  "geometry": {"coordinates":[153.10520935100001,-27.639383316],"type":"Point"}
}