{
  "type": "Feature",
  "properties": {
    "iso:country":"AU",
    "sg:address":"Fairway Drv",
    "sg:city":"Nowra",
    "sg:classifiers":[
        {
            "category":"Retail",
            "subcategory":"Event Space",
            "type":"Services"
        }
    ],
    "sg:phone":"+61 2 4421 3900",
    "sg:postcode":"2541",
    "sg:province":"NSW",
    "sg:tags":[
        "venue",
        "reception",
        "wedding"
    ],
    "wof:name":"Nowra Golf & Rec. Club",
    "wof:placetype":"venue"
},
  "geometry": {"coordinates":[150.595214844,-34.8640785217],"type":"Point"}
}