{
  "type": "Feature",
  "properties": {
    "iso:country":"AU",
    "sg:address":"Bradman St",
    "sg:city":"Caboolture",
    "sg:classifiers":[
        {
            "category":"Banks & Credit Unions",
            "subcategory":"Investment Brokerage",
            "type":"Services"
        }
    ],
    "sg:phone":"+61 7 5495 1011",
    "sg:postcode":"4510",
    "sg:province":"QLD",
    "sg:tags":[
        "debt",
        "collection"
    ],
    "wof:name":"B B Commercial Agency",
    "wof:placetype":"venue"
},
  "geometry": {"coordinates":[152.958664,-27.074341],"type":"Point"}
}