{
  "type": "Feature",
  "properties": {
    "iso:country":"AU",
    "sg:address":"Ste9/ 50 Great North Rd",
    "sg:city":"Five Dock",
    "sg:classifiers":[
        {
            "category":"Home & Garden",
            "subcategory":"Building Materials",
            "type":"Retail Goods"
        }
    ],
    "sg:phone":"+61 2 9713 2801",
    "sg:postcode":"2046",
    "sg:province":"NSW",
    "sg:tags":[
        "plaster",
        "plasterboard",
        "supply"
    ],
    "wof:name":"Jayvue Pty Ltd",
    "wof:placetype":"venue"
},
  "geometry": {"coordinates":[151.12927199999999,-33.870609],"type":"Point"}
}