{
  "type": "Feature",
  "properties": {
    "addr:full":"Shop 3, 12 Ross St Glenbrook NSW 2773",
    "addr:housenumber":"shop;12",
    "addr:postcode":"2773",
    "addr:street":"Ross St",
    "iso:country":"AU",
    "sg:address":"Shop 3, 12 Ross St",
    "sg:city":"Glenbrook",
    "sg:classifiers":[
        {
            "category":"Professional",
            "subcategory":"Accounting & Tax Preparation",
            "type":"Services"
        }
    ],
    "sg:phone":"+61 2 4739 5557",
    "sg:postcode":"2773",
    "sg:province":"NSW",
    "sg:tags":[
        "accountant",
        "auditor"
    ],
    "wof:name":"Hoffman & Co Accountants",
    "wof:placetype":"venue"
},
  "geometry": {"coordinates":[150.62176513700001,-33.7668991089],"type":"Point"}
}