{
  "type": "Feature",
  "properties": {
    "addr:full":"Unit 6/ 33 - 43 Neakin Rd Meadowbrook QLD 4131",
    "addr:housenumber":"43",
    "addr:postcode":"4131",
    "addr:street":"Neakin Rd",
    "iso:country":"AU",
    "sg:address":"Unit 6/ 33 - 43 Neakin Rd",
    "sg:city":"Meadowbrook",
    "sg:classifiers":[
        {
            "category":"Utilities",
            "subcategory":"Electric",
            "type":"Services"
        }
    ],
    "sg:phone":"+61 7 3200 3013",
    "sg:postcode":"4131",
    "sg:province":"QLD",
    "sg:tags":[
        "electrical",
        "contractor"
    ],
    "wof:name":"K & L Electrics",
    "wof:placetype":"venue"
},
  "geometry": {"coordinates":[153.14097595199999,-27.6637706757],"type":"Point"}
}