{
  "type": "Feature",
  "properties": {
    "addr:full":"Factory 2, 29 Henderson Rd Knoxfield VIC 3180",
    "addr:housenumber":"29",
    "addr:postcode":"3180",
    "addr:street":"Henderson Rd",
    "iso:country":"AU",
    "sg:address":"Factory 2, 29 Henderson Rd",
    "sg:city":"Knoxfield",
    "sg:classifiers":[
        {
            "category":"Shopping",
            "subcategory":"Bicycles & Sporting Goods",
            "type":"Retail Goods"
        }
    ],
    "sg:phone":"+61 3 9764 0799",
    "sg:postcode":"3180",
    "sg:province":"VIC",
    "sg:tags":[
        "chemical",
        "equipment",
        "pool",
        "swimming"
    ],
    "wof:name":"Poolstore International Pty Ltd",
    "wof:placetype":"venue"
},
  "geometry": {"coordinates":[145.248336792,-37.9036598206],"type":"Point"}
}