{
  "type": "Feature",
  "properties": {
    "addr:full":"209 Keen St Lismore NSW 2480",
    "addr:housenumber":"209",
    "addr:postcode":"2480",
    "addr:street":"Keen St",
    "iso:country":"AU",
    "sg:address":"209 Keen St",
    "sg:city":"Lismore",
    "sg:classifiers":[
        {
            "category":"Structure",
            "subcategory":"Bridge",
            "type":"Public Place"
        }
    ],
    "sg:phone":"+61 2 6621 4905",
    "sg:postcode":"2480",
    "sg:province":"NSW",
    "sg:tags":[
        "chainsaw",
        "brushcutters"
    ],
    "wof:name":"Diamond Service Centre",
    "wof:placetype":"venue"
},
  "geometry": {"coordinates":[153.276687622,-28.811416626],"type":"Point"}
}