{
  "type": "Feature",
  "properties": {
    "iso:country":"AU",
    "sg:address":"Cnr Botany & Gardeners Rds",
    "sg:city":"Mascot",
    "sg:classifiers":[
        {
            "category":"Shopping",
            "subcategory":"Mobile Phones",
            "type":"Retail Goods"
        }
    ],
    "sg:phone":"+61 1800 243 252",
    "sg:postcode":"2020",
    "sg:province":"NSW",
    "sg:tags":[
        "telephone",
        "accessory"
    ],
    "wof:name":"MobileCorp",
    "wof:placetype":"venue"
},
  "geometry": {"coordinates":[151.19451904300001,-33.9301872253],"type":"Point"}
}