{
  "type": "Feature",
  "properties": {
    "iso:country":"AU",
    "sg:address":"90a Blackwood Rd",
    "sg:city":"Manly West",
    "sg:classifiers":[
        {
            "category":"Building & Trades",
            "subcategory":"Plumbing",
            "type":"Services"
        }
    ],
    "sg:phone":"+61 7 3396 7145",
    "sg:postcode":"4179",
    "sg:province":"QLD",
    "sg:tags":[
        "plumber",
        "gasfitters"
    ],
    "wof:name":"Bayside Plumbing",
    "wof:placetype":"venue"
},
  "geometry": {"coordinates":[153.16969299300001,-27.4581069946],"type":"Point"}
}