{
  "type": "Feature",
  "properties": {
    "addr:full":"29 Ashleigh Ave Frankston VIC 3199",
    "addr:housenumber":"29",
    "addr:postcode":"3199",
    "addr:street":"Ashleigh Ave",
    "iso:country":"AU",
    "sg:address":"29 Ashleigh Ave",
    "sg:city":"Frankston",
    "sg:classifiers":[
        {
            "category":"Professional",
            "subcategory":"Art Services",
            "type":"Services"
        }
    ],
    "sg:phone":"+61 3 8790 8237",
    "sg:postcode":"3199",
    "sg:province":"VIC",
    "sg:tags":[
        "decorator",
        "painter"
    ],
    "wof:name":"K P World Of Colour",
    "wof:placetype":"venue"
},
  "geometry": {"coordinates":[145.14486694300001,-38.1445045471],"type":"Point"}
}