{
  "type": "Feature",
  "properties": {
    "iso:country":"AU",
    "sg:address":"43 Benwerrin Drv",
    "sg:city":"Burwood East",
    "sg:classifiers":[
        {
            "category":"Professional",
            "subcategory":"Accounting & Tax Preparation",
            "type":"Services"
        }
    ],
    "sg:phone":"+61 3 9803 7655",
    "sg:postcode":"3151",
    "sg:province":"VIC",
    "sg:tags":[
        "accountant",
        "auditor"
    ],
    "wof:name":"Bourke Liston & Co",
    "wof:placetype":"venue"
},
  "geometry": {"coordinates":[145.14332580600001,-37.855430603],"type":"Point"}
}