{
  "type": "Feature",
  "properties": {
    "addr:full":"U3/ 4 Castlereagh St Bundaberg South QLD 4670",
    "addr:housenumber":"4",
    "addr:postcode":"4670",
    "addr:street":"U3 /;Castlereagh St",
    "iso:country":"AU",
    "sg:address":"U3/ 4 Castlereagh St",
    "sg:city":"Bundaberg South",
    "sg:classifiers":[
        {
            "category":"Home & Garden",
            "subcategory":"Carpets & Floor Coverings",
            "type":"Retail Goods"
        }
    ],
    "sg:phone":"+61 7 4152 3731",
    "sg:postcode":"4670",
    "sg:province":"QLD",
    "sg:tags":[
        "tile",
        "wall",
        "layer"
    ],
    "wof:name":"Davids Tiling",
    "wof:placetype":"venue"
},
  "geometry": {"coordinates":[152.35931396500001,-24.8714237213],"type":"Point"}
}