{
  "type": "Feature",
  "properties": {
    "iso:country":"AU",
    "sg:address":"20 Barnett St",
    "sg:city":"Hampton",
    "sg:classifiers":[
        {
            "category":"Professional",
            "subcategory":"Secretarial Services",
            "type":"Services"
        }
    ],
    "sg:phone":"+61 3 9521 0688",
    "sg:postcode":"3188",
    "sg:province":"VIC",
    "sg:tags":[
        "typing"
    ],
    "wof:name":"A Total Secretarial Service",
    "wof:placetype":"venue"
},
  "geometry": {"coordinates":[145.019287109,-37.9333000183],"type":"Point"}
}