{
  "type": "Feature",
  "properties": {
    "addr:full":"PO Box 1181 Nightcliff NT 0814",
    "addr:postcode":"nt 0814",
    "iso:country":"AU",
    "sg:address":"PO Box 1181",
    "sg:city":"Nightcliff",
    "sg:classifiers":[
        {
            "category":"Professional",
            "subcategory":"Computer Services",
            "type":"Services"
        }
    ],
    "sg:phone":"+61 407 900 067",
    "sg:postcode":"0814",
    "sg:province":"NT",
    "sg:tags":[
        "consultant",
        "system"
    ],
    "wof:name":"Enterprise Network Solutions N.T. Pty Ltd",
    "wof:placetype":"venue"
},
  "geometry": {"coordinates":[130.856064,-12.387455],"type":"Point"}
}