{
  "type": "Feature",
  "properties": {
    "iso:country":"AU",
    "sg:address":"1 Vine St",
    "sg:city":"Avoca Beach",
    "sg:classifiers":[
        {
            "category":"Cafe",
            "type":"Food & Drink"
        }
    ],
    "sg:phone":"+61 2 4381 2095",
    "sg:postcode":"2251",
    "sg:province":"NSW",
    "wof:name":"The Kiosk Avoca Beach",
    "wof:placetype":"venue"
},
  "geometry": {"coordinates":[151.436965942,-33.4710578918],"type":"Point"}
}