{
  "type": "Feature",
  "properties": {
    "addr:full":"51 Navua Ave Aspley QLD 4034",
    "addr:housenumber":"51",
    "addr:postcode":"4034",
    "addr:street":"Navua Ave",
    "iso:country":"AU",
    "sg:address":"51 Navua Ave",
    "sg:city":"Aspley",
    "sg:classifiers":[
        {
            "category":"Building & Trades",
            "subcategory":"Plumbing",
            "type":"Services"
        }
    ],
    "sg:phone":"+61 418 894 085",
    "sg:postcode":"4034",
    "sg:province":"QLD",
    "sg:tags":[
        "plumber",
        "gasfitters"
    ],
    "wof:name":"A & J Laing Plumbing Specialists",
    "wof:placetype":"venue"
},
  "geometry": {"coordinates":[153.021973,-27.36149],"type":"Point"}
}