{
  "type": "Feature",
  "properties": {
    "iso:country":"AU",
    "sg:address":"8 Tamarisk Drv",
    "sg:city":"Halls Head",
    "sg:classifiers":[
        {
            "category":"Building & Trades",
            "subcategory":"Construction",
            "type":"Services"
        }
    ],
    "sg:phone":"+61 8 9535 4699",
    "sg:postcode":"6210",
    "sg:province":"WA",
    "sg:tags":[
        "contractor"
    ],
    "wof:name":"Chapple Rob",
    "wof:placetype":"venue"
},
  "geometry": {"coordinates":[115.689957,-32.547226],"type":"Point"}
}