{
  "type": "Feature",
  "properties": {
    "addr:full":"Shop 1/ 182 Waldron Rd Chester Hill NSW 2162",
    "addr:housenumber":"shop 1 / 182",
    "addr:postcode":"2162",
    "addr:street":"Waldron Rd",
    "iso:country":"AU",
    "sg:address":"Shop 1/ 182 Waldron Rd",
    "sg:city":"Chester Hill",
    "sg:classifiers":[
        {
            "category":"Food & Beverages",
            "subcategory":"Supermarket",
            "type":"Retail Goods"
        }
    ],
    "sg:phone":"+61 2 9644 9836",
    "sg:postcode":"2162",
    "sg:province":"NSW",
    "sg:tags":[
        "grocery",
        "store"
    ],
    "wof:name":"T & K Convinience Store",
    "wof:placetype":"venue"
},
  "geometry": {"coordinates":[150.999557495,-33.8827285767],"type":"Point"}
}