{
  "type": "Feature",
  "properties": {
    "addr:full":"19 Daringa St Mile End SA 5031",
    "addr:housenumber":"19",
    "addr:postcode":"5031",
    "addr:street":"Daringa St",
    "iso:country":"AU",
    "sg:address":"19 Daringa St",
    "sg:city":"Mile End",
    "sg:classifiers":[
        {
            "category":"Utilities",
            "subcategory":"Electric",
            "type":"Services"
        }
    ],
    "sg:phone":"+61 8 8354 0377",
    "sg:postcode":"5031",
    "sg:province":"SA",
    "sg:tags":[
        "electrical",
        "contractor"
    ],
    "wof:name":"Enviro Bright Pty Ltd",
    "wof:placetype":"venue"
},
  "geometry": {"coordinates":[138.57168579099999,-34.9307632446],"type":"Point"}
}