{
  "type": "Feature",
  "properties": {
    "iso:country":"AU",
    "sg:address":"8 James St",
    "sg:city":"Strathmore",
    "sg:classifiers":[
        {
            "category":"Real Estate",
            "subcategory":"Architect",
            "type":"Services"
        }
    ],
    "sg:phone":"+61 3 9326 1511",
    "sg:postcode":"3041",
    "sg:province":"VIC",
    "sg:tags":[
        "building",
        "designer"
    ],
    "wof:name":"Danny Sacco & Partners Pty Ltd",
    "wof:placetype":"venue"
},
  "geometry": {"coordinates":[144.91812133799999,-37.7390098572],"type":"Point"}
}