{
  "type": "Feature",
  "properties": {
    "addr:full":"Shop 2 Davies Ave Mt Eliza VIC 3930",
    "addr:housenumber":"shop 2",
    "addr:postcode":"3930",
    "addr:street":"Davies Ave",
    "iso:country":"AU",
    "sg:address":"Shop 2 Davies Ave",
    "sg:city":"Mt Eliza",
    "sg:classifiers":[
        {
            "category":"Shopping",
            "subcategory":"Bicycles & Sporting Goods",
            "type":"Retail Goods"
        }
    ],
    "sg:phone":"+61 3 9787 6444",
    "sg:postcode":"3930",
    "sg:province":"VIC",
    "sg:tags":[
        "chemical",
        "equipment",
        "pool",
        "swimming"
    ],
    "wof:name":"Beautiful Swim",
    "wof:placetype":"venue"
},
  "geometry": {"coordinates":[145.090942383,-38.1831741333],"type":"Point"}
}