{
  "type": "Feature",
  "properties": {
    "addr:full":"48 Alderbury St Floreat WA 6014",
    "addr:housenumber":"48",
    "addr:postcode":"6014",
    "addr:street":"Alderbury St",
    "iso:country":"AU",
    "sg:address":"48 Alderbury St",
    "sg:city":"Floreat",
    "sg:classifiers":[
        {
            "category":"Personal",
            "subcategory":"Massage",
            "type":"Services"
        }
    ],
    "sg:phone":"+61 8 9387 1997",
    "sg:postcode":"6014",
    "sg:province":"WA",
    "sg:tags":[
        "therapy"
    ],
    "wof:name":"Rodney Hunt",
    "wof:placetype":"venue"
},
  "geometry": {"coordinates":[115.79692077599999,-31.9440937042],"type":"Point"}
}