{
  "type": "Feature",
  "properties": {
    "addr:full":"Cnr Burwood Rd & Carter St Belfield NSW 2191",
    "addr:postcode":"2191",
    "addr:street":"Burwood Rd & Carter St",
    "iso:country":"AU",
    "sg:address":"Cnr Burwood Rd & Carter St",
    "sg:city":"Belfield",
    "sg:classifiers":[
        {
            "category":"Retail",
            "subcategory":"Auto Repair",
            "type":"Services"
        }
    ],
    "sg:phone":"+61 2 9642 2335",
    "sg:postcode":"2191",
    "sg:province":"NSW",
    "sg:tags":[
        "repairer",
        "motor",
        "engineer"
    ],
    "wof:name":"Belfield Service Centre",
    "wof:placetype":"venue"
},
  "geometry": {"coordinates":[151.085037,-33.904579],"type":"Point"}
}