{
  "type": "Feature",
  "properties": {
    "addr:full":"Shop 3 205 Merrylands Rd Merrylands NSW 2160",
    "addr:housenumber":"shop 3",
    "addr:postcode":"205;2160",
    "addr:street":"Merrylands Rd",
    "iso:country":"AU",
    "sg:address":"Shop 3 205 Merrylands Rd",
    "sg:city":"Merrylands",
    "sg:classifiers":[
        {
            "category":"Shopping",
            "subcategory":"Optical Goods",
            "type":"Retail Goods"
        }
    ],
    "sg:phone":"+61 2 9637 8085",
    "sg:postcode":"2160",
    "sg:province":"NSW",
    "sg:tags":[
        "dispenser",
        "prescription"
    ],
    "wof:name":"The Spectacle Spot",
    "wof:placetype":"venue"
},
  "geometry": {"coordinates":[150.98907470699999,-33.836151123],"type":"Point"}
}