{
  "type": "Feature",
  "properties": {
    "addr:full":"79 Crannys St Yeppoon QLD 4703",
    "addr:housenumber":"79",
    "addr:postcode":"4703",
    "addr:street":"Crannys St",
    "iso:country":"AU",
    "sg:address":"79 Crannys St",
    "sg:city":"Yeppoon",
    "sg:classifiers":[
        {
            "category":"Shopping",
            "subcategory":"Computers & Home Electronics",
            "type":"Retail Goods"
        }
    ],
    "sg:phone":"+61 7 4938 3333",
    "sg:postcode":"4703",
    "sg:province":"QLD",
    "sg:tags":[
        "hardware",
        "equipment"
    ],
    "wof:name":"Cyclops Systems",
    "wof:placetype":"venue"
},
  "geometry": {"coordinates":[150.73150634800001,-23.105714798],"type":"Point"}
}