{
  "type": "Feature",
  "properties": {
    "addr:full":"112 Fairy St Warrnambool VIC 3280",
    "addr:housenumber":"112",
    "addr:postcode":"3280",
    "addr:street":"Fairy St",
    "iso:country":"AU",
    "sg:address":"112 Fairy St",
    "sg:city":"Warrnambool",
    "sg:classifiers":[
        {
            "category":"Travel",
            "subcategory":"Hotels & Motels",
            "type":"Entertainment"
        }
    ],
    "sg:phone":"+61 3 5561 3932",
    "sg:postcode":"3280",
    "sg:province":"VIC",
    "sg:tags":[
        "accommodation"
    ],
    "wof:name":"Cally Hotel",
    "wof:placetype":"venue"
},
  "geometry": {"coordinates":[142.47979736299999,-38.3808937073],"type":"Point"}
}