{
  "type": "Feature",
  "properties": {
    "iso:country":"AU",
    "sg:address":"221 Corcoran St",
    "sg:city":"Currajong",
    "sg:classifiers":[
        {
            "category":"Utilities",
            "subcategory":"Water",
            "type":"Services"
        }
    ],
    "sg:phone":"+61 7 4779 2206",
    "sg:postcode":"4812",
    "sg:province":"QLD",
    "sg:tags":[
        "hot",
        "system"
    ],
    "wof:name":"Wares Plumbing Service Pty Ltd",
    "wof:placetype":"venue"
},
  "geometry": {"coordinates":[146.777161,-19.276909],"type":"Point"}
}