{
  "type": "Feature",
  "properties": {
    "addr:full":"Unit 6 1 Alvan St Mt Lawley WA 6050",
    "addr:housenumber":"1",
    "addr:postcode":"6050",
    "addr:street":"Alvan St",
    "iso:country":"AU",
    "sg:address":"Unit 6 1 Alvan St",
    "sg:city":"Mt Lawley",
    "sg:classifiers":[
        {
            "category":"Organizations",
            "subcategory":"Professional Association",
            "type":"Services"
        }
    ],
    "sg:phone":"+61 8 9370 5224",
    "sg:postcode":"6050",
    "sg:province":"WA",
    "sg:tags":[
        "organisation",
        "business"
    ],
    "wof:name":"Australasian Association of Clinical Biochemists Inc",
    "wof:placetype":"venue"
},
  "geometry": {"coordinates":[115.873497009,-31.9346065521],"type":"Point"}
}