{
  "type": "Feature",
  "properties": {
    "addr:full":"245 Albert St Mall Brisbane QLD 4000",
    "addr:housenumber":"245",
    "addr:postcode":"4000",
    "addr:street":"Albert St Mall",
    "iso:country":"AU",
    "sg:address":"245 Albert St",
    "sg:city":"Mall Brisbane",
    "sg:classifiers":[
        {
            "category":"Health Services",
            "subcategory":"Doctor",
            "type":"Services"
        }
    ],
    "sg:phone":"+61 7 3211 3611",
    "sg:postcode":"4000",
    "sg:province":"QLD",
    "sg:tags":[
        "medical",
        "practitioner"
    ],
    "wof:name":"A Brisbane CBD Travel Clinic",
    "wof:placetype":"venue"
},
  "geometry": {"coordinates":[153.0259552,-27.4701690674],"type":"Point"}
}