{
  "type": "Feature",
  "properties": {
    "addr:full":"264 Banna Ave Griffith NSW 2680",
    "addr:housenumber":"264",
    "addr:postcode":"2680",
    "addr:street":"Banna Ave",
    "iso:country":"AU",
    "sg:address":"264 Banna Ave",
    "sg:city":"Griffith",
    "sg:classifiers":[
        {
            "category":"Shopping",
            "subcategory":"Clothing, Apparel, & Fashions",
            "type":"Retail Goods"
        }
    ],
    "sg:phone":"+61 2 6962 5591",
    "sg:postcode":"2680",
    "sg:province":"NSW",
    "sg:tags":[
        "menswear"
    ],
    "wof:name":"Lowes Menswear",
    "wof:placetype":"venue"
},
  "geometry": {"coordinates":[146.04658499999999,-34.288223],"type":"Point"}
}