{
  "type": "Feature",
  "properties": {
    "iso:country":"AU",
    "sg:address":"70 Queen St",
    "sg:city":"Campbelltown",
    "sg:classifiers":[
        {
            "category":"Autos & Motor Vehicles",
            "subcategory":"Automobile Sales",
            "type":"Retail Goods"
        }
    ],
    "sg:phone":"+61 2 4627 8866",
    "sg:postcode":"2560",
    "sg:province":"NSW",
    "sg:tags":[
        "car",
        "used"
    ],
    "wof:name":"Nadana Pty Ltd",
    "wof:placetype":"venue"
},
  "geometry": {"coordinates":[150.81887817399999,-34.0618057251],"type":"Point"}
}