{
  "type": "Feature",
  "properties": {
    "addr:full":"129 James St Toowoomba QLD 4350",
    "addr:housenumber":"129",
    "addr:postcode":"4350",
    "addr:street":"James St",
    "iso:country":"AU",
    "sg:address":"129 James St",
    "sg:city":"Toowoomba",
    "sg:classifiers":[
        {
            "category":"Organizations",
            "subcategory":"Community Association",
            "type":"Services"
        }
    ],
    "sg:phone":"+61 7 4637 9600",
    "sg:postcode":"4350",
    "sg:province":"QLD",
    "sg:tags":[
        "organisation",
        "family",
        "welfare"
    ],
    "wof:name":"R.E.F.S. Toowoomba",
    "wof:placetype":"venue"
},
  "geometry": {"coordinates":[151.958923,-27.569466],"type":"Point"}
}