{
  "type": "Feature",
  "properties": {
    "addr:full":"112 Calais Rd Wembley Downs WA 6019",
    "addr:housenumber":"112",
    "addr:postcode":"6019",
    "addr:street":"Calais Rd",
    "iso:country":"AU",
    "sg:address":"112 Calais Rd",
    "sg:city":"Wembley Downs",
    "sg:classifiers":[
        {
            "category":"Utilities",
            "subcategory":"Electric",
            "type":"Services"
        }
    ],
    "sg:phone":"+61 409 084 972",
    "sg:postcode":"6019",
    "sg:province":"WA",
    "sg:tags":[
        "electrical",
        "contractor"
    ],
    "wof:name":"ESP ELECTRICAL SERVICE PROVIDER",
    "wof:placetype":"venue"
},
  "geometry": {"coordinates":[115.76841735799999,-31.9093475342],"type":"Point"}
}