{
  "type": "Feature",
  "properties": {
    "iso:country":"AU",
    "sg:address":"808 Mount Alexander Rd",
    "sg:city":"Moonee Ponds",
    "sg:classifiers":[
        {
            "category":"Health Services",
            "subcategory":"Chiropractor",
            "type":"Services"
        }
    ],
    "sg:phone":"+61 3 9326 1444",
    "sg:postcode":"3039",
    "sg:province":"VIC",
    "wof:name":"Ziros Grant Dr",
    "wof:placetype":"venue"
},
  "geometry": {"coordinates":[144.921616,-37.760807],"type":"Point"}
}