{
  "type": "Feature",
  "properties": {
    "addr:full":"26 Pike St Rydalmere NSW 2116",
    "addr:housenumber":"26",
    "addr:postcode":"2116",
    "addr:street":"Pike St",
    "iso:country":"AU",
    "sg:address":"26 Pike St",
    "sg:city":"Rydalmere",
    "sg:classifiers":[
        {
            "category":"Transit Center",
            "subcategory":"Freight",
            "type":"Transportation"
        }
    ],
    "sg:phone":"+61 2 9898 5844",
    "sg:postcode":"2116",
    "sg:province":"NSW",
    "sg:tags":[
        "forklift",
        "truck"
    ],
    "wof:name":"Mitsubishi Forklift Trucks",
    "wof:placetype":"venue"
},
  "geometry": {"coordinates":[151.036987305,-33.8176612854],"type":"Point"}
}