{
  "type": "Feature",
  "properties": {
    "addr:full":"Warrego Hwy Gatton QLD 4343",
    "addr:postcode":"4343",
    "addr:street":"Warrego Hwy",
    "iso:country":"AU",
    "sg:address":"Warrego Hwy",
    "sg:city":"Gatton",
    "sg:classifiers":[
        {
            "category":"Wholesale",
            "subcategory":"Fruits & Vegetables",
            "type":"Manufacturing & Wholesale Goods"
        }
    ],
    "sg:phone":"+61 7 5466 5441",
    "sg:postcode":"4343",
    "sg:province":"QLD",
    "sg:tags":[
        "produce",
        "grain"
    ],
    "wof:name":"Qualipac Produce",
    "wof:placetype":"venue"
},
  "geometry": {"coordinates":[152.320388794,-27.5503425598],"type":"Point"}
}