{
  "type": "Feature",
  "properties": {
    "addr:full":"199 Victoria St Kings Cross NSW 2011",
    "addr:housenumber":"199",
    "addr:postcode":"2011",
    "addr:street":"Victoria St",
    "iso:country":"AU",
    "sg:address":"199 Victoria St",
    "sg:city":"Kings Cross",
    "sg:classifiers":[
        {
            "category":"Personal",
            "subcategory":"Beauty Salon",
            "type":"Services"
        }
    ],
    "sg:phone":"+61 2 9358 5059",
    "sg:postcode":"2011",
    "sg:province":"NSW",
    "sg:tags":[
        "hairdresser"
    ],
    "wof:name":"Fontana For Men",
    "wof:placetype":"venue"
},
  "geometry": {"coordinates":[151.22207641599999,-33.8747177124],"type":"Point"}
}