{
  "type": "Feature",
  "properties": {
    "addr:full":"4 Argent Pl Ringwood VIC 3134",
    "addr:housenumber":"4",
    "addr:postcode":"3134",
    "addr:street":"Argent Pl",
    "iso:country":"AU",
    "sg:address":"4 Argent Pl",
    "sg:city":"Ringwood",
    "sg:classifiers":[
        {
            "category":"Building & Trades",
            "subcategory":"Plumbing",
            "type":"Services"
        }
    ],
    "sg:phone":"+61 3 8587 9266",
    "sg:postcode":"3134",
    "sg:province":"VIC",
    "sg:tags":[
        "equipment",
        "valves"
    ],
    "wof:name":"Goyen Controls Co Pty Ltd",
    "wof:placetype":"venue"
},
  "geometry": {"coordinates":[145.213943481,-37.8276176453],"type":"Point"}
}