{
  "type": "Feature",
  "properties": {
    "addr:full":"151 Lynch Rd Fawkner VIC 3060",
    "addr:housenumber":"151",
    "addr:postcode":"3060",
    "addr:street":"Lynch Rd",
    "iso:country":"AU",
    "sg:address":"151 Lynch Rd",
    "sg:city":"Fawkner",
    "sg:classifiers":[
        {
            "category":"Retail",
            "subcategory":"Auto Repair",
            "type":"Services"
        }
    ],
    "sg:phone":"+61 3 9359 6660",
    "sg:postcode":"3060",
    "sg:province":"VIC",
    "sg:tags":[
        "engine",
        "reconditioning"
    ],
    "wof:name":"MDB Cylinder Heads",
    "wof:placetype":"venue"
},
  "geometry": {"coordinates":[144.96315002399999,-37.7110061646],"type":"Point"}
}