{
  "type": "Feature",
  "properties": {
    "addr:full":"397 Hellawell Rds Sunnybank Hills QLD 4109",
    "addr:housenumber":"397",
    "addr:postcode":"4109",
    "addr:street":"Hellawell Rds",
    "iso:country":"AU",
    "sg:address":"397 Hellawell Rds",
    "sg:city":"Sunnybank Hills",
    "sg:classifiers":[
        {
            "category":"Retail",
            "subcategory":"Self-service Laundry",
            "type":"Services"
        }
    ],
    "sg:phone":"+61 7 3272 0272",
    "sg:postcode":"4109",
    "sg:province":"QLD",
    "wof:name":"Sunnybank Hills Laundry World",
    "wof:placetype":"venue"
},
  "geometry": {"coordinates":[153.05752563499999,-27.5992965698],"type":"Point"}
}