{
  "type": "Feature",
  "properties": {
    "addr:full":"143 Errol St North Melbourne VIC 3051",
    "addr:housenumber":"143",
    "addr:postcode":"3051",
    "addr:street":"Errol St",
    "iso:country":"AU",
    "sg:address":"143 Errol St",
    "sg:city":"North Melbourne",
    "sg:classifiers":[
        {
            "category":"Banks & Credit Unions",
            "subcategory":"Financial Services",
            "type":"Services"
        }
    ],
    "sg:phone":"+61 1300 858 120",
    "sg:postcode":"3051",
    "sg:province":"VIC",
    "sg:tags":[
        "surge",
        "protection",
        "lightning"
    ],
    "wof:name":"A.C.E.S.",
    "wof:placetype":"venue"
},
  "geometry": {"coordinates":[144.949752808,-37.8014144897],"type":"Point"}
}