{
  "type": "Feature",
  "properties": {
    "addr:full":"3 Sandiland St Mallanganee NSW 2469",
    "addr:housenumber":"3",
    "addr:postcode":"2469",
    "addr:street":"Sandiland St",
    "iso:country":"AU",
    "sg:address":"3 Sandiland St",
    "sg:city":"Mallanganee",
    "sg:classifiers":[
        {
            "category":"Freight",
            "type":"Transportation"
        }
    ],
    "sg:phone":"+61 2 6664 5195",
    "sg:postcode":"2469",
    "sg:province":"NSW",
    "sg:tags":[
        "light",
        "carrier"
    ],
    "wof:name":"Fitzhenry S P & D P",
    "wof:placetype":"venue"
},
  "geometry": {"coordinates":[152.71844482399999,-28.9064884186],"type":"Point"}
}