{
  "type": "Feature",
  "properties": {
    "addr:full":"849 Pascoe Vale Rd Glenroy VIC 3046",
    "addr:housenumber":"849",
    "addr:postcode":"3046",
    "addr:street":"Pascoe Vale Rd",
    "iso:country":"AU",
    "sg:address":"849 Pascoe Vale Rd",
    "sg:city":"Glenroy",
    "sg:classifiers":[
        {
            "category":"Health Services",
            "subcategory":"Dentist",
            "type":"Services"
        }
    ],
    "sg:phone":"+61 3 9306 9721",
    "sg:postcode":"3046",
    "sg:province":"VIC",
    "wof:name":"McCormack Peter F Dr.",
    "wof:placetype":"venue"
},
  "geometry": {"coordinates":[144.91526794399999,-37.7031745911],"type":"Point"}
}