{
  "type": "Feature",
  "properties": {
    "iso:country":"AU",
    "sg:address":"702 Glenferrie Rd",
    "sg:city":"Hawthorn",
    "sg:classifiers":[
        {
            "category":"Food & Beverages",
            "subcategory":"Specialty",
            "type":"Retail Goods"
        }
    ],
    "sg:phone":"+61 3 9819 1039",
    "sg:postcode":"3122",
    "sg:province":"VIC",
    "sg:tags":[
        "product",
        "health"
    ],
    "wof:name":"Good Vibration Health Shop",
    "wof:placetype":"venue"
},
  "geometry": {"coordinates":[145.03596496599999,-37.8201904297],"type":"Point"}
}