{
  "type": "Feature",
  "properties": {
    "iso:country":"AU",
    "sg:address":"3530 Great Eastern Hwy",
    "sg:city":"Mahogany Creek",
    "sg:classifiers":[
        {
            "category":"Building & Trades",
            "subcategory":"Construction",
            "type":"Services"
        }
    ],
    "sg:phone":"+61 418 779 949",
    "sg:postcode":"6072",
    "sg:province":"WA",
    "sg:tags":[
        "fencing",
        "contractor"
    ],
    "wof:name":"Goddard D",
    "wof:placetype":"venue"
},
  "geometry": {"coordinates":[116.12700700000001,-31.899933],"type":"Point"}
}