{
  "type": "Feature",
  "properties": {
    "iso:country":"AU",
    "sg:address":"153 Sydney Rd",
    "sg:city":"Brunswick",
    "sg:classifiers":[
        {
            "category":"Personal",
            "subcategory":"Beauty Salon",
            "type":"Services"
        }
    ],
    "sg:phone":"+61 3 9381 1121",
    "sg:postcode":"3056",
    "sg:province":"VIC",
    "sg:tags":[
        "hairdresser"
    ],
    "wof:name":"Witzand Hair Studio",
    "wof:placetype":"venue"
},
  "geometry": {"coordinates":[144.960845947,-37.7736320496],"type":"Point"}
}