{
  "type": "Feature",
  "properties": {
    "addr:full":"U1/ 3 King Edward Rd Osborne Park WA 6017",
    "addr:housenumber":"3",
    "addr:postcode":"6017",
    "addr:street":"U1 /;King Edward Rd",
    "iso:country":"AU",
    "sg:address":"U1/ 3 King Edward Rd",
    "sg:city":"Osborne Park",
    "sg:classifiers":[
        {
            "category":"Farming",
            "subcategory":"Farm & Veterinary Services",
            "type":"Manufacturing & Wholesale Goods"
        }
    ],
    "sg:phone":"+61 8 9244 7477",
    "sg:postcode":"6017",
    "sg:province":"WA",
    "sg:tags":[
        "irrigation",
        "reticulation",
        "system"
    ],
    "wof:name":"Total Eden Osborne Park",
    "wof:placetype":"venue"
},
  "geometry": {"coordinates":[115.804450989,-31.9037075043],"type":"Point"}
}