{
  "type": "Feature",
  "properties": {
    "iso:country":"AU",
    "sg:address":"Ruthven & Long St",
    "sg:city":"Toowoomba",
    "sg:classifiers":[
        {
            "category":"Food & Beverages",
            "subcategory":"Liquor & Beverages",
            "type":"Retail Goods"
        }
    ],
    "sg:phone":"+61 7 4638 9357",
    "sg:postcode":"4350",
    "sg:province":"QLD",
    "sg:tags":[
        "store"
    ],
    "wof:name":"Mr Corks",
    "wof:placetype":"venue"
},
  "geometry": {"coordinates":[151.951904,-27.569506],"type":"Point"}
}