{
  "type": "Feature",
  "properties": {
    "iso:country":"AU",
    "sg:address":"3 Ross River Rd",
    "sg:city":"Mundingburra",
    "sg:classifiers":[
        {
            "category":"Fast Food",
            "type":"Food & Drink"
        }
    ],
    "sg:phone":"+61 7 4725 5181",
    "sg:postcode":"4812",
    "sg:province":"QLD",
    "sg:tags":[
        "away",
        "take"
    ],
    "wof:name":"Franks Pizza Napoli & Vesuviana Restaurant",
    "wof:placetype":"venue"
},
  "geometry": {"coordinates":[146.795853,-19.291286],"type":"Point"}
}