{
  "type": "Feature",
  "properties": {
    "addr:full":"16 Burns St Hillston NSW 2675",
    "addr:housenumber":"16",
    "addr:postcode":"2675",
    "addr:street":"Burns St",
    "iso:country":"AU",
    "sg:address":"16 Burns St",
    "sg:city":"Hillston",
    "sg:classifiers":[
        {
            "category":"Building & Trades",
            "subcategory":"Landscaping Services",
            "type":"Services"
        }
    ],
    "sg:phone":"+61 2 6967 1110",
    "sg:postcode":"2675",
    "sg:province":"NSW",
    "sg:tags":[
        "fertilizer",
        "spreading",
        "insecticide"
    ],
    "wof:name":"Agri-Tech Services",
    "wof:placetype":"venue"
},
  "geometry": {"coordinates":[145.53811645499999,-33.4802093506],"type":"Point"}
}