{
  "type": "Feature",
  "properties": {
    "addr:full":"Phoenix Holistic Cntr, 31 Rowe St Woollahra NSW 2025",
    "addr:housenumber":"31",
    "addr:postcode":"2025",
    "addr:street":"Rowe St",
    "iso:country":"AU",
    "sg:address":"Phoenix Holistic Cntr, 31 Rowe St",
    "sg:city":"Woollahra",
    "sg:classifiers":[
        {
            "category":"Health Services",
            "subcategory":"Health Practitioner",
            "type":"Services"
        }
    ],
    "sg:phone":"+61 2 9386 1225",
    "sg:postcode":"2025",
    "sg:province":"NSW",
    "sg:tags":[
        "hypnotherapy"
    ],
    "wof:name":"Phillips-Moore Julie",
    "wof:placetype":"venue"
},
  "geometry": {"coordinates":[151.24851989699999,-33.8901329041],"type":"Point"}
}