{
  "type": "Feature",
  "properties": {
    "addr:full":"Jambin Rd Biloela QLD 4715",
    "addr:postcode":"4715",
    "addr:street":"Jambin Rd",
    "iso:country":"AU",
    "sg:address":"Jambin Rd",
    "sg:city":"Biloela",
    "sg:classifiers":[
        {
            "category":"Building & Trades",
            "subcategory":"Landscaping Services",
            "type":"Services"
        }
    ],
    "sg:phone":"+61 7 4995 3139",
    "sg:postcode":"4715",
    "sg:province":"QLD",
    "sg:tags":[
        "grazier"
    ],
    "wof:name":"Semple K H & R M",
    "wof:placetype":"venue"
},
  "geometry": {"coordinates":[150.51252746599999,-24.4025592804],"type":"Point"}
}