{
  "type": "Feature",
  "properties": {
    "addr:full":"Lot 44, Tramway Rd Morwell VIC 3840",
    "addr:postcode":"3840",
    "addr:street":"Tramway Rd",
    "iso:country":"AU",
    "sg:address":"Lot 44, Tramway Rd",
    "sg:city":"Morwell",
    "sg:classifiers":[
        {
            "category":"Commercial Area",
            "type":"Public Place"
        }
    ],
    "sg:phone":"+61 3 5133 9350",
    "sg:postcode":"3840",
    "sg:province":"VIC",
    "sg:tags":[
        "heavy",
        "carrier"
    ],
    "wof:name":"Hoepners Transport Group",
    "wof:placetype":"venue"
},
  "geometry": {"coordinates":[146.422607422,-38.2987518311],"type":"Point"}
}