{
  "type": "Feature",
  "properties": {
    "iso:country":"AU",
    "sg:address":"Swanbank Rd",
    "sg:city":"Maylands",
    "sg:classifiers":[
        {
            "category":"Retail",
            "subcategory":"Event Space",
            "type":"Services"
        }
    ],
    "sg:phone":"+61 8 9370 4090",
    "sg:postcode":"6051",
    "sg:province":"WA",
    "sg:tags":[
        "venue",
        "reception",
        "wedding"
    ],
    "wof:name":"Peninsula Golf Course",
    "wof:placetype":"venue"
},
  "geometry": {"coordinates":[115.902771,-31.939966],"type":"Point"}
}