{
  "type": "Feature",
  "properties": {
    "addr:full":"12 Toorak Park Ave Mermaid Waters QLD 4218",
    "addr:housenumber":"12",
    "addr:postcode":"4218",
    "addr:street":"Toorak Park Ave",
    "iso:country":"AU",
    "sg:address":"12 Toorak Park Ave",
    "sg:city":"Mermaid Waters",
    "sg:classifiers":[
        {
            "category":"Shopping",
            "subcategory":"Stationery & Office Supplies",
            "type":"Retail Goods"
        }
    ],
    "sg:phone":"+61 403 202 063",
    "sg:postcode":"4218",
    "sg:province":"QLD",
    "sg:tags":[
        "equipment",
        "display",
        "exhibition"
    ],
    "wof:name":"D.C. Creations",
    "wof:placetype":"venue"
},
  "geometry": {"coordinates":[153.435302734,-28.0571613312],"type":"Point"}
}