{
  "type": "Feature",
  "properties": {
    "addr:full":"6 Wimbledon Ave Elwood VIC 3184",
    "addr:housenumber":"6",
    "addr:postcode":"3184",
    "addr:street":"Wimbledon Ave",
    "iso:country":"AU",
    "sg:address":"6 Wimbledon Ave",
    "sg:city":"Elwood",
    "sg:classifiers":[
        {
            "category":"Health Services",
            "subcategory":"Doctor",
            "type":"Services"
        }
    ],
    "sg:phone":"+61 3 9531 2394",
    "sg:postcode":"3184",
    "sg:province":"VIC",
    "sg:tags":[
        "medical",
        "practitioner"
    ],
    "wof:name":"Lancaster D.J. & S.J.",
    "wof:placetype":"venue"
},
  "geometry": {"coordinates":[144.988677978,-37.8727798462],"type":"Point"}
}