{
  "type": "Feature",
  "properties": {
    "addr:full":"3 St James Mews Brighton VIC 3186",
    "addr:housenumber":"3",
    "addr:postcode":"3186",
    "addr:street":"St James Mews",
    "iso:country":"AU",
    "sg:address":"3 St James Mews",
    "sg:city":"Brighton",
    "sg:classifiers":[
        {
            "category":"Professional",
            "subcategory":"Business Services",
            "type":"Services"
        }
    ],
    "sg:phone":"+61 3 9596 1007",
    "sg:postcode":"3186",
    "sg:province":"VIC",
    "sg:tags":[
        "management",
        "event"
    ],
    "wof:name":"Event Matters",
    "wof:placetype":"venue"
},
  "geometry": {"coordinates":[144.997680664,-37.9021224976],"type":"Point"}
}