{
  "type": "Feature",
  "properties": {
    "iso:country":"AU",
    "sg:address":"Pacific Pde",
    "sg:city":"North Kirra",
    "sg:classifiers":[
        {
            "category":"Arena",
            "subcategory":"Sports Club",
            "type":"Entertainment"
        }
    ],
    "sg:phone":"+61 7 5536 2876",
    "sg:postcode":"4225",
    "sg:province":"QLD",
    "sg:tags":[
        "life",
        "surfing",
        "saving"
    ],
    "wof:name":"North Kirra S.L.S.C.",
    "wof:placetype":"venue"
},
  "geometry": {"coordinates":[153.52195739699999,-28.1657848358],"type":"Point"}
}