{
  "type": "Feature",
  "properties": {
    "addr:full":"624 Port Hacking Rd Caringbah NSW 2229",
    "addr:housenumber":"624",
    "addr:postcode":"2229",
    "addr:street":"Port Hacking Rd",
    "iso:country":"AU",
    "sg:address":"624 Port Hacking Rd",
    "sg:city":"Caringbah",
    "sg:classifiers":[
        {
            "category":"Building & Trades",
            "subcategory":"Construction",
            "type":"Services"
        }
    ],
    "sg:phone":"+61 407 256 346",
    "sg:postcode":"2229",
    "sg:province":"NSW",
    "sg:tags":[
        "contractor"
    ],
    "wof:name":"Peter Bova Building",
    "wof:placetype":"venue"
},
  "geometry": {"coordinates":[151.12374877900001,-34.0654373169],"type":"Point"}
}