{
  "type": "Feature",
  "properties": {
    "iso:country":"AU",
    "sg:address":"18 Second St",
    "sg:city":"Orroroo",
    "sg:classifiers":[
        {
            "category":"Food & Beverages",
            "subcategory":"Supermarket",
            "type":"Retail Goods"
        }
    ],
    "sg:phone":"+61 8 8658 1092",
    "sg:postcode":"5431",
    "sg:province":"SA",
    "sg:tags":[
        "grocery",
        "store"
    ],
    "wof:name":"Orroroo IGA Supermarket & Cafe",
    "wof:placetype":"venue"
},
  "geometry": {"coordinates":[138.61293029800001,-32.7340431213],"type":"Point"}
}