{
  "type": "Feature",
  "properties": {
    "addr:full":"Unit 4/ 125 Rockingham Rd Hamilton Hill WA 6163",
    "addr:housenumber":"/ 125",
    "addr:postcode":"6163",
    "addr:street":"Rockingham Rd",
    "iso:country":"AU",
    "sg:address":"Unit 4/ 125 Rockingham Rd",
    "sg:city":"Hamilton Hill",
    "sg:classifiers":[
        {
            "category":"Wholesale",
            "subcategory":"Auto Parts",
            "type":"Manufacturing & Wholesale Goods"
        }
    ],
    "sg:phone":"+61 8 9418 4121",
    "sg:postcode":"6163",
    "sg:province":"WA",
    "sg:tags":[
        "transmission",
        "automotive",
        "truck"
    ],
    "wof:name":"Performance Automatic Transmissions",
    "wof:placetype":"venue"
},
  "geometry": {"coordinates":[115.777496,-32.086662],"type":"Point"}
}