{
  "type": "Feature",
  "properties": {
    "iso:country":"AU",
    "sg:address":"Unit 2/ 24 Alexandra St",
    "sg:city":"Drummoyne",
    "sg:classifiers":[
        {
            "category":"Building & Trades",
            "subcategory":"Cleaning & Sanitation",
            "type":"Services"
        }
    ],
    "sg:phone":"+61 2 9181 1328",
    "sg:postcode":"2047",
    "sg:province":"NSW",
    "sg:tags":[
        "industrial",
        "commercial",
        "contractor"
    ],
    "wof:name":"A-1 Kepem Cleaning Services",
    "wof:placetype":"venue"
},
  "geometry": {"coordinates":[151.158981,-33.852589],"type":"Point"}
}