{
  "type": "Feature",
  "properties": {
    "addr:full":"145 Victoria Ave Albert Park VIC 3206",
    "addr:housenumber":"145",
    "addr:postcode":"3206",
    "addr:street":"Victoria Ave",
    "iso:country":"AU",
    "sg:address":"145 Victoria Ave",
    "sg:city":"Albert Park",
    "sg:classifiers":[
        {
            "category":"Retail",
            "subcategory":"Laundry & Dry Cleaning",
            "type":"Services"
        }
    ],
    "sg:phone":"+61 3 9699 6781",
    "sg:postcode":"3206",
    "sg:province":"VIC",
    "wof:name":"Wash Doctor Coin Laundry The",
    "wof:placetype":"venue"
},
  "geometry": {"coordinates":[144.94982899999999,-37.846066],"type":"Point"}
}