{
  "type": "Feature",
  "properties": {
    "iso:country":"AU",
    "sg:address":"145 Victoria Ave",
    "sg:city":"Albert Park",
    "sg:classifiers":[
        {
            "category":"Retail",
            "subcategory":"Laundry & Dry Cleaning",
            "type":"Services"
        }
    ],
    "sg:phone":"+61 3 9699 6781",
    "sg:postcode":"3206",
    "sg:province":"VIC",
    "wof:name":"Wash Doctor Coin Laundry The",
    "wof:placetype":"venue"
},
  "geometry": {"coordinates":[144.949829,-37.846066],"type":"Point"}
}