{
  "type": "Feature",
  "properties": {
    "addr:full":"14 Kirkpatrick Drv Ballarat VIC 3350",
    "addr:housenumber":"14",
    "addr:postcode":"3350",
    "addr:street":"Kirkpatrick Drv",
    "iso:country":"AU",
    "sg:address":"14 Kirkpatrick Drv",
    "sg:city":"Ballarat",
    "sg:classifiers":[
        {
            "category":"Professional",
            "subcategory":"Art Services",
            "type":"Services"
        }
    ],
    "sg:phone":"+61 3 5335 9060",
    "sg:postcode":"3350",
    "sg:province":"VIC",
    "sg:tags":[
        "decorator",
        "painter"
    ],
    "wof:name":"Holloways Painting Contractors Pty Ltd",
    "wof:placetype":"venue"
},
  "geometry": {"coordinates":[143.821045,-37.579681],"type":"Point"}
}