{
  "type": "Feature",
  "properties": {
    "addr:full":"Unit 3/ 143 Coreen Ave Penrith NSW 2750",
    "addr:housenumber":"/ 143",
    "addr:postcode":"2750",
    "addr:street":"Coreen Ave",
    "iso:country":"AU",
    "sg:address":"Unit 3/ 143 Coreen Ave",
    "sg:city":"Penrith",
    "sg:classifiers":[
        {
            "category":"Wholesale",
            "subcategory":"Scrap",
            "type":"Manufacturing & Wholesale Goods"
        }
    ],
    "sg:phone":"+61 2 4732 4033",
    "sg:postcode":"2750",
    "sg:province":"NSW",
    "sg:tags":[
        "merchant",
        "metal"
    ],
    "wof:name":"Top Dollars Metal Recyclers",
    "wof:placetype":"venue"
},
  "geometry": {"coordinates":[150.69433593799999,-33.743560791],"type":"Point"}
}