{
  "type": "Feature",
  "properties": {
    "addr:full":"6/ 13 Rodmay St Tuncurry NSW 2428",
    "addr:housenumber":"/ 13",
    "addr:postcode":"2428",
    "addr:street":"Rodmay St",
    "iso:country":"AU",
    "sg:address":"6/ 13 Rodmay St",
    "sg:city":"Tuncurry",
    "sg:classifiers":[
        {
            "category":"Farming",
            "subcategory":"Fish & Marine Products",
            "type":"Manufacturing & Wholesale Goods"
        }
    ],
    "sg:phone":"+61 2 6555 7414",
    "sg:postcode":"2428",
    "sg:province":"NSW",
    "sg:tags":[
        "production",
        "seafood",
        "processing"
    ],
    "wof:name":"Forster Fresh Seafoods",
    "wof:placetype":"venue"
},
  "geometry": {"coordinates":[152.49142499999999,-32.165287],"type":"Point"}
}