{
  "type": "Feature",
  "properties": {
    "addr:full":"Shellharbour Sq Shopng Cntr Lake Entrance Rd Shellharbour NSW 2529",
    "addr:postcode":"2529",
    "addr:street":"Shellharbour;Shopng;Rd",
    "iso:country":"AU",
    "sg:address":"Shellharbour Sq Shopng Cntr Lake Entrance Rd",
    "sg:city":"Shellharbour",
    "sg:classifiers":[
        {
            "category":"Insurance",
            "subcategory":"Hazard Insurance",
            "type":"Services"
        }
    ],
    "sg:phone":"+61 13 10 10",
    "sg:postcode":"2529",
    "sg:province":"NSW",
    "sg:tags":[
        "fire",
        "accident",
        "marine"
    ],
    "wof:name":"GIO General Ltd",
    "wof:placetype":"venue"
},
  "geometry": {"coordinates":[150.84370422399999,-34.55909729],"type":"Point"}
}