{
  "type": "Feature",
  "properties": {
    "iso:country":"AU",
    "sg:address":"34 Halgania Way",
    "sg:city":"Duncraig",
    "sg:classifiers":[
        {
            "category":"Professional",
            "subcategory":"Art Services",
            "type":"Services"
        }
    ],
    "sg:phone":"+61 417 145 315",
    "sg:postcode":"6023",
    "sg:province":"WA",
    "sg:tags":[
        "decorator",
        "painter"
    ],
    "wof:name":"Graham Iffla & Company",
    "wof:placetype":"venue"
},
  "geometry": {"coordinates":[115.78447723399999,-31.8436813354],"type":"Point"}
}