{
  "type": "Feature",
  "properties": {
    "addr:full":"10 Eagle St Brisbane QLD 4000",
    "addr:housenumber":"10",
    "addr:postcode":"4000",
    "addr:street":"Eagle St",
    "iso:country":"AU",
    "sg:address":"10 Eagle St",
    "sg:city":"Brisbane",
    "sg:classifiers":[
        {
            "category":"Professional",
            "subcategory":"Detective & Security Services",
            "type":"Services"
        }
    ],
    "sg:phone":"+61 1300 789 121",
    "sg:postcode":"4000",
    "sg:province":"QLD",
    "sg:tags":[
        "investigator"
    ],
    "wof:name":"A. AAABA Charlies Angels",
    "wof:placetype":"venue"
},
  "geometry": {"coordinates":[153.03001403799999,-27.4687213898],"type":"Point"}
}