{
  "type": "Feature",
  "properties": {
    "iso:country":"AU",
    "sg:address":"Unit 3 & 4 / 27 John St",
    "sg:city":"Telarah",
    "sg:classifiers":[
        {
            "category":"Organizations",
            "subcategory":"Community Association",
            "type":"Services"
        }
    ],
    "sg:phone":"+61 2 4932 5566",
    "sg:postcode":"2320",
    "sg:province":"NSW",
    "sg:tags":[
        "organisation",
        "family",
        "welfare"
    ],
    "wof:name":"Maitland Community Care Services Inc.",
    "wof:placetype":"venue"
},
  "geometry": {"coordinates":[151.53788757300001,-32.7252044678],"type":"Point"}
}