{
  "type": "Feature",
  "properties": {
    "addr:full":"25- 27 Park Way Braeside VIC 3195",
    "addr:housenumber":"27",
    "addr:postcode":"3195",
    "addr:street":"Way",
    "iso:country":"AU",
    "sg:address":"25- 27 Park Way",
    "sg:city":"Braeside",
    "sg:classifiers":[
        {
            "category":"Retail",
            "subcategory":"Laundry & Dry Cleaning",
            "type":"Services"
        }
    ],
    "sg:phone":"+61 3 9587 9500",
    "sg:postcode":"3195",
    "sg:province":"VIC",
    "wof:name":"Princes Laundry Services Pty Ltd",
    "wof:placetype":"venue"
},
  "geometry": {"coordinates":[145.12113952600001,-37.9987831116],"type":"Point"}
}