{
  "type": "Feature",
  "properties": {
    "addr:full":"80 Hope St Brunswick VIC 3056",
    "addr:housenumber":"80",
    "addr:postcode":"3056",
    "addr:street":"Hope St",
    "iso:country":"AU",
    "sg:address":"80 Hope St",
    "sg:city":"Brunswick",
    "sg:classifiers":[
        {
            "category":"Retail",
            "subcategory":"Auto Repair",
            "type":"Services"
        }
    ],
    "sg:phone":"+61 3 9387 7970",
    "sg:postcode":"3056",
    "sg:province":"VIC",
    "sg:tags":[
        "repairer",
        "motor",
        "engineer"
    ],
    "wof:name":"Headtrade",
    "wof:placetype":"venue"
},
  "geometry": {"coordinates":[144.95689392099999,-37.7634391785],"type":"Point"}
}