{
  "type": "Feature",
  "properties": {
    "addr:full":"78 Basnett St Chermside West QLD 4032",
    "addr:housenumber":"78",
    "addr:postcode":"4032",
    "addr:street":"Basnett St",
    "iso:country":"AU",
    "sg:address":"78 Basnett St",
    "sg:city":"Chermside West",
    "sg:classifiers":[
        {
            "category":"Food & Beverages",
            "subcategory":"Supermarket",
            "type":"Retail Goods"
        }
    ],
    "sg:phone":"+61 7 3359 4544",
    "sg:postcode":"4032",
    "sg:province":"QLD",
    "sg:tags":[
        "grocery",
        "store"
    ],
    "wof:name":"West Chermside Food Store",
    "wof:placetype":"venue"
},
  "geometry": {"coordinates":[153.01243600000001,-27.384182],"type":"Point"}
}