{
  "type": "Feature",
  "properties": {
    "iso:country":"AU",
    "sg:address":"65 Sutherland St",
    "sg:city":"Kilmore",
    "sg:classifiers":[
        {
            "category":"Social Services",
            "subcategory":"Child Care",
            "type":"Services"
        }
    ],
    "sg:phone":"+61 3 5781 1300",
    "sg:postcode":"3764",
    "sg:province":"VIC",
    "wof:name":"Sutherland St. Child Care & Kindergarten",
    "wof:placetype":"venue"
},
  "geometry": {"coordinates":[144.9478302,-37.303981781],"type":"Point"}
}