{
  "type": "Feature",
  "properties": {
    "addr:full":"50 Kellett St Potts Point NSW 2011",
    "addr:housenumber":"50",
    "addr:postcode":"2011",
    "addr:street":"Kellett St",
    "iso:country":"AU",
    "sg:address":"50 Kellett St",
    "sg:city":"Potts Point",
    "sg:classifiers":[
        {
            "category":"Personal",
            "subcategory":"Adult",
            "type":"Services"
        }
    ],
    "sg:phone":"+61 2 9380 2873",
    "sg:postcode":"2011",
    "sg:province":"NSW",
    "sg:tags":[
        "vic",
        "except",
        "state",
        "escort",
        "social",
        "qld"
    ],
    "wof:name":"Our Elegant Touch",
    "wof:placetype":"venue"
},
  "geometry": {"coordinates":[151.22430419899999,-33.8741493225],"type":"Point"}
}