{
  "type": "Feature",
  "properties": {
    "addr:full":"12 Invictus Crt Sale VIC 3850",
    "addr:housenumber":"12",
    "addr:postcode":"3850",
    "addr:street":"Invictus Crt",
    "iso:country":"AU",
    "sg:address":"12 Invictus Crt",
    "sg:city":"Sale",
    "sg:classifiers":[
        {
            "category":"Farming",
            "subcategory":"Dairy Farm",
            "type":"Manufacturing & Wholesale Goods"
        }
    ],
    "sg:phone":"+61 3 5144 2585",
    "sg:postcode":"3850",
    "sg:province":"VIC",
    "wof:name":"Somerville's Food Wholesaler",
    "wof:placetype":"venue"
},
  "geometry": {"coordinates":[147.08830261200001,-38.1025924683],"type":"Point"}
}