{
  "type": "Feature",
  "properties": {
    "addr:full":"25 Cotswold St Carina QLD 4152",
    "addr:housenumber":"25",
    "addr:postcode":"4152",
    "addr:street":"Cotswold St",
    "iso:country":"AU",
    "sg:address":"25 Cotswold St",
    "sg:city":"Carina",
    "sg:classifiers":[
        {
            "category":"Building & Trades",
            "subcategory":"Construction",
            "type":"Services"
        }
    ],
    "sg:phone":"+61 7 3398 3732",
    "sg:postcode":"4152",
    "sg:province":"QLD",
    "sg:tags":[
        "industrial",
        "commercial",
        "air conditioning"
    ],
    "wof:name":"Haven Building Products",
    "wof:placetype":"venue"
},
  "geometry": {"coordinates":[153.09342956500001,-27.4816322327],"type":"Point"}
}