{
  "type": "Feature",
  "properties": {
    "iso:country":"AU",
    "sg:address":"5 Hawke Drv",
    "sg:city":"Woolgoolga",
    "sg:classifiers":[
        {
            "category":"Social Services",
            "subcategory":"Adult Care",
            "type":"Services"
        }
    ],
    "sg:phone":"+61 2 6654 1578",
    "sg:postcode":"2456",
    "sg:province":"NSW",
    "sg:tags":[
        "towing"
    ],
    "wof:name":"Cooper Phil",
    "wof:placetype":"venue"
},
  "geometry": {"coordinates":[153.193161,-30.121841],"type":"Point"}
}