{
  "type": "Feature",
  "properties": {
    "iso:country":"AU",
    "sg:address":"78 High St",
    "sg:city":"Fremantle",
    "sg:classifiers":[
        {
            "category":"Health Services",
            "subcategory":"Health Practitioner",
            "type":"Services"
        }
    ],
    "sg:phone":"+61 8 9336 3222",
    "sg:postcode":"6160",
    "sg:province":"WA",
    "sg:tags":[
        "acupuncture"
    ],
    "wof:name":"Jacqueline Corner",
    "wof:placetype":"venue"
},
  "geometry": {"coordinates":[115.746002,-32.054489],"type":"Point"}
}