{
  "type": "Feature",
  "properties": {
    "addr:full":"57b Boundary Rd Dubbo NSW 2830",
    "addr:housenumber":"57b",
    "addr:postcode":"2830",
    "addr:street":"Boundary Rd",
    "iso:country":"AU",
    "sg:address":"57b Boundary Rd",
    "sg:city":"Dubbo",
    "sg:classifiers":[
        {
            "category":"Personal",
            "subcategory":"Beauty Salon",
            "type":"Services"
        }
    ],
    "sg:phone":"+61 2 6882 0942",
    "sg:postcode":"2830",
    "sg:province":"NSW",
    "sg:tags":[
        "hairdresser"
    ],
    "sg:website":"http://www.fuzehair.com.au",
    "wof:name":"Fuze",
    "wof:placetype":"venue"
},
  "geometry": {"coordinates":[148.605560303,-32.2672462463],"type":"Point"}
}