{
  "type": "Feature",
  "properties": {
    "addr:full":"7 Wilson St Burnie TAS 7320",
    "addr:housenumber":"7",
    "addr:postcode":"7320",
    "addr:street":"Wilson St",
    "iso:country":"AU",
    "sg:address":"7 Wilson St",
    "sg:city":"Burnie",
    "sg:classifiers":[
        {
            "category":"Shopping",
            "subcategory":"Computers & Home Electronics",
            "type":"Retail Goods"
        }
    ],
    "sg:phone":"+61 3 6432 3611",
    "sg:postcode":"7320",
    "sg:province":"TAS",
    "sg:tags":[
        "hi-fi",
        "equipment"
    ],
    "wof:name":"Burnie Sound & Visual",
    "wof:placetype":"venue"
},
  "geometry": {"coordinates":[145.90701300000001,-41.050476],"type":"Point"}
}