{
  "type": "Feature",
  "properties": {
    "iso:country":"AU",
    "sg:address":"41 Hampden Road,",
    "sg:city":"Battery Point",
    "sg:classifiers":[
        {
            "category":"Fast Food",
            "type":"Food & Drink"
        }
    ],
    "sg:phone":"+61 3 6223 4500",
    "sg:postcode":"7004",
    "sg:province":"TAS",
    "sg:tags":[
        "away",
        "take"
    ],
    "wof:name":"Magic Curries Indian Restaurant",
    "wof:placetype":"venue"
},
  "geometry": {"coordinates":[147.33457946799999,-42.8894462585],"type":"Point"}
}