{
  "type": "Feature",
  "properties": {
    "addr:full":"122 Elliot St Whyalla Playford SA 5600",
    "addr:housenumber":"122",
    "addr:postcode":"5600",
    "addr:street":"Elliot St",
    "iso:country":"AU",
    "sg:address":"122 Elliot St",
    "sg:city":"Whyalla Playford",
    "sg:classifiers":[
        {
            "category":"Health Services",
            "subcategory":"Chiropractor",
            "type":"Services"
        }
    ],
    "sg:phone":"+61 8 8645 0880",
    "sg:postcode":"5600",
    "sg:province":"SA",
    "wof:name":"A and A Access Chiropractic Centre",
    "wof:placetype":"venue"
},
  "geometry": {"coordinates":[137.564987,-33.02792],"type":"Point"}
}