{
  "type": "Feature",
  "properties": {
    "addr:full":"1665 Main Rd Nubeena TAS 7184",
    "addr:housenumber":"1665",
    "addr:postcode":"7184",
    "addr:street":"Main Rd",
    "iso:country":"AU",
    "sg:address":"1665 Main Rd",
    "sg:city":"Nubeena",
    "sg:classifiers":[
        {
            "category":"Personal",
            "subcategory":"Beauty Salon",
            "type":"Services"
        }
    ],
    "sg:phone":"+61 3 6250 1033",
    "sg:postcode":"7184",
    "sg:province":"TAS",
    "sg:tags":[
        "hairdresser"
    ],
    "wof:name":"Tj's Hair Studio",
    "wof:placetype":"venue"
},
  "geometry": {"coordinates":[147.742233,-43.100994],"type":"Point"}
}