{
  "type": "Feature",
  "properties": {
    "iso:country":"AU",
    "sg:address":"19 Angus Ave",
    "sg:city":"Epping",
    "sg:classifiers":[
        {
            "category":"Retail",
            "subcategory":"Repair Shop",
            "type":"Services"
        }
    ],
    "sg:phone":"+61 2 9876 3642",
    "sg:postcode":"2121",
    "sg:province":"NSW",
    "sg:tags":[
        "leadlights"
    ],
    "wof:name":"Arnaud Leadlight",
    "wof:placetype":"venue"
},
  "geometry": {"coordinates":[151.066040039,-33.7750587463],"type":"Point"}
}