{
  "type": "Feature",
  "properties": {
    "iso:country":"AU",
    "sg:address":"15 Alma Rd",
    "sg:city":"New Lambton",
    "sg:classifiers":[
        {
            "category":"Professional",
            "subcategory":"Computer Services",
            "type":"Services"
        }
    ],
    "sg:phone":"+61 2 4952 6611",
    "sg:postcode":"2305",
    "sg:province":"NSW",
    "sg:tags":[
        "information"
    ],
    "wof:name":"Hunter Media Monitoring",
    "wof:placetype":"venue"
},
  "geometry": {"coordinates":[151.714508,-32.92205],"type":"Point"}
}