{
  "type": "Feature",
  "properties": {
    "addr:full":"91 Gascoigne St Kingswood NSW 2747",
    "addr:housenumber":"91",
    "addr:postcode":"2747",
    "addr:street":"Gascoigne St",
    "iso:country":"AU",
    "sg:address":"91 Gascoigne St",
    "sg:city":"Kingswood",
    "sg:classifiers":[
        {
            "category":"Building & Trades",
            "subcategory":"Construction",
            "type":"Services"
        }
    ],
    "sg:phone":"+61 2 4721 8328",
    "sg:postcode":"2747",
    "sg:province":"NSW",
    "sg:tags":[
        "fencing",
        "contractor"
    ],
    "wof:name":"Penrith Wrought Iron",
    "wof:placetype":"venue"
},
  "geometry": {"coordinates":[150.71766662600001,-33.7533302307],"type":"Point"}
}