{
  "type": "Feature",
  "properties": {
    "addr:full":"897 Pacific Hwy Pymble NSW 2073",
    "addr:housenumber":"897",
    "addr:postcode":"2073",
    "addr:street":"Pacific Hwy",
    "iso:country":"AU",
    "sg:address":"897 Pacific Hwy",
    "sg:city":"Pymble",
    "sg:classifiers":[
        {
            "category":"Real Estate",
            "subcategory":"Architect",
            "type":"Services"
        }
    ],
    "sg:phone":"+61 2 9440 2304",
    "sg:postcode":"2073",
    "sg:province":"NSW",
    "wof:name":"Horizon Project Solutions",
    "wof:placetype":"venue"
},
  "geometry": {"coordinates":[151.145385742,-33.7470779419],"type":"Point"}
}