{
  "type": "Feature",
  "properties": {
    "addr:full":"PO Box 6 Happy Valley SA 5159",
    "addr:postcode":"5159",
    "iso:country":"AU",
    "sg:address":"PO Box 6",
    "sg:city":"Happy Valley",
    "sg:classifiers":[
        {
            "category":"Home & Garden",
            "subcategory":"Building Materials",
            "type":"Retail Goods"
        }
    ],
    "sg:phone":"+61 1800 243 332",
    "sg:postcode":"5159",
    "sg:province":"SA",
    "sg:tags":[
        "shutter",
        "roller",
        "grille"
    ],
    "wof:name":"A. Able Blinds",
    "wof:placetype":"venue"
},
  "geometry": {"coordinates":[138.57586669899999,-35.0831108093],"type":"Point"}
}