{
  "type": "Feature",
  "properties": {
    "addr:full":"417 Sturt St Ballarat VIC 3350",
    "addr:housenumber":"417",
    "addr:postcode":"3350",
    "addr:street":"Sturt St",
    "iso:country":"AU",
    "sg:address":"417 Sturt St",
    "sg:city":"Ballarat",
    "sg:classifiers":[
        {
            "category":"Shopping",
            "subcategory":"Music",
            "type":"Retail Goods"
        }
    ],
    "sg:phone":"+61 3 5333 1789",
    "sg:postcode":"3350",
    "sg:province":"VIC",
    "sg:tags":[
        "store"
    ],
    "wof:name":"Black Swan CD's",
    "wof:placetype":"venue"
},
  "geometry": {"coordinates":[143.85389699999999,-37.561806],"type":"Point"}
}