{
  "type": "Feature",
  "properties": {
    "addr:full":"561 Botany Rd Waterloo NSW 2017",
    "addr:housenumber":"561",
    "addr:postcode":"2017",
    "addr:street":"Botany Rd",
    "iso:country":"AU",
    "sg:address":"561 Botany Rd",
    "sg:city":"Waterloo",
    "sg:classifiers":[
        {
            "category":"Health Services",
            "subcategory":"Doctor",
            "type":"Services"
        }
    ],
    "sg:phone":"+61 2 9319 5999",
    "sg:postcode":"2017",
    "sg:province":"NSW",
    "sg:tags":[
        "occupational",
        "safety"
    ],
    "wof:name":"Immex",
    "wof:placetype":"venue"
},
  "geometry": {"coordinates":[151.20257568400001,-33.9100341797],"type":"Point"}
}