{
  "type": "Feature",
  "properties": {
    "addr:full":"68 Ollier Crs Prospect NSW 2148",
    "addr:housenumber":"68",
    "addr:postcode":"2148",
    "addr:street":"Ollier Crs",
    "iso:country":"AU",
    "sg:address":"68 Ollier Crs",
    "sg:city":"Prospect",
    "sg:classifiers":[
        {
            "category":"Retail",
            "subcategory":"Storage",
            "type":"Services"
        }
    ],
    "sg:phone":"+61 2 9831 7308",
    "sg:postcode":"2148",
    "sg:province":"NSW",
    "sg:tags":[
        "removal",
        "furniture"
    ],
    "wof:name":"P & D Distribution",
    "wof:placetype":"venue"
},
  "geometry": {"coordinates":[150.91659545900001,-33.8005409241],"type":"Point"}
}