{
  "type": "Feature",
  "properties": {
    "iso:country":"AU",
    "sg:address":"Ste12 51-55 City Rd",
    "sg:city":"Southbank",
    "sg:classifiers":[
        {
            "category":"Real Estate",
            "subcategory":"Developer",
            "type":"Services"
        }
    ],
    "sg:phone":"+61 3 9645 0330",
    "sg:postcode":"3006",
    "sg:province":"VIC",
    "sg:tags":[
        "development"
    ],
    "wof:name":"J.L.R. Property Group Pty Ltd",
    "wof:placetype":"venue"
},
  "geometry": {"coordinates":[144.96621704099999,-37.8218078613],"type":"Point"}
}