{
  "type": "Feature",
  "properties": {
    "addr:full":"61 Sharp St Cooma NSW 2630",
    "addr:housenumber":"61",
    "addr:postcode":"2630",
    "addr:street":"Sharp St",
    "iso:country":"AU",
    "sg:address":"61 Sharp St",
    "sg:city":"Cooma",
    "sg:classifiers":[
        {
            "category":"Retail",
            "subcategory":"Auto Repair",
            "type":"Services"
        }
    ],
    "sg:phone":"+61 2 6452 4211",
    "sg:postcode":"2630",
    "sg:province":"NSW",
    "sg:tags":[
        "repairer",
        "motor",
        "engineer"
    ],
    "wof:name":"Highland Motors",
    "wof:placetype":"venue"
},
  "geometry": {"coordinates":[149.13395690900001,-36.2314414978],"type":"Point"}
}