{
  "type": "Feature",
  "properties": {
    "addr:full":"235 Sinnamon Rd Jindalee QLD 4074",
    "addr:housenumber":"235",
    "addr:postcode":"4074",
    "addr:street":"Sinnamon Rd",
    "iso:country":"AU",
    "sg:address":"235 Sinnamon Rd",
    "sg:city":"Jindalee",
    "sg:classifiers":[
        {
            "category":"Food & Beverages",
            "subcategory":"Bakery",
            "type":"Retail Goods"
        }
    ],
    "sg:phone":"+61 7 3279 5888",
    "sg:postcode":"4074",
    "sg:province":"QLD",
    "sg:tags":[
        "baker"
    ],
    "wof:name":"Allsports Bakery",
    "wof:placetype":"venue"
},
  "geometry": {"coordinates":[152.94418335,-27.5318374634],"type":"Point"}
}