{
  "type": "Feature",
  "properties": {
    "addr:full":"9 Kimberley Rd Burleigh Gardens QLD 4220",
    "addr:housenumber":"9",
    "addr:postcode":"4220",
    "addr:street":"Kimberley Rd",
    "iso:country":"AU",
    "sg:address":"9 Kimberley Rd",
    "sg:city":"Burleigh Gardens",
    "sg:classifiers":[
        {
            "category":"Building & Trades",
            "subcategory":"Equipment Rental",
            "type":"Services"
        }
    ],
    "sg:phone":"+61 7 5593 4688",
    "sg:postcode":"4220",
    "sg:province":"QLD",
    "sg:tags":[
        "crane",
        "hire"
    ],
    "sg:website":"http://www.goldcoastcranes.com.au",
    "wof:name":"Gold Coast Cranes",
    "wof:placetype":"venue"
},
  "geometry": {"coordinates":[153.41354370100001,-28.1056747437],"type":"Point"}
}