{
  "type": "Feature",
  "properties": {
    "addr:full":"Head Office Australia 2 Redwood Drv Notting Hill VIC 3168",
    "addr:housenumber":"2",
    "addr:postcode":"3168",
    "addr:street":"Redwood Drv",
    "iso:country":"AU",
    "sg:address":"Head Office Australia 2 Redwood Drv",
    "sg:city":"Notting Hill",
    "sg:classifiers":[
        {
            "category":"Manufacturing",
            "subcategory":"Retail Goods",
            "type":"Manufacturing & Wholesale Goods"
        }
    ],
    "sg:phone":"+61 1800 664 266",
    "sg:postcode":"3168",
    "sg:province":"VIC",
    "sg:tags":[
        "merchant",
        "pump",
        "mfrs"
    ],
    "wof:name":"Onga",
    "wof:placetype":"venue"
},
  "geometry": {"coordinates":[145.13230895999999,-37.9033927917],"type":"Point"}
}