{
  "type": "Feature",
  "properties": {
    "iso:country":"AU",
    "sg:address":"PO Box 3106",
    "sg:city":"North Mackay",
    "sg:classifiers":[
        {
            "category":"Retail",
            "subcategory":"Driving School",
            "type":"Services"
        }
    ],
    "sg:phone":"+61 7 4955 5244",
    "sg:postcode":"4740",
    "sg:province":"QLD",
    "wof:name":"Mackay Driving School",
    "wof:placetype":"venue"
},
  "geometry": {"coordinates":[149.18261699999999,-21.123739],"type":"Point"}
}