{
  "type": "Feature",
  "properties": {
    "iso:country":"AU",
    "sg:address":"43 Danfield Drv",
    "sg:city":"Tarneit",
    "sg:classifiers":[
        {
            "category":"Building & Trades",
            "subcategory":"Construction",
            "type":"Services"
        }
    ],
    "sg:phone":"+61 488 188 804",
    "sg:postcode":"3029",
    "sg:province":"VIC",
    "sg:tags":[
        "window",
        "tinting"
    ],
    "sg:website":"http://www.tintshield.com.au",
    "wof:name":"Tint Shield",
    "wof:placetype":"venue"
},
  "geometry": {"coordinates":[144.673065,-37.844242],"type":"Point"}
}