{
  "type": "Feature",
  "properties": {
    "addr:full":"Shp 21b/ 1097 Barrenjoey Rd Palm Beach NSW 2108",
    "addr:housenumber":"21b / 1097",
    "addr:postcode":"2108",
    "addr:street":"Barrenjoey Rd",
    "iso:country":"AU",
    "sg:address":"Shp 21b/ 1097 Barrenjoey Rd",
    "sg:city":"Palm Beach",
    "sg:classifiers":[
        {
            "category":"Cafe",
            "type":"Food & Drink"
        }
    ],
    "sg:phone":"+61 2 9974 5724",
    "sg:postcode":"2108",
    "sg:province":"NSW",
    "wof:name":"Seasoned Cafe",
    "wof:placetype":"venue"
},
  "geometry": {"coordinates":[151.31904602,-33.5997467041],"type":"Point"}
}