{
  "type": "Feature",
  "properties": {
    "addr:full":"36 Maloney Drv Wodonga VIC 3690",
    "addr:housenumber":"36",
    "addr:postcode":"3690",
    "addr:street":"Maloney Drv",
    "iso:country":"AU",
    "sg:address":"36 Maloney Drv",
    "sg:city":"Wodonga",
    "sg:classifiers":[
        {
            "category":"Manufacturing",
            "subcategory":"Paper Products",
            "type":"Manufacturing & Wholesale Goods"
        }
    ],
    "sg:phone":"+61 2 6056 1588",
    "sg:postcode":"3690",
    "sg:province":"VIC",
    "sg:tags":[
        "tube",
        "cardboard"
    ],
    "wof:name":"Sonoco Australia Pty Ltd",
    "wof:placetype":"venue"
},
  "geometry": {"coordinates":[146.853240967,-36.1040649414],"type":"Point"}
}