{
  "type": "Feature",
  "properties": {
    "addr:full":"U8a/ 10-12 Woodville St Hurstville NSW 2220",
    "addr:housenumber":"10-12",
    "addr:postcode":"2220",
    "addr:street":"Woodville St",
    "iso:country":"AU",
    "sg:address":"U8a/ 10-12 Woodville St",
    "sg:city":"Hurstville",
    "sg:classifiers":[
        {
            "category":"Banks & Credit Unions",
            "subcategory":"Financial Services",
            "type":"Services"
        }
    ],
    "sg:phone":"+61 2 9586 4978",
    "sg:postcode":"2220",
    "sg:province":"NSW",
    "sg:tags":[
        "loan",
        "finance",
        "mortgage"
    ],
    "wof:name":"Turvey Holdings Pty Ltd",
    "wof:placetype":"venue"
},
  "geometry": {"coordinates":[151.103393555,-33.9650306702],"type":"Point"}
}