{
  "type": "Feature",
  "properties": {
    "iso:country":"AU",
    "sg:address":"Cnr Alice & Rocky Sts",
    "sg:city":"Maryborough",
    "sg:classifiers":[
        {
            "category":"Autos & Motor Vehicles",
            "subcategory":"Fuel & Gas Station",
            "type":"Retail Goods"
        }
    ],
    "sg:phone":"+61 7 4121 3876",
    "sg:postcode":"4650",
    "sg:province":"QLD",
    "wof:name":"Astron Service Station",
    "wof:placetype":"venue"
},
  "geometry": {"coordinates":[152.69215399999999,-25.535246],"type":"Point"}
}