{
  "type": "Feature",
  "properties": {
    "addr:full":"70 Lower Heidelberg Rd Ivanhoe VIC 3079",
    "addr:housenumber":"70",
    "addr:postcode":"3079",
    "addr:street":"Lower Heidelberg Rd",
    "iso:country":"AU",
    "sg:address":"70 Lower Heidelberg Rd",
    "sg:city":"Ivanhoe",
    "sg:classifiers":[
        {
            "category":"Personal",
            "subcategory":"Beauty Salon",
            "type":"Services"
        }
    ],
    "sg:phone":"+61 3 9497 5100",
    "sg:postcode":"3079",
    "sg:province":"VIC",
    "wof:name":"Sync- detoxify-nourish-regenerate",
    "wof:placetype":"venue"
},
  "geometry": {"coordinates":[145.04623413100001,-37.7719497681],"type":"Point"}
}