{
  "type": "Feature",
  "properties": {
    "addr:full":"Dann St Campbells Creek VIC 3451",
    "addr:postcode":"3451",
    "addr:street":"Dann St",
    "iso:country":"AU",
    "sg:address":"Dann St",
    "sg:city":"Campbells Creek",
    "sg:classifiers":[
        {
            "category":"Building & Trades",
            "subcategory":"Construction",
            "type":"Services"
        }
    ],
    "sg:phone":"+61 3 5472 2935",
    "sg:postcode":"3451",
    "sg:province":"VIC",
    "sg:tags":[
        "contractor"
    ],
    "wof:name":"I & S Landsborough",
    "wof:placetype":"venue"
},
  "geometry": {"coordinates":[144.194381714,-37.0892295837],"type":"Point"}
}