{
  "type": "Feature",
  "properties": {
    "addr:full":"Albany Hwy Maddington WA 6109",
    "addr:postcode":"6109",
    "addr:street":"Albany Hwy",
    "iso:country":"AU",
    "sg:address":"Albany Hwy",
    "sg:city":"Maddington",
    "sg:classifiers":[
        {
            "category":"Shopping",
            "subcategory":"Computers & Home Electronics",
            "type":"Retail Goods"
        }
    ],
    "sg:phone":"+61 417 175 409",
    "sg:postcode":"6109",
    "sg:province":"WA",
    "sg:tags":[
        "small",
        "equipment",
        "business"
    ],
    "wof:name":"At Home Computer Shop Metro",
    "wof:placetype":"venue"
},
  "geometry": {"coordinates":[115.98346710200001,-32.050819397],"type":"Point"}
}