{
  "type": "Feature",
  "properties": {
    "iso:country":"AU",
    "sg:address":"1 Short St",
    "sg:city":"Airport West",
    "sg:classifiers":[
        {
            "category":"Utilities",
            "subcategory":"Mobile Phone",
            "type":"Services"
        }
    ],
    "sg:phone":"+61 3 9374 2893",
    "sg:postcode":"3042",
    "sg:province":"VIC",
    "sg:tags":[
        "aviation",
        "consultant"
    ],
    "wof:name":"Aerofuels Essendon Pty Ltd",
    "wof:placetype":"venue"
},
  "geometry": {"coordinates":[144.87289428700001,-37.7464981079],"type":"Point"}
}