{
  "type": "Feature",
  "properties": {
    "iso:country":"AU",
    "sg:address":"503 Kangaroo Valley Rd",
    "sg:city":"Berry",
    "sg:classifiers":[
        {
            "category":"Health Services",
            "subcategory":"Health Practitioner",
            "type":"Services"
        }
    ],
    "sg:phone":"+61 2 4464 1060",
    "sg:postcode":"2535",
    "sg:province":"NSW",
    "sg:tags":[
        "naturopath"
    ],
    "wof:name":"Lauren Cunio",
    "wof:placetype":"venue"
},
  "geometry": {"coordinates":[150.68371582,-34.7714118958],"type":"Point"}
}