{
  "type": "Feature",
  "properties": {
    "iso:country":"AU",
    "sg:address":"50 Marine Tce",
    "sg:city":"Burnie",
    "sg:classifiers":[
        {
            "category":"Insurance",
            "subcategory":"Health Insurance",
            "type":"Services"
        }
    ],
    "sg:phone":"+61 3 6432 1199",
    "sg:postcode":"7320",
    "sg:province":"TAS",
    "sg:website":"http://www.hciltd.com.au",
    "wof:name":"Health Care Insurance",
    "wof:placetype":"venue"
},
  "geometry": {"coordinates":[145.89825400000001,-41.075859],"type":"Point"}
}