{
  "type": "Feature",
  "properties": {
    "iso:country":"AU",
    "sg:address":"Lot 83 13 Jenmark Pl",
    "sg:city":"Dubbo",
    "sg:classifiers":[
        {
            "category":"Home & Garden",
            "subcategory":"Building Materials",
            "type":"Retail Goods"
        }
    ],
    "sg:phone":"+61 13 31 66",
    "sg:postcode":"2830",
    "sg:province":"NSW",
    "sg:tags":[
        "fire",
        "resistant",
        "supply"
    ],
    "wof:name":"Wormald",
    "wof:placetype":"venue"
},
  "geometry": {"coordinates":[148.631958008,-32.2490386963],"type":"Point"}
}