{
  "type": "Feature",
  "properties": {
    "iso:country":"AU",
    "sg:address":"50- 52 Fitzmaurice St",
    "sg:city":"Wagga Wagga",
    "sg:classifiers":[
        {
            "category":"Organizations",
            "subcategory":"Labor Organization",
            "type":"Services"
        }
    ],
    "sg:phone":"+61 2 6931 7688",
    "sg:postcode":"2650",
    "sg:province":"NSW",
    "sg:tags":[
        "union"
    ],
    "wof:name":"Transport Workers&#039; Union Of Australia (NSW Branch)",
    "wof:placetype":"venue"
},
  "geometry": {"coordinates":[147.36988830600001,-35.1065139771],"type":"Point"}
}