{
  "type": "Feature",
  "properties": {
    "addr:full":"Peel St Tamworth NSW 2340",
    "addr:postcode":"2340",
    "addr:street":"Peel St",
    "iso:country":"AU",
    "sg:address":"Peel St",
    "sg:city":"Tamworth",
    "sg:classifiers":[
        {
            "category":"Professional",
            "subcategory":"Art Services",
            "type":"Services"
        }
    ],
    "sg:phone":"+61 2 6766 7274",
    "sg:postcode":"2340",
    "sg:province":"NSW",
    "sg:tags":[
        "graphic",
        "designer"
    ],
    "wof:name":"Redline Design",
    "wof:placetype":"venue"
},
  "geometry": {"coordinates":[150.93011474599999,-31.0908851624],"type":"Point"}
}