{
  "type": "Feature",
  "properties": {
    "iso:country":"AU",
    "sg:address":"Shop 283, Penrith Plaza Jane St",
    "sg:city":"Penrith",
    "sg:classifiers":[
        {
            "category":"Shopping",
            "subcategory":"Shoes",
            "type":"Retail Goods"
        }
    ],
    "sg:phone":"+61 2 4732 5111",
    "sg:postcode":"2740",
    "sg:province":"NSW",
    "sg:tags":[
        "footwear"
    ],
    "wof:name":"Diana Ferrari",
    "wof:placetype":"venue"
},
  "geometry": {"coordinates":[150.69517500000001,-33.750534],"type":"Point"}
}