{
  "type": "Feature",
  "properties": {
    "addr:full":"101 Brighton Rd Sandgate QLD 4017",
    "addr:housenumber":"101",
    "addr:postcode":"4017",
    "addr:street":"Brighton Rd",
    "iso:country":"AU",
    "sg:address":"101 Brighton Rd",
    "sg:city":"Sandgate",
    "sg:classifiers":[
        {
            "category":"Banks & Credit Unions",
            "subcategory":"Bank",
            "type":"Services"
        }
    ],
    "sg:phone":"+61 13 20 32",
    "sg:postcode":"4017",
    "sg:province":"QLD",
    "wof:name":"Westpac",
    "wof:placetype":"venue"
},
  "geometry": {"coordinates":[153.068191528,-27.318189621],"type":"Point"}
}