{
  "type": "Feature",
  "properties": {
    "addr:full":"PO Box 2010 Woden ACT 2606",
    "addr:postcode":"2606",
    "iso:country":"AU",
    "sg:address":"PO Box 2010",
    "sg:city":"Woden",
    "sg:classifiers":[
        {
            "category":"Professional",
            "subcategory":"Printing & Photocopies",
            "type":"Services"
        }
    ],
    "sg:phone":"+61 2 6281 6281",
    "sg:postcode":"2606",
    "sg:province":"ACT",
    "sg:tags":[
        "publishing",
        "desktop"
    ],
    "wof:name":"Add Apt Graphics",
    "wof:placetype":"venue"
},
  "geometry": {"coordinates":[149.081420898,-35.3464202881],"type":"Point"}
}