{
  "type": "Feature",
  "properties": {
    "iso:country":"AU",
    "sg:address":"100 Keys Rd",
    "sg:city":"Keysborough",
    "sg:classifiers":[
        {
            "category":"Building & Trades",
            "subcategory":"Landscaping Services",
            "type":"Services"
        }
    ],
    "sg:phone":"+61 448 800 952",
    "sg:postcode":"3173",
    "sg:province":"VIC",
    "sg:tags":[
        "designer",
        "landscape",
        "contractor"
    ],
    "wof:name":"S E Garden Creations",
    "wof:placetype":"venue"
},
  "geometry": {"coordinates":[145.17013549800001,-38.0233001709],"type":"Point"}
}