{
  "type": "Feature",
  "properties": {
    "iso:country":"AU",
    "sg:address":"PO Box 1159",
    "sg:city":"Canning Bridge",
    "sg:classifiers":[
        {
            "category":"Communications",
            "type":"Services"
        }
    ],
    "sg:phone":"+61 1800 133 750",
    "sg:postcode":"6153",
    "sg:province":"WA",
    "sg:tags":[
        "equipment",
        "radio"
    ],
    "wof:name":"Comsource International",
    "wof:placetype":"venue"
},
  "geometry": {"coordinates":[115.852959,-32.011127],"type":"Point"}
}