{
  "type": "Feature",
  "properties": {
    "addr:full":"Shop 7, 62 Islander Rd Hervey Bay QLD 4655",
    "addr:housenumber":"shop;62",
    "addr:postcode":"4655",
    "addr:street":"Islander Rd",
    "iso:country":"AU",
    "sg:address":"Shop 7, 62 Islander Rd",
    "sg:city":"Hervey Bay",
    "sg:classifiers":[
        {
            "category":"Home & Garden",
            "subcategory":"Building Materials",
            "type":"Retail Goods"
        }
    ],
    "sg:phone":"+61 7 4124 1956",
    "sg:postcode":"4655",
    "sg:province":"QLD",
    "sg:tags":[
        "fitting",
        "door"
    ],
    "wof:name":"Good Look Garage Doors",
    "wof:placetype":"venue"
},
  "geometry": {"coordinates":[152.83149700000001,-25.285177],"type":"Point"}
}