{
  "type": "Feature",
  "properties": {
    "iso:country":"AU",
    "sg:address":"93a Young St",
    "sg:city":"Carrington",
    "sg:classifiers":[
        {
            "category":"Professional",
            "subcategory":"Accounting & Tax Preparation",
            "type":"Services"
        }
    ],
    "sg:phone":"+61 2 4969 6266",
    "sg:postcode":"2294",
    "sg:province":"NSW",
    "sg:tags":[
        "consultant",
        "taxation"
    ],
    "wof:name":"Lawrence Rundle Rapson Pty Ltd",
    "wof:placetype":"venue"
},
  "geometry": {"coordinates":[151.765335083,-32.914981842],"type":"Point"}
}