{
  "type": "Feature",
  "properties": {
    "iso:country":"AU",
    "sg:address":"19 Cobia Vis",
    "sg:city":"Yanchep",
    "sg:classifiers":[
        {
            "category":"Professional",
            "subcategory":"Art Services",
            "type":"Services"
        }
    ],
    "sg:phone":"+61 8 9561 1260",
    "sg:postcode":"6035",
    "sg:province":"WA",
    "sg:tags":[
        "decorator",
        "painter"
    ],
    "wof:name":"Yanchep Painting Service",
    "wof:placetype":"venue"
},
  "geometry": {"coordinates":[115.64997100799999,-31.5447807312],"type":"Point"}
}