{
  "type": "Feature",
  "properties": {
    "iso:country":"AU",
    "sg:address":"26B Dickens St",
    "sg:city":"St Kilda",
    "sg:classifiers":[
        {
            "category":"Health Services",
            "subcategory":"Doctor",
            "type":"Services"
        }
    ],
    "sg:phone":"+61 3 9525 5388",
    "sg:postcode":"3182",
    "sg:province":"VIC",
    "sg:tags":[
        "medical",
        "practitioner"
    ],
    "wof:name":"Womens Day Centre",
    "wof:placetype":"venue"
},
  "geometry": {"coordinates":[144.98208618199999,-37.8731803894],"type":"Point"}
}