{
  "type": "Feature",
  "properties": {
    "addr:full":"Lot 1 Males Rd Moorooduc VIC 3933",
    "addr:postcode":"3933",
    "addr:street":"Males Rd",
    "iso:country":"AU",
    "sg:address":"Lot 1 Males Rd",
    "sg:city":"Moorooduc",
    "sg:classifiers":[
        {
            "category":"Building & Trades",
            "subcategory":"Construction",
            "type":"Services"
        }
    ],
    "sg:phone":"+61 3 5978 8446",
    "sg:postcode":"3933",
    "sg:province":"VIC",
    "sg:tags":[
        "fencing",
        "contractor"
    ],
    "wof:name":"Allen Leigh",
    "wof:placetype":"venue"
},
  "geometry": {"coordinates":[145.096893311,-38.2600250244],"type":"Point"}
}