{
  "type": "Feature",
  "properties": {
    "iso:country":"AU",
    "sg:address":"1 Carinish Rd",
    "sg:city":"Oakleigh South",
    "sg:classifiers":[
        {
            "category":"Wholesale",
            "subcategory":"Medical Equipment & Supplies",
            "type":"Manufacturing & Wholesale Goods"
        }
    ],
    "sg:phone":"+61 3 9540 0199",
    "sg:postcode":"3167",
    "sg:province":"VIC",
    "sg:tags":[
        "aid",
        "care",
        "health",
        "home"
    ],
    "wof:name":"Health Care At Home Pty Ltd",
    "wof:placetype":"venue"
},
  "geometry": {"coordinates":[145.10794067399999,-37.9145927429],"type":"Point"}
}