{
  "type": "Feature",
  "properties": {
    "addr:full":"Lvl 1, 281 Bay St Brighton-le-Sands NSW 2216",
    "addr:housenumber":"281",
    "addr:postcode":"2216",
    "addr:street":"Bay St",
    "iso:country":"AU",
    "sg:address":"Lvl 1, 281 Bay St",
    "sg:city":"Brighton-le-Sands",
    "sg:classifiers":[
        {
            "category":"Professional",
            "subcategory":"Accounting & Tax Preparation",
            "type":"Services"
        }
    ],
    "sg:phone":"+61 2 9556 2555",
    "sg:postcode":"2216",
    "sg:province":"NSW",
    "sg:tags":[
        "consultant",
        "taxation"
    ],
    "wof:name":"H&R Block",
    "wof:placetype":"venue"
},
  "geometry": {"coordinates":[151.153503,-33.959866],"type":"Point"}
}