{
  "type": "Feature",
  "properties": {
    "iso:country":"AU",
    "sg:address":"Stowe Rd",
    "sg:city":"Calliope",
    "sg:classifiers":[
        {
            "category":"Sports & Exercise",
            "subcategory":"Golf",
            "type":"Entertainment"
        }
    ],
    "sg:phone":"+61 7 4975 7454",
    "sg:postcode":"4680",
    "sg:province":"QLD",
    "sg:tags":[
        "club"
    ],
    "wof:name":"Calliope Country Club",
    "wof:placetype":"venue"
},
  "geometry": {"coordinates":[151.193481445,-24.0018119812],"type":"Point"}
}