{
  "type": "Feature",
  "properties": {
    "addr:full":"Suite 5, Calley Professional Centre. Calley Dve (Cnr South St) Leeming WA 6149",
    "addr:postcode":"6149",
    "addr:street":"Calley Dve Cnr South St",
    "iso:country":"AU",
    "sg:address":"Suite 5, Calley Professional Centre. Calley Dve (Cnr South St)",
    "sg:city":"Leeming",
    "sg:classifiers":[
        {
            "category":"Banks & Credit Unions",
            "subcategory":"Financial Services",
            "type":"Services"
        }
    ],
    "sg:phone":"+61 8 9332 5088",
    "sg:postcode":"6149",
    "sg:province":"WA",
    "sg:tags":[
        "settlement",
        "nt",
        "agent",
        "wa"
    ],
    "wof:name":"Prestige Settlements",
    "wof:placetype":"venue"
},
  "geometry": {"coordinates":[115.85244,-32.073669],"type":"Point"}
}