{
  "type": "Feature",
  "properties": {
    "iso:country":"AU",
    "sg:address":"100 Station Rd",
    "sg:city":"Seven Hills",
    "sg:classifiers":[
        {
            "category":"Shopping",
            "subcategory":"Computers & Home Electronics",
            "type":"Retail Goods"
        }
    ],
    "sg:phone":"+61 417 733 370",
    "sg:postcode":"2147",
    "sg:province":"NSW",
    "sg:tags":[
        "hardware",
        "equipment"
    ],
    "wof:name":"Laptop - World",
    "wof:placetype":"venue"
},
  "geometry": {"coordinates":[150.944625855,-33.7753295898],"type":"Point"}
}