{
  "type": "Feature",
  "properties": {
    "addr:full":"Paternoster Rd Cockatoo VIC 3781",
    "addr:postcode":"3781",
    "addr:street":"Paternoster Rd",
    "iso:country":"AU",
    "sg:address":"Paternoster Rd",
    "sg:city":"Cockatoo",
    "sg:classifiers":[
        {
            "category":"Farming",
            "subcategory":"Farm",
            "type":"Manufacturing & Wholesale Goods"
        }
    ],
    "sg:phone":"+61 3 5968 8184",
    "sg:postcode":"3781",
    "sg:province":"VIC",
    "sg:tags":[
        "farmer"
    ],
    "wof:name":"Coniglione R",
    "wof:placetype":"venue"
},
  "geometry": {"coordinates":[145.479477,-37.945271],"type":"Point"}
}