{
  "type": "Feature",
  "properties": {
    "addr:full":"Campbell St Euroa VIC 3666",
    "addr:postcode":"3666",
    "addr:street":"St",
    "iso:country":"AU",
    "sg:address":"Campbell St",
    "sg:city":"Euroa",
    "sg:classifiers":[
        {
            "category":"Education",
            "subcategory":"School",
            "type":"Public Place"
        }
    ],
    "sg:phone":"+61 3 5795 2512",
    "sg:postcode":"3666",
    "sg:province":"VIC",
    "sg:tags":[
        "state",
        "except",
        "nsw"
    ],
    "wof:name":"Euroa Secondary College",
    "wof:placetype":"venue"
},
  "geometry": {"coordinates":[145.56367492699999,-36.7553024292],"type":"Point"}
}