{
  "type": "Feature",
  "properties": {
    "addr:full":"67 Francis St Wingfield SA 5013",
    "addr:housenumber":"67",
    "addr:postcode":"5013",
    "addr:street":"Francis St",
    "iso:country":"AU",
    "sg:address":"67 Francis St",
    "sg:city":"Wingfield",
    "sg:classifiers":[
        {
            "category":"Building & Trades",
            "subcategory":"Construction",
            "type":"Services"
        }
    ],
    "sg:phone":"+61 409 670 535",
    "sg:postcode":"5013",
    "sg:province":"SA",
    "sg:tags":[
        "joinery"
    ],
    "wof:name":"Denis I Harkin",
    "wof:placetype":"venue"
},
  "geometry": {"coordinates":[138.517120361,-34.840221405],"type":"Point"}
}