{
  "type": "Feature",
  "properties": {
    "iso:country":"AU",
    "sg:address":"PO Box 1247",
    "sg:city":"Blackburn North",
    "sg:classifiers":[
        {
            "category":"Wholesale",
            "subcategory":"Toys & Hobbies",
            "type":"Manufacturing & Wholesale Goods"
        }
    ],
    "sg:phone":"+61 407 883 950",
    "sg:postcode":"3130",
    "sg:province":"VIC",
    "sg:tags":[
        "mfrs"
    ],
    "wof:name":"Clay Time",
    "wof:placetype":"venue"
},
  "geometry": {"coordinates":[145.14466857900001,-37.8003692627],"type":"Point"}
}