{
  "type": "Feature",
  "properties": {
    "addr:full":"Yangebup Primary School 55 Moorhen Drv Yangebup WA 6164",
    "addr:housenumber":"55",
    "addr:postcode":"6164",
    "addr:street":"Moorhen Drv",
    "iso:country":"AU",
    "sg:address":"Yangebup Primary School 55 Moorhen Drv",
    "sg:city":"Yangebup",
    "sg:classifiers":[
        {
            "category":"Education",
            "subcategory":"School",
            "type":"Public Place"
        }
    ],
    "sg:phone":"+61 8 9417 1210",
    "sg:postcode":"6164",
    "sg:province":"WA",
    "sg:tags":[
        "state",
        "except",
        "nsw"
    ],
    "wof:name":"Schools Government (Public)",
    "wof:placetype":"venue"
},
  "geometry": {"coordinates":[115.817886,-32.119926],"type":"Point"}
}