{
  "type": "Feature",
  "properties": {
    "addr:full":"2/3 61- 65 Eton St Sutherland NSW 2232",
    "addr:housenumber":"/;65",
    "addr:postcode":"2232",
    "addr:street":"3 61;Eton St",
    "iso:country":"AU",
    "sg:address":"2/3 61- 65 Eton St",
    "sg:city":"Sutherland",
    "sg:classifiers":[
        {
            "category":"Health Services",
            "subcategory":"Dentist",
            "type":"Services"
        }
    ],
    "sg:phone":"+61 2 9542 2255",
    "sg:postcode":"2232",
    "sg:province":"NSW",
    "wof:name":"Hayfa Hadi",
    "wof:placetype":"venue"
},
  "geometry": {"coordinates":[151.05789184599999,-34.0351867676],"type":"Point"}
}