{
  "type": "Feature",
  "properties": {
    "iso:country":"AU",
    "sg:address":"2 / 308 Lower Dandenong Rd",
    "sg:city":"Mordialloc",
    "sg:classifiers":[
        {
            "category":"Utilities",
            "subcategory":"Refuse",
            "type":"Services"
        }
    ],
    "sg:phone":"+61 1300 559 152",
    "sg:postcode":"3195",
    "sg:province":"VIC",
    "sg:tags":[
        "remover",
        "rubbish"
    ],
    "wof:name":"Metropolitan Bin Hire",
    "wof:placetype":"venue"
},
  "geometry": {"coordinates":[145.105560303,-37.9861755371],"type":"Point"}
}