{
  "type": "Feature",
  "properties": {
    "iso:country":"AU",
    "sg:address":"580 Glenfern Rd",
    "sg:city":"New Norfolk",
    "sg:classifiers":[
        {
            "category":"Utilities",
            "subcategory":"Water",
            "type":"Services"
        }
    ],
    "sg:phone":"+61 3 6261 5446",
    "sg:postcode":"7140",
    "sg:province":"TAS",
    "sg:tags":[
        "cartage"
    ],
    "wof:name":"Derwent Valley Water Cartage",
    "wof:placetype":"venue"
},
  "geometry": {"coordinates":[147.023651,-42.774235],"type":"Point"}
}