{
  "type": "Feature",
  "properties": {
    "addr:full":"171 Oxford St Darlinghurst NSW 2010",
    "addr:housenumber":"171",
    "addr:postcode":"2010",
    "addr:street":"Oxford St",
    "iso:country":"AU",
    "sg:address":"171 Oxford St",
    "sg:city":"Darlinghurst",
    "sg:classifiers":[
        {
            "category":"Retail",
            "subcategory":"Car Wash",
            "type":"Services"
        }
    ],
    "sg:phone":"+61 2 9360 4760",
    "sg:postcode":"2010",
    "sg:province":"NSW",
    "sg:tags":[
        "wholesaler",
        "apron",
        "mfrs"
    ],
    "wof:name":"Fraser & Hughes Pty Ltd",
    "wof:placetype":"venue"
},
  "geometry": {"coordinates":[151.216339111,-33.8803710938],"type":"Point"}
}