{
  "type": "Feature",
  "properties": {
    "iso:country":"AU",
    "sg:address":"Suite 102, Medici Medical Cntr, 13-15 Scott St (opposite St Vincents)",
    "sg:city":"Toowoomba",
    "sg:classifiers":[
        {
            "category":"Personal",
            "subcategory":"Beauty Salon",
            "type":"Services"
        }
    ],
    "sg:phone":"+61 7 4638 2700",
    "sg:postcode":"4350",
    "sg:province":"QLD",
    "sg:website":"http://www.cosmeticelegance.com.au",
    "wof:name":"Cosmetic Elegance Clinic",
    "wof:placetype":"venue"
},
  "geometry": {"coordinates":[151.97283899999999,-27.565639],"type":"Point"}
}