{
  "type": "Feature",
  "properties": {
    "iso:country":"AU",
    "sg:address":"1 C Woodcroft Ave",
    "sg:city":"St Georges",
    "sg:classifiers":[
        {
            "category":"Banks & Credit Unions",
            "subcategory":"Bank",
            "type":"Services"
        }
    ],
    "sg:phone":"+61 413 625 079",
    "sg:postcode":"5064",
    "sg:province":"SA",
    "sg:tags":[
        "line",
        "marking",
        "road"
    ],
    "wof:name":"Adelaide Line Marking",
    "wof:placetype":"venue"
},
  "geometry": {"coordinates":[138.648605347,-34.9516410828],"type":"Point"}
}