{
  "type": "Feature",
  "properties": {
    "addr:full":"31- 41 McNaughton Rd Clayton VIC 3168",
    "addr:housenumber":"41",
    "addr:postcode":"3168",
    "addr:street":"Mcnaughton Rd",
    "iso:country":"AU",
    "sg:address":"31- 41 McNaughton Rd",
    "sg:city":"Clayton",
    "sg:classifiers":[
        {
            "category":"Food & Beverages",
            "subcategory":"Supermarket",
            "type":"Retail Goods"
        }
    ],
    "sg:phone":"+61 3 9543 8333",
    "sg:postcode":"3168",
    "sg:province":"VIC",
    "sg:tags":[
        "grocery",
        "store"
    ],
    "wof:name":"Jewel Food Stores Pty Ltd",
    "wof:placetype":"venue"
},
  "geometry": {"coordinates":[145.13954162600001,-37.9250679016],"type":"Point"}
}