{
  "type": "Feature",
  "properties": {
    "addr:full":"Cnr Kellicar & Tindall Sts Campbelltown NSW 2560",
    "addr:postcode":"2560",
    "addr:street":"Cnr Kellicar & Tindall Sts",
    "iso:country":"AU",
    "sg:address":"Cnr Kellicar & Tindall Sts",
    "sg:city":"Campbelltown",
    "sg:classifiers":[
        {
            "category":"Food & Beverages",
            "subcategory":"Supermarket",
            "type":"Retail Goods"
        }
    ],
    "sg:phone":"+61 2 4628 3017",
    "sg:postcode":"2560",
    "sg:province":"NSW",
    "sg:tags":[
        "grocery",
        "store"
    ],
    "wof:name":"Jewel Food Stores Pty Ltd",
    "wof:placetype":"venue"
},
  "geometry": {"coordinates":[150.81658935600001,-34.0640983582],"type":"Point"}
}