{
  "type": "Feature",
  "properties": {
    "addr:full":"SteG11/ 1 Bar St Balmain NSW 2041",
    "addr:postcode":"2041",
    "addr:street":"St",
    "iso:country":"AU",
    "sg:address":"SteG11/ 1 Bar St",
    "sg:city":"Balmain",
    "sg:classifiers":[
        {
            "category":"Social Services",
            "type":"Services"
        }
    ],
    "sg:phone":"+61 2 9818 8004",
    "sg:postcode":"2041",
    "sg:province":"NSW",
    "sg:tags":[
        "disabled",
        "person",
        "equipment"
    ],
    "wof:name":"Essential Service Providers",
    "wof:placetype":"venue"
},
  "geometry": {"coordinates":[151.17486600000001,-33.858067],"type":"Point"}
}