{
  "type": "Feature",
  "properties": {
    "iso:country":"AU",
    "sg:address":"Unit 8, 151 Hartley Rd",
    "sg:city":"Smeaton Grange",
    "sg:classifiers":[
        {
            "category":"Retail",
            "subcategory":"Auto Repair",
            "type":"Services"
        }
    ],
    "sg:phone":"+61 2 4648 2156",
    "sg:postcode":"2567",
    "sg:province":"NSW",
    "sg:tags":[
        "body",
        "motor",
        "trimmer"
    ],
    "wof:name":"X-Trim",
    "wof:placetype":"venue"
},
  "geometry": {"coordinates":[150.75637817399999,-34.0390548706],"type":"Point"}
}