{
  "type": "Feature",
  "properties": {
    "addr:full":"6 Aldinga St Brendale QLD 4500",
    "addr:housenumber":"6",
    "addr:postcode":"4500",
    "addr:street":"Aldinga St",
    "iso:country":"AU",
    "sg:address":"6 Aldinga St",
    "sg:city":"Brendale",
    "sg:classifiers":[
        {
            "category":"Home & Garden",
            "subcategory":"Hardware",
            "type":"Retail Goods"
        }
    ],
    "sg:phone":"+61 7 3889 6289",
    "sg:postcode":"4500",
    "sg:province":"QLD",
    "sg:tags":[
        "supply",
        "maker",
        "cabinet"
    ],
    "wof:name":"Queensland Benchtops & Doors",
    "wof:placetype":"venue"
},
  "geometry": {"coordinates":[152.97943115199999,-27.3172340393],"type":"Point"}
}