{
  "type": "Feature",
  "properties": {
    "iso:country":"AU",
    "sg:address":"Shp5/ 5 Montgomery St",
    "sg:city":"Kogarah",
    "sg:classifiers":[
        {
            "category":"Fast Food",
            "type":"Food & Drink"
        }
    ],
    "sg:phone":"+61 2 9553 9130",
    "sg:postcode":"2217",
    "sg:province":"NSW",
    "sg:tags":[
        "away",
        "take"
    ],
    "wof:name":"Pretty Healthy",
    "wof:placetype":"venue"
},
  "geometry": {"coordinates":[151.133194,-33.963009],"type":"Point"}
}