{
  "type": "Feature",
  "properties": {
    "addr:full":"17 Elizaberth St Devonport TAS 7310",
    "addr:housenumber":"17",
    "addr:postcode":"7310",
    "addr:street":"Elizaberth St",
    "iso:country":"AU",
    "sg:address":"17 Elizaberth St",
    "sg:city":"Devonport",
    "sg:classifiers":[
        {
            "category":"Retail",
            "subcategory":"Auto Repair",
            "type":"Services"
        }
    ],
    "sg:phone":"+61 3 6423 2330",
    "sg:postcode":"7310",
    "sg:province":"TAS",
    "sg:tags":[
        "repairer",
        "motor",
        "engineer"
    ],
    "wof:name":"Duncan Harvey Autos",
    "wof:placetype":"venue"
},
  "geometry": {"coordinates":[146.36018371599999,-41.1895256042],"type":"Point"}
}