{
  "type": "Feature",
  "properties": {
    "iso:country":"AU",
    "sg:address":"120 Main Rd",
    "sg:city":"McLaren Vale",
    "sg:classifiers":[
        {
            "category":"Health Services",
            "subcategory":"Dentist",
            "type":"Services"
        }
    ],
    "sg:phone":"+61 8 8323 8457",
    "sg:postcode":"5171",
    "sg:province":"SA",
    "wof:name":"Spoor Jason Dr",
    "wof:placetype":"venue"
},
  "geometry": {"coordinates":[138.53715515100001,-35.2149658203],"type":"Point"}
}