{
  "type": "Feature",
  "properties": {
    "iso:country":"AU",
    "sg:address":"3 Kefford St",
    "sg:city":"Wellington Point",
    "sg:classifiers":[
        {
            "category":"Professional",
            "subcategory":"Art Services",
            "type":"Services"
        }
    ],
    "sg:phone":"+61 7 3822 5662",
    "sg:postcode":"4160",
    "sg:province":"QLD",
    "sg:tags":[
        "decorator",
        "painter"
    ],
    "wof:name":"Chris Turner & Co",
    "wof:placetype":"venue"
},
  "geometry": {"coordinates":[153.240325928,-27.507314682],"type":"Point"}
}