{
  "type": "Feature",
  "properties": {
    "addr:full":"10 Bark Crt Coomera QLD 4209",
    "addr:housenumber":"10",
    "addr:postcode":"4209",
    "addr:street":"Bark Crt",
    "iso:country":"AU",
    "sg:address":"10 Bark Crt",
    "sg:city":"Coomera",
    "sg:classifiers":[
        {
            "category":"Industrial Area",
            "type":"Public Place"
        }
    ],
    "sg:phone":"+61 414 727 009",
    "sg:postcode":"4209",
    "sg:province":"QLD",
    "sg:tags":[
        "floor"
    ],
    "wof:name":"Mark Fletcher",
    "wof:placetype":"venue"
},
  "geometry": {"coordinates":[153.31878662099999,-27.8777484894],"type":"Point"}
}