{
  "type": "Feature",
  "properties": {
    "addr:full":"309 Main St Bairnsdale VIC 3875",
    "addr:housenumber":"309",
    "addr:postcode":"3875",
    "addr:street":"Main St",
    "iso:country":"AU",
    "sg:address":"309 Main St",
    "sg:city":"Bairnsdale",
    "sg:classifiers":[
        {
            "category":"Health Services",
            "subcategory":"Health Practitioner",
            "type":"Services"
        }
    ],
    "sg:phone":"+61 3 5152 3323",
    "sg:postcode":"3875",
    "sg:province":"VIC",
    "sg:tags":[
        "physiotherapist"
    ],
    "wof:name":"Main St Physiotherapy Clinic",
    "wof:placetype":"venue"
},
  "geometry": {"coordinates":[147.827224731,-37.7086296082],"type":"Point"}
}