{
  "type": "Feature",
  "properties": {
    "addr:full":"5 Mc Cubbin St Kew East VIC 3102",
    "addr:housenumber":"5",
    "addr:postcode":"3102",
    "addr:street":"Mc Cubbin",
    "iso:country":"AU",
    "sg:address":"5 Mc Cubbin St",
    "sg:city":"Kew East",
    "sg:classifiers":[
        {
            "category":"Professional",
            "subcategory":"Art Services",
            "type":"Services"
        }
    ],
    "sg:phone":"+61 3 9859 5273",
    "sg:postcode":"3102",
    "sg:province":"VIC",
    "sg:tags":[
        "decorator",
        "painter"
    ],
    "wof:name":"Vancea Painting Services",
    "wof:placetype":"venue"
},
  "geometry": {"coordinates":[145.061767578,-37.7882766724],"type":"Point"}
}