{
  "type": "Feature",
  "properties": {
    "addr:full":"3 Errol St Braybrook VIC 3019",
    "addr:housenumber":"3",
    "addr:postcode":"3019",
    "addr:street":"Errol St",
    "iso:country":"AU",
    "sg:address":"3 Errol St",
    "sg:city":"Braybrook",
    "sg:classifiers":[
        {
            "category":"Building & Trades",
            "subcategory":"Equipment Rental",
            "type":"Services"
        }
    ],
    "sg:phone":"+61 3 9312 5658",
    "sg:postcode":"3019",
    "sg:province":"VIC",
    "sg:tags":[
        "saw"
    ],
    "wof:name":"Footscray Saw Sharpening",
    "wof:placetype":"venue"
},
  "geometry": {"coordinates":[144.85458374000001,-37.7793617249],"type":"Point"}
}