{
  "type": "Feature",
  "properties": {
    "addr:full":"740 Burke Rd Camberwell VIC 3124",
    "addr:housenumber":"740",
    "addr:postcode":"3124",
    "addr:street":"Burke Rd",
    "iso:country":"AU",
    "sg:address":"740 Burke Rd",
    "sg:city":"Camberwell",
    "sg:classifiers":[
        {
            "category":"Personal",
            "subcategory":"Beauty Salon",
            "type":"Services"
        }
    ],
    "sg:phone":"+61 3 9882 4188",
    "sg:postcode":"3124",
    "sg:province":"VIC",
    "sg:tags":[
        "hairdresser"
    ],
    "wof:name":"Fratelle Hair & Make Up",
    "wof:placetype":"venue"
},
  "geometry": {"coordinates":[145.057937622,-37.8256950378],"type":"Point"}
}