{
  "type": "Feature",
  "properties": {
    "iso:country":"AU",
    "sg:address":"545 High St",
    "sg:city":"Epping",
    "sg:classifiers":[
        {
            "category":"Building & Trades",
            "subcategory":"Cleaning & Sanitation",
            "type":"Services"
        }
    ],
    "sg:phone":"+61 1300 226 626",
    "sg:postcode":"3076",
    "sg:province":"VIC",
    "sg:tags":[
        "industrial",
        "commercial",
        "contractor"
    ],
    "wof:name":"Mr. Can Man",
    "wof:placetype":"venue"
},
  "geometry": {"coordinates":[145.00616455100001,-37.8534431458],"type":"Point"}
}