{
  "type": "Feature",
  "properties": {
    "addr:full":"10/ 22 Cliff St Milsons Point NSW 2061",
    "addr:housenumber":"10 / 22",
    "addr:postcode":"2061",
    "addr:street":"Cliff St",
    "iso:country":"AU",
    "sg:address":"10/ 22 Cliff St",
    "sg:city":"Milsons Point",
    "sg:classifiers":[
        {
            "category":"Health Services",
            "subcategory":"Health Practitioner",
            "type":"Services"
        }
    ],
    "sg:phone":"+61 2 9979 3213",
    "sg:postcode":"2061",
    "sg:province":"NSW",
    "sg:tags":[
        "psychologist"
    ],
    "wof:name":"Mentors Psychology for Business",
    "wof:placetype":"venue"
},
  "geometry": {"coordinates":[151.21023559599999,-33.8447113037],"type":"Point"}
}