{
  "type": "Feature",
  "properties": {
    "iso:country":"AU",
    "sg:address":"21 Aplin Rd",
    "sg:city":"Thursday Island",
    "sg:classifiers":[
        {
            "category":"Education",
            "subcategory":"School",
            "type":"Public Place"
        }
    ],
    "sg:phone":"+61 7 4069 2240",
    "sg:postcode":"4875",
    "sg:province":"QLD",
    "sg:tags":[
        "state",
        "except",
        "nsw"
    ],
    "wof:name":"Thursday Island High School",
    "wof:placetype":"venue"
},
  "geometry": {"coordinates":[142.219512939,-10.574801445],"type":"Point"}
}