{
  "type": "Feature",
  "properties": {
    "addr:full":"5/ 55 Pruen Rd Berrimah NT 0828",
    "addr:housenumber":"/ 55",
    "addr:postcode":"nt 0828",
    "addr:street":"Pruen Rd",
    "iso:country":"AU",
    "sg:address":"5/ 55 Pruen Rd",
    "sg:city":"Berrimah",
    "sg:classifiers":[
        {
            "category":"Home & Garden",
            "subcategory":"Hardware",
            "type":"Retail Goods"
        }
    ],
    "sg:phone":"+61 8 8984 4195",
    "sg:postcode":"0828",
    "sg:province":"NT",
    "sg:tags":[
        "plumber",
        "supply"
    ],
    "wof:name":"Reece Pty Ltd",
    "wof:placetype":"venue"
},
  "geometry": {"coordinates":[130.92965698200001,-12.4379396439],"type":"Point"}
}