{
  "type": "Feature",
  "properties": {
    "iso:country":"AU",
    "sg:address":"263 Maitland Rd",
    "sg:city":"Cessnock",
    "sg:classifiers":[
        {
            "category":"Professional",
            "subcategory":"Computer Services",
            "type":"Services"
        }
    ],
    "sg:phone":"+61 2 4991 2562",
    "sg:postcode":"2325",
    "sg:province":"NSW",
    "sg:tags":[
        "equipment",
        "networking",
        "installation"
    ],
    "wof:name":"Baker MarkComputer Service",
    "wof:placetype":"venue"
},
  "geometry": {"coordinates":[151.361053467,-32.8296165466],"type":"Point"}
}