{
  "type": "Feature",
  "properties": {
    "addr:full":"Gilles Hwy Yungaburra QLD 4872",
    "addr:postcode":"4872",
    "addr:street":"Gilles Hwy",
    "iso:country":"AU",
    "sg:address":"Gilles Hwy",
    "sg:city":"Yungaburra",
    "sg:classifiers":[
        {
            "category":"Utilities",
            "subcategory":"Electric",
            "type":"Services"
        }
    ],
    "sg:phone":"+61 7 4095 3833",
    "sg:postcode":"4872",
    "sg:province":"QLD",
    "sg:tags":[
        "electrical",
        "contractor"
    ],
    "wof:name":"Fox Electrics",
    "wof:placetype":"venue"
},
  "geometry": {"coordinates":[145.1068573,-17.9841003418],"type":"Point"}
}