{
  "type": "Feature",
  "properties": {
    "addr:full":"King St Clontarf QLD 4019",
    "addr:postcode":"4019",
    "addr:street":"King St",
    "iso:country":"AU",
    "sg:address":"King St",
    "sg:city":"Clontarf",
    "sg:classifiers":[
        {
            "category":"Education",
            "subcategory":"School",
            "type":"Public Place"
        }
    ],
    "sg:phone":"+61 7 3480 4777",
    "sg:postcode":"4019",
    "sg:province":"QLD",
    "sg:tags":[
        "state",
        "except",
        "nsw"
    ],
    "wof:name":"Clontarf Beach State High School",
    "wof:placetype":"venue"
},
  "geometry": {"coordinates":[153.08480835,-27.2475223541],"type":"Point"}
}