{
  "type": "Feature",
  "properties": {
    "addr:full":"12 Monomeath Ave Toorak VIC 3142",
    "addr:housenumber":"12",
    "addr:postcode":"3142",
    "addr:street":"Monomeath Ave",
    "iso:country":"AU",
    "sg:address":"12 Monomeath Ave",
    "sg:city":"Toorak",
    "sg:classifiers":[
        {
            "category":"Real Estate",
            "subcategory":"Architect",
            "type":"Services"
        }
    ],
    "sg:phone":"+61 3 9822 2370",
    "sg:postcode":"3142",
    "sg:province":"VIC",
    "wof:name":"Allison Hopper",
    "wof:placetype":"venue"
},
  "geometry": {"coordinates":[145.03112793,-37.8406715393],"type":"Point"}
}