{
  "type": "Feature",
  "properties": {
    "iso:country":"AU",
    "sg:address":"133 Victoria Rd",
    "sg:city":"Gladesville",
    "sg:classifiers":[
        {
            "category":"Shopping",
            "subcategory":"Bicycles & Sporting Goods",
            "type":"Retail Goods"
        }
    ],
    "sg:phone":"+61 2 9879 0300",
    "sg:postcode":"2111",
    "sg:province":"NSW",
    "sg:tags":[
        "chemical",
        "equipment",
        "pool",
        "swimming"
    ],
    "wof:name":"Aquapool.co Pty Ltd",
    "wof:placetype":"venue"
},
  "geometry": {"coordinates":[151.12832641599999,-33.8357696533],"type":"Point"}
}