{
  "type": "Feature",
  "properties": {
    "addr:full":"Level 9 51 Pitt St Sydney NSW 2000",
    "addr:housenumber":"51",
    "addr:postcode":"2000",
    "addr:street":"Pitt St",
    "iso:country":"AU",
    "sg:address":"Level 9 51 Pitt St",
    "sg:city":"Sydney",
    "sg:classifiers":[
        {
            "category":"Professional",
            "subcategory":"Accounting & Tax Preparation",
            "type":"Services"
        }
    ],
    "sg:phone":"+61 2 9233 6433",
    "sg:postcode":"2000",
    "sg:province":"NSW",
    "sg:tags":[
        "accountant",
        "auditor"
    ],
    "wof:name":"Farrar & Wybenga",
    "wof:placetype":"venue"
},
  "geometry": {"coordinates":[151.20887756400001,-33.8628616333],"type":"Point"}
}