{
  "type": "Feature",
  "properties": {
    "addr:full":"211 George St Bathurst NSW 2795",
    "addr:housenumber":"211",
    "addr:postcode":"2795",
    "addr:street":"George St",
    "iso:country":"AU",
    "sg:address":"211 George St",
    "sg:city":"Bathurst",
    "sg:classifiers":[
        {
            "category":"Professional",
            "subcategory":"Accounting & Tax Preparation",
            "type":"Services"
        }
    ],
    "sg:phone":"+61 2 6332 5029",
    "sg:postcode":"2795",
    "sg:province":"NSW",
    "sg:tags":[
        "consultant",
        "taxation"
    ],
    "wof:name":"Clements Bruce",
    "wof:placetype":"venue"
},
  "geometry": {"coordinates":[149.575561523,-33.4186859131],"type":"Point"}
}