{
  "type": "Feature",
  "properties": {
    "addr:full":"Shp1/ 80 Walkerville Tce Walkerville SA 5081",
    "addr:housenumber":"80",
    "addr:postcode":"5081",
    "addr:street":"Walkerville Tce",
    "iso:country":"AU",
    "sg:address":"Shp1/ 80 Walkerville Tce",
    "sg:city":"Walkerville",
    "sg:classifiers":[
        {
            "category":"Fast Food",
            "type":"Food & Drink"
        }
    ],
    "sg:phone":"+61 8 8342 3338",
    "sg:postcode":"5081",
    "sg:province":"SA",
    "sg:tags":[
        "away",
        "take"
    ],
    "wof:name":"Walkerville Yiros & Take-Away",
    "wof:placetype":"venue"
},
  "geometry": {"coordinates":[138.615356445,-34.8969154358],"type":"Point"}
}