{
  "type": "Feature",
  "properties": {
    "addr:full":"Bellevue Rd Tumbi Umbi NSW 2261",
    "addr:postcode":"2261",
    "addr:street":"Bellevue Rd",
    "iso:country":"AU",
    "sg:address":"Bellevue Rd",
    "sg:city":"Tumbi Umbi",
    "sg:classifiers":[
        {
            "category":"Education",
            "subcategory":"School",
            "type":"Public Place"
        }
    ],
    "sg:phone":"+61 2 4385 6802",
    "sg:postcode":"2261",
    "sg:province":"NSW",
    "sg:tags":[
        "state",
        "-",
        "nsw"
    ],
    "wof:name":"Tumbi Umbi High School",
    "wof:placetype":"venue"
},
  "geometry": {"coordinates":[151.45344499999999,-33.393333],"type":"Point"}
}