{
  "type": "Feature",
  "properties": {
    "iso:country":"AU",
    "sg:address":"Unit 4, 61- 71 Nestor Drv",
    "sg:city":"Meadowbrook",
    "sg:classifiers":[
        {
            "category":"Communications",
            "subcategory":"Film & Video Production",
            "type":"Services"
        }
    ],
    "sg:phone":"+61 7 3200 2555",
    "sg:postcode":"4131",
    "sg:province":"QLD",
    "sg:tags":[
        "lighting",
        "emergency",
        "power"
    ],
    "wof:name":"Clevertronics Pty Ltd",
    "wof:placetype":"venue"
},
  "geometry": {"coordinates":[153.13313293499999,-27.6672611237],"type":"Point"}
}