{
  "type": "Feature",
  "properties": {
    "addr:full":"U1/ 32 Carrington St Lismore NSW 2480",
    "addr:housenumber":"32",
    "addr:postcode":"2480",
    "addr:street":"U1 /;Carrington St",
    "iso:country":"AU",
    "sg:address":"U1/ 32 Carrington St",
    "sg:city":"Lismore",
    "sg:classifiers":[
        {
            "category":"Manufacturing",
            "subcategory":"Food",
            "type":"Manufacturing & Wholesale Goods"
        }
    ],
    "sg:phone":"+61 2 6622 0558",
    "sg:postcode":"2480",
    "sg:province":"NSW",
    "sg:tags":[
        "function",
        "catering"
    ],
    "wof:name":"Little Deli The",
    "wof:placetype":"venue"
},
  "geometry": {"coordinates":[153.27682495100001,-28.80950737],"type":"Point"}
}