{
  "type": "Feature",
  "properties": {
    "iso:country":"AU",
    "sg:address":"47 Moore St",
    "sg:city":"Hurstville",
    "sg:classifiers":[
        {
            "category":"Professional",
            "subcategory":"Accounting & Tax Preparation",
            "type":"Services"
        }
    ],
    "sg:phone":"+61 2 9502 1188",
    "sg:postcode":"2220",
    "sg:province":"NSW",
    "sg:tags":[
        "accountant",
        "auditor"
    ],
    "wof:name":"Blanche Chan & Co",
    "wof:placetype":"venue"
},
  "geometry": {"coordinates":[151.10429382300001,-33.9543457031],"type":"Point"}
}