{
  "type": "Feature",
  "properties": {
    "iso:country":"AU",
    "sg:address":"2 Kangaroo Drv",
    "sg:city":"Blackbutt",
    "sg:classifiers":[
        {
            "category":"Social Services",
            "subcategory":"Child Care",
            "type":"Services"
        }
    ],
    "sg:phone":"+61 2 4297 6297",
    "sg:postcode":"2529",
    "sg:province":"NSW",
    "wof:name":"Wilbur Whale Childcare Centre",
    "wof:placetype":"venue"
},
  "geometry": {"coordinates":[150.835479736,-34.5725021362],"type":"Point"}
}