{
  "type": "Feature",
  "properties": {
    "addr:full":"100 Boundary St West End QLD 4101",
    "addr:housenumber":"100",
    "addr:postcode":"4101",
    "addr:street":"Boundary St",
    "iso:country":"AU",
    "sg:address":"100 Boundary St",
    "sg:city":"West End",
    "sg:classifiers":[
        {
            "category":"Food & Beverages",
            "subcategory":"Liquor & Beverages",
            "type":"Retail Goods"
        }
    ],
    "sg:phone":"+61 7 3846 6680",
    "sg:postcode":"4101",
    "sg:province":"QLD",
    "sg:tags":[
        "store"
    ],
    "wof:name":"Liquor Legends",
    "wof:placetype":"venue"
},
  "geometry": {"coordinates":[153.01258850100001,-27.4787578583],"type":"Point"}
}