{
  "type": "Feature",
  "properties": {
    "addr:full":"196 king St Caboolture QLD 4510",
    "addr:housenumber":"196",
    "addr:postcode":"4510",
    "addr:street":"King St",
    "iso:country":"AU",
    "sg:address":"196 king St",
    "sg:city":"Caboolture",
    "sg:classifiers":[
        {
            "category":"Health Services",
            "subcategory":"Chiropractor",
            "type":"Services"
        }
    ],
    "sg:phone":"+61 7 5495 7599",
    "sg:postcode":"4510",
    "sg:province":"QLD",
    "wof:name":"Clark Lisa",
    "wof:placetype":"venue"
},
  "geometry": {"coordinates":[152.93626399999999,-27.081848],"type":"Point"}
}