{
  "type": "Feature",
  "properties": {
    "addr:full":"59 Walker St Casino NSW 2470",
    "addr:housenumber":"59",
    "addr:postcode":"2470",
    "addr:street":"Walker St",
    "iso:country":"AU",
    "sg:address":"59 Walker St",
    "sg:city":"Casino",
    "sg:classifiers":[
        {
            "category":"Shopping",
            "subcategory":"Shoes",
            "type":"Retail Goods"
        }
    ],
    "sg:phone":"+61 2 6662 1465",
    "sg:postcode":"2470",
    "sg:province":"NSW",
    "sg:tags":[
        "footwear"
    ],
    "wof:name":"Nance's Shoe Store",
    "wof:placetype":"venue"
},
  "geometry": {"coordinates":[153.04818725600001,-28.8645362854],"type":"Point"}
}